Workbook

Sheet Dashboard
A1: Neighborhood Cafe — 3-Year Plan
A2: Change the scenario in B4 (1 = Low, 2 = Base, 3 = High); every sheet recalculates.
A4: Scenario selector | B4: 2 | C4: =CHOOSE(B4,"Low","Base","High") -> Base
A6: Key metrics
B7: Year 1 | C7: Year 2 | D7: Year 3
A8: Revenue | B8: ='P&L'!B5 -> 319800 | C8: ='P&L'!C5 -> 408769.92 | D8: ='P&L'!D5 -> 446295
A9: Gross profit | B9: ='P&L'!B7 -> 214266 | C9: ='P&L'!C7 -> 273875.85 | D9: ='P&L'!D7 -> 299017.65
A10: EBITDA | B10: ='P&L'!B14 -> 1232 | C10: ='P&L'!C14 -> 54409.549 | D10: ='P&L'!D14 -> 74549.503
A11: EBITDA margin | B11: ='P&L'!B15 -> 0.0038524078 | C11: ='P&L'!C15 -> 0.13310556 | D11: ='P&L'!D15 -> 0.16704087
A12: Net income | B12: ='P&L'!B19 -> -23023.623 | C12: ='P&L'!C19 -> 24926.401 | D12: ='P&L'!D19 -> 40836.965
A13: Year-end cash | B13: ='P&L'!B21 -> 59833.52 | C13: ='P&L'!C21 -> 107617.06 | D13: ='P&L'!D21 -> 171311.17
A15: Health
A16: First month with positive EBITDA | B16: =IFERROR(MATCH(1,Monthly!$C$29:$AL$29,0),"Not within horizon") -> 6
A17: Lowest cash balance | B17: =MIN(Monthly!$C$27:$AL$27) -> 41793.333
A18: Month of lowest cash | B18: =MATCH(B17,Monthly!$C$27:$AL$27,0) -> 5
A19: Model checks | B19: =Checks!B13 -> PASS

Sheet Inputs
A1: Inputs — Low / Base / High
A2: Illustrative assumptions for a demo — replace with your own numbers.
A4: Driver | B4: Low | C4: Base | D4: High | E4: Active | F4: Unit | G4: Note
A5: Customers per day at full traffic | B5: 120 | C5: 160 | D5: 210 | E5: =CHOOSE(Dashboard!$B$4,B5,C5,D5) -> 160 | F5: # | G5: User / brief input
A6: Months to reach full traffic | B6: 9 | C6: 6 | D6: 4 | E6: =CHOOSE(Dashboard!$B$4,B6,C6,D6) -> 6 | F6: months | G6: User / brief input
A7: Opening traffic, % of full | B7: 0.4 | C7: 0.5 | D7: 0.6 | E7: =CHOOSE(Dashboard!$B$4,B7,C7,D7) -> 0.5 | F7: % | G7: User / brief input
A8: Traffic growth per year (after Y1) | B8: 0.03 | C8: 0.06 | D8: 0.09 | E8: =CHOOSE(Dashboard!$B$4,B8,C8,D8) -> 0.06 | F8: % | G8: User / brief input
A9: Average ticket | B9: 5.5 | C9: 6.5 | D9: 7.5 | E9: =CHOOSE(Dashboard!$B$4,B9,C9,D9) -> 6.5 | F9: $ | G9: User / brief input
A10: Price growth per year | B10: 0.02 | C10: 0.03 | D10: 0.04 | E10: =CHOOSE(Dashboard!$B$4,B10,C10,D10) -> 0.03 | F10: % | G10: User / brief input
A11: Operating days per month | B11: 30 | C11: 30 | D11: 30 | E11: =CHOOSE(Dashboard!$B$4,B11,C11,D11) -> 30 | F11: days | G11: User / brief input
A12: COGS, % of revenue | B12: 0.36 | C12: 0.33 | D12: 0.3 | E12: =CHOOSE(Dashboard!$B$4,B12,C12,D12) -> 0.33 | F12: % | G12: User / brief input
A13: Rent per month | B13: 4500 | C13: 4500 | D13: 4500 | E13: =CHOOSE(Dashboard!$B$4,B13,C13,D13) -> 4500 | F13: $ | G13: User / brief input
A14: Staff (full-time equivalents) | B14: 3 | C14: 3.5 | D14: 4 | E14: =CHOOSE(Dashboard!$B$4,B14,C14,D14) -> 3.5 | F14: FTE | G14: User / brief input
A15: Salary per FTE per year | B15: 30000 | C15: 32000 | D15: 34000 | E15: =CHOOSE(Dashboard!$B$4,B15,C15,D15) -> 32000 | F15: $ | G15: User / brief input
A16: Payroll taxes & benefits | B16: 0.12 | C16: 0.12 | D16: 0.12 | E16: =CHOOSE(Dashboard!$B$4,B16,C16,D16) -> 0.12 | F16: % of salary | G16: User / brief input
... A23: Income tax rate | B23: 0.21 | C23: 0.21 | D23: 0.21 | E23: =CHOOSE(Dashboard!$B$4,B23,C23,D23) -> 0.21 | F23: % | G23: User / brief input
A25: Legend: blue = input you can change · black = formula · green = link to another sheet. Column E follows the scenario on the Dashboard.

Sheet Monthly
A1: Monthly projection
A2: All values in $ unless stated. Every month uses the same formula.
A3: Month # | C3: 1 | D3: 2 | E3: 3 | F3: 4 | G3: 5 | H3: 6 | I3: 7 | J3: 8 | K3: 9 | L3: 10 | M3: 11 | N3: 12 | O3: 13 | P3: 14 | Q3: 15 | R3: 16 | S3: 17 | T3: 18 | U3: 19 | V3: 20 | W3: 21 | X3: 22 | Y3: 23 | Z3: 24 | AA3: 25 | AB3: 26 | AC3: 27 | AD3: 28 | AE3: 29 | AF3: 30 | AG3: 31 | AH3: 32 | AI3: 33 | AJ3: 34 | AK3: 35 | AL3: 36
A4: Year # | C4: =ROUNDUP(C3/12,0) -> 1 | D4: =ROUNDUP(D3/12,0) -> 1 | E4: =ROUNDUP(E3/12,0) -> 1 | F4: =ROUNDUP(F3/12,0) -> 1 | G4: =ROUNDUP(G3/12,0) -> 1 | H4: =ROUNDUP(H3/12,0) -> 1 | I4: =ROUNDUP(I3/12,0) -> 1 | J4: =ROUNDUP(J3/12,0) -> 1 | ... AL4: =ROUNDUP(AL3/12,0) -> 3
A5: Revenue build
A6: Traffic ramp factor | C6: =MIN(1,Inputs!$E$7+(1-Inputs!$E$7)*(C3-1)/MAX(1,Inputs!$E$6)) -> 0.5 | D6: =MIN(1,Inputs!$E$7+(1-Inputs!$E$7)*(D3-1)/MAX(1,Inputs!$E$6)) -> 0.58333333 | E6: =MIN(1,Inputs!$E$7+(1-Inputs!$E$7)*(E3-1)/MAX(1,Inputs!$E$6)) -> 0.66666667 | F6: =MIN(1,Inputs!$E$7+(1-Inputs!$E$7)*(F3-1)/MAX(1,Inputs!$E$6)) -> 0.75 | G6: =MIN(1,Inputs!$E$7+(1-Inputs!$E$7)*(G3-1)/MAX(1,Inputs!$E$6)) -> 0.83333333 | H6: =MIN(1,Inputs!$E$7+(1-Inputs!$E$7)*(H3-1)/MAX(1,Inputs!$E$6)) -> 0.91666667 | I6: =MIN(1,Inputs!$E$7+(1-Inputs!$E$7)*(I3-1)/MAX(1,Inputs!$E$6)) -> 1 | J6: =MIN(1,Inputs!$E$7+(1-Inputs!$E$7)*(J3-1)/MAX(1,Inputs!$E$6)) -> 1 | ... AL6: =MIN(1,Inputs!$E$7+(1-Inputs!$E$7)*(AL3-1)/MAX(1,Inputs!$E$6)) -> 1
A7: Customers per day | C7: =Inputs!$E$5*C6*(1+Inputs!$E$8)^(C4-1) -> 80 | D7: =Inputs!$E$5*D6*(1+Inputs!$E$8)^(D4-1) -> 93.333333 | E7: =Inputs!$E$5*E6*(1+Inputs!$E$8)^(E4-1) -> 106.66667 | F7: =Inputs!$E$5*F6*(1+Inputs!$E$8)^(F4-1) -> 120 | G7: =Inputs!$E$5*G6*(1+Inputs!$E$8)^(G4-1) -> 133.33333 | H7: =Inputs!$E$5*H6*(1+Inputs!$E$8)^(H4-1) -> 146.66667 | I7: =Inputs!$E$5*I6*(1+Inputs!$E$8)^(I4-1) -> 160 | J7: =Inputs!$E$5*J6*(1+Inputs!$E$8)^(J4-1) -> 160 | ... AL7: =Inputs!$E$5*AL6*(1+Inputs!$E$8)^(AL4-1) -> 179.776
A8: Average ticket ($) | C8: =Inputs!$E$9*(1+Inputs!$E$10)^(C4-1) -> 6.5 | D8: =Inputs!$E$9*(1+Inputs!$E$10)^(D4-1) -> 6.5 | E8: =Inputs!$E$9*(1+Inputs!$E$10)^(E4-1) -> 6.5 | F8: =Inputs!$E$9*(1+Inputs!$E$10)^(F4-1) -> 6.5 | G8: =Inputs!$E$9*(1+Inputs!$E$10)^(G4-1) -> 6.5 | H8: =Inputs!$E$9*(1+Inputs!$E$10)^(H4-1) -> 6.5 | I8: =Inputs!$E$9*(1+Inputs!$E$10)^(I4-1) -> 6.5 | J8: =Inputs!$E$9*(1+Inputs!$E$10)^(J4-1) -> 6.5 | ... AL8: =Inputs!$E$9*(1+Inputs!$E$10)^(AL4-1) -> 6.89585
A9: Operating days | C9: =Inputs!$E$11 -> 30 | D9: =Inputs!$E$11 -> 30 | E9: =Inputs!$E$11 -> 30 | F9: =Inputs!$E$11 -> 30 | G9: =Inputs!$E$11 -> 30 | H9: =Inputs!$E$11 -> 30 | I9: =Inputs!$E$11 -> 30 | J9: =Inputs!$E$11 -> 30 | ... AL9: =Inputs!$E$11 -> 30
A10: Revenue | C10: =C7*C8*C9 -> 15600 | D10: =D7*D8*D9 -> 18200 | E10: =E7*E8*E9 -> 20800 | F10: =F7*F8*F9 -> 23400 | G10: =G7*G8*G9 -> 26000 | H10: =H7*H8*H9 -> 28600 | I10: =I7*I8*I9 -> 31200 | J10: =J7*J8*J9 -> 31200 | ... AL10: =AL7*AL8*AL9 -> 37191.25
A11: COGS | C11: =-C10*Inputs!$E$12 -> -5148 | D11: =-D10*Inputs!$E$12 -> -6006 | E11: =-E10*Inputs!$E$12 -> -6864 | F11: =-F10*Inputs!$E$12 -> -7722 | G11: =-G10*Inputs!$E$12 -> -8580 | H11: =-H10*Inputs!$E$12 -> -9438 | I11: =-I10*Inputs!$E$12 -> -10296 | J11: =-J10*Inputs!$E$12 -> -10296 | ... AL11: =-AL10*Inputs!$E$12 -> -12273.112
A12: Gross profit | C12: =C10+C11 -> 10452 | D12: =D10+D11 -> 12194 | E12: =E10+E11 -> 13936 | F12: =F10+F11 -> 15678 | G12: =G10+G11 -> 17420 | H12: =H10+H11 -> 19162 | I12: =I10+I11 -> 20904 | J12: =J10+J11 -> 20904 | ... AL12: =AL10+AL11 -> 24918.137
A13: Operating expenses
A14: Rent | C14: =-Inputs!$E$13 -> -4500 | D14: =-Inputs!$E$13 -> -4500 | E14: =-Inputs!$E$13 -> -4500 | F14: =-Inputs!$E$13 -> -4500 | G14: =-Inputs!$E$13 -> -4500 | H14: =-Inputs!$E$13 -> -4500 | I14: =-Inputs!$E$13 -> -4500 | J14: =-Inputs!$E$13 -> -4500 | ... AL14: =-Inputs!$E$13 -> -4500
A15: Payroll | C15: =-Inputs!$E$14*Inputs!$E$15/12*(1+Inputs!$E$16)*(1+Inputs!$E$17)^(C4-1) -> -10453.333 | D15: =-Inputs!$E$14*Inputs!$E$15/12*(1+Inputs!$E$16)*(1+Inputs!$E$17)^(D4-1) -> -10453.333 | E15: =-Inputs!$E$14*Inputs!$E$15/12*(1+Inputs!$E$16)*(1+Inputs!$E$17)^(E4-1) -> -10453.333 | F15: =-Inputs!$E$14*Inputs!$E$15/12*(1+Inputs!$E$16)*(1+Inputs!$E$17)^(F4-1) -> -10453.333 | G15: =-Inputs!$E$14*Inputs!$E$15/12*(1+Inputs!$E$16)*(1+Inputs!$E$17)^(G4-1) -> -10453.333 | H15: =-Inputs!$E$14*Inputs!$E$15/12*(1+Inputs!$E$16)*(1+Inputs!$E$17)^(H4-1) -> -10453.333 | I15: =-Inputs!$E$14*Inputs!$E$15/12*(1+Inputs!$E$16)*(1+Inputs!$E$17)^(I4-1) -> -10453.333 | J15: =-Inputs!$E$14*Inputs!$E$15/12*(1+Inputs!$E$16)*(1+Inputs!$E$17)^(J4-1) -> -10453.333 | ... AL15: =-Inputs!$E$14*Inputs!$E$15/12*(1+Inputs!$E$16)*(1+Inputs!$E$17)^(AL4-1) -> -11089.941
A16: Marketing | C16: =-C10*Inputs!$E$18 -> -468 | D16: =-D10*Inputs!$E$18 -> -546 | E16: =-E10*Inputs!$E$18 -> -624 | F16: =-F10*Inputs!$E$18 -> -702 | G16: =-G10*Inputs!$E$18 -> -780 | H16: =-H10*Inputs!$E$18 -> -858 | I16: =-I10*Inputs!$E$18 -> -936 | J16: =-J10*Inputs!$E$18 -> -936 | ... AL16: =-AL10*Inputs!$E$18 -> -1115.7375
A17: Utilities & other | C17: =-Inputs!$E$19 -> -2000 | D17: =-Inputs!$E$19 -> -2000 | E17: =-Inputs!$E$19 -> -2000 | F17: =-Inputs!$E$19 -> -2000 | G17: =-Inputs!$E$19 -> -2000 | H17: =-Inputs!$E$19 -> -2000 | I17: =-Inputs!$E$19 -> -2000 | J17: =-Inputs!$E$19 -> -2000 | ... AL17: =-Inputs!$E$19 -> -2000
A18: Total operating expenses | C18: =SUM(C14:C17) -> -17421.333 | D18: =SUM(D14:D17) -> -17499.333 | E18: =SUM(E14:E17) -> -17577.333 | F18: =SUM(F14:F17) -> -17655.333 | G18: =SUM(G14:G17) -> -17733.333 | H18: =SUM(H14:H17) -> -17811.333 | I18: =SUM(I14:I17) -> -17889.333 | J18: =SUM(J14:J17) -> -17889.333 | ... AL18: =SUM(AL14:AL17) -> -18705.679
A19: EBITDA | C19: =C12+C18 -> -6969.3333 | D19: =D12+D18 -> -5305.3333 | E19: =E12+E18 -> -3641.3333 | F19: =F12+F18 -> -1977.3333 | G19: =G12+G18 -> -313.33333 | H19: =H12+H18 -> 1350.6667 | I19: =I12+I18 -> 3014.6667 | J19: =J12+J18 -> 3014.6667 | ... AL19: =AL12+AL18 -> 6212.4586
A20: Depreciation | C20: =IF(C3<=Inputs!$E$22*12,-Inputs!$E$20/MAX(1,Inputs!$E$22*12),0) -> -1904.7619 | D20: =IF(D3<=Inputs!$E$22*12,-Inputs!$E$20/MAX(1,Inputs!$E$22*12),0) -> -1904.7619 | E20: =IF(E3<=Inputs!$E$22*12,-Inputs!$E$20/MAX(1,Inputs!$E$22*12),0) -> -1904.7619 | F20: =IF(F3<=Inputs!$E$22*12,-Inputs!$E$20/MAX(1,Inputs!$E$22*12),0) -> -1904.7619 | G20: =IF(G3<=Inputs!$E$22*12,-Inputs!$E$20/MAX(1,Inputs!$E$22*12),0) -> -1904.7619 | H20: =IF(H3<=Inputs!$E$22*12,-Inputs!$E$20/MAX(1,Inputs!$E$22*12),0) -> -1904.7619 | I20: =IF(I3<=Inputs!$E$22*12,-Inputs!$E$20/MAX(1,Inputs!$E$22*12),0) -> -1904.7619 | J20: =IF(J3<=Inputs!$E$22*12,-Inputs!$E$20/MAX(1,Inputs!$E$22*12),0) -> -1904.7619 | ... AL20: =IF(AL3<=Inputs!$E$22*12,-Inputs!$E$20/MAX(1,Inputs!$E$22*12),0) -> -1904.7619
A21: EBIT | C21: =C19+C20 -> -8874.0952 | D21: =D19+D20 -> -7210.0952 | E21: =E19+E20 -> -5546.0952 | F21: =F19+F20 -> -3882.0952 | G21: =G19+G20 -> -2218.0952 | H21: =H19+H20 -> -554.09524 | I21: =I19+I20 -> 1109.9048 | J21: =J19+J20 -> 1109.9048 | ... AL21: =AL19+AL20 -> 4307.6967
A22: Income tax | C22: =-MAX(0,C21)*Inputs!$E$23 -> 0 | D22: =-MAX(0,D21)*Inputs!$E$23 -> 0 | E22: =-MAX(0,E21)*Inputs!$E$23 -> 0 | F22: =-MAX(0,F21)*Inputs!$E$23 -> 0 | G22: =-MAX(0,G21)*Inputs!$E$23 -> 0 | H22: =-MAX(0,H21)*Inputs!$E$23 -> 0 | I22: =-MAX(0,I21)*Inputs!$E$23 -> -233.08 | J22: =-MAX(0,J21)*Inputs!$E$23 -> -233.08 | ... AL22: =-MAX(0,AL21)*Inputs!$E$23 -> -904.6163
A23: Net income | C23: =C21+C22 -> -8874.0952 | D23: =D21+D22 -> -7210.0952 | E23: =E21+E22 -> -5546.0952 | F23: =F21+F22 -> -3882.0952 | G23: =G21+G22 -> -2218.0952 | H23: =H21+H22 -> -554.09524 | I23: =I21+I22 -> 876.82476 | J23: =J21+J22 -> 876.82476 | ... AL23: =AL21+AL22 -> 3403.0804
A24: Cash
A25: Opening cash | C25: =Inputs!$E$21-Inputs!$E$20 -> 60000 | D25: =C27 -> 53030.667 | E25: =D27 -> 47725.333 | F25: =E27 -> 44084 | G25: =F27 -> 42106.667 | H25: =G27 -> 41793.333 | I25: =H27 -> 43144 | J25: =I27 -> 45925.587 | K25: =J27 -> 48707.173 | ... AL25: =AK27 -> 166003.33
A26: Operating cash flow | C26: =C23-C20 -> -6969.3333 | D26: =D23-D20 -> -5305.3333 | E26: =E23-E20 -> -3641.3333 | F26: =F23-F20 -> -1977.3333 | G26: =G23-G20 -> -313.33333 | H26: =H23-H20 -> 1350.6667 | I26: =I23-I20 -> 2781.5867 | J26: =J23-J20 -> 2781.5867 | ... AL26: =AL23-AL20 -> 5307.8423
A27: Closing cash | C27: =C25+C26 -> 53030.667 | D27: =D25+D26 -> 47725.333 | E27: =E25+E26 -> 44084 | F27: =F25+F26 -> 42106.667 | G27: =G25+G26 -> 41793.333 | H27: =H25+H26 -> 43144 | I27: =I25+I26 -> 45925.587 | J27: =J25+J26 -> 48707.173 | ... AL27: =AL25+AL26 -> 171311.17
A29: Helper: EBITDA positive (1/0) | C29: =IF(C19>0,1,0) -> 0 | D29: =IF(D19>0,1,0) -> 0 | E29: =IF(E19>0,1,0) -> 0 | F29: =IF(F19>0,1,0) -> 0 | G29: =IF(G19>0,1,0) -> 0 | H29: =IF(H19>0,1,0) -> 1 | I29: =IF(I19>0,1,0) -> 1 | J29: =IF(J19>0,1,0) -> 1 | ... AL29: =IF(AL19>0,1,0) -> 1

Sheet P&L
A1: Annual P&L and cash
A2: Rolled up from the Monthly sheet with SUMIF on the year row.
A3: Year # | B3: 1 | C3: 2 | D3: 3
B4: Year 1 | C4: Year 2 | D4: Year 3
A5: Revenue | B5: =SUMIF(Monthly!$C$4:$AL$4,B$3,Monthly!$C$10:$AL$10) -> 319800 | C5: =SUMIF(Monthly!$C$4:$AL$4,C$3,Monthly!$C$10:$AL$10) -> 408769.92 | D5: =SUMIF(Monthly!$C$4:$AL$4,D$3,Monthly!$C$10:$AL$10) -> 446295
A6: COGS | B6: =SUMIF(Monthly!$C$4:$AL$4,B$3,Monthly!$C$11:$AL$11) -> -105534 | C6: =SUMIF(Monthly!$C$4:$AL$4,C$3,Monthly!$C$11:$AL$11) -> -134894.07 | D6: =SUMIF(Monthly!$C$4:$AL$4,D$3,Monthly!$C$11:$AL$11) -> -147277.35
A7: Gross profit | B7: =SUMIF(Monthly!$C$4:$AL$4,B$3,Monthly!$C$12:$AL$12) -> 214266 | C7: =SUMIF(Monthly!$C$4:$AL$4,C$3,Monthly!$C$12:$AL$12) -> 273875.85 | D7: =SUMIF(Monthly!$C$4:$AL$4,D$3,Monthly!$C$12:$AL$12) -> 299017.65
A8: Gross margin | B8: =IF(B5=0,0,B7/B5) -> 0.67 | C8: =IF(C5=0,0,C7/C5) -> 0.67 | D8: =IF(D5=0,0,D7/D5) -> 0.67
A9: Rent | B9: =SUMIF(Monthly!$C$4:$AL$4,B$3,Monthly!$C$14:$AL$14) -> -54000 | C9: =SUMIF(Monthly!$C$4:$AL$4,C$3,Monthly!$C$14:$AL$14) -> -54000 | D9: =SUMIF(Monthly!$C$4:$AL$4,D$3,Monthly!$C$14:$AL$14) -> -54000
A10: Payroll | B10: =SUMIF(Monthly!$C$4:$AL$4,B$3,Monthly!$C$15:$AL$15) -> -125440 | C10: =SUMIF(Monthly!$C$4:$AL$4,C$3,Monthly!$C$15:$AL$15) -> -129203.2 | D10: =SUMIF(Monthly!$C$4:$AL$4,D$3,Monthly!$C$15:$AL$15) -> -133079.3
A11: Marketing | B11: =SUMIF(Monthly!$C$4:$AL$4,B$3,Monthly!$C$16:$AL$16) -> -9594 | C11: =SUMIF(Monthly!$C$4:$AL$4,C$3,Monthly!$C$16:$AL$16) -> -12263.098 | D11: =SUMIF(Monthly!$C$4:$AL$4,D$3,Monthly!$C$16:$AL$16) -> -13388.85
A12: Utilities & other | B12: =SUMIF(Monthly!$C$4:$AL$4,B$3,Monthly!$C$17:$AL$17) -> -24000 | C12: =SUMIF(Monthly!$C$4:$AL$4,C$3,Monthly!$C$17:$AL$17) -> -24000 | D12: =SUMIF(Monthly!$C$4:$AL$4,D$3,Monthly!$C$17:$AL$17) -> -24000
A13: Total operating expenses | B13: =SUMIF(Monthly!$C$4:$AL$4,B$3,Monthly!$C$18:$AL$18) -> -213034 | C13: =SUMIF(Monthly!$C$4:$AL$4,C$3,Monthly!$C$18:$AL$18) -> -219466.3 | D13: =SUMIF(Monthly!$C$4:$AL$4,D$3,Monthly!$C$18:$AL$18) -> -224468.15
A14: EBITDA | B14: =SUMIF(Monthly!$C$4:$AL$4,B$3,Monthly!$C$19:$AL$19) -> 1232 | C14: =SUMIF(Monthly!$C$4:$AL$4,C$3,Monthly!$C$19:$AL$19) -> 54409.549 | D14: =SUMIF(Monthly!$C$4:$AL$4,D$3,Monthly!$C$19:$AL$19) -> 74549.503
A15: EBITDA margin | B15: =IF(B5=0,0,B14/B5) -> 0.0038524078 | C15: =IF(C5=0,0,C14/C5) -> 0.13310556 | D15: =IF(D5=0,0,D14/D5) -> 0.16704087
A16: Depreciation | B16: =SUMIF(Monthly!$C$4:$AL$4,B$3,Monthly!$C$20:$AL$20) -> -22857.143 | C16: =SUMIF(Monthly!$C$4:$AL$4,C$3,Monthly!$C$20:$AL$20) -> -22857.143 | D16: =SUMIF(Monthly!$C$4:$AL$4,D$3,Monthly!$C$20:$AL$20) -> -22857.143
A17: EBIT | B17: =SUMIF(Monthly!$C$4:$AL$4,B$3,Monthly!$C$21:$AL$21) -> -21625.143 | C17: =SUMIF(Monthly!$C$4:$AL$4,C$3,Monthly!$C$21:$AL$21) -> 31552.406 | D17: =SUMIF(Monthly!$C$4:$AL$4,D$3,Monthly!$C$21:$AL$21) -> 51692.36
A18: Income tax | B18: =SUMIF(Monthly!$C$4:$AL$4,B$3,Monthly!$C$22:$AL$22) -> -1398.48 | C18: =SUMIF(Monthly!$C$4:$AL$4,C$3,Monthly!$C$22:$AL$22) -> -6626.0052 | D18: =SUMIF(Monthly!$C$4:$AL$4,D$3,Monthly!$C$22:$AL$22) -> -10855.396
A19: Net income | B19: =SUMIF(Monthly!$C$4:$AL$4,B$3,Monthly!$C$23:$AL$23) -> -23023.623 | C19: =SUMIF(Monthly!$C$4:$AL$4,C$3,Monthly!$C$23:$AL$23) -> 24926.401 | D19: =SUMIF(Monthly!$C$4:$AL$4,D$3,Monthly!$C$23:$AL$23) -> 40836.965
A20: Net margin | B20: =IF(B5=0,0,B19/B5) -> -0.071993818 | C20: =IF(C5=0,0,C19/C5) -> 0.060979048 | D20: =IF(D5=0,0,D19/D5) -> 0.091502178
A21: Year-end cash | B21: =INDEX(Monthly!$C$27:$AL$27,B3*12) -> 59833.52 | C21: =INDEX(Monthly!$C$27:$AL$27,C3*12) -> 107617.06 | D21: =INDEX(Monthly!$C$27:$AL$27,D3*12) -> 171311.17

Sheet Checks
A1: Model checks
A2: Live formulas: they re-run every time an input changes.
A3: Check | B3: Result | C3: What it tests
A4: Annual revenue ties to monthly | B4: =IF(ABS(SUM('P&L'!B5:D5)-SUM(Monthly!$C$10:$AL$10))<0.5,"PASS","FAIL") -> PASS | C4: Sum of annual revenue equals sum of monthly revenue
A5: Cash roll-forward | B5: =IF(ABS(Monthly!$AL$27-(Monthly!$C$25+SUM(Monthly!$C$26:$AL$26)))<0.5,"PASS","FAIL") -> PASS | C5: Closing cash = opening cash + all operating cash flow
A6: EBITDA reconciliation | B6: =IF(ABS(SUM(Monthly!$C$19:$AL$19)-SUM(Monthly!$C$12:$AL$12)-SUM(Monthly!$C$18:$AL$18))<0.5,"PASS","FAIL") -> PASS | C6: EBITDA = gross profit − operating expenses, every month
A7: Scenario selector valid | B7: =IF(AND(ISNUMBER(Dashboard!B4),Dashboard!B4>=1,Dashboard!B4<=3,INT(Dashboard!B4)=Dashboard!B4),"PASS","FAIL") -> PASS | C7: Dashboard!B4 is 1, 2 or 3
A8: Scenario ordering on revenue drivers | B8: =IF(AND(Inputs!$B$5<=Inputs!$C$5,Inputs!$C$5<=Inputs!$D$5,Inputs!$B$9<=Inputs!$C$9,Inputs!$C$9<=Inputs!$D$9),"PASS","FAIL") -> PASS | C8: Low ≤ Base ≤ High for traffic and ticket
A9: Margins within 0–100% | B9: =IF(AND(MIN('P&L'!B8:D8)>=0,MAX('P&L'!B8:D8)<=1),"PASS","FAIL") -> PASS | C9: Gross margin never negative or above 100%
A10: No error values | B10: =IF(SUMPRODUCT(--ISERROR(Monthly!$C$3:$AL$29))=0,"PASS","FAIL") -> PASS | C10: No error values (divide-by-zero, broken references, bad types) in the monthly grid
A11: Funding sufficient (cash ≥ 0) | B11: =IF(MIN(Monthly!$C$27:$AL$27)>=0,"PASS","WARN") -> PASS | C11: Business warning, not an error: cash dips below zero in this scenario
A13: Overall verdict | B13: =IF(COUNTIF(B4:B11,"FAIL")>0,"FAIL",IF(COUNTIF(B4:B11,"WARN")>0,"PASS WITH WARNINGS","PASS")) -> PASS
