Workbook

Sheet Cover
B2: SaaS company — financial model
B3: 5-year financial model · monthly detail · Low / Base / High scenarios · US dollars
B5: Active scenario | D5: =Dashboard!C4&" (change on the Dashboard, cell B4)" -> Base (change on the Dashboard, cell B4)
B6: Model checks | D6: =Checks!B22 -> PASS
B7: Prepared | D7: 20 October 2026
B9: Contents
C10: PRESENTATION
B11: 1 | C11: =HYPERLINK("#'Dashboard'!A1","Dashboard") -> Dashboard | D11: Scenario switch, key numbers, core financials, 4 charts
B12: 2 | C12: =HYPERLINK("#'Summary'!A1","Summary") -> Summary | D12: Income statement, cash flow, balance sheet — 5 years and any year by month
B13: 3 | C13: =HYPERLINK("#'Scenarios'!A1","Scenarios") -> Scenarios | D13: Low / Base / High side by side: drivers, outputs, charts
B14: 4 | C14: =HYPERLINK("#'Break-even'!A1","Break-even") -> Break-even | D14: Startup costs, funding need, break-even timing and revenue
B15: 5 | C15: =HYPERLINK("#'Valuation'!A1","Valuation") -> Valuation | D15: Free cash flow, DCF (perpetual growth and exit multiple), WACC × growth sensitivity
B16: 6 | C16: =HYPERLINK("#'Sources & Uses'!A1","Sources & Uses") -> Sources & Uses | D16: Funding structure, sources and uses of cash for the first months
B17: 7 | C17: =HYPERLINK("#'KPIs'!A1","KPIs") -> KPIs | D17: Industry metrics, financial ratios, DuPont analysis
C18: INPUTS
B19: 8 | C19: =HYPERLINK("#'Inputs'!A1","Inputs") -> Inputs | D19: Every assumption, Low / Base / High, with units and comments
C20: STATEMENTS
B21: 9 | C21: =HYPERLINK("#'P&L'!A1","P&L") -> P&L | D21: Annual profit & loss
B22: 10 | C22: =HYPERLINK("#'Cash Flow'!A1","Cash Flow") -> Cash Flow | D22: Annual cash flow statement
B23: 11 | C23: =HYPERLINK("#'Balance Sheet'!A1","Balance Sheet") -> Balance Sheet | D23: Balance sheet at year end
C24: CALCULATIONS
B25: 12 | C25: =HYPERLINK("#'Monthly'!A1","Monthly") -> Monthly | D25: Month-by-month engine of the model
B26: 13 | C26: =HYPERLINK("#'Headcount'!A1","Headcount") -> Headcount | D26: Team and payroll by month
C27: CONTROL
B28: 14 | C28: =HYPERLINK("#'Checks'!A1","Checks") -> Checks | D28: Live integrity checks; overall verdict
B30: How to read this file
C31: 1,000 | D31: Input you can change (yellow cell, blue figure) — on Inputs, plus the two view switches
C32: 1,000 | D32: Formula — calculated, do not overwrite
C33: 1,000 | D33: Link to another sheet
C34: 1,000 | D34: Active value the model uses
B36: Prototype of workbook standard v1 (internal review). Numbers come from the production engine; the Scenarios sheet's Low / Base / High columns are a build-time snapshot.

Sheet Dashboard
A1: Dashboard | W1: =HYPERLINK("#'Cover'!A1","◂ Contents") -> ◂ Contents
A2: SaaS company — financial model
A4: Active scenario | B4: 2 | C4: =CHOOSE(B4,"Low","Base","High") -> Base | D4: 1 = Low · 2 = Base · 3 = High — every sheet follows this cell | S4: Model checks | T4: =Checks!B22 -> PASS
A6: REVENUE · YEAR 5 | C6: EBITDA MARGIN · YEAR 5 | H6: NET INCOME · YEAR 5 | L6: LOWEST CASH BALANCE | P6: FUNDING REQUIRED | T6: ENTERPRISE VALUE (DCF)
A7: ='P&L'!F5 -> 26732395 | C7: ='P&L'!F16 -> 0.25044286 | H7: ='P&L'!F22 -> 5289000.5 | L7: =MIN(Monthly!$C$76:$BJ$76) -> 1760226.5 | P7: ='Break-even'!B12 -> 1145773.5 | T7: =Valuation!B30 -> 40195041
A8: =IF('P&L'!B5>0,"CAGR "&TEXT(('P&L'!F5/'P&L'!B5)^(1/4)-1,"0%"),"") -> CAGR 27% | C8: ="EBITDA "&TEXT('P&L'!F15/1000000,"$0.0")&"M" -> EBITDA $6.7M | H8: ="Net margin "&TEXT('P&L'!F23,"0%") -> Net margin 20% | L8: ="in month "&MATCH(MIN(Monthly!$C$76:$BJ$76),Monthly!$C$76:$BJ$76,0) -> in month 1 | P8: =IF('Break-even'!B17>=0,"Covered by funding raised","Shortfall "&TEXT(-'Break-even'!B17/1000000,"$0.0")&"M") -> Shortfall $0.1M | T8: ="Average of 2 methods" -> Average of 2 methods
A10: Core financials ($'000) — active scenario
B11: ='P&L'!B4 -> Year 1 | C11: ='P&L'!C4 -> Year 2 | D11: ='P&L'!D4 -> Year 3 | E11: ='P&L'!E4 -> Year 4 | F11: ='P&L'!F4 -> Year 5
A12: Revenue | B12: ='P&L'!B5 -> 10216766 | C12: ='P&L'!C5 -> 12946280 | D12: ='P&L'!D5 -> 16448495 | E12: ='P&L'!E5 -> 20947000 | F12: ='P&L'!F5 -> 26732395
A13: Gross profit | B13: ='P&L'!B7 -> 9115572.1 | C13: ='P&L'!C7 -> 11555505 | D13: ='P&L'!D7 -> 14686438 | E13: ='P&L'!E7 -> 18708530 | F13: ='P&L'!F7 -> 23881957
A14: Gross margin | B14: ='P&L'!B8 -> 0.89221699 | C14: ='P&L'!C8 -> 0.8925734 | D14: ='P&L'!D8 -> 0.89287426 | E14: ='P&L'!E8 -> 0.89313648 | F14: ='P&L'!F8 -> 0.89337139
A15: Operating expenses | B15: ='P&L'!B14 -> -7622400 | C15: ='P&L'!C14 -> -9305892 | D15: ='P&L'!D14 -> -11392489 | E15: ='P&L'!E14 -> -13979315 | F15: ='P&L'!F14 -> -17187019
A16: EBITDA | B16: ='P&L'!B15 -> 1493172.1 | C16: ='P&L'!C15 -> 2249612.9 | D16: ='P&L'!D15 -> 3293948.5 | E16: ='P&L'!E15 -> 4729214.2 | F16: ='P&L'!F15 -> 6694937.4
A17: EBITDA margin | B17: ='P&L'!B16 -> 0.14614919 | C17: ='P&L'!C16 -> 0.1737652 | D17: ='P&L'!D16 -> 0.20025835 | E17: ='P&L'!E16 -> 0.22577048 | F17: ='P&L'!F16 -> 0.25044286
A18: Net income | B18: ='P&L'!B22 -> 1140105.9 | C18: ='P&L'!C22 -> 1737694.2 | D18: ='P&L'!D22 -> 2562719.3 | E18: ='P&L'!E22 -> 3736079.2 | F18: ='P&L'!F22 -> 5289000.5
A19: Net margin | B19: ='P&L'!B23 -> 0.11159167 | C19: ='P&L'!C23 -> 0.13422344 | D19: ='P&L'!D23 -> 0.15580266 | E19: ='P&L'!E23 -> 0.17835868 | F19: ='P&L'!F23 -> 0.19784986
A20: Operating cash flow | B20: ='Cash Flow'!B11 -> 2273134.7 | C20: ='Cash Flow'!C11 -> 2078342.8 | D20: ='Cash Flow'!D11 -> 2985771.8 | E20: ='Cash Flow'!E11 -> 4215445.8 | F20: ='Cash Flow'!F11 -> 5905773.3
A21: Investing cash flow | B21: ='Cash Flow'!B12 -> -150000 | C21: ='Cash Flow'!C12 -> 0 | D21: ='Cash Flow'!D12 -> 0 | E21: ='Cash Flow'!E12 -> 0 | F21: ='Cash Flow'!F12 -> 0
A22: Financing cash flow | B22: ='Cash Flow'!B16 -> 1000000 | C22: ='Cash Flow'!C16 -> 0 | D22: ='Cash Flow'!D16 -> 0 | E22: ='Cash Flow'!E16 -> 0 | F22: ='Cash Flow'!F16 -> 0
A23: Net change in cash | B23: ='Cash Flow'!B17 -> 3123134.7 | C23: ='Cash Flow'!C17 -> 2078342.8 | D23: ='Cash Flow'!D17 -> 2985771.8 | E23: ='Cash Flow'!E17 -> 4215445.8 | F23: ='Cash Flow'!F17 -> 5905773.3
A24: Year-end cash | B24: ='Balance Sheet'!B5 -> 3123134.7 | C24: ='Balance Sheet'!C5 -> 5201477.5 | D24: ='Balance Sheet'!D5 -> 8187249.2 | E24: ='Balance Sheet'!E5 -> 12402695 | F24: ='Balance Sheet'!F5 -> 18308468
A26: SaaS metrics
B27: ='P&L'!B4 -> Year 1 | C27: ='P&L'!C4 -> Year 2 | D27: ='P&L'!D4 -> Year 3 | E27: ='P&L'!E4 -> Year 4 | F27: ='P&L'!F4 -> Year 5
A28: Paying customers (year end) | B28: =KPIs!B27 -> 3608.1828 | C28: =KPIs!C27 -> 4380.8763 | D28: =KPIs!D27 -> 5357.1408 | E28: =KPIs!E27 -> 6586.8077 | F28: =KPIs!F27 -> 8133.3379
A29: ARR (year-end MRR × 12) | B29: =KPIs!B31 -> 11385918 | C29: =KPIs!C31 -> 14445582 | D29: =KPIs!D31 -> 18373030 | E29: =KPIs!E31 -> 23420246 | F29: =KPIs!F31 -> 29914934
A30: LTV ÷ CAC | B30: =KPIs!B40 -> 26.069112 | C30: =KPIs!C40 -> 28.160132 | D30: =KPIs!D40 -> 30.323023 | E30: =KPIs!E40 -> 32.59655 | F30: =KPIs!F40 -> 35.017261
A31: Team (FTE, year end) | B31: =INDEX(Headcount!$C$12:$BJ$12,12) -> 48 | C31: =INDEX(Headcount!$C$12:$BJ$12,24) -> 57.3 | D31: =INDEX(Headcount!$C$12:$BJ$12,36) -> 68.415 | E31: =INDEX(Headcount!$C$12:$BJ$12,48) -> 81.70125 | F31: =INDEX(Headcount!$C$12:$BJ$12,60) -> 97.585238
A33: Funding & valuation ($'000) — active scenario
A34: Equity raised | F34: =Inputs!E46 -> 1000000
A35: Loan drawn | F35: =Inputs!E47 -> 0
A36: Funding required (incl. cash buffer) | F36: ='Break-even'!B12 -> 1145773.5
A37: Funding surplus / (shortfall) | F37: ='Break-even'!B17 -> -145773.53
A38: ="Lowest cash balance (month "&MATCH(MIN(Monthly!$C$76:$BJ$76),Monthly!$C$76:$BJ$76,0)&")" -> Lowest cash balance (month 1) | F38: =MIN(Monthly!$C$76:$BJ$76) -> 1760226.5
A39: First month with positive EBITDA | F39: ='Break-even'!B21 -> 1
A40: Cash invested paid back | F40: =IF(ISNUMBER('Break-even'!B23),"Month "&'Break-even'!B23,'Break-even'!B23) -> No investment to pay back
A41: Enterprise value — perpetual growth | F41: =Valuation!B27 -> 45888961
A42: Enterprise value — exit multiple | F42: =Valuation!C27 -> 34501121
A43: Enterprise value — average | F43: =Valuation!B30 -> 40195041

Sheet Summary
A1: Financial statements summary | U1: =HYPERLINK("#'Cover'!A1","◂ Contents") -> ◂ Contents
A2: SaaS company — financial model | P2: Select detailed year: | R2: 1
A5: Income statement ($'000) — 5 years | H5: ="Income statement ($'000) — Year "&$R$2&", by month" -> Income statement ($'000) — Year 1, by month
B6: ='P&L'!B4 -> Year 1 | C6: ='P&L'!C4 -> Year 2 | D6: ='P&L'!D4 -> Year 3 | E6: ='P&L'!E4 -> Year 4 | F6: ='P&L'!F4 -> Year 5 | H6: =INDEX(Monthly!$C$3:$BJ$3,($R$2-1)*12+1) -> M1 | I6: =INDEX(Monthly!$C$3:$BJ$3,($R$2-1)*12+2) -> M2 | J6: =INDEX(Monthly!$C$3:$BJ$3,($R$2-1)*12+3) -> M3 | K6: =INDEX(Monthly!$C$3:$BJ$3,($R$2-1)*12+4) -> M4 | L6: =INDEX(Monthly!$C$3:$BJ$3,($R$2-1)*12+5) -> M5 | M6: =INDEX(Monthly!$C$3:$BJ$3,($R$2-1)*12+6) -> M6 | N6: =INDEX(Monthly!$C$3:$BJ$3,($R$2-1)*12+7) -> M7 | O6: =INDEX(Monthly!$C$3:$BJ$3,($R$2-1)*12+8) -> M8 | P6: =INDEX(Monthly!$C$3:$BJ$3,($R$2-1)*12+9) -> M9 | Q6: =INDEX(Monthly!$C$3:$BJ$3,($R$2-1)*12+10) -> M10 | R6: =INDEX(Monthly!$C$3:$BJ$3,($R$2-1)*12+11) -> M11 | S6: =INDEX(Monthly!$C$3:$BJ$3,($R$2-1)*12+12) -> M12
A7: Revenue | B7: ='P&L'!B5 -> 10216766 | C7: ='P&L'!C5 -> 12946280 | D7: ='P&L'!D5 -> 16448495 | E7: ='P&L'!E5 -> 20947000 | F7: ='P&L'!F5 -> 26732395 | H7: =INDEX(Monthly!$C$24:$BJ$24,($R$2-1)*12+1) -> 758750 | I7: =INDEX(Monthly!$C$24:$BJ$24,($R$2-1)*12+2) -> 776162.5 | J7: =INDEX(Monthly!$C$24:$BJ$24,($R$2-1)*12+3) -> 793400.88 | K7: =INDEX(Monthly!$C$24:$BJ$24,($R$2-1)*12+4) -> 810466.87 | L7: =INDEX(Monthly!$C$24:$BJ$24,($R$2-1)*12+5) -> 827362.2 | M7: =INDEX(Monthly!$C$24:$BJ$24,($R$2-1)*12+6) -> 844088.58 | N7: =INDEX(Monthly!$C$24:$BJ$24,($R$2-1)*12+7) -> 860647.69 | O7: =INDEX(Monthly!$C$24:$BJ$24,($R$2-1)*12+8) -> 877041.21 | P7: =INDEX(Monthly!$C$24:$BJ$24,($R$2-1)*12+9) -> 893270.8 | Q7: =INDEX(Monthly!$C$24:$BJ$24,($R$2-1)*12+10) -> 909338.09 | R7: =INDEX(Monthly!$C$24:$BJ$24,($R$2-1)*12+11) -> 925244.71 | S7: =INDEX(Monthly!$C$24:$BJ$24,($R$2-1)*12+12) -> 940992.26
A8: Cost of revenue | B8: ='P&L'!B6 -> -1101193.7 | C8: ='P&L'!C6 -> -1390774.9 | D8: ='P&L'!D6 -> -1762057.1 | E8: ='P&L'!E6 -> -2238470.1 | F8: ='P&L'!F6 -> -2850438 | H8: =INDEX(Monthly!$C$25:$BJ$25,($R$2-1)*12+1) -> -81930 | I8: =INDEX(Monthly!$C$25:$BJ$25,($R$2-1)*12+2) -> -83780.425 | J8: =INDEX(Monthly!$C$25:$BJ$25,($R$2-1)*12+3) -> -85611.8 | K8: =INDEX(Monthly!$C$25:$BJ$25,($R$2-1)*12+4) -> -87424.323 | L8: =INDEX(Monthly!$C$25:$BJ$25,($R$2-1)*12+5) -> -89218.192 | M8: =INDEX(Monthly!$C$25:$BJ$25,($R$2-1)*12+6) -> -90993.6 | N8: =INDEX(Monthly!$C$25:$BJ$25,($R$2-1)*12+7) -> -92750.74 | O8: =INDEX(Monthly!$C$25:$BJ$25,($R$2-1)*12+8) -> -94489.803 | P8: =INDEX(Monthly!$C$25:$BJ$25,($R$2-1)*12+9) -> -96210.977 | Q8: =INDEX(Monthly!$C$25:$BJ$25,($R$2-1)*12+10) -> -97914.447 | R8: =INDEX(Monthly!$C$25:$BJ$25,($R$2-1)*12+11) -> -99600.4 | S8: =INDEX(Monthly!$C$25:$BJ$25,($R$2-1)*12+12) -> -101269.02
A9: Gross profit | B9: ='P&L'!B7 -> 9115572.1 | C9: ='P&L'!C7 -> 11555505 | D9: ='P&L'!D7 -> 14686438 | E9: ='P&L'!E7 -> 18708530 | F9: ='P&L'!F7 -> 23881957 | H9: =INDEX(Monthly!$C$26:$BJ$26,($R$2-1)*12+1) -> 676820 | I9: =INDEX(Monthly!$C$26:$BJ$26,($R$2-1)*12+2) -> 692382.07 | J9: =INDEX(Monthly!$C$26:$BJ$26,($R$2-1)*12+3) -> 707789.08 | K9: =INDEX(Monthly!$C$26:$BJ$26,($R$2-1)*12+4) -> 723042.54 | L9: =INDEX(Monthly!$C$26:$BJ$26,($R$2-1)*12+5) -> 738144.01 | M9: =INDEX(Monthly!$C$26:$BJ$26,($R$2-1)*12+6) -> 753094.98 | N9: =INDEX(Monthly!$C$26:$BJ$26,($R$2-1)*12+7) -> 767896.95 | O9: =INDEX(Monthly!$C$26:$BJ$26,($R$2-1)*12+8) -> 782551.41 | P9: =INDEX(Monthly!$C$26:$BJ$26,($R$2-1)*12+9) -> 797059.82 | Q9: =INDEX(Monthly!$C$26:$BJ$26,($R$2-1)*12+10) -> 811423.65 | R9: =INDEX(Monthly!$C$26:$BJ$26,($R$2-1)*12+11) -> 825644.31 | S9: =INDEX(Monthly!$C$26:$BJ$26,($R$2-1)*12+12) -> 839723.25
A10: Gross margin | B10: ='P&L'!B8 -> 0.89221699 | C10: ='P&L'!C8 -> 0.8925734 | D10: ='P&L'!D8 -> 0.89287426 | E10: ='P&L'!E8 -> 0.89313648 | F10: ='P&L'!F8 -> 0.89337139 | H10: =IF(H7=0,0,H9/H7) -> 0.89201977 | I10: =IF(I7=0,0,I9/I7) -> 0.89205814 | J10: =IF(J7=0,0,J9/J7) -> 0.89209515 | K10: =IF(K7=0,0,K9/K7) -> 0.89213091 | L10: =IF(L7=0,0,L9/L7) -> 0.8921655 | M10: =IF(M7=0,0,M9/M7) -> 0.89219899 | N10: =IF(N7=0,0,N9/N7) -> 0.89223147 | O10: =IF(O7=0,0,O9/O7) -> 0.89226298 | ... S10: =IF(S7=0,0,S9/S7) -> 0.89238061
A11: Operating expenses | B11: ='P&L'!B14 -> -7622400 | C11: ='P&L'!C14 -> -9305892 | D11: ='P&L'!D14 -> -11392489 | E11: ='P&L'!E14 -> -13979315 | F11: ='P&L'!F14 -> -17187019 | H11: =INDEX(Monthly!$C$34:$BJ$34,($R$2-1)*12+1) -> -635200 | I11: =INDEX(Monthly!$C$34:$BJ$34,($R$2-1)*12+2) -> -635200 | J11: =INDEX(Monthly!$C$34:$BJ$34,($R$2-1)*12+3) -> -635200 | K11: =INDEX(Monthly!$C$34:$BJ$34,($R$2-1)*12+4) -> -635200 | L11: =INDEX(Monthly!$C$34:$BJ$34,($R$2-1)*12+5) -> -635200 | M11: =INDEX(Monthly!$C$34:$BJ$34,($R$2-1)*12+6) -> -635200 | N11: =INDEX(Monthly!$C$34:$BJ$34,($R$2-1)*12+7) -> -635200 | O11: =INDEX(Monthly!$C$34:$BJ$34,($R$2-1)*12+8) -> -635200 | P11: =INDEX(Monthly!$C$34:$BJ$34,($R$2-1)*12+9) -> -635200 | Q11: =INDEX(Monthly!$C$34:$BJ$34,($R$2-1)*12+10) -> -635200 | R11: =INDEX(Monthly!$C$34:$BJ$34,($R$2-1)*12+11) -> -635200 | S11: =INDEX(Monthly!$C$34:$BJ$34,($R$2-1)*12+12) -> -635200
A12: EBITDA | B12: ='P&L'!B15 -> 1493172.1 | C12: ='P&L'!C15 -> 2249612.9 | D12: ='P&L'!D15 -> 3293948.5 | E12: ='P&L'!E15 -> 4729214.2 | F12: ='P&L'!F15 -> 6694937.4 | H12: =INDEX(Monthly!$C$35:$BJ$35,($R$2-1)*12+1) -> 41620 | I12: =INDEX(Monthly!$C$35:$BJ$35,($R$2-1)*12+2) -> 57182.075 | J12: =INDEX(Monthly!$C$35:$BJ$35,($R$2-1)*12+3) -> 72589.075 | K12: =INDEX(Monthly!$C$35:$BJ$35,($R$2-1)*12+4) -> 87842.543 | L12: =INDEX(Monthly!$C$35:$BJ$35,($R$2-1)*12+5) -> 102944.01 | M12: =INDEX(Monthly!$C$35:$BJ$35,($R$2-1)*12+6) -> 117894.98 | N12: =INDEX(Monthly!$C$35:$BJ$35,($R$2-1)*12+7) -> 132696.95 | O12: =INDEX(Monthly!$C$35:$BJ$35,($R$2-1)*12+8) -> 147351.41 | P12: =INDEX(Monthly!$C$35:$BJ$35,($R$2-1)*12+9) -> 161859.82 | Q12: =INDEX(Monthly!$C$35:$BJ$35,($R$2-1)*12+10) -> 176223.65 | R12: =INDEX(Monthly!$C$35:$BJ$35,($R$2-1)*12+11) -> 190444.31 | S12: =INDEX(Monthly!$C$35:$BJ$35,($R$2-1)*12+12) -> 204523.25
A13: EBITDA margin | B13: ='P&L'!B16 -> 0.14614919 | C13: ='P&L'!C16 -> 0.1737652 | D13: ='P&L'!D16 -> 0.20025835 | E13: ='P&L'!E16 -> 0.22577048 | F13: ='P&L'!F16 -> 0.25044286 | H13: =IF(H7=0,0,H12/H7) -> 0.054853377 | I13: =IF(I7=0,0,I12/I7) -> 0.073672813 | J13: =IF(J7=0,0,J12/J7) -> 0.091491045 | K13: =IF(K7=0,0,K12/K7) -> 0.10838511 | L13: =IF(L7=0,0,L12/L7) -> 0.12442435 | M13: =IF(M7=0,0,M12/M7) -> 0.13967133 | N13: =IF(N7=0,0,N12/N7) -> 0.15418266 | O13: =IF(O7=0,0,O12/O7) -> 0.16800968 | ... S13: =IF(S7=0,0,S12/S7) -> 0.21734849
A14: Depreciation | B14: ='P&L'!B17 -> -50000 | C14: ='P&L'!C17 -> -50000 | D14: ='P&L'!D17 -> -50000 | E14: ='P&L'!E17 -> 0 | F14: ='P&L'!F17 -> 0 | H14: =INDEX(Monthly!$C$49:$BJ$49,($R$2-1)*12+1) -> -4166.6667 | I14: =INDEX(Monthly!$C$49:$BJ$49,($R$2-1)*12+2) -> -4166.6667 | J14: =INDEX(Monthly!$C$49:$BJ$49,($R$2-1)*12+3) -> -4166.6667 | K14: =INDEX(Monthly!$C$49:$BJ$49,($R$2-1)*12+4) -> -4166.6667 | L14: =INDEX(Monthly!$C$49:$BJ$49,($R$2-1)*12+5) -> -4166.6667 | M14: =INDEX(Monthly!$C$49:$BJ$49,($R$2-1)*12+6) -> -4166.6667 | N14: =INDEX(Monthly!$C$49:$BJ$49,($R$2-1)*12+7) -> -4166.6667 | O14: =INDEX(Monthly!$C$49:$BJ$49,($R$2-1)*12+8) -> -4166.6667 | P14: =INDEX(Monthly!$C$49:$BJ$49,($R$2-1)*12+9) -> -4166.6667 | Q14: =INDEX(Monthly!$C$49:$BJ$49,($R$2-1)*12+10) -> -4166.6667 | R14: =INDEX(Monthly!$C$49:$BJ$49,($R$2-1)*12+11) -> -4166.6667 | S14: =INDEX(Monthly!$C$49:$BJ$49,($R$2-1)*12+12) -> -4166.6667
A15: EBIT | B15: ='P&L'!B18 -> 1443172.1 | C15: ='P&L'!C18 -> 2199612.9 | D15: ='P&L'!D18 -> 3243948.5 | E15: ='P&L'!E18 -> 4729214.2 | F15: ='P&L'!F18 -> 6694937.4 | H15: =INDEX(Monthly!$C$38:$BJ$38,($R$2-1)*12+1) -> 37453.333 | I15: =INDEX(Monthly!$C$38:$BJ$38,($R$2-1)*12+2) -> 53015.408 | J15: =INDEX(Monthly!$C$38:$BJ$38,($R$2-1)*12+3) -> 68422.408 | K15: =INDEX(Monthly!$C$38:$BJ$38,($R$2-1)*12+4) -> 83675.876 | L15: =INDEX(Monthly!$C$38:$BJ$38,($R$2-1)*12+5) -> 98777.339 | M15: =INDEX(Monthly!$C$38:$BJ$38,($R$2-1)*12+6) -> 113728.31 | N15: =INDEX(Monthly!$C$38:$BJ$38,($R$2-1)*12+7) -> 128530.28 | O15: =INDEX(Monthly!$C$38:$BJ$38,($R$2-1)*12+8) -> 143184.74 | P15: =INDEX(Monthly!$C$38:$BJ$38,($R$2-1)*12+9) -> 157693.16 | Q15: =INDEX(Monthly!$C$38:$BJ$38,($R$2-1)*12+10) -> 172056.98 | R15: =INDEX(Monthly!$C$38:$BJ$38,($R$2-1)*12+11) -> 186277.65 | S15: =INDEX(Monthly!$C$38:$BJ$38,($R$2-1)*12+12) -> 200356.58
A16: Interest | B16: ='P&L'!B19 -> 0 | C16: ='P&L'!C19 -> 0 | D16: ='P&L'!D19 -> 0 | E16: ='P&L'!E19 -> 0 | F16: ='P&L'!F19 -> 0 | H16: =INDEX(Monthly!$C$39:$BJ$39,($R$2-1)*12+1) -> 0 | I16: =INDEX(Monthly!$C$39:$BJ$39,($R$2-1)*12+2) -> 0 | J16: =INDEX(Monthly!$C$39:$BJ$39,($R$2-1)*12+3) -> 0 | K16: =INDEX(Monthly!$C$39:$BJ$39,($R$2-1)*12+4) -> 0 | L16: =INDEX(Monthly!$C$39:$BJ$39,($R$2-1)*12+5) -> 0 | M16: =INDEX(Monthly!$C$39:$BJ$39,($R$2-1)*12+6) -> 0 | N16: =INDEX(Monthly!$C$39:$BJ$39,($R$2-1)*12+7) -> 0 | O16: =INDEX(Monthly!$C$39:$BJ$39,($R$2-1)*12+8) -> 0 | P16: =INDEX(Monthly!$C$39:$BJ$39,($R$2-1)*12+9) -> 0 | Q16: =INDEX(Monthly!$C$39:$BJ$39,($R$2-1)*12+10) -> 0 | R16: =INDEX(Monthly!$C$39:$BJ$39,($R$2-1)*12+11) -> 0 | S16: =INDEX(Monthly!$C$39:$BJ$39,($R$2-1)*12+12) -> 0
A17: Pre-tax income | B17: ='P&L'!B20 -> 1443172.1 | C17: ='P&L'!C20 -> 2199612.9 | D17: ='P&L'!D20 -> 3243948.5 | E17: ='P&L'!E20 -> 4729214.2 | F17: ='P&L'!F20 -> 6694937.4 | H17: =INDEX(Monthly!$C$40:$BJ$40,($R$2-1)*12+1) -> 37453.333 | I17: =INDEX(Monthly!$C$40:$BJ$40,($R$2-1)*12+2) -> 53015.408 | J17: =INDEX(Monthly!$C$40:$BJ$40,($R$2-1)*12+3) -> 68422.408 | K17: =INDEX(Monthly!$C$40:$BJ$40,($R$2-1)*12+4) -> 83675.876 | L17: =INDEX(Monthly!$C$40:$BJ$40,($R$2-1)*12+5) -> 98777.339 | M17: =INDEX(Monthly!$C$40:$BJ$40,($R$2-1)*12+6) -> 113728.31 | N17: =INDEX(Monthly!$C$40:$BJ$40,($R$2-1)*12+7) -> 128530.28 | O17: =INDEX(Monthly!$C$40:$BJ$40,($R$2-1)*12+8) -> 143184.74 | P17: =INDEX(Monthly!$C$40:$BJ$40,($R$2-1)*12+9) -> 157693.16 | Q17: =INDEX(Monthly!$C$40:$BJ$40,($R$2-1)*12+10) -> 172056.98 | R17: =INDEX(Monthly!$C$40:$BJ$40,($R$2-1)*12+11) -> 186277.65 | S17: =INDEX(Monthly!$C$40:$BJ$40,($R$2-1)*12+12) -> 200356.58
A18: Income tax | B18: ='P&L'!B21 -> -303066.13 | C18: ='P&L'!C21 -> -461918.7 | D18: ='P&L'!D21 -> -681229.18 | E18: ='P&L'!E21 -> -993134.99 | F18: ='P&L'!F21 -> -1405936.8 | H18: =INDEX(Monthly!$C$43:$BJ$43,($R$2-1)*12+1) -> -7865.2 | I18: =INDEX(Monthly!$C$43:$BJ$43,($R$2-1)*12+2) -> -11133.236 | J18: =INDEX(Monthly!$C$43:$BJ$43,($R$2-1)*12+3) -> -14368.706 | K18: =INDEX(Monthly!$C$43:$BJ$43,($R$2-1)*12+4) -> -17571.934 | L18: =INDEX(Monthly!$C$43:$BJ$43,($R$2-1)*12+5) -> -20743.241 | M18: =INDEX(Monthly!$C$43:$BJ$43,($R$2-1)*12+6) -> -23882.945 | N18: =INDEX(Monthly!$C$43:$BJ$43,($R$2-1)*12+7) -> -26991.359 | O18: =INDEX(Monthly!$C$43:$BJ$43,($R$2-1)*12+8) -> -30068.796 | P18: =INDEX(Monthly!$C$43:$BJ$43,($R$2-1)*12+9) -> -33115.563 | Q18: =INDEX(Monthly!$C$43:$BJ$43,($R$2-1)*12+10) -> -36131.966 | R18: =INDEX(Monthly!$C$43:$BJ$43,($R$2-1)*12+11) -> -39118.306 | S18: =INDEX(Monthly!$C$43:$BJ$43,($R$2-1)*12+12) -> -42074.882
A19: Net income | B19: ='P&L'!B22 -> 1140105.9 | C19: ='P&L'!C22 -> 1737694.2 | D19: ='P&L'!D22 -> 2562719.3 | E19: ='P&L'!E22 -> 3736079.2 | F19: ='P&L'!F22 -> 5289000.5 | H19: =INDEX(Monthly!$C$44:$BJ$44,($R$2-1)*12+1) -> 29588.133 | I19: =INDEX(Monthly!$C$44:$BJ$44,($R$2-1)*12+2) -> 41882.173 | J19: =INDEX(Monthly!$C$44:$BJ$44,($R$2-1)*12+3) -> 54053.703 | K19: =INDEX(Monthly!$C$44:$BJ$44,($R$2-1)*12+4) -> 66103.942 | L19: =INDEX(Monthly!$C$44:$BJ$44,($R$2-1)*12+5) -> 78034.098 | M19: =INDEX(Monthly!$C$44:$BJ$44,($R$2-1)*12+6) -> 89845.364 | N19: =INDEX(Monthly!$C$44:$BJ$44,($R$2-1)*12+7) -> 101538.92 | O19: =INDEX(Monthly!$C$44:$BJ$44,($R$2-1)*12+8) -> 113115.95 | P19: =INDEX(Monthly!$C$44:$BJ$44,($R$2-1)*12+9) -> 124577.59 | Q19: =INDEX(Monthly!$C$44:$BJ$44,($R$2-1)*12+10) -> 135925.01 | R19: =INDEX(Monthly!$C$44:$BJ$44,($R$2-1)*12+11) -> 147159.34 | S19: =INDEX(Monthly!$C$44:$BJ$44,($R$2-1)*12+12) -> 158281.7
A20: Net margin | B20: ='P&L'!B23 -> 0.11159167 | C20: ='P&L'!C23 -> 0.13422344 | D20: ='P&L'!D23 -> 0.15580266 | E20: ='P&L'!E23 -> 0.17835868 | F20: ='P&L'!F23 -> 0.19784986 | H20: =IF(H7=0,0,H19/H7) -> 0.038995892 | I20: =IF(I7=0,0,I19/I7) -> 0.053960572 | J20: =IF(J7=0,0,J19/J7) -> 0.068129119 | K20: =IF(K7=0,0,K19/K7) -> 0.081562794 | L20: =IF(L7=0,0,L19/L7) -> 0.094316731 | M20: =IF(M7=0,0,M19/M7) -> 0.10644068 | N20: =IF(N7=0,0,N19/N7) -> 0.11797966 | O20: =IF(O7=0,0,O19/O7) -> 0.12897449 | ... S20: =IF(S7=0,0,S19/S7) -> 0.16820723
A22: Cash flow ($'000) — 5 years | H22: ="Cash flow ($'000) — Year "&$R$2&", by month" -> Cash flow ($'000) — Year 1, by month
B23: ='P&L'!B4 -> Year 1 | C23: ='P&L'!C4 -> Year 2 | D23: ='P&L'!D4 -> Year 3 | E23: ='P&L'!E4 -> Year 4 | F23: ='P&L'!F4 -> Year 5 | H23: =INDEX(Monthly!$C$3:$BJ$3,($R$2-1)*12+1) -> M1 | I23: =INDEX(Monthly!$C$3:$BJ$3,($R$2-1)*12+2) -> M2 | J23: =INDEX(Monthly!$C$3:$BJ$3,($R$2-1)*12+3) -> M3 | K23: =INDEX(Monthly!$C$3:$BJ$3,($R$2-1)*12+4) -> M4 | L23: =INDEX(Monthly!$C$3:$BJ$3,($R$2-1)*12+5) -> M5 | M23: =INDEX(Monthly!$C$3:$BJ$3,($R$2-1)*12+6) -> M6 | N23: =INDEX(Monthly!$C$3:$BJ$3,($R$2-1)*12+7) -> M7 | O23: =INDEX(Monthly!$C$3:$BJ$3,($R$2-1)*12+8) -> M8 | P23: =INDEX(Monthly!$C$3:$BJ$3,($R$2-1)*12+9) -> M9 | Q23: =INDEX(Monthly!$C$3:$BJ$3,($R$2-1)*12+10) -> M10 | R23: =INDEX(Monthly!$C$3:$BJ$3,($R$2-1)*12+11) -> M11 | S23: =INDEX(Monthly!$C$3:$BJ$3,($R$2-1)*12+12) -> M12
A24: Operating cash flow | B24: ='Cash Flow'!B11 -> 2273134.7 | C24: ='Cash Flow'!C11 -> 2078342.8 | D24: ='Cash Flow'!D11 -> 2985771.8 | E24: ='Cash Flow'!E11 -> 4215445.8 | F24: ='Cash Flow'!F11 -> 5905773.3 | H24: =INDEX(Monthly!$C$70:$BJ$70,($R$2-1)*12+1) -> 910226.47 | I24: =INDEX(Monthly!$C$70:$BJ$70,($R$2-1)*12+2) -> 65787.181 | J24: =INDEX(Monthly!$C$70:$BJ$70,($R$2-1)*12+3) -> 77760.782 | K24: =INDEX(Monthly!$C$70:$BJ$70,($R$2-1)*12+4) -> 89615.079 | L24: =INDEX(Monthly!$C$70:$BJ$70,($R$2-1)*12+5) -> 101351.26 | M24: =INDEX(Monthly!$C$70:$BJ$70,($R$2-1)*12+6) -> 112970.5 | N24: =INDEX(Monthly!$C$70:$BJ$70,($R$2-1)*12+7) -> 124473.96 | O24: =INDEX(Monthly!$C$70:$BJ$70,($R$2-1)*12+8) -> 135862.79 | P24: =INDEX(Monthly!$C$70:$BJ$70,($R$2-1)*12+9) -> 147138.14 | Q24: =INDEX(Monthly!$C$70:$BJ$70,($R$2-1)*12+10) -> 158301.13 | R24: =INDEX(Monthly!$C$70:$BJ$70,($R$2-1)*12+11) -> 169352.88 | S24: =INDEX(Monthly!$C$70:$BJ$70,($R$2-1)*12+12) -> 180294.49
A25: Capital spending | B25: ='Cash Flow'!B12 -> -150000 | C25: ='Cash Flow'!C12 -> 0 | D25: ='Cash Flow'!D12 -> 0 | E25: ='Cash Flow'!E12 -> 0 | F25: ='Cash Flow'!F12 -> 0 | H25: =INDEX(Monthly!$C$71:$BJ$71,($R$2-1)*12+1) -> -150000 | I25: =INDEX(Monthly!$C$71:$BJ$71,($R$2-1)*12+2) -> 0 | J25: =INDEX(Monthly!$C$71:$BJ$71,($R$2-1)*12+3) -> 0 | K25: =INDEX(Monthly!$C$71:$BJ$71,($R$2-1)*12+4) -> 0 | L25: =INDEX(Monthly!$C$71:$BJ$71,($R$2-1)*12+5) -> 0 | M25: =INDEX(Monthly!$C$71:$BJ$71,($R$2-1)*12+6) -> 0 | N25: =INDEX(Monthly!$C$71:$BJ$71,($R$2-1)*12+7) -> 0 | O25: =INDEX(Monthly!$C$71:$BJ$71,($R$2-1)*12+8) -> 0 | P25: =INDEX(Monthly!$C$71:$BJ$71,($R$2-1)*12+9) -> 0 | Q25: =INDEX(Monthly!$C$71:$BJ$71,($R$2-1)*12+10) -> 0 | R25: =INDEX(Monthly!$C$71:$BJ$71,($R$2-1)*12+11) -> 0 | S25: =INDEX(Monthly!$C$71:$BJ$71,($R$2-1)*12+12) -> 0
A26: Equity raised | B26: ='Cash Flow'!B13 -> 1000000 | C26: ='Cash Flow'!C13 -> 0 | D26: ='Cash Flow'!D13 -> 0 | E26: ='Cash Flow'!E13 -> 0 | F26: ='Cash Flow'!F13 -> 0 | H26: =INDEX(Monthly!$C$72:$BJ$72,($R$2-1)*12+1) -> 1000000 | I26: =INDEX(Monthly!$C$72:$BJ$72,($R$2-1)*12+2) -> 0 | J26: =INDEX(Monthly!$C$72:$BJ$72,($R$2-1)*12+3) -> 0 | K26: =INDEX(Monthly!$C$72:$BJ$72,($R$2-1)*12+4) -> 0 | L26: =INDEX(Monthly!$C$72:$BJ$72,($R$2-1)*12+5) -> 0 | M26: =INDEX(Monthly!$C$72:$BJ$72,($R$2-1)*12+6) -> 0 | N26: =INDEX(Monthly!$C$72:$BJ$72,($R$2-1)*12+7) -> 0 | O26: =INDEX(Monthly!$C$72:$BJ$72,($R$2-1)*12+8) -> 0 | P26: =INDEX(Monthly!$C$72:$BJ$72,($R$2-1)*12+9) -> 0 | Q26: =INDEX(Monthly!$C$72:$BJ$72,($R$2-1)*12+10) -> 0 | R26: =INDEX(Monthly!$C$72:$BJ$72,($R$2-1)*12+11) -> 0 | S26: =INDEX(Monthly!$C$72:$BJ$72,($R$2-1)*12+12) -> 0
A27: Loan drawdown | B27: ='Cash Flow'!B14 -> 0 | C27: ='Cash Flow'!C14 -> 0 | D27: ='Cash Flow'!D14 -> 0 | E27: ='Cash Flow'!E14 -> 0 | F27: ='Cash Flow'!F14 -> 0 | H27: =INDEX(Monthly!$C$55:$BJ$55,($R$2-1)*12+1) -> 0 | I27: =INDEX(Monthly!$C$55:$BJ$55,($R$2-1)*12+2) -> 0 | J27: =INDEX(Monthly!$C$55:$BJ$55,($R$2-1)*12+3) -> 0 | K27: =INDEX(Monthly!$C$55:$BJ$55,($R$2-1)*12+4) -> 0 | L27: =INDEX(Monthly!$C$55:$BJ$55,($R$2-1)*12+5) -> 0 | M27: =INDEX(Monthly!$C$55:$BJ$55,($R$2-1)*12+6) -> 0 | N27: =INDEX(Monthly!$C$55:$BJ$55,($R$2-1)*12+7) -> 0 | O27: =INDEX(Monthly!$C$55:$BJ$55,($R$2-1)*12+8) -> 0 | P27: =INDEX(Monthly!$C$55:$BJ$55,($R$2-1)*12+9) -> 0 | Q27: =INDEX(Monthly!$C$55:$BJ$55,($R$2-1)*12+10) -> 0 | R27: =INDEX(Monthly!$C$55:$BJ$55,($R$2-1)*12+11) -> 0 | S27: =INDEX(Monthly!$C$55:$BJ$55,($R$2-1)*12+12) -> 0
A28: Loan repayment | B28: ='Cash Flow'!B15 -> 0 | C28: ='Cash Flow'!C15 -> 0 | D28: ='Cash Flow'!D15 -> 0 | E28: ='Cash Flow'!E15 -> 0 | F28: ='Cash Flow'!F15 -> 0 | H28: =INDEX(Monthly!$C$56:$BJ$56,($R$2-1)*12+1) -> 0 | I28: =INDEX(Monthly!$C$56:$BJ$56,($R$2-1)*12+2) -> 0 | J28: =INDEX(Monthly!$C$56:$BJ$56,($R$2-1)*12+3) -> 0 | K28: =INDEX(Monthly!$C$56:$BJ$56,($R$2-1)*12+4) -> 0 | L28: =INDEX(Monthly!$C$56:$BJ$56,($R$2-1)*12+5) -> 0 | M28: =INDEX(Monthly!$C$56:$BJ$56,($R$2-1)*12+6) -> 0 | N28: =INDEX(Monthly!$C$56:$BJ$56,($R$2-1)*12+7) -> 0 | O28: =INDEX(Monthly!$C$56:$BJ$56,($R$2-1)*12+8) -> 0 | P28: =INDEX(Monthly!$C$56:$BJ$56,($R$2-1)*12+9) -> 0 | Q28: =INDEX(Monthly!$C$56:$BJ$56,($R$2-1)*12+10) -> 0 | R28: =INDEX(Monthly!$C$56:$BJ$56,($R$2-1)*12+11) -> 0 | S28: =INDEX(Monthly!$C$56:$BJ$56,($R$2-1)*12+12) -> 0
A29: Financing cash flow | B29: ='Cash Flow'!B16 -> 1000000 | C29: ='Cash Flow'!C16 -> 0 | D29: ='Cash Flow'!D16 -> 0 | E29: ='Cash Flow'!E16 -> 0 | F29: ='Cash Flow'!F16 -> 0 | H29: =INDEX(Monthly!$C$73:$BJ$73,($R$2-1)*12+1) -> 1000000 | I29: =INDEX(Monthly!$C$73:$BJ$73,($R$2-1)*12+2) -> 0 | J29: =INDEX(Monthly!$C$73:$BJ$73,($R$2-1)*12+3) -> 0 | K29: =INDEX(Monthly!$C$73:$BJ$73,($R$2-1)*12+4) -> 0 | L29: =INDEX(Monthly!$C$73:$BJ$73,($R$2-1)*12+5) -> 0 | M29: =INDEX(Monthly!$C$73:$BJ$73,($R$2-1)*12+6) -> 0 | N29: =INDEX(Monthly!$C$73:$BJ$73,($R$2-1)*12+7) -> 0 | O29: =INDEX(Monthly!$C$73:$BJ$73,($R$2-1)*12+8) -> 0 | P29: =INDEX(Monthly!$C$73:$BJ$73,($R$2-1)*12+9) -> 0 | Q29: =INDEX(Monthly!$C$73:$BJ$73,($R$2-1)*12+10) -> 0 | R29: =INDEX(Monthly!$C$73:$BJ$73,($R$2-1)*12+11) -> 0 | S29: =INDEX(Monthly!$C$73:$BJ$73,($R$2-1)*12+12) -> 0
A30: Net change in cash | B30: ='Cash Flow'!B17 -> 3123134.7 | C30: ='Cash Flow'!C17 -> 2078342.8 | D30: ='Cash Flow'!D17 -> 2985771.8 | E30: ='Cash Flow'!E17 -> 4215445.8 | F30: ='Cash Flow'!F17 -> 5905773.3 | H30: =INDEX(Monthly!$C$74:$BJ$74,($R$2-1)*12+1) -> 1760226.5 | I30: =INDEX(Monthly!$C$74:$BJ$74,($R$2-1)*12+2) -> 65787.181 | J30: =INDEX(Monthly!$C$74:$BJ$74,($R$2-1)*12+3) -> 77760.782 | K30: =INDEX(Monthly!$C$74:$BJ$74,($R$2-1)*12+4) -> 89615.079 | L30: =INDEX(Monthly!$C$74:$BJ$74,($R$2-1)*12+5) -> 101351.26 | M30: =INDEX(Monthly!$C$74:$BJ$74,($R$2-1)*12+6) -> 112970.5 | N30: =INDEX(Monthly!$C$74:$BJ$74,($R$2-1)*12+7) -> 124473.96 | O30: =INDEX(Monthly!$C$74:$BJ$74,($R$2-1)*12+8) -> 135862.79 | P30: =INDEX(Monthly!$C$74:$BJ$74,($R$2-1)*12+9) -> 147138.14 | Q30: =INDEX(Monthly!$C$74:$BJ$74,($R$2-1)*12+10) -> 158301.13 | R30: =INDEX(Monthly!$C$74:$BJ$74,($R$2-1)*12+11) -> 169352.88 | S30: =INDEX(Monthly!$C$74:$BJ$74,($R$2-1)*12+12) -> 180294.49
A31: Closing cash | B31: ='Cash Flow'!B19 -> 3123134.7 | C31: ='Cash Flow'!C19 -> 5201477.5 | D31: ='Cash Flow'!D19 -> 8187249.2 | E31: ='Cash Flow'!E19 -> 12402695 | F31: ='Cash Flow'!F19 -> 18308468 | H31: =INDEX(Monthly!$C$76:$BJ$76,($R$2-1)*12+1) -> 1760226.5 | I31: =INDEX(Monthly!$C$76:$BJ$76,($R$2-1)*12+2) -> 1826013.6 | J31: =INDEX(Monthly!$C$76:$BJ$76,($R$2-1)*12+3) -> 1903774.4 | K31: =INDEX(Monthly!$C$76:$BJ$76,($R$2-1)*12+4) -> 1993389.5 | L31: =INDEX(Monthly!$C$76:$BJ$76,($R$2-1)*12+5) -> 2094740.8 | M31: =INDEX(Monthly!$C$76:$BJ$76,($R$2-1)*12+6) -> 2207711.3 | N31: =INDEX(Monthly!$C$76:$BJ$76,($R$2-1)*12+7) -> 2332185.2 | O31: =INDEX(Monthly!$C$76:$BJ$76,($R$2-1)*12+8) -> 2468048 | P31: =INDEX(Monthly!$C$76:$BJ$76,($R$2-1)*12+9) -> 2615186.2 | Q31: =INDEX(Monthly!$C$76:$BJ$76,($R$2-1)*12+10) -> 2773487.3 | R31: =INDEX(Monthly!$C$76:$BJ$76,($R$2-1)*12+11) -> 2942840.2 | S31: =INDEX(Monthly!$C$76:$BJ$76,($R$2-1)*12+12) -> 3123134.7
A39: Balance sheet at year end ($'000) | H39: ="Balance sheet at month end ($'000) — Year "&$R$2 -> Balance sheet at month end ($'000) — Year 1
B40: ='P&L'!B4 -> Year 1 | C40: ='P&L'!C4 -> Year 2 | D40: ='P&L'!D4 -> Year 3 | E40: ='P&L'!E4 -> Year 4 | F40: ='P&L'!F4 -> Year 5 | H40: =INDEX(Monthly!$C$3:$BJ$3,($R$2-1)*12+1) -> M1 | I40: =INDEX(Monthly!$C$3:$BJ$3,($R$2-1)*12+2) -> M2 | J40: =INDEX(Monthly!$C$3:$BJ$3,($R$2-1)*12+3) -> M3 | K40: =INDEX(Monthly!$C$3:$BJ$3,($R$2-1)*12+4) -> M4 | L40: =INDEX(Monthly!$C$3:$BJ$3,($R$2-1)*12+5) -> M5 | M40: =INDEX(Monthly!$C$3:$BJ$3,($R$2-1)*12+6) -> M6 | N40: =INDEX(Monthly!$C$3:$BJ$3,($R$2-1)*12+7) -> M7 | O40: =INDEX(Monthly!$C$3:$BJ$3,($R$2-1)*12+8) -> M8 | P40: =INDEX(Monthly!$C$3:$BJ$3,($R$2-1)*12+9) -> M9 | Q40: =INDEX(Monthly!$C$3:$BJ$3,($R$2-1)*12+10) -> M10 | R40: =INDEX(Monthly!$C$3:$BJ$3,($R$2-1)*12+11) -> M11 | S40: =INDEX(Monthly!$C$3:$BJ$3,($R$2-1)*12+12) -> M12
A41: Cash | B41: ='Balance Sheet'!B5 -> 3123134.7 | C41: ='Balance Sheet'!C5 -> 5201477.5 | D41: ='Balance Sheet'!D5 -> 8187249.2 | E41: ='Balance Sheet'!E5 -> 12402695 | F41: ='Balance Sheet'!F5 -> 18308468 | H41: =INDEX(Monthly!$C$76:$BJ$76,($R$2-1)*12+1) -> 1760226.5 | I41: =INDEX(Monthly!$C$76:$BJ$76,($R$2-1)*12+2) -> 1826013.6 | J41: =INDEX(Monthly!$C$76:$BJ$76,($R$2-1)*12+3) -> 1903774.4 | K41: =INDEX(Monthly!$C$76:$BJ$76,($R$2-1)*12+4) -> 1993389.5 | L41: =INDEX(Monthly!$C$76:$BJ$76,($R$2-1)*12+5) -> 2094740.8 | M41: =INDEX(Monthly!$C$76:$BJ$76,($R$2-1)*12+6) -> 2207711.3 | N41: =INDEX(Monthly!$C$76:$BJ$76,($R$2-1)*12+7) -> 2332185.2 | O41: =INDEX(Monthly!$C$76:$BJ$76,($R$2-1)*12+8) -> 2468048 | P41: =INDEX(Monthly!$C$76:$BJ$76,($R$2-1)*12+9) -> 2615186.2 | Q41: =INDEX(Monthly!$C$76:$BJ$76,($R$2-1)*12+10) -> 2773487.3 | R41: =INDEX(Monthly!$C$76:$BJ$76,($R$2-1)*12+11) -> 2942840.2 | S41: =INDEX(Monthly!$C$76:$BJ$76,($R$2-1)*12+12) -> 3123134.7
A42: Accounts receivable | B42: ='Balance Sheet'!B6 -> 156832.04 | C42: ='Balance Sheet'!C6 -> 198958.68 | D42: ='Balance Sheet'!D6 -> 253031.66 | E42: ='Balance Sheet'!E6 -> 322519.09 | F42: ='Balance Sheet'!F6 -> 411930.95 | H42: =INDEX(Monthly!$C$60:$BJ$60,($R$2-1)*12+1) -> 126458.33 | I42: =INDEX(Monthly!$C$60:$BJ$60,($R$2-1)*12+2) -> 129360.42 | J42: =INDEX(Monthly!$C$60:$BJ$60,($R$2-1)*12+3) -> 132233.48 | K42: =INDEX(Monthly!$C$60:$BJ$60,($R$2-1)*12+4) -> 135077.81 | L42: =INDEX(Monthly!$C$60:$BJ$60,($R$2-1)*12+5) -> 137893.7 | M42: =INDEX(Monthly!$C$60:$BJ$60,($R$2-1)*12+6) -> 140681.43 | N42: =INDEX(Monthly!$C$60:$BJ$60,($R$2-1)*12+7) -> 143441.28 | O42: =INDEX(Monthly!$C$60:$BJ$60,($R$2-1)*12+8) -> 146173.54 | P42: =INDEX(Monthly!$C$60:$BJ$60,($R$2-1)*12+9) -> 148878.47 | Q42: =INDEX(Monthly!$C$60:$BJ$60,($R$2-1)*12+10) -> 151556.35 | R42: =INDEX(Monthly!$C$60:$BJ$60,($R$2-1)*12+11) -> 154207.45 | S42: =INDEX(Monthly!$C$60:$BJ$60,($R$2-1)*12+12) -> 156832.04
A43: Inventory | B43: ='Balance Sheet'!B7 -> 0 | C43: ='Balance Sheet'!C7 -> 0 | D43: ='Balance Sheet'!D7 -> 0 | E43: ='Balance Sheet'!E7 -> 0 | F43: ='Balance Sheet'!F7 -> 0 | H43: =INDEX(Monthly!$C$61:$BJ$61,($R$2-1)*12+1) -> 0 | I43: =INDEX(Monthly!$C$61:$BJ$61,($R$2-1)*12+2) -> 0 | J43: =INDEX(Monthly!$C$61:$BJ$61,($R$2-1)*12+3) -> 0 | K43: =INDEX(Monthly!$C$61:$BJ$61,($R$2-1)*12+4) -> 0 | L43: =INDEX(Monthly!$C$61:$BJ$61,($R$2-1)*12+5) -> 0 | M43: =INDEX(Monthly!$C$61:$BJ$61,($R$2-1)*12+6) -> 0 | N43: =INDEX(Monthly!$C$61:$BJ$61,($R$2-1)*12+7) -> 0 | O43: =INDEX(Monthly!$C$61:$BJ$61,($R$2-1)*12+8) -> 0 | P43: =INDEX(Monthly!$C$61:$BJ$61,($R$2-1)*12+9) -> 0 | Q43: =INDEX(Monthly!$C$61:$BJ$61,($R$2-1)*12+10) -> 0 | R43: =INDEX(Monthly!$C$61:$BJ$61,($R$2-1)*12+11) -> 0 | S43: =INDEX(Monthly!$C$61:$BJ$61,($R$2-1)*12+12) -> 0
A44: Net fixed assets | B44: ='Balance Sheet'!B8 -> 100000 | C44: ='Balance Sheet'!C8 -> 50000 | D44: ='Balance Sheet'!D8 -> 0 | E44: ='Balance Sheet'!E8 -> 0 | F44: ='Balance Sheet'!F8 -> 0 | H44: =INDEX(Monthly!$C$51:$BJ$51,($R$2-1)*12+1) -> 145833.33 | I44: =INDEX(Monthly!$C$51:$BJ$51,($R$2-1)*12+2) -> 141666.67 | J44: =INDEX(Monthly!$C$51:$BJ$51,($R$2-1)*12+3) -> 137500 | K44: =INDEX(Monthly!$C$51:$BJ$51,($R$2-1)*12+4) -> 133333.33 | L44: =INDEX(Monthly!$C$51:$BJ$51,($R$2-1)*12+5) -> 129166.67 | M44: =INDEX(Monthly!$C$51:$BJ$51,($R$2-1)*12+6) -> 125000 | N44: =INDEX(Monthly!$C$51:$BJ$51,($R$2-1)*12+7) -> 120833.33 | O44: =INDEX(Monthly!$C$51:$BJ$51,($R$2-1)*12+8) -> 116666.67 | P44: =INDEX(Monthly!$C$51:$BJ$51,($R$2-1)*12+9) -> 112500 | Q44: =INDEX(Monthly!$C$51:$BJ$51,($R$2-1)*12+10) -> 108333.33 | R44: =INDEX(Monthly!$C$51:$BJ$51,($R$2-1)*12+11) -> 104166.67 | S44: =INDEX(Monthly!$C$51:$BJ$51,($R$2-1)*12+12) -> 100000
A45: Total assets | B45: ='Balance Sheet'!B9 -> 3379966.7 | C45: ='Balance Sheet'!C9 -> 5450436.1 | D45: ='Balance Sheet'!D9 -> 8440280.9 | E45: ='Balance Sheet'!E9 -> 12725214 | F45: ='Balance Sheet'!F9 -> 18720399 | H45: =INDEX(Monthly!$C$94:$BJ$94,($R$2-1)*12+1) -> 2032518.1 | I45: =INDEX(Monthly!$C$94:$BJ$94,($R$2-1)*12+2) -> 2097040.7 | J45: =INDEX(Monthly!$C$94:$BJ$94,($R$2-1)*12+3) -> 2173507.9 | K45: =INDEX(Monthly!$C$94:$BJ$94,($R$2-1)*12+4) -> 2261800.7 | L45: =INDEX(Monthly!$C$94:$BJ$94,($R$2-1)*12+5) -> 2361801.1 | M45: =INDEX(Monthly!$C$94:$BJ$94,($R$2-1)*12+6) -> 2473392.7 | N45: =INDEX(Monthly!$C$94:$BJ$94,($R$2-1)*12+7) -> 2596459.8 | O45: =INDEX(Monthly!$C$94:$BJ$94,($R$2-1)*12+8) -> 2730888.2 | P45: =INDEX(Monthly!$C$94:$BJ$94,($R$2-1)*12+9) -> 2876564.6 | Q45: =INDEX(Monthly!$C$94:$BJ$94,($R$2-1)*12+10) -> 3033377 | R45: =INDEX(Monthly!$C$94:$BJ$94,($R$2-1)*12+11) -> 3201214.3 | S45: =INDEX(Monthly!$C$94:$BJ$94,($R$2-1)*12+12) -> 3379966.7
A46: Accounts payable | B46: ='Balance Sheet'!B10 -> 101269.02 | C46: ='Balance Sheet'!C10 -> 128077.78 | D46: ='Balance Sheet'!D10 -> 162458.51 | E46: ='Balance Sheet'!E10 -> 206590.9 | F46: ='Balance Sheet'!F10 -> 263306.81 | H46: =INDEX(Monthly!$C$62:$BJ$62,($R$2-1)*12+1) -> 81930 | I46: =INDEX(Monthly!$C$62:$BJ$62,($R$2-1)*12+2) -> 83780.425 | J46: =INDEX(Monthly!$C$62:$BJ$62,($R$2-1)*12+3) -> 85611.8 | K46: =INDEX(Monthly!$C$62:$BJ$62,($R$2-1)*12+4) -> 87424.323 | L46: =INDEX(Monthly!$C$62:$BJ$62,($R$2-1)*12+5) -> 89218.192 | M46: =INDEX(Monthly!$C$62:$BJ$62,($R$2-1)*12+6) -> 90993.6 | N46: =INDEX(Monthly!$C$62:$BJ$62,($R$2-1)*12+7) -> 92750.74 | O46: =INDEX(Monthly!$C$62:$BJ$62,($R$2-1)*12+8) -> 94489.803 | P46: =INDEX(Monthly!$C$62:$BJ$62,($R$2-1)*12+9) -> 96210.977 | Q46: =INDEX(Monthly!$C$62:$BJ$62,($R$2-1)*12+10) -> 97914.447 | R46: =INDEX(Monthly!$C$62:$BJ$62,($R$2-1)*12+11) -> 99600.4 | S46: =INDEX(Monthly!$C$62:$BJ$62,($R$2-1)*12+12) -> 101269.02
A47: Deferred revenue | B47: ='Balance Sheet'!B11 -> 1138591.8 | C47: ='Balance Sheet'!C11 -> 1444558.2 | D47: ='Balance Sheet'!D11 -> 1837303 | E47: ='Balance Sheet'!E11 -> 2342024.6 | F47: ='Balance Sheet'!F11 -> 2991493.4 | H47: =INDEX(Monthly!$C$66:$BJ$66,($R$2-1)*12+1) -> 921000 | I47: =INDEX(Monthly!$C$66:$BJ$66,($R$2-1)*12+2) -> 941790 | J47: =INDEX(Monthly!$C$66:$BJ$66,($R$2-1)*12+3) -> 962372.1 | K47: =INDEX(Monthly!$C$66:$BJ$66,($R$2-1)*12+4) -> 982748.38 | L47: =INDEX(Monthly!$C$66:$BJ$66,($R$2-1)*12+5) -> 1002920.9 | M47: =INDEX(Monthly!$C$66:$BJ$66,($R$2-1)*12+6) -> 1022891.7 | N47: =INDEX(Monthly!$C$66:$BJ$66,($R$2-1)*12+7) -> 1042662.8 | O47: =INDEX(Monthly!$C$66:$BJ$66,($R$2-1)*12+8) -> 1062236.1 | P47: =INDEX(Monthly!$C$66:$BJ$66,($R$2-1)*12+9) -> 1081613.8 | Q47: =INDEX(Monthly!$C$66:$BJ$66,($R$2-1)*12+10) -> 1100797.6 | R47: =INDEX(Monthly!$C$66:$BJ$66,($R$2-1)*12+11) -> 1119789.7 | S47: =INDEX(Monthly!$C$66:$BJ$66,($R$2-1)*12+12) -> 1138591.8
A48: Loan | B48: ='Balance Sheet'!B12 -> 0 | C48: ='Balance Sheet'!C12 -> 0 | D48: ='Balance Sheet'!D12 -> 0 | E48: ='Balance Sheet'!E12 -> 0 | F48: ='Balance Sheet'!F12 -> 0 | H48: =INDEX(Monthly!$C$57:$BJ$57,($R$2-1)*12+1) -> 0 | I48: =INDEX(Monthly!$C$57:$BJ$57,($R$2-1)*12+2) -> 0 | J48: =INDEX(Monthly!$C$57:$BJ$57,($R$2-1)*12+3) -> 0 | K48: =INDEX(Monthly!$C$57:$BJ$57,($R$2-1)*12+4) -> 0 | L48: =INDEX(Monthly!$C$57:$BJ$57,($R$2-1)*12+5) -> 0 | M48: =INDEX(Monthly!$C$57:$BJ$57,($R$2-1)*12+6) -> 0 | N48: =INDEX(Monthly!$C$57:$BJ$57,($R$2-1)*12+7) -> 0 | O48: =INDEX(Monthly!$C$57:$BJ$57,($R$2-1)*12+8) -> 0 | P48: =INDEX(Monthly!$C$57:$BJ$57,($R$2-1)*12+9) -> 0 | Q48: =INDEX(Monthly!$C$57:$BJ$57,($R$2-1)*12+10) -> 0 | R48: =INDEX(Monthly!$C$57:$BJ$57,($R$2-1)*12+11) -> 0 | S48: =INDEX(Monthly!$C$57:$BJ$57,($R$2-1)*12+12) -> 0
A49: Total liabilities | B49: ='Balance Sheet'!B13 -> 1239860.8 | C49: ='Balance Sheet'!C13 -> 1572636 | D49: ='Balance Sheet'!D13 -> 1999761.5 | E49: ='Balance Sheet'!E13 -> 2548615.5 | F49: ='Balance Sheet'!F13 -> 3254800.2 | H49: =INDEX(Monthly!$C$95:$BJ$95,($R$2-1)*12+1) -> 1002930 | I49: =INDEX(Monthly!$C$95:$BJ$95,($R$2-1)*12+2) -> 1025570.4 | J49: =INDEX(Monthly!$C$95:$BJ$95,($R$2-1)*12+3) -> 1047983.9 | K49: =INDEX(Monthly!$C$95:$BJ$95,($R$2-1)*12+4) -> 1070172.7 | L49: =INDEX(Monthly!$C$95:$BJ$95,($R$2-1)*12+5) -> 1092139.1 | M49: =INDEX(Monthly!$C$95:$BJ$95,($R$2-1)*12+6) -> 1113885.3 | N49: =INDEX(Monthly!$C$95:$BJ$95,($R$2-1)*12+7) -> 1135413.5 | O49: =INDEX(Monthly!$C$95:$BJ$95,($R$2-1)*12+8) -> 1156725.9 | P49: =INDEX(Monthly!$C$95:$BJ$95,($R$2-1)*12+9) -> 1177824.8 | Q49: =INDEX(Monthly!$C$95:$BJ$95,($R$2-1)*12+10) -> 1198712.1 | R49: =INDEX(Monthly!$C$95:$BJ$95,($R$2-1)*12+11) -> 1219390.1 | S49: =INDEX(Monthly!$C$95:$BJ$95,($R$2-1)*12+12) -> 1239860.8
A50: Paid-in capital | B50: ='Balance Sheet'!B14 -> 1000000 | C50: ='Balance Sheet'!C14 -> 1000000 | D50: ='Balance Sheet'!D14 -> 1000000 | E50: ='Balance Sheet'!E14 -> 1000000 | F50: ='Balance Sheet'!F14 -> 1000000 | H50: =INDEX(Monthly!$C$92:$BJ$92,($R$2-1)*12+1) -> 1000000 | I50: =INDEX(Monthly!$C$92:$BJ$92,($R$2-1)*12+2) -> 1000000 | J50: =INDEX(Monthly!$C$92:$BJ$92,($R$2-1)*12+3) -> 1000000 | K50: =INDEX(Monthly!$C$92:$BJ$92,($R$2-1)*12+4) -> 1000000 | L50: =INDEX(Monthly!$C$92:$BJ$92,($R$2-1)*12+5) -> 1000000 | M50: =INDEX(Monthly!$C$92:$BJ$92,($R$2-1)*12+6) -> 1000000 | N50: =INDEX(Monthly!$C$92:$BJ$92,($R$2-1)*12+7) -> 1000000 | O50: =INDEX(Monthly!$C$92:$BJ$92,($R$2-1)*12+8) -> 1000000 | P50: =INDEX(Monthly!$C$92:$BJ$92,($R$2-1)*12+9) -> 1000000 | Q50: =INDEX(Monthly!$C$92:$BJ$92,($R$2-1)*12+10) -> 1000000 | R50: =INDEX(Monthly!$C$92:$BJ$92,($R$2-1)*12+11) -> 1000000 | S50: =INDEX(Monthly!$C$92:$BJ$92,($R$2-1)*12+12) -> 1000000
A51: Retained earnings | B51: ='Balance Sheet'!B15 -> 1140105.9 | C51: ='Balance Sheet'!C15 -> 2877800.1 | D51: ='Balance Sheet'!D15 -> 5440519.4 | E51: ='Balance Sheet'!E15 -> 9176598.6 | F51: ='Balance Sheet'!F15 -> 14465599 | H51: =INDEX(Monthly!$C$93:$BJ$93,($R$2-1)*12+1) -> 29588.133 | I51: =INDEX(Monthly!$C$93:$BJ$93,($R$2-1)*12+2) -> 71470.306 | J51: =INDEX(Monthly!$C$93:$BJ$93,($R$2-1)*12+3) -> 125524.01 | K51: =INDEX(Monthly!$C$93:$BJ$93,($R$2-1)*12+4) -> 191627.95 | L51: =INDEX(Monthly!$C$93:$BJ$93,($R$2-1)*12+5) -> 269662.05 | M51: =INDEX(Monthly!$C$93:$BJ$93,($R$2-1)*12+6) -> 359507.41 | N51: =INDEX(Monthly!$C$93:$BJ$93,($R$2-1)*12+7) -> 461046.34 | O51: =INDEX(Monthly!$C$93:$BJ$93,($R$2-1)*12+8) -> 574162.28 | P51: =INDEX(Monthly!$C$93:$BJ$93,($R$2-1)*12+9) -> 698739.88 | Q51: =INDEX(Monthly!$C$93:$BJ$93,($R$2-1)*12+10) -> 834664.89 | R51: =INDEX(Monthly!$C$93:$BJ$93,($R$2-1)*12+11) -> 981824.23 | S51: =INDEX(Monthly!$C$93:$BJ$93,($R$2-1)*12+12) -> 1140105.9
A52: Total equity | B52: ='Balance Sheet'!B16 -> 2140105.9 | C52: ='Balance Sheet'!C16 -> 3877800.1 | D52: ='Balance Sheet'!D16 -> 6440519.4 | E52: ='Balance Sheet'!E16 -> 10176599 | F52: ='Balance Sheet'!F16 -> 15465599 | H52: =INDEX(Monthly!$C$96:$BJ$96,($R$2-1)*12+1) -> 1029588.1 | I52: =INDEX(Monthly!$C$96:$BJ$96,($R$2-1)*12+2) -> 1071470.3 | J52: =INDEX(Monthly!$C$96:$BJ$96,($R$2-1)*12+3) -> 1125524 | K52: =INDEX(Monthly!$C$96:$BJ$96,($R$2-1)*12+4) -> 1191628 | L52: =INDEX(Monthly!$C$96:$BJ$96,($R$2-1)*12+5) -> 1269662 | M52: =INDEX(Monthly!$C$96:$BJ$96,($R$2-1)*12+6) -> 1359507.4 | N52: =INDEX(Monthly!$C$96:$BJ$96,($R$2-1)*12+7) -> 1461046.3 | O52: =INDEX(Monthly!$C$96:$BJ$96,($R$2-1)*12+8) -> 1574162.3 | P52: =INDEX(Monthly!$C$96:$BJ$96,($R$2-1)*12+9) -> 1698739.9 | Q52: =INDEX(Monthly!$C$96:$BJ$96,($R$2-1)*12+10) -> 1834664.9 | R52: =INDEX(Monthly!$C$96:$BJ$96,($R$2-1)*12+11) -> 1981824.2 | S52: =INDEX(Monthly!$C$96:$BJ$96,($R$2-1)*12+12) -> 2140105.9
A53: Total liabilities & equity | B53: ='Balance Sheet'!B17 -> 3379966.7 | C53: ='Balance Sheet'!C17 -> 5450436.1 | D53: ='Balance Sheet'!D17 -> 8440280.9 | E53: ='Balance Sheet'!E17 -> 12725214 | F53: ='Balance Sheet'!F17 -> 18720399 | H53: =INDEX(Monthly!$C$97:$BJ$97,($R$2-1)*12+1) -> 2032518.1 | I53: =INDEX(Monthly!$C$97:$BJ$97,($R$2-1)*12+2) -> 2097040.7 | J53: =INDEX(Monthly!$C$97:$BJ$97,($R$2-1)*12+3) -> 2173507.9 | K53: =INDEX(Monthly!$C$97:$BJ$97,($R$2-1)*12+4) -> 2261800.7 | L53: =INDEX(Monthly!$C$97:$BJ$97,($R$2-1)*12+5) -> 2361801.1 | M53: =INDEX(Monthly!$C$97:$BJ$97,($R$2-1)*12+6) -> 2473392.7 | N53: =INDEX(Monthly!$C$97:$BJ$97,($R$2-1)*12+7) -> 2596459.8 | O53: =INDEX(Monthly!$C$97:$BJ$97,($R$2-1)*12+8) -> 2730888.2 | P53: =INDEX(Monthly!$C$97:$BJ$97,($R$2-1)*12+9) -> 2876564.6 | Q53: =INDEX(Monthly!$C$97:$BJ$97,($R$2-1)*12+10) -> 3033377 | R53: =INDEX(Monthly!$C$97:$BJ$97,($R$2-1)*12+11) -> 3201214.3 | S53: =INDEX(Monthly!$C$97:$BJ$97,($R$2-1)*12+12) -> 3379966.7

Sheet Scenarios
A1: Scenario analysis | I1: =HYPERLINK("#'Cover'!A1","◂ Contents") -> ◂ Contents
A2: SaaS company — financial model
A3: Low / Base / High columns: values the model engine computed for each scenario when the file was built (prototype snapshot — the production version keeps them live). Active = live, follows Dashboard!B4.
A5: Key drivers by scenario (from Inputs)
A6: Driver | B6: Low | C6: Base | D6: High | E6: Active | F6: Unit
A7: =Inputs!A8 -> Average MRR per new customer (ARPA) | B7: =Inputs!B8 -> 230 | C7: =Inputs!C8 -> 250 | D7: =Inputs!D8 -> 270 | E7: =Inputs!E8 -> 250 | F7: =Inputs!F8 -> $ / month
A8: =Inputs!A10 -> Customer churn per month | B8: =Inputs!B10 -> 0.02 | C8: =Inputs!C10 -> 0.015 | D8: =Inputs!D10 -> 0.01 | E8: =Inputs!E10 -> 0.015 | F8: =Inputs!F10 -> %
A9: =Inputs!A12 -> Organic / referral new customers per month (year 1) | B9: =Inputs!B12 -> 30 | C9: =Inputs!C12 -> 40 | D9: =Inputs!D12 -> 50 | E9: =Inputs!E12 -> 40 | F9: =Inputs!F12 -> # / month
A10: =Inputs!A16 -> Paid customer acquisition cost (CAC) | B10: =Inputs!B16 -> 1200 | C10: =Inputs!C16 -> 1000 | D10: =Inputs!D16 -> 800 | E10: =Inputs!E16 -> 1000 | F10: =Inputs!F16 -> $
A11: =Inputs!A9 -> Price increase per year for new customers | B11: =Inputs!B9 -> 0 | C11: =Inputs!C9 -> 0.03 | D11: =Inputs!D9 -> 0.05 | E11: =Inputs!E9 -> 0.03 | F11: =Inputs!F9 -> %
A12: =Inputs!A11 -> Expansion MRR per month, % of opening MRR | B12: =Inputs!B11 -> 0 | C12: =Inputs!C11 -> 0.005 | D12: =Inputs!D11 -> 0.01 | E12: =Inputs!E11 -> 0.005 | F12: =Inputs!F11 -> %
A13: =Inputs!A18 -> Hosting & payment fees, % of revenue | B13: =Inputs!B18 -> 0.12 | C13: =Inputs!C18 -> 0.1 | D13: =Inputs!D18 -> 0.08 | E13: =Inputs!E18 -> 0.1 | F13: =Inputs!F18 -> %
A14: =Inputs!A64 -> Discount rate (WACC) | B14: =Inputs!B64 -> 0.15 | C14: =Inputs!C64 -> 0.12 | D14: =Inputs!D64 -> 0.1 | E14: =Inputs!E64 -> 0.12 | F14: =Inputs!F64 -> %
A15: =Inputs!A66 -> Exit multiple (EV ÷ final-year EBITDA) | B15: =Inputs!B66 -> 5 | C15: =Inputs!C66 -> 6 | D15: =Inputs!D66 -> 8 | E15: =Inputs!E66 -> 6 | F15: =Inputs!F66 -> x
A17: Outputs by scenario
B18: Low | C18: Base | D18: High | E18: Active
A19: Revenue — 5-year total | B19: 52979171 | C19: 87290935 | D19: 1.4747377e+08 | E19: =SUM('P&L'!B5:F5) -> 87290935
A20: Revenue — year 5 | B20: 13174504 | C20: 26732395 | D20: 53852064 | E20: ='P&L'!F5 -> 26732395
A21: EBITDA — 5-year total | B21: -13556478 | C21: 18460885 | D21: 75555334 | E21: =SUM('P&L'!B15:F15) -> 18460885
A22: EBITDA margin — year 5 | B22: -0.43761018 | C22: 0.25044286 | D22: 0.5969312 | E22: ='P&L'!F16 -> 0.25044286
A23: Net income — 5-year total | B23: -13706478 | C23: 14465599 | D23: 59570214 | E23: =SUM('P&L'!B22:F22) -> 14465599
A24: Year-end cash — year 5 | B24: -11344393 | C24: 18308468 | D24: 66488118 | E24: ='Balance Sheet'!F5 -> 18308468
A25: Lowest cash balance | B25: -11344393 | C25: 1760226.5 | D25: 1891837.2 | E25: =MIN(Monthly!$C$76:$BJ$76) -> 1760226.5
A26: Funding required (incl. buffer) | B26: 14250393 | C26: 1145773.5 | D26: 1014162.8 | E26: ='Break-even'!B12 -> 1145773.5
A27: Enterprise value (DCF, average) | B27: -24094296 | C27: 40195041 | D27: 2.4963975e+08 | E27: =Valuation!B30 -> 40195041
A29: Revenue by year and scenario ($'000)
B30: ='P&L'!B4 -> Year 1 | C30: ='P&L'!C4 -> Year 2 | D30: ='P&L'!D4 -> Year 3 | E30: ='P&L'!E4 -> Year 4 | F30: ='P&L'!F4 -> Year 5
A31: Revenue — Low | B31: 8588999.9 | C31: 9317509.2 | D31: 10310936 | E31: 11587222 | F31: 13174504
A32: Revenue — Base | B32: 10216766 | C32: 12946280 | D32: 16448495 | E32: 20947000 | F32: 26732395
A33: Revenue — High | B33: 12150000 | C33: 17947980 | D33: 26041848 | E33: 37481874 | F33: 53852064
A35: EBITDA by year and scenario ($'000)
B36: ='P&L'!B4 -> Year 1 | C36: ='P&L'!C4 -> Year 2 | D36: ='P&L'!D4 -> Year 3 | E36: ='P&L'!E4 -> Year 4 | F36: ='P&L'!F4 -> Year 5
A37: EBITDA — Low | B37: -176110.52 | C37: -1228016.7 | D37: -2453356.1 | E37: -3933697.9 | F37: -5765297.2
A38: EBITDA — Base | B38: 1493172.1 | C38: 2249612.9 | D38: 3293948.5 | E38: 4729214.2 | F38: 6694937.4
A39: EBITDA — High | B39: 3491692.1 | C39: 7119867.4 | D39: 12449911 | E39: 20347886 | F39: 32145977
A41: Net income by year and scenario ($'000)
B42: ='P&L'!B4 -> Year 1 | C42: ='P&L'!C4 -> Year 2 | D42: ='P&L'!D4 -> Year 3 | E42: ='P&L'!E4 -> Year 4 | F42: ='P&L'!F4 -> Year 5
A43: Net income — Low | B43: -226110.52 | C43: -1278016.7 | D43: -2503356.1 | E43: -3933697.9 | F43: -5765297.2
A44: Net income — Base | B44: 1140105.9 | C44: 1737694.2 | D44: 2562719.3 | E44: 3736079.2 | F44: 5289000.5
A45: Net income — High | B45: 2718936.7 | C45: 5585195.2 | D45: 9795930 | E45: 16074830 | F45: 25395322
A47: Year-end cash by year and scenario ($'000)
B48: ='P&L'!B4 -> Year 1 | C48: ='P&L'!C4 -> Year 2 | D48: ='P&L'!D4 -> Year 3 | E48: ='P&L'!E4 -> Year 4 | F48: ='P&L'!F4 -> Year 5
A49: Year-end cash — Low | B49: 1536504.7 | C49: 391374.65 | D49: -1952750.5 | E49: -5748660.1 | F49: -11344393
A50: Year-end cash — Base | B50: 3123134.7 | C50: 5201477.5 | D50: 8187249.2 | E50: 12402695 | F50: 18308468
A51: Year-end cash — High | B51: 4979154.4 | C51: 11241959 | D51: 21968415 | E51: 39294076 | F51: 66488118

Sheet Break-even
A1: Startup costs, funding need and break-even | H1: =HYPERLINK("#'Cover'!A1","◂ Contents") -> ◂ Contents
A2: Live for the selected scenario. Periods are counted in months from the start of the plan.
A3: Scenario shown | B3: =CHOOSE(Dashboard!$B$4,"Low","Base","High") -> Base
A5: Startup costs & funding need (up to the lowest cash point)
A6: Lowest cash point (month #) | B6: =MATCH(MIN(Monthly!$C$76:$BJ$76),Monthly!$C$76:$BJ$76,0) -> 1
A7: Capital spending up to the lowest cash point | B7: =SUMPRODUCT(--(Monthly!$C$4:$BJ$4<=$B$6),Monthly!$C$47:$BJ$47) -> 150000
A8: Operating cash burn up to the lowest cash point | B8: =-SUMPRODUCT(--(Monthly!$C$4:$BJ$4<=$B$6),Monthly!$C$70:$BJ$70) -> -910226.47 | D8: Losses and working capital before the business funds itself
A9: Loan repayments up to the lowest cash point | B9: =-SUMPRODUCT(--(Monthly!$C$4:$BJ$4<=$B$6),Monthly!$C$56:$BJ$56) -> 0
A10: Total uses of funds | B10: =B7+B8+B9 -> -760226.47
A11: Minimum cash buffer to keep | B11: =Inputs!$E$61 -> 1906000 | D11: Input on the Inputs sheet
A12: Funding required (uses + buffer) | B12: =B10+B11 -> 1145773.5
A14: Equity raised | B14: =Inputs!$E$46 -> 1000000
A15: Loan drawn | B15: =Inputs!$E$47 -> 0
A16: Total sources of funds | B16: =B14+B15 -> 1000000
A17: Funding surplus / (shortfall) | B17: =B16-B12 -> -145773.53 | D17: Negative = raise at least this much more
A18: Lowest cash balance in the plan | B18: =MIN(Monthly!$C$76:$BJ$76) -> 1760226.5 | D18: Equals sources minus uses
A20: Break-even timing
A21: First month with positive EBITDA (month #) | B21: =IFERROR(MATCH(1,Monthly!$C$77:$BJ$77,0),"Not within horizon") -> 1
A22: First month with positive net income (month #) | B22: =IFERROR(MATCH(1,Monthly!$C$84:$BJ$84,0),"Not within horizon") -> 1
A23: Cash invested paid back (month #) | B23: =IF(MIN(Monthly!$C$86:$BJ$86)>=0,"No investment to pay back",IFERROR(MATCH(1,Monthly!$C$88:$BJ$88,0),"Not within horizon")) -> No investment to pay back | D23: Cumulative operating + investing cash flow back to zero
A25: Annual break-even revenue
A26: Year # | B26: 1 | C26: 2 | D26: 3 | E26: 4 | F26: 5
B27: Year 1 | C27: Year 2 | D27: Year 3 | E27: Year 4 | F27: Year 5
A28: Revenue | B28: =SUMIF(Monthly!$C$5:$BJ$5,B$26,Monthly!$C$24:$BJ$24) -> 10216766 | C28: =SUMIF(Monthly!$C$5:$BJ$5,C$26,Monthly!$C$24:$BJ$24) -> 12946280 | D28: =SUMIF(Monthly!$C$5:$BJ$5,D$26,Monthly!$C$24:$BJ$24) -> 16448495 | E28: =SUMIF(Monthly!$C$5:$BJ$5,E$26,Monthly!$C$24:$BJ$24) -> 20947000 | F28: =SUMIF(Monthly!$C$5:$BJ$5,F$26,Monthly!$C$24:$BJ$24) -> 26732395
A29: Gross profit | B29: =SUMIF(Monthly!$C$5:$BJ$5,B$26,Monthly!$C$26:$BJ$26) -> 9115572.1 | C29: =SUMIF(Monthly!$C$5:$BJ$5,C$26,Monthly!$C$26:$BJ$26) -> 11555505 | D29: =SUMIF(Monthly!$C$5:$BJ$5,D$26,Monthly!$C$26:$BJ$26) -> 14686438 | E29: =SUMIF(Monthly!$C$5:$BJ$5,E$26,Monthly!$C$26:$BJ$26) -> 18708530 | F29: =SUMIF(Monthly!$C$5:$BJ$5,F$26,Monthly!$C$26:$BJ$26) -> 23881957
A30: Gross margin (contribution) | B30: =IF(B28=0,0,B29/B28) -> 0.89221699 | C30: =IF(C28=0,0,C29/C28) -> 0.8925734 | D30: =IF(D28=0,0,D29/D28) -> 0.89287426 | E30: =IF(E28=0,0,E29/E28) -> 0.89313648 | F30: =IF(F28=0,0,F29/F28) -> 0.89337139
A31: Operating expenses (treated as fixed) | B31: =-SUMIF(Monthly!$C$5:$BJ$5,B$26,Monthly!$C$34:$BJ$34) -> 7622400 | C31: =-SUMIF(Monthly!$C$5:$BJ$5,C$26,Monthly!$C$34:$BJ$34) -> 9305892 | D31: =-SUMIF(Monthly!$C$5:$BJ$5,D$26,Monthly!$C$34:$BJ$34) -> 11392489 | E31: =-SUMIF(Monthly!$C$5:$BJ$5,E$26,Monthly!$C$34:$BJ$34) -> 13979315 | F31: =-SUMIF(Monthly!$C$5:$BJ$5,F$26,Monthly!$C$34:$BJ$34) -> 17187019
A32: Break-even revenue (EBITDA = 0) | B32: =IF(B30>0,B31/B30,"n/a") -> 8543213.2 | C32: =IF(C30>0,C31/C30,"n/a") -> 10425912 | D32: =IF(D30>0,D31/D30,"n/a") -> 12759343 | E32: =IF(E30>0,E31/E30,"n/a") -> 15651936 | F32: =IF(F30>0,F31/F30,"n/a") -> 19238381
A33: Margin of safety (revenue above break-even) | B33: =IF(AND(ISNUMBER(B32),B28>0),(B28-B32)/B28,"n/a") -> 0.16380454 | C33: =IF(AND(ISNUMBER(C32),C28>0),(C28-C32)/C28,"n/a") -> 0.19467889 | D33: =IF(AND(ISNUMBER(D32),D28>0),(D28-D32)/D28,"n/a") -> 0.22428506 | E33: =IF(AND(ISNUMBER(E32),E28>0),(E28-E32)/E28,"n/a") -> 0.25278385 | F33: =IF(AND(ISNUMBER(F32),F28>0),(F28-F32)/F28,"n/a") -> 0.28033454
A35: Simplification: cost of sales is treated as variable and operating expenses as fixed, so break-even revenue = operating expenses ÷ gross margin.

Sheet Valuation
A1: Discounted cash flow valuation | H1: =HYPERLINK("#'Cover'!A1","◂ Contents") -> ◂ Contents
A2: Enterprise value at the start of the plan, before the funding raised in period 1. Year-end discounting.
A3: Scenario shown | B3: =CHOOSE(Dashboard!$B$4,"Low","Base","High") -> Base
A5: Assumptions (active scenario, from the Inputs sheet)
A6: Discount rate (WACC) | B6: =Inputs!$E$64 -> 0.12
A7: Terminal growth rate | B7: =Inputs!$E$65 -> 0.02
A8: Exit multiple (EV ÷ final-year EBITDA) | B8: =Inputs!$E$66 -> 6
A9: Tax rate (for the interest tax shield) | B9: =Inputs!$E$58 -> 0.21
A10: Sensitivity step: WACC | B10: =Inputs!$E$67 -> 0.01
A11: Sensitivity step: terminal growth | B11: =Inputs!$E$68 -> 0.005
A13: Free cash flow by year
A14: Year # | B14: 1 | C14: 2 | D14: 3 | E14: 4 | F14: 5
B15: Year 1 | C15: Year 2 | D15: Year 3 | E15: Year 4 | F15: Year 5
A16: EBITDA | B16: =SUMIF(Monthly!$C$5:$BJ$5,B$14,Monthly!$C$35:$BJ$35) -> 1493172.1 | C16: =SUMIF(Monthly!$C$5:$BJ$5,C$14,Monthly!$C$35:$BJ$35) -> 2249612.9 | D16: =SUMIF(Monthly!$C$5:$BJ$5,D$14,Monthly!$C$35:$BJ$35) -> 3293948.5 | E16: =SUMIF(Monthly!$C$5:$BJ$5,E$14,Monthly!$C$35:$BJ$35) -> 4729214.2 | F16: =SUMIF(Monthly!$C$5:$BJ$5,F$14,Monthly!$C$35:$BJ$35) -> 6694937.4
A17: Unlevered free cash flow | B17: =SUMIF(Monthly!$C$5:$BJ$5,B$14,Monthly!$C$89:$BJ$89) -> 2123134.7 | C17: =SUMIF(Monthly!$C$5:$BJ$5,C$14,Monthly!$C$89:$BJ$89) -> 2078342.8 | D17: =SUMIF(Monthly!$C$5:$BJ$5,D$14,Monthly!$C$89:$BJ$89) -> 2985771.8 | E17: =SUMIF(Monthly!$C$5:$BJ$5,E$14,Monthly!$C$89:$BJ$89) -> 4215445.8 | F17: =SUMIF(Monthly!$C$5:$BJ$5,F$14,Monthly!$C$89:$BJ$89) -> 5905773.3
A18: Discount factor | B18: =1/(1+Inputs!$E$64)^B$14 -> 0.89285714 | C18: =1/(1+Inputs!$E$64)^C$14 -> 0.79719388 | D18: =1/(1+Inputs!$E$64)^D$14 -> 0.71178025 | E18: =1/(1+Inputs!$E$64)^E$14 -> 0.63551808 | F18: =1/(1+Inputs!$E$64)^F$14 -> 0.56742686
A19: Present value of free cash flow | B19: =B17*B18 -> 1895656 | C19: =C17*C18 -> 1656842.1 | D19: =D17*D18 -> 2125213.4 | E19: =E17*E18 -> 2678992 | F19: =F17*F18 -> 3351094.4
A21: Enterprise value
B22: Perpetual growth | C22: Exit multiple
A23: Present value of the plan's free cash flows | B23: =SUM($B$19:$F$19) -> 11707798 | C23: =B23 -> 11707798
A24: Final-year free cash flow | final-year EBITDA | B24: =$F$17 -> 5905773.3 | C24: =$F$16 -> 6694937.4
A25: Terminal value at the end of year 5 | B25: =IF($B$6>$B$7,B24*(1+$B$7)/($B$6-$B$7),0) -> 60238888 | C25: =C24*$B$8 -> 40169624
A26: Present value of the terminal value | B26: =B25/(1+$B$6)^$F$14 -> 34181163 | C26: =C25/(1+$B$6)^$F$14 -> 22793324
A27: Enterprise value | B27: =B23+B26 -> 45888961 | C27: =C23+C26 -> 34501121
A28: Terminal value share of enterprise value | B28: =IF(B27<>0,B26/B27,0) -> 0.74486679 | C28: =IF(C27<>0,C26/C27,0) -> 0.66065457
A29: Cross-check: implied exit multiple | implied perpetual growth | B29: =IF(C24>0,B25/C24,"n/a") -> 8.9976776 | C29: =IF(C25+B24<>0,(C25*$B$6-B24)/(C25+B24),"n/a") -> -0.02355744
A30: Enterprise value — average of the two methods | B30: =AVERAGE(B27,C27) -> 40195041
A32: Sensitivity: enterprise value (perpetual growth) by WACC and terminal growth
A33: WACC ↓ · terminal growth → | B33: =$B$7+(-2)*$B$11 -> 0.01 | C33: =$B$7+(-1)*$B$11 -> 0.015 | D33: =$B$7+(0)*$B$11 -> 0.02 | E33: =$B$7+(1)*$B$11 -> 0.025 | F33: =$B$7+(2)*$B$11 -> 0.03
A34: =$B$6+(-2)*$B$10 -> 0.1 | B34: =IF($A34>B$33,SUMPRODUCT($B$17:$F$17/(1+$A34)^$B$14:$F$14)+$F$17*(1+B$33)/($A34-B$33)/(1+$A34)^$F$14,"n/a") -> 53589362 | C34: =IF($A34>C$33,SUMPRODUCT($B$17:$F$17/(1+$A34)^$B$14:$F$14)+$F$17*(1+C$33)/($A34-C$33)/(1+$A34)^$F$14,"n/a") -> 56225782 | D34: =IF($A34>D$33,SUMPRODUCT($B$17:$F$17/(1+$A34)^$B$14:$F$14)+$F$17*(1+D$33)/($A34-D$33)/(1+$A34)^$F$14,"n/a") -> 59191755 | E34: =IF($A34>E$33,SUMPRODUCT($B$17:$F$17/(1+$A34)^$B$14:$F$14)+$F$17*(1+E$33)/($A34-E$33)/(1+$A34)^$F$14,"n/a") -> 62553191 | F34: =IF($A34>F$33,SUMPRODUCT($B$17:$F$17/(1+$A34)^$B$14:$F$14)+$F$17*(1+F$33)/($A34-F$33)/(1+$A34)^$F$14,"n/a") -> 66394831
A35: =$B$6+(-1)*$B$10 -> 0.11 | B35: =IF($A35>B$33,SUMPRODUCT($B$17:$F$17/(1+$A35)^$B$14:$F$14)+$F$17*(1+B$33)/($A35-B$33)/(1+$A35)^$F$14,"n/a") -> 47462737 | C35: =IF($A35>C$33,SUMPRODUCT($B$17:$F$17/(1+$A35)^$B$14:$F$14)+$F$17*(1+C$33)/($A35-C$33)/(1+$A35)^$F$14,"n/a") -> 49510272 | D35: =IF($A35>D$33,SUMPRODUCT($B$17:$F$17/(1+$A35)^$B$14:$F$14)+$F$17*(1+D$33)/($A35-D$33)/(1+$A35)^$F$14,"n/a") -> 51785310 | E35: =IF($A35>E$33,SUMPRODUCT($B$17:$F$17/(1+$A35)^$B$14:$F$14)+$F$17*(1+E$33)/($A35-E$33)/(1+$A35)^$F$14,"n/a") -> 54328000 | F35: =IF($A35>F$33,SUMPRODUCT($B$17:$F$17/(1+$A35)^$B$14:$F$14)+$F$17*(1+F$33)/($A35-F$33)/(1+$A35)^$F$14,"n/a") -> 57188527
A36: =$B$6+(0)*$B$10 -> 0.12 | B36: =IF($A36>B$33,SUMPRODUCT($B$17:$F$17/(1+$A36)^$B$14:$F$14)+$F$17*(1+B$33)/($A36-B$33)/(1+$A36)^$F$14,"n/a") -> 42476937 | C36: =IF($A36>C$33,SUMPRODUCT($B$17:$F$17/(1+$A36)^$B$14:$F$14)+$F$17*(1+C$33)/($A36-C$33)/(1+$A36)^$F$14,"n/a") -> 44101710 | D36: =IF($A36>D$33,SUMPRODUCT($B$17:$F$17/(1+$A36)^$B$14:$F$14)+$F$17*(1+D$33)/($A36-D$33)/(1+$A36)^$F$14,"n/a") -> 45888961 | E36: =IF($A36>E$33,SUMPRODUCT($B$17:$F$17/(1+$A36)^$B$14:$F$14)+$F$17*(1+E$33)/($A36-E$33)/(1+$A36)^$F$14,"n/a") -> 47864343 | F36: =IF($A36>F$33,SUMPRODUCT($B$17:$F$17/(1+$A36)^$B$14:$F$14)+$F$17*(1+F$33)/($A36-F$33)/(1+$A36)^$F$14,"n/a") -> 50059212
A37: =$B$6+(1)*$B$10 -> 0.13 | B37: =IF($A37>B$33,SUMPRODUCT($B$17:$F$17/(1+$A37)^$B$14:$F$14)+$F$17*(1+B$33)/($A37-B$33)/(1+$A37)^$F$14,"n/a") -> 38345574 | C37: =IF($A37>C$33,SUMPRODUCT($B$17:$F$17/(1+$A37)^$B$14:$F$14)+$F$17*(1+C$33)/($A37-C$33)/(1+$A37)^$F$14,"n/a") -> 39657937 | D37: =IF($A37>D$33,SUMPRODUCT($B$17:$F$17/(1+$A37)^$B$14:$F$14)+$F$17*(1+D$33)/($A37-D$33)/(1+$A37)^$F$14,"n/a") -> 41089605 | E37: =IF($A37>E$33,SUMPRODUCT($B$17:$F$17/(1+$A37)^$B$14:$F$14)+$F$17*(1+E$33)/($A37-E$33)/(1+$A37)^$F$14,"n/a") -> 42657623 | F37: =IF($A37>F$33,SUMPRODUCT($B$17:$F$17/(1+$A37)^$B$14:$F$14)+$F$17*(1+F$33)/($A37-F$33)/(1+$A37)^$F$14,"n/a") -> 44382443
A38: =$B$6+(2)*$B$10 -> 0.14 | B38: =IF($A38>B$33,SUMPRODUCT($B$17:$F$17/(1+$A38)^$B$14:$F$14)+$F$17*(1+B$33)/($A38-B$33)/(1+$A38)^$F$14,"n/a") -> 34870439 | C38: =IF($A38>C$33,SUMPRODUCT($B$17:$F$17/(1+$A38)^$B$14:$F$14)+$F$17*(1+C$33)/($A38-C$33)/(1+$A38)^$F$14,"n/a") -> 35946345 | D38: =IF($A38>D$33,SUMPRODUCT($B$17:$F$17/(1+$A38)^$B$14:$F$14)+$F$17*(1+D$33)/($A38-D$33)/(1+$A38)^$F$14,"n/a") -> 37111909 | E38: =IF($A38>E$33,SUMPRODUCT($B$17:$F$17/(1+$A38)^$B$14:$F$14)+$F$17*(1+E$33)/($A38-E$33)/(1+$A38)^$F$14,"n/a") -> 38378826 | F38: =IF($A38>F$33,SUMPRODUCT($B$17:$F$17/(1+$A38)^$B$14:$F$14)+$F$17*(1+F$33)/($A38-F$33)/(1+$A38)^$F$14,"n/a") -> 39760918
A40: Free cash flow = operating cash flow + interest × (1 − tax rate) − capital spending. Cells marked n/a: WACC not above growth.

Sheet Sources & Uses
A1: Sources and uses of funds | I1: =HYPERLINK("#'Cover'!A1","◂ Contents") -> ◂ Contents
A2: SaaS company — financial model
A5: Funding structure ($'000) — raised at the start of the plan
B6: Amount | C6: Share
A7: Equity | B7: =Inputs!E46 -> 1000000 | C7: =IF($B$9=0,0,B7/$B$9) -> 1
A8: Debt (loan) | B8: =Inputs!E47 -> 0 | C8: =IF($B$9=0,0,B8/$B$9) -> 0
A9: Total funding | B9: =B7+B8 -> 1000000 | C9: =IF($B$9=0,0,B9/$B$9) -> 1
A10: Gearing (debt ÷ equity) | B10: =IF(B7=0,0,B8/B7) -> 0
A11: Funding required by the plan (Break-even sheet) | B11: ='Break-even'!B12 -> 1145773.5
A12: Surplus / (shortfall) | B12: ='Break-even'!B17 -> -145773.53
A14: ="Sources and uses — first "&$B$15&" months ($'000)" -> Sources and uses — first 12 months ($'000)
A15: Period covered (months from the start) | B15: 12
A16: Sources | B16: Amount | C16: Share | E16: Uses | F16: Amount | G16: Share
A17: Equity raised | B17: =SUMPRODUCT(--(Monthly!$C$4:$BJ$4<=$B$15),Monthly!$C$72:$BJ$72) -> 1000000 | C17: =IF($B$21=0,0,B17/$B$21) -> 0.30551752 | E17: Cash used by operations | F17: =MAX(0,-SUMPRODUCT(--(Monthly!$C$4:$BJ$4<=$B$15),Monthly!$C$70:$BJ$70)) -> 0 | G17: =IF($F$21=0,0,F17/$F$21) -> 0
A18: Loan drawdowns | B18: =SUMPRODUCT(--(Monthly!$C$4:$BJ$4<=$B$15),Monthly!$C$55:$BJ$55) -> 0 | C18: =IF($B$21=0,0,B18/$B$21) -> 0 | E18: Capital spending | F18: =-SUMPRODUCT(--(Monthly!$C$4:$BJ$4<=$B$15),Monthly!$C$71:$BJ$71) -> 150000 | G18: =IF($F$21=0,0,F18/$F$21) -> 0.045827629
A19: Cash generated by operations | B19: =MAX(0,SUMPRODUCT(--(Monthly!$C$4:$BJ$4<=$B$15),Monthly!$C$70:$BJ$70)) -> 2273134.7 | C19: =IF($B$21=0,0,B19/$B$21) -> 0.69448248 | E19: Loan repayments | F19: =-SUMPRODUCT(--(Monthly!$C$4:$BJ$4<=$B$15),Monthly!$C$56:$BJ$56) -> 0 | G19: =IF($F$21=0,0,F19/$F$21) -> 0
E20: Cash at the end of the period | F20: =INDEX(Monthly!$C$76:$BJ$76,$B$15) -> 3123134.7 | G20: =IF($F$21=0,0,F20/$F$21) -> 0.95417237
A21: Total sources | B21: =SUM(B17:B20) -> 3273134.7 | C21: =IF(B21=0,0,1) -> 1 | E21: Total uses | F21: =SUM(F17:F20) -> 3273134.7 | G21: =IF(F21=0,0,1) -> 1
A22: Sources − uses (must be 0; opening cash is 0) | B22: =B21-F21 -> 0

Sheet KPIs
A1: KPIs & ratios | I1: =HYPERLINK("#'Cover'!A1","◂ Contents") -> ◂ Contents
A2: Industry metrics and financial ratios for the active scenario.
A4: Financial ratios
B5: ='P&L'!B4 -> Year 1 | C5: ='P&L'!C4 -> Year 2 | D5: ='P&L'!D4 -> Year 3 | E5: ='P&L'!E4 -> Year 4 | F5: ='P&L'!F4 -> Year 5 | G5: Target
A6: Revenue growth | B6: - | C6: =IF('P&L'!B5=0,0,'P&L'!C5/'P&L'!B5-1) -> 0.26716027 | D6: =IF('P&L'!C5=0,0,'P&L'!D5/'P&L'!C5-1) -> 0.27051902 | E6: =IF('P&L'!D5=0,0,'P&L'!E5/'P&L'!D5-1) -> 0.27349038 | F6: =IF('P&L'!E5=0,0,'P&L'!F5/'P&L'!E5-1) -> 0.27619206
A7: Gross margin | B7: ='P&L'!B8 -> 0.89221699 | C7: ='P&L'!C8 -> 0.8925734 | D7: ='P&L'!D8 -> 0.89287426 | E7: ='P&L'!E8 -> 0.89313648 | F7: ='P&L'!F8 -> 0.89337139
A8: EBITDA margin | B8: ='P&L'!B16 -> 0.14614919 | C8: ='P&L'!C16 -> 0.1737652 | D8: ='P&L'!D16 -> 0.20025835 | E8: ='P&L'!E16 -> 0.22577048 | F8: ='P&L'!F16 -> 0.25044286
A9: Net margin | B9: ='P&L'!B23 -> 0.11159167 | C9: ='P&L'!C23 -> 0.13422344 | D9: ='P&L'!D23 -> 0.15580266 | E9: ='P&L'!E23 -> 0.17835868 | F9: ='P&L'!F23 -> 0.19784986
A10: Payroll, % of revenue | B10: =IF('P&L'!B5=0,0,-'P&L'!B9/'P&L'!B5) -> 0.61428442 | C10: =IF('P&L'!C5=0,0,-'P&L'!C9/'P&L'!C5) -> 0.60239329 | D10: =IF('P&L'!D5=0,0,-'P&L'!D9/'P&L'!D5) -> 0.58926621 | E10: =IF('P&L'!E5=0,0,-'P&L'!E9/'P&L'!E5) -> 0.57517035 | F10: =IF('P&L'!F5=0,0,-'P&L'!F9/'P&L'!F5) -> 0.56030797
A11: Paid marketing, % of revenue | B11: =IF('P&L'!B5=0,0,-'P&L'!B10/'P&L'!B5) -> 0.070472399 | C11: =IF('P&L'!C5=0,0,-'P&L'!C10/'P&L'!C5) -> 0.066737319 | D11: =IF('P&L'!D5=0,0,-'P&L'!D10/'P&L'!D5) -> 0.063033124 | E11: =IF('P&L'!E5=0,0,-'P&L'!E10/'P&L'!E5) -> 0.059395618 | F11: =IF('P&L'!F5=0,0,-'P&L'!F10/'P&L'!F5) -> 0.055849542
A12: Operating expenses, % of revenue | B12: =IF('P&L'!B5=0,0,-'P&L'!B14/'P&L'!B5) -> 0.7460678 | C12: =IF('P&L'!C5=0,0,-'P&L'!C14/'P&L'!C5) -> 0.7188082 | D12: =IF('P&L'!D5=0,0,-'P&L'!D14/'P&L'!D5) -> 0.69261591 | E12: =IF('P&L'!E5=0,0,-'P&L'!E14/'P&L'!E5) -> 0.667366 | F12: =IF('P&L'!F5=0,0,-'P&L'!F14/'P&L'!F5) -> 0.64292853
A13: Current ratio (current assets ÷ current liabilities) | B13: =IF(('Balance Sheet'!B10+'Balance Sheet'!B11)=0,0,('Balance Sheet'!B5+'Balance Sheet'!B6+'Balance Sheet'!B7)/('Balance Sheet'!B10+'Balance Sheet'!B11)) -> 2.6454315 | C13: =IF(('Balance Sheet'!C10+'Balance Sheet'!C11)=0,0,('Balance Sheet'!C5+'Balance Sheet'!C6+'Balance Sheet'!C7)/('Balance Sheet'!C10+'Balance Sheet'!C11)) -> 3.4340025 | D13: =IF(('Balance Sheet'!D10+'Balance Sheet'!D11)=0,0,('Balance Sheet'!D5+'Balance Sheet'!D6+'Balance Sheet'!D7)/('Balance Sheet'!D10+'Balance Sheet'!D11)) -> 4.2206437 | E13: =IF(('Balance Sheet'!E10+'Balance Sheet'!E11)=0,0,('Balance Sheet'!E5+'Balance Sheet'!E6+'Balance Sheet'!E7)/('Balance Sheet'!E10+'Balance Sheet'!E11)) -> 4.9929909 | F13: =IF(('Balance Sheet'!F10+'Balance Sheet'!F11)=0,0,('Balance Sheet'!F5+'Balance Sheet'!F6+'Balance Sheet'!F7)/('Balance Sheet'!F10+'Balance Sheet'!F11)) -> 5.7516278
A14: Debt ÷ equity | B14: =IF('Balance Sheet'!B16<=0,0,'Balance Sheet'!B12/'Balance Sheet'!B16) -> 0 | C14: =IF('Balance Sheet'!C16<=0,0,'Balance Sheet'!C12/'Balance Sheet'!C16) -> 0 | D14: =IF('Balance Sheet'!D16<=0,0,'Balance Sheet'!D12/'Balance Sheet'!D16) -> 0 | E14: =IF('Balance Sheet'!E16<=0,0,'Balance Sheet'!E12/'Balance Sheet'!E16) -> 0 | F14: =IF('Balance Sheet'!F16<=0,0,'Balance Sheet'!F12/'Balance Sheet'!F16) -> 0
A15: Return on assets (net income ÷ year-end assets) | B15: =IF('Balance Sheet'!B9=0,0,'P&L'!B22/'Balance Sheet'!B9) -> 0.33731277 | C15: =IF('Balance Sheet'!C9=0,0,'P&L'!C22/'Balance Sheet'!C9) -> 0.31881745 | D15: =IF('Balance Sheet'!D9=0,0,'P&L'!D22/'Balance Sheet'!D9) -> 0.30362962 | E15: =IF('Balance Sheet'!E9=0,0,'P&L'!E22/'Balance Sheet'!E9) -> 0.29359657 | F15: =IF('Balance Sheet'!F9=0,0,'P&L'!F22/'Balance Sheet'!F9) -> 0.28252605
A16: Return on equity (net income ÷ year-end equity) | B16: =IF('Balance Sheet'!B16<=0,0,'P&L'!B22/'Balance Sheet'!B16) -> 0.53273341 | C16: =IF('Balance Sheet'!C16<=0,0,'P&L'!C22/'Balance Sheet'!C16) -> 0.4481134 | D16: =IF('Balance Sheet'!D16<=0,0,'P&L'!D22/'Balance Sheet'!D16) -> 0.39790569 | E16: =IF('Balance Sheet'!E16<=0,0,'P&L'!E22/'Balance Sheet'!E16) -> 0.36712456 | F16: =IF('Balance Sheet'!F16<=0,0,'P&L'!F22/'Balance Sheet'!F16) -> 0.34198484
A18: DuPont analysis — return on equity = net margin × asset turnover × equity multiplier
B19: ='P&L'!B4 -> Year 1 | C19: ='P&L'!C4 -> Year 2 | D19: ='P&L'!D4 -> Year 3 | E19: ='P&L'!E4 -> Year 4 | F19: ='P&L'!F4 -> Year 5
A20: Net margin | B20: ='P&L'!B23 -> 0.11159167 | C20: ='P&L'!C23 -> 0.13422344 | D20: ='P&L'!D23 -> 0.15580266 | E20: ='P&L'!E23 -> 0.17835868 | F20: ='P&L'!F23 -> 0.19784986
A21: × Asset turnover (revenue ÷ assets) | B21: =IF('Balance Sheet'!B9=0,0,'P&L'!B5/'Balance Sheet'!B9) -> 3.0227415 | C21: =IF('Balance Sheet'!C9=0,0,'P&L'!C5/'Balance Sheet'!C9) -> 2.3752741 | D21: =IF('Balance Sheet'!D9=0,0,'P&L'!D5/'Balance Sheet'!D9) -> 1.9488089 | E21: =IF('Balance Sheet'!E9=0,0,'P&L'!E5/'Balance Sheet'!E9) -> 1.6461019 | F21: =IF('Balance Sheet'!F9=0,0,'P&L'!F5/'Balance Sheet'!F9) -> 1.4279821
A22: × Equity multiplier (assets ÷ equity) | B22: =IF('Balance Sheet'!B16<=0,0,'Balance Sheet'!B9/'Balance Sheet'!B16) -> 1.5793455 | C22: =IF('Balance Sheet'!C16<=0,0,'Balance Sheet'!C9/'Balance Sheet'!C16) -> 1.4055485 | D22: =IF('Balance Sheet'!D16<=0,0,'Balance Sheet'!D9/'Balance Sheet'!D16) -> 1.3104969 | E22: =IF('Balance Sheet'!E16<=0,0,'Balance Sheet'!E9/'Balance Sheet'!E16) -> 1.2504388 | F22: =IF('Balance Sheet'!F16<=0,0,'Balance Sheet'!F9/'Balance Sheet'!F16) -> 1.2104542
A23: Return on equity (product of the three) | B23: =B20*B21*B22 -> 0.53273341 | C23: =C20*C21*C22 -> 0.4481134 | D23: =D20*D21*D22 -> 0.39790569 | E23: =E20*E21*E22 -> 0.36712456 | F23: =F20*F21*F22 -> 0.34198484
A24: SaaS metrics
A25: Year # | B25: 1 | C25: 2 | D25: 3 | E25: 4 | F25: 5
B26: Year 1 | C26: Year 2 | D26: Year 3 | E26: Year 4 | F26: Year 5 | G26: Target
A27: Customers (year end) | B27: =INDEX(Monthly!$C$13:$BJ$13,B$25*12) -> 3608.1828 | C27: =INDEX(Monthly!$C$13:$BJ$13,C$25*12) -> 4380.8763 | D27: =INDEX(Monthly!$C$13:$BJ$13,D$25*12) -> 5357.1408 | E27: =INDEX(Monthly!$C$13:$BJ$13,E$25*12) -> 6586.8077 | F27: =INDEX(Monthly!$C$13:$BJ$13,F$25*12) -> 8133.3379
A28: New customers in the year | B28: =SUMIF(Monthly!$C$5:$BJ$5,B$25,Monthly!$C$10:$BJ$10) -> 1200 | C28: =SUMIF(Monthly!$C$5:$BJ$5,C$25,Monthly!$C$10:$BJ$10) -> 1488 | D28: =SUMIF(Monthly!$C$5:$BJ$5,D$25,Monthly!$C$10:$BJ$10) -> 1848 | E28: =SUMIF(Monthly!$C$5:$BJ$5,E$25,Monthly!$C$10:$BJ$10) -> 2298.72 | F28: =SUMIF(Monthly!$C$5:$BJ$5,F$25,Monthly!$C$10:$BJ$10) -> 2863.92
A29: Customers lost in the year | B29: =SUMIF(Monthly!$C$5:$BJ$5,B$25,Monthly!$C$12:$BJ$12) -> -591.81722 | C29: =SUMIF(Monthly!$C$5:$BJ$5,C$25,Monthly!$C$12:$BJ$12) -> -715.30645 | D29: =SUMIF(Monthly!$C$5:$BJ$5,D$25,Monthly!$C$12:$BJ$12) -> -871.73554 | E29: =SUMIF(Monthly!$C$5:$BJ$5,E$25,Monthly!$C$12:$BJ$12) -> -1069.0531 | F29: =SUMIF(Monthly!$C$5:$BJ$5,F$25,Monthly!$C$12:$BJ$12) -> -1317.3899
A30: MRR (year end) | B30: =INDEX(Monthly!$C$21:$BJ$21,B$25*12) -> 948826.47 | C30: =INDEX(Monthly!$C$21:$BJ$21,C$25*12) -> 1203798.5 | D30: =INDEX(Monthly!$C$21:$BJ$21,D$25*12) -> 1531085.8 | E30: =INDEX(Monthly!$C$21:$BJ$21,E$25*12) -> 1951687.2 | F30: =INDEX(Monthly!$C$21:$BJ$21,F$25*12) -> 2492911.2
A31: ARR (year-end MRR × 12) | B31: =B30*12 -> 11385918 | C31: =C30*12 -> 14445582 | D31: =D30*12 -> 18373030 | E31: =E30*12 -> 23420246 | F31: =F30*12 -> 29914934
A32: Average MRR per customer (year end) | B32: =IF(B27=0,0,B30/B27) -> 262.96519 | C32: =IF(C27=0,0,C30/C27) -> 274.78487 | D32: =IF(D27=0,0,D30/D27) -> 285.8028 | E32: =IF(E27=0,0,E30/E27) -> 296.30244 | F32: =IF(F27=0,0,F30/F27) -> 306.5053
A33: Revenue | B33: =SUMIF(Monthly!$C$5:$BJ$5,B$25,Monthly!$C$24:$BJ$24) -> 10216766 | C33: =SUMIF(Monthly!$C$5:$BJ$5,C$25,Monthly!$C$24:$BJ$24) -> 12946280 | D33: =SUMIF(Monthly!$C$5:$BJ$5,D$25,Monthly!$C$24:$BJ$24) -> 16448495 | E33: =SUMIF(Monthly!$C$5:$BJ$5,E$25,Monthly!$C$24:$BJ$24) -> 20947000 | F33: =SUMIF(Monthly!$C$5:$BJ$5,F$25,Monthly!$C$24:$BJ$24) -> 26732395
A34: Gross profit | B34: =SUMIF(Monthly!$C$5:$BJ$5,B$25,Monthly!$C$26:$BJ$26) -> 9115572.1 | C34: =SUMIF(Monthly!$C$5:$BJ$5,C$25,Monthly!$C$26:$BJ$26) -> 11555505 | D34: =SUMIF(Monthly!$C$5:$BJ$5,D$25,Monthly!$C$26:$BJ$26) -> 14686438 | E34: =SUMIF(Monthly!$C$5:$BJ$5,E$25,Monthly!$C$26:$BJ$26) -> 18708530 | F34: =SUMIF(Monthly!$C$5:$BJ$5,F$25,Monthly!$C$26:$BJ$26) -> 23881957
A35: Gross margin | B35: =IF(B33=0,0,B34/B33) -> 0.89221699 | C35: =IF(C33=0,0,C34/C33) -> 0.8925734 | D35: =IF(D33=0,0,D34/D33) -> 0.89287426 | E35: =IF(E33=0,0,E34/E33) -> 0.89313648 | F35: =IF(F33=0,0,F34/F33) -> 0.89337139
A36: Paid marketing spend | B36: =-SUMIF(Monthly!$C$5:$BJ$5,B$25,Monthly!$C$30:$BJ$30) -> 720000 | C36: =-SUMIF(Monthly!$C$5:$BJ$5,C$25,Monthly!$C$30:$BJ$30) -> 864000 | D36: =-SUMIF(Monthly!$C$5:$BJ$5,D$25,Monthly!$C$30:$BJ$30) -> 1036800 | E36: =-SUMIF(Monthly!$C$5:$BJ$5,E$25,Monthly!$C$30:$BJ$30) -> 1244160 | F36: =-SUMIF(Monthly!$C$5:$BJ$5,F$25,Monthly!$C$30:$BJ$30) -> 1492992
A37: Blended CAC (paid spend ÷ all new customers) | B37: =IF(B28=0,0,B36/B28) -> 600 | C37: =IF(C28=0,0,C36/C28) -> 580.64516 | D37: =IF(D28=0,0,D36/D28) -> 561.03896 | E37: =IF(E28=0,0,E36/E28) -> 541.24034 | F37: =IF(F28=0,0,F36/F28) -> 521.31065
A38: Customer churn per month | B38: =INDEX(Monthly!$C$81:$BJ$81,B$25*12) -> 0.015 | C38: =INDEX(Monthly!$C$81:$BJ$81,C$25*12) -> 0.015 | D38: =INDEX(Monthly!$C$81:$BJ$81,D$25*12) -> 0.015 | E38: =INDEX(Monthly!$C$81:$BJ$81,E$25*12) -> 0.015 | F38: =INDEX(Monthly!$C$81:$BJ$81,F$25*12) -> 0.015
A39: Customer lifetime value (MRR × margin ÷ churn) | B39: =IF(B38=0,0,B32*B35/B38) -> 15641.467 | C39: =IF(C38=0,0,C32*C35/C38) -> 16351.044 | D39: =IF(D38=0,0,D32*D35/D38) -> 17012.397 | E39: =IF(E38=0,0,E32*E35/E38) -> 17642.568 | F39: =IF(F38=0,0,F32*F35/F38) -> 18254.871
A40: LTV ÷ CAC | B40: =IF(B37=0,0,B39/B37) -> 26.069112 | C40: =IF(C37=0,0,C39/C37) -> 28.160132 | D40: =IF(D37=0,0,D39/D37) -> 30.323023 | E40: =IF(E37=0,0,E39/E37) -> 32.59655 | F40: =IF(F37=0,0,F39/F37) -> 35.017261
A41: CAC payback (months of gross profit) | B41: =IF(B32*B35<=0,0,B37/(B32*B35)) -> 2.5573048 | C41: =IF(C32*C35<=0,0,C37/(C32*C35)) -> 2.3674131 | D41: =IF(D32*D35<=0,0,D37/(D32*D35)) -> 2.1985495 | E41: =IF(E32*E35<=0,0,E37/(E32*E35)) -> 2.0452062 | F41: =IF(F32*F35<=0,0,F37/(F32*F35)) -> 1.903823
A42: Net burn per month (year end) | B42: =INDEX(Monthly!$C$80:$BJ$80,B$25*12) -> -180294.49 | C42: =INDEX(Monthly!$C$80:$BJ$80,C$25*12) -> -253004.28 | D42: =INDEX(Monthly!$C$80:$BJ$80,D$25*12) -> -351269.91 | E42: =INDEX(Monthly!$C$80:$BJ$80,E$25*12) -> -482972.01 | F42: =INDEX(Monthly!$C$80:$BJ$80,F$25*12) -> -661623.54
A43: Cash (year end) | B43: =INDEX(Monthly!$C$76:$BJ$76,B$25*12) -> 3123134.7 | C43: =INDEX(Monthly!$C$76:$BJ$76,C$25*12) -> 5201477.5 | D43: =INDEX(Monthly!$C$76:$BJ$76,D$25*12) -> 8187249.2 | E43: =INDEX(Monthly!$C$76:$BJ$76,E$25*12) -> 12402695 | F43: =INDEX(Monthly!$C$76:$BJ$76,F$25*12) -> 18308468
A44: Runway at year-end burn (months; - = not burning) | B44: =IF(B42<=0,0,MAX(0,B43)/B42) -> 0 | C44: =IF(C42<=0,0,MAX(0,C43)/C42) -> 0 | D44: =IF(D42<=0,0,MAX(0,D43)/D42) -> 0 | E44: =IF(E42<=0,0,MAX(0,E43)/E42) -> 0 | F44: =IF(F42<=0,0,MAX(0,F43)/F42) -> 0

Sheet Inputs
A1: Inputs | I1: =HYPERLINK("#'Cover'!A1","◂ Contents") -> ◂ Contents
A2: Every assumption lives here once, with Low / Base / High values. Change the yellow cells; the active scenario is chosen on the Dashboard.
A5: Driver | B5: Low | C5: Base | D5: High | E5: Active | F5: Unit | G5: Source / comment
A6: Business drivers
A7: Paying customers at start | B7: 3000 | C7: 3000 | D7: 3000 | E7: =CHOOSE(Dashboard!$B$4,B7,C7,D7) -> 3000 | F7: # | G7: Low ≤ Base ≤ High
A8: Average MRR per new customer (ARPA) | B8: 230 | C8: 250 | D8: 270 | E8: =CHOOSE(Dashboard!$B$4,B8,C8,D8) -> 250 | F8: $ / month | G8: Low ≤ Base ≤ High
A9: Price increase per year for new customers | B9: 0 | C9: 0.03 | D9: 0.05 | E9: =CHOOSE(Dashboard!$B$4,B9,C9,D9) -> 0.03 | F9: % | G9: Low ≤ Base ≤ High
A10: Customer churn per month | B10: 0.02 | C10: 0.015 | D10: 0.01 | E10: =CHOOSE(Dashboard!$B$4,B10,C10,D10) -> 0.015 | F10: % | G10: Low ≥ Base ≥ High (lower is better)
A11: Expansion MRR per month, % of opening MRR | B11: 0 | C11: 0.005 | D11: 0.01 | E11: =CHOOSE(Dashboard!$B$4,B11,C11,D11) -> 0.005 | F11: % | G11: Low ≤ Base ≤ High
A12: Organic / referral new customers per month (year 1) | B12: 30 | C12: 40 | D12: 50 | E12: =CHOOSE(Dashboard!$B$4,B12,C12,D12) -> 40 | F12: # / month | G12: Low ≤ Base ≤ High
A13: Growth of organic new customers per year | B13: 0.1 | C13: 0.3 | D13: 0.5 | E13: =CHOOSE(Dashboard!$B$4,B13,C13,D13) -> 0.3 | F13: % | G13: Low ≤ Base ≤ High
A14: Paid marketing budget per month (year 1) | B14: 60000 | C14: 60000 | D14: 60000 | E14: =CHOOSE(Dashboard!$B$4,B14,C14,D14) -> 60000 | F14: $ / month
A15: Paid marketing budget growth per year | B15: 0.2 | C15: 0.2 | D15: 0.2 | E15: =CHOOSE(Dashboard!$B$4,B15,C15,D15) -> 0.2 | F15: %
A16: Paid customer acquisition cost (CAC) | B16: 1200 | C16: 1000 | D16: 800 | E16: =CHOOSE(Dashboard!$B$4,B16,C16,D16) -> 1000 | F16: $ | G16: Low ≥ Base ≥ High (lower is better)
A17: Share of MRR billed annually in advance | B17: 0.2 | C17: 0.2 | D17: 0.2 | E17: =CHOOSE(Dashboard!$B$4,B17,C17,D17) -> 0.2 | F17: %
A18: Hosting & payment fees, % of revenue | B18: 0.12 | C18: 0.1 | D18: 0.08 | E18: =CHOOSE(Dashboard!$B$4,B18,C18,D18) -> 0.1 | F18: % | G18: Low ≥ Base ≥ High (lower is better)
A19: Support & onboarding cost per customer per month | B19: 3 | C19: 2 | D19: 1.5 | E19: =CHOOSE(Dashboard!$B$4,B19,C19,D19) -> 2 | F19: $ | G19: Low ≥ Base ≥ High (lower is better)
A20: Software & tools per FTE per month | B20: 150 | C20: 150 | D20: 150 | E20: =CHOOSE(Dashboard!$B$4,B20,C20,D20) -> 150 | F20: $
A21: Office & rent per month | B21: 20000 | C21: 20000 | D21: 20000 | E21: =CHOOSE(Dashboard!$B$4,B21,C21,D21) -> 20000 | F21: $
A22: Other G&A per month (legal, accounting, insurance) | B22: 25000 | C22: 25000 | D22: 25000 | E22: =CHOOSE(Dashboard!$B$4,B22,C22,D22) -> 25000 | F22: $
A23: Start-up capex (equipment) | B23: 150000 | C23: 150000 | D23: 150000 | E23: =CHOOSE(Dashboard!$B$4,B23,C23,D23) -> 150000 | F23: $
A25: Headcount
A26: Engineering & product: headcount (FTE) | B26: 20 | C26: 20 | D26: 20 | E26: =CHOOSE(Dashboard!$B$4,B26,C26,D26) -> 20 | F26: FTE | G26: Low ≤ Base ≤ High
A27: Engineering & product: salary per FTE per year | B27: 135000 | C27: 135000 | D27: 135000 | E27: =CHOOSE(Dashboard!$B$4,B27,C27,D27) -> 135000 | F27: $
A28: Engineering & product: headcount growth per year | B28: 0.2 | C28: 0.2 | D28: 0.2 | E28: =CHOOSE(Dashboard!$B$4,B28,C28,D28) -> 0.2 | F28: % | G28: Low ≤ Base ≤ High
A29: Engineering & product: first month on payroll | B29: 1 | C29: 1 | D29: 1 | E29: =CHOOSE(Dashboard!$B$4,B29,C29,D29) -> 1 | F29: month #
A30: Sales & marketing: headcount (FTE) | B30: 14 | C30: 14 | D30: 14 | E30: =CHOOSE(Dashboard!$B$4,B30,C30,D30) -> 14 | F30: FTE | G30: Low ≤ Base ≤ High
A31: Sales & marketing: salary per FTE per year | B31: 105000 | C31: 105000 | D31: 105000 | E31: =CHOOSE(Dashboard!$B$4,B31,C31,D31) -> 105000 | F31: $
A32: Sales & marketing: headcount growth per year | B32: 0.2 | C32: 0.2 | D32: 0.2 | E32: =CHOOSE(Dashboard!$B$4,B32,C32,D32) -> 0.2 | F32: % | G32: Low ≤ Base ≤ High
A33: Sales & marketing: first month on payroll | B33: 1 | C33: 1 | D33: 1 | E33: =CHOOSE(Dashboard!$B$4,B33,C33,D33) -> 1 | F33: month #
A34: Customer success: headcount (FTE) | B34: 8 | C34: 8 | D34: 8 | E34: =CHOOSE(Dashboard!$B$4,B34,C34,D34) -> 8 | F34: FTE | G34: Low ≤ Base ≤ High
A35: Customer success: salary per FTE per year | B35: 65000 | C35: 65000 | D35: 65000 | E35: =CHOOSE(Dashboard!$B$4,B35,C35,D35) -> 65000 | F35: $
A36: Customer success: headcount growth per year | B36: 0.2 | C36: 0.2 | D36: 0.2 | E36: =CHOOSE(Dashboard!$B$4,B36,C36,D36) -> 0.2 | F36: % | G36: Low ≤ Base ≤ High
A37: Customer success: first month on payroll | B37: 1 | C37: 1 | D37: 1 | E37: =CHOOSE(Dashboard!$B$4,B37,C37,D37) -> 1 | F37: month #
A38: G&A (finance, ops): headcount (FTE) | B38: 6 | C38: 6 | D38: 6 | E38: =CHOOSE(Dashboard!$B$4,B38,C38,D38) -> 6 | F38: FTE | G38: Low ≤ Base ≤ High
A39: G&A (finance, ops): salary per FTE per year | B39: 90000 | C39: 90000 | D39: 90000 | E39: =CHOOSE(Dashboard!$B$4,B39,C39,D39) -> 90000 | F39: $
A40: G&A (finance, ops): headcount growth per year | B40: 0.15 | C40: 0.15 | D40: 0.15 | E40: =CHOOSE(Dashboard!$B$4,B40,C40,D40) -> 0.15 | F40: % | G40: Low ≤ Base ≤ High
A41: G&A (finance, ops): first month on payroll | B41: 1 | C41: 1 | D41: 1 | E41: =CHOOSE(Dashboard!$B$4,B41,C41,D41) -> 1 | F41: month #
A42: Payroll taxes & benefits, % of salary | B42: 0.2 | C42: 0.2 | D42: 0.2 | E42: =CHOOSE(Dashboard!$B$4,B42,C42,D42) -> 0.2 | F42: %
A43: Wage growth per year | B43: 0.04 | C43: 0.04 | D43: 0.04 | E43: =CHOOSE(Dashboard!$B$4,B43,C43,D43) -> 0.04 | F43: %
A45: Funding
A46: Equity raised at start | B46: 1000000 | C46: 1000000 | D46: 1000000 | E46: =CHOOSE(Dashboard!$B$4,B46,C46,D46) -> 1000000 | F46: $
A47: Loan drawn at start | B47: 0 | C47: 0 | D47: 0 | E47: =CHOOSE(Dashboard!$B$4,B47,C47,D47) -> 0 | F47: $
A48: Loan interest rate per year | B48: 0 | C48: 0 | D48: 0 | E48: =CHOOSE(Dashboard!$B$4,B48,C48,D48) -> 0 | F48: %
A49: Loan repayment term | B49: 1 | C49: 1 | D49: 1 | E49: =CHOOSE(Dashboard!$B$4,B49,C49,D49) -> 1 | F49: years
A51: Working capital
A52: Customer payment terms (receivable days) | B52: 5 | C52: 5 | D52: 5 | E52: =CHOOSE(Dashboard!$B$4,B52,C52,D52) -> 5 | F52: days
A53: Inventory held (days of COGS) | B53: 0 | C53: 0 | D53: 0 | E53: =CHOOSE(Dashboard!$B$4,B53,C53,D53) -> 0 | F53: days
A54: Supplier payment terms (payable days) | B54: 30 | C54: 30 | D54: 30 | E54: =CHOOSE(Dashboard!$B$4,B54,C54,D54) -> 30 | F54: days
A56: Tax & depreciation
A57: Depreciation period for capex | B57: 3 | C57: 3 | D57: 3 | E57: =CHOOSE(Dashboard!$B$4,B57,C57,D57) -> 3 | F57: years
A58: Income tax rate | B58: 0.21 | C58: 0.21 | D58: 0.21 | E58: =CHOOSE(Dashboard!$B$4,B58,C58,D58) -> 0.21 | F58: %
A60: Break-even & funding
A61: Minimum cash buffer to keep | B61: 1906000 | C61: 1906000 | D61: 1906000 | E61: =CHOOSE(Dashboard!$B$4,B61,C61,D61) -> 1906000 | F61: $ | G61: About 3 months of costs
A63: Valuation
A64: Discount rate (WACC) | B64: 0.15 | C64: 0.12 | D64: 0.1 | E64: =CHOOSE(Dashboard!$B$4,B64,C64,D64) -> 0.12 | F64: % | G64: Low ≥ Base ≥ High (lower is better)
A65: Terminal growth rate (perpetuity) | B65: 0.01 | C65: 0.02 | D65: 0.03 | E65: =CHOOSE(Dashboard!$B$4,B65,C65,D65) -> 0.02 | F65: % | G65: Low ≤ Base ≤ High
A66: Exit multiple (EV ÷ final-year EBITDA) | B66: 5 | C66: 6 | D66: 8 | E66: =CHOOSE(Dashboard!$B$4,B66,C66,D66) -> 6 | F66: x | G66: Low ≤ Base ≤ High
A67: Sensitivity table: WACC step | B67: 0.01 | C67: 0.01 | D67: 0.01 | E67: =CHOOSE(Dashboard!$B$4,B67,C67,D67) -> 0.01 | F67: %
A68: Sensitivity table: growth step | B68: 0.005 | C68: 0.005 | D68: 0.005 | E68: =CHOOSE(Dashboard!$B$4,B68,C68,D68) -> 0.005 | F68: %
A70: Legend: yellow cell with blue figure = input you can change · black = formula · green = link to another sheet · grey = active value used by the model

Sheet P&L
A1: Annual profit & loss | H1: =HYPERLINK("#'Cover'!A1","◂ Contents") -> ◂ Contents
A2: Rolled up from the period detail (SUMIF on the year row; balances at year end).
A3: Year # | B3: 1 | C3: 2 | D3: 3 | E3: 4 | F3: 5
B4: Year 1 | C4: Year 2 | D4: Year 3 | E4: Year 4 | F4: Year 5
A5: Revenue | B5: =SUMIF(Monthly!$C$5:$BJ$5,B$3,Monthly!$C$24:$BJ$24) -> 10216766 | C5: =SUMIF(Monthly!$C$5:$BJ$5,C$3,Monthly!$C$24:$BJ$24) -> 12946280 | D5: =SUMIF(Monthly!$C$5:$BJ$5,D$3,Monthly!$C$24:$BJ$24) -> 16448495 | E5: =SUMIF(Monthly!$C$5:$BJ$5,E$3,Monthly!$C$24:$BJ$24) -> 20947000 | F5: =SUMIF(Monthly!$C$5:$BJ$5,F$3,Monthly!$C$24:$BJ$24) -> 26732395
A6: Hosting, payment fees & support | B6: =SUMIF(Monthly!$C$5:$BJ$5,B$3,Monthly!$C$25:$BJ$25) -> -1101193.7 | C6: =SUMIF(Monthly!$C$5:$BJ$5,C$3,Monthly!$C$25:$BJ$25) -> -1390774.9 | D6: =SUMIF(Monthly!$C$5:$BJ$5,D$3,Monthly!$C$25:$BJ$25) -> -1762057.1 | E6: =SUMIF(Monthly!$C$5:$BJ$5,E$3,Monthly!$C$25:$BJ$25) -> -2238470.1 | F6: =SUMIF(Monthly!$C$5:$BJ$5,F$3,Monthly!$C$25:$BJ$25) -> -2850438
A7: Gross profit | B7: =SUMIF(Monthly!$C$5:$BJ$5,B$3,Monthly!$C$26:$BJ$26) -> 9115572.1 | C7: =SUMIF(Monthly!$C$5:$BJ$5,C$3,Monthly!$C$26:$BJ$26) -> 11555505 | D7: =SUMIF(Monthly!$C$5:$BJ$5,D$3,Monthly!$C$26:$BJ$26) -> 14686438 | E7: =SUMIF(Monthly!$C$5:$BJ$5,E$3,Monthly!$C$26:$BJ$26) -> 18708530 | F7: =SUMIF(Monthly!$C$5:$BJ$5,F$3,Monthly!$C$26:$BJ$26) -> 23881957
A8: Gross margin | B8: =IF(B5=0,0,B7/B5) -> 0.89221699 | C8: =IF(C5=0,0,C7/C5) -> 0.8925734 | D8: =IF(D5=0,0,D7/D5) -> 0.89287426 | E8: =IF(E5=0,0,E7/E5) -> 0.89313648 | F8: =IF(F5=0,0,F7/F5) -> 0.89337139
A9: Payroll | B9: =SUMIF(Monthly!$C$5:$BJ$5,B$3,Monthly!$C$29:$BJ$29) -> -6276000 | C9: =SUMIF(Monthly!$C$5:$BJ$5,C$3,Monthly!$C$29:$BJ$29) -> -7798752 | D9: =SUMIF(Monthly!$C$5:$BJ$5,D$3,Monthly!$C$29:$BJ$29) -> -9692542.1 | E9: =SUMIF(Monthly!$C$5:$BJ$5,E$3,Monthly!$C$29:$BJ$29) -> -12048093 | F9: =SUMIF(Monthly!$C$5:$BJ$5,F$3,Monthly!$C$29:$BJ$29) -> -14978374
A10: Paid marketing | B10: =SUMIF(Monthly!$C$5:$BJ$5,B$3,Monthly!$C$30:$BJ$30) -> -720000 | C10: =SUMIF(Monthly!$C$5:$BJ$5,C$3,Monthly!$C$30:$BJ$30) -> -864000 | D10: =SUMIF(Monthly!$C$5:$BJ$5,D$3,Monthly!$C$30:$BJ$30) -> -1036800 | E10: =SUMIF(Monthly!$C$5:$BJ$5,E$3,Monthly!$C$30:$BJ$30) -> -1244160 | F10: =SUMIF(Monthly!$C$5:$BJ$5,F$3,Monthly!$C$30:$BJ$30) -> -1492992
A11: Software & tools | B11: =SUMIF(Monthly!$C$5:$BJ$5,B$3,Monthly!$C$31:$BJ$31) -> -86400 | C11: =SUMIF(Monthly!$C$5:$BJ$5,C$3,Monthly!$C$31:$BJ$31) -> -103140 | D11: =SUMIF(Monthly!$C$5:$BJ$5,D$3,Monthly!$C$31:$BJ$31) -> -123147 | E11: =SUMIF(Monthly!$C$5:$BJ$5,E$3,Monthly!$C$31:$BJ$31) -> -147062.25 | F11: =SUMIF(Monthly!$C$5:$BJ$5,F$3,Monthly!$C$31:$BJ$31) -> -175653.43
A12: Office & rent | B12: =SUMIF(Monthly!$C$5:$BJ$5,B$3,Monthly!$C$32:$BJ$32) -> -240000 | C12: =SUMIF(Monthly!$C$5:$BJ$5,C$3,Monthly!$C$32:$BJ$32) -> -240000 | D12: =SUMIF(Monthly!$C$5:$BJ$5,D$3,Monthly!$C$32:$BJ$32) -> -240000 | E12: =SUMIF(Monthly!$C$5:$BJ$5,E$3,Monthly!$C$32:$BJ$32) -> -240000 | F12: =SUMIF(Monthly!$C$5:$BJ$5,F$3,Monthly!$C$32:$BJ$32) -> -240000
A13: Other G&A | B13: =SUMIF(Monthly!$C$5:$BJ$5,B$3,Monthly!$C$33:$BJ$33) -> -300000 | C13: =SUMIF(Monthly!$C$5:$BJ$5,C$3,Monthly!$C$33:$BJ$33) -> -300000 | D13: =SUMIF(Monthly!$C$5:$BJ$5,D$3,Monthly!$C$33:$BJ$33) -> -300000 | E13: =SUMIF(Monthly!$C$5:$BJ$5,E$3,Monthly!$C$33:$BJ$33) -> -300000 | F13: =SUMIF(Monthly!$C$5:$BJ$5,F$3,Monthly!$C$33:$BJ$33) -> -300000
A14: Total operating expenses | B14: =SUMIF(Monthly!$C$5:$BJ$5,B$3,Monthly!$C$34:$BJ$34) -> -7622400 | C14: =SUMIF(Monthly!$C$5:$BJ$5,C$3,Monthly!$C$34:$BJ$34) -> -9305892 | D14: =SUMIF(Monthly!$C$5:$BJ$5,D$3,Monthly!$C$34:$BJ$34) -> -11392489 | E14: =SUMIF(Monthly!$C$5:$BJ$5,E$3,Monthly!$C$34:$BJ$34) -> -13979315 | F14: =SUMIF(Monthly!$C$5:$BJ$5,F$3,Monthly!$C$34:$BJ$34) -> -17187019
A15: EBITDA | B15: =SUMIF(Monthly!$C$5:$BJ$5,B$3,Monthly!$C$35:$BJ$35) -> 1493172.1 | C15: =SUMIF(Monthly!$C$5:$BJ$5,C$3,Monthly!$C$35:$BJ$35) -> 2249612.9 | D15: =SUMIF(Monthly!$C$5:$BJ$5,D$3,Monthly!$C$35:$BJ$35) -> 3293948.5 | E15: =SUMIF(Monthly!$C$5:$BJ$5,E$3,Monthly!$C$35:$BJ$35) -> 4729214.2 | F15: =SUMIF(Monthly!$C$5:$BJ$5,F$3,Monthly!$C$35:$BJ$35) -> 6694937.4
A16: EBITDA margin | B16: =IF(B5=0,0,B15/B5) -> 0.14614919 | C16: =IF(C5=0,0,C15/C5) -> 0.1737652 | D16: =IF(D5=0,0,D15/D5) -> 0.20025835 | E16: =IF(E5=0,0,E15/E5) -> 0.22577048 | F16: =IF(F5=0,0,F15/F5) -> 0.25044286
A17: Depreciation | B17: =SUMIF(Monthly!$C$5:$BJ$5,B$3,Monthly!$C$49:$BJ$49) -> -50000 | C17: =SUMIF(Monthly!$C$5:$BJ$5,C$3,Monthly!$C$49:$BJ$49) -> -50000 | D17: =SUMIF(Monthly!$C$5:$BJ$5,D$3,Monthly!$C$49:$BJ$49) -> -50000 | E17: =SUMIF(Monthly!$C$5:$BJ$5,E$3,Monthly!$C$49:$BJ$49) -> 0 | F17: =SUMIF(Monthly!$C$5:$BJ$5,F$3,Monthly!$C$49:$BJ$49) -> 0
A18: EBIT | B18: =SUMIF(Monthly!$C$5:$BJ$5,B$3,Monthly!$C$38:$BJ$38) -> 1443172.1 | C18: =SUMIF(Monthly!$C$5:$BJ$5,C$3,Monthly!$C$38:$BJ$38) -> 2199612.9 | D18: =SUMIF(Monthly!$C$5:$BJ$5,D$3,Monthly!$C$38:$BJ$38) -> 3243948.5 | E18: =SUMIF(Monthly!$C$5:$BJ$5,E$3,Monthly!$C$38:$BJ$38) -> 4729214.2 | F18: =SUMIF(Monthly!$C$5:$BJ$5,F$3,Monthly!$C$38:$BJ$38) -> 6694937.4
A19: Interest | B19: =SUMIF(Monthly!$C$5:$BJ$5,B$3,Monthly!$C$39:$BJ$39) -> 0 | C19: =SUMIF(Monthly!$C$5:$BJ$5,C$3,Monthly!$C$39:$BJ$39) -> 0 | D19: =SUMIF(Monthly!$C$5:$BJ$5,D$3,Monthly!$C$39:$BJ$39) -> 0 | E19: =SUMIF(Monthly!$C$5:$BJ$5,E$3,Monthly!$C$39:$BJ$39) -> 0 | F19: =SUMIF(Monthly!$C$5:$BJ$5,F$3,Monthly!$C$39:$BJ$39) -> 0
A20: Pre-tax income | B20: =SUMIF(Monthly!$C$5:$BJ$5,B$3,Monthly!$C$40:$BJ$40) -> 1443172.1 | C20: =SUMIF(Monthly!$C$5:$BJ$5,C$3,Monthly!$C$40:$BJ$40) -> 2199612.9 | D20: =SUMIF(Monthly!$C$5:$BJ$5,D$3,Monthly!$C$40:$BJ$40) -> 3243948.5 | E20: =SUMIF(Monthly!$C$5:$BJ$5,E$3,Monthly!$C$40:$BJ$40) -> 4729214.2 | F20: =SUMIF(Monthly!$C$5:$BJ$5,F$3,Monthly!$C$40:$BJ$40) -> 6694937.4
A21: Income tax | B21: =SUMIF(Monthly!$C$5:$BJ$5,B$3,Monthly!$C$43:$BJ$43) -> -303066.13 | C21: =SUMIF(Monthly!$C$5:$BJ$5,C$3,Monthly!$C$43:$BJ$43) -> -461918.7 | D21: =SUMIF(Monthly!$C$5:$BJ$5,D$3,Monthly!$C$43:$BJ$43) -> -681229.18 | E21: =SUMIF(Monthly!$C$5:$BJ$5,E$3,Monthly!$C$43:$BJ$43) -> -993134.99 | F21: =SUMIF(Monthly!$C$5:$BJ$5,F$3,Monthly!$C$43:$BJ$43) -> -1405936.8
A22: Net income | B22: =SUMIF(Monthly!$C$5:$BJ$5,B$3,Monthly!$C$44:$BJ$44) -> 1140105.9 | C22: =SUMIF(Monthly!$C$5:$BJ$5,C$3,Monthly!$C$44:$BJ$44) -> 1737694.2 | D22: =SUMIF(Monthly!$C$5:$BJ$5,D$3,Monthly!$C$44:$BJ$44) -> 2562719.3 | E22: =SUMIF(Monthly!$C$5:$BJ$5,E$3,Monthly!$C$44:$BJ$44) -> 3736079.2 | F22: =SUMIF(Monthly!$C$5:$BJ$5,F$3,Monthly!$C$44:$BJ$44) -> 5289000.5
A23: Net margin | B23: =IF(B5=0,0,B22/B5) -> 0.11159167 | C23: =IF(C5=0,0,C22/C5) -> 0.13422344 | D23: =IF(D5=0,0,D22/D5) -> 0.15580266 | E23: =IF(E5=0,0,E22/E5) -> 0.17835868 | F23: =IF(F5=0,0,F22/F5) -> 0.19784986

Sheet Cash Flow
A1: Annual cash flow statement | H1: =HYPERLINK("#'Cover'!A1","◂ Contents") -> ◂ Contents
A2: Rolled up from the period detail (SUMIF on the year row; balances at year end).
A3: Year # | B3: 1 | C3: 2 | D3: 3 | E3: 4 | F3: 5
B4: Year 1 | C4: Year 2 | D4: Year 3 | E4: Year 4 | F4: Year 5
A5: Net income | B5: =SUMIF(Monthly!$C$5:$BJ$5,B$3,Monthly!$C$44:$BJ$44) -> 1140105.9 | C5: =SUMIF(Monthly!$C$5:$BJ$5,C$3,Monthly!$C$44:$BJ$44) -> 1737694.2 | D5: =SUMIF(Monthly!$C$5:$BJ$5,D$3,Monthly!$C$44:$BJ$44) -> 2562719.3 | E5: =SUMIF(Monthly!$C$5:$BJ$5,E$3,Monthly!$C$44:$BJ$44) -> 3736079.2 | F5: =SUMIF(Monthly!$C$5:$BJ$5,F$3,Monthly!$C$44:$BJ$44) -> 5289000.5
A6: Add back depreciation | B6: =-SUMIF(Monthly!$C$5:$BJ$5,B$3,Monthly!$C$49:$BJ$49) -> 50000 | C6: =-SUMIF(Monthly!$C$5:$BJ$5,C$3,Monthly!$C$49:$BJ$49) -> 50000 | D6: =-SUMIF(Monthly!$C$5:$BJ$5,D$3,Monthly!$C$49:$BJ$49) -> 50000 | E6: =-SUMIF(Monthly!$C$5:$BJ$5,E$3,Monthly!$C$49:$BJ$49) -> 0 | F6: =-SUMIF(Monthly!$C$5:$BJ$5,F$3,Monthly!$C$49:$BJ$49) -> 0
A7: (Increase) / decrease in receivables | B7: =SUMIF(Monthly!$C$5:$BJ$5,B$3,Monthly!$C$63:$BJ$63) -> -156832.04 | C7: =SUMIF(Monthly!$C$5:$BJ$5,C$3,Monthly!$C$63:$BJ$63) -> -42126.633 | D7: =SUMIF(Monthly!$C$5:$BJ$5,D$3,Monthly!$C$63:$BJ$63) -> -54072.985 | E7: =SUMIF(Monthly!$C$5:$BJ$5,E$3,Monthly!$C$63:$BJ$63) -> -69487.43 | F7: =SUMIF(Monthly!$C$5:$BJ$5,F$3,Monthly!$C$63:$BJ$63) -> -89411.861
A8: (Increase) / decrease in inventory | B8: =SUMIF(Monthly!$C$5:$BJ$5,B$3,Monthly!$C$64:$BJ$64) -> 0 | C8: =SUMIF(Monthly!$C$5:$BJ$5,C$3,Monthly!$C$64:$BJ$64) -> 0 | D8: =SUMIF(Monthly!$C$5:$BJ$5,D$3,Monthly!$C$64:$BJ$64) -> 0 | E8: =SUMIF(Monthly!$C$5:$BJ$5,E$3,Monthly!$C$64:$BJ$64) -> 0 | F8: =SUMIF(Monthly!$C$5:$BJ$5,F$3,Monthly!$C$64:$BJ$64) -> 0
A9: Increase / (decrease) in payables | B9: =SUMIF(Monthly!$C$5:$BJ$5,B$3,Monthly!$C$65:$BJ$65) -> 101269.02 | C9: =SUMIF(Monthly!$C$5:$BJ$5,C$3,Monthly!$C$65:$BJ$65) -> 26808.769 | D9: =SUMIF(Monthly!$C$5:$BJ$5,D$3,Monthly!$C$65:$BJ$65) -> 34380.73 | E9: =SUMIF(Monthly!$C$5:$BJ$5,E$3,Monthly!$C$65:$BJ$65) -> 44132.386 | F9: =SUMIF(Monthly!$C$5:$BJ$5,F$3,Monthly!$C$65:$BJ$65) -> 56715.911
A10: Increase / (decrease) in deferred revenue (annual plans, ~6 months unearned) | B10: =SUMIF(Monthly!$C$5:$BJ$5,B$3,Monthly!$C$67:$BJ$67) -> 1138591.8 | C10: =SUMIF(Monthly!$C$5:$BJ$5,C$3,Monthly!$C$67:$BJ$67) -> 305966.48 | D10: =SUMIF(Monthly!$C$5:$BJ$5,D$3,Monthly!$C$67:$BJ$67) -> 392744.75 | E10: =SUMIF(Monthly!$C$5:$BJ$5,E$3,Monthly!$C$67:$BJ$67) -> 504721.63 | F10: =SUMIF(Monthly!$C$5:$BJ$5,F$3,Monthly!$C$67:$BJ$67) -> 649468.76
A11: Operating cash flow | B11: =SUMIF(Monthly!$C$5:$BJ$5,B$3,Monthly!$C$70:$BJ$70) -> 2273134.7 | C11: =SUMIF(Monthly!$C$5:$BJ$5,C$3,Monthly!$C$70:$BJ$70) -> 2078342.8 | D11: =SUMIF(Monthly!$C$5:$BJ$5,D$3,Monthly!$C$70:$BJ$70) -> 2985771.8 | E11: =SUMIF(Monthly!$C$5:$BJ$5,E$3,Monthly!$C$70:$BJ$70) -> 4215445.8 | F11: =SUMIF(Monthly!$C$5:$BJ$5,F$3,Monthly!$C$70:$BJ$70) -> 5905773.3
A12: Capital spending | B12: =SUMIF(Monthly!$C$5:$BJ$5,B$3,Monthly!$C$71:$BJ$71) -> -150000 | C12: =SUMIF(Monthly!$C$5:$BJ$5,C$3,Monthly!$C$71:$BJ$71) -> 0 | D12: =SUMIF(Monthly!$C$5:$BJ$5,D$3,Monthly!$C$71:$BJ$71) -> 0 | E12: =SUMIF(Monthly!$C$5:$BJ$5,E$3,Monthly!$C$71:$BJ$71) -> 0 | F12: =SUMIF(Monthly!$C$5:$BJ$5,F$3,Monthly!$C$71:$BJ$71) -> 0
A13: Equity raised | B13: =SUMIF(Monthly!$C$5:$BJ$5,B$3,Monthly!$C$72:$BJ$72) -> 1000000 | C13: =SUMIF(Monthly!$C$5:$BJ$5,C$3,Monthly!$C$72:$BJ$72) -> 0 | D13: =SUMIF(Monthly!$C$5:$BJ$5,D$3,Monthly!$C$72:$BJ$72) -> 0 | E13: =SUMIF(Monthly!$C$5:$BJ$5,E$3,Monthly!$C$72:$BJ$72) -> 0 | F13: =SUMIF(Monthly!$C$5:$BJ$5,F$3,Monthly!$C$72:$BJ$72) -> 0
A14: Loan drawdown | B14: =SUMIF(Monthly!$C$5:$BJ$5,B$3,Monthly!$C$55:$BJ$55) -> 0 | C14: =SUMIF(Monthly!$C$5:$BJ$5,C$3,Monthly!$C$55:$BJ$55) -> 0 | D14: =SUMIF(Monthly!$C$5:$BJ$5,D$3,Monthly!$C$55:$BJ$55) -> 0 | E14: =SUMIF(Monthly!$C$5:$BJ$5,E$3,Monthly!$C$55:$BJ$55) -> 0 | F14: =SUMIF(Monthly!$C$5:$BJ$5,F$3,Monthly!$C$55:$BJ$55) -> 0
A15: Loan repayment | B15: =SUMIF(Monthly!$C$5:$BJ$5,B$3,Monthly!$C$56:$BJ$56) -> 0 | C15: =SUMIF(Monthly!$C$5:$BJ$5,C$3,Monthly!$C$56:$BJ$56) -> 0 | D15: =SUMIF(Monthly!$C$5:$BJ$5,D$3,Monthly!$C$56:$BJ$56) -> 0 | E15: =SUMIF(Monthly!$C$5:$BJ$5,E$3,Monthly!$C$56:$BJ$56) -> 0 | F15: =SUMIF(Monthly!$C$5:$BJ$5,F$3,Monthly!$C$56:$BJ$56) -> 0
A16: Financing cash flow | B16: =SUMIF(Monthly!$C$5:$BJ$5,B$3,Monthly!$C$73:$BJ$73) -> 1000000 | C16: =SUMIF(Monthly!$C$5:$BJ$5,C$3,Monthly!$C$73:$BJ$73) -> 0 | D16: =SUMIF(Monthly!$C$5:$BJ$5,D$3,Monthly!$C$73:$BJ$73) -> 0 | E16: =SUMIF(Monthly!$C$5:$BJ$5,E$3,Monthly!$C$73:$BJ$73) -> 0 | F16: =SUMIF(Monthly!$C$5:$BJ$5,F$3,Monthly!$C$73:$BJ$73) -> 0
A17: Net change in cash | B17: =SUMIF(Monthly!$C$5:$BJ$5,B$3,Monthly!$C$74:$BJ$74) -> 3123134.7 | C17: =SUMIF(Monthly!$C$5:$BJ$5,C$3,Monthly!$C$74:$BJ$74) -> 2078342.8 | D17: =SUMIF(Monthly!$C$5:$BJ$5,D$3,Monthly!$C$74:$BJ$74) -> 2985771.8 | E17: =SUMIF(Monthly!$C$5:$BJ$5,E$3,Monthly!$C$74:$BJ$74) -> 4215445.8 | F17: =SUMIF(Monthly!$C$5:$BJ$5,F$3,Monthly!$C$74:$BJ$74) -> 5905773.3
A18: Opening cash | B18: =INDEX(Monthly!$C$75:$BJ$75,(B$3-1)*12+1) -> 0 | C18: =INDEX(Monthly!$C$75:$BJ$75,(C$3-1)*12+1) -> 3123134.7 | D18: =INDEX(Monthly!$C$75:$BJ$75,(D$3-1)*12+1) -> 5201477.5 | E18: =INDEX(Monthly!$C$75:$BJ$75,(E$3-1)*12+1) -> 8187249.2 | F18: =INDEX(Monthly!$C$75:$BJ$75,(F$3-1)*12+1) -> 12402695
A19: Closing cash | B19: =INDEX(Monthly!$C$76:$BJ$76,B$3*12) -> 3123134.7 | C19: =INDEX(Monthly!$C$76:$BJ$76,C$3*12) -> 5201477.5 | D19: =INDEX(Monthly!$C$76:$BJ$76,D$3*12) -> 8187249.2 | E19: =INDEX(Monthly!$C$76:$BJ$76,E$3*12) -> 12402695 | F19: =INDEX(Monthly!$C$76:$BJ$76,F$3*12) -> 18308468

Sheet Balance Sheet
A1: Balance sheet at year end | H1: =HYPERLINK("#'Cover'!A1","◂ Contents") -> ◂ Contents
A2: Rolled up from the period detail (SUMIF on the year row; balances at year end).
A3: Year # | B3: 1 | C3: 2 | D3: 3 | E3: 4 | F3: 5
B4: Year 1 | C4: Year 2 | D4: Year 3 | E4: Year 4 | F4: Year 5
A5: Cash | B5: =INDEX(Monthly!$C$76:$BJ$76,B$3*12) -> 3123134.7 | C5: =INDEX(Monthly!$C$76:$BJ$76,C$3*12) -> 5201477.5 | D5: =INDEX(Monthly!$C$76:$BJ$76,D$3*12) -> 8187249.2 | E5: =INDEX(Monthly!$C$76:$BJ$76,E$3*12) -> 12402695 | F5: =INDEX(Monthly!$C$76:$BJ$76,F$3*12) -> 18308468
A6: Accounts receivable | B6: =INDEX(Monthly!$C$60:$BJ$60,B$3*12) -> 156832.04 | C6: =INDEX(Monthly!$C$60:$BJ$60,C$3*12) -> 198958.68 | D6: =INDEX(Monthly!$C$60:$BJ$60,D$3*12) -> 253031.66 | E6: =INDEX(Monthly!$C$60:$BJ$60,E$3*12) -> 322519.09 | F6: =INDEX(Monthly!$C$60:$BJ$60,F$3*12) -> 411930.95
A7: Inventory | B7: =INDEX(Monthly!$C$61:$BJ$61,B$3*12) -> 0 | C7: =INDEX(Monthly!$C$61:$BJ$61,C$3*12) -> 0 | D7: =INDEX(Monthly!$C$61:$BJ$61,D$3*12) -> 0 | E7: =INDEX(Monthly!$C$61:$BJ$61,E$3*12) -> 0 | F7: =INDEX(Monthly!$C$61:$BJ$61,F$3*12) -> 0
A8: Net fixed assets | B8: =INDEX(Monthly!$C$51:$BJ$51,B$3*12) -> 100000 | C8: =INDEX(Monthly!$C$51:$BJ$51,C$3*12) -> 50000 | D8: =INDEX(Monthly!$C$51:$BJ$51,D$3*12) -> 0 | E8: =INDEX(Monthly!$C$51:$BJ$51,E$3*12) -> 0 | F8: =INDEX(Monthly!$C$51:$BJ$51,F$3*12) -> 0
A9: Total assets | B9: =INDEX(Monthly!$C$94:$BJ$94,B$3*12) -> 3379966.7 | C9: =INDEX(Monthly!$C$94:$BJ$94,C$3*12) -> 5450436.1 | D9: =INDEX(Monthly!$C$94:$BJ$94,D$3*12) -> 8440280.9 | E9: =INDEX(Monthly!$C$94:$BJ$94,E$3*12) -> 12725214 | F9: =INDEX(Monthly!$C$94:$BJ$94,F$3*12) -> 18720399
A10: Accounts payable | B10: =INDEX(Monthly!$C$62:$BJ$62,B$3*12) -> 101269.02 | C10: =INDEX(Monthly!$C$62:$BJ$62,C$3*12) -> 128077.78 | D10: =INDEX(Monthly!$C$62:$BJ$62,D$3*12) -> 162458.51 | E10: =INDEX(Monthly!$C$62:$BJ$62,E$3*12) -> 206590.9 | F10: =INDEX(Monthly!$C$62:$BJ$62,F$3*12) -> 263306.81
A11: Deferred revenue (annual plans, ~6 months unearned) | B11: =INDEX(Monthly!$C$66:$BJ$66,B$3*12) -> 1138591.8 | C11: =INDEX(Monthly!$C$66:$BJ$66,C$3*12) -> 1444558.2 | D11: =INDEX(Monthly!$C$66:$BJ$66,D$3*12) -> 1837303 | E11: =INDEX(Monthly!$C$66:$BJ$66,E$3*12) -> 2342024.6 | F11: =INDEX(Monthly!$C$66:$BJ$66,F$3*12) -> 2991493.4
A12: Loan | B12: =INDEX(Monthly!$C$57:$BJ$57,B$3*12) -> 0 | C12: =INDEX(Monthly!$C$57:$BJ$57,C$3*12) -> 0 | D12: =INDEX(Monthly!$C$57:$BJ$57,D$3*12) -> 0 | E12: =INDEX(Monthly!$C$57:$BJ$57,E$3*12) -> 0 | F12: =INDEX(Monthly!$C$57:$BJ$57,F$3*12) -> 0
A13: Total liabilities | B13: =INDEX(Monthly!$C$95:$BJ$95,B$3*12) -> 1239860.8 | C13: =INDEX(Monthly!$C$95:$BJ$95,C$3*12) -> 1572636 | D13: =INDEX(Monthly!$C$95:$BJ$95,D$3*12) -> 1999761.5 | E13: =INDEX(Monthly!$C$95:$BJ$95,E$3*12) -> 2548615.5 | F13: =INDEX(Monthly!$C$95:$BJ$95,F$3*12) -> 3254800.2
A14: Paid-in capital | B14: =INDEX(Monthly!$C$92:$BJ$92,B$3*12) -> 1000000 | C14: =INDEX(Monthly!$C$92:$BJ$92,C$3*12) -> 1000000 | D14: =INDEX(Monthly!$C$92:$BJ$92,D$3*12) -> 1000000 | E14: =INDEX(Monthly!$C$92:$BJ$92,E$3*12) -> 1000000 | F14: =INDEX(Monthly!$C$92:$BJ$92,F$3*12) -> 1000000
A15: Retained earnings | B15: =INDEX(Monthly!$C$93:$BJ$93,B$3*12) -> 1140105.9 | C15: =INDEX(Monthly!$C$93:$BJ$93,C$3*12) -> 2877800.1 | D15: =INDEX(Monthly!$C$93:$BJ$93,D$3*12) -> 5440519.4 | E15: =INDEX(Monthly!$C$93:$BJ$93,E$3*12) -> 9176598.6 | F15: =INDEX(Monthly!$C$93:$BJ$93,F$3*12) -> 14465599
A16: Total equity | B16: =INDEX(Monthly!$C$96:$BJ$96,B$3*12) -> 2140105.9 | C16: =INDEX(Monthly!$C$96:$BJ$96,C$3*12) -> 3877800.1 | D16: =INDEX(Monthly!$C$96:$BJ$96,D$3*12) -> 6440519.4 | E16: =INDEX(Monthly!$C$96:$BJ$96,E$3*12) -> 10176599 | F16: =INDEX(Monthly!$C$96:$BJ$96,F$3*12) -> 15465599
A17: Total liabilities & equity | B17: =INDEX(Monthly!$C$97:$BJ$97,B$3*12) -> 3379966.7 | C17: =INDEX(Monthly!$C$97:$BJ$97,C$3*12) -> 5450436.1 | D17: =INDEX(Monthly!$C$97:$BJ$97,D$3*12) -> 8440280.9 | E17: =INDEX(Monthly!$C$97:$BJ$97,E$3*12) -> 12725214 | F17: =INDEX(Monthly!$C$97:$BJ$97,F$3*12) -> 18720399
A18: Check: assets − liabilities − equity (must be 0) | B18: =INDEX(Monthly!$C$98:$BJ$98,B$3*12) -> 0 | C18: =INDEX(Monthly!$C$98:$BJ$98,C$3*12) -> 0 | D18: =INDEX(Monthly!$C$98:$BJ$98,D$3*12) -> 0 | E18: =INDEX(Monthly!$C$98:$BJ$98,E$3*12) -> 0 | F18: =INDEX(Monthly!$C$98:$BJ$98,F$3*12) -> 0

Sheet Monthly
A1: Monthly projection | D1: =HYPERLINK("#'Cover'!A1","◂ Contents") -> ◂ Contents
A2: $ unless stated; costs shown as negatives. Every period uses the same formula.
A3: Month | C3: M1 | D3: M2 | E3: M3 | F3: M4 | G3: M5 | H3: M6 | I3: M7 | J3: M8 | K3: M9 | L3: M10 | M3: M11 | N3: M12 | O3: M13 | P3: M14 | Q3: M15 | R3: M16 | S3: M17 | T3: M18 | U3: M19 | V3: M20 | W3: M21 | X3: M22 | Y3: M23 | Z3: M24 | AA3: M25 | AB3: M26 | AC3: M27 | AD3: M28 | AE3: M29 | AF3: M30 | AG3: M31 | AH3: M32 | AI3: M33 | AJ3: M34 | AK3: M35 | AL3: M36 | AM3: M37 | AN3: M38 | AO3: M39 | AP3: M40 | AQ3: M41 | AR3: M42 | AS3: M43 | AT3: M44 | AU3: M45 | AV3: M46 | AW3: M47 | AX3: M48 | AY3: M49 | AZ3: M50 | BA3: M51 | BB3: M52 | BC3: M53 | BD3: M54 | BE3: M55 | BF3: M56 | BG3: M57 | BH3: M58 | BI3: M59 | BJ3: M60
A4: Period # | C4: 1 | D4: 2 | E4: 3 | F4: 4 | G4: 5 | H4: 6 | I4: 7 | J4: 8 | K4: 9 | L4: 10 | M4: 11 | N4: 12 | O4: 13 | P4: 14 | Q4: 15 | R4: 16 | S4: 17 | T4: 18 | U4: 19 | V4: 20 | W4: 21 | X4: 22 | Y4: 23 | Z4: 24 | AA4: 25 | AB4: 26 | AC4: 27 | AD4: 28 | AE4: 29 | AF4: 30 | AG4: 31 | AH4: 32 | AI4: 33 | AJ4: 34 | AK4: 35 | AL4: 36 | AM4: 37 | AN4: 38 | AO4: 39 | AP4: 40 | AQ4: 41 | AR4: 42 | AS4: 43 | AT4: 44 | AU4: 45 | AV4: 46 | AW4: 47 | AX4: 48 | AY4: 49 | AZ4: 50 | BA4: 51 | BB4: 52 | BC4: 53 | BD4: 54 | BE4: 55 | BF4: 56 | BG4: 57 | BH4: 58 | BI4: 59 | BJ4: 60
A5: Year # | C5: =ROUNDUP(C4*1/12,0) -> 1 | D5: =ROUNDUP(D4*1/12,0) -> 1 | E5: =ROUNDUP(E4*1/12,0) -> 1 | F5: =ROUNDUP(F4*1/12,0) -> 1 | G5: =ROUNDUP(G4*1/12,0) -> 1 | H5: =ROUNDUP(H4*1/12,0) -> 1 | I5: =ROUNDUP(I4*1/12,0) -> 1 | J5: =ROUNDUP(J4*1/12,0) -> 1 | ... BJ5: =ROUNDUP(BJ4*1/12,0) -> 5
A7: Customers
A8: New customers — organic / referral | C8: =Inputs!$E$12*(1+Inputs!$E$13)^(C$5-1)*1 -> 40 | D8: =Inputs!$E$12*(1+Inputs!$E$13)^(D$5-1)*1 -> 40 | E8: =Inputs!$E$12*(1+Inputs!$E$13)^(E$5-1)*1 -> 40 | F8: =Inputs!$E$12*(1+Inputs!$E$13)^(F$5-1)*1 -> 40 | G8: =Inputs!$E$12*(1+Inputs!$E$13)^(G$5-1)*1 -> 40 | H8: =Inputs!$E$12*(1+Inputs!$E$13)^(H$5-1)*1 -> 40 | I8: =Inputs!$E$12*(1+Inputs!$E$13)^(I$5-1)*1 -> 40 | J8: =Inputs!$E$12*(1+Inputs!$E$13)^(J$5-1)*1 -> 40 | ... BJ8: =Inputs!$E$12*(1+Inputs!$E$13)^(BJ$5-1)*1 -> 114.244
A9: New customers — paid marketing | C9: =-C30/MAX(1,Inputs!$E$16) -> 60 | D9: =-D30/MAX(1,Inputs!$E$16) -> 60 | E9: =-E30/MAX(1,Inputs!$E$16) -> 60 | F9: =-F30/MAX(1,Inputs!$E$16) -> 60 | G9: =-G30/MAX(1,Inputs!$E$16) -> 60 | H9: =-H30/MAX(1,Inputs!$E$16) -> 60 | I9: =-I30/MAX(1,Inputs!$E$16) -> 60 | J9: =-J30/MAX(1,Inputs!$E$16) -> 60 | ... BJ9: =-BJ30/MAX(1,Inputs!$E$16) -> 124.416
A10: New customers — total | C10: =C8+C9 -> 100 | D10: =D8+D9 -> 100 | E10: =E8+E9 -> 100 | F10: =F8+F9 -> 100 | G10: =G8+G9 -> 100 | H10: =H8+H9 -> 100 | I10: =I8+I9 -> 100 | J10: =J8+J9 -> 100 | ... BJ10: =BJ8+BJ9 -> 238.66
A11: Customers — opening | C11: =Inputs!$E$7 -> 3000 | D11: =C13 -> 3055 | E11: =D13 -> 3109.175 | F11: =E13 -> 3162.5374 | G11: =F13 -> 3215.0993 | H11: =G13 -> 3266.8728 | I11: =H13 -> 3317.8697 | J11: =I13 -> 3368.1017 | K11: =J13 -> 3417.5802 | ... BJ11: =BI13 -> 8014.9014
A12: Customers lost (churn) | C12: =-C11*Inputs!$E$10 -> -45 | D12: =-D11*Inputs!$E$10 -> -45.825 | E12: =-E11*Inputs!$E$10 -> -46.637625 | F12: =-F11*Inputs!$E$10 -> -47.438061 | G12: =-G11*Inputs!$E$10 -> -48.22649 | H12: =-H11*Inputs!$E$10 -> -49.003092 | I12: =-I11*Inputs!$E$10 -> -49.768046 | J12: =-J11*Inputs!$E$10 -> -50.521525 | ... BJ12: =-BJ11*Inputs!$E$10 -> -120.22352
A13: Customers — closing | C13: =C11+C10+C12 -> 3055 | D13: =D11+D10+D12 -> 3109.175 | E13: =E11+E10+E12 -> 3162.5374 | F13: =F11+F10+F12 -> 3215.0993 | G13: =G11+G10+G12 -> 3266.8728 | H13: =H11+H10+H12 -> 3317.8697 | I13: =I11+I10+I12 -> 3368.1017 | J13: =J11+J10+J12 -> 3417.5802 | ... BJ13: =BJ11+BJ10+BJ12 -> 8133.3379
A14: MRR per new customer | C14: =Inputs!$E$8*(1+Inputs!$E$9)^(C$5-1) -> 250 | D14: =Inputs!$E$8*(1+Inputs!$E$9)^(D$5-1) -> 250 | E14: =Inputs!$E$8*(1+Inputs!$E$9)^(E$5-1) -> 250 | F14: =Inputs!$E$8*(1+Inputs!$E$9)^(F$5-1) -> 250 | G14: =Inputs!$E$8*(1+Inputs!$E$9)^(G$5-1) -> 250 | H14: =Inputs!$E$8*(1+Inputs!$E$9)^(H$5-1) -> 250 | I14: =Inputs!$E$8*(1+Inputs!$E$9)^(I$5-1) -> 250 | J14: =Inputs!$E$8*(1+Inputs!$E$9)^(J$5-1) -> 250 | ... BJ14: =Inputs!$E$8*(1+Inputs!$E$9)^(BJ$5-1) -> 281.3772
A16: MRR waterfall
A17: Opening MRR | C17: =Inputs!$E$7*Inputs!$E$8 -> 750000 | D17: =C21 -> 767500 | E17: =D21 -> 784825 | F17: =E21 -> 801976.75 | G17: =F21 -> 818956.98 | H17: =G21 -> 835767.41 | I17: =H21 -> 852409.74 | J17: =I21 -> 868885.64 | K17: =J21 -> 885196.78 | ... BJ17: =BI21 -> 2450260.3
A18: New MRR | C18: =C10*C14 -> 25000 | D18: =D10*D14 -> 25000 | E18: =E10*E14 -> 25000 | F18: =F10*F14 -> 25000 | G18: =G10*G14 -> 25000 | H18: =H10*H14 -> 25000 | I18: =I10*I14 -> 25000 | J18: =J10*J14 -> 25000 | ... BJ18: =BJ10*BJ14 -> 67153.483
A19: Expansion MRR | C19: =C17*Inputs!$E$11 -> 3750 | D19: =D17*Inputs!$E$11 -> 3837.5 | E19: =E17*Inputs!$E$11 -> 3924.125 | F19: =F17*Inputs!$E$11 -> 4009.8837 | G19: =G17*Inputs!$E$11 -> 4094.7849 | H19: =H17*Inputs!$E$11 -> 4178.8371 | I19: =I17*Inputs!$E$11 -> 4262.0487 | J19: =J17*Inputs!$E$11 -> 4344.4282 | ... BJ19: =BJ17*Inputs!$E$11 -> 12251.301
A20: Churned MRR | C20: =-C17*Inputs!$E$10 -> -11250 | D20: =-D17*Inputs!$E$10 -> -11512.5 | E20: =-E17*Inputs!$E$10 -> -11772.375 | F20: =-F17*Inputs!$E$10 -> -12029.651 | G20: =-G17*Inputs!$E$10 -> -12284.355 | H20: =-H17*Inputs!$E$10 -> -12536.511 | I20: =-I17*Inputs!$E$10 -> -12786.146 | J20: =-J17*Inputs!$E$10 -> -13033.285 | ... BJ20: =-BJ17*Inputs!$E$10 -> -36753.904
A21: Closing MRR | C21: =C17+C18+C19+C20 -> 767500 | D21: =D17+D18+D19+D20 -> 784825 | E21: =E17+E18+E19+E20 -> 801976.75 | F21: =F17+F18+F19+F20 -> 818956.98 | G21: =G17+G18+G19+G20 -> 835767.41 | H21: =H17+H18+H19+H20 -> 852409.74 | I21: =I17+I18+I19+I20 -> 868885.64 | J21: =J17+J18+J19+J20 -> 885196.78 | ... BJ21: =BJ17+BJ18+BJ19+BJ20 -> 2492911.2
A23: Revenue & cost of revenue
A24: Revenue (average MRR × months) | C24: =(C17+C21)/2*1 -> 758750 | D24: =(D17+D21)/2*1 -> 776162.5 | E24: =(E17+E21)/2*1 -> 793400.88 | F24: =(F17+F21)/2*1 -> 810466.87 | G24: =(G17+G21)/2*1 -> 827362.2 | H24: =(H17+H21)/2*1 -> 844088.58 | I24: =(I17+I21)/2*1 -> 860647.69 | J24: =(J17+J21)/2*1 -> 877041.21 | ... BJ24: =(BJ17+BJ21)/2*1 -> 2471585.7
A25: Hosting, payment fees & support | C25: =-(C24*Inputs!$E$18+(C11+C13)/2*Inputs!$E$19*1) -> -81930 | D25: =-(D24*Inputs!$E$18+(D11+D13)/2*Inputs!$E$19*1) -> -83780.425 | E25: =-(E24*Inputs!$E$18+(E11+E13)/2*Inputs!$E$19*1) -> -85611.8 | F25: =-(F24*Inputs!$E$18+(F11+F13)/2*Inputs!$E$19*1) -> -87424.323 | G25: =-(G24*Inputs!$E$18+(G11+G13)/2*Inputs!$E$19*1) -> -89218.192 | H25: =-(H24*Inputs!$E$18+(H11+H13)/2*Inputs!$E$19*1) -> -90993.6 | I25: =-(I24*Inputs!$E$18+(I11+I13)/2*Inputs!$E$19*1) -> -92750.74 | J25: =-(J24*Inputs!$E$18+(J11+J13)/2*Inputs!$E$19*1) -> -94489.803 | ... BJ25: =-(BJ24*Inputs!$E$18+(BJ11+BJ13)/2*Inputs!$E$19*1) -> -263306.81
A26: Gross profit | C26: =C24+C25 -> 676820 | D26: =D24+D25 -> 692382.07 | E26: =E24+E25 -> 707789.08 | F26: =F24+F25 -> 723042.54 | G26: =G24+G25 -> 738144.01 | H26: =H24+H25 -> 753094.98 | I26: =I24+I25 -> 767896.95 | J26: =J24+J25 -> 782551.41 | ... BJ26: =BJ24+BJ25 -> 2208278.9
A28: Operating expenses
A29: Payroll | C29: =Headcount!C19 -> -523000 | D29: =Headcount!D19 -> -523000 | E29: =Headcount!E19 -> -523000 | F29: =Headcount!F19 -> -523000 | G29: =Headcount!G19 -> -523000 | H29: =Headcount!H19 -> -523000 | I29: =Headcount!I19 -> -523000 | J29: =Headcount!J19 -> -523000 | ... BJ29: =Headcount!BJ19 -> -1248197.8
A30: Paid marketing | C30: =-Inputs!$E$14*(1+Inputs!$E$15)^(C$5-1)*1 -> -60000 | D30: =-Inputs!$E$14*(1+Inputs!$E$15)^(D$5-1)*1 -> -60000 | E30: =-Inputs!$E$14*(1+Inputs!$E$15)^(E$5-1)*1 -> -60000 | F30: =-Inputs!$E$14*(1+Inputs!$E$15)^(F$5-1)*1 -> -60000 | G30: =-Inputs!$E$14*(1+Inputs!$E$15)^(G$5-1)*1 -> -60000 | H30: =-Inputs!$E$14*(1+Inputs!$E$15)^(H$5-1)*1 -> -60000 | I30: =-Inputs!$E$14*(1+Inputs!$E$15)^(I$5-1)*1 -> -60000 | J30: =-Inputs!$E$14*(1+Inputs!$E$15)^(J$5-1)*1 -> -60000 | ... BJ30: =-Inputs!$E$14*(1+Inputs!$E$15)^(BJ$5-1)*1 -> -124416
A31: Software & tools | C31: =-Headcount!C12*Inputs!$E$20*1 -> -7200 | D31: =-Headcount!D12*Inputs!$E$20*1 -> -7200 | E31: =-Headcount!E12*Inputs!$E$20*1 -> -7200 | F31: =-Headcount!F12*Inputs!$E$20*1 -> -7200 | G31: =-Headcount!G12*Inputs!$E$20*1 -> -7200 | H31: =-Headcount!H12*Inputs!$E$20*1 -> -7200 | I31: =-Headcount!I12*Inputs!$E$20*1 -> -7200 | J31: =-Headcount!J12*Inputs!$E$20*1 -> -7200 | ... BJ31: =-Headcount!BJ12*Inputs!$E$20*1 -> -14637.786
A32: Office & rent | C32: =-Inputs!$E$21*1 -> -20000 | D32: =-Inputs!$E$21*1 -> -20000 | E32: =-Inputs!$E$21*1 -> -20000 | F32: =-Inputs!$E$21*1 -> -20000 | G32: =-Inputs!$E$21*1 -> -20000 | H32: =-Inputs!$E$21*1 -> -20000 | I32: =-Inputs!$E$21*1 -> -20000 | J32: =-Inputs!$E$21*1 -> -20000 | ... BJ32: =-Inputs!$E$21*1 -> -20000
A33: Other G&A | C33: =-Inputs!$E$22*1 -> -25000 | D33: =-Inputs!$E$22*1 -> -25000 | E33: =-Inputs!$E$22*1 -> -25000 | F33: =-Inputs!$E$22*1 -> -25000 | G33: =-Inputs!$E$22*1 -> -25000 | H33: =-Inputs!$E$22*1 -> -25000 | I33: =-Inputs!$E$22*1 -> -25000 | J33: =-Inputs!$E$22*1 -> -25000 | ... BJ33: =-Inputs!$E$22*1 -> -25000
A34: Total operating expenses | C34: =C29+C30+C31+C32+C33 -> -635200 | D34: =D29+D30+D31+D32+D33 -> -635200 | E34: =E29+E30+E31+E32+E33 -> -635200 | F34: =F29+F30+F31+F32+F33 -> -635200 | G34: =G29+G30+G31+G32+G33 -> -635200 | H34: =H29+H30+H31+H32+H33 -> -635200 | I34: =I29+I30+I31+I32+I33 -> -635200 | J34: =J29+J30+J31+J32+J33 -> -635200 | ... BJ34: =BJ29+BJ30+BJ31+BJ32+BJ33 -> -1432251.6
A35: EBITDA | C35: =C26+C34 -> 41620 | D35: =D26+D34 -> 57182.075 | E35: =E26+E34 -> 72589.075 | F35: =F26+F34 -> 87842.543 | G35: =G26+G34 -> 102944.01 | H35: =H26+H34 -> 117894.98 | I35: =I26+I34 -> 132696.95 | J35: =J26+J34 -> 147351.41 | ... BJ35: =BJ26+BJ34 -> 776027.29
A37: Profit after depreciation, interest, tax
A38: EBIT | C38: =C35+C49 -> 37453.333 | D38: =D35+D49 -> 53015.408 | E38: =E35+E49 -> 68422.408 | F38: =F35+F49 -> 83675.876 | G38: =G35+G49 -> 98777.339 | H38: =H35+H49 -> 113728.31 | I38: =I35+I49 -> 128530.28 | J38: =J35+J49 -> 143184.74 | ... BJ38: =BJ35+BJ49 -> 776027.29
A39: Interest on loan (average balance after drawdown) | C39: =-(C54+C55+C57)/2*Inputs!$E$48/12 -> 0 | D39: =-(D54+D55+D57)/2*Inputs!$E$48/12 -> 0 | E39: =-(E54+E55+E57)/2*Inputs!$E$48/12 -> 0 | F39: =-(F54+F55+F57)/2*Inputs!$E$48/12 -> 0 | G39: =-(G54+G55+G57)/2*Inputs!$E$48/12 -> 0 | H39: =-(H54+H55+H57)/2*Inputs!$E$48/12 -> 0 | I39: =-(I54+I55+I57)/2*Inputs!$E$48/12 -> 0 | J39: =-(J54+J55+J57)/2*Inputs!$E$48/12 -> 0 | ... BJ39: =-(BJ54+BJ55+BJ57)/2*Inputs!$E$48/12 -> 0
A40: Pre-tax income | C40: =C38+C39 -> 37453.333 | D40: =D38+D39 -> 53015.408 | E40: =E38+E39 -> 68422.408 | F40: =F38+F39 -> 83675.876 | G40: =G38+G39 -> 98777.339 | H40: =H38+H39 -> 113728.31 | I40: =I38+I39 -> 128530.28 | J40: =J38+J39 -> 143184.74 | ... BJ40: =BJ38+BJ39 -> 776027.29
A41: Helper: cumulative pre-tax income | C41: =C40 -> 37453.333 | D41: =C41+D40 -> 90468.742 | E41: =D41+E40 -> 158891.15 | F41: =E41+F40 -> 242567.03 | G41: =F41+G40 -> 341344.37 | H41: =G41+H40 -> 455072.67 | I41: =H41+I40 -> 583602.96 | J41: =I41+J40 -> 726787.7 | K41: =J41+K40 -> 884480.86 | ... BJ41: =BI41+BJ40 -> 18310885
A42: Helper: cumulative taxable income (losses carried forward) | C42: =MAX(0,C41) -> 37453.333 | D42: =MAX(C42,D41) -> 90468.742 | E42: =MAX(D42,E41) -> 158891.15 | F42: =MAX(E42,F41) -> 242567.03 | G42: =MAX(F42,G41) -> 341344.37 | H42: =MAX(G42,H41) -> 455072.67 | I42: =MAX(H42,I41) -> 583602.96 | J42: =MAX(I42,J41) -> 726787.7 | K42: =MAX(J42,K41) -> 884480.86 | ... BJ42: =MAX(BI42,BJ41) -> 18310885
A43: Income tax | C43: =-C42*Inputs!$E$58 -> -7865.2 | D43: =-(D42-C42)*Inputs!$E$58 -> -11133.236 | E43: =-(E42-D42)*Inputs!$E$58 -> -14368.706 | F43: =-(F42-E42)*Inputs!$E$58 -> -17571.934 | G43: =-(G42-F42)*Inputs!$E$58 -> -20743.241 | H43: =-(H42-G42)*Inputs!$E$58 -> -23882.945 | I43: =-(I42-H42)*Inputs!$E$58 -> -26991.359 | J43: =-(J42-I42)*Inputs!$E$58 -> -30068.796 | K43: =-(K42-J42)*Inputs!$E$58 -> -33115.563 | ... BJ43: =-(BJ42-BI42)*Inputs!$E$58 -> -162965.73
A44: Net income | C44: =C40+C43 -> 29588.133 | D44: =D40+D43 -> 41882.173 | E44: =E40+E43 -> 54053.703 | F44: =F40+F43 -> 66103.942 | G44: =G40+G43 -> 78034.098 | H44: =H40+H43 -> 89845.364 | I44: =I40+I43 -> 101538.92 | J44: =J40+J43 -> 113115.95 | ... BJ44: =BJ40+BJ43 -> 613061.56
A46: Fixed assets & capital spending
A47: Capital spending | C47: =IF(C$4=1,Inputs!$E$23,0) -> 150000 | D47: =IF(D$4=1,Inputs!$E$23,0) -> 0 | E47: =IF(E$4=1,Inputs!$E$23,0) -> 0 | F47: =IF(F$4=1,Inputs!$E$23,0) -> 0 | G47: =IF(G$4=1,Inputs!$E$23,0) -> 0 | H47: =IF(H$4=1,Inputs!$E$23,0) -> 0 | I47: =IF(I$4=1,Inputs!$E$23,0) -> 0 | J47: =IF(J$4=1,Inputs!$E$23,0) -> 0 | ... BJ47: =IF(BJ$4=1,Inputs!$E$23,0) -> 0
A48: Fixed assets at cost | C48: =C47 -> 150000 | D48: =C48+D47 -> 150000 | E48: =D48+E47 -> 150000 | F48: =E48+F47 -> 150000 | G48: =F48+G47 -> 150000 | H48: =G48+H47 -> 150000 | I48: =H48+I47 -> 150000 | J48: =I48+J47 -> 150000 | K48: =J48+K47 -> 150000 | ... BJ48: =BI48+BJ47 -> 150000
A49: Depreciation | C49: =-MIN(C48/MAX(1,Inputs!$E$57*12),C47) -> -4166.6667 | D49: =-MIN(D48/MAX(1,Inputs!$E$57*12),C51+D47) -> -4166.6667 | E49: =-MIN(E48/MAX(1,Inputs!$E$57*12),D51+E47) -> -4166.6667 | F49: =-MIN(F48/MAX(1,Inputs!$E$57*12),E51+F47) -> -4166.6667 | G49: =-MIN(G48/MAX(1,Inputs!$E$57*12),F51+G47) -> -4166.6667 | H49: =-MIN(H48/MAX(1,Inputs!$E$57*12),G51+H47) -> -4166.6667 | I49: =-MIN(I48/MAX(1,Inputs!$E$57*12),H51+I47) -> -4166.6667 | J49: =-MIN(J48/MAX(1,Inputs!$E$57*12),I51+J47) -> -4166.6667 | K49: =-MIN(K48/MAX(1,Inputs!$E$57*12),J51+K47) -> -4166.6667 | ... BJ49: =-MIN(BJ48/MAX(1,Inputs!$E$57*12),BI51+BJ47) -> 0
A50: Accumulated depreciation | C50: =C49 -> -4166.6667 | D50: =C50+D49 -> -8333.3333 | E50: =D50+E49 -> -12500 | F50: =E50+F49 -> -16666.667 | G50: =F50+G49 -> -20833.333 | H50: =G50+H49 -> -25000 | I50: =H50+I49 -> -29166.667 | J50: =I50+J49 -> -33333.333 | K50: =J50+K49 -> -37500 | ... BJ50: =BI50+BJ49 -> -150000
A51: Net fixed assets | C51: =C48+C50 -> 145833.33 | D51: =D48+D50 -> 141666.67 | E51: =E48+E50 -> 137500 | F51: =F48+F50 -> 133333.33 | G51: =G48+G50 -> 129166.67 | H51: =H48+H50 -> 125000 | I51: =I48+I50 -> 120833.33 | J51: =J48+J50 -> 116666.67 | ... BJ51: =BJ48+BJ50 -> 0
A53: Debt
A54: Loan — opening balance | C54: =0 -> 0 | D54: =C57 -> 0 | E54: =D57 -> 0 | F54: =E57 -> 0 | G54: =F57 -> 0 | H54: =G57 -> 0 | I54: =H57 -> 0 | J54: =I57 -> 0 | K54: =J57 -> 0 | ... BJ54: =BI57 -> 0
A55: Loan drawdown | C55: =IF(C$4=1,Inputs!$E$47,0) -> 0 | D55: =IF(D$4=1,Inputs!$E$47,0) -> 0 | E55: =IF(E$4=1,Inputs!$E$47,0) -> 0 | F55: =IF(F$4=1,Inputs!$E$47,0) -> 0 | G55: =IF(G$4=1,Inputs!$E$47,0) -> 0 | H55: =IF(H$4=1,Inputs!$E$47,0) -> 0 | I55: =IF(I$4=1,Inputs!$E$47,0) -> 0 | J55: =IF(J$4=1,Inputs!$E$47,0) -> 0 | ... BJ55: =IF(BJ$4=1,Inputs!$E$47,0) -> 0
A56: Loan repayment | C56: =-MIN(C54,Inputs!$E$47/MAX(1,Inputs!$E$49*12)) -> 0 | D56: =-MIN(D54,Inputs!$E$47/MAX(1,Inputs!$E$49*12)) -> 0 | E56: =-MIN(E54,Inputs!$E$47/MAX(1,Inputs!$E$49*12)) -> 0 | F56: =-MIN(F54,Inputs!$E$47/MAX(1,Inputs!$E$49*12)) -> 0 | G56: =-MIN(G54,Inputs!$E$47/MAX(1,Inputs!$E$49*12)) -> 0 | H56: =-MIN(H54,Inputs!$E$47/MAX(1,Inputs!$E$49*12)) -> 0 | I56: =-MIN(I54,Inputs!$E$47/MAX(1,Inputs!$E$49*12)) -> 0 | J56: =-MIN(J54,Inputs!$E$47/MAX(1,Inputs!$E$49*12)) -> 0 | ... BJ56: =-MIN(BJ54,Inputs!$E$47/MAX(1,Inputs!$E$49*12)) -> 0
A57: Loan — closing balance | C57: =C54+C55+C56 -> 0 | D57: =D54+D55+D56 -> 0 | E57: =E54+E55+E56 -> 0 | F57: =F54+F55+F56 -> 0 | G57: =G54+G55+G56 -> 0 | H57: =H54+H55+H56 -> 0 | I57: =I54+I55+I56 -> 0 | J57: =J54+J55+J56 -> 0 | ... BJ57: =BJ54+BJ55+BJ56 -> 0
A59: Working capital
A60: Accounts receivable | C60: =C24*Inputs!$E$52/30 -> 126458.33 | D60: =D24*Inputs!$E$52/30 -> 129360.42 | E60: =E24*Inputs!$E$52/30 -> 132233.48 | F60: =F24*Inputs!$E$52/30 -> 135077.81 | G60: =G24*Inputs!$E$52/30 -> 137893.7 | H60: =H24*Inputs!$E$52/30 -> 140681.43 | I60: =I24*Inputs!$E$52/30 -> 143441.28 | J60: =J24*Inputs!$E$52/30 -> 146173.54 | ... BJ60: =BJ24*Inputs!$E$52/30 -> 411930.95
A61: Inventory | C61: =-C25*Inputs!$E$53/30 -> 0 | D61: =-D25*Inputs!$E$53/30 -> 0 | E61: =-E25*Inputs!$E$53/30 -> 0 | F61: =-F25*Inputs!$E$53/30 -> 0 | G61: =-G25*Inputs!$E$53/30 -> 0 | H61: =-H25*Inputs!$E$53/30 -> 0 | I61: =-I25*Inputs!$E$53/30 -> 0 | J61: =-J25*Inputs!$E$53/30 -> 0 | ... BJ61: =-BJ25*Inputs!$E$53/30 -> 0
A62: Accounts payable | C62: =-C25*Inputs!$E$54/30 -> 81930 | D62: =-D25*Inputs!$E$54/30 -> 83780.425 | E62: =-E25*Inputs!$E$54/30 -> 85611.8 | F62: =-F25*Inputs!$E$54/30 -> 87424.323 | G62: =-G25*Inputs!$E$54/30 -> 89218.192 | H62: =-H25*Inputs!$E$54/30 -> 90993.6 | I62: =-I25*Inputs!$E$54/30 -> 92750.74 | J62: =-J25*Inputs!$E$54/30 -> 94489.803 | ... BJ62: =-BJ25*Inputs!$E$54/30 -> 263306.81
A63: (Increase) / decrease in receivables | C63: =-C60 -> -126458.33 | D63: =C60-D60 -> -2902.0833 | E63: =D60-E60 -> -2873.0625 | F63: =E60-F60 -> -2844.3319 | G63: =F60-G60 -> -2815.8886 | H63: =G60-H60 -> -2787.7297 | I63: =H60-I60 -> -2759.8524 | J63: =I60-J60 -> -2732.2539 | K63: =J60-K60 -> -2704.9313 | ... BJ63: =BI60-BJ60 -> -7144.3815
A64: (Increase) / decrease in inventory | C64: =-C61 -> 0 | D64: =C61-D61 -> 0 | E64: =D61-E61 -> 0 | F64: =E61-F61 -> 0 | G64: =F61-G61 -> 0 | H64: =G61-H61 -> 0 | I64: =H61-I61 -> 0 | J64: =I61-J61 -> 0 | K64: =J61-K61 -> 0 | ... BJ64: =BI61-BJ61 -> 0
A65: Increase / (decrease) in payables | C65: =C62 -> 81930 | D65: =D62-C62 -> 1850.425 | E65: =E62-D62 -> 1831.3749 | F65: =F62-E62 -> 1812.5234 | G65: =G62-F62 -> 1793.8686 | H65: =H62-G62 -> 1775.4082 | I65: =I62-H62 -> 1757.1403 | J65: =J62-I62 -> 1739.0627 | K65: =K62-J62 -> 1721.1736 | ... BJ65: =BJ62-BI62 -> 4525.3054
A66: Deferred revenue (annual plans, ~6 months unearned) | C66: =C21*Inputs!$E$17*6 -> 921000 | D66: =D21*Inputs!$E$17*6 -> 941790 | E66: =E21*Inputs!$E$17*6 -> 962372.1 | F66: =F21*Inputs!$E$17*6 -> 982748.38 | G66: =G21*Inputs!$E$17*6 -> 1002920.9 | H66: =H21*Inputs!$E$17*6 -> 1022891.7 | I66: =I21*Inputs!$E$17*6 -> 1042662.8 | J66: =J21*Inputs!$E$17*6 -> 1062236.1 | ... BJ66: =BJ21*Inputs!$E$17*6 -> 2991493.4
A67: Increase / (decrease) in deferred revenue (annual plans, ~6 months unearned) | C67: =C66 -> 921000 | D67: =D66-C66 -> 20790 | E67: =E66-D66 -> 20582.1 | F67: =F66-E66 -> 20376.279 | G67: =G66-F66 -> 20172.516 | H67: =H66-G66 -> 19970.791 | I67: =I66-H66 -> 19771.083 | J67: =J66-I66 -> 19573.372 | K67: =K66-J66 -> 19377.639 | ... BJ67: =BJ66-BI66 -> 51181.056
A69: Cash flow
A70: Operating cash flow | C70: =C44-C49+C63+C64+C65+C67 -> 910226.47 | D70: =D44-D49+D63+D64+D65+D67 -> 65787.181 | E70: =E44-E49+E63+E64+E65+E67 -> 77760.782 | F70: =F44-F49+F63+F64+F65+F67 -> 89615.079 | G70: =G44-G49+G63+G64+G65+G67 -> 101351.26 | H70: =H44-H49+H63+H64+H65+H67 -> 112970.5 | I70: =I44-I49+I63+I64+I65+I67 -> 124473.96 | J70: =J44-J49+J63+J64+J65+J67 -> 135862.79 | ... BJ70: =BJ44-BJ49+BJ63+BJ64+BJ65+BJ67 -> 661623.54
A71: Investing cash flow (capex) | C71: =-C47 -> -150000 | D71: =-D47 -> 0 | E71: =-E47 -> 0 | F71: =-F47 -> 0 | G71: =-G47 -> 0 | H71: =-H47 -> 0 | I71: =-I47 -> 0 | J71: =-J47 -> 0 | ... BJ71: =-BJ47 -> 0
A72: Equity raised | C72: =IF(C$4=1,Inputs!$E$46,0) -> 1000000 | D72: =IF(D$4=1,Inputs!$E$46,0) -> 0 | E72: =IF(E$4=1,Inputs!$E$46,0) -> 0 | F72: =IF(F$4=1,Inputs!$E$46,0) -> 0 | G72: =IF(G$4=1,Inputs!$E$46,0) -> 0 | H72: =IF(H$4=1,Inputs!$E$46,0) -> 0 | I72: =IF(I$4=1,Inputs!$E$46,0) -> 0 | J72: =IF(J$4=1,Inputs!$E$46,0) -> 0 | ... BJ72: =IF(BJ$4=1,Inputs!$E$46,0) -> 0
A73: Financing cash flow | C73: =C72+C55+C56 -> 1000000 | D73: =D72+D55+D56 -> 0 | E73: =E72+E55+E56 -> 0 | F73: =F72+F55+F56 -> 0 | G73: =G72+G55+G56 -> 0 | H73: =H72+H55+H56 -> 0 | I73: =I72+I55+I56 -> 0 | J73: =J72+J55+J56 -> 0 | ... BJ73: =BJ72+BJ55+BJ56 -> 0
A74: Net cash flow | C74: =C70+C71+C73 -> 1760226.5 | D74: =D70+D71+D73 -> 65787.181 | E74: =E70+E71+E73 -> 77760.782 | F74: =F70+F71+F73 -> 89615.079 | G74: =G70+G71+G73 -> 101351.26 | H74: =H70+H71+H73 -> 112970.5 | I74: =I70+I71+I73 -> 124473.96 | J74: =J70+J71+J73 -> 135862.79 | ... BJ74: =BJ70+BJ71+BJ73 -> 661623.54
A75: Opening cash | C75: =0 -> 0 | D75: =C76 -> 1760226.5 | E75: =D76 -> 1826013.6 | F75: =E76 -> 1903774.4 | G75: =F76 -> 1993389.5 | H75: =G76 -> 2094740.8 | I75: =H76 -> 2207711.3 | J75: =I76 -> 2332185.2 | K75: =J76 -> 2468048 | ... BJ75: =BI76 -> 17646845
A76: Closing cash | C76: =C75+C74 -> 1760226.5 | D76: =D75+D74 -> 1826013.6 | E76: =E75+E74 -> 1903774.4 | F76: =F75+F74 -> 1993389.5 | G76: =G75+G74 -> 2094740.8 | H76: =H75+H74 -> 2207711.3 | I76: =I75+I74 -> 2332185.2 | J76: =J75+J74 -> 2468048 | ... BJ76: =BJ75+BJ74 -> 18308468
A77: Helper: EBITDA positive (1/0) | C77: =IF(C35>0,1,0) -> 1 | D77: =IF(D35>0,1,0) -> 1 | E77: =IF(E35>0,1,0) -> 1 | F77: =IF(F35>0,1,0) -> 1 | G77: =IF(G35>0,1,0) -> 1 | H77: =IF(H35>0,1,0) -> 1 | I77: =IF(I35>0,1,0) -> 1 | J77: =IF(J35>0,1,0) -> 1 | ... BJ77: =IF(BJ35>0,1,0) -> 1
A79: SaaS metric helpers
A80: Net burn per month (operating + investing; negative = cash generative) | C80: =-(C70+C71)/1 -> -760226.47 | D80: =-(D70+D71)/1 -> -65787.181 | E80: =-(E70+E71)/1 -> -77760.782 | F80: =-(F70+F71)/1 -> -89615.079 | G80: =-(G70+G71)/1 -> -101351.26 | H80: =-(H70+H71)/1 -> -112970.5 | I80: =-(I70+I71)/1 -> -124473.96 | J80: =-(J70+J71)/1 -> -135862.79 | ... BJ80: =-(BJ70+BJ71)/1 -> -661623.54
A81: Customer churn per month | C81: =Inputs!$E$10 -> 0.015 | D81: =Inputs!$E$10 -> 0.015 | E81: =Inputs!$E$10 -> 0.015 | F81: =Inputs!$E$10 -> 0.015 | G81: =Inputs!$E$10 -> 0.015 | H81: =Inputs!$E$10 -> 0.015 | I81: =Inputs!$E$10 -> 0.015 | J81: =Inputs!$E$10 -> 0.015 | ... BJ81: =Inputs!$E$10 -> 0.015
A83: Goal modules
A84: Helper: net income positive (1/0) | C84: =IF(C44>0,1,0) -> 1 | D84: =IF(D44>0,1,0) -> 1 | E84: =IF(E44>0,1,0) -> 1 | F84: =IF(F44>0,1,0) -> 1 | G84: =IF(G44>0,1,0) -> 1 | H84: =IF(H44>0,1,0) -> 1 | I84: =IF(I44>0,1,0) -> 1 | J84: =IF(J44>0,1,0) -> 1 | ... BJ84: =IF(BJ44>0,1,0) -> 1
A85: Cash flow before financing (operating + investing) | C85: =C70+C71 -> 760226.47 | D85: =D70+D71 -> 65787.181 | E85: =E70+E71 -> 77760.782 | F85: =F70+F71 -> 89615.079 | G85: =G70+G71 -> 101351.26 | H85: =H70+H71 -> 112970.5 | I85: =I70+I71 -> 124473.96 | J85: =J70+J71 -> 135862.79 | ... BJ85: =BJ70+BJ71 -> 661623.54
A86: Cumulative cash flow before financing | C86: =C85 -> 760226.47 | D86: =C86+D85 -> 826013.65 | E86: =D86+E85 -> 903774.43 | F86: =E86+F85 -> 993389.51 | G86: =F86+G85 -> 1094740.8 | H86: =G86+H85 -> 1207711.3 | I86: =H86+I85 -> 1332185.2 | J86: =I86+J85 -> 1468048 | K86: =J86+K85 -> 1615186.2 | ... BJ86: =BI86+BJ85 -> 17308468
A87: Helper: lowest cumulative cash flow so far | C87: =C86 -> 760226.47 | D87: =MIN(C87,D86) -> 760226.47 | E87: =MIN(D87,E86) -> 760226.47 | F87: =MIN(E87,F86) -> 760226.47 | G87: =MIN(F87,G86) -> 760226.47 | H87: =MIN(G87,H86) -> 760226.47 | I87: =MIN(H87,I86) -> 760226.47 | J87: =MIN(I87,J86) -> 760226.47 | K87: =MIN(J87,K86) -> 760226.47 | ... BJ87: =MIN(BI87,BJ86) -> 760226.47
A88: Helper: investment paid back (1/0) | C88: =IF(AND(C86>=0,C87<0),1,0) -> 0 | D88: =IF(AND(D86>=0,D87<0),1,0) -> 0 | E88: =IF(AND(E86>=0,E87<0),1,0) -> 0 | F88: =IF(AND(F86>=0,F87<0),1,0) -> 0 | G88: =IF(AND(G86>=0,G87<0),1,0) -> 0 | H88: =IF(AND(H86>=0,H87<0),1,0) -> 0 | I88: =IF(AND(I86>=0,I87<0),1,0) -> 0 | J88: =IF(AND(J86>=0,J87<0),1,0) -> 0 | ... BJ88: =IF(AND(BJ86>=0,BJ87<0),1,0) -> 0
A89: Unlevered free cash flow (operating + after-tax interest − capex) | C89: =C70-C39*(1-Inputs!$E$58)+C71 -> 760226.47 | D89: =D70-D39*(1-Inputs!$E$58)+D71 -> 65787.181 | E89: =E70-E39*(1-Inputs!$E$58)+E71 -> 77760.782 | F89: =F70-F39*(1-Inputs!$E$58)+F71 -> 89615.079 | G89: =G70-G39*(1-Inputs!$E$58)+G71 -> 101351.26 | H89: =H70-H39*(1-Inputs!$E$58)+H71 -> 112970.5 | I89: =I70-I39*(1-Inputs!$E$58)+I71 -> 124473.96 | J89: =J70-J39*(1-Inputs!$E$58)+J71 -> 135862.79 | ... BJ89: =BJ70-BJ39*(1-Inputs!$E$58)+BJ71 -> 661623.54
A91: Balance sheet
A92: Paid-in capital | C92: =C72 -> 1000000 | D92: =C92+D72 -> 1000000 | E92: =D92+E72 -> 1000000 | F92: =E92+F72 -> 1000000 | G92: =F92+G72 -> 1000000 | H92: =G92+H72 -> 1000000 | I92: =H92+I72 -> 1000000 | J92: =I92+J72 -> 1000000 | K92: =J92+K72 -> 1000000 | ... BJ92: =BI92+BJ72 -> 1000000
A93: Retained earnings | C93: =C44 -> 29588.133 | D93: =C93+D44 -> 71470.306 | E93: =D93+E44 -> 125524.01 | F93: =E93+F44 -> 191627.95 | G93: =F93+G44 -> 269662.05 | H93: =G93+H44 -> 359507.41 | I93: =H93+I44 -> 461046.34 | J93: =I93+J44 -> 574162.28 | K93: =J93+K44 -> 698739.88 | ... BJ93: =BI93+BJ44 -> 14465599
A94: Total assets | C94: =C76+C60+C61+C51 -> 2032518.1 | D94: =D76+D60+D61+D51 -> 2097040.7 | E94: =E76+E60+E61+E51 -> 2173507.9 | F94: =F76+F60+F61+F51 -> 2261800.7 | G94: =G76+G60+G61+G51 -> 2361801.1 | H94: =H76+H60+H61+H51 -> 2473392.7 | I94: =I76+I60+I61+I51 -> 2596459.8 | J94: =J76+J60+J61+J51 -> 2730888.2 | ... BJ94: =BJ76+BJ60+BJ61+BJ51 -> 18720399
A95: Total liabilities | C95: =C62+C57+C66 -> 1002930 | D95: =D62+D57+D66 -> 1025570.4 | E95: =E62+E57+E66 -> 1047983.9 | F95: =F62+F57+F66 -> 1070172.7 | G95: =G62+G57+G66 -> 1092139.1 | H95: =H62+H57+H66 -> 1113885.3 | I95: =I62+I57+I66 -> 1135413.5 | J95: =J62+J57+J66 -> 1156725.9 | ... BJ95: =BJ62+BJ57+BJ66 -> 3254800.2
A96: Total equity | C96: =C92+C93 -> 1029588.1 | D96: =D92+D93 -> 1071470.3 | E96: =E92+E93 -> 1125524 | F96: =F92+F93 -> 1191628 | G96: =G92+G93 -> 1269662 | H96: =H92+H93 -> 1359507.4 | I96: =I92+I93 -> 1461046.3 | J96: =J92+J93 -> 1574162.3 | ... BJ96: =BJ92+BJ93 -> 15465599
A97: Total liabilities & equity | C97: =C95+C96 -> 2032518.1 | D97: =D95+D96 -> 2097040.7 | E97: =E95+E96 -> 2173507.9 | F97: =F95+F96 -> 2261800.7 | G97: =G95+G96 -> 2361801.1 | H97: =H95+H96 -> 2473392.7 | I97: =I95+I96 -> 2596459.8 | J97: =J95+J96 -> 2730888.2 | ... BJ97: =BJ95+BJ96 -> 18720399
A98: Check: assets − liabilities − equity | C98: =C94-C97 -> 0 | D98: =D94-D97 -> 0 | E98: =E94-E97 -> 0 | F98: =F94-F97 -> 0 | G98: =G94-G97 -> 0 | H98: =H94-H97 -> 0 | I98: =I94-I97 -> 0 | J98: =J94-J97 -> 0 | ... BJ98: =BJ94-BJ97 -> 0

Sheet Headcount
A1: Headcount & payroll | D1: =HYPERLINK("#'Cover'!A1","◂ Contents") -> ◂ Contents
A2: $ unless stated; costs shown as negatives. Every period uses the same formula.
A3: Month | C3: M1 | D3: M2 | E3: M3 | F3: M4 | G3: M5 | H3: M6 | I3: M7 | J3: M8 | K3: M9 | L3: M10 | M3: M11 | N3: M12 | O3: M13 | P3: M14 | Q3: M15 | R3: M16 | S3: M17 | T3: M18 | U3: M19 | V3: M20 | W3: M21 | X3: M22 | Y3: M23 | Z3: M24 | AA3: M25 | AB3: M26 | AC3: M27 | AD3: M28 | AE3: M29 | AF3: M30 | AG3: M31 | AH3: M32 | AI3: M33 | AJ3: M34 | AK3: M35 | AL3: M36 | AM3: M37 | AN3: M38 | AO3: M39 | AP3: M40 | AQ3: M41 | AR3: M42 | AS3: M43 | AT3: M44 | AU3: M45 | AV3: M46 | AW3: M47 | AX3: M48 | AY3: M49 | AZ3: M50 | BA3: M51 | BB3: M52 | BC3: M53 | BD3: M54 | BE3: M55 | BF3: M56 | BG3: M57 | BH3: M58 | BI3: M59 | BJ3: M60
A4: Period # | C4: 1 | D4: 2 | E4: 3 | F4: 4 | G4: 5 | H4: 6 | I4: 7 | J4: 8 | K4: 9 | L4: 10 | M4: 11 | N4: 12 | O4: 13 | P4: 14 | Q4: 15 | R4: 16 | S4: 17 | T4: 18 | U4: 19 | V4: 20 | W4: 21 | X4: 22 | Y4: 23 | Z4: 24 | AA4: 25 | AB4: 26 | AC4: 27 | AD4: 28 | AE4: 29 | AF4: 30 | AG4: 31 | AH4: 32 | AI4: 33 | AJ4: 34 | AK4: 35 | AL4: 36 | AM4: 37 | AN4: 38 | AO4: 39 | AP4: 40 | AQ4: 41 | AR4: 42 | AS4: 43 | AT4: 44 | AU4: 45 | AV4: 46 | AW4: 47 | AX4: 48 | AY4: 49 | AZ4: 50 | BA4: 51 | BB4: 52 | BC4: 53 | BD4: 54 | BE4: 55 | BF4: 56 | BG4: 57 | BH4: 58 | BI4: 59 | BJ4: 60
A5: Year # | C5: =ROUNDUP(C4*1/12,0) -> 1 | D5: =ROUNDUP(D4*1/12,0) -> 1 | E5: =ROUNDUP(E4*1/12,0) -> 1 | F5: =ROUNDUP(F4*1/12,0) -> 1 | G5: =ROUNDUP(G4*1/12,0) -> 1 | H5: =ROUNDUP(H4*1/12,0) -> 1 | I5: =ROUNDUP(I4*1/12,0) -> 1 | J5: =ROUNDUP(J4*1/12,0) -> 1 | ... BJ5: =ROUNDUP(BJ4*1/12,0) -> 5
A7: Headcount (FTE)
A8: Engineering & product — FTE | C8: =Inputs!$E$26*(1+Inputs!$E$28)^(C$5-1)*MAX(0,MIN(1,C$4*1-Inputs!$E$29+1))/1 -> 20 | D8: =Inputs!$E$26*(1+Inputs!$E$28)^(D$5-1)*MAX(0,MIN(1,D$4*1-Inputs!$E$29+1))/1 -> 20 | E8: =Inputs!$E$26*(1+Inputs!$E$28)^(E$5-1)*MAX(0,MIN(1,E$4*1-Inputs!$E$29+1))/1 -> 20 | F8: =Inputs!$E$26*(1+Inputs!$E$28)^(F$5-1)*MAX(0,MIN(1,F$4*1-Inputs!$E$29+1))/1 -> 20 | G8: =Inputs!$E$26*(1+Inputs!$E$28)^(G$5-1)*MAX(0,MIN(1,G$4*1-Inputs!$E$29+1))/1 -> 20 | H8: =Inputs!$E$26*(1+Inputs!$E$28)^(H$5-1)*MAX(0,MIN(1,H$4*1-Inputs!$E$29+1))/1 -> 20 | I8: =Inputs!$E$26*(1+Inputs!$E$28)^(I$5-1)*MAX(0,MIN(1,I$4*1-Inputs!$E$29+1))/1 -> 20 | J8: =Inputs!$E$26*(1+Inputs!$E$28)^(J$5-1)*MAX(0,MIN(1,J$4*1-Inputs!$E$29+1))/1 -> 20 | ... BJ8: =Inputs!$E$26*(1+Inputs!$E$28)^(BJ$5-1)*MAX(0,MIN(1,BJ$4*1-Inputs!$E$29+1))/1 -> 41.472
A9: Sales & marketing — FTE | C9: =Inputs!$E$30*(1+Inputs!$E$32)^(C$5-1)*MAX(0,MIN(1,C$4*1-Inputs!$E$33+1))/1 -> 14 | D9: =Inputs!$E$30*(1+Inputs!$E$32)^(D$5-1)*MAX(0,MIN(1,D$4*1-Inputs!$E$33+1))/1 -> 14 | E9: =Inputs!$E$30*(1+Inputs!$E$32)^(E$5-1)*MAX(0,MIN(1,E$4*1-Inputs!$E$33+1))/1 -> 14 | F9: =Inputs!$E$30*(1+Inputs!$E$32)^(F$5-1)*MAX(0,MIN(1,F$4*1-Inputs!$E$33+1))/1 -> 14 | G9: =Inputs!$E$30*(1+Inputs!$E$32)^(G$5-1)*MAX(0,MIN(1,G$4*1-Inputs!$E$33+1))/1 -> 14 | H9: =Inputs!$E$30*(1+Inputs!$E$32)^(H$5-1)*MAX(0,MIN(1,H$4*1-Inputs!$E$33+1))/1 -> 14 | I9: =Inputs!$E$30*(1+Inputs!$E$32)^(I$5-1)*MAX(0,MIN(1,I$4*1-Inputs!$E$33+1))/1 -> 14 | J9: =Inputs!$E$30*(1+Inputs!$E$32)^(J$5-1)*MAX(0,MIN(1,J$4*1-Inputs!$E$33+1))/1 -> 14 | ... BJ9: =Inputs!$E$30*(1+Inputs!$E$32)^(BJ$5-1)*MAX(0,MIN(1,BJ$4*1-Inputs!$E$33+1))/1 -> 29.0304
A10: Customer success — FTE | C10: =Inputs!$E$34*(1+Inputs!$E$36)^(C$5-1)*MAX(0,MIN(1,C$4*1-Inputs!$E$37+1))/1 -> 8 | D10: =Inputs!$E$34*(1+Inputs!$E$36)^(D$5-1)*MAX(0,MIN(1,D$4*1-Inputs!$E$37+1))/1 -> 8 | E10: =Inputs!$E$34*(1+Inputs!$E$36)^(E$5-1)*MAX(0,MIN(1,E$4*1-Inputs!$E$37+1))/1 -> 8 | F10: =Inputs!$E$34*(1+Inputs!$E$36)^(F$5-1)*MAX(0,MIN(1,F$4*1-Inputs!$E$37+1))/1 -> 8 | G10: =Inputs!$E$34*(1+Inputs!$E$36)^(G$5-1)*MAX(0,MIN(1,G$4*1-Inputs!$E$37+1))/1 -> 8 | H10: =Inputs!$E$34*(1+Inputs!$E$36)^(H$5-1)*MAX(0,MIN(1,H$4*1-Inputs!$E$37+1))/1 -> 8 | I10: =Inputs!$E$34*(1+Inputs!$E$36)^(I$5-1)*MAX(0,MIN(1,I$4*1-Inputs!$E$37+1))/1 -> 8 | J10: =Inputs!$E$34*(1+Inputs!$E$36)^(J$5-1)*MAX(0,MIN(1,J$4*1-Inputs!$E$37+1))/1 -> 8 | ... BJ10: =Inputs!$E$34*(1+Inputs!$E$36)^(BJ$5-1)*MAX(0,MIN(1,BJ$4*1-Inputs!$E$37+1))/1 -> 16.5888
A11: G&A (finance, ops) — FTE | C11: =Inputs!$E$38*(1+Inputs!$E$40)^(C$5-1)*MAX(0,MIN(1,C$4*1-Inputs!$E$41+1))/1 -> 6 | D11: =Inputs!$E$38*(1+Inputs!$E$40)^(D$5-1)*MAX(0,MIN(1,D$4*1-Inputs!$E$41+1))/1 -> 6 | E11: =Inputs!$E$38*(1+Inputs!$E$40)^(E$5-1)*MAX(0,MIN(1,E$4*1-Inputs!$E$41+1))/1 -> 6 | F11: =Inputs!$E$38*(1+Inputs!$E$40)^(F$5-1)*MAX(0,MIN(1,F$4*1-Inputs!$E$41+1))/1 -> 6 | G11: =Inputs!$E$38*(1+Inputs!$E$40)^(G$5-1)*MAX(0,MIN(1,G$4*1-Inputs!$E$41+1))/1 -> 6 | H11: =Inputs!$E$38*(1+Inputs!$E$40)^(H$5-1)*MAX(0,MIN(1,H$4*1-Inputs!$E$41+1))/1 -> 6 | I11: =Inputs!$E$38*(1+Inputs!$E$40)^(I$5-1)*MAX(0,MIN(1,I$4*1-Inputs!$E$41+1))/1 -> 6 | J11: =Inputs!$E$38*(1+Inputs!$E$40)^(J$5-1)*MAX(0,MIN(1,J$4*1-Inputs!$E$41+1))/1 -> 6 | ... BJ11: =Inputs!$E$38*(1+Inputs!$E$40)^(BJ$5-1)*MAX(0,MIN(1,BJ$4*1-Inputs!$E$41+1))/1 -> 10.494037
A12: Total FTE | C12: =C8+C9+C10+C11 -> 48 | D12: =D8+D9+D10+D11 -> 48 | E12: =E8+E9+E10+E11 -> 48 | F12: =F8+F9+F10+F11 -> 48 | G12: =G8+G9+G10+G11 -> 48 | H12: =H8+H9+H10+H11 -> 48 | I12: =I8+I9+I10+I11 -> 48 | J12: =J8+J9+J10+J11 -> 48 | ... BJ12: =BJ8+BJ9+BJ10+BJ11 -> 97.585238
A14: Payroll cost (salary + taxes & benefits)
A15: Engineering & product — payroll cost | C15: =-C8*Inputs!$E$27/12*1*(1+Inputs!$E$42)*(1+Inputs!$E$43)^(C$5-1) -> -270000 | D15: =-D8*Inputs!$E$27/12*1*(1+Inputs!$E$42)*(1+Inputs!$E$43)^(D$5-1) -> -270000 | E15: =-E8*Inputs!$E$27/12*1*(1+Inputs!$E$42)*(1+Inputs!$E$43)^(E$5-1) -> -270000 | F15: =-F8*Inputs!$E$27/12*1*(1+Inputs!$E$42)*(1+Inputs!$E$43)^(F$5-1) -> -270000 | G15: =-G8*Inputs!$E$27/12*1*(1+Inputs!$E$42)*(1+Inputs!$E$43)^(G$5-1) -> -270000 | H15: =-H8*Inputs!$E$27/12*1*(1+Inputs!$E$42)*(1+Inputs!$E$43)^(H$5-1) -> -270000 | I15: =-I8*Inputs!$E$27/12*1*(1+Inputs!$E$42)*(1+Inputs!$E$43)^(I$5-1) -> -270000 | J15: =-J8*Inputs!$E$27/12*1*(1+Inputs!$E$42)*(1+Inputs!$E$43)^(J$5-1) -> -270000 | ... BJ15: =-BJ8*Inputs!$E$27/12*1*(1+Inputs!$E$42)*(1+Inputs!$E$43)^(BJ$5-1) -> -654971.05
A16: Sales & marketing — payroll cost | C16: =-C9*Inputs!$E$31/12*1*(1+Inputs!$E$42)*(1+Inputs!$E$43)^(C$5-1) -> -147000 | D16: =-D9*Inputs!$E$31/12*1*(1+Inputs!$E$42)*(1+Inputs!$E$43)^(D$5-1) -> -147000 | E16: =-E9*Inputs!$E$31/12*1*(1+Inputs!$E$42)*(1+Inputs!$E$43)^(E$5-1) -> -147000 | F16: =-F9*Inputs!$E$31/12*1*(1+Inputs!$E$42)*(1+Inputs!$E$43)^(F$5-1) -> -147000 | G16: =-G9*Inputs!$E$31/12*1*(1+Inputs!$E$42)*(1+Inputs!$E$43)^(G$5-1) -> -147000 | H16: =-H9*Inputs!$E$31/12*1*(1+Inputs!$E$42)*(1+Inputs!$E$43)^(H$5-1) -> -147000 | I16: =-I9*Inputs!$E$31/12*1*(1+Inputs!$E$42)*(1+Inputs!$E$43)^(I$5-1) -> -147000 | J16: =-J9*Inputs!$E$31/12*1*(1+Inputs!$E$42)*(1+Inputs!$E$43)^(J$5-1) -> -147000 | ... BJ16: =-BJ9*Inputs!$E$31/12*1*(1+Inputs!$E$42)*(1+Inputs!$E$43)^(BJ$5-1) -> -356595.35
A17: Customer success — payroll cost | C17: =-C10*Inputs!$E$35/12*1*(1+Inputs!$E$42)*(1+Inputs!$E$43)^(C$5-1) -> -52000 | D17: =-D10*Inputs!$E$35/12*1*(1+Inputs!$E$42)*(1+Inputs!$E$43)^(D$5-1) -> -52000 | E17: =-E10*Inputs!$E$35/12*1*(1+Inputs!$E$42)*(1+Inputs!$E$43)^(E$5-1) -> -52000 | F17: =-F10*Inputs!$E$35/12*1*(1+Inputs!$E$42)*(1+Inputs!$E$43)^(F$5-1) -> -52000 | G17: =-G10*Inputs!$E$35/12*1*(1+Inputs!$E$42)*(1+Inputs!$E$43)^(G$5-1) -> -52000 | H17: =-H10*Inputs!$E$35/12*1*(1+Inputs!$E$42)*(1+Inputs!$E$43)^(H$5-1) -> -52000 | I17: =-I10*Inputs!$E$35/12*1*(1+Inputs!$E$42)*(1+Inputs!$E$43)^(I$5-1) -> -52000 | J17: =-J10*Inputs!$E$35/12*1*(1+Inputs!$E$42)*(1+Inputs!$E$43)^(J$5-1) -> -52000 | ... BJ17: =-BJ10*Inputs!$E$35/12*1*(1+Inputs!$E$42)*(1+Inputs!$E$43)^(BJ$5-1) -> -126142.57
A18: G&A (finance, ops) — payroll cost | C18: =-C11*Inputs!$E$39/12*1*(1+Inputs!$E$42)*(1+Inputs!$E$43)^(C$5-1) -> -54000 | D18: =-D11*Inputs!$E$39/12*1*(1+Inputs!$E$42)*(1+Inputs!$E$43)^(D$5-1) -> -54000 | E18: =-E11*Inputs!$E$39/12*1*(1+Inputs!$E$42)*(1+Inputs!$E$43)^(E$5-1) -> -54000 | F18: =-F11*Inputs!$E$39/12*1*(1+Inputs!$E$42)*(1+Inputs!$E$43)^(F$5-1) -> -54000 | G18: =-G11*Inputs!$E$39/12*1*(1+Inputs!$E$42)*(1+Inputs!$E$43)^(G$5-1) -> -54000 | H18: =-H11*Inputs!$E$39/12*1*(1+Inputs!$E$42)*(1+Inputs!$E$43)^(H$5-1) -> -54000 | I18: =-I11*Inputs!$E$39/12*1*(1+Inputs!$E$42)*(1+Inputs!$E$43)^(I$5-1) -> -54000 | J18: =-J11*Inputs!$E$39/12*1*(1+Inputs!$E$42)*(1+Inputs!$E$43)^(J$5-1) -> -54000 | ... BJ18: =-BJ11*Inputs!$E$39/12*1*(1+Inputs!$E$42)*(1+Inputs!$E$43)^(BJ$5-1) -> -110488.86
A19: Total payroll | C19: =C15+C16+C17+C18 -> -523000 | D19: =D15+D16+D17+D18 -> -523000 | E19: =E15+E16+E17+E18 -> -523000 | F19: =F15+F16+F17+F18 -> -523000 | G19: =G15+G16+G17+G18 -> -523000 | H19: =H15+H16+H17+H18 -> -523000 | I19: =I15+I16+I17+I18 -> -523000 | J19: =J15+J16+J17+J18 -> -523000 | ... BJ19: =BJ15+BJ16+BJ17+BJ18 -> -1248197.8

Sheet Checks
A1: Model checks | E1: =HYPERLINK("#'Cover'!A1","◂ Contents") -> ◂ Contents
A2: Live formulas: they re-run every time an input changes.
A3: Check | B3: Result | C3: What it tests
A4: Annual revenue ties to period detail | B4: =IF(ABS(SUM('P&L'!$B$5:$F$5)-SUM(Monthly!$C$24:$BJ$24))<0.5,"PASS","FAIL") -> PASS | C4: Sum of annual revenue equals the sum of every period
A5: Annual net income ties to period detail | B5: =IF(ABS(SUM('P&L'!$B$22:$F$22)-SUM(Monthly!$C$44:$BJ$44))<0.5,"PASS","FAIL") -> PASS | C5: Sum of annual net income equals the sum of every period
A6: EBITDA reconciliation | B6: =IF(ABS(SUM(Monthly!$C$35:$BJ$35)-SUM(Monthly!$C$26:$BJ$26)-SUM(Monthly!$C$34:$BJ$34))<0.5,"PASS","FAIL") -> PASS | C6: EBITDA = gross profit + operating expenses (costs are negative)
A7: Cash roll-forward | B7: =IF(ABS(INDEX(Monthly!$C$76:$BJ$76,60)-SUM(Monthly!$C$74:$BJ$74))<0.5,"PASS","FAIL") -> PASS | C7: Closing cash = all net cash flows since the start (opening cash is zero)
A8: Scenario selector valid | B8: =IF(AND(ISNUMBER(Dashboard!B4),Dashboard!B4>=1,Dashboard!B4<=3,INT(Dashboard!B4)=Dashboard!B4),"PASS","FAIL") -> PASS | C8: Dashboard!B4 is 1, 2 or 3
A9: Scenario ordering of drivers | B9: =IF(AND(Inputs!$B$7<=Inputs!$C$7,Inputs!$C$7<=Inputs!$D$7,Inputs!$B$8<=Inputs!$C$8,Inputs!$C$8<=Inputs!$D$8,Inputs!$B$9<=Inputs!$C$9,Inputs!$C$9<=Inputs!$D$9,Inputs!$B$10>=Inputs!$C$10,Inputs!$C$10>=Inputs!$D$10,Inputs!$B$11<=Inputs!$C$11,Inputs!$C$11<=Inputs!$D$11,Inputs!$B$12<=Inputs!$C$12,Inputs!$C$12<=Inputs!$D$12,Inputs!$B$13<=Inputs!$C$13,Inputs!$C$13<=Inputs!$D$13,Inputs!$B$16>=Inputs!$C$16,Inputs!$C$16>=Inputs!$D$16,Inputs!$B$18>=Inputs!$C$18,Inputs!$C$18>=Inputs!$D$18,Inputs!$B$19>=Inputs!$C$19,Inputs!$C$19>=Inputs!$D$19,Inputs!$B$26<=Inputs!$C$26,Inputs!$C$26<=Inputs!$D$26,Inputs!$B$28<=Inputs!$C$28,Inputs!$C$28<=Inputs!$D$28,Inputs!$B$30<=Inputs!$C$30,Inputs!$C$30<=Inputs!$D$30,Inputs!$B$32<=Inputs!$C$32,Inputs!$C$32<=Inputs!$D$32,Inputs!$B$34<=Inputs!$C$34,Inputs!$C$34<=Inputs!$D$34,Inputs!$B$36<=Inputs!$C$36,Inputs!$C$36<=Inputs!$D$36,Inputs!$B$38<=Inputs!$C$38,Inputs!$C$38<=Inputs!$D$38,Inputs!$B$40<=Inputs!$C$40,Inputs!$C$40<=Inputs!$D$40,Inputs!$B$64>=Inputs!$C$64,Inputs!$C$64>=Inputs!$D$64,Inputs!$B$65<=Inputs!$C$65,Inputs!$C$65<=Inputs!$D$65,Inputs!$B$66<=Inputs!$C$66,Inputs!$C$66<=Inputs!$D$66),"PASS","FAIL") -> PASS | C9: Low / Base / High ordered the right way for every growth and cost driver
A10: Gross margin within 0–100% | B10: =IF(AND(MIN('P&L'!$B$8:$F$8)>=0,MAX('P&L'!$B$8:$F$8)<=1),"PASS","FAIL") -> PASS | C10: Gross margin never negative or above 100%
A11: Loan balance never negative | B11: =IF(MIN(Monthly!$C$57:$BJ$57)>=-0.5,"PASS","FAIL") -> PASS | C11: Repayments never exceed the loan
A12: Funding table ties to the cash flow | B12: =IF(ABS('Break-even'!B18-('Break-even'!B16-'Break-even'!B10))<0.5,"PASS","FAIL") -> PASS | C12: Lowest cash balance = sources of funds − uses of funds up to that point
A13: Valuation: discounting ties to NPV() | B13: =IF(ABS(Valuation!B23-NPV(Valuation!B6,Valuation!$B$17:$F$17))<0.5,"PASS","FAIL") -> PASS | C13: Sum of discounted free cash flows equals Excel's NPV of the same flows
A14: Valuation: WACC above terminal growth | B14: =IF(Valuation!B6>Valuation!B7,"PASS","FAIL") -> PASS | C14: The perpetual-growth formula needs WACC > g
A15: Valuation: sensitivity centre = enterprise value | B15: =IF(ABS(Valuation!D36-Valuation!B27)<0.5,"PASS","FAIL") -> PASS | C15: The middle of the WACC × growth table reproduces the headline value
A16: Valuation: final-year cash flow positive | B16: =IF(Valuation!$F$17>0,"PASS","WARN") -> PASS | C16: Business warning: a negative final-year cash flow gives a negative terminal value (often a 1-year plan still carrying start-up spending)
A17: Summary ties to period detail | B17: =IF(ABS(SUM(Summary!$B$7:$F$7)-SUM(Monthly!$C$24:$BJ$24))<0.5,"PASS","FAIL") -> PASS | C17: Revenue on the Summary sheet equals the sum of every period
A18: No error values | B18: =IF(SUMPRODUCT(--ISERROR(Monthly!$C$4:$BJ$98))+SUMPRODUCT(--ISERROR(Headcount!$C$4:$BJ$19))+SUMPRODUCT(--ISERROR('P&L'!$B$3:$F$23))+SUMPRODUCT(--ISERROR('Cash Flow'!$B$3:$F$19))+SUMPRODUCT(--ISERROR('Balance Sheet'!$B$3:$F$18))+SUMPRODUCT(--ISERROR(KPIs!$B$4:$F$44))+SUMPRODUCT(--ISERROR('Break-even'!$B$26:$F$33))+SUMPRODUCT(--ISERROR(Valuation!$B$14:$F$19))+SUMPRODUCT(--ISERROR('Break-even'!$B$3:$F$35))+SUMPRODUCT(--ISERROR(Valuation!$A$3:$F$40))+SUMPRODUCT(--ISERROR(Summary!$B$5:$S$55))+SUMPRODUCT(--ISERROR(Dashboard!$A$6:$W$45))+SUMPRODUCT(--ISERROR(Scenarios!$B$5:$F$60))+SUMPRODUCT(--ISERROR('Sources & Uses'!$B$5:$G$30))=0,"PASS","FAIL") -> PASS | C18: No error values (divide-by-zero, broken references) on any calculation sheet
A19: Balance sheet balances every period | B19: =IF(SUMPRODUCT(--(ABS(Monthly!$C$98:$BJ$98)>0.5))=0,"PASS","FAIL") -> PASS | C19: Assets = liabilities + equity in every period
A20: Funding sufficient (cash ≥ 0) | B20: =IF(MIN(Monthly!$C$76:$BJ$76)>=0,"PASS","WARN") -> PASS | C20: Business warning, not an error: cash dips below zero in this scenario
A21: Sources & uses balance | B21: =IF(ABS('Sources & Uses'!B21-'Sources & Uses'!F21)<0.5,"PASS","FAIL") -> PASS | C21: Sources of funds = uses of funds (incl. closing cash) for the period
A22: Overall verdict | B22: =IF(COUNTIF(B4:B21,"FAIL")>0,"FAIL",IF(COUNTIF(B4:B21,"WARN")>0,"PASS WITH WARNINGS","PASS")) -> PASS
