Workbook

Sheet Cover
B2: Auto repair shop financial model (planning)
B3: 5-year financial model · monthly detail · Low / Base / High scenarios · US dollars · Full plan
B5: Purpose | D5: Revenue and profit plan
B6: Active scenario | D6: =Dashboard!C4&" (change it on the Dashboard, cell B4)" -> Base (change it on the Dashboard, cell B4)
B7: Model checks | D7: =Checks!B25 -> PASS
B8: Prepared | D8: 22 October 2026
B10: Contents
C11: PRESENTATION
B12: 1 | C12: =HYPERLINK("#Dashboard!A1","Dashboard") -> Dashboard | D12: Scenario switch, key numbers, core financials
B13: 2 | C13: =HYPERLINK("#Summary!A1","Summary") -> Summary | D13: Income statement, cash flow and balance sheet — every year and any year by month
B14: 3 | C14: =HYPERLINK("#Scenarios!A1","Scenarios") -> Scenarios | D14: Low / Base / High side by side: drivers, outputs, charts
B15: 4 | C15: =HYPERLINK("#'Break-even'!A1","Break-even") -> Break-even | D15: Startup costs, funding need, break-even timing and revenue
B16: 5 | C16: =HYPERLINK("#Valuation!A1","Valuation") -> Valuation | D16: Free cash flow, DCF (perpetual growth and exit multiple), WACC × growth sensitivity
B17: 6 | C17: =HYPERLINK("#'Sources & Uses'!A1","Sources & Uses") -> Sources & Uses | D17: Funding structure, sources and uses of cash for the first months
B18: 7 | C18: =HYPERLINK("#KPIs!A1","KPIs") -> KPIs | D18: Financial ratios, DuPont analysis, industry metrics
C19: INPUTS
B20: 8 | C20: =HYPERLINK("#Inputs!A1","Inputs") -> Inputs | D20: Every assumption, Low / Base / High, with units and comments
C21: STATEMENTS
B22: 9 | C22: =HYPERLINK("#'P&L'!A1","P&L") -> P&L | D22: Annual profit & loss
B23: 10 | C23: =HYPERLINK("#'Cash Flow'!A1","Cash Flow") -> Cash Flow | D23: Annual cash flow statement
B24: 11 | C24: =HYPERLINK("#'Balance Sheet'!A1","Balance Sheet") -> Balance Sheet | D24: Balance sheet at year end
C25: CALCULATIONS
B26: 12 | C26: =HYPERLINK("#Monthly!A1","Monthly") -> Monthly | D26: Month-by-month engine of the model
B27: 13 | C27: =HYPERLINK("#Headcount!A1","Headcount") -> Headcount | D27: Team and payroll
B28: 14 | C28: =HYPERLINK("#'Scenario calc'!A1","Scenario calc") -> Scenario calc | D28: Low, Base and High calculated side by side for the Scenarios sheet
C29: CONTROL
B30: 15 | C30: =HYPERLINK("#Checks!A1","Checks") -> Checks | D30: Live integrity checks and the overall verdict
B32: How to read this file
C33: 1000 | D33: Input you can change — yellow cell with a blue figure (Inputs sheet and the view switches)
C34: 1000 | D34: Formula — calculated, do not overwrite
C35: 1000 | D35: Link to another sheet
C36: 1000 | D36: Active value the model uses (follows the scenario)

Sheet Dashboard
A1: Dashboard | W1: =HYPERLINK("#'Cover'!A1","◂ Contents") -> ◂ Contents
A2: Auto repair shop financial model (planning)
A4: Active scenario | B4: 2 | C4: =CHOOSE(B4,"Low","Base","High") -> Base | D4: 1 = Low · 2 = Base · 3 = High — every sheet follows this cell | S4: Model checks | T4: =Checks!B25 -> PASS
A6: REVENUE · YEAR 5 | C6: EBITDA MARGIN · YEAR 5 | H6: NET INCOME · YEAR 5 | L6: LOWEST CASH BALANCE | P6: FUNDING REQUIRED | T6: ENTERPRISE VALUE (DCF)
A7: =F12 -> 2372818.7 | C7: =F17 -> 0.19822375 | H7: =F18 -> 319393.4 | L7: =F39 -> 83558.366 | P7: =F37 -> 824441.63 | T7: =F44 -> 644631.29
A8: =IF(AND(B12>0,F12>=0),(F12/B12)^(1/4)-1,"CAGR n/a") -> 0.17043825 | C8: =F16 -> 470349.01 | H8: =F19 -> 0.13460506 | L8: ='Break-even'!B6 -> 10 | P8: =IF(F38>=0,"Covered by funding raised",-F38) -> 94441.634 | T8: Average of 2 methods
A10: Core financials ($'000) — active scenario
B11: 1 | C11: 2 | D11: 3 | E11: 4 | F11: 5
A12: Revenue | B12: =SUMIF(Monthly!$C$5:$BJ$5,B$11,Monthly!$C$28:$BJ$28) -> 1264359.4 | C12: =SUMIF(Monthly!$C$5:$BJ$5,C$11,Monthly!$C$28:$BJ$28) -> 1987198.3 | D12: =SUMIF(Monthly!$C$5:$BJ$5,D$11,Monthly!$C$28:$BJ$28) -> 2108218.7 | E12: =SUMIF(Monthly!$C$5:$BJ$5,E$11,Monthly!$C$28:$BJ$28) -> 2236609.2 | F12: =SUMIF(Monthly!$C$5:$BJ$5,F$11,Monthly!$C$28:$BJ$28) -> 2372818.7
A13: Gross profit | B13: =SUMIF(Monthly!$C$5:$BJ$5,B$11,Monthly!$C$36:$BJ$36) -> 481658.44 | C13: =SUMIF(Monthly!$C$5:$BJ$5,C$11,Monthly!$C$36:$BJ$36) -> 999978.46 | D13: =SUMIF(Monthly!$C$5:$BJ$5,D$11,Monthly!$C$36:$BJ$36) -> 1075151.6 | E13: =SUMIF(Monthly!$C$5:$BJ$5,E$11,Monthly!$C$36:$BJ$36) -> 1155330.9 | F13: =SUMIF(Monthly!$C$5:$BJ$5,F$11,Monthly!$C$36:$BJ$36) -> 1240834.3
A14: Gross margin | B14: =IF(B12=0,0,B13/B12) -> 0.38095058 | C14: =IF(C12=0,0,C13/C12) -> 0.5032102 | D14: =IF(D12=0,0,D13/D12) -> 0.50998104 | E14: =IF(E12=0,0,E13/E12) -> 0.51655467 | F14: =IF(F12=0,0,F13/F12) -> 0.52293683
A15: Operating expenses | B15: =SUMIF(Monthly!$C$5:$BJ$5,B$11,Monthly!$C$45:$BJ$45) -> -712680.78 | C15: =SUMIF(Monthly!$C$5:$BJ$5,C$11,Monthly!$C$45:$BJ$45) -> -735288.45 | D15: =SUMIF(Monthly!$C$5:$BJ$5,D$11,Monthly!$C$45:$BJ$45) -> -743733.24 | E15: =SUMIF(Monthly!$C$5:$BJ$5,E$11,Monthly!$C$45:$BJ$45) -> -755634.75 | F15: =SUMIF(Monthly!$C$5:$BJ$5,F$11,Monthly!$C$45:$BJ$45) -> -770485.29
A16: EBITDA | B16: =SUMIF(Monthly!$C$5:$BJ$5,B$11,Monthly!$C$46:$BJ$46) -> -231022.34 | C16: =SUMIF(Monthly!$C$5:$BJ$5,C$11,Monthly!$C$46:$BJ$46) -> 264690.01 | D16: =SUMIF(Monthly!$C$5:$BJ$5,D$11,Monthly!$C$46:$BJ$46) -> 331418.32 | E16: =SUMIF(Monthly!$C$5:$BJ$5,E$11,Monthly!$C$46:$BJ$46) -> 399696.18 | F16: =SUMIF(Monthly!$C$5:$BJ$5,F$11,Monthly!$C$46:$BJ$46) -> 470349.01
A17: EBITDA margin | B17: =IF(B12=0,0,B16/B12) -> -0.18271889 | C17: =IF(C12=0,0,C16/C12) -> 0.13319758 | D17: =IF(D12=0,0,D16/D12) -> 0.15720301 | E17: =IF(E12=0,0,E16/E12) -> 0.17870631 | F17: =IF(F12=0,0,F16/F12) -> 0.19822375
A18: Net income | B18: =SUMIF(Monthly!$C$5:$BJ$5,B$11,Monthly!$C$55:$BJ$55) -> -299921.9 | C18: =SUMIF(Monthly!$C$5:$BJ$5,C$11,Monthly!$C$55:$BJ$55) -> 196493.58 | D18: =SUMIF(Monthly!$C$5:$BJ$5,D$11,Monthly!$C$55:$BJ$55) -> 230229.53 | E18: =SUMIF(Monthly!$C$5:$BJ$5,E$11,Monthly!$C$55:$BJ$55) -> 263013.37 | F18: =SUMIF(Monthly!$C$5:$BJ$5,F$11,Monthly!$C$55:$BJ$55) -> 319393.4
A19: Net margin | B19: =IF(B12=0,0,B18/B12) -> -0.23721254 | C19: =IF(C12=0,0,C18/C12) -> 0.098879705 | D19: =IF(D12=0,0,D18/D12) -> 0.10920571 | E19: =IF(E12=0,0,E18/E12) -> 0.11759469 | F19: =IF(F12=0,0,F18/F12) -> 0.13460506
A20: Operating cash flow | B20: =SUMIF(Monthly!$C$5:$BJ$5,B$11,Monthly!$C$85:$BJ$85) -> -223610.34 | C20: =SUMIF(Monthly!$C$5:$BJ$5,C$11,Monthly!$C$85:$BJ$85) -> 248240.76 | D20: =SUMIF(Monthly!$C$5:$BJ$5,D$11,Monthly!$C$85:$BJ$85) -> 284136.04 | E20: =SUMIF(Monthly!$C$5:$BJ$5,E$11,Monthly!$C$85:$BJ$85) -> 319470.09 | F20: =SUMIF(Monthly!$C$5:$BJ$5,F$11,Monthly!$C$85:$BJ$85) -> 378402.78
A21: Investing cash flow | B21: =SUMIF(Monthly!$C$5:$BJ$5,B$11,Monthly!$C$86:$BJ$86) -> -382000 | C21: =SUMIF(Monthly!$C$5:$BJ$5,C$11,Monthly!$C$86:$BJ$86) -> -20000 | D21: =SUMIF(Monthly!$C$5:$BJ$5,D$11,Monthly!$C$86:$BJ$86) -> -20000 | E21: =SUMIF(Monthly!$C$5:$BJ$5,E$11,Monthly!$C$86:$BJ$86) -> -20000 | F21: =SUMIF(Monthly!$C$5:$BJ$5,F$11,Monthly!$C$86:$BJ$86) -> -20000
A22: Financing cash flow | B22: =SUMIF(Monthly!$C$5:$BJ$5,B$11,Monthly!$C$88:$BJ$88) -> 697261.9 | C22: =SUMIF(Monthly!$C$5:$BJ$5,C$11,Monthly!$C$88:$BJ$88) -> -35714.286 | D22: =SUMIF(Monthly!$C$5:$BJ$5,D$11,Monthly!$C$88:$BJ$88) -> -35714.286 | E22: =SUMIF(Monthly!$C$5:$BJ$5,E$11,Monthly!$C$88:$BJ$88) -> -35714.286 | F22: =SUMIF(Monthly!$C$5:$BJ$5,F$11,Monthly!$C$88:$BJ$88) -> -35714.286
A23: Net change in cash | B23: =SUMIF(Monthly!$C$5:$BJ$5,B$11,Monthly!$C$89:$BJ$89) -> 91651.565 | C23: =SUMIF(Monthly!$C$5:$BJ$5,C$11,Monthly!$C$89:$BJ$89) -> 192526.47 | D23: =SUMIF(Monthly!$C$5:$BJ$5,D$11,Monthly!$C$89:$BJ$89) -> 228421.75 | E23: =SUMIF(Monthly!$C$5:$BJ$5,E$11,Monthly!$C$89:$BJ$89) -> 263755.81 | F23: =SUMIF(Monthly!$C$5:$BJ$5,F$11,Monthly!$C$89:$BJ$89) -> 322688.49
A24: Year-end cash | B24: =INDEX(Monthly!$C$91:$BJ$91,B$11*12) -> 91651.565 | C24: =INDEX(Monthly!$C$91:$BJ$91,C$11*12) -> 284178.03 | D24: =INDEX(Monthly!$C$91:$BJ$91,D$11*12) -> 512599.78 | E24: =INDEX(Monthly!$C$91:$BJ$91,E$11*12) -> 776355.59 | F24: =INDEX(Monthly!$C$91:$BJ$91,F$11*12) -> 1099044.1
A26: Auto repair metrics
B27: 1 | C27: 2 | D27: 3 | E27: 4 | F27: 5
A28: Billed labor hours | B28: =KPIs!B31 -> 5467.5 | C28: =KPIs!C31 -> 8343 | D28: =KPIs!D31 -> 8593.29 | E28: =KPIs!E31 -> 8851.0887 | F28: =KPIs!F31 -> 9116.6214
A29: Shop capacity used | B29: =KPIs!B33 -> 0.51775568 | C29: =KPIs!C33 -> 0.79005682 | D29: =KPIs!D33 -> 0.81375852 | E29: =KPIs!E33 -> 0.83817128 | F29: =KPIs!F33 -> 0.86331642
A30: Revenue per repair order | B30: =KPIs!B40 -> 462.5 | C30: =KPIs!C40 -> 476.375 | D30: =KPIs!D40 -> 490.66625 | E30: =KPIs!E40 -> 505.38624 | F30: =KPIs!F40 -> 520.54782
A31: Revenue per billed hour | B31: =KPIs!B41 -> 231.25 | C31: =KPIs!C41 -> 238.1875 | D31: =KPIs!D41 -> 245.33312 | E31: =KPIs!E41 -> 252.69312 | F31: =KPIs!F41 -> 260.27391
A32: Team (FTE, year end) | B32: =INDEX(Headcount!$C$11:$BJ$11,B$27*12) -> 8 | C32: =INDEX(Headcount!$C$11:$BJ$11,C$27*12) -> 8 | D32: =INDEX(Headcount!$C$11:$BJ$11,D$27*12) -> 8 | E32: =INDEX(Headcount!$C$11:$BJ$11,E$27*12) -> 8 | F32: =INDEX(Headcount!$C$11:$BJ$11,F$27*12) -> 8
A34: Funding & valuation ($'000) — active scenario
A35: Equity raised | F35: =Inputs!$E$67 -> 480000
A36: Loan drawn | F36: =Inputs!$E$68 -> 250000
A37: Funding required (incl. cash buffer) | F37: ='Break-even'!B12 -> 824441.63
A38: Funding surplus / (shortfall) | F38: ='Break-even'!B17 -> -94441.634
A39: ="Lowest cash balance (month "&'Break-even'!B6&")" -> Lowest cash balance (month 10) | F39: ='Break-even'!B18 -> 83558.366
A40: First month with positive EBITDA | F40: ='Break-even'!B21 -> 10
A41: Cash invested paid back | F41: ='Break-even'!B23 -> 41
A42: Enterprise value — perpetual growth | F42: =Valuation!B27 -> 601563.28
A43: Enterprise value — exit multiple | F43: =Valuation!C27 -> 687699.3
A44: Enterprise value — average | F44: =Valuation!B30 -> 644631.29

Sheet Summary
A1: Financial statements summary | U1: =HYPERLINK("#'Cover'!A1","◂ Contents") -> ◂ Contents
A2: Auto repair shop financial model (planning) | P2: Select detailed year: | R2: 1
A5: Income statement ($'000) — by year | H5: ="Income statement ($'000) — Year "&$R$2&", by month" -> Income statement ($'000) — Year 1, by month
B6: 1 | C6: 2 | D6: 3 | E6: 4 | F6: 5 | H6: =INDEX(Monthly!$C$4:$BJ$4,($R$2-1)*12+1) -> 1 | I6: =INDEX(Monthly!$C$4:$BJ$4,($R$2-1)*12+2) -> 2 | J6: =INDEX(Monthly!$C$4:$BJ$4,($R$2-1)*12+3) -> 3 | K6: =INDEX(Monthly!$C$4:$BJ$4,($R$2-1)*12+4) -> 4 | L6: =INDEX(Monthly!$C$4:$BJ$4,($R$2-1)*12+5) -> 5 | M6: =INDEX(Monthly!$C$4:$BJ$4,($R$2-1)*12+6) -> 6 | N6: =INDEX(Monthly!$C$4:$BJ$4,($R$2-1)*12+7) -> 7 | O6: =INDEX(Monthly!$C$4:$BJ$4,($R$2-1)*12+8) -> 8 | P6: =INDEX(Monthly!$C$4:$BJ$4,($R$2-1)*12+9) -> 9 | Q6: =INDEX(Monthly!$C$4:$BJ$4,($R$2-1)*12+10) -> 10 | R6: =INDEX(Monthly!$C$4:$BJ$4,($R$2-1)*12+11) -> 11 | S6: =INDEX(Monthly!$C$4:$BJ$4,($R$2-1)*12+12) -> 12
A7: Revenue | B7: ='P&L'!B5 -> 1264359.4 | C7: ='P&L'!C5 -> 1987198.3 | D7: ='P&L'!D5 -> 2108218.7 | E7: ='P&L'!E5 -> 2236609.2 | F7: ='P&L'!F5 -> 2372818.7 | H7: =INDEX(Monthly!$C$28:$BJ$28,($R$2-1)*12+1) -> 62437.5 | I7: =INDEX(Monthly!$C$28:$BJ$28,($R$2-1)*12+2) -> 70242.188 | J7: =INDEX(Monthly!$C$28:$BJ$28,($R$2-1)*12+3) -> 78046.875 | K7: =INDEX(Monthly!$C$28:$BJ$28,($R$2-1)*12+4) -> 85851.562 | L7: =INDEX(Monthly!$C$28:$BJ$28,($R$2-1)*12+5) -> 93656.25 | M7: =INDEX(Monthly!$C$28:$BJ$28,($R$2-1)*12+6) -> 101460.94 | N7: =INDEX(Monthly!$C$28:$BJ$28,($R$2-1)*12+7) -> 109265.62 | O7: =INDEX(Monthly!$C$28:$BJ$28,($R$2-1)*12+8) -> 117070.31 | P7: =INDEX(Monthly!$C$28:$BJ$28,($R$2-1)*12+9) -> 124875 | Q7: =INDEX(Monthly!$C$28:$BJ$28,($R$2-1)*12+10) -> 132679.69 | R7: =INDEX(Monthly!$C$28:$BJ$28,($R$2-1)*12+11) -> 140484.38 | S7: =INDEX(Monthly!$C$28:$BJ$28,($R$2-1)*12+12) -> 148289.06
A8: Cost of sales | B8: ='P&L'!B6 -> -782700.94 | C8: ='P&L'!C6 -> -987219.85 | D8: ='P&L'!D6 -> -1033067.1 | E8: ='P&L'!E6 -> -1081278.3 | F8: ='P&L'!F6 -> -1131984.4 | H8: =INDEX(Monthly!$C$35:$BJ$35,($R$2-1)*12+1) -> -53878.75 | I8: =INDEX(Monthly!$C$35:$BJ$35,($R$2-1)*12+2) -> -55941.719 | J8: =INDEX(Monthly!$C$35:$BJ$35,($R$2-1)*12+3) -> -58004.688 | K8: =INDEX(Monthly!$C$35:$BJ$35,($R$2-1)*12+4) -> -60067.656 | L8: =INDEX(Monthly!$C$35:$BJ$35,($R$2-1)*12+5) -> -62130.625 | M8: =INDEX(Monthly!$C$35:$BJ$35,($R$2-1)*12+6) -> -64193.594 | N8: =INDEX(Monthly!$C$35:$BJ$35,($R$2-1)*12+7) -> -66256.562 | O8: =INDEX(Monthly!$C$35:$BJ$35,($R$2-1)*12+8) -> -68319.531 | P8: =INDEX(Monthly!$C$35:$BJ$35,($R$2-1)*12+9) -> -70382.5 | Q8: =INDEX(Monthly!$C$35:$BJ$35,($R$2-1)*12+10) -> -72445.469 | R8: =INDEX(Monthly!$C$35:$BJ$35,($R$2-1)*12+11) -> -74508.438 | S8: =INDEX(Monthly!$C$35:$BJ$35,($R$2-1)*12+12) -> -76571.406
A9: Gross profit | B9: ='P&L'!B7 -> 481658.44 | C9: ='P&L'!C7 -> 999978.46 | D9: ='P&L'!D7 -> 1075151.6 | E9: ='P&L'!E7 -> 1155330.9 | F9: ='P&L'!F7 -> 1240834.3 | H9: =INDEX(Monthly!$C$36:$BJ$36,($R$2-1)*12+1) -> 8558.75 | I9: =INDEX(Monthly!$C$36:$BJ$36,($R$2-1)*12+2) -> 14300.469 | J9: =INDEX(Monthly!$C$36:$BJ$36,($R$2-1)*12+3) -> 20042.188 | K9: =INDEX(Monthly!$C$36:$BJ$36,($R$2-1)*12+4) -> 25783.906 | L9: =INDEX(Monthly!$C$36:$BJ$36,($R$2-1)*12+5) -> 31525.625 | M9: =INDEX(Monthly!$C$36:$BJ$36,($R$2-1)*12+6) -> 37267.344 | N9: =INDEX(Monthly!$C$36:$BJ$36,($R$2-1)*12+7) -> 43009.062 | O9: =INDEX(Monthly!$C$36:$BJ$36,($R$2-1)*12+8) -> 48750.781 | P9: =INDEX(Monthly!$C$36:$BJ$36,($R$2-1)*12+9) -> 54492.5 | Q9: =INDEX(Monthly!$C$36:$BJ$36,($R$2-1)*12+10) -> 60234.219 | R9: =INDEX(Monthly!$C$36:$BJ$36,($R$2-1)*12+11) -> 65975.938 | S9: =INDEX(Monthly!$C$36:$BJ$36,($R$2-1)*12+12) -> 71717.656
A10: Gross margin | B10: ='P&L'!B8 -> 0.38095058 | C10: ='P&L'!C8 -> 0.5032102 | D10: ='P&L'!D8 -> 0.50998104 | E10: ='P&L'!E8 -> 0.51655467 | F10: ='P&L'!F8 -> 0.52293683 | H10: =IF(H7=0,0,H9/H7) -> 0.13707708 | I10: =IF(I7=0,0,I9/I7) -> 0.20358803 | J10: =IF(J7=0,0,J9/J7) -> 0.2567968 | K10: =IF(K7=0,0,K9/K7) -> 0.30033124 | L10: =IF(L7=0,0,L9/L7) -> 0.33660994 | M10: =IF(M7=0,0,M9/M7) -> 0.36730731 | N10: =IF(N7=0,0,N9/N7) -> 0.39361933 | O10: =IF(O7=0,0,O9/O7) -> 0.41642309 | ... S10: =IF(S7=0,0,S9/S7) -> 0.48363416
A11: Total operating expenses | B11: ='P&L'!B15 -> -712680.78 | C11: ='P&L'!C15 -> -735288.45 | D11: ='P&L'!D15 -> -743733.24 | E11: ='P&L'!E15 -> -755634.75 | F11: ='P&L'!F15 -> -770485.29 | H11: =INDEX(Monthly!$C$45:$BJ$45,($R$2-1)*12+1) -> -58102.292 | I11: =INDEX(Monthly!$C$45:$BJ$45,($R$2-1)*12+2) -> -58336.432 | J11: =INDEX(Monthly!$C$45:$BJ$45,($R$2-1)*12+3) -> -58570.573 | K11: =INDEX(Monthly!$C$45:$BJ$45,($R$2-1)*12+4) -> -58804.714 | L11: =INDEX(Monthly!$C$45:$BJ$45,($R$2-1)*12+5) -> -59038.854 | M11: =INDEX(Monthly!$C$45:$BJ$45,($R$2-1)*12+6) -> -59272.995 | N11: =INDEX(Monthly!$C$45:$BJ$45,($R$2-1)*12+7) -> -59507.135 | O11: =INDEX(Monthly!$C$45:$BJ$45,($R$2-1)*12+8) -> -59741.276 | P11: =INDEX(Monthly!$C$45:$BJ$45,($R$2-1)*12+9) -> -59975.417 | Q11: =INDEX(Monthly!$C$45:$BJ$45,($R$2-1)*12+10) -> -60209.557 | R11: =INDEX(Monthly!$C$45:$BJ$45,($R$2-1)*12+11) -> -60443.698 | S11: =INDEX(Monthly!$C$45:$BJ$45,($R$2-1)*12+12) -> -60677.839
A12: EBITDA | B12: ='P&L'!B16 -> -231022.34 | C12: ='P&L'!C16 -> 264690.01 | D12: ='P&L'!D16 -> 331418.32 | E12: ='P&L'!E16 -> 399696.18 | F12: ='P&L'!F16 -> 470349.01 | H12: =INDEX(Monthly!$C$46:$BJ$46,($R$2-1)*12+1) -> -49543.542 | I12: =INDEX(Monthly!$C$46:$BJ$46,($R$2-1)*12+2) -> -44035.964 | J12: =INDEX(Monthly!$C$46:$BJ$46,($R$2-1)*12+3) -> -38528.385 | K12: =INDEX(Monthly!$C$46:$BJ$46,($R$2-1)*12+4) -> -33020.807 | L12: =INDEX(Monthly!$C$46:$BJ$46,($R$2-1)*12+5) -> -27513.229 | M12: =INDEX(Monthly!$C$46:$BJ$46,($R$2-1)*12+6) -> -22005.651 | N12: =INDEX(Monthly!$C$46:$BJ$46,($R$2-1)*12+7) -> -16498.073 | O12: =INDEX(Monthly!$C$46:$BJ$46,($R$2-1)*12+8) -> -10990.495 | P12: =INDEX(Monthly!$C$46:$BJ$46,($R$2-1)*12+9) -> -5482.9167 | Q12: =INDEX(Monthly!$C$46:$BJ$46,($R$2-1)*12+10) -> 24.661458 | R12: =INDEX(Monthly!$C$46:$BJ$46,($R$2-1)*12+11) -> 5532.2396 | S12: =INDEX(Monthly!$C$46:$BJ$46,($R$2-1)*12+12) -> 11039.818
A13: EBITDA margin | B13: ='P&L'!B17 -> -0.18271889 | C13: ='P&L'!C17 -> 0.13319758 | D13: ='P&L'!D17 -> 0.15720301 | E13: ='P&L'!E17 -> 0.17870631 | F13: ='P&L'!F17 -> 0.19822375 | H13: =IF(H7=0,0,H12/H7) -> -0.79349016 | I13: =IF(I7=0,0,I12/I7) -> -0.62691618 | J13: =IF(J7=0,0,J12/J7) -> -0.49365699 | K13: =IF(K7=0,0,K12/K7) -> -0.38462675 | L13: =IF(L7=0,0,L12/L7) -> -0.29376821 | M13: =IF(M7=0,0,M12/M7) -> -0.21688791 | N13: =IF(N7=0,0,N12/N7) -> -0.15099051 | O13: =IF(O7=0,0,O12/O7) -> -0.093879435 | ... S13: =IF(S7=0,0,S12/S7) -> 0.074447957
A14: Depreciation | B14: ='P&L'!B18 -> -47750 | C14: ='P&L'!C18 -> -50250 | D14: ='P&L'!D18 -> -52750 | E14: ='P&L'!E18 -> -55250 | F14: ='P&L'!F18 -> -57750 | H14: =INDEX(Monthly!$C$66:$BJ$66,($R$2-1)*12+1) -> -3979.1667 | I14: =INDEX(Monthly!$C$66:$BJ$66,($R$2-1)*12+2) -> -3979.1667 | J14: =INDEX(Monthly!$C$66:$BJ$66,($R$2-1)*12+3) -> -3979.1667 | K14: =INDEX(Monthly!$C$66:$BJ$66,($R$2-1)*12+4) -> -3979.1667 | L14: =INDEX(Monthly!$C$66:$BJ$66,($R$2-1)*12+5) -> -3979.1667 | M14: =INDEX(Monthly!$C$66:$BJ$66,($R$2-1)*12+6) -> -3979.1667 | N14: =INDEX(Monthly!$C$66:$BJ$66,($R$2-1)*12+7) -> -3979.1667 | O14: =INDEX(Monthly!$C$66:$BJ$66,($R$2-1)*12+8) -> -3979.1667 | P14: =INDEX(Monthly!$C$66:$BJ$66,($R$2-1)*12+9) -> -3979.1667 | Q14: =INDEX(Monthly!$C$66:$BJ$66,($R$2-1)*12+10) -> -3979.1667 | R14: =INDEX(Monthly!$C$66:$BJ$66,($R$2-1)*12+11) -> -3979.1667 | S14: =INDEX(Monthly!$C$66:$BJ$66,($R$2-1)*12+12) -> -3979.1667
A15: EBIT | B15: ='P&L'!B19 -> -278772.34 | C15: ='P&L'!C19 -> 214440.01 | D15: ='P&L'!D19 -> 278668.32 | E15: ='P&L'!E19 -> 344446.18 | F15: ='P&L'!F19 -> 412599.01 | H15: =INDEX(Monthly!$C$49:$BJ$49,($R$2-1)*12+1) -> -53522.708 | I15: =INDEX(Monthly!$C$49:$BJ$49,($R$2-1)*12+2) -> -48015.13 | J15: =INDEX(Monthly!$C$49:$BJ$49,($R$2-1)*12+3) -> -42507.552 | K15: =INDEX(Monthly!$C$49:$BJ$49,($R$2-1)*12+4) -> -36999.974 | L15: =INDEX(Monthly!$C$49:$BJ$49,($R$2-1)*12+5) -> -31492.396 | M15: =INDEX(Monthly!$C$49:$BJ$49,($R$2-1)*12+6) -> -25984.818 | N15: =INDEX(Monthly!$C$49:$BJ$49,($R$2-1)*12+7) -> -20477.24 | O15: =INDEX(Monthly!$C$49:$BJ$49,($R$2-1)*12+8) -> -14969.661 | P15: =INDEX(Monthly!$C$49:$BJ$49,($R$2-1)*12+9) -> -9462.0833 | Q15: =INDEX(Monthly!$C$49:$BJ$49,($R$2-1)*12+10) -> -3954.5052 | R15: =INDEX(Monthly!$C$49:$BJ$49,($R$2-1)*12+11) -> 1553.0729 | S15: =INDEX(Monthly!$C$49:$BJ$49,($R$2-1)*12+12) -> 7060.651
A16: Interest | B16: ='P&L'!B20 -> -21149.554 | C16: ='P&L'!C20 -> -17946.429 | D16: ='P&L'!D20 -> -14732.143 | E16: ='P&L'!E20 -> -11517.857 | F16: ='P&L'!F20 -> -8303.5714 | H16: =INDEX(Monthly!$C$50:$BJ$50,($R$2-1)*12+1) -> -1875 | I16: =INDEX(Monthly!$C$50:$BJ$50,($R$2-1)*12+2) -> -1863.8393 | J16: =INDEX(Monthly!$C$50:$BJ$50,($R$2-1)*12+3) -> -1841.5179 | K16: =INDEX(Monthly!$C$50:$BJ$50,($R$2-1)*12+4) -> -1819.1964 | L16: =INDEX(Monthly!$C$50:$BJ$50,($R$2-1)*12+5) -> -1796.875 | M16: =INDEX(Monthly!$C$50:$BJ$50,($R$2-1)*12+6) -> -1774.5536 | N16: =INDEX(Monthly!$C$50:$BJ$50,($R$2-1)*12+7) -> -1752.2321 | O16: =INDEX(Monthly!$C$50:$BJ$50,($R$2-1)*12+8) -> -1729.9107 | P16: =INDEX(Monthly!$C$50:$BJ$50,($R$2-1)*12+9) -> -1707.5893 | Q16: =INDEX(Monthly!$C$50:$BJ$50,($R$2-1)*12+10) -> -1685.2679 | R16: =INDEX(Monthly!$C$50:$BJ$50,($R$2-1)*12+11) -> -1662.9464 | S16: =INDEX(Monthly!$C$50:$BJ$50,($R$2-1)*12+12) -> -1640.625
A17: Pre-tax income | B17: ='P&L'!B21 -> -299921.9 | C17: ='P&L'!C21 -> 196493.58 | D17: ='P&L'!D21 -> 263936.18 | E17: ='P&L'!E21 -> 332928.32 | F17: ='P&L'!F21 -> 404295.44 | H17: =INDEX(Monthly!$C$51:$BJ$51,($R$2-1)*12+1) -> -55397.708 | I17: =INDEX(Monthly!$C$51:$BJ$51,($R$2-1)*12+2) -> -49878.969 | J17: =INDEX(Monthly!$C$51:$BJ$51,($R$2-1)*12+3) -> -44349.07 | K17: =INDEX(Monthly!$C$51:$BJ$51,($R$2-1)*12+4) -> -38819.17 | L17: =INDEX(Monthly!$C$51:$BJ$51,($R$2-1)*12+5) -> -33289.271 | M17: =INDEX(Monthly!$C$51:$BJ$51,($R$2-1)*12+6) -> -27759.371 | N17: =INDEX(Monthly!$C$51:$BJ$51,($R$2-1)*12+7) -> -22229.472 | O17: =INDEX(Monthly!$C$51:$BJ$51,($R$2-1)*12+8) -> -16699.572 | P17: =INDEX(Monthly!$C$51:$BJ$51,($R$2-1)*12+9) -> -11169.673 | Q17: =INDEX(Monthly!$C$51:$BJ$51,($R$2-1)*12+10) -> -5639.7731 | R17: =INDEX(Monthly!$C$51:$BJ$51,($R$2-1)*12+11) -> -109.87351 | S17: =INDEX(Monthly!$C$51:$BJ$51,($R$2-1)*12+12) -> 5420.026
A18: Income tax | B18: ='P&L'!B22 -> 0 | C18: ='P&L'!C22 -> 0 | D18: ='P&L'!D22 -> -33706.652 | E18: ='P&L'!E22 -> -69914.948 | F18: ='P&L'!F22 -> -84902.043 | H18: =INDEX(Monthly!$C$54:$BJ$54,($R$2-1)*12+1) -> 0 | I18: =INDEX(Monthly!$C$54:$BJ$54,($R$2-1)*12+2) -> 0 | J18: =INDEX(Monthly!$C$54:$BJ$54,($R$2-1)*12+3) -> 0 | K18: =INDEX(Monthly!$C$54:$BJ$54,($R$2-1)*12+4) -> 0 | L18: =INDEX(Monthly!$C$54:$BJ$54,($R$2-1)*12+5) -> 0 | M18: =INDEX(Monthly!$C$54:$BJ$54,($R$2-1)*12+6) -> 0 | N18: =INDEX(Monthly!$C$54:$BJ$54,($R$2-1)*12+7) -> 0 | O18: =INDEX(Monthly!$C$54:$BJ$54,($R$2-1)*12+8) -> 0 | P18: =INDEX(Monthly!$C$54:$BJ$54,($R$2-1)*12+9) -> 0 | Q18: =INDEX(Monthly!$C$54:$BJ$54,($R$2-1)*12+10) -> 0 | R18: =INDEX(Monthly!$C$54:$BJ$54,($R$2-1)*12+11) -> 0 | S18: =INDEX(Monthly!$C$54:$BJ$54,($R$2-1)*12+12) -> 0
A19: Net income | B19: ='P&L'!B23 -> -299921.9 | C19: ='P&L'!C23 -> 196493.58 | D19: ='P&L'!D23 -> 230229.53 | E19: ='P&L'!E23 -> 263013.37 | F19: ='P&L'!F23 -> 319393.4 | H19: =INDEX(Monthly!$C$55:$BJ$55,($R$2-1)*12+1) -> -55397.708 | I19: =INDEX(Monthly!$C$55:$BJ$55,($R$2-1)*12+2) -> -49878.969 | J19: =INDEX(Monthly!$C$55:$BJ$55,($R$2-1)*12+3) -> -44349.07 | K19: =INDEX(Monthly!$C$55:$BJ$55,($R$2-1)*12+4) -> -38819.17 | L19: =INDEX(Monthly!$C$55:$BJ$55,($R$2-1)*12+5) -> -33289.271 | M19: =INDEX(Monthly!$C$55:$BJ$55,($R$2-1)*12+6) -> -27759.371 | N19: =INDEX(Monthly!$C$55:$BJ$55,($R$2-1)*12+7) -> -22229.472 | O19: =INDEX(Monthly!$C$55:$BJ$55,($R$2-1)*12+8) -> -16699.572 | P19: =INDEX(Monthly!$C$55:$BJ$55,($R$2-1)*12+9) -> -11169.673 | Q19: =INDEX(Monthly!$C$55:$BJ$55,($R$2-1)*12+10) -> -5639.7731 | R19: =INDEX(Monthly!$C$55:$BJ$55,($R$2-1)*12+11) -> -109.87351 | S19: =INDEX(Monthly!$C$55:$BJ$55,($R$2-1)*12+12) -> 5420.026
A20: Net margin | B20: ='P&L'!B24 -> -0.23721254 | C20: ='P&L'!C24 -> 0.098879705 | D20: ='P&L'!D24 -> 0.10920571 | E20: ='P&L'!E24 -> 0.11759469 | F20: ='P&L'!F24 -> 0.13460506 | H20: =IF(H7=0,0,H19/H7) -> -0.88725058 | I20: =IF(I7=0,0,I19/I7) -> -0.71009989 | J20: =IF(J7=0,0,J19/J7) -> -0.56823633 | K20: =IF(K7=0,0,K19/K7) -> -0.45216615 | L20: =IF(L7=0,0,L19/L7) -> -0.355441 | M20: =IF(M7=0,0,M19/M7) -> -0.27359664 | N20: =IF(N7=0,0,N19/N7) -> -0.20344433 | O20: =IF(O7=0,0,O19/O7) -> -0.14264566 | ... S20: =IF(S7=0,0,S19/S7) -> 0.03655041
A22: Cash flow ($'000) — by year | H22: ="Cash flow ($'000) — Year "&$R$2&", by month" -> Cash flow ($'000) — Year 1, by month
B23: 1 | C23: 2 | D23: 3 | E23: 4 | F23: 5 | H23: =INDEX(Monthly!$C$4:$BJ$4,($R$2-1)*12+1) -> 1 | I23: =INDEX(Monthly!$C$4:$BJ$4,($R$2-1)*12+2) -> 2 | J23: =INDEX(Monthly!$C$4:$BJ$4,($R$2-1)*12+3) -> 3 | K23: =INDEX(Monthly!$C$4:$BJ$4,($R$2-1)*12+4) -> 4 | L23: =INDEX(Monthly!$C$4:$BJ$4,($R$2-1)*12+5) -> 5 | M23: =INDEX(Monthly!$C$4:$BJ$4,($R$2-1)*12+6) -> 6 | N23: =INDEX(Monthly!$C$4:$BJ$4,($R$2-1)*12+7) -> 7 | O23: =INDEX(Monthly!$C$4:$BJ$4,($R$2-1)*12+8) -> 8 | P23: =INDEX(Monthly!$C$4:$BJ$4,($R$2-1)*12+9) -> 9 | Q23: =INDEX(Monthly!$C$4:$BJ$4,($R$2-1)*12+10) -> 10 | R23: =INDEX(Monthly!$C$4:$BJ$4,($R$2-1)*12+11) -> 11 | S23: =INDEX(Monthly!$C$4:$BJ$4,($R$2-1)*12+12) -> 12
A24: Operating cash flow | B24: ='Cash Flow'!B10 -> -223610.34 | C24: ='Cash Flow'!C10 -> 248240.76 | D24: ='Cash Flow'!D10 -> 284136.04 | E24: ='Cash Flow'!E10 -> 319470.09 | F24: ='Cash Flow'!F10 -> 378402.78 | H24: =INDEX(Monthly!$C$85:$BJ$85,($R$2-1)*12+1) -> -27131 | I24: =INDEX(Monthly!$C$85:$BJ$85,($R$2-1)*12+2) -> -45511.256 | J24: =INDEX(Monthly!$C$85:$BJ$85,($R$2-1)*12+3) -> -39981.356 | K24: =INDEX(Monthly!$C$85:$BJ$85,($R$2-1)*12+4) -> -34451.457 | L24: =INDEX(Monthly!$C$85:$BJ$85,($R$2-1)*12+5) -> -28921.557 | M24: =INDEX(Monthly!$C$85:$BJ$85,($R$2-1)*12+6) -> -23391.658 | N24: =INDEX(Monthly!$C$85:$BJ$85,($R$2-1)*12+7) -> -17861.758 | O24: =INDEX(Monthly!$C$85:$BJ$85,($R$2-1)*12+8) -> -12331.859 | P24: =INDEX(Monthly!$C$85:$BJ$85,($R$2-1)*12+9) -> -6801.9591 | Q24: =INDEX(Monthly!$C$85:$BJ$85,($R$2-1)*12+10) -> -1272.0595 | R24: =INDEX(Monthly!$C$85:$BJ$85,($R$2-1)*12+11) -> 4257.84 | S24: =INDEX(Monthly!$C$85:$BJ$85,($R$2-1)*12+12) -> 9787.7396
A25: Capital spending | B25: ='Cash Flow'!B11 -> -382000 | C25: ='Cash Flow'!C11 -> -20000 | D25: ='Cash Flow'!D11 -> -20000 | E25: ='Cash Flow'!E11 -> -20000 | F25: ='Cash Flow'!F11 -> -20000 | H25: =INDEX(Monthly!$C$86:$BJ$86,($R$2-1)*12+1) -> -382000 | I25: =INDEX(Monthly!$C$86:$BJ$86,($R$2-1)*12+2) -> 0 | J25: =INDEX(Monthly!$C$86:$BJ$86,($R$2-1)*12+3) -> 0 | K25: =INDEX(Monthly!$C$86:$BJ$86,($R$2-1)*12+4) -> 0 | L25: =INDEX(Monthly!$C$86:$BJ$86,($R$2-1)*12+5) -> 0 | M25: =INDEX(Monthly!$C$86:$BJ$86,($R$2-1)*12+6) -> 0 | N25: =INDEX(Monthly!$C$86:$BJ$86,($R$2-1)*12+7) -> 0 | O25: =INDEX(Monthly!$C$86:$BJ$86,($R$2-1)*12+8) -> 0 | P25: =INDEX(Monthly!$C$86:$BJ$86,($R$2-1)*12+9) -> 0 | Q25: =INDEX(Monthly!$C$86:$BJ$86,($R$2-1)*12+10) -> 0 | R25: =INDEX(Monthly!$C$86:$BJ$86,($R$2-1)*12+11) -> 0 | S25: =INDEX(Monthly!$C$86:$BJ$86,($R$2-1)*12+12) -> 0
A26: Equity raised | B26: ='Cash Flow'!B12 -> 480000 | C26: ='Cash Flow'!C12 -> 0 | D26: ='Cash Flow'!D12 -> 0 | E26: ='Cash Flow'!E12 -> 0 | F26: ='Cash Flow'!F12 -> 0 | H26: =INDEX(Monthly!$C$87:$BJ$87,($R$2-1)*12+1) -> 480000 | I26: =INDEX(Monthly!$C$87:$BJ$87,($R$2-1)*12+2) -> 0 | J26: =INDEX(Monthly!$C$87:$BJ$87,($R$2-1)*12+3) -> 0 | K26: =INDEX(Monthly!$C$87:$BJ$87,($R$2-1)*12+4) -> 0 | L26: =INDEX(Monthly!$C$87:$BJ$87,($R$2-1)*12+5) -> 0 | M26: =INDEX(Monthly!$C$87:$BJ$87,($R$2-1)*12+6) -> 0 | N26: =INDEX(Monthly!$C$87:$BJ$87,($R$2-1)*12+7) -> 0 | O26: =INDEX(Monthly!$C$87:$BJ$87,($R$2-1)*12+8) -> 0 | P26: =INDEX(Monthly!$C$87:$BJ$87,($R$2-1)*12+9) -> 0 | Q26: =INDEX(Monthly!$C$87:$BJ$87,($R$2-1)*12+10) -> 0 | R26: =INDEX(Monthly!$C$87:$BJ$87,($R$2-1)*12+11) -> 0 | S26: =INDEX(Monthly!$C$87:$BJ$87,($R$2-1)*12+12) -> 0
A27: Loan drawdown | B27: ='Cash Flow'!B13 -> 250000 | C27: ='Cash Flow'!C13 -> 0 | D27: ='Cash Flow'!D13 -> 0 | E27: ='Cash Flow'!E13 -> 0 | F27: ='Cash Flow'!F13 -> 0 | H27: =INDEX(Monthly!$C$72:$BJ$72,($R$2-1)*12+1) -> 250000 | I27: =INDEX(Monthly!$C$72:$BJ$72,($R$2-1)*12+2) -> 0 | J27: =INDEX(Monthly!$C$72:$BJ$72,($R$2-1)*12+3) -> 0 | K27: =INDEX(Monthly!$C$72:$BJ$72,($R$2-1)*12+4) -> 0 | L27: =INDEX(Monthly!$C$72:$BJ$72,($R$2-1)*12+5) -> 0 | M27: =INDEX(Monthly!$C$72:$BJ$72,($R$2-1)*12+6) -> 0 | N27: =INDEX(Monthly!$C$72:$BJ$72,($R$2-1)*12+7) -> 0 | O27: =INDEX(Monthly!$C$72:$BJ$72,($R$2-1)*12+8) -> 0 | P27: =INDEX(Monthly!$C$72:$BJ$72,($R$2-1)*12+9) -> 0 | Q27: =INDEX(Monthly!$C$72:$BJ$72,($R$2-1)*12+10) -> 0 | R27: =INDEX(Monthly!$C$72:$BJ$72,($R$2-1)*12+11) -> 0 | S27: =INDEX(Monthly!$C$72:$BJ$72,($R$2-1)*12+12) -> 0
A28: Loan repayment | B28: ='Cash Flow'!B14 -> -32738.095 | C28: ='Cash Flow'!C14 -> -35714.286 | D28: ='Cash Flow'!D14 -> -35714.286 | E28: ='Cash Flow'!E14 -> -35714.286 | F28: ='Cash Flow'!F14 -> -35714.286 | H28: =INDEX(Monthly!$C$73:$BJ$73,($R$2-1)*12+1) -> 0 | I28: =INDEX(Monthly!$C$73:$BJ$73,($R$2-1)*12+2) -> -2976.1905 | J28: =INDEX(Monthly!$C$73:$BJ$73,($R$2-1)*12+3) -> -2976.1905 | K28: =INDEX(Monthly!$C$73:$BJ$73,($R$2-1)*12+4) -> -2976.1905 | L28: =INDEX(Monthly!$C$73:$BJ$73,($R$2-1)*12+5) -> -2976.1905 | M28: =INDEX(Monthly!$C$73:$BJ$73,($R$2-1)*12+6) -> -2976.1905 | N28: =INDEX(Monthly!$C$73:$BJ$73,($R$2-1)*12+7) -> -2976.1905 | O28: =INDEX(Monthly!$C$73:$BJ$73,($R$2-1)*12+8) -> -2976.1905 | P28: =INDEX(Monthly!$C$73:$BJ$73,($R$2-1)*12+9) -> -2976.1905 | Q28: =INDEX(Monthly!$C$73:$BJ$73,($R$2-1)*12+10) -> -2976.1905 | R28: =INDEX(Monthly!$C$73:$BJ$73,($R$2-1)*12+11) -> -2976.1905 | S28: =INDEX(Monthly!$C$73:$BJ$73,($R$2-1)*12+12) -> -2976.1905
A29: Financing cash flow | B29: ='Cash Flow'!B15 -> 697261.9 | C29: ='Cash Flow'!C15 -> -35714.286 | D29: ='Cash Flow'!D15 -> -35714.286 | E29: ='Cash Flow'!E15 -> -35714.286 | F29: ='Cash Flow'!F15 -> -35714.286 | H29: =INDEX(Monthly!$C$88:$BJ$88,($R$2-1)*12+1) -> 730000 | I29: =INDEX(Monthly!$C$88:$BJ$88,($R$2-1)*12+2) -> -2976.1905 | J29: =INDEX(Monthly!$C$88:$BJ$88,($R$2-1)*12+3) -> -2976.1905 | K29: =INDEX(Monthly!$C$88:$BJ$88,($R$2-1)*12+4) -> -2976.1905 | L29: =INDEX(Monthly!$C$88:$BJ$88,($R$2-1)*12+5) -> -2976.1905 | M29: =INDEX(Monthly!$C$88:$BJ$88,($R$2-1)*12+6) -> -2976.1905 | N29: =INDEX(Monthly!$C$88:$BJ$88,($R$2-1)*12+7) -> -2976.1905 | O29: =INDEX(Monthly!$C$88:$BJ$88,($R$2-1)*12+8) -> -2976.1905 | P29: =INDEX(Monthly!$C$88:$BJ$88,($R$2-1)*12+9) -> -2976.1905 | Q29: =INDEX(Monthly!$C$88:$BJ$88,($R$2-1)*12+10) -> -2976.1905 | R29: =INDEX(Monthly!$C$88:$BJ$88,($R$2-1)*12+11) -> -2976.1905 | S29: =INDEX(Monthly!$C$88:$BJ$88,($R$2-1)*12+12) -> -2976.1905
A30: Net change in cash | B30: ='Cash Flow'!B16 -> 91651.565 | C30: ='Cash Flow'!C16 -> 192526.47 | D30: ='Cash Flow'!D16 -> 228421.75 | E30: ='Cash Flow'!E16 -> 263755.81 | F30: ='Cash Flow'!F16 -> 322688.49 | H30: =INDEX(Monthly!$C$89:$BJ$89,($R$2-1)*12+1) -> 320869 | I30: =INDEX(Monthly!$C$89:$BJ$89,($R$2-1)*12+2) -> -48487.446 | J30: =INDEX(Monthly!$C$89:$BJ$89,($R$2-1)*12+3) -> -42957.547 | K30: =INDEX(Monthly!$C$89:$BJ$89,($R$2-1)*12+4) -> -37427.647 | L30: =INDEX(Monthly!$C$89:$BJ$89,($R$2-1)*12+5) -> -31897.748 | M30: =INDEX(Monthly!$C$89:$BJ$89,($R$2-1)*12+6) -> -26367.848 | N30: =INDEX(Monthly!$C$89:$BJ$89,($R$2-1)*12+7) -> -20837.949 | O30: =INDEX(Monthly!$C$89:$BJ$89,($R$2-1)*12+8) -> -15308.049 | P30: =INDEX(Monthly!$C$89:$BJ$89,($R$2-1)*12+9) -> -9778.1496 | Q30: =INDEX(Monthly!$C$89:$BJ$89,($R$2-1)*12+10) -> -4248.25 | R30: =INDEX(Monthly!$C$89:$BJ$89,($R$2-1)*12+11) -> 1281.6496 | S30: =INDEX(Monthly!$C$89:$BJ$89,($R$2-1)*12+12) -> 6811.5491
A31: Closing cash | B31: ='Cash Flow'!B18 -> 91651.565 | C31: ='Cash Flow'!C18 -> 284178.03 | D31: ='Cash Flow'!D18 -> 512599.78 | E31: ='Cash Flow'!E18 -> 776355.59 | F31: ='Cash Flow'!F18 -> 1099044.1 | H31: =INDEX(Monthly!$C$91:$BJ$91,($R$2-1)*12+1) -> 320869 | I31: =INDEX(Monthly!$C$91:$BJ$91,($R$2-1)*12+2) -> 272381.55 | J31: =INDEX(Monthly!$C$91:$BJ$91,($R$2-1)*12+3) -> 229424.01 | K31: =INDEX(Monthly!$C$91:$BJ$91,($R$2-1)*12+4) -> 191996.36 | L31: =INDEX(Monthly!$C$91:$BJ$91,($R$2-1)*12+5) -> 160098.61 | M31: =INDEX(Monthly!$C$91:$BJ$91,($R$2-1)*12+6) -> 133730.76 | N31: =INDEX(Monthly!$C$91:$BJ$91,($R$2-1)*12+7) -> 112892.81 | O31: =INDEX(Monthly!$C$91:$BJ$91,($R$2-1)*12+8) -> 97584.766 | P31: =INDEX(Monthly!$C$91:$BJ$91,($R$2-1)*12+9) -> 87806.616 | Q31: =INDEX(Monthly!$C$91:$BJ$91,($R$2-1)*12+10) -> 83558.366 | R31: =INDEX(Monthly!$C$91:$BJ$91,($R$2-1)*12+11) -> 84840.016 | S31: =INDEX(Monthly!$C$91:$BJ$91,($R$2-1)*12+12) -> 91651.565
A39: Balance sheet at year end ($'000) | H39: ="Balance sheet at month end ($'000) — Year "&$R$2 -> Balance sheet at month end ($'000) — Year 1
B40: 1 | C40: 2 | D40: 3 | E40: 4 | F40: 5 | H40: =INDEX(Monthly!$C$4:$BJ$4,($R$2-1)*12+1) -> 1 | I40: =INDEX(Monthly!$C$4:$BJ$4,($R$2-1)*12+2) -> 2 | J40: =INDEX(Monthly!$C$4:$BJ$4,($R$2-1)*12+3) -> 3 | K40: =INDEX(Monthly!$C$4:$BJ$4,($R$2-1)*12+4) -> 4 | L40: =INDEX(Monthly!$C$4:$BJ$4,($R$2-1)*12+5) -> 5 | M40: =INDEX(Monthly!$C$4:$BJ$4,($R$2-1)*12+6) -> 6 | N40: =INDEX(Monthly!$C$4:$BJ$4,($R$2-1)*12+7) -> 7 | O40: =INDEX(Monthly!$C$4:$BJ$4,($R$2-1)*12+8) -> 8 | P40: =INDEX(Monthly!$C$4:$BJ$4,($R$2-1)*12+9) -> 9 | Q40: =INDEX(Monthly!$C$4:$BJ$4,($R$2-1)*12+10) -> 10 | R40: =INDEX(Monthly!$C$4:$BJ$4,($R$2-1)*12+11) -> 11 | S40: =INDEX(Monthly!$C$4:$BJ$4,($R$2-1)*12+12) -> 12
A41: Cash | B41: ='Balance Sheet'!B5 -> 91651.565 | C41: ='Balance Sheet'!C5 -> 284178.03 | D41: ='Balance Sheet'!D5 -> 512599.78 | E41: ='Balance Sheet'!E5 -> 776355.59 | F41: ='Balance Sheet'!F5 -> 1099044.1 | H41: =INDEX(Monthly!$C$91:$BJ$91,($R$2-1)*12+1) -> 320869 | I41: =INDEX(Monthly!$C$91:$BJ$91,($R$2-1)*12+2) -> 272381.55 | J41: =INDEX(Monthly!$C$91:$BJ$91,($R$2-1)*12+3) -> 229424.01 | K41: =INDEX(Monthly!$C$91:$BJ$91,($R$2-1)*12+4) -> 191996.36 | L41: =INDEX(Monthly!$C$91:$BJ$91,($R$2-1)*12+5) -> 160098.61 | M41: =INDEX(Monthly!$C$91:$BJ$91,($R$2-1)*12+6) -> 133730.76 | N41: =INDEX(Monthly!$C$91:$BJ$91,($R$2-1)*12+7) -> 112892.81 | O41: =INDEX(Monthly!$C$91:$BJ$91,($R$2-1)*12+8) -> 97584.766 | P41: =INDEX(Monthly!$C$91:$BJ$91,($R$2-1)*12+9) -> 87806.616 | Q41: =INDEX(Monthly!$C$91:$BJ$91,($R$2-1)*12+10) -> 83558.366 | R41: =INDEX(Monthly!$C$91:$BJ$91,($R$2-1)*12+11) -> 84840.016 | S41: =INDEX(Monthly!$C$91:$BJ$91,($R$2-1)*12+12) -> 91651.565
A42: Accounts receivable | B42: ='Balance Sheet'!B6 -> 14828.906 | C42: ='Balance Sheet'!C6 -> 16559.986 | D42: ='Balance Sheet'!D6 -> 17568.489 | E42: ='Balance Sheet'!E6 -> 18638.41 | F42: ='Balance Sheet'!F6 -> 19773.489 | H42: =INDEX(Monthly!$C$77:$BJ$77,($R$2-1)*12+1) -> 6243.75 | I42: =INDEX(Monthly!$C$77:$BJ$77,($R$2-1)*12+2) -> 7024.2188 | J42: =INDEX(Monthly!$C$77:$BJ$77,($R$2-1)*12+3) -> 7804.6875 | K42: =INDEX(Monthly!$C$77:$BJ$77,($R$2-1)*12+4) -> 8585.1562 | L42: =INDEX(Monthly!$C$77:$BJ$77,($R$2-1)*12+5) -> 9365.625 | M42: =INDEX(Monthly!$C$77:$BJ$77,($R$2-1)*12+6) -> 10146.094 | N42: =INDEX(Monthly!$C$77:$BJ$77,($R$2-1)*12+7) -> 10926.562 | O42: =INDEX(Monthly!$C$77:$BJ$77,($R$2-1)*12+8) -> 11707.031 | P42: =INDEX(Monthly!$C$77:$BJ$77,($R$2-1)*12+9) -> 12487.5 | Q42: =INDEX(Monthly!$C$77:$BJ$77,($R$2-1)*12+10) -> 13267.969 | R42: =INDEX(Monthly!$C$77:$BJ$77,($R$2-1)*12+11) -> 14048.438 | S42: =INDEX(Monthly!$C$77:$BJ$77,($R$2-1)*12+12) -> 14828.906
A43: Inventory | B43: ='Balance Sheet'!B7 -> 20419.042 | C43: ='Balance Sheet'!C7 -> 21938.219 | D43: ='Balance Sheet'!D7 -> 22957.047 | E43: ='Balance Sheet'!E7 -> 24028.406 | F43: ='Balance Sheet'!F7 -> 25155.209 | H43: =INDEX(Monthly!$C$78:$BJ$78,($R$2-1)*12+1) -> 14367.667 | I43: =INDEX(Monthly!$C$78:$BJ$78,($R$2-1)*12+2) -> 14917.792 | J43: =INDEX(Monthly!$C$78:$BJ$78,($R$2-1)*12+3) -> 15467.917 | K43: =INDEX(Monthly!$C$78:$BJ$78,($R$2-1)*12+4) -> 16018.042 | L43: =INDEX(Monthly!$C$78:$BJ$78,($R$2-1)*12+5) -> 16568.167 | M43: =INDEX(Monthly!$C$78:$BJ$78,($R$2-1)*12+6) -> 17118.292 | N43: =INDEX(Monthly!$C$78:$BJ$78,($R$2-1)*12+7) -> 17668.417 | O43: =INDEX(Monthly!$C$78:$BJ$78,($R$2-1)*12+8) -> 18218.542 | P43: =INDEX(Monthly!$C$78:$BJ$78,($R$2-1)*12+9) -> 18768.667 | Q43: =INDEX(Monthly!$C$78:$BJ$78,($R$2-1)*12+10) -> 19318.792 | R43: =INDEX(Monthly!$C$78:$BJ$78,($R$2-1)*12+11) -> 19868.917 | S43: =INDEX(Monthly!$C$78:$BJ$78,($R$2-1)*12+12) -> 20419.042
A44: Net fixed assets | B44: ='Balance Sheet'!B8 -> 334250 | C44: ='Balance Sheet'!C8 -> 304000 | D44: ='Balance Sheet'!D8 -> 271250 | E44: ='Balance Sheet'!E8 -> 236000 | F44: ='Balance Sheet'!F8 -> 198250 | H44: =INDEX(Monthly!$C$68:$BJ$68,($R$2-1)*12+1) -> 378020.83 | I44: =INDEX(Monthly!$C$68:$BJ$68,($R$2-1)*12+2) -> 374041.67 | J44: =INDEX(Monthly!$C$68:$BJ$68,($R$2-1)*12+3) -> 370062.5 | K44: =INDEX(Monthly!$C$68:$BJ$68,($R$2-1)*12+4) -> 366083.33 | L44: =INDEX(Monthly!$C$68:$BJ$68,($R$2-1)*12+5) -> 362104.17 | M44: =INDEX(Monthly!$C$68:$BJ$68,($R$2-1)*12+6) -> 358125 | N44: =INDEX(Monthly!$C$68:$BJ$68,($R$2-1)*12+7) -> 354145.83 | O44: =INDEX(Monthly!$C$68:$BJ$68,($R$2-1)*12+8) -> 350166.67 | P44: =INDEX(Monthly!$C$68:$BJ$68,($R$2-1)*12+9) -> 346187.5 | Q44: =INDEX(Monthly!$C$68:$BJ$68,($R$2-1)*12+10) -> 342208.33 | R44: =INDEX(Monthly!$C$68:$BJ$68,($R$2-1)*12+11) -> 338229.17 | S44: =INDEX(Monthly!$C$68:$BJ$68,($R$2-1)*12+12) -> 334250
A45: Total assets | B45: ='Balance Sheet'!B9 -> 461149.51 | C45: ='Balance Sheet'!C9 -> 626676.24 | D45: ='Balance Sheet'!D9 -> 824375.32 | E45: ='Balance Sheet'!E9 -> 1055022.4 | F45: ='Balance Sheet'!F9 -> 1342222.8 | H45: =INDEX(Monthly!$C$105:$BJ$105,($R$2-1)*12+1) -> 719501.25 | I45: =INDEX(Monthly!$C$105:$BJ$105,($R$2-1)*12+2) -> 668365.23 | J45: =INDEX(Monthly!$C$105:$BJ$105,($R$2-1)*12+3) -> 622759.11 | K45: =INDEX(Monthly!$C$105:$BJ$105,($R$2-1)*12+4) -> 582682.89 | L45: =INDEX(Monthly!$C$105:$BJ$105,($R$2-1)*12+5) -> 548136.57 | M45: =INDEX(Monthly!$C$105:$BJ$105,($R$2-1)*12+6) -> 519120.15 | N45: =INDEX(Monthly!$C$105:$BJ$105,($R$2-1)*12+7) -> 495633.63 | O45: =INDEX(Monthly!$C$105:$BJ$105,($R$2-1)*12+8) -> 477677.01 | P45: =INDEX(Monthly!$C$105:$BJ$105,($R$2-1)*12+9) -> 465250.28 | Q45: =INDEX(Monthly!$C$105:$BJ$105,($R$2-1)*12+10) -> 458353.46 | R45: =INDEX(Monthly!$C$105:$BJ$105,($R$2-1)*12+11) -> 456986.54 | S45: =INDEX(Monthly!$C$105:$BJ$105,($R$2-1)*12+12) -> 461149.51
A46: Accounts payable | B46: ='Balance Sheet'!B10 -> 63809.505 | C46: ='Balance Sheet'!C10 -> 68556.934 | D46: ='Balance Sheet'!D10 -> 71740.773 | E46: ='Balance Sheet'!E10 -> 75088.769 | F46: ='Balance Sheet'!F10 -> 78610.028 | H46: =INDEX(Monthly!$C$79:$BJ$79,($R$2-1)*12+1) -> 44898.958 | I46: =INDEX(Monthly!$C$79:$BJ$79,($R$2-1)*12+2) -> 46618.099 | J46: =INDEX(Monthly!$C$79:$BJ$79,($R$2-1)*12+3) -> 48337.24 | K46: =INDEX(Monthly!$C$79:$BJ$79,($R$2-1)*12+4) -> 50056.38 | L46: =INDEX(Monthly!$C$79:$BJ$79,($R$2-1)*12+5) -> 51775.521 | M46: =INDEX(Monthly!$C$79:$BJ$79,($R$2-1)*12+6) -> 53494.661 | N46: =INDEX(Monthly!$C$79:$BJ$79,($R$2-1)*12+7) -> 55213.802 | O46: =INDEX(Monthly!$C$79:$BJ$79,($R$2-1)*12+8) -> 56932.943 | P46: =INDEX(Monthly!$C$79:$BJ$79,($R$2-1)*12+9) -> 58652.083 | Q46: =INDEX(Monthly!$C$79:$BJ$79,($R$2-1)*12+10) -> 60371.224 | R46: =INDEX(Monthly!$C$79:$BJ$79,($R$2-1)*12+11) -> 62090.365 | S46: =INDEX(Monthly!$C$79:$BJ$79,($R$2-1)*12+12) -> 63809.505
A47: Loan | B47: ='Balance Sheet'!B11 -> 217261.9 | C47: ='Balance Sheet'!C11 -> 181547.62 | D47: ='Balance Sheet'!D11 -> 145833.33 | E47: ='Balance Sheet'!E11 -> 110119.05 | F47: ='Balance Sheet'!F11 -> 74404.762 | H47: =INDEX(Monthly!$C$74:$BJ$74,($R$2-1)*12+1) -> 250000 | I47: =INDEX(Monthly!$C$74:$BJ$74,($R$2-1)*12+2) -> 247023.81 | J47: =INDEX(Monthly!$C$74:$BJ$74,($R$2-1)*12+3) -> 244047.62 | K47: =INDEX(Monthly!$C$74:$BJ$74,($R$2-1)*12+4) -> 241071.43 | L47: =INDEX(Monthly!$C$74:$BJ$74,($R$2-1)*12+5) -> 238095.24 | M47: =INDEX(Monthly!$C$74:$BJ$74,($R$2-1)*12+6) -> 235119.05 | N47: =INDEX(Monthly!$C$74:$BJ$74,($R$2-1)*12+7) -> 232142.86 | O47: =INDEX(Monthly!$C$74:$BJ$74,($R$2-1)*12+8) -> 229166.67 | P47: =INDEX(Monthly!$C$74:$BJ$74,($R$2-1)*12+9) -> 226190.48 | Q47: =INDEX(Monthly!$C$74:$BJ$74,($R$2-1)*12+10) -> 223214.29 | R47: =INDEX(Monthly!$C$74:$BJ$74,($R$2-1)*12+11) -> 220238.1 | S47: =INDEX(Monthly!$C$74:$BJ$74,($R$2-1)*12+12) -> 217261.9
A48: Total liabilities | B48: ='Balance Sheet'!B12 -> 281071.41 | C48: ='Balance Sheet'!C12 -> 250104.55 | D48: ='Balance Sheet'!D12 -> 217574.11 | E48: ='Balance Sheet'!E12 -> 185207.82 | F48: ='Balance Sheet'!F12 -> 153014.79 | H48: =INDEX(Monthly!$C$106:$BJ$106,($R$2-1)*12+1) -> 294898.96 | I48: =INDEX(Monthly!$C$106:$BJ$106,($R$2-1)*12+2) -> 293641.91 | J48: =INDEX(Monthly!$C$106:$BJ$106,($R$2-1)*12+3) -> 292384.86 | K48: =INDEX(Monthly!$C$106:$BJ$106,($R$2-1)*12+4) -> 291127.81 | L48: =INDEX(Monthly!$C$106:$BJ$106,($R$2-1)*12+5) -> 289870.76 | M48: =INDEX(Monthly!$C$106:$BJ$106,($R$2-1)*12+6) -> 288613.71 | N48: =INDEX(Monthly!$C$106:$BJ$106,($R$2-1)*12+7) -> 287356.66 | O48: =INDEX(Monthly!$C$106:$BJ$106,($R$2-1)*12+8) -> 286099.61 | P48: =INDEX(Monthly!$C$106:$BJ$106,($R$2-1)*12+9) -> 284842.56 | Q48: =INDEX(Monthly!$C$106:$BJ$106,($R$2-1)*12+10) -> 283585.51 | R48: =INDEX(Monthly!$C$106:$BJ$106,($R$2-1)*12+11) -> 282328.46 | S48: =INDEX(Monthly!$C$106:$BJ$106,($R$2-1)*12+12) -> 281071.41
A49: Paid-in capital | B49: ='Balance Sheet'!B13 -> 480000 | C49: ='Balance Sheet'!C13 -> 480000 | D49: ='Balance Sheet'!D13 -> 480000 | E49: ='Balance Sheet'!E13 -> 480000 | F49: ='Balance Sheet'!F13 -> 480000 | H49: =INDEX(Monthly!$C$103:$BJ$103,($R$2-1)*12+1) -> 480000 | I49: =INDEX(Monthly!$C$103:$BJ$103,($R$2-1)*12+2) -> 480000 | J49: =INDEX(Monthly!$C$103:$BJ$103,($R$2-1)*12+3) -> 480000 | K49: =INDEX(Monthly!$C$103:$BJ$103,($R$2-1)*12+4) -> 480000 | L49: =INDEX(Monthly!$C$103:$BJ$103,($R$2-1)*12+5) -> 480000 | M49: =INDEX(Monthly!$C$103:$BJ$103,($R$2-1)*12+6) -> 480000 | N49: =INDEX(Monthly!$C$103:$BJ$103,($R$2-1)*12+7) -> 480000 | O49: =INDEX(Monthly!$C$103:$BJ$103,($R$2-1)*12+8) -> 480000 | P49: =INDEX(Monthly!$C$103:$BJ$103,($R$2-1)*12+9) -> 480000 | Q49: =INDEX(Monthly!$C$103:$BJ$103,($R$2-1)*12+10) -> 480000 | R49: =INDEX(Monthly!$C$103:$BJ$103,($R$2-1)*12+11) -> 480000 | S49: =INDEX(Monthly!$C$103:$BJ$103,($R$2-1)*12+12) -> 480000
A50: Retained earnings | B50: ='Balance Sheet'!B14 -> -299921.9 | C50: ='Balance Sheet'!C14 -> -103428.31 | D50: ='Balance Sheet'!D14 -> 126801.21 | E50: ='Balance Sheet'!E14 -> 389814.59 | F50: ='Balance Sheet'!F14 -> 709207.99 | H50: =INDEX(Monthly!$C$104:$BJ$104,($R$2-1)*12+1) -> -55397.708 | I50: =INDEX(Monthly!$C$104:$BJ$104,($R$2-1)*12+2) -> -105276.68 | J50: =INDEX(Monthly!$C$104:$BJ$104,($R$2-1)*12+3) -> -149625.75 | K50: =INDEX(Monthly!$C$104:$BJ$104,($R$2-1)*12+4) -> -188444.92 | L50: =INDEX(Monthly!$C$104:$BJ$104,($R$2-1)*12+5) -> -221734.19 | M50: =INDEX(Monthly!$C$104:$BJ$104,($R$2-1)*12+6) -> -249493.56 | N50: =INDEX(Monthly!$C$104:$BJ$104,($R$2-1)*12+7) -> -271723.03 | O50: =INDEX(Monthly!$C$104:$BJ$104,($R$2-1)*12+8) -> -288422.6 | P50: =INDEX(Monthly!$C$104:$BJ$104,($R$2-1)*12+9) -> -299592.28 | Q50: =INDEX(Monthly!$C$104:$BJ$104,($R$2-1)*12+10) -> -305232.05 | R50: =INDEX(Monthly!$C$104:$BJ$104,($R$2-1)*12+11) -> -305341.92 | S50: =INDEX(Monthly!$C$104:$BJ$104,($R$2-1)*12+12) -> -299921.9
A51: Total equity | B51: ='Balance Sheet'!B15 -> 180078.1 | C51: ='Balance Sheet'!C15 -> 376571.69 | D51: ='Balance Sheet'!D15 -> 606801.21 | E51: ='Balance Sheet'!E15 -> 869814.59 | F51: ='Balance Sheet'!F15 -> 1189208 | H51: =INDEX(Monthly!$C$107:$BJ$107,($R$2-1)*12+1) -> 424602.29 | I51: =INDEX(Monthly!$C$107:$BJ$107,($R$2-1)*12+2) -> 374723.32 | J51: =INDEX(Monthly!$C$107:$BJ$107,($R$2-1)*12+3) -> 330374.25 | K51: =INDEX(Monthly!$C$107:$BJ$107,($R$2-1)*12+4) -> 291555.08 | L51: =INDEX(Monthly!$C$107:$BJ$107,($R$2-1)*12+5) -> 258265.81 | M51: =INDEX(Monthly!$C$107:$BJ$107,($R$2-1)*12+6) -> 230506.44 | N51: =INDEX(Monthly!$C$107:$BJ$107,($R$2-1)*12+7) -> 208276.97 | O51: =INDEX(Monthly!$C$107:$BJ$107,($R$2-1)*12+8) -> 191577.4 | P51: =INDEX(Monthly!$C$107:$BJ$107,($R$2-1)*12+9) -> 180407.72 | Q51: =INDEX(Monthly!$C$107:$BJ$107,($R$2-1)*12+10) -> 174767.95 | R51: =INDEX(Monthly!$C$107:$BJ$107,($R$2-1)*12+11) -> 174658.08 | S51: =INDEX(Monthly!$C$107:$BJ$107,($R$2-1)*12+12) -> 180078.1
A52: Total liabilities & equity | B52: ='Balance Sheet'!B16 -> 461149.51 | C52: ='Balance Sheet'!C16 -> 626676.24 | D52: ='Balance Sheet'!D16 -> 824375.32 | E52: ='Balance Sheet'!E16 -> 1055022.4 | F52: ='Balance Sheet'!F16 -> 1342222.8 | H52: =INDEX(Monthly!$C$108:$BJ$108,($R$2-1)*12+1) -> 719501.25 | I52: =INDEX(Monthly!$C$108:$BJ$108,($R$2-1)*12+2) -> 668365.23 | J52: =INDEX(Monthly!$C$108:$BJ$108,($R$2-1)*12+3) -> 622759.11 | K52: =INDEX(Monthly!$C$108:$BJ$108,($R$2-1)*12+4) -> 582682.89 | L52: =INDEX(Monthly!$C$108:$BJ$108,($R$2-1)*12+5) -> 548136.57 | M52: =INDEX(Monthly!$C$108:$BJ$108,($R$2-1)*12+6) -> 519120.15 | N52: =INDEX(Monthly!$C$108:$BJ$108,($R$2-1)*12+7) -> 495633.63 | O52: =INDEX(Monthly!$C$108:$BJ$108,($R$2-1)*12+8) -> 477677.01 | P52: =INDEX(Monthly!$C$108:$BJ$108,($R$2-1)*12+9) -> 465250.28 | Q52: =INDEX(Monthly!$C$108:$BJ$108,($R$2-1)*12+10) -> 458353.46 | R52: =INDEX(Monthly!$C$108:$BJ$108,($R$2-1)*12+11) -> 456986.54 | S52: =INDEX(Monthly!$C$108:$BJ$108,($R$2-1)*12+12) -> 461149.51

Sheet Scenarios
A1: Scenarios — Low / Base / High | H1: =HYPERLINK("#'Cover'!A1","◂ Contents") -> ◂ Contents
A2: All three scenarios calculated side by side, live: change any input and every column updates. Active = the scenario chosen on the Dashboard.
A5: Key drivers
A6: Driver | B6: Low | C6: Base | D6: High | E6: Active
A7: Repair orders per operating day at maturity (year 1) (orders) | B7: =Inputs!$B$7 -> 11 | C7: =Inputs!$C$7 -> 13.5 | D7: =Inputs!$D$7 -> 16 | E7: =Inputs!$E$7 -> 13.5
A8: Effective labor rate per billed hour (year 1) ($) | B8: =Inputs!$B$21 -> 118 | C8: =Inputs!$C$21 -> 125 | D8: =Inputs!$D$21 -> 132 | E8: =Inputs!$E$21 -> 125
A9: Service bays (lifts) (bays) | B9: =Inputs!$B$15 -> 6 | C9: =Inputs!$C$15 -> 6 | D9: =Inputs!$D$15 -> 6 | E9: =Inputs!$E$15 -> 6
A10: Parts gross margin, % of parts sales (%) | B10: =Inputs!$B$27 -> 0.44 | C10: =Inputs!$C$27 -> 0.47 | D10: =Inputs!$D$27 -> 0.5 | E10: =Inputs!$E$27 -> 0.47
A11: Shop rent or land cost per month ($) | B11: =Inputs!$B$36 -> 18000 | C11: =Inputs!$C$36 -> 18000 | D11: =Inputs!$D$36 -> 18000 | E11: =Inputs!$E$36 -> 18000
A12: Lift & bay equipment per bay (month 1) ($) | B12: =Inputs!$B$44 -> 22000 | C12: =Inputs!$C$44 -> 22000 | D12: =Inputs!$D$44 -> 22000 | E12: =Inputs!$E$44 -> 22000
A13: Equity raised at start ($) | B13: =Inputs!$B$67 -> 480000 | C13: =Inputs!$C$67 -> 480000 | D13: =Inputs!$D$67 -> 480000 | E13: =Inputs!$E$67 -> 480000
A15: Results by scenario ($'000)
A16: Output | B16: Low | C16: Base | D16: High | E16: Active
A17: Revenue — final year | B17: =F30 -> 1474694.1 | C17: =F31 -> 2372818.7 | D17: =F32 -> 3288753.2 | E17: ='P&L'!F5 -> 2372818.7
A18: Revenue — whole plan | B18: =SUM(B30:F30) -> 6525711.6 | C18: =SUM(B31:F31) -> 9969204.3 | D18: =SUM(B32:F32) -> 13811972 | E18: =SUM('P&L'!$B$5:$F$5) -> 9969204.3
A19: EBITDA — final year | B19: =F36 -> -217532.97 | C19: =F37 -> 470349.01 | D19: =F38 -> 1158398.3 | E19: ='P&L'!F16 -> 470349.01
A20: EBITDA margin — final year | B20: =IF(B17=0,0,B19/B17) -> -0.14751058 | C20: =IF(C17=0,0,C19/C17) -> 0.19822375 | D20: =IF(D17=0,0,D19/D17) -> 0.35223023 | E20: =IF(E17=0,0,E19/E17) -> 0.19822375
A21: Net income — final year | B21: =F42 -> -283586.54 | C21: =F43 -> 319393.4 | D21: =F44 -> 862952.33 | E21: ='P&L'!F23 -> 319393.4
A22: Net income — whole plan | B22: =SUM(B42:F42) -> -1711891.7 | C22: =SUM(B43:F43) -> 709207.99 | D22: =SUM(B44:F44) -> 3004950.9 | E22: =SUM('P&L'!$B$23:$F$23) -> 709207.99
A23: Cash at the end of the plan | B23: =F48 -> -1323478.8 | C23: =F49 -> 1099044.1 | D23: =F50 -> 3396116.6 | E23: ='Balance Sheet'!F5 -> 1099044.1
A24: Lowest cash balance | B24: =MIN('Scenario calc'!$C$93:$BJ$93) -> -1323478.8 | C24: =MIN('Scenario calc'!$C$215:$BJ$215) -> 83558.366 | D24: =MIN('Scenario calc'!$C$337:$BJ$337) -> 316875.55 | E24: ='Break-even'!B18 -> 83558.366
A25: Lowest cash point (month #) | B25: =MATCH(MIN('Scenario calc'!$C$93:$BJ$93),'Scenario calc'!$C$93:$BJ$93,0) -> 60 | C25: =MATCH(MIN('Scenario calc'!$C$215:$BJ$215),'Scenario calc'!$C$215:$BJ$215,0) -> 10 | D25: =MATCH(MIN('Scenario calc'!$C$337:$BJ$337),'Scenario calc'!$C$337:$BJ$337,0) -> 4 | E25: ='Break-even'!B6 -> 10
A26: Funding required (incl. cash buffer) | B26: =SUMPRODUCT(--('Scenario calc'!$C$6:$BJ$6<=B25),'Scenario calc'!$C$65:$BJ$65)-SUMPRODUCT(--('Scenario calc'!$C$6:$BJ$6<=B25),'Scenario calc'!$C$87:$BJ$87)-SUMPRODUCT(--('Scenario calc'!$C$6:$BJ$6<=B25),'Scenario calc'!$C$75:$BJ$75)+Inputs!$B$82 -> 2231478.8 | C26: =SUMPRODUCT(--('Scenario calc'!$C$128:$BJ$128<=C25),'Scenario calc'!$C$187:$BJ$187)-SUMPRODUCT(--('Scenario calc'!$C$128:$BJ$128<=C25),'Scenario calc'!$C$209:$BJ$209)-SUMPRODUCT(--('Scenario calc'!$C$128:$BJ$128<=C25),'Scenario calc'!$C$197:$BJ$197)+Inputs!$C$82 -> 824441.63 | D26: =SUMPRODUCT(--('Scenario calc'!$C$250:$BJ$250<=D25),'Scenario calc'!$C$309:$BJ$309)-SUMPRODUCT(--('Scenario calc'!$C$250:$BJ$250<=D25),'Scenario calc'!$C$331:$BJ$331)-SUMPRODUCT(--('Scenario calc'!$C$250:$BJ$250<=D25),'Scenario calc'!$C$319:$BJ$319)+Inputs!$D$82 -> 591124.45 | E26: ='Break-even'!B12 -> 824441.63
A28: Revenue by year ($'000)
A29: Scenario | B29: 1 | C29: 2 | D29: 3 | E29: 4 | F29: 5
A30: Low | B30: =SUMIF('Scenario calc'!$C$7:$BJ$7,B$29,'Scenario calc'!$C$30:$BJ$30) -> 766147.8 | C30: =SUMIF('Scenario calc'!$C$7:$BJ$7,C$29,'Scenario calc'!$C$30:$BJ$30) -> 1379139.9 | D30: =SUMIF('Scenario calc'!$C$7:$BJ$7,D$29,'Scenario calc'!$C$30:$BJ$30) -> 1445636.8 | E30: =SUMIF('Scenario calc'!$C$7:$BJ$7,E$29,'Scenario calc'!$C$30:$BJ$30) -> 1460093.1 | F30: =SUMIF('Scenario calc'!$C$7:$BJ$7,F$29,'Scenario calc'!$C$30:$BJ$30) -> 1474694.1
A31: Base | B31: =SUMIF('Scenario calc'!$C$129:$BJ$129,B$29,'Scenario calc'!$C$152:$BJ$152) -> 1264359.4 | C31: =SUMIF('Scenario calc'!$C$129:$BJ$129,C$29,'Scenario calc'!$C$152:$BJ$152) -> 1987198.3 | D31: =SUMIF('Scenario calc'!$C$129:$BJ$129,D$29,'Scenario calc'!$C$152:$BJ$152) -> 2108218.7 | E31: =SUMIF('Scenario calc'!$C$129:$BJ$129,E$29,'Scenario calc'!$C$152:$BJ$152) -> 2236609.2 | F31: =SUMIF('Scenario calc'!$C$129:$BJ$129,F$29,'Scenario calc'!$C$152:$BJ$152) -> 2372818.7
A32: High | B32: =SUMIF('Scenario calc'!$C$251:$BJ$251,B$29,'Scenario calc'!$C$274:$BJ$274) -> 1874160 | C32: =SUMIF('Scenario calc'!$C$251:$BJ$251,C$29,'Scenario calc'!$C$274:$BJ$274) -> 2609777.7 | D32: =SUMIF('Scenario calc'!$C$251:$BJ$251,D$29,'Scenario calc'!$C$274:$BJ$274) -> 2877018.9 | E32: =SUMIF('Scenario calc'!$C$251:$BJ$251,E$29,'Scenario calc'!$C$274:$BJ$274) -> 3162262.7 | F32: =SUMIF('Scenario calc'!$C$251:$BJ$251,F$29,'Scenario calc'!$C$274:$BJ$274) -> 3288753.2
A34: EBITDA by year ($'000)
A35: Scenario | B35: 1 | C35: 2 | D35: 3 | E35: 4 | F35: 5
A36: Low | B36: =SUMIF('Scenario calc'!$C$7:$BJ$7,B$35,'Scenario calc'!$C$48:$BJ$48) -> -599131.83 | C36: =SUMIF('Scenario calc'!$C$7:$BJ$7,C$35,'Scenario calc'!$C$48:$BJ$48) -> -193996.8 | D36: =SUMIF('Scenario calc'!$C$7:$BJ$7,D$35,'Scenario calc'!$C$48:$BJ$48) -> -171788.17 | E36: =SUMIF('Scenario calc'!$C$7:$BJ$7,E$35,'Scenario calc'!$C$48:$BJ$48) -> -192042.36 | F36: =SUMIF('Scenario calc'!$C$7:$BJ$7,F$35,'Scenario calc'!$C$48:$BJ$48) -> -217532.97
A37: Base | B37: =SUMIF('Scenario calc'!$C$129:$BJ$129,B$35,'Scenario calc'!$C$170:$BJ$170) -> -231022.34 | C37: =SUMIF('Scenario calc'!$C$129:$BJ$129,C$35,'Scenario calc'!$C$170:$BJ$170) -> 264690.01 | D37: =SUMIF('Scenario calc'!$C$129:$BJ$129,D$35,'Scenario calc'!$C$170:$BJ$170) -> 331418.32 | E37: =SUMIF('Scenario calc'!$C$129:$BJ$129,E$35,'Scenario calc'!$C$170:$BJ$170) -> 399696.18 | F37: =SUMIF('Scenario calc'!$C$129:$BJ$129,F$35,'Scenario calc'!$C$170:$BJ$170) -> 470349.01
A38: High | B38: =SUMIF('Scenario calc'!$C$251:$BJ$251,B$35,'Scenario calc'!$C$292:$BJ$292) -> 232857.52 | C38: =SUMIF('Scenario calc'!$C$251:$BJ$251,C$35,'Scenario calc'!$C$292:$BJ$292) -> 743169.36 | D38: =SUMIF('Scenario calc'!$C$251:$BJ$251,D$35,'Scenario calc'!$C$292:$BJ$292) -> 912841.9 | E38: =SUMIF('Scenario calc'!$C$251:$BJ$251,E$35,'Scenario calc'!$C$292:$BJ$292) -> 1093867.8 | F38: =SUMIF('Scenario calc'!$C$251:$BJ$251,F$35,'Scenario calc'!$C$292:$BJ$292) -> 1158398.3
A40: Net income by year ($'000)
A41: Scenario | B41: 1 | C41: 2 | D41: 3 | E41: 4 | F41: 5
A42: Low | B42: =SUMIF('Scenario calc'!$C$7:$BJ$7,B$41,'Scenario calc'!$C$57:$BJ$57) -> -668031.38 | C42: =SUMIF('Scenario calc'!$C$7:$BJ$7,C$41,'Scenario calc'!$C$57:$BJ$57) -> -262193.23 | D42: =SUMIF('Scenario calc'!$C$7:$BJ$7,D$41,'Scenario calc'!$C$57:$BJ$57) -> -239270.32 | E42: =SUMIF('Scenario calc'!$C$7:$BJ$7,E$41,'Scenario calc'!$C$57:$BJ$57) -> -258810.22 | F42: =SUMIF('Scenario calc'!$C$7:$BJ$7,F$41,'Scenario calc'!$C$57:$BJ$57) -> -283586.54
A43: Base | B43: =SUMIF('Scenario calc'!$C$129:$BJ$129,B$41,'Scenario calc'!$C$179:$BJ$179) -> -299921.9 | C43: =SUMIF('Scenario calc'!$C$129:$BJ$129,C$41,'Scenario calc'!$C$179:$BJ$179) -> 196493.58 | D43: =SUMIF('Scenario calc'!$C$129:$BJ$129,D$41,'Scenario calc'!$C$179:$BJ$179) -> 230229.53 | E43: =SUMIF('Scenario calc'!$C$129:$BJ$129,E$41,'Scenario calc'!$C$179:$BJ$179) -> 263013.37 | F43: =SUMIF('Scenario calc'!$C$129:$BJ$129,F$41,'Scenario calc'!$C$179:$BJ$179) -> 319393.4
A44: High | B44: =SUMIF('Scenario calc'!$C$251:$BJ$251,B$41,'Scenario calc'!$C$301:$BJ$301) -> 129526.79 | C44: =SUMIF('Scenario calc'!$C$251:$BJ$251,C$41,'Scenario calc'!$C$301:$BJ$301) -> 533228.62 | D44: =SUMIF('Scenario calc'!$C$251:$BJ$251,D$41,'Scenario calc'!$C$301:$BJ$301) -> 667834.21 | E44: =SUMIF('Scenario calc'!$C$251:$BJ$251,E$41,'Scenario calc'!$C$301:$BJ$301) -> 811408.92 | F44: =SUMIF('Scenario calc'!$C$251:$BJ$251,F$41,'Scenario calc'!$C$301:$BJ$301) -> 862952.33
A46: Cash at year end by year ($'000)
A47: Scenario | B47: 1 | C47: 2 | D47: 3 | E47: 4 | F47: 5
A48: Low | B48: =INDEX('Scenario calc'!$C$93:$BJ$93,B$47*12) -> -278223.44 | C48: =INDEX('Scenario calc'!$C$93:$BJ$93,C$47*12) -> -543389.16 | D48: =INDEX('Scenario calc'!$C$93:$BJ$93,D$47*12) -> -784670.1 | E48: =INDEX('Scenario calc'!$C$93:$BJ$93,E$47*12) -> -1042955 | F48: =INDEX('Scenario calc'!$C$93:$BJ$93,F$47*12) -> -1323478.8
A49: Base | B49: =INDEX('Scenario calc'!$C$215:$BJ$215,B$47*12) -> 91651.565 | C49: =INDEX('Scenario calc'!$C$215:$BJ$215,C$47*12) -> 284178.03 | D49: =INDEX('Scenario calc'!$C$215:$BJ$215,D$47*12) -> 512599.78 | E49: =INDEX('Scenario calc'!$C$215:$BJ$215,E$47*12) -> 776355.59 | F49: =INDEX('Scenario calc'!$C$215:$BJ$215,F$47*12) -> 1099044.1
A50: High | B50: =INDEX('Scenario calc'!$C$337:$BJ$337,B$47*12) -> 521761.06 | C50: =INDEX('Scenario calc'!$C$337:$BJ$337,C$47*12) -> 1050984.4 | D50: =INDEX('Scenario calc'!$C$337:$BJ$337,D$47*12) -> 1717416.7 | E50: =INDEX('Scenario calc'!$C$337:$BJ$337,E$47*12) -> 2530004.5 | F50: =INDEX('Scenario calc'!$C$337:$BJ$337,F$47*12) -> 3396116.6

Sheet Break-even
A1: Startup costs, funding need and break-even | H1: =HYPERLINK("#'Cover'!A1","◂ Contents") -> ◂ Contents
A2: Live for the selected scenario. Periods are counted in months from the start of the plan.
A3: Scenario shown | B3: =CHOOSE(Dashboard!$B$4,"Low","Base","High") -> Base
A5: Startup costs & funding need (up to the lowest cash point)
A6: Lowest cash point (month #) | B6: =MATCH(MIN(Monthly!$C$91:$BJ$91),Monthly!$C$91:$BJ$91,0) -> 10
A7: Capital spending up to the lowest cash point | B7: =SUMPRODUCT(--(Monthly!$C$4:$BJ$4<=$B$6),Monthly!$C$63:$BJ$63) -> 382000
A8: Operating cash burn up to the lowest cash point | B8: =-SUMPRODUCT(--(Monthly!$C$4:$BJ$4<=$B$6),Monthly!$C$85:$BJ$85) -> 237655.92 | D8: Losses and working capital before the business funds itself
A9: Loan repayments up to the lowest cash point | B9: =-SUMPRODUCT(--(Monthly!$C$4:$BJ$4<=$B$6),Monthly!$C$73:$BJ$73) -> 26785.714
A10: Total uses of funds | B10: =B7+B8+B9 -> 646441.63
A11: Minimum cash buffer to keep | B11: =Inputs!$E$82 -> 178000 | D11: Input on the Inputs sheet
A12: Funding required (uses + buffer) | B12: =B10+B11 -> 824441.63
A14: Equity raised | B14: =Inputs!$E$67 -> 480000
A15: Loan drawn | B15: =Inputs!$E$68 -> 250000
A16: Total sources of funds | B16: =B14+B15 -> 730000
A17: Funding surplus / (shortfall) | B17: =B16-B12 -> -94441.634 | D17: Negative = raise at least this much more
A18: Lowest cash balance in the plan | B18: =MIN(Monthly!$C$91:$BJ$91) -> 83558.366 | D18: Equals sources minus uses
A20: Break-even timing
A21: First month with positive EBITDA (month #) | B21: =IFERROR(MATCH(1,Monthly!$C$92:$BJ$92,0),"Not within horizon") -> 10
A22: First month with positive net income (month #) | B22: =IFERROR(MATCH(1,Monthly!$C$95:$BJ$95,0),"Not within horizon") -> 12
A23: Cash invested paid back (month #) | B23: =IF(MIN(Monthly!$C$97:$BJ$97)>=0,"No investment to pay back",IFERROR(MATCH(1,Monthly!$C$99:$BJ$99,0),"Not within horizon")) -> 41 | D23: Cumulative operating + investing cash flow back to zero
A25: Annual break-even revenue
A26: Year # | B26: 1 | C26: 2 | D26: 3 | E26: 4 | F26: 5
B27: Year 1 | C27: Year 2 | D27: Year 3 | E27: Year 4 | F27: Year 5
A28: Revenue | B28: =SUMIF(Monthly!$C$5:$BJ$5,B$26,Monthly!$C$28:$BJ$28) -> 1264359.4 | C28: =SUMIF(Monthly!$C$5:$BJ$5,C$26,Monthly!$C$28:$BJ$28) -> 1987198.3 | D28: =SUMIF(Monthly!$C$5:$BJ$5,D$26,Monthly!$C$28:$BJ$28) -> 2108218.7 | E28: =SUMIF(Monthly!$C$5:$BJ$5,E$26,Monthly!$C$28:$BJ$28) -> 2236609.2 | F28: =SUMIF(Monthly!$C$5:$BJ$5,F$26,Monthly!$C$28:$BJ$28) -> 2372818.7
A29: Gross profit | B29: =SUMIF(Monthly!$C$5:$BJ$5,B$26,Monthly!$C$36:$BJ$36) -> 481658.44 | C29: =SUMIF(Monthly!$C$5:$BJ$5,C$26,Monthly!$C$36:$BJ$36) -> 999978.46 | D29: =SUMIF(Monthly!$C$5:$BJ$5,D$26,Monthly!$C$36:$BJ$36) -> 1075151.6 | E29: =SUMIF(Monthly!$C$5:$BJ$5,E$26,Monthly!$C$36:$BJ$36) -> 1155330.9 | F29: =SUMIF(Monthly!$C$5:$BJ$5,F$26,Monthly!$C$36:$BJ$36) -> 1240834.3
A30: Gross margin (contribution) | B30: =IF(B28=0,0,B29/B28) -> 0.38095058 | C30: =IF(C28=0,0,C29/C28) -> 0.5032102 | D30: =IF(D28=0,0,D29/D28) -> 0.50998104 | E30: =IF(E28=0,0,E29/E28) -> 0.51655467 | F30: =IF(F28=0,0,F29/F28) -> 0.52293683
A31: Operating expenses (treated as fixed) | B31: =-SUMIF(Monthly!$C$5:$BJ$5,B$26,Monthly!$C$45:$BJ$45) -> 712680.78 | C31: =-SUMIF(Monthly!$C$5:$BJ$5,C$26,Monthly!$C$45:$BJ$45) -> 735288.45 | D31: =-SUMIF(Monthly!$C$5:$BJ$5,D$26,Monthly!$C$45:$BJ$45) -> 743733.24 | E31: =-SUMIF(Monthly!$C$5:$BJ$5,E$26,Monthly!$C$45:$BJ$45) -> 755634.75 | F31: =-SUMIF(Monthly!$C$5:$BJ$5,F$26,Monthly!$C$45:$BJ$45) -> 770485.29
A32: Break-even revenue (EBITDA = 0) | B32: =IF(B30>0,B31/B30,"n/a") -> 1870795.9 | C32: =IF(C30>0,C31/C30,"n/a") -> 1461195.4 | D32: =IF(D30>0,D31/D30,"n/a") -> 1458354.7 | E32: =IF(E30>0,E31/E30,"n/a") -> 1462836 | F32: =IF(F30>0,F31/F30,"n/a") -> 1473381.2
A33: Margin of safety (revenue above break-even) | B33: =IF(AND(ISNUMBER(B32),B28>0),(B28-B32)/B28,"n/a") -> -0.47963936 | C33: =IF(AND(ISNUMBER(C32),C28>0),(C28-C32)/C28,"n/a") -> 0.26469571 | D33: =IF(AND(ISNUMBER(D32),D28>0),(D28-D32)/D28,"n/a") -> 0.30825266 | E33: =IF(AND(ISNUMBER(E32),E28>0),(E28-E32)/E28,"n/a") -> 0.34595817 | F33: =IF(AND(ISNUMBER(F32),F28>0),(F28-F32)/F28,"n/a") -> 0.37905868
A35: Simplification: cost of sales is treated as variable and operating expenses as fixed, so break-even revenue = operating expenses ÷ gross margin.

Sheet Valuation
A1: Discounted cash flow valuation | H1: =HYPERLINK("#'Cover'!A1","◂ Contents") -> ◂ Contents
A2: Enterprise value at the start of the plan, before the funding raised in period 1. Year-end discounting.
A3: Scenario shown | B3: =CHOOSE(Dashboard!$B$4,"Low","Base","High") -> Base
A5: Assumptions (active scenario, from the Inputs sheet)
A6: Discount rate (WACC) | B6: =Inputs!$E$85 -> 0.25
A7: Terminal growth rate | B7: =Inputs!$E$86 -> 0.02
A8: Exit multiple (EV ÷ final-year EBITDA) | B8: =Inputs!$E$87 -> 4
A9: Tax rate (for the interest tax shield) | B9: =Inputs!$E$79 -> 0.21
A10: Sensitivity step: WACC | B10: =Inputs!$E$88 -> 0.01
A11: Sensitivity step: terminal growth | B11: =Inputs!$E$89 -> 0.005
A13: Free cash flow by year
A14: Year # | B14: 1 | C14: 2 | D14: 3 | E14: 4 | F14: 5
B15: Year 1 | C15: Year 2 | D15: Year 3 | E15: Year 4 | F15: Year 5
A16: EBITDA | B16: =SUMIF(Monthly!$C$5:$BJ$5,B$14,Monthly!$C$46:$BJ$46) -> -231022.34 | C16: =SUMIF(Monthly!$C$5:$BJ$5,C$14,Monthly!$C$46:$BJ$46) -> 264690.01 | D16: =SUMIF(Monthly!$C$5:$BJ$5,D$14,Monthly!$C$46:$BJ$46) -> 331418.32 | E16: =SUMIF(Monthly!$C$5:$BJ$5,E$14,Monthly!$C$46:$BJ$46) -> 399696.18 | F16: =SUMIF(Monthly!$C$5:$BJ$5,F$14,Monthly!$C$46:$BJ$46) -> 470349.01
A17: Unlevered free cash flow | B17: =SUMIF(Monthly!$C$5:$BJ$5,B$14,Monthly!$C$100:$BJ$100) -> -588902.19 | C17: =SUMIF(Monthly!$C$5:$BJ$5,C$14,Monthly!$C$100:$BJ$100) -> 242418.43 | D17: =SUMIF(Monthly!$C$5:$BJ$5,D$14,Monthly!$C$100:$BJ$100) -> 275774.43 | E17: =SUMIF(Monthly!$C$5:$BJ$5,E$14,Monthly!$C$100:$BJ$100) -> 308569.2 | F17: =SUMIF(Monthly!$C$5:$BJ$5,F$14,Monthly!$C$100:$BJ$100) -> 364962.6
A18: Discount factor | B18: =1/(1+Inputs!$E$85)^B$14 -> 0.8 | C18: =1/(1+Inputs!$E$85)^C$14 -> 0.64 | D18: =1/(1+Inputs!$E$85)^D$14 -> 0.512 | E18: =1/(1+Inputs!$E$85)^E$14 -> 0.4096 | F18: =1/(1+Inputs!$E$85)^F$14 -> 0.32768
A19: Present value of free cash flow | B19: =B17*B18 -> -471121.75 | C19: =C17*C18 -> 155147.8 | D19: =D17*D18 -> 141196.51 | E19: =E17*E18 -> 126389.94 | F19: =F17*F18 -> 119590.94
A21: Enterprise value
B22: Perpetual growth | C22: Exit multiple
A23: Present value of the plan's free cash flows | B23: =SUM($B$19:$F$19) -> 71203.439 | C23: =B23 -> 71203.439
A24: Final-year free cash flow | final-year EBITDA | B24: =$F$17 -> 364962.6 | C24: =$F$16 -> 470349.01
A25: Terminal value at the end of year 5 | B25: =IF($B$6>$B$7,B24*(1+$B$7)/($B$6-$B$7),0) -> 1618529.8 | C25: =C24*$B$8 -> 1881396.1
A26: Present value of the terminal value | B26: =B25/(1+$B$6)^$F$14 -> 530359.84 | C26: =C25/(1+$B$6)^$F$14 -> 616495.86
A27: Enterprise value | B27: =B23+B26 -> 601563.28 | C27: =C23+C26 -> 687699.3
A28: Terminal value share of enterprise value | B28: =IF(B27<>0,B26/B27,0) -> 0.881636 | C28: =IF(C27<>0,C26/C27,0) -> 0.89646138
A29: Cross-check: implied exit multiple | implied perpetual growth | B29: =IF(C24>0,B25/C24,"n/a") -> 3.4411251 | C29: =IF(C25+B24<>0,(C25*$B$6-B24)/(C25+B24),"n/a") -> 0.046914332
A30: Enterprise value — average of the two methods | B30: =AVERAGE(B27,C27) -> 644631.29
A32: Sensitivity: enterprise value (perpetual growth) by WACC and terminal growth
A33: WACC ↓ · terminal growth → | B33: =$B$7+(-2)*$B$11 -> 0.01 | C33: =$B$7+(-1)*$B$11 -> 0.015 | D33: =$B$7+(0)*$B$11 -> 0.02 | E33: =$B$7+(1)*$B$11 -> 0.025 | F33: =$B$7+(2)*$B$11 -> 0.03
A34: =$B$6+(-2)*$B$10 -> 0.23 | B34: =IF($A34>B$33,SUMPRODUCT($B$17:$F$17/(1+$A34)^$B$14:$F$14)+$F$17*(1+B$33)/($A34-B$33)/(1+$A34)^$F$14,"n/a") -> 689240.24 | C34: =IF($A34>C$33,SUMPRODUCT($B$17:$F$17/(1+$A34)^$B$14:$F$14)+$F$17*(1+C$33)/($A34-C$33)/(1+$A34)^$F$14,"n/a") -> 706095.55 | D34: =IF($A34>D$33,SUMPRODUCT($B$17:$F$17/(1+$A34)^$B$14:$F$14)+$F$17*(1+D$33)/($A34-D$33)/(1+$A34)^$F$14,"n/a") -> 723753.5 | E34: =IF($A34>E$33,SUMPRODUCT($B$17:$F$17/(1+$A34)^$B$14:$F$14)+$F$17*(1+E$33)/($A34-E$33)/(1+$A34)^$F$14,"n/a") -> 742272.81 | F34: =IF($A34>F$33,SUMPRODUCT($B$17:$F$17/(1+$A34)^$B$14:$F$14)+$F$17*(1+F$33)/($A34-F$33)/(1+$A34)^$F$14,"n/a") -> 761718.08
A35: =$B$6+(-1)*$B$10 -> 0.24 | B35: =IF($A35>B$33,SUMPRODUCT($B$17:$F$17/(1+$A35)^$B$14:$F$14)+$F$17*(1+B$33)/($A35-B$33)/(1+$A35)^$F$14,"n/a") -> 629067.87 | C35: =IF($A35>C$33,SUMPRODUCT($B$17:$F$17/(1+$A35)^$B$14:$F$14)+$F$17*(1+C$33)/($A35-C$33)/(1+$A35)^$F$14,"n/a") -> 643982.81 | D35: =IF($A35>D$33,SUMPRODUCT($B$17:$F$17/(1+$A35)^$B$14:$F$14)+$F$17*(1+D$33)/($A35-D$33)/(1+$A35)^$F$14,"n/a") -> 659575.69 | E35: =IF($A35>E$33,SUMPRODUCT($B$17:$F$17/(1+$A35)^$B$14:$F$14)+$F$17*(1+E$33)/($A35-E$33)/(1+$A35)^$F$14,"n/a") -> 675893.82 | F35: =IF($A35>F$33,SUMPRODUCT($B$17:$F$17/(1+$A35)^$B$14:$F$14)+$F$17*(1+F$33)/($A35-F$33)/(1+$A35)^$F$14,"n/a") -> 692989.01
A36: =$B$6+(0)*$B$10 -> 0.25 | B36: =IF($A36>B$33,SUMPRODUCT($B$17:$F$17/(1+$A36)^$B$14:$F$14)+$F$17*(1+B$33)/($A36-B$33)/(1+$A36)^$F$14,"n/a") -> 574482 | C36: =IF($A36>C$33,SUMPRODUCT($B$17:$F$17/(1+$A36)^$B$14:$F$14)+$F$17*(1+C$33)/($A36-C$33)/(1+$A36)^$F$14,"n/a") -> 587734.54 | D36: =IF($A36>D$33,SUMPRODUCT($B$17:$F$17/(1+$A36)^$B$14:$F$14)+$F$17*(1+D$33)/($A36-D$33)/(1+$A36)^$F$14,"n/a") -> 601563.28 | E36: =IF($A36>E$33,SUMPRODUCT($B$17:$F$17/(1+$A36)^$B$14:$F$14)+$F$17*(1+E$33)/($A36-E$33)/(1+$A36)^$F$14,"n/a") -> 616006.63 | F36: =IF($A36>F$33,SUMPRODUCT($B$17:$F$17/(1+$A36)^$B$14:$F$14)+$F$17*(1+F$33)/($A36-F$33)/(1+$A36)^$F$14,"n/a") -> 631106.5
A37: =$B$6+(1)*$B$10 -> 0.26 | B37: =IF($A37>B$33,SUMPRODUCT($B$17:$F$17/(1+$A37)^$B$14:$F$14)+$F$17*(1+B$33)/($A37-B$33)/(1+$A37)^$F$14,"n/a") -> 524795.41 | C37: =IF($A37>C$33,SUMPRODUCT($B$17:$F$17/(1+$A37)^$B$14:$F$14)+$F$17*(1+C$33)/($A37-C$33)/(1+$A37)^$F$14,"n/a") -> 536615.76 | D37: =IF($A37>D$33,SUMPRODUCT($B$17:$F$17/(1+$A37)^$B$14:$F$14)+$F$17*(1+D$33)/($A37-D$33)/(1+$A37)^$F$14,"n/a") -> 548928.61 | E37: =IF($A37>E$33,SUMPRODUCT($B$17:$F$17/(1+$A37)^$B$14:$F$14)+$F$17*(1+E$33)/($A37-E$33)/(1+$A37)^$F$14,"n/a") -> 561765.42 | F37: =IF($A37>F$33,SUMPRODUCT($B$17:$F$17/(1+$A37)^$B$14:$F$14)+$F$17*(1+F$33)/($A37-F$33)/(1+$A37)^$F$14,"n/a") -> 575160.35
A38: =$B$6+(2)*$B$10 -> 0.27 | B38: =IF($A38>B$33,SUMPRODUCT($B$17:$F$17/(1+$A38)^$B$14:$F$14)+$F$17*(1+B$33)/($A38-B$33)/(1+$A38)^$F$14,"n/a") -> 479427.32 | C38: =IF($A38>C$33,SUMPRODUCT($B$17:$F$17/(1+$A38)^$B$14:$F$14)+$F$17*(1+C$33)/($A38-C$33)/(1+$A38)^$F$14,"n/a") -> 490007.42 | D38: =IF($A38>D$33,SUMPRODUCT($B$17:$F$17/(1+$A38)^$B$14:$F$14)+$F$17*(1+D$33)/($A38-D$33)/(1+$A38)^$F$14,"n/a") -> 501010.73 | E38: =IF($A38>E$33,SUMPRODUCT($B$17:$F$17/(1+$A38)^$B$14:$F$14)+$F$17*(1+E$33)/($A38-E$33)/(1+$A38)^$F$14,"n/a") -> 512463.15 | F38: =IF($A38>F$33,SUMPRODUCT($B$17:$F$17/(1+$A38)^$B$14:$F$14)+$F$17*(1+F$33)/($A38-F$33)/(1+$A38)^$F$14,"n/a") -> 524392.76
A40: Free cash flow = operating cash flow + interest × (1 − tax rate) − capital spending. Cells marked n/a: WACC not above growth.

Sheet Sources & Uses
A1: Sources and uses of funds | E1: =HYPERLINK("#'Cover'!A1","◂ Contents") -> ◂ Contents
A2: Live for the selected scenario. Where the money comes from and where it goes in the period set below.
A3: Scenario shown | B3: =CHOOSE(Dashboard!$B$4,"Low","Base","High") -> Base
A5: Funding structure ($'000) — raised at the start of the plan
B6: Amount | C6: Share
A7: Equity | B7: =Inputs!$E$67 -> 480000 | C7: =IF($B$9=0,0,B7/$B$9) -> 0.65753425
A8: Debt (loan) | B8: =Inputs!$E$68 -> 250000 | C8: =IF($B$9=0,0,B8/$B$9) -> 0.34246575
A9: Total funding | B9: =B7+B8 -> 730000 | C9: =IF(B9=0,0,1) -> 1
A10: Gearing (debt ÷ equity) | B10: =IF(B7<=0,IF(B8>0,"n/a",0),B8/B7) -> 0.52083333 | D10: n/a: debt without positive equity
A11: Funding required by the plan (Break-even sheet) | B11: ='Break-even'!B12 -> 824441.63
A12: Funding surplus / (shortfall) | B12: ='Break-even'!B17 -> -94441.634
A14: ="Sources and uses of cash in the first "&$B$16&IF($B$16=1," month"," months")&" ($'000)" -> Sources and uses of cash in the first 12 months ($'000)
A15: Period covered (months from the start) | B15: 12 | D15: 1 to 60 (capped)
A16: Months used | B16: =MIN(60,MAX(1,ROUND(B15,0))) -> 12
A17: Sources | B17: Amount | C17: Share
A18: Equity raised | B18: =SUMPRODUCT(--(Monthly!$C$4:$BJ$4<=$B$16),Monthly!$C$87:$BJ$87) -> 480000 | C18: =IF($B$21=0,0,B18/$B$21) -> 0.65753425
A19: Loan drawdowns | B19: =SUMPRODUCT(--(Monthly!$C$4:$BJ$4<=$B$16),Monthly!$C$72:$BJ$72) -> 250000 | C19: =IF($B$21=0,0,B19/$B$21) -> 0.34246575
A20: Cash generated by operations | B20: =MAX(0,SUMPRODUCT(--(Monthly!$C$4:$BJ$4<=$B$16),Monthly!$C$85:$BJ$85)) -> 0 | C20: =IF($B$21=0,0,B20/$B$21) -> 0
A21: Total sources | B21: =SUM(B18:B20) -> 730000 | C21: =IF(B21=0,0,1) -> 1
A23: Uses | B23: Amount | C23: Share
A24: Cash used by operations | B24: =MAX(0,-SUMPRODUCT(--(Monthly!$C$4:$BJ$4<=$B$16),Monthly!$C$85:$BJ$85)) -> 223610.34 | C24: =IF($B$28=0,0,B24/$B$28) -> 0.30631553
A25: Capital spending | B25: =-SUMPRODUCT(--(Monthly!$C$4:$BJ$4<=$B$16),Monthly!$C$86:$BJ$86) -> 382000 | C25: =IF($B$28=0,0,B25/$B$28) -> 0.52328767
A26: Loan repayments | B26: =-SUMPRODUCT(--(Monthly!$C$4:$BJ$4<=$B$16),Monthly!$C$73:$BJ$73) -> 32738.095 | C26: =IF($B$28=0,0,B26/$B$28) -> 0.044846706
A27: Cash at the end of the period | B27: =INDEX(Monthly!$C$91:$BJ$91,$B$16) -> 91651.565 | C27: =IF($B$28=0,0,B27/$B$28) -> 0.12555009
A28: Total uses | B28: =SUM(B24:B27) -> 730000 | C28: =IF(B28=0,0,1) -> 1
A29: Sources − uses (must be 0; opening cash is 0) | B29: =B21-B28 -> 0

Sheet KPIs
A1: KPIs & ratios | I1: =HYPERLINK("#'Cover'!A1","◂ Contents") -> ◂ Contents
A2: Auto repair shop financial model (planning) — industry metrics and financial ratios for the active scenario
A4: Financial ratios
B5: 1 | C5: 2 | D5: 3 | E5: 4 | F5: 5 | G5: Target
A6: Revenue growth | B6: =IF(N('P&L'!A5)<=0,"n/a",'P&L'!B5/'P&L'!A5-1) -> n/a | C6: =IF(N('P&L'!B5)<=0,"n/a",'P&L'!C5/'P&L'!B5-1) -> 0.5717037 | D6: =IF(N('P&L'!C5)<=0,"n/a",'P&L'!D5/'P&L'!C5-1) -> 0.0609 | E6: =IF(N('P&L'!D5)<=0,"n/a",'P&L'!E5/'P&L'!D5-1) -> 0.0609 | F6: =IF(N('P&L'!E5)<=0,"n/a",'P&L'!F5/'P&L'!E5-1) -> 0.0609
A7: Gross margin | B7: =IF('P&L'!B5<=0,"n/a",'P&L'!B7/'P&L'!B5) -> 0.38095058 | C7: =IF('P&L'!C5<=0,"n/a",'P&L'!C7/'P&L'!C5) -> 0.5032102 | D7: =IF('P&L'!D5<=0,"n/a",'P&L'!D7/'P&L'!D5) -> 0.50998104 | E7: =IF('P&L'!E5<=0,"n/a",'P&L'!E7/'P&L'!E5) -> 0.51655467 | F7: =IF('P&L'!F5<=0,"n/a",'P&L'!F7/'P&L'!F5) -> 0.52293683
A8: EBITDA margin | B8: =IF('P&L'!B5<=0,"n/a",'P&L'!B16/'P&L'!B5) -> -0.18271889 | C8: =IF('P&L'!C5<=0,"n/a",'P&L'!C16/'P&L'!C5) -> 0.13319758 | D8: =IF('P&L'!D5<=0,"n/a",'P&L'!D16/'P&L'!D5) -> 0.15720301 | E8: =IF('P&L'!E5<=0,"n/a",'P&L'!E16/'P&L'!E5) -> 0.17870631 | F8: =IF('P&L'!F5<=0,"n/a",'P&L'!F16/'P&L'!F5) -> 0.19822375
A9: Net margin | B9: =IF('P&L'!B5<=0,"n/a",'P&L'!B23/'P&L'!B5) -> -0.23721254 | C9: =IF('P&L'!C5<=0,"n/a",'P&L'!C23/'P&L'!C5) -> 0.098879705 | D9: =IF('P&L'!D5<=0,"n/a",'P&L'!D23/'P&L'!D5) -> 0.10920571 | E9: =IF('P&L'!E5<=0,"n/a",'P&L'!E23/'P&L'!E5) -> 0.11759469 | F9: =IF('P&L'!F5<=0,"n/a",'P&L'!F23/'P&L'!F5) -> 0.13460506
A10: Payroll, % of revenue | B10: =IF('P&L'!B5<=0,"n/a",-SUMIF(Headcount!$C$5:$BJ$5,B$5,Headcount!$C$17:$BJ$17)/'P&L'!B5) -> 0.52299213 | C10: =IF('P&L'!C5<=0,"n/a",-SUMIF(Headcount!$C$5:$BJ$5,C$5,Headcount!$C$17:$BJ$17)/'P&L'!C5) -> 0.34273756 | D10: =IF('P&L'!D5<=0,"n/a",-SUMIF(Headcount!$C$5:$BJ$5,D$5,Headcount!$C$17:$BJ$17)/'P&L'!D5) -> 0.33275491 | E10: =IF('P&L'!E5<=0,"n/a",-SUMIF(Headcount!$C$5:$BJ$5,E$5,Headcount!$C$17:$BJ$17)/'P&L'!E5) -> 0.32306302 | F10: =IF('P&L'!F5<=0,"n/a",-SUMIF(Headcount!$C$5:$BJ$5,F$5,Headcount!$C$17:$BJ$17)/'P&L'!F5) -> 0.31365342
A11: Marketing, % of revenue | B11: =IF('P&L'!B5<=0,"n/a",-'P&L'!B13/'P&L'!B5) -> 0.066436807 | C11: =IF('P&L'!C5<=0,"n/a",-'P&L'!C13/'P&L'!C5) -> 0.033816454 | D11: =IF('P&L'!D5<=0,"n/a",-'P&L'!D13/'P&L'!D5) -> 0.025500201 | E11: =IF('P&L'!E5<=0,"n/a",-'P&L'!E13/'P&L'!E5) -> 0.019229108 | F11: =IF('P&L'!F5<=0,"n/a",-'P&L'!F13/'P&L'!F5) -> 0.014500223
A12: Operating expenses, % of revenue | B12: =IF('P&L'!B5<=0,"n/a",-'P&L'!B15/'P&L'!B5) -> 0.56366947 | C12: =IF('P&L'!C5<=0,"n/a",-'P&L'!C15/'P&L'!C5) -> 0.37001262 | D12: =IF('P&L'!D5<=0,"n/a",-'P&L'!D15/'P&L'!D5) -> 0.35277803 | E12: =IF('P&L'!E5<=0,"n/a",-'P&L'!E15/'P&L'!E5) -> 0.33784836 | F12: =IF('P&L'!F5<=0,"n/a",-'P&L'!F15/'P&L'!F5) -> 0.32471309
A13: Current ratio (current assets ÷ current liabilities) | B13: =IF(('Balance Sheet'!B12-'Balance Sheet'!B11)<=0,"n/a",('Balance Sheet'!B5+'Balance Sheet'!B6+'Balance Sheet'!B7)/('Balance Sheet'!B12-'Balance Sheet'!B11)) -> 1.9887243 | C13: =IF(('Balance Sheet'!C12-'Balance Sheet'!C11)<=0,"n/a",('Balance Sheet'!C5+'Balance Sheet'!C6+'Balance Sheet'!C7)/('Balance Sheet'!C12-'Balance Sheet'!C11)) -> 4.70669 | D13: =IF(('Balance Sheet'!D12-'Balance Sheet'!D11)<=0,"n/a",('Balance Sheet'!D5+'Balance Sheet'!D6+'Balance Sheet'!D7)/('Balance Sheet'!D12-'Balance Sheet'!D11)) -> 7.7100552 | E13: =IF(('Balance Sheet'!E12-'Balance Sheet'!E11)<=0,"n/a",('Balance Sheet'!E5+'Balance Sheet'!E6+'Balance Sheet'!E7)/('Balance Sheet'!E12-'Balance Sheet'!E11)) -> 10.907389 | F13: =IF(('Balance Sheet'!F12-'Balance Sheet'!F11)<=0,"n/a",('Balance Sheet'!F5+'Balance Sheet'!F6+'Balance Sheet'!F7)/('Balance Sheet'!F12-'Balance Sheet'!F11)) -> 14.552504
A14: Debt ÷ equity (loan ÷ total equity) | B14: =IF('Balance Sheet'!B15<=0,"n/a",'Balance Sheet'!B11/'Balance Sheet'!B15) -> 1.2064871 | C14: =IF('Balance Sheet'!C15<=0,"n/a",'Balance Sheet'!C11/'Balance Sheet'!C15) -> 0.4821064 | D14: =IF('Balance Sheet'!D15<=0,"n/a",'Balance Sheet'!D11/'Balance Sheet'!D15) -> 0.24033131 | E14: =IF('Balance Sheet'!E15<=0,"n/a",'Balance Sheet'!E11/'Balance Sheet'!E15) -> 0.1266006 | F14: =IF('Balance Sheet'!F15<=0,"n/a",'Balance Sheet'!F11/'Balance Sheet'!F15) -> 0.062566652
A15: Return on assets (net income ÷ year-end assets) | B15: =IF('Balance Sheet'!B9<=0,"n/a",'P&L'!B23/'Balance Sheet'!B9) -> -0.65037887 | C15: =IF('Balance Sheet'!C9<=0,"n/a",'P&L'!C23/'Balance Sheet'!C9) -> 0.3135488 | D15: =IF('Balance Sheet'!D9<=0,"n/a",'P&L'!D23/'Balance Sheet'!D9) -> 0.27927756 | E15: =IF('Balance Sheet'!E9<=0,"n/a",'P&L'!E23/'Balance Sheet'!E9) -> 0.24929648 | F15: =IF('Balance Sheet'!F9<=0,"n/a",'P&L'!F23/'Balance Sheet'!F9) -> 0.23795856
A16: Return on equity (net income ÷ year-end equity) | B16: =IF('Balance Sheet'!B15<=0,"n/a",'P&L'!B23/'Balance Sheet'!B15) -> -1.6655101 | C16: =IF('Balance Sheet'!C15<=0,"n/a",'P&L'!C23/'Balance Sheet'!C15) -> 0.52179596 | D16: =IF('Balance Sheet'!D15<=0,"n/a",'P&L'!D23/'Balance Sheet'!D15) -> 0.37941508 | E16: =IF('Balance Sheet'!E15<=0,"n/a",'P&L'!E23/'Balance Sheet'!E15) -> 0.30237867 | F16: =IF('Balance Sheet'!F15<=0,"n/a",'P&L'!F23/'Balance Sheet'!F15) -> 0.26857657
A18: DuPont analysis — return on equity = net margin × asset turnover × equity multiplier
B19: 1 | C19: 2 | D19: 3 | E19: 4 | F19: 5
A20: Net margin | B20: =IF('P&L'!B5<=0,"n/a",'P&L'!B23/'P&L'!B5) -> -0.23721254 | C20: =IF('P&L'!C5<=0,"n/a",'P&L'!C23/'P&L'!C5) -> 0.098879705 | D20: =IF('P&L'!D5<=0,"n/a",'P&L'!D23/'P&L'!D5) -> 0.10920571 | E20: =IF('P&L'!E5<=0,"n/a",'P&L'!E23/'P&L'!E5) -> 0.11759469 | F20: =IF('P&L'!F5<=0,"n/a",'P&L'!F23/'P&L'!F5) -> 0.13460506
A21: × Asset turnover (revenue ÷ assets) | B21: =IF('Balance Sheet'!B9<=0,"n/a",'P&L'!B5/'Balance Sheet'!B9) -> 2.7417559 | C21: =IF('Balance Sheet'!C9<=0,"n/a",'P&L'!C5/'Balance Sheet'!C9) -> 3.1710127 | D21: =IF('Balance Sheet'!D9<=0,"n/a",'P&L'!D5/'Balance Sheet'!D9) -> 2.557353 | E21: =IF('Balance Sheet'!E9<=0,"n/a",'P&L'!E5/'Balance Sheet'!E9) -> 2.1199637 | F21: =IF('Balance Sheet'!F9<=0,"n/a",'P&L'!F5/'Balance Sheet'!F9) -> 1.7678278
A22: × Equity multiplier (assets ÷ equity) | B22: =IF('Balance Sheet'!B15<=0,"n/a",'Balance Sheet'!B9/'Balance Sheet'!B15) -> 2.5608306 | C22: =IF('Balance Sheet'!C15<=0,"n/a",'Balance Sheet'!C9/'Balance Sheet'!C15) -> 1.6641619 | D22: =IF('Balance Sheet'!D15<=0,"n/a",'Balance Sheet'!D9/'Balance Sheet'!D15) -> 1.3585591 | E22: =IF('Balance Sheet'!E15<=0,"n/a",'Balance Sheet'!E9/'Balance Sheet'!E15) -> 1.2129279 | F22: =IF('Balance Sheet'!F15<=0,"n/a",'Balance Sheet'!F9/'Balance Sheet'!F15) -> 1.1286695
A23: Return on equity (product of the three) | B23: =IF(AND(ISNUMBER(B20),ISNUMBER(B21),ISNUMBER(B22)),B20*B21*B22,"n/a") -> -1.6655101 | C23: =IF(AND(ISNUMBER(C20),ISNUMBER(C21),ISNUMBER(C22)),C20*C21*C22,"n/a") -> 0.52179596 | D23: =IF(AND(ISNUMBER(D20),ISNUMBER(D21),ISNUMBER(D22)),D20*D21*D22,"n/a") -> 0.37941508 | E23: =IF(AND(ISNUMBER(E20),ISNUMBER(E21),ISNUMBER(E22)),E20*E21*E22,"n/a") -> 0.30237867 | F23: =IF(AND(ISNUMBER(F20),ISNUMBER(F21),ISNUMBER(F22)),F20*F21*F22,"n/a") -> 0.26857657
A24: Check: product − return on equity (must be 0) | B24: =IF(AND(ISNUMBER(B23),ISNUMBER(B16)),B23-B16,IF(ISNUMBER(B23),1,IF(AND(ISNUMBER(B16),ISNUMBER(B20),ISNUMBER(B21)),1,0))) -> 0 | C24: =IF(AND(ISNUMBER(C23),ISNUMBER(C16)),C23-C16,IF(ISNUMBER(C23),1,IF(AND(ISNUMBER(C16),ISNUMBER(C20),ISNUMBER(C21)),1,0))) -> 0 | D24: =IF(AND(ISNUMBER(D23),ISNUMBER(D16)),D23-D16,IF(ISNUMBER(D23),1,IF(AND(ISNUMBER(D16),ISNUMBER(D20),ISNUMBER(D21)),1,0))) -> 0 | E24: =IF(AND(ISNUMBER(E23),ISNUMBER(E16)),E23-E16,IF(ISNUMBER(E23),1,IF(AND(ISNUMBER(E16),ISNUMBER(E20),ISNUMBER(E21)),1,0))) -> 0 | F24: =IF(AND(ISNUMBER(F23),ISNUMBER(F16)),F23-F16,IF(ISNUMBER(F23),1,IF(AND(ISNUMBER(F16),ISNUMBER(F20),ISNUMBER(F21)),1,0))) -> 0
A26: Auto repair metrics ($'000; per-unit rows in $)
A27: Year # | B27: 1 | C27: 2 | D27: 3 | E27: 4 | F27: 5
B28: Year 1 | C28: Year 2 | D28: Year 3 | E28: Year 4 | F28: Year 5 | G28: Target
A29: Technicians (FTE, year end) | B29: =INDEX(Monthly!$C$14:$BJ$14,B$27*12) -> 5 | C29: =INDEX(Monthly!$C$14:$BJ$14,C$27*12) -> 5 | D29: =INDEX(Monthly!$C$14:$BJ$14,D$27*12) -> 5 | E29: =INDEX(Monthly!$C$14:$BJ$14,E$27*12) -> 5 | F29: =INDEX(Monthly!$C$14:$BJ$14,F$27*12) -> 5
A30: Repair orders completed | B30: =SUMIF(Monthly!$C$5:$BJ$5,B$27,Monthly!$C$21:$BJ$21) -> 2733.75 | C30: =SUMIF(Monthly!$C$5:$BJ$5,C$27,Monthly!$C$21:$BJ$21) -> 4171.5 | D30: =SUMIF(Monthly!$C$5:$BJ$5,D$27,Monthly!$C$21:$BJ$21) -> 4296.645 | E30: =SUMIF(Monthly!$C$5:$BJ$5,E$27,Monthly!$C$21:$BJ$21) -> 4425.5444 | F30: =SUMIF(Monthly!$C$5:$BJ$5,F$27,Monthly!$C$21:$BJ$21) -> 4558.3107
A31: Billed labor hours | B31: =SUMIF(Monthly!$C$5:$BJ$5,B$27,Monthly!$C$18:$BJ$18) -> 5467.5 | C31: =SUMIF(Monthly!$C$5:$BJ$5,C$27,Monthly!$C$18:$BJ$18) -> 8343 | D31: =SUMIF(Monthly!$C$5:$BJ$5,D$27,Monthly!$C$18:$BJ$18) -> 8593.29 | E31: =SUMIF(Monthly!$C$5:$BJ$5,E$27,Monthly!$C$18:$BJ$18) -> 8851.0887 | F31: =SUMIF(Monthly!$C$5:$BJ$5,F$27,Monthly!$C$18:$BJ$18) -> 9116.6214
A32: Billed-hour capacity (lower of bays and technicians) | B32: =SUMIF(Monthly!$C$5:$BJ$5,B$27,Monthly!$C$17:$BJ$17) -> 10560 | C32: =SUMIF(Monthly!$C$5:$BJ$5,C$27,Monthly!$C$17:$BJ$17) -> 10560 | D32: =SUMIF(Monthly!$C$5:$BJ$5,D$27,Monthly!$C$17:$BJ$17) -> 10560 | E32: =SUMIF(Monthly!$C$5:$BJ$5,E$27,Monthly!$C$17:$BJ$17) -> 10560 | F32: =SUMIF(Monthly!$C$5:$BJ$5,F$27,Monthly!$C$17:$BJ$17) -> 10560
A33: Shop capacity used | B33: =IF(B32=0,0,B31/B32) -> 0.51775568 | C33: =IF(C32=0,0,C31/C32) -> 0.79005682 | D33: =IF(D32=0,0,D31/D32) -> 0.81375852 | E33: =IF(E32=0,0,E31/E32) -> 0.83817128 | F33: =IF(F32=0,0,F31/F32) -> 0.86331642
A34: Bay capacity used (billed hours ÷ bay limit) | B34: =IF(Inputs!$E$15*Inputs!$E$16*Inputs!$E$10=0,0,B31/(Inputs!$E$15*Inputs!$E$16*Inputs!$E$10*12)) -> 0.46730769 | C34: =IF(Inputs!$E$15*Inputs!$E$16*Inputs!$E$10=0,0,C31/(Inputs!$E$15*Inputs!$E$16*Inputs!$E$10*12)) -> 0.71307692 | D34: =IF(Inputs!$E$15*Inputs!$E$16*Inputs!$E$10=0,0,D31/(Inputs!$E$15*Inputs!$E$16*Inputs!$E$10*12)) -> 0.73446923 | E34: =IF(Inputs!$E$15*Inputs!$E$16*Inputs!$E$10=0,0,E31/(Inputs!$E$15*Inputs!$E$16*Inputs!$E$10*12)) -> 0.75650331 | F34: =IF(Inputs!$E$15*Inputs!$E$16*Inputs!$E$10=0,0,F31/(Inputs!$E$15*Inputs!$E$16*Inputs!$E$10*12)) -> 0.77919841
A35: Billed hours lost to the capacity limit | B35: =SUMIF(Monthly!$C$5:$BJ$5,B$27,Monthly!$C$19:$BJ$19) -> 0 | C35: =SUMIF(Monthly!$C$5:$BJ$5,C$27,Monthly!$C$19:$BJ$19) -> 0 | D35: =SUMIF(Monthly!$C$5:$BJ$5,D$27,Monthly!$C$19:$BJ$19) -> 0 | E35: =SUMIF(Monthly!$C$5:$BJ$5,E$27,Monthly!$C$19:$BJ$19) -> 0 | F35: =SUMIF(Monthly!$C$5:$BJ$5,F$27,Monthly!$C$19:$BJ$19) -> 0
A36: Revenue | B36: =SUMIF(Monthly!$C$5:$BJ$5,B$27,Monthly!$C$28:$BJ$28) -> 1264359.4 | C36: =SUMIF(Monthly!$C$5:$BJ$5,C$27,Monthly!$C$28:$BJ$28) -> 1987198.3 | D36: =SUMIF(Monthly!$C$5:$BJ$5,D$27,Monthly!$C$28:$BJ$28) -> 2108218.7 | E36: =SUMIF(Monthly!$C$5:$BJ$5,E$27,Monthly!$C$28:$BJ$28) -> 2236609.2 | F36: =SUMIF(Monthly!$C$5:$BJ$5,F$27,Monthly!$C$28:$BJ$28) -> 2372818.7
A37: Labor revenue | B37: =SUMIF(Monthly!$C$5:$BJ$5,B$27,Monthly!$C$25:$BJ$25) -> 683437.5 | C37: =SUMIF(Monthly!$C$5:$BJ$5,C$27,Monthly!$C$25:$BJ$25) -> 1074161.2 | D37: =SUMIF(Monthly!$C$5:$BJ$5,D$27,Monthly!$C$25:$BJ$25) -> 1139577.7 | E37: =SUMIF(Monthly!$C$5:$BJ$5,E$27,Monthly!$C$25:$BJ$25) -> 1208978 | F37: =SUMIF(Monthly!$C$5:$BJ$5,F$27,Monthly!$C$25:$BJ$25) -> 1282604.7
A38: Parts revenue | B38: =SUMIF(Monthly!$C$5:$BJ$5,B$27,Monthly!$C$26:$BJ$26) -> 546750 | C38: =SUMIF(Monthly!$C$5:$BJ$5,C$27,Monthly!$C$26:$BJ$26) -> 859329 | D38: =SUMIF(Monthly!$C$5:$BJ$5,D$27,Monthly!$C$26:$BJ$26) -> 911662.14 | E38: =SUMIF(Monthly!$C$5:$BJ$5,E$27,Monthly!$C$26:$BJ$26) -> 967182.36 | F38: =SUMIF(Monthly!$C$5:$BJ$5,F$27,Monthly!$C$26:$BJ$26) -> 1026083.8
A39: Parts share of revenue | B39: =IF(B36=0,0,B38/B36) -> 0.43243243 | C39: =IF(C36=0,0,C38/C36) -> 0.43243243 | D39: =IF(D36=0,0,D38/D36) -> 0.43243243 | E39: =IF(E36=0,0,E38/E36) -> 0.43243243 | F39: =IF(F36=0,0,F38/F36) -> 0.43243243
A40: Revenue per repair order ($) | B40: =IF(B30=0,0,B36/B30) -> 462.5 | C40: =IF(C30=0,0,C36/C30) -> 476.375 | D40: =IF(D30=0,0,D36/D30) -> 490.66625 | E40: =IF(E30=0,0,E36/E30) -> 505.38624 | F40: =IF(F30=0,0,F36/F30) -> 520.54782
A41: Revenue per billed hour ($) | B41: =IF(B31=0,0,B36/B31) -> 231.25 | C41: =IF(C31=0,0,C36/C31) -> 238.1875 | D41: =IF(D31=0,0,D36/D31) -> 245.33312 | E41: =IF(E31=0,0,E36/E31) -> 252.69312 | F41: =IF(F31=0,0,F36/F31) -> 260.27391
A42: Revenue per technician (year-end FTE) | B42: =IF(B29=0,0,B36/B29) -> 252871.88 | C42: =IF(C29=0,0,C36/C29) -> 397439.66 | D42: =IF(D29=0,0,D36/D29) -> 421643.74 | E42: =IF(E29=0,0,E36/E29) -> 447321.84 | F42: =IF(F29=0,0,F36/F29) -> 474563.74
A43: Parts cost | B43: =SUMIF(Monthly!$C$5:$BJ$5,B$27,Monthly!$C$32:$BJ$32) -> -289777.5 | C43: =SUMIF(Monthly!$C$5:$BJ$5,C$27,Monthly!$C$32:$BJ$32) -> -455444.37 | D43: =SUMIF(Monthly!$C$5:$BJ$5,D$27,Monthly!$C$32:$BJ$32) -> -483180.93 | E43: =SUMIF(Monthly!$C$5:$BJ$5,E$27,Monthly!$C$32:$BJ$32) -> -512606.65 | F43: =SUMIF(Monthly!$C$5:$BJ$5,F$27,Monthly!$C$32:$BJ$32) -> -543824.4
A44: Parts gross margin | B44: =IF(B38=0,0,(B38+B43)/B38) -> 0.47 | C44: =IF(C38=0,0,(C38+C43)/C38) -> 0.47 | D44: =IF(D38=0,0,(D38+D43)/D38) -> 0.47 | E44: =IF(E38=0,0,(E38+E43)/E38) -> 0.47 | F44: =IF(F38=0,0,(F38+F43)/F38) -> 0.47
A45: Gross profit | B45: =SUMIF(Monthly!$C$5:$BJ$5,B$27,Monthly!$C$36:$BJ$36) -> 481658.44 | C45: =SUMIF(Monthly!$C$5:$BJ$5,C$27,Monthly!$C$36:$BJ$36) -> 999978.46 | D45: =SUMIF(Monthly!$C$5:$BJ$5,D$27,Monthly!$C$36:$BJ$36) -> 1075151.6 | E45: =SUMIF(Monthly!$C$5:$BJ$5,E$27,Monthly!$C$36:$BJ$36) -> 1155330.9 | F45: =SUMIF(Monthly!$C$5:$BJ$5,F$27,Monthly!$C$36:$BJ$36) -> 1240834.3
A46: Gross margin | B46: =IF(B36=0,0,B45/B36) -> 0.38095058 | C46: =IF(C36=0,0,C45/C36) -> 0.5032102 | D46: =IF(D36=0,0,D45/D36) -> 0.50998104 | E46: =IF(E36=0,0,E45/E36) -> 0.51655467 | F46: =IF(F36=0,0,F45/F36) -> 0.52293683
A47: EBITDA | B47: =SUMIF(Monthly!$C$5:$BJ$5,B$27,Monthly!$C$46:$BJ$46) -> -231022.34 | C47: =SUMIF(Monthly!$C$5:$BJ$5,C$27,Monthly!$C$46:$BJ$46) -> 264690.01 | D47: =SUMIF(Monthly!$C$5:$BJ$5,D$27,Monthly!$C$46:$BJ$46) -> 331418.32 | E47: =SUMIF(Monthly!$C$5:$BJ$5,E$27,Monthly!$C$46:$BJ$46) -> 399696.18 | F47: =SUMIF(Monthly!$C$5:$BJ$5,F$27,Monthly!$C$46:$BJ$46) -> 470349.01
A48: EBITDA margin | B48: =IF(B36=0,0,B47/B36) -> -0.18271889 | C48: =IF(C36=0,0,C47/C36) -> 0.13319758 | D48: =IF(D36=0,0,D47/D36) -> 0.15720301 | E48: =IF(E36=0,0,E47/E36) -> 0.17870631 | F48: =IF(F36=0,0,F47/F36) -> 0.19822375

Sheet Inputs
A1: Inputs — Low / Base / High | I1: =HYPERLINK("#'Cover'!A1","◂ Contents") -> ◂ Contents
A2: Illustrative assumptions - replace them with your own numbers.
A5: Driver | B5: Low | C5: Base | D5: High | E5: Active | F5: Unit | G5: Source / comment
A6: Repair orders
A7: Repair orders per operating day at maturity (year 1) | B7: 11 | C7: 13.5 | D7: 16 | E7: =CHOOSE(Dashboard!$B$4,B7,C7,D7) -> 13.5 | F7: orders | G7: Low ≤ Base ≤ High
A8: Repair orders growth per year | B8: 0 | C8: 0.03 | D8: 0.06 | E8: =CHOOSE(Dashboard!$B$4,B8,C8,D8) -> 0.03 | F8: % | G8: Low ≤ Base ≤ High
A9: Billed labor hours per repair order | B9: 2 | C9: 2 | D9: 2 | E9: =CHOOSE(Dashboard!$B$4,B9,C9,D9) -> 2 | F9: hours | G9: Low ≤ Base ≤ High
A10: Operating days per month | B10: 25 | C10: 25 | D10: 25 | E10: =CHOOSE(Dashboard!$B$4,B10,C10,D10) -> 25 | F10: days
A11: Months to reach mature order volume (0 = already mature) | B11: 16 | C11: 12 | D11: 9 | E11: =CHOOSE(Dashboard!$B$4,B11,C11,D11) -> 12 | F11: months | G11: Low ≥ Base ≥ High (lower is better)
A12: Order volume in month 1, % of mature | B12: 0.3 | C12: 0.4 | D12: 0.5 | E12: =CHOOSE(Dashboard!$B$4,B12,C12,D12) -> 0.4 | F12: % | G12: Low ≤ Base ≤ High
A14: Shop capacity
A15: Service bays (lifts) | B15: 6 | C15: 6 | D15: 6 | E15: =CHOOSE(Dashboard!$B$4,B15,C15,D15) -> 6 | F15: bays
A16: Billed hours one bay can carry per operating day | B16: 6 | C16: 6.5 | D16: 7 | E16: =CHOOSE(Dashboard!$B$4,B16,C16,D16) -> 6.5 | F16: hours | G16: Low ≤ Base ≤ High
A17: Paid hours per technician per operating day | B17: 8 | C17: 8 | D17: 8 | E17: =CHOOSE(Dashboard!$B$4,B17,C17,D17) -> 8 | F17: hours
A18: Technician efficiency (billed hours per paid hour) | B18: 0.82 | C18: 0.88 | D18: 0.95 | E18: =CHOOSE(Dashboard!$B$4,B18,C18,D18) -> 0.88 | F18: % | G18: Low ≤ Base ≤ High
A20: Labor prices
A21: Effective labor rate per billed hour (year 1) | B21: 118 | C21: 125 | D21: 132 | E21: =CHOOSE(Dashboard!$B$4,B21,C21,D21) -> 125 | F21: $ | G21: Low ≤ Base ≤ High
A22: Price increase per year | B22: 0.01 | C22: 0.03 | D22: 0.04 | E22: =CHOOSE(Dashboard!$B$4,B22,C22,D22) -> 0.03 | F22: % | G22: Low ≤ Base ≤ High
A23: Shop supplies fee, % of labor revenue | B23: 0.04 | C23: 0.05 | D23: 0.05 | E23: =CHOOSE(Dashboard!$B$4,B23,C23,D23) -> 0.05 | F23: % | G23: Low ≤ Base ≤ High
A25: Parts & supplies
A26: Parts sales per billed labor hour (year 1) | B26: 92 | C26: 100 | D26: 108 | E26: =CHOOSE(Dashboard!$B$4,B26,C26,D26) -> 100 | F26: $ | G26: Low ≤ Base ≤ High
A27: Parts gross margin, % of parts sales | B27: 0.44 | C27: 0.47 | D27: 0.5 | E27: =CHOOSE(Dashboard!$B$4,B27,C27,D27) -> 0.47 | F27: % | G27: Low ≤ Base ≤ High
A29: Cost of sales
A30: Shop supplies & waste disposal cost, % of labor revenue | B30: 0.04 | C30: 0.035 | D30: 0.03 | E30: =CHOOSE(Dashboard!$B$4,B30,C30,D30) -> 0.035 | F30: % | G30: Low ≥ Base ≥ High (lower is better)
A31: Comebacks & warranty rework, % of labor revenue | B31: 0.04 | C31: 0.03 | D31: 0.025 | E31: =CHOOSE(Dashboard!$B$4,B31,C31,D31) -> 0.03 | F31: % | G31: Low ≥ Base ≥ High (lower is better)
A32: Card processing fees, % of revenue | B32: 0.032 | C32: 0.03 | D32: 0.028 | E32: =CHOOSE(Dashboard!$B$4,B32,C32,D32) -> 0.03 | F32: % | G32: Low ≥ Base ≥ High (lower is better)
A33: Cost increase per year (insurance, software & other) | B33: 0.04 | C33: 0.03 | D33: 0.025 | E33: =CHOOSE(Dashboard!$B$4,B33,C33,D33) -> 0.03 | F33: % | G33: Low ≥ Base ≥ High (lower is better)
A35: Shop costs
A36: Shop rent or land cost per month | B36: 18000 | C36: 18000 | D36: 18000 | E36: =CHOOSE(Dashboard!$B$4,B36,C36,D36) -> 18000 | F36: $
A37: Rent increase per year | B37: 0.03 | C37: 0.03 | D37: 0.03 | E37: =CHOOSE(Dashboard!$B$4,B37,C37,D37) -> 0.03 | F37: %
A38: Insurance (garage liability, property) per month | B38: 4500 | C38: 4500 | D38: 4500 | E38: =CHOOSE(Dashboard!$B$4,B38,C38,D38) -> 4500 | F38: $
A39: Shop software, diagnostic subscriptions, utilities & other G&A per month | B39: 9000 | C39: 9000 | D39: 9000 | E39: =CHOOSE(Dashboard!$B$4,B39,C39,D39) -> 9000 | F39: $
A40: Marketing budget per month (year 1) | B40: 7000 | C40: 7000 | D40: 7000 | E40: =CHOOSE(Dashboard!$B$4,B40,C40,D40) -> 7000 | F40: $
A41: Marketing budget growth per year | B41: -0.3 | C41: -0.2 | D41: -0.1 | E41: =CHOOSE(Dashboard!$B$4,B41,C41,D41) -> -0.2 | F41: % | G41: Low ≤ Base ≤ High
A43: Capital spending
A44: Lift & bay equipment per bay (month 1) | B44: 22000 | C44: 22000 | D44: 22000 | E44: =CHOOSE(Dashboard!$B$4,B44,C44,D44) -> 22000 | F44: $
A45: Diagnostic tools & scan equipment (month 1) | B45: 70000 | C45: 70000 | D45: 70000 | E45: =CHOOSE(Dashboard!$B$4,B45,C45,D45) -> 70000 | F45: $
A46: Leasehold improvements & signage (month 1) | B46: 180000 | C46: 180000 | D46: 180000 | E46: =CHOOSE(Dashboard!$B$4,B46,C46,D46) -> 180000 | F46: $
A47: Land or building purchase (month 1; never depreciated, 0 = leased shop) | B47: 0 | C47: 0 | D47: 0 | E47: =CHOOSE(Dashboard!$B$4,B47,C47,D47) -> 0 | F47: $
A48: Equipment & tool refresh per year (from year 2) | B48: 20000 | C48: 20000 | D48: 20000 | E48: =CHOOSE(Dashboard!$B$4,B48,C48,D48) -> 20000 | F48: $
A50: Headcount
A51: Technicians: headcount (FTE) | B51: 5 | C51: 5 | D51: 5 | E51: =CHOOSE(Dashboard!$B$4,B51,C51,D51) -> 5 | F51: FTE | G51: Low ≤ Base ≤ High
A52: Technicians: salary per FTE per year | B52: 78000 | C52: 78000 | D52: 78000 | E52: =CHOOSE(Dashboard!$B$4,B52,C52,D52) -> 78000 | F52: $
A53: Technicians: headcount growth per year | B53: 0 | C53: 0 | D53: 0 | E53: =CHOOSE(Dashboard!$B$4,B53,C53,D53) -> 0 | F53: % | G53: Low ≤ Base ≤ High
A54: Technicians: first month on payroll | B54: 1 | C54: 1 | D54: 1 | E54: =CHOOSE(Dashboard!$B$4,B54,C54,D54) -> 1 | F54: month #
A55: Service advisors & front desk: headcount (FTE) | B55: 2 | C55: 2 | D55: 2 | E55: =CHOOSE(Dashboard!$B$4,B55,C55,D55) -> 2 | F55: FTE | G55: Low ≤ Base ≤ High
A56: Service advisors & front desk: salary per FTE per year | B56: 50000 | C56: 50000 | D56: 50000 | E56: =CHOOSE(Dashboard!$B$4,B56,C56,D56) -> 50000 | F56: $
A57: Service advisors & front desk: headcount growth per year | B57: 0 | C57: 0 | D57: 0 | E57: =CHOOSE(Dashboard!$B$4,B57,C57,D57) -> 0 | F57: % | G57: Low ≤ Base ≤ High
A58: Service advisors & front desk: first month on payroll | B58: 1 | C58: 1 | D58: 1 | E58: =CHOOSE(Dashboard!$B$4,B58,C58,D58) -> 1 | F58: month #
A59: Shop manager: headcount (FTE) | B59: 1 | C59: 1 | D59: 1 | E59: =CHOOSE(Dashboard!$B$4,B59,C59,D59) -> 1 | F59: FTE | G59: Low ≤ Base ≤ High
A60: Shop manager: salary per FTE per year | B60: 85000 | C60: 85000 | D60: 85000 | E60: =CHOOSE(Dashboard!$B$4,B60,C60,D60) -> 85000 | F60: $
A61: Shop manager: headcount growth per year | B61: 0 | C61: 0 | D61: 0 | E61: =CHOOSE(Dashboard!$B$4,B61,C61,D61) -> 0 | F61: % | G61: Low ≤ Base ≤ High
A62: Shop manager: first month on payroll | B62: 1 | C62: 1 | D62: 1 | E62: =CHOOSE(Dashboard!$B$4,B62,C62,D62) -> 1 | F62: month #
A63: Payroll taxes & benefits, % of salary | B63: 0.15 | C63: 0.15 | D63: 0.15 | E63: =CHOOSE(Dashboard!$B$4,B63,C63,D63) -> 0.15 | F63: %
A64: Wage growth per year | B64: 0.04 | C64: 0.03 | D64: 0.03 | E64: =CHOOSE(Dashboard!$B$4,B64,C64,D64) -> 0.03 | F64: %
A66: Funding
A67: Equity raised at start | B67: 480000 | C67: 480000 | D67: 480000 | E67: =CHOOSE(Dashboard!$B$4,B67,C67,D67) -> 480000 | F67: $
A68: Loan drawn at start | B68: 250000 | C68: 250000 | D68: 250000 | E68: =CHOOSE(Dashboard!$B$4,B68,C68,D68) -> 250000 | F68: $
A69: Loan interest rate per year | B69: 0.09 | C69: 0.09 | D69: 0.09 | E69: =CHOOSE(Dashboard!$B$4,B69,C69,D69) -> 0.09 | F69: %
A70: Loan repayment term | B70: 7 | C70: 7 | D70: 7 | E70: =CHOOSE(Dashboard!$B$4,B70,C70,D70) -> 7 | F70: years
A72: Working capital
A73: Customer payment terms (receivable days) | B73: 3 | C73: 3 | D73: 3 | E73: =CHOOSE(Dashboard!$B$4,B73,C73,D73) -> 3 | F73: days
A74: Inventory held (days of COGS) | B74: 8 | C74: 8 | D74: 8 | E74: =CHOOSE(Dashboard!$B$4,B74,C74,D74) -> 8 | F74: days
A75: Supplier payment terms (payable days) | B75: 25 | C75: 25 | D75: 25 | E75: =CHOOSE(Dashboard!$B$4,B75,C75,D75) -> 25 | F75: days
A77: Tax & depreciation
A78: Depreciation period for capex | B78: 8 | C78: 8 | D78: 8 | E78: =CHOOSE(Dashboard!$B$4,B78,C78,D78) -> 8 | F78: years
A79: Income tax rate | B79: 0.21 | C79: 0.21 | D79: 0.21 | E79: =CHOOSE(Dashboard!$B$4,B79,C79,D79) -> 0.21 | F79: %
A81: Break-even & funding
A82: Minimum cash buffer to keep | B82: 178000 | C82: 178000 | D82: 178000 | E82: =CHOOSE(Dashboard!$B$4,B82,C82,D82) -> 178000 | F82: $ | G82: About 3 months of costs
A84: Valuation
A85: Discount rate (WACC) | B85: 0.3 | C85: 0.25 | D85: 0.2 | E85: =CHOOSE(Dashboard!$B$4,B85,C85,D85) -> 0.25 | F85: % | G85: Low ≥ Base ≥ High (lower is better)
A86: Terminal growth rate (perpetuity) | B86: 0.01 | C86: 0.02 | D86: 0.03 | E86: =CHOOSE(Dashboard!$B$4,B86,C86,D86) -> 0.02 | F86: % | G86: Low ≤ Base ≤ High
A87: Exit multiple (EV ÷ final-year EBITDA) | B87: 3 | C87: 4 | D87: 5 | E87: =CHOOSE(Dashboard!$B$4,B87,C87,D87) -> 4 | F87: x | G87: Low ≤ Base ≤ High
A88: Sensitivity table: WACC step | B88: 0.01 | C88: 0.01 | D88: 0.01 | E88: =CHOOSE(Dashboard!$B$4,B88,C88,D88) -> 0.01 | F88: %
A89: Sensitivity table: growth step | B89: 0.005 | C89: 0.005 | D89: 0.005 | E89: =CHOOSE(Dashboard!$B$4,B89,C89,D89) -> 0.005 | F89: %
A91: Legend: yellow cell with blue figure = input you can change · black = formula · green = link to another sheet · grey = active value (column E follows the scenario on the Dashboard).

Sheet P&L
A1: Annual profit & loss | H1: =HYPERLINK("#'Cover'!A1","◂ Contents") -> ◂ Contents
A2: Rolled up from the period detail (SUMIF on the year row; balances at year end).
A3: Year # | B3: 1 | C3: 2 | D3: 3 | E3: 4 | F3: 5
B4: Year 1 | C4: Year 2 | D4: Year 3 | E4: Year 4 | F4: Year 5
A5: Revenue | B5: =SUMIF(Monthly!$C$5:$BJ$5,B$3,Monthly!$C$28:$BJ$28) -> 1264359.4 | C5: =SUMIF(Monthly!$C$5:$BJ$5,C$3,Monthly!$C$28:$BJ$28) -> 1987198.3 | D5: =SUMIF(Monthly!$C$5:$BJ$5,D$3,Monthly!$C$28:$BJ$28) -> 2108218.7 | E5: =SUMIF(Monthly!$C$5:$BJ$5,E$3,Monthly!$C$28:$BJ$28) -> 2236609.2 | F5: =SUMIF(Monthly!$C$5:$BJ$5,F$3,Monthly!$C$28:$BJ$28) -> 2372818.7
A6: Cost of sales | B6: =SUMIF(Monthly!$C$5:$BJ$5,B$3,Monthly!$C$35:$BJ$35) -> -782700.94 | C6: =SUMIF(Monthly!$C$5:$BJ$5,C$3,Monthly!$C$35:$BJ$35) -> -987219.85 | D6: =SUMIF(Monthly!$C$5:$BJ$5,D$3,Monthly!$C$35:$BJ$35) -> -1033067.1 | E6: =SUMIF(Monthly!$C$5:$BJ$5,E$3,Monthly!$C$35:$BJ$35) -> -1081278.3 | F6: =SUMIF(Monthly!$C$5:$BJ$5,F$3,Monthly!$C$35:$BJ$35) -> -1131984.4
A7: Gross profit | B7: =SUMIF(Monthly!$C$5:$BJ$5,B$3,Monthly!$C$36:$BJ$36) -> 481658.44 | C7: =SUMIF(Monthly!$C$5:$BJ$5,C$3,Monthly!$C$36:$BJ$36) -> 999978.46 | D7: =SUMIF(Monthly!$C$5:$BJ$5,D$3,Monthly!$C$36:$BJ$36) -> 1075151.6 | E7: =SUMIF(Monthly!$C$5:$BJ$5,E$3,Monthly!$C$36:$BJ$36) -> 1155330.9 | F7: =SUMIF(Monthly!$C$5:$BJ$5,F$3,Monthly!$C$36:$BJ$36) -> 1240834.3
A8: Gross margin | B8: =IF(B5=0,0,B7/B5) -> 0.38095058 | C8: =IF(C5=0,0,C7/C5) -> 0.5032102 | D8: =IF(D5=0,0,D7/D5) -> 0.50998104 | E8: =IF(E5=0,0,E7/E5) -> 0.51655467 | F8: =IF(F5=0,0,F7/F5) -> 0.52293683
A9: Advisors, manager & other payroll | B9: =SUMIF(Monthly!$C$5:$BJ$5,B$3,Monthly!$C$39:$BJ$39) -> -212750 | C9: =SUMIF(Monthly!$C$5:$BJ$5,C$3,Monthly!$C$39:$BJ$39) -> -219132.5 | D9: =SUMIF(Monthly!$C$5:$BJ$5,D$3,Monthly!$C$39:$BJ$39) -> -225706.48 | E9: =SUMIF(Monthly!$C$5:$BJ$5,E$3,Monthly!$C$39:$BJ$39) -> -232477.67 | F9: =SUMIF(Monthly!$C$5:$BJ$5,F$3,Monthly!$C$39:$BJ$39) -> -239452
A10: Shop rent or land cost | B10: =SUMIF(Monthly!$C$5:$BJ$5,B$3,Monthly!$C$40:$BJ$40) -> -216000 | C10: =SUMIF(Monthly!$C$5:$BJ$5,C$3,Monthly!$C$40:$BJ$40) -> -222480 | D10: =SUMIF(Monthly!$C$5:$BJ$5,D$3,Monthly!$C$40:$BJ$40) -> -229154.4 | E10: =SUMIF(Monthly!$C$5:$BJ$5,E$3,Monthly!$C$40:$BJ$40) -> -236029.03 | F10: =SUMIF(Monthly!$C$5:$BJ$5,F$3,Monthly!$C$40:$BJ$40) -> -243109.9
A11: Insurance | B11: =SUMIF(Monthly!$C$5:$BJ$5,B$3,Monthly!$C$41:$BJ$41) -> -54000 | C11: =SUMIF(Monthly!$C$5:$BJ$5,C$3,Monthly!$C$41:$BJ$41) -> -55620 | D11: =SUMIF(Monthly!$C$5:$BJ$5,D$3,Monthly!$C$41:$BJ$41) -> -57288.6 | E11: =SUMIF(Monthly!$C$5:$BJ$5,E$3,Monthly!$C$41:$BJ$41) -> -59007.258 | F11: =SUMIF(Monthly!$C$5:$BJ$5,F$3,Monthly!$C$41:$BJ$41) -> -60777.476
A12: Software, utilities & other G&A | B12: =SUMIF(Monthly!$C$5:$BJ$5,B$3,Monthly!$C$42:$BJ$42) -> -108000 | C12: =SUMIF(Monthly!$C$5:$BJ$5,C$3,Monthly!$C$42:$BJ$42) -> -111240 | D12: =SUMIF(Monthly!$C$5:$BJ$5,D$3,Monthly!$C$42:$BJ$42) -> -114577.2 | E12: =SUMIF(Monthly!$C$5:$BJ$5,E$3,Monthly!$C$42:$BJ$42) -> -118014.52 | F12: =SUMIF(Monthly!$C$5:$BJ$5,F$3,Monthly!$C$42:$BJ$42) -> -121554.95
A13: Marketing | B13: =SUMIF(Monthly!$C$5:$BJ$5,B$3,Monthly!$C$43:$BJ$43) -> -84000 | C13: =SUMIF(Monthly!$C$5:$BJ$5,C$3,Monthly!$C$43:$BJ$43) -> -67200 | D13: =SUMIF(Monthly!$C$5:$BJ$5,D$3,Monthly!$C$43:$BJ$43) -> -53760 | E13: =SUMIF(Monthly!$C$5:$BJ$5,E$3,Monthly!$C$43:$BJ$43) -> -43008 | F13: =SUMIF(Monthly!$C$5:$BJ$5,F$3,Monthly!$C$43:$BJ$43) -> -34406.4
A14: Card processing fees | B14: =SUMIF(Monthly!$C$5:$BJ$5,B$3,Monthly!$C$44:$BJ$44) -> -37930.781 | C14: =SUMIF(Monthly!$C$5:$BJ$5,C$3,Monthly!$C$44:$BJ$44) -> -59615.949 | D14: =SUMIF(Monthly!$C$5:$BJ$5,D$3,Monthly!$C$44:$BJ$44) -> -63246.561 | E14: =SUMIF(Monthly!$C$5:$BJ$5,E$3,Monthly!$C$44:$BJ$44) -> -67098.276 | F14: =SUMIF(Monthly!$C$5:$BJ$5,F$3,Monthly!$C$44:$BJ$44) -> -71184.561
A15: Total operating expenses | B15: =SUMIF(Monthly!$C$5:$BJ$5,B$3,Monthly!$C$45:$BJ$45) -> -712680.78 | C15: =SUMIF(Monthly!$C$5:$BJ$5,C$3,Monthly!$C$45:$BJ$45) -> -735288.45 | D15: =SUMIF(Monthly!$C$5:$BJ$5,D$3,Monthly!$C$45:$BJ$45) -> -743733.24 | E15: =SUMIF(Monthly!$C$5:$BJ$5,E$3,Monthly!$C$45:$BJ$45) -> -755634.75 | F15: =SUMIF(Monthly!$C$5:$BJ$5,F$3,Monthly!$C$45:$BJ$45) -> -770485.29
A16: EBITDA | B16: =SUMIF(Monthly!$C$5:$BJ$5,B$3,Monthly!$C$46:$BJ$46) -> -231022.34 | C16: =SUMIF(Monthly!$C$5:$BJ$5,C$3,Monthly!$C$46:$BJ$46) -> 264690.01 | D16: =SUMIF(Monthly!$C$5:$BJ$5,D$3,Monthly!$C$46:$BJ$46) -> 331418.32 | E16: =SUMIF(Monthly!$C$5:$BJ$5,E$3,Monthly!$C$46:$BJ$46) -> 399696.18 | F16: =SUMIF(Monthly!$C$5:$BJ$5,F$3,Monthly!$C$46:$BJ$46) -> 470349.01
A17: EBITDA margin | B17: =IF(B5=0,0,B16/B5) -> -0.18271889 | C17: =IF(C5=0,0,C16/C5) -> 0.13319758 | D17: =IF(D5=0,0,D16/D5) -> 0.15720301 | E17: =IF(E5=0,0,E16/E5) -> 0.17870631 | F17: =IF(F5=0,0,F16/F5) -> 0.19822375
A18: Depreciation | B18: =SUMIF(Monthly!$C$5:$BJ$5,B$3,Monthly!$C$66:$BJ$66) -> -47750 | C18: =SUMIF(Monthly!$C$5:$BJ$5,C$3,Monthly!$C$66:$BJ$66) -> -50250 | D18: =SUMIF(Monthly!$C$5:$BJ$5,D$3,Monthly!$C$66:$BJ$66) -> -52750 | E18: =SUMIF(Monthly!$C$5:$BJ$5,E$3,Monthly!$C$66:$BJ$66) -> -55250 | F18: =SUMIF(Monthly!$C$5:$BJ$5,F$3,Monthly!$C$66:$BJ$66) -> -57750
A19: EBIT | B19: =SUMIF(Monthly!$C$5:$BJ$5,B$3,Monthly!$C$49:$BJ$49) -> -278772.34 | C19: =SUMIF(Monthly!$C$5:$BJ$5,C$3,Monthly!$C$49:$BJ$49) -> 214440.01 | D19: =SUMIF(Monthly!$C$5:$BJ$5,D$3,Monthly!$C$49:$BJ$49) -> 278668.32 | E19: =SUMIF(Monthly!$C$5:$BJ$5,E$3,Monthly!$C$49:$BJ$49) -> 344446.18 | F19: =SUMIF(Monthly!$C$5:$BJ$5,F$3,Monthly!$C$49:$BJ$49) -> 412599.01
A20: Interest | B20: =SUMIF(Monthly!$C$5:$BJ$5,B$3,Monthly!$C$50:$BJ$50) -> -21149.554 | C20: =SUMIF(Monthly!$C$5:$BJ$5,C$3,Monthly!$C$50:$BJ$50) -> -17946.429 | D20: =SUMIF(Monthly!$C$5:$BJ$5,D$3,Monthly!$C$50:$BJ$50) -> -14732.143 | E20: =SUMIF(Monthly!$C$5:$BJ$5,E$3,Monthly!$C$50:$BJ$50) -> -11517.857 | F20: =SUMIF(Monthly!$C$5:$BJ$5,F$3,Monthly!$C$50:$BJ$50) -> -8303.5714
A21: Pre-tax income | B21: =SUMIF(Monthly!$C$5:$BJ$5,B$3,Monthly!$C$51:$BJ$51) -> -299921.9 | C21: =SUMIF(Monthly!$C$5:$BJ$5,C$3,Monthly!$C$51:$BJ$51) -> 196493.58 | D21: =SUMIF(Monthly!$C$5:$BJ$5,D$3,Monthly!$C$51:$BJ$51) -> 263936.18 | E21: =SUMIF(Monthly!$C$5:$BJ$5,E$3,Monthly!$C$51:$BJ$51) -> 332928.32 | F21: =SUMIF(Monthly!$C$5:$BJ$5,F$3,Monthly!$C$51:$BJ$51) -> 404295.44
A22: Income tax | B22: =SUMIF(Monthly!$C$5:$BJ$5,B$3,Monthly!$C$54:$BJ$54) -> 0 | C22: =SUMIF(Monthly!$C$5:$BJ$5,C$3,Monthly!$C$54:$BJ$54) -> 0 | D22: =SUMIF(Monthly!$C$5:$BJ$5,D$3,Monthly!$C$54:$BJ$54) -> -33706.652 | E22: =SUMIF(Monthly!$C$5:$BJ$5,E$3,Monthly!$C$54:$BJ$54) -> -69914.948 | F22: =SUMIF(Monthly!$C$5:$BJ$5,F$3,Monthly!$C$54:$BJ$54) -> -84902.043
A23: Net income | B23: =SUMIF(Monthly!$C$5:$BJ$5,B$3,Monthly!$C$55:$BJ$55) -> -299921.9 | C23: =SUMIF(Monthly!$C$5:$BJ$5,C$3,Monthly!$C$55:$BJ$55) -> 196493.58 | D23: =SUMIF(Monthly!$C$5:$BJ$5,D$3,Monthly!$C$55:$BJ$55) -> 230229.53 | E23: =SUMIF(Monthly!$C$5:$BJ$5,E$3,Monthly!$C$55:$BJ$55) -> 263013.37 | F23: =SUMIF(Monthly!$C$5:$BJ$5,F$3,Monthly!$C$55:$BJ$55) -> 319393.4
A24: Net margin | B24: =IF(B5=0,0,B23/B5) -> -0.23721254 | C24: =IF(C5=0,0,C23/C5) -> 0.098879705 | D24: =IF(D5=0,0,D23/D5) -> 0.10920571 | E24: =IF(E5=0,0,E23/E5) -> 0.11759469 | F24: =IF(F5=0,0,F23/F5) -> 0.13460506

Sheet Cash Flow
A1: Annual cash flow statement | H1: =HYPERLINK("#'Cover'!A1","◂ Contents") -> ◂ Contents
A2: Rolled up from the period detail (SUMIF on the year row; balances at year end).
A3: Year # | B3: 1 | C3: 2 | D3: 3 | E3: 4 | F3: 5
B4: Year 1 | C4: Year 2 | D4: Year 3 | E4: Year 4 | F4: Year 5
A5: Net income | B5: =SUMIF(Monthly!$C$5:$BJ$5,B$3,Monthly!$C$55:$BJ$55) -> -299921.9 | C5: =SUMIF(Monthly!$C$5:$BJ$5,C$3,Monthly!$C$55:$BJ$55) -> 196493.58 | D5: =SUMIF(Monthly!$C$5:$BJ$5,D$3,Monthly!$C$55:$BJ$55) -> 230229.53 | E5: =SUMIF(Monthly!$C$5:$BJ$5,E$3,Monthly!$C$55:$BJ$55) -> 263013.37 | F5: =SUMIF(Monthly!$C$5:$BJ$5,F$3,Monthly!$C$55:$BJ$55) -> 319393.4
A6: Add back depreciation | B6: =-SUMIF(Monthly!$C$5:$BJ$5,B$3,Monthly!$C$66:$BJ$66) -> 47750 | C6: =-SUMIF(Monthly!$C$5:$BJ$5,C$3,Monthly!$C$66:$BJ$66) -> 50250 | D6: =-SUMIF(Monthly!$C$5:$BJ$5,D$3,Monthly!$C$66:$BJ$66) -> 52750 | E6: =-SUMIF(Monthly!$C$5:$BJ$5,E$3,Monthly!$C$66:$BJ$66) -> 55250 | F6: =-SUMIF(Monthly!$C$5:$BJ$5,F$3,Monthly!$C$66:$BJ$66) -> 57750
A7: (Increase) / decrease in receivables | B7: =SUMIF(Monthly!$C$5:$BJ$5,B$3,Monthly!$C$80:$BJ$80) -> -14828.906 | C7: =SUMIF(Monthly!$C$5:$BJ$5,C$3,Monthly!$C$80:$BJ$80) -> -1731.0797 | D7: =SUMIF(Monthly!$C$5:$BJ$5,D$3,Monthly!$C$80:$BJ$80) -> -1008.5031 | E7: =SUMIF(Monthly!$C$5:$BJ$5,E$3,Monthly!$C$80:$BJ$80) -> -1069.921 | F7: =SUMIF(Monthly!$C$5:$BJ$5,F$3,Monthly!$C$80:$BJ$80) -> -1135.0792
A8: (Increase) / decrease in inventory | B8: =SUMIF(Monthly!$C$5:$BJ$5,B$3,Monthly!$C$81:$BJ$81) -> -20419.042 | C8: =SUMIF(Monthly!$C$5:$BJ$5,C$3,Monthly!$C$81:$BJ$81) -> -1519.1772 | D8: =SUMIF(Monthly!$C$5:$BJ$5,D$3,Monthly!$C$81:$BJ$81) -> -1018.8284 | E8: =SUMIF(Monthly!$C$5:$BJ$5,E$3,Monthly!$C$81:$BJ$81) -> -1071.3588 | F8: =SUMIF(Monthly!$C$5:$BJ$5,F$3,Monthly!$C$81:$BJ$81) -> -1126.8028
A9: Increase / (decrease) in payables | B9: =SUMIF(Monthly!$C$5:$BJ$5,B$3,Monthly!$C$82:$BJ$82) -> 63809.505 | C9: =SUMIF(Monthly!$C$5:$BJ$5,C$3,Monthly!$C$82:$BJ$82) -> 4747.4289 | D9: =SUMIF(Monthly!$C$5:$BJ$5,D$3,Monthly!$C$82:$BJ$82) -> 3183.8389 | E9: =SUMIF(Monthly!$C$5:$BJ$5,E$3,Monthly!$C$82:$BJ$82) -> 3347.9963 | F9: =SUMIF(Monthly!$C$5:$BJ$5,F$3,Monthly!$C$82:$BJ$82) -> 3521.2588
A10: Operating cash flow | B10: =SUMIF(Monthly!$C$5:$BJ$5,B$3,Monthly!$C$85:$BJ$85) -> -223610.34 | C10: =SUMIF(Monthly!$C$5:$BJ$5,C$3,Monthly!$C$85:$BJ$85) -> 248240.76 | D10: =SUMIF(Monthly!$C$5:$BJ$5,D$3,Monthly!$C$85:$BJ$85) -> 284136.04 | E10: =SUMIF(Monthly!$C$5:$BJ$5,E$3,Monthly!$C$85:$BJ$85) -> 319470.09 | F10: =SUMIF(Monthly!$C$5:$BJ$5,F$3,Monthly!$C$85:$BJ$85) -> 378402.78
A11: Capital spending | B11: =SUMIF(Monthly!$C$5:$BJ$5,B$3,Monthly!$C$86:$BJ$86) -> -382000 | C11: =SUMIF(Monthly!$C$5:$BJ$5,C$3,Monthly!$C$86:$BJ$86) -> -20000 | D11: =SUMIF(Monthly!$C$5:$BJ$5,D$3,Monthly!$C$86:$BJ$86) -> -20000 | E11: =SUMIF(Monthly!$C$5:$BJ$5,E$3,Monthly!$C$86:$BJ$86) -> -20000 | F11: =SUMIF(Monthly!$C$5:$BJ$5,F$3,Monthly!$C$86:$BJ$86) -> -20000
A12: Equity raised | B12: =SUMIF(Monthly!$C$5:$BJ$5,B$3,Monthly!$C$87:$BJ$87) -> 480000 | C12: =SUMIF(Monthly!$C$5:$BJ$5,C$3,Monthly!$C$87:$BJ$87) -> 0 | D12: =SUMIF(Monthly!$C$5:$BJ$5,D$3,Monthly!$C$87:$BJ$87) -> 0 | E12: =SUMIF(Monthly!$C$5:$BJ$5,E$3,Monthly!$C$87:$BJ$87) -> 0 | F12: =SUMIF(Monthly!$C$5:$BJ$5,F$3,Monthly!$C$87:$BJ$87) -> 0
A13: Loan drawdown | B13: =SUMIF(Monthly!$C$5:$BJ$5,B$3,Monthly!$C$72:$BJ$72) -> 250000 | C13: =SUMIF(Monthly!$C$5:$BJ$5,C$3,Monthly!$C$72:$BJ$72) -> 0 | D13: =SUMIF(Monthly!$C$5:$BJ$5,D$3,Monthly!$C$72:$BJ$72) -> 0 | E13: =SUMIF(Monthly!$C$5:$BJ$5,E$3,Monthly!$C$72:$BJ$72) -> 0 | F13: =SUMIF(Monthly!$C$5:$BJ$5,F$3,Monthly!$C$72:$BJ$72) -> 0
A14: Loan repayment | B14: =SUMIF(Monthly!$C$5:$BJ$5,B$3,Monthly!$C$73:$BJ$73) -> -32738.095 | C14: =SUMIF(Monthly!$C$5:$BJ$5,C$3,Monthly!$C$73:$BJ$73) -> -35714.286 | D14: =SUMIF(Monthly!$C$5:$BJ$5,D$3,Monthly!$C$73:$BJ$73) -> -35714.286 | E14: =SUMIF(Monthly!$C$5:$BJ$5,E$3,Monthly!$C$73:$BJ$73) -> -35714.286 | F14: =SUMIF(Monthly!$C$5:$BJ$5,F$3,Monthly!$C$73:$BJ$73) -> -35714.286
A15: Financing cash flow | B15: =SUMIF(Monthly!$C$5:$BJ$5,B$3,Monthly!$C$88:$BJ$88) -> 697261.9 | C15: =SUMIF(Monthly!$C$5:$BJ$5,C$3,Monthly!$C$88:$BJ$88) -> -35714.286 | D15: =SUMIF(Monthly!$C$5:$BJ$5,D$3,Monthly!$C$88:$BJ$88) -> -35714.286 | E15: =SUMIF(Monthly!$C$5:$BJ$5,E$3,Monthly!$C$88:$BJ$88) -> -35714.286 | F15: =SUMIF(Monthly!$C$5:$BJ$5,F$3,Monthly!$C$88:$BJ$88) -> -35714.286
A16: Net change in cash | B16: =SUMIF(Monthly!$C$5:$BJ$5,B$3,Monthly!$C$89:$BJ$89) -> 91651.565 | C16: =SUMIF(Monthly!$C$5:$BJ$5,C$3,Monthly!$C$89:$BJ$89) -> 192526.47 | D16: =SUMIF(Monthly!$C$5:$BJ$5,D$3,Monthly!$C$89:$BJ$89) -> 228421.75 | E16: =SUMIF(Monthly!$C$5:$BJ$5,E$3,Monthly!$C$89:$BJ$89) -> 263755.81 | F16: =SUMIF(Monthly!$C$5:$BJ$5,F$3,Monthly!$C$89:$BJ$89) -> 322688.49
A17: Opening cash | B17: =INDEX(Monthly!$C$90:$BJ$90,(B$3-1)*12+1) -> 0 | C17: =INDEX(Monthly!$C$90:$BJ$90,(C$3-1)*12+1) -> 91651.565 | D17: =INDEX(Monthly!$C$90:$BJ$90,(D$3-1)*12+1) -> 284178.03 | E17: =INDEX(Monthly!$C$90:$BJ$90,(E$3-1)*12+1) -> 512599.78 | F17: =INDEX(Monthly!$C$90:$BJ$90,(F$3-1)*12+1) -> 776355.59
A18: Closing cash | B18: =INDEX(Monthly!$C$91:$BJ$91,B$3*12) -> 91651.565 | C18: =INDEX(Monthly!$C$91:$BJ$91,C$3*12) -> 284178.03 | D18: =INDEX(Monthly!$C$91:$BJ$91,D$3*12) -> 512599.78 | E18: =INDEX(Monthly!$C$91:$BJ$91,E$3*12) -> 776355.59 | F18: =INDEX(Monthly!$C$91:$BJ$91,F$3*12) -> 1099044.1

Sheet Balance Sheet
A1: Balance sheet at year end | H1: =HYPERLINK("#'Cover'!A1","◂ Contents") -> ◂ Contents
A2: Rolled up from the period detail (SUMIF on the year row; balances at year end).
A3: Year # | B3: 1 | C3: 2 | D3: 3 | E3: 4 | F3: 5
B4: Year 1 | C4: Year 2 | D4: Year 3 | E4: Year 4 | F4: Year 5
A5: Cash | B5: =INDEX(Monthly!$C$91:$BJ$91,B$3*12) -> 91651.565 | C5: =INDEX(Monthly!$C$91:$BJ$91,C$3*12) -> 284178.03 | D5: =INDEX(Monthly!$C$91:$BJ$91,D$3*12) -> 512599.78 | E5: =INDEX(Monthly!$C$91:$BJ$91,E$3*12) -> 776355.59 | F5: =INDEX(Monthly!$C$91:$BJ$91,F$3*12) -> 1099044.1
A6: Accounts receivable | B6: =INDEX(Monthly!$C$77:$BJ$77,B$3*12) -> 14828.906 | C6: =INDEX(Monthly!$C$77:$BJ$77,C$3*12) -> 16559.986 | D6: =INDEX(Monthly!$C$77:$BJ$77,D$3*12) -> 17568.489 | E6: =INDEX(Monthly!$C$77:$BJ$77,E$3*12) -> 18638.41 | F6: =INDEX(Monthly!$C$77:$BJ$77,F$3*12) -> 19773.489
A7: Inventory | B7: =INDEX(Monthly!$C$78:$BJ$78,B$3*12) -> 20419.042 | C7: =INDEX(Monthly!$C$78:$BJ$78,C$3*12) -> 21938.219 | D7: =INDEX(Monthly!$C$78:$BJ$78,D$3*12) -> 22957.047 | E7: =INDEX(Monthly!$C$78:$BJ$78,E$3*12) -> 24028.406 | F7: =INDEX(Monthly!$C$78:$BJ$78,F$3*12) -> 25155.209
A8: Net fixed assets | B8: =INDEX(Monthly!$C$68:$BJ$68,B$3*12) -> 334250 | C8: =INDEX(Monthly!$C$68:$BJ$68,C$3*12) -> 304000 | D8: =INDEX(Monthly!$C$68:$BJ$68,D$3*12) -> 271250 | E8: =INDEX(Monthly!$C$68:$BJ$68,E$3*12) -> 236000 | F8: =INDEX(Monthly!$C$68:$BJ$68,F$3*12) -> 198250
A9: Total assets | B9: =INDEX(Monthly!$C$105:$BJ$105,B$3*12) -> 461149.51 | C9: =INDEX(Monthly!$C$105:$BJ$105,C$3*12) -> 626676.24 | D9: =INDEX(Monthly!$C$105:$BJ$105,D$3*12) -> 824375.32 | E9: =INDEX(Monthly!$C$105:$BJ$105,E$3*12) -> 1055022.4 | F9: =INDEX(Monthly!$C$105:$BJ$105,F$3*12) -> 1342222.8
A10: Accounts payable | B10: =INDEX(Monthly!$C$79:$BJ$79,B$3*12) -> 63809.505 | C10: =INDEX(Monthly!$C$79:$BJ$79,C$3*12) -> 68556.934 | D10: =INDEX(Monthly!$C$79:$BJ$79,D$3*12) -> 71740.773 | E10: =INDEX(Monthly!$C$79:$BJ$79,E$3*12) -> 75088.769 | F10: =INDEX(Monthly!$C$79:$BJ$79,F$3*12) -> 78610.028
A11: Loan | B11: =INDEX(Monthly!$C$74:$BJ$74,B$3*12) -> 217261.9 | C11: =INDEX(Monthly!$C$74:$BJ$74,C$3*12) -> 181547.62 | D11: =INDEX(Monthly!$C$74:$BJ$74,D$3*12) -> 145833.33 | E11: =INDEX(Monthly!$C$74:$BJ$74,E$3*12) -> 110119.05 | F11: =INDEX(Monthly!$C$74:$BJ$74,F$3*12) -> 74404.762
A12: Total liabilities | B12: =INDEX(Monthly!$C$106:$BJ$106,B$3*12) -> 281071.41 | C12: =INDEX(Monthly!$C$106:$BJ$106,C$3*12) -> 250104.55 | D12: =INDEX(Monthly!$C$106:$BJ$106,D$3*12) -> 217574.11 | E12: =INDEX(Monthly!$C$106:$BJ$106,E$3*12) -> 185207.82 | F12: =INDEX(Monthly!$C$106:$BJ$106,F$3*12) -> 153014.79
A13: Paid-in capital | B13: =INDEX(Monthly!$C$103:$BJ$103,B$3*12) -> 480000 | C13: =INDEX(Monthly!$C$103:$BJ$103,C$3*12) -> 480000 | D13: =INDEX(Monthly!$C$103:$BJ$103,D$3*12) -> 480000 | E13: =INDEX(Monthly!$C$103:$BJ$103,E$3*12) -> 480000 | F13: =INDEX(Monthly!$C$103:$BJ$103,F$3*12) -> 480000
A14: Retained earnings | B14: =INDEX(Monthly!$C$104:$BJ$104,B$3*12) -> -299921.9 | C14: =INDEX(Monthly!$C$104:$BJ$104,C$3*12) -> -103428.31 | D14: =INDEX(Monthly!$C$104:$BJ$104,D$3*12) -> 126801.21 | E14: =INDEX(Monthly!$C$104:$BJ$104,E$3*12) -> 389814.59 | F14: =INDEX(Monthly!$C$104:$BJ$104,F$3*12) -> 709207.99
A15: Total equity | B15: =INDEX(Monthly!$C$107:$BJ$107,B$3*12) -> 180078.1 | C15: =INDEX(Monthly!$C$107:$BJ$107,C$3*12) -> 376571.69 | D15: =INDEX(Monthly!$C$107:$BJ$107,D$3*12) -> 606801.21 | E15: =INDEX(Monthly!$C$107:$BJ$107,E$3*12) -> 869814.59 | F15: =INDEX(Monthly!$C$107:$BJ$107,F$3*12) -> 1189208
A16: Total liabilities & equity | B16: =INDEX(Monthly!$C$108:$BJ$108,B$3*12) -> 461149.51 | C16: =INDEX(Monthly!$C$108:$BJ$108,C$3*12) -> 626676.24 | D16: =INDEX(Monthly!$C$108:$BJ$108,D$3*12) -> 824375.32 | E16: =INDEX(Monthly!$C$108:$BJ$108,E$3*12) -> 1055022.4 | F16: =INDEX(Monthly!$C$108:$BJ$108,F$3*12) -> 1342222.8
A17: Check: assets − liabilities − equity (must be 0) | B17: =INDEX(Monthly!$C$109:$BJ$109,B$3*12) -> 0 | C17: =INDEX(Monthly!$C$109:$BJ$109,C$3*12) -> 0 | D17: =INDEX(Monthly!$C$109:$BJ$109,D$3*12) -> 0 | E17: =INDEX(Monthly!$C$109:$BJ$109,E$3*12) -> 0 | F17: =INDEX(Monthly!$C$109:$BJ$109,F$3*12) -> 0

Sheet Monthly
A1: Monthly projection | D1: =HYPERLINK("#'Cover'!A1","◂ Contents") -> ◂ Contents
A2: $ unless stated; costs shown as negatives. Every period uses the same formula.
A3: Month | C3: M1 | D3: M2 | E3: M3 | F3: M4 | G3: M5 | H3: M6 | I3: M7 | J3: M8 | K3: M9 | L3: M10 | M3: M11 | N3: M12 | O3: M13 | P3: M14 | Q3: M15 | R3: M16 | S3: M17 | T3: M18 | U3: M19 | V3: M20 | W3: M21 | X3: M22 | Y3: M23 | Z3: M24 | AA3: M25 | AB3: M26 | AC3: M27 | AD3: M28 | AE3: M29 | AF3: M30 | AG3: M31 | AH3: M32 | AI3: M33 | AJ3: M34 | AK3: M35 | AL3: M36 | AM3: M37 | AN3: M38 | AO3: M39 | AP3: M40 | AQ3: M41 | AR3: M42 | AS3: M43 | AT3: M44 | AU3: M45 | AV3: M46 | AW3: M47 | AX3: M48 | AY3: M49 | AZ3: M50 | BA3: M51 | BB3: M52 | BC3: M53 | BD3: M54 | BE3: M55 | BF3: M56 | BG3: M57 | BH3: M58 | BI3: M59 | BJ3: M60
A4: Period # | C4: 1 | D4: 2 | E4: 3 | F4: 4 | G4: 5 | H4: 6 | I4: 7 | J4: 8 | K4: 9 | L4: 10 | M4: 11 | N4: 12 | O4: 13 | P4: 14 | Q4: 15 | R4: 16 | S4: 17 | T4: 18 | U4: 19 | V4: 20 | W4: 21 | X4: 22 | Y4: 23 | Z4: 24 | AA4: 25 | AB4: 26 | AC4: 27 | AD4: 28 | AE4: 29 | AF4: 30 | AG4: 31 | AH4: 32 | AI4: 33 | AJ4: 34 | AK4: 35 | AL4: 36 | AM4: 37 | AN4: 38 | AO4: 39 | AP4: 40 | AQ4: 41 | AR4: 42 | AS4: 43 | AT4: 44 | AU4: 45 | AV4: 46 | AW4: 47 | AX4: 48 | AY4: 49 | AZ4: 50 | BA4: 51 | BB4: 52 | BC4: 53 | BD4: 54 | BE4: 55 | BF4: 56 | BG4: 57 | BH4: 58 | BI4: 59 | BJ4: 60
A5: Year # | C5: =ROUNDUP(C4*1/12,0) -> 1 | D5: =ROUNDUP(D4*1/12,0) -> 1 | E5: =ROUNDUP(E4*1/12,0) -> 1 | F5: =ROUNDUP(F4*1/12,0) -> 1 | G5: =ROUNDUP(G4*1/12,0) -> 1 | H5: =ROUNDUP(H4*1/12,0) -> 1 | I5: =ROUNDUP(I4*1/12,0) -> 1 | J5: =ROUNDUP(J4*1/12,0) -> 1 | ... BJ5: =ROUNDUP(BJ4*1/12,0) -> 5
A7: Demand
A8: Helper: months of the period still on the ramp-up | C8: =MAX(0,MIN(1,Inputs!$E$11-(C$4-1)*1)) -> 1 | D8: =MAX(0,MIN(1,Inputs!$E$11-(D$4-1)*1)) -> 1 | E8: =MAX(0,MIN(1,Inputs!$E$11-(E$4-1)*1)) -> 1 | F8: =MAX(0,MIN(1,Inputs!$E$11-(F$4-1)*1)) -> 1 | G8: =MAX(0,MIN(1,Inputs!$E$11-(G$4-1)*1)) -> 1 | H8: =MAX(0,MIN(1,Inputs!$E$11-(H$4-1)*1)) -> 1 | I8: =MAX(0,MIN(1,Inputs!$E$11-(I$4-1)*1)) -> 1 | J8: =MAX(0,MIN(1,Inputs!$E$11-(J$4-1)*1)) -> 1 | ... BJ8: =MAX(0,MIN(1,Inputs!$E$11-(BJ$4-1)*1)) -> 0
A9: Ramp-up factor (share of mature order volume) | C9: =IF(Inputs!$E$11<=0,1,(C8*Inputs!$E$12+(1-Inputs!$E$12)/MAX(1,Inputs!$E$11)*(C8*(C$4-1)*1+C8*(C8-1)/2)+1-C8)/1) -> 0.4 | D9: =IF(Inputs!$E$11<=0,1,(D8*Inputs!$E$12+(1-Inputs!$E$12)/MAX(1,Inputs!$E$11)*(D8*(D$4-1)*1+D8*(D8-1)/2)+1-D8)/1) -> 0.45 | E9: =IF(Inputs!$E$11<=0,1,(E8*Inputs!$E$12+(1-Inputs!$E$12)/MAX(1,Inputs!$E$11)*(E8*(E$4-1)*1+E8*(E8-1)/2)+1-E8)/1) -> 0.5 | F9: =IF(Inputs!$E$11<=0,1,(F8*Inputs!$E$12+(1-Inputs!$E$12)/MAX(1,Inputs!$E$11)*(F8*(F$4-1)*1+F8*(F8-1)/2)+1-F8)/1) -> 0.55 | G9: =IF(Inputs!$E$11<=0,1,(G8*Inputs!$E$12+(1-Inputs!$E$12)/MAX(1,Inputs!$E$11)*(G8*(G$4-1)*1+G8*(G8-1)/2)+1-G8)/1) -> 0.6 | H9: =IF(Inputs!$E$11<=0,1,(H8*Inputs!$E$12+(1-Inputs!$E$12)/MAX(1,Inputs!$E$11)*(H8*(H$4-1)*1+H8*(H8-1)/2)+1-H8)/1) -> 0.65 | I9: =IF(Inputs!$E$11<=0,1,(I8*Inputs!$E$12+(1-Inputs!$E$12)/MAX(1,Inputs!$E$11)*(I8*(I$4-1)*1+I8*(I8-1)/2)+1-I8)/1) -> 0.7 | J9: =IF(Inputs!$E$11<=0,1,(J8*Inputs!$E$12+(1-Inputs!$E$12)/MAX(1,Inputs!$E$11)*(J8*(J$4-1)*1+J8*(J8-1)/2)+1-J8)/1) -> 0.75 | ... BJ9: =IF(Inputs!$E$11<=0,1,(BJ8*Inputs!$E$12+(1-Inputs!$E$12)/MAX(1,Inputs!$E$11)*(BJ8*(BJ$4-1)*1+BJ8*(BJ8-1)/2)+1-BJ8)/1) -> 1
A10: Repair orders demanded | C10: =Inputs!$E$7*(1+Inputs!$E$8)^(C$5-1)*Inputs!$E$10*1*C9 -> 135 | D10: =Inputs!$E$7*(1+Inputs!$E$8)^(D$5-1)*Inputs!$E$10*1*D9 -> 151.875 | E10: =Inputs!$E$7*(1+Inputs!$E$8)^(E$5-1)*Inputs!$E$10*1*E9 -> 168.75 | F10: =Inputs!$E$7*(1+Inputs!$E$8)^(F$5-1)*Inputs!$E$10*1*F9 -> 185.625 | G10: =Inputs!$E$7*(1+Inputs!$E$8)^(G$5-1)*Inputs!$E$10*1*G9 -> 202.5 | H10: =Inputs!$E$7*(1+Inputs!$E$8)^(H$5-1)*Inputs!$E$10*1*H9 -> 219.375 | I10: =Inputs!$E$7*(1+Inputs!$E$8)^(I$5-1)*Inputs!$E$10*1*I9 -> 236.25 | J10: =Inputs!$E$7*(1+Inputs!$E$8)^(J$5-1)*Inputs!$E$10*1*J9 -> 253.125 | ... BJ10: =Inputs!$E$7*(1+Inputs!$E$8)^(BJ$5-1)*Inputs!$E$10*1*BJ9 -> 379.85922
A11: Billed hours demanded | C11: =C10*Inputs!$E$9 -> 270 | D11: =D10*Inputs!$E$9 -> 303.75 | E11: =E10*Inputs!$E$9 -> 337.5 | F11: =F10*Inputs!$E$9 -> 371.25 | G11: =G10*Inputs!$E$9 -> 405 | H11: =H10*Inputs!$E$9 -> 438.75 | I11: =I10*Inputs!$E$9 -> 472.5 | J11: =J10*Inputs!$E$9 -> 506.25 | ... BJ11: =BJ10*Inputs!$E$9 -> 759.71845
A13: Capacity
A14: Technicians (FTE) | C14: =Headcount!C8 -> 5 | D14: =Headcount!D8 -> 5 | E14: =Headcount!E8 -> 5 | F14: =Headcount!F8 -> 5 | G14: =Headcount!G8 -> 5 | H14: =Headcount!H8 -> 5 | I14: =Headcount!I8 -> 5 | J14: =Headcount!J8 -> 5 | ... BJ14: =Headcount!BJ8 -> 5
A15: Bay capacity (bays × billed hours per bay-day × operating days) | C15: =Inputs!$E$15*Inputs!$E$16*Inputs!$E$10*1 -> 975 | D15: =Inputs!$E$15*Inputs!$E$16*Inputs!$E$10*1 -> 975 | E15: =Inputs!$E$15*Inputs!$E$16*Inputs!$E$10*1 -> 975 | F15: =Inputs!$E$15*Inputs!$E$16*Inputs!$E$10*1 -> 975 | G15: =Inputs!$E$15*Inputs!$E$16*Inputs!$E$10*1 -> 975 | H15: =Inputs!$E$15*Inputs!$E$16*Inputs!$E$10*1 -> 975 | I15: =Inputs!$E$15*Inputs!$E$16*Inputs!$E$10*1 -> 975 | J15: =Inputs!$E$15*Inputs!$E$16*Inputs!$E$10*1 -> 975 | ... BJ15: =Inputs!$E$15*Inputs!$E$16*Inputs!$E$10*1 -> 975
A16: Technician capacity (FTE × paid hours × efficiency × operating days) | C16: =C14*Inputs!$E$17*Inputs!$E$18*Inputs!$E$10*1 -> 880 | D16: =D14*Inputs!$E$17*Inputs!$E$18*Inputs!$E$10*1 -> 880 | E16: =E14*Inputs!$E$17*Inputs!$E$18*Inputs!$E$10*1 -> 880 | F16: =F14*Inputs!$E$17*Inputs!$E$18*Inputs!$E$10*1 -> 880 | G16: =G14*Inputs!$E$17*Inputs!$E$18*Inputs!$E$10*1 -> 880 | H16: =H14*Inputs!$E$17*Inputs!$E$18*Inputs!$E$10*1 -> 880 | I16: =I14*Inputs!$E$17*Inputs!$E$18*Inputs!$E$10*1 -> 880 | J16: =J14*Inputs!$E$17*Inputs!$E$18*Inputs!$E$10*1 -> 880 | ... BJ16: =BJ14*Inputs!$E$17*Inputs!$E$18*Inputs!$E$10*1 -> 880
A17: Billed-hour capacity (lower of bays and technicians) | C17: =MIN(C15,C16) -> 880 | D17: =MIN(D15,D16) -> 880 | E17: =MIN(E15,E16) -> 880 | F17: =MIN(F15,F16) -> 880 | G17: =MIN(G15,G16) -> 880 | H17: =MIN(H15,H16) -> 880 | I17: =MIN(I15,I16) -> 880 | J17: =MIN(J15,J16) -> 880 | ... BJ17: =MIN(BJ15,BJ16) -> 880
A18: Billed labor hours (demand capped by capacity) | C18: =MIN(C11,C17) -> 270 | D18: =MIN(D11,D17) -> 303.75 | E18: =MIN(E11,E17) -> 337.5 | F18: =MIN(F11,F17) -> 371.25 | G18: =MIN(G11,G17) -> 405 | H18: =MIN(H11,H17) -> 438.75 | I18: =MIN(I11,I17) -> 472.5 | J18: =MIN(J11,J17) -> 506.25 | ... BJ18: =MIN(BJ11,BJ17) -> 759.71845
A19: Billed hours lost to the capacity limit | C19: =C11-C18 -> 0 | D19: =D11-D18 -> 0 | E19: =E11-E18 -> 0 | F19: =F11-F18 -> 0 | G19: =G11-G18 -> 0 | H19: =H11-H18 -> 0 | I19: =I11-I18 -> 0 | J19: =J11-J18 -> 0 | ... BJ19: =BJ11-BJ18 -> 0
A20: Share of demand the shop can serve | C20: =MIN(1,C18/MAX(1,C11)) -> 1 | D20: =MIN(1,D18/MAX(1,D11)) -> 1 | E20: =MIN(1,E18/MAX(1,E11)) -> 1 | F20: =MIN(1,F18/MAX(1,F11)) -> 1 | G20: =MIN(1,G18/MAX(1,G11)) -> 1 | H20: =MIN(1,H18/MAX(1,H11)) -> 1 | I20: =MIN(1,I18/MAX(1,I11)) -> 1 | J20: =MIN(1,J18/MAX(1,J11)) -> 1 | ... BJ20: =MIN(1,BJ18/MAX(1,BJ11)) -> 1
A21: Repair orders completed | C21: =C10*C20 -> 135 | D21: =D10*D20 -> 151.875 | E21: =E10*E20 -> 168.75 | F21: =F10*F20 -> 185.625 | G21: =G10*G20 -> 202.5 | H21: =H10*H20 -> 219.375 | I21: =I10*I20 -> 236.25 | J21: =J10*J20 -> 253.125 | ... BJ21: =BJ10*BJ20 -> 379.85922
A23: Revenue
A24: Effective labor rate per billed hour | C24: =Inputs!$E$21*(1+Inputs!$E$22)^(C$5-1) -> 125 | D24: =Inputs!$E$21*(1+Inputs!$E$22)^(D$5-1) -> 125 | E24: =Inputs!$E$21*(1+Inputs!$E$22)^(E$5-1) -> 125 | F24: =Inputs!$E$21*(1+Inputs!$E$22)^(F$5-1) -> 125 | G24: =Inputs!$E$21*(1+Inputs!$E$22)^(G$5-1) -> 125 | H24: =Inputs!$E$21*(1+Inputs!$E$22)^(H$5-1) -> 125 | I24: =Inputs!$E$21*(1+Inputs!$E$22)^(I$5-1) -> 125 | J24: =Inputs!$E$21*(1+Inputs!$E$22)^(J$5-1) -> 125 | ... BJ24: =Inputs!$E$21*(1+Inputs!$E$22)^(BJ$5-1) -> 140.6886
A25: Labor revenue | C25: =C18*C24 -> 33750 | D25: =D18*D24 -> 37968.75 | E25: =E18*E24 -> 42187.5 | F25: =F18*F24 -> 46406.25 | G25: =G18*G24 -> 50625 | H25: =H18*H24 -> 54843.75 | I25: =I18*I24 -> 59062.5 | J25: =J18*J24 -> 63281.25 | ... BJ25: =BJ18*BJ24 -> 106883.73
A26: Parts revenue | C26: =C18*Inputs!$E$26*(1+Inputs!$E$22)^(C$5-1) -> 27000 | D26: =D18*Inputs!$E$26*(1+Inputs!$E$22)^(D$5-1) -> 30375 | E26: =E18*Inputs!$E$26*(1+Inputs!$E$22)^(E$5-1) -> 33750 | F26: =F18*Inputs!$E$26*(1+Inputs!$E$22)^(F$5-1) -> 37125 | G26: =G18*Inputs!$E$26*(1+Inputs!$E$22)^(G$5-1) -> 40500 | H26: =H18*Inputs!$E$26*(1+Inputs!$E$22)^(H$5-1) -> 43875 | I26: =I18*Inputs!$E$26*(1+Inputs!$E$22)^(I$5-1) -> 47250 | J26: =J18*Inputs!$E$26*(1+Inputs!$E$22)^(J$5-1) -> 50625 | ... BJ26: =BJ18*Inputs!$E$26*(1+Inputs!$E$22)^(BJ$5-1) -> 85506.98
A27: Shop supplies fee | C27: =C25*Inputs!$E$23 -> 1687.5 | D27: =D25*Inputs!$E$23 -> 1898.4375 | E27: =E25*Inputs!$E$23 -> 2109.375 | F27: =F25*Inputs!$E$23 -> 2320.3125 | G27: =G25*Inputs!$E$23 -> 2531.25 | H27: =H25*Inputs!$E$23 -> 2742.1875 | I27: =I25*Inputs!$E$23 -> 2953.125 | J27: =J25*Inputs!$E$23 -> 3164.0625 | ... BJ27: =BJ25*Inputs!$E$23 -> 5344.1863
A28: Revenue | C28: =C25+C26+C27 -> 62437.5 | D28: =D25+D26+D27 -> 70242.188 | E28: =E25+E26+E27 -> 78046.875 | F28: =F25+F26+F27 -> 85851.562 | G28: =G25+G26+G27 -> 93656.25 | H28: =H25+H26+H27 -> 101460.94 | I28: =I25+I26+I27 -> 109265.62 | J28: =J25+J26+J27 -> 117070.31 | ... BJ28: =BJ25+BJ26+BJ27 -> 197734.89
A30: Cost of sales
A31: Technician payroll | C31: =Headcount!C14 -> -37375 | D31: =Headcount!D14 -> -37375 | E31: =Headcount!E14 -> -37375 | F31: =Headcount!F14 -> -37375 | G31: =Headcount!G14 -> -37375 | H31: =Headcount!H14 -> -37375 | I31: =Headcount!I14 -> -37375 | J31: =Headcount!J14 -> -37375 | ... BJ31: =Headcount!BJ14 -> -42065.892
A32: Parts cost | C32: =-C26*(1-Inputs!$E$27) -> -14310 | D32: =-D26*(1-Inputs!$E$27) -> -16098.75 | E32: =-E26*(1-Inputs!$E$27) -> -17887.5 | F32: =-F26*(1-Inputs!$E$27) -> -19676.25 | G32: =-G26*(1-Inputs!$E$27) -> -21465 | H32: =-H26*(1-Inputs!$E$27) -> -23253.75 | I32: =-I26*(1-Inputs!$E$27) -> -25042.5 | J32: =-J26*(1-Inputs!$E$27) -> -26831.25 | ... BJ32: =-BJ26*(1-Inputs!$E$27) -> -45318.7
A33: Shop supplies & waste disposal | C33: =-C25*Inputs!$E$30 -> -1181.25 | D33: =-D25*Inputs!$E$30 -> -1328.9062 | E33: =-E25*Inputs!$E$30 -> -1476.5625 | F33: =-F25*Inputs!$E$30 -> -1624.2188 | G33: =-G25*Inputs!$E$30 -> -1771.875 | H33: =-H25*Inputs!$E$30 -> -1919.5312 | I33: =-I25*Inputs!$E$30 -> -2067.1875 | J33: =-J25*Inputs!$E$30 -> -2214.8438 | ... BJ33: =-BJ25*Inputs!$E$30 -> -3740.9304
A34: Comebacks & warranty rework | C34: =-C25*Inputs!$E$31 -> -1012.5 | D34: =-D25*Inputs!$E$31 -> -1139.0625 | E34: =-E25*Inputs!$E$31 -> -1265.625 | F34: =-F25*Inputs!$E$31 -> -1392.1875 | G34: =-G25*Inputs!$E$31 -> -1518.75 | H34: =-H25*Inputs!$E$31 -> -1645.3125 | I34: =-I25*Inputs!$E$31 -> -1771.875 | J34: =-J25*Inputs!$E$31 -> -1898.4375 | ... BJ34: =-BJ25*Inputs!$E$31 -> -3206.5118
A35: Cost of sales | C35: =C31+C32+C33+C34 -> -53878.75 | D35: =D31+D32+D33+D34 -> -55941.719 | E35: =E31+E32+E33+E34 -> -58004.688 | F35: =F31+F32+F33+F34 -> -60067.656 | G35: =G31+G32+G33+G34 -> -62130.625 | H35: =H31+H32+H33+H34 -> -64193.594 | I35: =I31+I32+I33+I34 -> -66256.562 | J35: =J31+J32+J33+J34 -> -68319.531 | ... BJ35: =BJ31+BJ32+BJ33+BJ34 -> -94332.034
A36: Gross profit | C36: =C28+C35 -> 8558.75 | D36: =D28+D35 -> 14300.469 | E36: =E28+E35 -> 20042.188 | F36: =F28+F35 -> 25783.906 | G36: =G28+G35 -> 31525.625 | H36: =H28+H35 -> 37267.344 | I36: =I28+I35 -> 43009.062 | J36: =J28+J35 -> 48750.781 | ... BJ36: =BJ28+BJ35 -> 103402.86
A38: Operating expenses
A39: Advisors, manager & other payroll | C39: =Headcount!C17-Headcount!C14 -> -17729.167 | D39: =Headcount!D17-Headcount!D14 -> -17729.167 | E39: =Headcount!E17-Headcount!E14 -> -17729.167 | F39: =Headcount!F17-Headcount!F14 -> -17729.167 | G39: =Headcount!G17-Headcount!G14 -> -17729.167 | H39: =Headcount!H17-Headcount!H14 -> -17729.167 | I39: =Headcount!I17-Headcount!I14 -> -17729.167 | J39: =Headcount!J17-Headcount!J14 -> -17729.167 | ... BJ39: =Headcount!BJ17-Headcount!BJ14 -> -19954.333
A40: Shop rent or land cost | C40: =-Inputs!$E$36*(1+Inputs!$E$37)^(C$5-1)*1 -> -18000 | D40: =-Inputs!$E$36*(1+Inputs!$E$37)^(D$5-1)*1 -> -18000 | E40: =-Inputs!$E$36*(1+Inputs!$E$37)^(E$5-1)*1 -> -18000 | F40: =-Inputs!$E$36*(1+Inputs!$E$37)^(F$5-1)*1 -> -18000 | G40: =-Inputs!$E$36*(1+Inputs!$E$37)^(G$5-1)*1 -> -18000 | H40: =-Inputs!$E$36*(1+Inputs!$E$37)^(H$5-1)*1 -> -18000 | I40: =-Inputs!$E$36*(1+Inputs!$E$37)^(I$5-1)*1 -> -18000 | J40: =-Inputs!$E$36*(1+Inputs!$E$37)^(J$5-1)*1 -> -18000 | ... BJ40: =-Inputs!$E$36*(1+Inputs!$E$37)^(BJ$5-1)*1 -> -20259.159
A41: Insurance | C41: =-Inputs!$E$38*(1+Inputs!$E$33)^(C$5-1)*1 -> -4500 | D41: =-Inputs!$E$38*(1+Inputs!$E$33)^(D$5-1)*1 -> -4500 | E41: =-Inputs!$E$38*(1+Inputs!$E$33)^(E$5-1)*1 -> -4500 | F41: =-Inputs!$E$38*(1+Inputs!$E$33)^(F$5-1)*1 -> -4500 | G41: =-Inputs!$E$38*(1+Inputs!$E$33)^(G$5-1)*1 -> -4500 | H41: =-Inputs!$E$38*(1+Inputs!$E$33)^(H$5-1)*1 -> -4500 | I41: =-Inputs!$E$38*(1+Inputs!$E$33)^(I$5-1)*1 -> -4500 | J41: =-Inputs!$E$38*(1+Inputs!$E$33)^(J$5-1)*1 -> -4500 | ... BJ41: =-Inputs!$E$38*(1+Inputs!$E$33)^(BJ$5-1)*1 -> -5064.7896
A42: Software, utilities & other G&A | C42: =-Inputs!$E$39*(1+Inputs!$E$33)^(C$5-1)*1 -> -9000 | D42: =-Inputs!$E$39*(1+Inputs!$E$33)^(D$5-1)*1 -> -9000 | E42: =-Inputs!$E$39*(1+Inputs!$E$33)^(E$5-1)*1 -> -9000 | F42: =-Inputs!$E$39*(1+Inputs!$E$33)^(F$5-1)*1 -> -9000 | G42: =-Inputs!$E$39*(1+Inputs!$E$33)^(G$5-1)*1 -> -9000 | H42: =-Inputs!$E$39*(1+Inputs!$E$33)^(H$5-1)*1 -> -9000 | I42: =-Inputs!$E$39*(1+Inputs!$E$33)^(I$5-1)*1 -> -9000 | J42: =-Inputs!$E$39*(1+Inputs!$E$33)^(J$5-1)*1 -> -9000 | ... BJ42: =-Inputs!$E$39*(1+Inputs!$E$33)^(BJ$5-1)*1 -> -10129.579
A43: Marketing | C43: =-Inputs!$E$40*(1+Inputs!$E$41)^(C$5-1)*1 -> -7000 | D43: =-Inputs!$E$40*(1+Inputs!$E$41)^(D$5-1)*1 -> -7000 | E43: =-Inputs!$E$40*(1+Inputs!$E$41)^(E$5-1)*1 -> -7000 | F43: =-Inputs!$E$40*(1+Inputs!$E$41)^(F$5-1)*1 -> -7000 | G43: =-Inputs!$E$40*(1+Inputs!$E$41)^(G$5-1)*1 -> -7000 | H43: =-Inputs!$E$40*(1+Inputs!$E$41)^(H$5-1)*1 -> -7000 | I43: =-Inputs!$E$40*(1+Inputs!$E$41)^(I$5-1)*1 -> -7000 | J43: =-Inputs!$E$40*(1+Inputs!$E$41)^(J$5-1)*1 -> -7000 | ... BJ43: =-Inputs!$E$40*(1+Inputs!$E$41)^(BJ$5-1)*1 -> -2867.2
A44: Card processing fees | C44: =-C28*Inputs!$E$32 -> -1873.125 | D44: =-D28*Inputs!$E$32 -> -2107.2656 | E44: =-E28*Inputs!$E$32 -> -2341.4062 | F44: =-F28*Inputs!$E$32 -> -2575.5469 | G44: =-G28*Inputs!$E$32 -> -2809.6875 | H44: =-H28*Inputs!$E$32 -> -3043.8281 | I44: =-I28*Inputs!$E$32 -> -3277.9688 | J44: =-J28*Inputs!$E$32 -> -3512.1094 | ... BJ44: =-BJ28*Inputs!$E$32 -> -5932.0468
A45: Total operating expenses | C45: =C39+C40+C41+C42+C43+C44 -> -58102.292 | D45: =D39+D40+D41+D42+D43+D44 -> -58336.432 | E45: =E39+E40+E41+E42+E43+E44 -> -58570.573 | F45: =F39+F40+F41+F42+F43+F44 -> -58804.714 | G45: =G39+G40+G41+G42+G43+G44 -> -59038.854 | H45: =H39+H40+H41+H42+H43+H44 -> -59272.995 | I45: =I39+I40+I41+I42+I43+I44 -> -59507.135 | J45: =J39+J40+J41+J42+J43+J44 -> -59741.276 | ... BJ45: =BJ39+BJ40+BJ41+BJ42+BJ43+BJ44 -> -64207.108
A46: EBITDA | C46: =C36+C45 -> -49543.542 | D46: =D36+D45 -> -44035.964 | E46: =E36+E45 -> -38528.385 | F46: =F36+F45 -> -33020.807 | G46: =G36+G45 -> -27513.229 | H46: =H36+H45 -> -22005.651 | I46: =I36+I45 -> -16498.073 | J46: =J36+J45 -> -10990.495 | ... BJ46: =BJ36+BJ45 -> 39195.751
A48: Profit after depreciation, interest, tax
A49: EBIT | C49: =C46+C66 -> -53522.708 | D49: =D46+D66 -> -48015.13 | E49: =E46+E66 -> -42507.552 | F49: =F46+F66 -> -36999.974 | G49: =G46+G66 -> -31492.396 | H49: =H46+H66 -> -25984.818 | I49: =I46+I66 -> -20477.24 | J49: =J46+J66 -> -14969.661 | ... BJ49: =BJ46+BJ66 -> 34383.251
A50: Interest on loan (average balance after drawdown) | C50: =-(C71+C72+C74)/2*Inputs!$E$69/12 -> -1875 | D50: =-(D71+D72+D74)/2*Inputs!$E$69/12 -> -1863.8393 | E50: =-(E71+E72+E74)/2*Inputs!$E$69/12 -> -1841.5179 | F50: =-(F71+F72+F74)/2*Inputs!$E$69/12 -> -1819.1964 | G50: =-(G71+G72+G74)/2*Inputs!$E$69/12 -> -1796.875 | H50: =-(H71+H72+H74)/2*Inputs!$E$69/12 -> -1774.5536 | I50: =-(I71+I72+I74)/2*Inputs!$E$69/12 -> -1752.2321 | J50: =-(J71+J72+J74)/2*Inputs!$E$69/12 -> -1729.9107 | ... BJ50: =-(BJ71+BJ72+BJ74)/2*Inputs!$E$69/12 -> -569.19643
A51: Pre-tax income | C51: =C49+C50 -> -55397.708 | D51: =D49+D50 -> -49878.969 | E51: =E49+E50 -> -44349.07 | F51: =F49+F50 -> -38819.17 | G51: =G49+G50 -> -33289.271 | H51: =H49+H50 -> -27759.371 | I51: =I49+I50 -> -22229.472 | J51: =J49+J50 -> -16699.572 | ... BJ51: =BJ49+BJ50 -> 33814.055
A52: Helper: cumulative pre-tax income | C52: =C51 -> -55397.708 | D52: =C52+D51 -> -105276.68 | E52: =D52+E51 -> -149625.75 | F52: =E52+F51 -> -188444.92 | G52: =F52+G51 -> -221734.19 | H52: =G52+H51 -> -249493.56 | I52: =H52+I51 -> -271723.03 | J52: =I52+J51 -> -288422.6 | K52: =J52+K51 -> -299592.28 | ... BJ52: =BI52+BJ51 -> 897731.63
A53: Helper: cumulative taxable income (losses carried forward) | C53: =MAX(0,C52) -> 0 | D53: =MAX(C53,D52) -> 0 | E53: =MAX(D53,E52) -> 0 | F53: =MAX(E53,F52) -> 0 | G53: =MAX(F53,G52) -> 0 | H53: =MAX(G53,H52) -> 0 | I53: =MAX(H53,I52) -> 0 | J53: =MAX(I53,J52) -> 0 | K53: =MAX(J53,K52) -> 0 | ... BJ53: =MAX(BI53,BJ52) -> 897731.63
A54: Income tax | C54: =-C53*Inputs!$E$79 -> 0 | D54: =-(D53-C53)*Inputs!$E$79 -> 0 | E54: =-(E53-D53)*Inputs!$E$79 -> 0 | F54: =-(F53-E53)*Inputs!$E$79 -> 0 | G54: =-(G53-F53)*Inputs!$E$79 -> 0 | H54: =-(H53-G53)*Inputs!$E$79 -> 0 | I54: =-(I53-H53)*Inputs!$E$79 -> 0 | J54: =-(J53-I53)*Inputs!$E$79 -> 0 | K54: =-(K53-J53)*Inputs!$E$79 -> 0 | ... BJ54: =-(BJ53-BI53)*Inputs!$E$79 -> -7100.9515
A55: Net income | C55: =C51+C54 -> -55397.708 | D55: =D51+D54 -> -49878.969 | E55: =E51+E54 -> -44349.07 | F55: =F51+F54 -> -38819.17 | G55: =G51+G54 -> -33289.271 | H55: =H51+H54 -> -27759.371 | I55: =I51+I54 -> -22229.472 | J55: =J51+J54 -> -16699.572 | ... BJ55: =BJ51+BJ54 -> 26713.103
A57: Fixed assets & capital spending
A58: Lifts & bay equipment | C58: =IF(C$4=1,Inputs!$E$15*Inputs!$E$44,0) -> 132000 | D58: =IF(D$4=1,Inputs!$E$15*Inputs!$E$44,0) -> 0 | E58: =IF(E$4=1,Inputs!$E$15*Inputs!$E$44,0) -> 0 | F58: =IF(F$4=1,Inputs!$E$15*Inputs!$E$44,0) -> 0 | G58: =IF(G$4=1,Inputs!$E$15*Inputs!$E$44,0) -> 0 | H58: =IF(H$4=1,Inputs!$E$15*Inputs!$E$44,0) -> 0 | I58: =IF(I$4=1,Inputs!$E$15*Inputs!$E$44,0) -> 0 | J58: =IF(J$4=1,Inputs!$E$15*Inputs!$E$44,0) -> 0 | ... BJ58: =IF(BJ$4=1,Inputs!$E$15*Inputs!$E$44,0) -> 0
A59: Diagnostic tools & scan equipment | C59: =IF(C$4=1,Inputs!$E$45,0) -> 70000 | D59: =IF(D$4=1,Inputs!$E$45,0) -> 0 | E59: =IF(E$4=1,Inputs!$E$45,0) -> 0 | F59: =IF(F$4=1,Inputs!$E$45,0) -> 0 | G59: =IF(G$4=1,Inputs!$E$45,0) -> 0 | H59: =IF(H$4=1,Inputs!$E$45,0) -> 0 | I59: =IF(I$4=1,Inputs!$E$45,0) -> 0 | J59: =IF(J$4=1,Inputs!$E$45,0) -> 0 | ... BJ59: =IF(BJ$4=1,Inputs!$E$45,0) -> 0
A60: Leasehold improvements & signage | C60: =IF(C$4=1,Inputs!$E$46,0) -> 180000 | D60: =IF(D$4=1,Inputs!$E$46,0) -> 0 | E60: =IF(E$4=1,Inputs!$E$46,0) -> 0 | F60: =IF(F$4=1,Inputs!$E$46,0) -> 0 | G60: =IF(G$4=1,Inputs!$E$46,0) -> 0 | H60: =IF(H$4=1,Inputs!$E$46,0) -> 0 | I60: =IF(I$4=1,Inputs!$E$46,0) -> 0 | J60: =IF(J$4=1,Inputs!$E$46,0) -> 0 | ... BJ60: =IF(BJ$4=1,Inputs!$E$46,0) -> 0
A61: Land or building (not depreciated) | C61: =IF(C$4=1,Inputs!$E$47,0) -> 0 | D61: =IF(D$4=1,Inputs!$E$47,0) -> 0 | E61: =IF(E$4=1,Inputs!$E$47,0) -> 0 | F61: =IF(F$4=1,Inputs!$E$47,0) -> 0 | G61: =IF(G$4=1,Inputs!$E$47,0) -> 0 | H61: =IF(H$4=1,Inputs!$E$47,0) -> 0 | I61: =IF(I$4=1,Inputs!$E$47,0) -> 0 | J61: =IF(J$4=1,Inputs!$E$47,0) -> 0 | ... BJ61: =IF(BJ$4=1,Inputs!$E$47,0) -> 0
A62: Equipment & tool refresh (first period of each year from year 2) | C62: =IF(AND(C$5>1,MOD(C$4-1,12)=0),Inputs!$E$48,0) -> 0 | D62: =IF(AND(D$5>1,MOD(D$4-1,12)=0),Inputs!$E$48,0) -> 0 | E62: =IF(AND(E$5>1,MOD(E$4-1,12)=0),Inputs!$E$48,0) -> 0 | F62: =IF(AND(F$5>1,MOD(F$4-1,12)=0),Inputs!$E$48,0) -> 0 | G62: =IF(AND(G$5>1,MOD(G$4-1,12)=0),Inputs!$E$48,0) -> 0 | H62: =IF(AND(H$5>1,MOD(H$4-1,12)=0),Inputs!$E$48,0) -> 0 | I62: =IF(AND(I$5>1,MOD(I$4-1,12)=0),Inputs!$E$48,0) -> 0 | J62: =IF(AND(J$5>1,MOD(J$4-1,12)=0),Inputs!$E$48,0) -> 0 | ... BJ62: =IF(AND(BJ$5>1,MOD(BJ$4-1,12)=0),Inputs!$E$48,0) -> 0
A63: Capital spending | C63: =C58+C59+C60+C61+C62 -> 382000 | D63: =D58+D59+D60+D61+D62 -> 0 | E63: =E58+E59+E60+E61+E62 -> 0 | F63: =F58+F59+F60+F61+F62 -> 0 | G63: =G58+G59+G60+G61+G62 -> 0 | H63: =H58+H59+H60+H61+H62 -> 0 | I63: =I58+I59+I60+I61+I62 -> 0 | J63: =J58+J59+J60+J61+J62 -> 0 | ... BJ63: =BJ58+BJ59+BJ60+BJ61+BJ62 -> 0
A64: Fixed assets at cost | C64: =C63 -> 382000 | D64: =C64+D63 -> 382000 | E64: =D64+E63 -> 382000 | F64: =E64+F63 -> 382000 | G64: =F64+G63 -> 382000 | H64: =G64+H63 -> 382000 | I64: =H64+I63 -> 382000 | J64: =I64+J63 -> 382000 | K64: =J64+K63 -> 382000 | ... BJ64: =BI64+BJ63 -> 462000
A65: Land at cost (not depreciated) | C65: =C61 -> 0 | D65: =C65+D61 -> 0 | E65: =D65+E61 -> 0 | F65: =E65+F61 -> 0 | G65: =F65+G61 -> 0 | H65: =G65+H61 -> 0 | I65: =H65+I61 -> 0 | J65: =I65+J61 -> 0 | K65: =J65+K61 -> 0 | ... BJ65: =BI65+BJ61 -> 0
A66: Depreciation | C66: =-MIN((C64-C65)/MAX(1,Inputs!$E$78*12),C63-C65) -> -3979.1667 | D66: =-MIN((D64-D65)/MAX(1,Inputs!$E$78*12),C68+D63-D65) -> -3979.1667 | E66: =-MIN((E64-E65)/MAX(1,Inputs!$E$78*12),D68+E63-E65) -> -3979.1667 | F66: =-MIN((F64-F65)/MAX(1,Inputs!$E$78*12),E68+F63-F65) -> -3979.1667 | G66: =-MIN((G64-G65)/MAX(1,Inputs!$E$78*12),F68+G63-G65) -> -3979.1667 | H66: =-MIN((H64-H65)/MAX(1,Inputs!$E$78*12),G68+H63-H65) -> -3979.1667 | I66: =-MIN((I64-I65)/MAX(1,Inputs!$E$78*12),H68+I63-I65) -> -3979.1667 | J66: =-MIN((J64-J65)/MAX(1,Inputs!$E$78*12),I68+J63-J65) -> -3979.1667 | K66: =-MIN((K64-K65)/MAX(1,Inputs!$E$78*12),J68+K63-K65) -> -3979.1667 | ... BJ66: =-MIN((BJ64-BJ65)/MAX(1,Inputs!$E$78*12),BI68+BJ63-BJ65) -> -4812.5
A67: Accumulated depreciation | C67: =C66 -> -3979.1667 | D67: =C67+D66 -> -7958.3333 | E67: =D67+E66 -> -11937.5 | F67: =E67+F66 -> -15916.667 | G67: =F67+G66 -> -19895.833 | H67: =G67+H66 -> -23875 | I67: =H67+I66 -> -27854.167 | J67: =I67+J66 -> -31833.333 | K67: =J67+K66 -> -35812.5 | ... BJ67: =BI67+BJ66 -> -263750
A68: Net fixed assets | C68: =C64+C67 -> 378020.83 | D68: =D64+D67 -> 374041.67 | E68: =E64+E67 -> 370062.5 | F68: =F64+F67 -> 366083.33 | G68: =G64+G67 -> 362104.17 | H68: =H64+H67 -> 358125 | I68: =I64+I67 -> 354145.83 | J68: =J64+J67 -> 350166.67 | ... BJ68: =BJ64+BJ67 -> 198250
A70: Debt
A71: Loan — opening balance | C71: =0 -> 0 | D71: =C74 -> 250000 | E71: =D74 -> 247023.81 | F71: =E74 -> 244047.62 | G71: =F74 -> 241071.43 | H71: =G74 -> 238095.24 | I71: =H74 -> 235119.05 | J71: =I74 -> 232142.86 | K71: =J74 -> 229166.67 | ... BJ71: =BI74 -> 77380.952
A72: Loan drawdown | C72: =IF(C$4=1,Inputs!$E$68,0) -> 250000 | D72: =IF(D$4=1,Inputs!$E$68,0) -> 0 | E72: =IF(E$4=1,Inputs!$E$68,0) -> 0 | F72: =IF(F$4=1,Inputs!$E$68,0) -> 0 | G72: =IF(G$4=1,Inputs!$E$68,0) -> 0 | H72: =IF(H$4=1,Inputs!$E$68,0) -> 0 | I72: =IF(I$4=1,Inputs!$E$68,0) -> 0 | J72: =IF(J$4=1,Inputs!$E$68,0) -> 0 | ... BJ72: =IF(BJ$4=1,Inputs!$E$68,0) -> 0
A73: Loan repayment | C73: =-MIN(C71,Inputs!$E$68/MAX(1,Inputs!$E$70*12)) -> 0 | D73: =-MIN(D71,Inputs!$E$68/MAX(1,Inputs!$E$70*12)) -> -2976.1905 | E73: =-MIN(E71,Inputs!$E$68/MAX(1,Inputs!$E$70*12)) -> -2976.1905 | F73: =-MIN(F71,Inputs!$E$68/MAX(1,Inputs!$E$70*12)) -> -2976.1905 | G73: =-MIN(G71,Inputs!$E$68/MAX(1,Inputs!$E$70*12)) -> -2976.1905 | H73: =-MIN(H71,Inputs!$E$68/MAX(1,Inputs!$E$70*12)) -> -2976.1905 | I73: =-MIN(I71,Inputs!$E$68/MAX(1,Inputs!$E$70*12)) -> -2976.1905 | J73: =-MIN(J71,Inputs!$E$68/MAX(1,Inputs!$E$70*12)) -> -2976.1905 | ... BJ73: =-MIN(BJ71,Inputs!$E$68/MAX(1,Inputs!$E$70*12)) -> -2976.1905
A74: Loan — closing balance | C74: =C71+C72+C73 -> 250000 | D74: =D71+D72+D73 -> 247023.81 | E74: =E71+E72+E73 -> 244047.62 | F74: =F71+F72+F73 -> 241071.43 | G74: =G71+G72+G73 -> 238095.24 | H74: =H71+H72+H73 -> 235119.05 | I74: =I71+I72+I73 -> 232142.86 | J74: =J71+J72+J73 -> 229166.67 | ... BJ74: =BJ71+BJ72+BJ73 -> 74404.762
A76: Working capital
A77: Accounts receivable | C77: =C28*Inputs!$E$73/30 -> 6243.75 | D77: =D28*Inputs!$E$73/30 -> 7024.2188 | E77: =E28*Inputs!$E$73/30 -> 7804.6875 | F77: =F28*Inputs!$E$73/30 -> 8585.1562 | G77: =G28*Inputs!$E$73/30 -> 9365.625 | H77: =H28*Inputs!$E$73/30 -> 10146.094 | I77: =I28*Inputs!$E$73/30 -> 10926.562 | J77: =J28*Inputs!$E$73/30 -> 11707.031 | ... BJ77: =BJ28*Inputs!$E$73/30 -> 19773.489
A78: Inventory | C78: =-C35*Inputs!$E$74/30 -> 14367.667 | D78: =-D35*Inputs!$E$74/30 -> 14917.792 | E78: =-E35*Inputs!$E$74/30 -> 15467.917 | F78: =-F35*Inputs!$E$74/30 -> 16018.042 | G78: =-G35*Inputs!$E$74/30 -> 16568.167 | H78: =-H35*Inputs!$E$74/30 -> 17118.292 | I78: =-I35*Inputs!$E$74/30 -> 17668.417 | J78: =-J35*Inputs!$E$74/30 -> 18218.542 | ... BJ78: =-BJ35*Inputs!$E$74/30 -> 25155.209
A79: Accounts payable | C79: =-C35*Inputs!$E$75/30 -> 44898.958 | D79: =-D35*Inputs!$E$75/30 -> 46618.099 | E79: =-E35*Inputs!$E$75/30 -> 48337.24 | F79: =-F35*Inputs!$E$75/30 -> 50056.38 | G79: =-G35*Inputs!$E$75/30 -> 51775.521 | H79: =-H35*Inputs!$E$75/30 -> 53494.661 | I79: =-I35*Inputs!$E$75/30 -> 55213.802 | J79: =-J35*Inputs!$E$75/30 -> 56932.943 | ... BJ79: =-BJ35*Inputs!$E$75/30 -> 78610.028
A80: (Increase) / decrease in receivables | C80: =-C77 -> -6243.75 | D80: =C77-D77 -> -780.46875 | E80: =D77-E77 -> -780.46875 | F80: =E77-F77 -> -780.46875 | G80: =F77-G77 -> -780.46875 | H80: =G77-H77 -> -780.46875 | I80: =H77-I77 -> -780.46875 | J80: =I77-J77 -> -780.46875 | K80: =J77-K77 -> -780.46875 | ... BJ80: =BI77-BJ77 -> 0
A81: (Increase) / decrease in inventory | C81: =-C78 -> -14367.667 | D81: =C78-D78 -> -550.125 | E81: =D78-E78 -> -550.125 | F81: =E78-F78 -> -550.125 | G81: =F78-G78 -> -550.125 | H81: =G78-H78 -> -550.125 | I81: =H78-I78 -> -550.125 | J81: =I78-J78 -> -550.125 | K81: =J78-K78 -> -550.125 | ... BJ81: =BI78-BJ78 -> 0
A82: Increase / (decrease) in payables | C82: =C79 -> 44898.958 | D82: =D79-C79 -> 1719.1406 | E82: =E79-D79 -> 1719.1406 | F82: =F79-E79 -> 1719.1406 | G82: =G79-F79 -> 1719.1406 | H82: =H79-G79 -> 1719.1406 | I82: =I79-H79 -> 1719.1406 | J82: =J79-I79 -> 1719.1406 | K82: =K79-J79 -> 1719.1406 | ... BJ82: =BJ79-BI79 -> 0
A84: Cash flow
A85: Operating cash flow | C85: =C55-C66+C80+C81+C82 -> -27131 | D85: =D55-D66+D80+D81+D82 -> -45511.256 | E85: =E55-E66+E80+E81+E82 -> -39981.356 | F85: =F55-F66+F80+F81+F82 -> -34451.457 | G85: =G55-G66+G80+G81+G82 -> -28921.557 | H85: =H55-H66+H80+H81+H82 -> -23391.658 | I85: =I55-I66+I80+I81+I82 -> -17861.758 | J85: =J55-J66+J80+J81+J82 -> -12331.859 | ... BJ85: =BJ55-BJ66+BJ80+BJ81+BJ82 -> 31525.603
A86: Investing cash flow (capex) | C86: =-C63 -> -382000 | D86: =-D63 -> 0 | E86: =-E63 -> 0 | F86: =-F63 -> 0 | G86: =-G63 -> 0 | H86: =-H63 -> 0 | I86: =-I63 -> 0 | J86: =-J63 -> 0 | ... BJ86: =-BJ63 -> 0
A87: Equity raised | C87: =IF(C$4=1,Inputs!$E$67,0) -> 480000 | D87: =IF(D$4=1,Inputs!$E$67,0) -> 0 | E87: =IF(E$4=1,Inputs!$E$67,0) -> 0 | F87: =IF(F$4=1,Inputs!$E$67,0) -> 0 | G87: =IF(G$4=1,Inputs!$E$67,0) -> 0 | H87: =IF(H$4=1,Inputs!$E$67,0) -> 0 | I87: =IF(I$4=1,Inputs!$E$67,0) -> 0 | J87: =IF(J$4=1,Inputs!$E$67,0) -> 0 | ... BJ87: =IF(BJ$4=1,Inputs!$E$67,0) -> 0
A88: Financing cash flow | C88: =C87+C72+C73 -> 730000 | D88: =D87+D72+D73 -> -2976.1905 | E88: =E87+E72+E73 -> -2976.1905 | F88: =F87+F72+F73 -> -2976.1905 | G88: =G87+G72+G73 -> -2976.1905 | H88: =H87+H72+H73 -> -2976.1905 | I88: =I87+I72+I73 -> -2976.1905 | J88: =J87+J72+J73 -> -2976.1905 | ... BJ88: =BJ87+BJ72+BJ73 -> -2976.1905
A89: Net cash flow | C89: =C85+C86+C88 -> 320869 | D89: =D85+D86+D88 -> -48487.446 | E89: =E85+E86+E88 -> -42957.547 | F89: =F85+F86+F88 -> -37427.647 | G89: =G85+G86+G88 -> -31897.748 | H89: =H85+H86+H88 -> -26367.848 | I89: =I85+I86+I88 -> -20837.949 | J89: =J85+J86+J88 -> -15308.049 | ... BJ89: =BJ85+BJ86+BJ88 -> 28549.413
A90: Opening cash | C90: =0 -> 0 | D90: =C91 -> 320869 | E90: =D91 -> 272381.55 | F90: =E91 -> 229424.01 | G90: =F91 -> 191996.36 | H90: =G91 -> 160098.61 | I90: =H91 -> 133730.76 | J90: =I91 -> 112892.81 | K90: =J91 -> 97584.766 | ... BJ90: =BI91 -> 1070494.7
A91: Closing cash | C91: =C90+C89 -> 320869 | D91: =D90+D89 -> 272381.55 | E91: =E90+E89 -> 229424.01 | F91: =F90+F89 -> 191996.36 | G91: =G90+G89 -> 160098.61 | H91: =H90+H89 -> 133730.76 | I91: =I90+I89 -> 112892.81 | J91: =J90+J89 -> 97584.766 | ... BJ91: =BJ90+BJ89 -> 1099044.1
A92: Helper: EBITDA positive (1/0) | C92: =IF(C46>0,1,0) -> 0 | D92: =IF(D46>0,1,0) -> 0 | E92: =IF(E46>0,1,0) -> 0 | F92: =IF(F46>0,1,0) -> 0 | G92: =IF(G46>0,1,0) -> 0 | H92: =IF(H46>0,1,0) -> 0 | I92: =IF(I46>0,1,0) -> 0 | J92: =IF(J46>0,1,0) -> 0 | ... BJ92: =IF(BJ46>0,1,0) -> 1
A94: Goal modules
A95: Helper: net income positive (1/0) | C95: =IF(C55>0,1,0) -> 0 | D95: =IF(D55>0,1,0) -> 0 | E95: =IF(E55>0,1,0) -> 0 | F95: =IF(F55>0,1,0) -> 0 | G95: =IF(G55>0,1,0) -> 0 | H95: =IF(H55>0,1,0) -> 0 | I95: =IF(I55>0,1,0) -> 0 | J95: =IF(J55>0,1,0) -> 0 | ... BJ95: =IF(BJ55>0,1,0) -> 1
A96: Cash flow before financing (operating + investing) | C96: =C85+C86 -> -409131 | D96: =D85+D86 -> -45511.256 | E96: =E85+E86 -> -39981.356 | F96: =F85+F86 -> -34451.457 | G96: =G85+G86 -> -28921.557 | H96: =H85+H86 -> -23391.658 | I96: =I85+I86 -> -17861.758 | J96: =J85+J86 -> -12331.859 | ... BJ96: =BJ85+BJ86 -> 31525.603
A97: Cumulative cash flow before financing | C97: =C96 -> -409131 | D97: =C97+D96 -> -454642.26 | E97: =D97+E96 -> -494623.61 | F97: =E97+F96 -> -529075.07 | G97: =F97+G96 -> -557996.63 | H97: =G97+H96 -> -581388.28 | I97: =H97+I96 -> -599250.04 | J97: =I97+J96 -> -611581.9 | K97: =J97+K96 -> -618383.86 | ... BJ97: =BI97+BJ96 -> 544639.32
A98: Helper: lowest cumulative cash flow so far | C98: =C97 -> -409131 | D98: =MIN(C98,D97) -> -454642.26 | E98: =MIN(D98,E97) -> -494623.61 | F98: =MIN(E98,F97) -> -529075.07 | G98: =MIN(F98,G97) -> -557996.63 | H98: =MIN(G98,H97) -> -581388.28 | I98: =MIN(H98,I97) -> -599250.04 | J98: =MIN(I98,J97) -> -611581.9 | K98: =MIN(J98,K97) -> -618383.86 | ... BJ98: =MIN(BI98,BJ97) -> -619655.92
A99: Helper: investment paid back (1/0) | C99: =IF(AND(C97>=0,C98<0),1,0) -> 0 | D99: =IF(AND(D97>=0,D98<0),1,0) -> 0 | E99: =IF(AND(E97>=0,E98<0),1,0) -> 0 | F99: =IF(AND(F97>=0,F98<0),1,0) -> 0 | G99: =IF(AND(G97>=0,G98<0),1,0) -> 0 | H99: =IF(AND(H97>=0,H98<0),1,0) -> 0 | I99: =IF(AND(I97>=0,I98<0),1,0) -> 0 | J99: =IF(AND(J97>=0,J98<0),1,0) -> 0 | ... BJ99: =IF(AND(BJ97>=0,BJ98<0),1,0) -> 1
A100: Unlevered free cash flow (operating + after-tax interest − capex) | C100: =C85-C50*(1-Inputs!$E$79)+C86 -> -407649.75 | D100: =D85-D50*(1-Inputs!$E$79)+D86 -> -44038.823 | E100: =E85-E50*(1-Inputs!$E$79)+E86 -> -38526.557 | F100: =F85-F50*(1-Inputs!$E$79)+F86 -> -33014.292 | G100: =G85-G50*(1-Inputs!$E$79)+G86 -> -27502.026 | H100: =H85-H50*(1-Inputs!$E$79)+H86 -> -21989.76 | I100: =I85-I50*(1-Inputs!$E$79)+I86 -> -16477.495 | J100: =J85-J50*(1-Inputs!$E$79)+J86 -> -10965.229 | ... BJ100: =BJ85-BJ50*(1-Inputs!$E$79)+BJ86 -> 31975.268
A102: Balance sheet
A103: Paid-in capital | C103: =C87 -> 480000 | D103: =C103+D87 -> 480000 | E103: =D103+E87 -> 480000 | F103: =E103+F87 -> 480000 | G103: =F103+G87 -> 480000 | H103: =G103+H87 -> 480000 | I103: =H103+I87 -> 480000 | J103: =I103+J87 -> 480000 | K103: =J103+K87 -> 480000 | ... BJ103: =BI103+BJ87 -> 480000
A104: Retained earnings | C104: =C55 -> -55397.708 | D104: =C104+D55 -> -105276.68 | E104: =D104+E55 -> -149625.75 | F104: =E104+F55 -> -188444.92 | G104: =F104+G55 -> -221734.19 | H104: =G104+H55 -> -249493.56 | I104: =H104+I55 -> -271723.03 | J104: =I104+J55 -> -288422.6 | K104: =J104+K55 -> -299592.28 | ... BJ104: =BI104+BJ55 -> 709207.99
A105: Total assets | C105: =C91+C77+C78+C68 -> 719501.25 | D105: =D91+D77+D78+D68 -> 668365.23 | E105: =E91+E77+E78+E68 -> 622759.11 | F105: =F91+F77+F78+F68 -> 582682.89 | G105: =G91+G77+G78+G68 -> 548136.57 | H105: =H91+H77+H78+H68 -> 519120.15 | I105: =I91+I77+I78+I68 -> 495633.63 | J105: =J91+J77+J78+J68 -> 477677.01 | ... BJ105: =BJ91+BJ77+BJ78+BJ68 -> 1342222.8
A106: Total liabilities | C106: =C79+C74 -> 294898.96 | D106: =D79+D74 -> 293641.91 | E106: =E79+E74 -> 292384.86 | F106: =F79+F74 -> 291127.81 | G106: =G79+G74 -> 289870.76 | H106: =H79+H74 -> 288613.71 | I106: =I79+I74 -> 287356.66 | J106: =J79+J74 -> 286099.61 | ... BJ106: =BJ79+BJ74 -> 153014.79
A107: Total equity | C107: =C103+C104 -> 424602.29 | D107: =D103+D104 -> 374723.32 | E107: =E103+E104 -> 330374.25 | F107: =F103+F104 -> 291555.08 | G107: =G103+G104 -> 258265.81 | H107: =H103+H104 -> 230506.44 | I107: =I103+I104 -> 208276.97 | J107: =J103+J104 -> 191577.4 | ... BJ107: =BJ103+BJ104 -> 1189208
A108: Total liabilities & equity | C108: =C106+C107 -> 719501.25 | D108: =D106+D107 -> 668365.23 | E108: =E106+E107 -> 622759.11 | F108: =F106+F107 -> 582682.89 | G108: =G106+G107 -> 548136.57 | H108: =H106+H107 -> 519120.15 | I108: =I106+I107 -> 495633.63 | J108: =J106+J107 -> 477677.01 | ... BJ108: =BJ106+BJ107 -> 1342222.8
A109: Check: assets − liabilities − equity | C109: =C105-C108 -> 0 | D109: =D105-D108 -> 0 | E109: =E105-E108 -> 0 | F109: =F105-F108 -> 0 | G109: =G105-G108 -> 0 | H109: =H105-H108 -> 0 | I109: =I105-I108 -> 0 | J109: =J105-J108 -> 0 | ... BJ109: =BJ105-BJ108 -> 0

Sheet Headcount
A1: Headcount & payroll | D1: =HYPERLINK("#'Cover'!A1","◂ Contents") -> ◂ Contents
A2: $ unless stated; costs shown as negatives. Every period uses the same formula.
A3: Month | C3: M1 | D3: M2 | E3: M3 | F3: M4 | G3: M5 | H3: M6 | I3: M7 | J3: M8 | K3: M9 | L3: M10 | M3: M11 | N3: M12 | O3: M13 | P3: M14 | Q3: M15 | R3: M16 | S3: M17 | T3: M18 | U3: M19 | V3: M20 | W3: M21 | X3: M22 | Y3: M23 | Z3: M24 | AA3: M25 | AB3: M26 | AC3: M27 | AD3: M28 | AE3: M29 | AF3: M30 | AG3: M31 | AH3: M32 | AI3: M33 | AJ3: M34 | AK3: M35 | AL3: M36 | AM3: M37 | AN3: M38 | AO3: M39 | AP3: M40 | AQ3: M41 | AR3: M42 | AS3: M43 | AT3: M44 | AU3: M45 | AV3: M46 | AW3: M47 | AX3: M48 | AY3: M49 | AZ3: M50 | BA3: M51 | BB3: M52 | BC3: M53 | BD3: M54 | BE3: M55 | BF3: M56 | BG3: M57 | BH3: M58 | BI3: M59 | BJ3: M60
A4: Period # | C4: 1 | D4: 2 | E4: 3 | F4: 4 | G4: 5 | H4: 6 | I4: 7 | J4: 8 | K4: 9 | L4: 10 | M4: 11 | N4: 12 | O4: 13 | P4: 14 | Q4: 15 | R4: 16 | S4: 17 | T4: 18 | U4: 19 | V4: 20 | W4: 21 | X4: 22 | Y4: 23 | Z4: 24 | AA4: 25 | AB4: 26 | AC4: 27 | AD4: 28 | AE4: 29 | AF4: 30 | AG4: 31 | AH4: 32 | AI4: 33 | AJ4: 34 | AK4: 35 | AL4: 36 | AM4: 37 | AN4: 38 | AO4: 39 | AP4: 40 | AQ4: 41 | AR4: 42 | AS4: 43 | AT4: 44 | AU4: 45 | AV4: 46 | AW4: 47 | AX4: 48 | AY4: 49 | AZ4: 50 | BA4: 51 | BB4: 52 | BC4: 53 | BD4: 54 | BE4: 55 | BF4: 56 | BG4: 57 | BH4: 58 | BI4: 59 | BJ4: 60
A5: Year # | C5: =ROUNDUP(C4*1/12,0) -> 1 | D5: =ROUNDUP(D4*1/12,0) -> 1 | E5: =ROUNDUP(E4*1/12,0) -> 1 | F5: =ROUNDUP(F4*1/12,0) -> 1 | G5: =ROUNDUP(G4*1/12,0) -> 1 | H5: =ROUNDUP(H4*1/12,0) -> 1 | I5: =ROUNDUP(I4*1/12,0) -> 1 | J5: =ROUNDUP(J4*1/12,0) -> 1 | ... BJ5: =ROUNDUP(BJ4*1/12,0) -> 5
A7: Headcount (FTE)
A8: Technicians — FTE | C8: =Inputs!$E$51*(1+Inputs!$E$53)^(C$5-1)*MAX(0,MIN(1,C$4*1-Inputs!$E$54+1))/1 -> 5 | D8: =Inputs!$E$51*(1+Inputs!$E$53)^(D$5-1)*MAX(0,MIN(1,D$4*1-Inputs!$E$54+1))/1 -> 5 | E8: =Inputs!$E$51*(1+Inputs!$E$53)^(E$5-1)*MAX(0,MIN(1,E$4*1-Inputs!$E$54+1))/1 -> 5 | F8: =Inputs!$E$51*(1+Inputs!$E$53)^(F$5-1)*MAX(0,MIN(1,F$4*1-Inputs!$E$54+1))/1 -> 5 | G8: =Inputs!$E$51*(1+Inputs!$E$53)^(G$5-1)*MAX(0,MIN(1,G$4*1-Inputs!$E$54+1))/1 -> 5 | H8: =Inputs!$E$51*(1+Inputs!$E$53)^(H$5-1)*MAX(0,MIN(1,H$4*1-Inputs!$E$54+1))/1 -> 5 | I8: =Inputs!$E$51*(1+Inputs!$E$53)^(I$5-1)*MAX(0,MIN(1,I$4*1-Inputs!$E$54+1))/1 -> 5 | J8: =Inputs!$E$51*(1+Inputs!$E$53)^(J$5-1)*MAX(0,MIN(1,J$4*1-Inputs!$E$54+1))/1 -> 5 | ... BJ8: =Inputs!$E$51*(1+Inputs!$E$53)^(BJ$5-1)*MAX(0,MIN(1,BJ$4*1-Inputs!$E$54+1))/1 -> 5
A9: Service advisors & front desk — FTE | C9: =Inputs!$E$55*(1+Inputs!$E$57)^(C$5-1)*MAX(0,MIN(1,C$4*1-Inputs!$E$58+1))/1 -> 2 | D9: =Inputs!$E$55*(1+Inputs!$E$57)^(D$5-1)*MAX(0,MIN(1,D$4*1-Inputs!$E$58+1))/1 -> 2 | E9: =Inputs!$E$55*(1+Inputs!$E$57)^(E$5-1)*MAX(0,MIN(1,E$4*1-Inputs!$E$58+1))/1 -> 2 | F9: =Inputs!$E$55*(1+Inputs!$E$57)^(F$5-1)*MAX(0,MIN(1,F$4*1-Inputs!$E$58+1))/1 -> 2 | G9: =Inputs!$E$55*(1+Inputs!$E$57)^(G$5-1)*MAX(0,MIN(1,G$4*1-Inputs!$E$58+1))/1 -> 2 | H9: =Inputs!$E$55*(1+Inputs!$E$57)^(H$5-1)*MAX(0,MIN(1,H$4*1-Inputs!$E$58+1))/1 -> 2 | I9: =Inputs!$E$55*(1+Inputs!$E$57)^(I$5-1)*MAX(0,MIN(1,I$4*1-Inputs!$E$58+1))/1 -> 2 | J9: =Inputs!$E$55*(1+Inputs!$E$57)^(J$5-1)*MAX(0,MIN(1,J$4*1-Inputs!$E$58+1))/1 -> 2 | ... BJ9: =Inputs!$E$55*(1+Inputs!$E$57)^(BJ$5-1)*MAX(0,MIN(1,BJ$4*1-Inputs!$E$58+1))/1 -> 2
A10: Shop manager — FTE | C10: =Inputs!$E$59*(1+Inputs!$E$61)^(C$5-1)*MAX(0,MIN(1,C$4*1-Inputs!$E$62+1))/1 -> 1 | D10: =Inputs!$E$59*(1+Inputs!$E$61)^(D$5-1)*MAX(0,MIN(1,D$4*1-Inputs!$E$62+1))/1 -> 1 | E10: =Inputs!$E$59*(1+Inputs!$E$61)^(E$5-1)*MAX(0,MIN(1,E$4*1-Inputs!$E$62+1))/1 -> 1 | F10: =Inputs!$E$59*(1+Inputs!$E$61)^(F$5-1)*MAX(0,MIN(1,F$4*1-Inputs!$E$62+1))/1 -> 1 | G10: =Inputs!$E$59*(1+Inputs!$E$61)^(G$5-1)*MAX(0,MIN(1,G$4*1-Inputs!$E$62+1))/1 -> 1 | H10: =Inputs!$E$59*(1+Inputs!$E$61)^(H$5-1)*MAX(0,MIN(1,H$4*1-Inputs!$E$62+1))/1 -> 1 | I10: =Inputs!$E$59*(1+Inputs!$E$61)^(I$5-1)*MAX(0,MIN(1,I$4*1-Inputs!$E$62+1))/1 -> 1 | J10: =Inputs!$E$59*(1+Inputs!$E$61)^(J$5-1)*MAX(0,MIN(1,J$4*1-Inputs!$E$62+1))/1 -> 1 | ... BJ10: =Inputs!$E$59*(1+Inputs!$E$61)^(BJ$5-1)*MAX(0,MIN(1,BJ$4*1-Inputs!$E$62+1))/1 -> 1
A11: Total FTE | C11: =C8+C9+C10 -> 8 | D11: =D8+D9+D10 -> 8 | E11: =E8+E9+E10 -> 8 | F11: =F8+F9+F10 -> 8 | G11: =G8+G9+G10 -> 8 | H11: =H8+H9+H10 -> 8 | I11: =I8+I9+I10 -> 8 | J11: =J8+J9+J10 -> 8 | ... BJ11: =BJ8+BJ9+BJ10 -> 8
A13: Payroll cost (salary + taxes & benefits)
A14: Technicians — payroll cost | C14: =-C8*Inputs!$E$52/12*1*(1+Inputs!$E$63)*(1+Inputs!$E$64)^(C$5-1) -> -37375 | D14: =-D8*Inputs!$E$52/12*1*(1+Inputs!$E$63)*(1+Inputs!$E$64)^(D$5-1) -> -37375 | E14: =-E8*Inputs!$E$52/12*1*(1+Inputs!$E$63)*(1+Inputs!$E$64)^(E$5-1) -> -37375 | F14: =-F8*Inputs!$E$52/12*1*(1+Inputs!$E$63)*(1+Inputs!$E$64)^(F$5-1) -> -37375 | G14: =-G8*Inputs!$E$52/12*1*(1+Inputs!$E$63)*(1+Inputs!$E$64)^(G$5-1) -> -37375 | H14: =-H8*Inputs!$E$52/12*1*(1+Inputs!$E$63)*(1+Inputs!$E$64)^(H$5-1) -> -37375 | I14: =-I8*Inputs!$E$52/12*1*(1+Inputs!$E$63)*(1+Inputs!$E$64)^(I$5-1) -> -37375 | J14: =-J8*Inputs!$E$52/12*1*(1+Inputs!$E$63)*(1+Inputs!$E$64)^(J$5-1) -> -37375 | ... BJ14: =-BJ8*Inputs!$E$52/12*1*(1+Inputs!$E$63)*(1+Inputs!$E$64)^(BJ$5-1) -> -42065.892
A15: Service advisors & front desk — payroll cost | C15: =-C9*Inputs!$E$56/12*1*(1+Inputs!$E$63)*(1+Inputs!$E$64)^(C$5-1) -> -9583.3333 | D15: =-D9*Inputs!$E$56/12*1*(1+Inputs!$E$63)*(1+Inputs!$E$64)^(D$5-1) -> -9583.3333 | E15: =-E9*Inputs!$E$56/12*1*(1+Inputs!$E$63)*(1+Inputs!$E$64)^(E$5-1) -> -9583.3333 | F15: =-F9*Inputs!$E$56/12*1*(1+Inputs!$E$63)*(1+Inputs!$E$64)^(F$5-1) -> -9583.3333 | G15: =-G9*Inputs!$E$56/12*1*(1+Inputs!$E$63)*(1+Inputs!$E$64)^(G$5-1) -> -9583.3333 | H15: =-H9*Inputs!$E$56/12*1*(1+Inputs!$E$63)*(1+Inputs!$E$64)^(H$5-1) -> -9583.3333 | I15: =-I9*Inputs!$E$56/12*1*(1+Inputs!$E$63)*(1+Inputs!$E$64)^(I$5-1) -> -9583.3333 | J15: =-J9*Inputs!$E$56/12*1*(1+Inputs!$E$63)*(1+Inputs!$E$64)^(J$5-1) -> -9583.3333 | ... BJ15: =-BJ9*Inputs!$E$56/12*1*(1+Inputs!$E$63)*(1+Inputs!$E$64)^(BJ$5-1) -> -10786.126
A16: Shop manager — payroll cost | C16: =-C10*Inputs!$E$60/12*1*(1+Inputs!$E$63)*(1+Inputs!$E$64)^(C$5-1) -> -8145.8333 | D16: =-D10*Inputs!$E$60/12*1*(1+Inputs!$E$63)*(1+Inputs!$E$64)^(D$5-1) -> -8145.8333 | E16: =-E10*Inputs!$E$60/12*1*(1+Inputs!$E$63)*(1+Inputs!$E$64)^(E$5-1) -> -8145.8333 | F16: =-F10*Inputs!$E$60/12*1*(1+Inputs!$E$63)*(1+Inputs!$E$64)^(F$5-1) -> -8145.8333 | G16: =-G10*Inputs!$E$60/12*1*(1+Inputs!$E$63)*(1+Inputs!$E$64)^(G$5-1) -> -8145.8333 | H16: =-H10*Inputs!$E$60/12*1*(1+Inputs!$E$63)*(1+Inputs!$E$64)^(H$5-1) -> -8145.8333 | I16: =-I10*Inputs!$E$60/12*1*(1+Inputs!$E$63)*(1+Inputs!$E$64)^(I$5-1) -> -8145.8333 | J16: =-J10*Inputs!$E$60/12*1*(1+Inputs!$E$63)*(1+Inputs!$E$64)^(J$5-1) -> -8145.8333 | ... BJ16: =-BJ10*Inputs!$E$60/12*1*(1+Inputs!$E$63)*(1+Inputs!$E$64)^(BJ$5-1) -> -9168.2072
A17: Total payroll | C17: =C14+C15+C16 -> -55104.167 | D17: =D14+D15+D16 -> -55104.167 | E17: =E14+E15+E16 -> -55104.167 | F17: =F14+F15+F16 -> -55104.167 | G17: =G14+G15+G16 -> -55104.167 | H17: =H14+H15+H16 -> -55104.167 | I17: =I14+I15+I16 -> -55104.167 | J17: =J14+J15+J16 -> -55104.167 | ... BJ17: =BJ14+BJ15+BJ16 -> -62020.225

Sheet Scenario calc
A1: Scenario calculation — Low, Base and High side by side | D1: =HYPERLINK("#'Cover'!A1","◂ Contents") -> ◂ Contents
A2: The model's period calculation, copied three times; each copy reads its own Inputs column. Feeds the Scenarios sheet only.
A4: Low scenario — reads Inputs column B
A5: Month | C5: M1 | D5: M2 | E5: M3 | F5: M4 | G5: M5 | H5: M6 | I5: M7 | J5: M8 | K5: M9 | L5: M10 | M5: M11 | N5: M12 | O5: M13 | P5: M14 | Q5: M15 | R5: M16 | S5: M17 | T5: M18 | U5: M19 | V5: M20 | W5: M21 | X5: M22 | Y5: M23 | Z5: M24 | AA5: M25 | AB5: M26 | AC5: M27 | AD5: M28 | AE5: M29 | AF5: M30 | AG5: M31 | AH5: M32 | AI5: M33 | AJ5: M34 | AK5: M35 | AL5: M36 | AM5: M37 | AN5: M38 | AO5: M39 | AP5: M40 | AQ5: M41 | AR5: M42 | AS5: M43 | AT5: M44 | AU5: M45 | AV5: M46 | AW5: M47 | AX5: M48 | AY5: M49 | AZ5: M50 | BA5: M51 | BB5: M52 | BC5: M53 | BD5: M54 | BE5: M55 | BF5: M56 | BG5: M57 | BH5: M58 | BI5: M59 | BJ5: M60
A6: Period # | C6: 1 | D6: 2 | E6: 3 | F6: 4 | G6: 5 | H6: 6 | I6: 7 | J6: 8 | K6: 9 | L6: 10 | M6: 11 | N6: 12 | O6: 13 | P6: 14 | Q6: 15 | R6: 16 | S6: 17 | T6: 18 | U6: 19 | V6: 20 | W6: 21 | X6: 22 | Y6: 23 | Z6: 24 | AA6: 25 | AB6: 26 | AC6: 27 | AD6: 28 | AE6: 29 | AF6: 30 | AG6: 31 | AH6: 32 | AI6: 33 | AJ6: 34 | AK6: 35 | AL6: 36 | AM6: 37 | AN6: 38 | AO6: 39 | AP6: 40 | AQ6: 41 | AR6: 42 | AS6: 43 | AT6: 44 | AU6: 45 | AV6: 46 | AW6: 47 | AX6: 48 | AY6: 49 | AZ6: 50 | BA6: 51 | BB6: 52 | BC6: 53 | BD6: 54 | BE6: 55 | BF6: 56 | BG6: 57 | BH6: 58 | BI6: 59 | BJ6: 60
A7: Year # | C7: =ROUNDUP(C6*1/12,0) -> 1 | D7: =ROUNDUP(D6*1/12,0) -> 1 | E7: =ROUNDUP(E6*1/12,0) -> 1 | F7: =ROUNDUP(F6*1/12,0) -> 1 | G7: =ROUNDUP(G6*1/12,0) -> 1 | H7: =ROUNDUP(H6*1/12,0) -> 1 | I7: =ROUNDUP(I6*1/12,0) -> 1 | J7: =ROUNDUP(J6*1/12,0) -> 1 | ... BJ7: =ROUNDUP(BJ6*1/12,0) -> 5
A9: Demand
A10: Helper: months of the period still on the ramp-up | C10: =MAX(0,MIN(1,Inputs!$B$11-(C$6-1)*1)) -> 1 | D10: =MAX(0,MIN(1,Inputs!$B$11-(D$6-1)*1)) -> 1 | E10: =MAX(0,MIN(1,Inputs!$B$11-(E$6-1)*1)) -> 1 | F10: =MAX(0,MIN(1,Inputs!$B$11-(F$6-1)*1)) -> 1 | G10: =MAX(0,MIN(1,Inputs!$B$11-(G$6-1)*1)) -> 1 | H10: =MAX(0,MIN(1,Inputs!$B$11-(H$6-1)*1)) -> 1 | I10: =MAX(0,MIN(1,Inputs!$B$11-(I$6-1)*1)) -> 1 | J10: =MAX(0,MIN(1,Inputs!$B$11-(J$6-1)*1)) -> 1 | ... BJ10: =MAX(0,MIN(1,Inputs!$B$11-(BJ$6-1)*1)) -> 0
A11: Ramp-up factor (share of mature order volume) | C11: =IF(Inputs!$B$11<=0,1,(C10*Inputs!$B$12+(1-Inputs!$B$12)/MAX(1,Inputs!$B$11)*(C10*(C$6-1)*1+C10*(C10-1)/2)+1-C10)/1) -> 0.3 | D11: =IF(Inputs!$B$11<=0,1,(D10*Inputs!$B$12+(1-Inputs!$B$12)/MAX(1,Inputs!$B$11)*(D10*(D$6-1)*1+D10*(D10-1)/2)+1-D10)/1) -> 0.34375 | E11: =IF(Inputs!$B$11<=0,1,(E10*Inputs!$B$12+(1-Inputs!$B$12)/MAX(1,Inputs!$B$11)*(E10*(E$6-1)*1+E10*(E10-1)/2)+1-E10)/1) -> 0.3875 | F11: =IF(Inputs!$B$11<=0,1,(F10*Inputs!$B$12+(1-Inputs!$B$12)/MAX(1,Inputs!$B$11)*(F10*(F$6-1)*1+F10*(F10-1)/2)+1-F10)/1) -> 0.43125 | G11: =IF(Inputs!$B$11<=0,1,(G10*Inputs!$B$12+(1-Inputs!$B$12)/MAX(1,Inputs!$B$11)*(G10*(G$6-1)*1+G10*(G10-1)/2)+1-G10)/1) -> 0.475 | H11: =IF(Inputs!$B$11<=0,1,(H10*Inputs!$B$12+(1-Inputs!$B$12)/MAX(1,Inputs!$B$11)*(H10*(H$6-1)*1+H10*(H10-1)/2)+1-H10)/1) -> 0.51875 | I11: =IF(Inputs!$B$11<=0,1,(I10*Inputs!$B$12+(1-Inputs!$B$12)/MAX(1,Inputs!$B$11)*(I10*(I$6-1)*1+I10*(I10-1)/2)+1-I10)/1) -> 0.5625 | J11: =IF(Inputs!$B$11<=0,1,(J10*Inputs!$B$12+(1-Inputs!$B$12)/MAX(1,Inputs!$B$11)*(J10*(J$6-1)*1+J10*(J10-1)/2)+1-J10)/1) -> 0.60625 | ... BJ11: =IF(Inputs!$B$11<=0,1,(BJ10*Inputs!$B$12+(1-Inputs!$B$12)/MAX(1,Inputs!$B$11)*(BJ10*(BJ$6-1)*1+BJ10*(BJ10-1)/2)+1-BJ10)/1) -> 1
A12: Repair orders demanded | C12: =Inputs!$B$7*(1+Inputs!$B$8)^(C$7-1)*Inputs!$B$10*1*C11 -> 82.5 | D12: =Inputs!$B$7*(1+Inputs!$B$8)^(D$7-1)*Inputs!$B$10*1*D11 -> 94.53125 | E12: =Inputs!$B$7*(1+Inputs!$B$8)^(E$7-1)*Inputs!$B$10*1*E11 -> 106.5625 | F12: =Inputs!$B$7*(1+Inputs!$B$8)^(F$7-1)*Inputs!$B$10*1*F11 -> 118.59375 | G12: =Inputs!$B$7*(1+Inputs!$B$8)^(G$7-1)*Inputs!$B$10*1*G11 -> 130.625 | H12: =Inputs!$B$7*(1+Inputs!$B$8)^(H$7-1)*Inputs!$B$10*1*H11 -> 142.65625 | I12: =Inputs!$B$7*(1+Inputs!$B$8)^(I$7-1)*Inputs!$B$10*1*I11 -> 154.6875 | J12: =Inputs!$B$7*(1+Inputs!$B$8)^(J$7-1)*Inputs!$B$10*1*J11 -> 166.71875 | ... BJ12: =Inputs!$B$7*(1+Inputs!$B$8)^(BJ$7-1)*Inputs!$B$10*1*BJ11 -> 275
A13: Billed hours demanded | C13: =C12*Inputs!$B$9 -> 165 | D13: =D12*Inputs!$B$9 -> 189.0625 | E13: =E12*Inputs!$B$9 -> 213.125 | F13: =F12*Inputs!$B$9 -> 237.1875 | G13: =G12*Inputs!$B$9 -> 261.25 | H13: =H12*Inputs!$B$9 -> 285.3125 | I13: =I12*Inputs!$B$9 -> 309.375 | J13: =J12*Inputs!$B$9 -> 333.4375 | ... BJ13: =BJ12*Inputs!$B$9 -> 550
A15: Capacity
A16: Technicians (FTE) | C16: =C114 -> 5 | D16: =D114 -> 5 | E16: =E114 -> 5 | F16: =F114 -> 5 | G16: =G114 -> 5 | H16: =H114 -> 5 | I16: =I114 -> 5 | J16: =J114 -> 5 | ... BJ16: =BJ114 -> 5
A17: Bay capacity (bays × billed hours per bay-day × operating days) | C17: =Inputs!$B$15*Inputs!$B$16*Inputs!$B$10*1 -> 900 | D17: =Inputs!$B$15*Inputs!$B$16*Inputs!$B$10*1 -> 900 | E17: =Inputs!$B$15*Inputs!$B$16*Inputs!$B$10*1 -> 900 | F17: =Inputs!$B$15*Inputs!$B$16*Inputs!$B$10*1 -> 900 | G17: =Inputs!$B$15*Inputs!$B$16*Inputs!$B$10*1 -> 900 | H17: =Inputs!$B$15*Inputs!$B$16*Inputs!$B$10*1 -> 900 | I17: =Inputs!$B$15*Inputs!$B$16*Inputs!$B$10*1 -> 900 | J17: =Inputs!$B$15*Inputs!$B$16*Inputs!$B$10*1 -> 900 | ... BJ17: =Inputs!$B$15*Inputs!$B$16*Inputs!$B$10*1 -> 900
A18: Technician capacity (FTE × paid hours × efficiency × operating days) | C18: =C16*Inputs!$B$17*Inputs!$B$18*Inputs!$B$10*1 -> 820 | D18: =D16*Inputs!$B$17*Inputs!$B$18*Inputs!$B$10*1 -> 820 | E18: =E16*Inputs!$B$17*Inputs!$B$18*Inputs!$B$10*1 -> 820 | F18: =F16*Inputs!$B$17*Inputs!$B$18*Inputs!$B$10*1 -> 820 | G18: =G16*Inputs!$B$17*Inputs!$B$18*Inputs!$B$10*1 -> 820 | H18: =H16*Inputs!$B$17*Inputs!$B$18*Inputs!$B$10*1 -> 820 | I18: =I16*Inputs!$B$17*Inputs!$B$18*Inputs!$B$10*1 -> 820 | J18: =J16*Inputs!$B$17*Inputs!$B$18*Inputs!$B$10*1 -> 820 | ... BJ18: =BJ16*Inputs!$B$17*Inputs!$B$18*Inputs!$B$10*1 -> 820
A19: Billed-hour capacity (lower of bays and technicians) | C19: =MIN(C17,C18) -> 820 | D19: =MIN(D17,D18) -> 820 | E19: =MIN(E17,E18) -> 820 | F19: =MIN(F17,F18) -> 820 | G19: =MIN(G17,G18) -> 820 | H19: =MIN(H17,H18) -> 820 | I19: =MIN(I17,I18) -> 820 | J19: =MIN(J17,J18) -> 820 | ... BJ19: =MIN(BJ17,BJ18) -> 820
A20: Billed labor hours (demand capped by capacity) | C20: =MIN(C13,C19) -> 165 | D20: =MIN(D13,D19) -> 189.0625 | E20: =MIN(E13,E19) -> 213.125 | F20: =MIN(F13,F19) -> 237.1875 | G20: =MIN(G13,G19) -> 261.25 | H20: =MIN(H13,H19) -> 285.3125 | I20: =MIN(I13,I19) -> 309.375 | J20: =MIN(J13,J19) -> 333.4375 | ... BJ20: =MIN(BJ13,BJ19) -> 550
A21: Billed hours lost to the capacity limit | C21: =C13-C20 -> 0 | D21: =D13-D20 -> 0 | E21: =E13-E20 -> 0 | F21: =F13-F20 -> 0 | G21: =G13-G20 -> 0 | H21: =H13-H20 -> 0 | I21: =I13-I20 -> 0 | J21: =J13-J20 -> 0 | ... BJ21: =BJ13-BJ20 -> 0
A22: Share of demand the shop can serve | C22: =MIN(1,C20/MAX(1,C13)) -> 1 | D22: =MIN(1,D20/MAX(1,D13)) -> 1 | E22: =MIN(1,E20/MAX(1,E13)) -> 1 | F22: =MIN(1,F20/MAX(1,F13)) -> 1 | G22: =MIN(1,G20/MAX(1,G13)) -> 1 | H22: =MIN(1,H20/MAX(1,H13)) -> 1 | I22: =MIN(1,I20/MAX(1,I13)) -> 1 | J22: =MIN(1,J20/MAX(1,J13)) -> 1 | ... BJ22: =MIN(1,BJ20/MAX(1,BJ13)) -> 1
A23: Repair orders completed | C23: =C12*C22 -> 82.5 | D23: =D12*D22 -> 94.53125 | E23: =E12*E22 -> 106.5625 | F23: =F12*F22 -> 118.59375 | G23: =G12*G22 -> 130.625 | H23: =H12*H22 -> 142.65625 | I23: =I12*I22 -> 154.6875 | J23: =J12*J22 -> 166.71875 | ... BJ23: =BJ12*BJ22 -> 275
A25: Revenue
A26: Effective labor rate per billed hour | C26: =Inputs!$B$21*(1+Inputs!$B$22)^(C$7-1) -> 118 | D26: =Inputs!$B$21*(1+Inputs!$B$22)^(D$7-1) -> 118 | E26: =Inputs!$B$21*(1+Inputs!$B$22)^(E$7-1) -> 118 | F26: =Inputs!$B$21*(1+Inputs!$B$22)^(F$7-1) -> 118 | G26: =Inputs!$B$21*(1+Inputs!$B$22)^(G$7-1) -> 118 | H26: =Inputs!$B$21*(1+Inputs!$B$22)^(H$7-1) -> 118 | I26: =Inputs!$B$21*(1+Inputs!$B$22)^(I$7-1) -> 118 | J26: =Inputs!$B$21*(1+Inputs!$B$22)^(J$7-1) -> 118 | ... BJ26: =Inputs!$B$21*(1+Inputs!$B$22)^(BJ$7-1) -> 122.79127
A27: Labor revenue | C27: =C20*C26 -> 19470 | D27: =D20*D26 -> 22309.375 | E27: =E20*E26 -> 25148.75 | F27: =F20*F26 -> 27988.125 | G27: =G20*G26 -> 30827.5 | H27: =H20*H26 -> 33666.875 | I27: =I20*I26 -> 36506.25 | J27: =J20*J26 -> 39345.625 | ... BJ27: =BJ20*BJ26 -> 67535.2
A28: Parts revenue | C28: =C20*Inputs!$B$26*(1+Inputs!$B$22)^(C$7-1) -> 15180 | D28: =D20*Inputs!$B$26*(1+Inputs!$B$22)^(D$7-1) -> 17393.75 | E28: =E20*Inputs!$B$26*(1+Inputs!$B$22)^(E$7-1) -> 19607.5 | F28: =F20*Inputs!$B$26*(1+Inputs!$B$22)^(F$7-1) -> 21821.25 | G28: =G20*Inputs!$B$26*(1+Inputs!$B$22)^(G$7-1) -> 24035 | H28: =H20*Inputs!$B$26*(1+Inputs!$B$22)^(H$7-1) -> 26248.75 | I28: =I20*Inputs!$B$26*(1+Inputs!$B$22)^(I$7-1) -> 28462.5 | J28: =J20*Inputs!$B$26*(1+Inputs!$B$22)^(J$7-1) -> 30676.25 | ... BJ28: =BJ20*Inputs!$B$26*(1+Inputs!$B$22)^(BJ$7-1) -> 52654.563
A29: Shop supplies fee | C29: =C27*Inputs!$B$23 -> 778.8 | D29: =D27*Inputs!$B$23 -> 892.375 | E29: =E27*Inputs!$B$23 -> 1005.95 | F29: =F27*Inputs!$B$23 -> 1119.525 | G29: =G27*Inputs!$B$23 -> 1233.1 | H29: =H27*Inputs!$B$23 -> 1346.675 | I29: =I27*Inputs!$B$23 -> 1460.25 | J29: =J27*Inputs!$B$23 -> 1573.825 | ... BJ29: =BJ27*Inputs!$B$23 -> 2701.408
A30: Revenue | C30: =C27+C28+C29 -> 35428.8 | D30: =D27+D28+D29 -> 40595.5 | E30: =E27+E28+E29 -> 45762.2 | F30: =F27+F28+F29 -> 50928.9 | G30: =G27+G28+G29 -> 56095.6 | H30: =H27+H28+H29 -> 61262.3 | I30: =I27+I28+I29 -> 66429 | J30: =J27+J28+J29 -> 71595.7 | ... BJ30: =BJ27+BJ28+BJ29 -> 122891.17
A32: Cost of sales
A33: Technician payroll | C33: =C120 -> -37375 | D33: =D120 -> -37375 | E33: =E120 -> -37375 | F33: =F120 -> -37375 | G33: =G120 -> -37375 | H33: =H120 -> -37375 | I33: =I120 -> -37375 | J33: =J120 -> -37375 | ... BJ33: =BJ120 -> -43723.464
A34: Parts cost | C34: =-C28*(1-Inputs!$B$27) -> -8500.8 | D34: =-D28*(1-Inputs!$B$27) -> -9740.5 | E34: =-E28*(1-Inputs!$B$27) -> -10980.2 | F34: =-F28*(1-Inputs!$B$27) -> -12219.9 | G34: =-G28*(1-Inputs!$B$27) -> -13459.6 | H34: =-H28*(1-Inputs!$B$27) -> -14699.3 | I34: =-I28*(1-Inputs!$B$27) -> -15939 | J34: =-J28*(1-Inputs!$B$27) -> -17178.7 | ... BJ34: =-BJ28*(1-Inputs!$B$27) -> -29486.555
A35: Shop supplies & waste disposal | C35: =-C27*Inputs!$B$30 -> -778.8 | D35: =-D27*Inputs!$B$30 -> -892.375 | E35: =-E27*Inputs!$B$30 -> -1005.95 | F35: =-F27*Inputs!$B$30 -> -1119.525 | G35: =-G27*Inputs!$B$30 -> -1233.1 | H35: =-H27*Inputs!$B$30 -> -1346.675 | I35: =-I27*Inputs!$B$30 -> -1460.25 | J35: =-J27*Inputs!$B$30 -> -1573.825 | ... BJ35: =-BJ27*Inputs!$B$30 -> -2701.408
A36: Comebacks & warranty rework | C36: =-C27*Inputs!$B$31 -> -778.8 | D36: =-D27*Inputs!$B$31 -> -892.375 | E36: =-E27*Inputs!$B$31 -> -1005.95 | F36: =-F27*Inputs!$B$31 -> -1119.525 | G36: =-G27*Inputs!$B$31 -> -1233.1 | H36: =-H27*Inputs!$B$31 -> -1346.675 | I36: =-I27*Inputs!$B$31 -> -1460.25 | J36: =-J27*Inputs!$B$31 -> -1573.825 | ... BJ36: =-BJ27*Inputs!$B$31 -> -2701.408
A37: Cost of sales | C37: =C33+C34+C35+C36 -> -47433.4 | D37: =D33+D34+D35+D36 -> -48900.25 | E37: =E33+E34+E35+E36 -> -50367.1 | F37: =F33+F34+F35+F36 -> -51833.95 | G37: =G33+G34+G35+G36 -> -53300.8 | H37: =H33+H34+H35+H36 -> -54767.65 | I37: =I33+I34+I35+I36 -> -56234.5 | J37: =J33+J34+J35+J36 -> -57701.35 | ... BJ37: =BJ33+BJ34+BJ35+BJ36 -> -78612.835
A38: Gross profit | C38: =C30+C37 -> -12004.6 | D38: =D30+D37 -> -8304.75 | E38: =E30+E37 -> -4604.9 | F38: =F30+F37 -> -905.05 | G38: =G30+G37 -> 2794.8 | H38: =H30+H37 -> 6494.65 | I38: =I30+I37 -> 10194.5 | J38: =J30+J37 -> 13894.35 | ... BJ38: =BJ30+BJ37 -> 44278.336
A40: Operating expenses
A41: Advisors, manager & other payroll | C41: =C123-C120 -> -17729.167 | D41: =D123-D120 -> -17729.167 | E41: =E123-E120 -> -17729.167 | F41: =F123-F120 -> -17729.167 | G41: =G123-G120 -> -17729.167 | H41: =H123-H120 -> -17729.167 | I41: =I123-I120 -> -17729.167 | J41: =J123-J120 -> -17729.167 | ... BJ41: =BJ123-BJ120 -> -20740.617
A42: Shop rent or land cost | C42: =-Inputs!$B$36*(1+Inputs!$B$37)^(C$7-1)*1 -> -18000 | D42: =-Inputs!$B$36*(1+Inputs!$B$37)^(D$7-1)*1 -> -18000 | E42: =-Inputs!$B$36*(1+Inputs!$B$37)^(E$7-1)*1 -> -18000 | F42: =-Inputs!$B$36*(1+Inputs!$B$37)^(F$7-1)*1 -> -18000 | G42: =-Inputs!$B$36*(1+Inputs!$B$37)^(G$7-1)*1 -> -18000 | H42: =-Inputs!$B$36*(1+Inputs!$B$37)^(H$7-1)*1 -> -18000 | I42: =-Inputs!$B$36*(1+Inputs!$B$37)^(I$7-1)*1 -> -18000 | J42: =-Inputs!$B$36*(1+Inputs!$B$37)^(J$7-1)*1 -> -18000 | ... BJ42: =-Inputs!$B$36*(1+Inputs!$B$37)^(BJ$7-1)*1 -> -20259.159
A43: Insurance | C43: =-Inputs!$B$38*(1+Inputs!$B$33)^(C$7-1)*1 -> -4500 | D43: =-Inputs!$B$38*(1+Inputs!$B$33)^(D$7-1)*1 -> -4500 | E43: =-Inputs!$B$38*(1+Inputs!$B$33)^(E$7-1)*1 -> -4500 | F43: =-Inputs!$B$38*(1+Inputs!$B$33)^(F$7-1)*1 -> -4500 | G43: =-Inputs!$B$38*(1+Inputs!$B$33)^(G$7-1)*1 -> -4500 | H43: =-Inputs!$B$38*(1+Inputs!$B$33)^(H$7-1)*1 -> -4500 | I43: =-Inputs!$B$38*(1+Inputs!$B$33)^(I$7-1)*1 -> -4500 | J43: =-Inputs!$B$38*(1+Inputs!$B$33)^(J$7-1)*1 -> -4500 | ... BJ43: =-Inputs!$B$38*(1+Inputs!$B$33)^(BJ$7-1)*1 -> -5264.3635
A44: Software, utilities & other G&A | C44: =-Inputs!$B$39*(1+Inputs!$B$33)^(C$7-1)*1 -> -9000 | D44: =-Inputs!$B$39*(1+Inputs!$B$33)^(D$7-1)*1 -> -9000 | E44: =-Inputs!$B$39*(1+Inputs!$B$33)^(E$7-1)*1 -> -9000 | F44: =-Inputs!$B$39*(1+Inputs!$B$33)^(F$7-1)*1 -> -9000 | G44: =-Inputs!$B$39*(1+Inputs!$B$33)^(G$7-1)*1 -> -9000 | H44: =-Inputs!$B$39*(1+Inputs!$B$33)^(H$7-1)*1 -> -9000 | I44: =-Inputs!$B$39*(1+Inputs!$B$33)^(I$7-1)*1 -> -9000 | J44: =-Inputs!$B$39*(1+Inputs!$B$33)^(J$7-1)*1 -> -9000 | ... BJ44: =-Inputs!$B$39*(1+Inputs!$B$33)^(BJ$7-1)*1 -> -10528.727
A45: Marketing | C45: =-Inputs!$B$40*(1+Inputs!$B$41)^(C$7-1)*1 -> -7000 | D45: =-Inputs!$B$40*(1+Inputs!$B$41)^(D$7-1)*1 -> -7000 | E45: =-Inputs!$B$40*(1+Inputs!$B$41)^(E$7-1)*1 -> -7000 | F45: =-Inputs!$B$40*(1+Inputs!$B$41)^(F$7-1)*1 -> -7000 | G45: =-Inputs!$B$40*(1+Inputs!$B$41)^(G$7-1)*1 -> -7000 | H45: =-Inputs!$B$40*(1+Inputs!$B$41)^(H$7-1)*1 -> -7000 | I45: =-Inputs!$B$40*(1+Inputs!$B$41)^(I$7-1)*1 -> -7000 | J45: =-Inputs!$B$40*(1+Inputs!$B$41)^(J$7-1)*1 -> -7000 | ... BJ45: =-Inputs!$B$40*(1+Inputs!$B$41)^(BJ$7-1)*1 -> -1680.7
A46: Card processing fees | C46: =-C30*Inputs!$B$32 -> -1133.7216 | D46: =-D30*Inputs!$B$32 -> -1299.056 | E46: =-E30*Inputs!$B$32 -> -1464.3904 | F46: =-F30*Inputs!$B$32 -> -1629.7248 | G46: =-G30*Inputs!$B$32 -> -1795.0592 | H46: =-H30*Inputs!$B$32 -> -1960.3936 | I46: =-I30*Inputs!$B$32 -> -2125.728 | J46: =-J30*Inputs!$B$32 -> -2291.0624 | ... BJ46: =-BJ30*Inputs!$B$32 -> -3932.5175
A47: Total operating expenses | C47: =C41+C42+C43+C44+C45+C46 -> -57362.888 | D47: =D41+D42+D43+D44+D45+D46 -> -57528.223 | E47: =E41+E42+E43+E44+E45+E46 -> -57693.557 | F47: =F41+F42+F43+F44+F45+F46 -> -57858.891 | G47: =G41+G42+G43+G44+G45+G46 -> -58024.226 | H47: =H41+H42+H43+H44+H45+H46 -> -58189.56 | I47: =I41+I42+I43+I44+I45+I46 -> -58354.895 | J47: =J41+J42+J43+J44+J45+J46 -> -58520.229 | ... BJ47: =BJ41+BJ42+BJ43+BJ44+BJ45+BJ46 -> -62406.084
A48: EBITDA | C48: =C38+C47 -> -69367.488 | D48: =D38+D47 -> -65832.973 | E48: =E38+E47 -> -62298.457 | F48: =F38+F47 -> -58763.941 | G48: =G38+G47 -> -55229.426 | H48: =H38+H47 -> -51694.91 | I48: =I38+I47 -> -48160.395 | J48: =J38+J47 -> -44625.879 | ... BJ48: =BJ38+BJ47 -> -18127.748
A50: Profit after depreciation, interest, tax
A51: EBIT | C51: =C48+C68 -> -73346.655 | D51: =D48+D68 -> -69812.139 | E51: =E48+E68 -> -66277.624 | F51: =F48+F68 -> -62743.108 | G51: =G48+G68 -> -59208.593 | H51: =H48+H68 -> -55674.077 | I51: =I48+I68 -> -52139.561 | J51: =J48+J68 -> -48605.046 | ... BJ51: =BJ48+BJ68 -> -22940.248
A52: Interest on loan (average balance after drawdown) | C52: =-(C73+C74+C76)/2*Inputs!$B$69/12 -> -1875 | D52: =-(D73+D74+D76)/2*Inputs!$B$69/12 -> -1863.8393 | E52: =-(E73+E74+E76)/2*Inputs!$B$69/12 -> -1841.5179 | F52: =-(F73+F74+F76)/2*Inputs!$B$69/12 -> -1819.1964 | G52: =-(G73+G74+G76)/2*Inputs!$B$69/12 -> -1796.875 | H52: =-(H73+H74+H76)/2*Inputs!$B$69/12 -> -1774.5536 | I52: =-(I73+I74+I76)/2*Inputs!$B$69/12 -> -1752.2321 | J52: =-(J73+J74+J76)/2*Inputs!$B$69/12 -> -1729.9107 | ... BJ52: =-(BJ73+BJ74+BJ76)/2*Inputs!$B$69/12 -> -569.19643
A53: Pre-tax income | C53: =C51+C52 -> -75221.655 | D53: =D51+D52 -> -71675.979 | E53: =E51+E52 -> -68119.142 | F53: =F51+F52 -> -64562.305 | G53: =G51+G52 -> -61005.468 | H53: =H51+H52 -> -57448.631 | I53: =I51+I52 -> -53891.793 | J53: =J51+J52 -> -50334.956 | ... BJ53: =BJ51+BJ52 -> -23509.444
A54: Helper: cumulative pre-tax income | C54: =C53 -> -75221.655 | D54: =C54+D53 -> -146897.63 | E54: =D54+E53 -> -215016.78 | F54: =E54+F53 -> -279579.08 | G54: =F54+G53 -> -340584.55 | H54: =G54+H53 -> -398033.18 | I54: =H54+I53 -> -451924.97 | J54: =I54+J53 -> -502259.93 | K54: =J54+K53 -> -549038.05 | ... BJ54: =BI54+BJ53 -> -1711891.7
A55: Helper: cumulative taxable income (losses carried forward) | C55: =MAX(0,C54) -> 0 | D55: =MAX(C55,D54) -> 0 | E55: =MAX(D55,E54) -> 0 | F55: =MAX(E55,F54) -> 0 | G55: =MAX(F55,G54) -> 0 | H55: =MAX(G55,H54) -> 0 | I55: =MAX(H55,I54) -> 0 | J55: =MAX(I55,J54) -> 0 | K55: =MAX(J55,K54) -> 0 | ... BJ55: =MAX(BI55,BJ54) -> 0
A56: Income tax | C56: =-C55*Inputs!$B$79 -> 0 | D56: =-(D55-C55)*Inputs!$B$79 -> 0 | E56: =-(E55-D55)*Inputs!$B$79 -> 0 | F56: =-(F55-E55)*Inputs!$B$79 -> 0 | G56: =-(G55-F55)*Inputs!$B$79 -> 0 | H56: =-(H55-G55)*Inputs!$B$79 -> 0 | I56: =-(I55-H55)*Inputs!$B$79 -> 0 | J56: =-(J55-I55)*Inputs!$B$79 -> 0 | K56: =-(K55-J55)*Inputs!$B$79 -> 0 | ... BJ56: =-(BJ55-BI55)*Inputs!$B$79 -> 0
A57: Net income | C57: =C53+C56 -> -75221.655 | D57: =D53+D56 -> -71675.979 | E57: =E53+E56 -> -68119.142 | F57: =F53+F56 -> -64562.305 | G57: =G53+G56 -> -61005.468 | H57: =H53+H56 -> -57448.631 | I57: =I53+I56 -> -53891.793 | J57: =J53+J56 -> -50334.956 | ... BJ57: =BJ53+BJ56 -> -23509.444
A59: Fixed assets & capital spending
A60: Lifts & bay equipment | C60: =IF(C$6=1,Inputs!$B$15*Inputs!$B$44,0) -> 132000 | D60: =IF(D$6=1,Inputs!$B$15*Inputs!$B$44,0) -> 0 | E60: =IF(E$6=1,Inputs!$B$15*Inputs!$B$44,0) -> 0 | F60: =IF(F$6=1,Inputs!$B$15*Inputs!$B$44,0) -> 0 | G60: =IF(G$6=1,Inputs!$B$15*Inputs!$B$44,0) -> 0 | H60: =IF(H$6=1,Inputs!$B$15*Inputs!$B$44,0) -> 0 | I60: =IF(I$6=1,Inputs!$B$15*Inputs!$B$44,0) -> 0 | J60: =IF(J$6=1,Inputs!$B$15*Inputs!$B$44,0) -> 0 | ... BJ60: =IF(BJ$6=1,Inputs!$B$15*Inputs!$B$44,0) -> 0
A61: Diagnostic tools & scan equipment | C61: =IF(C$6=1,Inputs!$B$45,0) -> 70000 | D61: =IF(D$6=1,Inputs!$B$45,0) -> 0 | E61: =IF(E$6=1,Inputs!$B$45,0) -> 0 | F61: =IF(F$6=1,Inputs!$B$45,0) -> 0 | G61: =IF(G$6=1,Inputs!$B$45,0) -> 0 | H61: =IF(H$6=1,Inputs!$B$45,0) -> 0 | I61: =IF(I$6=1,Inputs!$B$45,0) -> 0 | J61: =IF(J$6=1,Inputs!$B$45,0) -> 0 | ... BJ61: =IF(BJ$6=1,Inputs!$B$45,0) -> 0
A62: Leasehold improvements & signage | C62: =IF(C$6=1,Inputs!$B$46,0) -> 180000 | D62: =IF(D$6=1,Inputs!$B$46,0) -> 0 | E62: =IF(E$6=1,Inputs!$B$46,0) -> 0 | F62: =IF(F$6=1,Inputs!$B$46,0) -> 0 | G62: =IF(G$6=1,Inputs!$B$46,0) -> 0 | H62: =IF(H$6=1,Inputs!$B$46,0) -> 0 | I62: =IF(I$6=1,Inputs!$B$46,0) -> 0 | J62: =IF(J$6=1,Inputs!$B$46,0) -> 0 | ... BJ62: =IF(BJ$6=1,Inputs!$B$46,0) -> 0
A63: Land or building (not depreciated) | C63: =IF(C$6=1,Inputs!$B$47,0) -> 0 | D63: =IF(D$6=1,Inputs!$B$47,0) -> 0 | E63: =IF(E$6=1,Inputs!$B$47,0) -> 0 | F63: =IF(F$6=1,Inputs!$B$47,0) -> 0 | G63: =IF(G$6=1,Inputs!$B$47,0) -> 0 | H63: =IF(H$6=1,Inputs!$B$47,0) -> 0 | I63: =IF(I$6=1,Inputs!$B$47,0) -> 0 | J63: =IF(J$6=1,Inputs!$B$47,0) -> 0 | ... BJ63: =IF(BJ$6=1,Inputs!$B$47,0) -> 0
A64: Equipment & tool refresh (first period of each year from year 2) | C64: =IF(AND(C$7>1,MOD(C$6-1,12)=0),Inputs!$B$48,0) -> 0 | D64: =IF(AND(D$7>1,MOD(D$6-1,12)=0),Inputs!$B$48,0) -> 0 | E64: =IF(AND(E$7>1,MOD(E$6-1,12)=0),Inputs!$B$48,0) -> 0 | F64: =IF(AND(F$7>1,MOD(F$6-1,12)=0),Inputs!$B$48,0) -> 0 | G64: =IF(AND(G$7>1,MOD(G$6-1,12)=0),Inputs!$B$48,0) -> 0 | H64: =IF(AND(H$7>1,MOD(H$6-1,12)=0),Inputs!$B$48,0) -> 0 | I64: =IF(AND(I$7>1,MOD(I$6-1,12)=0),Inputs!$B$48,0) -> 0 | J64: =IF(AND(J$7>1,MOD(J$6-1,12)=0),Inputs!$B$48,0) -> 0 | ... BJ64: =IF(AND(BJ$7>1,MOD(BJ$6-1,12)=0),Inputs!$B$48,0) -> 0
A65: Capital spending | C65: =C60+C61+C62+C63+C64 -> 382000 | D65: =D60+D61+D62+D63+D64 -> 0 | E65: =E60+E61+E62+E63+E64 -> 0 | F65: =F60+F61+F62+F63+F64 -> 0 | G65: =G60+G61+G62+G63+G64 -> 0 | H65: =H60+H61+H62+H63+H64 -> 0 | I65: =I60+I61+I62+I63+I64 -> 0 | J65: =J60+J61+J62+J63+J64 -> 0 | ... BJ65: =BJ60+BJ61+BJ62+BJ63+BJ64 -> 0
A66: Fixed assets at cost | C66: =C65 -> 382000 | D66: =C66+D65 -> 382000 | E66: =D66+E65 -> 382000 | F66: =E66+F65 -> 382000 | G66: =F66+G65 -> 382000 | H66: =G66+H65 -> 382000 | I66: =H66+I65 -> 382000 | J66: =I66+J65 -> 382000 | K66: =J66+K65 -> 382000 | ... BJ66: =BI66+BJ65 -> 462000
A67: Land at cost (not depreciated) | C67: =C63 -> 0 | D67: =C67+D63 -> 0 | E67: =D67+E63 -> 0 | F67: =E67+F63 -> 0 | G67: =F67+G63 -> 0 | H67: =G67+H63 -> 0 | I67: =H67+I63 -> 0 | J67: =I67+J63 -> 0 | K67: =J67+K63 -> 0 | ... BJ67: =BI67+BJ63 -> 0
A68: Depreciation | C68: =-MIN((C66-C67)/MAX(1,Inputs!$B$78*12),C65-C67) -> -3979.1667 | D68: =-MIN((D66-D67)/MAX(1,Inputs!$B$78*12),C70+D65-D67) -> -3979.1667 | E68: =-MIN((E66-E67)/MAX(1,Inputs!$B$78*12),D70+E65-E67) -> -3979.1667 | F68: =-MIN((F66-F67)/MAX(1,Inputs!$B$78*12),E70+F65-F67) -> -3979.1667 | G68: =-MIN((G66-G67)/MAX(1,Inputs!$B$78*12),F70+G65-G67) -> -3979.1667 | H68: =-MIN((H66-H67)/MAX(1,Inputs!$B$78*12),G70+H65-H67) -> -3979.1667 | I68: =-MIN((I66-I67)/MAX(1,Inputs!$B$78*12),H70+I65-I67) -> -3979.1667 | J68: =-MIN((J66-J67)/MAX(1,Inputs!$B$78*12),I70+J65-J67) -> -3979.1667 | K68: =-MIN((K66-K67)/MAX(1,Inputs!$B$78*12),J70+K65-K67) -> -3979.1667 | ... BJ68: =-MIN((BJ66-BJ67)/MAX(1,Inputs!$B$78*12),BI70+BJ65-BJ67) -> -4812.5
A69: Accumulated depreciation | C69: =C68 -> -3979.1667 | D69: =C69+D68 -> -7958.3333 | E69: =D69+E68 -> -11937.5 | F69: =E69+F68 -> -15916.667 | G69: =F69+G68 -> -19895.833 | H69: =G69+H68 -> -23875 | I69: =H69+I68 -> -27854.167 | J69: =I69+J68 -> -31833.333 | K69: =J69+K68 -> -35812.5 | ... BJ69: =BI69+BJ68 -> -263750
A70: Net fixed assets | C70: =C66+C69 -> 378020.83 | D70: =D66+D69 -> 374041.67 | E70: =E66+E69 -> 370062.5 | F70: =F66+F69 -> 366083.33 | G70: =G66+G69 -> 362104.17 | H70: =H66+H69 -> 358125 | I70: =I66+I69 -> 354145.83 | J70: =J66+J69 -> 350166.67 | ... BJ70: =BJ66+BJ69 -> 198250
A72: Debt
A73: Loan — opening balance | C73: =0 -> 0 | D73: =C76 -> 250000 | E73: =D76 -> 247023.81 | F73: =E76 -> 244047.62 | G73: =F76 -> 241071.43 | H73: =G76 -> 238095.24 | I73: =H76 -> 235119.05 | J73: =I76 -> 232142.86 | K73: =J76 -> 229166.67 | ... BJ73: =BI76 -> 77380.952
A74: Loan drawdown | C74: =IF(C$6=1,Inputs!$B$68,0) -> 250000 | D74: =IF(D$6=1,Inputs!$B$68,0) -> 0 | E74: =IF(E$6=1,Inputs!$B$68,0) -> 0 | F74: =IF(F$6=1,Inputs!$B$68,0) -> 0 | G74: =IF(G$6=1,Inputs!$B$68,0) -> 0 | H74: =IF(H$6=1,Inputs!$B$68,0) -> 0 | I74: =IF(I$6=1,Inputs!$B$68,0) -> 0 | J74: =IF(J$6=1,Inputs!$B$68,0) -> 0 | ... BJ74: =IF(BJ$6=1,Inputs!$B$68,0) -> 0
A75: Loan repayment | C75: =-MIN(C73,Inputs!$B$68/MAX(1,Inputs!$B$70*12)) -> 0 | D75: =-MIN(D73,Inputs!$B$68/MAX(1,Inputs!$B$70*12)) -> -2976.1905 | E75: =-MIN(E73,Inputs!$B$68/MAX(1,Inputs!$B$70*12)) -> -2976.1905 | F75: =-MIN(F73,Inputs!$B$68/MAX(1,Inputs!$B$70*12)) -> -2976.1905 | G75: =-MIN(G73,Inputs!$B$68/MAX(1,Inputs!$B$70*12)) -> -2976.1905 | H75: =-MIN(H73,Inputs!$B$68/MAX(1,Inputs!$B$70*12)) -> -2976.1905 | I75: =-MIN(I73,Inputs!$B$68/MAX(1,Inputs!$B$70*12)) -> -2976.1905 | J75: =-MIN(J73,Inputs!$B$68/MAX(1,Inputs!$B$70*12)) -> -2976.1905 | ... BJ75: =-MIN(BJ73,Inputs!$B$68/MAX(1,Inputs!$B$70*12)) -> -2976.1905
A76: Loan — closing balance | C76: =C73+C74+C75 -> 250000 | D76: =D73+D74+D75 -> 247023.81 | E76: =E73+E74+E75 -> 244047.62 | F76: =F73+F74+F75 -> 241071.43 | G76: =G73+G74+G75 -> 238095.24 | H76: =H73+H74+H75 -> 235119.05 | I76: =I73+I74+I75 -> 232142.86 | J76: =J73+J74+J75 -> 229166.67 | ... BJ76: =BJ73+BJ74+BJ75 -> 74404.762
A78: Working capital
A79: Accounts receivable | C79: =C30*Inputs!$B$73/30 -> 3542.88 | D79: =D30*Inputs!$B$73/30 -> 4059.55 | E79: =E30*Inputs!$B$73/30 -> 4576.22 | F79: =F30*Inputs!$B$73/30 -> 5092.89 | G79: =G30*Inputs!$B$73/30 -> 5609.56 | H79: =H30*Inputs!$B$73/30 -> 6126.23 | I79: =I30*Inputs!$B$73/30 -> 6642.9 | J79: =J30*Inputs!$B$73/30 -> 7159.57 | ... BJ79: =BJ30*Inputs!$B$73/30 -> 12289.117
A80: Inventory | C80: =-C37*Inputs!$B$74/30 -> 12648.907 | D80: =-D37*Inputs!$B$74/30 -> 13040.067 | E80: =-E37*Inputs!$B$74/30 -> 13431.227 | F80: =-F37*Inputs!$B$74/30 -> 13822.387 | G80: =-G37*Inputs!$B$74/30 -> 14213.547 | H80: =-H37*Inputs!$B$74/30 -> 14604.707 | I80: =-I37*Inputs!$B$74/30 -> 14995.867 | J80: =-J37*Inputs!$B$74/30 -> 15387.027 | ... BJ80: =-BJ37*Inputs!$B$74/30 -> 20963.423
A81: Accounts payable | C81: =-C37*Inputs!$B$75/30 -> 39527.833 | D81: =-D37*Inputs!$B$75/30 -> 40750.208 | E81: =-E37*Inputs!$B$75/30 -> 41972.583 | F81: =-F37*Inputs!$B$75/30 -> 43194.958 | G81: =-G37*Inputs!$B$75/30 -> 44417.333 | H81: =-H37*Inputs!$B$75/30 -> 45639.708 | I81: =-I37*Inputs!$B$75/30 -> 46862.083 | J81: =-J37*Inputs!$B$75/30 -> 48084.458 | ... BJ81: =-BJ37*Inputs!$B$75/30 -> 65510.696
A82: (Increase) / decrease in receivables | C82: =-C79 -> -3542.88 | D82: =C79-D79 -> -516.67 | E82: =D79-E79 -> -516.67 | F82: =E79-F79 -> -516.67 | G82: =F79-G79 -> -516.67 | H82: =G79-H79 -> -516.67 | I82: =H79-I79 -> -516.67 | J82: =I79-J79 -> -516.67 | K82: =J79-K79 -> -516.67 | ... BJ82: =BI79-BJ79 -> 0
A83: (Increase) / decrease in inventory | C83: =-C80 -> -12648.907 | D83: =C80-D80 -> -391.16 | E83: =D80-E80 -> -391.16 | F83: =E80-F80 -> -391.16 | G83: =F80-G80 -> -391.16 | H83: =G80-H80 -> -391.16 | I83: =H80-I80 -> -391.16 | J83: =I80-J80 -> -391.16 | K83: =J80-K80 -> -391.16 | ... BJ83: =BI80-BJ80 -> 0
A84: Increase / (decrease) in payables | C84: =C81 -> 39527.833 | D84: =D81-C81 -> 1222.375 | E84: =E81-D81 -> 1222.375 | F84: =F81-E81 -> 1222.375 | G84: =G81-F81 -> 1222.375 | H84: =H81-G81 -> 1222.375 | I84: =I81-H81 -> 1222.375 | J84: =J81-I81 -> 1222.375 | K84: =K81-J81 -> 1222.375 | ... BJ84: =BJ81-BI81 -> 0
A86: Cash flow
A87: Operating cash flow | C87: =C57-C68+C82+C83+C84 -> -47906.442 | D87: =D57-D68+D82+D83+D84 -> -67382.267 | E87: =E57-E68+E82+E83+E84 -> -63825.43 | F87: =F57-F68+F82+F83+F84 -> -60268.593 | G87: =G57-G68+G82+G83+G84 -> -56711.756 | H87: =H57-H68+H82+H83+H84 -> -53154.919 | I87: =I57-I68+I82+I83+I84 -> -49598.082 | J87: =J57-J68+J82+J83+J84 -> -46041.245 | ... BJ87: =BJ57-BJ68+BJ82+BJ83+BJ84 -> -18696.944
A88: Investing cash flow (capex) | C88: =-C65 -> -382000 | D88: =-D65 -> 0 | E88: =-E65 -> 0 | F88: =-F65 -> 0 | G88: =-G65 -> 0 | H88: =-H65 -> 0 | I88: =-I65 -> 0 | J88: =-J65 -> 0 | ... BJ88: =-BJ65 -> 0
A89: Equity raised | C89: =IF(C$6=1,Inputs!$B$67,0) -> 480000 | D89: =IF(D$6=1,Inputs!$B$67,0) -> 0 | E89: =IF(E$6=1,Inputs!$B$67,0) -> 0 | F89: =IF(F$6=1,Inputs!$B$67,0) -> 0 | G89: =IF(G$6=1,Inputs!$B$67,0) -> 0 | H89: =IF(H$6=1,Inputs!$B$67,0) -> 0 | I89: =IF(I$6=1,Inputs!$B$67,0) -> 0 | J89: =IF(J$6=1,Inputs!$B$67,0) -> 0 | ... BJ89: =IF(BJ$6=1,Inputs!$B$67,0) -> 0
A90: Financing cash flow | C90: =C89+C74+C75 -> 730000 | D90: =D89+D74+D75 -> -2976.1905 | E90: =E89+E74+E75 -> -2976.1905 | F90: =F89+F74+F75 -> -2976.1905 | G90: =G89+G74+G75 -> -2976.1905 | H90: =H89+H74+H75 -> -2976.1905 | I90: =I89+I74+I75 -> -2976.1905 | J90: =J89+J74+J75 -> -2976.1905 | ... BJ90: =BJ89+BJ74+BJ75 -> -2976.1905
A91: Net cash flow | C91: =C87+C88+C90 -> 300093.56 | D91: =D87+D88+D90 -> -70358.457 | E91: =E87+E88+E90 -> -66801.62 | F91: =F87+F88+F90 -> -63244.783 | G91: =G87+G88+G90 -> -59687.946 | H91: =H87+H88+H90 -> -56131.109 | I91: =I87+I88+I90 -> -52574.272 | J91: =J87+J88+J90 -> -49017.435 | ... BJ91: =BJ87+BJ88+BJ90 -> -21673.135
A92: Opening cash | C92: =0 -> 0 | D92: =C93 -> 300093.56 | E92: =D93 -> 229735.1 | F92: =E93 -> 162933.48 | G92: =F93 -> 99688.697 | H92: =G93 -> 40000.751 | I92: =H93 -> -16130.358 | J92: =I93 -> -68704.631 | K92: =J93 -> -117722.07 | ... BJ92: =BI93 -> -1301805.6
A93: Closing cash | C93: =C92+C91 -> 300093.56 | D93: =D92+D91 -> 229735.1 | E93: =E92+E91 -> 162933.48 | F93: =F92+F91 -> 99688.697 | G93: =G92+G91 -> 40000.751 | H93: =H92+H91 -> -16130.358 | I93: =I92+I91 -> -68704.631 | J93: =J92+J91 -> -117722.07 | ... BJ93: =BJ92+BJ91 -> -1323478.8
A94: Helper: EBITDA positive (1/0) | C94: =IF(C48>0,1,0) -> 0 | D94: =IF(D48>0,1,0) -> 0 | E94: =IF(E48>0,1,0) -> 0 | F94: =IF(F48>0,1,0) -> 0 | G94: =IF(G48>0,1,0) -> 0 | H94: =IF(H48>0,1,0) -> 0 | I94: =IF(I48>0,1,0) -> 0 | J94: =IF(J48>0,1,0) -> 0 | ... BJ94: =IF(BJ48>0,1,0) -> 0
A96: Goal modules
A97: Helper: net income positive (1/0) | C97: =IF(C57>0,1,0) -> 0 | D97: =IF(D57>0,1,0) -> 0 | E97: =IF(E57>0,1,0) -> 0 | F97: =IF(F57>0,1,0) -> 0 | G97: =IF(G57>0,1,0) -> 0 | H97: =IF(H57>0,1,0) -> 0 | I97: =IF(I57>0,1,0) -> 0 | J97: =IF(J57>0,1,0) -> 0 | ... BJ97: =IF(BJ57>0,1,0) -> 0
A98: Cash flow before financing (operating + investing) | C98: =C87+C88 -> -429906.44 | D98: =D87+D88 -> -67382.267 | E98: =E87+E88 -> -63825.43 | F98: =F87+F88 -> -60268.593 | G98: =G87+G88 -> -56711.756 | H98: =H87+H88 -> -53154.919 | I98: =I87+I88 -> -49598.082 | J98: =J87+J88 -> -46041.245 | ... BJ98: =BJ87+BJ88 -> -18696.944
A99: Cumulative cash flow before financing | C99: =C98 -> -429906.44 | D99: =C99+D98 -> -497288.71 | E99: =D99+E98 -> -561114.14 | F99: =E99+F98 -> -621382.73 | G99: =F99+G98 -> -678094.49 | H99: =G99+H98 -> -731249.41 | I99: =H99+I98 -> -780847.49 | J99: =I99+J98 -> -826888.73 | K99: =J99+K98 -> -869373.14 | ... BJ99: =BI99+BJ98 -> -1877883.5
A100: Helper: lowest cumulative cash flow so far | C100: =C99 -> -429906.44 | D100: =MIN(C100,D99) -> -497288.71 | E100: =MIN(D100,E99) -> -561114.14 | F100: =MIN(E100,F99) -> -621382.73 | G100: =MIN(F100,G99) -> -678094.49 | H100: =MIN(G100,H99) -> -731249.41 | I100: =MIN(H100,I99) -> -780847.49 | J100: =MIN(I100,J99) -> -826888.73 | K100: =MIN(J100,K99) -> -869373.14 | ... BJ100: =MIN(BI100,BJ99) -> -1877883.5
A101: Helper: investment paid back (1/0) | C101: =IF(AND(C99>=0,C100<0),1,0) -> 0 | D101: =IF(AND(D99>=0,D100<0),1,0) -> 0 | E101: =IF(AND(E99>=0,E100<0),1,0) -> 0 | F101: =IF(AND(F99>=0,F100<0),1,0) -> 0 | G101: =IF(AND(G99>=0,G100<0),1,0) -> 0 | H101: =IF(AND(H99>=0,H100<0),1,0) -> 0 | I101: =IF(AND(I99>=0,I100<0),1,0) -> 0 | J101: =IF(AND(J99>=0,J100<0),1,0) -> 0 | ... BJ101: =IF(AND(BJ99>=0,BJ100<0),1,0) -> 0
A102: Unlevered free cash flow (operating + after-tax interest − capex) | C102: =C87-C52*(1-Inputs!$B$79)+C88 -> -428425.19 | D102: =D87-D52*(1-Inputs!$B$79)+D88 -> -65909.834 | E102: =E87-E52*(1-Inputs!$B$79)+E88 -> -62370.631 | F102: =F87-F52*(1-Inputs!$B$79)+F88 -> -58831.428 | G102: =G87-G52*(1-Inputs!$B$79)+G88 -> -55292.225 | H102: =H87-H52*(1-Inputs!$B$79)+H88 -> -51753.022 | I102: =I87-I52*(1-Inputs!$B$79)+I88 -> -48213.818 | J102: =J87-J52*(1-Inputs!$B$79)+J88 -> -44674.615 | ... BJ102: =BJ87-BJ52*(1-Inputs!$B$79)+BJ88 -> -18247.279
A104: Balance sheet
A105: Paid-in capital | C105: =C89 -> 480000 | D105: =C105+D89 -> 480000 | E105: =D105+E89 -> 480000 | F105: =E105+F89 -> 480000 | G105: =F105+G89 -> 480000 | H105: =G105+H89 -> 480000 | I105: =H105+I89 -> 480000 | J105: =I105+J89 -> 480000 | K105: =J105+K89 -> 480000 | ... BJ105: =BI105+BJ89 -> 480000
A106: Retained earnings | C106: =C57 -> -75221.655 | D106: =C106+D57 -> -146897.63 | E106: =D106+E57 -> -215016.78 | F106: =E106+F57 -> -279579.08 | G106: =F106+G57 -> -340584.55 | H106: =G106+H57 -> -398033.18 | I106: =H106+I57 -> -451924.97 | J106: =I106+J57 -> -502259.93 | K106: =J106+K57 -> -549038.05 | ... BJ106: =BI106+BJ57 -> -1711891.7
A107: Total assets | C107: =C93+C79+C80+C70 -> 694306.18 | D107: =D93+D79+D80+D70 -> 620876.38 | E107: =E93+E79+E80+E70 -> 551003.43 | F107: =F93+F79+F80+F70 -> 484687.31 | G107: =G93+G79+G80+G70 -> 421928.02 | H107: =H93+H79+H80+H70 -> 362725.58 | I107: =I93+I79+I80+I70 -> 307079.97 | J107: =J93+J79+J80+J70 -> 254991.2 | ... BJ107: =BJ93+BJ79+BJ80+BJ70 -> -1091976.2
A108: Total liabilities | C108: =C81+C76 -> 289527.83 | D108: =D81+D76 -> 287774.02 | E108: =E81+E76 -> 286020.2 | F108: =F81+F76 -> 284266.39 | G108: =G81+G76 -> 282512.57 | H108: =H81+H76 -> 280758.76 | I108: =I81+I76 -> 279004.94 | J108: =J81+J76 -> 277251.12 | ... BJ108: =BJ81+BJ76 -> 139915.46
A109: Total equity | C109: =C105+C106 -> 404778.35 | D109: =D105+D106 -> 333102.37 | E109: =E105+E106 -> 264983.22 | F109: =F105+F106 -> 200420.92 | G109: =G105+G106 -> 139415.45 | H109: =H105+H106 -> 81966.822 | I109: =I105+I106 -> 28075.029 | J109: =J105+J106 -> -22259.928 | ... BJ109: =BJ105+BJ106 -> -1231891.7
A110: Total liabilities & equity | C110: =C108+C109 -> 694306.18 | D110: =D108+D109 -> 620876.38 | E110: =E108+E109 -> 551003.43 | F110: =F108+F109 -> 484687.31 | G110: =G108+G109 -> 421928.02 | H110: =H108+H109 -> 362725.58 | I110: =I108+I109 -> 307079.97 | J110: =J108+J109 -> 254991.2 | ... BJ110: =BJ108+BJ109 -> -1091976.2
A111: Check: assets − liabilities − equity | C111: =C107-C110 -> 0 | D111: =D107-D110 -> 0 | E111: =E107-E110 -> 0 | F111: =F107-F110 -> 0 | G111: =G107-G110 -> 0 | H111: =H107-H110 -> 0 | I111: =I107-I110 -> 0 | J111: =J107-J110 -> 0 | ... BJ111: =BJ107-BJ110 -> 0
A113: Headcount (FTE)
A114: Technicians — FTE | C114: =Inputs!$B$51*(1+Inputs!$B$53)^(C$7-1)*MAX(0,MIN(1,C$6*1-Inputs!$B$54+1))/1 -> 5 | D114: =Inputs!$B$51*(1+Inputs!$B$53)^(D$7-1)*MAX(0,MIN(1,D$6*1-Inputs!$B$54+1))/1 -> 5 | E114: =Inputs!$B$51*(1+Inputs!$B$53)^(E$7-1)*MAX(0,MIN(1,E$6*1-Inputs!$B$54+1))/1 -> 5 | F114: =Inputs!$B$51*(1+Inputs!$B$53)^(F$7-1)*MAX(0,MIN(1,F$6*1-Inputs!$B$54+1))/1 -> 5 | G114: =Inputs!$B$51*(1+Inputs!$B$53)^(G$7-1)*MAX(0,MIN(1,G$6*1-Inputs!$B$54+1))/1 -> 5 | H114: =Inputs!$B$51*(1+Inputs!$B$53)^(H$7-1)*MAX(0,MIN(1,H$6*1-Inputs!$B$54+1))/1 -> 5 | I114: =Inputs!$B$51*(1+Inputs!$B$53)^(I$7-1)*MAX(0,MIN(1,I$6*1-Inputs!$B$54+1))/1 -> 5 | J114: =Inputs!$B$51*(1+Inputs!$B$53)^(J$7-1)*MAX(0,MIN(1,J$6*1-Inputs!$B$54+1))/1 -> 5 | ... BJ114: =Inputs!$B$51*(1+Inputs!$B$53)^(BJ$7-1)*MAX(0,MIN(1,BJ$6*1-Inputs!$B$54+1))/1 -> 5
...

Sheet Checks
A1: Model checks | E1: =HYPERLINK("#'Cover'!A1","◂ Contents") -> ◂ Contents
A2: Live formulas: they re-run every time an input changes.
A3: Check | B3: Result | C3: What it tests
A4: Annual revenue ties to period detail | B4: =IF(ABS(SUM('P&L'!$B$5:$F$5)-SUM(Monthly!$C$28:$BJ$28))<0.5,"PASS","FAIL") -> PASS | C4: Sum of annual revenue equals the sum of every period
A5: Annual net income ties to period detail | B5: =IF(ABS(SUM('P&L'!$B$23:$F$23)-SUM(Monthly!$C$55:$BJ$55))<0.5,"PASS","FAIL") -> PASS | C5: Sum of annual net income equals the sum of every period
A6: EBITDA reconciliation | B6: =IF(ABS(SUM(Monthly!$C$46:$BJ$46)-SUM(Monthly!$C$36:$BJ$36)-SUM(Monthly!$C$45:$BJ$45))<0.5,"PASS","FAIL") -> PASS | C6: EBITDA = gross profit + operating expenses (costs are negative)
A7: Cash roll-forward | B7: =IF(ABS(INDEX(Monthly!$C$91:$BJ$91,60)-SUM(Monthly!$C$89:$BJ$89))<0.5,"PASS","FAIL") -> PASS | C7: Closing cash = all net cash flows since the start (opening cash is zero)
A8: Scenario selector valid | B8: =IF(AND(ISNUMBER(Dashboard!B4),Dashboard!B4>=1,Dashboard!B4<=3,INT(Dashboard!B4)=Dashboard!B4),"PASS","FAIL") -> PASS | C8: Dashboard!B4 is 1, 2 or 3
A9: Scenario ordering of drivers | B9: =IF(AND(Inputs!$B$7<=Inputs!$C$7,Inputs!$C$7<=Inputs!$D$7,Inputs!$B$8<=Inputs!$C$8,Inputs!$C$8<=Inputs!$D$8,Inputs!$B$9<=Inputs!$C$9,Inputs!$C$9<=Inputs!$D$9,Inputs!$B$11>=Inputs!$C$11,Inputs!$C$11>=Inputs!$D$11,Inputs!$B$12<=Inputs!$C$12,Inputs!$C$12<=Inputs!$D$12,Inputs!$B$16<=Inputs!$C$16,Inputs!$C$16<=Inputs!$D$16,Inputs!$B$18<=Inputs!$C$18,Inputs!$C$18<=Inputs!$D$18,Inputs!$B$21<=Inputs!$C$21,Inputs!$C$21<=Inputs!$D$21,Inputs!$B$22<=Inputs!$C$22,Inputs!$C$22<=Inputs!$D$22,Inputs!$B$23<=Inputs!$C$23,Inputs!$C$23<=Inputs!$D$23,Inputs!$B$26<=Inputs!$C$26,Inputs!$C$26<=Inputs!$D$26,Inputs!$B$27<=Inputs!$C$27,Inputs!$C$27<=Inputs!$D$27,Inputs!$B$30>=Inputs!$C$30,Inputs!$C$30>=Inputs!$D$30,Inputs!$B$31>=Inputs!$C$31,Inputs!$C$31>=Inputs!$D$31,Inputs!$B$32>=Inputs!$C$32,Inputs!$C$32>=Inputs!$D$32,Inputs!$B$33>=Inputs!$C$33,Inputs!$C$33>=Inputs!$D$33,Inputs!$B$41<=Inputs!$C$41,Inputs!$C$41<=Inputs!$D$41,Inputs!$B$51<=Inputs!$C$51,Inputs!$C$51<=Inputs!$D$51,Inputs!$B$53<=Inputs!$C$53,Inputs!$C$53<=Inputs!$D$53,Inputs!$B$55<=Inputs!$C$55,Inputs!$C$55<=Inputs!$D$55,Inputs!$B$57<=Inputs!$C$57,Inputs!$C$57<=Inputs!$D$57,Inputs!$B$59<=Inputs!$C$59,Inputs!$C$59<=Inputs!$D$59,Inputs!$B$61<=Inputs!$C$61,Inputs!$C$61<=Inputs!$D$61,Inputs!$B$85>=Inputs!$C$85,Inputs!$C$85>=Inputs!$D$85,Inputs!$B$86<=Inputs!$C$86,Inputs!$C$86<=Inputs!$D$86,Inputs!$B$87<=Inputs!$C$87,Inputs!$C$87<=Inputs!$D$87),"PASS","FAIL") -> PASS | C9: Low / Base / High ordered the right way for every growth and cost driver
A10: Gross margin within 0–100% | B10: =IF(AND(MIN('P&L'!$B$8:$F$8)>=0,MAX('P&L'!$B$8:$F$8)<=1),"PASS","FAIL") -> PASS | C10: Gross margin never negative or above 100%
A11: Loan balance never negative | B11: =IF(MIN(Monthly!$C$74:$BJ$74)>=-0.5,"PASS","FAIL") -> PASS | C11: Repayments never exceed the loan
A12: Funding table ties to the cash flow | B12: =IF(ABS('Break-even'!B18-('Break-even'!B16-'Break-even'!B10))<0.5,"PASS","FAIL") -> PASS | C12: Lowest cash balance = sources of funds − uses of funds up to that point
A13: Valuation: discounting ties to NPV() | B13: =IF(ABS(Valuation!B23-NPV(Valuation!B6,Valuation!$B$17:$F$17))<0.5,"PASS","FAIL") -> PASS | C13: Sum of discounted free cash flows equals Excel's NPV of the same flows
A14: Valuation: WACC above terminal growth | B14: =IF(Valuation!B6>Valuation!B7,"PASS","FAIL") -> PASS | C14: The perpetual-growth formula needs WACC > g
A15: Valuation: sensitivity centre = enterprise value | B15: =IF(ABS(Valuation!D36-Valuation!B27)<0.5,"PASS","FAIL") -> PASS | C15: The middle of the WACC × growth table reproduces the headline value
A16: Valuation: final-year cash flow positive | B16: =IF(Valuation!$F$17>0,"PASS","WARN") -> PASS | C16: Business warning: a negative final-year cash flow gives a negative terminal value (often a 1-year plan still carrying start-up spending)
A17: Sources & uses balance | B17: =IF(ABS('Sources & Uses'!B21-'Sources & Uses'!B28)<0.5,"PASS","FAIL") -> PASS | C17: Sources of funds = uses of funds (incl. cash at the end) for the Sources & Uses period
A18: No error values | B18: =IF(SUMPRODUCT(--ISERROR(Monthly!$C$4:$BJ$109))+SUMPRODUCT(--ISERROR(Headcount!$C$4:$BJ$17))+SUMPRODUCT(--ISERROR('P&L'!$B$3:$F$24))+SUMPRODUCT(--ISERROR('Cash Flow'!$B$3:$F$18))+SUMPRODUCT(--ISERROR('Balance Sheet'!$B$3:$F$17))+SUMPRODUCT(--ISERROR(KPIs!$B$27:$F$48))+SUMPRODUCT(--ISERROR('Break-even'!$B$26:$F$33))+SUMPRODUCT(--ISERROR(Valuation!$B$14:$F$19))+SUMPRODUCT(--ISERROR('Break-even'!$B$3:$F$35))+SUMPRODUCT(--ISERROR(Valuation!$A$3:$F$40))+SUMPRODUCT(--ISERROR('Sources & Uses'!$B$3:$C$30))+SUMPRODUCT(--ISERROR(Dashboard!$A$6:$W$44))+SUMPRODUCT(--ISERROR(Summary!$A$5:$S$52))+SUMPRODUCT(--ISERROR(KPIs!$A$4:$G$48))+SUMPRODUCT(--ISERROR('Scenario calc'!$C$6:$BJ$123))+SUMPRODUCT(--ISERROR('Scenario calc'!$C$128:$BJ$245))+SUMPRODUCT(--ISERROR('Scenario calc'!$C$250:$BJ$367))+SUMPRODUCT(--ISERROR(Scenarios!$B$5:$F$50))=0,"PASS","FAIL") -> PASS | C18: No error values (divide-by-zero, broken references) on any calculation sheet
A19: Summary ties to statements | B19: =IF(IFERROR(AND(SUMPRODUCT(--(ABS(Summary!$B$7:$F$7-'P&L'!$B$5:$F$5)>0.5))=0,SUMPRODUCT(--(ABS(Summary!$B$19:$F$19-'P&L'!$B$23:$F$23)>0.5))=0,SUMPRODUCT(--(ABS(Summary!$B$31:$F$31-'Cash Flow'!$B$18:$F$18)>0.5))=0,SUMPRODUCT(--(ABS(Summary!$B$41:$F$41-'Balance Sheet'!$B$5:$F$5)>0.5))=0,ABS(SUM(Summary!$H$7:$S$7)-INDEX(Summary!$B$7:$F$7,Summary!$R$2))<0.5,ABS(SUM(Summary!$H$19:$S$19)-INDEX(Summary!$B$19:$F$19,Summary!$R$2))<0.5,ABS(Summary!$S$31-INDEX(Summary!$B$31:$F$31,Summary!$R$2))<0.5),FALSE()),"PASS","FAIL") -> PASS | C19: Summary revenue, net income and closing cash equal the statements every year; the detailed year adds up to its annual figure
A20: DuPont ties to return on equity | B20: =IF(SUMPRODUCT(--(ABS(KPIs!$B$24:$F$24)>0.000000001))>0,"FAIL",IF(SUMPRODUCT(ISNUMBER(KPIs!$B$23:$F$23)*ISNUMBER(KPIs!$B$16:$F$16))=0,"n/a","PASS")) -> PASS | C20: Net margin × asset turnover × equity multiplier equals return on equity every year; n/a = no year where both are defined (a one-sided n/a is a FAIL)
A21: Scenarios: Active = selected scenario | B21: =IF(IFERROR(AND(ABS(Scenarios!E17-INDEX(Scenarios!B17:D17,1,Dashboard!$B$4))<0.5,ABS(Scenarios!E18-INDEX(Scenarios!B18:D18,1,Dashboard!$B$4))<0.5,ABS(Scenarios!E19-INDEX(Scenarios!B19:D19,1,Dashboard!$B$4))<0.5,ABS(Scenarios!E20-INDEX(Scenarios!B20:D20,1,Dashboard!$B$4))<0.000001,ABS(Scenarios!E21-INDEX(Scenarios!B21:D21,1,Dashboard!$B$4))<0.5,ABS(Scenarios!E22-INDEX(Scenarios!B22:D22,1,Dashboard!$B$4))<0.5,ABS(Scenarios!E23-INDEX(Scenarios!B23:D23,1,Dashboard!$B$4))<0.5,ABS(Scenarios!E24-INDEX(Scenarios!B24:D24,1,Dashboard!$B$4))<0.5,ABS(Scenarios!E25-INDEX(Scenarios!B25:D25,1,Dashboard!$B$4))<0.5,ABS(Scenarios!E26-INDEX(Scenarios!B26:D26,1,Dashboard!$B$4))<0.5),FALSE()),"PASS","FAIL") -> PASS | C21: On the Scenarios sheet the live model (Active) equals the Low / Base / High column chosen on the Dashboard for every output
A22: Balance sheet balances every period | B22: =IF(SUMPRODUCT(--(ABS(Monthly!$C$109:$BJ$109)>0.5))=0,"PASS","FAIL") -> PASS | C22: Assets = liabilities + equity in every period
A23: Funding sufficient (cash ≥ 0) | B23: =IF(MIN(Monthly!$C$91:$BJ$91)>=0,"PASS","WARN") -> PASS | C23: Business warning, not an error: cash dips below zero in this scenario
A25: Overall verdict | B25: =IF(COUNTIF(B4:B23,"FAIL")>0,"FAIL",IF(COUNTIF(B4:B23,"WARN")>0,"PASS WITH WARNINGS","PASS")) -> PASS
