Workbook

Sheet Cover
B2: Bakery financial model (growing)
B3: 3-year financial model · monthly detail · Low / Base / High scenarios · US dollars · Full plan
B5: Purpose | D5: Revenue and profit plan
B6: Active scenario | D6: =Dashboard!C4&" (change it on the Dashboard, cell B4)" -> Base (change it on the Dashboard, cell B4)
B7: Model checks | D7: =Checks!B24 -> PASS
B8: Prepared | D8: 21 October 2026
B10: Contents
C11: PRESENTATION
B12: 1 | C12: =HYPERLINK("#Dashboard!A1","Dashboard") -> Dashboard | D12: Scenario switch, key numbers, core financials
B13: 2 | C13: =HYPERLINK("#Summary!A1","Summary") -> Summary | D13: Income statement, cash flow and balance sheet — every year and any year by month
B14: 3 | C14: =HYPERLINK("#'Break-even'!A1","Break-even") -> Break-even | D14: Startup costs, funding need, break-even timing and revenue
B15: 4 | C15: =HYPERLINK("#Valuation!A1","Valuation") -> Valuation | D15: Free cash flow, DCF (perpetual growth and exit multiple), WACC × growth sensitivity
B16: 5 | C16: =HYPERLINK("#'Sources & Uses'!A1","Sources & Uses") -> Sources & Uses | D16: Funding structure, sources and uses of cash for the first months
B17: 6 | C17: =HYPERLINK("#KPIs!A1","KPIs") -> KPIs | D17: Financial ratios, DuPont analysis, industry metrics
C18: INPUTS
B19: 7 | C19: =HYPERLINK("#Inputs!A1","Inputs") -> Inputs | D19: Every assumption, Low / Base / High, with units and comments
C20: STATEMENTS
B21: 8 | C21: =HYPERLINK("#'P&L'!A1","P&L") -> P&L | D21: Annual profit & loss
B22: 9 | C22: =HYPERLINK("#'Cash Flow'!A1","Cash Flow") -> Cash Flow | D22: Annual cash flow statement
B23: 10 | C23: =HYPERLINK("#'Balance Sheet'!A1","Balance Sheet") -> Balance Sheet | D23: Balance sheet at year end
C24: CALCULATIONS
B25: 11 | C25: =HYPERLINK("#Monthly!A1","Monthly") -> Monthly | D25: Month-by-month engine of the model
B26: 12 | C26: =HYPERLINK("#Headcount!A1","Headcount") -> Headcount | D26: Team and payroll
C27: CONTROL
B28: 13 | C28: =HYPERLINK("#Checks!A1","Checks") -> Checks | D28: Live integrity checks and the overall verdict
B30: How to read this file
C31: 1000 | D31: Input you can change — yellow cell with a blue figure (Inputs sheet and the view switches)
C32: 1000 | D32: Formula — calculated, do not overwrite
C33: 1000 | D33: Link to another sheet
C34: 1000 | D34: Active value the model uses (follows the scenario)

Sheet Dashboard
A1: Dashboard | W1: =HYPERLINK("#'Cover'!A1","◂ Contents") -> ◂ Contents
A2: Bakery financial model (growing)
A4: Active scenario | B4: 2 | C4: =CHOOSE(B4,"Low","Base","High") -> Base | D4: 1 = Low · 2 = Base · 3 = High — every sheet follows this cell | S4: Model checks | T4: =Checks!B24 -> PASS
A6: REVENUE · YEAR 3 | C6: EBITDA MARGIN · YEAR 3 | H6: NET INCOME · YEAR 3 | L6: LOWEST CASH BALANCE | P6: FUNDING REQUIRED | T6: ENTERPRISE VALUE (DCF)
A7: =D12 -> 1890162.9 | C7: =D17 -> 0.12348307 | H7: =D18 -> 169019.96 | L7: =F39 -> 43218.391 | P7: =F37 -> 329781.61 | T7: =F44 -> 1043766.4
A8: =IF(AND(B12>0,D12>=0),(D12/B12)^(1/2)-1,"CAGR n/a") -> 0.094434492 | C8: =D16 -> 233403.12 | H8: =D19 -> 0.089420843 | L8: ='Break-even'!B6 -> 1 | P8: =IF(F38>=0,"Covered by funding raised",-F38) -> 189781.61 | T8: Average of 2 methods
A10: Core financials ($'000) — active scenario
B11: 1 | C11: 2 | D11: 3
A12: Revenue | B12: =SUMIF(Monthly!$C$5:$AL$5,B$11,Monthly!$C$22:$AL$22) -> 1578046.1 | C12: =SUMIF(Monthly!$C$5:$AL$5,C$11,Monthly!$C$22:$AL$22) -> 1736372.4 | D12: =SUMIF(Monthly!$C$5:$AL$5,D$11,Monthly!$C$22:$AL$22) -> 1890162.9
A13: Gross profit | B13: =SUMIF(Monthly!$C$5:$AL$5,B$11,Monthly!$C$29:$AL$29) -> 1077227.7 | C13: =SUMIF(Monthly!$C$5:$AL$5,C$11,Monthly!$C$29:$AL$29) -> 1183311.2 | D13: =SUMIF(Monthly!$C$5:$AL$5,D$11,Monthly!$C$29:$AL$29) -> 1285883.7
A14: Gross margin | B14: =IF(B12=0,0,B13/B12) -> 0.68263384 | C14: =IF(C12=0,0,C13/C12) -> 0.68148469 | D14: =IF(D12=0,0,D13/D12) -> 0.68030311
A15: Operating expenses | B15: =SUMIF(Monthly!$C$5:$AL$5,B$11,Monthly!$C$40:$AL$40) -> -931495.62 | C15: =SUMIF(Monthly!$C$5:$AL$5,C$11,Monthly!$C$40:$AL$40) -> -990021.96 | D15: =SUMIF(Monthly!$C$5:$AL$5,D$11,Monthly!$C$40:$AL$40) -> -1052480.5
A16: EBITDA | B16: =SUMIF(Monthly!$C$5:$AL$5,B$11,Monthly!$C$41:$AL$41) -> 145732.04 | C16: =SUMIF(Monthly!$C$5:$AL$5,C$11,Monthly!$C$41:$AL$41) -> 193289.21 | D16: =SUMIF(Monthly!$C$5:$AL$5,D$11,Monthly!$C$41:$AL$41) -> 233403.12
A17: EBITDA margin | B17: =IF(B12=0,0,B16/B12) -> 0.092349671 | C17: =IF(C12=0,0,C16/C12) -> 0.11131783 | D17: =IF(D12=0,0,D16/D12) -> 0.12348307
A18: Net income | B18: =SUMIF(Monthly!$C$5:$AL$5,B$11,Monthly!$C$50:$AL$50) -> 100050.56 | C18: =SUMIF(Monthly!$C$5:$AL$5,C$11,Monthly!$C$50:$AL$50) -> 137835.57 | D18: =SUMIF(Monthly!$C$5:$AL$5,D$11,Monthly!$C$50:$AL$50) -> 169019.96
A19: Net margin | B19: =IF(B12=0,0,B18/B12) -> 0.063401547 | C19: =IF(C12=0,0,C18/C12) -> 0.079381341 | D19: =IF(D12=0,0,D18/D12) -> 0.089420843
A20: Operating cash flow | B20: =SUMIF(Monthly!$C$5:$AL$5,B$11,Monthly!$C$74:$AL$74) -> 101363.96 | C20: =SUMIF(Monthly!$C$5:$AL$5,C$11,Monthly!$C$74:$AL$74) -> 150896.6 | D20: =SUMIF(Monthly!$C$5:$AL$5,D$11,Monthly!$C$74:$AL$74) -> 184000.33
A21: Investing cash flow | B21: =SUMIF(Monthly!$C$5:$AL$5,B$11,Monthly!$C$75:$AL$75) -> -90000 | C21: =SUMIF(Monthly!$C$5:$AL$5,C$11,Monthly!$C$75:$AL$75) -> -14000 | D21: =SUMIF(Monthly!$C$5:$AL$5,D$11,Monthly!$C$75:$AL$75) -> -14000
A22: Financing cash flow | B22: =SUMIF(Monthly!$C$5:$AL$5,B$11,Monthly!$C$77:$AL$77) -> 125333.33 | C22: =SUMIF(Monthly!$C$5:$AL$5,C$11,Monthly!$C$77:$AL$77) -> -16000 | D22: =SUMIF(Monthly!$C$5:$AL$5,D$11,Monthly!$C$77:$AL$77) -> -16000
A23: Net change in cash | B23: =SUMIF(Monthly!$C$5:$AL$5,B$11,Monthly!$C$78:$AL$78) -> 136697.29 | C23: =SUMIF(Monthly!$C$5:$AL$5,C$11,Monthly!$C$78:$AL$78) -> 120896.6 | D23: =SUMIF(Monthly!$C$5:$AL$5,D$11,Monthly!$C$78:$AL$78) -> 154000.33
A24: Year-end cash | B24: =INDEX(Monthly!$C$80:$AL$80,B$11*12) -> 136697.29 | C24: =INDEX(Monthly!$C$80:$AL$80,C$11*12) -> 257593.89 | D24: =INDEX(Monthly!$C$80:$AL$80,D$11*12) -> 411594.23
A26: Bakery metrics
B27: 1 | C27: 2 | D27: 3
A28: Retail counter revenue | B28: =KPIs!B35 -> 1134382.1 | C28: =KPIs!C35 -> 1218082.9 | D28: =KPIs!D35 -> 1292264.2
A29: Wholesale revenue | B29: =KPIs!B36 -> 443664 | C29: =KPIs!C36 -> 518289.41 | D29: =KPIs!D36 -> 597898.66
A30: Customers per day (average) | B30: =KPIs!B31 -> 316.16 | C30: =KPIs!C31 -> 329.6 | D30: =KPIs!D31 -> 339.488
A31: Wholesale accounts (year end) | B31: =KPIs!B33 -> 16 | C31: =KPIs!C33 -> 17.92 | D31: =KPIs!D33 -> 20.0704
A32: Team (FTE, year end) | B32: =INDEX(Headcount!$C$11:$AL$11,B$27*12) -> 13.5 | C32: =INDEX(Headcount!$C$11:$AL$11,C$27*12) -> 14.22 | D32: =INDEX(Headcount!$C$11:$AL$11,D$27*12) -> 14.9832
A34: Funding & valuation ($'000) — active scenario
A35: Equity raised | F35: =Inputs!$E$58 -> 60000
A36: Loan drawn | F36: =Inputs!$E$59 -> 80000
A37: Funding required (incl. cash buffer) | F37: ='Break-even'!B12 -> 329781.61
A38: Funding surplus / (shortfall) | F38: ='Break-even'!B17 -> -189781.61
A39: ="Lowest cash balance (month "&'Break-even'!B6&")" -> Lowest cash balance (month 1) | F39: ='Break-even'!B18 -> 43218.391
A40: First month with positive EBITDA | F40: ='Break-even'!B21 -> 1
A41: Cash invested paid back | F41: ='Break-even'!B23 -> 12
A42: Enterprise value — perpetual growth | F42: =Valuation!B27 -> 1035783.3
A43: Enterprise value — exit multiple | F43: =Valuation!C27 -> 1051749.5
A44: Enterprise value — average | F44: =Valuation!B30 -> 1043766.4

Sheet Summary
A1: Financial statements summary | U1: =HYPERLINK("#'Cover'!A1","◂ Contents") -> ◂ Contents
A2: Bakery financial model (growing) | P2: Select detailed year: | R2: 1
A5: Income statement ($'000) — by year | H5: ="Income statement ($'000) — Year "&$R$2&", by month" -> Income statement ($'000) — Year 1, by month
B6: 1 | C6: 2 | D6: 3 | H6: =INDEX(Monthly!$C$4:$AL$4,($R$2-1)*12+1) -> 1 | I6: =INDEX(Monthly!$C$4:$AL$4,($R$2-1)*12+2) -> 2 | J6: =INDEX(Monthly!$C$4:$AL$4,($R$2-1)*12+3) -> 3 | K6: =INDEX(Monthly!$C$4:$AL$4,($R$2-1)*12+4) -> 4 | L6: =INDEX(Monthly!$C$4:$AL$4,($R$2-1)*12+5) -> 5 | M6: =INDEX(Monthly!$C$4:$AL$4,($R$2-1)*12+6) -> 6 | N6: =INDEX(Monthly!$C$4:$AL$4,($R$2-1)*12+7) -> 7 | O6: =INDEX(Monthly!$C$4:$AL$4,($R$2-1)*12+8) -> 8 | P6: =INDEX(Monthly!$C$4:$AL$4,($R$2-1)*12+9) -> 9 | Q6: =INDEX(Monthly!$C$4:$AL$4,($R$2-1)*12+10) -> 10 | R6: =INDEX(Monthly!$C$4:$AL$4,($R$2-1)*12+11) -> 11 | S6: =INDEX(Monthly!$C$4:$AL$4,($R$2-1)*12+12) -> 12
A7: Revenue | B7: ='P&L'!B5 -> 1578046.1 | C7: ='P&L'!C5 -> 1736372.4 | D7: ='P&L'!D5 -> 1890162.9 | H7: =INDEX(Monthly!$C$22:$AL$22,($R$2-1)*12+1) -> 116363.52 | I7: =INDEX(Monthly!$C$22:$AL$22,($R$2-1)*12+2) -> 122828.16 | J7: =INDEX(Monthly!$C$22:$AL$22,($R$2-1)*12+3) -> 129292.8 | K7: =INDEX(Monthly!$C$22:$AL$22,($R$2-1)*12+4) -> 129292.8 | L7: =INDEX(Monthly!$C$22:$AL$22,($R$2-1)*12+5) -> 129292.8 | M7: =INDEX(Monthly!$C$22:$AL$22,($R$2-1)*12+6) -> 129292.8 | N7: =INDEX(Monthly!$C$22:$AL$22,($R$2-1)*12+7) -> 129292.8 | O7: =INDEX(Monthly!$C$22:$AL$22,($R$2-1)*12+8) -> 129292.8 | P7: =INDEX(Monthly!$C$22:$AL$22,($R$2-1)*12+9) -> 129292.8 | Q7: =INDEX(Monthly!$C$22:$AL$22,($R$2-1)*12+10) -> 129292.8 | R7: =INDEX(Monthly!$C$22:$AL$22,($R$2-1)*12+11) -> 152256 | S7: =INDEX(Monthly!$C$22:$AL$22,($R$2-1)*12+12) -> 152256
A8: Cost of sales | B8: ='P&L'!B6 -> -500818.42 | C8: ='P&L'!C6 -> -553061.18 | D8: ='P&L'!D6 -> -604279.19 | H8: =INDEX(Monthly!$C$28:$AL$28,($R$2-1)*12+1) -> -36994.826 | I8: =INDEX(Monthly!$C$28:$AL$28,($R$2-1)*12+2) -> -39050.094 | J8: =INDEX(Monthly!$C$28:$AL$28,($R$2-1)*12+3) -> -41105.362 | K8: =INDEX(Monthly!$C$28:$AL$28,($R$2-1)*12+4) -> -41105.362 | L8: =INDEX(Monthly!$C$28:$AL$28,($R$2-1)*12+5) -> -41105.362 | M8: =INDEX(Monthly!$C$28:$AL$28,($R$2-1)*12+6) -> -41105.362 | N8: =INDEX(Monthly!$C$28:$AL$28,($R$2-1)*12+7) -> -41105.362 | O8: =INDEX(Monthly!$C$28:$AL$28,($R$2-1)*12+8) -> -41105.362 | P8: =INDEX(Monthly!$C$28:$AL$28,($R$2-1)*12+9) -> -41105.362 | Q8: =INDEX(Monthly!$C$28:$AL$28,($R$2-1)*12+10) -> -41105.362 | R8: =INDEX(Monthly!$C$28:$AL$28,($R$2-1)*12+11) -> -47965.303 | S8: =INDEX(Monthly!$C$28:$AL$28,($R$2-1)*12+12) -> -47965.303
A9: Gross profit | B9: ='P&L'!B7 -> 1077227.7 | C9: ='P&L'!C7 -> 1183311.2 | D9: ='P&L'!D7 -> 1285883.7 | H9: =INDEX(Monthly!$C$29:$AL$29,($R$2-1)*12+1) -> 79368.694 | I9: =INDEX(Monthly!$C$29:$AL$29,($R$2-1)*12+2) -> 83778.066 | J9: =INDEX(Monthly!$C$29:$AL$29,($R$2-1)*12+3) -> 88187.438 | K9: =INDEX(Monthly!$C$29:$AL$29,($R$2-1)*12+4) -> 88187.438 | L9: =INDEX(Monthly!$C$29:$AL$29,($R$2-1)*12+5) -> 88187.438 | M9: =INDEX(Monthly!$C$29:$AL$29,($R$2-1)*12+6) -> 88187.438 | N9: =INDEX(Monthly!$C$29:$AL$29,($R$2-1)*12+7) -> 88187.438 | O9: =INDEX(Monthly!$C$29:$AL$29,($R$2-1)*12+8) -> 88187.438 | P9: =INDEX(Monthly!$C$29:$AL$29,($R$2-1)*12+9) -> 88187.438 | Q9: =INDEX(Monthly!$C$29:$AL$29,($R$2-1)*12+10) -> 88187.438 | R9: =INDEX(Monthly!$C$29:$AL$29,($R$2-1)*12+11) -> 104290.7 | S9: =INDEX(Monthly!$C$29:$AL$29,($R$2-1)*12+12) -> 104290.7
A10: Gross margin | B10: ='P&L'!B8 -> 0.68263384 | C10: ='P&L'!C8 -> 0.68148469 | D10: ='P&L'!D8 -> 0.68030311 | H10: =IF(H7=0,0,H9/H7) -> 0.6820754 | I10: =IF(I7=0,0,I9/I7) -> 0.6820754 | J10: =IF(J7=0,0,J9/J7) -> 0.6820754 | K10: =IF(K7=0,0,K9/K7) -> 0.6820754 | L10: =IF(L7=0,0,L9/L7) -> 0.6820754 | M10: =IF(M7=0,0,M9/M7) -> 0.6820754 | N10: =IF(N7=0,0,N9/N7) -> 0.6820754 | O10: =IF(O7=0,0,O9/O7) -> 0.6820754 | ... S10: =IF(S7=0,0,S9/S7) -> 0.68496937
A11: Total operating expenses | B11: ='P&L'!B17 -> -931495.62 | C11: ='P&L'!C17 -> -990021.96 | D11: ='P&L'!D17 -> -1052480.5 | H11: =INDEX(Monthly!$C$40:$AL$40,($R$2-1)*12+1) -> -76716.628 | I11: =INDEX(Monthly!$C$40:$AL$40,($R$2-1)*12+2) -> -77130.514 | J11: =INDEX(Monthly!$C$40:$AL$40,($R$2-1)*12+3) -> -77544.401 | K11: =INDEX(Monthly!$C$40:$AL$40,($R$2-1)*12+4) -> -77544.401 | L11: =INDEX(Monthly!$C$40:$AL$40,($R$2-1)*12+5) -> -77544.401 | M11: =INDEX(Monthly!$C$40:$AL$40,($R$2-1)*12+6) -> -77544.401 | N11: =INDEX(Monthly!$C$40:$AL$40,($R$2-1)*12+7) -> -77544.401 | O11: =INDEX(Monthly!$C$40:$AL$40,($R$2-1)*12+8) -> -77544.401 | P11: =INDEX(Monthly!$C$40:$AL$40,($R$2-1)*12+9) -> -77544.401 | Q11: =INDEX(Monthly!$C$40:$AL$40,($R$2-1)*12+10) -> -77544.401 | R11: =INDEX(Monthly!$C$40:$AL$40,($R$2-1)*12+11) -> -78646.635 | S11: =INDEX(Monthly!$C$40:$AL$40,($R$2-1)*12+12) -> -78646.635
A12: EBITDA | B12: ='P&L'!B18 -> 145732.04 | C12: ='P&L'!C18 -> 193289.21 | D12: ='P&L'!D18 -> 233403.12 | H12: =INDEX(Monthly!$C$41:$AL$41,($R$2-1)*12+1) -> 2652.0663 | I12: =INDEX(Monthly!$C$41:$AL$41,($R$2-1)*12+2) -> 6647.5515 | J12: =INDEX(Monthly!$C$41:$AL$41,($R$2-1)*12+3) -> 10643.037 | K12: =INDEX(Monthly!$C$41:$AL$41,($R$2-1)*12+4) -> 10643.037 | L12: =INDEX(Monthly!$C$41:$AL$41,($R$2-1)*12+5) -> 10643.037 | M12: =INDEX(Monthly!$C$41:$AL$41,($R$2-1)*12+6) -> 10643.037 | N12: =INDEX(Monthly!$C$41:$AL$41,($R$2-1)*12+7) -> 10643.037 | O12: =INDEX(Monthly!$C$41:$AL$41,($R$2-1)*12+8) -> 10643.037 | P12: =INDEX(Monthly!$C$41:$AL$41,($R$2-1)*12+9) -> 10643.037 | Q12: =INDEX(Monthly!$C$41:$AL$41,($R$2-1)*12+10) -> 10643.037 | R12: =INDEX(Monthly!$C$41:$AL$41,($R$2-1)*12+11) -> 25644.062 | S12: =INDEX(Monthly!$C$41:$AL$41,($R$2-1)*12+12) -> 25644.062
A13: EBITDA margin | B13: ='P&L'!B19 -> 0.092349671 | C13: ='P&L'!C19 -> 0.11131783 | D13: ='P&L'!D19 -> 0.12348307 | H13: =IF(H7=0,0,H12/H7) -> 0.022791218 | I13: =IF(I7=0,0,I12/I7) -> 0.054120745 | J13: =IF(J7=0,0,J12/J7) -> 0.082317319 | K13: =IF(K7=0,0,K12/K7) -> 0.082317319 | L13: =IF(L7=0,0,L12/L7) -> 0.082317319 | M13: =IF(M7=0,0,M12/M7) -> 0.082317319 | N13: =IF(N7=0,0,N12/N7) -> 0.082317319 | O13: =IF(O7=0,0,O12/O7) -> 0.082317319 | ... S13: =IF(S7=0,0,S12/S7) -> 0.16842727
A14: Depreciation | B14: ='P&L'!B20 -> -12857.143 | C14: ='P&L'!C20 -> -13940.476 | D14: ='P&L'!D20 -> -15940.476 | H14: =INDEX(Monthly!$C$55:$AL$55,($R$2-1)*12+1) -> -1071.4286 | I14: =INDEX(Monthly!$C$55:$AL$55,($R$2-1)*12+2) -> -1071.4286 | J14: =INDEX(Monthly!$C$55:$AL$55,($R$2-1)*12+3) -> -1071.4286 | K14: =INDEX(Monthly!$C$55:$AL$55,($R$2-1)*12+4) -> -1071.4286 | L14: =INDEX(Monthly!$C$55:$AL$55,($R$2-1)*12+5) -> -1071.4286 | M14: =INDEX(Monthly!$C$55:$AL$55,($R$2-1)*12+6) -> -1071.4286 | N14: =INDEX(Monthly!$C$55:$AL$55,($R$2-1)*12+7) -> -1071.4286 | O14: =INDEX(Monthly!$C$55:$AL$55,($R$2-1)*12+8) -> -1071.4286 | P14: =INDEX(Monthly!$C$55:$AL$55,($R$2-1)*12+9) -> -1071.4286 | Q14: =INDEX(Monthly!$C$55:$AL$55,($R$2-1)*12+10) -> -1071.4286 | R14: =INDEX(Monthly!$C$55:$AL$55,($R$2-1)*12+11) -> -1071.4286 | S14: =INDEX(Monthly!$C$55:$AL$55,($R$2-1)*12+12) -> -1071.4286
A15: EBIT | B15: ='P&L'!B21 -> 132874.89 | C15: ='P&L'!C21 -> 179348.73 | D15: ='P&L'!D21 -> 217462.64 | H15: =INDEX(Monthly!$C$44:$AL$44,($R$2-1)*12+1) -> 1580.6377 | I15: =INDEX(Monthly!$C$44:$AL$44,($R$2-1)*12+2) -> 5576.1229 | J15: =INDEX(Monthly!$C$44:$AL$44,($R$2-1)*12+3) -> 9571.6081 | K15: =INDEX(Monthly!$C$44:$AL$44,($R$2-1)*12+4) -> 9571.6081 | L15: =INDEX(Monthly!$C$44:$AL$44,($R$2-1)*12+5) -> 9571.6081 | M15: =INDEX(Monthly!$C$44:$AL$44,($R$2-1)*12+6) -> 9571.6081 | N15: =INDEX(Monthly!$C$44:$AL$44,($R$2-1)*12+7) -> 9571.6081 | O15: =INDEX(Monthly!$C$44:$AL$44,($R$2-1)*12+8) -> 9571.6081 | P15: =INDEX(Monthly!$C$44:$AL$44,($R$2-1)*12+9) -> 9571.6081 | Q15: =INDEX(Monthly!$C$44:$AL$44,($R$2-1)*12+10) -> 9571.6081 | R15: =INDEX(Monthly!$C$44:$AL$44,($R$2-1)*12+11) -> 24572.634 | S15: =INDEX(Monthly!$C$44:$AL$44,($R$2-1)*12+12) -> 24572.634
A16: Interest | B16: ='P&L'!B22 -> -6228.6111 | C16: ='P&L'!C22 -> -4873.3333 | D16: ='P&L'!D22 -> -3513.3333 | H16: =INDEX(Monthly!$C$45:$AL$45,($R$2-1)*12+1) -> -566.66667 | I16: =INDEX(Monthly!$C$45:$AL$45,($R$2-1)*12+2) -> -561.94444 | J16: =INDEX(Monthly!$C$45:$AL$45,($R$2-1)*12+3) -> -552.5 | K16: =INDEX(Monthly!$C$45:$AL$45,($R$2-1)*12+4) -> -543.05556 | L16: =INDEX(Monthly!$C$45:$AL$45,($R$2-1)*12+5) -> -533.61111 | M16: =INDEX(Monthly!$C$45:$AL$45,($R$2-1)*12+6) -> -524.16667 | N16: =INDEX(Monthly!$C$45:$AL$45,($R$2-1)*12+7) -> -514.72222 | O16: =INDEX(Monthly!$C$45:$AL$45,($R$2-1)*12+8) -> -505.27778 | P16: =INDEX(Monthly!$C$45:$AL$45,($R$2-1)*12+9) -> -495.83333 | Q16: =INDEX(Monthly!$C$45:$AL$45,($R$2-1)*12+10) -> -486.38889 | R16: =INDEX(Monthly!$C$45:$AL$45,($R$2-1)*12+11) -> -476.94444 | S16: =INDEX(Monthly!$C$45:$AL$45,($R$2-1)*12+12) -> -467.5
A17: Pre-tax income | B17: ='P&L'!B23 -> 126646.28 | C17: ='P&L'!C23 -> 174475.4 | D17: ='P&L'!D23 -> 213949.31 | H17: =INDEX(Monthly!$C$46:$AL$46,($R$2-1)*12+1) -> 1013.9711 | I17: =INDEX(Monthly!$C$46:$AL$46,($R$2-1)*12+2) -> 5014.1785 | J17: =INDEX(Monthly!$C$46:$AL$46,($R$2-1)*12+3) -> 9019.1081 | K17: =INDEX(Monthly!$C$46:$AL$46,($R$2-1)*12+4) -> 9028.5525 | L17: =INDEX(Monthly!$C$46:$AL$46,($R$2-1)*12+5) -> 9037.997 | M17: =INDEX(Monthly!$C$46:$AL$46,($R$2-1)*12+6) -> 9047.4414 | N17: =INDEX(Monthly!$C$46:$AL$46,($R$2-1)*12+7) -> 9056.8859 | O17: =INDEX(Monthly!$C$46:$AL$46,($R$2-1)*12+8) -> 9066.3303 | P17: =INDEX(Monthly!$C$46:$AL$46,($R$2-1)*12+9) -> 9075.7747 | Q17: =INDEX(Monthly!$C$46:$AL$46,($R$2-1)*12+10) -> 9085.2192 | R17: =INDEX(Monthly!$C$46:$AL$46,($R$2-1)*12+11) -> 24095.689 | S17: =INDEX(Monthly!$C$46:$AL$46,($R$2-1)*12+12) -> 24105.134
A18: Income tax | B18: ='P&L'!B24 -> -26595.719 | C18: ='P&L'!C24 -> -36639.834 | D18: ='P&L'!D24 -> -44929.355 | H18: =INDEX(Monthly!$C$49:$AL$49,($R$2-1)*12+1) -> -212.93393 | I18: =INDEX(Monthly!$C$49:$AL$49,($R$2-1)*12+2) -> -1052.9775 | J18: =INDEX(Monthly!$C$49:$AL$49,($R$2-1)*12+3) -> -1894.0127 | K18: =INDEX(Monthly!$C$49:$AL$49,($R$2-1)*12+4) -> -1895.996 | L18: =INDEX(Monthly!$C$49:$AL$49,($R$2-1)*12+5) -> -1897.9794 | M18: =INDEX(Monthly!$C$49:$AL$49,($R$2-1)*12+6) -> -1899.9627 | N18: =INDEX(Monthly!$C$49:$AL$49,($R$2-1)*12+7) -> -1901.946 | O18: =INDEX(Monthly!$C$49:$AL$49,($R$2-1)*12+8) -> -1903.9294 | P18: =INDEX(Monthly!$C$49:$AL$49,($R$2-1)*12+9) -> -1905.9127 | Q18: =INDEX(Monthly!$C$49:$AL$49,($R$2-1)*12+10) -> -1907.896 | R18: =INDEX(Monthly!$C$49:$AL$49,($R$2-1)*12+11) -> -5060.0948 | S18: =INDEX(Monthly!$C$49:$AL$49,($R$2-1)*12+12) -> -5062.0781
A19: Net income | B19: ='P&L'!B25 -> 100050.56 | C19: ='P&L'!C25 -> 137835.57 | D19: ='P&L'!D25 -> 169019.96 | H19: =INDEX(Monthly!$C$50:$AL$50,($R$2-1)*12+1) -> 801.03715 | I19: =INDEX(Monthly!$C$50:$AL$50,($R$2-1)*12+2) -> 3961.201 | J19: =INDEX(Monthly!$C$50:$AL$50,($R$2-1)*12+3) -> 7125.0954 | K19: =INDEX(Monthly!$C$50:$AL$50,($R$2-1)*12+4) -> 7132.5565 | L19: =INDEX(Monthly!$C$50:$AL$50,($R$2-1)*12+5) -> 7140.0176 | M19: =INDEX(Monthly!$C$50:$AL$50,($R$2-1)*12+6) -> 7147.4787 | N19: =INDEX(Monthly!$C$50:$AL$50,($R$2-1)*12+7) -> 7154.9398 | O19: =INDEX(Monthly!$C$50:$AL$50,($R$2-1)*12+8) -> 7162.4009 | P19: =INDEX(Monthly!$C$50:$AL$50,($R$2-1)*12+9) -> 7169.862 | Q19: =INDEX(Monthly!$C$50:$AL$50,($R$2-1)*12+10) -> 7177.3232 | R19: =INDEX(Monthly!$C$50:$AL$50,($R$2-1)*12+11) -> 19035.595 | S19: =INDEX(Monthly!$C$50:$AL$50,($R$2-1)*12+12) -> 19043.056
A20: Net margin | B20: ='P&L'!B26 -> 0.063401547 | C20: ='P&L'!C26 -> 0.079381341 | D20: ='P&L'!D26 -> 0.089420843 | H20: =IF(H7=0,0,H19/H7) -> 0.0068839199 | I20: =IF(I7=0,0,I19/I7) -> 0.032249942 | J20: =IF(J7=0,0,J19/J7) -> 0.055108215 | K20: =IF(K7=0,0,K19/K7) -> 0.055165922 | L20: =IF(L7=0,0,L19/L7) -> 0.055223629 | M20: =IF(M7=0,0,M19/M7) -> 0.055281336 | N20: =IF(N7=0,0,N19/N7) -> 0.055339043 | O20: =IF(O7=0,0,O19/O7) -> 0.05539675 | ... S20: =IF(S7=0,0,S19/S7) -> 0.12507261
A22: Cash flow ($'000) — by year | H22: ="Cash flow ($'000) — Year "&$R$2&", by month" -> Cash flow ($'000) — Year 1, by month
B23: 1 | C23: 2 | D23: 3 | H23: =INDEX(Monthly!$C$4:$AL$4,($R$2-1)*12+1) -> 1 | I23: =INDEX(Monthly!$C$4:$AL$4,($R$2-1)*12+2) -> 2 | J23: =INDEX(Monthly!$C$4:$AL$4,($R$2-1)*12+3) -> 3 | K23: =INDEX(Monthly!$C$4:$AL$4,($R$2-1)*12+4) -> 4 | L23: =INDEX(Monthly!$C$4:$AL$4,($R$2-1)*12+5) -> 5 | M23: =INDEX(Monthly!$C$4:$AL$4,($R$2-1)*12+6) -> 6 | N23: =INDEX(Monthly!$C$4:$AL$4,($R$2-1)*12+7) -> 7 | O23: =INDEX(Monthly!$C$4:$AL$4,($R$2-1)*12+8) -> 8 | P23: =INDEX(Monthly!$C$4:$AL$4,($R$2-1)*12+9) -> 9 | Q23: =INDEX(Monthly!$C$4:$AL$4,($R$2-1)*12+10) -> 10 | R23: =INDEX(Monthly!$C$4:$AL$4,($R$2-1)*12+11) -> 11 | S23: =INDEX(Monthly!$C$4:$AL$4,($R$2-1)*12+12) -> 12
A24: Operating cash flow | B24: ='Cash Flow'!B10 -> 101363.96 | C24: ='Cash Flow'!C10 -> 150896.6 | D24: ='Cash Flow'!D10 -> 184000.33 | H24: =INDEX(Monthly!$C$74:$AL$74,($R$2-1)*12+1) -> -6781.6092 | I24: =INDEX(Monthly!$C$74:$AL$74,($R$2-1)*12+2) -> 4551.8476 | J24: =INDEX(Monthly!$C$74:$AL$74,($R$2-1)*12+3) -> 7715.742 | K24: =INDEX(Monthly!$C$74:$AL$74,($R$2-1)*12+4) -> 8203.9851 | L24: =INDEX(Monthly!$C$74:$AL$74,($R$2-1)*12+5) -> 8211.4462 | M24: =INDEX(Monthly!$C$74:$AL$74,($R$2-1)*12+6) -> 8218.9073 | N24: =INDEX(Monthly!$C$74:$AL$74,($R$2-1)*12+7) -> 8226.3684 | O24: =INDEX(Monthly!$C$74:$AL$74,($R$2-1)*12+8) -> 8233.8295 | P24: =INDEX(Monthly!$C$74:$AL$74,($R$2-1)*12+9) -> 8241.2906 | Q24: =INDEX(Monthly!$C$74:$AL$74,($R$2-1)*12+10) -> 8248.7517 | R24: =INDEX(Monthly!$C$74:$AL$74,($R$2-1)*12+11) -> 18178.914 | S24: =INDEX(Monthly!$C$74:$AL$74,($R$2-1)*12+12) -> 20114.484
A25: Capital spending | B25: ='Cash Flow'!B11 -> -90000 | C25: ='Cash Flow'!C11 -> -14000 | D25: ='Cash Flow'!D11 -> -14000 | H25: =INDEX(Monthly!$C$75:$AL$75,($R$2-1)*12+1) -> -90000 | I25: =INDEX(Monthly!$C$75:$AL$75,($R$2-1)*12+2) -> 0 | J25: =INDEX(Monthly!$C$75:$AL$75,($R$2-1)*12+3) -> 0 | K25: =INDEX(Monthly!$C$75:$AL$75,($R$2-1)*12+4) -> 0 | L25: =INDEX(Monthly!$C$75:$AL$75,($R$2-1)*12+5) -> 0 | M25: =INDEX(Monthly!$C$75:$AL$75,($R$2-1)*12+6) -> 0 | N25: =INDEX(Monthly!$C$75:$AL$75,($R$2-1)*12+7) -> 0 | O25: =INDEX(Monthly!$C$75:$AL$75,($R$2-1)*12+8) -> 0 | P25: =INDEX(Monthly!$C$75:$AL$75,($R$2-1)*12+9) -> 0 | Q25: =INDEX(Monthly!$C$75:$AL$75,($R$2-1)*12+10) -> 0 | R25: =INDEX(Monthly!$C$75:$AL$75,($R$2-1)*12+11) -> 0 | S25: =INDEX(Monthly!$C$75:$AL$75,($R$2-1)*12+12) -> 0
A26: Equity raised | B26: ='Cash Flow'!B12 -> 60000 | C26: ='Cash Flow'!C12 -> 0 | D26: ='Cash Flow'!D12 -> 0 | H26: =INDEX(Monthly!$C$76:$AL$76,($R$2-1)*12+1) -> 60000 | I26: =INDEX(Monthly!$C$76:$AL$76,($R$2-1)*12+2) -> 0 | J26: =INDEX(Monthly!$C$76:$AL$76,($R$2-1)*12+3) -> 0 | K26: =INDEX(Monthly!$C$76:$AL$76,($R$2-1)*12+4) -> 0 | L26: =INDEX(Monthly!$C$76:$AL$76,($R$2-1)*12+5) -> 0 | M26: =INDEX(Monthly!$C$76:$AL$76,($R$2-1)*12+6) -> 0 | N26: =INDEX(Monthly!$C$76:$AL$76,($R$2-1)*12+7) -> 0 | O26: =INDEX(Monthly!$C$76:$AL$76,($R$2-1)*12+8) -> 0 | P26: =INDEX(Monthly!$C$76:$AL$76,($R$2-1)*12+9) -> 0 | Q26: =INDEX(Monthly!$C$76:$AL$76,($R$2-1)*12+10) -> 0 | R26: =INDEX(Monthly!$C$76:$AL$76,($R$2-1)*12+11) -> 0 | S26: =INDEX(Monthly!$C$76:$AL$76,($R$2-1)*12+12) -> 0
A27: Loan drawdown | B27: ='Cash Flow'!B13 -> 80000 | C27: ='Cash Flow'!C13 -> 0 | D27: ='Cash Flow'!D13 -> 0 | H27: =INDEX(Monthly!$C$61:$AL$61,($R$2-1)*12+1) -> 80000 | I27: =INDEX(Monthly!$C$61:$AL$61,($R$2-1)*12+2) -> 0 | J27: =INDEX(Monthly!$C$61:$AL$61,($R$2-1)*12+3) -> 0 | K27: =INDEX(Monthly!$C$61:$AL$61,($R$2-1)*12+4) -> 0 | L27: =INDEX(Monthly!$C$61:$AL$61,($R$2-1)*12+5) -> 0 | M27: =INDEX(Monthly!$C$61:$AL$61,($R$2-1)*12+6) -> 0 | N27: =INDEX(Monthly!$C$61:$AL$61,($R$2-1)*12+7) -> 0 | O27: =INDEX(Monthly!$C$61:$AL$61,($R$2-1)*12+8) -> 0 | P27: =INDEX(Monthly!$C$61:$AL$61,($R$2-1)*12+9) -> 0 | Q27: =INDEX(Monthly!$C$61:$AL$61,($R$2-1)*12+10) -> 0 | R27: =INDEX(Monthly!$C$61:$AL$61,($R$2-1)*12+11) -> 0 | S27: =INDEX(Monthly!$C$61:$AL$61,($R$2-1)*12+12) -> 0
A28: Loan repayment | B28: ='Cash Flow'!B14 -> -14666.667 | C28: ='Cash Flow'!C14 -> -16000 | D28: ='Cash Flow'!D14 -> -16000 | H28: =INDEX(Monthly!$C$62:$AL$62,($R$2-1)*12+1) -> 0 | I28: =INDEX(Monthly!$C$62:$AL$62,($R$2-1)*12+2) -> -1333.3333 | J28: =INDEX(Monthly!$C$62:$AL$62,($R$2-1)*12+3) -> -1333.3333 | K28: =INDEX(Monthly!$C$62:$AL$62,($R$2-1)*12+4) -> -1333.3333 | L28: =INDEX(Monthly!$C$62:$AL$62,($R$2-1)*12+5) -> -1333.3333 | M28: =INDEX(Monthly!$C$62:$AL$62,($R$2-1)*12+6) -> -1333.3333 | N28: =INDEX(Monthly!$C$62:$AL$62,($R$2-1)*12+7) -> -1333.3333 | O28: =INDEX(Monthly!$C$62:$AL$62,($R$2-1)*12+8) -> -1333.3333 | P28: =INDEX(Monthly!$C$62:$AL$62,($R$2-1)*12+9) -> -1333.3333 | Q28: =INDEX(Monthly!$C$62:$AL$62,($R$2-1)*12+10) -> -1333.3333 | R28: =INDEX(Monthly!$C$62:$AL$62,($R$2-1)*12+11) -> -1333.3333 | S28: =INDEX(Monthly!$C$62:$AL$62,($R$2-1)*12+12) -> -1333.3333
A29: Financing cash flow | B29: ='Cash Flow'!B15 -> 125333.33 | C29: ='Cash Flow'!C15 -> -16000 | D29: ='Cash Flow'!D15 -> -16000 | H29: =INDEX(Monthly!$C$77:$AL$77,($R$2-1)*12+1) -> 140000 | I29: =INDEX(Monthly!$C$77:$AL$77,($R$2-1)*12+2) -> -1333.3333 | J29: =INDEX(Monthly!$C$77:$AL$77,($R$2-1)*12+3) -> -1333.3333 | K29: =INDEX(Monthly!$C$77:$AL$77,($R$2-1)*12+4) -> -1333.3333 | L29: =INDEX(Monthly!$C$77:$AL$77,($R$2-1)*12+5) -> -1333.3333 | M29: =INDEX(Monthly!$C$77:$AL$77,($R$2-1)*12+6) -> -1333.3333 | N29: =INDEX(Monthly!$C$77:$AL$77,($R$2-1)*12+7) -> -1333.3333 | O29: =INDEX(Monthly!$C$77:$AL$77,($R$2-1)*12+8) -> -1333.3333 | P29: =INDEX(Monthly!$C$77:$AL$77,($R$2-1)*12+9) -> -1333.3333 | Q29: =INDEX(Monthly!$C$77:$AL$77,($R$2-1)*12+10) -> -1333.3333 | R29: =INDEX(Monthly!$C$77:$AL$77,($R$2-1)*12+11) -> -1333.3333 | S29: =INDEX(Monthly!$C$77:$AL$77,($R$2-1)*12+12) -> -1333.3333
A30: Net change in cash | B30: ='Cash Flow'!B16 -> 136697.29 | C30: ='Cash Flow'!C16 -> 120896.6 | D30: ='Cash Flow'!D16 -> 154000.33 | H30: =INDEX(Monthly!$C$78:$AL$78,($R$2-1)*12+1) -> 43218.391 | I30: =INDEX(Monthly!$C$78:$AL$78,($R$2-1)*12+2) -> 3218.5143 | J30: =INDEX(Monthly!$C$78:$AL$78,($R$2-1)*12+3) -> 6382.4087 | K30: =INDEX(Monthly!$C$78:$AL$78,($R$2-1)*12+4) -> 6870.6517 | L30: =INDEX(Monthly!$C$78:$AL$78,($R$2-1)*12+5) -> 6878.1128 | M30: =INDEX(Monthly!$C$78:$AL$78,($R$2-1)*12+6) -> 6885.574 | N30: =INDEX(Monthly!$C$78:$AL$78,($R$2-1)*12+7) -> 6893.0351 | O30: =INDEX(Monthly!$C$78:$AL$78,($R$2-1)*12+8) -> 6900.4962 | P30: =INDEX(Monthly!$C$78:$AL$78,($R$2-1)*12+9) -> 6907.9573 | Q30: =INDEX(Monthly!$C$78:$AL$78,($R$2-1)*12+10) -> 6915.4184 | R30: =INDEX(Monthly!$C$78:$AL$78,($R$2-1)*12+11) -> 16845.58 | S30: =INDEX(Monthly!$C$78:$AL$78,($R$2-1)*12+12) -> 18781.151
A31: Closing cash | B31: ='Cash Flow'!B18 -> 136697.29 | C31: ='Cash Flow'!C18 -> 257593.89 | D31: ='Cash Flow'!D18 -> 411594.23 | H31: =INDEX(Monthly!$C$80:$AL$80,($R$2-1)*12+1) -> 43218.391 | I31: =INDEX(Monthly!$C$80:$AL$80,($R$2-1)*12+2) -> 46436.905 | J31: =INDEX(Monthly!$C$80:$AL$80,($R$2-1)*12+3) -> 52819.314 | K31: =INDEX(Monthly!$C$80:$AL$80,($R$2-1)*12+4) -> 59689.965 | L31: =INDEX(Monthly!$C$80:$AL$80,($R$2-1)*12+5) -> 66568.078 | M31: =INDEX(Monthly!$C$80:$AL$80,($R$2-1)*12+6) -> 73453.652 | N31: =INDEX(Monthly!$C$80:$AL$80,($R$2-1)*12+7) -> 80346.687 | O31: =INDEX(Monthly!$C$80:$AL$80,($R$2-1)*12+8) -> 87247.183 | P31: =INDEX(Monthly!$C$80:$AL$80,($R$2-1)*12+9) -> 94155.141 | Q31: =INDEX(Monthly!$C$80:$AL$80,($R$2-1)*12+10) -> 101070.56 | R31: =INDEX(Monthly!$C$80:$AL$80,($R$2-1)*12+11) -> 117916.14 | S31: =INDEX(Monthly!$C$80:$AL$80,($R$2-1)*12+12) -> 136697.29
A39: Balance sheet at year end ($'000) | H39: ="Balance sheet at month end ($'000) — Year "&$R$2 -> Balance sheet at month end ($'000) — Year 1
B40: 1 | C40: 2 | D40: 3 | H40: =INDEX(Monthly!$C$4:$AL$4,($R$2-1)*12+1) -> 1 | I40: =INDEX(Monthly!$C$4:$AL$4,($R$2-1)*12+2) -> 2 | J40: =INDEX(Monthly!$C$4:$AL$4,($R$2-1)*12+3) -> 3 | K40: =INDEX(Monthly!$C$4:$AL$4,($R$2-1)*12+4) -> 4 | L40: =INDEX(Monthly!$C$4:$AL$4,($R$2-1)*12+5) -> 5 | M40: =INDEX(Monthly!$C$4:$AL$4,($R$2-1)*12+6) -> 6 | N40: =INDEX(Monthly!$C$4:$AL$4,($R$2-1)*12+7) -> 7 | O40: =INDEX(Monthly!$C$4:$AL$4,($R$2-1)*12+8) -> 8 | P40: =INDEX(Monthly!$C$4:$AL$4,($R$2-1)*12+9) -> 9 | Q40: =INDEX(Monthly!$C$4:$AL$4,($R$2-1)*12+10) -> 10 | R40: =INDEX(Monthly!$C$4:$AL$4,($R$2-1)*12+11) -> 11 | S40: =INDEX(Monthly!$C$4:$AL$4,($R$2-1)*12+12) -> 12
A41: Cash | B41: ='Balance Sheet'!B5 -> 136697.29 | C41: ='Balance Sheet'!C5 -> 257593.89 | D41: ='Balance Sheet'!D5 -> 411594.23 | H41: =INDEX(Monthly!$C$80:$AL$80,($R$2-1)*12+1) -> 43218.391 | I41: =INDEX(Monthly!$C$80:$AL$80,($R$2-1)*12+2) -> 46436.905 | J41: =INDEX(Monthly!$C$80:$AL$80,($R$2-1)*12+3) -> 52819.314 | K41: =INDEX(Monthly!$C$80:$AL$80,($R$2-1)*12+4) -> 59689.965 | L41: =INDEX(Monthly!$C$80:$AL$80,($R$2-1)*12+5) -> 66568.078 | M41: =INDEX(Monthly!$C$80:$AL$80,($R$2-1)*12+6) -> 73453.652 | N41: =INDEX(Monthly!$C$80:$AL$80,($R$2-1)*12+7) -> 80346.687 | O41: =INDEX(Monthly!$C$80:$AL$80,($R$2-1)*12+8) -> 87247.183 | P41: =INDEX(Monthly!$C$80:$AL$80,($R$2-1)*12+9) -> 94155.141 | Q41: =INDEX(Monthly!$C$80:$AL$80,($R$2-1)*12+10) -> 101070.56 | R41: =INDEX(Monthly!$C$80:$AL$80,($R$2-1)*12+11) -> 117916.14 | S41: =INDEX(Monthly!$C$80:$AL$80,($R$2-1)*12+12) -> 136697.29
A42: Accounts receivable | B42: ='Balance Sheet'!B6 -> 35526.4 | C42: ='Balance Sheet'!C6 -> 38499.785 | D42: ='Balance Sheet'!D6 -> 41778.639 | H42: =INDEX(Monthly!$C$66:$AL$66,($R$2-1)*12+1) -> 27151.488 | I42: =INDEX(Monthly!$C$66:$AL$66,($R$2-1)*12+2) -> 28659.904 | J42: =INDEX(Monthly!$C$66:$AL$66,($R$2-1)*12+3) -> 30168.32 | K42: =INDEX(Monthly!$C$66:$AL$66,($R$2-1)*12+4) -> 30168.32 | L42: =INDEX(Monthly!$C$66:$AL$66,($R$2-1)*12+5) -> 30168.32 | M42: =INDEX(Monthly!$C$66:$AL$66,($R$2-1)*12+6) -> 30168.32 | N42: =INDEX(Monthly!$C$66:$AL$66,($R$2-1)*12+7) -> 30168.32 | O42: =INDEX(Monthly!$C$66:$AL$66,($R$2-1)*12+8) -> 30168.32 | P42: =INDEX(Monthly!$C$66:$AL$66,($R$2-1)*12+9) -> 30168.32 | Q42: =INDEX(Monthly!$C$66:$AL$66,($R$2-1)*12+10) -> 30168.32 | R42: =INDEX(Monthly!$C$66:$AL$66,($R$2-1)*12+11) -> 35526.4 | S42: =INDEX(Monthly!$C$66:$AL$66,($R$2-1)*12+12) -> 35526.4
A43: Inventory | B43: ='Balance Sheet'!B7 -> 4796.5303 | C43: ='Balance Sheet'!C7 -> 5215.3191 | D43: ='Balance Sheet'!D7 -> 5679.0702 | H43: =INDEX(Monthly!$C$67:$AL$67,($R$2-1)*12+1) -> 3699.4826 | I43: =INDEX(Monthly!$C$67:$AL$67,($R$2-1)*12+2) -> 3905.0094 | J43: =INDEX(Monthly!$C$67:$AL$67,($R$2-1)*12+3) -> 4110.5362 | K43: =INDEX(Monthly!$C$67:$AL$67,($R$2-1)*12+4) -> 4110.5362 | L43: =INDEX(Monthly!$C$67:$AL$67,($R$2-1)*12+5) -> 4110.5362 | M43: =INDEX(Monthly!$C$67:$AL$67,($R$2-1)*12+6) -> 4110.5362 | N43: =INDEX(Monthly!$C$67:$AL$67,($R$2-1)*12+7) -> 4110.5362 | O43: =INDEX(Monthly!$C$67:$AL$67,($R$2-1)*12+8) -> 4110.5362 | P43: =INDEX(Monthly!$C$67:$AL$67,($R$2-1)*12+9) -> 4110.5362 | Q43: =INDEX(Monthly!$C$67:$AL$67,($R$2-1)*12+10) -> 4110.5362 | R43: =INDEX(Monthly!$C$67:$AL$67,($R$2-1)*12+11) -> 4796.5303 | S43: =INDEX(Monthly!$C$67:$AL$67,($R$2-1)*12+12) -> 4796.5303
A44: Net fixed assets | B44: ='Balance Sheet'!B8 -> 77142.857 | C44: ='Balance Sheet'!C8 -> 77202.381 | D44: ='Balance Sheet'!D8 -> 75261.905 | H44: =INDEX(Monthly!$C$57:$AL$57,($R$2-1)*12+1) -> 88928.571 | I44: =INDEX(Monthly!$C$57:$AL$57,($R$2-1)*12+2) -> 87857.143 | J44: =INDEX(Monthly!$C$57:$AL$57,($R$2-1)*12+3) -> 86785.714 | K44: =INDEX(Monthly!$C$57:$AL$57,($R$2-1)*12+4) -> 85714.286 | L44: =INDEX(Monthly!$C$57:$AL$57,($R$2-1)*12+5) -> 84642.857 | M44: =INDEX(Monthly!$C$57:$AL$57,($R$2-1)*12+6) -> 83571.429 | N44: =INDEX(Monthly!$C$57:$AL$57,($R$2-1)*12+7) -> 82500 | O44: =INDEX(Monthly!$C$57:$AL$57,($R$2-1)*12+8) -> 81428.571 | P44: =INDEX(Monthly!$C$57:$AL$57,($R$2-1)*12+9) -> 80357.143 | Q44: =INDEX(Monthly!$C$57:$AL$57,($R$2-1)*12+10) -> 79285.714 | R44: =INDEX(Monthly!$C$57:$AL$57,($R$2-1)*12+11) -> 78214.286 | S44: =INDEX(Monthly!$C$57:$AL$57,($R$2-1)*12+12) -> 77142.857
A45: Total assets | B45: ='Balance Sheet'!B9 -> 254163.08 | C45: ='Balance Sheet'!C9 -> 378511.38 | D45: ='Balance Sheet'!D9 -> 534313.84 | H45: =INDEX(Monthly!$C$94:$AL$94,($R$2-1)*12+1) -> 162997.93 | I45: =INDEX(Monthly!$C$94:$AL$94,($R$2-1)*12+2) -> 166858.96 | J45: =INDEX(Monthly!$C$94:$AL$94,($R$2-1)*12+3) -> 173883.88 | K45: =INDEX(Monthly!$C$94:$AL$94,($R$2-1)*12+4) -> 179683.11 | L45: =INDEX(Monthly!$C$94:$AL$94,($R$2-1)*12+5) -> 185489.79 | M45: =INDEX(Monthly!$C$94:$AL$94,($R$2-1)*12+6) -> 191303.94 | N45: =INDEX(Monthly!$C$94:$AL$94,($R$2-1)*12+7) -> 197125.54 | O45: =INDEX(Monthly!$C$94:$AL$94,($R$2-1)*12+8) -> 202954.61 | P45: =INDEX(Monthly!$C$94:$AL$94,($R$2-1)*12+9) -> 208791.14 | Q45: =INDEX(Monthly!$C$94:$AL$94,($R$2-1)*12+10) -> 214635.13 | R45: =INDEX(Monthly!$C$94:$AL$94,($R$2-1)*12+11) -> 236453.36 | S45: =INDEX(Monthly!$C$94:$AL$94,($R$2-1)*12+12) -> 254163.08
A46: Accounts payable | B46: ='Balance Sheet'!B10 -> 28779.182 | C46: ='Balance Sheet'!C10 -> 31291.915 | D46: ='Balance Sheet'!D10 -> 34074.421 | H46: =INDEX(Monthly!$C$68:$AL$68,($R$2-1)*12+1) -> 22196.896 | I46: =INDEX(Monthly!$C$68:$AL$68,($R$2-1)*12+2) -> 23430.057 | J46: =INDEX(Monthly!$C$68:$AL$68,($R$2-1)*12+3) -> 24663.217 | K46: =INDEX(Monthly!$C$68:$AL$68,($R$2-1)*12+4) -> 24663.217 | L46: =INDEX(Monthly!$C$68:$AL$68,($R$2-1)*12+5) -> 24663.217 | M46: =INDEX(Monthly!$C$68:$AL$68,($R$2-1)*12+6) -> 24663.217 | N46: =INDEX(Monthly!$C$68:$AL$68,($R$2-1)*12+7) -> 24663.217 | O46: =INDEX(Monthly!$C$68:$AL$68,($R$2-1)*12+8) -> 24663.217 | P46: =INDEX(Monthly!$C$68:$AL$68,($R$2-1)*12+9) -> 24663.217 | Q46: =INDEX(Monthly!$C$68:$AL$68,($R$2-1)*12+10) -> 24663.217 | R46: =INDEX(Monthly!$C$68:$AL$68,($R$2-1)*12+11) -> 28779.182 | S46: =INDEX(Monthly!$C$68:$AL$68,($R$2-1)*12+12) -> 28779.182
A47: Loan | B47: ='Balance Sheet'!B11 -> 65333.333 | C47: ='Balance Sheet'!C11 -> 49333.333 | D47: ='Balance Sheet'!D11 -> 33333.333 | H47: =INDEX(Monthly!$C$63:$AL$63,($R$2-1)*12+1) -> 80000 | I47: =INDEX(Monthly!$C$63:$AL$63,($R$2-1)*12+2) -> 78666.667 | J47: =INDEX(Monthly!$C$63:$AL$63,($R$2-1)*12+3) -> 77333.333 | K47: =INDEX(Monthly!$C$63:$AL$63,($R$2-1)*12+4) -> 76000 | L47: =INDEX(Monthly!$C$63:$AL$63,($R$2-1)*12+5) -> 74666.667 | M47: =INDEX(Monthly!$C$63:$AL$63,($R$2-1)*12+6) -> 73333.333 | N47: =INDEX(Monthly!$C$63:$AL$63,($R$2-1)*12+7) -> 72000 | O47: =INDEX(Monthly!$C$63:$AL$63,($R$2-1)*12+8) -> 70666.667 | P47: =INDEX(Monthly!$C$63:$AL$63,($R$2-1)*12+9) -> 69333.333 | Q47: =INDEX(Monthly!$C$63:$AL$63,($R$2-1)*12+10) -> 68000 | R47: =INDEX(Monthly!$C$63:$AL$63,($R$2-1)*12+11) -> 66666.667 | S47: =INDEX(Monthly!$C$63:$AL$63,($R$2-1)*12+12) -> 65333.333
A48: Total liabilities | B48: ='Balance Sheet'!B12 -> 94112.515 | C48: ='Balance Sheet'!C12 -> 80625.248 | D48: ='Balance Sheet'!D12 -> 67407.755 | H48: =INDEX(Monthly!$C$95:$AL$95,($R$2-1)*12+1) -> 102196.9 | I48: =INDEX(Monthly!$C$95:$AL$95,($R$2-1)*12+2) -> 102096.72 | J48: =INDEX(Monthly!$C$95:$AL$95,($R$2-1)*12+3) -> 101996.55 | K48: =INDEX(Monthly!$C$95:$AL$95,($R$2-1)*12+4) -> 100663.22 | L48: =INDEX(Monthly!$C$95:$AL$95,($R$2-1)*12+5) -> 99329.884 | M48: =INDEX(Monthly!$C$95:$AL$95,($R$2-1)*12+6) -> 97996.551 | N48: =INDEX(Monthly!$C$95:$AL$95,($R$2-1)*12+7) -> 96663.217 | O48: =INDEX(Monthly!$C$95:$AL$95,($R$2-1)*12+8) -> 95329.884 | P48: =INDEX(Monthly!$C$95:$AL$95,($R$2-1)*12+9) -> 93996.551 | Q48: =INDEX(Monthly!$C$95:$AL$95,($R$2-1)*12+10) -> 92663.217 | R48: =INDEX(Monthly!$C$95:$AL$95,($R$2-1)*12+11) -> 95445.848 | S48: =INDEX(Monthly!$C$95:$AL$95,($R$2-1)*12+12) -> 94112.515
A49: Paid-in capital | B49: ='Balance Sheet'!B13 -> 60000 | C49: ='Balance Sheet'!C13 -> 60000 | D49: ='Balance Sheet'!D13 -> 60000 | H49: =INDEX(Monthly!$C$92:$AL$92,($R$2-1)*12+1) -> 60000 | I49: =INDEX(Monthly!$C$92:$AL$92,($R$2-1)*12+2) -> 60000 | J49: =INDEX(Monthly!$C$92:$AL$92,($R$2-1)*12+3) -> 60000 | K49: =INDEX(Monthly!$C$92:$AL$92,($R$2-1)*12+4) -> 60000 | L49: =INDEX(Monthly!$C$92:$AL$92,($R$2-1)*12+5) -> 60000 | M49: =INDEX(Monthly!$C$92:$AL$92,($R$2-1)*12+6) -> 60000 | N49: =INDEX(Monthly!$C$92:$AL$92,($R$2-1)*12+7) -> 60000 | O49: =INDEX(Monthly!$C$92:$AL$92,($R$2-1)*12+8) -> 60000 | P49: =INDEX(Monthly!$C$92:$AL$92,($R$2-1)*12+9) -> 60000 | Q49: =INDEX(Monthly!$C$92:$AL$92,($R$2-1)*12+10) -> 60000 | R49: =INDEX(Monthly!$C$92:$AL$92,($R$2-1)*12+11) -> 60000 | S49: =INDEX(Monthly!$C$92:$AL$92,($R$2-1)*12+12) -> 60000
A50: Retained earnings | B50: ='Balance Sheet'!B14 -> 100050.56 | C50: ='Balance Sheet'!C14 -> 237886.13 | D50: ='Balance Sheet'!D14 -> 406906.08 | H50: =INDEX(Monthly!$C$93:$AL$93,($R$2-1)*12+1) -> 801.03715 | I50: =INDEX(Monthly!$C$93:$AL$93,($R$2-1)*12+2) -> 4762.2381 | J50: =INDEX(Monthly!$C$93:$AL$93,($R$2-1)*12+3) -> 11887.334 | K50: =INDEX(Monthly!$C$93:$AL$93,($R$2-1)*12+4) -> 19019.89 | L50: =INDEX(Monthly!$C$93:$AL$93,($R$2-1)*12+5) -> 26159.908 | M50: =INDEX(Monthly!$C$93:$AL$93,($R$2-1)*12+6) -> 33307.386 | N50: =INDEX(Monthly!$C$93:$AL$93,($R$2-1)*12+7) -> 40462.326 | O50: =INDEX(Monthly!$C$93:$AL$93,($R$2-1)*12+8) -> 47624.727 | P50: =INDEX(Monthly!$C$93:$AL$93,($R$2-1)*12+9) -> 54794.589 | Q50: =INDEX(Monthly!$C$93:$AL$93,($R$2-1)*12+10) -> 61971.912 | R50: =INDEX(Monthly!$C$93:$AL$93,($R$2-1)*12+11) -> 81007.507 | S50: =INDEX(Monthly!$C$93:$AL$93,($R$2-1)*12+12) -> 100050.56
A51: Total equity | B51: ='Balance Sheet'!B15 -> 160050.56 | C51: ='Balance Sheet'!C15 -> 297886.13 | D51: ='Balance Sheet'!D15 -> 466906.08 | H51: =INDEX(Monthly!$C$96:$AL$96,($R$2-1)*12+1) -> 60801.037 | I51: =INDEX(Monthly!$C$96:$AL$96,($R$2-1)*12+2) -> 64762.238 | J51: =INDEX(Monthly!$C$96:$AL$96,($R$2-1)*12+3) -> 71887.334 | K51: =INDEX(Monthly!$C$96:$AL$96,($R$2-1)*12+4) -> 79019.89 | L51: =INDEX(Monthly!$C$96:$AL$96,($R$2-1)*12+5) -> 86159.908 | M51: =INDEX(Monthly!$C$96:$AL$96,($R$2-1)*12+6) -> 93307.386 | N51: =INDEX(Monthly!$C$96:$AL$96,($R$2-1)*12+7) -> 100462.33 | O51: =INDEX(Monthly!$C$96:$AL$96,($R$2-1)*12+8) -> 107624.73 | P51: =INDEX(Monthly!$C$96:$AL$96,($R$2-1)*12+9) -> 114794.59 | Q51: =INDEX(Monthly!$C$96:$AL$96,($R$2-1)*12+10) -> 121971.91 | R51: =INDEX(Monthly!$C$96:$AL$96,($R$2-1)*12+11) -> 141007.51 | S51: =INDEX(Monthly!$C$96:$AL$96,($R$2-1)*12+12) -> 160050.56
A52: Total liabilities & equity | B52: ='Balance Sheet'!B16 -> 254163.08 | C52: ='Balance Sheet'!C16 -> 378511.38 | D52: ='Balance Sheet'!D16 -> 534313.84 | H52: =INDEX(Monthly!$C$97:$AL$97,($R$2-1)*12+1) -> 162997.93 | I52: =INDEX(Monthly!$C$97:$AL$97,($R$2-1)*12+2) -> 166858.96 | J52: =INDEX(Monthly!$C$97:$AL$97,($R$2-1)*12+3) -> 173883.88 | K52: =INDEX(Monthly!$C$97:$AL$97,($R$2-1)*12+4) -> 179683.11 | L52: =INDEX(Monthly!$C$97:$AL$97,($R$2-1)*12+5) -> 185489.79 | M52: =INDEX(Monthly!$C$97:$AL$97,($R$2-1)*12+6) -> 191303.94 | N52: =INDEX(Monthly!$C$97:$AL$97,($R$2-1)*12+7) -> 197125.54 | O52: =INDEX(Monthly!$C$97:$AL$97,($R$2-1)*12+8) -> 202954.61 | P52: =INDEX(Monthly!$C$97:$AL$97,($R$2-1)*12+9) -> 208791.14 | Q52: =INDEX(Monthly!$C$97:$AL$97,($R$2-1)*12+10) -> 214635.13 | R52: =INDEX(Monthly!$C$97:$AL$97,($R$2-1)*12+11) -> 236453.36 | S52: =INDEX(Monthly!$C$97:$AL$97,($R$2-1)*12+12) -> 254163.08

Sheet Break-even
A1: Startup costs, funding need and break-even | F1: =HYPERLINK("#'Cover'!A1","◂ Contents") -> ◂ Contents
A2: Live for the selected scenario. Periods are counted in months from the start of the plan.
A3: Scenario shown | B3: =CHOOSE(Dashboard!$B$4,"Low","Base","High") -> Base
A5: Startup costs & funding need (up to the lowest cash point)
A6: Lowest cash point (month #) | B6: =MATCH(MIN(Monthly!$C$80:$AL$80),Monthly!$C$80:$AL$80,0) -> 1
A7: Capital spending up to the lowest cash point | B7: =SUMPRODUCT(--(Monthly!$C$4:$AL$4<=$B$6),Monthly!$C$53:$AL$53) -> 90000
A8: Operating cash burn up to the lowest cash point | B8: =-SUMPRODUCT(--(Monthly!$C$4:$AL$4<=$B$6),Monthly!$C$74:$AL$74) -> 6781.6092 | D8: Losses and working capital before the business funds itself
A9: Loan repayments up to the lowest cash point | B9: =-SUMPRODUCT(--(Monthly!$C$4:$AL$4<=$B$6),Monthly!$C$62:$AL$62) -> 0
A10: Total uses of funds | B10: =B7+B8+B9 -> 96781.609
A11: Minimum cash buffer to keep | B11: =Inputs!$E$73 -> 233000 | D11: Input on the Inputs sheet
A12: Funding required (uses + buffer) | B12: =B10+B11 -> 329781.61
A14: Equity raised | B14: =Inputs!$E$58 -> 60000
A15: Loan drawn | B15: =Inputs!$E$59 -> 80000
A16: Total sources of funds | B16: =B14+B15 -> 140000
A17: Funding surplus / (shortfall) | B17: =B16-B12 -> -189781.61 | D17: Negative = raise at least this much more
A18: Lowest cash balance in the plan | B18: =MIN(Monthly!$C$80:$AL$80) -> 43218.391 | D18: Equals sources minus uses
A20: Break-even timing
A21: First month with positive EBITDA (month #) | B21: =IFERROR(MATCH(1,Monthly!$C$81:$AL$81,0),"Not within horizon") -> 1
A22: First month with positive net income (month #) | B22: =IFERROR(MATCH(1,Monthly!$C$84:$AL$84,0),"Not within horizon") -> 1
A23: Cash invested paid back (month #) | B23: =IF(MIN(Monthly!$C$86:$AL$86)>=0,"No investment to pay back",IFERROR(MATCH(1,Monthly!$C$88:$AL$88,0),"Not within horizon")) -> 12 | D23: Cumulative operating + investing cash flow back to zero
A25: Annual break-even revenue
A26: Year # | B26: 1 | C26: 2 | D26: 3
B27: Year 1 | C27: Year 2 | D27: Year 3
A28: Revenue | B28: =SUMIF(Monthly!$C$5:$AL$5,B$26,Monthly!$C$22:$AL$22) -> 1578046.1 | C28: =SUMIF(Monthly!$C$5:$AL$5,C$26,Monthly!$C$22:$AL$22) -> 1736372.4 | D28: =SUMIF(Monthly!$C$5:$AL$5,D$26,Monthly!$C$22:$AL$22) -> 1890162.9
A29: Gross profit | B29: =SUMIF(Monthly!$C$5:$AL$5,B$26,Monthly!$C$29:$AL$29) -> 1077227.7 | C29: =SUMIF(Monthly!$C$5:$AL$5,C$26,Monthly!$C$29:$AL$29) -> 1183311.2 | D29: =SUMIF(Monthly!$C$5:$AL$5,D$26,Monthly!$C$29:$AL$29) -> 1285883.7
A30: Gross margin (contribution) | B30: =IF(B28=0,0,B29/B28) -> 0.68263384 | C30: =IF(C28=0,0,C29/C28) -> 0.68148469 | D30: =IF(D28=0,0,D29/D28) -> 0.68030311
A31: Operating expenses (treated as fixed) | B31: =-SUMIF(Monthly!$C$5:$AL$5,B$26,Monthly!$C$40:$AL$40) -> 931495.62 | C31: =-SUMIF(Monthly!$C$5:$AL$5,C$26,Monthly!$C$40:$AL$40) -> 990021.96 | D31: =-SUMIF(Monthly!$C$5:$AL$5,D$26,Monthly!$C$40:$AL$40) -> 1052480.5
A32: Break-even revenue (EBITDA = 0) | B32: =IF(B30>0,B31/B30,"n/a") -> 1364561.2 | C32: =IF(C30>0,C31/C30,"n/a") -> 1452742.8 | D32: =IF(D30>0,D31/D30,"n/a") -> 1547075.9
A33: Margin of safety (revenue above break-even) | B33: =IF(AND(ISNUMBER(B32),B28>0),(B28-B32)/B28,"n/a") -> 0.13528434 | C33: =IF(AND(ISNUMBER(C32),C28>0),(C28-C32)/C28,"n/a") -> 0.16334605 | D33: =IF(AND(ISNUMBER(D32),D28>0),(D28-D32)/D28,"n/a") -> 0.18151185
A35: Simplification: cost of sales is treated as variable and operating expenses as fixed, so break-even revenue = operating expenses ÷ gross margin.

Sheet Valuation
A1: Discounted cash flow valuation | H1: =HYPERLINK("#'Cover'!A1","◂ Contents") -> ◂ Contents
A2: Enterprise value at the start of the plan, before the funding raised in period 1. Year-end discounting.
A3: Scenario shown | B3: =CHOOSE(Dashboard!$B$4,"Low","Base","High") -> Base
A5: Assumptions (active scenario, from the Inputs sheet)
A6: Discount rate (WACC) | B6: =Inputs!$E$76 -> 0.16
A7: Terminal growth rate | B7: =Inputs!$E$77 -> 0.02
A8: Exit multiple (EV ÷ final-year EBITDA) | B8: =Inputs!$E$78 -> 5.5
A9: Tax rate (for the interest tax shield) | B9: =Inputs!$E$70 -> 0.21
A10: Sensitivity step: WACC | B10: =Inputs!$E$79 -> 0.01
A11: Sensitivity step: terminal growth | B11: =Inputs!$E$80 -> 0.005
A13: Free cash flow by year
A14: Year # | B14: 1 | C14: 2 | D14: 3
B15: Year 1 | C15: Year 2 | D15: Year 3
A16: EBITDA | B16: =SUMIF(Monthly!$C$5:$AL$5,B$14,Monthly!$C$41:$AL$41) -> 145732.04 | C16: =SUMIF(Monthly!$C$5:$AL$5,C$14,Monthly!$C$41:$AL$41) -> 193289.21 | D16: =SUMIF(Monthly!$C$5:$AL$5,D$14,Monthly!$C$41:$AL$41) -> 233403.12
A17: Unlevered free cash flow | B17: =SUMIF(Monthly!$C$5:$AL$5,B$14,Monthly!$C$89:$AL$89) -> 16284.56 | C17: =SUMIF(Monthly!$C$5:$AL$5,C$14,Monthly!$C$89:$AL$89) -> 140746.53 | D17: =SUMIF(Monthly!$C$5:$AL$5,D$14,Monthly!$C$89:$AL$89) -> 172775.87
A18: Discount factor | B18: =1/(1+Inputs!$E$76)^B$14 -> 0.86206897 | C18: =1/(1+Inputs!$E$76)^C$14 -> 0.7431629 | D18: =1/(1+Inputs!$E$76)^D$14 -> 0.64065767
A19: Present value of free cash flow | B19: =B17*B18 -> 14038.414 | C19: =C17*C18 -> 104597.6 | D19: =D17*D18 -> 110690.19
A21: Enterprise value
B22: Perpetual growth | C22: Exit multiple
A23: Present value of the plan's free cash flows | B23: =SUM($B$19:$D$19) -> 229326.2 | C23: =B23 -> 229326.2
A24: Final-year free cash flow | final-year EBITDA | B24: =$D$17 -> 172775.87 | C24: =$D$16 -> 233403.12
A25: Terminal value at the end of year 3 | B25: =IF($B$6>$B$7,B24*(1+$B$7)/($B$6-$B$7),0) -> 1258795.6 | C25: =C24*$B$8 -> 1283717.2
A26: Present value of the terminal value | B26: =B25/(1+$B$6)^$D$14 -> 806457.06 | C26: =C25/(1+$B$6)^$D$14 -> 822423.25
A27: Enterprise value | B27: =B23+B26 -> 1035783.3 | C27: =C23+C26 -> 1051749.5
A28: Terminal value share of enterprise value | B28: =IF(B27<>0,B26/B27,0) -> 0.77859634 | C28: =IF(C27<>0,C26/C27,0) -> 0.78195738
A29: Cross-check: implied exit multiple | implied perpetual growth | B29: =IF(C24>0,B25/C24,"n/a") -> 5.3932253 | C29: =IF(C25+B24<>0,(C25*$B$6-B24)/(C25+B24),"n/a") -> 0.022395493
A30: Enterprise value — average of the two methods | B30: =AVERAGE(B27,C27) -> 1043766.4
A32: Sensitivity: enterprise value (perpetual growth) by WACC and terminal growth
A33: WACC ↓ · terminal growth → | B33: =$B$7+(-2)*$B$11 -> 0.01 | C33: =$B$7+(-1)*$B$11 -> 0.015 | D33: =$B$7+(0)*$B$11 -> 0.02 | E33: =$B$7+(1)*$B$11 -> 0.025 | F33: =$B$7+(2)*$B$11 -> 0.03
A34: =$B$6+(-2)*$B$10 -> 0.14 | B34: =IF($A34>B$33,SUMPRODUCT($B$17:$D$17/(1+$A34)^$B$14:$D$14)+$D$17*(1+B$33)/($A34-B$33)/(1+$A34)^$D$14,"n/a") -> 1145241.7 | C34: =IF($A34>C$33,SUMPRODUCT($B$17:$D$17/(1+$A34)^$B$14:$D$14)+$D$17*(1+C$33)/($A34-C$33)/(1+$A34)^$D$14,"n/a") -> 1186147.9 | D34: =IF($A34>D$33,SUMPRODUCT($B$17:$D$17/(1+$A34)^$B$14:$D$14)+$D$17*(1+D$33)/($A34-D$33)/(1+$A34)^$D$14,"n/a") -> 1230463.1 | E34: =IF($A34>E$33,SUMPRODUCT($B$17:$D$17/(1+$A34)^$B$14:$D$14)+$D$17*(1+E$33)/($A34-E$33)/(1+$A34)^$D$14,"n/a") -> 1278631.7 | F34: =IF($A34>F$33,SUMPRODUCT($B$17:$D$17/(1+$A34)^$B$14:$D$14)+$D$17*(1+F$33)/($A34-F$33)/(1+$A34)^$D$14,"n/a") -> 1331179.3
A35: =$B$6+(-1)*$B$10 -> 0.15 | B35: =IF($A35>B$33,SUMPRODUCT($B$17:$D$17/(1+$A35)^$B$14:$D$14)+$D$17*(1+B$33)/($A35-B$33)/(1+$A35)^$D$14,"n/a") -> 1053752.1 | C35: =IF($A35>C$33,SUMPRODUCT($B$17:$D$17/(1+$A35)^$B$14:$D$14)+$D$17*(1+C$33)/($A35-C$33)/(1+$A35)^$D$14,"n/a") -> 1088313.8 | D35: =IF($A35>D$33,SUMPRODUCT($B$17:$D$17/(1+$A35)^$B$14:$D$14)+$D$17*(1+D$33)/($A35-D$33)/(1+$A35)^$D$14,"n/a") -> 1125534.1 | E35: =IF($A35>E$33,SUMPRODUCT($B$17:$D$17/(1+$A35)^$B$14:$D$14)+$D$17*(1+E$33)/($A35-E$33)/(1+$A35)^$D$14,"n/a") -> 1165732.1 | F35: =IF($A35>F$33,SUMPRODUCT($B$17:$D$17/(1+$A35)^$B$14:$D$14)+$D$17*(1+F$33)/($A35-F$33)/(1+$A35)^$D$14,"n/a") -> 1209279.9
A36: =$B$6+(0)*$B$10 -> 0.16 | B36: =IF($A36>B$33,SUMPRODUCT($B$17:$D$17/(1+$A36)^$B$14:$D$14)+$D$17*(1+B$33)/($A36-B$33)/(1+$A36)^$D$14,"n/a") -> 974640.12 | C36: =IF($A36>C$33,SUMPRODUCT($B$17:$D$17/(1+$A36)^$B$14:$D$14)+$D$17*(1+C$33)/($A36-C$33)/(1+$A36)^$D$14,"n/a") -> 1004157.5 | D36: =IF($A36>D$33,SUMPRODUCT($B$17:$D$17/(1+$A36)^$B$14:$D$14)+$D$17*(1+D$33)/($A36-D$33)/(1+$A36)^$D$14,"n/a") -> 1035783.3 | E36: =IF($A36>E$33,SUMPRODUCT($B$17:$D$17/(1+$A36)^$B$14:$D$14)+$D$17*(1+E$33)/($A36-E$33)/(1+$A36)^$D$14,"n/a") -> 1069751.7 | F36: =IF($A36>F$33,SUMPRODUCT($B$17:$D$17/(1+$A36)^$B$14:$D$14)+$D$17*(1+F$33)/($A36-F$33)/(1+$A36)^$D$14,"n/a") -> 1106333.1
A37: =$B$6+(1)*$B$10 -> 0.17 | B37: =IF($A37>B$33,SUMPRODUCT($B$17:$D$17/(1+$A37)^$B$14:$D$14)+$D$17*(1+B$33)/($A37-B$33)/(1+$A37)^$D$14,"n/a") -> 905580.13 | C37: =IF($A37>C$33,SUMPRODUCT($B$17:$D$17/(1+$A37)^$B$14:$D$14)+$D$17*(1+C$33)/($A37-C$33)/(1+$A37)^$D$14,"n/a") -> 931026.73 | D37: =IF($A37>D$33,SUMPRODUCT($B$17:$D$17/(1+$A37)^$B$14:$D$14)+$D$17*(1+D$33)/($A37-D$33)/(1+$A37)^$D$14,"n/a") -> 958169.76 | E37: =IF($A37>E$33,SUMPRODUCT($B$17:$D$17/(1+$A37)^$B$14:$D$14)+$D$17*(1+E$33)/($A37-E$33)/(1+$A37)^$D$14,"n/a") -> 987184.73 | F37: =IF($A37>F$33,SUMPRODUCT($B$17:$D$17/(1+$A37)^$B$14:$D$14)+$D$17*(1+F$33)/($A37-F$33)/(1+$A37)^$D$14,"n/a") -> 1018272.2
A38: =$B$6+(2)*$B$10 -> 0.18 | B38: =IF($A38>B$33,SUMPRODUCT($B$17:$D$17/(1+$A38)^$B$14:$D$14)+$D$17*(1+B$33)/($A38-B$33)/(1+$A38)^$D$14,"n/a") -> 844793.84 | C38: =IF($A38>C$33,SUMPRODUCT($B$17:$D$17/(1+$A38)^$B$14:$D$14)+$D$17*(1+C$33)/($A38-C$33)/(1+$A38)^$D$14,"n/a") -> 866912.37 | D38: =IF($A38>D$33,SUMPRODUCT($B$17:$D$17/(1+$A38)^$B$14:$D$14)+$D$17*(1+D$33)/($A38-D$33)/(1+$A38)^$D$14,"n/a") -> 890413.3 | E38: =IF($A38>E$33,SUMPRODUCT($B$17:$D$17/(1+$A38)^$B$14:$D$14)+$D$17*(1+E$33)/($A38-E$33)/(1+$A38)^$D$14,"n/a") -> 915430.43 | F38: =IF($A38>F$33,SUMPRODUCT($B$17:$D$17/(1+$A38)^$B$14:$D$14)+$D$17*(1+F$33)/($A38-F$33)/(1+$A38)^$D$14,"n/a") -> 942115.36
A40: Free cash flow = operating cash flow + interest × (1 − tax rate) − capital spending. Cells marked n/a: WACC not above growth.

Sheet Sources & Uses
A1: Sources and uses of funds | E1: =HYPERLINK("#'Cover'!A1","◂ Contents") -> ◂ Contents
A2: Live for the selected scenario. Where the money comes from and where it goes in the period set below.
A3: Scenario shown | B3: =CHOOSE(Dashboard!$B$4,"Low","Base","High") -> Base
A5: Funding structure ($'000) — raised at the start of the plan
B6: Amount | C6: Share
A7: Equity | B7: =Inputs!$E$58 -> 60000 | C7: =IF($B$9=0,0,B7/$B$9) -> 0.42857143
A8: Debt (loan) | B8: =Inputs!$E$59 -> 80000 | C8: =IF($B$9=0,0,B8/$B$9) -> 0.57142857
A9: Total funding | B9: =B7+B8 -> 140000 | C9: =IF(B9=0,0,1) -> 1
A10: Gearing (debt ÷ equity) | B10: =IF(B7<=0,IF(B8>0,"n/a",0),B8/B7) -> 1.3333333 | D10: n/a: debt without positive equity
A11: Funding required by the plan (Break-even sheet) | B11: ='Break-even'!B12 -> 329781.61
A12: Funding surplus / (shortfall) | B12: ='Break-even'!B17 -> -189781.61
A14: ="Sources and uses of cash in the first "&$B$16&IF($B$16=1," month"," months")&" ($'000)" -> Sources and uses of cash in the first 12 months ($'000)
A15: Period covered (months from the start) | B15: 12 | D15: 1 to 36 (capped)
A16: Months used | B16: =MIN(36,MAX(1,ROUND(B15,0))) -> 12
A17: Sources | B17: Amount | C17: Share
A18: Equity raised | B18: =SUMPRODUCT(--(Monthly!$C$4:$AL$4<=$B$16),Monthly!$C$76:$AL$76) -> 60000 | C18: =IF($B$21=0,0,B18/$B$21) -> 0.24858724
A19: Loan drawdowns | B19: =SUMPRODUCT(--(Monthly!$C$4:$AL$4<=$B$16),Monthly!$C$61:$AL$61) -> 80000 | C19: =IF($B$21=0,0,B19/$B$21) -> 0.33144965
A20: Cash generated by operations | B20: =MAX(0,SUMPRODUCT(--(Monthly!$C$4:$AL$4<=$B$16),Monthly!$C$74:$AL$74)) -> 101363.96 | C20: =IF($B$21=0,0,B20/$B$21) -> 0.41996311
A21: Total sources | B21: =SUM(B18:B20) -> 241363.96 | C21: =IF(B21=0,0,1) -> 1
A23: Uses | B23: Amount | C23: Share
A24: Cash used by operations | B24: =MAX(0,-SUMPRODUCT(--(Monthly!$C$4:$AL$4<=$B$16),Monthly!$C$74:$AL$74)) -> 0 | C24: =IF($B$28=0,0,B24/$B$28) -> 0
A25: Capital spending | B25: =-SUMPRODUCT(--(Monthly!$C$4:$AL$4<=$B$16),Monthly!$C$75:$AL$75) -> 90000 | C25: =IF($B$28=0,0,B25/$B$28) -> 0.37288086
A26: Loan repayments | B26: =-SUMPRODUCT(--(Monthly!$C$4:$AL$4<=$B$16),Monthly!$C$62:$AL$62) -> 14666.667 | C26: =IF($B$28=0,0,B26/$B$28) -> 0.06076577
A27: Cash at the end of the period | B27: =INDEX(Monthly!$C$80:$AL$80,$B$16) -> 136697.29 | C27: =IF($B$28=0,0,B27/$B$28) -> 0.56635337
A28: Total uses | B28: =SUM(B24:B27) -> 241363.96 | C28: =IF(B28=0,0,1) -> 1
A29: Sources − uses (must be 0; opening cash is 0) | B29: =B21-B28 -> 0

Sheet KPIs
A1: KPIs & ratios | G1: =HYPERLINK("#'Cover'!A1","◂ Contents") -> ◂ Contents
A2: Bakery financial model (growing) — industry metrics and financial ratios for the active scenario
A4: Financial ratios
B5: 1 | C5: 2 | D5: 3 | E5: Target
A6: Revenue growth | B6: =IF(N('P&L'!A5)<=0,"n/a",'P&L'!B5/'P&L'!A5-1) -> n/a | C6: =IF(N('P&L'!B5)<=0,"n/a",'P&L'!C5/'P&L'!B5-1) -> 0.10033058 | D6: =IF(N('P&L'!C5)<=0,"n/a",'P&L'!D5/'P&L'!C5-1) -> 0.088570003
A7: Gross margin | B7: =IF('P&L'!B5<=0,"n/a",'P&L'!B7/'P&L'!B5) -> 0.68263384 | C7: =IF('P&L'!C5<=0,"n/a",'P&L'!C7/'P&L'!C5) -> 0.68148469 | D7: =IF('P&L'!D5<=0,"n/a",'P&L'!D7/'P&L'!D5) -> 0.68030311
A8: EBITDA margin | B8: =IF('P&L'!B5<=0,"n/a",'P&L'!B18/'P&L'!B5) -> 0.092349671 | C8: =IF('P&L'!C5<=0,"n/a",'P&L'!C18/'P&L'!C5) -> 0.11131783 | D8: =IF('P&L'!D5<=0,"n/a",'P&L'!D18/'P&L'!D5) -> 0.12348307
A9: Net margin | B9: =IF('P&L'!B5<=0,"n/a",'P&L'!B25/'P&L'!B5) -> 0.063401547 | C9: =IF('P&L'!C5<=0,"n/a",'P&L'!C25/'P&L'!C5) -> 0.079381341 | D9: =IF('P&L'!D5<=0,"n/a",'P&L'!D25/'P&L'!D5) -> 0.089420843
A10: Payroll, % of revenue | B10: =IF('P&L'!B5<=0,"n/a",-SUMIF(Headcount!$C$5:$AL$5,B$5,Headcount!$C$17:$AL$17)/'P&L'!B5) -> 0.37616139 | C10: =IF('P&L'!C5<=0,"n/a",-SUMIF(Headcount!$C$5:$AL$5,C$5,Headcount!$C$17:$AL$17)/'P&L'!C5) -> 0.3695379 | D10: =IF('P&L'!D5<=0,"n/a",-SUMIF(Headcount!$C$5:$AL$5,D$5,Headcount!$C$17:$AL$17)/'P&L'!D5) -> 0.36712665
A11: Marketing, % of revenue | B11: =IF('P&L'!B5<=0,"n/a",-'P&L'!B14/'P&L'!B5) -> 0.02 | C11: =IF('P&L'!C5<=0,"n/a",-'P&L'!C14/'P&L'!C5) -> 0.02 | D11: =IF('P&L'!D5<=0,"n/a",-'P&L'!D14/'P&L'!D5) -> 0.02
A12: Operating expenses, % of revenue | B12: =IF('P&L'!B5<=0,"n/a",-'P&L'!B17/'P&L'!B5) -> 0.59028417 | C12: =IF('P&L'!C5<=0,"n/a",-'P&L'!C17/'P&L'!C5) -> 0.57016685 | D12: =IF('P&L'!D5<=0,"n/a",-'P&L'!D17/'P&L'!D5) -> 0.55682003
A13: Current ratio (current assets ÷ current liabilities) | B13: =IF(('Balance Sheet'!B12-'Balance Sheet'!B11)<=0,"n/a",('Balance Sheet'!B5+'Balance Sheet'!B6+'Balance Sheet'!B7)/('Balance Sheet'!B12-'Balance Sheet'!B11)) -> 6.1509817 | C13: =IF(('Balance Sheet'!C12-'Balance Sheet'!C11)<=0,"n/a",('Balance Sheet'!C5+'Balance Sheet'!C6+'Balance Sheet'!C7)/('Balance Sheet'!C12-'Balance Sheet'!C11)) -> 9.6289728 | D13: =IF(('Balance Sheet'!D12-'Balance Sheet'!D11)<=0,"n/a",('Balance Sheet'!D5+'Balance Sheet'!D6+'Balance Sheet'!D7)/('Balance Sheet'!D12-'Balance Sheet'!D11)) -> 13.472039
A14: Debt ÷ equity (loan ÷ total equity) | B14: =IF('Balance Sheet'!B15<=0,"n/a",'Balance Sheet'!B11/'Balance Sheet'!B15) -> 0.40820433 | C14: =IF('Balance Sheet'!C15<=0,"n/a",'Balance Sheet'!C11/'Balance Sheet'!C15) -> 0.16561138 | D14: =IF('Balance Sheet'!D15<=0,"n/a",'Balance Sheet'!D11/'Balance Sheet'!D15) -> 0.071391945
A15: Return on assets (net income ÷ year-end assets) | B15: =IF('Balance Sheet'!B9<=0,"n/a",'P&L'!B25/'Balance Sheet'!B9) -> 0.39364712 | C15: =IF('Balance Sheet'!C9<=0,"n/a",'P&L'!C25/'Balance Sheet'!C9) -> 0.36415171 | D15: =IF('Balance Sheet'!D9<=0,"n/a",'P&L'!D25/'Balance Sheet'!D9) -> 0.31633086
A16: Return on equity (net income ÷ year-end equity) | B16: =IF('Balance Sheet'!B15<=0,"n/a",'P&L'!B25/'Balance Sheet'!B15) -> 0.62511847 | C16: =IF('Balance Sheet'!C15<=0,"n/a",'P&L'!C25/'Balance Sheet'!C15) -> 0.46271227 | D16: =IF('Balance Sheet'!D15<=0,"n/a",'P&L'!D25/'Balance Sheet'!D15) -> 0.3619999
A18: DuPont analysis — return on equity = net margin × asset turnover × equity multiplier
B19: 1 | C19: 2 | D19: 3
A20: Net margin | B20: =IF('P&L'!B5<=0,"n/a",'P&L'!B25/'P&L'!B5) -> 0.063401547 | C20: =IF('P&L'!C5<=0,"n/a",'P&L'!C25/'P&L'!C5) -> 0.079381341 | D20: =IF('P&L'!D5<=0,"n/a",'P&L'!D25/'P&L'!D5) -> 0.089420843
A21: × Asset turnover (revenue ÷ assets) | B21: =IF('Balance Sheet'!B9<=0,"n/a",'P&L'!B5/'Balance Sheet'!B9) -> 6.2087936 | C21: =IF('Balance Sheet'!C9<=0,"n/a",'P&L'!C5/'Balance Sheet'!C9) -> 4.5873716 | D21: =IF('Balance Sheet'!D9<=0,"n/a",'P&L'!D5/'Balance Sheet'!D9) -> 3.5375518
A22: × Equity multiplier (assets ÷ equity) | B22: =IF('Balance Sheet'!B15<=0,"n/a",'Balance Sheet'!B9/'Balance Sheet'!B15) -> 1.5880174 | C22: =IF('Balance Sheet'!C15<=0,"n/a",'Balance Sheet'!C9/'Balance Sheet'!C15) -> 1.2706579 | D22: =IF('Balance Sheet'!D15<=0,"n/a",'Balance Sheet'!D9/'Balance Sheet'!D15) -> 1.1443711
A23: Return on equity (product of the three) | B23: =IF(AND(ISNUMBER(B20),ISNUMBER(B21),ISNUMBER(B22)),B20*B21*B22,"n/a") -> 0.62511847 | C23: =IF(AND(ISNUMBER(C20),ISNUMBER(C21),ISNUMBER(C22)),C20*C21*C22,"n/a") -> 0.46271227 | D23: =IF(AND(ISNUMBER(D20),ISNUMBER(D21),ISNUMBER(D22)),D20*D21*D22,"n/a") -> 0.3619999
A24: Check: product − return on equity (must be 0) | B24: =IF(AND(ISNUMBER(B23),ISNUMBER(B16)),B23-B16,IF(ISNUMBER(B23),1,IF(AND(ISNUMBER(B16),ISNUMBER(B20),ISNUMBER(B21)),1,0))) -> 0 | C24: =IF(AND(ISNUMBER(C23),ISNUMBER(C16)),C23-C16,IF(ISNUMBER(C23),1,IF(AND(ISNUMBER(C16),ISNUMBER(C20),ISNUMBER(C21)),1,0))) -> 0 | D24: =IF(AND(ISNUMBER(D23),ISNUMBER(D16)),D23-D16,IF(ISNUMBER(D23),1,IF(AND(ISNUMBER(D16),ISNUMBER(D20),ISNUMBER(D21)),1,0))) -> 0
A26: Bakery metrics ($'000; per-unit rows in $)
A27: Year # | B27: 1 | C27: 2 | D27: 3
B28: Year 1 | C28: Year 2 | D28: Year 3 | E28: Target
A29: Opening days in the year | B29: =SUMIF(Monthly!$C$5:$AL$5,B$27,Monthly!$C$11:$AL$11) -> 312 | C29: =SUMIF(Monthly!$C$5:$AL$5,C$27,Monthly!$C$11:$AL$11) -> 312 | D29: =SUMIF(Monthly!$C$5:$AL$5,D$27,Monthly!$C$11:$AL$11) -> 312
A30: Retail transactions | B30: =SUMIF(Monthly!$C$5:$AL$5,B$27,Monthly!$C$12:$AL$12) -> 98641.92 | C30: =SUMIF(Monthly!$C$5:$AL$5,C$27,Monthly!$C$12:$AL$12) -> 102835.2 | D30: =SUMIF(Monthly!$C$5:$AL$5,D$27,Monthly!$C$12:$AL$12) -> 105920.26
A31: Customers per day (average) | B31: =IF(B29=0,0,B30/B29) -> 316.16 | C31: =IF(C29=0,0,C30/C29) -> 329.6 | D31: =IF(D29=0,0,D30/D29) -> 339.488
A32: Average ticket ($) | B32: =IF(B30=0,0,B35/B30) -> 11.5 | C32: =IF(C30=0,0,C35/C30) -> 11.845 | D32: =IF(D30=0,0,D35/D30) -> 12.20035
A33: Wholesale accounts (year end) | B33: =INDEX(Monthly!$C$17:$AL$17,B$27*12) -> 16 | C33: =INDEX(Monthly!$C$17:$AL$17,C$27*12) -> 17.92 | D33: =INDEX(Monthly!$C$17:$AL$17,D$27*12) -> 20.0704
A34: Revenue | B34: =SUMIF(Monthly!$C$5:$AL$5,B$27,Monthly!$C$22:$AL$22) -> 1578046.1 | C34: =SUMIF(Monthly!$C$5:$AL$5,C$27,Monthly!$C$22:$AL$22) -> 1736372.4 | D34: =SUMIF(Monthly!$C$5:$AL$5,D$27,Monthly!$C$22:$AL$22) -> 1890162.9
A35: Retail counter revenue | B35: =SUMIF(Monthly!$C$5:$AL$5,B$27,Monthly!$C$14:$AL$14) -> 1134382.1 | C35: =SUMIF(Monthly!$C$5:$AL$5,C$27,Monthly!$C$14:$AL$14) -> 1218082.9 | D35: =SUMIF(Monthly!$C$5:$AL$5,D$27,Monthly!$C$14:$AL$14) -> 1292264.2
A36: Wholesale revenue | B36: =SUMIF(Monthly!$C$5:$AL$5,B$27,Monthly!$C$19:$AL$19) -> 443664 | C36: =SUMIF(Monthly!$C$5:$AL$5,C$27,Monthly!$C$19:$AL$19) -> 518289.41 | D36: =SUMIF(Monthly!$C$5:$AL$5,D$27,Monthly!$C$19:$AL$19) -> 597898.66
A37: Wholesale share of revenue | B37: =IF(B34=0,0,B36/B34) -> 0.28114768 | C37: =IF(C34=0,0,C36/C34) -> 0.29848978 | D37: =IF(D34=0,0,D36/D34) -> 0.31632124
A38: Retail revenue per opening day ($) | B38: =IF(B29=0,0,B35/B29) -> 3635.84 | C38: =IF(C29=0,0,C35/C29) -> 3904.112 | D38: =IF(D29=0,0,D35/D29) -> 4141.8724
A39: Waste cost (unsold retail production) | B39: =-SUMIF(Monthly!$C$5:$AL$5,B$27,Monthly!$C$26:$AL$26) -> 26925.992 | C39: =-SUMIF(Monthly!$C$5:$AL$5,C$27,Monthly!$C$26:$AL$26) -> 28912.738 | D39: =-SUMIF(Monthly!$C$5:$AL$5,D$27,Monthly!$C$26:$AL$26) -> 30673.524
A40: Waste cost, % of retail revenue | B40: =IF(B35=0,0,B39/B35) -> 0.023736264 | C40: =IF(C35=0,0,C39/C35) -> 0.023736264 | D40: =IF(D35=0,0,D39/D35) -> 0.023736264
A41: Wholesale delivery cost | B41: =-SUMIF(Monthly!$C$5:$AL$5,B$27,Monthly!$C$35:$AL$35) -> 36972 | C41: =-SUMIF(Monthly!$C$5:$AL$5,C$27,Monthly!$C$35:$AL$35) -> 41932.8 | D41: =-SUMIF(Monthly!$C$5:$AL$5,D$27,Monthly!$C$35:$AL$35) -> 46964.736
A42: Gross profit | B42: =SUMIF(Monthly!$C$5:$AL$5,B$27,Monthly!$C$29:$AL$29) -> 1077227.7 | C42: =SUMIF(Monthly!$C$5:$AL$5,C$27,Monthly!$C$29:$AL$29) -> 1183311.2 | D42: =SUMIF(Monthly!$C$5:$AL$5,D$27,Monthly!$C$29:$AL$29) -> 1285883.7
A43: Gross margin | B43: =IF(B34=0,0,B42/B34) -> 0.68263384 | C43: =IF(C34=0,0,C42/C34) -> 0.68148469 | D43: =IF(D34=0,0,D42/D34) -> 0.68030311
A44: Cost of sales | B44: =-SUMIF(Monthly!$C$5:$AL$5,B$27,Monthly!$C$28:$AL$28) -> 500818.42 | C44: =-SUMIF(Monthly!$C$5:$AL$5,C$27,Monthly!$C$28:$AL$28) -> 553061.18 | D44: =-SUMIF(Monthly!$C$5:$AL$5,D$27,Monthly!$C$28:$AL$28) -> 604279.19
A45: Payroll | B45: =-SUMIF(Monthly!$C$5:$AL$5,B$27,Monthly!$C$32:$AL$32) -> 593600 | C45: =-SUMIF(Monthly!$C$5:$AL$5,C$27,Monthly!$C$32:$AL$32) -> 641655.39 | D45: =-SUMIF(Monthly!$C$5:$AL$5,D$27,Monthly!$C$32:$AL$32) -> 693929.16
A46: Prime cost (cost of sales + payroll) % of revenue | B46: =IF(B34=0,0,(B44+B45)/B34) -> 0.69352755 | C46: =IF(C34=0,0,(C44+C45)/C34) -> 0.68805321 | D46: =IF(D34=0,0,(D44+D45)/D34) -> 0.68682354
A47: EBITDA | B47: =SUMIF(Monthly!$C$5:$AL$5,B$27,Monthly!$C$41:$AL$41) -> 145732.04 | C47: =SUMIF(Monthly!$C$5:$AL$5,C$27,Monthly!$C$41:$AL$41) -> 193289.21 | D47: =SUMIF(Monthly!$C$5:$AL$5,D$27,Monthly!$C$41:$AL$41) -> 233403.12
A48: EBITDA margin | B48: =IF(B34=0,0,B47/B34) -> 0.092349671 | C48: =IF(C34=0,0,C47/C34) -> 0.11131783 | D48: =IF(D34=0,0,D47/D34) -> 0.12348307

Sheet Inputs
A1: Inputs — Low / Base / High | I1: =HYPERLINK("#'Cover'!A1","◂ Contents") -> ◂ Contents
A2: Illustrative assumptions — replace them with your own numbers.
A5: Driver | B5: Low | C5: Base | D5: High | E5: Active | F5: Unit | G5: Source / comment
A6: Retail counter
A7: Customers per day at full traffic | B7: 300 | C7: 320 | D7: 340 | E7: =CHOOSE(Dashboard!$B$4,B7,C7,D7) -> 320 | F7: # | G7: Low ≤ Base ≤ High
A8: Months to reach full traffic | B8: 3 | C8: 2 | D8: 1 | E8: =CHOOSE(Dashboard!$B$4,B8,C8,D8) -> 2 | F8: months | G8: Low ≥ Base ≥ High (lower is better)
A9: Opening traffic, % of full | B9: 0.85 | C9: 0.9 | D9: 0.95 | E9: =CHOOSE(Dashboard!$B$4,B9,C9,D9) -> 0.9 | F9: % | G9: Low ≤ Base ≤ High
A10: Traffic growth per year (after year 1) | B10: 0.01 | C10: 0.03 | D10: 0.05 | E10: =CHOOSE(Dashboard!$B$4,B10,C10,D10) -> 0.03 | F10: % | G10: Low ≤ Base ≤ High
A11: Average ticket per customer (year 1) | B11: 11 | C11: 11.5 | D11: 12 | E11: =CHOOSE(Dashboard!$B$4,B11,C11,D11) -> 11.5 | F11: $ | G11: Low ≤ Base ≤ High
A12: Price increase per year | B12: 0.02 | C12: 0.03 | D12: 0.04 | E12: =CHOOSE(Dashboard!$B$4,B12,C12,D12) -> 0.03 | F12: % | G12: Low ≤ Base ≤ High
A13: Opening days per week | B13: 6 | C13: 6 | D13: 6 | E13: =CHOOSE(Dashboard!$B$4,B13,C13,D13) -> 6 | F13: days
A14: Holiday uplift, Nov-Dec (monthly models) | B14: 0.2 | C14: 0.2 | D14: 0.2 | E14: =CHOOSE(Dashboard!$B$4,B14,C14,D14) -> 0.2 | F14: %
A16: Wholesale
A17: Wholesale accounts at full ramp (year 1) | B17: 13 | C17: 16 | D17: 19 | E17: =CHOOSE(Dashboard!$B$4,B17,C17,D17) -> 16 | F17: # | G17: Low ≤ Base ≤ High
A18: Wholesale accounts growth per year | B18: 0.08 | C18: 0.12 | D18: 0.16 | E18: =CHOOSE(Dashboard!$B$4,B18,C18,D18) -> 0.12 | F18: % | G18: Low ≤ Base ≤ High
A19: Order value per account per week (year 1) | B19: 500 | C19: 540 | D19: 580 | E19: =CHOOSE(Dashboard!$B$4,B19,C19,D19) -> 540 | F19: $ | G19: Low ≤ Base ≤ High
A20: Deliveries per account per week | B20: 5 | C20: 5 | D20: 5 | E20: =CHOOSE(Dashboard!$B$4,B20,C20,D20) -> 5 | F20: #
A21: Delivery cost per drop (driver, fuel, van) | B21: 9.5 | C21: 9 | D21: 8.5 | E21: =CHOOSE(Dashboard!$B$4,B21,C21,D21) -> 9 | F21: $ | G21: Low ≥ Base ≥ High (lower is better)
A23: Cost of sales
A24: Ingredients, % of retail sales | B24: 0.255 | C24: 0.24 | D24: 0.225 | E24: =CHOOSE(Dashboard!$B$4,B24,C24,D24) -> 0.24 | F24: % | G24: Low ≥ Base ≥ High (lower is better)
A25: Ingredients, % of wholesale sales | B25: 0.345 | C25: 0.33 | D25: 0.315 | E25: =CHOOSE(Dashboard!$B$4,B25,C25,D25) -> 0.33 | F25: % | G25: Low ≥ Base ≥ High (lower is better)
A26: Retail production baked but not sold (waste) | B26: 0.11 | C26: 0.09 | D26: 0.07 | E26: =CHOOSE(Dashboard!$B$4,B26,C26,D26) -> 0.09 | F26: % | G26: Low ≥ Base ≥ High (lower is better)
A27: Packaging, % of sales | B27: 0.037 | C27: 0.035 | D27: 0.033 | E27: =CHOOSE(Dashboard!$B$4,B27,C27,D27) -> 0.035 | F27: % | G27: Low ≥ Base ≥ High (lower is better)
A29: Operating costs
A30: Rent per month | B30: 12000 | C30: 12000 | D30: 12000 | E30: =CHOOSE(Dashboard!$B$4,B30,C30,D30) -> 12000 | F30: $
A31: Utilities per month (gas, power, water) | B31: 4000 | C31: 4000 | D31: 4000 | E31: =CHOOSE(Dashboard!$B$4,B31,C31,D31) -> 4000 | F31: $
A32: Equipment repairs & cleaning per month | B32: 1000 | C32: 1000 | D32: 1000 | E32: =CHOOSE(Dashboard!$B$4,B32,C32,D32) -> 1000 | F32: $
A33: Marketing, % of revenue | B33: 0.022 | C33: 0.02 | D33: 0.018 | E33: =CHOOSE(Dashboard!$B$4,B33,C33,D33) -> 0.02 | F33: % | G33: Low ≥ Base ≥ High (lower is better)
A34: Card processing fees, % of retail sales | B34: 0.029 | C34: 0.028 | D34: 0.027 | E34: =CHOOSE(Dashboard!$B$4,B34,C34,D34) -> 0.028 | F34: % | G34: Low ≥ Base ≥ High (lower is better)
A35: Insurance, licences & other G&A per month | B35: 2800 | C35: 2800 | D35: 2800 | E35: =CHOOSE(Dashboard!$B$4,B35,C35,D35) -> 2800 | F35: $
A37: Equipment
A38: Fit-out & equipment: ovens, mixers, cases | B38: 90000 | C38: 90000 | D38: 90000 | E38: =CHOOSE(Dashboard!$B$4,B38,C38,D38) -> 90000 | F38: $
A39: Equipment replacement per year (from year 2) | B39: 14000 | C39: 14000 | D39: 14000 | E39: =CHOOSE(Dashboard!$B$4,B39,C39,D39) -> 14000 | F39: $
A41: Headcount
A42: Bakers & production: headcount (FTE) | B42: 5 | C42: 5 | D42: 5 | E42: =CHOOSE(Dashboard!$B$4,B42,C42,D42) -> 5 | F42: FTE | G42: Low ≤ Base ≤ High
A43: Bakers & production: salary per FTE per year | B43: 44000 | C43: 44000 | D43: 44000 | E43: =CHOOSE(Dashboard!$B$4,B43,C43,D43) -> 44000 | F43: $
A44: Bakers & production: headcount growth per year | B44: 0.06 | C44: 0.06 | D44: 0.06 | E44: =CHOOSE(Dashboard!$B$4,B44,C44,D44) -> 0.06 | F44: % | G44: Low ≤ Base ≤ High
A45: Bakers & production: first month on payroll | B45: 1 | C45: 1 | D45: 1 | E45: =CHOOSE(Dashboard!$B$4,B45,C45,D45) -> 1 | F45: month #
A46: Counter staff: headcount (FTE) | B46: 7 | C46: 7 | D46: 7 | E46: =CHOOSE(Dashboard!$B$4,B46,C46,D46) -> 7 | F46: FTE | G46: Low ≤ Base ≤ High
A47: Counter staff: salary per FTE per year | B47: 31000 | C47: 31000 | D47: 31000 | E47: =CHOOSE(Dashboard!$B$4,B47,C47,D47) -> 31000 | F47: $
A48: Counter staff: headcount growth per year | B48: 0.06 | C48: 0.06 | D48: 0.06 | E48: =CHOOSE(Dashboard!$B$4,B48,C48,D48) -> 0.06 | F48: % | G48: Low ≤ Base ≤ High
A49: Counter staff: first month on payroll | B49: 1 | C49: 1 | D49: 1 | E49: =CHOOSE(Dashboard!$B$4,B49,C49,D49) -> 1 | F49: month #
A50: Manager: headcount (FTE) | B50: 1.5 | C50: 1.5 | D50: 1.5 | E50: =CHOOSE(Dashboard!$B$4,B50,C50,D50) -> 1.5 | F50: FTE | G50: Low ≤ Base ≤ High
A51: Manager: salary per FTE per year | B51: 62000 | C51: 62000 | D51: 62000 | E51: =CHOOSE(Dashboard!$B$4,B51,C51,D51) -> 62000 | F51: $
A52: Manager: headcount growth per year | B52: 0 | C52: 0 | D52: 0 | E52: =CHOOSE(Dashboard!$B$4,B52,C52,D52) -> 0 | F52: % | G52: Low ≤ Base ≤ High
A53: Manager: first month on payroll | B53: 1 | C53: 1 | D53: 1 | E53: =CHOOSE(Dashboard!$B$4,B53,C53,D53) -> 1 | F53: month #
A54: Payroll taxes & benefits, % of salary | B54: 0.12 | C54: 0.12 | D54: 0.12 | E54: =CHOOSE(Dashboard!$B$4,B54,C54,D54) -> 0.12 | F54: %
A55: Wage growth per year | B55: 0.03 | C55: 0.03 | D55: 0.03 | E55: =CHOOSE(Dashboard!$B$4,B55,C55,D55) -> 0.03 | F55: %
A57: Funding
A58: Equity raised at start | B58: 60000 | C58: 60000 | D58: 60000 | E58: =CHOOSE(Dashboard!$B$4,B58,C58,D58) -> 60000 | F58: $
A59: Loan drawn at start | B59: 80000 | C59: 80000 | D59: 80000 | E59: =CHOOSE(Dashboard!$B$4,B59,C59,D59) -> 80000 | F59: $
A60: Loan interest rate per year | B60: 0.085 | C60: 0.085 | D60: 0.085 | E60: =CHOOSE(Dashboard!$B$4,B60,C60,D60) -> 0.085 | F60: %
A61: Loan repayment term | B61: 5 | C61: 5 | D61: 5 | E61: =CHOOSE(Dashboard!$B$4,B61,C61,D61) -> 5 | F61: years
A63: Working capital
A64: Customer payment terms (receivable days) | B64: 7 | C64: 7 | D64: 7 | E64: =CHOOSE(Dashboard!$B$4,B64,C64,D64) -> 7 | F64: days
A65: Inventory held (days of COGS) | B65: 3 | C65: 3 | D65: 3 | E65: =CHOOSE(Dashboard!$B$4,B65,C65,D65) -> 3 | F65: days
A66: Supplier payment terms (payable days) | B66: 18 | C66: 18 | D66: 18 | E66: =CHOOSE(Dashboard!$B$4,B66,C66,D66) -> 18 | F66: days
A68: Tax & depreciation
A69: Depreciation period for capex | B69: 7 | C69: 7 | D69: 7 | E69: =CHOOSE(Dashboard!$B$4,B69,C69,D69) -> 7 | F69: years
A70: Income tax rate | B70: 0.21 | C70: 0.21 | D70: 0.21 | E70: =CHOOSE(Dashboard!$B$4,B70,C70,D70) -> 0.21 | F70: %
A72: Break-even & funding
A73: Minimum cash buffer to keep | B73: 233000 | C73: 233000 | D73: 233000 | E73: =CHOOSE(Dashboard!$B$4,B73,C73,D73) -> 233000 | F73: $ | G73: About 3 months of costs
A75: Valuation
A76: Discount rate (WACC) | B76: 0.2 | C76: 0.16 | D76: 0.13 | E76: =CHOOSE(Dashboard!$B$4,B76,C76,D76) -> 0.16 | F76: % | G76: Low ≥ Base ≥ High (lower is better)
A77: Terminal growth rate (perpetuity) | B77: 0.01 | C77: 0.02 | D77: 0.03 | E77: =CHOOSE(Dashboard!$B$4,B77,C77,D77) -> 0.02 | F77: % | G77: Low ≤ Base ≤ High
A78: Exit multiple (EV ÷ final-year EBITDA) | B78: 4 | C78: 5.5 | D78: 7 | E78: =CHOOSE(Dashboard!$B$4,B78,C78,D78) -> 5.5 | F78: x | G78: Low ≤ Base ≤ High
A79: Sensitivity table: WACC step | B79: 0.01 | C79: 0.01 | D79: 0.01 | E79: =CHOOSE(Dashboard!$B$4,B79,C79,D79) -> 0.01 | F79: %
A80: Sensitivity table: growth step | B80: 0.005 | C80: 0.005 | D80: 0.005 | E80: =CHOOSE(Dashboard!$B$4,B80,C80,D80) -> 0.005 | F80: %
A82: Legend: yellow cell with blue figure = input you can change · black = formula · green = link to another sheet · grey = active value (column E follows the scenario on the Dashboard).

Sheet P&L
A1: Annual profit & loss | F1: =HYPERLINK("#'Cover'!A1","◂ Contents") -> ◂ Contents
A2: Rolled up from the period detail (SUMIF on the year row; balances at year end).
A3: Year # | B3: 1 | C3: 2 | D3: 3
B4: Year 1 | C4: Year 2 | D4: Year 3
A5: Revenue | B5: =SUMIF(Monthly!$C$5:$AL$5,B$3,Monthly!$C$22:$AL$22) -> 1578046.1 | C5: =SUMIF(Monthly!$C$5:$AL$5,C$3,Monthly!$C$22:$AL$22) -> 1736372.4 | D5: =SUMIF(Monthly!$C$5:$AL$5,D$3,Monthly!$C$22:$AL$22) -> 1890162.9
A6: Cost of sales | B6: =SUMIF(Monthly!$C$5:$AL$5,B$3,Monthly!$C$28:$AL$28) -> -500818.42 | C6: =SUMIF(Monthly!$C$5:$AL$5,C$3,Monthly!$C$28:$AL$28) -> -553061.18 | D6: =SUMIF(Monthly!$C$5:$AL$5,D$3,Monthly!$C$28:$AL$28) -> -604279.19
A7: Gross profit | B7: =SUMIF(Monthly!$C$5:$AL$5,B$3,Monthly!$C$29:$AL$29) -> 1077227.7 | C7: =SUMIF(Monthly!$C$5:$AL$5,C$3,Monthly!$C$29:$AL$29) -> 1183311.2 | D7: =SUMIF(Monthly!$C$5:$AL$5,D$3,Monthly!$C$29:$AL$29) -> 1285883.7
A8: Gross margin | B8: =IF(B5=0,0,B7/B5) -> 0.68263384 | C8: =IF(C5=0,0,C7/C5) -> 0.68148469 | D8: =IF(D5=0,0,D7/D5) -> 0.68030311
A9: Payroll (bakers, counter, manager) | B9: =SUMIF(Monthly!$C$5:$AL$5,B$3,Monthly!$C$32:$AL$32) -> -593600 | C9: =SUMIF(Monthly!$C$5:$AL$5,C$3,Monthly!$C$32:$AL$32) -> -641655.39 | D9: =SUMIF(Monthly!$C$5:$AL$5,D$3,Monthly!$C$32:$AL$32) -> -693929.16
A10: Rent | B10: =SUMIF(Monthly!$C$5:$AL$5,B$3,Monthly!$C$33:$AL$33) -> -144000 | C10: =SUMIF(Monthly!$C$5:$AL$5,C$3,Monthly!$C$33:$AL$33) -> -144000 | D10: =SUMIF(Monthly!$C$5:$AL$5,D$3,Monthly!$C$33:$AL$33) -> -144000
A11: Utilities (ovens) | B11: =SUMIF(Monthly!$C$5:$AL$5,B$3,Monthly!$C$34:$AL$34) -> -48000 | C11: =SUMIF(Monthly!$C$5:$AL$5,C$3,Monthly!$C$34:$AL$34) -> -48000 | D11: =SUMIF(Monthly!$C$5:$AL$5,D$3,Monthly!$C$34:$AL$34) -> -48000
A12: Wholesale delivery | B12: =SUMIF(Monthly!$C$5:$AL$5,B$3,Monthly!$C$35:$AL$35) -> -36972 | C12: =SUMIF(Monthly!$C$5:$AL$5,C$3,Monthly!$C$35:$AL$35) -> -41932.8 | D12: =SUMIF(Monthly!$C$5:$AL$5,D$3,Monthly!$C$35:$AL$35) -> -46964.736
A13: Equipment repairs & cleaning | B13: =SUMIF(Monthly!$C$5:$AL$5,B$3,Monthly!$C$36:$AL$36) -> -12000 | C13: =SUMIF(Monthly!$C$5:$AL$5,C$3,Monthly!$C$36:$AL$36) -> -12000 | D13: =SUMIF(Monthly!$C$5:$AL$5,D$3,Monthly!$C$36:$AL$36) -> -12000
A14: Marketing | B14: =SUMIF(Monthly!$C$5:$AL$5,B$3,Monthly!$C$37:$AL$37) -> -31560.922 | C14: =SUMIF(Monthly!$C$5:$AL$5,C$3,Monthly!$C$37:$AL$37) -> -34727.447 | D14: =SUMIF(Monthly!$C$5:$AL$5,D$3,Monthly!$C$37:$AL$37) -> -37803.257
A15: Card processing fees | B15: =SUMIF(Monthly!$C$5:$AL$5,B$3,Monthly!$C$38:$AL$38) -> -31762.698 | C15: =SUMIF(Monthly!$C$5:$AL$5,C$3,Monthly!$C$38:$AL$38) -> -34106.322 | D15: =SUMIF(Monthly!$C$5:$AL$5,D$3,Monthly!$C$38:$AL$38) -> -36183.397
A16: Insurance, licences & other G&A | B16: =SUMIF(Monthly!$C$5:$AL$5,B$3,Monthly!$C$39:$AL$39) -> -33600 | C16: =SUMIF(Monthly!$C$5:$AL$5,C$3,Monthly!$C$39:$AL$39) -> -33600 | D16: =SUMIF(Monthly!$C$5:$AL$5,D$3,Monthly!$C$39:$AL$39) -> -33600
A17: Total operating expenses | B17: =SUMIF(Monthly!$C$5:$AL$5,B$3,Monthly!$C$40:$AL$40) -> -931495.62 | C17: =SUMIF(Monthly!$C$5:$AL$5,C$3,Monthly!$C$40:$AL$40) -> -990021.96 | D17: =SUMIF(Monthly!$C$5:$AL$5,D$3,Monthly!$C$40:$AL$40) -> -1052480.5
A18: EBITDA | B18: =SUMIF(Monthly!$C$5:$AL$5,B$3,Monthly!$C$41:$AL$41) -> 145732.04 | C18: =SUMIF(Monthly!$C$5:$AL$5,C$3,Monthly!$C$41:$AL$41) -> 193289.21 | D18: =SUMIF(Monthly!$C$5:$AL$5,D$3,Monthly!$C$41:$AL$41) -> 233403.12
A19: EBITDA margin | B19: =IF(B5=0,0,B18/B5) -> 0.092349671 | C19: =IF(C5=0,0,C18/C5) -> 0.11131783 | D19: =IF(D5=0,0,D18/D5) -> 0.12348307
A20: Depreciation | B20: =SUMIF(Monthly!$C$5:$AL$5,B$3,Monthly!$C$55:$AL$55) -> -12857.143 | C20: =SUMIF(Monthly!$C$5:$AL$5,C$3,Monthly!$C$55:$AL$55) -> -13940.476 | D20: =SUMIF(Monthly!$C$5:$AL$5,D$3,Monthly!$C$55:$AL$55) -> -15940.476
A21: EBIT | B21: =SUMIF(Monthly!$C$5:$AL$5,B$3,Monthly!$C$44:$AL$44) -> 132874.89 | C21: =SUMIF(Monthly!$C$5:$AL$5,C$3,Monthly!$C$44:$AL$44) -> 179348.73 | D21: =SUMIF(Monthly!$C$5:$AL$5,D$3,Monthly!$C$44:$AL$44) -> 217462.64
A22: Interest | B22: =SUMIF(Monthly!$C$5:$AL$5,B$3,Monthly!$C$45:$AL$45) -> -6228.6111 | C22: =SUMIF(Monthly!$C$5:$AL$5,C$3,Monthly!$C$45:$AL$45) -> -4873.3333 | D22: =SUMIF(Monthly!$C$5:$AL$5,D$3,Monthly!$C$45:$AL$45) -> -3513.3333
A23: Pre-tax income | B23: =SUMIF(Monthly!$C$5:$AL$5,B$3,Monthly!$C$46:$AL$46) -> 126646.28 | C23: =SUMIF(Monthly!$C$5:$AL$5,C$3,Monthly!$C$46:$AL$46) -> 174475.4 | D23: =SUMIF(Monthly!$C$5:$AL$5,D$3,Monthly!$C$46:$AL$46) -> 213949.31
A24: Income tax | B24: =SUMIF(Monthly!$C$5:$AL$5,B$3,Monthly!$C$49:$AL$49) -> -26595.719 | C24: =SUMIF(Monthly!$C$5:$AL$5,C$3,Monthly!$C$49:$AL$49) -> -36639.834 | D24: =SUMIF(Monthly!$C$5:$AL$5,D$3,Monthly!$C$49:$AL$49) -> -44929.355
A25: Net income | B25: =SUMIF(Monthly!$C$5:$AL$5,B$3,Monthly!$C$50:$AL$50) -> 100050.56 | C25: =SUMIF(Monthly!$C$5:$AL$5,C$3,Monthly!$C$50:$AL$50) -> 137835.57 | D25: =SUMIF(Monthly!$C$5:$AL$5,D$3,Monthly!$C$50:$AL$50) -> 169019.96
A26: Net margin | B26: =IF(B5=0,0,B25/B5) -> 0.063401547 | C26: =IF(C5=0,0,C25/C5) -> 0.079381341 | D26: =IF(D5=0,0,D25/D5) -> 0.089420843

Sheet Cash Flow
A1: Annual cash flow statement | F1: =HYPERLINK("#'Cover'!A1","◂ Contents") -> ◂ Contents
A2: Rolled up from the period detail (SUMIF on the year row; balances at year end).
A3: Year # | B3: 1 | C3: 2 | D3: 3
B4: Year 1 | C4: Year 2 | D4: Year 3
A5: Net income | B5: =SUMIF(Monthly!$C$5:$AL$5,B$3,Monthly!$C$50:$AL$50) -> 100050.56 | C5: =SUMIF(Monthly!$C$5:$AL$5,C$3,Monthly!$C$50:$AL$50) -> 137835.57 | D5: =SUMIF(Monthly!$C$5:$AL$5,D$3,Monthly!$C$50:$AL$50) -> 169019.96
A6: Add back depreciation | B6: =-SUMIF(Monthly!$C$5:$AL$5,B$3,Monthly!$C$55:$AL$55) -> 12857.143 | C6: =-SUMIF(Monthly!$C$5:$AL$5,C$3,Monthly!$C$55:$AL$55) -> 13940.476 | D6: =-SUMIF(Monthly!$C$5:$AL$5,D$3,Monthly!$C$55:$AL$55) -> 15940.476
A7: (Increase) / decrease in receivables | B7: =SUMIF(Monthly!$C$5:$AL$5,B$3,Monthly!$C$69:$AL$69) -> -35526.4 | C7: =SUMIF(Monthly!$C$5:$AL$5,C$3,Monthly!$C$69:$AL$69) -> -2973.385 | D7: =SUMIF(Monthly!$C$5:$AL$5,D$3,Monthly!$C$69:$AL$69) -> -3278.8536
A8: (Increase) / decrease in inventory | B8: =SUMIF(Monthly!$C$5:$AL$5,B$3,Monthly!$C$70:$AL$70) -> -4796.5303 | C8: =SUMIF(Monthly!$C$5:$AL$5,C$3,Monthly!$C$70:$AL$70) -> -418.78881 | D8: =SUMIF(Monthly!$C$5:$AL$5,D$3,Monthly!$C$70:$AL$70) -> -463.75111
A9: Increase / (decrease) in payables | B9: =SUMIF(Monthly!$C$5:$AL$5,B$3,Monthly!$C$71:$AL$71) -> 28779.182 | C9: =SUMIF(Monthly!$C$5:$AL$5,C$3,Monthly!$C$71:$AL$71) -> 2512.7328 | D9: =SUMIF(Monthly!$C$5:$AL$5,D$3,Monthly!$C$71:$AL$71) -> 2782.5067
A10: Operating cash flow | B10: =SUMIF(Monthly!$C$5:$AL$5,B$3,Monthly!$C$74:$AL$74) -> 101363.96 | C10: =SUMIF(Monthly!$C$5:$AL$5,C$3,Monthly!$C$74:$AL$74) -> 150896.6 | D10: =SUMIF(Monthly!$C$5:$AL$5,D$3,Monthly!$C$74:$AL$74) -> 184000.33
A11: Capital spending | B11: =SUMIF(Monthly!$C$5:$AL$5,B$3,Monthly!$C$75:$AL$75) -> -90000 | C11: =SUMIF(Monthly!$C$5:$AL$5,C$3,Monthly!$C$75:$AL$75) -> -14000 | D11: =SUMIF(Monthly!$C$5:$AL$5,D$3,Monthly!$C$75:$AL$75) -> -14000
A12: Equity raised | B12: =SUMIF(Monthly!$C$5:$AL$5,B$3,Monthly!$C$76:$AL$76) -> 60000 | C12: =SUMIF(Monthly!$C$5:$AL$5,C$3,Monthly!$C$76:$AL$76) -> 0 | D12: =SUMIF(Monthly!$C$5:$AL$5,D$3,Monthly!$C$76:$AL$76) -> 0
A13: Loan drawdown | B13: =SUMIF(Monthly!$C$5:$AL$5,B$3,Monthly!$C$61:$AL$61) -> 80000 | C13: =SUMIF(Monthly!$C$5:$AL$5,C$3,Monthly!$C$61:$AL$61) -> 0 | D13: =SUMIF(Monthly!$C$5:$AL$5,D$3,Monthly!$C$61:$AL$61) -> 0
A14: Loan repayment | B14: =SUMIF(Monthly!$C$5:$AL$5,B$3,Monthly!$C$62:$AL$62) -> -14666.667 | C14: =SUMIF(Monthly!$C$5:$AL$5,C$3,Monthly!$C$62:$AL$62) -> -16000 | D14: =SUMIF(Monthly!$C$5:$AL$5,D$3,Monthly!$C$62:$AL$62) -> -16000
A15: Financing cash flow | B15: =SUMIF(Monthly!$C$5:$AL$5,B$3,Monthly!$C$77:$AL$77) -> 125333.33 | C15: =SUMIF(Monthly!$C$5:$AL$5,C$3,Monthly!$C$77:$AL$77) -> -16000 | D15: =SUMIF(Monthly!$C$5:$AL$5,D$3,Monthly!$C$77:$AL$77) -> -16000
A16: Net change in cash | B16: =SUMIF(Monthly!$C$5:$AL$5,B$3,Monthly!$C$78:$AL$78) -> 136697.29 | C16: =SUMIF(Monthly!$C$5:$AL$5,C$3,Monthly!$C$78:$AL$78) -> 120896.6 | D16: =SUMIF(Monthly!$C$5:$AL$5,D$3,Monthly!$C$78:$AL$78) -> 154000.33
A17: Opening cash | B17: =INDEX(Monthly!$C$79:$AL$79,(B$3-1)*12+1) -> 0 | C17: =INDEX(Monthly!$C$79:$AL$79,(C$3-1)*12+1) -> 136697.29 | D17: =INDEX(Monthly!$C$79:$AL$79,(D$3-1)*12+1) -> 257593.89
A18: Closing cash | B18: =INDEX(Monthly!$C$80:$AL$80,B$3*12) -> 136697.29 | C18: =INDEX(Monthly!$C$80:$AL$80,C$3*12) -> 257593.89 | D18: =INDEX(Monthly!$C$80:$AL$80,D$3*12) -> 411594.23

Sheet Balance Sheet
A1: Balance sheet at year end | F1: =HYPERLINK("#'Cover'!A1","◂ Contents") -> ◂ Contents
A2: Rolled up from the period detail (SUMIF on the year row; balances at year end).
A3: Year # | B3: 1 | C3: 2 | D3: 3
B4: Year 1 | C4: Year 2 | D4: Year 3
A5: Cash | B5: =INDEX(Monthly!$C$80:$AL$80,B$3*12) -> 136697.29 | C5: =INDEX(Monthly!$C$80:$AL$80,C$3*12) -> 257593.89 | D5: =INDEX(Monthly!$C$80:$AL$80,D$3*12) -> 411594.23
A6: Accounts receivable | B6: =INDEX(Monthly!$C$66:$AL$66,B$3*12) -> 35526.4 | C6: =INDEX(Monthly!$C$66:$AL$66,C$3*12) -> 38499.785 | D6: =INDEX(Monthly!$C$66:$AL$66,D$3*12) -> 41778.639
A7: Inventory | B7: =INDEX(Monthly!$C$67:$AL$67,B$3*12) -> 4796.5303 | C7: =INDEX(Monthly!$C$67:$AL$67,C$3*12) -> 5215.3191 | D7: =INDEX(Monthly!$C$67:$AL$67,D$3*12) -> 5679.0702
A8: Net fixed assets | B8: =INDEX(Monthly!$C$57:$AL$57,B$3*12) -> 77142.857 | C8: =INDEX(Monthly!$C$57:$AL$57,C$3*12) -> 77202.381 | D8: =INDEX(Monthly!$C$57:$AL$57,D$3*12) -> 75261.905
A9: Total assets | B9: =INDEX(Monthly!$C$94:$AL$94,B$3*12) -> 254163.08 | C9: =INDEX(Monthly!$C$94:$AL$94,C$3*12) -> 378511.38 | D9: =INDEX(Monthly!$C$94:$AL$94,D$3*12) -> 534313.84
A10: Accounts payable | B10: =INDEX(Monthly!$C$68:$AL$68,B$3*12) -> 28779.182 | C10: =INDEX(Monthly!$C$68:$AL$68,C$3*12) -> 31291.915 | D10: =INDEX(Monthly!$C$68:$AL$68,D$3*12) -> 34074.421
A11: Loan | B11: =INDEX(Monthly!$C$63:$AL$63,B$3*12) -> 65333.333 | C11: =INDEX(Monthly!$C$63:$AL$63,C$3*12) -> 49333.333 | D11: =INDEX(Monthly!$C$63:$AL$63,D$3*12) -> 33333.333
A12: Total liabilities | B12: =INDEX(Monthly!$C$95:$AL$95,B$3*12) -> 94112.515 | C12: =INDEX(Monthly!$C$95:$AL$95,C$3*12) -> 80625.248 | D12: =INDEX(Monthly!$C$95:$AL$95,D$3*12) -> 67407.755
A13: Paid-in capital | B13: =INDEX(Monthly!$C$92:$AL$92,B$3*12) -> 60000 | C13: =INDEX(Monthly!$C$92:$AL$92,C$3*12) -> 60000 | D13: =INDEX(Monthly!$C$92:$AL$92,D$3*12) -> 60000
A14: Retained earnings | B14: =INDEX(Monthly!$C$93:$AL$93,B$3*12) -> 100050.56 | C14: =INDEX(Monthly!$C$93:$AL$93,C$3*12) -> 237886.13 | D14: =INDEX(Monthly!$C$93:$AL$93,D$3*12) -> 406906.08
A15: Total equity | B15: =INDEX(Monthly!$C$96:$AL$96,B$3*12) -> 160050.56 | C15: =INDEX(Monthly!$C$96:$AL$96,C$3*12) -> 297886.13 | D15: =INDEX(Monthly!$C$96:$AL$96,D$3*12) -> 466906.08
A16: Total liabilities & equity | B16: =INDEX(Monthly!$C$97:$AL$97,B$3*12) -> 254163.08 | C16: =INDEX(Monthly!$C$97:$AL$97,C$3*12) -> 378511.38 | D16: =INDEX(Monthly!$C$97:$AL$97,D$3*12) -> 534313.84
A17: Check: assets − liabilities − equity (must be 0) | B17: =INDEX(Monthly!$C$98:$AL$98,B$3*12) -> 0 | C17: =INDEX(Monthly!$C$98:$AL$98,C$3*12) -> 0 | D17: =INDEX(Monthly!$C$98:$AL$98,D$3*12) -> 0

Sheet Monthly
A1: Monthly projection | D1: =HYPERLINK("#'Cover'!A1","◂ Contents") -> ◂ Contents
A2: $ unless stated; costs shown as negatives. Every period uses the same formula.
A3: Month | C3: M1 | D3: M2 | E3: M3 | F3: M4 | G3: M5 | H3: M6 | I3: M7 | J3: M8 | K3: M9 | L3: M10 | M3: M11 | N3: M12 | O3: M13 | P3: M14 | Q3: M15 | R3: M16 | S3: M17 | T3: M18 | U3: M19 | V3: M20 | W3: M21 | X3: M22 | Y3: M23 | Z3: M24 | AA3: M25 | AB3: M26 | AC3: M27 | AD3: M28 | AE3: M29 | AF3: M30 | AG3: M31 | AH3: M32 | AI3: M33 | AJ3: M34 | AK3: M35 | AL3: M36
A4: Period # | C4: 1 | D4: 2 | E4: 3 | F4: 4 | G4: 5 | H4: 6 | I4: 7 | J4: 8 | K4: 9 | L4: 10 | M4: 11 | N4: 12 | O4: 13 | P4: 14 | Q4: 15 | R4: 16 | S4: 17 | T4: 18 | U4: 19 | V4: 20 | W4: 21 | X4: 22 | Y4: 23 | Z4: 24 | AA4: 25 | AB4: 26 | AC4: 27 | AD4: 28 | AE4: 29 | AF4: 30 | AG4: 31 | AH4: 32 | AI4: 33 | AJ4: 34 | AK4: 35 | AL4: 36
A5: Year # | C5: =ROUNDUP(C4*1/12,0) -> 1 | D5: =ROUNDUP(D4*1/12,0) -> 1 | E5: =ROUNDUP(E4*1/12,0) -> 1 | F5: =ROUNDUP(F4*1/12,0) -> 1 | G5: =ROUNDUP(G4*1/12,0) -> 1 | H5: =ROUNDUP(H4*1/12,0) -> 1 | I5: =ROUNDUP(I4*1/12,0) -> 1 | J5: =ROUNDUP(J4*1/12,0) -> 1 | ... AL5: =ROUNDUP(AL4*1/12,0) -> 3
A7: Retail counter
A8: Traffic ramp factor | C8: =MIN(1,Inputs!$E$9+(1-Inputs!$E$9)*(C$4-1)/MAX(1,Inputs!$E$8)) -> 0.9 | D8: =MIN(1,Inputs!$E$9+(1-Inputs!$E$9)*(D$4-1)/MAX(1,Inputs!$E$8)) -> 0.95 | E8: =MIN(1,Inputs!$E$9+(1-Inputs!$E$9)*(E$4-1)/MAX(1,Inputs!$E$8)) -> 1 | F8: =MIN(1,Inputs!$E$9+(1-Inputs!$E$9)*(F$4-1)/MAX(1,Inputs!$E$8)) -> 1 | G8: =MIN(1,Inputs!$E$9+(1-Inputs!$E$9)*(G$4-1)/MAX(1,Inputs!$E$8)) -> 1 | H8: =MIN(1,Inputs!$E$9+(1-Inputs!$E$9)*(H$4-1)/MAX(1,Inputs!$E$8)) -> 1 | I8: =MIN(1,Inputs!$E$9+(1-Inputs!$E$9)*(I$4-1)/MAX(1,Inputs!$E$8)) -> 1 | J8: =MIN(1,Inputs!$E$9+(1-Inputs!$E$9)*(J$4-1)/MAX(1,Inputs!$E$8)) -> 1 | ... AL8: =MIN(1,Inputs!$E$9+(1-Inputs!$E$9)*(AL$4-1)/MAX(1,Inputs!$E$8)) -> 1
A9: Season factor (November-December peak) | C9: =IF(MOD(C$4-1,12)>=10,1+Inputs!$E$14,1-Inputs!$E$14/5) -> 0.96 | D9: =IF(MOD(D$4-1,12)>=10,1+Inputs!$E$14,1-Inputs!$E$14/5) -> 0.96 | E9: =IF(MOD(E$4-1,12)>=10,1+Inputs!$E$14,1-Inputs!$E$14/5) -> 0.96 | F9: =IF(MOD(F$4-1,12)>=10,1+Inputs!$E$14,1-Inputs!$E$14/5) -> 0.96 | G9: =IF(MOD(G$4-1,12)>=10,1+Inputs!$E$14,1-Inputs!$E$14/5) -> 0.96 | H9: =IF(MOD(H$4-1,12)>=10,1+Inputs!$E$14,1-Inputs!$E$14/5) -> 0.96 | I9: =IF(MOD(I$4-1,12)>=10,1+Inputs!$E$14,1-Inputs!$E$14/5) -> 0.96 | J9: =IF(MOD(J$4-1,12)>=10,1+Inputs!$E$14,1-Inputs!$E$14/5) -> 0.96 | ... AL9: =IF(MOD(AL$4-1,12)>=10,1+Inputs!$E$14,1-Inputs!$E$14/5) -> 1.2
A10: Customers per day | C10: =Inputs!$E$7*C8*(1+Inputs!$E$10)^(C$5-1)*C9 -> 276.48 | D10: =Inputs!$E$7*D8*(1+Inputs!$E$10)^(D$5-1)*D9 -> 291.84 | E10: =Inputs!$E$7*E8*(1+Inputs!$E$10)^(E$5-1)*E9 -> 307.2 | F10: =Inputs!$E$7*F8*(1+Inputs!$E$10)^(F$5-1)*F9 -> 307.2 | G10: =Inputs!$E$7*G8*(1+Inputs!$E$10)^(G$5-1)*G9 -> 307.2 | H10: =Inputs!$E$7*H8*(1+Inputs!$E$10)^(H$5-1)*H9 -> 307.2 | I10: =Inputs!$E$7*I8*(1+Inputs!$E$10)^(I$5-1)*I9 -> 307.2 | J10: =Inputs!$E$7*J8*(1+Inputs!$E$10)^(J$5-1)*J9 -> 307.2 | ... AL10: =Inputs!$E$7*AL8*(1+Inputs!$E$10)^(AL$5-1)*AL9 -> 407.3856
A11: Opening days in period | C11: =Inputs!$E$13*52/12*1 -> 26 | D11: =Inputs!$E$13*52/12*1 -> 26 | E11: =Inputs!$E$13*52/12*1 -> 26 | F11: =Inputs!$E$13*52/12*1 -> 26 | G11: =Inputs!$E$13*52/12*1 -> 26 | H11: =Inputs!$E$13*52/12*1 -> 26 | I11: =Inputs!$E$13*52/12*1 -> 26 | J11: =Inputs!$E$13*52/12*1 -> 26 | ... AL11: =Inputs!$E$13*52/12*1 -> 26
A12: Retail transactions | C12: =C10*C11 -> 7188.48 | D12: =D10*D11 -> 7587.84 | E12: =E10*E11 -> 7987.2 | F12: =F10*F11 -> 7987.2 | G12: =G10*G11 -> 7987.2 | H12: =H10*H11 -> 7987.2 | I12: =I10*I11 -> 7987.2 | J12: =J10*J11 -> 7987.2 | ... AL12: =AL10*AL11 -> 10592.026
A13: Average ticket | C13: =Inputs!$E$11*(1+Inputs!$E$12)^(C$5-1) -> 11.5 | D13: =Inputs!$E$11*(1+Inputs!$E$12)^(D$5-1) -> 11.5 | E13: =Inputs!$E$11*(1+Inputs!$E$12)^(E$5-1) -> 11.5 | F13: =Inputs!$E$11*(1+Inputs!$E$12)^(F$5-1) -> 11.5 | G13: =Inputs!$E$11*(1+Inputs!$E$12)^(G$5-1) -> 11.5 | H13: =Inputs!$E$11*(1+Inputs!$E$12)^(H$5-1) -> 11.5 | I13: =Inputs!$E$11*(1+Inputs!$E$12)^(I$5-1) -> 11.5 | J13: =Inputs!$E$11*(1+Inputs!$E$12)^(J$5-1) -> 11.5 | ... AL13: =Inputs!$E$11*(1+Inputs!$E$12)^(AL$5-1) -> 12.20035
A14: Retail revenue | C14: =C12*C13 -> 82667.52 | D14: =D12*D13 -> 87260.16 | E14: =E12*E13 -> 91852.8 | F14: =F12*F13 -> 91852.8 | G14: =G12*G13 -> 91852.8 | H14: =H12*H13 -> 91852.8 | I14: =I12*I13 -> 91852.8 | J14: =J12*J13 -> 91852.8 | ... AL14: =AL12*AL13 -> 129226.42
A16: Wholesale
A17: Wholesale accounts | C17: =Inputs!$E$17*C8*(1+Inputs!$E$18)^(C$5-1) -> 14.4 | D17: =Inputs!$E$17*D8*(1+Inputs!$E$18)^(D$5-1) -> 15.2 | E17: =Inputs!$E$17*E8*(1+Inputs!$E$18)^(E$5-1) -> 16 | F17: =Inputs!$E$17*F8*(1+Inputs!$E$18)^(F$5-1) -> 16 | G17: =Inputs!$E$17*G8*(1+Inputs!$E$18)^(G$5-1) -> 16 | H17: =Inputs!$E$17*H8*(1+Inputs!$E$18)^(H$5-1) -> 16 | I17: =Inputs!$E$17*I8*(1+Inputs!$E$18)^(I$5-1) -> 16 | J17: =Inputs!$E$17*J8*(1+Inputs!$E$18)^(J$5-1) -> 16 | ... AL17: =Inputs!$E$17*AL8*(1+Inputs!$E$18)^(AL$5-1) -> 20.0704
A18: Order value per account per week | C18: =Inputs!$E$19*(1+Inputs!$E$12)^(C$5-1) -> 540 | D18: =Inputs!$E$19*(1+Inputs!$E$12)^(D$5-1) -> 540 | E18: =Inputs!$E$19*(1+Inputs!$E$12)^(E$5-1) -> 540 | F18: =Inputs!$E$19*(1+Inputs!$E$12)^(F$5-1) -> 540 | G18: =Inputs!$E$19*(1+Inputs!$E$12)^(G$5-1) -> 540 | H18: =Inputs!$E$19*(1+Inputs!$E$12)^(H$5-1) -> 540 | I18: =Inputs!$E$19*(1+Inputs!$E$12)^(I$5-1) -> 540 | J18: =Inputs!$E$19*(1+Inputs!$E$12)^(J$5-1) -> 540 | ... AL18: =Inputs!$E$19*(1+Inputs!$E$12)^(AL$5-1) -> 572.886
A19: Wholesale revenue | C19: =C17*C18*52/12*1 -> 33696 | D19: =D17*D18*52/12*1 -> 35568 | E19: =E17*E18*52/12*1 -> 37440 | F19: =F17*F18*52/12*1 -> 37440 | G19: =G17*G18*52/12*1 -> 37440 | H19: =H17*H18*52/12*1 -> 37440 | I19: =I17*I18*52/12*1 -> 37440 | J19: =J17*J18*52/12*1 -> 37440 | ... AL19: =AL17*AL18*52/12*1 -> 49824.888
A21: Revenue
A22: Revenue | C22: =C14+C19 -> 116363.52 | D22: =D14+D19 -> 122828.16 | E22: =E14+E19 -> 129292.8 | F22: =F14+F19 -> 129292.8 | G22: =G14+G19 -> 129292.8 | H22: =H14+H19 -> 129292.8 | I22: =I14+I19 -> 129292.8 | J22: =J14+J19 -> 129292.8 | ... AL22: =AL14+AL19 -> 179051.31
A24: Cost of sales
A25: Ingredients sold | C25: =-(C14*Inputs!$E$24+C19*Inputs!$E$25) -> -30959.885 | D25: =-(D14*Inputs!$E$24+D19*Inputs!$E$25) -> -32679.878 | E25: =-(E14*Inputs!$E$24+E19*Inputs!$E$25) -> -34399.872 | F25: =-(F14*Inputs!$E$24+F19*Inputs!$E$25) -> -34399.872 | G25: =-(G14*Inputs!$E$24+G19*Inputs!$E$25) -> -34399.872 | H25: =-(H14*Inputs!$E$24+H19*Inputs!$E$25) -> -34399.872 | I25: =-(I14*Inputs!$E$24+I19*Inputs!$E$25) -> -34399.872 | J25: =-(J14*Inputs!$E$24+J19*Inputs!$E$25) -> -34399.872 | ... AL25: =-(AL14*Inputs!$E$24+AL19*Inputs!$E$25) -> -47456.554
A26: Waste (retail production not sold, at ingredient cost) | C26: =-C14*Inputs!$E$24*Inputs!$E$26/MAX(0.01,1-Inputs!$E$26) -> -1962.2181 | D26: =-D14*Inputs!$E$24*Inputs!$E$26/MAX(0.01,1-Inputs!$E$26) -> -2071.2302 | E26: =-E14*Inputs!$E$24*Inputs!$E$26/MAX(0.01,1-Inputs!$E$26) -> -2180.2423 | F26: =-F14*Inputs!$E$24*Inputs!$E$26/MAX(0.01,1-Inputs!$E$26) -> -2180.2423 | G26: =-G14*Inputs!$E$24*Inputs!$E$26/MAX(0.01,1-Inputs!$E$26) -> -2180.2423 | H26: =-H14*Inputs!$E$24*Inputs!$E$26/MAX(0.01,1-Inputs!$E$26) -> -2180.2423 | I26: =-I14*Inputs!$E$24*Inputs!$E$26/MAX(0.01,1-Inputs!$E$26) -> -2180.2423 | J26: =-J14*Inputs!$E$24*Inputs!$E$26/MAX(0.01,1-Inputs!$E$26) -> -2180.2423 | ... AL26: =-AL14*Inputs!$E$24*Inputs!$E$26/MAX(0.01,1-Inputs!$E$26) -> -3067.3524
A27: Packaging | C27: =-C22*Inputs!$E$27 -> -4072.7232 | D27: =-D22*Inputs!$E$27 -> -4298.9856 | E27: =-E22*Inputs!$E$27 -> -4525.248 | F27: =-F22*Inputs!$E$27 -> -4525.248 | G27: =-G22*Inputs!$E$27 -> -4525.248 | H27: =-H22*Inputs!$E$27 -> -4525.248 | I27: =-I22*Inputs!$E$27 -> -4525.248 | J27: =-J22*Inputs!$E$27 -> -4525.248 | ... AL27: =-AL22*Inputs!$E$27 -> -6266.7958
A28: Cost of sales | C28: =C25+C26+C27 -> -36994.826 | D28: =D25+D26+D27 -> -39050.094 | E28: =E25+E26+E27 -> -41105.362 | F28: =F25+F26+F27 -> -41105.362 | G28: =G25+G26+G27 -> -41105.362 | H28: =H25+H26+H27 -> -41105.362 | I28: =I25+I26+I27 -> -41105.362 | J28: =J25+J26+J27 -> -41105.362 | ... AL28: =AL25+AL26+AL27 -> -56790.702
A29: Gross profit | C29: =C22+C28 -> 79368.694 | D29: =D22+D28 -> 83778.066 | E29: =E22+E28 -> 88187.438 | F29: =F22+F28 -> 88187.438 | G29: =G22+G28 -> 88187.438 | H29: =H22+H28 -> 88187.438 | I29: =I22+I28 -> 88187.438 | J29: =J22+J28 -> 88187.438 | ... AL29: =AL22+AL28 -> 122260.61
A31: Operating expenses
A32: Payroll (bakers, counter, manager) | C32: =Headcount!C17 -> -49466.667 | D32: =Headcount!D17 -> -49466.667 | E32: =Headcount!E17 -> -49466.667 | F32: =Headcount!F17 -> -49466.667 | G32: =Headcount!G17 -> -49466.667 | H32: =Headcount!H17 -> -49466.667 | I32: =Headcount!I17 -> -49466.667 | J32: =Headcount!J17 -> -49466.667 | ... AL32: =Headcount!AL17 -> -57827.43
A33: Rent | C33: =-Inputs!$E$30*1 -> -12000 | D33: =-Inputs!$E$30*1 -> -12000 | E33: =-Inputs!$E$30*1 -> -12000 | F33: =-Inputs!$E$30*1 -> -12000 | G33: =-Inputs!$E$30*1 -> -12000 | H33: =-Inputs!$E$30*1 -> -12000 | I33: =-Inputs!$E$30*1 -> -12000 | J33: =-Inputs!$E$30*1 -> -12000 | ... AL33: =-Inputs!$E$30*1 -> -12000
A34: Utilities (ovens) | C34: =-Inputs!$E$31*1 -> -4000 | D34: =-Inputs!$E$31*1 -> -4000 | E34: =-Inputs!$E$31*1 -> -4000 | F34: =-Inputs!$E$31*1 -> -4000 | G34: =-Inputs!$E$31*1 -> -4000 | H34: =-Inputs!$E$31*1 -> -4000 | I34: =-Inputs!$E$31*1 -> -4000 | J34: =-Inputs!$E$31*1 -> -4000 | ... AL34: =-Inputs!$E$31*1 -> -4000
A35: Wholesale delivery | C35: =-C17*Inputs!$E$20*52/12*1*Inputs!$E$21 -> -2808 | D35: =-D17*Inputs!$E$20*52/12*1*Inputs!$E$21 -> -2964 | E35: =-E17*Inputs!$E$20*52/12*1*Inputs!$E$21 -> -3120 | F35: =-F17*Inputs!$E$20*52/12*1*Inputs!$E$21 -> -3120 | G35: =-G17*Inputs!$E$20*52/12*1*Inputs!$E$21 -> -3120 | H35: =-H17*Inputs!$E$20*52/12*1*Inputs!$E$21 -> -3120 | I35: =-I17*Inputs!$E$20*52/12*1*Inputs!$E$21 -> -3120 | J35: =-J17*Inputs!$E$20*52/12*1*Inputs!$E$21 -> -3120 | ... AL35: =-AL17*Inputs!$E$20*52/12*1*Inputs!$E$21 -> -3913.728
A36: Equipment repairs & cleaning | C36: =-Inputs!$E$32*1 -> -1000 | D36: =-Inputs!$E$32*1 -> -1000 | E36: =-Inputs!$E$32*1 -> -1000 | F36: =-Inputs!$E$32*1 -> -1000 | G36: =-Inputs!$E$32*1 -> -1000 | H36: =-Inputs!$E$32*1 -> -1000 | I36: =-Inputs!$E$32*1 -> -1000 | J36: =-Inputs!$E$32*1 -> -1000 | ... AL36: =-Inputs!$E$32*1 -> -1000
A37: Marketing | C37: =-C22*Inputs!$E$33 -> -2327.2704 | D37: =-D22*Inputs!$E$33 -> -2456.5632 | E37: =-E22*Inputs!$E$33 -> -2585.856 | F37: =-F22*Inputs!$E$33 -> -2585.856 | G37: =-G22*Inputs!$E$33 -> -2585.856 | H37: =-H22*Inputs!$E$33 -> -2585.856 | I37: =-I22*Inputs!$E$33 -> -2585.856 | J37: =-J22*Inputs!$E$33 -> -2585.856 | ... AL37: =-AL22*Inputs!$E$33 -> -3581.0262
A38: Card processing fees | C38: =-C14*Inputs!$E$34 -> -2314.6906 | D38: =-D14*Inputs!$E$34 -> -2443.2845 | E38: =-E14*Inputs!$E$34 -> -2571.8784 | F38: =-F14*Inputs!$E$34 -> -2571.8784 | G38: =-G14*Inputs!$E$34 -> -2571.8784 | H38: =-H14*Inputs!$E$34 -> -2571.8784 | I38: =-I14*Inputs!$E$34 -> -2571.8784 | J38: =-J14*Inputs!$E$34 -> -2571.8784 | ... AL38: =-AL14*Inputs!$E$34 -> -3618.3397
A39: Insurance, licences & other G&A | C39: =-Inputs!$E$35*1 -> -2800 | D39: =-Inputs!$E$35*1 -> -2800 | E39: =-Inputs!$E$35*1 -> -2800 | F39: =-Inputs!$E$35*1 -> -2800 | G39: =-Inputs!$E$35*1 -> -2800 | H39: =-Inputs!$E$35*1 -> -2800 | I39: =-Inputs!$E$35*1 -> -2800 | J39: =-Inputs!$E$35*1 -> -2800 | ... AL39: =-Inputs!$E$35*1 -> -2800
A40: Total operating expenses | C40: =C32+C33+C34+C35+C36+C37+C38+C39 -> -76716.628 | D40: =D32+D33+D34+D35+D36+D37+D38+D39 -> -77130.514 | E40: =E32+E33+E34+E35+E36+E37+E38+E39 -> -77544.401 | F40: =F32+F33+F34+F35+F36+F37+F38+F39 -> -77544.401 | G40: =G32+G33+G34+G35+G36+G37+G38+G39 -> -77544.401 | H40: =H32+H33+H34+H35+H36+H37+H38+H39 -> -77544.401 | I40: =I32+I33+I34+I35+I36+I37+I38+I39 -> -77544.401 | J40: =J32+J33+J34+J35+J36+J37+J38+J39 -> -77544.401 | ... AL40: =AL32+AL33+AL34+AL35+AL36+AL37+AL38+AL39 -> -88740.524
A41: EBITDA | C41: =C29+C40 -> 2652.0663 | D41: =D29+D40 -> 6647.5515 | E41: =E29+E40 -> 10643.037 | F41: =F29+F40 -> 10643.037 | G41: =G29+G40 -> 10643.037 | H41: =H29+H40 -> 10643.037 | I41: =I29+I40 -> 10643.037 | J41: =J29+J40 -> 10643.037 | ... AL41: =AL29+AL40 -> 33520.082
A43: Profit after depreciation, interest, tax
A44: EBIT | C44: =C41+C55 -> 1580.6377 | D44: =D41+D55 -> 5576.1229 | E44: =E41+E55 -> 9571.6081 | F44: =F41+F55 -> 9571.6081 | G44: =G41+G55 -> 9571.6081 | H44: =H41+H55 -> 9571.6081 | I44: =I41+I55 -> 9571.6081 | J44: =J41+J55 -> 9571.6081 | ... AL44: =AL41+AL55 -> 32115.32
A45: Interest on loan (average balance after drawdown) | C45: =-(C60+C61+C63)/2*Inputs!$E$60/12 -> -566.66667 | D45: =-(D60+D61+D63)/2*Inputs!$E$60/12 -> -561.94444 | E45: =-(E60+E61+E63)/2*Inputs!$E$60/12 -> -552.5 | F45: =-(F60+F61+F63)/2*Inputs!$E$60/12 -> -543.05556 | G45: =-(G60+G61+G63)/2*Inputs!$E$60/12 -> -533.61111 | H45: =-(H60+H61+H63)/2*Inputs!$E$60/12 -> -524.16667 | I45: =-(I60+I61+I63)/2*Inputs!$E$60/12 -> -514.72222 | J45: =-(J60+J61+J63)/2*Inputs!$E$60/12 -> -505.27778 | ... AL45: =-(AL60+AL61+AL63)/2*Inputs!$E$60/12 -> -240.83333
A46: Pre-tax income | C46: =C44+C45 -> 1013.9711 | D46: =D44+D45 -> 5014.1785 | E46: =E44+E45 -> 9019.1081 | F46: =F44+F45 -> 9028.5525 | G46: =G44+G45 -> 9037.997 | H46: =H44+H45 -> 9047.4414 | I46: =I44+I45 -> 9056.8859 | J46: =J44+J45 -> 9066.3303 | ... AL46: =AL44+AL45 -> 31874.487
A47: Helper: cumulative pre-tax income | C47: =C46 -> 1013.9711 | D47: =C47+D46 -> 6028.1495 | E47: =D47+E46 -> 15047.258 | F47: =E47+F46 -> 24075.81 | G47: =F47+G46 -> 33113.807 | H47: =G47+H46 -> 42161.249 | I47: =H47+I46 -> 51218.134 | J47: =I47+J46 -> 60284.465 | K47: =J47+K46 -> 69360.239 | ... AL47: =AK47+AL46 -> 515070.99
A48: Helper: cumulative taxable income (losses carried forward) | C48: =MAX(0,C47) -> 1013.9711 | D48: =MAX(C48,D47) -> 6028.1495 | E48: =MAX(D48,E47) -> 15047.258 | F48: =MAX(E48,F47) -> 24075.81 | G48: =MAX(F48,G47) -> 33113.807 | H48: =MAX(G48,H47) -> 42161.249 | I48: =MAX(H48,I47) -> 51218.134 | J48: =MAX(I48,J47) -> 60284.465 | K48: =MAX(J48,K47) -> 69360.239 | ... AL48: =MAX(AK48,AL47) -> 515070.99
A49: Income tax | C49: =-C48*Inputs!$E$70 -> -212.93393 | D49: =-(D48-C48)*Inputs!$E$70 -> -1052.9775 | E49: =-(E48-D48)*Inputs!$E$70 -> -1894.0127 | F49: =-(F48-E48)*Inputs!$E$70 -> -1895.996 | G49: =-(G48-F48)*Inputs!$E$70 -> -1897.9794 | H49: =-(H48-G48)*Inputs!$E$70 -> -1899.9627 | I49: =-(I48-H48)*Inputs!$E$70 -> -1901.946 | J49: =-(J48-I48)*Inputs!$E$70 -> -1903.9294 | K49: =-(K48-J48)*Inputs!$E$70 -> -1905.9127 | ... AL49: =-(AL48-AK48)*Inputs!$E$70 -> -6693.6423
A50: Net income | C50: =C46+C49 -> 801.03715 | D50: =D46+D49 -> 3961.201 | E50: =E46+E49 -> 7125.0954 | F50: =F46+F49 -> 7132.5565 | G50: =G46+G49 -> 7140.0176 | H50: =H46+H49 -> 7147.4787 | I50: =I46+I49 -> 7154.9398 | J50: =J46+J49 -> 7162.4009 | ... AL50: =AL46+AL49 -> 25180.845
A52: Fixed assets & capital spending
A53: Capital spending (fit-out, ovens, mixers, display cases) | C53: =IF(C$4=1,Inputs!$E$38,0)+IF(C$5>1,Inputs!$E$39*1/12,0) -> 90000 | D53: =IF(D$4=1,Inputs!$E$38,0)+IF(D$5>1,Inputs!$E$39*1/12,0) -> 0 | E53: =IF(E$4=1,Inputs!$E$38,0)+IF(E$5>1,Inputs!$E$39*1/12,0) -> 0 | F53: =IF(F$4=1,Inputs!$E$38,0)+IF(F$5>1,Inputs!$E$39*1/12,0) -> 0 | G53: =IF(G$4=1,Inputs!$E$38,0)+IF(G$5>1,Inputs!$E$39*1/12,0) -> 0 | H53: =IF(H$4=1,Inputs!$E$38,0)+IF(H$5>1,Inputs!$E$39*1/12,0) -> 0 | I53: =IF(I$4=1,Inputs!$E$38,0)+IF(I$5>1,Inputs!$E$39*1/12,0) -> 0 | J53: =IF(J$4=1,Inputs!$E$38,0)+IF(J$5>1,Inputs!$E$39*1/12,0) -> 0 | ... AL53: =IF(AL$4=1,Inputs!$E$38,0)+IF(AL$5>1,Inputs!$E$39*1/12,0) -> 1166.6667
A54: Fixed assets at cost | C54: =C53 -> 90000 | D54: =C54+D53 -> 90000 | E54: =D54+E53 -> 90000 | F54: =E54+F53 -> 90000 | G54: =F54+G53 -> 90000 | H54: =G54+H53 -> 90000 | I54: =H54+I53 -> 90000 | J54: =I54+J53 -> 90000 | K54: =J54+K53 -> 90000 | ... AL54: =AK54+AL53 -> 118000
A55: Depreciation | C55: =-MIN(C54/MAX(1,Inputs!$E$69*12),C53) -> -1071.4286 | D55: =-MIN(D54/MAX(1,Inputs!$E$69*12),C57+D53) -> -1071.4286 | E55: =-MIN(E54/MAX(1,Inputs!$E$69*12),D57+E53) -> -1071.4286 | F55: =-MIN(F54/MAX(1,Inputs!$E$69*12),E57+F53) -> -1071.4286 | G55: =-MIN(G54/MAX(1,Inputs!$E$69*12),F57+G53) -> -1071.4286 | H55: =-MIN(H54/MAX(1,Inputs!$E$69*12),G57+H53) -> -1071.4286 | I55: =-MIN(I54/MAX(1,Inputs!$E$69*12),H57+I53) -> -1071.4286 | J55: =-MIN(J54/MAX(1,Inputs!$E$69*12),I57+J53) -> -1071.4286 | K55: =-MIN(K54/MAX(1,Inputs!$E$69*12),J57+K53) -> -1071.4286 | ... AL55: =-MIN(AL54/MAX(1,Inputs!$E$69*12),AK57+AL53) -> -1404.7619
A56: Accumulated depreciation | C56: =C55 -> -1071.4286 | D56: =C56+D55 -> -2142.8571 | E56: =D56+E55 -> -3214.2857 | F56: =E56+F55 -> -4285.7143 | G56: =F56+G55 -> -5357.1429 | H56: =G56+H55 -> -6428.5714 | I56: =H56+I55 -> -7500 | J56: =I56+J55 -> -8571.4286 | K56: =J56+K55 -> -9642.8571 | ... AL56: =AK56+AL55 -> -42738.095
A57: Net fixed assets | C57: =C54+C56 -> 88928.571 | D57: =D54+D56 -> 87857.143 | E57: =E54+E56 -> 86785.714 | F57: =F54+F56 -> 85714.286 | G57: =G54+G56 -> 84642.857 | H57: =H54+H56 -> 83571.429 | I57: =I54+I56 -> 82500 | J57: =J54+J56 -> 81428.571 | ... AL57: =AL54+AL56 -> 75261.905
A59: Debt
A60: Loan — opening balance | C60: =0 -> 0 | D60: =C63 -> 80000 | E60: =D63 -> 78666.667 | F60: =E63 -> 77333.333 | G60: =F63 -> 76000 | H60: =G63 -> 74666.667 | I60: =H63 -> 73333.333 | J60: =I63 -> 72000 | K60: =J63 -> 70666.667 | ... AL60: =AK63 -> 34666.667
A61: Loan drawdown | C61: =IF(C$4=1,Inputs!$E$59,0) -> 80000 | D61: =IF(D$4=1,Inputs!$E$59,0) -> 0 | E61: =IF(E$4=1,Inputs!$E$59,0) -> 0 | F61: =IF(F$4=1,Inputs!$E$59,0) -> 0 | G61: =IF(G$4=1,Inputs!$E$59,0) -> 0 | H61: =IF(H$4=1,Inputs!$E$59,0) -> 0 | I61: =IF(I$4=1,Inputs!$E$59,0) -> 0 | J61: =IF(J$4=1,Inputs!$E$59,0) -> 0 | ... AL61: =IF(AL$4=1,Inputs!$E$59,0) -> 0
A62: Loan repayment | C62: =-MIN(C60,Inputs!$E$59/MAX(1,Inputs!$E$61*12)) -> 0 | D62: =-MIN(D60,Inputs!$E$59/MAX(1,Inputs!$E$61*12)) -> -1333.3333 | E62: =-MIN(E60,Inputs!$E$59/MAX(1,Inputs!$E$61*12)) -> -1333.3333 | F62: =-MIN(F60,Inputs!$E$59/MAX(1,Inputs!$E$61*12)) -> -1333.3333 | G62: =-MIN(G60,Inputs!$E$59/MAX(1,Inputs!$E$61*12)) -> -1333.3333 | H62: =-MIN(H60,Inputs!$E$59/MAX(1,Inputs!$E$61*12)) -> -1333.3333 | I62: =-MIN(I60,Inputs!$E$59/MAX(1,Inputs!$E$61*12)) -> -1333.3333 | J62: =-MIN(J60,Inputs!$E$59/MAX(1,Inputs!$E$61*12)) -> -1333.3333 | ... AL62: =-MIN(AL60,Inputs!$E$59/MAX(1,Inputs!$E$61*12)) -> -1333.3333
A63: Loan — closing balance | C63: =C60+C61+C62 -> 80000 | D63: =D60+D61+D62 -> 78666.667 | E63: =E60+E61+E62 -> 77333.333 | F63: =F60+F61+F62 -> 76000 | G63: =G60+G61+G62 -> 74666.667 | H63: =H60+H61+H62 -> 73333.333 | I63: =I60+I61+I62 -> 72000 | J63: =J60+J61+J62 -> 70666.667 | ... AL63: =AL60+AL61+AL62 -> 33333.333
A65: Working capital
A66: Accounts receivable | C66: =C22*Inputs!$E$64/30 -> 27151.488 | D66: =D22*Inputs!$E$64/30 -> 28659.904 | E66: =E22*Inputs!$E$64/30 -> 30168.32 | F66: =F22*Inputs!$E$64/30 -> 30168.32 | G66: =G22*Inputs!$E$64/30 -> 30168.32 | H66: =H22*Inputs!$E$64/30 -> 30168.32 | I66: =I22*Inputs!$E$64/30 -> 30168.32 | J66: =J22*Inputs!$E$64/30 -> 30168.32 | ... AL66: =AL22*Inputs!$E$64/30 -> 41778.639
A67: Inventory | C67: =-C28*Inputs!$E$65/30 -> 3699.4826 | D67: =-D28*Inputs!$E$65/30 -> 3905.0094 | E67: =-E28*Inputs!$E$65/30 -> 4110.5362 | F67: =-F28*Inputs!$E$65/30 -> 4110.5362 | G67: =-G28*Inputs!$E$65/30 -> 4110.5362 | H67: =-H28*Inputs!$E$65/30 -> 4110.5362 | I67: =-I28*Inputs!$E$65/30 -> 4110.5362 | J67: =-J28*Inputs!$E$65/30 -> 4110.5362 | ... AL67: =-AL28*Inputs!$E$65/30 -> 5679.0702
A68: Accounts payable | C68: =-C28*Inputs!$E$66/30 -> 22196.896 | D68: =-D28*Inputs!$E$66/30 -> 23430.057 | E68: =-E28*Inputs!$E$66/30 -> 24663.217 | F68: =-F28*Inputs!$E$66/30 -> 24663.217 | G68: =-G28*Inputs!$E$66/30 -> 24663.217 | H68: =-H28*Inputs!$E$66/30 -> 24663.217 | I68: =-I28*Inputs!$E$66/30 -> 24663.217 | J68: =-J28*Inputs!$E$66/30 -> 24663.217 | ... AL68: =-AL28*Inputs!$E$66/30 -> 34074.421
A69: (Increase) / decrease in receivables | C69: =-C66 -> -27151.488 | D69: =C66-D66 -> -1508.416 | E69: =D66-E66 -> -1508.416 | F69: =E66-F66 -> 0 | G69: =F66-G66 -> 0 | H69: =G66-H66 -> 0 | I69: =H66-I66 -> 0 | J69: =I66-J66 -> 0 | K69: =J66-K66 -> 0 | ... AL69: =AK66-AL66 -> 0
A70: (Increase) / decrease in inventory | C70: =-C67 -> -3699.4826 | D70: =C67-D67 -> -205.52681 | E70: =D67-E67 -> -205.52681 | F70: =E67-F67 -> 0 | G70: =F67-G67 -> 0 | H70: =G67-H67 -> 0 | I70: =H67-I67 -> 0 | J70: =I67-J67 -> 0 | K70: =J67-K67 -> 0 | ... AL70: =AK67-AL67 -> 0
A71: Increase / (decrease) in payables | C71: =C68 -> 22196.896 | D71: =D68-C68 -> 1233.1609 | E71: =E68-D68 -> 1233.1609 | F71: =F68-E68 -> 0 | G71: =G68-F68 -> 0 | H71: =H68-G68 -> 0 | I71: =I68-H68 -> 0 | J71: =J68-I68 -> 0 | K71: =K68-J68 -> 0 | ... AL71: =AL68-AK68 -> 0
A73: Cash flow
A74: Operating cash flow | C74: =C50-C55+C69+C70+C71 -> -6781.6092 | D74: =D50-D55+D69+D70+D71 -> 4551.8476 | E74: =E50-E55+E69+E70+E71 -> 7715.742 | F74: =F50-F55+F69+F70+F71 -> 8203.9851 | G74: =G50-G55+G69+G70+G71 -> 8211.4462 | H74: =H50-H55+H69+H70+H71 -> 8218.9073 | I74: =I50-I55+I69+I70+I71 -> 8226.3684 | J74: =J50-J55+J69+J70+J71 -> 8233.8295 | ... AL74: =AL50-AL55+AL69+AL70+AL71 -> 26585.607
A75: Investing cash flow (capex) | C75: =-C53 -> -90000 | D75: =-D53 -> 0 | E75: =-E53 -> 0 | F75: =-F53 -> 0 | G75: =-G53 -> 0 | H75: =-H53 -> 0 | I75: =-I53 -> 0 | J75: =-J53 -> 0 | ... AL75: =-AL53 -> -1166.6667
A76: Equity raised | C76: =IF(C$4=1,Inputs!$E$58,0) -> 60000 | D76: =IF(D$4=1,Inputs!$E$58,0) -> 0 | E76: =IF(E$4=1,Inputs!$E$58,0) -> 0 | F76: =IF(F$4=1,Inputs!$E$58,0) -> 0 | G76: =IF(G$4=1,Inputs!$E$58,0) -> 0 | H76: =IF(H$4=1,Inputs!$E$58,0) -> 0 | I76: =IF(I$4=1,Inputs!$E$58,0) -> 0 | J76: =IF(J$4=1,Inputs!$E$58,0) -> 0 | ... AL76: =IF(AL$4=1,Inputs!$E$58,0) -> 0
A77: Financing cash flow | C77: =C76+C61+C62 -> 140000 | D77: =D76+D61+D62 -> -1333.3333 | E77: =E76+E61+E62 -> -1333.3333 | F77: =F76+F61+F62 -> -1333.3333 | G77: =G76+G61+G62 -> -1333.3333 | H77: =H76+H61+H62 -> -1333.3333 | I77: =I76+I61+I62 -> -1333.3333 | J77: =J76+J61+J62 -> -1333.3333 | ... AL77: =AL76+AL61+AL62 -> -1333.3333
A78: Net cash flow | C78: =C74+C75+C77 -> 43218.391 | D78: =D74+D75+D77 -> 3218.5143 | E78: =E74+E75+E77 -> 6382.4087 | F78: =F74+F75+F77 -> 6870.6517 | G78: =G74+G75+G77 -> 6878.1128 | H78: =H74+H75+H77 -> 6885.574 | I78: =I74+I75+I77 -> 6893.0351 | J78: =J74+J75+J77 -> 6900.4962 | ... AL78: =AL74+AL75+AL77 -> 24085.607
A79: Opening cash | C79: =0 -> 0 | D79: =C80 -> 43218.391 | E79: =D80 -> 46436.905 | F79: =E80 -> 52819.314 | G79: =F80 -> 59689.965 | H79: =G80 -> 66568.078 | I79: =H80 -> 73453.652 | J79: =I80 -> 80346.687 | K79: =J80 -> 87247.183 | ... AL79: =AK80 -> 387508.62
A80: Closing cash | C80: =C79+C78 -> 43218.391 | D80: =D79+D78 -> 46436.905 | E80: =E79+E78 -> 52819.314 | F80: =F79+F78 -> 59689.965 | G80: =G79+G78 -> 66568.078 | H80: =H79+H78 -> 73453.652 | I80: =I79+I78 -> 80346.687 | J80: =J79+J78 -> 87247.183 | ... AL80: =AL79+AL78 -> 411594.23
A81: Helper: EBITDA positive (1/0) | C81: =IF(C41>0,1,0) -> 1 | D81: =IF(D41>0,1,0) -> 1 | E81: =IF(E41>0,1,0) -> 1 | F81: =IF(F41>0,1,0) -> 1 | G81: =IF(G41>0,1,0) -> 1 | H81: =IF(H41>0,1,0) -> 1 | I81: =IF(I41>0,1,0) -> 1 | J81: =IF(J41>0,1,0) -> 1 | ... AL81: =IF(AL41>0,1,0) -> 1
A83: Goal modules
A84: Helper: net income positive (1/0) | C84: =IF(C50>0,1,0) -> 1 | D84: =IF(D50>0,1,0) -> 1 | E84: =IF(E50>0,1,0) -> 1 | F84: =IF(F50>0,1,0) -> 1 | G84: =IF(G50>0,1,0) -> 1 | H84: =IF(H50>0,1,0) -> 1 | I84: =IF(I50>0,1,0) -> 1 | J84: =IF(J50>0,1,0) -> 1 | ... AL84: =IF(AL50>0,1,0) -> 1
A85: Cash flow before financing (operating + investing) | C85: =C74+C75 -> -96781.609 | D85: =D74+D75 -> 4551.8476 | E85: =E74+E75 -> 7715.742 | F85: =F74+F75 -> 8203.9851 | G85: =G74+G75 -> 8211.4462 | H85: =H74+H75 -> 8218.9073 | I85: =I74+I75 -> 8226.3684 | J85: =J74+J75 -> 8233.8295 | ... AL85: =AL74+AL75 -> 25418.94
A86: Cumulative cash flow before financing | C86: =C85 -> -96781.609 | D86: =C86+D85 -> -92229.762 | E86: =D86+E85 -> -84514.02 | F86: =E86+F85 -> -76310.035 | G86: =F86+G85 -> -68098.588 | H86: =G86+H85 -> -59879.681 | I86: =H86+I85 -> -51653.313 | J86: =I86+J85 -> -43419.483 | K86: =J86+K85 -> -35178.193 | ... AL86: =AK86+AL85 -> 318260.89
A87: Helper: lowest cumulative cash flow so far | C87: =C86 -> -96781.609 | D87: =MIN(C87,D86) -> -96781.609 | E87: =MIN(D87,E86) -> -96781.609 | F87: =MIN(E87,F86) -> -96781.609 | G87: =MIN(F87,G86) -> -96781.609 | H87: =MIN(G87,H86) -> -96781.609 | I87: =MIN(H87,I86) -> -96781.609 | J87: =MIN(I87,J86) -> -96781.609 | K87: =MIN(J87,K86) -> -96781.609 | ... AL87: =MIN(AK87,AL86) -> -96781.609
A88: Helper: investment paid back (1/0) | C88: =IF(AND(C86>=0,C87<0),1,0) -> 0 | D88: =IF(AND(D86>=0,D87<0),1,0) -> 0 | E88: =IF(AND(E86>=0,E87<0),1,0) -> 0 | F88: =IF(AND(F86>=0,F87<0),1,0) -> 0 | G88: =IF(AND(G86>=0,G87<0),1,0) -> 0 | H88: =IF(AND(H86>=0,H87<0),1,0) -> 0 | I88: =IF(AND(I86>=0,I87<0),1,0) -> 0 | J88: =IF(AND(J86>=0,J87<0),1,0) -> 0 | ... AL88: =IF(AND(AL86>=0,AL87<0),1,0) -> 1
A89: Unlevered free cash flow (operating + after-tax interest − capex) | C89: =C74-C45*(1-Inputs!$E$70)+C75 -> -96333.943 | D89: =D74-D45*(1-Inputs!$E$70)+D75 -> 4995.7837 | E89: =E74-E45*(1-Inputs!$E$70)+E75 -> 8152.217 | F89: =F74-F45*(1-Inputs!$E$70)+F75 -> 8632.999 | G89: =G74-G45*(1-Inputs!$E$70)+G75 -> 8632.999 | H89: =H74-H45*(1-Inputs!$E$70)+H75 -> 8632.999 | I89: =I74-I45*(1-Inputs!$E$70)+I75 -> 8632.999 | J89: =J74-J45*(1-Inputs!$E$70)+J75 -> 8632.999 | ... AL89: =AL74-AL45*(1-Inputs!$E$70)+AL75 -> 25609.198
A91: Balance sheet
A92: Paid-in capital | C92: =C76 -> 60000 | D92: =C92+D76 -> 60000 | E92: =D92+E76 -> 60000 | F92: =E92+F76 -> 60000 | G92: =F92+G76 -> 60000 | H92: =G92+H76 -> 60000 | I92: =H92+I76 -> 60000 | J92: =I92+J76 -> 60000 | K92: =J92+K76 -> 60000 | ... AL92: =AK92+AL76 -> 60000
A93: Retained earnings | C93: =C50 -> 801.03715 | D93: =C93+D50 -> 4762.2381 | E93: =D93+E50 -> 11887.334 | F93: =E93+F50 -> 19019.89 | G93: =F93+G50 -> 26159.908 | H93: =G93+H50 -> 33307.386 | I93: =H93+I50 -> 40462.326 | J93: =I93+J50 -> 47624.727 | K93: =J93+K50 -> 54794.589 | ... AL93: =AK93+AL50 -> 406906.08
A94: Total assets | C94: =C80+C66+C67+C57 -> 162997.93 | D94: =D80+D66+D67+D57 -> 166858.96 | E94: =E80+E66+E67+E57 -> 173883.88 | F94: =F80+F66+F67+F57 -> 179683.11 | G94: =G80+G66+G67+G57 -> 185489.79 | H94: =H80+H66+H67+H57 -> 191303.94 | I94: =I80+I66+I67+I57 -> 197125.54 | J94: =J80+J66+J67+J57 -> 202954.61 | ... AL94: =AL80+AL66+AL67+AL57 -> 534313.84
A95: Total liabilities | C95: =C68+C63 -> 102196.9 | D95: =D68+D63 -> 102096.72 | E95: =E68+E63 -> 101996.55 | F95: =F68+F63 -> 100663.22 | G95: =G68+G63 -> 99329.884 | H95: =H68+H63 -> 97996.551 | I95: =I68+I63 -> 96663.217 | J95: =J68+J63 -> 95329.884 | ... AL95: =AL68+AL63 -> 67407.755
A96: Total equity | C96: =C92+C93 -> 60801.037 | D96: =D92+D93 -> 64762.238 | E96: =E92+E93 -> 71887.334 | F96: =F92+F93 -> 79019.89 | G96: =G92+G93 -> 86159.908 | H96: =H92+H93 -> 93307.386 | I96: =I92+I93 -> 100462.33 | J96: =J92+J93 -> 107624.73 | ... AL96: =AL92+AL93 -> 466906.08
A97: Total liabilities & equity | C97: =C95+C96 -> 162997.93 | D97: =D95+D96 -> 166858.96 | E97: =E95+E96 -> 173883.88 | F97: =F95+F96 -> 179683.11 | G97: =G95+G96 -> 185489.79 | H97: =H95+H96 -> 191303.94 | I97: =I95+I96 -> 197125.54 | J97: =J95+J96 -> 202954.61 | ... AL97: =AL95+AL96 -> 534313.84
A98: Check: assets − liabilities − equity | C98: =C94-C97 -> 0 | D98: =D94-D97 -> 0 | E98: =E94-E97 -> 0 | F98: =F94-F97 -> 0 | G98: =G94-G97 -> 0 | H98: =H94-H97 -> 0 | I98: =I94-I97 -> 0 | J98: =J94-J97 -> 0 | ... AL98: =AL94-AL97 -> 0

Sheet Headcount
A1: Headcount & payroll | D1: =HYPERLINK("#'Cover'!A1","◂ Contents") -> ◂ Contents
A2: $ unless stated; costs shown as negatives. Every period uses the same formula.
A3: Month | C3: M1 | D3: M2 | E3: M3 | F3: M4 | G3: M5 | H3: M6 | I3: M7 | J3: M8 | K3: M9 | L3: M10 | M3: M11 | N3: M12 | O3: M13 | P3: M14 | Q3: M15 | R3: M16 | S3: M17 | T3: M18 | U3: M19 | V3: M20 | W3: M21 | X3: M22 | Y3: M23 | Z3: M24 | AA3: M25 | AB3: M26 | AC3: M27 | AD3: M28 | AE3: M29 | AF3: M30 | AG3: M31 | AH3: M32 | AI3: M33 | AJ3: M34 | AK3: M35 | AL3: M36
A4: Period # | C4: 1 | D4: 2 | E4: 3 | F4: 4 | G4: 5 | H4: 6 | I4: 7 | J4: 8 | K4: 9 | L4: 10 | M4: 11 | N4: 12 | O4: 13 | P4: 14 | Q4: 15 | R4: 16 | S4: 17 | T4: 18 | U4: 19 | V4: 20 | W4: 21 | X4: 22 | Y4: 23 | Z4: 24 | AA4: 25 | AB4: 26 | AC4: 27 | AD4: 28 | AE4: 29 | AF4: 30 | AG4: 31 | AH4: 32 | AI4: 33 | AJ4: 34 | AK4: 35 | AL4: 36
A5: Year # | C5: =ROUNDUP(C4*1/12,0) -> 1 | D5: =ROUNDUP(D4*1/12,0) -> 1 | E5: =ROUNDUP(E4*1/12,0) -> 1 | F5: =ROUNDUP(F4*1/12,0) -> 1 | G5: =ROUNDUP(G4*1/12,0) -> 1 | H5: =ROUNDUP(H4*1/12,0) -> 1 | I5: =ROUNDUP(I4*1/12,0) -> 1 | J5: =ROUNDUP(J4*1/12,0) -> 1 | ... AL5: =ROUNDUP(AL4*1/12,0) -> 3
A7: Headcount (FTE)
A8: Bakers & production — FTE | C8: =Inputs!$E$42*(1+Inputs!$E$44)^(C$5-1)*MAX(0,MIN(1,C$4*1-Inputs!$E$45+1))/1 -> 5 | D8: =Inputs!$E$42*(1+Inputs!$E$44)^(D$5-1)*MAX(0,MIN(1,D$4*1-Inputs!$E$45+1))/1 -> 5 | E8: =Inputs!$E$42*(1+Inputs!$E$44)^(E$5-1)*MAX(0,MIN(1,E$4*1-Inputs!$E$45+1))/1 -> 5 | F8: =Inputs!$E$42*(1+Inputs!$E$44)^(F$5-1)*MAX(0,MIN(1,F$4*1-Inputs!$E$45+1))/1 -> 5 | G8: =Inputs!$E$42*(1+Inputs!$E$44)^(G$5-1)*MAX(0,MIN(1,G$4*1-Inputs!$E$45+1))/1 -> 5 | H8: =Inputs!$E$42*(1+Inputs!$E$44)^(H$5-1)*MAX(0,MIN(1,H$4*1-Inputs!$E$45+1))/1 -> 5 | I8: =Inputs!$E$42*(1+Inputs!$E$44)^(I$5-1)*MAX(0,MIN(1,I$4*1-Inputs!$E$45+1))/1 -> 5 | J8: =Inputs!$E$42*(1+Inputs!$E$44)^(J$5-1)*MAX(0,MIN(1,J$4*1-Inputs!$E$45+1))/1 -> 5 | ... AL8: =Inputs!$E$42*(1+Inputs!$E$44)^(AL$5-1)*MAX(0,MIN(1,AL$4*1-Inputs!$E$45+1))/1 -> 5.618
A9: Counter staff — FTE | C9: =Inputs!$E$46*(1+Inputs!$E$48)^(C$5-1)*MAX(0,MIN(1,C$4*1-Inputs!$E$49+1))/1 -> 7 | D9: =Inputs!$E$46*(1+Inputs!$E$48)^(D$5-1)*MAX(0,MIN(1,D$4*1-Inputs!$E$49+1))/1 -> 7 | E9: =Inputs!$E$46*(1+Inputs!$E$48)^(E$5-1)*MAX(0,MIN(1,E$4*1-Inputs!$E$49+1))/1 -> 7 | F9: =Inputs!$E$46*(1+Inputs!$E$48)^(F$5-1)*MAX(0,MIN(1,F$4*1-Inputs!$E$49+1))/1 -> 7 | G9: =Inputs!$E$46*(1+Inputs!$E$48)^(G$5-1)*MAX(0,MIN(1,G$4*1-Inputs!$E$49+1))/1 -> 7 | H9: =Inputs!$E$46*(1+Inputs!$E$48)^(H$5-1)*MAX(0,MIN(1,H$4*1-Inputs!$E$49+1))/1 -> 7 | I9: =Inputs!$E$46*(1+Inputs!$E$48)^(I$5-1)*MAX(0,MIN(1,I$4*1-Inputs!$E$49+1))/1 -> 7 | J9: =Inputs!$E$46*(1+Inputs!$E$48)^(J$5-1)*MAX(0,MIN(1,J$4*1-Inputs!$E$49+1))/1 -> 7 | ... AL9: =Inputs!$E$46*(1+Inputs!$E$48)^(AL$5-1)*MAX(0,MIN(1,AL$4*1-Inputs!$E$49+1))/1 -> 7.8652
A10: Manager — FTE | C10: =Inputs!$E$50*(1+Inputs!$E$52)^(C$5-1)*MAX(0,MIN(1,C$4*1-Inputs!$E$53+1))/1 -> 1.5 | D10: =Inputs!$E$50*(1+Inputs!$E$52)^(D$5-1)*MAX(0,MIN(1,D$4*1-Inputs!$E$53+1))/1 -> 1.5 | E10: =Inputs!$E$50*(1+Inputs!$E$52)^(E$5-1)*MAX(0,MIN(1,E$4*1-Inputs!$E$53+1))/1 -> 1.5 | F10: =Inputs!$E$50*(1+Inputs!$E$52)^(F$5-1)*MAX(0,MIN(1,F$4*1-Inputs!$E$53+1))/1 -> 1.5 | G10: =Inputs!$E$50*(1+Inputs!$E$52)^(G$5-1)*MAX(0,MIN(1,G$4*1-Inputs!$E$53+1))/1 -> 1.5 | H10: =Inputs!$E$50*(1+Inputs!$E$52)^(H$5-1)*MAX(0,MIN(1,H$4*1-Inputs!$E$53+1))/1 -> 1.5 | I10: =Inputs!$E$50*(1+Inputs!$E$52)^(I$5-1)*MAX(0,MIN(1,I$4*1-Inputs!$E$53+1))/1 -> 1.5 | J10: =Inputs!$E$50*(1+Inputs!$E$52)^(J$5-1)*MAX(0,MIN(1,J$4*1-Inputs!$E$53+1))/1 -> 1.5 | ... AL10: =Inputs!$E$50*(1+Inputs!$E$52)^(AL$5-1)*MAX(0,MIN(1,AL$4*1-Inputs!$E$53+1))/1 -> 1.5
A11: Total FTE | C11: =C8+C9+C10 -> 13.5 | D11: =D8+D9+D10 -> 13.5 | E11: =E8+E9+E10 -> 13.5 | F11: =F8+F9+F10 -> 13.5 | G11: =G8+G9+G10 -> 13.5 | H11: =H8+H9+H10 -> 13.5 | I11: =I8+I9+I10 -> 13.5 | J11: =J8+J9+J10 -> 13.5 | ... AL11: =AL8+AL9+AL10 -> 14.9832
A13: Payroll cost (salary + taxes & benefits)
A14: Bakers & production — payroll cost | C14: =-C8*Inputs!$E$43/12*1*(1+Inputs!$E$54)*(1+Inputs!$E$55)^(C$5-1) -> -20533.333 | D14: =-D8*Inputs!$E$43/12*1*(1+Inputs!$E$54)*(1+Inputs!$E$55)^(D$5-1) -> -20533.333 | E14: =-E8*Inputs!$E$43/12*1*(1+Inputs!$E$54)*(1+Inputs!$E$55)^(E$5-1) -> -20533.333 | F14: =-F8*Inputs!$E$43/12*1*(1+Inputs!$E$54)*(1+Inputs!$E$55)^(F$5-1) -> -20533.333 | G14: =-G8*Inputs!$E$43/12*1*(1+Inputs!$E$54)*(1+Inputs!$E$55)^(G$5-1) -> -20533.333 | H14: =-H8*Inputs!$E$43/12*1*(1+Inputs!$E$54)*(1+Inputs!$E$55)^(H$5-1) -> -20533.333 | I14: =-I8*Inputs!$E$43/12*1*(1+Inputs!$E$54)*(1+Inputs!$E$55)^(I$5-1) -> -20533.333 | J14: =-J8*Inputs!$E$43/12*1*(1+Inputs!$E$54)*(1+Inputs!$E$55)^(J$5-1) -> -20533.333 | ... AL14: =-AL8*Inputs!$E$43/12*1*(1+Inputs!$E$54)*(1+Inputs!$E$55)^(AL$5-1) -> -24476.293
A15: Counter staff — payroll cost | C15: =-C9*Inputs!$E$47/12*1*(1+Inputs!$E$54)*(1+Inputs!$E$55)^(C$5-1) -> -20253.333 | D15: =-D9*Inputs!$E$47/12*1*(1+Inputs!$E$54)*(1+Inputs!$E$55)^(D$5-1) -> -20253.333 | E15: =-E9*Inputs!$E$47/12*1*(1+Inputs!$E$54)*(1+Inputs!$E$55)^(E$5-1) -> -20253.333 | F15: =-F9*Inputs!$E$47/12*1*(1+Inputs!$E$54)*(1+Inputs!$E$55)^(F$5-1) -> -20253.333 | G15: =-G9*Inputs!$E$47/12*1*(1+Inputs!$E$54)*(1+Inputs!$E$55)^(G$5-1) -> -20253.333 | H15: =-H9*Inputs!$E$47/12*1*(1+Inputs!$E$54)*(1+Inputs!$E$55)^(H$5-1) -> -20253.333 | I15: =-I9*Inputs!$E$47/12*1*(1+Inputs!$E$54)*(1+Inputs!$E$55)^(I$5-1) -> -20253.333 | J15: =-J9*Inputs!$E$47/12*1*(1+Inputs!$E$54)*(1+Inputs!$E$55)^(J$5-1) -> -20253.333 | ... AL15: =-AL9*Inputs!$E$47/12*1*(1+Inputs!$E$54)*(1+Inputs!$E$55)^(AL$5-1) -> -24142.525
A16: Manager — payroll cost | C16: =-C10*Inputs!$E$51/12*1*(1+Inputs!$E$54)*(1+Inputs!$E$55)^(C$5-1) -> -8680 | D16: =-D10*Inputs!$E$51/12*1*(1+Inputs!$E$54)*(1+Inputs!$E$55)^(D$5-1) -> -8680 | E16: =-E10*Inputs!$E$51/12*1*(1+Inputs!$E$54)*(1+Inputs!$E$55)^(E$5-1) -> -8680 | F16: =-F10*Inputs!$E$51/12*1*(1+Inputs!$E$54)*(1+Inputs!$E$55)^(F$5-1) -> -8680 | G16: =-G10*Inputs!$E$51/12*1*(1+Inputs!$E$54)*(1+Inputs!$E$55)^(G$5-1) -> -8680 | H16: =-H10*Inputs!$E$51/12*1*(1+Inputs!$E$54)*(1+Inputs!$E$55)^(H$5-1) -> -8680 | I16: =-I10*Inputs!$E$51/12*1*(1+Inputs!$E$54)*(1+Inputs!$E$55)^(I$5-1) -> -8680 | J16: =-J10*Inputs!$E$51/12*1*(1+Inputs!$E$54)*(1+Inputs!$E$55)^(J$5-1) -> -8680 | ... AL16: =-AL10*Inputs!$E$51/12*1*(1+Inputs!$E$54)*(1+Inputs!$E$55)^(AL$5-1) -> -9208.612
A17: Total payroll | C17: =C14+C15+C16 -> -49466.667 | D17: =D14+D15+D16 -> -49466.667 | E17: =E14+E15+E16 -> -49466.667 | F17: =F14+F15+F16 -> -49466.667 | G17: =G14+G15+G16 -> -49466.667 | H17: =H14+H15+H16 -> -49466.667 | I17: =I14+I15+I16 -> -49466.667 | J17: =J14+J15+J16 -> -49466.667 | ... AL17: =AL14+AL15+AL16 -> -57827.43

Sheet Checks
A1: Model checks | E1: =HYPERLINK("#'Cover'!A1","◂ Contents") -> ◂ Contents
A2: Live formulas: they re-run every time an input changes.
A3: Check | B3: Result | C3: What it tests
A4: Annual revenue ties to period detail | B4: =IF(ABS(SUM('P&L'!$B$5:$D$5)-SUM(Monthly!$C$22:$AL$22))<0.5,"PASS","FAIL") -> PASS | C4: Sum of annual revenue equals the sum of every period
A5: Annual net income ties to period detail | B5: =IF(ABS(SUM('P&L'!$B$25:$D$25)-SUM(Monthly!$C$50:$AL$50))<0.5,"PASS","FAIL") -> PASS | C5: Sum of annual net income equals the sum of every period
A6: EBITDA reconciliation | B6: =IF(ABS(SUM(Monthly!$C$41:$AL$41)-SUM(Monthly!$C$29:$AL$29)-SUM(Monthly!$C$40:$AL$40))<0.5,"PASS","FAIL") -> PASS | C6: EBITDA = gross profit + operating expenses (costs are negative)
A7: Cash roll-forward | B7: =IF(ABS(INDEX(Monthly!$C$80:$AL$80,36)-SUM(Monthly!$C$78:$AL$78))<0.5,"PASS","FAIL") -> PASS | C7: Closing cash = all net cash flows since the start (opening cash is zero)
A8: Scenario selector valid | B8: =IF(AND(ISNUMBER(Dashboard!B4),Dashboard!B4>=1,Dashboard!B4<=3,INT(Dashboard!B4)=Dashboard!B4),"PASS","FAIL") -> PASS | C8: Dashboard!B4 is 1, 2 or 3
A9: Scenario ordering of drivers | B9: =IF(AND(Inputs!$B$7<=Inputs!$C$7,Inputs!$C$7<=Inputs!$D$7,Inputs!$B$8>=Inputs!$C$8,Inputs!$C$8>=Inputs!$D$8,Inputs!$B$9<=Inputs!$C$9,Inputs!$C$9<=Inputs!$D$9,Inputs!$B$10<=Inputs!$C$10,Inputs!$C$10<=Inputs!$D$10,Inputs!$B$11<=Inputs!$C$11,Inputs!$C$11<=Inputs!$D$11,Inputs!$B$12<=Inputs!$C$12,Inputs!$C$12<=Inputs!$D$12,Inputs!$B$17<=Inputs!$C$17,Inputs!$C$17<=Inputs!$D$17,Inputs!$B$18<=Inputs!$C$18,Inputs!$C$18<=Inputs!$D$18,Inputs!$B$19<=Inputs!$C$19,Inputs!$C$19<=Inputs!$D$19,Inputs!$B$21>=Inputs!$C$21,Inputs!$C$21>=Inputs!$D$21,Inputs!$B$24>=Inputs!$C$24,Inputs!$C$24>=Inputs!$D$24,Inputs!$B$25>=Inputs!$C$25,Inputs!$C$25>=Inputs!$D$25,Inputs!$B$26>=Inputs!$C$26,Inputs!$C$26>=Inputs!$D$26,Inputs!$B$27>=Inputs!$C$27,Inputs!$C$27>=Inputs!$D$27,Inputs!$B$33>=Inputs!$C$33,Inputs!$C$33>=Inputs!$D$33,Inputs!$B$34>=Inputs!$C$34,Inputs!$C$34>=Inputs!$D$34,Inputs!$B$42<=Inputs!$C$42,Inputs!$C$42<=Inputs!$D$42,Inputs!$B$44<=Inputs!$C$44,Inputs!$C$44<=Inputs!$D$44,Inputs!$B$46<=Inputs!$C$46,Inputs!$C$46<=Inputs!$D$46,Inputs!$B$48<=Inputs!$C$48,Inputs!$C$48<=Inputs!$D$48,Inputs!$B$50<=Inputs!$C$50,Inputs!$C$50<=Inputs!$D$50,Inputs!$B$52<=Inputs!$C$52,Inputs!$C$52<=Inputs!$D$52,Inputs!$B$76>=Inputs!$C$76,Inputs!$C$76>=Inputs!$D$76,Inputs!$B$77<=Inputs!$C$77,Inputs!$C$77<=Inputs!$D$77,Inputs!$B$78<=Inputs!$C$78,Inputs!$C$78<=Inputs!$D$78),"PASS","FAIL") -> PASS | C9: Low / Base / High ordered the right way for every growth and cost driver
A10: Gross margin within 0–100% | B10: =IF(AND(MIN('P&L'!$B$8:$D$8)>=0,MAX('P&L'!$B$8:$D$8)<=1),"PASS","FAIL") -> PASS | C10: Gross margin never negative or above 100%
A11: Loan balance never negative | B11: =IF(MIN(Monthly!$C$63:$AL$63)>=-0.5,"PASS","FAIL") -> PASS | C11: Repayments never exceed the loan
A12: Funding table ties to the cash flow | B12: =IF(ABS('Break-even'!B18-('Break-even'!B16-'Break-even'!B10))<0.5,"PASS","FAIL") -> PASS | C12: Lowest cash balance = sources of funds − uses of funds up to that point
A13: Valuation: discounting ties to NPV() | B13: =IF(ABS(Valuation!B23-NPV(Valuation!B6,Valuation!$B$17:$D$17))<0.5,"PASS","FAIL") -> PASS | C13: Sum of discounted free cash flows equals Excel's NPV of the same flows
A14: Valuation: WACC above terminal growth | B14: =IF(Valuation!B6>Valuation!B7,"PASS","FAIL") -> PASS | C14: The perpetual-growth formula needs WACC > g
A15: Valuation: sensitivity centre = enterprise value | B15: =IF(ABS(Valuation!D36-Valuation!B27)<0.5,"PASS","FAIL") -> PASS | C15: The middle of the WACC × growth table reproduces the headline value
A16: Valuation: final-year cash flow positive | B16: =IF(Valuation!$D$17>0,"PASS","WARN") -> PASS | C16: Business warning: a negative final-year cash flow gives a negative terminal value (often a 1-year plan still carrying start-up spending)
A17: Sources & uses balance | B17: =IF(ABS('Sources & Uses'!B21-'Sources & Uses'!B28)<0.5,"PASS","FAIL") -> PASS | C17: Sources of funds = uses of funds (incl. cash at the end) for the Sources & Uses period
A18: No error values | B18: =IF(SUMPRODUCT(--ISERROR(Monthly!$C$4:$AL$98))+SUMPRODUCT(--ISERROR(Headcount!$C$4:$AL$17))+SUMPRODUCT(--ISERROR('P&L'!$B$3:$D$26))+SUMPRODUCT(--ISERROR('Cash Flow'!$B$3:$D$18))+SUMPRODUCT(--ISERROR('Balance Sheet'!$B$3:$D$17))+SUMPRODUCT(--ISERROR(KPIs!$B$27:$D$48))+SUMPRODUCT(--ISERROR('Break-even'!$B$26:$D$33))+SUMPRODUCT(--ISERROR(Valuation!$B$14:$D$19))+SUMPRODUCT(--ISERROR('Break-even'!$B$3:$D$35))+SUMPRODUCT(--ISERROR(Valuation!$A$3:$F$40))+SUMPRODUCT(--ISERROR('Sources & Uses'!$B$3:$C$30))+SUMPRODUCT(--ISERROR(Dashboard!$A$6:$W$44))+SUMPRODUCT(--ISERROR(Summary!$A$5:$S$52))+SUMPRODUCT(--ISERROR(KPIs!$A$4:$E$48))=0,"PASS","FAIL") -> PASS | C18: No error values (divide-by-zero, broken references) on any calculation sheet
A19: Summary ties to statements | B19: =IF(IFERROR(AND(SUMPRODUCT(--(ABS(Summary!$B$7:$D$7-'P&L'!$B$5:$D$5)>0.5))=0,SUMPRODUCT(--(ABS(Summary!$B$19:$D$19-'P&L'!$B$25:$D$25)>0.5))=0,SUMPRODUCT(--(ABS(Summary!$B$31:$D$31-'Cash Flow'!$B$18:$D$18)>0.5))=0,SUMPRODUCT(--(ABS(Summary!$B$41:$D$41-'Balance Sheet'!$B$5:$D$5)>0.5))=0,ABS(SUM(Summary!$H$7:$S$7)-INDEX(Summary!$B$7:$D$7,Summary!$R$2))<0.5,ABS(SUM(Summary!$H$19:$S$19)-INDEX(Summary!$B$19:$D$19,Summary!$R$2))<0.5,ABS(Summary!$S$31-INDEX(Summary!$B$31:$D$31,Summary!$R$2))<0.5),FALSE()),"PASS","FAIL") -> PASS | C19: Summary revenue, net income and closing cash equal the statements every year; the detailed year adds up to its annual figure
A20: DuPont ties to return on equity | B20: =IF(SUMPRODUCT(--(ABS(KPIs!$B$24:$D$24)>0.000000001))>0,"FAIL",IF(SUMPRODUCT(ISNUMBER(KPIs!$B$23:$D$23)*ISNUMBER(KPIs!$B$16:$D$16))=0,"n/a","PASS")) -> PASS | C20: Net margin × asset turnover × equity multiplier equals return on equity every year; n/a = no year where both are defined (a one-sided n/a is a FAIL)
A21: Balance sheet balances every period | B21: =IF(SUMPRODUCT(--(ABS(Monthly!$C$98:$AL$98)>0.5))=0,"PASS","FAIL") -> PASS | C21: Assets = liabilities + equity in every period
A22: Funding sufficient (cash ≥ 0) | B22: =IF(MIN(Monthly!$C$80:$AL$80)>=0,"PASS","WARN") -> PASS | C22: Business warning, not an error: cash dips below zero in this scenario
A24: Overall verdict | B24: =IF(COUNTIF(B4:B22,"FAIL")>0,"FAIL",IF(COUNTIF(B4:B22,"WARN")>0,"PASS WITH WARNINGS","PASS")) -> PASS
