Workbook

Sheet Cover
B2: Bakery financial model (growing)
B3: 5-year financial model · monthly detail · Low / Base / High scenarios · US dollars · Full plan
B5: Purpose | D5: Revenue and profit plan
B6: Active scenario | D6: =Dashboard!C4&" (change it on the Dashboard, cell B4)" -> Base (change it on the Dashboard, cell B4)
B7: Model checks | D7: =Checks!B25 -> PASS
B8: Prepared | D8: 21 October 2026
B10: Contents
C11: PRESENTATION
B12: 1 | C12: =HYPERLINK("#Dashboard!A1","Dashboard") -> Dashboard | D12: Scenario switch, key numbers, core financials
B13: 2 | C13: =HYPERLINK("#Summary!A1","Summary") -> Summary | D13: Income statement, cash flow and balance sheet — every year and any year by month
B14: 3 | C14: =HYPERLINK("#Scenarios!A1","Scenarios") -> Scenarios | D14: Low / Base / High side by side: drivers, outputs, charts
B15: 4 | C15: =HYPERLINK("#'Break-even'!A1","Break-even") -> Break-even | D15: Startup costs, funding need, break-even timing and revenue
B16: 5 | C16: =HYPERLINK("#Valuation!A1","Valuation") -> Valuation | D16: Free cash flow, DCF (perpetual growth and exit multiple), WACC × growth sensitivity
B17: 6 | C17: =HYPERLINK("#'Sources & Uses'!A1","Sources & Uses") -> Sources & Uses | D17: Funding structure, sources and uses of cash for the first months
B18: 7 | C18: =HYPERLINK("#KPIs!A1","KPIs") -> KPIs | D18: Financial ratios, DuPont analysis, industry metrics
C19: INPUTS
B20: 8 | C20: =HYPERLINK("#Inputs!A1","Inputs") -> Inputs | D20: Every assumption, Low / Base / High, with units and comments
C21: STATEMENTS
B22: 9 | C22: =HYPERLINK("#'P&L'!A1","P&L") -> P&L | D22: Annual profit & loss
B23: 10 | C23: =HYPERLINK("#'Cash Flow'!A1","Cash Flow") -> Cash Flow | D23: Annual cash flow statement
B24: 11 | C24: =HYPERLINK("#'Balance Sheet'!A1","Balance Sheet") -> Balance Sheet | D24: Balance sheet at year end
C25: CALCULATIONS
B26: 12 | C26: =HYPERLINK("#Monthly!A1","Monthly") -> Monthly | D26: Month-by-month engine of the model
B27: 13 | C27: =HYPERLINK("#Headcount!A1","Headcount") -> Headcount | D27: Team and payroll
B28: 14 | C28: =HYPERLINK("#'Scenario calc'!A1","Scenario calc") -> Scenario calc | D28: Low, Base and High calculated side by side for the Scenarios sheet
C29: CONTROL
B30: 15 | C30: =HYPERLINK("#Checks!A1","Checks") -> Checks | D30: Live integrity checks and the overall verdict
B32: How to read this file
C33: 1000 | D33: Input you can change — yellow cell with a blue figure (Inputs sheet and the view switches)
C34: 1000 | D34: Formula — calculated, do not overwrite
C35: 1000 | D35: Link to another sheet
C36: 1000 | D36: Active value the model uses (follows the scenario)

Sheet Dashboard
A1: Dashboard | W1: =HYPERLINK("#'Cover'!A1","◂ Contents") -> ◂ Contents
A2: Bakery financial model (growing)
A4: Active scenario | B4: 2 | C4: =CHOOSE(B4,"Low","Base","High") -> Base | D4: 1 = Low · 2 = Base · 3 = High — every sheet follows this cell | S4: Model checks | T4: =Checks!B25 -> PASS
A6: REVENUE · YEAR 5 | C6: EBITDA MARGIN · YEAR 5 | H6: NET INCOME · YEAR 5 | L6: LOWEST CASH BALANCE | P6: FUNDING REQUIRED | T6: ENTERPRISE VALUE (DCF)
A7: =F12 -> 2250134.1 | C7: =F17 -> 0.1467825 | H7: =F18 -> 244541.73 | L7: =F39 -> 35320.959 | P7: =F37 -> 337679.04 | T7: =F44 -> 1316371.7
A8: =IF(AND(B12>0,F12>=0),(F12/B12)^(1/4)-1,"CAGR n/a") -> 0.092852837 | C8: =F16 -> 330280.3 | H8: =F19 -> 0.10867874 | L8: ='Break-even'!B6 -> 1 | P8: =IF(F38>=0,"Covered by funding raised",-F38) -> 197679.04 | T8: Average of 2 methods
A10: Core financials ($'000) — active scenario
B11: 1 | C11: 2 | D11: 3 | E11: 4 | F11: 5
A12: Revenue | B12: =SUMIF(Monthly!$C$5:$BJ$5,B$11,Monthly!$C$22:$BJ$22) -> 1577472 | C12: =SUMIF(Monthly!$C$5:$BJ$5,C$11,Monthly!$C$22:$BJ$22) -> 1736372.4 | D12: =SUMIF(Monthly!$C$5:$BJ$5,D$11,Monthly!$C$22:$BJ$22) -> 1890162.9 | E12: =SUMIF(Monthly!$C$5:$BJ$5,E$11,Monthly!$C$22:$BJ$22) -> 2060699 | F12: =SUMIF(Monthly!$C$5:$BJ$5,F$11,Monthly!$C$22:$BJ$22) -> 2250134.1
A13: Gross profit | B13: =SUMIF(Monthly!$C$5:$BJ$5,B$11,Monthly!$C$29:$BJ$29) -> 1076825.1 | C13: =SUMIF(Monthly!$C$5:$BJ$5,C$11,Monthly!$C$29:$BJ$29) -> 1183311.2 | D13: =SUMIF(Monthly!$C$5:$BJ$5,D$11,Monthly!$C$29:$BJ$29) -> 1285883.7 | E13: =SUMIF(Monthly!$C$5:$BJ$5,E$11,Monthly!$C$29:$BJ$29) -> 1399389 | F13: =SUMIF(Monthly!$C$5:$BJ$5,F$11,Monthly!$C$29:$BJ$29) -> 1525212.7
A14: Gross margin | B14: =IF(B12=0,0,B13/B12) -> 0.68262706 | C14: =IF(C12=0,0,C13/C12) -> 0.68148469 | D14: =IF(D12=0,0,D13/D12) -> 0.68030311 | E14: =IF(E12=0,0,E13/E12) -> 0.67908462 | F14: =IF(F12=0,0,F13/F12) -> 0.67783194
A15: Operating expenses | B15: =SUMIF(Monthly!$C$5:$BJ$5,B$11,Monthly!$C$40:$BJ$40) -> -931468.06 | C15: =SUMIF(Monthly!$C$5:$BJ$5,C$11,Monthly!$C$40:$BJ$40) -> -990021.96 | D15: =SUMIF(Monthly!$C$5:$BJ$5,D$11,Monthly!$C$40:$BJ$40) -> -1052480.5 | E15: =SUMIF(Monthly!$C$5:$BJ$5,E$11,Monthly!$C$40:$BJ$40) -> -1120604.2 | F15: =SUMIF(Monthly!$C$5:$BJ$5,F$11,Monthly!$C$40:$BJ$40) -> -1194932.4
A16: EBITDA | B16: =SUMIF(Monthly!$C$5:$BJ$5,B$11,Monthly!$C$41:$BJ$41) -> 145357.01 | C16: =SUMIF(Monthly!$C$5:$BJ$5,C$11,Monthly!$C$41:$BJ$41) -> 193289.21 | D16: =SUMIF(Monthly!$C$5:$BJ$5,D$11,Monthly!$C$41:$BJ$41) -> 233403.12 | E16: =SUMIF(Monthly!$C$5:$BJ$5,E$11,Monthly!$C$41:$BJ$41) -> 278784.79 | F16: =SUMIF(Monthly!$C$5:$BJ$5,F$11,Monthly!$C$41:$BJ$41) -> 330280.3
A17: EBITDA margin | B17: =IF(B12=0,0,B16/B12) -> 0.092145541 | C17: =IF(C12=0,0,C16/C12) -> 0.11131783 | D17: =IF(D12=0,0,D16/D12) -> 0.12348307 | E17: =IF(E12=0,0,E16/E12) -> 0.13528652 | F17: =IF(F12=0,0,F16/F12) -> 0.1467825
A18: Net income | B18: =SUMIF(Monthly!$C$5:$BJ$5,B$11,Monthly!$C$50:$BJ$50) -> 99754.292 | C18: =SUMIF(Monthly!$C$5:$BJ$5,C$11,Monthly!$C$50:$BJ$50) -> 137835.57 | D18: =SUMIF(Monthly!$C$5:$BJ$5,D$11,Monthly!$C$50:$BJ$50) -> 169019.96 | E18: =SUMIF(Monthly!$C$5:$BJ$5,E$11,Monthly!$C$50:$BJ$50) -> 204365.88 | F18: =SUMIF(Monthly!$C$5:$BJ$5,F$11,Monthly!$C$50:$BJ$50) -> 244541.73
A19: Net margin | B19: =IF(B12=0,0,B18/B12) -> 0.063236807 | C19: =IF(C12=0,0,C18/C12) -> 0.079381341 | D19: =IF(D12=0,0,D18/D12) -> 0.089420843 | E19: =IF(E12=0,0,E18/E12) -> 0.099173086 | F19: =IF(F12=0,0,F18/F12) -> 0.10867874
A20: Operating cash flow | B20: =SUMIF(Monthly!$C$5:$BJ$5,B$11,Monthly!$C$74:$BJ$74) -> 90917.287 | C20: =SUMIF(Monthly!$C$5:$BJ$5,C$11,Monthly!$C$74:$BJ$74) -> 150047.06 | D20: =SUMIF(Monthly!$C$5:$BJ$5,D$11,Monthly!$C$74:$BJ$74) -> 183063.52 | E20: =SUMIF(Monthly!$C$5:$BJ$5,E$11,Monthly!$C$74:$BJ$74) -> 220221.66 | F20: =SUMIF(Monthly!$C$5:$BJ$5,F$11,Monthly!$C$74:$BJ$74) -> 262187.19
A21: Investing cash flow | B21: =SUMIF(Monthly!$C$5:$BJ$5,B$11,Monthly!$C$75:$BJ$75) -> -90000 | C21: =SUMIF(Monthly!$C$5:$BJ$5,C$11,Monthly!$C$75:$BJ$75) -> -14000 | D21: =SUMIF(Monthly!$C$5:$BJ$5,D$11,Monthly!$C$75:$BJ$75) -> -14000 | E21: =SUMIF(Monthly!$C$5:$BJ$5,E$11,Monthly!$C$75:$BJ$75) -> -14000 | F21: =SUMIF(Monthly!$C$5:$BJ$5,F$11,Monthly!$C$75:$BJ$75) -> -14000
A22: Financing cash flow | B22: =SUMIF(Monthly!$C$5:$BJ$5,B$11,Monthly!$C$77:$BJ$77) -> 125333.33 | C22: =SUMIF(Monthly!$C$5:$BJ$5,C$11,Monthly!$C$77:$BJ$77) -> -16000 | D22: =SUMIF(Monthly!$C$5:$BJ$5,D$11,Monthly!$C$77:$BJ$77) -> -16000 | E22: =SUMIF(Monthly!$C$5:$BJ$5,E$11,Monthly!$C$77:$BJ$77) -> -16000 | F22: =SUMIF(Monthly!$C$5:$BJ$5,F$11,Monthly!$C$77:$BJ$77) -> -16000
A23: Net change in cash | B23: =SUMIF(Monthly!$C$5:$BJ$5,B$11,Monthly!$C$78:$BJ$78) -> 126250.62 | C23: =SUMIF(Monthly!$C$5:$BJ$5,C$11,Monthly!$C$78:$BJ$78) -> 120047.06 | D23: =SUMIF(Monthly!$C$5:$BJ$5,D$11,Monthly!$C$78:$BJ$78) -> 153063.52 | E23: =SUMIF(Monthly!$C$5:$BJ$5,E$11,Monthly!$C$78:$BJ$78) -> 190221.66 | F23: =SUMIF(Monthly!$C$5:$BJ$5,F$11,Monthly!$C$78:$BJ$78) -> 232187.19
A24: Year-end cash | B24: =INDEX(Monthly!$C$80:$BJ$80,B$11*12) -> 126250.62 | C24: =INDEX(Monthly!$C$80:$BJ$80,C$11*12) -> 246297.68 | D24: =INDEX(Monthly!$C$80:$BJ$80,D$11*12) -> 399361.2 | E24: =INDEX(Monthly!$C$80:$BJ$80,E$11*12) -> 589582.86 | F24: =INDEX(Monthly!$C$80:$BJ$80,F$11*12) -> 821770.05
A26: Bakery metrics
B27: 1 | C27: 2 | D27: 3 | E27: 4 | F27: 5
A28: Retail counter revenue | B28: =KPIs!B35 -> 1133808 | C28: =KPIs!C35 -> 1218082.9 | D28: =KPIs!D35 -> 1292264.2 | E28: =KPIs!E35 -> 1370963.1 | F28: =KPIs!F35 -> 1454454.7
A29: Wholesale revenue | B29: =KPIs!B36 -> 443664 | C29: =KPIs!C36 -> 518289.41 | D29: =KPIs!D36 -> 597898.66 | E29: =KPIs!E36 -> 689735.9 | F29: =KPIs!F36 -> 795679.33
A30: Customers per day (average) | B30: =KPIs!B31 -> 316 | C30: =KPIs!C31 -> 329.6 | D30: =KPIs!D31 -> 339.488 | E30: =KPIs!E31 -> 349.67264 | F30: =KPIs!F31 -> 360.16282
A31: Wholesale accounts | B31: =KPIs!B33 -> 16 | C31: =KPIs!C33 -> 17.92 | D31: =KPIs!D33 -> 20.0704 | E31: =KPIs!E33 -> 22.478848 | F31: =KPIs!F33 -> 25.17631
A32: Team (FTE, year end) | B32: =INDEX(Headcount!$C$11:$BJ$11,B$27*12) -> 13.5 | C32: =INDEX(Headcount!$C$11:$BJ$11,C$27*12) -> 14.22 | D32: =INDEX(Headcount!$C$11:$BJ$11,D$27*12) -> 14.9832 | E32: =INDEX(Headcount!$C$11:$BJ$11,E$27*12) -> 15.792192 | F32: =INDEX(Headcount!$C$11:$BJ$11,F$27*12) -> 16.649724
A34: Funding & valuation ($'000) — active scenario
A35: Equity raised | F35: =Inputs!$E$58 -> 60000
A36: Loan drawn | F36: =Inputs!$E$59 -> 80000
A37: Funding required (incl. cash buffer) | F37: ='Break-even'!B12 -> 337679.04
A38: Funding surplus / (shortfall) | F38: ='Break-even'!B17 -> -197679.04
A39: ="Lowest cash balance (month "&'Break-even'!B6&")" -> Lowest cash balance (month 1) | F39: ='Break-even'!B18 -> 35320.959
A40: First month with positive EBITDA | F40: ='Break-even'!B21 -> 1
A41: Cash invested paid back | F41: ='Break-even'!B23 -> 12
A42: Enterprise value — perpetual growth | F42: =Valuation!B27 -> 1315477.9
A43: Enterprise value — exit multiple | F43: =Valuation!C27 -> 1317265.5
A44: Enterprise value — average | F44: =Valuation!B30 -> 1316371.7

Sheet Summary
A1: Financial statements summary | U1: =HYPERLINK("#'Cover'!A1","◂ Contents") -> ◂ Contents
A2: Bakery financial model (growing) | P2: Select detailed year: | R2: 1
A5: Income statement ($'000) — by year | H5: ="Income statement ($'000) — Year "&$R$2&", by month" -> Income statement ($'000) — Year 1, by month
B6: 1 | C6: 2 | D6: 3 | E6: 4 | F6: 5 | H6: =INDEX(Monthly!$C$4:$BJ$4,($R$2-1)*12+1) -> 1 | I6: =INDEX(Monthly!$C$4:$BJ$4,($R$2-1)*12+2) -> 2 | J6: =INDEX(Monthly!$C$4:$BJ$4,($R$2-1)*12+3) -> 3 | K6: =INDEX(Monthly!$C$4:$BJ$4,($R$2-1)*12+4) -> 4 | L6: =INDEX(Monthly!$C$4:$BJ$4,($R$2-1)*12+5) -> 5 | M6: =INDEX(Monthly!$C$4:$BJ$4,($R$2-1)*12+6) -> 6 | N6: =INDEX(Monthly!$C$4:$BJ$4,($R$2-1)*12+7) -> 7 | O6: =INDEX(Monthly!$C$4:$BJ$4,($R$2-1)*12+8) -> 8 | P6: =INDEX(Monthly!$C$4:$BJ$4,($R$2-1)*12+9) -> 9 | Q6: =INDEX(Monthly!$C$4:$BJ$4,($R$2-1)*12+10) -> 10 | R6: =INDEX(Monthly!$C$4:$BJ$4,($R$2-1)*12+11) -> 11 | S6: =INDEX(Monthly!$C$4:$BJ$4,($R$2-1)*12+12) -> 12
A7: Revenue | B7: ='P&L'!B5 -> 1577472 | C7: ='P&L'!C5 -> 1736372.4 | D7: ='P&L'!D5 -> 1890162.9 | E7: ='P&L'!E5 -> 2060699 | F7: ='P&L'!F5 -> 2250134.1 | H7: =INDEX(Monthly!$C$22:$BJ$22,($R$2-1)*12+1) -> 115980.8 | I7: =INDEX(Monthly!$C$22:$BJ$22,($R$2-1)*12+2) -> 122636.8 | J7: =INDEX(Monthly!$C$22:$BJ$22,($R$2-1)*12+3) -> 129292.8 | K7: =INDEX(Monthly!$C$22:$BJ$22,($R$2-1)*12+4) -> 129292.8 | L7: =INDEX(Monthly!$C$22:$BJ$22,($R$2-1)*12+5) -> 129292.8 | M7: =INDEX(Monthly!$C$22:$BJ$22,($R$2-1)*12+6) -> 129292.8 | N7: =INDEX(Monthly!$C$22:$BJ$22,($R$2-1)*12+7) -> 129292.8 | O7: =INDEX(Monthly!$C$22:$BJ$22,($R$2-1)*12+8) -> 129292.8 | P7: =INDEX(Monthly!$C$22:$BJ$22,($R$2-1)*12+9) -> 129292.8 | Q7: =INDEX(Monthly!$C$22:$BJ$22,($R$2-1)*12+10) -> 129292.8 | R7: =INDEX(Monthly!$C$22:$BJ$22,($R$2-1)*12+11) -> 152256 | S7: =INDEX(Monthly!$C$22:$BJ$22,($R$2-1)*12+12) -> 152256
A8: Cost of sales | B8: ='P&L'!B6 -> -500646.93 | C8: ='P&L'!C6 -> -553061.18 | D8: ='P&L'!D6 -> -604279.19 | E8: ='P&L'!E6 -> -661309.99 | F8: ='P&L'!F6 -> -724921.33 | H8: =INDEX(Monthly!$C$28:$BJ$28,($R$2-1)*12+1) -> -36880.494 | I8: =INDEX(Monthly!$C$28:$BJ$28,($R$2-1)*12+2) -> -38992.928 | J8: =INDEX(Monthly!$C$28:$BJ$28,($R$2-1)*12+3) -> -41105.362 | K8: =INDEX(Monthly!$C$28:$BJ$28,($R$2-1)*12+4) -> -41105.362 | L8: =INDEX(Monthly!$C$28:$BJ$28,($R$2-1)*12+5) -> -41105.362 | M8: =INDEX(Monthly!$C$28:$BJ$28,($R$2-1)*12+6) -> -41105.362 | N8: =INDEX(Monthly!$C$28:$BJ$28,($R$2-1)*12+7) -> -41105.362 | O8: =INDEX(Monthly!$C$28:$BJ$28,($R$2-1)*12+8) -> -41105.362 | P8: =INDEX(Monthly!$C$28:$BJ$28,($R$2-1)*12+9) -> -41105.362 | Q8: =INDEX(Monthly!$C$28:$BJ$28,($R$2-1)*12+10) -> -41105.362 | R8: =INDEX(Monthly!$C$28:$BJ$28,($R$2-1)*12+11) -> -47965.303 | S8: =INDEX(Monthly!$C$28:$BJ$28,($R$2-1)*12+12) -> -47965.303
A9: Gross profit | B9: ='P&L'!B7 -> 1076825.1 | C9: ='P&L'!C7 -> 1183311.2 | D9: ='P&L'!D7 -> 1285883.7 | E9: ='P&L'!E7 -> 1399389 | F9: ='P&L'!F7 -> 1525212.7 | H9: =INDEX(Monthly!$C$29:$BJ$29,($R$2-1)*12+1) -> 79100.306 | I9: =INDEX(Monthly!$C$29:$BJ$29,($R$2-1)*12+2) -> 83643.872 | J9: =INDEX(Monthly!$C$29:$BJ$29,($R$2-1)*12+3) -> 88187.438 | K9: =INDEX(Monthly!$C$29:$BJ$29,($R$2-1)*12+4) -> 88187.438 | L9: =INDEX(Monthly!$C$29:$BJ$29,($R$2-1)*12+5) -> 88187.438 | M9: =INDEX(Monthly!$C$29:$BJ$29,($R$2-1)*12+6) -> 88187.438 | N9: =INDEX(Monthly!$C$29:$BJ$29,($R$2-1)*12+7) -> 88187.438 | O9: =INDEX(Monthly!$C$29:$BJ$29,($R$2-1)*12+8) -> 88187.438 | P9: =INDEX(Monthly!$C$29:$BJ$29,($R$2-1)*12+9) -> 88187.438 | Q9: =INDEX(Monthly!$C$29:$BJ$29,($R$2-1)*12+10) -> 88187.438 | R9: =INDEX(Monthly!$C$29:$BJ$29,($R$2-1)*12+11) -> 104290.7 | S9: =INDEX(Monthly!$C$29:$BJ$29,($R$2-1)*12+12) -> 104290.7
A10: Gross margin | B10: ='P&L'!B8 -> 0.68262706 | C10: ='P&L'!C8 -> 0.68148469 | D10: ='P&L'!D8 -> 0.68030311 | E10: ='P&L'!E8 -> 0.67908462 | F10: ='P&L'!F8 -> 0.67783194 | H10: =IF(H7=0,0,H9/H7) -> 0.68201208 | I10: =IF(I7=0,0,I9/I7) -> 0.68204545 | J10: =IF(J7=0,0,J9/J7) -> 0.6820754 | K10: =IF(K7=0,0,K9/K7) -> 0.6820754 | L10: =IF(L7=0,0,L9/L7) -> 0.6820754 | M10: =IF(M7=0,0,M9/M7) -> 0.6820754 | N10: =IF(N7=0,0,N9/N7) -> 0.6820754 | O10: =IF(O7=0,0,O9/O7) -> 0.6820754 | ... S10: =IF(S7=0,0,S9/S7) -> 0.68496937
A11: Total operating expenses | B11: ='P&L'!B17 -> -931468.06 | C11: ='P&L'!C17 -> -990021.96 | D11: ='P&L'!D17 -> -1052480.5 | E11: ='P&L'!E17 -> -1120604.2 | F11: ='P&L'!F17 -> -1194932.4 | H11: =INDEX(Monthly!$C$40:$BJ$40,($R$2-1)*12+1) -> -76698.257 | I11: =INDEX(Monthly!$C$40:$BJ$40,($R$2-1)*12+2) -> -77121.329 | J11: =INDEX(Monthly!$C$40:$BJ$40,($R$2-1)*12+3) -> -77544.401 | K11: =INDEX(Monthly!$C$40:$BJ$40,($R$2-1)*12+4) -> -77544.401 | L11: =INDEX(Monthly!$C$40:$BJ$40,($R$2-1)*12+5) -> -77544.401 | M11: =INDEX(Monthly!$C$40:$BJ$40,($R$2-1)*12+6) -> -77544.401 | N11: =INDEX(Monthly!$C$40:$BJ$40,($R$2-1)*12+7) -> -77544.401 | O11: =INDEX(Monthly!$C$40:$BJ$40,($R$2-1)*12+8) -> -77544.401 | P11: =INDEX(Monthly!$C$40:$BJ$40,($R$2-1)*12+9) -> -77544.401 | Q11: =INDEX(Monthly!$C$40:$BJ$40,($R$2-1)*12+10) -> -77544.401 | R11: =INDEX(Monthly!$C$40:$BJ$40,($R$2-1)*12+11) -> -78646.635 | S11: =INDEX(Monthly!$C$40:$BJ$40,($R$2-1)*12+12) -> -78646.635
A12: EBITDA | B12: ='P&L'!B18 -> 145357.01 | C12: ='P&L'!C18 -> 193289.21 | D12: ='P&L'!D18 -> 233403.12 | E12: ='P&L'!E18 -> 278784.79 | F12: ='P&L'!F18 -> 330280.3 | H12: =INDEX(Monthly!$C$41:$BJ$41,($R$2-1)*12+1) -> 2402.0492 | I12: =INDEX(Monthly!$C$41:$BJ$41,($R$2-1)*12+2) -> 6522.5429 | J12: =INDEX(Monthly!$C$41:$BJ$41,($R$2-1)*12+3) -> 10643.037 | K12: =INDEX(Monthly!$C$41:$BJ$41,($R$2-1)*12+4) -> 10643.037 | L12: =INDEX(Monthly!$C$41:$BJ$41,($R$2-1)*12+5) -> 10643.037 | M12: =INDEX(Monthly!$C$41:$BJ$41,($R$2-1)*12+6) -> 10643.037 | N12: =INDEX(Monthly!$C$41:$BJ$41,($R$2-1)*12+7) -> 10643.037 | O12: =INDEX(Monthly!$C$41:$BJ$41,($R$2-1)*12+8) -> 10643.037 | P12: =INDEX(Monthly!$C$41:$BJ$41,($R$2-1)*12+9) -> 10643.037 | Q12: =INDEX(Monthly!$C$41:$BJ$41,($R$2-1)*12+10) -> 10643.037 | R12: =INDEX(Monthly!$C$41:$BJ$41,($R$2-1)*12+11) -> 25644.062 | S12: =INDEX(Monthly!$C$41:$BJ$41,($R$2-1)*12+12) -> 25644.062
A13: EBITDA margin | B13: ='P&L'!B19 -> 0.092145541 | C13: ='P&L'!C19 -> 0.11131783 | D13: ='P&L'!D19 -> 0.12348307 | E13: ='P&L'!E19 -> 0.13528652 | F13: ='P&L'!F19 -> 0.1467825 | H13: =IF(H7=0,0,H12/H7) -> 0.020710749 | I13: =IF(I7=0,0,I12/I7) -> 0.053185854 | J13: =IF(J7=0,0,J12/J7) -> 0.082317319 | K13: =IF(K7=0,0,K12/K7) -> 0.082317319 | L13: =IF(L7=0,0,L12/L7) -> 0.082317319 | M13: =IF(M7=0,0,M12/M7) -> 0.082317319 | N13: =IF(N7=0,0,N12/N7) -> 0.082317319 | O13: =IF(O7=0,0,O12/O7) -> 0.082317319 | ... S13: =IF(S7=0,0,S12/S7) -> 0.16842727
A14: Depreciation | B14: ='P&L'!B20 -> -12857.143 | C14: ='P&L'!C20 -> -13940.476 | D14: ='P&L'!D20 -> -15940.476 | E14: ='P&L'!E20 -> -17940.476 | F14: ='P&L'!F20 -> -19940.476 | H14: =INDEX(Monthly!$C$55:$BJ$55,($R$2-1)*12+1) -> -1071.4286 | I14: =INDEX(Monthly!$C$55:$BJ$55,($R$2-1)*12+2) -> -1071.4286 | J14: =INDEX(Monthly!$C$55:$BJ$55,($R$2-1)*12+3) -> -1071.4286 | K14: =INDEX(Monthly!$C$55:$BJ$55,($R$2-1)*12+4) -> -1071.4286 | L14: =INDEX(Monthly!$C$55:$BJ$55,($R$2-1)*12+5) -> -1071.4286 | M14: =INDEX(Monthly!$C$55:$BJ$55,($R$2-1)*12+6) -> -1071.4286 | N14: =INDEX(Monthly!$C$55:$BJ$55,($R$2-1)*12+7) -> -1071.4286 | O14: =INDEX(Monthly!$C$55:$BJ$55,($R$2-1)*12+8) -> -1071.4286 | P14: =INDEX(Monthly!$C$55:$BJ$55,($R$2-1)*12+9) -> -1071.4286 | Q14: =INDEX(Monthly!$C$55:$BJ$55,($R$2-1)*12+10) -> -1071.4286 | R14: =INDEX(Monthly!$C$55:$BJ$55,($R$2-1)*12+11) -> -1071.4286 | S14: =INDEX(Monthly!$C$55:$BJ$55,($R$2-1)*12+12) -> -1071.4286
A15: EBIT | B15: ='P&L'!B21 -> 132499.87 | C15: ='P&L'!C21 -> 179348.73 | D15: ='P&L'!D21 -> 217462.64 | E15: ='P&L'!E21 -> 260844.32 | F15: ='P&L'!F21 -> 310339.82 | H15: =INDEX(Monthly!$C$44:$BJ$44,($R$2-1)*12+1) -> 1330.6206 | I15: =INDEX(Monthly!$C$44:$BJ$44,($R$2-1)*12+2) -> 5451.1144 | J15: =INDEX(Monthly!$C$44:$BJ$44,($R$2-1)*12+3) -> 9571.6081 | K15: =INDEX(Monthly!$C$44:$BJ$44,($R$2-1)*12+4) -> 9571.6081 | L15: =INDEX(Monthly!$C$44:$BJ$44,($R$2-1)*12+5) -> 9571.6081 | M15: =INDEX(Monthly!$C$44:$BJ$44,($R$2-1)*12+6) -> 9571.6081 | N15: =INDEX(Monthly!$C$44:$BJ$44,($R$2-1)*12+7) -> 9571.6081 | O15: =INDEX(Monthly!$C$44:$BJ$44,($R$2-1)*12+8) -> 9571.6081 | P15: =INDEX(Monthly!$C$44:$BJ$44,($R$2-1)*12+9) -> 9571.6081 | Q15: =INDEX(Monthly!$C$44:$BJ$44,($R$2-1)*12+10) -> 9571.6081 | R15: =INDEX(Monthly!$C$44:$BJ$44,($R$2-1)*12+11) -> 24572.634 | S15: =INDEX(Monthly!$C$44:$BJ$44,($R$2-1)*12+12) -> 24572.634
A16: Interest | B16: ='P&L'!B22 -> -6228.6111 | C16: ='P&L'!C22 -> -4873.3333 | D16: ='P&L'!D22 -> -3513.3333 | E16: ='P&L'!E22 -> -2153.3333 | F16: ='P&L'!F22 -> -793.33333 | H16: =INDEX(Monthly!$C$45:$BJ$45,($R$2-1)*12+1) -> -566.66667 | I16: =INDEX(Monthly!$C$45:$BJ$45,($R$2-1)*12+2) -> -561.94444 | J16: =INDEX(Monthly!$C$45:$BJ$45,($R$2-1)*12+3) -> -552.5 | K16: =INDEX(Monthly!$C$45:$BJ$45,($R$2-1)*12+4) -> -543.05556 | L16: =INDEX(Monthly!$C$45:$BJ$45,($R$2-1)*12+5) -> -533.61111 | M16: =INDEX(Monthly!$C$45:$BJ$45,($R$2-1)*12+6) -> -524.16667 | N16: =INDEX(Monthly!$C$45:$BJ$45,($R$2-1)*12+7) -> -514.72222 | O16: =INDEX(Monthly!$C$45:$BJ$45,($R$2-1)*12+8) -> -505.27778 | P16: =INDEX(Monthly!$C$45:$BJ$45,($R$2-1)*12+9) -> -495.83333 | Q16: =INDEX(Monthly!$C$45:$BJ$45,($R$2-1)*12+10) -> -486.38889 | R16: =INDEX(Monthly!$C$45:$BJ$45,($R$2-1)*12+11) -> -476.94444 | S16: =INDEX(Monthly!$C$45:$BJ$45,($R$2-1)*12+12) -> -467.5
A17: Pre-tax income | B17: ='P&L'!B23 -> 126271.26 | C17: ='P&L'!C23 -> 174475.4 | D17: ='P&L'!D23 -> 213949.31 | E17: ='P&L'!E23 -> 258690.98 | F17: ='P&L'!F23 -> 309546.49 | H17: =INDEX(Monthly!$C$46:$BJ$46,($R$2-1)*12+1) -> 763.95398 | I17: =INDEX(Monthly!$C$46:$BJ$46,($R$2-1)*12+2) -> 4889.1699 | J17: =INDEX(Monthly!$C$46:$BJ$46,($R$2-1)*12+3) -> 9019.1081 | K17: =INDEX(Monthly!$C$46:$BJ$46,($R$2-1)*12+4) -> 9028.5525 | L17: =INDEX(Monthly!$C$46:$BJ$46,($R$2-1)*12+5) -> 9037.997 | M17: =INDEX(Monthly!$C$46:$BJ$46,($R$2-1)*12+6) -> 9047.4414 | N17: =INDEX(Monthly!$C$46:$BJ$46,($R$2-1)*12+7) -> 9056.8859 | O17: =INDEX(Monthly!$C$46:$BJ$46,($R$2-1)*12+8) -> 9066.3303 | P17: =INDEX(Monthly!$C$46:$BJ$46,($R$2-1)*12+9) -> 9075.7747 | Q17: =INDEX(Monthly!$C$46:$BJ$46,($R$2-1)*12+10) -> 9085.2192 | R17: =INDEX(Monthly!$C$46:$BJ$46,($R$2-1)*12+11) -> 24095.689 | S17: =INDEX(Monthly!$C$46:$BJ$46,($R$2-1)*12+12) -> 24105.134
A18: Income tax | B18: ='P&L'!B24 -> -26516.964 | C18: ='P&L'!C24 -> -36639.834 | D18: ='P&L'!D24 -> -44929.355 | E18: ='P&L'!E24 -> -54325.106 | F18: ='P&L'!F24 -> -65004.763 | H18: =INDEX(Monthly!$C$49:$BJ$49,($R$2-1)*12+1) -> -160.43034 | I18: =INDEX(Monthly!$C$49:$BJ$49,($R$2-1)*12+2) -> -1026.7257 | J18: =INDEX(Monthly!$C$49:$BJ$49,($R$2-1)*12+3) -> -1894.0127 | K18: =INDEX(Monthly!$C$49:$BJ$49,($R$2-1)*12+4) -> -1895.996 | L18: =INDEX(Monthly!$C$49:$BJ$49,($R$2-1)*12+5) -> -1897.9794 | M18: =INDEX(Monthly!$C$49:$BJ$49,($R$2-1)*12+6) -> -1899.9627 | N18: =INDEX(Monthly!$C$49:$BJ$49,($R$2-1)*12+7) -> -1901.946 | O18: =INDEX(Monthly!$C$49:$BJ$49,($R$2-1)*12+8) -> -1903.9294 | P18: =INDEX(Monthly!$C$49:$BJ$49,($R$2-1)*12+9) -> -1905.9127 | Q18: =INDEX(Monthly!$C$49:$BJ$49,($R$2-1)*12+10) -> -1907.896 | R18: =INDEX(Monthly!$C$49:$BJ$49,($R$2-1)*12+11) -> -5060.0948 | S18: =INDEX(Monthly!$C$49:$BJ$49,($R$2-1)*12+12) -> -5062.0781
A19: Net income | B19: ='P&L'!B25 -> 99754.292 | C19: ='P&L'!C25 -> 137835.57 | D19: ='P&L'!D25 -> 169019.96 | E19: ='P&L'!E25 -> 204365.88 | F19: ='P&L'!F25 -> 244541.73 | H19: =INDEX(Monthly!$C$50:$BJ$50,($R$2-1)*12+1) -> 603.52364 | I19: =INDEX(Monthly!$C$50:$BJ$50,($R$2-1)*12+2) -> 3862.4442 | J19: =INDEX(Monthly!$C$50:$BJ$50,($R$2-1)*12+3) -> 7125.0954 | K19: =INDEX(Monthly!$C$50:$BJ$50,($R$2-1)*12+4) -> 7132.5565 | L19: =INDEX(Monthly!$C$50:$BJ$50,($R$2-1)*12+5) -> 7140.0176 | M19: =INDEX(Monthly!$C$50:$BJ$50,($R$2-1)*12+6) -> 7147.4787 | N19: =INDEX(Monthly!$C$50:$BJ$50,($R$2-1)*12+7) -> 7154.9398 | O19: =INDEX(Monthly!$C$50:$BJ$50,($R$2-1)*12+8) -> 7162.4009 | P19: =INDEX(Monthly!$C$50:$BJ$50,($R$2-1)*12+9) -> 7169.862 | Q19: =INDEX(Monthly!$C$50:$BJ$50,($R$2-1)*12+10) -> 7177.3232 | R19: =INDEX(Monthly!$C$50:$BJ$50,($R$2-1)*12+11) -> 19035.595 | S19: =INDEX(Monthly!$C$50:$BJ$50,($R$2-1)*12+12) -> 19043.056
A20: Net margin | B20: ='P&L'!B26 -> 0.063236807 | C20: ='P&L'!C26 -> 0.079381341 | D20: ='P&L'!D26 -> 0.089420843 | E20: ='P&L'!E26 -> 0.099173086 | F20: ='P&L'!F26 -> 0.10867874 | H20: =IF(H7=0,0,H19/H7) -> 0.0052036513 | I20: =IF(I7=0,0,I19/I7) -> 0.031494985 | J20: =IF(J7=0,0,J19/J7) -> 0.055108215 | K20: =IF(K7=0,0,K19/K7) -> 0.055165922 | L20: =IF(L7=0,0,L19/L7) -> 0.055223629 | M20: =IF(M7=0,0,M19/M7) -> 0.055281336 | N20: =IF(N7=0,0,N19/N7) -> 0.055339043 | O20: =IF(O7=0,0,O19/O7) -> 0.05539675 | ... S20: =IF(S7=0,0,S19/S7) -> 0.12507261
A22: Cash flow ($'000) — by year | H22: ="Cash flow ($'000) — Year "&$R$2&", by month" -> Cash flow ($'000) — Year 1, by month
B23: 1 | C23: 2 | D23: 3 | E23: 4 | F23: 5 | H23: =INDEX(Monthly!$C$4:$BJ$4,($R$2-1)*12+1) -> 1 | I23: =INDEX(Monthly!$C$4:$BJ$4,($R$2-1)*12+2) -> 2 | J23: =INDEX(Monthly!$C$4:$BJ$4,($R$2-1)*12+3) -> 3 | K23: =INDEX(Monthly!$C$4:$BJ$4,($R$2-1)*12+4) -> 4 | L23: =INDEX(Monthly!$C$4:$BJ$4,($R$2-1)*12+5) -> 5 | M23: =INDEX(Monthly!$C$4:$BJ$4,($R$2-1)*12+6) -> 6 | N23: =INDEX(Monthly!$C$4:$BJ$4,($R$2-1)*12+7) -> 7 | O23: =INDEX(Monthly!$C$4:$BJ$4,($R$2-1)*12+8) -> 8 | P23: =INDEX(Monthly!$C$4:$BJ$4,($R$2-1)*12+9) -> 9 | Q23: =INDEX(Monthly!$C$4:$BJ$4,($R$2-1)*12+10) -> 10 | R23: =INDEX(Monthly!$C$4:$BJ$4,($R$2-1)*12+11) -> 11 | S23: =INDEX(Monthly!$C$4:$BJ$4,($R$2-1)*12+12) -> 12
A24: Operating cash flow | B24: ='Cash Flow'!B10 -> 90917.287 | C24: ='Cash Flow'!C10 -> 150047.06 | D24: ='Cash Flow'!D10 -> 183063.52 | E24: ='Cash Flow'!E10 -> 220221.66 | F24: ='Cash Flow'!F10 -> 262187.19 | H24: =INDEX(Monthly!$C$74:$BJ$74,($R$2-1)*12+1) -> -14679.041 | I24: =INDEX(Monthly!$C$74:$BJ$74,($R$2-1)*12+2) -> 3993.2899 | J24: =INDEX(Monthly!$C$74:$BJ$74,($R$2-1)*12+3) -> 7255.9411 | K24: =INDEX(Monthly!$C$74:$BJ$74,($R$2-1)*12+4) -> 8203.9851 | L24: =INDEX(Monthly!$C$74:$BJ$74,($R$2-1)*12+5) -> 8211.4462 | M24: =INDEX(Monthly!$C$74:$BJ$74,($R$2-1)*12+6) -> 8218.9073 | N24: =INDEX(Monthly!$C$74:$BJ$74,($R$2-1)*12+7) -> 8226.3684 | O24: =INDEX(Monthly!$C$74:$BJ$74,($R$2-1)*12+8) -> 8233.8295 | P24: =INDEX(Monthly!$C$74:$BJ$74,($R$2-1)*12+9) -> 8241.2906 | Q24: =INDEX(Monthly!$C$74:$BJ$74,($R$2-1)*12+10) -> 8248.7517 | R24: =INDEX(Monthly!$C$74:$BJ$74,($R$2-1)*12+11) -> 16648.034 | S24: =INDEX(Monthly!$C$74:$BJ$74,($R$2-1)*12+12) -> 20114.484
A25: Capital spending | B25: ='Cash Flow'!B11 -> -90000 | C25: ='Cash Flow'!C11 -> -14000 | D25: ='Cash Flow'!D11 -> -14000 | E25: ='Cash Flow'!E11 -> -14000 | F25: ='Cash Flow'!F11 -> -14000 | H25: =INDEX(Monthly!$C$75:$BJ$75,($R$2-1)*12+1) -> -90000 | I25: =INDEX(Monthly!$C$75:$BJ$75,($R$2-1)*12+2) -> 0 | J25: =INDEX(Monthly!$C$75:$BJ$75,($R$2-1)*12+3) -> 0 | K25: =INDEX(Monthly!$C$75:$BJ$75,($R$2-1)*12+4) -> 0 | L25: =INDEX(Monthly!$C$75:$BJ$75,($R$2-1)*12+5) -> 0 | M25: =INDEX(Monthly!$C$75:$BJ$75,($R$2-1)*12+6) -> 0 | N25: =INDEX(Monthly!$C$75:$BJ$75,($R$2-1)*12+7) -> 0 | O25: =INDEX(Monthly!$C$75:$BJ$75,($R$2-1)*12+8) -> 0 | P25: =INDEX(Monthly!$C$75:$BJ$75,($R$2-1)*12+9) -> 0 | Q25: =INDEX(Monthly!$C$75:$BJ$75,($R$2-1)*12+10) -> 0 | R25: =INDEX(Monthly!$C$75:$BJ$75,($R$2-1)*12+11) -> 0 | S25: =INDEX(Monthly!$C$75:$BJ$75,($R$2-1)*12+12) -> 0
A26: Equity raised | B26: ='Cash Flow'!B12 -> 60000 | C26: ='Cash Flow'!C12 -> 0 | D26: ='Cash Flow'!D12 -> 0 | E26: ='Cash Flow'!E12 -> 0 | F26: ='Cash Flow'!F12 -> 0 | H26: =INDEX(Monthly!$C$76:$BJ$76,($R$2-1)*12+1) -> 60000 | I26: =INDEX(Monthly!$C$76:$BJ$76,($R$2-1)*12+2) -> 0 | J26: =INDEX(Monthly!$C$76:$BJ$76,($R$2-1)*12+3) -> 0 | K26: =INDEX(Monthly!$C$76:$BJ$76,($R$2-1)*12+4) -> 0 | L26: =INDEX(Monthly!$C$76:$BJ$76,($R$2-1)*12+5) -> 0 | M26: =INDEX(Monthly!$C$76:$BJ$76,($R$2-1)*12+6) -> 0 | N26: =INDEX(Monthly!$C$76:$BJ$76,($R$2-1)*12+7) -> 0 | O26: =INDEX(Monthly!$C$76:$BJ$76,($R$2-1)*12+8) -> 0 | P26: =INDEX(Monthly!$C$76:$BJ$76,($R$2-1)*12+9) -> 0 | Q26: =INDEX(Monthly!$C$76:$BJ$76,($R$2-1)*12+10) -> 0 | R26: =INDEX(Monthly!$C$76:$BJ$76,($R$2-1)*12+11) -> 0 | S26: =INDEX(Monthly!$C$76:$BJ$76,($R$2-1)*12+12) -> 0
A27: Loan drawdown | B27: ='Cash Flow'!B13 -> 80000 | C27: ='Cash Flow'!C13 -> 0 | D27: ='Cash Flow'!D13 -> 0 | E27: ='Cash Flow'!E13 -> 0 | F27: ='Cash Flow'!F13 -> 0 | H27: =INDEX(Monthly!$C$61:$BJ$61,($R$2-1)*12+1) -> 80000 | I27: =INDEX(Monthly!$C$61:$BJ$61,($R$2-1)*12+2) -> 0 | J27: =INDEX(Monthly!$C$61:$BJ$61,($R$2-1)*12+3) -> 0 | K27: =INDEX(Monthly!$C$61:$BJ$61,($R$2-1)*12+4) -> 0 | L27: =INDEX(Monthly!$C$61:$BJ$61,($R$2-1)*12+5) -> 0 | M27: =INDEX(Monthly!$C$61:$BJ$61,($R$2-1)*12+6) -> 0 | N27: =INDEX(Monthly!$C$61:$BJ$61,($R$2-1)*12+7) -> 0 | O27: =INDEX(Monthly!$C$61:$BJ$61,($R$2-1)*12+8) -> 0 | P27: =INDEX(Monthly!$C$61:$BJ$61,($R$2-1)*12+9) -> 0 | Q27: =INDEX(Monthly!$C$61:$BJ$61,($R$2-1)*12+10) -> 0 | R27: =INDEX(Monthly!$C$61:$BJ$61,($R$2-1)*12+11) -> 0 | S27: =INDEX(Monthly!$C$61:$BJ$61,($R$2-1)*12+12) -> 0
A28: Loan repayment | B28: ='Cash Flow'!B14 -> -14666.667 | C28: ='Cash Flow'!C14 -> -16000 | D28: ='Cash Flow'!D14 -> -16000 | E28: ='Cash Flow'!E14 -> -16000 | F28: ='Cash Flow'!F14 -> -16000 | H28: =INDEX(Monthly!$C$62:$BJ$62,($R$2-1)*12+1) -> 0 | I28: =INDEX(Monthly!$C$62:$BJ$62,($R$2-1)*12+2) -> -1333.3333 | J28: =INDEX(Monthly!$C$62:$BJ$62,($R$2-1)*12+3) -> -1333.3333 | K28: =INDEX(Monthly!$C$62:$BJ$62,($R$2-1)*12+4) -> -1333.3333 | L28: =INDEX(Monthly!$C$62:$BJ$62,($R$2-1)*12+5) -> -1333.3333 | M28: =INDEX(Monthly!$C$62:$BJ$62,($R$2-1)*12+6) -> -1333.3333 | N28: =INDEX(Monthly!$C$62:$BJ$62,($R$2-1)*12+7) -> -1333.3333 | O28: =INDEX(Monthly!$C$62:$BJ$62,($R$2-1)*12+8) -> -1333.3333 | P28: =INDEX(Monthly!$C$62:$BJ$62,($R$2-1)*12+9) -> -1333.3333 | Q28: =INDEX(Monthly!$C$62:$BJ$62,($R$2-1)*12+10) -> -1333.3333 | R28: =INDEX(Monthly!$C$62:$BJ$62,($R$2-1)*12+11) -> -1333.3333 | S28: =INDEX(Monthly!$C$62:$BJ$62,($R$2-1)*12+12) -> -1333.3333
A29: Financing cash flow | B29: ='Cash Flow'!B15 -> 125333.33 | C29: ='Cash Flow'!C15 -> -16000 | D29: ='Cash Flow'!D15 -> -16000 | E29: ='Cash Flow'!E15 -> -16000 | F29: ='Cash Flow'!F15 -> -16000 | H29: =INDEX(Monthly!$C$77:$BJ$77,($R$2-1)*12+1) -> 140000 | I29: =INDEX(Monthly!$C$77:$BJ$77,($R$2-1)*12+2) -> -1333.3333 | J29: =INDEX(Monthly!$C$77:$BJ$77,($R$2-1)*12+3) -> -1333.3333 | K29: =INDEX(Monthly!$C$77:$BJ$77,($R$2-1)*12+4) -> -1333.3333 | L29: =INDEX(Monthly!$C$77:$BJ$77,($R$2-1)*12+5) -> -1333.3333 | M29: =INDEX(Monthly!$C$77:$BJ$77,($R$2-1)*12+6) -> -1333.3333 | N29: =INDEX(Monthly!$C$77:$BJ$77,($R$2-1)*12+7) -> -1333.3333 | O29: =INDEX(Monthly!$C$77:$BJ$77,($R$2-1)*12+8) -> -1333.3333 | P29: =INDEX(Monthly!$C$77:$BJ$77,($R$2-1)*12+9) -> -1333.3333 | Q29: =INDEX(Monthly!$C$77:$BJ$77,($R$2-1)*12+10) -> -1333.3333 | R29: =INDEX(Monthly!$C$77:$BJ$77,($R$2-1)*12+11) -> -1333.3333 | S29: =INDEX(Monthly!$C$77:$BJ$77,($R$2-1)*12+12) -> -1333.3333
A30: Net change in cash | B30: ='Cash Flow'!B16 -> 126250.62 | C30: ='Cash Flow'!C16 -> 120047.06 | D30: ='Cash Flow'!D16 -> 153063.52 | E30: ='Cash Flow'!E16 -> 190221.66 | F30: ='Cash Flow'!F16 -> 232187.19 | H30: =INDEX(Monthly!$C$78:$BJ$78,($R$2-1)*12+1) -> 35320.959 | I30: =INDEX(Monthly!$C$78:$BJ$78,($R$2-1)*12+2) -> 2659.9566 | J30: =INDEX(Monthly!$C$78:$BJ$78,($R$2-1)*12+3) -> 5922.6078 | K30: =INDEX(Monthly!$C$78:$BJ$78,($R$2-1)*12+4) -> 6870.6517 | L30: =INDEX(Monthly!$C$78:$BJ$78,($R$2-1)*12+5) -> 6878.1128 | M30: =INDEX(Monthly!$C$78:$BJ$78,($R$2-1)*12+6) -> 6885.574 | N30: =INDEX(Monthly!$C$78:$BJ$78,($R$2-1)*12+7) -> 6893.0351 | O30: =INDEX(Monthly!$C$78:$BJ$78,($R$2-1)*12+8) -> 6900.4962 | P30: =INDEX(Monthly!$C$78:$BJ$78,($R$2-1)*12+9) -> 6907.9573 | Q30: =INDEX(Monthly!$C$78:$BJ$78,($R$2-1)*12+10) -> 6915.4184 | R30: =INDEX(Monthly!$C$78:$BJ$78,($R$2-1)*12+11) -> 15314.7 | S30: =INDEX(Monthly!$C$78:$BJ$78,($R$2-1)*12+12) -> 18781.151
A31: Closing cash | B31: ='Cash Flow'!B18 -> 126250.62 | C31: ='Cash Flow'!C18 -> 246297.68 | D31: ='Cash Flow'!D18 -> 399361.2 | E31: ='Cash Flow'!E18 -> 589582.86 | F31: ='Cash Flow'!F18 -> 821770.05 | H31: =INDEX(Monthly!$C$80:$BJ$80,($R$2-1)*12+1) -> 35320.959 | I31: =INDEX(Monthly!$C$80:$BJ$80,($R$2-1)*12+2) -> 37980.916 | J31: =INDEX(Monthly!$C$80:$BJ$80,($R$2-1)*12+3) -> 43903.523 | K31: =INDEX(Monthly!$C$80:$BJ$80,($R$2-1)*12+4) -> 50774.175 | L31: =INDEX(Monthly!$C$80:$BJ$80,($R$2-1)*12+5) -> 57652.288 | M31: =INDEX(Monthly!$C$80:$BJ$80,($R$2-1)*12+6) -> 64537.862 | N31: =INDEX(Monthly!$C$80:$BJ$80,($R$2-1)*12+7) -> 71430.897 | O31: =INDEX(Monthly!$C$80:$BJ$80,($R$2-1)*12+8) -> 78331.393 | P31: =INDEX(Monthly!$C$80:$BJ$80,($R$2-1)*12+9) -> 85239.35 | Q31: =INDEX(Monthly!$C$80:$BJ$80,($R$2-1)*12+10) -> 92154.769 | R31: =INDEX(Monthly!$C$80:$BJ$80,($R$2-1)*12+11) -> 107469.47 | S31: =INDEX(Monthly!$C$80:$BJ$80,($R$2-1)*12+12) -> 126250.62
A39: Balance sheet at year end ($'000) | H39: ="Balance sheet at month end ($'000) — Year "&$R$2 -> Balance sheet at month end ($'000) — Year 1
B40: 1 | C40: 2 | D40: 3 | E40: 4 | F40: 5 | H40: =INDEX(Monthly!$C$4:$BJ$4,($R$2-1)*12+1) -> 1 | I40: =INDEX(Monthly!$C$4:$BJ$4,($R$2-1)*12+2) -> 2 | J40: =INDEX(Monthly!$C$4:$BJ$4,($R$2-1)*12+3) -> 3 | K40: =INDEX(Monthly!$C$4:$BJ$4,($R$2-1)*12+4) -> 4 | L40: =INDEX(Monthly!$C$4:$BJ$4,($R$2-1)*12+5) -> 5 | M40: =INDEX(Monthly!$C$4:$BJ$4,($R$2-1)*12+6) -> 6 | N40: =INDEX(Monthly!$C$4:$BJ$4,($R$2-1)*12+7) -> 7 | O40: =INDEX(Monthly!$C$4:$BJ$4,($R$2-1)*12+8) -> 8 | P40: =INDEX(Monthly!$C$4:$BJ$4,($R$2-1)*12+9) -> 9 | Q40: =INDEX(Monthly!$C$4:$BJ$4,($R$2-1)*12+10) -> 10 | R40: =INDEX(Monthly!$C$4:$BJ$4,($R$2-1)*12+11) -> 11 | S40: =INDEX(Monthly!$C$4:$BJ$4,($R$2-1)*12+12) -> 12
A41: Cash | B41: ='Balance Sheet'!B5 -> 126250.62 | C41: ='Balance Sheet'!C5 -> 246297.68 | D41: ='Balance Sheet'!D5 -> 399361.2 | E41: ='Balance Sheet'!E5 -> 589582.86 | F41: ='Balance Sheet'!F5 -> 821770.05 | H41: =INDEX(Monthly!$C$80:$BJ$80,($R$2-1)*12+1) -> 35320.959 | I41: =INDEX(Monthly!$C$80:$BJ$80,($R$2-1)*12+2) -> 37980.916 | J41: =INDEX(Monthly!$C$80:$BJ$80,($R$2-1)*12+3) -> 43903.523 | K41: =INDEX(Monthly!$C$80:$BJ$80,($R$2-1)*12+4) -> 50774.175 | L41: =INDEX(Monthly!$C$80:$BJ$80,($R$2-1)*12+5) -> 57652.288 | M41: =INDEX(Monthly!$C$80:$BJ$80,($R$2-1)*12+6) -> 64537.862 | N41: =INDEX(Monthly!$C$80:$BJ$80,($R$2-1)*12+7) -> 71430.897 | O41: =INDEX(Monthly!$C$80:$BJ$80,($R$2-1)*12+8) -> 78331.393 | P41: =INDEX(Monthly!$C$80:$BJ$80,($R$2-1)*12+9) -> 85239.35 | Q41: =INDEX(Monthly!$C$80:$BJ$80,($R$2-1)*12+10) -> 92154.769 | R41: =INDEX(Monthly!$C$80:$BJ$80,($R$2-1)*12+11) -> 107469.47 | S41: =INDEX(Monthly!$C$80:$BJ$80,($R$2-1)*12+12) -> 126250.62
A42: Accounts receivable | B42: ='Balance Sheet'!B6 -> 45676.8 | C42: ='Balance Sheet'!C6 -> 49499.724 | D42: ='Balance Sheet'!D6 -> 53715.392 | E42: ='Balance Sheet'!E6 -> 58372.29 | F42: ='Balance Sheet'!F6 -> 63525.625 | H42: =INDEX(Monthly!$C$66:$BJ$66,($R$2-1)*12+1) -> 34794.24 | I42: =INDEX(Monthly!$C$66:$BJ$66,($R$2-1)*12+2) -> 36791.04 | J42: =INDEX(Monthly!$C$66:$BJ$66,($R$2-1)*12+3) -> 38787.84 | K42: =INDEX(Monthly!$C$66:$BJ$66,($R$2-1)*12+4) -> 38787.84 | L42: =INDEX(Monthly!$C$66:$BJ$66,($R$2-1)*12+5) -> 38787.84 | M42: =INDEX(Monthly!$C$66:$BJ$66,($R$2-1)*12+6) -> 38787.84 | N42: =INDEX(Monthly!$C$66:$BJ$66,($R$2-1)*12+7) -> 38787.84 | O42: =INDEX(Monthly!$C$66:$BJ$66,($R$2-1)*12+8) -> 38787.84 | P42: =INDEX(Monthly!$C$66:$BJ$66,($R$2-1)*12+9) -> 38787.84 | Q42: =INDEX(Monthly!$C$66:$BJ$66,($R$2-1)*12+10) -> 38787.84 | R42: =INDEX(Monthly!$C$66:$BJ$66,($R$2-1)*12+11) -> 45676.8 | S42: =INDEX(Monthly!$C$66:$BJ$66,($R$2-1)*12+12) -> 45676.8
A43: Inventory | B43: ='Balance Sheet'!B7 -> 4796.5303 | C43: ='Balance Sheet'!C7 -> 5215.3191 | D43: ='Balance Sheet'!D7 -> 5679.0702 | E43: ='Balance Sheet'!E7 -> 6193.5106 | F43: ='Balance Sheet'!F7 -> 6765.175 | H43: =INDEX(Monthly!$C$67:$BJ$67,($R$2-1)*12+1) -> 3688.0494 | I43: =INDEX(Monthly!$C$67:$BJ$67,($R$2-1)*12+2) -> 3899.2928 | J43: =INDEX(Monthly!$C$67:$BJ$67,($R$2-1)*12+3) -> 4110.5362 | K43: =INDEX(Monthly!$C$67:$BJ$67,($R$2-1)*12+4) -> 4110.5362 | L43: =INDEX(Monthly!$C$67:$BJ$67,($R$2-1)*12+5) -> 4110.5362 | M43: =INDEX(Monthly!$C$67:$BJ$67,($R$2-1)*12+6) -> 4110.5362 | N43: =INDEX(Monthly!$C$67:$BJ$67,($R$2-1)*12+7) -> 4110.5362 | O43: =INDEX(Monthly!$C$67:$BJ$67,($R$2-1)*12+8) -> 4110.5362 | P43: =INDEX(Monthly!$C$67:$BJ$67,($R$2-1)*12+9) -> 4110.5362 | Q43: =INDEX(Monthly!$C$67:$BJ$67,($R$2-1)*12+10) -> 4110.5362 | R43: =INDEX(Monthly!$C$67:$BJ$67,($R$2-1)*12+11) -> 4796.5303 | S43: =INDEX(Monthly!$C$67:$BJ$67,($R$2-1)*12+12) -> 4796.5303
A44: Net fixed assets | B44: ='Balance Sheet'!B8 -> 77142.857 | C44: ='Balance Sheet'!C8 -> 77202.381 | D44: ='Balance Sheet'!D8 -> 75261.905 | E44: ='Balance Sheet'!E8 -> 71321.429 | F44: ='Balance Sheet'!F8 -> 65380.952 | H44: =INDEX(Monthly!$C$57:$BJ$57,($R$2-1)*12+1) -> 88928.571 | I44: =INDEX(Monthly!$C$57:$BJ$57,($R$2-1)*12+2) -> 87857.143 | J44: =INDEX(Monthly!$C$57:$BJ$57,($R$2-1)*12+3) -> 86785.714 | K44: =INDEX(Monthly!$C$57:$BJ$57,($R$2-1)*12+4) -> 85714.286 | L44: =INDEX(Monthly!$C$57:$BJ$57,($R$2-1)*12+5) -> 84642.857 | M44: =INDEX(Monthly!$C$57:$BJ$57,($R$2-1)*12+6) -> 83571.429 | N44: =INDEX(Monthly!$C$57:$BJ$57,($R$2-1)*12+7) -> 82500 | O44: =INDEX(Monthly!$C$57:$BJ$57,($R$2-1)*12+8) -> 81428.571 | P44: =INDEX(Monthly!$C$57:$BJ$57,($R$2-1)*12+9) -> 80357.143 | Q44: =INDEX(Monthly!$C$57:$BJ$57,($R$2-1)*12+10) -> 79285.714 | R44: =INDEX(Monthly!$C$57:$BJ$57,($R$2-1)*12+11) -> 78214.286 | S44: =INDEX(Monthly!$C$57:$BJ$57,($R$2-1)*12+12) -> 77142.857
A45: Total assets | B45: ='Balance Sheet'!B9 -> 253866.81 | C45: ='Balance Sheet'!C9 -> 378215.11 | D45: ='Balance Sheet'!D9 -> 534017.57 | E45: ='Balance Sheet'!E9 -> 725470.09 | F45: ='Balance Sheet'!F9 -> 957441.8 | H45: =INDEX(Monthly!$C$94:$BJ$94,($R$2-1)*12+1) -> 162731.82 | I45: =INDEX(Monthly!$C$94:$BJ$94,($R$2-1)*12+2) -> 166528.39 | J45: =INDEX(Monthly!$C$94:$BJ$94,($R$2-1)*12+3) -> 173587.61 | K45: =INDEX(Monthly!$C$94:$BJ$94,($R$2-1)*12+4) -> 179386.84 | L45: =INDEX(Monthly!$C$94:$BJ$94,($R$2-1)*12+5) -> 185193.52 | M45: =INDEX(Monthly!$C$94:$BJ$94,($R$2-1)*12+6) -> 191007.67 | N45: =INDEX(Monthly!$C$94:$BJ$94,($R$2-1)*12+7) -> 196829.27 | O45: =INDEX(Monthly!$C$94:$BJ$94,($R$2-1)*12+8) -> 202658.34 | P45: =INDEX(Monthly!$C$94:$BJ$94,($R$2-1)*12+9) -> 208494.87 | Q45: =INDEX(Monthly!$C$94:$BJ$94,($R$2-1)*12+10) -> 214338.86 | R45: =INDEX(Monthly!$C$94:$BJ$94,($R$2-1)*12+11) -> 236157.09 | S45: =INDEX(Monthly!$C$94:$BJ$94,($R$2-1)*12+12) -> 253866.81
A46: Accounts payable | B46: ='Balance Sheet'!B10 -> 28779.182 | C46: ='Balance Sheet'!C10 -> 31291.915 | D46: ='Balance Sheet'!D10 -> 34074.421 | E46: ='Balance Sheet'!E10 -> 37161.063 | F46: ='Balance Sheet'!F10 -> 40591.05 | H46: =INDEX(Monthly!$C$68:$BJ$68,($R$2-1)*12+1) -> 22128.296 | I46: =INDEX(Monthly!$C$68:$BJ$68,($R$2-1)*12+2) -> 23395.757 | J46: =INDEX(Monthly!$C$68:$BJ$68,($R$2-1)*12+3) -> 24663.217 | K46: =INDEX(Monthly!$C$68:$BJ$68,($R$2-1)*12+4) -> 24663.217 | L46: =INDEX(Monthly!$C$68:$BJ$68,($R$2-1)*12+5) -> 24663.217 | M46: =INDEX(Monthly!$C$68:$BJ$68,($R$2-1)*12+6) -> 24663.217 | N46: =INDEX(Monthly!$C$68:$BJ$68,($R$2-1)*12+7) -> 24663.217 | O46: =INDEX(Monthly!$C$68:$BJ$68,($R$2-1)*12+8) -> 24663.217 | P46: =INDEX(Monthly!$C$68:$BJ$68,($R$2-1)*12+9) -> 24663.217 | Q46: =INDEX(Monthly!$C$68:$BJ$68,($R$2-1)*12+10) -> 24663.217 | R46: =INDEX(Monthly!$C$68:$BJ$68,($R$2-1)*12+11) -> 28779.182 | S46: =INDEX(Monthly!$C$68:$BJ$68,($R$2-1)*12+12) -> 28779.182
A47: Loan | B47: ='Balance Sheet'!B11 -> 65333.333 | C47: ='Balance Sheet'!C11 -> 49333.333 | D47: ='Balance Sheet'!D11 -> 33333.333 | E47: ='Balance Sheet'!E11 -> 17333.333 | F47: ='Balance Sheet'!F11 -> 1333.3333 | H47: =INDEX(Monthly!$C$63:$BJ$63,($R$2-1)*12+1) -> 80000 | I47: =INDEX(Monthly!$C$63:$BJ$63,($R$2-1)*12+2) -> 78666.667 | J47: =INDEX(Monthly!$C$63:$BJ$63,($R$2-1)*12+3) -> 77333.333 | K47: =INDEX(Monthly!$C$63:$BJ$63,($R$2-1)*12+4) -> 76000 | L47: =INDEX(Monthly!$C$63:$BJ$63,($R$2-1)*12+5) -> 74666.667 | M47: =INDEX(Monthly!$C$63:$BJ$63,($R$2-1)*12+6) -> 73333.333 | N47: =INDEX(Monthly!$C$63:$BJ$63,($R$2-1)*12+7) -> 72000 | O47: =INDEX(Monthly!$C$63:$BJ$63,($R$2-1)*12+8) -> 70666.667 | P47: =INDEX(Monthly!$C$63:$BJ$63,($R$2-1)*12+9) -> 69333.333 | Q47: =INDEX(Monthly!$C$63:$BJ$63,($R$2-1)*12+10) -> 68000 | R47: =INDEX(Monthly!$C$63:$BJ$63,($R$2-1)*12+11) -> 66666.667 | S47: =INDEX(Monthly!$C$63:$BJ$63,($R$2-1)*12+12) -> 65333.333
A48: Total liabilities | B48: ='Balance Sheet'!B12 -> 94112.515 | C48: ='Balance Sheet'!C12 -> 80625.248 | D48: ='Balance Sheet'!D12 -> 67407.755 | E48: ='Balance Sheet'!E12 -> 54494.397 | F48: ='Balance Sheet'!F12 -> 41924.384 | H48: =INDEX(Monthly!$C$95:$BJ$95,($R$2-1)*12+1) -> 102128.3 | I48: =INDEX(Monthly!$C$95:$BJ$95,($R$2-1)*12+2) -> 102062.42 | J48: =INDEX(Monthly!$C$95:$BJ$95,($R$2-1)*12+3) -> 101996.55 | K48: =INDEX(Monthly!$C$95:$BJ$95,($R$2-1)*12+4) -> 100663.22 | L48: =INDEX(Monthly!$C$95:$BJ$95,($R$2-1)*12+5) -> 99329.884 | M48: =INDEX(Monthly!$C$95:$BJ$95,($R$2-1)*12+6) -> 97996.551 | N48: =INDEX(Monthly!$C$95:$BJ$95,($R$2-1)*12+7) -> 96663.217 | O48: =INDEX(Monthly!$C$95:$BJ$95,($R$2-1)*12+8) -> 95329.884 | P48: =INDEX(Monthly!$C$95:$BJ$95,($R$2-1)*12+9) -> 93996.551 | Q48: =INDEX(Monthly!$C$95:$BJ$95,($R$2-1)*12+10) -> 92663.217 | R48: =INDEX(Monthly!$C$95:$BJ$95,($R$2-1)*12+11) -> 95445.848 | S48: =INDEX(Monthly!$C$95:$BJ$95,($R$2-1)*12+12) -> 94112.515
A49: Paid-in capital | B49: ='Balance Sheet'!B13 -> 60000 | C49: ='Balance Sheet'!C13 -> 60000 | D49: ='Balance Sheet'!D13 -> 60000 | E49: ='Balance Sheet'!E13 -> 60000 | F49: ='Balance Sheet'!F13 -> 60000 | H49: =INDEX(Monthly!$C$92:$BJ$92,($R$2-1)*12+1) -> 60000 | I49: =INDEX(Monthly!$C$92:$BJ$92,($R$2-1)*12+2) -> 60000 | J49: =INDEX(Monthly!$C$92:$BJ$92,($R$2-1)*12+3) -> 60000 | K49: =INDEX(Monthly!$C$92:$BJ$92,($R$2-1)*12+4) -> 60000 | L49: =INDEX(Monthly!$C$92:$BJ$92,($R$2-1)*12+5) -> 60000 | M49: =INDEX(Monthly!$C$92:$BJ$92,($R$2-1)*12+6) -> 60000 | N49: =INDEX(Monthly!$C$92:$BJ$92,($R$2-1)*12+7) -> 60000 | O49: =INDEX(Monthly!$C$92:$BJ$92,($R$2-1)*12+8) -> 60000 | P49: =INDEX(Monthly!$C$92:$BJ$92,($R$2-1)*12+9) -> 60000 | Q49: =INDEX(Monthly!$C$92:$BJ$92,($R$2-1)*12+10) -> 60000 | R49: =INDEX(Monthly!$C$92:$BJ$92,($R$2-1)*12+11) -> 60000 | S49: =INDEX(Monthly!$C$92:$BJ$92,($R$2-1)*12+12) -> 60000
A50: Retained earnings | B50: ='Balance Sheet'!B14 -> 99754.292 | C50: ='Balance Sheet'!C14 -> 237589.86 | D50: ='Balance Sheet'!D14 -> 406609.81 | E50: ='Balance Sheet'!E14 -> 610975.69 | F50: ='Balance Sheet'!F14 -> 855517.42 | H50: =INDEX(Monthly!$C$93:$BJ$93,($R$2-1)*12+1) -> 603.52364 | I50: =INDEX(Monthly!$C$93:$BJ$93,($R$2-1)*12+2) -> 4465.9679 | J50: =INDEX(Monthly!$C$93:$BJ$93,($R$2-1)*12+3) -> 11591.063 | K50: =INDEX(Monthly!$C$93:$BJ$93,($R$2-1)*12+4) -> 18723.62 | L50: =INDEX(Monthly!$C$93:$BJ$93,($R$2-1)*12+5) -> 25863.637 | M50: =INDEX(Monthly!$C$93:$BJ$93,($R$2-1)*12+6) -> 33011.116 | N50: =INDEX(Monthly!$C$93:$BJ$93,($R$2-1)*12+7) -> 40166.056 | O50: =INDEX(Monthly!$C$93:$BJ$93,($R$2-1)*12+8) -> 47328.457 | P50: =INDEX(Monthly!$C$93:$BJ$93,($R$2-1)*12+9) -> 54498.319 | Q50: =INDEX(Monthly!$C$93:$BJ$93,($R$2-1)*12+10) -> 61675.642 | R50: =INDEX(Monthly!$C$93:$BJ$93,($R$2-1)*12+11) -> 80711.237 | S50: =INDEX(Monthly!$C$93:$BJ$93,($R$2-1)*12+12) -> 99754.292
A51: Total equity | B51: ='Balance Sheet'!B15 -> 159754.29 | C51: ='Balance Sheet'!C15 -> 297589.86 | D51: ='Balance Sheet'!D15 -> 466609.81 | E51: ='Balance Sheet'!E15 -> 670975.69 | F51: ='Balance Sheet'!F15 -> 915517.42 | H51: =INDEX(Monthly!$C$96:$BJ$96,($R$2-1)*12+1) -> 60603.524 | I51: =INDEX(Monthly!$C$96:$BJ$96,($R$2-1)*12+2) -> 64465.968 | J51: =INDEX(Monthly!$C$96:$BJ$96,($R$2-1)*12+3) -> 71591.063 | K51: =INDEX(Monthly!$C$96:$BJ$96,($R$2-1)*12+4) -> 78723.62 | L51: =INDEX(Monthly!$C$96:$BJ$96,($R$2-1)*12+5) -> 85863.637 | M51: =INDEX(Monthly!$C$96:$BJ$96,($R$2-1)*12+6) -> 93011.116 | N51: =INDEX(Monthly!$C$96:$BJ$96,($R$2-1)*12+7) -> 100166.06 | O51: =INDEX(Monthly!$C$96:$BJ$96,($R$2-1)*12+8) -> 107328.46 | P51: =INDEX(Monthly!$C$96:$BJ$96,($R$2-1)*12+9) -> 114498.32 | Q51: =INDEX(Monthly!$C$96:$BJ$96,($R$2-1)*12+10) -> 121675.64 | R51: =INDEX(Monthly!$C$96:$BJ$96,($R$2-1)*12+11) -> 140711.24 | S51: =INDEX(Monthly!$C$96:$BJ$96,($R$2-1)*12+12) -> 159754.29
A52: Total liabilities & equity | B52: ='Balance Sheet'!B16 -> 253866.81 | C52: ='Balance Sheet'!C16 -> 378215.11 | D52: ='Balance Sheet'!D16 -> 534017.57 | E52: ='Balance Sheet'!E16 -> 725470.09 | F52: ='Balance Sheet'!F16 -> 957441.8 | H52: =INDEX(Monthly!$C$97:$BJ$97,($R$2-1)*12+1) -> 162731.82 | I52: =INDEX(Monthly!$C$97:$BJ$97,($R$2-1)*12+2) -> 166528.39 | J52: =INDEX(Monthly!$C$97:$BJ$97,($R$2-1)*12+3) -> 173587.61 | K52: =INDEX(Monthly!$C$97:$BJ$97,($R$2-1)*12+4) -> 179386.84 | L52: =INDEX(Monthly!$C$97:$BJ$97,($R$2-1)*12+5) -> 185193.52 | M52: =INDEX(Monthly!$C$97:$BJ$97,($R$2-1)*12+6) -> 191007.67 | N52: =INDEX(Monthly!$C$97:$BJ$97,($R$2-1)*12+7) -> 196829.27 | O52: =INDEX(Monthly!$C$97:$BJ$97,($R$2-1)*12+8) -> 202658.34 | P52: =INDEX(Monthly!$C$97:$BJ$97,($R$2-1)*12+9) -> 208494.87 | Q52: =INDEX(Monthly!$C$97:$BJ$97,($R$2-1)*12+10) -> 214338.86 | R52: =INDEX(Monthly!$C$97:$BJ$97,($R$2-1)*12+11) -> 236157.09 | S52: =INDEX(Monthly!$C$97:$BJ$97,($R$2-1)*12+12) -> 253866.81

Sheet Scenarios
A1: Scenarios — Low / Base / High | H1: =HYPERLINK("#'Cover'!A1","◂ Contents") -> ◂ Contents
A2: All three scenarios calculated side by side, live: change any input and every column updates. Active = the scenario chosen on the Dashboard.
A5: Key drivers
A6: Driver | B6: Low | C6: Base | D6: High | E6: Active
A7: Customers per day at full traffic (#) | B7: =Inputs!$B$7 -> 300 | C7: =Inputs!$C$7 -> 320 | D7: =Inputs!$D$7 -> 340 | E7: =Inputs!$E$7 -> 320
A8: Average ticket per customer (year 1) ($) | B8: =Inputs!$B$11 -> 11 | C8: =Inputs!$C$11 -> 11.5 | D8: =Inputs!$D$11 -> 12 | E8: =Inputs!$E$11 -> 11.5
A9: Wholesale accounts at full ramp (year 1) (#) | B9: =Inputs!$B$17 -> 13 | C9: =Inputs!$C$17 -> 16 | D9: =Inputs!$D$17 -> 19 | E9: =Inputs!$E$17 -> 16
A10: Order value per account per week (year 1) ($) | B10: =Inputs!$B$19 -> 500 | C10: =Inputs!$C$19 -> 540 | D10: =Inputs!$D$19 -> 580 | E10: =Inputs!$E$19 -> 540
A11: Retail production baked but not sold (waste) (%) | B11: =Inputs!$B$26 -> 0.11 | C11: =Inputs!$C$26 -> 0.09 | D11: =Inputs!$D$26 -> 0.07 | E11: =Inputs!$E$26 -> 0.09
A12: Rent per month ($) | B12: =Inputs!$B$30 -> 12000 | C12: =Inputs!$C$30 -> 12000 | D12: =Inputs!$D$30 -> 12000 | E12: =Inputs!$E$30 -> 12000
A13: Fit-out & equipment: ovens, mixers, cases ($) | B13: =Inputs!$B$38 -> 90000 | C13: =Inputs!$C$38 -> 90000 | D13: =Inputs!$D$38 -> 90000 | E13: =Inputs!$E$38 -> 90000
A14: Equity raised at start ($) | B14: =Inputs!$B$58 -> 60000 | C14: =Inputs!$C$58 -> 60000 | D14: =Inputs!$D$58 -> 60000 | E14: =Inputs!$E$58 -> 60000
A16: Results by scenario ($'000)
A17: Output | B17: Low | C17: Base | D17: High | E17: Active
A18: Revenue — final year | B18: =F31 -> 1657475.5 | C18: =F32 -> 2250134.1 | D18: =F33 -> 3023920.1 | E18: ='P&L'!F5 -> 2250134.1
A19: Revenue — whole plan | B19: =SUM(B31:F31) -> 7504388.9 | C19: =SUM(B32:F32) -> 9514840.3 | D19: =SUM(B33:F33) -> 11959331 | E19: =SUM('P&L'!$B$5:$F$5) -> 9514840.3
A20: EBITDA — final year | B20: =F37 -> -71930.045 | C20: =F38 -> 330280.3 | D20: =F39 -> 874226.08 | E20: ='P&L'!F18 -> 330280.3
A21: EBITDA margin — final year | B21: =IF(B18=0,0,B20/B18) -> -0.04339735 | C21: =IF(C18=0,0,C20/C18) -> 0.1467825 | D21: =IF(D18=0,0,D20/D18) -> 0.28910356 | E21: =IF(E18=0,0,E20/E18) -> 0.1467825
A22: Net income — final year | B22: =F43 -> -92663.854 | C22: =F44 -> 244541.73 | D22: =F45 -> 674258.89 | E22: ='P&L'!F25 -> 244541.73
A23: Net income — whole plan | B23: =SUM(B43:F43) -> -333349.89 | C23: =SUM(B44:F44) -> 855517.42 | D23: =SUM(B45:F45) -> 2264810.6 | E23: =SUM('P&L'!$B$25:$F$25) -> 855517.42
A24: Cash at the end of the plan | B24: =F49 -> -357950.96 | C24: =F50 -> 821770.05 | D24: =F51 -> 2218597.8 | E24: ='Balance Sheet'!F5 -> 821770.05
A25: Lowest cash balance | B25: =MIN('Scenario calc'!$C$82:$BJ$82) -> -361898 | C25: =MIN('Scenario calc'!$C$193:$BJ$193) -> 35320.959 | D25: =MIN('Scenario calc'!$C$304:$BJ$304) -> 45608.962 | E25: ='Break-even'!B18 -> 35320.959
A26: Lowest cash point (month #) | B26: =MATCH(MIN('Scenario calc'!$C$82:$BJ$82),'Scenario calc'!$C$82:$BJ$82,0) -> 58 | C26: =MATCH(MIN('Scenario calc'!$C$193:$BJ$193),'Scenario calc'!$C$193:$BJ$193,0) -> 1 | D26: =MATCH(MIN('Scenario calc'!$C$304:$BJ$304),'Scenario calc'!$C$304:$BJ$304,0) -> 1 | E26: ='Break-even'!B6 -> 1
A27: Funding required (incl. cash buffer) | B27: =SUMPRODUCT(--('Scenario calc'!$C$6:$BJ$6<=B26),'Scenario calc'!$C$55:$BJ$55)-SUMPRODUCT(--('Scenario calc'!$C$6:$BJ$6<=B26),'Scenario calc'!$C$76:$BJ$76)-SUMPRODUCT(--('Scenario calc'!$C$6:$BJ$6<=B26),'Scenario calc'!$C$64:$BJ$64)+Inputs!$B$73 -> 734898 | C27: =SUMPRODUCT(--('Scenario calc'!$C$117:$BJ$117<=C26),'Scenario calc'!$C$166:$BJ$166)-SUMPRODUCT(--('Scenario calc'!$C$117:$BJ$117<=C26),'Scenario calc'!$C$187:$BJ$187)-SUMPRODUCT(--('Scenario calc'!$C$117:$BJ$117<=C26),'Scenario calc'!$C$175:$BJ$175)+Inputs!$C$73 -> 337679.04 | D27: =SUMPRODUCT(--('Scenario calc'!$C$228:$BJ$228<=D26),'Scenario calc'!$C$277:$BJ$277)-SUMPRODUCT(--('Scenario calc'!$C$228:$BJ$228<=D26),'Scenario calc'!$C$298:$BJ$298)-SUMPRODUCT(--('Scenario calc'!$C$228:$BJ$228<=D26),'Scenario calc'!$C$286:$BJ$286)+Inputs!$D$73 -> 327391.04 | E27: ='Break-even'!B12 -> 337679.04
A29: Revenue by year ($'000)
A30: Scenario | B30: 1 | C30: 2 | D30: 3 | E30: 4 | F30: 5
A31: Low | B31: =SUMIF('Scenario calc'!$C$7:$BJ$7,B$30,'Scenario calc'!$C$24:$BJ$24) -> 1333410 | C31: =SUMIF('Scenario calc'!$C$7:$BJ$7,C$30,'Scenario calc'!$C$24:$BJ$24) -> 1433034.7 | D31: =SUMIF('Scenario calc'!$C$7:$BJ$7,D$30,'Scenario calc'!$C$24:$BJ$24) -> 1502897.5 | E31: =SUMIF('Scenario calc'!$C$7:$BJ$7,E$30,'Scenario calc'!$C$24:$BJ$24) -> 1577571.2 | F31: =SUMIF('Scenario calc'!$C$7:$BJ$7,F$30,'Scenario calc'!$C$24:$BJ$24) -> 1657475.5
A32: Base | B32: =SUMIF('Scenario calc'!$C$118:$BJ$118,B$30,'Scenario calc'!$C$135:$BJ$135) -> 1577472 | C32: =SUMIF('Scenario calc'!$C$118:$BJ$118,C$30,'Scenario calc'!$C$135:$BJ$135) -> 1736372.4 | D32: =SUMIF('Scenario calc'!$C$118:$BJ$118,D$30,'Scenario calc'!$C$135:$BJ$135) -> 1890162.9 | E32: =SUMIF('Scenario calc'!$C$118:$BJ$118,E$30,'Scenario calc'!$C$135:$BJ$135) -> 2060699 | F32: =SUMIF('Scenario calc'!$C$118:$BJ$118,F$30,'Scenario calc'!$C$135:$BJ$135) -> 2250134.1
A33: High | B33: =SUMIF('Scenario calc'!$C$229:$BJ$229,B$30,'Scenario calc'!$C$246:$BJ$246) -> 1838308.3 | C33: =SUMIF('Scenario calc'!$C$229:$BJ$229,C$30,'Scenario calc'!$C$246:$BJ$246) -> 2081387.8 | D33: =SUMIF('Scenario calc'!$C$229:$BJ$229,D$30,'Scenario calc'!$C$246:$BJ$246) -> 2351961.9 | E33: =SUMIF('Scenario calc'!$C$229:$BJ$229,E$30,'Scenario calc'!$C$246:$BJ$246) -> 2663752.4 | F33: =SUMIF('Scenario calc'!$C$229:$BJ$229,F$30,'Scenario calc'!$C$246:$BJ$246) -> 3023920.1
A35: EBITDA by year ($'000)
A36: Scenario | B36: 1 | C36: 2 | D36: 3 | E36: 4 | F36: 5
A37: Low | B37: =SUMIF('Scenario calc'!$C$7:$BJ$7,B$36,'Scenario calc'!$C$43:$BJ$43) -> -38197.939 | C37: =SUMIF('Scenario calc'!$C$7:$BJ$7,C$36,'Scenario calc'!$C$43:$BJ$43) -> -28572.905 | D37: =SUMIF('Scenario calc'!$C$7:$BJ$7,D$36,'Scenario calc'!$C$43:$BJ$43) -> -41038.323 | E37: =SUMIF('Scenario calc'!$C$7:$BJ$7,E$36,'Scenario calc'!$C$43:$BJ$43) -> -55429.69 | F37: =SUMIF('Scenario calc'!$C$7:$BJ$7,F$36,'Scenario calc'!$C$43:$BJ$43) -> -71930.045
A38: Base | B38: =SUMIF('Scenario calc'!$C$118:$BJ$118,B$36,'Scenario calc'!$C$154:$BJ$154) -> 145357.01 | C38: =SUMIF('Scenario calc'!$C$118:$BJ$118,C$36,'Scenario calc'!$C$154:$BJ$154) -> 193289.21 | D38: =SUMIF('Scenario calc'!$C$118:$BJ$118,D$36,'Scenario calc'!$C$154:$BJ$154) -> 233403.12 | E38: =SUMIF('Scenario calc'!$C$118:$BJ$118,E$36,'Scenario calc'!$C$154:$BJ$154) -> 278784.79 | F38: =SUMIF('Scenario calc'!$C$118:$BJ$118,F$36,'Scenario calc'!$C$154:$BJ$154) -> 330280.3
A39: High | B39: =SUMIF('Scenario calc'!$C$229:$BJ$229,B$36,'Scenario calc'!$C$265:$BJ$265) -> 350866.4 | C39: =SUMIF('Scenario calc'!$C$229:$BJ$229,C$36,'Scenario calc'!$C$265:$BJ$265) -> 455669.07 | D39: =SUMIF('Scenario calc'!$C$229:$BJ$229,D$36,'Scenario calc'!$C$265:$BJ$265) -> 573037.01 | E39: =SUMIF('Scenario calc'!$C$229:$BJ$229,E$36,'Scenario calc'!$C$265:$BJ$265) -> 711231.3 | F39: =SUMIF('Scenario calc'!$C$229:$BJ$229,F$36,'Scenario calc'!$C$265:$BJ$265) -> 874226.08
A41: Net income by year ($'000)
A42: Scenario | B42: 1 | C42: 2 | D42: 3 | E42: 4 | F42: 5
A43: Low | B43: =SUMIF('Scenario calc'!$C$7:$BJ$7,B$42,'Scenario calc'!$C$52:$BJ$52) -> -57283.693 | C43: =SUMIF('Scenario calc'!$C$7:$BJ$7,C$42,'Scenario calc'!$C$52:$BJ$52) -> -47386.715 | D43: =SUMIF('Scenario calc'!$C$7:$BJ$7,D$42,'Scenario calc'!$C$52:$BJ$52) -> -60492.133 | E43: =SUMIF('Scenario calc'!$C$7:$BJ$7,E$42,'Scenario calc'!$C$52:$BJ$52) -> -75523.499 | F43: =SUMIF('Scenario calc'!$C$7:$BJ$7,F$42,'Scenario calc'!$C$52:$BJ$52) -> -92663.854
A44: Base | B44: =SUMIF('Scenario calc'!$C$118:$BJ$118,B$42,'Scenario calc'!$C$163:$BJ$163) -> 99754.292 | C44: =SUMIF('Scenario calc'!$C$118:$BJ$118,C$42,'Scenario calc'!$C$163:$BJ$163) -> 137835.57 | D44: =SUMIF('Scenario calc'!$C$118:$BJ$118,D$42,'Scenario calc'!$C$163:$BJ$163) -> 169019.96 | E44: =SUMIF('Scenario calc'!$C$118:$BJ$118,E$42,'Scenario calc'!$C$163:$BJ$163) -> 204365.88 | F44: =SUMIF('Scenario calc'!$C$118:$BJ$118,F$42,'Scenario calc'!$C$163:$BJ$163) -> 244541.73
A45: High | B45: =SUMIF('Scenario calc'!$C$229:$BJ$229,B$42,'Scenario calc'!$C$274:$BJ$274) -> 262106.71 | C45: =SUMIF('Scenario calc'!$C$229:$BJ$229,C$42,'Scenario calc'!$C$274:$BJ$274) -> 345115.65 | D45: =SUMIF('Scenario calc'!$C$229:$BJ$229,D$42,'Scenario calc'!$C$274:$BJ$274) -> 437330.73 | E45: =SUMIF('Scenario calc'!$C$229:$BJ$229,E$42,'Scenario calc'!$C$274:$BJ$274) -> 545998.61 | F45: =SUMIF('Scenario calc'!$C$229:$BJ$229,F$42,'Scenario calc'!$C$274:$BJ$274) -> 674258.89
A47: Cash at year end by year ($'000)
A48: Scenario | B48: 1 | C48: 2 | D48: 3 | E48: 4 | F48: 5
A49: Low | B49: =INDEX('Scenario calc'!$C$82:$BJ$82,B$48*12) -> -26396.736 | C49: =INDEX('Scenario calc'!$C$82:$BJ$82,C$48*12) -> -90584.75 | D49: =INDEX('Scenario calc'!$C$82:$BJ$82,D$48*12) -> -165922.86 | E49: =INDEX('Scenario calc'!$C$82:$BJ$82,E$48*12) -> -254340.61 | F49: =INDEX('Scenario calc'!$C$82:$BJ$82,F$48*12) -> -357950.96
A50: Base | B50: =INDEX('Scenario calc'!$C$193:$BJ$193,B$48*12) -> 126250.62 | C50: =INDEX('Scenario calc'!$C$193:$BJ$193,C$48*12) -> 246297.68 | D50: =INDEX('Scenario calc'!$C$193:$BJ$193,D$48*12) -> 399361.2 | E50: =INDEX('Scenario calc'!$C$193:$BJ$193,E$48*12) -> 589582.86 | F50: =INDEX('Scenario calc'!$C$193:$BJ$193,F$48*12) -> 821770.05
A51: High | B51: =INDEX('Scenario calc'!$C$304:$BJ$304,B$48*12) -> 283590.56 | C51: =INDEX('Scenario calc'!$C$304:$BJ$304,C$48*12) -> 609501.35 | D51: =INDEX('Scenario calc'!$C$304:$BJ$304,D$48*12) -> 1029195.8 | E51: =INDEX('Scenario calc'!$C$304:$BJ$304,E$48*12) -> 1559057.6 | F51: =INDEX('Scenario calc'!$C$304:$BJ$304,F$48*12) -> 2218597.8

Sheet Break-even
A1: Startup costs, funding need and break-even | H1: =HYPERLINK("#'Cover'!A1","◂ Contents") -> ◂ Contents
A2: Live for the selected scenario. Periods are counted in months from the start of the plan.
A3: Scenario shown | B3: =CHOOSE(Dashboard!$B$4,"Low","Base","High") -> Base
A5: Startup costs & funding need (up to the lowest cash point)
A6: Lowest cash point (month #) | B6: =MATCH(MIN(Monthly!$C$80:$BJ$80),Monthly!$C$80:$BJ$80,0) -> 1
A7: Capital spending up to the lowest cash point | B7: =SUMPRODUCT(--(Monthly!$C$4:$BJ$4<=$B$6),Monthly!$C$53:$BJ$53) -> 90000
A8: Operating cash burn up to the lowest cash point | B8: =-SUMPRODUCT(--(Monthly!$C$4:$BJ$4<=$B$6),Monthly!$C$74:$BJ$74) -> 14679.041 | D8: Losses and working capital before the business funds itself
A9: Loan repayments up to the lowest cash point | B9: =-SUMPRODUCT(--(Monthly!$C$4:$BJ$4<=$B$6),Monthly!$C$62:$BJ$62) -> 0
A10: Total uses of funds | B10: =B7+B8+B9 -> 104679.04
A11: Minimum cash buffer to keep | B11: =Inputs!$E$73 -> 233000 | D11: Input on the Inputs sheet
A12: Funding required (uses + buffer) | B12: =B10+B11 -> 337679.04
A14: Equity raised | B14: =Inputs!$E$58 -> 60000
A15: Loan drawn | B15: =Inputs!$E$59 -> 80000
A16: Total sources of funds | B16: =B14+B15 -> 140000
A17: Funding surplus / (shortfall) | B17: =B16-B12 -> -197679.04 | D17: Negative = raise at least this much more
A18: Lowest cash balance in the plan | B18: =MIN(Monthly!$C$80:$BJ$80) -> 35320.959 | D18: Equals sources minus uses
A20: Break-even timing
A21: First month with positive EBITDA (month #) | B21: =IFERROR(MATCH(1,Monthly!$C$81:$BJ$81,0),"Not within horizon") -> 1
A22: First month with positive net income (month #) | B22: =IFERROR(MATCH(1,Monthly!$C$84:$BJ$84,0),"Not within horizon") -> 1
A23: Cash invested paid back (month #) | B23: =IF(MIN(Monthly!$C$86:$BJ$86)>=0,"No investment to pay back",IFERROR(MATCH(1,Monthly!$C$88:$BJ$88,0),"Not within horizon")) -> 12 | D23: Cumulative operating + investing cash flow back to zero
A25: Annual break-even revenue
A26: Year # | B26: 1 | C26: 2 | D26: 3 | E26: 4 | F26: 5
B27: Year 1 | C27: Year 2 | D27: Year 3 | E27: Year 4 | F27: Year 5
A28: Revenue | B28: =SUMIF(Monthly!$C$5:$BJ$5,B$26,Monthly!$C$22:$BJ$22) -> 1577472 | C28: =SUMIF(Monthly!$C$5:$BJ$5,C$26,Monthly!$C$22:$BJ$22) -> 1736372.4 | D28: =SUMIF(Monthly!$C$5:$BJ$5,D$26,Monthly!$C$22:$BJ$22) -> 1890162.9 | E28: =SUMIF(Monthly!$C$5:$BJ$5,E$26,Monthly!$C$22:$BJ$22) -> 2060699 | F28: =SUMIF(Monthly!$C$5:$BJ$5,F$26,Monthly!$C$22:$BJ$22) -> 2250134.1
A29: Gross profit | B29: =SUMIF(Monthly!$C$5:$BJ$5,B$26,Monthly!$C$29:$BJ$29) -> 1076825.1 | C29: =SUMIF(Monthly!$C$5:$BJ$5,C$26,Monthly!$C$29:$BJ$29) -> 1183311.2 | D29: =SUMIF(Monthly!$C$5:$BJ$5,D$26,Monthly!$C$29:$BJ$29) -> 1285883.7 | E29: =SUMIF(Monthly!$C$5:$BJ$5,E$26,Monthly!$C$29:$BJ$29) -> 1399389 | F29: =SUMIF(Monthly!$C$5:$BJ$5,F$26,Monthly!$C$29:$BJ$29) -> 1525212.7
A30: Gross margin (contribution) | B30: =IF(B28=0,0,B29/B28) -> 0.68262706 | C30: =IF(C28=0,0,C29/C28) -> 0.68148469 | D30: =IF(D28=0,0,D29/D28) -> 0.68030311 | E30: =IF(E28=0,0,E29/E28) -> 0.67908462 | F30: =IF(F28=0,0,F29/F28) -> 0.67783194
A31: Operating expenses (treated as fixed) | B31: =-SUMIF(Monthly!$C$5:$BJ$5,B$26,Monthly!$C$40:$BJ$40) -> 931468.06 | C31: =-SUMIF(Monthly!$C$5:$BJ$5,C$26,Monthly!$C$40:$BJ$40) -> 990021.96 | D31: =-SUMIF(Monthly!$C$5:$BJ$5,D$26,Monthly!$C$40:$BJ$40) -> 1052480.5 | E31: =-SUMIF(Monthly!$C$5:$BJ$5,E$26,Monthly!$C$40:$BJ$40) -> 1120604.2 | F31: =-SUMIF(Monthly!$C$5:$BJ$5,F$26,Monthly!$C$40:$BJ$40) -> 1194932.4
A32: Break-even revenue (EBITDA = 0) | B32: =IF(B30>0,B31/B30,"n/a") -> 1364534.3 | C32: =IF(C30>0,C31/C30,"n/a") -> 1452742.8 | D32: =IF(D30>0,D31/D30,"n/a") -> 1547075.9 | E32: =IF(E30>0,E31/E30,"n/a") -> 1650168.7 | F32: =IF(F30>0,F31/F30,"n/a") -> 1762874.2
A33: Margin of safety (revenue above break-even) | B33: =IF(AND(ISNUMBER(B32),B28>0),(B28-B32)/B28,"n/a") -> 0.13498665 | C33: =IF(AND(ISNUMBER(C32),C28>0),(C28-C32)/C28,"n/a") -> 0.16334605 | D33: =IF(AND(ISNUMBER(D32),D28>0),(D28-D32)/D28,"n/a") -> 0.18151185 | E33: =IF(AND(ISNUMBER(E32),E28>0),(E28-E32)/E28,"n/a") -> 0.19921894 | F33: =IF(AND(ISNUMBER(F32),F28>0),(F28-F32)/F28,"n/a") -> 0.21654704
A35: Simplification: cost of sales is treated as variable and operating expenses as fixed, so break-even revenue = operating expenses ÷ gross margin.

Sheet Valuation
A1: Discounted cash flow valuation | H1: =HYPERLINK("#'Cover'!A1","◂ Contents") -> ◂ Contents
A2: Enterprise value at the start of the plan, before the funding raised in period 1. Year-end discounting.
A3: Scenario shown | B3: =CHOOSE(Dashboard!$B$4,"Low","Base","High") -> Base
A5: Assumptions (active scenario, from the Inputs sheet)
A6: Discount rate (WACC) | B6: =Inputs!$E$76 -> 0.16
A7: Terminal growth rate | B7: =Inputs!$E$77 -> 0.02
A8: Exit multiple (EV ÷ final-year EBITDA) | B8: =Inputs!$E$78 -> 5.5
A9: Tax rate (for the interest tax shield) | B9: =Inputs!$E$70 -> 0.21
A10: Sensitivity step: WACC | B10: =Inputs!$E$79 -> 0.01
A11: Sensitivity step: terminal growth | B11: =Inputs!$E$80 -> 0.005
A13: Free cash flow by year
A14: Year # | B14: 1 | C14: 2 | D14: 3 | E14: 4 | F14: 5
B15: Year 1 | C15: Year 2 | D15: Year 3 | E15: Year 4 | F15: Year 5
A16: EBITDA | B16: =SUMIF(Monthly!$C$5:$BJ$5,B$14,Monthly!$C$41:$BJ$41) -> 145357.01 | C16: =SUMIF(Monthly!$C$5:$BJ$5,C$14,Monthly!$C$41:$BJ$41) -> 193289.21 | D16: =SUMIF(Monthly!$C$5:$BJ$5,D$14,Monthly!$C$41:$BJ$41) -> 233403.12 | E16: =SUMIF(Monthly!$C$5:$BJ$5,E$14,Monthly!$C$41:$BJ$41) -> 278784.79 | F16: =SUMIF(Monthly!$C$5:$BJ$5,F$14,Monthly!$C$41:$BJ$41) -> 330280.3
A17: Unlevered free cash flow | B17: =SUMIF(Monthly!$C$5:$BJ$5,B$14,Monthly!$C$89:$BJ$89) -> 5837.8896 | C17: =SUMIF(Monthly!$C$5:$BJ$5,C$14,Monthly!$C$89:$BJ$89) -> 139897 | D17: =SUMIF(Monthly!$C$5:$BJ$5,D$14,Monthly!$C$89:$BJ$89) -> 171839.05 | E17: =SUMIF(Monthly!$C$5:$BJ$5,E$14,Monthly!$C$89:$BJ$89) -> 207922.79 | F17: =SUMIF(Monthly!$C$5:$BJ$5,F$14,Monthly!$C$89:$BJ$89) -> 248813.92
A18: Discount factor | B18: =1/(1+Inputs!$E$76)^B$14 -> 0.86206897 | C18: =1/(1+Inputs!$E$76)^C$14 -> 0.7431629 | D18: =1/(1+Inputs!$E$76)^D$14 -> 0.64065767 | E18: =1/(1+Inputs!$E$76)^E$14 -> 0.5522911 | F18: =1/(1+Inputs!$E$76)^F$14 -> 0.47611302
A19: Present value of free cash flow | B19: =B17*B18 -> 5032.6634 | C19: =C17*C18 -> 103966.26 | D19: =D17*D18 -> 110090.01 | E19: =E17*E18 -> 114833.91 | F19: =F17*F18 -> 118463.55
A21: Enterprise value
B22: Perpetual growth | C22: Exit multiple
A23: Present value of the plan's free cash flows | B23: =SUM($B$19:$F$19) -> 452386.38 | C23: =B23 -> 452386.38
A24: Final-year free cash flow | final-year EBITDA | B24: =$F$17 -> 248813.92 | C24: =$F$16 -> 330280.3
A25: Terminal value at the end of year 5 | B25: =IF($B$6>$B$7,B24*(1+$B$7)/($B$6-$B$7),0) -> 1812787.2 | C25: =C24*$B$8 -> 1816541.6
A26: Present value of the terminal value | B26: =B25/(1+$B$6)^$F$14 -> 863091.56 | C26: =C25/(1+$B$6)^$F$14 -> 864879.12
A27: Enterprise value | B27: =B23+B26 -> 1315477.9 | C27: =C23+C26 -> 1317265.5
A28: Terminal value share of enterprise value | B28: =IF(B27<>0,B26/B27,0) -> 0.65610493 | C28: =IF(C27<>0,C26/C27,0) -> 0.6565716
A29: Cross-check: implied exit multiple | implied perpetual growth | B29: =IF(C24>0,B25/C24,"n/a") -> 5.4886324 | C29: =IF(C25+B24<>0,(C25*$B$6-B24)/(C25+B24),"n/a") -> 0.020254498
A30: Enterprise value — average of the two methods | B30: =AVERAGE(B27,C27) -> 1316371.7
A32: Sensitivity: enterprise value (perpetual growth) by WACC and terminal growth
A33: WACC ↓ · terminal growth → | B33: =$B$7+(-2)*$B$11 -> 0.01 | C33: =$B$7+(-1)*$B$11 -> 0.015 | D33: =$B$7+(0)*$B$11 -> 0.02 | E33: =$B$7+(1)*$B$11 -> 0.025 | F33: =$B$7+(2)*$B$11 -> 0.03
A34: =$B$6+(-2)*$B$10 -> 0.14 | B34: =IF($A34>B$33,SUMPRODUCT($B$17:$F$17/(1+$A34)^$B$14:$F$14)+$F$17*(1+B$33)/($A34-B$33)/(1+$A34)^$F$14,"n/a") -> 1485074.6 | C34: =IF($A34>C$33,SUMPRODUCT($B$17:$F$17/(1+$A34)^$B$14:$F$14)+$F$17*(1+C$33)/($A34-C$33)/(1+$A34)^$F$14,"n/a") -> 1530403.1 | D34: =IF($A34>D$33,SUMPRODUCT($B$17:$F$17/(1+$A34)^$B$14:$F$14)+$F$17*(1+D$33)/($A34-D$33)/(1+$A34)^$F$14,"n/a") -> 1579509.1 | E34: =IF($A34>E$33,SUMPRODUCT($B$17:$F$17/(1+$A34)^$B$14:$F$14)+$F$17*(1+E$33)/($A34-E$33)/(1+$A34)^$F$14,"n/a") -> 1632885.1 | F34: =IF($A34>F$33,SUMPRODUCT($B$17:$F$17/(1+$A34)^$B$14:$F$14)+$F$17*(1+F$33)/($A34-F$33)/(1+$A34)^$F$14,"n/a") -> 1691113.5
A35: =$B$6+(-1)*$B$10 -> 0.15 | B35: =IF($A35>B$33,SUMPRODUCT($B$17:$F$17/(1+$A35)^$B$14:$F$14)+$F$17*(1+B$33)/($A35-B$33)/(1+$A35)^$F$14,"n/a") -> 1358870.2 | C35: =IF($A35>C$33,SUMPRODUCT($B$17:$F$17/(1+$A35)^$B$14:$F$14)+$F$17*(1+C$33)/($A35-C$33)/(1+$A35)^$F$14,"n/a") -> 1396505.2 | D35: =IF($A35>D$33,SUMPRODUCT($B$17:$F$17/(1+$A35)^$B$14:$F$14)+$F$17*(1+D$33)/($A35-D$33)/(1+$A35)^$F$14,"n/a") -> 1437035.1 | E35: =IF($A35>E$33,SUMPRODUCT($B$17:$F$17/(1+$A35)^$B$14:$F$14)+$F$17*(1+E$33)/($A35-E$33)/(1+$A35)^$F$14,"n/a") -> 1480807.5 | F35: =IF($A35>F$33,SUMPRODUCT($B$17:$F$17/(1+$A35)^$B$14:$F$14)+$F$17*(1+F$33)/($A35-F$33)/(1+$A35)^$F$14,"n/a") -> 1528227.6
A36: =$B$6+(0)*$B$10 -> 0.16 | B36: =IF($A36>B$33,SUMPRODUCT($B$17:$F$17/(1+$A36)^$B$14:$F$14)+$F$17*(1+B$33)/($A36-B$33)/(1+$A36)^$F$14,"n/a") -> 1250040.9 | C36: =IF($A36>C$33,SUMPRODUCT($B$17:$F$17/(1+$A36)^$B$14:$F$14)+$F$17*(1+C$33)/($A36-C$33)/(1+$A36)^$F$14,"n/a") -> 1281631.2 | D36: =IF($A36>D$33,SUMPRODUCT($B$17:$F$17/(1+$A36)^$B$14:$F$14)+$F$17*(1+D$33)/($A36-D$33)/(1+$A36)^$F$14,"n/a") -> 1315477.9 | E36: =IF($A36>E$33,SUMPRODUCT($B$17:$F$17/(1+$A36)^$B$14:$F$14)+$F$17*(1+E$33)/($A36-E$33)/(1+$A36)^$F$14,"n/a") -> 1351831.8 | F36: =IF($A36>F$33,SUMPRODUCT($B$17:$F$17/(1+$A36)^$B$14:$F$14)+$F$17*(1+F$33)/($A36-F$33)/(1+$A36)^$F$14,"n/a") -> 1390982.2
A37: =$B$6+(1)*$B$10 -> 0.17 | B37: =IF($A37>B$33,SUMPRODUCT($B$17:$F$17/(1+$A37)^$B$14:$F$14)+$F$17*(1+B$33)/($A37-B$33)/(1+$A37)^$F$14,"n/a") -> 1155307.8 | C37: =IF($A37>C$33,SUMPRODUCT($B$17:$F$17/(1+$A37)^$B$14:$F$14)+$F$17*(1+C$33)/($A37-C$33)/(1+$A37)^$F$14,"n/a") -> 1182077.9 | D37: =IF($A37>D$33,SUMPRODUCT($B$17:$F$17/(1+$A37)^$B$14:$F$14)+$F$17*(1+D$33)/($A37-D$33)/(1+$A37)^$F$14,"n/a") -> 1210632.6 | E37: =IF($A37>E$33,SUMPRODUCT($B$17:$F$17/(1+$A37)^$B$14:$F$14)+$F$17*(1+E$33)/($A37-E$33)/(1+$A37)^$F$14,"n/a") -> 1241156.7 | F37: =IF($A37>F$33,SUMPRODUCT($B$17:$F$17/(1+$A37)^$B$14:$F$14)+$F$17*(1+F$33)/($A37-F$33)/(1+$A37)^$F$14,"n/a") -> 1273861
A38: =$B$6+(2)*$B$10 -> 0.18 | B38: =IF($A38>B$33,SUMPRODUCT($B$17:$F$17/(1+$A38)^$B$14:$F$14)+$F$17*(1+B$33)/($A38-B$33)/(1+$A38)^$F$14,"n/a") -> 1072164.5 | C38: =IF($A38>C$33,SUMPRODUCT($B$17:$F$17/(1+$A38)^$B$14:$F$14)+$F$17*(1+C$33)/($A38-C$33)/(1+$A38)^$F$14,"n/a") -> 1095040.7 | D38: =IF($A38>D$33,SUMPRODUCT($B$17:$F$17/(1+$A38)^$B$14:$F$14)+$F$17*(1+D$33)/($A38-D$33)/(1+$A38)^$F$14,"n/a") -> 1119346.6 | E38: =IF($A38>E$33,SUMPRODUCT($B$17:$F$17/(1+$A38)^$B$14:$F$14)+$F$17*(1+E$33)/($A38-E$33)/(1+$A38)^$F$14,"n/a") -> 1145220.7 | F38: =IF($A38>F$33,SUMPRODUCT($B$17:$F$17/(1+$A38)^$B$14:$F$14)+$F$17*(1+F$33)/($A38-F$33)/(1+$A38)^$F$14,"n/a") -> 1172819.7
A40: Free cash flow = operating cash flow + interest × (1 − tax rate) − capital spending. Cells marked n/a: WACC not above growth.

Sheet Sources & Uses
A1: Sources and uses of funds | E1: =HYPERLINK("#'Cover'!A1","◂ Contents") -> ◂ Contents
A2: Live for the selected scenario. Where the money comes from and where it goes in the period set below.
A3: Scenario shown | B3: =CHOOSE(Dashboard!$B$4,"Low","Base","High") -> Base
A5: Funding structure ($'000) — raised at the start of the plan
B6: Amount | C6: Share
A7: Equity | B7: =Inputs!$E$58 -> 60000 | C7: =IF($B$9=0,0,B7/$B$9) -> 0.42857143
A8: Debt (loan) | B8: =Inputs!$E$59 -> 80000 | C8: =IF($B$9=0,0,B8/$B$9) -> 0.57142857
A9: Total funding | B9: =B7+B8 -> 140000 | C9: =IF(B9=0,0,1) -> 1
A10: Gearing (debt ÷ equity) | B10: =IF(B7<=0,IF(B8>0,"n/a",0),B8/B7) -> 1.3333333 | D10: n/a: debt without positive equity
A11: Funding required by the plan (Break-even sheet) | B11: ='Break-even'!B12 -> 337679.04
A12: Funding surplus / (shortfall) | B12: ='Break-even'!B17 -> -197679.04
A14: ="Sources and uses of cash in the first "&$B$16&IF($B$16=1," month"," months")&" ($'000)" -> Sources and uses of cash in the first 12 months ($'000)
A15: Period covered (months from the start) | B15: 12 | D15: 1 to 60 (capped)
A16: Months used | B16: =MIN(60,MAX(1,ROUND(B15,0))) -> 12
A17: Sources | B17: Amount | C17: Share
A18: Equity raised | B18: =SUMPRODUCT(--(Monthly!$C$4:$BJ$4<=$B$16),Monthly!$C$76:$BJ$76) -> 60000 | C18: =IF($B$21=0,0,B18/$B$21) -> 0.2598333
A19: Loan drawdowns | B19: =SUMPRODUCT(--(Monthly!$C$4:$BJ$4<=$B$16),Monthly!$C$61:$BJ$61) -> 80000 | C19: =IF($B$21=0,0,B19/$B$21) -> 0.3464444
A20: Cash generated by operations | B20: =MAX(0,SUMPRODUCT(--(Monthly!$C$4:$BJ$4<=$B$16),Monthly!$C$74:$BJ$74)) -> 90917.287 | C20: =IF($B$21=0,0,B20/$B$21) -> 0.39372231
A21: Total sources | B21: =SUM(B18:B20) -> 230917.29 | C21: =IF(B21=0,0,1) -> 1
A23: Uses | B23: Amount | C23: Share
A24: Cash used by operations | B24: =MAX(0,-SUMPRODUCT(--(Monthly!$C$4:$BJ$4<=$B$16),Monthly!$C$74:$BJ$74)) -> 0 | C24: =IF($B$28=0,0,B24/$B$28) -> 0
A25: Capital spending | B25: =-SUMPRODUCT(--(Monthly!$C$4:$BJ$4<=$B$16),Monthly!$C$75:$BJ$75) -> 90000 | C25: =IF($B$28=0,0,B25/$B$28) -> 0.38974995
A26: Loan repayments | B26: =-SUMPRODUCT(--(Monthly!$C$4:$BJ$4<=$B$16),Monthly!$C$62:$BJ$62) -> 14666.667 | C26: =IF($B$28=0,0,B26/$B$28) -> 0.063514806
A27: Cash at the end of the period | B27: =INDEX(Monthly!$C$80:$BJ$80,$B$16) -> 126250.62 | C27: =IF($B$28=0,0,B27/$B$28) -> 0.54673525
A28: Total uses | B28: =SUM(B24:B27) -> 230917.29 | C28: =IF(B28=0,0,1) -> 1
A29: Sources − uses (must be 0; opening cash is 0) | B29: =B21-B28 -> 0

Sheet KPIs
A1: KPIs & ratios | I1: =HYPERLINK("#'Cover'!A1","◂ Contents") -> ◂ Contents
A2: Bakery financial model (growing) — industry metrics and financial ratios for the active scenario
A4: Financial ratios
B5: 1 | C5: 2 | D5: 3 | E5: 4 | F5: 5 | G5: Target
A6: Revenue growth | B6: =IF(N('P&L'!A5)<=0,"n/a",'P&L'!B5/'P&L'!A5-1) -> n/a | C6: =IF(N('P&L'!B5)<=0,"n/a",'P&L'!C5/'P&L'!B5-1) -> 0.10073101 | D6: =IF(N('P&L'!C5)<=0,"n/a",'P&L'!D5/'P&L'!C5-1) -> 0.088570003 | E6: =IF(N('P&L'!D5)<=0,"n/a",'P&L'!E5/'P&L'!D5-1) -> 0.090222979 | F6: =IF(N('P&L'!E5)<=0,"n/a",'P&L'!F5/'P&L'!E5-1) -> 0.091927587
A7: Gross margin | B7: =IF('P&L'!B5<=0,"n/a",'P&L'!B7/'P&L'!B5) -> 0.68262706 | C7: =IF('P&L'!C5<=0,"n/a",'P&L'!C7/'P&L'!C5) -> 0.68148469 | D7: =IF('P&L'!D5<=0,"n/a",'P&L'!D7/'P&L'!D5) -> 0.68030311 | E7: =IF('P&L'!E5<=0,"n/a",'P&L'!E7/'P&L'!E5) -> 0.67908462 | F7: =IF('P&L'!F5<=0,"n/a",'P&L'!F7/'P&L'!F5) -> 0.67783194
A8: EBITDA margin | B8: =IF('P&L'!B5<=0,"n/a",'P&L'!B18/'P&L'!B5) -> 0.092145541 | C8: =IF('P&L'!C5<=0,"n/a",'P&L'!C18/'P&L'!C5) -> 0.11131783 | D8: =IF('P&L'!D5<=0,"n/a",'P&L'!D18/'P&L'!D5) -> 0.12348307 | E8: =IF('P&L'!E5<=0,"n/a",'P&L'!E18/'P&L'!E5) -> 0.13528652 | F8: =IF('P&L'!F5<=0,"n/a",'P&L'!F18/'P&L'!F5) -> 0.1467825
A9: Net margin | B9: =IF('P&L'!B5<=0,"n/a",'P&L'!B25/'P&L'!B5) -> 0.063236807 | C9: =IF('P&L'!C5<=0,"n/a",'P&L'!C25/'P&L'!C5) -> 0.079381341 | D9: =IF('P&L'!D5<=0,"n/a",'P&L'!D25/'P&L'!D5) -> 0.089420843 | E9: =IF('P&L'!E5<=0,"n/a",'P&L'!E25/'P&L'!E5) -> 0.099173086 | F9: =IF('P&L'!F5<=0,"n/a",'P&L'!F25/'P&L'!F5) -> 0.10867874
A10: Payroll, % of revenue | B10: =IF('P&L'!B5<=0,"n/a",-SUMIF(Headcount!$C$5:$BJ$5,B$5,Headcount!$C$17:$BJ$17)/'P&L'!B5) -> 0.37629828 | C10: =IF('P&L'!C5<=0,"n/a",-SUMIF(Headcount!$C$5:$BJ$5,C$5,Headcount!$C$17:$BJ$17)/'P&L'!C5) -> 0.3695379 | D10: =IF('P&L'!D5<=0,"n/a",-SUMIF(Headcount!$C$5:$BJ$5,D$5,Headcount!$C$17:$BJ$17)/'P&L'!D5) -> 0.36712665 | E10: =IF('P&L'!E5<=0,"n/a",-SUMIF(Headcount!$C$5:$BJ$5,E$5,Headcount!$C$17:$BJ$17)/'P&L'!E5) -> 0.36434373 | F10: =IF('P&L'!F5<=0,"n/a",-SUMIF(Headcount!$C$5:$BJ$5,F$5,Headcount!$C$17:$BJ$17)/'P&L'!F5) -> 0.36117513
A11: Marketing, % of revenue | B11: =IF('P&L'!B5<=0,"n/a",-'P&L'!B14/'P&L'!B5) -> 0.02 | C11: =IF('P&L'!C5<=0,"n/a",-'P&L'!C14/'P&L'!C5) -> 0.02 | D11: =IF('P&L'!D5<=0,"n/a",-'P&L'!D14/'P&L'!D5) -> 0.02 | E11: =IF('P&L'!E5<=0,"n/a",-'P&L'!E14/'P&L'!E5) -> 0.02 | F11: =IF('P&L'!F5<=0,"n/a",-'P&L'!F14/'P&L'!F5) -> 0.02
A12: Operating expenses, % of revenue | B12: =IF('P&L'!B5<=0,"n/a",-'P&L'!B17/'P&L'!B5) -> 0.59048152 | C12: =IF('P&L'!C5<=0,"n/a",-'P&L'!C17/'P&L'!C5) -> 0.57016685 | D12: =IF('P&L'!D5<=0,"n/a",-'P&L'!D17/'P&L'!D5) -> 0.55682003 | E12: =IF('P&L'!E5<=0,"n/a",-'P&L'!E17/'P&L'!E5) -> 0.5437981 | F12: =IF('P&L'!F5<=0,"n/a",-'P&L'!F17/'P&L'!F5) -> 0.53104944
A13: Current ratio (current assets ÷ current liabilities) | B13: =IF(('Balance Sheet'!B12-'Balance Sheet'!B11)<=0,"n/a",('Balance Sheet'!B5+'Balance Sheet'!B6+'Balance Sheet'!B7)/('Balance Sheet'!B12-'Balance Sheet'!B11)) -> 6.1406871 | C13: =IF(('Balance Sheet'!C12-'Balance Sheet'!C11)<=0,"n/a",('Balance Sheet'!C5+'Balance Sheet'!C6+'Balance Sheet'!C7)/('Balance Sheet'!C12-'Balance Sheet'!C11)) -> 9.6195049 | D13: =IF(('Balance Sheet'!D12-'Balance Sheet'!D11)<=0,"n/a",('Balance Sheet'!D5+'Balance Sheet'!D6+'Balance Sheet'!D7)/('Balance Sheet'!D12-'Balance Sheet'!D11)) -> 13.463344 | E13: =IF(('Balance Sheet'!E12-'Balance Sheet'!E11)<=0,"n/a",('Balance Sheet'!E5+'Balance Sheet'!E6+'Balance Sheet'!E7)/('Balance Sheet'!E12-'Balance Sheet'!E11)) -> 17.603066 | F13: =IF(('Balance Sheet'!F12-'Balance Sheet'!F11)<=0,"n/a",('Balance Sheet'!F5+'Balance Sheet'!F6+'Balance Sheet'!F7)/('Balance Sheet'!F12-'Balance Sheet'!F11)) -> 21.976787
A14: Debt ÷ equity (loan ÷ total equity) | B14: =IF('Balance Sheet'!B15<=0,"n/a",'Balance Sheet'!B11/'Balance Sheet'!B15) -> 0.40896136 | C14: =IF('Balance Sheet'!C15<=0,"n/a",'Balance Sheet'!C11/'Balance Sheet'!C15) -> 0.16577626 | D14: =IF('Balance Sheet'!D15<=0,"n/a",'Balance Sheet'!D11/'Balance Sheet'!D15) -> 0.071437274 | E14: =IF('Balance Sheet'!E15<=0,"n/a",'Balance Sheet'!E11/'Balance Sheet'!E15) -> 0.025833027 | F14: =IF('Balance Sheet'!F15<=0,"n/a",'Balance Sheet'!F11/'Balance Sheet'!F15) -> 0.0014563713
A15: Return on assets (net income ÷ year-end assets) | B15: =IF('Balance Sheet'!B9<=0,"n/a",'P&L'!B25/'Balance Sheet'!B9) -> 0.39293948 | C15: =IF('Balance Sheet'!C9<=0,"n/a",'P&L'!C25/'Balance Sheet'!C9) -> 0.36443697 | D15: =IF('Balance Sheet'!D9<=0,"n/a",'P&L'!D25/'Balance Sheet'!D9) -> 0.31650636 | E15: =IF('Balance Sheet'!E9<=0,"n/a",'P&L'!E25/'Balance Sheet'!E9) -> 0.28170131 | F15: =IF('Balance Sheet'!F9<=0,"n/a",'P&L'!F25/'Balance Sheet'!F9) -> 0.25541158
A16: Return on equity (net income ÷ year-end equity) | B16: =IF('Balance Sheet'!B15<=0,"n/a",'P&L'!B25/'Balance Sheet'!B15) -> 0.62442324 | C16: =IF('Balance Sheet'!C15<=0,"n/a",'P&L'!C25/'Balance Sheet'!C15) -> 0.46317293 | D16: =IF('Balance Sheet'!D15<=0,"n/a",'P&L'!D25/'Balance Sheet'!D15) -> 0.36222975 | E16: =IF('Balance Sheet'!E15<=0,"n/a",'P&L'!E25/'Balance Sheet'!E15) -> 0.30458015 | F16: =IF('Balance Sheet'!F15<=0,"n/a",'P&L'!F25/'Balance Sheet'!F15) -> 0.26710767
A18: DuPont analysis — return on equity = net margin × asset turnover × equity multiplier
B19: 1 | C19: 2 | D19: 3 | E19: 4 | F19: 5
A20: Net margin | B20: =IF('P&L'!B5<=0,"n/a",'P&L'!B25/'P&L'!B5) -> 0.063236807 | C20: =IF('P&L'!C5<=0,"n/a",'P&L'!C25/'P&L'!C5) -> 0.079381341 | D20: =IF('P&L'!D5<=0,"n/a",'P&L'!D25/'P&L'!D5) -> 0.089420843 | E20: =IF('P&L'!E5<=0,"n/a",'P&L'!E25/'P&L'!E5) -> 0.099173086 | F20: =IF('P&L'!F5<=0,"n/a",'P&L'!F25/'P&L'!F5) -> 0.10867874
A21: × Asset turnover (revenue ÷ assets) | B21: =IF('Balance Sheet'!B9<=0,"n/a",'P&L'!B5/'Balance Sheet'!B9) -> 6.2137781 | C21: =IF('Balance Sheet'!C9<=0,"n/a",'P&L'!C5/'Balance Sheet'!C9) -> 4.5909651 | D21: =IF('Balance Sheet'!D9<=0,"n/a",'P&L'!D5/'Balance Sheet'!D9) -> 3.5395144 | E21: =IF('Balance Sheet'!E9<=0,"n/a",'P&L'!E5/'Balance Sheet'!E9) -> 2.8405017 | F21: =IF('Balance Sheet'!F9<=0,"n/a",'P&L'!F5/'Balance Sheet'!F9) -> 2.3501523
A22: × Equity multiplier (assets ÷ equity) | B22: =IF('Balance Sheet'!B15<=0,"n/a",'Balance Sheet'!B9/'Balance Sheet'!B15) -> 1.5891079 | C22: =IF('Balance Sheet'!C15<=0,"n/a",'Balance Sheet'!C9/'Balance Sheet'!C15) -> 1.2709274 | D22: =IF('Balance Sheet'!D15<=0,"n/a",'Balance Sheet'!D9/'Balance Sheet'!D15) -> 1.1444628 | E22: =IF('Balance Sheet'!E15<=0,"n/a",'Balance Sheet'!E9/'Balance Sheet'!E15) -> 1.0812166 | F22: =IF('Balance Sheet'!F15<=0,"n/a",'Balance Sheet'!F9/'Balance Sheet'!F15) -> 1.0457931
A23: Return on equity (product of the three) | B23: =IF(AND(ISNUMBER(B20),ISNUMBER(B21),ISNUMBER(B22)),B20*B21*B22,"n/a") -> 0.62442324 | C23: =IF(AND(ISNUMBER(C20),ISNUMBER(C21),ISNUMBER(C22)),C20*C21*C22,"n/a") -> 0.46317293 | D23: =IF(AND(ISNUMBER(D20),ISNUMBER(D21),ISNUMBER(D22)),D20*D21*D22,"n/a") -> 0.36222975 | E23: =IF(AND(ISNUMBER(E20),ISNUMBER(E21),ISNUMBER(E22)),E20*E21*E22,"n/a") -> 0.30458015 | F23: =IF(AND(ISNUMBER(F20),ISNUMBER(F21),ISNUMBER(F22)),F20*F21*F22,"n/a") -> 0.26710767
A24: Check: product − return on equity (must be 0) | B24: =IF(AND(ISNUMBER(B23),ISNUMBER(B16)),B23-B16,IF(ISNUMBER(B23),1,IF(AND(ISNUMBER(B16),ISNUMBER(B20),ISNUMBER(B21)),1,0))) -> 0 | C24: =IF(AND(ISNUMBER(C23),ISNUMBER(C16)),C23-C16,IF(ISNUMBER(C23),1,IF(AND(ISNUMBER(C16),ISNUMBER(C20),ISNUMBER(C21)),1,0))) -> 0 | D24: =IF(AND(ISNUMBER(D23),ISNUMBER(D16)),D23-D16,IF(ISNUMBER(D23),1,IF(AND(ISNUMBER(D16),ISNUMBER(D20),ISNUMBER(D21)),1,0))) -> 0 | E24: =IF(AND(ISNUMBER(E23),ISNUMBER(E16)),E23-E16,IF(ISNUMBER(E23),1,IF(AND(ISNUMBER(E16),ISNUMBER(E20),ISNUMBER(E21)),1,0))) -> 0 | F24: =IF(AND(ISNUMBER(F23),ISNUMBER(F16)),F23-F16,IF(ISNUMBER(F23),1,IF(AND(ISNUMBER(F16),ISNUMBER(F20),ISNUMBER(F21)),1,0))) -> 0
A26: Bakery metrics ($'000; per-unit rows in $)
A27: Year # | B27: 1 | C27: 2 | D27: 3 | E27: 4 | F27: 5
B28: Year 1 | C28: Year 2 | D28: Year 3 | E28: Year 4 | F28: Year 5 | G28: Target
A29: Opening days in the year | B29: =SUMIF(Monthly!$C$5:$BJ$5,B$27,Monthly!$C$11:$BJ$11) -> 312 | C29: =SUMIF(Monthly!$C$5:$BJ$5,C$27,Monthly!$C$11:$BJ$11) -> 312 | D29: =SUMIF(Monthly!$C$5:$BJ$5,D$27,Monthly!$C$11:$BJ$11) -> 312 | E29: =SUMIF(Monthly!$C$5:$BJ$5,E$27,Monthly!$C$11:$BJ$11) -> 312 | F29: =SUMIF(Monthly!$C$5:$BJ$5,F$27,Monthly!$C$11:$BJ$11) -> 312
A30: Retail transactions | B30: =SUMIF(Monthly!$C$5:$BJ$5,B$27,Monthly!$C$12:$BJ$12) -> 98592 | C30: =SUMIF(Monthly!$C$5:$BJ$5,C$27,Monthly!$C$12:$BJ$12) -> 102835.2 | D30: =SUMIF(Monthly!$C$5:$BJ$5,D$27,Monthly!$C$12:$BJ$12) -> 105920.26 | E30: =SUMIF(Monthly!$C$5:$BJ$5,E$27,Monthly!$C$12:$BJ$12) -> 109097.86 | F30: =SUMIF(Monthly!$C$5:$BJ$5,F$27,Monthly!$C$12:$BJ$12) -> 112370.8
A31: Customers per day (average) | B31: =IF(B29=0,0,B30/B29) -> 316 | C31: =IF(C29=0,0,C30/C29) -> 329.6 | D31: =IF(D29=0,0,D30/D29) -> 339.488 | E31: =IF(E29=0,0,E30/E29) -> 349.67264 | F31: =IF(F29=0,0,F30/F29) -> 360.16282
A32: Average ticket ($) | B32: =IF(B30=0,0,B35/B30) -> 11.5 | C32: =IF(C30=0,0,C35/C30) -> 11.845 | D32: =IF(D30=0,0,D35/D30) -> 12.20035 | E32: =IF(E30=0,0,E35/E30) -> 12.566361 | F32: =IF(F30=0,0,F35/F30) -> 12.943351
A33: Wholesale accounts (year end; annual model: year average) | B33: =INDEX(Monthly!$C$17:$BJ$17,B$27*12) -> 16 | C33: =INDEX(Monthly!$C$17:$BJ$17,C$27*12) -> 17.92 | D33: =INDEX(Monthly!$C$17:$BJ$17,D$27*12) -> 20.0704 | E33: =INDEX(Monthly!$C$17:$BJ$17,E$27*12) -> 22.478848 | F33: =INDEX(Monthly!$C$17:$BJ$17,F$27*12) -> 25.17631
A34: Revenue | B34: =SUMIF(Monthly!$C$5:$BJ$5,B$27,Monthly!$C$22:$BJ$22) -> 1577472 | C34: =SUMIF(Monthly!$C$5:$BJ$5,C$27,Monthly!$C$22:$BJ$22) -> 1736372.4 | D34: =SUMIF(Monthly!$C$5:$BJ$5,D$27,Monthly!$C$22:$BJ$22) -> 1890162.9 | E34: =SUMIF(Monthly!$C$5:$BJ$5,E$27,Monthly!$C$22:$BJ$22) -> 2060699 | F34: =SUMIF(Monthly!$C$5:$BJ$5,F$27,Monthly!$C$22:$BJ$22) -> 2250134.1
A35: Retail counter revenue | B35: =SUMIF(Monthly!$C$5:$BJ$5,B$27,Monthly!$C$14:$BJ$14) -> 1133808 | C35: =SUMIF(Monthly!$C$5:$BJ$5,C$27,Monthly!$C$14:$BJ$14) -> 1218082.9 | D35: =SUMIF(Monthly!$C$5:$BJ$5,D$27,Monthly!$C$14:$BJ$14) -> 1292264.2 | E35: =SUMIF(Monthly!$C$5:$BJ$5,E$27,Monthly!$C$14:$BJ$14) -> 1370963.1 | F35: =SUMIF(Monthly!$C$5:$BJ$5,F$27,Monthly!$C$14:$BJ$14) -> 1454454.7
A36: Wholesale revenue | B36: =SUMIF(Monthly!$C$5:$BJ$5,B$27,Monthly!$C$19:$BJ$19) -> 443664 | C36: =SUMIF(Monthly!$C$5:$BJ$5,C$27,Monthly!$C$19:$BJ$19) -> 518289.41 | D36: =SUMIF(Monthly!$C$5:$BJ$5,D$27,Monthly!$C$19:$BJ$19) -> 597898.66 | E36: =SUMIF(Monthly!$C$5:$BJ$5,E$27,Monthly!$C$19:$BJ$19) -> 689735.9 | F36: =SUMIF(Monthly!$C$5:$BJ$5,F$27,Monthly!$C$19:$BJ$19) -> 795679.33
A37: Wholesale share of revenue | B37: =IF(B34=0,0,B36/B34) -> 0.28125 | C37: =IF(C34=0,0,C36/C34) -> 0.29848978 | D37: =IF(D34=0,0,D36/D34) -> 0.31632124 | E37: =IF(E34=0,0,E36/E34) -> 0.33470968 | F37: =IF(F34=0,0,F36/F34) -> 0.35361419
A38: Retail revenue per opening day ($) | B38: =IF(B29=0,0,B35/B29) -> 3634 | C38: =IF(C29=0,0,C35/C29) -> 3904.112 | D38: =IF(D29=0,0,D35/D29) -> 4141.8724 | E38: =IF(E29=0,0,E35/E29) -> 4394.1125 | F38: =IF(F29=0,0,F35/F29) -> 4661.7139
A39: Waste cost (unsold retail production) | B39: =-SUMIF(Monthly!$C$5:$BJ$5,B$27,Monthly!$C$26:$BJ$26) -> 26912.366 | C39: =-SUMIF(Monthly!$C$5:$BJ$5,C$27,Monthly!$C$26:$BJ$26) -> 28912.738 | D39: =-SUMIF(Monthly!$C$5:$BJ$5,D$27,Monthly!$C$26:$BJ$26) -> 30673.524 | E39: =-SUMIF(Monthly!$C$5:$BJ$5,E$27,Monthly!$C$26:$BJ$26) -> 32541.541 | F39: =-SUMIF(Monthly!$C$5:$BJ$5,F$27,Monthly!$C$26:$BJ$26) -> 34523.321
A40: Waste cost, % of retail revenue | B40: =IF(B35=0,0,B39/B35) -> 0.023736264 | C40: =IF(C35=0,0,C39/C35) -> 0.023736264 | D40: =IF(D35=0,0,D39/D35) -> 0.023736264 | E40: =IF(E35=0,0,E39/E35) -> 0.023736264 | F40: =IF(F35=0,0,F39/F35) -> 0.023736264
A41: Wholesale delivery cost | B41: =-SUMIF(Monthly!$C$5:$BJ$5,B$27,Monthly!$C$35:$BJ$35) -> 36972 | C41: =-SUMIF(Monthly!$C$5:$BJ$5,C$27,Monthly!$C$35:$BJ$35) -> 41932.8 | D41: =-SUMIF(Monthly!$C$5:$BJ$5,D$27,Monthly!$C$35:$BJ$35) -> 46964.736 | E41: =-SUMIF(Monthly!$C$5:$BJ$5,E$27,Monthly!$C$35:$BJ$35) -> 52600.504 | F41: =-SUMIF(Monthly!$C$5:$BJ$5,F$27,Monthly!$C$35:$BJ$35) -> 58912.565
A42: Gross profit | B42: =SUMIF(Monthly!$C$5:$BJ$5,B$27,Monthly!$C$29:$BJ$29) -> 1076825.1 | C42: =SUMIF(Monthly!$C$5:$BJ$5,C$27,Monthly!$C$29:$BJ$29) -> 1183311.2 | D42: =SUMIF(Monthly!$C$5:$BJ$5,D$27,Monthly!$C$29:$BJ$29) -> 1285883.7 | E42: =SUMIF(Monthly!$C$5:$BJ$5,E$27,Monthly!$C$29:$BJ$29) -> 1399389 | F42: =SUMIF(Monthly!$C$5:$BJ$5,F$27,Monthly!$C$29:$BJ$29) -> 1525212.7
A43: Gross margin | B43: =IF(B34=0,0,B42/B34) -> 0.68262706 | C43: =IF(C34=0,0,C42/C34) -> 0.68148469 | D43: =IF(D34=0,0,D42/D34) -> 0.68030311 | E43: =IF(E34=0,0,E42/E34) -> 0.67908462 | F43: =IF(F34=0,0,F42/F34) -> 0.67783194
A44: Cost of sales | B44: =-SUMIF(Monthly!$C$5:$BJ$5,B$27,Monthly!$C$28:$BJ$28) -> 500646.93 | C44: =-SUMIF(Monthly!$C$5:$BJ$5,C$27,Monthly!$C$28:$BJ$28) -> 553061.18 | D44: =-SUMIF(Monthly!$C$5:$BJ$5,D$27,Monthly!$C$28:$BJ$28) -> 604279.19 | E44: =-SUMIF(Monthly!$C$5:$BJ$5,E$27,Monthly!$C$28:$BJ$28) -> 661309.99 | F44: =-SUMIF(Monthly!$C$5:$BJ$5,F$27,Monthly!$C$28:$BJ$28) -> 724921.33
A45: Payroll | B45: =-SUMIF(Monthly!$C$5:$BJ$5,B$27,Monthly!$C$32:$BJ$32) -> 593600 | C45: =-SUMIF(Monthly!$C$5:$BJ$5,C$27,Monthly!$C$32:$BJ$32) -> 641655.39 | D45: =-SUMIF(Monthly!$C$5:$BJ$5,D$27,Monthly!$C$32:$BJ$32) -> 693929.16 | E45: =-SUMIF(Monthly!$C$5:$BJ$5,E$27,Monthly!$C$32:$BJ$32) -> 750802.75 | F45: =-SUMIF(Monthly!$C$5:$BJ$5,F$27,Monthly!$C$32:$BJ$32) -> 812692.46
A46: Prime cost (cost of sales + payroll) % of revenue | B46: =IF(B34=0,0,(B44+B45)/B34) -> 0.69367122 | C46: =IF(C34=0,0,(C44+C45)/C34) -> 0.68805321 | D46: =IF(D34=0,0,(D44+D45)/D34) -> 0.68682354 | E46: =IF(E34=0,0,(E44+E45)/E34) -> 0.6852591 | F46: =IF(F34=0,0,(F44+F45)/F34) -> 0.68334319
A47: EBITDA | B47: =SUMIF(Monthly!$C$5:$BJ$5,B$27,Monthly!$C$41:$BJ$41) -> 145357.01 | C47: =SUMIF(Monthly!$C$5:$BJ$5,C$27,Monthly!$C$41:$BJ$41) -> 193289.21 | D47: =SUMIF(Monthly!$C$5:$BJ$5,D$27,Monthly!$C$41:$BJ$41) -> 233403.12 | E47: =SUMIF(Monthly!$C$5:$BJ$5,E$27,Monthly!$C$41:$BJ$41) -> 278784.79 | F47: =SUMIF(Monthly!$C$5:$BJ$5,F$27,Monthly!$C$41:$BJ$41) -> 330280.3
A48: EBITDA margin | B48: =IF(B34=0,0,B47/B34) -> 0.092145541 | C48: =IF(C34=0,0,C47/C34) -> 0.11131783 | D48: =IF(D34=0,0,D47/D34) -> 0.12348307 | E48: =IF(E34=0,0,E47/E34) -> 0.13528652 | F48: =IF(F34=0,0,F47/F34) -> 0.1467825

Sheet Inputs
A1: Inputs — Low / Base / High | I1: =HYPERLINK("#'Cover'!A1","◂ Contents") -> ◂ Contents
A2: Illustrative assumptions — replace them with your own numbers.
A5: Driver | B5: Low | C5: Base | D5: High | E5: Active | F5: Unit | G5: Source / comment
A6: Retail counter
A7: Customers per day at full traffic | B7: 300 | C7: 320 | D7: 340 | E7: =CHOOSE(Dashboard!$B$4,B7,C7,D7) -> 320 | F7: # | G7: Low ≤ Base ≤ High
A8: Months to reach full traffic | B8: 3 | C8: 2 | D8: 1 | E8: =CHOOSE(Dashboard!$B$4,B8,C8,D8) -> 2 | F8: months | G8: Low ≥ Base ≥ High (lower is better)
A9: Opening traffic, % of full | B9: 0.85 | C9: 0.9 | D9: 0.95 | E9: =CHOOSE(Dashboard!$B$4,B9,C9,D9) -> 0.9 | F9: % | G9: Low ≤ Base ≤ High
A10: Traffic growth per year (after year 1) | B10: 0.01 | C10: 0.03 | D10: 0.05 | E10: =CHOOSE(Dashboard!$B$4,B10,C10,D10) -> 0.03 | F10: % | G10: Low ≤ Base ≤ High
A11: Average ticket per customer (year 1) | B11: 11 | C11: 11.5 | D11: 12 | E11: =CHOOSE(Dashboard!$B$4,B11,C11,D11) -> 11.5 | F11: $ | G11: Low ≤ Base ≤ High
A12: Price increase per year | B12: 0.02 | C12: 0.03 | D12: 0.04 | E12: =CHOOSE(Dashboard!$B$4,B12,C12,D12) -> 0.03 | F12: % | G12: Low ≤ Base ≤ High
A13: Opening days per week | B13: 6 | C13: 6 | D13: 6 | E13: =CHOOSE(Dashboard!$B$4,B13,C13,D13) -> 6 | F13: days
A14: Holiday uplift, Nov-Dec (monthly models) | B14: 0.2 | C14: 0.2 | D14: 0.2 | E14: =CHOOSE(Dashboard!$B$4,B14,C14,D14) -> 0.2 | F14: %
A16: Wholesale
A17: Wholesale accounts at full ramp (year 1) | B17: 13 | C17: 16 | D17: 19 | E17: =CHOOSE(Dashboard!$B$4,B17,C17,D17) -> 16 | F17: # | G17: Low ≤ Base ≤ High
A18: Wholesale accounts growth per year | B18: 0.08 | C18: 0.12 | D18: 0.16 | E18: =CHOOSE(Dashboard!$B$4,B18,C18,D18) -> 0.12 | F18: % | G18: Low ≤ Base ≤ High
A19: Order value per account per week (year 1) | B19: 500 | C19: 540 | D19: 580 | E19: =CHOOSE(Dashboard!$B$4,B19,C19,D19) -> 540 | F19: $ | G19: Low ≤ Base ≤ High
A20: Deliveries per account per week | B20: 5 | C20: 5 | D20: 5 | E20: =CHOOSE(Dashboard!$B$4,B20,C20,D20) -> 5 | F20: #
A21: Delivery cost per drop (driver, fuel, van) | B21: 9.5 | C21: 9 | D21: 8.5 | E21: =CHOOSE(Dashboard!$B$4,B21,C21,D21) -> 9 | F21: $ | G21: Low ≥ Base ≥ High (lower is better)
A23: Cost of sales
A24: Ingredients of items sold, % of retail sales (excl. waste) | B24: 0.255 | C24: 0.24 | D24: 0.225 | E24: =CHOOSE(Dashboard!$B$4,B24,C24,D24) -> 0.24 | F24: % | G24: Low ≥ Base ≥ High (lower is better)
A25: Ingredients of items sold, % of wholesale sales | B25: 0.345 | C25: 0.33 | D25: 0.315 | E25: =CHOOSE(Dashboard!$B$4,B25,C25,D25) -> 0.33 | F25: % | G25: Low ≥ Base ≥ High (lower is better)
A26: Retail production baked but not sold (waste) | B26: 0.11 | C26: 0.09 | D26: 0.07 | E26: =CHOOSE(Dashboard!$B$4,B26,C26,D26) -> 0.09 | F26: % | G26: Low ≥ Base ≥ High (lower is better)
A27: Packaging, % of sales | B27: 0.037 | C27: 0.035 | D27: 0.033 | E27: =CHOOSE(Dashboard!$B$4,B27,C27,D27) -> 0.035 | F27: % | G27: Low ≥ Base ≥ High (lower is better)
A29: Operating costs
A30: Rent per month | B30: 12000 | C30: 12000 | D30: 12000 | E30: =CHOOSE(Dashboard!$B$4,B30,C30,D30) -> 12000 | F30: $
A31: Utilities per month (gas, power, water) | B31: 4000 | C31: 4000 | D31: 4000 | E31: =CHOOSE(Dashboard!$B$4,B31,C31,D31) -> 4000 | F31: $
A32: Equipment repairs & cleaning per month | B32: 1000 | C32: 1000 | D32: 1000 | E32: =CHOOSE(Dashboard!$B$4,B32,C32,D32) -> 1000 | F32: $
A33: Marketing, % of revenue | B33: 0.022 | C33: 0.02 | D33: 0.018 | E33: =CHOOSE(Dashboard!$B$4,B33,C33,D33) -> 0.02 | F33: % | G33: Low ≥ Base ≥ High (lower is better)
A34: Card processing fees, % of retail sales | B34: 0.029 | C34: 0.028 | D34: 0.027 | E34: =CHOOSE(Dashboard!$B$4,B34,C34,D34) -> 0.028 | F34: % | G34: Low ≥ Base ≥ High (lower is better)
A35: Insurance, licences & other G&A per month | B35: 2800 | C35: 2800 | D35: 2800 | E35: =CHOOSE(Dashboard!$B$4,B35,C35,D35) -> 2800 | F35: $
A37: Equipment
A38: Fit-out & equipment: ovens, mixers, cases | B38: 90000 | C38: 90000 | D38: 90000 | E38: =CHOOSE(Dashboard!$B$4,B38,C38,D38) -> 90000 | F38: $
A39: Equipment replacement per year (from year 2) | B39: 14000 | C39: 14000 | D39: 14000 | E39: =CHOOSE(Dashboard!$B$4,B39,C39,D39) -> 14000 | F39: $
A41: Headcount
A42: Bakers & production: headcount (FTE) | B42: 5 | C42: 5 | D42: 5 | E42: =CHOOSE(Dashboard!$B$4,B42,C42,D42) -> 5 | F42: FTE | G42: Low ≤ Base ≤ High
A43: Bakers & production: salary per FTE per year | B43: 44000 | C43: 44000 | D43: 44000 | E43: =CHOOSE(Dashboard!$B$4,B43,C43,D43) -> 44000 | F43: $
A44: Bakers & production: headcount growth per year | B44: 0.06 | C44: 0.06 | D44: 0.06 | E44: =CHOOSE(Dashboard!$B$4,B44,C44,D44) -> 0.06 | F44: % | G44: Low ≤ Base ≤ High
A45: Bakers & production: first month on payroll | B45: 1 | C45: 1 | D45: 1 | E45: =CHOOSE(Dashboard!$B$4,B45,C45,D45) -> 1 | F45: month #
A46: Counter staff: headcount (FTE) | B46: 7 | C46: 7 | D46: 7 | E46: =CHOOSE(Dashboard!$B$4,B46,C46,D46) -> 7 | F46: FTE | G46: Low ≤ Base ≤ High
A47: Counter staff: salary per FTE per year | B47: 31000 | C47: 31000 | D47: 31000 | E47: =CHOOSE(Dashboard!$B$4,B47,C47,D47) -> 31000 | F47: $
A48: Counter staff: headcount growth per year | B48: 0.06 | C48: 0.06 | D48: 0.06 | E48: =CHOOSE(Dashboard!$B$4,B48,C48,D48) -> 0.06 | F48: % | G48: Low ≤ Base ≤ High
A49: Counter staff: first month on payroll | B49: 1 | C49: 1 | D49: 1 | E49: =CHOOSE(Dashboard!$B$4,B49,C49,D49) -> 1 | F49: month #
A50: Manager: headcount (FTE) | B50: 1.5 | C50: 1.5 | D50: 1.5 | E50: =CHOOSE(Dashboard!$B$4,B50,C50,D50) -> 1.5 | F50: FTE | G50: Low ≤ Base ≤ High
A51: Manager: salary per FTE per year | B51: 62000 | C51: 62000 | D51: 62000 | E51: =CHOOSE(Dashboard!$B$4,B51,C51,D51) -> 62000 | F51: $
A52: Manager: headcount growth per year | B52: 0 | C52: 0 | D52: 0 | E52: =CHOOSE(Dashboard!$B$4,B52,C52,D52) -> 0 | F52: % | G52: Low ≤ Base ≤ High
A53: Manager: first month on payroll | B53: 1 | C53: 1 | D53: 1 | E53: =CHOOSE(Dashboard!$B$4,B53,C53,D53) -> 1 | F53: month #
A54: Payroll taxes & benefits, % of salary | B54: 0.12 | C54: 0.12 | D54: 0.12 | E54: =CHOOSE(Dashboard!$B$4,B54,C54,D54) -> 0.12 | F54: %
A55: Wage growth per year | B55: 0.03 | C55: 0.03 | D55: 0.03 | E55: =CHOOSE(Dashboard!$B$4,B55,C55,D55) -> 0.03 | F55: %
A57: Funding
A58: Equity raised at start | B58: 60000 | C58: 60000 | D58: 60000 | E58: =CHOOSE(Dashboard!$B$4,B58,C58,D58) -> 60000 | F58: $
A59: Loan drawn at start | B59: 80000 | C59: 80000 | D59: 80000 | E59: =CHOOSE(Dashboard!$B$4,B59,C59,D59) -> 80000 | F59: $
A60: Loan interest rate per year | B60: 0.085 | C60: 0.085 | D60: 0.085 | E60: =CHOOSE(Dashboard!$B$4,B60,C60,D60) -> 0.085 | F60: %
A61: Loan repayment term | B61: 5 | C61: 5 | D61: 5 | E61: =CHOOSE(Dashboard!$B$4,B61,C61,D61) -> 5 | F61: years
A63: Working capital
A64: Customer payment terms (receivable days) | B64: 9 | C64: 9 | D64: 9 | E64: =CHOOSE(Dashboard!$B$4,B64,C64,D64) -> 9 | F64: days
A65: Inventory held (days of COGS) | B65: 3 | C65: 3 | D65: 3 | E65: =CHOOSE(Dashboard!$B$4,B65,C65,D65) -> 3 | F65: days
A66: Supplier payment terms (payable days) | B66: 18 | C66: 18 | D66: 18 | E66: =CHOOSE(Dashboard!$B$4,B66,C66,D66) -> 18 | F66: days
A68: Tax & depreciation
A69: Depreciation period for capex | B69: 7 | C69: 7 | D69: 7 | E69: =CHOOSE(Dashboard!$B$4,B69,C69,D69) -> 7 | F69: years
A70: Income tax rate | B70: 0.21 | C70: 0.21 | D70: 0.21 | E70: =CHOOSE(Dashboard!$B$4,B70,C70,D70) -> 0.21 | F70: %
A72: Break-even & funding
A73: Minimum cash buffer to keep | B73: 233000 | C73: 233000 | D73: 233000 | E73: =CHOOSE(Dashboard!$B$4,B73,C73,D73) -> 233000 | F73: $ | G73: About 3 months of costs
A75: Valuation
A76: Discount rate (WACC) | B76: 0.2 | C76: 0.16 | D76: 0.13 | E76: =CHOOSE(Dashboard!$B$4,B76,C76,D76) -> 0.16 | F76: % | G76: Low ≥ Base ≥ High (lower is better)
A77: Terminal growth rate (perpetuity) | B77: 0.01 | C77: 0.02 | D77: 0.03 | E77: =CHOOSE(Dashboard!$B$4,B77,C77,D77) -> 0.02 | F77: % | G77: Low ≤ Base ≤ High
A78: Exit multiple (EV ÷ final-year EBITDA) | B78: 4 | C78: 5.5 | D78: 7 | E78: =CHOOSE(Dashboard!$B$4,B78,C78,D78) -> 5.5 | F78: x | G78: Low ≤ Base ≤ High
A79: Sensitivity table: WACC step | B79: 0.01 | C79: 0.01 | D79: 0.01 | E79: =CHOOSE(Dashboard!$B$4,B79,C79,D79) -> 0.01 | F79: %
A80: Sensitivity table: growth step | B80: 0.005 | C80: 0.005 | D80: 0.005 | E80: =CHOOSE(Dashboard!$B$4,B80,C80,D80) -> 0.005 | F80: %
A82: Legend: yellow cell with blue figure = input you can change · black = formula · green = link to another sheet · grey = active value (column E follows the scenario on the Dashboard).

Sheet P&L
A1: Annual profit & loss | H1: =HYPERLINK("#'Cover'!A1","◂ Contents") -> ◂ Contents
A2: Rolled up from the period detail (SUMIF on the year row; balances at year end).
A3: Year # | B3: 1 | C3: 2 | D3: 3 | E3: 4 | F3: 5
B4: Year 1 | C4: Year 2 | D4: Year 3 | E4: Year 4 | F4: Year 5
A5: Revenue | B5: =SUMIF(Monthly!$C$5:$BJ$5,B$3,Monthly!$C$22:$BJ$22) -> 1577472 | C5: =SUMIF(Monthly!$C$5:$BJ$5,C$3,Monthly!$C$22:$BJ$22) -> 1736372.4 | D5: =SUMIF(Monthly!$C$5:$BJ$5,D$3,Monthly!$C$22:$BJ$22) -> 1890162.9 | E5: =SUMIF(Monthly!$C$5:$BJ$5,E$3,Monthly!$C$22:$BJ$22) -> 2060699 | F5: =SUMIF(Monthly!$C$5:$BJ$5,F$3,Monthly!$C$22:$BJ$22) -> 2250134.1
A6: Cost of sales | B6: =SUMIF(Monthly!$C$5:$BJ$5,B$3,Monthly!$C$28:$BJ$28) -> -500646.93 | C6: =SUMIF(Monthly!$C$5:$BJ$5,C$3,Monthly!$C$28:$BJ$28) -> -553061.18 | D6: =SUMIF(Monthly!$C$5:$BJ$5,D$3,Monthly!$C$28:$BJ$28) -> -604279.19 | E6: =SUMIF(Monthly!$C$5:$BJ$5,E$3,Monthly!$C$28:$BJ$28) -> -661309.99 | F6: =SUMIF(Monthly!$C$5:$BJ$5,F$3,Monthly!$C$28:$BJ$28) -> -724921.33
A7: Gross profit | B7: =SUMIF(Monthly!$C$5:$BJ$5,B$3,Monthly!$C$29:$BJ$29) -> 1076825.1 | C7: =SUMIF(Monthly!$C$5:$BJ$5,C$3,Monthly!$C$29:$BJ$29) -> 1183311.2 | D7: =SUMIF(Monthly!$C$5:$BJ$5,D$3,Monthly!$C$29:$BJ$29) -> 1285883.7 | E7: =SUMIF(Monthly!$C$5:$BJ$5,E$3,Monthly!$C$29:$BJ$29) -> 1399389 | F7: =SUMIF(Monthly!$C$5:$BJ$5,F$3,Monthly!$C$29:$BJ$29) -> 1525212.7
A8: Gross margin | B8: =IF(B5=0,0,B7/B5) -> 0.68262706 | C8: =IF(C5=0,0,C7/C5) -> 0.68148469 | D8: =IF(D5=0,0,D7/D5) -> 0.68030311 | E8: =IF(E5=0,0,E7/E5) -> 0.67908462 | F8: =IF(F5=0,0,F7/F5) -> 0.67783194
A9: Payroll (bakers, counter, manager) | B9: =SUMIF(Monthly!$C$5:$BJ$5,B$3,Monthly!$C$32:$BJ$32) -> -593600 | C9: =SUMIF(Monthly!$C$5:$BJ$5,C$3,Monthly!$C$32:$BJ$32) -> -641655.39 | D9: =SUMIF(Monthly!$C$5:$BJ$5,D$3,Monthly!$C$32:$BJ$32) -> -693929.16 | E9: =SUMIF(Monthly!$C$5:$BJ$5,E$3,Monthly!$C$32:$BJ$32) -> -750802.75 | F9: =SUMIF(Monthly!$C$5:$BJ$5,F$3,Monthly!$C$32:$BJ$32) -> -812692.46
A10: Rent | B10: =SUMIF(Monthly!$C$5:$BJ$5,B$3,Monthly!$C$33:$BJ$33) -> -144000 | C10: =SUMIF(Monthly!$C$5:$BJ$5,C$3,Monthly!$C$33:$BJ$33) -> -144000 | D10: =SUMIF(Monthly!$C$5:$BJ$5,D$3,Monthly!$C$33:$BJ$33) -> -144000 | E10: =SUMIF(Monthly!$C$5:$BJ$5,E$3,Monthly!$C$33:$BJ$33) -> -144000 | F10: =SUMIF(Monthly!$C$5:$BJ$5,F$3,Monthly!$C$33:$BJ$33) -> -144000
A11: Utilities (ovens) | B11: =SUMIF(Monthly!$C$5:$BJ$5,B$3,Monthly!$C$34:$BJ$34) -> -48000 | C11: =SUMIF(Monthly!$C$5:$BJ$5,C$3,Monthly!$C$34:$BJ$34) -> -48000 | D11: =SUMIF(Monthly!$C$5:$BJ$5,D$3,Monthly!$C$34:$BJ$34) -> -48000 | E11: =SUMIF(Monthly!$C$5:$BJ$5,E$3,Monthly!$C$34:$BJ$34) -> -48000 | F11: =SUMIF(Monthly!$C$5:$BJ$5,F$3,Monthly!$C$34:$BJ$34) -> -48000
A12: Wholesale delivery | B12: =SUMIF(Monthly!$C$5:$BJ$5,B$3,Monthly!$C$35:$BJ$35) -> -36972 | C12: =SUMIF(Monthly!$C$5:$BJ$5,C$3,Monthly!$C$35:$BJ$35) -> -41932.8 | D12: =SUMIF(Monthly!$C$5:$BJ$5,D$3,Monthly!$C$35:$BJ$35) -> -46964.736 | E12: =SUMIF(Monthly!$C$5:$BJ$5,E$3,Monthly!$C$35:$BJ$35) -> -52600.504 | F12: =SUMIF(Monthly!$C$5:$BJ$5,F$3,Monthly!$C$35:$BJ$35) -> -58912.565
A13: Equipment repairs & cleaning | B13: =SUMIF(Monthly!$C$5:$BJ$5,B$3,Monthly!$C$36:$BJ$36) -> -12000 | C13: =SUMIF(Monthly!$C$5:$BJ$5,C$3,Monthly!$C$36:$BJ$36) -> -12000 | D13: =SUMIF(Monthly!$C$5:$BJ$5,D$3,Monthly!$C$36:$BJ$36) -> -12000 | E13: =SUMIF(Monthly!$C$5:$BJ$5,E$3,Monthly!$C$36:$BJ$36) -> -12000 | F13: =SUMIF(Monthly!$C$5:$BJ$5,F$3,Monthly!$C$36:$BJ$36) -> -12000
A14: Marketing | B14: =SUMIF(Monthly!$C$5:$BJ$5,B$3,Monthly!$C$37:$BJ$37) -> -31549.44 | C14: =SUMIF(Monthly!$C$5:$BJ$5,C$3,Monthly!$C$37:$BJ$37) -> -34727.447 | D14: =SUMIF(Monthly!$C$5:$BJ$5,D$3,Monthly!$C$37:$BJ$37) -> -37803.257 | E14: =SUMIF(Monthly!$C$5:$BJ$5,E$3,Monthly!$C$37:$BJ$37) -> -41213.98 | F14: =SUMIF(Monthly!$C$5:$BJ$5,F$3,Monthly!$C$37:$BJ$37) -> -45002.681
A15: Card processing fees | B15: =SUMIF(Monthly!$C$5:$BJ$5,B$3,Monthly!$C$38:$BJ$38) -> -31746.624 | C15: =SUMIF(Monthly!$C$5:$BJ$5,C$3,Monthly!$C$38:$BJ$38) -> -34106.322 | D15: =SUMIF(Monthly!$C$5:$BJ$5,D$3,Monthly!$C$38:$BJ$38) -> -36183.397 | E15: =SUMIF(Monthly!$C$5:$BJ$5,E$3,Monthly!$C$38:$BJ$38) -> -38386.966 | F15: =SUMIF(Monthly!$C$5:$BJ$5,F$3,Monthly!$C$38:$BJ$38) -> -40724.733
A16: Insurance, licences & other G&A | B16: =SUMIF(Monthly!$C$5:$BJ$5,B$3,Monthly!$C$39:$BJ$39) -> -33600 | C16: =SUMIF(Monthly!$C$5:$BJ$5,C$3,Monthly!$C$39:$BJ$39) -> -33600 | D16: =SUMIF(Monthly!$C$5:$BJ$5,D$3,Monthly!$C$39:$BJ$39) -> -33600 | E16: =SUMIF(Monthly!$C$5:$BJ$5,E$3,Monthly!$C$39:$BJ$39) -> -33600 | F16: =SUMIF(Monthly!$C$5:$BJ$5,F$3,Monthly!$C$39:$BJ$39) -> -33600
A17: Total operating expenses | B17: =SUMIF(Monthly!$C$5:$BJ$5,B$3,Monthly!$C$40:$BJ$40) -> -931468.06 | C17: =SUMIF(Monthly!$C$5:$BJ$5,C$3,Monthly!$C$40:$BJ$40) -> -990021.96 | D17: =SUMIF(Monthly!$C$5:$BJ$5,D$3,Monthly!$C$40:$BJ$40) -> -1052480.5 | E17: =SUMIF(Monthly!$C$5:$BJ$5,E$3,Monthly!$C$40:$BJ$40) -> -1120604.2 | F17: =SUMIF(Monthly!$C$5:$BJ$5,F$3,Monthly!$C$40:$BJ$40) -> -1194932.4
A18: EBITDA | B18: =SUMIF(Monthly!$C$5:$BJ$5,B$3,Monthly!$C$41:$BJ$41) -> 145357.01 | C18: =SUMIF(Monthly!$C$5:$BJ$5,C$3,Monthly!$C$41:$BJ$41) -> 193289.21 | D18: =SUMIF(Monthly!$C$5:$BJ$5,D$3,Monthly!$C$41:$BJ$41) -> 233403.12 | E18: =SUMIF(Monthly!$C$5:$BJ$5,E$3,Monthly!$C$41:$BJ$41) -> 278784.79 | F18: =SUMIF(Monthly!$C$5:$BJ$5,F$3,Monthly!$C$41:$BJ$41) -> 330280.3
A19: EBITDA margin | B19: =IF(B5=0,0,B18/B5) -> 0.092145541 | C19: =IF(C5=0,0,C18/C5) -> 0.11131783 | D19: =IF(D5=0,0,D18/D5) -> 0.12348307 | E19: =IF(E5=0,0,E18/E5) -> 0.13528652 | F19: =IF(F5=0,0,F18/F5) -> 0.1467825
A20: Depreciation | B20: =SUMIF(Monthly!$C$5:$BJ$5,B$3,Monthly!$C$55:$BJ$55) -> -12857.143 | C20: =SUMIF(Monthly!$C$5:$BJ$5,C$3,Monthly!$C$55:$BJ$55) -> -13940.476 | D20: =SUMIF(Monthly!$C$5:$BJ$5,D$3,Monthly!$C$55:$BJ$55) -> -15940.476 | E20: =SUMIF(Monthly!$C$5:$BJ$5,E$3,Monthly!$C$55:$BJ$55) -> -17940.476 | F20: =SUMIF(Monthly!$C$5:$BJ$5,F$3,Monthly!$C$55:$BJ$55) -> -19940.476
A21: EBIT | B21: =SUMIF(Monthly!$C$5:$BJ$5,B$3,Monthly!$C$44:$BJ$44) -> 132499.87 | C21: =SUMIF(Monthly!$C$5:$BJ$5,C$3,Monthly!$C$44:$BJ$44) -> 179348.73 | D21: =SUMIF(Monthly!$C$5:$BJ$5,D$3,Monthly!$C$44:$BJ$44) -> 217462.64 | E21: =SUMIF(Monthly!$C$5:$BJ$5,E$3,Monthly!$C$44:$BJ$44) -> 260844.32 | F21: =SUMIF(Monthly!$C$5:$BJ$5,F$3,Monthly!$C$44:$BJ$44) -> 310339.82
A22: Interest | B22: =SUMIF(Monthly!$C$5:$BJ$5,B$3,Monthly!$C$45:$BJ$45) -> -6228.6111 | C22: =SUMIF(Monthly!$C$5:$BJ$5,C$3,Monthly!$C$45:$BJ$45) -> -4873.3333 | D22: =SUMIF(Monthly!$C$5:$BJ$5,D$3,Monthly!$C$45:$BJ$45) -> -3513.3333 | E22: =SUMIF(Monthly!$C$5:$BJ$5,E$3,Monthly!$C$45:$BJ$45) -> -2153.3333 | F22: =SUMIF(Monthly!$C$5:$BJ$5,F$3,Monthly!$C$45:$BJ$45) -> -793.33333
A23: Pre-tax income | B23: =SUMIF(Monthly!$C$5:$BJ$5,B$3,Monthly!$C$46:$BJ$46) -> 126271.26 | C23: =SUMIF(Monthly!$C$5:$BJ$5,C$3,Monthly!$C$46:$BJ$46) -> 174475.4 | D23: =SUMIF(Monthly!$C$5:$BJ$5,D$3,Monthly!$C$46:$BJ$46) -> 213949.31 | E23: =SUMIF(Monthly!$C$5:$BJ$5,E$3,Monthly!$C$46:$BJ$46) -> 258690.98 | F23: =SUMIF(Monthly!$C$5:$BJ$5,F$3,Monthly!$C$46:$BJ$46) -> 309546.49
A24: Income tax | B24: =SUMIF(Monthly!$C$5:$BJ$5,B$3,Monthly!$C$49:$BJ$49) -> -26516.964 | C24: =SUMIF(Monthly!$C$5:$BJ$5,C$3,Monthly!$C$49:$BJ$49) -> -36639.834 | D24: =SUMIF(Monthly!$C$5:$BJ$5,D$3,Monthly!$C$49:$BJ$49) -> -44929.355 | E24: =SUMIF(Monthly!$C$5:$BJ$5,E$3,Monthly!$C$49:$BJ$49) -> -54325.106 | F24: =SUMIF(Monthly!$C$5:$BJ$5,F$3,Monthly!$C$49:$BJ$49) -> -65004.763
A25: Net income | B25: =SUMIF(Monthly!$C$5:$BJ$5,B$3,Monthly!$C$50:$BJ$50) -> 99754.292 | C25: =SUMIF(Monthly!$C$5:$BJ$5,C$3,Monthly!$C$50:$BJ$50) -> 137835.57 | D25: =SUMIF(Monthly!$C$5:$BJ$5,D$3,Monthly!$C$50:$BJ$50) -> 169019.96 | E25: =SUMIF(Monthly!$C$5:$BJ$5,E$3,Monthly!$C$50:$BJ$50) -> 204365.88 | F25: =SUMIF(Monthly!$C$5:$BJ$5,F$3,Monthly!$C$50:$BJ$50) -> 244541.73
A26: Net margin | B26: =IF(B5=0,0,B25/B5) -> 0.063236807 | C26: =IF(C5=0,0,C25/C5) -> 0.079381341 | D26: =IF(D5=0,0,D25/D5) -> 0.089420843 | E26: =IF(E5=0,0,E25/E5) -> 0.099173086 | F26: =IF(F5=0,0,F25/F5) -> 0.10867874

Sheet Cash Flow
A1: Annual cash flow statement | H1: =HYPERLINK("#'Cover'!A1","◂ Contents") -> ◂ Contents
A2: Rolled up from the period detail (SUMIF on the year row; balances at year end).
A3: Year # | B3: 1 | C3: 2 | D3: 3 | E3: 4 | F3: 5
B4: Year 1 | C4: Year 2 | D4: Year 3 | E4: Year 4 | F4: Year 5
A5: Net income | B5: =SUMIF(Monthly!$C$5:$BJ$5,B$3,Monthly!$C$50:$BJ$50) -> 99754.292 | C5: =SUMIF(Monthly!$C$5:$BJ$5,C$3,Monthly!$C$50:$BJ$50) -> 137835.57 | D5: =SUMIF(Monthly!$C$5:$BJ$5,D$3,Monthly!$C$50:$BJ$50) -> 169019.96 | E5: =SUMIF(Monthly!$C$5:$BJ$5,E$3,Monthly!$C$50:$BJ$50) -> 204365.88 | F5: =SUMIF(Monthly!$C$5:$BJ$5,F$3,Monthly!$C$50:$BJ$50) -> 244541.73
A6: Add back depreciation | B6: =-SUMIF(Monthly!$C$5:$BJ$5,B$3,Monthly!$C$55:$BJ$55) -> 12857.143 | C6: =-SUMIF(Monthly!$C$5:$BJ$5,C$3,Monthly!$C$55:$BJ$55) -> 13940.476 | D6: =-SUMIF(Monthly!$C$5:$BJ$5,D$3,Monthly!$C$55:$BJ$55) -> 15940.476 | E6: =-SUMIF(Monthly!$C$5:$BJ$5,E$3,Monthly!$C$55:$BJ$55) -> 17940.476 | F6: =-SUMIF(Monthly!$C$5:$BJ$5,F$3,Monthly!$C$55:$BJ$55) -> 19940.476
A7: (Increase) / decrease in receivables | B7: =SUMIF(Monthly!$C$5:$BJ$5,B$3,Monthly!$C$69:$BJ$69) -> -45676.8 | C7: =SUMIF(Monthly!$C$5:$BJ$5,C$3,Monthly!$C$69:$BJ$69) -> -3822.9235 | D7: =SUMIF(Monthly!$C$5:$BJ$5,D$3,Monthly!$C$69:$BJ$69) -> -4215.6689 | E7: =SUMIF(Monthly!$C$5:$BJ$5,E$3,Monthly!$C$69:$BJ$69) -> -4656.8975 | F7: =SUMIF(Monthly!$C$5:$BJ$5,F$3,Monthly!$C$69:$BJ$69) -> -5153.3354
A8: (Increase) / decrease in inventory | B8: =SUMIF(Monthly!$C$5:$BJ$5,B$3,Monthly!$C$70:$BJ$70) -> -4796.5303 | C8: =SUMIF(Monthly!$C$5:$BJ$5,C$3,Monthly!$C$70:$BJ$70) -> -418.78881 | D8: =SUMIF(Monthly!$C$5:$BJ$5,D$3,Monthly!$C$70:$BJ$70) -> -463.75111 | E8: =SUMIF(Monthly!$C$5:$BJ$5,E$3,Monthly!$C$70:$BJ$70) -> -514.44038 | F8: =SUMIF(Monthly!$C$5:$BJ$5,F$3,Monthly!$C$70:$BJ$70) -> -571.66445
A9: Increase / (decrease) in payables | B9: =SUMIF(Monthly!$C$5:$BJ$5,B$3,Monthly!$C$71:$BJ$71) -> 28779.182 | C9: =SUMIF(Monthly!$C$5:$BJ$5,C$3,Monthly!$C$71:$BJ$71) -> 2512.7328 | D9: =SUMIF(Monthly!$C$5:$BJ$5,D$3,Monthly!$C$71:$BJ$71) -> 2782.5067 | E9: =SUMIF(Monthly!$C$5:$BJ$5,E$3,Monthly!$C$71:$BJ$71) -> 3086.6423 | F9: =SUMIF(Monthly!$C$5:$BJ$5,F$3,Monthly!$C$71:$BJ$71) -> 3429.9867
A10: Operating cash flow | B10: =SUMIF(Monthly!$C$5:$BJ$5,B$3,Monthly!$C$74:$BJ$74) -> 90917.287 | C10: =SUMIF(Monthly!$C$5:$BJ$5,C$3,Monthly!$C$74:$BJ$74) -> 150047.06 | D10: =SUMIF(Monthly!$C$5:$BJ$5,D$3,Monthly!$C$74:$BJ$74) -> 183063.52 | E10: =SUMIF(Monthly!$C$5:$BJ$5,E$3,Monthly!$C$74:$BJ$74) -> 220221.66 | F10: =SUMIF(Monthly!$C$5:$BJ$5,F$3,Monthly!$C$74:$BJ$74) -> 262187.19
A11: Capital spending | B11: =SUMIF(Monthly!$C$5:$BJ$5,B$3,Monthly!$C$75:$BJ$75) -> -90000 | C11: =SUMIF(Monthly!$C$5:$BJ$5,C$3,Monthly!$C$75:$BJ$75) -> -14000 | D11: =SUMIF(Monthly!$C$5:$BJ$5,D$3,Monthly!$C$75:$BJ$75) -> -14000 | E11: =SUMIF(Monthly!$C$5:$BJ$5,E$3,Monthly!$C$75:$BJ$75) -> -14000 | F11: =SUMIF(Monthly!$C$5:$BJ$5,F$3,Monthly!$C$75:$BJ$75) -> -14000
A12: Equity raised | B12: =SUMIF(Monthly!$C$5:$BJ$5,B$3,Monthly!$C$76:$BJ$76) -> 60000 | C12: =SUMIF(Monthly!$C$5:$BJ$5,C$3,Monthly!$C$76:$BJ$76) -> 0 | D12: =SUMIF(Monthly!$C$5:$BJ$5,D$3,Monthly!$C$76:$BJ$76) -> 0 | E12: =SUMIF(Monthly!$C$5:$BJ$5,E$3,Monthly!$C$76:$BJ$76) -> 0 | F12: =SUMIF(Monthly!$C$5:$BJ$5,F$3,Monthly!$C$76:$BJ$76) -> 0
A13: Loan drawdown | B13: =SUMIF(Monthly!$C$5:$BJ$5,B$3,Monthly!$C$61:$BJ$61) -> 80000 | C13: =SUMIF(Monthly!$C$5:$BJ$5,C$3,Monthly!$C$61:$BJ$61) -> 0 | D13: =SUMIF(Monthly!$C$5:$BJ$5,D$3,Monthly!$C$61:$BJ$61) -> 0 | E13: =SUMIF(Monthly!$C$5:$BJ$5,E$3,Monthly!$C$61:$BJ$61) -> 0 | F13: =SUMIF(Monthly!$C$5:$BJ$5,F$3,Monthly!$C$61:$BJ$61) -> 0
A14: Loan repayment | B14: =SUMIF(Monthly!$C$5:$BJ$5,B$3,Monthly!$C$62:$BJ$62) -> -14666.667 | C14: =SUMIF(Monthly!$C$5:$BJ$5,C$3,Monthly!$C$62:$BJ$62) -> -16000 | D14: =SUMIF(Monthly!$C$5:$BJ$5,D$3,Monthly!$C$62:$BJ$62) -> -16000 | E14: =SUMIF(Monthly!$C$5:$BJ$5,E$3,Monthly!$C$62:$BJ$62) -> -16000 | F14: =SUMIF(Monthly!$C$5:$BJ$5,F$3,Monthly!$C$62:$BJ$62) -> -16000
A15: Financing cash flow | B15: =SUMIF(Monthly!$C$5:$BJ$5,B$3,Monthly!$C$77:$BJ$77) -> 125333.33 | C15: =SUMIF(Monthly!$C$5:$BJ$5,C$3,Monthly!$C$77:$BJ$77) -> -16000 | D15: =SUMIF(Monthly!$C$5:$BJ$5,D$3,Monthly!$C$77:$BJ$77) -> -16000 | E15: =SUMIF(Monthly!$C$5:$BJ$5,E$3,Monthly!$C$77:$BJ$77) -> -16000 | F15: =SUMIF(Monthly!$C$5:$BJ$5,F$3,Monthly!$C$77:$BJ$77) -> -16000
A16: Net change in cash | B16: =SUMIF(Monthly!$C$5:$BJ$5,B$3,Monthly!$C$78:$BJ$78) -> 126250.62 | C16: =SUMIF(Monthly!$C$5:$BJ$5,C$3,Monthly!$C$78:$BJ$78) -> 120047.06 | D16: =SUMIF(Monthly!$C$5:$BJ$5,D$3,Monthly!$C$78:$BJ$78) -> 153063.52 | E16: =SUMIF(Monthly!$C$5:$BJ$5,E$3,Monthly!$C$78:$BJ$78) -> 190221.66 | F16: =SUMIF(Monthly!$C$5:$BJ$5,F$3,Monthly!$C$78:$BJ$78) -> 232187.19
A17: Opening cash | B17: =INDEX(Monthly!$C$79:$BJ$79,(B$3-1)*12+1) -> 0 | C17: =INDEX(Monthly!$C$79:$BJ$79,(C$3-1)*12+1) -> 126250.62 | D17: =INDEX(Monthly!$C$79:$BJ$79,(D$3-1)*12+1) -> 246297.68 | E17: =INDEX(Monthly!$C$79:$BJ$79,(E$3-1)*12+1) -> 399361.2 | F17: =INDEX(Monthly!$C$79:$BJ$79,(F$3-1)*12+1) -> 589582.86
A18: Closing cash | B18: =INDEX(Monthly!$C$80:$BJ$80,B$3*12) -> 126250.62 | C18: =INDEX(Monthly!$C$80:$BJ$80,C$3*12) -> 246297.68 | D18: =INDEX(Monthly!$C$80:$BJ$80,D$3*12) -> 399361.2 | E18: =INDEX(Monthly!$C$80:$BJ$80,E$3*12) -> 589582.86 | F18: =INDEX(Monthly!$C$80:$BJ$80,F$3*12) -> 821770.05

Sheet Balance Sheet
A1: Balance sheet at year end | H1: =HYPERLINK("#'Cover'!A1","◂ Contents") -> ◂ Contents
A2: Rolled up from the period detail (SUMIF on the year row; balances at year end).
A3: Year # | B3: 1 | C3: 2 | D3: 3 | E3: 4 | F3: 5
B4: Year 1 | C4: Year 2 | D4: Year 3 | E4: Year 4 | F4: Year 5
A5: Cash | B5: =INDEX(Monthly!$C$80:$BJ$80,B$3*12) -> 126250.62 | C5: =INDEX(Monthly!$C$80:$BJ$80,C$3*12) -> 246297.68 | D5: =INDEX(Monthly!$C$80:$BJ$80,D$3*12) -> 399361.2 | E5: =INDEX(Monthly!$C$80:$BJ$80,E$3*12) -> 589582.86 | F5: =INDEX(Monthly!$C$80:$BJ$80,F$3*12) -> 821770.05
A6: Accounts receivable | B6: =INDEX(Monthly!$C$66:$BJ$66,B$3*12) -> 45676.8 | C6: =INDEX(Monthly!$C$66:$BJ$66,C$3*12) -> 49499.724 | D6: =INDEX(Monthly!$C$66:$BJ$66,D$3*12) -> 53715.392 | E6: =INDEX(Monthly!$C$66:$BJ$66,E$3*12) -> 58372.29 | F6: =INDEX(Monthly!$C$66:$BJ$66,F$3*12) -> 63525.625
A7: Inventory | B7: =INDEX(Monthly!$C$67:$BJ$67,B$3*12) -> 4796.5303 | C7: =INDEX(Monthly!$C$67:$BJ$67,C$3*12) -> 5215.3191 | D7: =INDEX(Monthly!$C$67:$BJ$67,D$3*12) -> 5679.0702 | E7: =INDEX(Monthly!$C$67:$BJ$67,E$3*12) -> 6193.5106 | F7: =INDEX(Monthly!$C$67:$BJ$67,F$3*12) -> 6765.175
A8: Net fixed assets | B8: =INDEX(Monthly!$C$57:$BJ$57,B$3*12) -> 77142.857 | C8: =INDEX(Monthly!$C$57:$BJ$57,C$3*12) -> 77202.381 | D8: =INDEX(Monthly!$C$57:$BJ$57,D$3*12) -> 75261.905 | E8: =INDEX(Monthly!$C$57:$BJ$57,E$3*12) -> 71321.429 | F8: =INDEX(Monthly!$C$57:$BJ$57,F$3*12) -> 65380.952
A9: Total assets | B9: =INDEX(Monthly!$C$94:$BJ$94,B$3*12) -> 253866.81 | C9: =INDEX(Monthly!$C$94:$BJ$94,C$3*12) -> 378215.11 | D9: =INDEX(Monthly!$C$94:$BJ$94,D$3*12) -> 534017.57 | E9: =INDEX(Monthly!$C$94:$BJ$94,E$3*12) -> 725470.09 | F9: =INDEX(Monthly!$C$94:$BJ$94,F$3*12) -> 957441.8
A10: Accounts payable | B10: =INDEX(Monthly!$C$68:$BJ$68,B$3*12) -> 28779.182 | C10: =INDEX(Monthly!$C$68:$BJ$68,C$3*12) -> 31291.915 | D10: =INDEX(Monthly!$C$68:$BJ$68,D$3*12) -> 34074.421 | E10: =INDEX(Monthly!$C$68:$BJ$68,E$3*12) -> 37161.063 | F10: =INDEX(Monthly!$C$68:$BJ$68,F$3*12) -> 40591.05
A11: Loan | B11: =INDEX(Monthly!$C$63:$BJ$63,B$3*12) -> 65333.333 | C11: =INDEX(Monthly!$C$63:$BJ$63,C$3*12) -> 49333.333 | D11: =INDEX(Monthly!$C$63:$BJ$63,D$3*12) -> 33333.333 | E11: =INDEX(Monthly!$C$63:$BJ$63,E$3*12) -> 17333.333 | F11: =INDEX(Monthly!$C$63:$BJ$63,F$3*12) -> 1333.3333
A12: Total liabilities | B12: =INDEX(Monthly!$C$95:$BJ$95,B$3*12) -> 94112.515 | C12: =INDEX(Monthly!$C$95:$BJ$95,C$3*12) -> 80625.248 | D12: =INDEX(Monthly!$C$95:$BJ$95,D$3*12) -> 67407.755 | E12: =INDEX(Monthly!$C$95:$BJ$95,E$3*12) -> 54494.397 | F12: =INDEX(Monthly!$C$95:$BJ$95,F$3*12) -> 41924.384
A13: Paid-in capital | B13: =INDEX(Monthly!$C$92:$BJ$92,B$3*12) -> 60000 | C13: =INDEX(Monthly!$C$92:$BJ$92,C$3*12) -> 60000 | D13: =INDEX(Monthly!$C$92:$BJ$92,D$3*12) -> 60000 | E13: =INDEX(Monthly!$C$92:$BJ$92,E$3*12) -> 60000 | F13: =INDEX(Monthly!$C$92:$BJ$92,F$3*12) -> 60000
A14: Retained earnings | B14: =INDEX(Monthly!$C$93:$BJ$93,B$3*12) -> 99754.292 | C14: =INDEX(Monthly!$C$93:$BJ$93,C$3*12) -> 237589.86 | D14: =INDEX(Monthly!$C$93:$BJ$93,D$3*12) -> 406609.81 | E14: =INDEX(Monthly!$C$93:$BJ$93,E$3*12) -> 610975.69 | F14: =INDEX(Monthly!$C$93:$BJ$93,F$3*12) -> 855517.42
A15: Total equity | B15: =INDEX(Monthly!$C$96:$BJ$96,B$3*12) -> 159754.29 | C15: =INDEX(Monthly!$C$96:$BJ$96,C$3*12) -> 297589.86 | D15: =INDEX(Monthly!$C$96:$BJ$96,D$3*12) -> 466609.81 | E15: =INDEX(Monthly!$C$96:$BJ$96,E$3*12) -> 670975.69 | F15: =INDEX(Monthly!$C$96:$BJ$96,F$3*12) -> 915517.42
A16: Total liabilities & equity | B16: =INDEX(Monthly!$C$97:$BJ$97,B$3*12) -> 253866.81 | C16: =INDEX(Monthly!$C$97:$BJ$97,C$3*12) -> 378215.11 | D16: =INDEX(Monthly!$C$97:$BJ$97,D$3*12) -> 534017.57 | E16: =INDEX(Monthly!$C$97:$BJ$97,E$3*12) -> 725470.09 | F16: =INDEX(Monthly!$C$97:$BJ$97,F$3*12) -> 957441.8
A17: Check: assets − liabilities − equity (must be 0) | B17: =INDEX(Monthly!$C$98:$BJ$98,B$3*12) -> 0 | C17: =INDEX(Monthly!$C$98:$BJ$98,C$3*12) -> 0 | D17: =INDEX(Monthly!$C$98:$BJ$98,D$3*12) -> 0 | E17: =INDEX(Monthly!$C$98:$BJ$98,E$3*12) -> 0 | F17: =INDEX(Monthly!$C$98:$BJ$98,F$3*12) -> 0

Sheet Monthly
A1: Monthly projection | D1: =HYPERLINK("#'Cover'!A1","◂ Contents") -> ◂ Contents
A2: $ unless stated; costs shown as negatives. Every period uses the same formula.
A3: Month | C3: M1 | D3: M2 | E3: M3 | F3: M4 | G3: M5 | H3: M6 | I3: M7 | J3: M8 | K3: M9 | L3: M10 | M3: M11 | N3: M12 | O3: M13 | P3: M14 | Q3: M15 | R3: M16 | S3: M17 | T3: M18 | U3: M19 | V3: M20 | W3: M21 | X3: M22 | Y3: M23 | Z3: M24 | AA3: M25 | AB3: M26 | AC3: M27 | AD3: M28 | AE3: M29 | AF3: M30 | AG3: M31 | AH3: M32 | AI3: M33 | AJ3: M34 | AK3: M35 | AL3: M36 | AM3: M37 | AN3: M38 | AO3: M39 | AP3: M40 | AQ3: M41 | AR3: M42 | AS3: M43 | AT3: M44 | AU3: M45 | AV3: M46 | AW3: M47 | AX3: M48 | AY3: M49 | AZ3: M50 | BA3: M51 | BB3: M52 | BC3: M53 | BD3: M54 | BE3: M55 | BF3: M56 | BG3: M57 | BH3: M58 | BI3: M59 | BJ3: M60
A4: Period # | C4: 1 | D4: 2 | E4: 3 | F4: 4 | G4: 5 | H4: 6 | I4: 7 | J4: 8 | K4: 9 | L4: 10 | M4: 11 | N4: 12 | O4: 13 | P4: 14 | Q4: 15 | R4: 16 | S4: 17 | T4: 18 | U4: 19 | V4: 20 | W4: 21 | X4: 22 | Y4: 23 | Z4: 24 | AA4: 25 | AB4: 26 | AC4: 27 | AD4: 28 | AE4: 29 | AF4: 30 | AG4: 31 | AH4: 32 | AI4: 33 | AJ4: 34 | AK4: 35 | AL4: 36 | AM4: 37 | AN4: 38 | AO4: 39 | AP4: 40 | AQ4: 41 | AR4: 42 | AS4: 43 | AT4: 44 | AU4: 45 | AV4: 46 | AW4: 47 | AX4: 48 | AY4: 49 | AZ4: 50 | BA4: 51 | BB4: 52 | BC4: 53 | BD4: 54 | BE4: 55 | BF4: 56 | BG4: 57 | BH4: 58 | BI4: 59 | BJ4: 60
A5: Year # | C5: =ROUNDUP(C4*1/12,0) -> 1 | D5: =ROUNDUP(D4*1/12,0) -> 1 | E5: =ROUNDUP(E4*1/12,0) -> 1 | F5: =ROUNDUP(F4*1/12,0) -> 1 | G5: =ROUNDUP(G4*1/12,0) -> 1 | H5: =ROUNDUP(H4*1/12,0) -> 1 | I5: =ROUNDUP(I4*1/12,0) -> 1 | J5: =ROUNDUP(J4*1/12,0) -> 1 | ... BJ5: =ROUNDUP(BJ4*1/12,0) -> 5
A7: Retail counter
A8: Traffic ramp factor | C8: =MIN(1,Inputs!$E$9+(1-Inputs!$E$9)*(C$4-1)/MAX(1,Inputs!$E$8)) -> 0.9 | D8: =MIN(1,Inputs!$E$9+(1-Inputs!$E$9)*(D$4-1)/MAX(1,Inputs!$E$8)) -> 0.95 | E8: =MIN(1,Inputs!$E$9+(1-Inputs!$E$9)*(E$4-1)/MAX(1,Inputs!$E$8)) -> 1 | F8: =MIN(1,Inputs!$E$9+(1-Inputs!$E$9)*(F$4-1)/MAX(1,Inputs!$E$8)) -> 1 | G8: =MIN(1,Inputs!$E$9+(1-Inputs!$E$9)*(G$4-1)/MAX(1,Inputs!$E$8)) -> 1 | H8: =MIN(1,Inputs!$E$9+(1-Inputs!$E$9)*(H$4-1)/MAX(1,Inputs!$E$8)) -> 1 | I8: =MIN(1,Inputs!$E$9+(1-Inputs!$E$9)*(I$4-1)/MAX(1,Inputs!$E$8)) -> 1 | J8: =MIN(1,Inputs!$E$9+(1-Inputs!$E$9)*(J$4-1)/MAX(1,Inputs!$E$8)) -> 1 | ... BJ8: =MIN(1,Inputs!$E$9+(1-Inputs!$E$9)*(BJ$4-1)/MAX(1,Inputs!$E$8)) -> 1
A9: Season factor (November-December peak, added to the ramp) | C9: =IF(MOD(C$4-1,12)>=10,1+Inputs!$E$14,1-Inputs!$E$14/5) -> 0.96 | D9: =IF(MOD(D$4-1,12)>=10,1+Inputs!$E$14,1-Inputs!$E$14/5) -> 0.96 | E9: =IF(MOD(E$4-1,12)>=10,1+Inputs!$E$14,1-Inputs!$E$14/5) -> 0.96 | F9: =IF(MOD(F$4-1,12)>=10,1+Inputs!$E$14,1-Inputs!$E$14/5) -> 0.96 | G9: =IF(MOD(G$4-1,12)>=10,1+Inputs!$E$14,1-Inputs!$E$14/5) -> 0.96 | H9: =IF(MOD(H$4-1,12)>=10,1+Inputs!$E$14,1-Inputs!$E$14/5) -> 0.96 | I9: =IF(MOD(I$4-1,12)>=10,1+Inputs!$E$14,1-Inputs!$E$14/5) -> 0.96 | J9: =IF(MOD(J$4-1,12)>=10,1+Inputs!$E$14,1-Inputs!$E$14/5) -> 0.96 | ... BJ9: =IF(MOD(BJ$4-1,12)>=10,1+Inputs!$E$14,1-Inputs!$E$14/5) -> 1.2
A10: Customers per day | C10: =Inputs!$E$7*(1+Inputs!$E$10)^(C$5-1)*MAX(0,C8+C9-1) -> 275.2 | D10: =Inputs!$E$7*(1+Inputs!$E$10)^(D$5-1)*MAX(0,D8+D9-1) -> 291.2 | E10: =Inputs!$E$7*(1+Inputs!$E$10)^(E$5-1)*MAX(0,E8+E9-1) -> 307.2 | F10: =Inputs!$E$7*(1+Inputs!$E$10)^(F$5-1)*MAX(0,F8+F9-1) -> 307.2 | G10: =Inputs!$E$7*(1+Inputs!$E$10)^(G$5-1)*MAX(0,G8+G9-1) -> 307.2 | H10: =Inputs!$E$7*(1+Inputs!$E$10)^(H$5-1)*MAX(0,H8+H9-1) -> 307.2 | I10: =Inputs!$E$7*(1+Inputs!$E$10)^(I$5-1)*MAX(0,I8+I9-1) -> 307.2 | J10: =Inputs!$E$7*(1+Inputs!$E$10)^(J$5-1)*MAX(0,J8+J9-1) -> 307.2 | ... BJ10: =Inputs!$E$7*(1+Inputs!$E$10)^(BJ$5-1)*MAX(0,BJ8+BJ9-1) -> 432.19538
A11: Opening days in period | C11: =Inputs!$E$13*52/12*1 -> 26 | D11: =Inputs!$E$13*52/12*1 -> 26 | E11: =Inputs!$E$13*52/12*1 -> 26 | F11: =Inputs!$E$13*52/12*1 -> 26 | G11: =Inputs!$E$13*52/12*1 -> 26 | H11: =Inputs!$E$13*52/12*1 -> 26 | I11: =Inputs!$E$13*52/12*1 -> 26 | J11: =Inputs!$E$13*52/12*1 -> 26 | ... BJ11: =Inputs!$E$13*52/12*1 -> 26
A12: Retail transactions | C12: =C10*C11 -> 7155.2 | D12: =D10*D11 -> 7571.2 | E12: =E10*E11 -> 7987.2 | F12: =F10*F11 -> 7987.2 | G12: =G10*G11 -> 7987.2 | H12: =H10*H11 -> 7987.2 | I12: =I10*I11 -> 7987.2 | J12: =J10*J11 -> 7987.2 | ... BJ12: =BJ10*BJ11 -> 11237.08
A13: Average ticket | C13: =Inputs!$E$11*(1+Inputs!$E$12)^(C$5-1) -> 11.5 | D13: =Inputs!$E$11*(1+Inputs!$E$12)^(D$5-1) -> 11.5 | E13: =Inputs!$E$11*(1+Inputs!$E$12)^(E$5-1) -> 11.5 | F13: =Inputs!$E$11*(1+Inputs!$E$12)^(F$5-1) -> 11.5 | G13: =Inputs!$E$11*(1+Inputs!$E$12)^(G$5-1) -> 11.5 | H13: =Inputs!$E$11*(1+Inputs!$E$12)^(H$5-1) -> 11.5 | I13: =Inputs!$E$11*(1+Inputs!$E$12)^(I$5-1) -> 11.5 | J13: =Inputs!$E$11*(1+Inputs!$E$12)^(J$5-1) -> 11.5 | ... BJ13: =Inputs!$E$11*(1+Inputs!$E$12)^(BJ$5-1) -> 12.943351
A14: Retail revenue | C14: =C12*C13 -> 82284.8 | D14: =D12*D13 -> 87068.8 | E14: =E12*E13 -> 91852.8 | F14: =F12*F13 -> 91852.8 | G14: =G12*G13 -> 91852.8 | H14: =H12*H13 -> 91852.8 | I14: =I12*I13 -> 91852.8 | J14: =J12*J13 -> 91852.8 | ... BJ14: =BJ12*BJ13 -> 145445.47
A16: Wholesale
A17: Wholesale accounts | C17: =Inputs!$E$17*C8*(1+Inputs!$E$18)^(C$5-1) -> 14.4 | D17: =Inputs!$E$17*D8*(1+Inputs!$E$18)^(D$5-1) -> 15.2 | E17: =Inputs!$E$17*E8*(1+Inputs!$E$18)^(E$5-1) -> 16 | F17: =Inputs!$E$17*F8*(1+Inputs!$E$18)^(F$5-1) -> 16 | G17: =Inputs!$E$17*G8*(1+Inputs!$E$18)^(G$5-1) -> 16 | H17: =Inputs!$E$17*H8*(1+Inputs!$E$18)^(H$5-1) -> 16 | I17: =Inputs!$E$17*I8*(1+Inputs!$E$18)^(I$5-1) -> 16 | J17: =Inputs!$E$17*J8*(1+Inputs!$E$18)^(J$5-1) -> 16 | ... BJ17: =Inputs!$E$17*BJ8*(1+Inputs!$E$18)^(BJ$5-1) -> 25.17631
A18: Order value per account per week | C18: =Inputs!$E$19*(1+Inputs!$E$12)^(C$5-1) -> 540 | D18: =Inputs!$E$19*(1+Inputs!$E$12)^(D$5-1) -> 540 | E18: =Inputs!$E$19*(1+Inputs!$E$12)^(E$5-1) -> 540 | F18: =Inputs!$E$19*(1+Inputs!$E$12)^(F$5-1) -> 540 | G18: =Inputs!$E$19*(1+Inputs!$E$12)^(G$5-1) -> 540 | H18: =Inputs!$E$19*(1+Inputs!$E$12)^(H$5-1) -> 540 | I18: =Inputs!$E$19*(1+Inputs!$E$12)^(I$5-1) -> 540 | J18: =Inputs!$E$19*(1+Inputs!$E$12)^(J$5-1) -> 540 | ... BJ18: =Inputs!$E$19*(1+Inputs!$E$12)^(BJ$5-1) -> 607.77476
A19: Wholesale revenue | C19: =C17*C18*52/12*1 -> 33696 | D19: =D17*D18*52/12*1 -> 35568 | E19: =E17*E18*52/12*1 -> 37440 | F19: =F17*F18*52/12*1 -> 37440 | G19: =G17*G18*52/12*1 -> 37440 | H19: =H17*H18*52/12*1 -> 37440 | I19: =I17*I18*52/12*1 -> 37440 | J19: =J17*J18*52/12*1 -> 37440 | ... BJ19: =BJ17*BJ18*52/12*1 -> 66306.611
A21: Revenue
A22: Revenue | C22: =C14+C19 -> 115980.8 | D22: =D14+D19 -> 122636.8 | E22: =E14+E19 -> 129292.8 | F22: =F14+F19 -> 129292.8 | G22: =G14+G19 -> 129292.8 | H22: =H14+H19 -> 129292.8 | I22: =I14+I19 -> 129292.8 | J22: =J14+J19 -> 129292.8 | ... BJ22: =BJ14+BJ19 -> 211752.08
A24: Cost of sales
A25: Ingredients sold | C25: =-(C14*Inputs!$E$24+C19*Inputs!$E$25) -> -30868.032 | D25: =-(D14*Inputs!$E$24+D19*Inputs!$E$25) -> -32633.952 | E25: =-(E14*Inputs!$E$24+E19*Inputs!$E$25) -> -34399.872 | F25: =-(F14*Inputs!$E$24+F19*Inputs!$E$25) -> -34399.872 | G25: =-(G14*Inputs!$E$24+G19*Inputs!$E$25) -> -34399.872 | H25: =-(H14*Inputs!$E$24+H19*Inputs!$E$25) -> -34399.872 | I25: =-(I14*Inputs!$E$24+I19*Inputs!$E$25) -> -34399.872 | J25: =-(J14*Inputs!$E$24+J19*Inputs!$E$25) -> -34399.872 | ... BJ25: =-(BJ14*Inputs!$E$24+BJ19*Inputs!$E$25) -> -56788.095
A26: Waste (retail production not sold, at ingredient cost) | C26: =-C14*Inputs!$E$24*Inputs!$E$26*100/MAX(1,100-100*Inputs!$E$26) -> -1953.1337 | D26: =-D14*Inputs!$E$24*Inputs!$E$26*100/MAX(1,100-100*Inputs!$E$26) -> -2066.688 | E26: =-E14*Inputs!$E$24*Inputs!$E$26*100/MAX(1,100-100*Inputs!$E$26) -> -2180.2423 | F26: =-F14*Inputs!$E$24*Inputs!$E$26*100/MAX(1,100-100*Inputs!$E$26) -> -2180.2423 | G26: =-G14*Inputs!$E$24*Inputs!$E$26*100/MAX(1,100-100*Inputs!$E$26) -> -2180.2423 | H26: =-H14*Inputs!$E$24*Inputs!$E$26*100/MAX(1,100-100*Inputs!$E$26) -> -2180.2423 | I26: =-I14*Inputs!$E$24*Inputs!$E$26*100/MAX(1,100-100*Inputs!$E$26) -> -2180.2423 | J26: =-J14*Inputs!$E$24*Inputs!$E$26*100/MAX(1,100-100*Inputs!$E$26) -> -2180.2423 | ... BJ26: =-BJ14*Inputs!$E$24*Inputs!$E$26*100/MAX(1,100-100*Inputs!$E$26) -> -3452.3321
A27: Packaging | C27: =-C22*Inputs!$E$27 -> -4059.328 | D27: =-D22*Inputs!$E$27 -> -4292.288 | E27: =-E22*Inputs!$E$27 -> -4525.248 | F27: =-F22*Inputs!$E$27 -> -4525.248 | G27: =-G22*Inputs!$E$27 -> -4525.248 | H27: =-H22*Inputs!$E$27 -> -4525.248 | I27: =-I22*Inputs!$E$27 -> -4525.248 | J27: =-J22*Inputs!$E$27 -> -4525.248 | ... BJ27: =-BJ22*Inputs!$E$27 -> -7411.323
A28: Cost of sales | C28: =C25+C26+C27 -> -36880.494 | D28: =D25+D26+D27 -> -38992.928 | E28: =E25+E26+E27 -> -41105.362 | F28: =F25+F26+F27 -> -41105.362 | G28: =G25+G26+G27 -> -41105.362 | H28: =H25+H26+H27 -> -41105.362 | I28: =I25+I26+I27 -> -41105.362 | J28: =J25+J26+J27 -> -41105.362 | ... BJ28: =BJ25+BJ26+BJ27 -> -67651.75
A29: Gross profit | C29: =C22+C28 -> 79100.306 | D29: =D22+D28 -> 83643.872 | E29: =E22+E28 -> 88187.438 | F29: =F22+F28 -> 88187.438 | G29: =G22+G28 -> 88187.438 | H29: =H22+H28 -> 88187.438 | I29: =I22+I28 -> 88187.438 | J29: =J22+J28 -> 88187.438 | ... BJ29: =BJ22+BJ28 -> 144100.33
A31: Operating expenses
A32: Payroll (bakers, counter, manager) | C32: =Headcount!C17 -> -49466.667 | D32: =Headcount!D17 -> -49466.667 | E32: =Headcount!E17 -> -49466.667 | F32: =Headcount!F17 -> -49466.667 | G32: =Headcount!G17 -> -49466.667 | H32: =Headcount!H17 -> -49466.667 | I32: =Headcount!I17 -> -49466.667 | J32: =Headcount!J17 -> -49466.667 | ... BJ32: =Headcount!BJ17 -> -67724.372
A33: Rent | C33: =-Inputs!$E$30*1 -> -12000 | D33: =-Inputs!$E$30*1 -> -12000 | E33: =-Inputs!$E$30*1 -> -12000 | F33: =-Inputs!$E$30*1 -> -12000 | G33: =-Inputs!$E$30*1 -> -12000 | H33: =-Inputs!$E$30*1 -> -12000 | I33: =-Inputs!$E$30*1 -> -12000 | J33: =-Inputs!$E$30*1 -> -12000 | ... BJ33: =-Inputs!$E$30*1 -> -12000
A34: Utilities (ovens) | C34: =-Inputs!$E$31*1 -> -4000 | D34: =-Inputs!$E$31*1 -> -4000 | E34: =-Inputs!$E$31*1 -> -4000 | F34: =-Inputs!$E$31*1 -> -4000 | G34: =-Inputs!$E$31*1 -> -4000 | H34: =-Inputs!$E$31*1 -> -4000 | I34: =-Inputs!$E$31*1 -> -4000 | J34: =-Inputs!$E$31*1 -> -4000 | ... BJ34: =-Inputs!$E$31*1 -> -4000
A35: Wholesale delivery | C35: =-C17*Inputs!$E$20*52/12*1*Inputs!$E$21 -> -2808 | D35: =-D17*Inputs!$E$20*52/12*1*Inputs!$E$21 -> -2964 | E35: =-E17*Inputs!$E$20*52/12*1*Inputs!$E$21 -> -3120 | F35: =-F17*Inputs!$E$20*52/12*1*Inputs!$E$21 -> -3120 | G35: =-G17*Inputs!$E$20*52/12*1*Inputs!$E$21 -> -3120 | H35: =-H17*Inputs!$E$20*52/12*1*Inputs!$E$21 -> -3120 | I35: =-I17*Inputs!$E$20*52/12*1*Inputs!$E$21 -> -3120 | J35: =-J17*Inputs!$E$20*52/12*1*Inputs!$E$21 -> -3120 | ... BJ35: =-BJ17*Inputs!$E$20*52/12*1*Inputs!$E$21 -> -4909.3804
A36: Equipment repairs & cleaning | C36: =-Inputs!$E$32*1 -> -1000 | D36: =-Inputs!$E$32*1 -> -1000 | E36: =-Inputs!$E$32*1 -> -1000 | F36: =-Inputs!$E$32*1 -> -1000 | G36: =-Inputs!$E$32*1 -> -1000 | H36: =-Inputs!$E$32*1 -> -1000 | I36: =-Inputs!$E$32*1 -> -1000 | J36: =-Inputs!$E$32*1 -> -1000 | ... BJ36: =-Inputs!$E$32*1 -> -1000
A37: Marketing | C37: =-C22*Inputs!$E$33 -> -2319.616 | D37: =-D22*Inputs!$E$33 -> -2452.736 | E37: =-E22*Inputs!$E$33 -> -2585.856 | F37: =-F22*Inputs!$E$33 -> -2585.856 | G37: =-G22*Inputs!$E$33 -> -2585.856 | H37: =-H22*Inputs!$E$33 -> -2585.856 | I37: =-I22*Inputs!$E$33 -> -2585.856 | J37: =-J22*Inputs!$E$33 -> -2585.856 | ... BJ37: =-BJ22*Inputs!$E$33 -> -4235.0417
A38: Card processing fees | C38: =-C14*Inputs!$E$34 -> -2303.9744 | D38: =-D14*Inputs!$E$34 -> -2437.9264 | E38: =-E14*Inputs!$E$34 -> -2571.8784 | F38: =-F14*Inputs!$E$34 -> -2571.8784 | G38: =-G14*Inputs!$E$34 -> -2571.8784 | H38: =-H14*Inputs!$E$34 -> -2571.8784 | I38: =-I14*Inputs!$E$34 -> -2571.8784 | J38: =-J14*Inputs!$E$34 -> -2571.8784 | ... BJ38: =-BJ14*Inputs!$E$34 -> -4072.4733
A39: Insurance, licences & other G&A | C39: =-Inputs!$E$35*1 -> -2800 | D39: =-Inputs!$E$35*1 -> -2800 | E39: =-Inputs!$E$35*1 -> -2800 | F39: =-Inputs!$E$35*1 -> -2800 | G39: =-Inputs!$E$35*1 -> -2800 | H39: =-Inputs!$E$35*1 -> -2800 | I39: =-Inputs!$E$35*1 -> -2800 | J39: =-Inputs!$E$35*1 -> -2800 | ... BJ39: =-Inputs!$E$35*1 -> -2800
A40: Total operating expenses | C40: =C32+C33+C34+C35+C36+C37+C38+C39 -> -76698.257 | D40: =D32+D33+D34+D35+D36+D37+D38+D39 -> -77121.329 | E40: =E32+E33+E34+E35+E36+E37+E38+E39 -> -77544.401 | F40: =F32+F33+F34+F35+F36+F37+F38+F39 -> -77544.401 | G40: =G32+G33+G34+G35+G36+G37+G38+G39 -> -77544.401 | H40: =H32+H33+H34+H35+H36+H37+H38+H39 -> -77544.401 | I40: =I32+I33+I34+I35+I36+I37+I38+I39 -> -77544.401 | J40: =J32+J33+J34+J35+J36+J37+J38+J39 -> -77544.401 | ... BJ40: =BJ32+BJ33+BJ34+BJ35+BJ36+BJ37+BJ38+BJ39 -> -100741.27
A41: EBITDA | C41: =C29+C40 -> 2402.0492 | D41: =D29+D40 -> 6522.5429 | E41: =E29+E40 -> 10643.037 | F41: =F29+F40 -> 10643.037 | G41: =G29+G40 -> 10643.037 | H41: =H29+H40 -> 10643.037 | I41: =I29+I40 -> 10643.037 | J41: =J29+J40 -> 10643.037 | ... BJ41: =BJ29+BJ40 -> 43359.067
A43: Profit after depreciation, interest, tax
A44: EBIT | C44: =C41+C55 -> 1330.6206 | D44: =D41+D55 -> 5451.1144 | E44: =E41+E55 -> 9571.6081 | F44: =F41+F55 -> 9571.6081 | G44: =G41+G55 -> 9571.6081 | H44: =H41+H55 -> 9571.6081 | I44: =I41+I55 -> 9571.6081 | J44: =J41+J55 -> 9571.6081 | ... BJ44: =BJ41+BJ55 -> 41620.972
A45: Interest on loan (average balance after drawdown) | C45: =-(C60+C61+C63)/2*Inputs!$E$60/12 -> -566.66667 | D45: =-(D60+D61+D63)/2*Inputs!$E$60/12 -> -561.94444 | E45: =-(E60+E61+E63)/2*Inputs!$E$60/12 -> -552.5 | F45: =-(F60+F61+F63)/2*Inputs!$E$60/12 -> -543.05556 | G45: =-(G60+G61+G63)/2*Inputs!$E$60/12 -> -533.61111 | H45: =-(H60+H61+H63)/2*Inputs!$E$60/12 -> -524.16667 | I45: =-(I60+I61+I63)/2*Inputs!$E$60/12 -> -514.72222 | J45: =-(J60+J61+J63)/2*Inputs!$E$60/12 -> -505.27778 | ... BJ45: =-(BJ60+BJ61+BJ63)/2*Inputs!$E$60/12 -> -14.166667
A46: Pre-tax income | C46: =C44+C45 -> 763.95398 | D46: =D44+D45 -> 4889.1699 | E46: =E44+E45 -> 9019.1081 | F46: =F44+F45 -> 9028.5525 | G46: =G44+G45 -> 9037.997 | H46: =H44+H45 -> 9047.4414 | I46: =I44+I45 -> 9056.8859 | J46: =J44+J45 -> 9066.3303 | ... BJ46: =BJ44+BJ45 -> 41606.805
A47: Helper: cumulative pre-tax income | C47: =C46 -> 763.95398 | D47: =C47+D46 -> 5653.1239 | E47: =D47+E46 -> 14672.232 | F47: =E47+F46 -> 23700.784 | G47: =F47+G46 -> 32738.781 | H47: =G47+H46 -> 41786.223 | I47: =H47+I46 -> 50843.109 | J47: =I47+J46 -> 59909.439 | K47: =J47+K46 -> 68985.214 | ... BJ47: =BI47+BJ46 -> 1082933.4
A48: Helper: cumulative taxable income (losses carried forward) | C48: =MAX(0,C47) -> 763.95398 | D48: =MAX(C48,D47) -> 5653.1239 | E48: =MAX(D48,E47) -> 14672.232 | F48: =MAX(E48,F47) -> 23700.784 | G48: =MAX(F48,G47) -> 32738.781 | H48: =MAX(G48,H47) -> 41786.223 | I48: =MAX(H48,I47) -> 50843.109 | J48: =MAX(I48,J47) -> 59909.439 | K48: =MAX(J48,K47) -> 68985.214 | ... BJ48: =MAX(BI48,BJ47) -> 1082933.4
A49: Income tax | C49: =-C48*Inputs!$E$70 -> -160.43034 | D49: =-(D48-C48)*Inputs!$E$70 -> -1026.7257 | E49: =-(E48-D48)*Inputs!$E$70 -> -1894.0127 | F49: =-(F48-E48)*Inputs!$E$70 -> -1895.996 | G49: =-(G48-F48)*Inputs!$E$70 -> -1897.9794 | H49: =-(H48-G48)*Inputs!$E$70 -> -1899.9627 | I49: =-(I48-H48)*Inputs!$E$70 -> -1901.946 | J49: =-(J48-I48)*Inputs!$E$70 -> -1903.9294 | K49: =-(K48-J48)*Inputs!$E$70 -> -1905.9127 | ... BJ49: =-(BJ48-BI48)*Inputs!$E$70 -> -8737.4291
A50: Net income | C50: =C46+C49 -> 603.52364 | D50: =D46+D49 -> 3862.4442 | E50: =E46+E49 -> 7125.0954 | F50: =F46+F49 -> 7132.5565 | G50: =G46+G49 -> 7140.0176 | H50: =H46+H49 -> 7147.4787 | I50: =I46+I49 -> 7154.9398 | J50: =J46+J49 -> 7162.4009 | ... BJ50: =BJ46+BJ49 -> 32869.376
A52: Fixed assets & capital spending
A53: Capital spending (fit-out, ovens, mixers, display cases) | C53: =IF(C$4=1,Inputs!$E$38,0)+IF(C$5>1,Inputs!$E$39*1/12,0) -> 90000 | D53: =IF(D$4=1,Inputs!$E$38,0)+IF(D$5>1,Inputs!$E$39*1/12,0) -> 0 | E53: =IF(E$4=1,Inputs!$E$38,0)+IF(E$5>1,Inputs!$E$39*1/12,0) -> 0 | F53: =IF(F$4=1,Inputs!$E$38,0)+IF(F$5>1,Inputs!$E$39*1/12,0) -> 0 | G53: =IF(G$4=1,Inputs!$E$38,0)+IF(G$5>1,Inputs!$E$39*1/12,0) -> 0 | H53: =IF(H$4=1,Inputs!$E$38,0)+IF(H$5>1,Inputs!$E$39*1/12,0) -> 0 | I53: =IF(I$4=1,Inputs!$E$38,0)+IF(I$5>1,Inputs!$E$39*1/12,0) -> 0 | J53: =IF(J$4=1,Inputs!$E$38,0)+IF(J$5>1,Inputs!$E$39*1/12,0) -> 0 | ... BJ53: =IF(BJ$4=1,Inputs!$E$38,0)+IF(BJ$5>1,Inputs!$E$39*1/12,0) -> 1166.6667
A54: Fixed assets at cost | C54: =C53 -> 90000 | D54: =C54+D53 -> 90000 | E54: =D54+E53 -> 90000 | F54: =E54+F53 -> 90000 | G54: =F54+G53 -> 90000 | H54: =G54+H53 -> 90000 | I54: =H54+I53 -> 90000 | J54: =I54+J53 -> 90000 | K54: =J54+K53 -> 90000 | ... BJ54: =BI54+BJ53 -> 146000
A55: Depreciation | C55: =-MIN(C54/MAX(1,Inputs!$E$69*12),C53) -> -1071.4286 | D55: =-MIN(D54/MAX(1,Inputs!$E$69*12),C57+D53) -> -1071.4286 | E55: =-MIN(E54/MAX(1,Inputs!$E$69*12),D57+E53) -> -1071.4286 | F55: =-MIN(F54/MAX(1,Inputs!$E$69*12),E57+F53) -> -1071.4286 | G55: =-MIN(G54/MAX(1,Inputs!$E$69*12),F57+G53) -> -1071.4286 | H55: =-MIN(H54/MAX(1,Inputs!$E$69*12),G57+H53) -> -1071.4286 | I55: =-MIN(I54/MAX(1,Inputs!$E$69*12),H57+I53) -> -1071.4286 | J55: =-MIN(J54/MAX(1,Inputs!$E$69*12),I57+J53) -> -1071.4286 | K55: =-MIN(K54/MAX(1,Inputs!$E$69*12),J57+K53) -> -1071.4286 | ... BJ55: =-MIN(BJ54/MAX(1,Inputs!$E$69*12),BI57+BJ53) -> -1738.0952
A56: Accumulated depreciation | C56: =C55 -> -1071.4286 | D56: =C56+D55 -> -2142.8571 | E56: =D56+E55 -> -3214.2857 | F56: =E56+F55 -> -4285.7143 | G56: =F56+G55 -> -5357.1429 | H56: =G56+H55 -> -6428.5714 | I56: =H56+I55 -> -7500 | J56: =I56+J55 -> -8571.4286 | K56: =J56+K55 -> -9642.8571 | ... BJ56: =BI56+BJ55 -> -80619.048
A57: Net fixed assets | C57: =C54+C56 -> 88928.571 | D57: =D54+D56 -> 87857.143 | E57: =E54+E56 -> 86785.714 | F57: =F54+F56 -> 85714.286 | G57: =G54+G56 -> 84642.857 | H57: =H54+H56 -> 83571.429 | I57: =I54+I56 -> 82500 | J57: =J54+J56 -> 81428.571 | ... BJ57: =BJ54+BJ56 -> 65380.952
A59: Debt
A60: Loan — opening balance | C60: =0 -> 0 | D60: =C63 -> 80000 | E60: =D63 -> 78666.667 | F60: =E63 -> 77333.333 | G60: =F63 -> 76000 | H60: =G63 -> 74666.667 | I60: =H63 -> 73333.333 | J60: =I63 -> 72000 | K60: =J63 -> 70666.667 | ... BJ60: =BI63 -> 2666.6667
A61: Loan drawdown | C61: =IF(C$4=1,Inputs!$E$59,0) -> 80000 | D61: =IF(D$4=1,Inputs!$E$59,0) -> 0 | E61: =IF(E$4=1,Inputs!$E$59,0) -> 0 | F61: =IF(F$4=1,Inputs!$E$59,0) -> 0 | G61: =IF(G$4=1,Inputs!$E$59,0) -> 0 | H61: =IF(H$4=1,Inputs!$E$59,0) -> 0 | I61: =IF(I$4=1,Inputs!$E$59,0) -> 0 | J61: =IF(J$4=1,Inputs!$E$59,0) -> 0 | ... BJ61: =IF(BJ$4=1,Inputs!$E$59,0) -> 0
A62: Loan repayment | C62: =-MIN(C60,Inputs!$E$59/MAX(1,Inputs!$E$61*12)) -> 0 | D62: =-MIN(D60,Inputs!$E$59/MAX(1,Inputs!$E$61*12)) -> -1333.3333 | E62: =-MIN(E60,Inputs!$E$59/MAX(1,Inputs!$E$61*12)) -> -1333.3333 | F62: =-MIN(F60,Inputs!$E$59/MAX(1,Inputs!$E$61*12)) -> -1333.3333 | G62: =-MIN(G60,Inputs!$E$59/MAX(1,Inputs!$E$61*12)) -> -1333.3333 | H62: =-MIN(H60,Inputs!$E$59/MAX(1,Inputs!$E$61*12)) -> -1333.3333 | I62: =-MIN(I60,Inputs!$E$59/MAX(1,Inputs!$E$61*12)) -> -1333.3333 | J62: =-MIN(J60,Inputs!$E$59/MAX(1,Inputs!$E$61*12)) -> -1333.3333 | ... BJ62: =-MIN(BJ60,Inputs!$E$59/MAX(1,Inputs!$E$61*12)) -> -1333.3333
A63: Loan — closing balance | C63: =C60+C61+C62 -> 80000 | D63: =D60+D61+D62 -> 78666.667 | E63: =E60+E61+E62 -> 77333.333 | F63: =F60+F61+F62 -> 76000 | G63: =G60+G61+G62 -> 74666.667 | H63: =H60+H61+H62 -> 73333.333 | I63: =I60+I61+I62 -> 72000 | J63: =J60+J61+J62 -> 70666.667 | ... BJ63: =BJ60+BJ61+BJ62 -> 1333.3333
A65: Working capital
A66: Accounts receivable | C66: =C22*Inputs!$E$64/30 -> 34794.24 | D66: =D22*Inputs!$E$64/30 -> 36791.04 | E66: =E22*Inputs!$E$64/30 -> 38787.84 | F66: =F22*Inputs!$E$64/30 -> 38787.84 | G66: =G22*Inputs!$E$64/30 -> 38787.84 | H66: =H22*Inputs!$E$64/30 -> 38787.84 | I66: =I22*Inputs!$E$64/30 -> 38787.84 | J66: =J22*Inputs!$E$64/30 -> 38787.84 | ... BJ66: =BJ22*Inputs!$E$64/30 -> 63525.625
A67: Inventory | C67: =-C28*Inputs!$E$65/30 -> 3688.0494 | D67: =-D28*Inputs!$E$65/30 -> 3899.2928 | E67: =-E28*Inputs!$E$65/30 -> 4110.5362 | F67: =-F28*Inputs!$E$65/30 -> 4110.5362 | G67: =-G28*Inputs!$E$65/30 -> 4110.5362 | H67: =-H28*Inputs!$E$65/30 -> 4110.5362 | I67: =-I28*Inputs!$E$65/30 -> 4110.5362 | J67: =-J28*Inputs!$E$65/30 -> 4110.5362 | ... BJ67: =-BJ28*Inputs!$E$65/30 -> 6765.175
A68: Accounts payable | C68: =-C28*Inputs!$E$66/30 -> 22128.296 | D68: =-D28*Inputs!$E$66/30 -> 23395.757 | E68: =-E28*Inputs!$E$66/30 -> 24663.217 | F68: =-F28*Inputs!$E$66/30 -> 24663.217 | G68: =-G28*Inputs!$E$66/30 -> 24663.217 | H68: =-H28*Inputs!$E$66/30 -> 24663.217 | I68: =-I28*Inputs!$E$66/30 -> 24663.217 | J68: =-J28*Inputs!$E$66/30 -> 24663.217 | ... BJ68: =-BJ28*Inputs!$E$66/30 -> 40591.05
A69: (Increase) / decrease in receivables | C69: =-C66 -> -34794.24 | D69: =C66-D66 -> -1996.8 | E69: =D66-E66 -> -1996.8 | F69: =E66-F66 -> 0 | G69: =F66-G66 -> 0 | H69: =G66-H66 -> 0 | I69: =H66-I66 -> 0 | J69: =I66-J66 -> 0 | K69: =J66-K66 -> 0 | ... BJ69: =BI66-BJ66 -> 0
A70: (Increase) / decrease in inventory | C70: =-C67 -> -3688.0494 | D70: =C67-D67 -> -211.24343 | E70: =D67-E67 -> -211.24343 | F70: =E67-F67 -> 0 | G70: =F67-G67 -> 0 | H70: =G67-H67 -> 0 | I70: =H67-I67 -> 0 | J70: =I67-J67 -> 0 | K70: =J67-K67 -> 0 | ... BJ70: =BI67-BJ67 -> 0
A71: Increase / (decrease) in payables | C71: =C68 -> 22128.296 | D71: =D68-C68 -> 1267.4606 | E71: =E68-D68 -> 1267.4606 | F71: =F68-E68 -> 0 | G71: =G68-F68 -> 0 | H71: =H68-G68 -> 0 | I71: =I68-H68 -> 0 | J71: =J68-I68 -> 0 | K71: =K68-J68 -> 0 | ... BJ71: =BJ68-BI68 -> 0
A73: Cash flow
A74: Operating cash flow | C74: =C50-C55+C69+C70+C71 -> -14679.041 | D74: =D50-D55+D69+D70+D71 -> 3993.2899 | E74: =E50-E55+E69+E70+E71 -> 7255.9411 | F74: =F50-F55+F69+F70+F71 -> 8203.9851 | G74: =G50-G55+G69+G70+G71 -> 8211.4462 | H74: =H50-H55+H69+H70+H71 -> 8218.9073 | I74: =I50-I55+I69+I70+I71 -> 8226.3684 | J74: =J50-J55+J69+J70+J71 -> 8233.8295 | ... BJ74: =BJ50-BJ55+BJ69+BJ70+BJ71 -> 34607.471
A75: Investing cash flow (capex) | C75: =-C53 -> -90000 | D75: =-D53 -> 0 | E75: =-E53 -> 0 | F75: =-F53 -> 0 | G75: =-G53 -> 0 | H75: =-H53 -> 0 | I75: =-I53 -> 0 | J75: =-J53 -> 0 | ... BJ75: =-BJ53 -> -1166.6667
A76: Equity raised | C76: =IF(C$4=1,Inputs!$E$58,0) -> 60000 | D76: =IF(D$4=1,Inputs!$E$58,0) -> 0 | E76: =IF(E$4=1,Inputs!$E$58,0) -> 0 | F76: =IF(F$4=1,Inputs!$E$58,0) -> 0 | G76: =IF(G$4=1,Inputs!$E$58,0) -> 0 | H76: =IF(H$4=1,Inputs!$E$58,0) -> 0 | I76: =IF(I$4=1,Inputs!$E$58,0) -> 0 | J76: =IF(J$4=1,Inputs!$E$58,0) -> 0 | ... BJ76: =IF(BJ$4=1,Inputs!$E$58,0) -> 0
A77: Financing cash flow | C77: =C76+C61+C62 -> 140000 | D77: =D76+D61+D62 -> -1333.3333 | E77: =E76+E61+E62 -> -1333.3333 | F77: =F76+F61+F62 -> -1333.3333 | G77: =G76+G61+G62 -> -1333.3333 | H77: =H76+H61+H62 -> -1333.3333 | I77: =I76+I61+I62 -> -1333.3333 | J77: =J76+J61+J62 -> -1333.3333 | ... BJ77: =BJ76+BJ61+BJ62 -> -1333.3333
A78: Net cash flow | C78: =C74+C75+C77 -> 35320.959 | D78: =D74+D75+D77 -> 2659.9566 | E78: =E74+E75+E77 -> 5922.6078 | F78: =F74+F75+F77 -> 6870.6517 | G78: =G74+G75+G77 -> 6878.1128 | H78: =H74+H75+H77 -> 6885.574 | I78: =I74+I75+I77 -> 6893.0351 | J78: =J74+J75+J77 -> 6900.4962 | ... BJ78: =BJ74+BJ75+BJ77 -> 32107.471
A79: Opening cash | C79: =0 -> 0 | D79: =C80 -> 35320.959 | E79: =D80 -> 37980.916 | F79: =E80 -> 43903.523 | G79: =F80 -> 50774.175 | H79: =G80 -> 57652.288 | I79: =H80 -> 64537.862 | J79: =I80 -> 71430.897 | K79: =J80 -> 78331.393 | ... BJ79: =BI80 -> 789662.58
A80: Closing cash | C80: =C79+C78 -> 35320.959 | D80: =D79+D78 -> 37980.916 | E80: =E79+E78 -> 43903.523 | F80: =F79+F78 -> 50774.175 | G80: =G79+G78 -> 57652.288 | H80: =H79+H78 -> 64537.862 | I80: =I79+I78 -> 71430.897 | J80: =J79+J78 -> 78331.393 | ... BJ80: =BJ79+BJ78 -> 821770.05
A81: Helper: EBITDA positive (1/0) | C81: =IF(C41>0,1,0) -> 1 | D81: =IF(D41>0,1,0) -> 1 | E81: =IF(E41>0,1,0) -> 1 | F81: =IF(F41>0,1,0) -> 1 | G81: =IF(G41>0,1,0) -> 1 | H81: =IF(H41>0,1,0) -> 1 | I81: =IF(I41>0,1,0) -> 1 | J81: =IF(J41>0,1,0) -> 1 | ... BJ81: =IF(BJ41>0,1,0) -> 1
A83: Goal modules
A84: Helper: net income positive (1/0) | C84: =IF(C50>0,1,0) -> 1 | D84: =IF(D50>0,1,0) -> 1 | E84: =IF(E50>0,1,0) -> 1 | F84: =IF(F50>0,1,0) -> 1 | G84: =IF(G50>0,1,0) -> 1 | H84: =IF(H50>0,1,0) -> 1 | I84: =IF(I50>0,1,0) -> 1 | J84: =IF(J50>0,1,0) -> 1 | ... BJ84: =IF(BJ50>0,1,0) -> 1
A85: Cash flow before financing (operating + investing) | C85: =C74+C75 -> -104679.04 | D85: =D74+D75 -> 3993.2899 | E85: =E74+E75 -> 7255.9411 | F85: =F74+F75 -> 8203.9851 | G85: =G74+G75 -> 8211.4462 | H85: =H74+H75 -> 8218.9073 | I85: =I74+I75 -> 8226.3684 | J85: =J74+J75 -> 8233.8295 | ... BJ85: =BJ74+BJ75 -> 33440.805
A86: Cumulative cash flow before financing | C86: =C85 -> -104679.04 | D86: =C86+D85 -> -100685.75 | E86: =D86+E85 -> -93429.81 | F86: =E86+F85 -> -85225.825 | G86: =F86+G85 -> -77014.379 | H86: =G86+H85 -> -68795.471 | I86: =H86+I85 -> -60569.103 | J86: =I86+J85 -> -52335.273 | K86: =J86+K85 -> -44093.983 | ... BJ86: =BI86+BJ85 -> 760436.71
A87: Helper: lowest cumulative cash flow so far | C87: =C86 -> -104679.04 | D87: =MIN(C87,D86) -> -104679.04 | E87: =MIN(D87,E86) -> -104679.04 | F87: =MIN(E87,F86) -> -104679.04 | G87: =MIN(F87,G86) -> -104679.04 | H87: =MIN(G87,H86) -> -104679.04 | I87: =MIN(H87,I86) -> -104679.04 | J87: =MIN(I87,J86) -> -104679.04 | K87: =MIN(J87,K86) -> -104679.04 | ... BJ87: =MIN(BI87,BJ86) -> -104679.04
A88: Helper: investment paid back (1/0) | C88: =IF(AND(C86>=0,C87<0),1,0) -> 0 | D88: =IF(AND(D86>=0,D87<0),1,0) -> 0 | E88: =IF(AND(E86>=0,E87<0),1,0) -> 0 | F88: =IF(AND(F86>=0,F87<0),1,0) -> 0 | G88: =IF(AND(G86>=0,G87<0),1,0) -> 0 | H88: =IF(AND(H86>=0,H87<0),1,0) -> 0 | I88: =IF(AND(I86>=0,I87<0),1,0) -> 0 | J88: =IF(AND(J86>=0,J87<0),1,0) -> 0 | ... BJ88: =IF(AND(BJ86>=0,BJ87<0),1,0) -> 1
A89: Unlevered free cash flow (operating + after-tax interest − capex) | C89: =C74-C45*(1-Inputs!$E$70)+C75 -> -104231.37 | D89: =D74-D45*(1-Inputs!$E$70)+D75 -> 4437.2261 | E89: =E74-E45*(1-Inputs!$E$70)+E75 -> 7692.4161 | F89: =F74-F45*(1-Inputs!$E$70)+F75 -> 8632.999 | G89: =G74-G45*(1-Inputs!$E$70)+G75 -> 8632.999 | H89: =H74-H45*(1-Inputs!$E$70)+H75 -> 8632.999 | I89: =I74-I45*(1-Inputs!$E$70)+I75 -> 8632.999 | J89: =J74-J45*(1-Inputs!$E$70)+J75 -> 8632.999 | ... BJ89: =BJ74-BJ45*(1-Inputs!$E$70)+BJ75 -> 33451.996
A91: Balance sheet
A92: Paid-in capital | C92: =C76 -> 60000 | D92: =C92+D76 -> 60000 | E92: =D92+E76 -> 60000 | F92: =E92+F76 -> 60000 | G92: =F92+G76 -> 60000 | H92: =G92+H76 -> 60000 | I92: =H92+I76 -> 60000 | J92: =I92+J76 -> 60000 | K92: =J92+K76 -> 60000 | ... BJ92: =BI92+BJ76 -> 60000
A93: Retained earnings | C93: =C50 -> 603.52364 | D93: =C93+D50 -> 4465.9679 | E93: =D93+E50 -> 11591.063 | F93: =E93+F50 -> 18723.62 | G93: =F93+G50 -> 25863.637 | H93: =G93+H50 -> 33011.116 | I93: =H93+I50 -> 40166.056 | J93: =I93+J50 -> 47328.457 | K93: =J93+K50 -> 54498.319 | ... BJ93: =BI93+BJ50 -> 855517.42
A94: Total assets | C94: =C80+C66+C67+C57 -> 162731.82 | D94: =D80+D66+D67+D57 -> 166528.39 | E94: =E80+E66+E67+E57 -> 173587.61 | F94: =F80+F66+F67+F57 -> 179386.84 | G94: =G80+G66+G67+G57 -> 185193.52 | H94: =H80+H66+H67+H57 -> 191007.67 | I94: =I80+I66+I67+I57 -> 196829.27 | J94: =J80+J66+J67+J57 -> 202658.34 | ... BJ94: =BJ80+BJ66+BJ67+BJ57 -> 957441.8
A95: Total liabilities | C95: =C68+C63 -> 102128.3 | D95: =D68+D63 -> 102062.42 | E95: =E68+E63 -> 101996.55 | F95: =F68+F63 -> 100663.22 | G95: =G68+G63 -> 99329.884 | H95: =H68+H63 -> 97996.551 | I95: =I68+I63 -> 96663.217 | J95: =J68+J63 -> 95329.884 | ... BJ95: =BJ68+BJ63 -> 41924.384
A96: Total equity | C96: =C92+C93 -> 60603.524 | D96: =D92+D93 -> 64465.968 | E96: =E92+E93 -> 71591.063 | F96: =F92+F93 -> 78723.62 | G96: =G92+G93 -> 85863.637 | H96: =H92+H93 -> 93011.116 | I96: =I92+I93 -> 100166.06 | J96: =J92+J93 -> 107328.46 | ... BJ96: =BJ92+BJ93 -> 915517.42
A97: Total liabilities & equity | C97: =C95+C96 -> 162731.82 | D97: =D95+D96 -> 166528.39 | E97: =E95+E96 -> 173587.61 | F97: =F95+F96 -> 179386.84 | G97: =G95+G96 -> 185193.52 | H97: =H95+H96 -> 191007.67 | I97: =I95+I96 -> 196829.27 | J97: =J95+J96 -> 202658.34 | ... BJ97: =BJ95+BJ96 -> 957441.8
A98: Check: assets − liabilities − equity | C98: =C94-C97 -> 0 | D98: =D94-D97 -> 0 | E98: =E94-E97 -> 0 | F98: =F94-F97 -> 0 | G98: =G94-G97 -> 0 | H98: =H94-H97 -> 0 | I98: =I94-I97 -> 0 | J98: =J94-J97 -> 0 | ... BJ98: =BJ94-BJ97 -> 0

Sheet Headcount
A1: Headcount & payroll | D1: =HYPERLINK("#'Cover'!A1","◂ Contents") -> ◂ Contents
A2: $ unless stated; costs shown as negatives. Every period uses the same formula.
A3: Month | C3: M1 | D3: M2 | E3: M3 | F3: M4 | G3: M5 | H3: M6 | I3: M7 | J3: M8 | K3: M9 | L3: M10 | M3: M11 | N3: M12 | O3: M13 | P3: M14 | Q3: M15 | R3: M16 | S3: M17 | T3: M18 | U3: M19 | V3: M20 | W3: M21 | X3: M22 | Y3: M23 | Z3: M24 | AA3: M25 | AB3: M26 | AC3: M27 | AD3: M28 | AE3: M29 | AF3: M30 | AG3: M31 | AH3: M32 | AI3: M33 | AJ3: M34 | AK3: M35 | AL3: M36 | AM3: M37 | AN3: M38 | AO3: M39 | AP3: M40 | AQ3: M41 | AR3: M42 | AS3: M43 | AT3: M44 | AU3: M45 | AV3: M46 | AW3: M47 | AX3: M48 | AY3: M49 | AZ3: M50 | BA3: M51 | BB3: M52 | BC3: M53 | BD3: M54 | BE3: M55 | BF3: M56 | BG3: M57 | BH3: M58 | BI3: M59 | BJ3: M60
A4: Period # | C4: 1 | D4: 2 | E4: 3 | F4: 4 | G4: 5 | H4: 6 | I4: 7 | J4: 8 | K4: 9 | L4: 10 | M4: 11 | N4: 12 | O4: 13 | P4: 14 | Q4: 15 | R4: 16 | S4: 17 | T4: 18 | U4: 19 | V4: 20 | W4: 21 | X4: 22 | Y4: 23 | Z4: 24 | AA4: 25 | AB4: 26 | AC4: 27 | AD4: 28 | AE4: 29 | AF4: 30 | AG4: 31 | AH4: 32 | AI4: 33 | AJ4: 34 | AK4: 35 | AL4: 36 | AM4: 37 | AN4: 38 | AO4: 39 | AP4: 40 | AQ4: 41 | AR4: 42 | AS4: 43 | AT4: 44 | AU4: 45 | AV4: 46 | AW4: 47 | AX4: 48 | AY4: 49 | AZ4: 50 | BA4: 51 | BB4: 52 | BC4: 53 | BD4: 54 | BE4: 55 | BF4: 56 | BG4: 57 | BH4: 58 | BI4: 59 | BJ4: 60
A5: Year # | C5: =ROUNDUP(C4*1/12,0) -> 1 | D5: =ROUNDUP(D4*1/12,0) -> 1 | E5: =ROUNDUP(E4*1/12,0) -> 1 | F5: =ROUNDUP(F4*1/12,0) -> 1 | G5: =ROUNDUP(G4*1/12,0) -> 1 | H5: =ROUNDUP(H4*1/12,0) -> 1 | I5: =ROUNDUP(I4*1/12,0) -> 1 | J5: =ROUNDUP(J4*1/12,0) -> 1 | ... BJ5: =ROUNDUP(BJ4*1/12,0) -> 5
A7: Headcount (FTE)
A8: Bakers & production — FTE | C8: =Inputs!$E$42*(1+Inputs!$E$44)^(C$5-1)*MAX(0,MIN(1,C$4*1-Inputs!$E$45+1))/1 -> 5 | D8: =Inputs!$E$42*(1+Inputs!$E$44)^(D$5-1)*MAX(0,MIN(1,D$4*1-Inputs!$E$45+1))/1 -> 5 | E8: =Inputs!$E$42*(1+Inputs!$E$44)^(E$5-1)*MAX(0,MIN(1,E$4*1-Inputs!$E$45+1))/1 -> 5 | F8: =Inputs!$E$42*(1+Inputs!$E$44)^(F$5-1)*MAX(0,MIN(1,F$4*1-Inputs!$E$45+1))/1 -> 5 | G8: =Inputs!$E$42*(1+Inputs!$E$44)^(G$5-1)*MAX(0,MIN(1,G$4*1-Inputs!$E$45+1))/1 -> 5 | H8: =Inputs!$E$42*(1+Inputs!$E$44)^(H$5-1)*MAX(0,MIN(1,H$4*1-Inputs!$E$45+1))/1 -> 5 | I8: =Inputs!$E$42*(1+Inputs!$E$44)^(I$5-1)*MAX(0,MIN(1,I$4*1-Inputs!$E$45+1))/1 -> 5 | J8: =Inputs!$E$42*(1+Inputs!$E$44)^(J$5-1)*MAX(0,MIN(1,J$4*1-Inputs!$E$45+1))/1 -> 5 | ... BJ8: =Inputs!$E$42*(1+Inputs!$E$44)^(BJ$5-1)*MAX(0,MIN(1,BJ$4*1-Inputs!$E$45+1))/1 -> 6.3123848
A9: Counter staff — FTE | C9: =Inputs!$E$46*(1+Inputs!$E$48)^(C$5-1)*MAX(0,MIN(1,C$4*1-Inputs!$E$49+1))/1 -> 7 | D9: =Inputs!$E$46*(1+Inputs!$E$48)^(D$5-1)*MAX(0,MIN(1,D$4*1-Inputs!$E$49+1))/1 -> 7 | E9: =Inputs!$E$46*(1+Inputs!$E$48)^(E$5-1)*MAX(0,MIN(1,E$4*1-Inputs!$E$49+1))/1 -> 7 | F9: =Inputs!$E$46*(1+Inputs!$E$48)^(F$5-1)*MAX(0,MIN(1,F$4*1-Inputs!$E$49+1))/1 -> 7 | G9: =Inputs!$E$46*(1+Inputs!$E$48)^(G$5-1)*MAX(0,MIN(1,G$4*1-Inputs!$E$49+1))/1 -> 7 | H9: =Inputs!$E$46*(1+Inputs!$E$48)^(H$5-1)*MAX(0,MIN(1,H$4*1-Inputs!$E$49+1))/1 -> 7 | I9: =Inputs!$E$46*(1+Inputs!$E$48)^(I$5-1)*MAX(0,MIN(1,I$4*1-Inputs!$E$49+1))/1 -> 7 | J9: =Inputs!$E$46*(1+Inputs!$E$48)^(J$5-1)*MAX(0,MIN(1,J$4*1-Inputs!$E$49+1))/1 -> 7 | ... BJ9: =Inputs!$E$46*(1+Inputs!$E$48)^(BJ$5-1)*MAX(0,MIN(1,BJ$4*1-Inputs!$E$49+1))/1 -> 8.8373387
A10: Manager — FTE | C10: =Inputs!$E$50*(1+Inputs!$E$52)^(C$5-1)*MAX(0,MIN(1,C$4*1-Inputs!$E$53+1))/1 -> 1.5 | D10: =Inputs!$E$50*(1+Inputs!$E$52)^(D$5-1)*MAX(0,MIN(1,D$4*1-Inputs!$E$53+1))/1 -> 1.5 | E10: =Inputs!$E$50*(1+Inputs!$E$52)^(E$5-1)*MAX(0,MIN(1,E$4*1-Inputs!$E$53+1))/1 -> 1.5 | F10: =Inputs!$E$50*(1+Inputs!$E$52)^(F$5-1)*MAX(0,MIN(1,F$4*1-Inputs!$E$53+1))/1 -> 1.5 | G10: =Inputs!$E$50*(1+Inputs!$E$52)^(G$5-1)*MAX(0,MIN(1,G$4*1-Inputs!$E$53+1))/1 -> 1.5 | H10: =Inputs!$E$50*(1+Inputs!$E$52)^(H$5-1)*MAX(0,MIN(1,H$4*1-Inputs!$E$53+1))/1 -> 1.5 | I10: =Inputs!$E$50*(1+Inputs!$E$52)^(I$5-1)*MAX(0,MIN(1,I$4*1-Inputs!$E$53+1))/1 -> 1.5 | J10: =Inputs!$E$50*(1+Inputs!$E$52)^(J$5-1)*MAX(0,MIN(1,J$4*1-Inputs!$E$53+1))/1 -> 1.5 | ... BJ10: =Inputs!$E$50*(1+Inputs!$E$52)^(BJ$5-1)*MAX(0,MIN(1,BJ$4*1-Inputs!$E$53+1))/1 -> 1.5
A11: Total FTE | C11: =C8+C9+C10 -> 13.5 | D11: =D8+D9+D10 -> 13.5 | E11: =E8+E9+E10 -> 13.5 | F11: =F8+F9+F10 -> 13.5 | G11: =G8+G9+G10 -> 13.5 | H11: =H8+H9+H10 -> 13.5 | I11: =I8+I9+I10 -> 13.5 | J11: =J8+J9+J10 -> 13.5 | ... BJ11: =BJ8+BJ9+BJ10 -> 16.649724
A13: Payroll cost (salary + taxes & benefits)
A14: Bakers & production — payroll cost | C14: =-C8*Inputs!$E$43/12*1*(1+Inputs!$E$54)*(1+Inputs!$E$55)^(C$5-1) -> -20533.333 | D14: =-D8*Inputs!$E$43/12*1*(1+Inputs!$E$54)*(1+Inputs!$E$55)^(D$5-1) -> -20533.333 | E14: =-E8*Inputs!$E$43/12*1*(1+Inputs!$E$54)*(1+Inputs!$E$55)^(E$5-1) -> -20533.333 | F14: =-F8*Inputs!$E$43/12*1*(1+Inputs!$E$54)*(1+Inputs!$E$55)^(F$5-1) -> -20533.333 | G14: =-G8*Inputs!$E$43/12*1*(1+Inputs!$E$54)*(1+Inputs!$E$55)^(G$5-1) -> -20533.333 | H14: =-H8*Inputs!$E$43/12*1*(1+Inputs!$E$54)*(1+Inputs!$E$55)^(H$5-1) -> -20533.333 | I14: =-I8*Inputs!$E$43/12*1*(1+Inputs!$E$54)*(1+Inputs!$E$55)^(I$5-1) -> -20533.333 | J14: =-J8*Inputs!$E$43/12*1*(1+Inputs!$E$54)*(1+Inputs!$E$55)^(J$5-1) -> -20533.333 | ... BJ14: =-BJ8*Inputs!$E$43/12*1*(1+Inputs!$E$54)*(1+Inputs!$E$55)^(BJ$5-1) -> -29176.408
A15: Counter staff — payroll cost | C15: =-C9*Inputs!$E$47/12*1*(1+Inputs!$E$54)*(1+Inputs!$E$55)^(C$5-1) -> -20253.333 | D15: =-D9*Inputs!$E$47/12*1*(1+Inputs!$E$54)*(1+Inputs!$E$55)^(D$5-1) -> -20253.333 | E15: =-E9*Inputs!$E$47/12*1*(1+Inputs!$E$54)*(1+Inputs!$E$55)^(E$5-1) -> -20253.333 | F15: =-F9*Inputs!$E$47/12*1*(1+Inputs!$E$54)*(1+Inputs!$E$55)^(F$5-1) -> -20253.333 | G15: =-G9*Inputs!$E$47/12*1*(1+Inputs!$E$54)*(1+Inputs!$E$55)^(G$5-1) -> -20253.333 | H15: =-H9*Inputs!$E$47/12*1*(1+Inputs!$E$54)*(1+Inputs!$E$55)^(H$5-1) -> -20253.333 | I15: =-I9*Inputs!$E$47/12*1*(1+Inputs!$E$54)*(1+Inputs!$E$55)^(I$5-1) -> -20253.333 | J15: =-J9*Inputs!$E$47/12*1*(1+Inputs!$E$54)*(1+Inputs!$E$55)^(J$5-1) -> -20253.333 | ... BJ15: =-BJ9*Inputs!$E$47/12*1*(1+Inputs!$E$54)*(1+Inputs!$E$55)^(BJ$5-1) -> -28778.547
A16: Manager — payroll cost | C16: =-C10*Inputs!$E$51/12*1*(1+Inputs!$E$54)*(1+Inputs!$E$55)^(C$5-1) -> -8680 | D16: =-D10*Inputs!$E$51/12*1*(1+Inputs!$E$54)*(1+Inputs!$E$55)^(D$5-1) -> -8680 | E16: =-E10*Inputs!$E$51/12*1*(1+Inputs!$E$54)*(1+Inputs!$E$55)^(E$5-1) -> -8680 | F16: =-F10*Inputs!$E$51/12*1*(1+Inputs!$E$54)*(1+Inputs!$E$55)^(F$5-1) -> -8680 | G16: =-G10*Inputs!$E$51/12*1*(1+Inputs!$E$54)*(1+Inputs!$E$55)^(G$5-1) -> -8680 | H16: =-H10*Inputs!$E$51/12*1*(1+Inputs!$E$54)*(1+Inputs!$E$55)^(H$5-1) -> -8680 | I16: =-I10*Inputs!$E$51/12*1*(1+Inputs!$E$54)*(1+Inputs!$E$55)^(I$5-1) -> -8680 | J16: =-J10*Inputs!$E$51/12*1*(1+Inputs!$E$54)*(1+Inputs!$E$55)^(J$5-1) -> -8680 | ... BJ16: =-BJ10*Inputs!$E$51/12*1*(1+Inputs!$E$54)*(1+Inputs!$E$55)^(BJ$5-1) -> -9769.4165
A17: Total payroll | C17: =C14+C15+C16 -> -49466.667 | D17: =D14+D15+D16 -> -49466.667 | E17: =E14+E15+E16 -> -49466.667 | F17: =F14+F15+F16 -> -49466.667 | G17: =G14+G15+G16 -> -49466.667 | H17: =H14+H15+H16 -> -49466.667 | I17: =I14+I15+I16 -> -49466.667 | J17: =J14+J15+J16 -> -49466.667 | ... BJ17: =BJ14+BJ15+BJ16 -> -67724.372

Sheet Scenario calc
A1: Scenario calculation — Low, Base and High side by side | D1: =HYPERLINK("#'Cover'!A1","◂ Contents") -> ◂ Contents
A2: The model's period calculation, copied three times; each copy reads its own Inputs column. Feeds the Scenarios sheet only.
A4: Low scenario — reads Inputs column B
A5: Month | C5: M1 | D5: M2 | E5: M3 | F5: M4 | G5: M5 | H5: M6 | I5: M7 | J5: M8 | K5: M9 | L5: M10 | M5: M11 | N5: M12 | O5: M13 | P5: M14 | Q5: M15 | R5: M16 | S5: M17 | T5: M18 | U5: M19 | V5: M20 | W5: M21 | X5: M22 | Y5: M23 | Z5: M24 | AA5: M25 | AB5: M26 | AC5: M27 | AD5: M28 | AE5: M29 | AF5: M30 | AG5: M31 | AH5: M32 | AI5: M33 | AJ5: M34 | AK5: M35 | AL5: M36 | AM5: M37 | AN5: M38 | AO5: M39 | AP5: M40 | AQ5: M41 | AR5: M42 | AS5: M43 | AT5: M44 | AU5: M45 | AV5: M46 | AW5: M47 | AX5: M48 | AY5: M49 | AZ5: M50 | BA5: M51 | BB5: M52 | BC5: M53 | BD5: M54 | BE5: M55 | BF5: M56 | BG5: M57 | BH5: M58 | BI5: M59 | BJ5: M60
A6: Period # | C6: 1 | D6: 2 | E6: 3 | F6: 4 | G6: 5 | H6: 6 | I6: 7 | J6: 8 | K6: 9 | L6: 10 | M6: 11 | N6: 12 | O6: 13 | P6: 14 | Q6: 15 | R6: 16 | S6: 17 | T6: 18 | U6: 19 | V6: 20 | W6: 21 | X6: 22 | Y6: 23 | Z6: 24 | AA6: 25 | AB6: 26 | AC6: 27 | AD6: 28 | AE6: 29 | AF6: 30 | AG6: 31 | AH6: 32 | AI6: 33 | AJ6: 34 | AK6: 35 | AL6: 36 | AM6: 37 | AN6: 38 | AO6: 39 | AP6: 40 | AQ6: 41 | AR6: 42 | AS6: 43 | AT6: 44 | AU6: 45 | AV6: 46 | AW6: 47 | AX6: 48 | AY6: 49 | AZ6: 50 | BA6: 51 | BB6: 52 | BC6: 53 | BD6: 54 | BE6: 55 | BF6: 56 | BG6: 57 | BH6: 58 | BI6: 59 | BJ6: 60
A7: Year # | C7: =ROUNDUP(C6*1/12,0) -> 1 | D7: =ROUNDUP(D6*1/12,0) -> 1 | E7: =ROUNDUP(E6*1/12,0) -> 1 | F7: =ROUNDUP(F6*1/12,0) -> 1 | G7: =ROUNDUP(G6*1/12,0) -> 1 | H7: =ROUNDUP(H6*1/12,0) -> 1 | I7: =ROUNDUP(I6*1/12,0) -> 1 | J7: =ROUNDUP(J6*1/12,0) -> 1 | ... BJ7: =ROUNDUP(BJ6*1/12,0) -> 5
A9: Retail counter
A10: Traffic ramp factor | C10: =MIN(1,Inputs!$B$9+(1-Inputs!$B$9)*(C$6-1)/MAX(1,Inputs!$B$8)) -> 0.85 | D10: =MIN(1,Inputs!$B$9+(1-Inputs!$B$9)*(D$6-1)/MAX(1,Inputs!$B$8)) -> 0.9 | E10: =MIN(1,Inputs!$B$9+(1-Inputs!$B$9)*(E$6-1)/MAX(1,Inputs!$B$8)) -> 0.95 | F10: =MIN(1,Inputs!$B$9+(1-Inputs!$B$9)*(F$6-1)/MAX(1,Inputs!$B$8)) -> 1 | G10: =MIN(1,Inputs!$B$9+(1-Inputs!$B$9)*(G$6-1)/MAX(1,Inputs!$B$8)) -> 1 | H10: =MIN(1,Inputs!$B$9+(1-Inputs!$B$9)*(H$6-1)/MAX(1,Inputs!$B$8)) -> 1 | I10: =MIN(1,Inputs!$B$9+(1-Inputs!$B$9)*(I$6-1)/MAX(1,Inputs!$B$8)) -> 1 | J10: =MIN(1,Inputs!$B$9+(1-Inputs!$B$9)*(J$6-1)/MAX(1,Inputs!$B$8)) -> 1 | ... BJ10: =MIN(1,Inputs!$B$9+(1-Inputs!$B$9)*(BJ$6-1)/MAX(1,Inputs!$B$8)) -> 1
A11: Season factor (November-December peak, added to the ramp) | C11: =IF(MOD(C$6-1,12)>=10,1+Inputs!$B$14,1-Inputs!$B$14/5) -> 0.96 | D11: =IF(MOD(D$6-1,12)>=10,1+Inputs!$B$14,1-Inputs!$B$14/5) -> 0.96 | E11: =IF(MOD(E$6-1,12)>=10,1+Inputs!$B$14,1-Inputs!$B$14/5) -> 0.96 | F11: =IF(MOD(F$6-1,12)>=10,1+Inputs!$B$14,1-Inputs!$B$14/5) -> 0.96 | G11: =IF(MOD(G$6-1,12)>=10,1+Inputs!$B$14,1-Inputs!$B$14/5) -> 0.96 | H11: =IF(MOD(H$6-1,12)>=10,1+Inputs!$B$14,1-Inputs!$B$14/5) -> 0.96 | I11: =IF(MOD(I$6-1,12)>=10,1+Inputs!$B$14,1-Inputs!$B$14/5) -> 0.96 | J11: =IF(MOD(J$6-1,12)>=10,1+Inputs!$B$14,1-Inputs!$B$14/5) -> 0.96 | ... BJ11: =IF(MOD(BJ$6-1,12)>=10,1+Inputs!$B$14,1-Inputs!$B$14/5) -> 1.2
A12: Customers per day | C12: =Inputs!$B$7*(1+Inputs!$B$10)^(C$7-1)*MAX(0,C10+C11-1) -> 243 | D12: =Inputs!$B$7*(1+Inputs!$B$10)^(D$7-1)*MAX(0,D10+D11-1) -> 258 | E12: =Inputs!$B$7*(1+Inputs!$B$10)^(E$7-1)*MAX(0,E10+E11-1) -> 273 | F12: =Inputs!$B$7*(1+Inputs!$B$10)^(F$7-1)*MAX(0,F10+F11-1) -> 288 | G12: =Inputs!$B$7*(1+Inputs!$B$10)^(G$7-1)*MAX(0,G10+G11-1) -> 288 | H12: =Inputs!$B$7*(1+Inputs!$B$10)^(H$7-1)*MAX(0,H10+H11-1) -> 288 | I12: =Inputs!$B$7*(1+Inputs!$B$10)^(I$7-1)*MAX(0,I10+I11-1) -> 288 | J12: =Inputs!$B$7*(1+Inputs!$B$10)^(J$7-1)*MAX(0,J10+J11-1) -> 288 | ... BJ12: =Inputs!$B$7*(1+Inputs!$B$10)^(BJ$7-1)*MAX(0,BJ10+BJ11-1) -> 374.61744
A13: Opening days in period | C13: =Inputs!$B$13*52/12*1 -> 26 | D13: =Inputs!$B$13*52/12*1 -> 26 | E13: =Inputs!$B$13*52/12*1 -> 26 | F13: =Inputs!$B$13*52/12*1 -> 26 | G13: =Inputs!$B$13*52/12*1 -> 26 | H13: =Inputs!$B$13*52/12*1 -> 26 | I13: =Inputs!$B$13*52/12*1 -> 26 | J13: =Inputs!$B$13*52/12*1 -> 26 | ... BJ13: =Inputs!$B$13*52/12*1 -> 26
A14: Retail transactions | C14: =C12*C13 -> 6318 | D14: =D12*D13 -> 6708 | E14: =E12*E13 -> 7098 | F14: =F12*F13 -> 7488 | G14: =G12*G13 -> 7488 | H14: =H12*H13 -> 7488 | I14: =I12*I13 -> 7488 | J14: =J12*J13 -> 7488 | ... BJ14: =BJ12*BJ13 -> 9740.0535
A15: Average ticket | C15: =Inputs!$B$11*(1+Inputs!$B$12)^(C$7-1) -> 11 | D15: =Inputs!$B$11*(1+Inputs!$B$12)^(D$7-1) -> 11 | E15: =Inputs!$B$11*(1+Inputs!$B$12)^(E$7-1) -> 11 | F15: =Inputs!$B$11*(1+Inputs!$B$12)^(F$7-1) -> 11 | G15: =Inputs!$B$11*(1+Inputs!$B$12)^(G$7-1) -> 11 | H15: =Inputs!$B$11*(1+Inputs!$B$12)^(H$7-1) -> 11 | I15: =Inputs!$B$11*(1+Inputs!$B$12)^(I$7-1) -> 11 | J15: =Inputs!$B$11*(1+Inputs!$B$12)^(J$7-1) -> 11 | ... BJ15: =Inputs!$B$11*(1+Inputs!$B$12)^(BJ$7-1) -> 11.906754
A16: Retail revenue | C16: =C14*C15 -> 69498 | D16: =D14*D15 -> 73788 | E16: =E14*E15 -> 78078 | F16: =F14*F15 -> 82368 | G16: =G14*G15 -> 82368 | H16: =H14*H15 -> 82368 | I16: =I14*I15 -> 82368 | J16: =J14*J15 -> 82368 | ... BJ16: =BJ14*BJ15 -> 115972.42
A18: Wholesale
A19: Wholesale accounts | C19: =Inputs!$B$17*C10*(1+Inputs!$B$18)^(C$7-1) -> 11.05 | D19: =Inputs!$B$17*D10*(1+Inputs!$B$18)^(D$7-1) -> 11.7 | E19: =Inputs!$B$17*E10*(1+Inputs!$B$18)^(E$7-1) -> 12.35 | F19: =Inputs!$B$17*F10*(1+Inputs!$B$18)^(F$7-1) -> 13 | G19: =Inputs!$B$17*G10*(1+Inputs!$B$18)^(G$7-1) -> 13 | H19: =Inputs!$B$17*H10*(1+Inputs!$B$18)^(H$7-1) -> 13 | I19: =Inputs!$B$17*I10*(1+Inputs!$B$18)^(I$7-1) -> 13 | J19: =Inputs!$B$17*J10*(1+Inputs!$B$18)^(J$7-1) -> 13 | ... BJ19: =Inputs!$B$17*BJ10*(1+Inputs!$B$18)^(BJ$7-1) -> 17.686356
A20: Order value per account per week | C20: =Inputs!$B$19*(1+Inputs!$B$12)^(C$7-1) -> 500 | D20: =Inputs!$B$19*(1+Inputs!$B$12)^(D$7-1) -> 500 | E20: =Inputs!$B$19*(1+Inputs!$B$12)^(E$7-1) -> 500 | F20: =Inputs!$B$19*(1+Inputs!$B$12)^(F$7-1) -> 500 | G20: =Inputs!$B$19*(1+Inputs!$B$12)^(G$7-1) -> 500 | H20: =Inputs!$B$19*(1+Inputs!$B$12)^(H$7-1) -> 500 | I20: =Inputs!$B$19*(1+Inputs!$B$12)^(I$7-1) -> 500 | J20: =Inputs!$B$19*(1+Inputs!$B$12)^(J$7-1) -> 500 | ... BJ20: =Inputs!$B$19*(1+Inputs!$B$12)^(BJ$7-1) -> 541.21608
A21: Wholesale revenue | C21: =C19*C20*52/12*1 -> 23941.667 | D21: =D19*D20*52/12*1 -> 25350 | E21: =E19*E20*52/12*1 -> 26758.333 | F21: =F19*F20*52/12*1 -> 28166.667 | G21: =G19*G20*52/12*1 -> 28166.667 | H21: =H19*H20*52/12*1 -> 28166.667 | I21: =I19*I20*52/12*1 -> 28166.667 | J21: =J19*J20*52/12*1 -> 28166.667 | ... BJ21: =BJ19*BJ20*52/12*1 -> 41479.276
A23: Revenue
A24: Revenue | C24: =C16+C21 -> 93439.667 | D24: =D16+D21 -> 99138 | E24: =E16+E21 -> 104836.33 | F24: =F16+F21 -> 110534.67 | G24: =G16+G21 -> 110534.67 | H24: =H16+H21 -> 110534.67 | I24: =I16+I21 -> 110534.67 | J24: =J16+J21 -> 110534.67 | ... BJ24: =BJ16+BJ21 -> 157451.69
A26: Cost of sales
A27: Ingredients sold | C27: =-(C16*Inputs!$B$24+C21*Inputs!$B$25) -> -25981.865 | D27: =-(D16*Inputs!$B$24+D21*Inputs!$B$25) -> -27561.69 | E27: =-(E16*Inputs!$B$24+E21*Inputs!$B$25) -> -29141.515 | F27: =-(F16*Inputs!$B$24+F21*Inputs!$B$25) -> -30721.34 | G27: =-(G16*Inputs!$B$24+G21*Inputs!$B$25) -> -30721.34 | H27: =-(H16*Inputs!$B$24+H21*Inputs!$B$25) -> -30721.34 | I27: =-(I16*Inputs!$B$24+I21*Inputs!$B$25) -> -30721.34 | J27: =-(J16*Inputs!$B$24+J21*Inputs!$B$25) -> -30721.34 | ... BJ27: =-(BJ16*Inputs!$B$24+BJ21*Inputs!$B$25) -> -43883.317
A28: Waste (retail production not sold, at ingredient cost) | C28: =-C16*Inputs!$B$24*Inputs!$B$26*100/MAX(1,100-100*Inputs!$B$26) -> -2190.3583 | D28: =-D16*Inputs!$B$24*Inputs!$B$26*100/MAX(1,100-100*Inputs!$B$26) -> -2325.5656 | E28: =-E16*Inputs!$B$24*Inputs!$B$26*100/MAX(1,100-100*Inputs!$B$26) -> -2460.7729 | F28: =-F16*Inputs!$B$24*Inputs!$B$26*100/MAX(1,100-100*Inputs!$B$26) -> -2595.9802 | G28: =-G16*Inputs!$B$24*Inputs!$B$26*100/MAX(1,100-100*Inputs!$B$26) -> -2595.9802 | H28: =-H16*Inputs!$B$24*Inputs!$B$26*100/MAX(1,100-100*Inputs!$B$26) -> -2595.9802 | I28: =-I16*Inputs!$B$24*Inputs!$B$26*100/MAX(1,100-100*Inputs!$B$26) -> -2595.9802 | J28: =-J16*Inputs!$B$24*Inputs!$B$26*100/MAX(1,100-100*Inputs!$B$26) -> -2595.9802 | ... BJ28: =-BJ16*Inputs!$B$24*Inputs!$B$26*100/MAX(1,100-100*Inputs!$B$26) -> -3655.0858
A29: Packaging | C29: =-C24*Inputs!$B$27 -> -3457.2677 | D29: =-D24*Inputs!$B$27 -> -3668.106 | E29: =-E24*Inputs!$B$27 -> -3878.9443 | F29: =-F24*Inputs!$B$27 -> -4089.7827 | G29: =-G24*Inputs!$B$27 -> -4089.7827 | H29: =-H24*Inputs!$B$27 -> -4089.7827 | I29: =-I24*Inputs!$B$27 -> -4089.7827 | J29: =-J24*Inputs!$B$27 -> -4089.7827 | ... BJ29: =-BJ24*Inputs!$B$27 -> -5825.7127
A30: Cost of sales | C30: =C27+C28+C29 -> -31629.491 | D30: =D27+D28+D29 -> -33555.362 | E30: =E27+E28+E29 -> -35481.232 | F30: =F27+F28+F29 -> -37407.103 | G30: =G27+G28+G29 -> -37407.103 | H30: =H27+H28+H29 -> -37407.103 | I30: =I27+I28+I29 -> -37407.103 | J30: =J27+J28+J29 -> -37407.103 | ... BJ30: =BJ27+BJ28+BJ29 -> -53364.115
A31: Gross profit | C31: =C24+C30 -> 61810.176 | D31: =D24+D30 -> 65582.638 | E31: =E24+E30 -> 69355.101 | F31: =F24+F30 -> 73127.564 | G31: =G24+G30 -> 73127.564 | H31: =H24+H30 -> 73127.564 | I31: =I24+I30 -> 73127.564 | J31: =J24+J30 -> 73127.564 | ... BJ31: =BJ24+BJ30 -> 104087.58
A33: Operating expenses
A34: Payroll (bakers, counter, manager) | C34: =C112 -> -49466.667 | D34: =D112 -> -49466.667 | E34: =E112 -> -49466.667 | F34: =F112 -> -49466.667 | G34: =G112 -> -49466.667 | H34: =H112 -> -49466.667 | I34: =I112 -> -49466.667 | J34: =J112 -> -49466.667 | ... BJ34: =BJ112 -> -67724.372
A35: Rent | C35: =-Inputs!$B$30*1 -> -12000 | D35: =-Inputs!$B$30*1 -> -12000 | E35: =-Inputs!$B$30*1 -> -12000 | F35: =-Inputs!$B$30*1 -> -12000 | G35: =-Inputs!$B$30*1 -> -12000 | H35: =-Inputs!$B$30*1 -> -12000 | I35: =-Inputs!$B$30*1 -> -12000 | J35: =-Inputs!$B$30*1 -> -12000 | ... BJ35: =-Inputs!$B$30*1 -> -12000
A36: Utilities (ovens) | C36: =-Inputs!$B$31*1 -> -4000 | D36: =-Inputs!$B$31*1 -> -4000 | E36: =-Inputs!$B$31*1 -> -4000 | F36: =-Inputs!$B$31*1 -> -4000 | G36: =-Inputs!$B$31*1 -> -4000 | H36: =-Inputs!$B$31*1 -> -4000 | I36: =-Inputs!$B$31*1 -> -4000 | J36: =-Inputs!$B$31*1 -> -4000 | ... BJ36: =-Inputs!$B$31*1 -> -4000
A37: Wholesale delivery | C37: =-C19*Inputs!$B$20*52/12*1*Inputs!$B$21 -> -2274.4583 | D37: =-D19*Inputs!$B$20*52/12*1*Inputs!$B$21 -> -2408.25 | E37: =-E19*Inputs!$B$20*52/12*1*Inputs!$B$21 -> -2542.0417 | F37: =-F19*Inputs!$B$20*52/12*1*Inputs!$B$21 -> -2675.8333 | G37: =-G19*Inputs!$B$20*52/12*1*Inputs!$B$21 -> -2675.8333 | H37: =-H19*Inputs!$B$20*52/12*1*Inputs!$B$21 -> -2675.8333 | I37: =-I19*Inputs!$B$20*52/12*1*Inputs!$B$21 -> -2675.8333 | J37: =-J19*Inputs!$B$20*52/12*1*Inputs!$B$21 -> -2675.8333 | ... BJ37: =-BJ19*Inputs!$B$20*52/12*1*Inputs!$B$21 -> -3640.4417
A38: Equipment repairs & cleaning | C38: =-Inputs!$B$32*1 -> -1000 | D38: =-Inputs!$B$32*1 -> -1000 | E38: =-Inputs!$B$32*1 -> -1000 | F38: =-Inputs!$B$32*1 -> -1000 | G38: =-Inputs!$B$32*1 -> -1000 | H38: =-Inputs!$B$32*1 -> -1000 | I38: =-Inputs!$B$32*1 -> -1000 | J38: =-Inputs!$B$32*1 -> -1000 | ... BJ38: =-Inputs!$B$32*1 -> -1000
A39: Marketing | C39: =-C24*Inputs!$B$33 -> -2055.6727 | D39: =-D24*Inputs!$B$33 -> -2181.036 | E39: =-E24*Inputs!$B$33 -> -2306.3993 | F39: =-F24*Inputs!$B$33 -> -2431.7627 | G39: =-G24*Inputs!$B$33 -> -2431.7627 | H39: =-H24*Inputs!$B$33 -> -2431.7627 | I39: =-I24*Inputs!$B$33 -> -2431.7627 | J39: =-J24*Inputs!$B$33 -> -2431.7627 | ... BJ39: =-BJ24*Inputs!$B$33 -> -3463.9373
A40: Card processing fees | C40: =-C16*Inputs!$B$34 -> -2015.442 | D40: =-D16*Inputs!$B$34 -> -2139.852 | E40: =-E16*Inputs!$B$34 -> -2264.262 | F40: =-F16*Inputs!$B$34 -> -2388.672 | G40: =-G16*Inputs!$B$34 -> -2388.672 | H40: =-H16*Inputs!$B$34 -> -2388.672 | I40: =-I16*Inputs!$B$34 -> -2388.672 | J40: =-J16*Inputs!$B$34 -> -2388.672 | ... BJ40: =-BJ16*Inputs!$B$34 -> -3363.2002
A41: Insurance, licences & other G&A | C41: =-Inputs!$B$35*1 -> -2800 | D41: =-Inputs!$B$35*1 -> -2800 | E41: =-Inputs!$B$35*1 -> -2800 | F41: =-Inputs!$B$35*1 -> -2800 | G41: =-Inputs!$B$35*1 -> -2800 | H41: =-Inputs!$B$35*1 -> -2800 | I41: =-Inputs!$B$35*1 -> -2800 | J41: =-Inputs!$B$35*1 -> -2800 | ... BJ41: =-Inputs!$B$35*1 -> -2800
A42: Total operating expenses | C42: =C34+C35+C36+C37+C38+C39+C40+C41 -> -75612.24 | D42: =D34+D35+D36+D37+D38+D39+D40+D41 -> -75995.805 | E42: =E34+E35+E36+E37+E38+E39+E40+E41 -> -76379.37 | F42: =F34+F35+F36+F37+F38+F39+F40+F41 -> -76762.935 | G42: =G34+G35+G36+G37+G38+G39+G40+G41 -> -76762.935 | H42: =H34+H35+H36+H37+H38+H39+H40+H41 -> -76762.935 | I42: =I34+I35+I36+I37+I38+I39+I40+I41 -> -76762.935 | J42: =J34+J35+J36+J37+J38+J39+J40+J41 -> -76762.935 | ... BJ42: =BJ34+BJ35+BJ36+BJ37+BJ38+BJ39+BJ40+BJ41 -> -97991.951
A43: EBITDA | C43: =C31+C42 -> -13802.064 | D43: =D31+D42 -> -10413.166 | E43: =E31+E42 -> -7024.2686 | F43: =F31+F42 -> -3635.3709 | G43: =G31+G42 -> -3635.3709 | H43: =H31+H42 -> -3635.3709 | I43: =I31+I42 -> -3635.3709 | J43: =J31+J42 -> -3635.3709 | ... BJ43: =BJ31+BJ42 -> 6095.6285
A45: Profit after depreciation, interest, tax
A46: EBIT | C46: =C43+C57 -> -14873.493 | D46: =D43+D57 -> -11484.595 | E46: =E43+E57 -> -8095.6972 | F46: =F43+F57 -> -4706.7995 | G46: =G43+G57 -> -4706.7995 | H46: =H43+H57 -> -4706.7995 | I46: =I43+I57 -> -4706.7995 | J46: =J43+J57 -> -4706.7995 | ... BJ46: =BJ43+BJ57 -> 4357.5333
A47: Interest on loan (average balance after drawdown) | C47: =-(C62+C63+C65)/2*Inputs!$B$60/12 -> -566.66667 | D47: =-(D62+D63+D65)/2*Inputs!$B$60/12 -> -561.94444 | E47: =-(E62+E63+E65)/2*Inputs!$B$60/12 -> -552.5 | F47: =-(F62+F63+F65)/2*Inputs!$B$60/12 -> -543.05556 | G47: =-(G62+G63+G65)/2*Inputs!$B$60/12 -> -533.61111 | H47: =-(H62+H63+H65)/2*Inputs!$B$60/12 -> -524.16667 | I47: =-(I62+I63+I65)/2*Inputs!$B$60/12 -> -514.72222 | J47: =-(J62+J63+J65)/2*Inputs!$B$60/12 -> -505.27778 | ... BJ47: =-(BJ62+BJ63+BJ65)/2*Inputs!$B$60/12 -> -14.166667
A48: Pre-tax income | C48: =C46+C47 -> -15440.159 | D48: =D46+D47 -> -12046.539 | E48: =E46+E47 -> -8648.1972 | F48: =F46+F47 -> -5249.855 | G48: =G46+G47 -> -5240.4106 | H48: =H46+H47 -> -5230.9661 | I48: =I46+I47 -> -5221.5217 | J48: =J46+J47 -> -5212.0772 | ... BJ48: =BJ46+BJ47 -> 4343.3666
A49: Helper: cumulative pre-tax income | C49: =C48 -> -15440.159 | D49: =C49+D48 -> -27486.699 | E49: =D49+E48 -> -36134.896 | F49: =E49+F48 -> -41384.751 | G49: =F49+G48 -> -46625.161 | H49: =G49+H48 -> -51856.127 | I49: =H49+I48 -> -57077.649 | J49: =I49+J48 -> -62289.726 | K49: =J49+K48 -> -67492.359 | ... BJ49: =BI49+BJ48 -> -333349.89
A50: Helper: cumulative taxable income (losses carried forward) | C50: =MAX(0,C49) -> 0 | D50: =MAX(C50,D49) -> 0 | E50: =MAX(D50,E49) -> 0 | F50: =MAX(E50,F49) -> 0 | G50: =MAX(F50,G49) -> 0 | H50: =MAX(G50,H49) -> 0 | I50: =MAX(H50,I49) -> 0 | J50: =MAX(I50,J49) -> 0 | K50: =MAX(J50,K49) -> 0 | ... BJ50: =MAX(BI50,BJ49) -> 0
A51: Income tax | C51: =-C50*Inputs!$B$70 -> 0 | D51: =-(D50-C50)*Inputs!$B$70 -> 0 | E51: =-(E50-D50)*Inputs!$B$70 -> 0 | F51: =-(F50-E50)*Inputs!$B$70 -> 0 | G51: =-(G50-F50)*Inputs!$B$70 -> 0 | H51: =-(H50-G50)*Inputs!$B$70 -> 0 | I51: =-(I50-H50)*Inputs!$B$70 -> 0 | J51: =-(J50-I50)*Inputs!$B$70 -> 0 | K51: =-(K50-J50)*Inputs!$B$70 -> 0 | ... BJ51: =-(BJ50-BI50)*Inputs!$B$70 -> 0
A52: Net income | C52: =C48+C51 -> -15440.159 | D52: =D48+D51 -> -12046.539 | E52: =E48+E51 -> -8648.1972 | F52: =F48+F51 -> -5249.855 | G52: =G48+G51 -> -5240.4106 | H52: =H48+H51 -> -5230.9661 | I52: =I48+I51 -> -5221.5217 | J52: =J48+J51 -> -5212.0772 | ... BJ52: =BJ48+BJ51 -> 4343.3666
A54: Fixed assets & capital spending
A55: Capital spending (fit-out, ovens, mixers, display cases) | C55: =IF(C$6=1,Inputs!$B$38,0)+IF(C$7>1,Inputs!$B$39*1/12,0) -> 90000 | D55: =IF(D$6=1,Inputs!$B$38,0)+IF(D$7>1,Inputs!$B$39*1/12,0) -> 0 | E55: =IF(E$6=1,Inputs!$B$38,0)+IF(E$7>1,Inputs!$B$39*1/12,0) -> 0 | F55: =IF(F$6=1,Inputs!$B$38,0)+IF(F$7>1,Inputs!$B$39*1/12,0) -> 0 | G55: =IF(G$6=1,Inputs!$B$38,0)+IF(G$7>1,Inputs!$B$39*1/12,0) -> 0 | H55: =IF(H$6=1,Inputs!$B$38,0)+IF(H$7>1,Inputs!$B$39*1/12,0) -> 0 | I55: =IF(I$6=1,Inputs!$B$38,0)+IF(I$7>1,Inputs!$B$39*1/12,0) -> 0 | J55: =IF(J$6=1,Inputs!$B$38,0)+IF(J$7>1,Inputs!$B$39*1/12,0) -> 0 | ... BJ55: =IF(BJ$6=1,Inputs!$B$38,0)+IF(BJ$7>1,Inputs!$B$39*1/12,0) -> 1166.6667
A56: Fixed assets at cost | C56: =C55 -> 90000 | D56: =C56+D55 -> 90000 | E56: =D56+E55 -> 90000 | F56: =E56+F55 -> 90000 | G56: =F56+G55 -> 90000 | H56: =G56+H55 -> 90000 | I56: =H56+I55 -> 90000 | J56: =I56+J55 -> 90000 | K56: =J56+K55 -> 90000 | ... BJ56: =BI56+BJ55 -> 146000
A57: Depreciation | C57: =-MIN(C56/MAX(1,Inputs!$B$69*12),C55) -> -1071.4286 | D57: =-MIN(D56/MAX(1,Inputs!$B$69*12),C59+D55) -> -1071.4286 | E57: =-MIN(E56/MAX(1,Inputs!$B$69*12),D59+E55) -> -1071.4286 | F57: =-MIN(F56/MAX(1,Inputs!$B$69*12),E59+F55) -> -1071.4286 | G57: =-MIN(G56/MAX(1,Inputs!$B$69*12),F59+G55) -> -1071.4286 | H57: =-MIN(H56/MAX(1,Inputs!$B$69*12),G59+H55) -> -1071.4286 | I57: =-MIN(I56/MAX(1,Inputs!$B$69*12),H59+I55) -> -1071.4286 | J57: =-MIN(J56/MAX(1,Inputs!$B$69*12),I59+J55) -> -1071.4286 | K57: =-MIN(K56/MAX(1,Inputs!$B$69*12),J59+K55) -> -1071.4286 | ... BJ57: =-MIN(BJ56/MAX(1,Inputs!$B$69*12),BI59+BJ55) -> -1738.0952
A58: Accumulated depreciation | C58: =C57 -> -1071.4286 | D58: =C58+D57 -> -2142.8571 | E58: =D58+E57 -> -3214.2857 | F58: =E58+F57 -> -4285.7143 | G58: =F58+G57 -> -5357.1429 | H58: =G58+H57 -> -6428.5714 | I58: =H58+I57 -> -7500 | J58: =I58+J57 -> -8571.4286 | K58: =J58+K57 -> -9642.8571 | ... BJ58: =BI58+BJ57 -> -80619.048
A59: Net fixed assets | C59: =C56+C58 -> 88928.571 | D59: =D56+D58 -> 87857.143 | E59: =E56+E58 -> 86785.714 | F59: =F56+F58 -> 85714.286 | G59: =G56+G58 -> 84642.857 | H59: =H56+H58 -> 83571.429 | I59: =I56+I58 -> 82500 | J59: =J56+J58 -> 81428.571 | ... BJ59: =BJ56+BJ58 -> 65380.952
A61: Debt
A62: Loan — opening balance | C62: =0 -> 0 | D62: =C65 -> 80000 | E62: =D65 -> 78666.667 | F62: =E65 -> 77333.333 | G62: =F65 -> 76000 | H62: =G65 -> 74666.667 | I62: =H65 -> 73333.333 | J62: =I65 -> 72000 | K62: =J65 -> 70666.667 | ... BJ62: =BI65 -> 2666.6667
A63: Loan drawdown | C63: =IF(C$6=1,Inputs!$B$59,0) -> 80000 | D63: =IF(D$6=1,Inputs!$B$59,0) -> 0 | E63: =IF(E$6=1,Inputs!$B$59,0) -> 0 | F63: =IF(F$6=1,Inputs!$B$59,0) -> 0 | G63: =IF(G$6=1,Inputs!$B$59,0) -> 0 | H63: =IF(H$6=1,Inputs!$B$59,0) -> 0 | I63: =IF(I$6=1,Inputs!$B$59,0) -> 0 | J63: =IF(J$6=1,Inputs!$B$59,0) -> 0 | ... BJ63: =IF(BJ$6=1,Inputs!$B$59,0) -> 0
A64: Loan repayment | C64: =-MIN(C62,Inputs!$B$59/MAX(1,Inputs!$B$61*12)) -> 0 | D64: =-MIN(D62,Inputs!$B$59/MAX(1,Inputs!$B$61*12)) -> -1333.3333 | E64: =-MIN(E62,Inputs!$B$59/MAX(1,Inputs!$B$61*12)) -> -1333.3333 | F64: =-MIN(F62,Inputs!$B$59/MAX(1,Inputs!$B$61*12)) -> -1333.3333 | G64: =-MIN(G62,Inputs!$B$59/MAX(1,Inputs!$B$61*12)) -> -1333.3333 | H64: =-MIN(H62,Inputs!$B$59/MAX(1,Inputs!$B$61*12)) -> -1333.3333 | I64: =-MIN(I62,Inputs!$B$59/MAX(1,Inputs!$B$61*12)) -> -1333.3333 | J64: =-MIN(J62,Inputs!$B$59/MAX(1,Inputs!$B$61*12)) -> -1333.3333 | ... BJ64: =-MIN(BJ62,Inputs!$B$59/MAX(1,Inputs!$B$61*12)) -> -1333.3333
A65: Loan — closing balance | C65: =C62+C63+C64 -> 80000 | D65: =D62+D63+D64 -> 78666.667 | E65: =E62+E63+E64 -> 77333.333 | F65: =F62+F63+F64 -> 76000 | G65: =G62+G63+G64 -> 74666.667 | H65: =H62+H63+H64 -> 73333.333 | I65: =I62+I63+I64 -> 72000 | J65: =J62+J63+J64 -> 70666.667 | ... BJ65: =BJ62+BJ63+BJ64 -> 1333.3333
A67: Working capital
A68: Accounts receivable | C68: =C24*Inputs!$B$64/30 -> 28031.9 | D68: =D24*Inputs!$B$64/30 -> 29741.4 | E68: =E24*Inputs!$B$64/30 -> 31450.9 | F68: =F24*Inputs!$B$64/30 -> 33160.4 | G68: =G24*Inputs!$B$64/30 -> 33160.4 | H68: =H24*Inputs!$B$64/30 -> 33160.4 | I68: =I24*Inputs!$B$64/30 -> 33160.4 | J68: =J24*Inputs!$B$64/30 -> 33160.4 | ... BJ68: =BJ24*Inputs!$B$64/30 -> 47235.508
A69: Inventory | C69: =-C30*Inputs!$B$65/30 -> 3162.9491 | D69: =-D30*Inputs!$B$65/30 -> 3355.5362 | E69: =-E30*Inputs!$B$65/30 -> 3548.1232 | F69: =-F30*Inputs!$B$65/30 -> 3740.7103 | G69: =-G30*Inputs!$B$65/30 -> 3740.7103 | H69: =-H30*Inputs!$B$65/30 -> 3740.7103 | I69: =-I30*Inputs!$B$65/30 -> 3740.7103 | J69: =-J30*Inputs!$B$65/30 -> 3740.7103 | ... BJ69: =-BJ30*Inputs!$B$65/30 -> 5336.4115
A70: Accounts payable | C70: =-C30*Inputs!$B$66/30 -> 18977.695 | D70: =-D30*Inputs!$B$66/30 -> 20133.217 | E70: =-E30*Inputs!$B$66/30 -> 21288.739 | F70: =-F30*Inputs!$B$66/30 -> 22444.262 | G70: =-G30*Inputs!$B$66/30 -> 22444.262 | H70: =-H30*Inputs!$B$66/30 -> 22444.262 | I70: =-I30*Inputs!$B$66/30 -> 22444.262 | J70: =-J30*Inputs!$B$66/30 -> 22444.262 | ... BJ70: =-BJ30*Inputs!$B$66/30 -> 32018.469
A71: (Increase) / decrease in receivables | C71: =-C68 -> -28031.9 | D71: =C68-D68 -> -1709.5 | E71: =D68-E68 -> -1709.5 | F71: =E68-F68 -> -1709.5 | G71: =F68-G68 -> 0 | H71: =G68-H68 -> 0 | I71: =H68-I68 -> 0 | J71: =I68-J68 -> 0 | K71: =J68-K68 -> 0 | ... BJ71: =BI68-BJ68 -> 0
A72: (Increase) / decrease in inventory | C72: =-C69 -> -3162.9491 | D72: =C69-D69 -> -192.58706 | E72: =D69-E69 -> -192.58706 | F72: =E69-F69 -> -192.58706 | G72: =F69-G69 -> 0 | H72: =G69-H69 -> 0 | I72: =H69-I69 -> 0 | J72: =I69-J69 -> 0 | K72: =J69-K69 -> 0 | ... BJ72: =BI69-BJ69 -> 0
A73: Increase / (decrease) in payables | C73: =C70 -> 18977.695 | D73: =D70-C70 -> 1155.5224 | E73: =E70-D70 -> 1155.5224 | F73: =F70-E70 -> 1155.5224 | G73: =G70-F70 -> 0 | H73: =H70-G70 -> 0 | I73: =I70-H70 -> 0 | J73: =J70-I70 -> 0 | K73: =K70-J70 -> 0 | ... BJ73: =BJ70-BI70 -> 0
A75: Cash flow
A76: Operating cash flow | C76: =C52-C57+C71+C72+C73 -> -26585.885 | D76: =D52-D57+D71+D72+D73 -> -11721.675 | E76: =E52-E57+E71+E72+E73 -> -8323.3333 | F76: =F52-F57+F71+F72+F73 -> -4924.9911 | G76: =G52-G57+G71+G72+G73 -> -4168.982 | H76: =H52-H57+H71+H72+H73 -> -4159.5376 | I76: =I52-I57+I71+I72+I73 -> -4150.0931 | J76: =J52-J57+J71+J72+J73 -> -4140.6487 | ... BJ76: =BJ52-BJ57+BJ71+BJ72+BJ73 -> 6081.4619
A77: Investing cash flow (capex) | C77: =-C55 -> -90000 | D77: =-D55 -> 0 | E77: =-E55 -> 0 | F77: =-F55 -> 0 | G77: =-G55 -> 0 | H77: =-H55 -> 0 | I77: =-I55 -> 0 | J77: =-J55 -> 0 | ... BJ77: =-BJ55 -> -1166.6667
A78: Equity raised | C78: =IF(C$6=1,Inputs!$B$58,0) -> 60000 | D78: =IF(D$6=1,Inputs!$B$58,0) -> 0 | E78: =IF(E$6=1,Inputs!$B$58,0) -> 0 | F78: =IF(F$6=1,Inputs!$B$58,0) -> 0 | G78: =IF(G$6=1,Inputs!$B$58,0) -> 0 | H78: =IF(H$6=1,Inputs!$B$58,0) -> 0 | I78: =IF(I$6=1,Inputs!$B$58,0) -> 0 | J78: =IF(J$6=1,Inputs!$B$58,0) -> 0 | ... BJ78: =IF(BJ$6=1,Inputs!$B$58,0) -> 0
A79: Financing cash flow | C79: =C78+C63+C64 -> 140000 | D79: =D78+D63+D64 -> -1333.3333 | E79: =E78+E63+E64 -> -1333.3333 | F79: =F78+F63+F64 -> -1333.3333 | G79: =G78+G63+G64 -> -1333.3333 | H79: =H78+H63+H64 -> -1333.3333 | I79: =I78+I63+I64 -> -1333.3333 | J79: =J78+J63+J64 -> -1333.3333 | ... BJ79: =BJ78+BJ63+BJ64 -> -1333.3333
A80: Net cash flow | C80: =C76+C77+C79 -> 23414.115 | D80: =D76+D77+D79 -> -13055.009 | E80: =E76+E77+E79 -> -9656.6666 | F80: =F76+F77+F79 -> -6258.3245 | G80: =G76+G77+G79 -> -5502.3153 | H80: =H76+H77+H79 -> -5492.8709 | I80: =I76+I77+I79 -> -5483.4264 | J80: =J76+J77+J79 -> -5473.982 | ... BJ80: =BJ76+BJ77+BJ79 -> 3581.4619
A81: Opening cash | C81: =0 -> 0 | D81: =C82 -> 23414.115 | E81: =D82 -> 10359.106 | F81: =E82 -> 702.4395 | G81: =F82 -> -5555.885 | H81: =G82 -> -11058.2 | I81: =H82 -> -16551.071 | J81: =I82 -> -22034.498 | K81: =J82 -> -27508.48 | ... BJ81: =BI82 -> -361532.43
A82: Closing cash | C82: =C81+C80 -> 23414.115 | D82: =D81+D80 -> 10359.106 | E82: =E81+E80 -> 702.4395 | F82: =F81+F80 -> -5555.885 | G82: =G81+G80 -> -11058.2 | H82: =H81+H80 -> -16551.071 | I82: =I81+I80 -> -22034.498 | J82: =J81+J80 -> -27508.48 | ... BJ82: =BJ81+BJ80 -> -357950.96
A83: Helper: EBITDA positive (1/0) | C83: =IF(C43>0,1,0) -> 0 | D83: =IF(D43>0,1,0) -> 0 | E83: =IF(E43>0,1,0) -> 0 | F83: =IF(F43>0,1,0) -> 0 | G83: =IF(G43>0,1,0) -> 0 | H83: =IF(H43>0,1,0) -> 0 | I83: =IF(I43>0,1,0) -> 0 | J83: =IF(J43>0,1,0) -> 0 | ... BJ83: =IF(BJ43>0,1,0) -> 1
A85: Goal modules
A86: Helper: net income positive (1/0) | C86: =IF(C52>0,1,0) -> 0 | D86: =IF(D52>0,1,0) -> 0 | E86: =IF(E52>0,1,0) -> 0 | F86: =IF(F52>0,1,0) -> 0 | G86: =IF(G52>0,1,0) -> 0 | H86: =IF(H52>0,1,0) -> 0 | I86: =IF(I52>0,1,0) -> 0 | J86: =IF(J52>0,1,0) -> 0 | ... BJ86: =IF(BJ52>0,1,0) -> 1
A87: Cash flow before financing (operating + investing) | C87: =C76+C77 -> -116585.89 | D87: =D76+D77 -> -11721.675 | E87: =E76+E77 -> -8323.3333 | F87: =F76+F77 -> -4924.9911 | G87: =G76+G77 -> -4168.982 | H87: =H76+H77 -> -4159.5376 | I87: =I76+I77 -> -4150.0931 | J87: =J76+J77 -> -4140.6487 | ... BJ87: =BJ76+BJ77 -> 4914.7952
A88: Cumulative cash flow before financing | C88: =C87 -> -116585.89 | D88: =C88+D87 -> -128307.56 | E88: =D88+E87 -> -136630.89 | F88: =E88+F87 -> -141555.88 | G88: =F88+G87 -> -145724.87 | H88: =G88+H87 -> -149884.4 | I88: =H88+I87 -> -154034.5 | J88: =I88+J87 -> -158175.15 | K88: =J88+K87 -> -162306.35 | ... BJ88: =BI88+BJ87 -> -419284.3
A89: Helper: lowest cumulative cash flow so far | C89: =C88 -> -116585.89 | D89: =MIN(C89,D88) -> -128307.56 | E89: =MIN(D89,E88) -> -136630.89 | F89: =MIN(E89,F88) -> -141555.88 | G89: =MIN(F89,G88) -> -145724.87 | H89: =MIN(G89,H88) -> -149884.4 | I89: =MIN(H89,I88) -> -154034.5 | J89: =MIN(I89,J88) -> -158175.15 | K89: =MIN(J89,K88) -> -162306.35 | ... BJ89: =MIN(BI89,BJ88) -> -425898
A90: Helper: investment paid back (1/0) | C90: =IF(AND(C88>=0,C89<0),1,0) -> 0 | D90: =IF(AND(D88>=0,D89<0),1,0) -> 0 | E90: =IF(AND(E88>=0,E89<0),1,0) -> 0 | F90: =IF(AND(F88>=0,F89<0),1,0) -> 0 | G90: =IF(AND(G88>=0,G89<0),1,0) -> 0 | H90: =IF(AND(H88>=0,H89<0),1,0) -> 0 | I90: =IF(AND(I88>=0,I89<0),1,0) -> 0 | J90: =IF(AND(J88>=0,J89<0),1,0) -> 0 | ... BJ90: =IF(AND(BJ88>=0,BJ89<0),1,0) -> 0
A91: Unlevered free cash flow (operating + after-tax interest − capex) | C91: =C76-C47*(1-Inputs!$B$70)+C77 -> -116138.22 | D91: =D76-D47*(1-Inputs!$B$70)+D77 -> -11277.739 | E91: =E76-E47*(1-Inputs!$B$70)+E77 -> -7886.8583 | F91: =F76-F47*(1-Inputs!$B$70)+F77 -> -4495.9772 | G91: =G76-G47*(1-Inputs!$B$70)+G77 -> -3747.4292 | H91: =H76-H47*(1-Inputs!$B$70)+H77 -> -3745.4459 | I91: =I76-I47*(1-Inputs!$B$70)+I77 -> -3743.4626 | J91: =J76-J47*(1-Inputs!$B$70)+J77 -> -3741.4792 | ... BJ91: =BJ76-BJ47*(1-Inputs!$B$70)+BJ77 -> 4925.9869
A93: Balance sheet
A94: Paid-in capital | C94: =C78 -> 60000 | D94: =C94+D78 -> 60000 | E94: =D94+E78 -> 60000 | F94: =E94+F78 -> 60000 | G94: =F94+G78 -> 60000 | H94: =G94+H78 -> 60000 | I94: =H94+I78 -> 60000 | J94: =I94+J78 -> 60000 | K94: =J94+K78 -> 60000 | ... BJ94: =BI94+BJ78 -> 60000
A95: Retained earnings | C95: =C52 -> -15440.159 | D95: =C95+D52 -> -27486.699 | E95: =D95+E52 -> -36134.896 | F95: =E95+F52 -> -41384.751 | G95: =F95+G52 -> -46625.161 | H95: =G95+H52 -> -51856.127 | I95: =H95+I52 -> -57077.649 | J95: =I95+J52 -> -62289.726 | K95: =J95+K52 -> -67492.359 | ... BJ95: =BI95+BJ52 -> -333349.89
A96: Total assets | C96: =C82+C68+C69+C59 -> 143537.54 | D96: =D82+D68+D69+D59 -> 131313.19 | E96: =E82+E68+E69+E59 -> 122487.18 | F96: =F82+F68+F69+F59 -> 117059.51 | G96: =G82+G68+G69+G59 -> 110485.77 | H96: =H82+H68+H69+H59 -> 103921.47 | I96: =I82+I68+I69+I59 -> 97366.613 | J96: =J82+J68+J69+J59 -> 90821.202 | ... BJ96: =BJ82+BJ68+BJ69+BJ59 -> -239998.09
A97: Total liabilities | C97: =C70+C65 -> 98977.695 | D97: =D70+D65 -> 98799.884 | E97: =E70+E65 -> 98622.073 | F97: =F70+F65 -> 98444.262 | G97: =G70+G65 -> 97110.928 | H97: =H70+H65 -> 95777.595 | I97: =I70+I65 -> 94444.262 | J97: =J70+J65 -> 93110.928 | ... BJ97: =BJ70+BJ65 -> 33351.803
A98: Total equity | C98: =C94+C95 -> 44559.841 | D98: =D94+D95 -> 32513.301 | E98: =E94+E95 -> 23865.104 | F98: =F94+F95 -> 18615.249 | G98: =G94+G95 -> 13374.839 | H98: =H94+H95 -> 8143.8726 | I98: =I94+I95 -> 2922.3509 | J98: =J94+J95 -> -2289.7263 | ... BJ98: =BJ94+BJ95 -> -273349.89
A99: Total liabilities & equity | C99: =C97+C98 -> 143537.54 | D99: =D97+D98 -> 131313.19 | E99: =E97+E98 -> 122487.18 | F99: =F97+F98 -> 117059.51 | G99: =G97+G98 -> 110485.77 | H99: =H97+H98 -> 103921.47 | I99: =I97+I98 -> 97366.613 | J99: =J97+J98 -> 90821.202 | ... BJ99: =BJ97+BJ98 -> -239998.09
A100: Check: assets − liabilities − equity | C100: =C96-C99 -> 0 | D100: =D96-D99 -> 0 | E100: =E96-E99 -> 0 | F100: =F96-F99 -> 0 | G100: =G96-G99 -> 0 | H100: =H96-H99 -> 0 | I100: =I96-I99 -> 0 | J100: =J96-J99 -> 0 | ... BJ100: =BJ96-BJ99 -> 0
A102: Headcount (FTE)
A103: Bakers & production — FTE | C103: =Inputs!$B$42*(1+Inputs!$B$44)^(C$7-1)*MAX(0,MIN(1,C$6*1-Inputs!$B$45+1))/1 -> 5 | D103: =Inputs!$B$42*(1+Inputs!$B$44)^(D$7-1)*MAX(0,MIN(1,D$6*1-Inputs!$B$45+1))/1 -> 5 | E103: =Inputs!$B$42*(1+Inputs!$B$44)^(E$7-1)*MAX(0,MIN(1,E$6*1-Inputs!$B$45+1))/1 -> 5 | F103: =Inputs!$B$42*(1+Inputs!$B$44)^(F$7-1)*MAX(0,MIN(1,F$6*1-Inputs!$B$45+1))/1 -> 5 | G103: =Inputs!$B$42*(1+Inputs!$B$44)^(G$7-1)*MAX(0,MIN(1,G$6*1-Inputs!$B$45+1))/1 -> 5 | H103: =Inputs!$B$42*(1+Inputs!$B$44)^(H$7-1)*MAX(0,MIN(1,H$6*1-Inputs!$B$45+1))/1 -> 5 | I103: =Inputs!$B$42*(1+Inputs!$B$44)^(I$7-1)*MAX(0,MIN(1,I$6*1-Inputs!$B$45+1))/1 -> 5 | J103: =Inputs!$B$42*(1+Inputs!$B$44)^(J$7-1)*MAX(0,MIN(1,J$6*1-Inputs!$B$45+1))/1 -> 5 | ... BJ103: =Inputs!$B$42*(1+Inputs!$B$44)^(BJ$7-1)*MAX(0,MIN(1,BJ$6*1-Inputs!$B$45+1))/1 -> 6.3123848
A104: Counter staff — FTE | C104: =Inputs!$B$46*(1+Inputs!$B$48)^(C$7-1)*MAX(0,MIN(1,C$6*1-Inputs!$B$49+1))/1 -> 7 | D104: =Inputs!$B$46*(1+Inputs!$B$48)^(D$7-1)*MAX(0,MIN(1,D$6*1-Inputs!$B$49+1))/1 -> 7 | E104: =Inputs!$B$46*(1+Inputs!$B$48)^(E$7-1)*MAX(0,MIN(1,E$6*1-Inputs!$B$49+1))/1 -> 7 | F104: =Inputs!$B$46*(1+Inputs!$B$48)^(F$7-1)*MAX(0,MIN(1,F$6*1-Inputs!$B$49+1))/1 -> 7 | G104: =Inputs!$B$46*(1+Inputs!$B$48)^(G$7-1)*MAX(0,MIN(1,G$6*1-Inputs!$B$49+1))/1 -> 7 | H104: =Inputs!$B$46*(1+Inputs!$B$48)^(H$7-1)*MAX(0,MIN(1,H$6*1-Inputs!$B$49+1))/1 -> 7 | I104: =Inputs!$B$46*(1+Inputs!$B$48)^(I$7-1)*MAX(0,MIN(1,I$6*1-Inputs!$B$49+1))/1 -> 7 | J104: =Inputs!$B$46*(1+Inputs!$B$48)^(J$7-1)*MAX(0,MIN(1,J$6*1-Inputs!$B$49+1))/1 -> 7 | ... BJ104: =Inputs!$B$46*(1+Inputs!$B$48)^(BJ$7-1)*MAX(0,MIN(1,BJ$6*1-Inputs!$B$49+1))/1 -> 8.8373387
A105: Manager — FTE | C105: =Inputs!$B$50*(1+Inputs!$B$52)^(C$7-1)*MAX(0,MIN(1,C$6*1-Inputs!$B$53+1))/1 -> 1.5 | D105: =Inputs!$B$50*(1+Inputs!$B$52)^(D$7-1)*MAX(0,MIN(1,D$6*1-Inputs!$B$53+1))/1 -> 1.5 | E105: =Inputs!$B$50*(1+Inputs!$B$52)^(E$7-1)*MAX(0,MIN(1,E$6*1-Inputs!$B$53+1))/1 -> 1.5 | F105: =Inputs!$B$50*(1+Inputs!$B$52)^(F$7-1)*MAX(0,MIN(1,F$6*1-Inputs!$B$53+1))/1 -> 1.5 | G105: =Inputs!$B$50*(1+Inputs!$B$52)^(G$7-1)*MAX(0,MIN(1,G$6*1-Inputs!$B$53+1))/1 -> 1.5 | H105: =Inputs!$B$50*(1+Inputs!$B$52)^(H$7-1)*MAX(0,MIN(1,H$6*1-Inputs!$B$53+1))/1 -> 1.5 | I105: =Inputs!$B$50*(1+Inputs!$B$52)^(I$7-1)*MAX(0,MIN(1,I$6*1-Inputs!$B$53+1))/1 -> 1.5 | J105: =Inputs!$B$50*(1+Inputs!$B$52)^(J$7-1)*MAX(0,MIN(1,J$6*1-Inputs!$B$53+1))/1 -> 1.5 | ... BJ105: =Inputs!$B$50*(1+Inputs!$B$52)^(BJ$7-1)*MAX(0,MIN(1,BJ$6*1-Inputs!$B$53+1))/1 -> 1.5
A106: Total FTE | C106: =C103+C104+C105 -> 13.5 | D106: =D103+D104+D105 -> 13.5 | E106: =E103+E104+E105 -> 13.5 | F106: =F103+F104+F105 -> 13.5 | G106: =G103+G104+G105 -> 13.5 | H106: =H103+H104+H105 -> 13.5 | I106: =I103+I104+I105 -> 13.5 | J106: =J103+J104+J105 -> 13.5 | ... BJ106: =BJ103+BJ104+BJ105 -> 16.649724
A108: Payroll cost (salary + taxes & benefits)
A109: Bakers & production — payroll cost | C109: =-C103*Inputs!$B$43/12*1*(1+Inputs!$B$54)*(1+Inputs!$B$55)^(C$7-1) -> -20533.333 | D109: =-D103*Inputs!$B$43/12*1*(1+Inputs!$B$54)*(1+Inputs!$B$55)^(D$7-1) -> -20533.333 | E109: =-E103*Inputs!$B$43/12*1*(1+Inputs!$B$54)*(1+Inputs!$B$55)^(E$7-1) -> -20533.333 | F109: =-F103*Inputs!$B$43/12*1*(1+Inputs!$B$54)*(1+Inputs!$B$55)^(F$7-1) -> -20533.333 | G109: =-G103*Inputs!$B$43/12*1*(1+Inputs!$B$54)*(1+Inputs!$B$55)^(G$7-1) -> -20533.333 | H109: =-H103*Inputs!$B$43/12*1*(1+Inputs!$B$54)*(1+Inputs!$B$55)^(H$7-1) -> -20533.333 | I109: =-I103*Inputs!$B$43/12*1*(1+Inputs!$B$54)*(1+Inputs!$B$55)^(I$7-1) -> -20533.333 | J109: =-J103*Inputs!$B$43/12*1*(1+Inputs!$B$54)*(1+Inputs!$B$55)^(J$7-1) -> -20533.333 | ... BJ109: =-BJ103*Inputs!$B$43/12*1*(1+Inputs!$B$54)*(1+Inputs!$B$55)^(BJ$7-1) -> -29176.408
A110: Counter staff — payroll cost | C110: =-C104*Inputs!$B$47/12*1*(1+Inputs!$B$54)*(1+Inputs!$B$55)^(C$7-1) -> -20253.333 | D110: =-D104*Inputs!$B$47/12*1*(1+Inputs!$B$54)*(1+Inputs!$B$55)^(D$7-1) -> -20253.333 | E110: =-E104*Inputs!$B$47/12*1*(1+Inputs!$B$54)*(1+Inputs!$B$55)^(E$7-1) -> -20253.333 | F110: =-F104*Inputs!$B$47/12*1*(1+Inputs!$B$54)*(1+Inputs!$B$55)^(F$7-1) -> -20253.333 | G110: =-G104*Inputs!$B$47/12*1*(1+Inputs!$B$54)*(1+Inputs!$B$55)^(G$7-1) -> -20253.333 | H110: =-H104*Inputs!$B$47/12*1*(1+Inputs!$B$54)*(1+Inputs!$B$55)^(H$7-1) -> -20253.333 | I110: =-I104*Inputs!$B$47/12*1*(1+Inputs!$B$54)*(1+Inputs!$B$55)^(I$7-1) -> -20253.333 | J110: =-J104*Inputs!$B$47/12*1*(1+Inputs!$B$54)*(1+Inputs!$B$55)^(J$7-1) -> -20253.333 | ... BJ110: =-BJ104*Inputs!$B$47/12*1*(1+Inputs!$B$54)*(1+Inputs!$B$55)^(BJ$7-1) -> -28778.547
A111: Manager — payroll cost | C111: =-C105*Inputs!$B$51/12*1*(1+Inputs!$B$54)*(1+Inputs!$B$55)^(C$7-1) -> -8680 | D111: =-D105*Inputs!$B$51/12*1*(1+Inputs!$B$54)*(1+Inputs!$B$55)^(D$7-1) -> -8680 | E111: =-E105*Inputs!$B$51/12*1*(1+Inputs!$B$54)*(1+Inputs!$B$55)^(E$7-1) -> -8680 | F111: =-F105*Inputs!$B$51/12*1*(1+Inputs!$B$54)*(1+Inputs!$B$55)^(F$7-1) -> -8680 | G111: =-G105*Inputs!$B$51/12*1*(1+Inputs!$B$54)*(1+Inputs!$B$55)^(G$7-1) -> -8680 | H111: =-H105*Inputs!$B$51/12*1*(1+Inputs!$B$54)*(1+Inputs!$B$55)^(H$7-1) -> -8680 | I111: =-I105*Inputs!$B$51/12*1*(1+Inputs!$B$54)*(1+Inputs!$B$55)^(I$7-1) -> -8680 | J111: =-J105*Inputs!$B$51/12*1*(1+Inputs!$B$54)*(1+Inputs!$B$55)^(J$7-1) -> -8680 | ... BJ111: =-BJ105*Inputs!$B$51/12*1*(1+Inputs!$B$54)*(1+Inputs!$B$55)^(BJ$7-1) -> -9769.4165
A112: Total payroll | C112: =C109+C110+C111 -> -49466.667 | D112: =D109+D110+D111 -> -49466.667 | E112: =E109+E110+E111 -> -49466.667 | F112: =F109+F110+F111 -> -49466.667 | G112: =G109+G110+G111 -> -49466.667 | H112: =H109+H110+H111 -> -49466.667 | I112: =I109+I110+I111 -> -49466.667 | J112: =J109+J110+J111 -> -49466.667 | ... BJ112: =BJ109+BJ110+BJ111 -> -67724.372
A115: Base scenario — reads Inputs column C
A116: Month | C116: M1 | D116: M2 | E116: M3 | F116: M4 | G116: M5 | H116: M6 | I116: M7 | J116: M8 | K116: M9 | L116: M10 | M116: M11 | N116: M12 | O116: M13 | P116: M14 | Q116: M15 | R116: M16 | S116: M17 | T116: M18 | U116: M19 | V116: M20 | W116: M21 | X116: M22 | Y116: M23 | Z116: M24 | AA116: M25 | AB116: M26 | AC116: M27 | AD116: M28 | AE116: M29 | AF116: M30 | AG116: M31 | AH116: M32 | AI116: M33 | AJ116: M34 | AK116: M35 | AL116: M36 | AM116: M37 | AN116: M38 | AO116: M39 | AP116: M40 | AQ116: M41 | AR116: M42 | AS116: M43 | AT116: M44 | AU116: M45 | AV116: M46 | AW116: M47 | AX116: M48 | AY116: M49 | AZ116: M50 | BA116: M51 | BB116: M52 | BC116: M53 | BD116: M54 | BE116: M55 | BF116: M56 | BG116: M57 | BH116: M58 | BI116: M59 | BJ116: M60
A117: Period # | C117: 1 | D117: 2 | E117: 3 | F117: 4 | G117: 5 | H117: 6 | I117: 7 | J117: 8 | K117: 9 | L117: 10 | M117: 11 | N117: 12 | O117: 13 | P117: 14 | Q117: 15 | R117: 16 | S117: 17 | T117: 18 | U117: 19 | V117: 20 | W117: 21 | X117: 22 | Y117: 23 | Z117: 24 | AA117: 25 | AB117: 26 | AC117: 27 | AD117: 28 | AE117: 29 | AF117: 30 | AG117: 31 | AH117: 32 | AI117: 33 | AJ117: 34 | AK117: 35 | AL117: 36 | AM117: 37 | AN117: 38 | AO117: 39 | AP117: 40 | AQ117: 41 | AR117: 42 | AS117: 43 | AT117: 44 | AU117: 45 | AV117: 46 | AW117: 47 | AX117: 48 | AY117: 49 | AZ117: 50 | BA117: 51 | BB117: 52 | BC117: 53 | BD117: 54 | BE117: 55 | BF117: 56 | BG117: 57 | BH117: 58 | BI117: 59 | BJ117: 60
...

Sheet Checks
A1: Model checks | E1: =HYPERLINK("#'Cover'!A1","◂ Contents") -> ◂ Contents
A2: Live formulas: they re-run every time an input changes.
A3: Check | B3: Result | C3: What it tests
A4: Annual revenue ties to period detail | B4: =IF(ABS(SUM('P&L'!$B$5:$F$5)-SUM(Monthly!$C$22:$BJ$22))<0.5,"PASS","FAIL") -> PASS | C4: Sum of annual revenue equals the sum of every period
A5: Annual net income ties to period detail | B5: =IF(ABS(SUM('P&L'!$B$25:$F$25)-SUM(Monthly!$C$50:$BJ$50))<0.5,"PASS","FAIL") -> PASS | C5: Sum of annual net income equals the sum of every period
A6: EBITDA reconciliation | B6: =IF(ABS(SUM(Monthly!$C$41:$BJ$41)-SUM(Monthly!$C$29:$BJ$29)-SUM(Monthly!$C$40:$BJ$40))<0.5,"PASS","FAIL") -> PASS | C6: EBITDA = gross profit + operating expenses (costs are negative)
A7: Cash roll-forward | B7: =IF(ABS(INDEX(Monthly!$C$80:$BJ$80,60)-SUM(Monthly!$C$78:$BJ$78))<0.5,"PASS","FAIL") -> PASS | C7: Closing cash = all net cash flows since the start (opening cash is zero)
A8: Scenario selector valid | B8: =IF(AND(ISNUMBER(Dashboard!B4),Dashboard!B4>=1,Dashboard!B4<=3,INT(Dashboard!B4)=Dashboard!B4),"PASS","FAIL") -> PASS | C8: Dashboard!B4 is 1, 2 or 3
A9: Scenario ordering of drivers | B9: =IF(AND(Inputs!$B$7<=Inputs!$C$7,Inputs!$C$7<=Inputs!$D$7,Inputs!$B$8>=Inputs!$C$8,Inputs!$C$8>=Inputs!$D$8,Inputs!$B$9<=Inputs!$C$9,Inputs!$C$9<=Inputs!$D$9,Inputs!$B$10<=Inputs!$C$10,Inputs!$C$10<=Inputs!$D$10,Inputs!$B$11<=Inputs!$C$11,Inputs!$C$11<=Inputs!$D$11,Inputs!$B$12<=Inputs!$C$12,Inputs!$C$12<=Inputs!$D$12,Inputs!$B$17<=Inputs!$C$17,Inputs!$C$17<=Inputs!$D$17,Inputs!$B$18<=Inputs!$C$18,Inputs!$C$18<=Inputs!$D$18,Inputs!$B$19<=Inputs!$C$19,Inputs!$C$19<=Inputs!$D$19,Inputs!$B$21>=Inputs!$C$21,Inputs!$C$21>=Inputs!$D$21,Inputs!$B$24>=Inputs!$C$24,Inputs!$C$24>=Inputs!$D$24,Inputs!$B$25>=Inputs!$C$25,Inputs!$C$25>=Inputs!$D$25,Inputs!$B$26>=Inputs!$C$26,Inputs!$C$26>=Inputs!$D$26,Inputs!$B$27>=Inputs!$C$27,Inputs!$C$27>=Inputs!$D$27,Inputs!$B$33>=Inputs!$C$33,Inputs!$C$33>=Inputs!$D$33,Inputs!$B$34>=Inputs!$C$34,Inputs!$C$34>=Inputs!$D$34,Inputs!$B$42<=Inputs!$C$42,Inputs!$C$42<=Inputs!$D$42,Inputs!$B$44<=Inputs!$C$44,Inputs!$C$44<=Inputs!$D$44,Inputs!$B$46<=Inputs!$C$46,Inputs!$C$46<=Inputs!$D$46,Inputs!$B$48<=Inputs!$C$48,Inputs!$C$48<=Inputs!$D$48,Inputs!$B$50<=Inputs!$C$50,Inputs!$C$50<=Inputs!$D$50,Inputs!$B$52<=Inputs!$C$52,Inputs!$C$52<=Inputs!$D$52,Inputs!$B$76>=Inputs!$C$76,Inputs!$C$76>=Inputs!$D$76,Inputs!$B$77<=Inputs!$C$77,Inputs!$C$77<=Inputs!$D$77,Inputs!$B$78<=Inputs!$C$78,Inputs!$C$78<=Inputs!$D$78),"PASS","FAIL") -> PASS | C9: Low / Base / High ordered the right way for every growth and cost driver
A10: Gross margin within 0–100% | B10: =IF(AND(MIN('P&L'!$B$8:$F$8)>=0,MAX('P&L'!$B$8:$F$8)<=1),"PASS","FAIL") -> PASS | C10: Gross margin never negative or above 100%
A11: Loan balance never negative | B11: =IF(MIN(Monthly!$C$63:$BJ$63)>=-0.5,"PASS","FAIL") -> PASS | C11: Repayments never exceed the loan
A12: Funding table ties to the cash flow | B12: =IF(ABS('Break-even'!B18-('Break-even'!B16-'Break-even'!B10))<0.5,"PASS","FAIL") -> PASS | C12: Lowest cash balance = sources of funds − uses of funds up to that point
A13: Valuation: discounting ties to NPV() | B13: =IF(ABS(Valuation!B23-NPV(Valuation!B6,Valuation!$B$17:$F$17))<0.5,"PASS","FAIL") -> PASS | C13: Sum of discounted free cash flows equals Excel's NPV of the same flows
A14: Valuation: WACC above terminal growth | B14: =IF(Valuation!B6>Valuation!B7,"PASS","FAIL") -> PASS | C14: The perpetual-growth formula needs WACC > g
A15: Valuation: sensitivity centre = enterprise value | B15: =IF(ABS(Valuation!D36-Valuation!B27)<0.5,"PASS","FAIL") -> PASS | C15: The middle of the WACC × growth table reproduces the headline value
A16: Valuation: final-year cash flow positive | B16: =IF(Valuation!$F$17>0,"PASS","WARN") -> PASS | C16: Business warning: a negative final-year cash flow gives a negative terminal value (often a 1-year plan still carrying start-up spending)
A17: Sources & uses balance | B17: =IF(ABS('Sources & Uses'!B21-'Sources & Uses'!B28)<0.5,"PASS","FAIL") -> PASS | C17: Sources of funds = uses of funds (incl. cash at the end) for the Sources & Uses period
A18: No error values | B18: =IF(SUMPRODUCT(--ISERROR(Monthly!$C$4:$BJ$98))+SUMPRODUCT(--ISERROR(Headcount!$C$4:$BJ$17))+SUMPRODUCT(--ISERROR('P&L'!$B$3:$F$26))+SUMPRODUCT(--ISERROR('Cash Flow'!$B$3:$F$18))+SUMPRODUCT(--ISERROR('Balance Sheet'!$B$3:$F$17))+SUMPRODUCT(--ISERROR(KPIs!$B$27:$F$48))+SUMPRODUCT(--ISERROR('Break-even'!$B$26:$F$33))+SUMPRODUCT(--ISERROR(Valuation!$B$14:$F$19))+SUMPRODUCT(--ISERROR('Break-even'!$B$3:$F$35))+SUMPRODUCT(--ISERROR(Valuation!$A$3:$F$40))+SUMPRODUCT(--ISERROR('Sources & Uses'!$B$3:$C$30))+SUMPRODUCT(--ISERROR(Dashboard!$A$6:$W$44))+SUMPRODUCT(--ISERROR(Summary!$A$5:$S$52))+SUMPRODUCT(--ISERROR(KPIs!$A$4:$G$48))+SUMPRODUCT(--ISERROR('Scenario calc'!$C$6:$BJ$112))+SUMPRODUCT(--ISERROR('Scenario calc'!$C$117:$BJ$223))+SUMPRODUCT(--ISERROR('Scenario calc'!$C$228:$BJ$334))+SUMPRODUCT(--ISERROR(Scenarios!$B$5:$F$51))=0,"PASS","FAIL") -> PASS | C18: No error values (divide-by-zero, broken references) on any calculation sheet
A19: Summary ties to statements | B19: =IF(IFERROR(AND(SUMPRODUCT(--(ABS(Summary!$B$7:$F$7-'P&L'!$B$5:$F$5)>0.5))=0,SUMPRODUCT(--(ABS(Summary!$B$19:$F$19-'P&L'!$B$25:$F$25)>0.5))=0,SUMPRODUCT(--(ABS(Summary!$B$31:$F$31-'Cash Flow'!$B$18:$F$18)>0.5))=0,SUMPRODUCT(--(ABS(Summary!$B$41:$F$41-'Balance Sheet'!$B$5:$F$5)>0.5))=0,ABS(SUM(Summary!$H$7:$S$7)-INDEX(Summary!$B$7:$F$7,Summary!$R$2))<0.5,ABS(SUM(Summary!$H$19:$S$19)-INDEX(Summary!$B$19:$F$19,Summary!$R$2))<0.5,ABS(Summary!$S$31-INDEX(Summary!$B$31:$F$31,Summary!$R$2))<0.5),FALSE()),"PASS","FAIL") -> PASS | C19: Summary revenue, net income and closing cash equal the statements every year; the detailed year adds up to its annual figure
A20: DuPont ties to return on equity | B20: =IF(SUMPRODUCT(--(ABS(KPIs!$B$24:$F$24)>0.000000001))>0,"FAIL",IF(SUMPRODUCT(ISNUMBER(KPIs!$B$23:$F$23)*ISNUMBER(KPIs!$B$16:$F$16))=0,"n/a","PASS")) -> PASS | C20: Net margin × asset turnover × equity multiplier equals return on equity every year; n/a = no year where both are defined (a one-sided n/a is a FAIL)
A21: Scenarios: Active = selected scenario | B21: =IF(IFERROR(AND(ABS(Scenarios!E18-INDEX(Scenarios!B18:D18,1,Dashboard!$B$4))<0.5,ABS(Scenarios!E19-INDEX(Scenarios!B19:D19,1,Dashboard!$B$4))<0.5,ABS(Scenarios!E20-INDEX(Scenarios!B20:D20,1,Dashboard!$B$4))<0.5,ABS(Scenarios!E21-INDEX(Scenarios!B21:D21,1,Dashboard!$B$4))<0.000001,ABS(Scenarios!E22-INDEX(Scenarios!B22:D22,1,Dashboard!$B$4))<0.5,ABS(Scenarios!E23-INDEX(Scenarios!B23:D23,1,Dashboard!$B$4))<0.5,ABS(Scenarios!E24-INDEX(Scenarios!B24:D24,1,Dashboard!$B$4))<0.5,ABS(Scenarios!E25-INDEX(Scenarios!B25:D25,1,Dashboard!$B$4))<0.5,ABS(Scenarios!E26-INDEX(Scenarios!B26:D26,1,Dashboard!$B$4))<0.5,ABS(Scenarios!E27-INDEX(Scenarios!B27:D27,1,Dashboard!$B$4))<0.5),FALSE()),"PASS","FAIL") -> PASS | C21: On the Scenarios sheet the live model (Active) equals the Low / Base / High column chosen on the Dashboard for every output
A22: Balance sheet balances every period | B22: =IF(SUMPRODUCT(--(ABS(Monthly!$C$98:$BJ$98)>0.5))=0,"PASS","FAIL") -> PASS | C22: Assets = liabilities + equity in every period
A23: Funding sufficient (cash ≥ 0) | B23: =IF(MIN(Monthly!$C$80:$BJ$80)>=0,"PASS","WARN") -> PASS | C23: Business warning, not an error: cash dips below zero in this scenario
A25: Overall verdict | B25: =IF(COUNTIF(B4:B23,"FAIL")>0,"FAIL",IF(COUNTIF(B4:B23,"WARN")>0,"PASS WITH WARNINGS","PASS")) -> PASS
