Workbook

Sheet Cover
B2: Neighborhood Cafe — Financial Plan
B3: 3-year financial model · monthly detail · Low / Base / High scenarios · US dollars · Light plan
B5: Purpose | D5: Revenue and profit plan
B6: Active scenario | D6: =Dashboard!C4&" (change it on the Dashboard, cell B4)" -> Base (change it on the Dashboard, cell B4)
B7: Model checks | D7: =Checks!B16 -> PASS
B8: Prepared | D8: 22 October 2026
B10: Contents
C11: PRESENTATION
B12: 1 | C12: =HYPERLINK("#Dashboard!A1","Dashboard") -> Dashboard | D12: Scenario switch, key numbers, core financials
B13: 2 | C13: =HYPERLINK("#'Break-even'!A1","Break-even") -> Break-even | D13: Startup costs, funding need, break-even timing and revenue
C14: INPUTS
B15: 3 | C15: =HYPERLINK("#Inputs!A1","Inputs") -> Inputs | D15: Every assumption, Low / Base / High, with units and comments
C16: STATEMENTS
B17: 4 | C17: =HYPERLINK("#'P&L'!A1","P&L") -> P&L | D17: Annual profit & loss
C18: CONTROL
B19: 5 | C19: =HYPERLINK("#Checks!A1","Checks") -> Checks | D19: Live integrity checks and the overall verdict
B21: How to read this file
C22: 1000 | D22: Input you can change — yellow cell with a blue figure (Inputs sheet and the view switches)
C23: 1000 | D23: Formula — calculated, do not overwrite
C24: 1000 | D24: Link to another sheet
C25: 1000 | D25: Active value the model uses (follows the scenario)

Sheet Dashboard
A1: Dashboard | W1: =HYPERLINK("#'Cover'!A1","◂ Contents") -> ◂ Contents
A2: Neighborhood Cafe — Financial Plan
A4: Active scenario | B4: 2 | C4: =CHOOSE(B4,"Low","Base","High") -> Base | D4: 1 = Low · 2 = Base · 3 = High — every sheet follows this cell | S4: Model checks | T4: =Checks!B16 -> PASS
A6: REVENUE · YEAR 3 | C6: EBITDA MARGIN · YEAR 3 | H6: NET INCOME · YEAR 3 | L6: LOWEST CASH BALANCE | P6: FUNDING REQUIRED | T6: FIRST MONTH WITH POSITIVE EBITDA
A7: =D12 -> 446295 | C7: =D17 -> 0.16704087 | H7: =D18 -> 38334.239 | L7: =F37 -> 33683.978 | P7: =F35 -> 239316.02 | T7: =F38 -> 6
A8: =IF(AND(B12>0,D12>=0),(D12/B12)^(1/2)-1,"CAGR n/a") -> 0.18133149 | C8: =D16 -> 74549.503 | H8: =D19 -> 0.085894396 | L8: ='Break-even'!B6 -> 6 | P8: =IF(F36>=0,"Covered by funding raised",-F36) -> 19316.022 | T8: =IF(ISNUMBER('Break-even'!B22),"Net income positive from month "&'Break-even'!B22,"Net income not positive within horizon") -> Net income positive from month 7
A10: Core financials ($'000) — active scenario
B11: 1 | C11: 2 | D11: 3
A12: Revenue | B12: =SUMIF('P&L'!$C$27:$AL$27,B$11,'P&L'!$C$34:$AL$34) -> 319800 | C12: =SUMIF('P&L'!$C$27:$AL$27,C$11,'P&L'!$C$34:$AL$34) -> 408769.92 | D12: =SUMIF('P&L'!$C$27:$AL$27,D$11,'P&L'!$C$34:$AL$34) -> 446295
A13: Gross profit | B13: =SUMIF('P&L'!$C$27:$AL$27,B$11,'P&L'!$C$36:$AL$36) -> 214266 | C13: =SUMIF('P&L'!$C$27:$AL$27,C$11,'P&L'!$C$36:$AL$36) -> 273875.85 | D13: =SUMIF('P&L'!$C$27:$AL$27,D$11,'P&L'!$C$36:$AL$36) -> 299017.65
A14: Gross margin | B14: =IF(B12=0,0,B13/B12) -> 0.67 | C14: =IF(C12=0,0,C13/C12) -> 0.67 | D14: =IF(D12=0,0,D13/D12) -> 0.67
A15: Operating expenses | B15: =SUMIF('P&L'!$C$27:$AL$27,B$11,'P&L'!$C$43:$AL$43) -> -213034 | C15: =SUMIF('P&L'!$C$27:$AL$27,C$11,'P&L'!$C$43:$AL$43) -> -219466.3 | D15: =SUMIF('P&L'!$C$27:$AL$27,D$11,'P&L'!$C$43:$AL$43) -> -224468.15
A16: EBITDA | B16: =SUMIF('P&L'!$C$27:$AL$27,B$11,'P&L'!$C$44:$AL$44) -> 1232 | C16: =SUMIF('P&L'!$C$27:$AL$27,C$11,'P&L'!$C$44:$AL$44) -> 54409.549 | D16: =SUMIF('P&L'!$C$27:$AL$27,D$11,'P&L'!$C$44:$AL$44) -> 74549.503
A17: EBITDA margin | B17: =IF(B12=0,0,B16/B12) -> 0.0038524078 | C17: =IF(C12=0,0,C16/C12) -> 0.13310556 | D17: =IF(D12=0,0,D16/D12) -> 0.16704087
A18: Net income | B18: =SUMIF('P&L'!$C$27:$AL$27,B$11,'P&L'!$C$53:$AL$53) -> -27487.365 | C18: =SUMIF('P&L'!$C$27:$AL$27,C$11,'P&L'!$C$53:$AL$53) -> 26965.739 | D18: =SUMIF('P&L'!$C$27:$AL$27,D$11,'P&L'!$C$53:$AL$53) -> 38334.239
A19: Net margin | B19: =IF(B12=0,0,B18/B12) -> -0.085951736 | C19: =IF(C12=0,0,C18/C12) -> 0.065968013 | D19: =IF(D12=0,0,D18/D12) -> 0.085894396
A20: Operating cash flow | B20: =SUMIF('P&L'!$C$27:$AL$27,B$11,'P&L'!$C$77:$AL$77) -> -4307.8222 | C20: =SUMIF('P&L'!$C$27:$AL$27,C$11,'P&L'!$C$77:$AL$77) -> 49852.478 | D20: =SUMIF('P&L'!$C$27:$AL$27,D$11,'P&L'!$C$77:$AL$77) -> 61223.695
A21: Investing cash flow | B21: =SUMIF('P&L'!$C$27:$AL$27,B$11,'P&L'!$C$78:$AL$78) -> -160000 | C21: =SUMIF('P&L'!$C$27:$AL$27,C$11,'P&L'!$C$78:$AL$78) -> 0 | D21: =SUMIF('P&L'!$C$27:$AL$27,D$11,'P&L'!$C$78:$AL$78) -> 0
A22: Financing cash flow | B22: =SUMIF('P&L'!$C$27:$AL$27,B$11,'P&L'!$C$80:$AL$80) -> 205333.33 | C22: =SUMIF('P&L'!$C$27:$AL$27,C$11,'P&L'!$C$80:$AL$80) -> -16000 | D22: =SUMIF('P&L'!$C$27:$AL$27,D$11,'P&L'!$C$80:$AL$80) -> -16000
A23: Net change in cash | B23: =SUMIF('P&L'!$C$27:$AL$27,B$11,'P&L'!$C$81:$AL$81) -> 41025.511 | C23: =SUMIF('P&L'!$C$27:$AL$27,C$11,'P&L'!$C$81:$AL$81) -> 33852.478 | D23: =SUMIF('P&L'!$C$27:$AL$27,D$11,'P&L'!$C$81:$AL$81) -> 45223.695
A24: Year-end cash | B24: =INDEX('P&L'!$C$83:$AL$83,B$11*12) -> 41025.511 | C24: =INDEX('P&L'!$C$83:$AL$83,C$11*12) -> 74877.99 | D24: =INDEX('P&L'!$C$83:$AL$83,D$11*12) -> 120101.69
A26: Cafe metrics
B27: 1 | C27: 2 | D27: 3
A28: Customers per day (year end) | B28: =INDEX('P&L'!$C$31:$AL$31,B$27*12) -> 160 | C28: =INDEX('P&L'!$C$31:$AL$31,C$27*12) -> 169.6 | D28: =INDEX('P&L'!$C$31:$AL$31,D$27*12) -> 179.776
A29: Average ticket (year end) | B29: =INDEX('P&L'!$C$32:$AL$32,B$27*12) -> 6.5 | C29: =INDEX('P&L'!$C$32:$AL$32,C$27*12) -> 6.695 | D29: =INDEX('P&L'!$C$32:$AL$32,D$27*12) -> 6.89585
A30: Team (FTE, year end) | B30: =INDEX('P&L'!$C$95:$AL$95,B$27*12) -> 3.5 | C30: =INDEX('P&L'!$C$95:$AL$95,C$27*12) -> 3.5 | D30: =INDEX('P&L'!$C$95:$AL$95,D$27*12) -> 3.5
A32: Funding & valuation ($'000) — active scenario
A33: Equity raised | F33: =Inputs!$E$29 -> 140000
A34: Loan drawn | F34: =Inputs!$E$30 -> 80000
A35: Funding required (incl. cash buffer) | F35: ='Break-even'!B12 -> 239316.02
A36: Funding surplus / (shortfall) | F36: ='Break-even'!B17 -> -19316.022
A37: ="Lowest cash balance (month "&'Break-even'!B6&")" -> Lowest cash balance (month 6) | F37: ='Break-even'!B18 -> 33683.978
A38: First month with positive EBITDA | F38: ='Break-even'!B21 -> 6
A39: Cash invested paid back | F39: ='Break-even'!B23 -> Not within horizon

Sheet Break-even
A1: Startup costs, funding need and break-even | F1: =HYPERLINK("#'Cover'!A1","◂ Contents") -> ◂ Contents
A2: Live for the selected scenario. Periods are counted in months from the start of the plan.
A3: Scenario shown | B3: =CHOOSE(Dashboard!$B$4,"Low","Base","High") -> Base
A5: Startup costs & funding need (up to the lowest cash point)
A6: Lowest cash point (month #) | B6: =MATCH(MIN('P&L'!$C$83:$AL$83),'P&L'!$C$83:$AL$83,0) -> 6
A7: Capital spending up to the lowest cash point | B7: =SUMPRODUCT(--('P&L'!$C$26:$AL$26<=$B$6),'P&L'!$C$56:$AL$56) -> 160000
A8: Operating cash burn up to the lowest cash point | B8: =-SUMPRODUCT(--('P&L'!$C$26:$AL$26<=$B$6),'P&L'!$C$77:$AL$77) -> 19649.356 | D8: Losses and working capital before the business funds itself
A9: Loan repayments up to the lowest cash point | B9: =-SUMPRODUCT(--('P&L'!$C$26:$AL$26<=$B$6),'P&L'!$C$65:$AL$65) -> 6666.6667
A10: Total uses of funds | B10: =B7+B8+B9 -> 186316.02
A11: Minimum cash buffer to keep | B11: =Inputs!$E$44 -> 53000 | D11: Input on the Inputs sheet
A12: Funding required (uses + buffer) | B12: =B10+B11 -> 239316.02
A14: Equity raised | B14: =Inputs!$E$29 -> 140000
A15: Loan drawn | B15: =Inputs!$E$30 -> 80000
A16: Total sources of funds | B16: =B14+B15 -> 220000
A17: Funding surplus / (shortfall) | B17: =B16-B12 -> -19316.022 | D17: Negative = raise at least this much more
A18: Lowest cash balance in the plan | B18: =MIN('P&L'!$C$83:$AL$83) -> 33683.978 | D18: Equals sources minus uses
A20: Break-even timing
A21: First month with positive EBITDA (month #) | B21: =IFERROR(MATCH(1,'P&L'!$C$84:$AL$84,0),"Not within horizon") -> 6
A22: First month with positive net income (month #) | B22: =IFERROR(MATCH(1,'P&L'!$C$87:$AL$87,0),"Not within horizon") -> 7
A23: Cash invested paid back (month #) | B23: =IF(MIN('P&L'!$C$89:$AL$89)>=0,"No investment to pay back",IFERROR(MATCH(1,'P&L'!$C$91:$AL$91,0),"Not within horizon")) -> Not within horizon | D23: Cumulative operating + investing cash flow back to zero
A25: Annual break-even revenue
A26: Year # | B26: 1 | C26: 2 | D26: 3
B27: Year 1 | C27: Year 2 | D27: Year 3
A28: Revenue | B28: =SUMIF('P&L'!$C$27:$AL$27,B$26,'P&L'!$C$34:$AL$34) -> 319800 | C28: =SUMIF('P&L'!$C$27:$AL$27,C$26,'P&L'!$C$34:$AL$34) -> 408769.92 | D28: =SUMIF('P&L'!$C$27:$AL$27,D$26,'P&L'!$C$34:$AL$34) -> 446295
A29: Gross profit | B29: =SUMIF('P&L'!$C$27:$AL$27,B$26,'P&L'!$C$36:$AL$36) -> 214266 | C29: =SUMIF('P&L'!$C$27:$AL$27,C$26,'P&L'!$C$36:$AL$36) -> 273875.85 | D29: =SUMIF('P&L'!$C$27:$AL$27,D$26,'P&L'!$C$36:$AL$36) -> 299017.65
A30: Gross margin (contribution) | B30: =IF(B28=0,0,B29/B28) -> 0.67 | C30: =IF(C28=0,0,C29/C28) -> 0.67 | D30: =IF(D28=0,0,D29/D28) -> 0.67
A31: Operating expenses (treated as fixed) | B31: =-SUMIF('P&L'!$C$27:$AL$27,B$26,'P&L'!$C$43:$AL$43) -> 213034 | C31: =-SUMIF('P&L'!$C$27:$AL$27,C$26,'P&L'!$C$43:$AL$43) -> 219466.3 | D31: =-SUMIF('P&L'!$C$27:$AL$27,D$26,'P&L'!$C$43:$AL$43) -> 224468.15
A32: Break-even revenue (EBITDA = 0) | B32: =IF(B30>0,B31/B30,"n/a") -> 317961.19 | C32: =IF(C30>0,C31/C30,"n/a") -> 327561.64 | D32: =IF(D30>0,D31/D30,"n/a") -> 335027.08
A33: Margin of safety (revenue above break-even) | B33: =IF(AND(ISNUMBER(B32),B28>0),(B28-B32)/B28,"n/a") -> 0.0057498623 | C33: =IF(AND(ISNUMBER(C32),C28>0),(C28-C32)/C28,"n/a") -> 0.19866501 | D33: =IF(AND(ISNUMBER(D32),D28>0),(D28-D32)/D28,"n/a") -> 0.24931473
A35: Simplification: cost of sales is treated as variable and operating expenses as fixed, so break-even revenue = operating expenses ÷ gross margin. In a year with zero or negative gross margin there is no break-even revenue (n/a); the chart line shows 0 there.

Sheet Inputs
A1: Inputs — Low / Base / High | I1: =HYPERLINK("#'Cover'!A1","◂ Contents") -> ◂ Contents
A2: Illustrative assumptions for a demo — replace with your own numbers.
A5: Driver | B5: Low | C5: Base | D5: High | E5: Active | F5: Unit | G5: Source / comment
A6: Business drivers
A7: Customers per day at full traffic | B7: 120 | C7: 160 | D7: 210 | E7: =CHOOSE(Dashboard!$B$4,B7,C7,D7) -> 160 | F7: # | G7: Low ≤ Base ≤ High
A8: Months to reach full traffic | B8: 9 | C8: 6 | D8: 4 | E8: =CHOOSE(Dashboard!$B$4,B8,C8,D8) -> 6 | F8: months | G8: Low ≥ Base ≥ High (lower is better)
A9: Opening traffic, % of full | B9: 0.4 | C9: 0.5 | D9: 0.6 | E9: =CHOOSE(Dashboard!$B$4,B9,C9,D9) -> 0.5 | F9: % | G9: Low ≤ Base ≤ High
A10: Traffic growth per year (after year 1) | B10: 0.03 | C10: 0.06 | D10: 0.09 | E10: =CHOOSE(Dashboard!$B$4,B10,C10,D10) -> 0.06 | F10: % | G10: Low ≤ Base ≤ High
A11: Average ticket | B11: 5.5 | C11: 6.5 | D11: 7.5 | E11: =CHOOSE(Dashboard!$B$4,B11,C11,D11) -> 6.5 | F11: $ | G11: Low ≤ Base ≤ High
A12: Price growth per year | B12: 0.02 | C12: 0.03 | D12: 0.04 | E12: =CHOOSE(Dashboard!$B$4,B12,C12,D12) -> 0.03 | F12: % | G12: Low ≤ Base ≤ High
A13: Operating days per month | B13: 30 | C13: 30 | D13: 30 | E13: =CHOOSE(Dashboard!$B$4,B13,C13,D13) -> 30 | F13: days
A14: Food & beverage cost, % of revenue | B14: 0.36 | C14: 0.33 | D14: 0.3 | E14: =CHOOSE(Dashboard!$B$4,B14,C14,D14) -> 0.33 | F14: % | G14: Low ≥ Base ≥ High (lower is better)
A15: Rent per month | B15: 4500 | C15: 4500 | D15: 4500 | E15: =CHOOSE(Dashboard!$B$4,B15,C15,D15) -> 4500 | F15: $
A16: Marketing, % of revenue | B16: 0.04 | C16: 0.03 | D16: 0.03 | E16: =CHOOSE(Dashboard!$B$4,B16,C16,D16) -> 0.03 | F16: % | G16: Low ≥ Base ≥ High (lower is better)
A17: Utilities & other per month | B17: 2200 | C17: 2000 | D17: 2000 | E17: =CHOOSE(Dashboard!$B$4,B17,C17,D17) -> 2000 | F17: $ | G17: Low ≥ Base ≥ High (lower is better)
A18: Start-up capex (fit-out, equipment) | B18: 180000 | C18: 160000 | D18: 150000 | E18: =CHOOSE(Dashboard!$B$4,B18,C18,D18) -> 160000 | F18: $ | G18: Low ≥ Base ≥ High (lower is better)
A20: Headcount
A21: Cafe staff: headcount (FTE) | B21: 3 | C21: 3.5 | D21: 4 | E21: =CHOOSE(Dashboard!$B$4,B21,C21,D21) -> 3.5 | F21: FTE | G21: Low ≤ Base ≤ High
A22: Cafe staff: salary per FTE per year | B22: 30000 | C22: 32000 | D22: 34000 | E22: =CHOOSE(Dashboard!$B$4,B22,C22,D22) -> 32000 | F22: $
A23: Cafe staff: headcount growth per year | B23: 0 | C23: 0 | D23: 0 | E23: =CHOOSE(Dashboard!$B$4,B23,C23,D23) -> 0 | F23: % | G23: Low ≤ Base ≤ High
A24: Cafe staff: first month on payroll | B24: 1 | C24: 1 | D24: 1 | E24: =CHOOSE(Dashboard!$B$4,B24,C24,D24) -> 1 | F24: month #
A25: Payroll taxes & benefits, % of salary | B25: 0.12 | C25: 0.12 | D25: 0.12 | E25: =CHOOSE(Dashboard!$B$4,B25,C25,D25) -> 0.12 | F25: %
A26: Wage growth per year | B26: 0.03 | C26: 0.03 | D26: 0.03 | E26: =CHOOSE(Dashboard!$B$4,B26,C26,D26) -> 0.03 | F26: %
A28: Funding
A29: Equity raised at start | B29: 140000 | C29: 140000 | D29: 140000 | E29: =CHOOSE(Dashboard!$B$4,B29,C29,D29) -> 140000 | F29: $
A30: Loan drawn at start | B30: 80000 | C30: 80000 | D30: 80000 | E30: =CHOOSE(Dashboard!$B$4,B30,C30,D30) -> 80000 | F30: $
A31: Loan interest rate per year | B31: 0.08 | C31: 0.08 | D31: 0.08 | E31: =CHOOSE(Dashboard!$B$4,B31,C31,D31) -> 0.08 | F31: %
A32: Loan repayment term | B32: 5 | C32: 5 | D32: 5 | E32: =CHOOSE(Dashboard!$B$4,B32,C32,D32) -> 5 | F32: years
A34: Working capital
A35: Customer payment terms (receivable days) | B35: 2 | C35: 2 | D35: 2 | E35: =CHOOSE(Dashboard!$B$4,B35,C35,D35) -> 2 | F35: days
A36: Inventory held (days of COGS) | B36: 7 | C36: 7 | D36: 7 | E36: =CHOOSE(Dashboard!$B$4,B36,C36,D36) -> 7 | F36: days
A37: Supplier payment terms (payable days) | B37: 14 | C37: 14 | D37: 14 | E37: =CHOOSE(Dashboard!$B$4,B37,C37,D37) -> 14 | F37: days
A39: Tax & depreciation
A40: Depreciation period for capex | B40: 7 | C40: 7 | D40: 7 | E40: =CHOOSE(Dashboard!$B$4,B40,C40,D40) -> 7 | F40: years
A41: Income tax rate | B41: 0.21 | C41: 0.21 | D41: 0.21 | E41: =CHOOSE(Dashboard!$B$4,B41,C41,D41) -> 0.21 | F41: %
A43: Break-even & funding
A44: Minimum cash buffer to keep | B44: 53000 | C44: 53000 | D44: 53000 | E44: =CHOOSE(Dashboard!$B$4,B44,C44,D44) -> 53000 | F44: $ | G44: About 3 months of costs
A46: Legend: yellow cell with blue figure = input you can change · black = formula · green = link to another sheet · grey = active value (column E follows the scenario on the Dashboard).

Sheet P&L
A1: Neighborhood Cafe — Financial Plan — P&L | F1: =HYPERLINK("#'Cover'!A1","◂ Contents") -> ◂ Contents
A2: Rolled up from the period detail (SUMIF on the year row; balances at year end).
A3: Year # | B3: 1 | C3: 2 | D3: 3
B4: Year 1 | C4: Year 2 | D4: Year 3
A5: Revenue | B5: =SUMIF('P&L'!$C$27:$AL$27,B$3,'P&L'!$C$34:$AL$34) -> 319800 | C5: =SUMIF('P&L'!$C$27:$AL$27,C$3,'P&L'!$C$34:$AL$34) -> 408769.92 | D5: =SUMIF('P&L'!$C$27:$AL$27,D$3,'P&L'!$C$34:$AL$34) -> 446295
A6: Gross profit | B6: =SUMIF('P&L'!$C$27:$AL$27,B$3,'P&L'!$C$36:$AL$36) -> 214266 | C6: =SUMIF('P&L'!$C$27:$AL$27,C$3,'P&L'!$C$36:$AL$36) -> 273875.85 | D6: =SUMIF('P&L'!$C$27:$AL$27,D$3,'P&L'!$C$36:$AL$36) -> 299017.65
A7: Gross margin | B7: =IF(B5=0,0,B6/B5) -> 0.67 | C7: =IF(C5=0,0,C6/C5) -> 0.67 | D7: =IF(D5=0,0,D6/D5) -> 0.67
A8: Total operating expenses | B8: =SUMIF('P&L'!$C$27:$AL$27,B$3,'P&L'!$C$43:$AL$43) -> -213034 | C8: =SUMIF('P&L'!$C$27:$AL$27,C$3,'P&L'!$C$43:$AL$43) -> -219466.3 | D8: =SUMIF('P&L'!$C$27:$AL$27,D$3,'P&L'!$C$43:$AL$43) -> -224468.15
A9: EBITDA | B9: =SUMIF('P&L'!$C$27:$AL$27,B$3,'P&L'!$C$44:$AL$44) -> 1232 | C9: =SUMIF('P&L'!$C$27:$AL$27,C$3,'P&L'!$C$44:$AL$44) -> 54409.549 | D9: =SUMIF('P&L'!$C$27:$AL$27,D$3,'P&L'!$C$44:$AL$44) -> 74549.503
A10: EBITDA margin | B10: =IF(B5=0,0,B9/B5) -> 0.0038524078 | C10: =IF(C5=0,0,C9/C5) -> 0.13310556 | D10: =IF(D5=0,0,D9/D5) -> 0.16704087
A11: Net income | B11: =SUMIF('P&L'!$C$27:$AL$27,B$3,'P&L'!$C$53:$AL$53) -> -27487.365 | C11: =SUMIF('P&L'!$C$27:$AL$27,C$3,'P&L'!$C$53:$AL$53) -> 26965.739 | D11: =SUMIF('P&L'!$C$27:$AL$27,D$3,'P&L'!$C$53:$AL$53) -> 38334.239
A12: Year-end cash | B12: =INDEX('P&L'!$C$83:$AL$83,B$3*12) -> 41025.511 | C12: =INDEX('P&L'!$C$83:$AL$83,C$3*12) -> 74877.99 | D12: =INDEX('P&L'!$C$83:$AL$83,D$3*12) -> 120101.69
A13: Year-end loan balance | B13: =INDEX('P&L'!$C$66:$AL$66,B$3*12) -> 65333.333 | C13: =INDEX('P&L'!$C$66:$AL$66,C$3*12) -> 49333.333 | D13: =INDEX('P&L'!$C$66:$AL$66,D$3*12) -> 33333.333
A15: Cafe metrics
A16: Year # | B16: 1 | C16: 2 | D16: 3
B17: Year 1 | C17: Year 2 | D17: Year 3
A18: Customers per day (year end) | B18: =INDEX('P&L'!$C$31:$AL$31,B$16*12) -> 160 | C18: =INDEX('P&L'!$C$31:$AL$31,C$16*12) -> 169.6 | D18: =INDEX('P&L'!$C$31:$AL$31,D$16*12) -> 179.776
A19: Average ticket (year end) | B19: =INDEX('P&L'!$C$32:$AL$32,B$16*12) -> 6.5 | C19: =INDEX('P&L'!$C$32:$AL$32,C$16*12) -> 6.695 | D19: =INDEX('P&L'!$C$32:$AL$32,D$16*12) -> 6.89585
A20: Revenue | B20: =SUMIF('P&L'!$C$27:$AL$27,B$16,'P&L'!$C$34:$AL$34) -> 319800 | C20: =SUMIF('P&L'!$C$27:$AL$27,C$16,'P&L'!$C$34:$AL$34) -> 408769.92 | D20: =SUMIF('P&L'!$C$27:$AL$27,D$16,'P&L'!$C$34:$AL$34) -> 446295
A21: Gross profit | B21: =SUMIF('P&L'!$C$27:$AL$27,B$16,'P&L'!$C$36:$AL$36) -> 214266 | C21: =SUMIF('P&L'!$C$27:$AL$27,C$16,'P&L'!$C$36:$AL$36) -> 273875.85 | D21: =SUMIF('P&L'!$C$27:$AL$27,D$16,'P&L'!$C$36:$AL$36) -> 299017.65
A22: Gross margin | B22: =IF(B20=0,0,B21/B20) -> 0.67 | C22: =IF(C20=0,0,C21/C20) -> 0.67 | D22: =IF(D20=0,0,D21/D20) -> 0.67
A24: Monthly detail
A25: Month | C25: M1 | D25: M2 | E25: M3 | F25: M4 | G25: M5 | H25: M6 | I25: M7 | J25: M8 | K25: M9 | L25: M10 | M25: M11 | N25: M12 | O25: M13 | P25: M14 | Q25: M15 | R25: M16 | S25: M17 | T25: M18 | U25: M19 | V25: M20 | W25: M21 | X25: M22 | Y25: M23 | Z25: M24 | AA25: M25 | AB25: M26 | AC25: M27 | AD25: M28 | AE25: M29 | AF25: M30 | AG25: M31 | AH25: M32 | AI25: M33 | AJ25: M34 | AK25: M35 | AL25: M36
A26: Period # | C26: 1 | D26: 2 | E26: 3 | F26: 4 | G26: 5 | H26: 6 | I26: 7 | J26: 8 | K26: 9 | L26: 10 | M26: 11 | N26: 12 | O26: 13 | P26: 14 | Q26: 15 | R26: 16 | S26: 17 | T26: 18 | U26: 19 | V26: 20 | W26: 21 | X26: 22 | Y26: 23 | Z26: 24 | AA26: 25 | AB26: 26 | AC26: 27 | AD26: 28 | AE26: 29 | AF26: 30 | AG26: 31 | AH26: 32 | AI26: 33 | AJ26: 34 | AK26: 35 | AL26: 36
A27: Year # | C27: =ROUNDUP(C26*1/12,0) -> 1 | D27: =ROUNDUP(D26*1/12,0) -> 1 | E27: =ROUNDUP(E26*1/12,0) -> 1 | F27: =ROUNDUP(F26*1/12,0) -> 1 | G27: =ROUNDUP(G26*1/12,0) -> 1 | H27: =ROUNDUP(H26*1/12,0) -> 1 | I27: =ROUNDUP(I26*1/12,0) -> 1 | J27: =ROUNDUP(J26*1/12,0) -> 1 | ... AL27: =ROUNDUP(AL26*1/12,0) -> 3
A29: Revenue build
A30: Traffic ramp factor | C30: =MIN(1,Inputs!$E$9+(1-Inputs!$E$9)*(C$26-1)/MAX(1,Inputs!$E$8)) -> 0.5 | D30: =MIN(1,Inputs!$E$9+(1-Inputs!$E$9)*(D$26-1)/MAX(1,Inputs!$E$8)) -> 0.58333333 | E30: =MIN(1,Inputs!$E$9+(1-Inputs!$E$9)*(E$26-1)/MAX(1,Inputs!$E$8)) -> 0.66666667 | F30: =MIN(1,Inputs!$E$9+(1-Inputs!$E$9)*(F$26-1)/MAX(1,Inputs!$E$8)) -> 0.75 | G30: =MIN(1,Inputs!$E$9+(1-Inputs!$E$9)*(G$26-1)/MAX(1,Inputs!$E$8)) -> 0.83333333 | H30: =MIN(1,Inputs!$E$9+(1-Inputs!$E$9)*(H$26-1)/MAX(1,Inputs!$E$8)) -> 0.91666667 | I30: =MIN(1,Inputs!$E$9+(1-Inputs!$E$9)*(I$26-1)/MAX(1,Inputs!$E$8)) -> 1 | J30: =MIN(1,Inputs!$E$9+(1-Inputs!$E$9)*(J$26-1)/MAX(1,Inputs!$E$8)) -> 1 | ... AL30: =MIN(1,Inputs!$E$9+(1-Inputs!$E$9)*(AL$26-1)/MAX(1,Inputs!$E$8)) -> 1
A31: Customers per day | C31: =Inputs!$E$7*C30*(1+Inputs!$E$10)^(C$27-1) -> 80 | D31: =Inputs!$E$7*D30*(1+Inputs!$E$10)^(D$27-1) -> 93.333333 | E31: =Inputs!$E$7*E30*(1+Inputs!$E$10)^(E$27-1) -> 106.66667 | F31: =Inputs!$E$7*F30*(1+Inputs!$E$10)^(F$27-1) -> 120 | G31: =Inputs!$E$7*G30*(1+Inputs!$E$10)^(G$27-1) -> 133.33333 | H31: =Inputs!$E$7*H30*(1+Inputs!$E$10)^(H$27-1) -> 146.66667 | I31: =Inputs!$E$7*I30*(1+Inputs!$E$10)^(I$27-1) -> 160 | J31: =Inputs!$E$7*J30*(1+Inputs!$E$10)^(J$27-1) -> 160 | ... AL31: =Inputs!$E$7*AL30*(1+Inputs!$E$10)^(AL$27-1) -> 179.776
A32: Average ticket | C32: =Inputs!$E$11*(1+Inputs!$E$12)^(C$27-1) -> 6.5 | D32: =Inputs!$E$11*(1+Inputs!$E$12)^(D$27-1) -> 6.5 | E32: =Inputs!$E$11*(1+Inputs!$E$12)^(E$27-1) -> 6.5 | F32: =Inputs!$E$11*(1+Inputs!$E$12)^(F$27-1) -> 6.5 | G32: =Inputs!$E$11*(1+Inputs!$E$12)^(G$27-1) -> 6.5 | H32: =Inputs!$E$11*(1+Inputs!$E$12)^(H$27-1) -> 6.5 | I32: =Inputs!$E$11*(1+Inputs!$E$12)^(I$27-1) -> 6.5 | J32: =Inputs!$E$11*(1+Inputs!$E$12)^(J$27-1) -> 6.5 | ... AL32: =Inputs!$E$11*(1+Inputs!$E$12)^(AL$27-1) -> 6.89585
A33: Operating days in period | C33: =Inputs!$E$13*1 -> 30 | D33: =Inputs!$E$13*1 -> 30 | E33: =Inputs!$E$13*1 -> 30 | F33: =Inputs!$E$13*1 -> 30 | G33: =Inputs!$E$13*1 -> 30 | H33: =Inputs!$E$13*1 -> 30 | I33: =Inputs!$E$13*1 -> 30 | J33: =Inputs!$E$13*1 -> 30 | ... AL33: =Inputs!$E$13*1 -> 30
A34: Revenue | C34: =C31*C32*C33 -> 15600 | D34: =D31*D32*D33 -> 18200 | E34: =E31*E32*E33 -> 20800 | F34: =F31*F32*F33 -> 23400 | G34: =G31*G32*G33 -> 26000 | H34: =H31*H32*H33 -> 28600 | I34: =I31*I32*I33 -> 31200 | J34: =J31*J32*J33 -> 31200 | ... AL34: =AL31*AL32*AL33 -> 37191.25
A35: Food & beverage cost | C35: =-C34*Inputs!$E$14 -> -5148 | D35: =-D34*Inputs!$E$14 -> -6006 | E35: =-E34*Inputs!$E$14 -> -6864 | F35: =-F34*Inputs!$E$14 -> -7722 | G35: =-G34*Inputs!$E$14 -> -8580 | H35: =-H34*Inputs!$E$14 -> -9438 | I35: =-I34*Inputs!$E$14 -> -10296 | J35: =-J34*Inputs!$E$14 -> -10296 | ... AL35: =-AL34*Inputs!$E$14 -> -12273.112
A36: Gross profit | C36: =C34+C35 -> 10452 | D36: =D34+D35 -> 12194 | E36: =E34+E35 -> 13936 | F36: =F34+F35 -> 15678 | G36: =G34+G35 -> 17420 | H36: =H34+H35 -> 19162 | I36: =I34+I35 -> 20904 | J36: =J34+J35 -> 20904 | ... AL36: =AL34+AL35 -> 24918.137
A38: Operating expenses
A39: Rent | C39: =-Inputs!$E$15*1 -> -4500 | D39: =-Inputs!$E$15*1 -> -4500 | E39: =-Inputs!$E$15*1 -> -4500 | F39: =-Inputs!$E$15*1 -> -4500 | G39: =-Inputs!$E$15*1 -> -4500 | H39: =-Inputs!$E$15*1 -> -4500 | I39: =-Inputs!$E$15*1 -> -4500 | J39: =-Inputs!$E$15*1 -> -4500 | ... AL39: =-Inputs!$E$15*1 -> -4500
A40: Payroll | C40: =C99 -> -10453.333 | D40: =D99 -> -10453.333 | E40: =E99 -> -10453.333 | F40: =F99 -> -10453.333 | G40: =G99 -> -10453.333 | H40: =H99 -> -10453.333 | I40: =I99 -> -10453.333 | J40: =J99 -> -10453.333 | ... AL40: =AL99 -> -11089.941
A41: Marketing | C41: =-C34*Inputs!$E$16 -> -468 | D41: =-D34*Inputs!$E$16 -> -546 | E41: =-E34*Inputs!$E$16 -> -624 | F41: =-F34*Inputs!$E$16 -> -702 | G41: =-G34*Inputs!$E$16 -> -780 | H41: =-H34*Inputs!$E$16 -> -858 | I41: =-I34*Inputs!$E$16 -> -936 | J41: =-J34*Inputs!$E$16 -> -936 | ... AL41: =-AL34*Inputs!$E$16 -> -1115.7375
A42: Utilities & other | C42: =-Inputs!$E$17*1 -> -2000 | D42: =-Inputs!$E$17*1 -> -2000 | E42: =-Inputs!$E$17*1 -> -2000 | F42: =-Inputs!$E$17*1 -> -2000 | G42: =-Inputs!$E$17*1 -> -2000 | H42: =-Inputs!$E$17*1 -> -2000 | I42: =-Inputs!$E$17*1 -> -2000 | J42: =-Inputs!$E$17*1 -> -2000 | ... AL42: =-Inputs!$E$17*1 -> -2000
A43: Total operating expenses | C43: =C39+C40+C41+C42 -> -17421.333 | D43: =D39+D40+D41+D42 -> -17499.333 | E43: =E39+E40+E41+E42 -> -17577.333 | F43: =F39+F40+F41+F42 -> -17655.333 | G43: =G39+G40+G41+G42 -> -17733.333 | H43: =H39+H40+H41+H42 -> -17811.333 | I43: =I39+I40+I41+I42 -> -17889.333 | J43: =J39+J40+J41+J42 -> -17889.333 | ... AL43: =AL39+AL40+AL41+AL42 -> -18705.679
A44: EBITDA | C44: =C36+C43 -> -6969.3333 | D44: =D36+D43 -> -5305.3333 | E44: =E36+E43 -> -3641.3333 | F44: =F36+F43 -> -1977.3333 | G44: =G36+G43 -> -313.33333 | H44: =H36+H43 -> 1350.6667 | I44: =I36+I43 -> 3014.6667 | J44: =J36+J43 -> 3014.6667 | ... AL44: =AL36+AL43 -> 6212.4586
A46: Profit after depreciation, interest, tax
A47: EBIT | C47: =C44+C58 -> -8874.0952 | D47: =D44+D58 -> -7210.0952 | E47: =E44+E58 -> -5546.0952 | F47: =F44+F58 -> -3882.0952 | G47: =G44+G58 -> -2218.0952 | H47: =H44+H58 -> -554.09524 | I47: =I44+I58 -> 1109.9048 | J47: =J44+J58 -> 1109.9048 | ... AL47: =AL44+AL58 -> 4307.6967
A48: Interest on loan (average balance after drawdown) | C48: =-(C63+C64+C66)/2*Inputs!$E$31/12 -> -533.33333 | D48: =-(D63+D64+D66)/2*Inputs!$E$31/12 -> -528.88889 | E48: =-(E63+E64+E66)/2*Inputs!$E$31/12 -> -520 | F48: =-(F63+F64+F66)/2*Inputs!$E$31/12 -> -511.11111 | G48: =-(G63+G64+G66)/2*Inputs!$E$31/12 -> -502.22222 | H48: =-(H63+H64+H66)/2*Inputs!$E$31/12 -> -493.33333 | I48: =-(I63+I64+I66)/2*Inputs!$E$31/12 -> -484.44444 | J48: =-(J63+J64+J66)/2*Inputs!$E$31/12 -> -475.55556 | ... AL48: =-(AL63+AL64+AL66)/2*Inputs!$E$31/12 -> -226.66667
A49: Pre-tax income | C49: =C47+C48 -> -9407.4286 | D49: =D47+D48 -> -7738.9841 | E49: =E47+E48 -> -6066.0952 | F49: =F47+F48 -> -4393.2063 | G49: =G47+G48 -> -2720.3175 | H49: =H47+H48 -> -1047.4286 | I49: =I47+I48 -> 625.46032 | J49: =J47+J48 -> 634.34921 | ... AL49: =AL47+AL48 -> 4081.03
A50: Helper: cumulative pre-tax income | C50: =C49 -> -9407.4286 | D50: =C50+D49 -> -17146.413 | E50: =D50+E49 -> -23212.508 | F50: =E50+F49 -> -27605.714 | G50: =F50+G49 -> -30326.032 | H50: =G50+H49 -> -31373.46 | I50: =H50+I49 -> -30748 | J50: =I50+J49 -> -30113.651 | K50: =J50+K49 -> -29470.413 | ... AL50: =AK50+AL49 -> 47864.068
A51: Helper: cumulative taxable income (losses carried forward) | C51: =MAX(0,C50) -> 0 | D51: =MAX(C51,D50) -> 0 | E51: =MAX(D51,E50) -> 0 | F51: =MAX(E51,F50) -> 0 | G51: =MAX(F51,G50) -> 0 | H51: =MAX(G51,H50) -> 0 | I51: =MAX(H51,I50) -> 0 | J51: =MAX(I51,J50) -> 0 | K51: =MAX(J51,K50) -> 0 | ... AL51: =MAX(AK51,AL50) -> 47864.068
A52: Income tax | C52: =-C51*Inputs!$E$41 -> 0 | D52: =-(D51-C51)*Inputs!$E$41 -> 0 | E52: =-(E51-D51)*Inputs!$E$41 -> 0 | F52: =-(F51-E51)*Inputs!$E$41 -> 0 | G52: =-(G51-F51)*Inputs!$E$41 -> 0 | H52: =-(H51-G51)*Inputs!$E$41 -> 0 | I52: =-(I51-H51)*Inputs!$E$41 -> 0 | J52: =-(J51-I51)*Inputs!$E$41 -> 0 | K52: =-(K51-J51)*Inputs!$E$41 -> 0 | ... AL52: =-(AL51-AK51)*Inputs!$E$41 -> -857.0163
A53: Net income | C53: =C49+C52 -> -9407.4286 | D53: =D49+D52 -> -7738.9841 | E53: =E49+E52 -> -6066.0952 | F53: =F49+F52 -> -4393.2063 | G53: =G49+G52 -> -2720.3175 | H53: =H49+H52 -> -1047.4286 | I53: =I49+I52 -> 625.46032 | J53: =J49+J52 -> 634.34921 | ... AL53: =AL49+AL52 -> 3224.0137
A55: Fixed assets & capital spending
A56: Capital spending | C56: =IF(C$26=1,Inputs!$E$18,0) -> 160000 | D56: =IF(D$26=1,Inputs!$E$18,0) -> 0 | E56: =IF(E$26=1,Inputs!$E$18,0) -> 0 | F56: =IF(F$26=1,Inputs!$E$18,0) -> 0 | G56: =IF(G$26=1,Inputs!$E$18,0) -> 0 | H56: =IF(H$26=1,Inputs!$E$18,0) -> 0 | I56: =IF(I$26=1,Inputs!$E$18,0) -> 0 | J56: =IF(J$26=1,Inputs!$E$18,0) -> 0 | ... AL56: =IF(AL$26=1,Inputs!$E$18,0) -> 0
A57: Fixed assets at cost | C57: =C56 -> 160000 | D57: =C57+D56 -> 160000 | E57: =D57+E56 -> 160000 | F57: =E57+F56 -> 160000 | G57: =F57+G56 -> 160000 | H57: =G57+H56 -> 160000 | I57: =H57+I56 -> 160000 | J57: =I57+J56 -> 160000 | K57: =J57+K56 -> 160000 | ... AL57: =AK57+AL56 -> 160000
A58: Depreciation | C58: =-MIN(C57/MAX(1,Inputs!$E$40*12),C56) -> -1904.7619 | D58: =-MIN(D57/MAX(1,Inputs!$E$40*12),C60+D56) -> -1904.7619 | E58: =-MIN(E57/MAX(1,Inputs!$E$40*12),D60+E56) -> -1904.7619 | F58: =-MIN(F57/MAX(1,Inputs!$E$40*12),E60+F56) -> -1904.7619 | G58: =-MIN(G57/MAX(1,Inputs!$E$40*12),F60+G56) -> -1904.7619 | H58: =-MIN(H57/MAX(1,Inputs!$E$40*12),G60+H56) -> -1904.7619 | I58: =-MIN(I57/MAX(1,Inputs!$E$40*12),H60+I56) -> -1904.7619 | J58: =-MIN(J57/MAX(1,Inputs!$E$40*12),I60+J56) -> -1904.7619 | K58: =-MIN(K57/MAX(1,Inputs!$E$40*12),J60+K56) -> -1904.7619 | ... AL58: =-MIN(AL57/MAX(1,Inputs!$E$40*12),AK60+AL56) -> -1904.7619
A59: Accumulated depreciation | C59: =C58 -> -1904.7619 | D59: =C59+D58 -> -3809.5238 | E59: =D59+E58 -> -5714.2857 | F59: =E59+F58 -> -7619.0476 | G59: =F59+G58 -> -9523.8095 | H59: =G59+H58 -> -11428.571 | I59: =H59+I58 -> -13333.333 | J59: =I59+J58 -> -15238.095 | K59: =J59+K58 -> -17142.857 | ... AL59: =AK59+AL58 -> -68571.429
A60: Net fixed assets | C60: =C57+C59 -> 158095.24 | D60: =D57+D59 -> 156190.48 | E60: =E57+E59 -> 154285.71 | F60: =F57+F59 -> 152380.95 | G60: =G57+G59 -> 150476.19 | H60: =H57+H59 -> 148571.43 | I60: =I57+I59 -> 146666.67 | J60: =J57+J59 -> 144761.9 | ... AL60: =AL57+AL59 -> 91428.571
A62: Debt
A63: Loan — opening balance | C63: =0 -> 0 | D63: =C66 -> 80000 | E63: =D66 -> 78666.667 | F63: =E66 -> 77333.333 | G63: =F66 -> 76000 | H63: =G66 -> 74666.667 | I63: =H66 -> 73333.333 | J63: =I66 -> 72000 | K63: =J66 -> 70666.667 | ... AL63: =AK66 -> 34666.667
A64: Loan drawdown | C64: =IF(C$26=1,Inputs!$E$30,0) -> 80000 | D64: =IF(D$26=1,Inputs!$E$30,0) -> 0 | E64: =IF(E$26=1,Inputs!$E$30,0) -> 0 | F64: =IF(F$26=1,Inputs!$E$30,0) -> 0 | G64: =IF(G$26=1,Inputs!$E$30,0) -> 0 | H64: =IF(H$26=1,Inputs!$E$30,0) -> 0 | I64: =IF(I$26=1,Inputs!$E$30,0) -> 0 | J64: =IF(J$26=1,Inputs!$E$30,0) -> 0 | ... AL64: =IF(AL$26=1,Inputs!$E$30,0) -> 0
A65: Loan repayment | C65: =-MIN(C63,Inputs!$E$30/MAX(1,Inputs!$E$32*12)) -> 0 | D65: =-MIN(D63,Inputs!$E$30/MAX(1,Inputs!$E$32*12)) -> -1333.3333 | E65: =-MIN(E63,Inputs!$E$30/MAX(1,Inputs!$E$32*12)) -> -1333.3333 | F65: =-MIN(F63,Inputs!$E$30/MAX(1,Inputs!$E$32*12)) -> -1333.3333 | G65: =-MIN(G63,Inputs!$E$30/MAX(1,Inputs!$E$32*12)) -> -1333.3333 | H65: =-MIN(H63,Inputs!$E$30/MAX(1,Inputs!$E$32*12)) -> -1333.3333 | I65: =-MIN(I63,Inputs!$E$30/MAX(1,Inputs!$E$32*12)) -> -1333.3333 | J65: =-MIN(J63,Inputs!$E$30/MAX(1,Inputs!$E$32*12)) -> -1333.3333 | ... AL65: =-MIN(AL63,Inputs!$E$30/MAX(1,Inputs!$E$32*12)) -> -1333.3333
A66: Loan — closing balance | C66: =C63+C64+C65 -> 80000 | D66: =D63+D64+D65 -> 78666.667 | E66: =E63+E64+E65 -> 77333.333 | F66: =F63+F64+F65 -> 76000 | G66: =G63+G64+G65 -> 74666.667 | H66: =H63+H64+H65 -> 73333.333 | I66: =I63+I64+I65 -> 72000 | J66: =J63+J64+J65 -> 70666.667 | ... AL66: =AL63+AL64+AL65 -> 33333.333
A68: Working capital
A69: Accounts receivable | C69: =C34*Inputs!$E$35/30 -> 1040 | D69: =D34*Inputs!$E$35/30 -> 1213.3333 | E69: =E34*Inputs!$E$35/30 -> 1386.6667 | F69: =F34*Inputs!$E$35/30 -> 1560 | G69: =G34*Inputs!$E$35/30 -> 1733.3333 | H69: =H34*Inputs!$E$35/30 -> 1906.6667 | I69: =I34*Inputs!$E$35/30 -> 2080 | J69: =J34*Inputs!$E$35/30 -> 2080 | ... AL69: =AL34*Inputs!$E$35/30 -> 2479.4167
A70: Inventory | C70: =-C35*Inputs!$E$36/30 -> 1201.2 | D70: =-D35*Inputs!$E$36/30 -> 1401.4 | E70: =-E35*Inputs!$E$36/30 -> 1601.6 | F70: =-F35*Inputs!$E$36/30 -> 1801.8 | G70: =-G35*Inputs!$E$36/30 -> 2002 | H70: =-H35*Inputs!$E$36/30 -> 2202.2 | I70: =-I35*Inputs!$E$36/30 -> 2402.4 | J70: =-J35*Inputs!$E$36/30 -> 2402.4 | ... AL70: =-AL35*Inputs!$E$36/30 -> 2863.7262
A71: Accounts payable | C71: =-C35*Inputs!$E$37/30 -> 2402.4 | D71: =-D35*Inputs!$E$37/30 -> 2802.8 | E71: =-E35*Inputs!$E$37/30 -> 3203.2 | F71: =-F35*Inputs!$E$37/30 -> 3603.6 | G71: =-G35*Inputs!$E$37/30 -> 4004 | H71: =-H35*Inputs!$E$37/30 -> 4404.4 | I71: =-I35*Inputs!$E$37/30 -> 4804.8 | J71: =-J35*Inputs!$E$37/30 -> 4804.8 | ... AL71: =-AL35*Inputs!$E$37/30 -> 5727.4525
A72: (Increase) / decrease in receivables | C72: =-C69 -> -1040 | D72: =C69-D69 -> -173.33333 | E72: =D69-E69 -> -173.33333 | F72: =E69-F69 -> -173.33333 | G72: =F69-G69 -> -173.33333 | H72: =G69-H69 -> -173.33333 | I72: =H69-I69 -> -173.33333 | J72: =I69-J69 -> 0 | K72: =J69-K69 -> 0 | ... AL72: =AK69-AL69 -> 0
A73: (Increase) / decrease in inventory | C73: =-C70 -> -1201.2 | D73: =C70-D70 -> -200.2 | E73: =D70-E70 -> -200.2 | F73: =E70-F70 -> -200.2 | G73: =F70-G70 -> -200.2 | H73: =G70-H70 -> -200.2 | I73: =H70-I70 -> -200.2 | J73: =I70-J70 -> 0 | K73: =J70-K70 -> 0 | ... AL73: =AK70-AL70 -> 0
A74: Increase / (decrease) in payables | C74: =C71 -> 2402.4 | D74: =D71-C71 -> 400.4 | E74: =E71-D71 -> 400.4 | F74: =F71-E71 -> 400.4 | G74: =G71-F71 -> 400.4 | H74: =H71-G71 -> 400.4 | I74: =I71-H71 -> 400.4 | J74: =J71-I71 -> 0 | K74: =K71-J71 -> 0 | ... AL74: =AL71-AK71 -> 0
A76: Cash flow
A77: Operating cash flow | C77: =C53-C58+C72+C73+C74 -> -7341.4667 | D77: =D53-D58+D72+D73+D74 -> -5807.3556 | E77: =E53-E58+E72+E73+E74 -> -4134.4667 | F77: =F53-F58+F72+F73+F74 -> -2461.5778 | G77: =G53-G58+G72+G73+G74 -> -788.68889 | H77: =H53-H58+H72+H73+H74 -> 884.2 | I77: =I53-I58+I72+I73+I74 -> 2557.0889 | J77: =J53-J58+J72+J73+J74 -> 2539.1111 | ... AL77: =AL53-AL58+AL72+AL73+AL74 -> 5128.7756
A78: Investing cash flow (capex) | C78: =-C56 -> -160000 | D78: =-D56 -> 0 | E78: =-E56 -> 0 | F78: =-F56 -> 0 | G78: =-G56 -> 0 | H78: =-H56 -> 0 | I78: =-I56 -> 0 | J78: =-J56 -> 0 | ... AL78: =-AL56 -> 0
A79: Equity raised | C79: =IF(C$26=1,Inputs!$E$29,0) -> 140000 | D79: =IF(D$26=1,Inputs!$E$29,0) -> 0 | E79: =IF(E$26=1,Inputs!$E$29,0) -> 0 | F79: =IF(F$26=1,Inputs!$E$29,0) -> 0 | G79: =IF(G$26=1,Inputs!$E$29,0) -> 0 | H79: =IF(H$26=1,Inputs!$E$29,0) -> 0 | I79: =IF(I$26=1,Inputs!$E$29,0) -> 0 | J79: =IF(J$26=1,Inputs!$E$29,0) -> 0 | ... AL79: =IF(AL$26=1,Inputs!$E$29,0) -> 0
A80: Financing cash flow | C80: =C79+C64+C65 -> 220000 | D80: =D79+D64+D65 -> -1333.3333 | E80: =E79+E64+E65 -> -1333.3333 | F80: =F79+F64+F65 -> -1333.3333 | G80: =G79+G64+G65 -> -1333.3333 | H80: =H79+H64+H65 -> -1333.3333 | I80: =I79+I64+I65 -> -1333.3333 | J80: =J79+J64+J65 -> -1333.3333 | ... AL80: =AL79+AL64+AL65 -> -1333.3333
A81: Net cash flow | C81: =C77+C78+C80 -> 52658.533 | D81: =D77+D78+D80 -> -7140.6889 | E81: =E77+E78+E80 -> -5467.8 | F81: =F77+F78+F80 -> -3794.9111 | G81: =G77+G78+G80 -> -2122.0222 | H81: =H77+H78+H80 -> -449.13333 | I81: =I77+I78+I80 -> 1223.7556 | J81: =J77+J78+J80 -> 1205.7778 | ... AL81: =AL77+AL78+AL80 -> 3795.4423
A82: Opening cash | C82: =0 -> 0 | D82: =C83 -> 52658.533 | E82: =D83 -> 45517.844 | F82: =E83 -> 40050.044 | G82: =F83 -> 36255.133 | H82: =G83 -> 34133.111 | I82: =H83 -> 33683.978 | J82: =I83 -> 34907.733 | K82: =J83 -> 36113.511 | ... AL82: =AK83 -> 116306.24
A83: Closing cash | C83: =C82+C81 -> 52658.533 | D83: =D82+D81 -> 45517.844 | E83: =E82+E81 -> 40050.044 | F83: =F82+F81 -> 36255.133 | G83: =G82+G81 -> 34133.111 | H83: =H82+H81 -> 33683.978 | I83: =I82+I81 -> 34907.733 | J83: =J82+J81 -> 36113.511 | ... AL83: =AL82+AL81 -> 120101.69
A84: Helper: EBITDA positive (1/0) | C84: =IF(C44>0,1,0) -> 0 | D84: =IF(D44>0,1,0) -> 0 | E84: =IF(E44>0,1,0) -> 0 | F84: =IF(F44>0,1,0) -> 0 | G84: =IF(G44>0,1,0) -> 0 | H84: =IF(H44>0,1,0) -> 1 | I84: =IF(I44>0,1,0) -> 1 | J84: =IF(J44>0,1,0) -> 1 | ... AL84: =IF(AL44>0,1,0) -> 1
A86: Goal modules
A87: Helper: net income positive (1/0) | C87: =IF(C53>0,1,0) -> 0 | D87: =IF(D53>0,1,0) -> 0 | E87: =IF(E53>0,1,0) -> 0 | F87: =IF(F53>0,1,0) -> 0 | G87: =IF(G53>0,1,0) -> 0 | H87: =IF(H53>0,1,0) -> 0 | I87: =IF(I53>0,1,0) -> 1 | J87: =IF(J53>0,1,0) -> 1 | ... AL87: =IF(AL53>0,1,0) -> 1
A88: Cash flow before financing (operating + investing) | C88: =C77+C78 -> -167341.47 | D88: =D77+D78 -> -5807.3556 | E88: =E77+E78 -> -4134.4667 | F88: =F77+F78 -> -2461.5778 | G88: =G77+G78 -> -788.68889 | H88: =H77+H78 -> 884.2 | I88: =I77+I78 -> 2557.0889 | J88: =J77+J78 -> 2539.1111 | ... AL88: =AL77+AL78 -> 5128.7756
A89: Cumulative cash flow before financing | C89: =C88 -> -167341.47 | D89: =C89+D88 -> -173148.82 | E89: =D89+E88 -> -177283.29 | F89: =E89+F88 -> -179744.87 | G89: =F89+G88 -> -180533.56 | H89: =G89+H88 -> -179649.36 | I89: =H89+I88 -> -177092.27 | J89: =I89+J88 -> -174553.16 | K89: =J89+K88 -> -172005.16 | ... AL89: =AK89+AL88 -> -53231.648
A90: Helper: lowest cumulative cash flow so far | C90: =C89 -> -167341.47 | D90: =MIN(C90,D89) -> -173148.82 | E90: =MIN(D90,E89) -> -177283.29 | F90: =MIN(E90,F89) -> -179744.87 | G90: =MIN(F90,G89) -> -180533.56 | H90: =MIN(G90,H89) -> -180533.56 | I90: =MIN(H90,I89) -> -180533.56 | J90: =MIN(I90,J89) -> -180533.56 | K90: =MIN(J90,K89) -> -180533.56 | ... AL90: =MIN(AK90,AL89) -> -180533.56
A91: Helper: investment paid back (1/0) | C91: =IF(AND(C89>=0,C90<0),1,0) -> 0 | D91: =IF(AND(D89>=0,D90<0),1,0) -> 0 | E91: =IF(AND(E89>=0,E90<0),1,0) -> 0 | F91: =IF(AND(F89>=0,F90<0),1,0) -> 0 | G91: =IF(AND(G89>=0,G90<0),1,0) -> 0 | H91: =IF(AND(H89>=0,H90<0),1,0) -> 0 | I91: =IF(AND(I89>=0,I90<0),1,0) -> 0 | J91: =IF(AND(J89>=0,J90<0),1,0) -> 0 | ... AL91: =IF(AND(AL89>=0,AL90<0),1,0) -> 0
A93: Headcount (FTE)
A94: Cafe staff — FTE | C94: =Inputs!$E$21*(1+Inputs!$E$23)^(C$27-1)*MAX(0,MIN(1,C$26*1-Inputs!$E$24+1))/1 -> 3.5 | D94: =Inputs!$E$21*(1+Inputs!$E$23)^(D$27-1)*MAX(0,MIN(1,D$26*1-Inputs!$E$24+1))/1 -> 3.5 | E94: =Inputs!$E$21*(1+Inputs!$E$23)^(E$27-1)*MAX(0,MIN(1,E$26*1-Inputs!$E$24+1))/1 -> 3.5 | F94: =Inputs!$E$21*(1+Inputs!$E$23)^(F$27-1)*MAX(0,MIN(1,F$26*1-Inputs!$E$24+1))/1 -> 3.5 | G94: =Inputs!$E$21*(1+Inputs!$E$23)^(G$27-1)*MAX(0,MIN(1,G$26*1-Inputs!$E$24+1))/1 -> 3.5 | H94: =Inputs!$E$21*(1+Inputs!$E$23)^(H$27-1)*MAX(0,MIN(1,H$26*1-Inputs!$E$24+1))/1 -> 3.5 | I94: =Inputs!$E$21*(1+Inputs!$E$23)^(I$27-1)*MAX(0,MIN(1,I$26*1-Inputs!$E$24+1))/1 -> 3.5 | J94: =Inputs!$E$21*(1+Inputs!$E$23)^(J$27-1)*MAX(0,MIN(1,J$26*1-Inputs!$E$24+1))/1 -> 3.5 | ... AL94: =Inputs!$E$21*(1+Inputs!$E$23)^(AL$27-1)*MAX(0,MIN(1,AL$26*1-Inputs!$E$24+1))/1 -> 3.5
A95: Total FTE | C95: =C94 -> 3.5 | D95: =D94 -> 3.5 | E95: =E94 -> 3.5 | F95: =F94 -> 3.5 | G95: =G94 -> 3.5 | H95: =H94 -> 3.5 | I95: =I94 -> 3.5 | J95: =J94 -> 3.5 | ... AL95: =AL94 -> 3.5
A97: Payroll cost (salary + taxes & benefits)
A98: Cafe staff — payroll cost | C98: =-C94*Inputs!$E$22/12*1*(1+Inputs!$E$25)*(1+Inputs!$E$26)^(C$27-1) -> -10453.333 | D98: =-D94*Inputs!$E$22/12*1*(1+Inputs!$E$25)*(1+Inputs!$E$26)^(D$27-1) -> -10453.333 | E98: =-E94*Inputs!$E$22/12*1*(1+Inputs!$E$25)*(1+Inputs!$E$26)^(E$27-1) -> -10453.333 | F98: =-F94*Inputs!$E$22/12*1*(1+Inputs!$E$25)*(1+Inputs!$E$26)^(F$27-1) -> -10453.333 | G98: =-G94*Inputs!$E$22/12*1*(1+Inputs!$E$25)*(1+Inputs!$E$26)^(G$27-1) -> -10453.333 | H98: =-H94*Inputs!$E$22/12*1*(1+Inputs!$E$25)*(1+Inputs!$E$26)^(H$27-1) -> -10453.333 | I98: =-I94*Inputs!$E$22/12*1*(1+Inputs!$E$25)*(1+Inputs!$E$26)^(I$27-1) -> -10453.333 | J98: =-J94*Inputs!$E$22/12*1*(1+Inputs!$E$25)*(1+Inputs!$E$26)^(J$27-1) -> -10453.333 | ... AL98: =-AL94*Inputs!$E$22/12*1*(1+Inputs!$E$25)*(1+Inputs!$E$26)^(AL$27-1) -> -11089.941
A99: Total payroll | C99: =C98 -> -10453.333 | D99: =D98 -> -10453.333 | E99: =E98 -> -10453.333 | F99: =F98 -> -10453.333 | G99: =G98 -> -10453.333 | H99: =H98 -> -10453.333 | I99: =I98 -> -10453.333 | J99: =J98 -> -10453.333 | ... AL99: =AL98 -> -11089.941

Sheet Checks
A1: Model checks | E1: =HYPERLINK("#'Cover'!A1","◂ Contents") -> ◂ Contents
A2: Live formulas: they re-run every time an input changes.
A3: Check | B3: Result | C3: What it tests
A4: Annual revenue ties to period detail | B4: =IF(ABS(SUM('P&L'!$B$5:$D$5)-SUM('P&L'!$C$34:$AL$34))<0.5,"PASS","FAIL") -> PASS | C4: Sum of annual revenue equals the sum of every period
A5: Annual net income ties to period detail | B5: =IF(ABS(SUM('P&L'!$B$11:$D$11)-SUM('P&L'!$C$53:$AL$53))<0.5,"PASS","FAIL") -> PASS | C5: Sum of annual net income equals the sum of every period
A6: EBITDA reconciliation | B6: =IF(ABS(SUM('P&L'!$C$44:$AL$44)-SUM('P&L'!$C$36:$AL$36)-SUM('P&L'!$C$43:$AL$43))<0.5,"PASS","FAIL") -> PASS | C6: EBITDA = gross profit + operating expenses (costs are negative)
A7: Cash roll-forward | B7: =IF(ABS(INDEX('P&L'!$C$83:$AL$83,36)-SUM('P&L'!$C$81:$AL$81))<0.5,"PASS","FAIL") -> PASS | C7: Closing cash = all net cash flows since the start (opening cash is zero)
A8: Scenario selector valid | B8: =IF(AND(ISNUMBER(Dashboard!B4),Dashboard!B4>=1,Dashboard!B4<=3,INT(Dashboard!B4)=Dashboard!B4),"PASS","FAIL") -> PASS | C8: Dashboard!B4 is 1, 2 or 3
A9: Scenario ordering of drivers | B9: =IF(AND(Inputs!$B$7<=Inputs!$C$7,Inputs!$C$7<=Inputs!$D$7,Inputs!$B$8>=Inputs!$C$8,Inputs!$C$8>=Inputs!$D$8,Inputs!$B$9<=Inputs!$C$9,Inputs!$C$9<=Inputs!$D$9,Inputs!$B$10<=Inputs!$C$10,Inputs!$C$10<=Inputs!$D$10,Inputs!$B$11<=Inputs!$C$11,Inputs!$C$11<=Inputs!$D$11,Inputs!$B$12<=Inputs!$C$12,Inputs!$C$12<=Inputs!$D$12,Inputs!$B$14>=Inputs!$C$14,Inputs!$C$14>=Inputs!$D$14,Inputs!$B$16>=Inputs!$C$16,Inputs!$C$16>=Inputs!$D$16,Inputs!$B$17>=Inputs!$C$17,Inputs!$C$17>=Inputs!$D$17,Inputs!$B$18>=Inputs!$C$18,Inputs!$C$18>=Inputs!$D$18,Inputs!$B$21<=Inputs!$C$21,Inputs!$C$21<=Inputs!$D$21,Inputs!$B$23<=Inputs!$C$23,Inputs!$C$23<=Inputs!$D$23),"PASS","FAIL") -> PASS | C9: Low / Base / High ordered the right way for every growth and cost driver
A10: Gross margin within 0–100% | B10: =IF(AND(MIN('P&L'!$B$7:$D$7)>=0,MAX('P&L'!$B$7:$D$7)<=1),"PASS","FAIL") -> PASS | C10: Gross margin never negative or above 100%
A11: Loan balance never negative | B11: =IF(MIN('P&L'!$C$66:$AL$66)>=-0.5,"PASS","FAIL") -> PASS | C11: Repayments never exceed the loan
A12: Funding table ties to the cash flow | B12: =IF(ABS('Break-even'!B18-('Break-even'!B16-'Break-even'!B10))<0.5,"PASS","FAIL") -> PASS | C12: Lowest cash balance = sources of funds − uses of funds up to that point
A13: No error values | B13: =IF(SUMPRODUCT(--ISERROR('P&L'!$C$26:$AL$99))+SUMPRODUCT(--ISERROR('P&L'!$B$3:$D$13))+SUMPRODUCT(--ISERROR('P&L'!$B$16:$D$22))+SUMPRODUCT(--ISERROR('Break-even'!$B$26:$D$33))+SUMPRODUCT(--ISERROR('Break-even'!$B$3:$D$35))+SUMPRODUCT(--ISERROR(Dashboard!$A$6:$W$39))=0,"PASS","FAIL") -> PASS | C13: No error values (divide-by-zero, broken references) on any calculation sheet
A14: Funding sufficient (cash ≥ 0) | B14: =IF(MIN('P&L'!$C$83:$AL$83)>=0,"PASS","WARN") -> PASS | C14: Business warning, not an error: cash dips below zero in this scenario
A16: Overall verdict | B16: =IF(COUNTIF(B4:B14,"FAIL")>0,"FAIL",IF(COUNTIF(B4:B14,"WARN")>0,"PASS WITH WARNINGS","PASS")) -> PASS
