Workbook

Sheet Cover
B2: Car wash financial model (planning)
B3: 5-year financial model · monthly detail · Low / Base / High scenarios · US dollars · Full plan
B5: Purpose | D5: Revenue and profit plan
B6: Active scenario | D6: =Dashboard!C4&" (change it on the Dashboard, cell B4)" -> Base (change it on the Dashboard, cell B4)
B7: Model checks | D7: =Checks!B25 -> PASS
B8: Prepared | D8: 21 October 2026
B10: Contents
C11: PRESENTATION
B12: 1 | C12: =HYPERLINK("#Dashboard!A1","Dashboard") -> Dashboard | D12: Scenario switch, key numbers, core financials
B13: 2 | C13: =HYPERLINK("#Summary!A1","Summary") -> Summary | D13: Income statement, cash flow and balance sheet — every year and any year by month
B14: 3 | C14: =HYPERLINK("#Scenarios!A1","Scenarios") -> Scenarios | D14: Low / Base / High side by side: drivers, outputs, charts
B15: 4 | C15: =HYPERLINK("#'Break-even'!A1","Break-even") -> Break-even | D15: Startup costs, funding need, break-even timing and revenue
B16: 5 | C16: =HYPERLINK("#Valuation!A1","Valuation") -> Valuation | D16: Free cash flow, DCF (perpetual growth and exit multiple), WACC × growth sensitivity
B17: 6 | C17: =HYPERLINK("#'Sources & Uses'!A1","Sources & Uses") -> Sources & Uses | D17: Funding structure, sources and uses of cash for the first months
B18: 7 | C18: =HYPERLINK("#KPIs!A1","KPIs") -> KPIs | D18: Financial ratios, DuPont analysis, industry metrics
C19: INPUTS
B20: 8 | C20: =HYPERLINK("#Inputs!A1","Inputs") -> Inputs | D20: Every assumption, Low / Base / High, with units and comments
C21: STATEMENTS
B22: 9 | C22: =HYPERLINK("#'P&L'!A1","P&L") -> P&L | D22: Annual profit & loss
B23: 10 | C23: =HYPERLINK("#'Cash Flow'!A1","Cash Flow") -> Cash Flow | D23: Annual cash flow statement
B24: 11 | C24: =HYPERLINK("#'Balance Sheet'!A1","Balance Sheet") -> Balance Sheet | D24: Balance sheet at year end
C25: CALCULATIONS
B26: 12 | C26: =HYPERLINK("#Monthly!A1","Monthly") -> Monthly | D26: Month-by-month engine of the model
B27: 13 | C27: =HYPERLINK("#Headcount!A1","Headcount") -> Headcount | D27: Team and payroll
B28: 14 | C28: =HYPERLINK("#'Scenario calc'!A1","Scenario calc") -> Scenario calc | D28: Low, Base and High calculated side by side for the Scenarios sheet
C29: CONTROL
B30: 15 | C30: =HYPERLINK("#Checks!A1","Checks") -> Checks | D30: Live integrity checks and the overall verdict
B32: How to read this file
C33: 1000 | D33: Input you can change — yellow cell with a blue figure (Inputs sheet and the view switches)
C34: 1000 | D34: Formula — calculated, do not overwrite
C35: 1000 | D35: Link to another sheet
C36: 1000 | D36: Active value the model uses (follows the scenario)

Sheet Dashboard
A1: Dashboard | W1: =HYPERLINK("#'Cover'!A1","◂ Contents") -> ◂ Contents
A2: Car wash financial model (planning)
A4: Active scenario | B4: 2 | C4: =CHOOSE(B4,"Low","Base","High") -> Base | D4: 1 = Low · 2 = Base · 3 = High — every sheet follows this cell | S4: Model checks | T4: =Checks!B25 -> PASS
A6: REVENUE · YEAR 5 | C6: EBITDA MARGIN · YEAR 5 | H6: NET INCOME · YEAR 5 | L6: LOWEST CASH BALANCE | P6: FUNDING REQUIRED | T6: ENTERPRISE VALUE (DCF)
A7: =F12 -> 2440877.2 | C7: =F17 -> 0.35310317 | H7: =F18 -> 364506.48 | L7: =F39 -> 131554.54 | P7: =F37 -> 5249445.5 | T7: =F44 -> -1277795.6
A8: =IF(AND(B12>0,F12>=0),(F12/B12)^(1/4)-1,"CAGR n/a") -> 0.19922093 | C8: =F16 -> 861881.48 | H8: =F19 -> 0.14933422 | L8: ='Break-even'!B6 -> 26 | P8: =IF(F38>=0,"Covered by funding raised",-F38) -> 149445.46 | T8: Average of 2 methods
A10: Core financials ($'000) — active scenario
B11: 1 | C11: 2 | D11: 3 | E11: 4 | F11: 5
A12: Revenue | B12: =SUMIF(Monthly!$C$5:$BJ$5,B$11,Monthly!$C$37:$BJ$37) -> 1180182.4 | C12: =SUMIF(Monthly!$C$5:$BJ$5,C$11,Monthly!$C$37:$BJ$37) -> 1805881.5 | D12: =SUMIF(Monthly!$C$5:$BJ$5,D$11,Monthly!$C$37:$BJ$37) -> 2080276.6 | E12: =SUMIF(Monthly!$C$5:$BJ$5,E$11,Monthly!$C$37:$BJ$37) -> 2282431.1 | F12: =SUMIF(Monthly!$C$5:$BJ$5,F$11,Monthly!$C$37:$BJ$37) -> 2440877.2
A13: Gross profit | B13: =SUMIF(Monthly!$C$5:$BJ$5,B$11,Monthly!$C$46:$BJ$46) -> 999760.79 | C13: =SUMIF(Monthly!$C$5:$BJ$5,C$11,Monthly!$C$46:$BJ$46) -> 1517202.4 | D13: =SUMIF(Monthly!$C$5:$BJ$5,D$11,Monthly!$C$46:$BJ$46) -> 1736853.9 | E13: =SUMIF(Monthly!$C$5:$BJ$5,E$11,Monthly!$C$46:$BJ$46) -> 1897646.6 | F13: =SUMIF(Monthly!$C$5:$BJ$5,F$11,Monthly!$C$46:$BJ$46) -> 2022782
A14: Gross margin | B14: =IF(B12=0,0,B13/B12) -> 0.84712397 | C14: =IF(C12=0,0,C13/C12) -> 0.84014507 | D14: =IF(D12=0,0,D13/D12) -> 0.83491491 | E14: =IF(E12=0,0,E13/E12) -> 0.83141464 | F14: =IF(F12=0,0,F13/F12) -> 0.82871109
A15: Operating expenses | B15: =SUMIF(Monthly!$C$5:$BJ$5,B$11,Monthly!$C$54:$BJ$54) -> -1123040 | C15: =SUMIF(Monthly!$C$5:$BJ$5,C$11,Monthly!$C$54:$BJ$54) -> -1123611.2 | D15: =SUMIF(Monthly!$C$5:$BJ$5,D$11,Monthly!$C$54:$BJ$54) -> -1130823.5 | E15: =SUMIF(Monthly!$C$5:$BJ$5,E$11,Monthly!$C$54:$BJ$54) -> -1143551.4 | F15: =SUMIF(Monthly!$C$5:$BJ$5,F$11,Monthly!$C$54:$BJ$54) -> -1160900.5
A16: EBITDA | B16: =SUMIF(Monthly!$C$5:$BJ$5,B$11,Monthly!$C$55:$BJ$55) -> -123279.21 | C16: =SUMIF(Monthly!$C$5:$BJ$5,C$11,Monthly!$C$55:$BJ$55) -> 393591.21 | D16: =SUMIF(Monthly!$C$5:$BJ$5,D$11,Monthly!$C$55:$BJ$55) -> 606030.41 | E16: =SUMIF(Monthly!$C$5:$BJ$5,E$11,Monthly!$C$55:$BJ$55) -> 754095.19 | F16: =SUMIF(Monthly!$C$5:$BJ$5,F$11,Monthly!$C$55:$BJ$55) -> 861881.48
A17: EBITDA margin | B17: =IF(B12=0,0,B16/B12) -> -0.10445776 | C17: =IF(C12=0,0,C16/C12) -> 0.21794964 | D17: =IF(D12=0,0,D16/D12) -> 0.29132204 | E17: =IF(E12=0,0,E16/E12) -> 0.33039122 | F17: =IF(F12=0,0,F16/F12) -> 0.35310317
A18: Net income | B18: =SUMIF(Monthly!$C$5:$BJ$5,B$11,Monthly!$C$64:$BJ$64) -> -709232.33 | C18: =SUMIF(Monthly!$C$5:$BJ$5,C$11,Monthly!$C$64:$BJ$64) -> -170283.79 | D18: =SUMIF(Monthly!$C$5:$BJ$5,D$11,Monthly!$C$64:$BJ$64) -> 64322.078 | E18: =SUMIF(Monthly!$C$5:$BJ$5,E$11,Monthly!$C$64:$BJ$64) -> 234553.52 | F18: =SUMIF(Monthly!$C$5:$BJ$5,F$11,Monthly!$C$64:$BJ$64) -> 364506.48
A19: Net margin | B19: =IF(B12=0,0,B18/B12) -> -0.60095146 | C19: =IF(C12=0,0,C18/C12) -> -0.094294003 | D19: =IF(D12=0,0,D18/D12) -> 0.030919964 | E19: =IF(E12=0,0,E18/E12) -> 0.10276478 | F19: =IF(F12=0,0,F18/F12) -> 0.14933422
A20: Operating cash flow | B20: =SUMIF(Monthly!$C$5:$BJ$5,B$11,Monthly!$C$92:$BJ$92) -> -369557.79 | C20: =SUMIF(Monthly!$C$5:$BJ$5,C$11,Monthly!$C$92:$BJ$92) -> 174478.45 | D20: =SUMIF(Monthly!$C$5:$BJ$5,D$11,Monthly!$C$92:$BJ$92) -> 412515.86 | E20: =SUMIF(Monthly!$C$5:$BJ$5,E$11,Monthly!$C$92:$BJ$92) -> 586141.12 | F20: =SUMIF(Monthly!$C$5:$BJ$5,F$11,Monthly!$C$92:$BJ$92) -> 719465.28
A21: Investing cash flow | B21: =SUMIF(Monthly!$C$5:$BJ$5,B$11,Monthly!$C$93:$BJ$93) -> -4100000 | C21: =SUMIF(Monthly!$C$5:$BJ$5,C$11,Monthly!$C$93:$BJ$93) -> -40000 | D21: =SUMIF(Monthly!$C$5:$BJ$5,D$11,Monthly!$C$93:$BJ$93) -> -40000 | E21: =SUMIF(Monthly!$C$5:$BJ$5,E$11,Monthly!$C$93:$BJ$93) -> -40000 | F21: =SUMIF(Monthly!$C$5:$BJ$5,F$11,Monthly!$C$93:$BJ$93) -> -40000
A22: Financing cash flow | B22: =SUMIF(Monthly!$C$5:$BJ$5,B$11,Monthly!$C$95:$BJ$95) -> 4825000 | C22: =SUMIF(Monthly!$C$5:$BJ$5,C$11,Monthly!$C$95:$BJ$95) -> -300000 | D22: =SUMIF(Monthly!$C$5:$BJ$5,D$11,Monthly!$C$95:$BJ$95) -> -300000 | E22: =SUMIF(Monthly!$C$5:$BJ$5,E$11,Monthly!$C$95:$BJ$95) -> -300000 | F22: =SUMIF(Monthly!$C$5:$BJ$5,F$11,Monthly!$C$95:$BJ$95) -> -300000
A23: Net change in cash | B23: =SUMIF(Monthly!$C$5:$BJ$5,B$11,Monthly!$C$96:$BJ$96) -> 355442.21 | C23: =SUMIF(Monthly!$C$5:$BJ$5,C$11,Monthly!$C$96:$BJ$96) -> -165521.55 | D23: =SUMIF(Monthly!$C$5:$BJ$5,D$11,Monthly!$C$96:$BJ$96) -> 72515.855 | E23: =SUMIF(Monthly!$C$5:$BJ$5,E$11,Monthly!$C$96:$BJ$96) -> 246141.12 | F23: =SUMIF(Monthly!$C$5:$BJ$5,F$11,Monthly!$C$96:$BJ$96) -> 379465.28
A24: Year-end cash | B24: =INDEX(Monthly!$C$98:$BJ$98,B$11*12) -> 355442.21 | C24: =INDEX(Monthly!$C$98:$BJ$98,C$11*12) -> 189920.66 | D24: =INDEX(Monthly!$C$98:$BJ$98,D$11*12) -> 262436.52 | E24: =INDEX(Monthly!$C$98:$BJ$98,E$11*12) -> 508577.64 | F24: =INDEX(Monthly!$C$98:$BJ$98,F$11*12) -> 888042.92
A26: Car wash metrics
B27: 1 | C27: 2 | D27: 3 | E27: 4 | F27: 5
A28: Unlimited members (year end) | B28: =KPIs!B29 -> 972.08918 | C28: =KPIs!C29 -> 1644.3434 | D28: =KPIs!D29 -> 2081.656 | E28: =KPIs!E29 -> 2376.2884 | F28: =KPIs!F29 -> 2584.8337
A29: Washes per operating day | B29: =KPIs!B37 -> 255.65215 | C29: =KPIs!C37 -> 401.36881 | D29: =KPIs!D37 -> 466.96809 | E29: =KPIs!E37 -> 510.31287 | F29: =KPIs!F37 -> 540.17969
A30: Tunnel capacity used | B30: =KPIs!B39 -> 0.30183253 | C30: =KPIs!C39 -> 0.47387108 | D30: =KPIs!D39 -> 0.55132006 | E30: =KPIs!E39 -> 0.60249454 | F30: =KPIs!F39 -> 0.63775642
A31: Revenue per wash | B31: =KPIs!B45 -> 13.265403 | C31: =KPIs!C45 -> 12.929043 | D31: =KPIs!D45 -> 12.801317 | E31: =KPIs!E45 -> 12.852331 | F31: =KPIs!F45 -> 12.984596
A32: Team (FTE, year end) | B32: =INDEX(Headcount!$C$10:$BJ$10,B$27*12) -> 11 | C32: =INDEX(Headcount!$C$10:$BJ$10,C$27*12) -> 11 | D32: =INDEX(Headcount!$C$10:$BJ$10,D$27*12) -> 11 | E32: =INDEX(Headcount!$C$10:$BJ$10,E$27*12) -> 11 | F32: =INDEX(Headcount!$C$10:$BJ$10,F$27*12) -> 11
A34: Funding & valuation ($'000) — active scenario
A35: Equity raised | F35: =Inputs!$E$67 -> 2100000
A36: Loan drawn | F36: =Inputs!$E$68 -> 3000000
A37: Funding required (incl. cash buffer) | F37: ='Break-even'!B12 -> 5249445.5
A38: Funding surplus / (shortfall) | F38: ='Break-even'!B17 -> -149445.46
A39: ="Lowest cash balance (month "&'Break-even'!B6&")" -> Lowest cash balance (month 26) | F39: ='Break-even'!B18 -> 131554.54
A40: First month with positive EBITDA | F40: ='Break-even'!B21 -> 8
A41: Cash invested paid back | F41: ='Break-even'!B23 -> Not within horizon
A42: Enterprise value — perpetual growth | F42: =Valuation!B27 -> -1267217.7
A43: Enterprise value — exit multiple | F43: =Valuation!C27 -> -1288373.6
A44: Enterprise value — average | F44: =Valuation!B30 -> -1277795.6

Sheet Summary
A1: Financial statements summary | U1: =HYPERLINK("#'Cover'!A1","◂ Contents") -> ◂ Contents
A2: Car wash financial model (planning) | P2: Select detailed year: | R2: 1
A5: Income statement ($'000) — by year | H5: ="Income statement ($'000) — Year "&$R$2&", by month" -> Income statement ($'000) — Year 1, by month
B6: 1 | C6: 2 | D6: 3 | E6: 4 | F6: 5 | H6: =INDEX(Monthly!$C$4:$BJ$4,($R$2-1)*12+1) -> 1 | I6: =INDEX(Monthly!$C$4:$BJ$4,($R$2-1)*12+2) -> 2 | J6: =INDEX(Monthly!$C$4:$BJ$4,($R$2-1)*12+3) -> 3 | K6: =INDEX(Monthly!$C$4:$BJ$4,($R$2-1)*12+4) -> 4 | L6: =INDEX(Monthly!$C$4:$BJ$4,($R$2-1)*12+5) -> 5 | M6: =INDEX(Monthly!$C$4:$BJ$4,($R$2-1)*12+6) -> 6 | N6: =INDEX(Monthly!$C$4:$BJ$4,($R$2-1)*12+7) -> 7 | O6: =INDEX(Monthly!$C$4:$BJ$4,($R$2-1)*12+8) -> 8 | P6: =INDEX(Monthly!$C$4:$BJ$4,($R$2-1)*12+9) -> 9 | Q6: =INDEX(Monthly!$C$4:$BJ$4,($R$2-1)*12+10) -> 10 | R6: =INDEX(Monthly!$C$4:$BJ$4,($R$2-1)*12+11) -> 11 | S6: =INDEX(Monthly!$C$4:$BJ$4,($R$2-1)*12+12) -> 12
A7: Revenue | B7: ='P&L'!B5 -> 1180182.4 | C7: ='P&L'!C5 -> 1805881.5 | D7: ='P&L'!D5 -> 2080276.6 | E7: ='P&L'!E5 -> 2282431.1 | F7: ='P&L'!F5 -> 2440877.2 | H7: =INDEX(Monthly!$C$37:$BJ$37,($R$2-1)*12+1) -> 47943.358 | I7: =INDEX(Monthly!$C$37:$BJ$37,($R$2-1)*12+2) -> 54448.936 | J7: =INDEX(Monthly!$C$37:$BJ$37,($R$2-1)*12+3) -> 72773.402 | K7: =INDEX(Monthly!$C$37:$BJ$37,($R$2-1)*12+4) -> 81051.899 | L7: =INDEX(Monthly!$C$37:$BJ$37,($R$2-1)*12+5) -> 89490.276 | M7: =INDEX(Monthly!$C$37:$BJ$37,($R$2-1)*12+6) -> 98082.139 | N7: =INDEX(Monthly!$C$37:$BJ$37,($R$2-1)*12+7) -> 106821.35 | O7: =INDEX(Monthly!$C$37:$BJ$37,($R$2-1)*12+8) -> 115702.01 | P7: =INDEX(Monthly!$C$37:$BJ$37,($R$2-1)*12+9) -> 124718.46 | Q7: =INDEX(Monthly!$C$37:$BJ$37,($R$2-1)*12+10) -> 133865.28 | R7: =INDEX(Monthly!$C$37:$BJ$37,($R$2-1)*12+11) -> 136545.55 | S7: =INDEX(Monthly!$C$37:$BJ$37,($R$2-1)*12+12) -> 118739.73
A8: Cost of sales | B8: ='P&L'!B6 -> -180421.6 | C8: ='P&L'!C6 -> -288679.06 | D8: ='P&L'!D6 -> -343422.65 | E8: ='P&L'!E6 -> -384784.48 | F8: ='P&L'!F6 -> -418095.19 | H8: =INDEX(Monthly!$C$45:$BJ$45,($R$2-1)*12+1) -> -7071.9457 | I8: =INDEX(Monthly!$C$45:$BJ$45,($R$2-1)*12+2) -> -8031.4488 | J8: =INDEX(Monthly!$C$45:$BJ$45,($R$2-1)*12+3) -> -11076.835 | K8: =INDEX(Monthly!$C$45:$BJ$45,($R$2-1)*12+4) -> -12361.697 | L8: =INDEX(Monthly!$C$45:$BJ$45,($R$2-1)*12+5) -> -13678.718 | M8: =INDEX(Monthly!$C$45:$BJ$45,($R$2-1)*12+6) -> -15026.614 | N8: =INDEX(Monthly!$C$45:$BJ$45,($R$2-1)*12+7) -> -16404.147 | O8: =INDEX(Monthly!$C$45:$BJ$45,($R$2-1)*12+8) -> -17810.134 | P8: =INDEX(Monthly!$C$45:$BJ$45,($R$2-1)*12+9) -> -19243.436 | Q8: =INDEX(Monthly!$C$45:$BJ$45,($R$2-1)*12+10) -> -20702.96 | R8: =INDEX(Monthly!$C$45:$BJ$45,($R$2-1)*12+11) -> -21242.097 | S8: =INDEX(Monthly!$C$45:$BJ$45,($R$2-1)*12+12) -> -17771.565
A9: Gross profit | B9: ='P&L'!B7 -> 999760.79 | C9: ='P&L'!C7 -> 1517202.4 | D9: ='P&L'!D7 -> 1736853.9 | E9: ='P&L'!E7 -> 1897646.6 | F9: ='P&L'!F7 -> 2022782 | H9: =INDEX(Monthly!$C$46:$BJ$46,($R$2-1)*12+1) -> 40871.412 | I9: =INDEX(Monthly!$C$46:$BJ$46,($R$2-1)*12+2) -> 46417.487 | J9: =INDEX(Monthly!$C$46:$BJ$46,($R$2-1)*12+3) -> 61696.567 | K9: =INDEX(Monthly!$C$46:$BJ$46,($R$2-1)*12+4) -> 68690.202 | L9: =INDEX(Monthly!$C$46:$BJ$46,($R$2-1)*12+5) -> 75811.558 | M9: =INDEX(Monthly!$C$46:$BJ$46,($R$2-1)*12+6) -> 83055.526 | N9: =INDEX(Monthly!$C$46:$BJ$46,($R$2-1)*12+7) -> 90417.201 | O9: =INDEX(Monthly!$C$46:$BJ$46,($R$2-1)*12+8) -> 97891.875 | P9: =INDEX(Monthly!$C$46:$BJ$46,($R$2-1)*12+9) -> 105475.03 | Q9: =INDEX(Monthly!$C$46:$BJ$46,($R$2-1)*12+10) -> 113162.32 | R9: =INDEX(Monthly!$C$46:$BJ$46,($R$2-1)*12+11) -> 115303.45 | S9: =INDEX(Monthly!$C$46:$BJ$46,($R$2-1)*12+12) -> 100968.16
A10: Gross margin | B10: ='P&L'!B8 -> 0.84712397 | C10: ='P&L'!C8 -> 0.84014507 | D10: ='P&L'!D8 -> 0.83491491 | E10: ='P&L'!E8 -> 0.83141464 | F10: ='P&L'!F8 -> 0.82871109 | H10: =IF(H7=0,0,H9/H7) -> 0.85249373 | I10: =IF(I7=0,0,I9/I7) -> 0.85249576 | J10: =IF(J7=0,0,J9/J7) -> 0.84779006 | K10: =IF(K7=0,0,K9/K7) -> 0.84748418 | L10: =IF(L7=0,0,L9/L7) -> 0.84714855 | M10: =IF(M7=0,0,M9/M7) -> 0.84679562 | N10: =IF(N7=0,0,N9/N7) -> 0.84643381 | O10: =IF(O7=0,0,O9/O7) -> 0.84606893 | ... S10: =IF(S7=0,0,S9/S7) -> 0.85033177
A11: Total operating expenses | B11: ='P&L'!B14 -> -1123040 | C11: ='P&L'!C14 -> -1123611.2 | D11: ='P&L'!D14 -> -1130823.5 | E11: ='P&L'!E14 -> -1143551.4 | F11: ='P&L'!F14 -> -1160900.5 | H11: =INDEX(Monthly!$C$54:$BJ$54,($R$2-1)*12+1) -> -93586.667 | I11: =INDEX(Monthly!$C$54:$BJ$54,($R$2-1)*12+2) -> -93586.667 | J11: =INDEX(Monthly!$C$54:$BJ$54,($R$2-1)*12+3) -> -93586.667 | K11: =INDEX(Monthly!$C$54:$BJ$54,($R$2-1)*12+4) -> -93586.667 | L11: =INDEX(Monthly!$C$54:$BJ$54,($R$2-1)*12+5) -> -93586.667 | M11: =INDEX(Monthly!$C$54:$BJ$54,($R$2-1)*12+6) -> -93586.667 | N11: =INDEX(Monthly!$C$54:$BJ$54,($R$2-1)*12+7) -> -93586.667 | O11: =INDEX(Monthly!$C$54:$BJ$54,($R$2-1)*12+8) -> -93586.667 | P11: =INDEX(Monthly!$C$54:$BJ$54,($R$2-1)*12+9) -> -93586.667 | Q11: =INDEX(Monthly!$C$54:$BJ$54,($R$2-1)*12+10) -> -93586.667 | R11: =INDEX(Monthly!$C$54:$BJ$54,($R$2-1)*12+11) -> -93586.667 | S11: =INDEX(Monthly!$C$54:$BJ$54,($R$2-1)*12+12) -> -93586.667
A12: EBITDA | B12: ='P&L'!B15 -> -123279.21 | C12: ='P&L'!C15 -> 393591.21 | D12: ='P&L'!D15 -> 606030.41 | E12: ='P&L'!E15 -> 754095.19 | F12: ='P&L'!F15 -> 861881.48 | H12: =INDEX(Monthly!$C$55:$BJ$55,($R$2-1)*12+1) -> -52715.254 | I12: =INDEX(Monthly!$C$55:$BJ$55,($R$2-1)*12+2) -> -47169.18 | J12: =INDEX(Monthly!$C$55:$BJ$55,($R$2-1)*12+3) -> -31890.1 | K12: =INDEX(Monthly!$C$55:$BJ$55,($R$2-1)*12+4) -> -24896.465 | L12: =INDEX(Monthly!$C$55:$BJ$55,($R$2-1)*12+5) -> -17775.109 | M12: =INDEX(Monthly!$C$55:$BJ$55,($R$2-1)*12+6) -> -10531.141 | N12: =INDEX(Monthly!$C$55:$BJ$55,($R$2-1)*12+7) -> -3169.4659 | O12: =INDEX(Monthly!$C$55:$BJ$55,($R$2-1)*12+8) -> 4305.2082 | P12: =INDEX(Monthly!$C$55:$BJ$55,($R$2-1)*12+9) -> 11888.361 | Q12: =INDEX(Monthly!$C$55:$BJ$55,($R$2-1)*12+10) -> 19575.654 | R12: =INDEX(Monthly!$C$55:$BJ$55,($R$2-1)*12+11) -> 21716.787 | S12: =INDEX(Monthly!$C$55:$BJ$55,($R$2-1)*12+12) -> 7381.4964
A13: EBITDA margin | B13: ='P&L'!B16 -> -0.10445776 | C13: ='P&L'!C16 -> 0.21794964 | D13: ='P&L'!D16 -> 0.29132204 | E13: ='P&L'!E16 -> 0.33039122 | F13: ='P&L'!F16 -> 0.35310317 | H13: =IF(H7=0,0,H12/H7) -> -1.099532 | I13: =IF(I7=0,0,I12/I7) -> -0.86630122 | J13: =IF(J7=0,0,J12/J7) -> -0.43821093 | K13: =IF(K7=0,0,K12/K7) -> -0.30716695 | L13: =IF(L7=0,0,L12/L7) -> -0.19862615 | M13: =IF(M7=0,0,M12/M7) -> -0.10737063 | N13: =IF(N7=0,0,N12/N7) -> -0.029670716 | O13: =IF(O7=0,0,O12/O7) -> 0.03720945 | ... S13: =IF(S7=0,0,S12/S7) -> 0.062165347
A14: Depreciation | B14: ='P&L'!B17 -> -341666.67 | C14: ='P&L'!C17 -> -345000 | D14: ='P&L'!D17 -> -348333.33 | E14: ='P&L'!E17 -> -351666.67 | F14: ='P&L'!F17 -> -355000 | H14: =INDEX(Monthly!$C$73:$BJ$73,($R$2-1)*12+1) -> -28472.222 | I14: =INDEX(Monthly!$C$73:$BJ$73,($R$2-1)*12+2) -> -28472.222 | J14: =INDEX(Monthly!$C$73:$BJ$73,($R$2-1)*12+3) -> -28472.222 | K14: =INDEX(Monthly!$C$73:$BJ$73,($R$2-1)*12+4) -> -28472.222 | L14: =INDEX(Monthly!$C$73:$BJ$73,($R$2-1)*12+5) -> -28472.222 | M14: =INDEX(Monthly!$C$73:$BJ$73,($R$2-1)*12+6) -> -28472.222 | N14: =INDEX(Monthly!$C$73:$BJ$73,($R$2-1)*12+7) -> -28472.222 | O14: =INDEX(Monthly!$C$73:$BJ$73,($R$2-1)*12+8) -> -28472.222 | P14: =INDEX(Monthly!$C$73:$BJ$73,($R$2-1)*12+9) -> -28472.222 | Q14: =INDEX(Monthly!$C$73:$BJ$73,($R$2-1)*12+10) -> -28472.222 | R14: =INDEX(Monthly!$C$73:$BJ$73,($R$2-1)*12+11) -> -28472.222 | S14: =INDEX(Monthly!$C$73:$BJ$73,($R$2-1)*12+12) -> -28472.222
A15: EBIT | B15: ='P&L'!B18 -> -464945.87 | C15: ='P&L'!C18 -> 48591.208 | D15: ='P&L'!D18 -> 257697.08 | E15: ='P&L'!E18 -> 402428.52 | F15: ='P&L'!F18 -> 506881.48 | H15: =INDEX(Monthly!$C$58:$BJ$58,($R$2-1)*12+1) -> -81187.477 | I15: =INDEX(Monthly!$C$58:$BJ$58,($R$2-1)*12+2) -> -75641.402 | J15: =INDEX(Monthly!$C$58:$BJ$58,($R$2-1)*12+3) -> -60362.322 | K15: =INDEX(Monthly!$C$58:$BJ$58,($R$2-1)*12+4) -> -53368.687 | L15: =INDEX(Monthly!$C$58:$BJ$58,($R$2-1)*12+5) -> -46247.331 | M15: =INDEX(Monthly!$C$58:$BJ$58,($R$2-1)*12+6) -> -39003.363 | N15: =INDEX(Monthly!$C$58:$BJ$58,($R$2-1)*12+7) -> -31641.688 | O15: =INDEX(Monthly!$C$58:$BJ$58,($R$2-1)*12+8) -> -24167.014 | P15: =INDEX(Monthly!$C$58:$BJ$58,($R$2-1)*12+9) -> -16583.861 | Q15: =INDEX(Monthly!$C$58:$BJ$58,($R$2-1)*12+10) -> -8896.568 | R15: =INDEX(Monthly!$C$58:$BJ$58,($R$2-1)*12+11) -> -6755.4353 | S15: =INDEX(Monthly!$C$58:$BJ$58,($R$2-1)*12+12) -> -21090.726
A16: Interest | B16: ='P&L'!B19 -> -244286.46 | C16: ='P&L'!C19 -> -218875 | D16: ='P&L'!D19 -> -193375 | E16: ='P&L'!E19 -> -167875 | F16: ='P&L'!F19 -> -142375 | H16: =INDEX(Monthly!$C$59:$BJ$59,($R$2-1)*12+1) -> -21250 | I16: =INDEX(Monthly!$C$59:$BJ$59,($R$2-1)*12+2) -> -21161.458 | J16: =INDEX(Monthly!$C$59:$BJ$59,($R$2-1)*12+3) -> -20984.375 | K16: =INDEX(Monthly!$C$59:$BJ$59,($R$2-1)*12+4) -> -20807.292 | L16: =INDEX(Monthly!$C$59:$BJ$59,($R$2-1)*12+5) -> -20630.208 | M16: =INDEX(Monthly!$C$59:$BJ$59,($R$2-1)*12+6) -> -20453.125 | N16: =INDEX(Monthly!$C$59:$BJ$59,($R$2-1)*12+7) -> -20276.042 | O16: =INDEX(Monthly!$C$59:$BJ$59,($R$2-1)*12+8) -> -20098.958 | P16: =INDEX(Monthly!$C$59:$BJ$59,($R$2-1)*12+9) -> -19921.875 | Q16: =INDEX(Monthly!$C$59:$BJ$59,($R$2-1)*12+10) -> -19744.792 | R16: =INDEX(Monthly!$C$59:$BJ$59,($R$2-1)*12+11) -> -19567.708 | S16: =INDEX(Monthly!$C$59:$BJ$59,($R$2-1)*12+12) -> -19390.625
A17: Pre-tax income | B17: ='P&L'!B20 -> -709232.33 | C17: ='P&L'!C20 -> -170283.79 | D17: ='P&L'!D20 -> 64322.078 | E17: ='P&L'!E20 -> 234553.52 | F17: ='P&L'!F20 -> 364506.48 | H17: =INDEX(Monthly!$C$60:$BJ$60,($R$2-1)*12+1) -> -102437.48 | I17: =INDEX(Monthly!$C$60:$BJ$60,($R$2-1)*12+2) -> -96802.86 | J17: =INDEX(Monthly!$C$60:$BJ$60,($R$2-1)*12+3) -> -81346.697 | K17: =INDEX(Monthly!$C$60:$BJ$60,($R$2-1)*12+4) -> -74175.979 | L17: =INDEX(Monthly!$C$60:$BJ$60,($R$2-1)*12+5) -> -66877.539 | M17: =INDEX(Monthly!$C$60:$BJ$60,($R$2-1)*12+6) -> -59456.488 | N17: =INDEX(Monthly!$C$60:$BJ$60,($R$2-1)*12+7) -> -51917.73 | O17: =INDEX(Monthly!$C$60:$BJ$60,($R$2-1)*12+8) -> -44265.972 | P17: =INDEX(Monthly!$C$60:$BJ$60,($R$2-1)*12+9) -> -36505.736 | Q17: =INDEX(Monthly!$C$60:$BJ$60,($R$2-1)*12+10) -> -28641.36 | R17: =INDEX(Monthly!$C$60:$BJ$60,($R$2-1)*12+11) -> -26323.144 | S17: =INDEX(Monthly!$C$60:$BJ$60,($R$2-1)*12+12) -> -40481.351
A18: Income tax | B18: ='P&L'!B21 -> 0 | C18: ='P&L'!C21 -> 0 | D18: ='P&L'!D21 -> 0 | E18: ='P&L'!E21 -> 0 | F18: ='P&L'!F21 -> 0 | H18: =INDEX(Monthly!$C$63:$BJ$63,($R$2-1)*12+1) -> 0 | I18: =INDEX(Monthly!$C$63:$BJ$63,($R$2-1)*12+2) -> 0 | J18: =INDEX(Monthly!$C$63:$BJ$63,($R$2-1)*12+3) -> 0 | K18: =INDEX(Monthly!$C$63:$BJ$63,($R$2-1)*12+4) -> 0 | L18: =INDEX(Monthly!$C$63:$BJ$63,($R$2-1)*12+5) -> 0 | M18: =INDEX(Monthly!$C$63:$BJ$63,($R$2-1)*12+6) -> 0 | N18: =INDEX(Monthly!$C$63:$BJ$63,($R$2-1)*12+7) -> 0 | O18: =INDEX(Monthly!$C$63:$BJ$63,($R$2-1)*12+8) -> 0 | P18: =INDEX(Monthly!$C$63:$BJ$63,($R$2-1)*12+9) -> 0 | Q18: =INDEX(Monthly!$C$63:$BJ$63,($R$2-1)*12+10) -> 0 | R18: =INDEX(Monthly!$C$63:$BJ$63,($R$2-1)*12+11) -> 0 | S18: =INDEX(Monthly!$C$63:$BJ$63,($R$2-1)*12+12) -> 0
A19: Net income | B19: ='P&L'!B22 -> -709232.33 | C19: ='P&L'!C22 -> -170283.79 | D19: ='P&L'!D22 -> 64322.078 | E19: ='P&L'!E22 -> 234553.52 | F19: ='P&L'!F22 -> 364506.48 | H19: =INDEX(Monthly!$C$64:$BJ$64,($R$2-1)*12+1) -> -102437.48 | I19: =INDEX(Monthly!$C$64:$BJ$64,($R$2-1)*12+2) -> -96802.86 | J19: =INDEX(Monthly!$C$64:$BJ$64,($R$2-1)*12+3) -> -81346.697 | K19: =INDEX(Monthly!$C$64:$BJ$64,($R$2-1)*12+4) -> -74175.979 | L19: =INDEX(Monthly!$C$64:$BJ$64,($R$2-1)*12+5) -> -66877.539 | M19: =INDEX(Monthly!$C$64:$BJ$64,($R$2-1)*12+6) -> -59456.488 | N19: =INDEX(Monthly!$C$64:$BJ$64,($R$2-1)*12+7) -> -51917.73 | O19: =INDEX(Monthly!$C$64:$BJ$64,($R$2-1)*12+8) -> -44265.972 | P19: =INDEX(Monthly!$C$64:$BJ$64,($R$2-1)*12+9) -> -36505.736 | Q19: =INDEX(Monthly!$C$64:$BJ$64,($R$2-1)*12+10) -> -28641.36 | R19: =INDEX(Monthly!$C$64:$BJ$64,($R$2-1)*12+11) -> -26323.144 | S19: =INDEX(Monthly!$C$64:$BJ$64,($R$2-1)*12+12) -> -40481.351
A20: Net margin | B20: ='P&L'!B23 -> -0.60095146 | C20: ='P&L'!C23 -> -0.094294003 | D20: ='P&L'!D23 -> 0.030919964 | E20: ='P&L'!E23 -> 0.10276478 | F20: ='P&L'!F23 -> 0.14933422 | H20: =IF(H7=0,0,H19/H7) -> -2.1366354 | I20: =IF(I7=0,0,I19/I7) -> -1.777865 | J20: =IF(J7=0,0,J19/J7) -> -1.1178081 | K20: =IF(K7=0,0,K19/K7) -> -0.91516645 | L20: =IF(L7=0,0,L19/L7) -> -0.74731627 | M20: =IF(M7=0,0,M19/M7) -> -0.60619078 | N20: =IF(N7=0,0,N19/N7) -> -0.48602391 | O20: =IF(O7=0,0,O19/O7) -> -0.38258603 | ... S20: =IF(S7=0,0,S19/S7) -> -0.34092508
A22: Cash flow ($'000) — by year | H22: ="Cash flow ($'000) — Year "&$R$2&", by month" -> Cash flow ($'000) — Year 1, by month
B23: 1 | C23: 2 | D23: 3 | E23: 4 | F23: 5 | H23: =INDEX(Monthly!$C$4:$BJ$4,($R$2-1)*12+1) -> 1 | I23: =INDEX(Monthly!$C$4:$BJ$4,($R$2-1)*12+2) -> 2 | J23: =INDEX(Monthly!$C$4:$BJ$4,($R$2-1)*12+3) -> 3 | K23: =INDEX(Monthly!$C$4:$BJ$4,($R$2-1)*12+4) -> 4 | L23: =INDEX(Monthly!$C$4:$BJ$4,($R$2-1)*12+5) -> 5 | M23: =INDEX(Monthly!$C$4:$BJ$4,($R$2-1)*12+6) -> 6 | N23: =INDEX(Monthly!$C$4:$BJ$4,($R$2-1)*12+7) -> 7 | O23: =INDEX(Monthly!$C$4:$BJ$4,($R$2-1)*12+8) -> 8 | P23: =INDEX(Monthly!$C$4:$BJ$4,($R$2-1)*12+9) -> 9 | Q23: =INDEX(Monthly!$C$4:$BJ$4,($R$2-1)*12+10) -> 10 | R23: =INDEX(Monthly!$C$4:$BJ$4,($R$2-1)*12+11) -> 11 | S23: =INDEX(Monthly!$C$4:$BJ$4,($R$2-1)*12+12) -> 12
A24: Operating cash flow | B24: ='Cash Flow'!B10 -> -369557.79 | C24: ='Cash Flow'!C10 -> 174478.45 | D24: ='Cash Flow'!D10 -> 412515.86 | E24: ='Cash Flow'!E10 -> 586141.12 | F24: ='Cash Flow'!F10 -> 719465.28 | H24: =INDEX(Monthly!$C$92:$BJ$92,($R$2-1)*12+1) -> -74804.163 | I24: =INDEX(Monthly!$C$92:$BJ$92,($R$2-1)*12+2) -> -68444.509 | J24: =INDEX(Monthly!$C$92:$BJ$92,($R$2-1)*12+3) -> -53080.977 | K24: =INDEX(Monthly!$C$92:$BJ$92,($R$2-1)*12+4) -> -45827.369 | L24: =INDEX(Monthly!$C$92:$BJ$92,($R$2-1)*12+5) -> -38528.868 | M24: =INDEX(Monthly!$C$92:$BJ$92,($R$2-1)*12+6) -> -31107.758 | N24: =INDEX(Monthly!$C$92:$BJ$92,($R$2-1)*12+7) -> -23568.944 | O24: =INDEX(Monthly!$C$92:$BJ$92,($R$2-1)*12+8) -> -15917.132 | P24: =INDEX(Monthly!$C$92:$BJ$92,($R$2-1)*12+9) -> -8156.8434 | Q24: =INDEX(Monthly!$C$92:$BJ$92,($R$2-1)*12+10) -> -292.41714 | R24: =INDEX(Monthly!$C$92:$BJ$92,($R$2-1)*12+11) -> 2150.1061 | S24: =INDEX(Monthly!$C$92:$BJ$92,($R$2-1)*12+12) -> -11978.918
A25: Capital spending | B25: ='Cash Flow'!B11 -> -4100000 | C25: ='Cash Flow'!C11 -> -40000 | D25: ='Cash Flow'!D11 -> -40000 | E25: ='Cash Flow'!E11 -> -40000 | F25: ='Cash Flow'!F11 -> -40000 | H25: =INDEX(Monthly!$C$93:$BJ$93,($R$2-1)*12+1) -> -4100000 | I25: =INDEX(Monthly!$C$93:$BJ$93,($R$2-1)*12+2) -> 0 | J25: =INDEX(Monthly!$C$93:$BJ$93,($R$2-1)*12+3) -> 0 | K25: =INDEX(Monthly!$C$93:$BJ$93,($R$2-1)*12+4) -> 0 | L25: =INDEX(Monthly!$C$93:$BJ$93,($R$2-1)*12+5) -> 0 | M25: =INDEX(Monthly!$C$93:$BJ$93,($R$2-1)*12+6) -> 0 | N25: =INDEX(Monthly!$C$93:$BJ$93,($R$2-1)*12+7) -> 0 | O25: =INDEX(Monthly!$C$93:$BJ$93,($R$2-1)*12+8) -> 0 | P25: =INDEX(Monthly!$C$93:$BJ$93,($R$2-1)*12+9) -> 0 | Q25: =INDEX(Monthly!$C$93:$BJ$93,($R$2-1)*12+10) -> 0 | R25: =INDEX(Monthly!$C$93:$BJ$93,($R$2-1)*12+11) -> 0 | S25: =INDEX(Monthly!$C$93:$BJ$93,($R$2-1)*12+12) -> 0
A26: Equity raised | B26: ='Cash Flow'!B12 -> 2100000 | C26: ='Cash Flow'!C12 -> 0 | D26: ='Cash Flow'!D12 -> 0 | E26: ='Cash Flow'!E12 -> 0 | F26: ='Cash Flow'!F12 -> 0 | H26: =INDEX(Monthly!$C$94:$BJ$94,($R$2-1)*12+1) -> 2100000 | I26: =INDEX(Monthly!$C$94:$BJ$94,($R$2-1)*12+2) -> 0 | J26: =INDEX(Monthly!$C$94:$BJ$94,($R$2-1)*12+3) -> 0 | K26: =INDEX(Monthly!$C$94:$BJ$94,($R$2-1)*12+4) -> 0 | L26: =INDEX(Monthly!$C$94:$BJ$94,($R$2-1)*12+5) -> 0 | M26: =INDEX(Monthly!$C$94:$BJ$94,($R$2-1)*12+6) -> 0 | N26: =INDEX(Monthly!$C$94:$BJ$94,($R$2-1)*12+7) -> 0 | O26: =INDEX(Monthly!$C$94:$BJ$94,($R$2-1)*12+8) -> 0 | P26: =INDEX(Monthly!$C$94:$BJ$94,($R$2-1)*12+9) -> 0 | Q26: =INDEX(Monthly!$C$94:$BJ$94,($R$2-1)*12+10) -> 0 | R26: =INDEX(Monthly!$C$94:$BJ$94,($R$2-1)*12+11) -> 0 | S26: =INDEX(Monthly!$C$94:$BJ$94,($R$2-1)*12+12) -> 0
A27: Loan drawdown | B27: ='Cash Flow'!B13 -> 3000000 | C27: ='Cash Flow'!C13 -> 0 | D27: ='Cash Flow'!D13 -> 0 | E27: ='Cash Flow'!E13 -> 0 | F27: ='Cash Flow'!F13 -> 0 | H27: =INDEX(Monthly!$C$79:$BJ$79,($R$2-1)*12+1) -> 3000000 | I27: =INDEX(Monthly!$C$79:$BJ$79,($R$2-1)*12+2) -> 0 | J27: =INDEX(Monthly!$C$79:$BJ$79,($R$2-1)*12+3) -> 0 | K27: =INDEX(Monthly!$C$79:$BJ$79,($R$2-1)*12+4) -> 0 | L27: =INDEX(Monthly!$C$79:$BJ$79,($R$2-1)*12+5) -> 0 | M27: =INDEX(Monthly!$C$79:$BJ$79,($R$2-1)*12+6) -> 0 | N27: =INDEX(Monthly!$C$79:$BJ$79,($R$2-1)*12+7) -> 0 | O27: =INDEX(Monthly!$C$79:$BJ$79,($R$2-1)*12+8) -> 0 | P27: =INDEX(Monthly!$C$79:$BJ$79,($R$2-1)*12+9) -> 0 | Q27: =INDEX(Monthly!$C$79:$BJ$79,($R$2-1)*12+10) -> 0 | R27: =INDEX(Monthly!$C$79:$BJ$79,($R$2-1)*12+11) -> 0 | S27: =INDEX(Monthly!$C$79:$BJ$79,($R$2-1)*12+12) -> 0
A28: Loan repayment | B28: ='Cash Flow'!B14 -> -275000 | C28: ='Cash Flow'!C14 -> -300000 | D28: ='Cash Flow'!D14 -> -300000 | E28: ='Cash Flow'!E14 -> -300000 | F28: ='Cash Flow'!F14 -> -300000 | H28: =INDEX(Monthly!$C$80:$BJ$80,($R$2-1)*12+1) -> 0 | I28: =INDEX(Monthly!$C$80:$BJ$80,($R$2-1)*12+2) -> -25000 | J28: =INDEX(Monthly!$C$80:$BJ$80,($R$2-1)*12+3) -> -25000 | K28: =INDEX(Monthly!$C$80:$BJ$80,($R$2-1)*12+4) -> -25000 | L28: =INDEX(Monthly!$C$80:$BJ$80,($R$2-1)*12+5) -> -25000 | M28: =INDEX(Monthly!$C$80:$BJ$80,($R$2-1)*12+6) -> -25000 | N28: =INDEX(Monthly!$C$80:$BJ$80,($R$2-1)*12+7) -> -25000 | O28: =INDEX(Monthly!$C$80:$BJ$80,($R$2-1)*12+8) -> -25000 | P28: =INDEX(Monthly!$C$80:$BJ$80,($R$2-1)*12+9) -> -25000 | Q28: =INDEX(Monthly!$C$80:$BJ$80,($R$2-1)*12+10) -> -25000 | R28: =INDEX(Monthly!$C$80:$BJ$80,($R$2-1)*12+11) -> -25000 | S28: =INDEX(Monthly!$C$80:$BJ$80,($R$2-1)*12+12) -> -25000
A29: Financing cash flow | B29: ='Cash Flow'!B15 -> 4825000 | C29: ='Cash Flow'!C15 -> -300000 | D29: ='Cash Flow'!D15 -> -300000 | E29: ='Cash Flow'!E15 -> -300000 | F29: ='Cash Flow'!F15 -> -300000 | H29: =INDEX(Monthly!$C$95:$BJ$95,($R$2-1)*12+1) -> 5100000 | I29: =INDEX(Monthly!$C$95:$BJ$95,($R$2-1)*12+2) -> -25000 | J29: =INDEX(Monthly!$C$95:$BJ$95,($R$2-1)*12+3) -> -25000 | K29: =INDEX(Monthly!$C$95:$BJ$95,($R$2-1)*12+4) -> -25000 | L29: =INDEX(Monthly!$C$95:$BJ$95,($R$2-1)*12+5) -> -25000 | M29: =INDEX(Monthly!$C$95:$BJ$95,($R$2-1)*12+6) -> -25000 | N29: =INDEX(Monthly!$C$95:$BJ$95,($R$2-1)*12+7) -> -25000 | O29: =INDEX(Monthly!$C$95:$BJ$95,($R$2-1)*12+8) -> -25000 | P29: =INDEX(Monthly!$C$95:$BJ$95,($R$2-1)*12+9) -> -25000 | Q29: =INDEX(Monthly!$C$95:$BJ$95,($R$2-1)*12+10) -> -25000 | R29: =INDEX(Monthly!$C$95:$BJ$95,($R$2-1)*12+11) -> -25000 | S29: =INDEX(Monthly!$C$95:$BJ$95,($R$2-1)*12+12) -> -25000
A30: Net change in cash | B30: ='Cash Flow'!B16 -> 355442.21 | C30: ='Cash Flow'!C16 -> -165521.55 | D30: ='Cash Flow'!D16 -> 72515.855 | E30: ='Cash Flow'!E16 -> 246141.12 | F30: ='Cash Flow'!F16 -> 379465.28 | H30: =INDEX(Monthly!$C$96:$BJ$96,($R$2-1)*12+1) -> 925195.84 | I30: =INDEX(Monthly!$C$96:$BJ$96,($R$2-1)*12+2) -> -93444.509 | J30: =INDEX(Monthly!$C$96:$BJ$96,($R$2-1)*12+3) -> -78080.977 | K30: =INDEX(Monthly!$C$96:$BJ$96,($R$2-1)*12+4) -> -70827.369 | L30: =INDEX(Monthly!$C$96:$BJ$96,($R$2-1)*12+5) -> -63528.868 | M30: =INDEX(Monthly!$C$96:$BJ$96,($R$2-1)*12+6) -> -56107.758 | N30: =INDEX(Monthly!$C$96:$BJ$96,($R$2-1)*12+7) -> -48568.944 | O30: =INDEX(Monthly!$C$96:$BJ$96,($R$2-1)*12+8) -> -40917.132 | P30: =INDEX(Monthly!$C$96:$BJ$96,($R$2-1)*12+9) -> -33156.843 | Q30: =INDEX(Monthly!$C$96:$BJ$96,($R$2-1)*12+10) -> -25292.417 | R30: =INDEX(Monthly!$C$96:$BJ$96,($R$2-1)*12+11) -> -22849.894 | S30: =INDEX(Monthly!$C$96:$BJ$96,($R$2-1)*12+12) -> -36978.918
A31: Closing cash | B31: ='Cash Flow'!B18 -> 355442.21 | C31: ='Cash Flow'!C18 -> 189920.66 | D31: ='Cash Flow'!D18 -> 262436.52 | E31: ='Cash Flow'!E18 -> 508577.64 | F31: ='Cash Flow'!F18 -> 888042.92 | H31: =INDEX(Monthly!$C$98:$BJ$98,($R$2-1)*12+1) -> 925195.84 | I31: =INDEX(Monthly!$C$98:$BJ$98,($R$2-1)*12+2) -> 831751.33 | J31: =INDEX(Monthly!$C$98:$BJ$98,($R$2-1)*12+3) -> 753670.35 | K31: =INDEX(Monthly!$C$98:$BJ$98,($R$2-1)*12+4) -> 682842.98 | L31: =INDEX(Monthly!$C$98:$BJ$98,($R$2-1)*12+5) -> 619314.11 | M31: =INDEX(Monthly!$C$98:$BJ$98,($R$2-1)*12+6) -> 563206.36 | N31: =INDEX(Monthly!$C$98:$BJ$98,($R$2-1)*12+7) -> 514637.41 | O31: =INDEX(Monthly!$C$98:$BJ$98,($R$2-1)*12+8) -> 473720.28 | P31: =INDEX(Monthly!$C$98:$BJ$98,($R$2-1)*12+9) -> 440563.44 | Q31: =INDEX(Monthly!$C$98:$BJ$98,($R$2-1)*12+10) -> 415271.02 | R31: =INDEX(Monthly!$C$98:$BJ$98,($R$2-1)*12+11) -> 392421.13 | S31: =INDEX(Monthly!$C$98:$BJ$98,($R$2-1)*12+12) -> 355442.21
A39: Balance sheet at year end ($'000) | H39: ="Balance sheet at month end ($'000) — Year "&$R$2 -> Balance sheet at month end ($'000) — Year 1
B40: 1 | C40: 2 | D40: 3 | E40: 4 | F40: 5 | H40: =INDEX(Monthly!$C$4:$BJ$4,($R$2-1)*12+1) -> 1 | I40: =INDEX(Monthly!$C$4:$BJ$4,($R$2-1)*12+2) -> 2 | J40: =INDEX(Monthly!$C$4:$BJ$4,($R$2-1)*12+3) -> 3 | K40: =INDEX(Monthly!$C$4:$BJ$4,($R$2-1)*12+4) -> 4 | L40: =INDEX(Monthly!$C$4:$BJ$4,($R$2-1)*12+5) -> 5 | M40: =INDEX(Monthly!$C$4:$BJ$4,($R$2-1)*12+6) -> 6 | N40: =INDEX(Monthly!$C$4:$BJ$4,($R$2-1)*12+7) -> 7 | O40: =INDEX(Monthly!$C$4:$BJ$4,($R$2-1)*12+8) -> 8 | P40: =INDEX(Monthly!$C$4:$BJ$4,($R$2-1)*12+9) -> 9 | Q40: =INDEX(Monthly!$C$4:$BJ$4,($R$2-1)*12+10) -> 10 | R40: =INDEX(Monthly!$C$4:$BJ$4,($R$2-1)*12+11) -> 11 | S40: =INDEX(Monthly!$C$4:$BJ$4,($R$2-1)*12+12) -> 12
A41: Cash | B41: ='Balance Sheet'!B5 -> 355442.21 | C41: ='Balance Sheet'!C5 -> 189920.66 | D41: ='Balance Sheet'!D5 -> 262436.52 | E41: ='Balance Sheet'!E5 -> 508577.64 | F41: ='Balance Sheet'!F5 -> 888042.92 | H41: =INDEX(Monthly!$C$98:$BJ$98,($R$2-1)*12+1) -> 925195.84 | I41: =INDEX(Monthly!$C$98:$BJ$98,($R$2-1)*12+2) -> 831751.33 | J41: =INDEX(Monthly!$C$98:$BJ$98,($R$2-1)*12+3) -> 753670.35 | K41: =INDEX(Monthly!$C$98:$BJ$98,($R$2-1)*12+4) -> 682842.98 | L41: =INDEX(Monthly!$C$98:$BJ$98,($R$2-1)*12+5) -> 619314.11 | M41: =INDEX(Monthly!$C$98:$BJ$98,($R$2-1)*12+6) -> 563206.36 | N41: =INDEX(Monthly!$C$98:$BJ$98,($R$2-1)*12+7) -> 514637.41 | O41: =INDEX(Monthly!$C$98:$BJ$98,($R$2-1)*12+8) -> 473720.28 | P41: =INDEX(Monthly!$C$98:$BJ$98,($R$2-1)*12+9) -> 440563.44 | Q41: =INDEX(Monthly!$C$98:$BJ$98,($R$2-1)*12+10) -> 415271.02 | R41: =INDEX(Monthly!$C$98:$BJ$98,($R$2-1)*12+11) -> 392421.13 | S41: =INDEX(Monthly!$C$98:$BJ$98,($R$2-1)*12+12) -> 355442.21
A42: Accounts receivable | B42: ='Balance Sheet'!B6 -> 7915.9819 | C42: ='Balance Sheet'!C6 -> 9704.5001 | D42: ='Balance Sheet'!D6 -> 10979.008 | E42: ='Balance Sheet'!E6 -> 11939.788 | F42: ='Balance Sheet'!F6 -> 12712.467 | H42: =INDEX(Monthly!$C$84:$BJ$84,($R$2-1)*12+1) -> 3196.2239 | I42: =INDEX(Monthly!$C$84:$BJ$84,($R$2-1)*12+2) -> 3629.9291 | J42: =INDEX(Monthly!$C$84:$BJ$84,($R$2-1)*12+3) -> 4851.5601 | K42: =INDEX(Monthly!$C$84:$BJ$84,($R$2-1)*12+4) -> 5403.4599 | L42: =INDEX(Monthly!$C$84:$BJ$84,($R$2-1)*12+5) -> 5966.0184 | M42: =INDEX(Monthly!$C$84:$BJ$84,($R$2-1)*12+6) -> 6538.8093 | N42: =INDEX(Monthly!$C$84:$BJ$84,($R$2-1)*12+7) -> 7121.4232 | O42: =INDEX(Monthly!$C$84:$BJ$84,($R$2-1)*12+8) -> 7713.4673 | P42: =INDEX(Monthly!$C$84:$BJ$84,($R$2-1)*12+9) -> 8314.5643 | Q42: =INDEX(Monthly!$C$84:$BJ$84,($R$2-1)*12+10) -> 8924.3521 | R42: =INDEX(Monthly!$C$84:$BJ$84,($R$2-1)*12+11) -> 9103.0367 | S42: =INDEX(Monthly!$C$84:$BJ$84,($R$2-1)*12+12) -> 7915.9819
A43: Inventory | B43: ='Balance Sheet'!B7 -> 8885.7825 | C43: ='Balance Sheet'!C7 -> 11211.928 | D43: ='Balance Sheet'!D7 -> 12914.355 | E43: ='Balance Sheet'!E7 -> 14236.927 | F43: ='Balance Sheet'!F7 -> 15334.144 | H43: =INDEX(Monthly!$C$85:$BJ$85,($R$2-1)*12+1) -> 3535.9729 | I43: =INDEX(Monthly!$C$85:$BJ$85,($R$2-1)*12+2) -> 4015.7244 | J43: =INDEX(Monthly!$C$85:$BJ$85,($R$2-1)*12+3) -> 5538.4176 | K43: =INDEX(Monthly!$C$85:$BJ$85,($R$2-1)*12+4) -> 6180.8484 | L43: =INDEX(Monthly!$C$85:$BJ$85,($R$2-1)*12+5) -> 6839.3592 | M43: =INDEX(Monthly!$C$85:$BJ$85,($R$2-1)*12+6) -> 7513.3068 | N43: =INDEX(Monthly!$C$85:$BJ$85,($R$2-1)*12+7) -> 8202.0737 | O43: =INDEX(Monthly!$C$85:$BJ$85,($R$2-1)*12+8) -> 8905.0672 | P43: =INDEX(Monthly!$C$85:$BJ$85,($R$2-1)*12+9) -> 9621.7181 | Q43: =INDEX(Monthly!$C$85:$BJ$85,($R$2-1)*12+10) -> 10351.48 | R43: =INDEX(Monthly!$C$85:$BJ$85,($R$2-1)*12+11) -> 10621.048 | S43: =INDEX(Monthly!$C$85:$BJ$85,($R$2-1)*12+12) -> 8885.7825
A44: Net fixed assets | B44: ='Balance Sheet'!B8 -> 3758333.3 | C44: ='Balance Sheet'!C8 -> 3453333.3 | D44: ='Balance Sheet'!D8 -> 3145000 | E44: ='Balance Sheet'!E8 -> 2833333.3 | F44: ='Balance Sheet'!F8 -> 2518333.3 | H44: =INDEX(Monthly!$C$75:$BJ$75,($R$2-1)*12+1) -> 4071527.8 | I44: =INDEX(Monthly!$C$75:$BJ$75,($R$2-1)*12+2) -> 4043055.6 | J44: =INDEX(Monthly!$C$75:$BJ$75,($R$2-1)*12+3) -> 4014583.3 | K44: =INDEX(Monthly!$C$75:$BJ$75,($R$2-1)*12+4) -> 3986111.1 | L44: =INDEX(Monthly!$C$75:$BJ$75,($R$2-1)*12+5) -> 3957638.9 | M44: =INDEX(Monthly!$C$75:$BJ$75,($R$2-1)*12+6) -> 3929166.7 | N44: =INDEX(Monthly!$C$75:$BJ$75,($R$2-1)*12+7) -> 3900694.4 | O44: =INDEX(Monthly!$C$75:$BJ$75,($R$2-1)*12+8) -> 3872222.2 | P44: =INDEX(Monthly!$C$75:$BJ$75,($R$2-1)*12+9) -> 3843750 | Q44: =INDEX(Monthly!$C$75:$BJ$75,($R$2-1)*12+10) -> 3815277.8 | R44: =INDEX(Monthly!$C$75:$BJ$75,($R$2-1)*12+11) -> 3786805.6 | S44: =INDEX(Monthly!$C$75:$BJ$75,($R$2-1)*12+12) -> 3758333.3
A45: Total assets | B45: ='Balance Sheet'!B9 -> 4130577.3 | C45: ='Balance Sheet'!C9 -> 3664170.4 | D45: ='Balance Sheet'!D9 -> 3431329.9 | E45: ='Balance Sheet'!E9 -> 3368087.7 | F45: ='Balance Sheet'!F9 -> 3434422.9 | H45: =INDEX(Monthly!$C$112:$BJ$112,($R$2-1)*12+1) -> 5003455.8 | I45: =INDEX(Monthly!$C$112:$BJ$112,($R$2-1)*12+2) -> 4882452.5 | J45: =INDEX(Monthly!$C$112:$BJ$112,($R$2-1)*12+3) -> 4778643.7 | K45: =INDEX(Monthly!$C$112:$BJ$112,($R$2-1)*12+4) -> 4680538.4 | L45: =INDEX(Monthly!$C$112:$BJ$112,($R$2-1)*12+5) -> 4589758.4 | M45: =INDEX(Monthly!$C$112:$BJ$112,($R$2-1)*12+6) -> 4506425.1 | N45: =INDEX(Monthly!$C$112:$BJ$112,($R$2-1)*12+7) -> 4430655.4 | O45: =INDEX(Monthly!$C$112:$BJ$112,($R$2-1)*12+8) -> 4362561 | P45: =INDEX(Monthly!$C$112:$BJ$112,($R$2-1)*12+9) -> 4302249.7 | Q45: =INDEX(Monthly!$C$112:$BJ$112,($R$2-1)*12+10) -> 4249824.6 | R45: =INDEX(Monthly!$C$112:$BJ$112,($R$2-1)*12+11) -> 4198950.8 | S45: =INDEX(Monthly!$C$112:$BJ$112,($R$2-1)*12+12) -> 4130577.3
A46: Accounts payable | B46: ='Balance Sheet'!B10 -> 14809.638 | C46: ='Balance Sheet'!C10 -> 18686.546 | D46: ='Balance Sheet'!D10 -> 21523.926 | E46: ='Balance Sheet'!E10 -> 23728.212 | F46: ='Balance Sheet'!F10 -> 25556.907 | H46: =INDEX(Monthly!$C$86:$BJ$86,($R$2-1)*12+1) -> 5893.2881 | I46: =INDEX(Monthly!$C$86:$BJ$86,($R$2-1)*12+2) -> 6692.874 | J46: =INDEX(Monthly!$C$86:$BJ$86,($R$2-1)*12+3) -> 9230.696 | K46: =INDEX(Monthly!$C$86:$BJ$86,($R$2-1)*12+4) -> 10301.414 | L46: =INDEX(Monthly!$C$86:$BJ$86,($R$2-1)*12+5) -> 11398.932 | M46: =INDEX(Monthly!$C$86:$BJ$86,($R$2-1)*12+6) -> 12522.178 | N46: =INDEX(Monthly!$C$86:$BJ$86,($R$2-1)*12+7) -> 13670.123 | O46: =INDEX(Monthly!$C$86:$BJ$86,($R$2-1)*12+8) -> 14841.779 | P46: =INDEX(Monthly!$C$86:$BJ$86,($R$2-1)*12+9) -> 16036.197 | Q46: =INDEX(Monthly!$C$86:$BJ$86,($R$2-1)*12+10) -> 17252.467 | R46: =INDEX(Monthly!$C$86:$BJ$86,($R$2-1)*12+11) -> 17701.747 | S46: =INDEX(Monthly!$C$86:$BJ$86,($R$2-1)*12+12) -> 14809.638
A47: Loan | B47: ='Balance Sheet'!B11 -> 2725000 | C47: ='Balance Sheet'!C11 -> 2425000 | D47: ='Balance Sheet'!D11 -> 2125000 | E47: ='Balance Sheet'!E11 -> 1825000 | F47: ='Balance Sheet'!F11 -> 1525000 | H47: =INDEX(Monthly!$C$81:$BJ$81,($R$2-1)*12+1) -> 3000000 | I47: =INDEX(Monthly!$C$81:$BJ$81,($R$2-1)*12+2) -> 2975000 | J47: =INDEX(Monthly!$C$81:$BJ$81,($R$2-1)*12+3) -> 2950000 | K47: =INDEX(Monthly!$C$81:$BJ$81,($R$2-1)*12+4) -> 2925000 | L47: =INDEX(Monthly!$C$81:$BJ$81,($R$2-1)*12+5) -> 2900000 | M47: =INDEX(Monthly!$C$81:$BJ$81,($R$2-1)*12+6) -> 2875000 | N47: =INDEX(Monthly!$C$81:$BJ$81,($R$2-1)*12+7) -> 2850000 | O47: =INDEX(Monthly!$C$81:$BJ$81,($R$2-1)*12+8) -> 2825000 | P47: =INDEX(Monthly!$C$81:$BJ$81,($R$2-1)*12+9) -> 2800000 | Q47: =INDEX(Monthly!$C$81:$BJ$81,($R$2-1)*12+10) -> 2775000 | R47: =INDEX(Monthly!$C$81:$BJ$81,($R$2-1)*12+11) -> 2750000 | S47: =INDEX(Monthly!$C$81:$BJ$81,($R$2-1)*12+12) -> 2725000
A48: Total liabilities | B48: ='Balance Sheet'!B12 -> 2739809.6 | C48: ='Balance Sheet'!C12 -> 2443686.5 | D48: ='Balance Sheet'!D12 -> 2146523.9 | E48: ='Balance Sheet'!E12 -> 1848728.2 | F48: ='Balance Sheet'!F12 -> 1550556.9 | H48: =INDEX(Monthly!$C$113:$BJ$113,($R$2-1)*12+1) -> 3005893.3 | I48: =INDEX(Monthly!$C$113:$BJ$113,($R$2-1)*12+2) -> 2981692.9 | J48: =INDEX(Monthly!$C$113:$BJ$113,($R$2-1)*12+3) -> 2959230.7 | K48: =INDEX(Monthly!$C$113:$BJ$113,($R$2-1)*12+4) -> 2935301.4 | L48: =INDEX(Monthly!$C$113:$BJ$113,($R$2-1)*12+5) -> 2911398.9 | M48: =INDEX(Monthly!$C$113:$BJ$113,($R$2-1)*12+6) -> 2887522.2 | N48: =INDEX(Monthly!$C$113:$BJ$113,($R$2-1)*12+7) -> 2863670.1 | O48: =INDEX(Monthly!$C$113:$BJ$113,($R$2-1)*12+8) -> 2839841.8 | P48: =INDEX(Monthly!$C$113:$BJ$113,($R$2-1)*12+9) -> 2816036.2 | Q48: =INDEX(Monthly!$C$113:$BJ$113,($R$2-1)*12+10) -> 2792252.5 | R48: =INDEX(Monthly!$C$113:$BJ$113,($R$2-1)*12+11) -> 2767701.7 | S48: =INDEX(Monthly!$C$113:$BJ$113,($R$2-1)*12+12) -> 2739809.6
A49: Paid-in capital | B49: ='Balance Sheet'!B13 -> 2100000 | C49: ='Balance Sheet'!C13 -> 2100000 | D49: ='Balance Sheet'!D13 -> 2100000 | E49: ='Balance Sheet'!E13 -> 2100000 | F49: ='Balance Sheet'!F13 -> 2100000 | H49: =INDEX(Monthly!$C$110:$BJ$110,($R$2-1)*12+1) -> 2100000 | I49: =INDEX(Monthly!$C$110:$BJ$110,($R$2-1)*12+2) -> 2100000 | J49: =INDEX(Monthly!$C$110:$BJ$110,($R$2-1)*12+3) -> 2100000 | K49: =INDEX(Monthly!$C$110:$BJ$110,($R$2-1)*12+4) -> 2100000 | L49: =INDEX(Monthly!$C$110:$BJ$110,($R$2-1)*12+5) -> 2100000 | M49: =INDEX(Monthly!$C$110:$BJ$110,($R$2-1)*12+6) -> 2100000 | N49: =INDEX(Monthly!$C$110:$BJ$110,($R$2-1)*12+7) -> 2100000 | O49: =INDEX(Monthly!$C$110:$BJ$110,($R$2-1)*12+8) -> 2100000 | P49: =INDEX(Monthly!$C$110:$BJ$110,($R$2-1)*12+9) -> 2100000 | Q49: =INDEX(Monthly!$C$110:$BJ$110,($R$2-1)*12+10) -> 2100000 | R49: =INDEX(Monthly!$C$110:$BJ$110,($R$2-1)*12+11) -> 2100000 | S49: =INDEX(Monthly!$C$110:$BJ$110,($R$2-1)*12+12) -> 2100000
A50: Retained earnings | B50: ='Balance Sheet'!B14 -> -709232.33 | C50: ='Balance Sheet'!C14 -> -879516.12 | D50: ='Balance Sheet'!D14 -> -815194.05 | E50: ='Balance Sheet'!E14 -> -580640.52 | F50: ='Balance Sheet'!F14 -> -216134.04 | H50: =INDEX(Monthly!$C$111:$BJ$111,($R$2-1)*12+1) -> -102437.48 | I50: =INDEX(Monthly!$C$111:$BJ$111,($R$2-1)*12+2) -> -199240.34 | J50: =INDEX(Monthly!$C$111:$BJ$111,($R$2-1)*12+3) -> -280587.03 | K50: =INDEX(Monthly!$C$111:$BJ$111,($R$2-1)*12+4) -> -354763.01 | L50: =INDEX(Monthly!$C$111:$BJ$111,($R$2-1)*12+5) -> -421640.55 | M50: =INDEX(Monthly!$C$111:$BJ$111,($R$2-1)*12+6) -> -481097.04 | N50: =INDEX(Monthly!$C$111:$BJ$111,($R$2-1)*12+7) -> -533014.77 | O50: =INDEX(Monthly!$C$111:$BJ$111,($R$2-1)*12+8) -> -577280.74 | P50: =INDEX(Monthly!$C$111:$BJ$111,($R$2-1)*12+9) -> -613786.48 | Q50: =INDEX(Monthly!$C$111:$BJ$111,($R$2-1)*12+10) -> -642427.84 | R50: =INDEX(Monthly!$C$111:$BJ$111,($R$2-1)*12+11) -> -668750.98 | S50: =INDEX(Monthly!$C$111:$BJ$111,($R$2-1)*12+12) -> -709232.33
A51: Total equity | B51: ='Balance Sheet'!B15 -> 1390767.7 | C51: ='Balance Sheet'!C15 -> 1220483.9 | D51: ='Balance Sheet'!D15 -> 1284806 | E51: ='Balance Sheet'!E15 -> 1519359.5 | F51: ='Balance Sheet'!F15 -> 1883866 | H51: =INDEX(Monthly!$C$114:$BJ$114,($R$2-1)*12+1) -> 1997562.5 | I51: =INDEX(Monthly!$C$114:$BJ$114,($R$2-1)*12+2) -> 1900759.7 | J51: =INDEX(Monthly!$C$114:$BJ$114,($R$2-1)*12+3) -> 1819413 | K51: =INDEX(Monthly!$C$114:$BJ$114,($R$2-1)*12+4) -> 1745237 | L51: =INDEX(Monthly!$C$114:$BJ$114,($R$2-1)*12+5) -> 1678359.4 | M51: =INDEX(Monthly!$C$114:$BJ$114,($R$2-1)*12+6) -> 1618903 | N51: =INDEX(Monthly!$C$114:$BJ$114,($R$2-1)*12+7) -> 1566985.2 | O51: =INDEX(Monthly!$C$114:$BJ$114,($R$2-1)*12+8) -> 1522719.3 | P51: =INDEX(Monthly!$C$114:$BJ$114,($R$2-1)*12+9) -> 1486213.5 | Q51: =INDEX(Monthly!$C$114:$BJ$114,($R$2-1)*12+10) -> 1457572.2 | R51: =INDEX(Monthly!$C$114:$BJ$114,($R$2-1)*12+11) -> 1431249 | S51: =INDEX(Monthly!$C$114:$BJ$114,($R$2-1)*12+12) -> 1390767.7
A52: Total liabilities & equity | B52: ='Balance Sheet'!B16 -> 4130577.3 | C52: ='Balance Sheet'!C16 -> 3664170.4 | D52: ='Balance Sheet'!D16 -> 3431329.9 | E52: ='Balance Sheet'!E16 -> 3368087.7 | F52: ='Balance Sheet'!F16 -> 3434422.9 | H52: =INDEX(Monthly!$C$115:$BJ$115,($R$2-1)*12+1) -> 5003455.8 | I52: =INDEX(Monthly!$C$115:$BJ$115,($R$2-1)*12+2) -> 4882452.5 | J52: =INDEX(Monthly!$C$115:$BJ$115,($R$2-1)*12+3) -> 4778643.7 | K52: =INDEX(Monthly!$C$115:$BJ$115,($R$2-1)*12+4) -> 4680538.4 | L52: =INDEX(Monthly!$C$115:$BJ$115,($R$2-1)*12+5) -> 4589758.4 | M52: =INDEX(Monthly!$C$115:$BJ$115,($R$2-1)*12+6) -> 4506425.1 | N52: =INDEX(Monthly!$C$115:$BJ$115,($R$2-1)*12+7) -> 4430655.4 | O52: =INDEX(Monthly!$C$115:$BJ$115,($R$2-1)*12+8) -> 4362561 | P52: =INDEX(Monthly!$C$115:$BJ$115,($R$2-1)*12+9) -> 4302249.7 | Q52: =INDEX(Monthly!$C$115:$BJ$115,($R$2-1)*12+10) -> 4249824.6 | R52: =INDEX(Monthly!$C$115:$BJ$115,($R$2-1)*12+11) -> 4198950.8 | S52: =INDEX(Monthly!$C$115:$BJ$115,($R$2-1)*12+12) -> 4130577.3

Sheet Scenarios
A1: Scenarios — Low / Base / High | H1: =HYPERLINK("#'Cover'!A1","◂ Contents") -> ◂ Contents
A2: All three scenarios calculated side by side, live: change any input and every column updates. Active = the scenario chosen on the Dashboard.
A5: Key drivers
A6: Driver | B6: Low | C6: Base | D6: High | E6: Active
A7: Retail cars per operating day at maturity (year 1) (cars) | B7: =Inputs!$B$7 -> 200 | C7: =Inputs!$C$7 -> 240 | D7: =Inputs!$D$7 -> 280 | E7: =Inputs!$E$7 -> 240
A8: Average price per retail wash (year 1) ($) | B8: =Inputs!$B$27 -> 12 | C8: =Inputs!$C$27 -> 13 | D8: =Inputs!$D$27 -> 14 | E8: =Inputs!$E$27 -> 13
A9: Unlimited members at start (presale or current base) (#) | B9: =Inputs!$B$19 -> 150 | C9: =Inputs!$C$19 -> 250 | D9: =Inputs!$D$19 -> 350 | E9: =Inputs!$E$19 -> 250
A10: Unlimited plan fee per member per month (year 1) ($) | B10: =Inputs!$B$29 -> 32 | C10: =Inputs!$C$29 -> 35 | D10: =Inputs!$D$29 -> 38 | E10: =Inputs!$E$29 -> 35
A11: Members who cancel per month (%) | B11: =Inputs!$B$23 -> 0.05 | C11: =Inputs!$C$23 -> 0.04 | D11: =Inputs!$D$23 -> 0.032 | E11: =Inputs!$E$23 -> 0.04
A12: Site lease or land cost per month ($) | B12: =Inputs!$B$41 -> 30000 | C12: =Inputs!$C$41 -> 30000 | D12: =Inputs!$D$41 -> 30000 | E12: =Inputs!$E$41 -> 30000
A13: Tunnel equipment (month 1) ($) | B13: =Inputs!$B$49 -> 1650000 | C13: =Inputs!$C$49 -> 1650000 | D13: =Inputs!$D$49 -> 1650000 | E13: =Inputs!$E$49 -> 1650000
A14: Equity raised at start ($) | B14: =Inputs!$B$67 -> 2100000 | C14: =Inputs!$C$67 -> 2100000 | D14: =Inputs!$D$67 -> 2100000 | E14: =Inputs!$E$67 -> 2100000
A16: Results by scenario ($'000)
A17: Output | B17: Low | C17: Base | D17: High | E17: Active
A18: Revenue — final year | B18: =F31 -> 1509180.9 | C18: =F32 -> 2440877.2 | D18: =F33 -> 3820481.8 | E18: ='P&L'!F5 -> 2440877.2
A19: Revenue — whole plan | B19: =SUM(B31:F31) -> 6296493.3 | C19: =SUM(B32:F32) -> 9789648.8 | D19: =SUM(B33:F33) -> 14540688 | E19: =SUM('P&L'!$B$5:$F$5) -> 9789648.8
A20: EBITDA — final year | B20: =F37 -> 29088.848 | C20: =F38 -> 861881.48 | D20: =F39 -> 2118274.9 | E20: ='P&L'!F15 -> 861881.48
A21: EBITDA margin — final year | B21: =IF(B18=0,0,B20/B18) -> 0.019274593 | C21: =IF(C18=0,0,C20/C18) -> 0.35310317 | D21: =IF(D18=0,0,D20/D18) -> 0.5544523 | E21: =IF(E18=0,0,E20/E18) -> 0.35310317
A22: Net income — final year | B22: =F43 -> -468286.15 | C22: =F44 -> 364506.48 | D22: =F45 -> 1280510.9 | E22: ='P&L'!F22 -> 364506.48
A23: Net income — whole plan | B23: =SUM(B43:F43) -> -3340553.2 | C23: =SUM(B44:F44) -> -216134.04 | D23: =SUM(B45:F45) -> 3272119.7 | E23: =SUM('P&L'!$B$22:$F$22) -> -216134.04
A24: Cash at the end of the plan | B24: =F49 -> -2233642.3 | C24: =F50 -> 888042.92 | D24: =F51 -> 4371228 | E24: ='Balance Sheet'!F5 -> 888042.92
A25: Lowest cash balance | B25: =MIN('Scenario calc'!$C$100:$BJ$100) -> -2233642.3 | C25: =MIN('Scenario calc'!$C$227:$BJ$227) -> 131554.54 | D25: =MIN('Scenario calc'!$C$354:$BJ$354) -> 775910.09 | E25: ='Break-even'!B18 -> 131554.54
A26: Lowest cash point (month #) | B26: =MATCH(MIN('Scenario calc'!$C$100:$BJ$100),'Scenario calc'!$C$100:$BJ$100,0) -> 60 | C26: =MATCH(MIN('Scenario calc'!$C$227:$BJ$227),'Scenario calc'!$C$227:$BJ$227,0) -> 26 | D26: =MATCH(MIN('Scenario calc'!$C$354:$BJ$354),'Scenario calc'!$C$354:$BJ$354,0) -> 7 | E26: ='Break-even'!B6 -> 26
A27: Funding required (incl. cash buffer) | B27: =SUMPRODUCT(--('Scenario calc'!$C$6:$BJ$6<=B26),'Scenario calc'!$C$73:$BJ$73)-SUMPRODUCT(--('Scenario calc'!$C$6:$BJ$6<=B26),'Scenario calc'!$C$94:$BJ$94)-SUMPRODUCT(--('Scenario calc'!$C$6:$BJ$6<=B26),'Scenario calc'!$C$82:$BJ$82)+Inputs!$B$82 -> 7614642.3 | C27: =SUMPRODUCT(--('Scenario calc'!$C$133:$BJ$133<=C26),'Scenario calc'!$C$200:$BJ$200)-SUMPRODUCT(--('Scenario calc'!$C$133:$BJ$133<=C26),'Scenario calc'!$C$221:$BJ$221)-SUMPRODUCT(--('Scenario calc'!$C$133:$BJ$133<=C26),'Scenario calc'!$C$209:$BJ$209)+Inputs!$C$82 -> 5249445.5 | D27: =SUMPRODUCT(--('Scenario calc'!$C$260:$BJ$260<=D26),'Scenario calc'!$C$327:$BJ$327)-SUMPRODUCT(--('Scenario calc'!$C$260:$BJ$260<=D26),'Scenario calc'!$C$348:$BJ$348)-SUMPRODUCT(--('Scenario calc'!$C$260:$BJ$260<=D26),'Scenario calc'!$C$336:$BJ$336)+Inputs!$D$82 -> 4605089.9 | E27: ='Break-even'!B12 -> 5249445.5
A29: Revenue by year ($'000)
A30: Scenario | B30: 1 | C30: 2 | D30: 3 | E30: 4 | F30: 5
A31: Low | B31: =SUMIF('Scenario calc'!$C$7:$BJ$7,B$30,'Scenario calc'!$C$39:$BJ$39) -> 723753.78 | C31: =SUMIF('Scenario calc'!$C$7:$BJ$7,C$30,'Scenario calc'!$C$39:$BJ$39) -> 1233556.7 | D31: =SUMIF('Scenario calc'!$C$7:$BJ$7,D$30,'Scenario calc'!$C$39:$BJ$39) -> 1373352.6 | E31: =SUMIF('Scenario calc'!$C$7:$BJ$7,E$30,'Scenario calc'!$C$39:$BJ$39) -> 1456649.3 | F31: =SUMIF('Scenario calc'!$C$7:$BJ$7,F$30,'Scenario calc'!$C$39:$BJ$39) -> 1509180.9
A32: Base | B32: =SUMIF('Scenario calc'!$C$134:$BJ$134,B$30,'Scenario calc'!$C$166:$BJ$166) -> 1180182.4 | C32: =SUMIF('Scenario calc'!$C$134:$BJ$134,C$30,'Scenario calc'!$C$166:$BJ$166) -> 1805881.5 | D32: =SUMIF('Scenario calc'!$C$134:$BJ$134,D$30,'Scenario calc'!$C$166:$BJ$166) -> 2080276.6 | E32: =SUMIF('Scenario calc'!$C$134:$BJ$134,E$30,'Scenario calc'!$C$166:$BJ$166) -> 2282431.1 | F32: =SUMIF('Scenario calc'!$C$134:$BJ$134,F$30,'Scenario calc'!$C$166:$BJ$166) -> 2440877.2
A33: High | B33: =SUMIF('Scenario calc'!$C$261:$BJ$261,B$30,'Scenario calc'!$C$293:$BJ$293) -> 1713972.3 | C33: =SUMIF('Scenario calc'!$C$261:$BJ$261,C$30,'Scenario calc'!$C$293:$BJ$293) -> 2530234.4 | D33: =SUMIF('Scenario calc'!$C$261:$BJ$261,D$30,'Scenario calc'!$C$293:$BJ$293) -> 3028027.2 | E33: =SUMIF('Scenario calc'!$C$261:$BJ$261,E$30,'Scenario calc'!$C$293:$BJ$293) -> 3447972 | F33: =SUMIF('Scenario calc'!$C$261:$BJ$261,F$30,'Scenario calc'!$C$293:$BJ$293) -> 3820481.8
A35: EBITDA by year ($'000)
A36: Scenario | B36: 1 | C36: 2 | D36: 3 | E36: 4 | F36: 5
A37: Low | B37: =SUMIF('Scenario calc'!$C$7:$BJ$7,B$36,'Scenario calc'!$C$57:$BJ$57) -> -533892.68 | C37: =SUMIF('Scenario calc'!$C$7:$BJ$7,C$36,'Scenario calc'!$C$57:$BJ$57) -> -120382.6 | D37: =SUMIF('Scenario calc'!$C$7:$BJ$7,D$36,'Scenario calc'!$C$57:$BJ$57) -> -24636.3 | E37: =SUMIF('Scenario calc'!$C$7:$BJ$7,E$36,'Scenario calc'!$C$57:$BJ$57) -> 17722.667 | F37: =SUMIF('Scenario calc'!$C$7:$BJ$7,F$36,'Scenario calc'!$C$57:$BJ$57) -> 29088.848
A38: Base | B38: =SUMIF('Scenario calc'!$C$134:$BJ$134,B$36,'Scenario calc'!$C$184:$BJ$184) -> -123279.21 | C38: =SUMIF('Scenario calc'!$C$134:$BJ$134,C$36,'Scenario calc'!$C$184:$BJ$184) -> 393591.21 | D38: =SUMIF('Scenario calc'!$C$134:$BJ$134,D$36,'Scenario calc'!$C$184:$BJ$184) -> 606030.41 | E38: =SUMIF('Scenario calc'!$C$134:$BJ$134,E$36,'Scenario calc'!$C$184:$BJ$184) -> 754095.19 | F38: =SUMIF('Scenario calc'!$C$134:$BJ$134,F$36,'Scenario calc'!$C$184:$BJ$184) -> 861881.48
A39: High | B39: =SUMIF('Scenario calc'!$C$261:$BJ$261,B$36,'Scenario calc'!$C$311:$BJ$311) -> 374729.35 | C39: =SUMIF('Scenario calc'!$C$261:$BJ$261,C$36,'Scenario calc'!$C$311:$BJ$311) -> 1064559.3 | D39: =SUMIF('Scenario calc'!$C$261:$BJ$261,D$36,'Scenario calc'!$C$311:$BJ$311) -> 1475107.6 | E39: =SUMIF('Scenario calc'!$C$261:$BJ$261,E$36,'Scenario calc'!$C$311:$BJ$311) -> 1817705.5 | F39: =SUMIF('Scenario calc'!$C$261:$BJ$261,F$36,'Scenario calc'!$C$311:$BJ$311) -> 2118274.9
A41: Net income by year ($'000)
A42: Scenario | B42: 1 | C42: 2 | D42: 3 | E42: 4 | F42: 5
A43: Low | B43: =SUMIF('Scenario calc'!$C$7:$BJ$7,B$42,'Scenario calc'!$C$66:$BJ$66) -> -1119845.8 | C43: =SUMIF('Scenario calc'!$C$7:$BJ$7,C$42,'Scenario calc'!$C$66:$BJ$66) -> -684257.6 | D43: =SUMIF('Scenario calc'!$C$7:$BJ$7,D$42,'Scenario calc'!$C$66:$BJ$66) -> -566344.63 | E43: =SUMIF('Scenario calc'!$C$7:$BJ$7,E$42,'Scenario calc'!$C$66:$BJ$66) -> -501819 | F43: =SUMIF('Scenario calc'!$C$7:$BJ$7,F$42,'Scenario calc'!$C$66:$BJ$66) -> -468286.15
A44: Base | B44: =SUMIF('Scenario calc'!$C$134:$BJ$134,B$42,'Scenario calc'!$C$193:$BJ$193) -> -709232.33 | C44: =SUMIF('Scenario calc'!$C$134:$BJ$134,C$42,'Scenario calc'!$C$193:$BJ$193) -> -170283.79 | D44: =SUMIF('Scenario calc'!$C$134:$BJ$134,D$42,'Scenario calc'!$C$193:$BJ$193) -> 64322.078 | E44: =SUMIF('Scenario calc'!$C$134:$BJ$134,E$42,'Scenario calc'!$C$193:$BJ$193) -> 234553.52 | F44: =SUMIF('Scenario calc'!$C$134:$BJ$134,F$42,'Scenario calc'!$C$193:$BJ$193) -> 364506.48
A45: High | B45: =SUMIF('Scenario calc'!$C$261:$BJ$261,B$42,'Scenario calc'!$C$320:$BJ$320) -> -211223.77 | C45: =SUMIF('Scenario calc'!$C$261:$BJ$261,C$42,'Scenario calc'!$C$320:$BJ$320) -> 439897.6 | D45: =SUMIF('Scenario calc'!$C$261:$BJ$261,D$42,'Scenario calc'!$C$320:$BJ$320) -> 737385.45 | E45: =SUMIF('Scenario calc'!$C$261:$BJ$261,E$42,'Scenario calc'!$C$320:$BJ$320) -> 1025549.4 | F45: =SUMIF('Scenario calc'!$C$261:$BJ$261,F$42,'Scenario calc'!$C$320:$BJ$320) -> 1280510.9
A47: Cash at year end by year ($'000)
A48: Scenario | B48: 1 | C48: 2 | D48: 3 | E48: 4 | F48: 5
A49: Low | B49: =INDEX('Scenario calc'!$C$100:$BJ$100,B$48*12) -> -53672.949 | C49: =INDEX('Scenario calc'!$C$100:$BJ$100,C$48*12) -> -732788.65 | D49: =INDEX('Scenario calc'!$C$100:$BJ$100,D$48*12) -> -1290608.8 | E49: =INDEX('Scenario calc'!$C$100:$BJ$100,E$48*12) -> -1780561.6 | F49: =INDEX('Scenario calc'!$C$100:$BJ$100,F$48*12) -> -2233642.3
A50: Base | B50: =INDEX('Scenario calc'!$C$227:$BJ$227,B$48*12) -> 355442.21 | C50: =INDEX('Scenario calc'!$C$227:$BJ$227,C$48*12) -> 189920.66 | D50: =INDEX('Scenario calc'!$C$227:$BJ$227,D$48*12) -> 262436.52 | E50: =INDEX('Scenario calc'!$C$227:$BJ$227,E$48*12) -> 508577.64 | F50: =INDEX('Scenario calc'!$C$227:$BJ$227,F$48*12) -> 888042.92
A51: High | B51: =INDEX('Scenario calc'!$C$354:$BJ$354,B$48*12) -> 851182.53 | C51: =INDEX('Scenario calc'!$C$354:$BJ$354,C$48*12) -> 1295076 | D51: =INDEX('Scenario calc'!$C$354:$BJ$354,D$48*12) -> 2039947.6 | E51: =INDEX('Scenario calc'!$C$354:$BJ$354,E$48*12) -> 3076413.7 | F51: =INDEX('Scenario calc'!$C$354:$BJ$354,F$48*12) -> 4371228

Sheet Break-even
A1: Startup costs, funding need and break-even | H1: =HYPERLINK("#'Cover'!A1","◂ Contents") -> ◂ Contents
A2: Live for the selected scenario. Periods are counted in months from the start of the plan.
A3: Scenario shown | B3: =CHOOSE(Dashboard!$B$4,"Low","Base","High") -> Base
A5: Startup costs & funding need (up to the lowest cash point)
A6: Lowest cash point (month #) | B6: =MATCH(MIN(Monthly!$C$98:$BJ$98),Monthly!$C$98:$BJ$98,0) -> 26
A7: Capital spending up to the lowest cash point | B7: =SUMPRODUCT(--(Monthly!$C$4:$BJ$4<=$B$6),Monthly!$C$71:$BJ$71) -> 4180000
A8: Operating cash burn up to the lowest cash point | B8: =-SUMPRODUCT(--(Monthly!$C$4:$BJ$4<=$B$6),Monthly!$C$92:$BJ$92) -> 163445.46 | D8: Losses and working capital before the business funds itself
A9: Loan repayments up to the lowest cash point | B9: =-SUMPRODUCT(--(Monthly!$C$4:$BJ$4<=$B$6),Monthly!$C$80:$BJ$80) -> 625000
A10: Total uses of funds | B10: =B7+B8+B9 -> 4968445.5
A11: Minimum cash buffer to keep | B11: =Inputs!$E$82 -> 281000 | D11: Input on the Inputs sheet
A12: Funding required (uses + buffer) | B12: =B10+B11 -> 5249445.5
A14: Equity raised | B14: =Inputs!$E$67 -> 2100000
A15: Loan drawn | B15: =Inputs!$E$68 -> 3000000
A16: Total sources of funds | B16: =B14+B15 -> 5100000
A17: Funding surplus / (shortfall) | B17: =B16-B12 -> -149445.46 | D17: Negative = raise at least this much more
A18: Lowest cash balance in the plan | B18: =MIN(Monthly!$C$98:$BJ$98) -> 131554.54 | D18: Equals sources minus uses
A20: Break-even timing
A21: First month with positive EBITDA (month #) | B21: =IFERROR(MATCH(1,Monthly!$C$99:$BJ$99,0),"Not within horizon") -> 8
A22: First month with positive net income (month #) | B22: =IFERROR(MATCH(1,Monthly!$C$102:$BJ$102,0),"Not within horizon") -> 27
A23: Cash invested paid back (month #) | B23: =IF(MIN(Monthly!$C$104:$BJ$104)>=0,"No investment to pay back",IFERROR(MATCH(1,Monthly!$C$106:$BJ$106,0),"Not within horizon")) -> Not within horizon | D23: Cumulative operating + investing cash flow back to zero
A25: Annual break-even revenue
A26: Year # | B26: 1 | C26: 2 | D26: 3 | E26: 4 | F26: 5
B27: Year 1 | C27: Year 2 | D27: Year 3 | E27: Year 4 | F27: Year 5
A28: Revenue | B28: =SUMIF(Monthly!$C$5:$BJ$5,B$26,Monthly!$C$37:$BJ$37) -> 1180182.4 | C28: =SUMIF(Monthly!$C$5:$BJ$5,C$26,Monthly!$C$37:$BJ$37) -> 1805881.5 | D28: =SUMIF(Monthly!$C$5:$BJ$5,D$26,Monthly!$C$37:$BJ$37) -> 2080276.6 | E28: =SUMIF(Monthly!$C$5:$BJ$5,E$26,Monthly!$C$37:$BJ$37) -> 2282431.1 | F28: =SUMIF(Monthly!$C$5:$BJ$5,F$26,Monthly!$C$37:$BJ$37) -> 2440877.2
A29: Gross profit | B29: =SUMIF(Monthly!$C$5:$BJ$5,B$26,Monthly!$C$46:$BJ$46) -> 999760.79 | C29: =SUMIF(Monthly!$C$5:$BJ$5,C$26,Monthly!$C$46:$BJ$46) -> 1517202.4 | D29: =SUMIF(Monthly!$C$5:$BJ$5,D$26,Monthly!$C$46:$BJ$46) -> 1736853.9 | E29: =SUMIF(Monthly!$C$5:$BJ$5,E$26,Monthly!$C$46:$BJ$46) -> 1897646.6 | F29: =SUMIF(Monthly!$C$5:$BJ$5,F$26,Monthly!$C$46:$BJ$46) -> 2022782
A30: Gross margin (contribution) | B30: =IF(B28=0,0,B29/B28) -> 0.84712397 | C30: =IF(C28=0,0,C29/C28) -> 0.84014507 | D30: =IF(D28=0,0,D29/D28) -> 0.83491491 | E30: =IF(E28=0,0,E29/E28) -> 0.83141464 | F30: =IF(F28=0,0,F29/F28) -> 0.82871109
A31: Operating expenses (treated as fixed) | B31: =-SUMIF(Monthly!$C$5:$BJ$5,B$26,Monthly!$C$54:$BJ$54) -> 1123040 | C31: =-SUMIF(Monthly!$C$5:$BJ$5,C$26,Monthly!$C$54:$BJ$54) -> 1123611.2 | D31: =-SUMIF(Monthly!$C$5:$BJ$5,D$26,Monthly!$C$54:$BJ$54) -> 1130823.5 | E31: =-SUMIF(Monthly!$C$5:$BJ$5,E$26,Monthly!$C$54:$BJ$54) -> 1143551.4 | F31: =-SUMIF(Monthly!$C$5:$BJ$5,F$26,Monthly!$C$54:$BJ$54) -> 1160900.5
A32: Break-even revenue (EBITDA = 0) | B32: =IF(B30>0,B31/B30,"n/a") -> 1325709.2 | C32: =IF(C30>0,C31/C30,"n/a") -> 1337401.4 | D32: =IF(D30>0,D31/D30,"n/a") -> 1354417.7 | E32: =IF(E30>0,E31/E30,"n/a") -> 1375428.6 | F32: =IF(F30>0,F31/F30,"n/a") -> 1400850.7
A33: Margin of safety (revenue above break-even) | B33: =IF(AND(ISNUMBER(B32),B28>0),(B28-B32)/B28,"n/a") -> -0.1233087 | C33: =IF(AND(ISNUMBER(C32),C28>0),(C28-C32)/C28,"n/a") -> 0.25941905 | D33: =IF(AND(ISNUMBER(D32),D28>0),(D28-D32)/D28,"n/a") -> 0.34892422 | E33: =IF(AND(ISNUMBER(E32),E28>0),(E28-E32)/E28,"n/a") -> 0.39738441 | F33: =IF(AND(ISNUMBER(F32),F28>0),(F28-F32)/F28,"n/a") -> 0.42608718
A35: Simplification: cost of sales is treated as variable and operating expenses as fixed, so break-even revenue = operating expenses ÷ gross margin.

Sheet Valuation
A1: Discounted cash flow valuation | H1: =HYPERLINK("#'Cover'!A1","◂ Contents") -> ◂ Contents
A2: Enterprise value at the start of the plan, before the funding raised in period 1. Year-end discounting.
A3: Scenario shown | B3: =CHOOSE(Dashboard!$B$4,"Low","Base","High") -> Base
A5: Assumptions (active scenario, from the Inputs sheet)
A6: Discount rate (WACC) | B6: =Inputs!$E$85 -> 0.25
A7: Terminal growth rate | B7: =Inputs!$E$86 -> 0.02
A8: Exit multiple (EV ÷ final-year EBITDA) | B8: =Inputs!$E$87 -> 4
A9: Tax rate (for the interest tax shield) | B9: =Inputs!$E$79 -> 0.21
A10: Sensitivity step: WACC | B10: =Inputs!$E$88 -> 0.01
A11: Sensitivity step: terminal growth | B11: =Inputs!$E$89 -> 0.005
A13: Free cash flow by year
A14: Year # | B14: 1 | C14: 2 | D14: 3 | E14: 4 | F14: 5
B15: Year 1 | C15: Year 2 | D15: Year 3 | E15: Year 4 | F15: Year 5
A16: EBITDA | B16: =SUMIF(Monthly!$C$5:$BJ$5,B$14,Monthly!$C$55:$BJ$55) -> -123279.21 | C16: =SUMIF(Monthly!$C$5:$BJ$5,C$14,Monthly!$C$55:$BJ$55) -> 393591.21 | D16: =SUMIF(Monthly!$C$5:$BJ$5,D$14,Monthly!$C$55:$BJ$55) -> 606030.41 | E16: =SUMIF(Monthly!$C$5:$BJ$5,E$14,Monthly!$C$55:$BJ$55) -> 754095.19 | F16: =SUMIF(Monthly!$C$5:$BJ$5,F$14,Monthly!$C$55:$BJ$55) -> 861881.48
A17: Unlevered free cash flow | B17: =SUMIF(Monthly!$C$5:$BJ$5,B$14,Monthly!$C$107:$BJ$107) -> -4276571.5 | C17: =SUMIF(Monthly!$C$5:$BJ$5,C$14,Monthly!$C$107:$BJ$107) -> 307389.7 | D17: =SUMIF(Monthly!$C$5:$BJ$5,D$14,Monthly!$C$107:$BJ$107) -> 525282.11 | E17: =SUMIF(Monthly!$C$5:$BJ$5,E$14,Monthly!$C$107:$BJ$107) -> 678762.37 | F17: =SUMIF(Monthly!$C$5:$BJ$5,F$14,Monthly!$C$107:$BJ$107) -> 791941.53
A18: Discount factor | B18: =1/(1+Inputs!$E$85)^B$14 -> 0.8 | C18: =1/(1+Inputs!$E$85)^C$14 -> 0.64 | D18: =1/(1+Inputs!$E$85)^D$14 -> 0.512 | E18: =1/(1+Inputs!$E$85)^E$14 -> 0.4096 | F18: =1/(1+Inputs!$E$85)^F$14 -> 0.32768
A19: Present value of free cash flow | B19: =B17*B18 -> -3421257.2 | C19: =C17*C18 -> 196729.41 | D19: =D17*D18 -> 268944.44 | E19: =E17*E18 -> 278021.07 | F19: =F17*F18 -> 259503.4
A21: Enterprise value
B22: Perpetual growth | C22: Exit multiple
A23: Present value of the plan's free cash flows | B23: =SUM($B$19:$F$19) -> -2418058.9 | C23: =B23 -> -2418058.9
A24: Final-year free cash flow | final-year EBITDA | B24: =$F$17 -> 791941.53 | C24: =$F$16 -> 861881.48
A25: Terminal value at the end of year 5 | B25: =IF($B$6>$B$7,B24*(1+$B$7)/($B$6-$B$7),0) -> 3512088.5 | C25: =C24*$B$8 -> 3447525.9
A26: Present value of the terminal value | B26: =B25/(1+$B$6)^$F$14 -> 1150841.2 | C26: =C25/(1+$B$6)^$F$14 -> 1129685.3
A27: Enterprise value | B27: =B23+B26 -> -1267217.7 | C27: =C23+C26 -> -1288373.6
A28: Terminal value share of enterprise value | B28: =IF(B27<>0,B26/B27,0) -> -0.90816374 | C28: =IF(C27<>0,C26/C27,0) -> -0.87683054
A29: Cross-check: implied exit multiple | implied perpetual growth | B29: =IF(C24>0,B25/C24,"n/a") -> 4.0749089 | C29: =IF(C25+B24<>0,(C25*$B$6-B24)/(C25+B24),"n/a") -> 0.016497344
A30: Enterprise value — average of the two methods | B30: =AVERAGE(B27,C27) -> -1277795.6
A32: Sensitivity: enterprise value (perpetual growth) by WACC and terminal growth
A33: WACC ↓ · terminal growth → | B33: =$B$7+(-2)*$B$11 -> 0.01 | C33: =$B$7+(-1)*$B$11 -> 0.015 | D33: =$B$7+(0)*$B$11 -> 0.02 | E33: =$B$7+(1)*$B$11 -> 0.025 | F33: =$B$7+(2)*$B$11 -> 0.03
A34: =$B$6+(-2)*$B$10 -> 0.23 | B34: =IF($A34>B$33,SUMPRODUCT($B$17:$F$17/(1+$A34)^$B$14:$F$14)+$F$17*(1+B$33)/($A34-B$33)/(1+$A34)^$F$14,"n/a") -> -1122165.7 | C34: =IF($A34>C$33,SUMPRODUCT($B$17:$F$17/(1+$A34)^$B$14:$F$14)+$F$17*(1+C$33)/($A34-C$33)/(1+$A34)^$F$14,"n/a") -> -1085590.9 | D34: =IF($A34>D$33,SUMPRODUCT($B$17:$F$17/(1+$A34)^$B$14:$F$14)+$F$17*(1+D$33)/($A34-D$33)/(1+$A34)^$F$14,"n/a") -> -1047274.5 | E34: =IF($A34>E$33,SUMPRODUCT($B$17:$F$17/(1+$A34)^$B$14:$F$14)+$F$17*(1+E$33)/($A34-E$33)/(1+$A34)^$F$14,"n/a") -> -1007089 | F34: =IF($A34>F$33,SUMPRODUCT($B$17:$F$17/(1+$A34)^$B$14:$F$14)+$F$17*(1+F$33)/($A34-F$33)/(1+$A34)^$F$14,"n/a") -> -964894.17
A35: =$B$6+(-1)*$B$10 -> 0.24 | B35: =IF($A35>B$33,SUMPRODUCT($B$17:$F$17/(1+$A35)^$B$14:$F$14)+$F$17*(1+B$33)/($A35-B$33)/(1+$A35)^$F$14,"n/a") -> -1229937.5 | C35: =IF($A35>C$33,SUMPRODUCT($B$17:$F$17/(1+$A35)^$B$14:$F$14)+$F$17*(1+C$33)/($A35-C$33)/(1+$A35)^$F$14,"n/a") -> -1197573.2 | D35: =IF($A35>D$33,SUMPRODUCT($B$17:$F$17/(1+$A35)^$B$14:$F$14)+$F$17*(1+D$33)/($A35-D$33)/(1+$A35)^$F$14,"n/a") -> -1163737.8 | E35: =IF($A35>E$33,SUMPRODUCT($B$17:$F$17/(1+$A35)^$B$14:$F$14)+$F$17*(1+E$33)/($A35-E$33)/(1+$A35)^$F$14,"n/a") -> -1128328.7 | F35: =IF($A35>F$33,SUMPRODUCT($B$17:$F$17/(1+$A35)^$B$14:$F$14)+$F$17*(1+F$33)/($A35-F$33)/(1+$A35)^$F$14,"n/a") -> -1091233.4
A36: =$B$6+(0)*$B$10 -> 0.25 | B36: =IF($A36>B$33,SUMPRODUCT($B$17:$F$17/(1+$A36)^$B$14:$F$14)+$F$17*(1+B$33)/($A36-B$33)/(1+$A36)^$F$14,"n/a") -> -1325982.1 | C36: =IF($A36>C$33,SUMPRODUCT($B$17:$F$17/(1+$A36)^$B$14:$F$14)+$F$17*(1+C$33)/($A36-C$33)/(1+$A36)^$F$14,"n/a") -> -1297225 | D36: =IF($A36>D$33,SUMPRODUCT($B$17:$F$17/(1+$A36)^$B$14:$F$14)+$F$17*(1+D$33)/($A36-D$33)/(1+$A36)^$F$14,"n/a") -> -1267217.7 | E36: =IF($A36>E$33,SUMPRODUCT($B$17:$F$17/(1+$A36)^$B$14:$F$14)+$F$17*(1+E$33)/($A36-E$33)/(1+$A36)^$F$14,"n/a") -> -1235876.7 | F36: =IF($A36>F$33,SUMPRODUCT($B$17:$F$17/(1+$A36)^$B$14:$F$14)+$F$17*(1+F$33)/($A36-F$33)/(1+$A36)^$F$14,"n/a") -> -1203111.1
A37: =$B$6+(1)*$B$10 -> 0.26 | B37: =IF($A37>B$33,SUMPRODUCT($B$17:$F$17/(1+$A37)^$B$14:$F$14)+$F$17*(1+B$33)/($A37-B$33)/(1+$A37)^$F$14,"n/a") -> -1411780.3 | C37: =IF($A37>C$33,SUMPRODUCT($B$17:$F$17/(1+$A37)^$B$14:$F$14)+$F$17*(1+C$33)/($A37-C$33)/(1+$A37)^$F$14,"n/a") -> -1386131 | D37: =IF($A37>D$33,SUMPRODUCT($B$17:$F$17/(1+$A37)^$B$14:$F$14)+$F$17*(1+D$33)/($A37-D$33)/(1+$A37)^$F$14,"n/a") -> -1359413 | E37: =IF($A37>E$33,SUMPRODUCT($B$17:$F$17/(1+$A37)^$B$14:$F$14)+$F$17*(1+E$33)/($A37-E$33)/(1+$A37)^$F$14,"n/a") -> -1331558.1 | F37: =IF($A37>F$33,SUMPRODUCT($B$17:$F$17/(1+$A37)^$B$14:$F$14)+$F$17*(1+F$33)/($A37-F$33)/(1+$A37)^$F$14,"n/a") -> -1302492.1
A38: =$B$6+(2)*$B$10 -> 0.27 | B38: =IF($A38>B$33,SUMPRODUCT($B$17:$F$17/(1+$A38)^$B$14:$F$14)+$F$17*(1+B$33)/($A38-B$33)/(1+$A38)^$F$14,"n/a") -> -1488582.6 | C38: =IF($A38>C$33,SUMPRODUCT($B$17:$F$17/(1+$A38)^$B$14:$F$14)+$F$17*(1+C$33)/($A38-C$33)/(1+$A38)^$F$14,"n/a") -> -1465624.6 | D38: =IF($A38>D$33,SUMPRODUCT($B$17:$F$17/(1+$A38)^$B$14:$F$14)+$F$17*(1+D$33)/($A38-D$33)/(1+$A38)^$F$14,"n/a") -> -1441748.2 | E38: =IF($A38>E$33,SUMPRODUCT($B$17:$F$17/(1+$A38)^$B$14:$F$14)+$F$17*(1+E$33)/($A38-E$33)/(1+$A38)^$F$14,"n/a") -> -1416897.3 | F38: =IF($A38>F$33,SUMPRODUCT($B$17:$F$17/(1+$A38)^$B$14:$F$14)+$F$17*(1+F$33)/($A38-F$33)/(1+$A38)^$F$14,"n/a") -> -1391011
A40: Free cash flow = operating cash flow + interest × (1 − tax rate) − capital spending. Cells marked n/a: WACC not above growth.

Sheet Sources & Uses
A1: Sources and uses of funds | E1: =HYPERLINK("#'Cover'!A1","◂ Contents") -> ◂ Contents
A2: Live for the selected scenario. Where the money comes from and where it goes in the period set below.
A3: Scenario shown | B3: =CHOOSE(Dashboard!$B$4,"Low","Base","High") -> Base
A5: Funding structure ($'000) — raised at the start of the plan
B6: Amount | C6: Share
A7: Equity | B7: =Inputs!$E$67 -> 2100000 | C7: =IF($B$9=0,0,B7/$B$9) -> 0.41176471
A8: Debt (loan) | B8: =Inputs!$E$68 -> 3000000 | C8: =IF($B$9=0,0,B8/$B$9) -> 0.58823529
A9: Total funding | B9: =B7+B8 -> 5100000 | C9: =IF(B9=0,0,1) -> 1
A10: Gearing (debt ÷ equity) | B10: =IF(B7<=0,IF(B8>0,"n/a",0),B8/B7) -> 1.4285714 | D10: n/a: debt without positive equity
A11: Funding required by the plan (Break-even sheet) | B11: ='Break-even'!B12 -> 5249445.5
A12: Funding surplus / (shortfall) | B12: ='Break-even'!B17 -> -149445.46
A14: ="Sources and uses of cash in the first "&$B$16&IF($B$16=1," month"," months")&" ($'000)" -> Sources and uses of cash in the first 12 months ($'000)
A15: Period covered (months from the start) | B15: 12 | D15: 1 to 60 (capped)
A16: Months used | B16: =MIN(60,MAX(1,ROUND(B15,0))) -> 12
A17: Sources | B17: Amount | C17: Share
A18: Equity raised | B18: =SUMPRODUCT(--(Monthly!$C$4:$BJ$4<=$B$16),Monthly!$C$94:$BJ$94) -> 2100000 | C18: =IF($B$21=0,0,B18/$B$21) -> 0.41176471
A19: Loan drawdowns | B19: =SUMPRODUCT(--(Monthly!$C$4:$BJ$4<=$B$16),Monthly!$C$79:$BJ$79) -> 3000000 | C19: =IF($B$21=0,0,B19/$B$21) -> 0.58823529
A20: Cash generated by operations | B20: =MAX(0,SUMPRODUCT(--(Monthly!$C$4:$BJ$4<=$B$16),Monthly!$C$92:$BJ$92)) -> 0 | C20: =IF($B$21=0,0,B20/$B$21) -> 0
A21: Total sources | B21: =SUM(B18:B20) -> 5100000 | C21: =IF(B21=0,0,1) -> 1
A23: Uses | B23: Amount | C23: Share
A24: Cash used by operations | B24: =MAX(0,-SUMPRODUCT(--(Monthly!$C$4:$BJ$4<=$B$16),Monthly!$C$92:$BJ$92)) -> 369557.79 | C24: =IF($B$28=0,0,B24/$B$28) -> 0.072462312
A25: Capital spending | B25: =-SUMPRODUCT(--(Monthly!$C$4:$BJ$4<=$B$16),Monthly!$C$93:$BJ$93) -> 4100000 | C25: =IF($B$28=0,0,B25/$B$28) -> 0.80392157
A26: Loan repayments | B26: =-SUMPRODUCT(--(Monthly!$C$4:$BJ$4<=$B$16),Monthly!$C$80:$BJ$80) -> 275000 | C26: =IF($B$28=0,0,B26/$B$28) -> 0.053921569
A27: Cash at the end of the period | B27: =INDEX(Monthly!$C$98:$BJ$98,$B$16) -> 355442.21 | C27: =IF($B$28=0,0,B27/$B$28) -> 0.06969455
A28: Total uses | B28: =SUM(B24:B27) -> 5100000 | C28: =IF(B28=0,0,1) -> 1
A29: Sources − uses (must be 0; opening cash is 0) | B29: =B21-B28 -> 0

Sheet KPIs
A1: KPIs & ratios | I1: =HYPERLINK("#'Cover'!A1","◂ Contents") -> ◂ Contents
A2: Car wash financial model (planning) — industry metrics and financial ratios for the active scenario
A4: Financial ratios
B5: 1 | C5: 2 | D5: 3 | E5: 4 | F5: 5 | G5: Target
A6: Revenue growth | B6: =IF(N('P&L'!A5)<=0,"n/a",'P&L'!B5/'P&L'!A5-1) -> n/a | C6: =IF(N('P&L'!B5)<=0,"n/a",'P&L'!C5/'P&L'!B5-1) -> 0.53017151 | D6: =IF(N('P&L'!C5)<=0,"n/a",'P&L'!D5/'P&L'!C5-1) -> 0.15194526 | E6: =IF(N('P&L'!D5)<=0,"n/a",'P&L'!E5/'P&L'!D5-1) -> 0.097176748 | F6: =IF(N('P&L'!E5)<=0,"n/a",'P&L'!F5/'P&L'!E5-1) -> 0.069419886
A7: Gross margin | B7: =IF('P&L'!B5<=0,"n/a",'P&L'!B7/'P&L'!B5) -> 0.84712397 | C7: =IF('P&L'!C5<=0,"n/a",'P&L'!C7/'P&L'!C5) -> 0.84014507 | D7: =IF('P&L'!D5<=0,"n/a",'P&L'!D7/'P&L'!D5) -> 0.83491491 | E7: =IF('P&L'!E5<=0,"n/a",'P&L'!E7/'P&L'!E5) -> 0.83141464 | F7: =IF('P&L'!F5<=0,"n/a",'P&L'!F7/'P&L'!F5) -> 0.82871109
A8: EBITDA margin | B8: =IF('P&L'!B5<=0,"n/a",'P&L'!B15/'P&L'!B5) -> -0.10445776 | C8: =IF('P&L'!C5<=0,"n/a",'P&L'!C15/'P&L'!C5) -> 0.21794964 | D8: =IF('P&L'!D5<=0,"n/a",'P&L'!D15/'P&L'!D5) -> 0.29132204 | E8: =IF('P&L'!E5<=0,"n/a",'P&L'!E15/'P&L'!E5) -> 0.33039122 | F8: =IF('P&L'!F5<=0,"n/a",'P&L'!F15/'P&L'!F5) -> 0.35310317
A9: Net margin | B9: =IF('P&L'!B5<=0,"n/a",'P&L'!B22/'P&L'!B5) -> -0.60095146 | C9: =IF('P&L'!C5<=0,"n/a",'P&L'!C22/'P&L'!C5) -> -0.094294003 | D9: =IF('P&L'!D5<=0,"n/a",'P&L'!D22/'P&L'!D5) -> 0.030919964 | E9: =IF('P&L'!E5<=0,"n/a",'P&L'!E22/'P&L'!E5) -> 0.10276478 | F9: =IF('P&L'!F5<=0,"n/a",'P&L'!F22/'P&L'!F5) -> 0.14933422
A10: Payroll, % of revenue | B10: =IF('P&L'!B5<=0,"n/a",-SUMIF(Headcount!$C$5:$BJ$5,B$5,Headcount!$C$15:$BJ$15)/'P&L'!B5) -> 0.3720103 | C10: =IF('P&L'!C5<=0,"n/a",-SUMIF(Headcount!$C$5:$BJ$5,C$5,Headcount!$C$15:$BJ$15)/'P&L'!C5) -> 0.25041023 | D10: =IF('P&L'!D5<=0,"n/a",-SUMIF(Headcount!$C$5:$BJ$5,D$5,Headcount!$C$15:$BJ$15)/'P&L'!D5) -> 0.22390173 | E10: =IF('P&L'!E5<=0,"n/a",-SUMIF(Headcount!$C$5:$BJ$5,E$5,Headcount!$C$15:$BJ$15)/'P&L'!E5) -> 0.21019292 | F10: =IF('P&L'!F5<=0,"n/a",-SUMIF(Headcount!$C$5:$BJ$5,F$5,Headcount!$C$15:$BJ$15)/'P&L'!F5) -> 0.202445
A11: Marketing, % of revenue | B11: =IF('P&L'!B5<=0,"n/a",-'P&L'!B13/'P&L'!B5) -> 0.12201504 | C11: =IF('P&L'!C5<=0,"n/a",-'P&L'!C13/'P&L'!C5) -> 0.063791562 | D11: =IF('P&L'!D5<=0,"n/a",-'P&L'!D13/'P&L'!D5) -> 0.044301801 | E11: =IF('P&L'!E5<=0,"n/a",-'P&L'!E13/'P&L'!E5) -> 0.032302399 | F11: =IF('P&L'!F5<=0,"n/a",-'P&L'!F13/'P&L'!F5) -> 0.024164427
A12: Operating expenses, % of revenue | B12: =IF('P&L'!B5<=0,"n/a",-'P&L'!B14/'P&L'!B5) -> 0.95158173 | C12: =IF('P&L'!C5<=0,"n/a",-'P&L'!C14/'P&L'!C5) -> 0.62219543 | D12: =IF('P&L'!D5<=0,"n/a",-'P&L'!D14/'P&L'!D5) -> 0.54359287 | E12: =IF('P&L'!E5<=0,"n/a",-'P&L'!E14/'P&L'!E5) -> 0.50102342 | F12: =IF('P&L'!F5<=0,"n/a",-'P&L'!F14/'P&L'!F5) -> 0.47560792
A13: Current ratio (current assets ÷ current liabilities) | B13: =IF(('Balance Sheet'!B12-'Balance Sheet'!B11)<=0,"n/a",('Balance Sheet'!B5+'Balance Sheet'!B6+'Balance Sheet'!B7)/('Balance Sheet'!B12-'Balance Sheet'!B11)) -> 25.135252 | C13: =IF(('Balance Sheet'!C12-'Balance Sheet'!C11)<=0,"n/a",('Balance Sheet'!C5+'Balance Sheet'!C6+'Balance Sheet'!C7)/('Balance Sheet'!C12-'Balance Sheet'!C11)) -> 11.282828 | D13: =IF(('Balance Sheet'!D12-'Balance Sheet'!D11)<=0,"n/a",('Balance Sheet'!D5+'Balance Sheet'!D6+'Balance Sheet'!D7)/('Balance Sheet'!D12-'Balance Sheet'!D11)) -> 13.302865 | E13: =IF(('Balance Sheet'!E12-'Balance Sheet'!E11)<=0,"n/a",('Balance Sheet'!E5+'Balance Sheet'!E6+'Balance Sheet'!E7)/('Balance Sheet'!E12-'Balance Sheet'!E11)) -> 22.536648 | F13: =IF(('Balance Sheet'!F12-'Balance Sheet'!F11)<=0,"n/a",('Balance Sheet'!F5+'Balance Sheet'!F6+'Balance Sheet'!F7)/('Balance Sheet'!F12-'Balance Sheet'!F11)) -> 35.845086
A14: Debt ÷ equity (loan ÷ total equity) | B14: =IF('Balance Sheet'!B15<=0,"n/a",'Balance Sheet'!B11/'Balance Sheet'!B15) -> 1.9593495 | C14: =IF('Balance Sheet'!C15<=0,"n/a",'Balance Sheet'!C11/'Balance Sheet'!C15) -> 1.9869169 | D14: =IF('Balance Sheet'!D15<=0,"n/a",'Balance Sheet'!D11/'Balance Sheet'!D15) -> 1.6539463 | E14: =IF('Balance Sheet'!E15<=0,"n/a",'Balance Sheet'!E11/'Balance Sheet'!E15) -> 1.2011641 | F14: =IF('Balance Sheet'!F15<=0,"n/a",'Balance Sheet'!F11/'Balance Sheet'!F15) -> 0.80950558
A15: Return on assets (net income ÷ year-end assets) | B15: =IF('Balance Sheet'!B9<=0,"n/a",'P&L'!B22/'Balance Sheet'!B9) -> -0.17170296 | C15: =IF('Balance Sheet'!C9<=0,"n/a",'P&L'!C22/'Balance Sheet'!C9) -> -0.046472672 | D15: =IF('Balance Sheet'!D9<=0,"n/a",'P&L'!D22/'Balance Sheet'!D9) -> 0.018745525 | E15: =IF('Balance Sheet'!E9<=0,"n/a",'P&L'!E22/'Balance Sheet'!E9) -> 0.069639969 | F15: =IF('Balance Sheet'!F9<=0,"n/a",'P&L'!F22/'Balance Sheet'!F9) -> 0.10613326
A16: Return on equity (net income ÷ year-end equity) | B16: =IF('Balance Sheet'!B15<=0,"n/a",'P&L'!B22/'Balance Sheet'!B15) -> -0.50995745 | C16: =IF('Balance Sheet'!C15<=0,"n/a",'P&L'!C22/'Balance Sheet'!C15) -> -0.13952154 | D16: =IF('Balance Sheet'!D15<=0,"n/a",'P&L'!D22/'Balance Sheet'!D15) -> 0.050063652 | E16: =IF('Balance Sheet'!E15<=0,"n/a",'P&L'!E22/'Balance Sheet'!E15) -> 0.15437658 | F16: =IF('Balance Sheet'!F15<=0,"n/a",'P&L'!F22/'Balance Sheet'!F15) -> 0.19348855
A18: DuPont analysis — return on equity = net margin × asset turnover × equity multiplier
B19: 1 | C19: 2 | D19: 3 | E19: 4 | F19: 5
A20: Net margin | B20: =IF('P&L'!B5<=0,"n/a",'P&L'!B22/'P&L'!B5) -> -0.60095146 | C20: =IF('P&L'!C5<=0,"n/a",'P&L'!C22/'P&L'!C5) -> -0.094294003 | D20: =IF('P&L'!D5<=0,"n/a",'P&L'!D22/'P&L'!D5) -> 0.030919964 | E20: =IF('P&L'!E5<=0,"n/a",'P&L'!E22/'P&L'!E5) -> 0.10276478 | F20: =IF('P&L'!F5<=0,"n/a",'P&L'!F22/'P&L'!F5) -> 0.14933422
A21: × Asset turnover (revenue ÷ assets) | B21: =IF('Balance Sheet'!B9<=0,"n/a",'P&L'!B5/'Balance Sheet'!B9) -> 0.28571851 | C21: =IF('Balance Sheet'!C9<=0,"n/a",'P&L'!C5/'Balance Sheet'!C9) -> 0.49284866 | D21: =IF('Balance Sheet'!D9<=0,"n/a",'P&L'!D5/'Balance Sheet'!D9) -> 0.60625958 | E21: =IF('Balance Sheet'!E9<=0,"n/a",'P&L'!E5/'Balance Sheet'!E9) -> 0.6776638 | F21: =IF('Balance Sheet'!F9<=0,"n/a",'P&L'!F5/'Balance Sheet'!F9) -> 0.71070958
A22: × Equity multiplier (assets ÷ equity) | B22: =IF('Balance Sheet'!B15<=0,"n/a",'Balance Sheet'!B9/'Balance Sheet'!B15) -> 2.9699981 | C22: =IF('Balance Sheet'!C15<=0,"n/a",'Balance Sheet'!C9/'Balance Sheet'!C15) -> 3.0022276 | D22: =IF('Balance Sheet'!D15<=0,"n/a",'Balance Sheet'!D9/'Balance Sheet'!D15) -> 2.6706989 | E22: =IF('Balance Sheet'!E15<=0,"n/a",'Balance Sheet'!E9/'Balance Sheet'!E15) -> 2.2167813 | F22: =IF('Balance Sheet'!F15<=0,"n/a",'Balance Sheet'!F9/'Balance Sheet'!F15) -> 1.8230718
A23: Return on equity (product of the three) | B23: =IF(AND(ISNUMBER(B20),ISNUMBER(B21),ISNUMBER(B22)),B20*B21*B22,"n/a") -> -0.50995745 | C23: =IF(AND(ISNUMBER(C20),ISNUMBER(C21),ISNUMBER(C22)),C20*C21*C22,"n/a") -> -0.13952154 | D23: =IF(AND(ISNUMBER(D20),ISNUMBER(D21),ISNUMBER(D22)),D20*D21*D22,"n/a") -> 0.050063652 | E23: =IF(AND(ISNUMBER(E20),ISNUMBER(E21),ISNUMBER(E22)),E20*E21*E22,"n/a") -> 0.15437658 | F23: =IF(AND(ISNUMBER(F20),ISNUMBER(F21),ISNUMBER(F22)),F20*F21*F22,"n/a") -> 0.19348855
A24: Check: product − return on equity (must be 0) | B24: =IF(AND(ISNUMBER(B23),ISNUMBER(B16)),B23-B16,IF(ISNUMBER(B23),1,IF(AND(ISNUMBER(B16),ISNUMBER(B20),ISNUMBER(B21)),1,0))) -> 0 | C24: =IF(AND(ISNUMBER(C23),ISNUMBER(C16)),C23-C16,IF(ISNUMBER(C23),1,IF(AND(ISNUMBER(C16),ISNUMBER(C20),ISNUMBER(C21)),1,0))) -> 0 | D24: =IF(AND(ISNUMBER(D23),ISNUMBER(D16)),D23-D16,IF(ISNUMBER(D23),1,IF(AND(ISNUMBER(D16),ISNUMBER(D20),ISNUMBER(D21)),1,0))) -> 0 | E24: =IF(AND(ISNUMBER(E23),ISNUMBER(E16)),E23-E16,IF(ISNUMBER(E23),1,IF(AND(ISNUMBER(E16),ISNUMBER(E20),ISNUMBER(E21)),1,0))) -> 0 | F24: =IF(AND(ISNUMBER(F23),ISNUMBER(F16)),F23-F16,IF(ISNUMBER(F23),1,IF(AND(ISNUMBER(F16),ISNUMBER(F20),ISNUMBER(F21)),1,0))) -> 0
A26: Car wash metrics ($'000; per-unit rows in $)
A27: Year # | B27: 1 | C27: 2 | D27: 3 | E27: 4 | F27: 5
B28: Year 1 | C28: Year 2 | D28: Year 3 | E28: Year 4 | F28: Year 5 | G28: Target
A29: Unlimited members (year end) | B29: =INDEX(Monthly!$C$19:$BJ$19,B$27*12) -> 972.08918 | C29: =INDEX(Monthly!$C$19:$BJ$19,C$27*12) -> 1644.3434 | D29: =INDEX(Monthly!$C$19:$BJ$19,D$27*12) -> 2081.656 | E29: =INDEX(Monthly!$C$19:$BJ$19,E$27*12) -> 2376.2884 | F29: =INDEX(Monthly!$C$19:$BJ$19,F$27*12) -> 2584.8337
A30: New members in the year | B30: =SUMIF(Monthly!$C$5:$BJ$5,B$27,Monthly!$C$16:$BJ$16) -> 981.45307 | C30: =SUMIF(Monthly!$C$5:$BJ$5,C$27,Monthly!$C$16:$BJ$16) -> 1298.16 | D30: =SUMIF(Monthly!$C$5:$BJ$5,D$27,Monthly!$C$16:$BJ$16) -> 1329.66 | E30: =SUMIF(Monthly!$C$5:$BJ$5,E$27,Monthly!$C$16:$BJ$16) -> 1362.735 | F30: =SUMIF(Monthly!$C$5:$BJ$5,F$27,Monthly!$C$16:$BJ$16) -> 1397.4637
A31: Members who cancelled in the year | B31: =SUMIF(Monthly!$C$5:$BJ$5,B$27,Monthly!$C$18:$BJ$18) -> -259.36388 | C31: =SUMIF(Monthly!$C$5:$BJ$5,C$27,Monthly!$C$18:$BJ$18) -> -625.9058 | D31: =SUMIF(Monthly!$C$5:$BJ$5,D$27,Monthly!$C$18:$BJ$18) -> -892.34737 | E31: =SUMIF(Monthly!$C$5:$BJ$5,E$27,Monthly!$C$18:$BJ$18) -> -1068.1026 | F31: =SUMIF(Monthly!$C$5:$BJ$5,F$27,Monthly!$C$18:$BJ$18) -> -1188.9185
A32: Members who cancel per month | B32: =Inputs!$E$23 -> 0.04 | C32: =Inputs!$E$23 -> 0.04 | D32: =Inputs!$E$23 -> 0.04 | E32: =Inputs!$E$23 -> 0.04 | F32: =Inputs!$E$23 -> 0.04
A33: Washes in the year | B33: =SUMIF(Monthly!$C$5:$BJ$5,B$27,Monthly!$C$28:$BJ$28) -> 88966.949 | C33: =SUMIF(Monthly!$C$5:$BJ$5,C$27,Monthly!$C$28:$BJ$28) -> 139676.34 | D33: =SUMIF(Monthly!$C$5:$BJ$5,D$27,Monthly!$C$28:$BJ$28) -> 162504.89 | E33: =SUMIF(Monthly!$C$5:$BJ$5,E$27,Monthly!$C$28:$BJ$28) -> 177588.88 | F33: =SUMIF(Monthly!$C$5:$BJ$5,F$27,Monthly!$C$28:$BJ$28) -> 187982.53
A34: Retail cars washed | B34: =SUMIF(Monthly!$C$5:$BJ$5,B$27,Monthly!$C$26:$BJ$26) -> 64869.133 | C34: =SUMIF(Monthly!$C$5:$BJ$5,C$27,Monthly!$C$26:$BJ$26) -> 83520 | D34: =SUMIF(Monthly!$C$5:$BJ$5,D$27,Monthly!$C$26:$BJ$26) -> 83520 | E34: =SUMIF(Monthly!$C$5:$BJ$5,E$27,Monthly!$C$26:$BJ$26) -> 83520 | F34: =SUMIF(Monthly!$C$5:$BJ$5,F$27,Monthly!$C$26:$BJ$26) -> 83520
A35: Member washes | B35: =SUMIF(Monthly!$C$5:$BJ$5,B$27,Monthly!$C$27:$BJ$27) -> 24097.816 | C35: =SUMIF(Monthly!$C$5:$BJ$5,C$27,Monthly!$C$27:$BJ$27) -> 56156.344 | D35: =SUMIF(Monthly!$C$5:$BJ$5,D$27,Monthly!$C$27:$BJ$27) -> 78984.895 | E35: =SUMIF(Monthly!$C$5:$BJ$5,E$27,Monthly!$C$27:$BJ$27) -> 94068.88 | F35: =SUMIF(Monthly!$C$5:$BJ$5,F$27,Monthly!$C$27:$BJ$27) -> 104462.53
A36: Member share of washes | B36: =IF(B33=0,0,B35/B33) -> 0.27086256 | C36: =IF(C33=0,0,C35/C33) -> 0.40204621 | D36: =IF(D33=0,0,D35/D33) -> 0.48604625 | E36: =IF(E33=0,0,E35/E33) -> 0.52970028 | F36: =IF(F33=0,0,F35/F33) -> 0.5557034
A37: Washes per operating day | B37: =IF(Inputs!$E$8=0,0,B33/(Inputs!$E$8*12)) -> 255.65215 | C37: =IF(Inputs!$E$8=0,0,C33/(Inputs!$E$8*12)) -> 401.36881 | D37: =IF(Inputs!$E$8=0,0,D33/(Inputs!$E$8*12)) -> 466.96809 | E37: =IF(Inputs!$E$8=0,0,E33/(Inputs!$E$8*12)) -> 510.31287 | F37: =IF(Inputs!$E$8=0,0,F33/(Inputs!$E$8*12)) -> 540.17969
A38: Tunnel capacity (washes) | B38: =SUMIF(Monthly!$C$5:$BJ$5,B$27,Monthly!$C$24:$BJ$24) -> 294756 | C38: =SUMIF(Monthly!$C$5:$BJ$5,C$27,Monthly!$C$24:$BJ$24) -> 294756 | D38: =SUMIF(Monthly!$C$5:$BJ$5,D$27,Monthly!$C$24:$BJ$24) -> 294756 | E38: =SUMIF(Monthly!$C$5:$BJ$5,E$27,Monthly!$C$24:$BJ$24) -> 294756 | F38: =SUMIF(Monthly!$C$5:$BJ$5,F$27,Monthly!$C$24:$BJ$24) -> 294756
A39: Tunnel capacity used | B39: =IF(B38=0,0,B33/B38) -> 0.30183253 | C39: =IF(C38=0,0,C33/C38) -> 0.47387108 | D39: =IF(D38=0,0,D33/D38) -> 0.55132006 | E39: =IF(E38=0,0,E33/E38) -> 0.60249454 | F39: =IF(F38=0,0,F33/F38) -> 0.63775642
A40: Washes lost to the capacity limit | B40: =SUMIF(Monthly!$C$5:$BJ$5,B$27,Monthly!$C$29:$BJ$29) -> 0 | C40: =SUMIF(Monthly!$C$5:$BJ$5,C$27,Monthly!$C$29:$BJ$29) -> 0 | D40: =SUMIF(Monthly!$C$5:$BJ$5,D$27,Monthly!$C$29:$BJ$29) -> 0 | E40: =SUMIF(Monthly!$C$5:$BJ$5,E$27,Monthly!$C$29:$BJ$29) -> 0 | F40: =SUMIF(Monthly!$C$5:$BJ$5,F$27,Monthly!$C$29:$BJ$29) -> 0
A41: Revenue | B41: =SUMIF(Monthly!$C$5:$BJ$5,B$27,Monthly!$C$37:$BJ$37) -> 1180182.4 | C41: =SUMIF(Monthly!$C$5:$BJ$5,C$27,Monthly!$C$37:$BJ$37) -> 1805881.5 | D41: =SUMIF(Monthly!$C$5:$BJ$5,D$27,Monthly!$C$37:$BJ$37) -> 2080276.6 | E41: =SUMIF(Monthly!$C$5:$BJ$5,E$27,Monthly!$C$37:$BJ$37) -> 2282431.1 | F41: =SUMIF(Monthly!$C$5:$BJ$5,F$27,Monthly!$C$37:$BJ$37) -> 2440877.2
A42: Unlimited plan fees | B42: =SUMIF(Monthly!$C$5:$BJ$5,B$27,Monthly!$C$36:$BJ$36) -> 239579.96 | C42: =SUMIF(Monthly!$C$5:$BJ$5,C$27,Monthly!$C$36:$BJ$36) -> 570620.67 | D42: =SUMIF(Monthly!$C$5:$BJ$5,D$27,Monthly!$C$36:$BJ$36) -> 820310.58 | E42: =SUMIF(Monthly!$C$5:$BJ$5,E$27,Monthly!$C$36:$BJ$36) -> 997265.78 | F42: =SUMIF(Monthly!$C$5:$BJ$5,F$27,Monthly!$C$36:$BJ$36) -> 1130008.6
A43: Retail wash & add-on revenue | B43: =B41-B42 -> 940602.43 | C43: =C41-C42 -> 1235260.8 | D43: =D41-D42 -> 1259966 | E43: =E41-E42 -> 1285165.3 | F43: =F41-F42 -> 1310868.6
A44: Plan fees share of revenue | B44: =IF(B41=0,0,B42/B41) -> 0.20300249 | C44: =IF(C41=0,0,C42/C41) -> 0.31597903 | D44: =IF(D41=0,0,D42/D41) -> 0.39432765 | E44: =IF(E41=0,0,E42/E41) -> 0.43693138 | F44: =IF(F41=0,0,F42/F41) -> 0.46295183
A45: Revenue per wash ($) | B45: =IF(B33=0,0,B41/B33) -> 13.265403 | C45: =IF(C33=0,0,C41/C33) -> 12.929043 | D45: =IF(D33=0,0,D41/D33) -> 12.801317 | E45: =IF(E33=0,0,E41/E33) -> 12.852331 | F45: =IF(F33=0,0,F41/F33) -> 12.984596
A46: Plan fee revenue per member wash ($) | B46: =IF(B35=0,0,B42/B35) -> 9.9419781 | C46: =IF(C35=0,0,C42/C35) -> 10.161286 | D46: =IF(D35=0,0,D42/D35) -> 10.385664 | E46: =IF(E35=0,0,E42/E35) -> 10.601442 | F46: =IF(F35=0,0,F42/F35) -> 10.817358
A47: Chemicals, water & electricity | B47: =SUMIF(Monthly!$C$5:$BJ$5,B$27,Monthly!$C$43:$BJ$43) -> -145016.13 | C47: =SUMIF(Monthly!$C$5:$BJ$5,C$27,Monthly!$C$43:$BJ$43) -> -234502.61 | D47: =SUMIF(Monthly!$C$5:$BJ$5,D$27,Monthly!$C$43:$BJ$43) -> -281014.35 | E47: =SUMIF(Monthly!$C$5:$BJ$5,E$27,Monthly!$C$43:$BJ$43) -> -316311.55 | F47: =SUMIF(Monthly!$C$5:$BJ$5,F$27,Monthly!$C$43:$BJ$43) -> -344868.87
A48: Chemicals, water & electricity per wash ($) | B48: =IF(B33=0,0,-B47/B33) -> 1.63 | C48: =IF(C33=0,0,-C47/C33) -> 1.6789 | D48: =IF(D33=0,0,-D47/D33) -> 1.729267 | E48: =IF(E33=0,0,-E47/E33) -> 1.781145 | F48: =IF(F33=0,0,-F47/F33) -> 1.8345794
A49: Gross profit | B49: =SUMIF(Monthly!$C$5:$BJ$5,B$27,Monthly!$C$46:$BJ$46) -> 999760.79 | C49: =SUMIF(Monthly!$C$5:$BJ$5,C$27,Monthly!$C$46:$BJ$46) -> 1517202.4 | D49: =SUMIF(Monthly!$C$5:$BJ$5,D$27,Monthly!$C$46:$BJ$46) -> 1736853.9 | E49: =SUMIF(Monthly!$C$5:$BJ$5,E$27,Monthly!$C$46:$BJ$46) -> 1897646.6 | F49: =SUMIF(Monthly!$C$5:$BJ$5,F$27,Monthly!$C$46:$BJ$46) -> 2022782
A50: Gross margin | B50: =IF(B41=0,0,B49/B41) -> 0.84712397 | C50: =IF(C41=0,0,C49/C41) -> 0.84014507 | D50: =IF(D41=0,0,D49/D41) -> 0.83491491 | E50: =IF(E41=0,0,E49/E41) -> 0.83141464 | F50: =IF(F41=0,0,F49/F41) -> 0.82871109
A51: EBITDA | B51: =SUMIF(Monthly!$C$5:$BJ$5,B$27,Monthly!$C$55:$BJ$55) -> -123279.21 | C51: =SUMIF(Monthly!$C$5:$BJ$5,C$27,Monthly!$C$55:$BJ$55) -> 393591.21 | D51: =SUMIF(Monthly!$C$5:$BJ$5,D$27,Monthly!$C$55:$BJ$55) -> 606030.41 | E51: =SUMIF(Monthly!$C$5:$BJ$5,E$27,Monthly!$C$55:$BJ$55) -> 754095.19 | F51: =SUMIF(Monthly!$C$5:$BJ$5,F$27,Monthly!$C$55:$BJ$55) -> 861881.48
A52: EBITDA margin | B52: =IF(B41=0,0,B51/B41) -> -0.10445776 | C52: =IF(C41=0,0,C51/C41) -> 0.21794964 | D52: =IF(D41=0,0,D51/D41) -> 0.29132204 | E52: =IF(E41=0,0,E51/E41) -> 0.33039122 | F52: =IF(F41=0,0,F51/F41) -> 0.35310317

Sheet Inputs
A1: Inputs — Low / Base / High | I1: =HYPERLINK("#'Cover'!A1","◂ Contents") -> ◂ Contents
A2: Illustrative assumptions - replace them with your own numbers.
A5: Driver | B5: Low | C5: Base | D5: High | E5: Active | F5: Unit | G5: Source / comment
A6: Retail volume
A7: Retail cars per operating day at maturity (year 1) | B7: 200 | C7: 240 | D7: 280 | E7: =CHOOSE(Dashboard!$B$4,B7,C7,D7) -> 240 | F7: cars | G7: Low ≤ Base ≤ High
A8: Operating days per month | B8: 29 | C8: 29 | D8: 29 | E8: =CHOOSE(Dashboard!$B$4,B8,C8,D8) -> 29 | F8: days
A9: Months to reach mature retail volume (0 = already mature) | B9: 12 | C9: 9 | D9: 7 | E9: =CHOOSE(Dashboard!$B$4,B9,C9,D9) -> 9 | F9: months | G9: Low ≥ Base ≥ High (lower is better)
A10: Retail volume in month 1, % of mature | B10: 0.35 | C10: 0.45 | D10: 0.55 | E10: =CHOOSE(Dashboard!$B$4,B10,C10,D10) -> 0.45 | F10: % | G10: Low ≤ Base ≤ High
A11: Winter volume dip, December-February (monthly models) | B11: 0.2 | C11: 0.15 | D11: 0.1 | E11: =CHOOSE(Dashboard!$B$4,B11,C11,D11) -> 0.15 | F11: % | G11: Low ≥ Base ≥ High (lower is better)
A13: Tunnel capacity
A14: Rated tunnel speed | B14: 140 | C14: 140 | D14: 140 | E14: =CHOOSE(Dashboard!$B$4,B14,C14,D14) -> 140 | F14: cars/hour
A15: Hours open per day | B15: 11 | C15: 11 | D15: 11 | E15: =CHOOSE(Dashboard!$B$4,B15,C15,D15) -> 11 | F15: hours
A16: Practical throughput, % of rated speed over open hours | B16: 0.55 | C16: 0.55 | D16: 0.55 | E16: =CHOOSE(Dashboard!$B$4,B16,C16,D16) -> 0.55 | F16: %
A18: Unlimited members
A19: Unlimited members at start (presale or current base) | B19: 150 | C19: 250 | D19: 350 | E19: =CHOOSE(Dashboard!$B$4,B19,C19,D19) -> 250 | F19: # | G19: Low ≤ Base ≤ High
A20: Direct sign-ups per month at maturity (year 1) | B20: 40 | C20: 50 | D20: 60 | E20: =CHOOSE(Dashboard!$B$4,B20,C20,D20) -> 50 | F20: # | G20: Low ≤ Base ≤ High
A21: Direct sign-ups growth per year | B21: 0 | C21: 0.05 | D21: 0.1 | E21: =CHOOSE(Dashboard!$B$4,B21,C21,D21) -> 0.05 | F21: % | G21: Low ≤ Base ≤ High
A22: Retail cars that sign up for an unlimited plan | B22: 0.006 | C22: 0.008 | D22: 0.01 | E22: =CHOOSE(Dashboard!$B$4,B22,C22,D22) -> 0.008 | F22: % | G22: Low ≤ Base ≤ High
A23: Members who cancel per month | B23: 0.05 | C23: 0.04 | D23: 0.032 | E23: =CHOOSE(Dashboard!$B$4,B23,C23,D23) -> 0.04 | F23: % | G23: Low ≥ Base ≥ High (lower is better)
A24: Washes per member per month | B24: 3.8 | C24: 3.5 | D24: 3.2 | E24: =CHOOSE(Dashboard!$B$4,B24,C24,D24) -> 3.5 | F24: washes | G24: Low ≥ Base ≥ High (lower is better)
A26: Prices
A27: Average price per retail wash (year 1) | B27: 12 | C27: 13 | D27: 14 | E27: =CHOOSE(Dashboard!$B$4,B27,C27,D27) -> 13 | F27: $ | G27: Low ≤ Base ≤ High
A28: Add-on revenue per retail car (wax, ceramic, tire shine) | B28: 1.2 | C28: 1.5 | D28: 1.8 | E28: =CHOOSE(Dashboard!$B$4,B28,C28,D28) -> 1.5 | F28: $ | G28: Low ≤ Base ≤ High
A29: Unlimited plan fee per member per month (year 1) | B29: 32 | C29: 35 | D29: 38 | E29: =CHOOSE(Dashboard!$B$4,B29,C29,D29) -> 35 | F29: $ | G29: Low ≤ Base ≤ High
A30: Price increase per year | B30: 0.01 | C30: 0.02 | D30: 0.03 | E30: =CHOOSE(Dashboard!$B$4,B30,C30,D30) -> 0.02 | F30: % | G30: Low ≤ Base ≤ High
A32: Variable cost per wash
A33: Chemicals per wash | B33: 0.95 | C33: 0.85 | D33: 0.75 | E33: =CHOOSE(Dashboard!$B$4,B33,C33,D33) -> 0.85 | F33: $ | G33: Low ≥ Base ≥ High (lower is better)
A34: Fresh water per wash (after reclaim) | B34: 45 | C34: 40 | D34: 36 | E34: =CHOOSE(Dashboard!$B$4,B34,C34,D34) -> 40 | F34: gallons | G34: Low ≥ Base ≥ High (lower is better)
A35: Water and sewer rate per 1,000 gallons | B35: 10 | C35: 9 | D35: 8 | E35: =CHOOSE(Dashboard!$B$4,B35,C35,D35) -> 9 | F35: $ | G35: Low ≥ Base ≥ High (lower is better)
A36: Electricity per wash | B36: 0.45 | C36: 0.42 | D36: 0.4 | E36: =CHOOSE(Dashboard!$B$4,B36,C36,D36) -> 0.42 | F36: $ | G36: Low ≥ Base ≥ High (lower is better)
A37: Card processing fees, % of revenue | B37: 0.032 | C37: 0.03 | D37: 0.028 | E37: =CHOOSE(Dashboard!$B$4,B37,C37,D37) -> 0.03 | F37: % | G37: Low ≥ Base ≥ High (lower is better)
A38: Cost increase per year (per-wash costs, maintenance, other) | B38: 0.04 | C38: 0.03 | D38: 0.025 | E38: =CHOOSE(Dashboard!$B$4,B38,C38,D38) -> 0.03 | F38: % | G38: Low ≥ Base ≥ High (lower is better)
A40: Site costs
A41: Site lease or land cost per month | B41: 30000 | C41: 30000 | D41: 30000 | E41: =CHOOSE(Dashboard!$B$4,B41,C41,D41) -> 30000 | F41: $
A42: Lease increase per year | B42: 0.03 | C42: 0.03 | D42: 0.03 | E42: =CHOOSE(Dashboard!$B$4,B42,C42,D42) -> 0.03 | F42: %
A43: Equipment maintenance & repairs per month | B43: 5500 | C43: 5500 | D43: 5500 | E43: =CHOOSE(Dashboard!$B$4,B43,C43,D43) -> 5500 | F43: $
A44: Insurance, property tax, software & other G&A per month | B44: 9500 | C44: 9500 | D44: 9500 | E44: =CHOOSE(Dashboard!$B$4,B44,C44,D44) -> 9500 | F44: $
A45: Marketing budget per month (year 1) | B45: 12000 | C45: 12000 | D45: 12000 | E45: =CHOOSE(Dashboard!$B$4,B45,C45,D45) -> 12000 | F45: $
A46: Marketing budget growth per year | B46: -0.3 | C46: -0.2 | D46: -0.1 | E46: =CHOOSE(Dashboard!$B$4,B46,C46,D46) -> -0.2 | F46: % | G46: Low ≤ Base ≤ High
A48: Capital spending
A49: Tunnel equipment (month 1) | B49: 1650000 | C49: 1650000 | D49: 1650000 | E49: =CHOOSE(Dashboard!$B$4,B49,C49,D49) -> 1650000 | F49: $
A50: Building & site works (month 1) | B50: 2300000 | C50: 2300000 | D50: 2300000 | E50: =CHOOSE(Dashboard!$B$4,B50,C50,D50) -> 2300000 | F50: $
A51: Pay stations, signage & vacuums (month 1) | B51: 150000 | C51: 150000 | D51: 150000 | E51: =CHOOSE(Dashboard!$B$4,B51,C51,D51) -> 150000 | F51: $
A52: Equipment refresh & upgrades per year (from year 2) | B52: 40000 | C52: 40000 | D52: 40000 | E52: =CHOOSE(Dashboard!$B$4,B52,C52,D52) -> 40000 | F52: $
A54: Headcount
A55: Site manager: headcount (FTE) | B55: 1 | C55: 1 | D55: 1 | E55: =CHOOSE(Dashboard!$B$4,B55,C55,D55) -> 1 | F55: FTE | G55: Low ≤ Base ≤ High
A56: Site manager: salary per FTE per year | B56: 72000 | C56: 72000 | D56: 72000 | E56: =CHOOSE(Dashboard!$B$4,B56,C56,D56) -> 72000 | F56: $
A57: Site manager: headcount growth per year | B57: 0 | C57: 0 | D57: 0 | E57: =CHOOSE(Dashboard!$B$4,B57,C57,D57) -> 0 | F57: % | G57: Low ≤ Base ≤ High
A58: Site manager: first month on payroll | B58: 1 | C58: 1 | D58: 1 | E58: =CHOOSE(Dashboard!$B$4,B58,C58,D58) -> 1 | F58: month #
A59: Wash attendants & customer service: headcount (FTE) | B59: 10 | C59: 10 | D59: 10 | E59: =CHOOSE(Dashboard!$B$4,B59,C59,D59) -> 10 | F59: FTE | G59: Low ≤ Base ≤ High
A60: Wash attendants & customer service: salary per FTE per year | B60: 32000 | C60: 32000 | D60: 32000 | E60: =CHOOSE(Dashboard!$B$4,B60,C60,D60) -> 32000 | F60: $
A61: Wash attendants & customer service: headcount growth per year | B61: 0 | C61: 0 | D61: 0 | E61: =CHOOSE(Dashboard!$B$4,B61,C61,D61) -> 0 | F61: % | G61: Low ≤ Base ≤ High
A62: Wash attendants & customer service: first month on payroll | B62: 1 | C62: 1 | D62: 1 | E62: =CHOOSE(Dashboard!$B$4,B62,C62,D62) -> 1 | F62: month #
A63: Payroll taxes & benefits, % of salary | B63: 0.12 | C63: 0.12 | D63: 0.12 | E63: =CHOOSE(Dashboard!$B$4,B63,C63,D63) -> 0.12 | F63: %
A64: Wage growth per year | B64: 0.03 | C64: 0.03 | D64: 0.03 | E64: =CHOOSE(Dashboard!$B$4,B64,C64,D64) -> 0.03 | F64: %
A66: Funding
A67: Equity raised at start | B67: 2100000 | C67: 2100000 | D67: 2100000 | E67: =CHOOSE(Dashboard!$B$4,B67,C67,D67) -> 2100000 | F67: $
A68: Loan drawn at start | B68: 3000000 | C68: 3000000 | D68: 3000000 | E68: =CHOOSE(Dashboard!$B$4,B68,C68,D68) -> 3000000 | F68: $
A69: Loan interest rate per year | B69: 0.085 | C69: 0.085 | D69: 0.085 | E69: =CHOOSE(Dashboard!$B$4,B69,C69,D69) -> 0.085 | F69: %
A70: Loan repayment term | B70: 10 | C70: 10 | D70: 10 | E70: =CHOOSE(Dashboard!$B$4,B70,C70,D70) -> 10 | F70: years
A72: Working capital
A73: Customer payment terms (receivable days) | B73: 2 | C73: 2 | D73: 2 | E73: =CHOOSE(Dashboard!$B$4,B73,C73,D73) -> 2 | F73: days
A74: Inventory held (days of COGS) | B74: 15 | C74: 15 | D74: 15 | E74: =CHOOSE(Dashboard!$B$4,B74,C74,D74) -> 15 | F74: days
A75: Supplier payment terms (payable days) | B75: 25 | C75: 25 | D75: 25 | E75: =CHOOSE(Dashboard!$B$4,B75,C75,D75) -> 25 | F75: days
A77: Tax & depreciation
A78: Depreciation period for capex | B78: 12 | C78: 12 | D78: 12 | E78: =CHOOSE(Dashboard!$B$4,B78,C78,D78) -> 12 | F78: years
A79: Income tax rate | B79: 0.21 | C79: 0.21 | D79: 0.21 | E79: =CHOOSE(Dashboard!$B$4,B79,C79,D79) -> 0.21 | F79: %
A81: Break-even & funding
A82: Minimum cash buffer to keep | B82: 281000 | C82: 281000 | D82: 281000 | E82: =CHOOSE(Dashboard!$B$4,B82,C82,D82) -> 281000 | F82: $ | G82: About 3 months of costs
A84: Valuation
A85: Discount rate (WACC) | B85: 0.3 | C85: 0.25 | D85: 0.2 | E85: =CHOOSE(Dashboard!$B$4,B85,C85,D85) -> 0.25 | F85: % | G85: Low ≥ Base ≥ High (lower is better)
A86: Terminal growth rate (perpetuity) | B86: 0.01 | C86: 0.02 | D86: 0.03 | E86: =CHOOSE(Dashboard!$B$4,B86,C86,D86) -> 0.02 | F86: % | G86: Low ≤ Base ≤ High
A87: Exit multiple (EV ÷ final-year EBITDA) | B87: 3 | C87: 4 | D87: 5 | E87: =CHOOSE(Dashboard!$B$4,B87,C87,D87) -> 4 | F87: x | G87: Low ≤ Base ≤ High
A88: Sensitivity table: WACC step | B88: 0.01 | C88: 0.01 | D88: 0.01 | E88: =CHOOSE(Dashboard!$B$4,B88,C88,D88) -> 0.01 | F88: %
A89: Sensitivity table: growth step | B89: 0.005 | C89: 0.005 | D89: 0.005 | E89: =CHOOSE(Dashboard!$B$4,B89,C89,D89) -> 0.005 | F89: %
A91: Legend: yellow cell with blue figure = input you can change · black = formula · green = link to another sheet · grey = active value (column E follows the scenario on the Dashboard).

Sheet P&L
A1: Annual profit & loss | H1: =HYPERLINK("#'Cover'!A1","◂ Contents") -> ◂ Contents
A2: Rolled up from the period detail (SUMIF on the year row; balances at year end).
A3: Year # | B3: 1 | C3: 2 | D3: 3 | E3: 4 | F3: 5
B4: Year 1 | C4: Year 2 | D4: Year 3 | E4: Year 4 | F4: Year 5
A5: Revenue | B5: =SUMIF(Monthly!$C$5:$BJ$5,B$3,Monthly!$C$37:$BJ$37) -> 1180182.4 | C5: =SUMIF(Monthly!$C$5:$BJ$5,C$3,Monthly!$C$37:$BJ$37) -> 1805881.5 | D5: =SUMIF(Monthly!$C$5:$BJ$5,D$3,Monthly!$C$37:$BJ$37) -> 2080276.6 | E5: =SUMIF(Monthly!$C$5:$BJ$5,E$3,Monthly!$C$37:$BJ$37) -> 2282431.1 | F5: =SUMIF(Monthly!$C$5:$BJ$5,F$3,Monthly!$C$37:$BJ$37) -> 2440877.2
A6: Cost of sales | B6: =SUMIF(Monthly!$C$5:$BJ$5,B$3,Monthly!$C$45:$BJ$45) -> -180421.6 | C6: =SUMIF(Monthly!$C$5:$BJ$5,C$3,Monthly!$C$45:$BJ$45) -> -288679.06 | D6: =SUMIF(Monthly!$C$5:$BJ$5,D$3,Monthly!$C$45:$BJ$45) -> -343422.65 | E6: =SUMIF(Monthly!$C$5:$BJ$5,E$3,Monthly!$C$45:$BJ$45) -> -384784.48 | F6: =SUMIF(Monthly!$C$5:$BJ$5,F$3,Monthly!$C$45:$BJ$45) -> -418095.19
A7: Gross profit | B7: =SUMIF(Monthly!$C$5:$BJ$5,B$3,Monthly!$C$46:$BJ$46) -> 999760.79 | C7: =SUMIF(Monthly!$C$5:$BJ$5,C$3,Monthly!$C$46:$BJ$46) -> 1517202.4 | D7: =SUMIF(Monthly!$C$5:$BJ$5,D$3,Monthly!$C$46:$BJ$46) -> 1736853.9 | E7: =SUMIF(Monthly!$C$5:$BJ$5,E$3,Monthly!$C$46:$BJ$46) -> 1897646.6 | F7: =SUMIF(Monthly!$C$5:$BJ$5,F$3,Monthly!$C$46:$BJ$46) -> 2022782
A8: Gross margin | B8: =IF(B5=0,0,B7/B5) -> 0.84712397 | C8: =IF(C5=0,0,C7/C5) -> 0.84014507 | D8: =IF(D5=0,0,D7/D5) -> 0.83491491 | E8: =IF(E5=0,0,E7/E5) -> 0.83141464 | F8: =IF(F5=0,0,F7/F5) -> 0.82871109
A9: Site payroll | B9: =SUMIF(Monthly!$C$5:$BJ$5,B$3,Monthly!$C$49:$BJ$49) -> -439040 | C9: =SUMIF(Monthly!$C$5:$BJ$5,C$3,Monthly!$C$49:$BJ$49) -> -452211.2 | D9: =SUMIF(Monthly!$C$5:$BJ$5,D$3,Monthly!$C$49:$BJ$49) -> -465777.54 | E9: =SUMIF(Monthly!$C$5:$BJ$5,E$3,Monthly!$C$49:$BJ$49) -> -479750.86 | F9: =SUMIF(Monthly!$C$5:$BJ$5,F$3,Monthly!$C$49:$BJ$49) -> -494143.39
A10: Site lease or land cost | B10: =SUMIF(Monthly!$C$5:$BJ$5,B$3,Monthly!$C$50:$BJ$50) -> -360000 | C10: =SUMIF(Monthly!$C$5:$BJ$5,C$3,Monthly!$C$50:$BJ$50) -> -370800 | D10: =SUMIF(Monthly!$C$5:$BJ$5,D$3,Monthly!$C$50:$BJ$50) -> -381924 | E10: =SUMIF(Monthly!$C$5:$BJ$5,E$3,Monthly!$C$50:$BJ$50) -> -393381.72 | F10: =SUMIF(Monthly!$C$5:$BJ$5,F$3,Monthly!$C$50:$BJ$50) -> -405183.17
A11: Equipment maintenance & repairs | B11: =SUMIF(Monthly!$C$5:$BJ$5,B$3,Monthly!$C$51:$BJ$51) -> -66000 | C11: =SUMIF(Monthly!$C$5:$BJ$5,C$3,Monthly!$C$51:$BJ$51) -> -67980 | D11: =SUMIF(Monthly!$C$5:$BJ$5,D$3,Monthly!$C$51:$BJ$51) -> -70019.4 | E11: =SUMIF(Monthly!$C$5:$BJ$5,E$3,Monthly!$C$51:$BJ$51) -> -72119.982 | F11: =SUMIF(Monthly!$C$5:$BJ$5,F$3,Monthly!$C$51:$BJ$51) -> -74283.581
A12: Insurance, property tax, software & other | B12: =SUMIF(Monthly!$C$5:$BJ$5,B$3,Monthly!$C$52:$BJ$52) -> -114000 | C12: =SUMIF(Monthly!$C$5:$BJ$5,C$3,Monthly!$C$52:$BJ$52) -> -117420 | D12: =SUMIF(Monthly!$C$5:$BJ$5,D$3,Monthly!$C$52:$BJ$52) -> -120942.6 | E12: =SUMIF(Monthly!$C$5:$BJ$5,E$3,Monthly!$C$52:$BJ$52) -> -124570.88 | F12: =SUMIF(Monthly!$C$5:$BJ$5,F$3,Monthly!$C$52:$BJ$52) -> -128308
A13: Marketing | B13: =SUMIF(Monthly!$C$5:$BJ$5,B$3,Monthly!$C$53:$BJ$53) -> -144000 | C13: =SUMIF(Monthly!$C$5:$BJ$5,C$3,Monthly!$C$53:$BJ$53) -> -115200 | D13: =SUMIF(Monthly!$C$5:$BJ$5,D$3,Monthly!$C$53:$BJ$53) -> -92160 | E13: =SUMIF(Monthly!$C$5:$BJ$5,E$3,Monthly!$C$53:$BJ$53) -> -73728 | F13: =SUMIF(Monthly!$C$5:$BJ$5,F$3,Monthly!$C$53:$BJ$53) -> -58982.4
A14: Total operating expenses | B14: =SUMIF(Monthly!$C$5:$BJ$5,B$3,Monthly!$C$54:$BJ$54) -> -1123040 | C14: =SUMIF(Monthly!$C$5:$BJ$5,C$3,Monthly!$C$54:$BJ$54) -> -1123611.2 | D14: =SUMIF(Monthly!$C$5:$BJ$5,D$3,Monthly!$C$54:$BJ$54) -> -1130823.5 | E14: =SUMIF(Monthly!$C$5:$BJ$5,E$3,Monthly!$C$54:$BJ$54) -> -1143551.4 | F14: =SUMIF(Monthly!$C$5:$BJ$5,F$3,Monthly!$C$54:$BJ$54) -> -1160900.5
A15: EBITDA | B15: =SUMIF(Monthly!$C$5:$BJ$5,B$3,Monthly!$C$55:$BJ$55) -> -123279.21 | C15: =SUMIF(Monthly!$C$5:$BJ$5,C$3,Monthly!$C$55:$BJ$55) -> 393591.21 | D15: =SUMIF(Monthly!$C$5:$BJ$5,D$3,Monthly!$C$55:$BJ$55) -> 606030.41 | E15: =SUMIF(Monthly!$C$5:$BJ$5,E$3,Monthly!$C$55:$BJ$55) -> 754095.19 | F15: =SUMIF(Monthly!$C$5:$BJ$5,F$3,Monthly!$C$55:$BJ$55) -> 861881.48
A16: EBITDA margin | B16: =IF(B5=0,0,B15/B5) -> -0.10445776 | C16: =IF(C5=0,0,C15/C5) -> 0.21794964 | D16: =IF(D5=0,0,D15/D5) -> 0.29132204 | E16: =IF(E5=0,0,E15/E5) -> 0.33039122 | F16: =IF(F5=0,0,F15/F5) -> 0.35310317
A17: Depreciation | B17: =SUMIF(Monthly!$C$5:$BJ$5,B$3,Monthly!$C$73:$BJ$73) -> -341666.67 | C17: =SUMIF(Monthly!$C$5:$BJ$5,C$3,Monthly!$C$73:$BJ$73) -> -345000 | D17: =SUMIF(Monthly!$C$5:$BJ$5,D$3,Monthly!$C$73:$BJ$73) -> -348333.33 | E17: =SUMIF(Monthly!$C$5:$BJ$5,E$3,Monthly!$C$73:$BJ$73) -> -351666.67 | F17: =SUMIF(Monthly!$C$5:$BJ$5,F$3,Monthly!$C$73:$BJ$73) -> -355000
A18: EBIT | B18: =SUMIF(Monthly!$C$5:$BJ$5,B$3,Monthly!$C$58:$BJ$58) -> -464945.87 | C18: =SUMIF(Monthly!$C$5:$BJ$5,C$3,Monthly!$C$58:$BJ$58) -> 48591.208 | D18: =SUMIF(Monthly!$C$5:$BJ$5,D$3,Monthly!$C$58:$BJ$58) -> 257697.08 | E18: =SUMIF(Monthly!$C$5:$BJ$5,E$3,Monthly!$C$58:$BJ$58) -> 402428.52 | F18: =SUMIF(Monthly!$C$5:$BJ$5,F$3,Monthly!$C$58:$BJ$58) -> 506881.48
A19: Interest | B19: =SUMIF(Monthly!$C$5:$BJ$5,B$3,Monthly!$C$59:$BJ$59) -> -244286.46 | C19: =SUMIF(Monthly!$C$5:$BJ$5,C$3,Monthly!$C$59:$BJ$59) -> -218875 | D19: =SUMIF(Monthly!$C$5:$BJ$5,D$3,Monthly!$C$59:$BJ$59) -> -193375 | E19: =SUMIF(Monthly!$C$5:$BJ$5,E$3,Monthly!$C$59:$BJ$59) -> -167875 | F19: =SUMIF(Monthly!$C$5:$BJ$5,F$3,Monthly!$C$59:$BJ$59) -> -142375
A20: Pre-tax income | B20: =SUMIF(Monthly!$C$5:$BJ$5,B$3,Monthly!$C$60:$BJ$60) -> -709232.33 | C20: =SUMIF(Monthly!$C$5:$BJ$5,C$3,Monthly!$C$60:$BJ$60) -> -170283.79 | D20: =SUMIF(Monthly!$C$5:$BJ$5,D$3,Monthly!$C$60:$BJ$60) -> 64322.078 | E20: =SUMIF(Monthly!$C$5:$BJ$5,E$3,Monthly!$C$60:$BJ$60) -> 234553.52 | F20: =SUMIF(Monthly!$C$5:$BJ$5,F$3,Monthly!$C$60:$BJ$60) -> 364506.48
A21: Income tax | B21: =SUMIF(Monthly!$C$5:$BJ$5,B$3,Monthly!$C$63:$BJ$63) -> 0 | C21: =SUMIF(Monthly!$C$5:$BJ$5,C$3,Monthly!$C$63:$BJ$63) -> 0 | D21: =SUMIF(Monthly!$C$5:$BJ$5,D$3,Monthly!$C$63:$BJ$63) -> 0 | E21: =SUMIF(Monthly!$C$5:$BJ$5,E$3,Monthly!$C$63:$BJ$63) -> 0 | F21: =SUMIF(Monthly!$C$5:$BJ$5,F$3,Monthly!$C$63:$BJ$63) -> 0
A22: Net income | B22: =SUMIF(Monthly!$C$5:$BJ$5,B$3,Monthly!$C$64:$BJ$64) -> -709232.33 | C22: =SUMIF(Monthly!$C$5:$BJ$5,C$3,Monthly!$C$64:$BJ$64) -> -170283.79 | D22: =SUMIF(Monthly!$C$5:$BJ$5,D$3,Monthly!$C$64:$BJ$64) -> 64322.078 | E22: =SUMIF(Monthly!$C$5:$BJ$5,E$3,Monthly!$C$64:$BJ$64) -> 234553.52 | F22: =SUMIF(Monthly!$C$5:$BJ$5,F$3,Monthly!$C$64:$BJ$64) -> 364506.48
A23: Net margin | B23: =IF(B5=0,0,B22/B5) -> -0.60095146 | C23: =IF(C5=0,0,C22/C5) -> -0.094294003 | D23: =IF(D5=0,0,D22/D5) -> 0.030919964 | E23: =IF(E5=0,0,E22/E5) -> 0.10276478 | F23: =IF(F5=0,0,F22/F5) -> 0.14933422

Sheet Cash Flow
A1: Annual cash flow statement | H1: =HYPERLINK("#'Cover'!A1","◂ Contents") -> ◂ Contents
A2: Rolled up from the period detail (SUMIF on the year row; balances at year end).
A3: Year # | B3: 1 | C3: 2 | D3: 3 | E3: 4 | F3: 5
B4: Year 1 | C4: Year 2 | D4: Year 3 | E4: Year 4 | F4: Year 5
A5: Net income | B5: =SUMIF(Monthly!$C$5:$BJ$5,B$3,Monthly!$C$64:$BJ$64) -> -709232.33 | C5: =SUMIF(Monthly!$C$5:$BJ$5,C$3,Monthly!$C$64:$BJ$64) -> -170283.79 | D5: =SUMIF(Monthly!$C$5:$BJ$5,D$3,Monthly!$C$64:$BJ$64) -> 64322.078 | E5: =SUMIF(Monthly!$C$5:$BJ$5,E$3,Monthly!$C$64:$BJ$64) -> 234553.52 | F5: =SUMIF(Monthly!$C$5:$BJ$5,F$3,Monthly!$C$64:$BJ$64) -> 364506.48
A6: Add back depreciation | B6: =-SUMIF(Monthly!$C$5:$BJ$5,B$3,Monthly!$C$73:$BJ$73) -> 341666.67 | C6: =-SUMIF(Monthly!$C$5:$BJ$5,C$3,Monthly!$C$73:$BJ$73) -> 345000 | D6: =-SUMIF(Monthly!$C$5:$BJ$5,D$3,Monthly!$C$73:$BJ$73) -> 348333.33 | E6: =-SUMIF(Monthly!$C$5:$BJ$5,E$3,Monthly!$C$73:$BJ$73) -> 351666.67 | F6: =-SUMIF(Monthly!$C$5:$BJ$5,F$3,Monthly!$C$73:$BJ$73) -> 355000
A7: (Increase) / decrease in receivables | B7: =SUMIF(Monthly!$C$5:$BJ$5,B$3,Monthly!$C$87:$BJ$87) -> -7915.9819 | C7: =SUMIF(Monthly!$C$5:$BJ$5,C$3,Monthly!$C$87:$BJ$87) -> -1788.5183 | D7: =SUMIF(Monthly!$C$5:$BJ$5,D$3,Monthly!$C$87:$BJ$87) -> -1274.5082 | E7: =SUMIF(Monthly!$C$5:$BJ$5,E$3,Monthly!$C$87:$BJ$87) -> -960.77928 | F7: =SUMIF(Monthly!$C$5:$BJ$5,F$3,Monthly!$C$87:$BJ$87) -> -772.67948
A8: (Increase) / decrease in inventory | B8: =SUMIF(Monthly!$C$5:$BJ$5,B$3,Monthly!$C$88:$BJ$88) -> -8885.7825 | C8: =SUMIF(Monthly!$C$5:$BJ$5,C$3,Monthly!$C$88:$BJ$88) -> -2326.145 | D8: =SUMIF(Monthly!$C$5:$BJ$5,D$3,Monthly!$C$88:$BJ$88) -> -1702.4278 | E8: =SUMIF(Monthly!$C$5:$BJ$5,E$3,Monthly!$C$88:$BJ$88) -> -1322.5719 | F8: =SUMIF(Monthly!$C$5:$BJ$5,F$3,Monthly!$C$88:$BJ$88) -> -1097.2169
A9: Increase / (decrease) in payables | B9: =SUMIF(Monthly!$C$5:$BJ$5,B$3,Monthly!$C$89:$BJ$89) -> 14809.638 | C9: =SUMIF(Monthly!$C$5:$BJ$5,C$3,Monthly!$C$89:$BJ$89) -> 3876.9084 | D9: =SUMIF(Monthly!$C$5:$BJ$5,D$3,Monthly!$C$89:$BJ$89) -> 2837.3797 | E9: =SUMIF(Monthly!$C$5:$BJ$5,E$3,Monthly!$C$89:$BJ$89) -> 2204.2865 | F9: =SUMIF(Monthly!$C$5:$BJ$5,F$3,Monthly!$C$89:$BJ$89) -> 1828.6948
A10: Operating cash flow | B10: =SUMIF(Monthly!$C$5:$BJ$5,B$3,Monthly!$C$92:$BJ$92) -> -369557.79 | C10: =SUMIF(Monthly!$C$5:$BJ$5,C$3,Monthly!$C$92:$BJ$92) -> 174478.45 | D10: =SUMIF(Monthly!$C$5:$BJ$5,D$3,Monthly!$C$92:$BJ$92) -> 412515.86 | E10: =SUMIF(Monthly!$C$5:$BJ$5,E$3,Monthly!$C$92:$BJ$92) -> 586141.12 | F10: =SUMIF(Monthly!$C$5:$BJ$5,F$3,Monthly!$C$92:$BJ$92) -> 719465.28
A11: Capital spending | B11: =SUMIF(Monthly!$C$5:$BJ$5,B$3,Monthly!$C$93:$BJ$93) -> -4100000 | C11: =SUMIF(Monthly!$C$5:$BJ$5,C$3,Monthly!$C$93:$BJ$93) -> -40000 | D11: =SUMIF(Monthly!$C$5:$BJ$5,D$3,Monthly!$C$93:$BJ$93) -> -40000 | E11: =SUMIF(Monthly!$C$5:$BJ$5,E$3,Monthly!$C$93:$BJ$93) -> -40000 | F11: =SUMIF(Monthly!$C$5:$BJ$5,F$3,Monthly!$C$93:$BJ$93) -> -40000
A12: Equity raised | B12: =SUMIF(Monthly!$C$5:$BJ$5,B$3,Monthly!$C$94:$BJ$94) -> 2100000 | C12: =SUMIF(Monthly!$C$5:$BJ$5,C$3,Monthly!$C$94:$BJ$94) -> 0 | D12: =SUMIF(Monthly!$C$5:$BJ$5,D$3,Monthly!$C$94:$BJ$94) -> 0 | E12: =SUMIF(Monthly!$C$5:$BJ$5,E$3,Monthly!$C$94:$BJ$94) -> 0 | F12: =SUMIF(Monthly!$C$5:$BJ$5,F$3,Monthly!$C$94:$BJ$94) -> 0
A13: Loan drawdown | B13: =SUMIF(Monthly!$C$5:$BJ$5,B$3,Monthly!$C$79:$BJ$79) -> 3000000 | C13: =SUMIF(Monthly!$C$5:$BJ$5,C$3,Monthly!$C$79:$BJ$79) -> 0 | D13: =SUMIF(Monthly!$C$5:$BJ$5,D$3,Monthly!$C$79:$BJ$79) -> 0 | E13: =SUMIF(Monthly!$C$5:$BJ$5,E$3,Monthly!$C$79:$BJ$79) -> 0 | F13: =SUMIF(Monthly!$C$5:$BJ$5,F$3,Monthly!$C$79:$BJ$79) -> 0
A14: Loan repayment | B14: =SUMIF(Monthly!$C$5:$BJ$5,B$3,Monthly!$C$80:$BJ$80) -> -275000 | C14: =SUMIF(Monthly!$C$5:$BJ$5,C$3,Monthly!$C$80:$BJ$80) -> -300000 | D14: =SUMIF(Monthly!$C$5:$BJ$5,D$3,Monthly!$C$80:$BJ$80) -> -300000 | E14: =SUMIF(Monthly!$C$5:$BJ$5,E$3,Monthly!$C$80:$BJ$80) -> -300000 | F14: =SUMIF(Monthly!$C$5:$BJ$5,F$3,Monthly!$C$80:$BJ$80) -> -300000
A15: Financing cash flow | B15: =SUMIF(Monthly!$C$5:$BJ$5,B$3,Monthly!$C$95:$BJ$95) -> 4825000 | C15: =SUMIF(Monthly!$C$5:$BJ$5,C$3,Monthly!$C$95:$BJ$95) -> -300000 | D15: =SUMIF(Monthly!$C$5:$BJ$5,D$3,Monthly!$C$95:$BJ$95) -> -300000 | E15: =SUMIF(Monthly!$C$5:$BJ$5,E$3,Monthly!$C$95:$BJ$95) -> -300000 | F15: =SUMIF(Monthly!$C$5:$BJ$5,F$3,Monthly!$C$95:$BJ$95) -> -300000
A16: Net change in cash | B16: =SUMIF(Monthly!$C$5:$BJ$5,B$3,Monthly!$C$96:$BJ$96) -> 355442.21 | C16: =SUMIF(Monthly!$C$5:$BJ$5,C$3,Monthly!$C$96:$BJ$96) -> -165521.55 | D16: =SUMIF(Monthly!$C$5:$BJ$5,D$3,Monthly!$C$96:$BJ$96) -> 72515.855 | E16: =SUMIF(Monthly!$C$5:$BJ$5,E$3,Monthly!$C$96:$BJ$96) -> 246141.12 | F16: =SUMIF(Monthly!$C$5:$BJ$5,F$3,Monthly!$C$96:$BJ$96) -> 379465.28
A17: Opening cash | B17: =INDEX(Monthly!$C$97:$BJ$97,(B$3-1)*12+1) -> 0 | C17: =INDEX(Monthly!$C$97:$BJ$97,(C$3-1)*12+1) -> 355442.21 | D17: =INDEX(Monthly!$C$97:$BJ$97,(D$3-1)*12+1) -> 189920.66 | E17: =INDEX(Monthly!$C$97:$BJ$97,(E$3-1)*12+1) -> 262436.52 | F17: =INDEX(Monthly!$C$97:$BJ$97,(F$3-1)*12+1) -> 508577.64
A18: Closing cash | B18: =INDEX(Monthly!$C$98:$BJ$98,B$3*12) -> 355442.21 | C18: =INDEX(Monthly!$C$98:$BJ$98,C$3*12) -> 189920.66 | D18: =INDEX(Monthly!$C$98:$BJ$98,D$3*12) -> 262436.52 | E18: =INDEX(Monthly!$C$98:$BJ$98,E$3*12) -> 508577.64 | F18: =INDEX(Monthly!$C$98:$BJ$98,F$3*12) -> 888042.92

Sheet Balance Sheet
A1: Balance sheet at year end | H1: =HYPERLINK("#'Cover'!A1","◂ Contents") -> ◂ Contents
A2: Rolled up from the period detail (SUMIF on the year row; balances at year end).
A3: Year # | B3: 1 | C3: 2 | D3: 3 | E3: 4 | F3: 5
B4: Year 1 | C4: Year 2 | D4: Year 3 | E4: Year 4 | F4: Year 5
A5: Cash | B5: =INDEX(Monthly!$C$98:$BJ$98,B$3*12) -> 355442.21 | C5: =INDEX(Monthly!$C$98:$BJ$98,C$3*12) -> 189920.66 | D5: =INDEX(Monthly!$C$98:$BJ$98,D$3*12) -> 262436.52 | E5: =INDEX(Monthly!$C$98:$BJ$98,E$3*12) -> 508577.64 | F5: =INDEX(Monthly!$C$98:$BJ$98,F$3*12) -> 888042.92
A6: Accounts receivable | B6: =INDEX(Monthly!$C$84:$BJ$84,B$3*12) -> 7915.9819 | C6: =INDEX(Monthly!$C$84:$BJ$84,C$3*12) -> 9704.5001 | D6: =INDEX(Monthly!$C$84:$BJ$84,D$3*12) -> 10979.008 | E6: =INDEX(Monthly!$C$84:$BJ$84,E$3*12) -> 11939.788 | F6: =INDEX(Monthly!$C$84:$BJ$84,F$3*12) -> 12712.467
A7: Inventory | B7: =INDEX(Monthly!$C$85:$BJ$85,B$3*12) -> 8885.7825 | C7: =INDEX(Monthly!$C$85:$BJ$85,C$3*12) -> 11211.928 | D7: =INDEX(Monthly!$C$85:$BJ$85,D$3*12) -> 12914.355 | E7: =INDEX(Monthly!$C$85:$BJ$85,E$3*12) -> 14236.927 | F7: =INDEX(Monthly!$C$85:$BJ$85,F$3*12) -> 15334.144
A8: Net fixed assets | B8: =INDEX(Monthly!$C$75:$BJ$75,B$3*12) -> 3758333.3 | C8: =INDEX(Monthly!$C$75:$BJ$75,C$3*12) -> 3453333.3 | D8: =INDEX(Monthly!$C$75:$BJ$75,D$3*12) -> 3145000 | E8: =INDEX(Monthly!$C$75:$BJ$75,E$3*12) -> 2833333.3 | F8: =INDEX(Monthly!$C$75:$BJ$75,F$3*12) -> 2518333.3
A9: Total assets | B9: =INDEX(Monthly!$C$112:$BJ$112,B$3*12) -> 4130577.3 | C9: =INDEX(Monthly!$C$112:$BJ$112,C$3*12) -> 3664170.4 | D9: =INDEX(Monthly!$C$112:$BJ$112,D$3*12) -> 3431329.9 | E9: =INDEX(Monthly!$C$112:$BJ$112,E$3*12) -> 3368087.7 | F9: =INDEX(Monthly!$C$112:$BJ$112,F$3*12) -> 3434422.9
A10: Accounts payable | B10: =INDEX(Monthly!$C$86:$BJ$86,B$3*12) -> 14809.638 | C10: =INDEX(Monthly!$C$86:$BJ$86,C$3*12) -> 18686.546 | D10: =INDEX(Monthly!$C$86:$BJ$86,D$3*12) -> 21523.926 | E10: =INDEX(Monthly!$C$86:$BJ$86,E$3*12) -> 23728.212 | F10: =INDEX(Monthly!$C$86:$BJ$86,F$3*12) -> 25556.907
A11: Loan | B11: =INDEX(Monthly!$C$81:$BJ$81,B$3*12) -> 2725000 | C11: =INDEX(Monthly!$C$81:$BJ$81,C$3*12) -> 2425000 | D11: =INDEX(Monthly!$C$81:$BJ$81,D$3*12) -> 2125000 | E11: =INDEX(Monthly!$C$81:$BJ$81,E$3*12) -> 1825000 | F11: =INDEX(Monthly!$C$81:$BJ$81,F$3*12) -> 1525000
A12: Total liabilities | B12: =INDEX(Monthly!$C$113:$BJ$113,B$3*12) -> 2739809.6 | C12: =INDEX(Monthly!$C$113:$BJ$113,C$3*12) -> 2443686.5 | D12: =INDEX(Monthly!$C$113:$BJ$113,D$3*12) -> 2146523.9 | E12: =INDEX(Monthly!$C$113:$BJ$113,E$3*12) -> 1848728.2 | F12: =INDEX(Monthly!$C$113:$BJ$113,F$3*12) -> 1550556.9
A13: Paid-in capital | B13: =INDEX(Monthly!$C$110:$BJ$110,B$3*12) -> 2100000 | C13: =INDEX(Monthly!$C$110:$BJ$110,C$3*12) -> 2100000 | D13: =INDEX(Monthly!$C$110:$BJ$110,D$3*12) -> 2100000 | E13: =INDEX(Monthly!$C$110:$BJ$110,E$3*12) -> 2100000 | F13: =INDEX(Monthly!$C$110:$BJ$110,F$3*12) -> 2100000
A14: Retained earnings | B14: =INDEX(Monthly!$C$111:$BJ$111,B$3*12) -> -709232.33 | C14: =INDEX(Monthly!$C$111:$BJ$111,C$3*12) -> -879516.12 | D14: =INDEX(Monthly!$C$111:$BJ$111,D$3*12) -> -815194.05 | E14: =INDEX(Monthly!$C$111:$BJ$111,E$3*12) -> -580640.52 | F14: =INDEX(Monthly!$C$111:$BJ$111,F$3*12) -> -216134.04
A15: Total equity | B15: =INDEX(Monthly!$C$114:$BJ$114,B$3*12) -> 1390767.7 | C15: =INDEX(Monthly!$C$114:$BJ$114,C$3*12) -> 1220483.9 | D15: =INDEX(Monthly!$C$114:$BJ$114,D$3*12) -> 1284806 | E15: =INDEX(Monthly!$C$114:$BJ$114,E$3*12) -> 1519359.5 | F15: =INDEX(Monthly!$C$114:$BJ$114,F$3*12) -> 1883866
A16: Total liabilities & equity | B16: =INDEX(Monthly!$C$115:$BJ$115,B$3*12) -> 4130577.3 | C16: =INDEX(Monthly!$C$115:$BJ$115,C$3*12) -> 3664170.4 | D16: =INDEX(Monthly!$C$115:$BJ$115,D$3*12) -> 3431329.9 | E16: =INDEX(Monthly!$C$115:$BJ$115,E$3*12) -> 3368087.7 | F16: =INDEX(Monthly!$C$115:$BJ$115,F$3*12) -> 3434422.9
A17: Check: assets − liabilities − equity (must be 0) | B17: =INDEX(Monthly!$C$116:$BJ$116,B$3*12) -> 0 | C17: =INDEX(Monthly!$C$116:$BJ$116,C$3*12) -> 0 | D17: =INDEX(Monthly!$C$116:$BJ$116,D$3*12) -> 0 | E17: =INDEX(Monthly!$C$116:$BJ$116,E$3*12) -> 0 | F17: =INDEX(Monthly!$C$116:$BJ$116,F$3*12) -> 0

Sheet Monthly
A1: Monthly projection | D1: =HYPERLINK("#'Cover'!A1","◂ Contents") -> ◂ Contents
A2: $ unless stated; costs shown as negatives. Every period uses the same formula.
A3: Month | C3: M1 | D3: M2 | E3: M3 | F3: M4 | G3: M5 | H3: M6 | I3: M7 | J3: M8 | K3: M9 | L3: M10 | M3: M11 | N3: M12 | O3: M13 | P3: M14 | Q3: M15 | R3: M16 | S3: M17 | T3: M18 | U3: M19 | V3: M20 | W3: M21 | X3: M22 | Y3: M23 | Z3: M24 | AA3: M25 | AB3: M26 | AC3: M27 | AD3: M28 | AE3: M29 | AF3: M30 | AG3: M31 | AH3: M32 | AI3: M33 | AJ3: M34 | AK3: M35 | AL3: M36 | AM3: M37 | AN3: M38 | AO3: M39 | AP3: M40 | AQ3: M41 | AR3: M42 | AS3: M43 | AT3: M44 | AU3: M45 | AV3: M46 | AW3: M47 | AX3: M48 | AY3: M49 | AZ3: M50 | BA3: M51 | BB3: M52 | BC3: M53 | BD3: M54 | BE3: M55 | BF3: M56 | BG3: M57 | BH3: M58 | BI3: M59 | BJ3: M60
A4: Period # | C4: 1 | D4: 2 | E4: 3 | F4: 4 | G4: 5 | H4: 6 | I4: 7 | J4: 8 | K4: 9 | L4: 10 | M4: 11 | N4: 12 | O4: 13 | P4: 14 | Q4: 15 | R4: 16 | S4: 17 | T4: 18 | U4: 19 | V4: 20 | W4: 21 | X4: 22 | Y4: 23 | Z4: 24 | AA4: 25 | AB4: 26 | AC4: 27 | AD4: 28 | AE4: 29 | AF4: 30 | AG4: 31 | AH4: 32 | AI4: 33 | AJ4: 34 | AK4: 35 | AL4: 36 | AM4: 37 | AN4: 38 | AO4: 39 | AP4: 40 | AQ4: 41 | AR4: 42 | AS4: 43 | AT4: 44 | AU4: 45 | AV4: 46 | AW4: 47 | AX4: 48 | AY4: 49 | AZ4: 50 | BA4: 51 | BB4: 52 | BC4: 53 | BD4: 54 | BE4: 55 | BF4: 56 | BG4: 57 | BH4: 58 | BI4: 59 | BJ4: 60
A5: Year # | C5: =ROUNDUP(C4*1/12,0) -> 1 | D5: =ROUNDUP(D4*1/12,0) -> 1 | E5: =ROUNDUP(E4*1/12,0) -> 1 | F5: =ROUNDUP(F4*1/12,0) -> 1 | G5: =ROUNDUP(G4*1/12,0) -> 1 | H5: =ROUNDUP(H4*1/12,0) -> 1 | I5: =ROUNDUP(I4*1/12,0) -> 1 | J5: =ROUNDUP(J4*1/12,0) -> 1 | ... BJ5: =ROUNDUP(BJ4*1/12,0) -> 5
A7: Volume
A8: Helper: months of the period still on the ramp-up | C8: =MAX(0,MIN(1,Inputs!$E$9-(C$4-1)*1)) -> 1 | D8: =MAX(0,MIN(1,Inputs!$E$9-(D$4-1)*1)) -> 1 | E8: =MAX(0,MIN(1,Inputs!$E$9-(E$4-1)*1)) -> 1 | F8: =MAX(0,MIN(1,Inputs!$E$9-(F$4-1)*1)) -> 1 | G8: =MAX(0,MIN(1,Inputs!$E$9-(G$4-1)*1)) -> 1 | H8: =MAX(0,MIN(1,Inputs!$E$9-(H$4-1)*1)) -> 1 | I8: =MAX(0,MIN(1,Inputs!$E$9-(I$4-1)*1)) -> 1 | J8: =MAX(0,MIN(1,Inputs!$E$9-(J$4-1)*1)) -> 1 | ... BJ8: =MAX(0,MIN(1,Inputs!$E$9-(BJ$4-1)*1)) -> 0
A9: Ramp-up factor (share of mature retail volume) | C9: =IF(Inputs!$E$9<=0,1,(C8*Inputs!$E$10+(1-Inputs!$E$10)/MAX(1,Inputs!$E$9)*(C8*(C$4-1)*1+C8*(C8-1)/2)+1-C8)/1) -> 0.45 | D9: =IF(Inputs!$E$9<=0,1,(D8*Inputs!$E$10+(1-Inputs!$E$10)/MAX(1,Inputs!$E$9)*(D8*(D$4-1)*1+D8*(D8-1)/2)+1-D8)/1) -> 0.51111111 | E9: =IF(Inputs!$E$9<=0,1,(E8*Inputs!$E$10+(1-Inputs!$E$10)/MAX(1,Inputs!$E$9)*(E8*(E$4-1)*1+E8*(E8-1)/2)+1-E8)/1) -> 0.57222222 | F9: =IF(Inputs!$E$9<=0,1,(F8*Inputs!$E$10+(1-Inputs!$E$10)/MAX(1,Inputs!$E$9)*(F8*(F$4-1)*1+F8*(F8-1)/2)+1-F8)/1) -> 0.63333333 | G9: =IF(Inputs!$E$9<=0,1,(G8*Inputs!$E$10+(1-Inputs!$E$10)/MAX(1,Inputs!$E$9)*(G8*(G$4-1)*1+G8*(G8-1)/2)+1-G8)/1) -> 0.69444444 | H9: =IF(Inputs!$E$9<=0,1,(H8*Inputs!$E$10+(1-Inputs!$E$10)/MAX(1,Inputs!$E$9)*(H8*(H$4-1)*1+H8*(H8-1)/2)+1-H8)/1) -> 0.75555556 | I9: =IF(Inputs!$E$9<=0,1,(I8*Inputs!$E$10+(1-Inputs!$E$10)/MAX(1,Inputs!$E$9)*(I8*(I$4-1)*1+I8*(I8-1)/2)+1-I8)/1) -> 0.81666667 | J9: =IF(Inputs!$E$9<=0,1,(J8*Inputs!$E$10+(1-Inputs!$E$10)/MAX(1,Inputs!$E$9)*(J8*(J$4-1)*1+J8*(J8-1)/2)+1-J8)/1) -> 0.87777778 | ... BJ9: =IF(Inputs!$E$9<=0,1,(BJ8*Inputs!$E$10+(1-Inputs!$E$10)/MAX(1,Inputs!$E$9)*(BJ8*(BJ$4-1)*1+BJ8*(BJ8-1)/2)+1-BJ8)/1) -> 1
A10: Season factor (winter dip) | C10: =IF(OR(MOD(C$4-1,12)>=11,MOD(C$4-1,12)<=1),1-Inputs!$E$11,1+Inputs!$E$11/3) -> 0.85 | D10: =IF(OR(MOD(D$4-1,12)>=11,MOD(D$4-1,12)<=1),1-Inputs!$E$11,1+Inputs!$E$11/3) -> 0.85 | E10: =IF(OR(MOD(E$4-1,12)>=11,MOD(E$4-1,12)<=1),1-Inputs!$E$11,1+Inputs!$E$11/3) -> 1.05 | F10: =IF(OR(MOD(F$4-1,12)>=11,MOD(F$4-1,12)<=1),1-Inputs!$E$11,1+Inputs!$E$11/3) -> 1.05 | G10: =IF(OR(MOD(G$4-1,12)>=11,MOD(G$4-1,12)<=1),1-Inputs!$E$11,1+Inputs!$E$11/3) -> 1.05 | H10: =IF(OR(MOD(H$4-1,12)>=11,MOD(H$4-1,12)<=1),1-Inputs!$E$11,1+Inputs!$E$11/3) -> 1.05 | I10: =IF(OR(MOD(I$4-1,12)>=11,MOD(I$4-1,12)<=1),1-Inputs!$E$11,1+Inputs!$E$11/3) -> 1.05 | J10: =IF(OR(MOD(J$4-1,12)>=11,MOD(J$4-1,12)<=1),1-Inputs!$E$11,1+Inputs!$E$11/3) -> 1.05 | ... BJ10: =IF(OR(MOD(BJ$4-1,12)>=11,MOD(BJ$4-1,12)<=1),1-Inputs!$E$11,1+Inputs!$E$11/3) -> 0.85
A11: Retail cars demanded | C11: =Inputs!$E$7*Inputs!$E$8*1*C9*C10 -> 2662.2 | D11: =Inputs!$E$7*Inputs!$E$8*1*D9*D10 -> 3023.7333 | E11: =Inputs!$E$7*Inputs!$E$8*1*E9*E10 -> 4181.8 | F11: =Inputs!$E$7*Inputs!$E$8*1*F9*F10 -> 4628.4 | G11: =Inputs!$E$7*Inputs!$E$8*1*G9*G10 -> 5075 | H11: =Inputs!$E$7*Inputs!$E$8*1*H9*H10 -> 5521.6 | I11: =Inputs!$E$7*Inputs!$E$8*1*I9*I10 -> 5968.2 | J11: =Inputs!$E$7*Inputs!$E$8*1*J9*J10 -> 6414.8 | ... BJ11: =Inputs!$E$7*Inputs!$E$8*1*BJ9*BJ10 -> 5916
A13: Members
A14: New members from retail cars | C14: =C11*Inputs!$E$22 -> 21.2976 | D14: =D11*Inputs!$E$22 -> 24.189867 | E14: =E11*Inputs!$E$22 -> 33.4544 | F14: =F11*Inputs!$E$22 -> 37.0272 | G14: =G11*Inputs!$E$22 -> 40.6 | H14: =H11*Inputs!$E$22 -> 44.1728 | I14: =I11*Inputs!$E$22 -> 47.7456 | J14: =J11*Inputs!$E$22 -> 51.3184 | ... BJ14: =BJ11*Inputs!$E$22 -> 47.328
A15: New members from direct sign-ups | C15: =Inputs!$E$20*(1+Inputs!$E$21)^(C$5-1)*1*C9 -> 22.5 | D15: =Inputs!$E$20*(1+Inputs!$E$21)^(D$5-1)*1*D9 -> 25.555556 | E15: =Inputs!$E$20*(1+Inputs!$E$21)^(E$5-1)*1*E9 -> 28.611111 | F15: =Inputs!$E$20*(1+Inputs!$E$21)^(F$5-1)*1*F9 -> 31.666667 | G15: =Inputs!$E$20*(1+Inputs!$E$21)^(G$5-1)*1*G9 -> 34.722222 | H15: =Inputs!$E$20*(1+Inputs!$E$21)^(H$5-1)*1*H9 -> 37.777778 | I15: =Inputs!$E$20*(1+Inputs!$E$21)^(I$5-1)*1*I9 -> 40.833333 | J15: =Inputs!$E$20*(1+Inputs!$E$21)^(J$5-1)*1*J9 -> 43.888889 | ... BJ15: =Inputs!$E$20*(1+Inputs!$E$21)^(BJ$5-1)*1*BJ9 -> 60.775312
A16: New members - total | C16: =C14+C15 -> 43.7976 | D16: =D14+D15 -> 49.745422 | E16: =E14+E15 -> 62.065511 | F16: =F14+F15 -> 68.693867 | G16: =G14+G15 -> 75.322222 | H16: =H14+H15 -> 81.950578 | I16: =I14+I15 -> 88.578933 | J16: =J14+J15 -> 95.207289 | ... BJ16: =BJ14+BJ15 -> 108.10331
A17: Members - opening | C17: =Inputs!$E$19 -> 250 | D17: =C19 -> 283.7976 | E17: =D19 -> 322.19112 | F17: =E19 -> 371.36898 | G17: =F19 -> 425.20809 | H17: =G19 -> 483.52199 | I17: =H19 -> 546.13169 | J17: =I19 -> 612.86535 | K17: =J19 -> 683.55803 | ... BJ17: =BI19 -> 2579.9274
A18: Members who cancelled | C18: =C19-C17-C16 -> -10 | D18: =D19-D17-D16 -> -11.351904 | E18: =E19-E17-E16 -> -12.887645 | F18: =F19-F17-F16 -> -14.854759 | G18: =G19-G17-G16 -> -17.008324 | H18: =H19-H17-H16 -> -19.34088 | I18: =I19-I17-I16 -> -21.845268 | J18: =J19-J17-J16 -> -24.514614 | ... BJ18: =BJ19-BJ17-BJ16 -> -103.1971
A19: Members - closing | C19: =C17*(1-Inputs!$E$23)+C16 -> 283.7976 | D19: =D17*(1-Inputs!$E$23)+D16 -> 322.19112 | E19: =E17*(1-Inputs!$E$23)+E16 -> 371.36898 | F19: =F17*(1-Inputs!$E$23)+F16 -> 425.20809 | G19: =G17*(1-Inputs!$E$23)+G16 -> 483.52199 | H19: =H17*(1-Inputs!$E$23)+H16 -> 546.13169 | I19: =I17*(1-Inputs!$E$23)+I16 -> 612.86535 | J19: =J17*(1-Inputs!$E$23)+J16 -> 683.55803 | ... BJ19: =BJ17*(1-Inputs!$E$23)+BJ16 -> 2584.8337
A20: Members - average | C20: =(C17+C19)/2 -> 266.8988 | D20: =(D17+D19)/2 -> 302.99436 | E20: =(E17+E19)/2 -> 346.78005 | F20: =(F17+F19)/2 -> 398.28854 | G20: =(G17+G19)/2 -> 454.36504 | H20: =(H17+H19)/2 -> 514.82684 | I20: =(I17+I19)/2 -> 579.49852 | J20: =(J17+J19)/2 -> 648.21169 | ... BJ20: =(BJ17+BJ19)/2 -> 2582.3806
A22: Washes
A23: Member washes demanded | C23: =C20*Inputs!$E$24*C10*1 -> 794.02393 | D23: =D20*Inputs!$E$24*D10*1 -> 901.40822 | E23: =E20*Inputs!$E$24*E10*1 -> 1274.4167 | F23: =F20*Inputs!$E$24*F10*1 -> 1463.7104 | G23: =G20*Inputs!$E$24*G10*1 -> 1669.7915 | H23: =H20*Inputs!$E$24*H10*1 -> 1891.9886 | I23: =I20*Inputs!$E$24*I10*1 -> 2129.6571 | J23: =J20*Inputs!$E$24*J10*1 -> 2382.178 | ... BJ23: =BJ20*Inputs!$E$24*BJ10*1 -> 7682.5821
A24: Tunnel capacity (rated speed × hours × practical share × days) | C24: =Inputs!$E$14*Inputs!$E$15*Inputs!$E$16*Inputs!$E$8*1 -> 24563 | D24: =Inputs!$E$14*Inputs!$E$15*Inputs!$E$16*Inputs!$E$8*1 -> 24563 | E24: =Inputs!$E$14*Inputs!$E$15*Inputs!$E$16*Inputs!$E$8*1 -> 24563 | F24: =Inputs!$E$14*Inputs!$E$15*Inputs!$E$16*Inputs!$E$8*1 -> 24563 | G24: =Inputs!$E$14*Inputs!$E$15*Inputs!$E$16*Inputs!$E$8*1 -> 24563 | H24: =Inputs!$E$14*Inputs!$E$15*Inputs!$E$16*Inputs!$E$8*1 -> 24563 | I24: =Inputs!$E$14*Inputs!$E$15*Inputs!$E$16*Inputs!$E$8*1 -> 24563 | J24: =Inputs!$E$14*Inputs!$E$15*Inputs!$E$16*Inputs!$E$8*1 -> 24563 | ... BJ24: =Inputs!$E$14*Inputs!$E$15*Inputs!$E$16*Inputs!$E$8*1 -> 24563
A25: Share of demand the tunnel can wash | C25: =MIN(1,C24/MAX(1,C11+C23)) -> 1 | D25: =MIN(1,D24/MAX(1,D11+D23)) -> 1 | E25: =MIN(1,E24/MAX(1,E11+E23)) -> 1 | F25: =MIN(1,F24/MAX(1,F11+F23)) -> 1 | G25: =MIN(1,G24/MAX(1,G11+G23)) -> 1 | H25: =MIN(1,H24/MAX(1,H11+H23)) -> 1 | I25: =MIN(1,I24/MAX(1,I11+I23)) -> 1 | J25: =MIN(1,J24/MAX(1,J11+J23)) -> 1 | ... BJ25: =MIN(1,BJ24/MAX(1,BJ11+BJ23)) -> 1
A26: Retail cars washed | C26: =C11*C25 -> 2662.2 | D26: =D11*D25 -> 3023.7333 | E26: =E11*E25 -> 4181.8 | F26: =F11*F25 -> 4628.4 | G26: =G11*G25 -> 5075 | H26: =H11*H25 -> 5521.6 | I26: =I11*I25 -> 5968.2 | J26: =J11*J25 -> 6414.8 | ... BJ26: =BJ11*BJ25 -> 5916
A27: Member washes | C27: =C23*C25 -> 794.02393 | D27: =D23*D25 -> 901.40822 | E27: =E23*E25 -> 1274.4167 | F27: =F23*F25 -> 1463.7104 | G27: =G23*G25 -> 1669.7915 | H27: =H23*H25 -> 1891.9886 | I27: =I23*I25 -> 2129.6571 | J27: =J23*J25 -> 2382.178 | ... BJ27: =BJ23*BJ25 -> 7682.5821
A28: Washes - total | C28: =C26+C27 -> 3456.2239 | D28: =D26+D27 -> 3925.1416 | E28: =E26+E27 -> 5456.2167 | F28: =F26+F27 -> 6092.1104 | G28: =G26+G27 -> 6744.7915 | H28: =H26+H27 -> 7413.5886 | I28: =I26+I27 -> 8097.8571 | J28: =J26+J27 -> 8796.978 | ... BJ28: =BJ26+BJ27 -> 13598.582
A29: Washes lost to the capacity limit | C29: =C11+C23-C28 -> 0 | D29: =D11+D23-D28 -> 0 | E29: =E11+E23-E28 -> 0 | F29: =F11+F23-F28 -> 0 | G29: =G11+G23-G28 -> 0 | H29: =H11+H23-H28 -> 0 | I29: =I11+I23-I28 -> 0 | J29: =J11+J23-J28 -> 0 | ... BJ29: =BJ11+BJ23-BJ28 -> 0
A31: Revenue
A32: Average price per retail wash | C32: =Inputs!$E$27*(1+Inputs!$E$30)^(C$5-1) -> 13 | D32: =Inputs!$E$27*(1+Inputs!$E$30)^(D$5-1) -> 13 | E32: =Inputs!$E$27*(1+Inputs!$E$30)^(E$5-1) -> 13 | F32: =Inputs!$E$27*(1+Inputs!$E$30)^(F$5-1) -> 13 | G32: =Inputs!$E$27*(1+Inputs!$E$30)^(G$5-1) -> 13 | H32: =Inputs!$E$27*(1+Inputs!$E$30)^(H$5-1) -> 13 | I32: =Inputs!$E$27*(1+Inputs!$E$30)^(I$5-1) -> 13 | J32: =Inputs!$E$27*(1+Inputs!$E$30)^(J$5-1) -> 13 | ... BJ32: =Inputs!$E$27*(1+Inputs!$E$30)^(BJ$5-1) -> 14.071618
A33: Unlimited plan fee per month | C33: =Inputs!$E$29*(1+Inputs!$E$30)^(C$5-1) -> 35 | D33: =Inputs!$E$29*(1+Inputs!$E$30)^(D$5-1) -> 35 | E33: =Inputs!$E$29*(1+Inputs!$E$30)^(E$5-1) -> 35 | F33: =Inputs!$E$29*(1+Inputs!$E$30)^(F$5-1) -> 35 | G33: =Inputs!$E$29*(1+Inputs!$E$30)^(G$5-1) -> 35 | H33: =Inputs!$E$29*(1+Inputs!$E$30)^(H$5-1) -> 35 | I33: =Inputs!$E$29*(1+Inputs!$E$30)^(I$5-1) -> 35 | J33: =Inputs!$E$29*(1+Inputs!$E$30)^(J$5-1) -> 35 | ... BJ33: =Inputs!$E$29*(1+Inputs!$E$30)^(BJ$5-1) -> 37.885126
A34: Retail wash revenue | C34: =C26*C32 -> 34608.6 | D34: =D26*D32 -> 39308.533 | E34: =E26*E32 -> 54363.4 | F34: =F26*F32 -> 60169.2 | G34: =G26*G32 -> 65975 | H34: =H26*H32 -> 71780.8 | I34: =I26*I32 -> 77586.6 | J34: =J26*J32 -> 83392.4 | ... BJ34: =BJ26*BJ32 -> 83247.693
A35: Add-on revenue | C35: =C26*Inputs!$E$28*(1+Inputs!$E$30)^(C$5-1) -> 3993.3 | D35: =D26*Inputs!$E$28*(1+Inputs!$E$30)^(D$5-1) -> 4535.6 | E35: =E26*Inputs!$E$28*(1+Inputs!$E$30)^(E$5-1) -> 6272.7 | F35: =F26*Inputs!$E$28*(1+Inputs!$E$30)^(F$5-1) -> 6942.6 | G35: =G26*Inputs!$E$28*(1+Inputs!$E$30)^(G$5-1) -> 7612.5 | H35: =H26*Inputs!$E$28*(1+Inputs!$E$30)^(H$5-1) -> 8282.4 | I35: =I26*Inputs!$E$28*(1+Inputs!$E$30)^(I$5-1) -> 8952.3 | J35: =J26*Inputs!$E$28*(1+Inputs!$E$30)^(J$5-1) -> 9622.2 | ... BJ35: =BJ26*Inputs!$E$28*(1+Inputs!$E$30)^(BJ$5-1) -> 9605.503
A36: Unlimited plan fees | C36: =C20*C33*1 -> 9341.458 | D36: =D20*D33*1 -> 10604.803 | E36: =E20*E33*1 -> 12137.302 | F36: =F20*F33*1 -> 13940.099 | G36: =G20*G33*1 -> 15902.776 | H36: =H20*H33*1 -> 18018.939 | I36: =I20*I33*1 -> 20282.448 | J36: =J20*J33*1 -> 22687.409 | ... BJ36: =BJ20*BJ33*1 -> 97833.812
A37: Revenue | C37: =C34+C35+C36 -> 47943.358 | D37: =D34+D35+D36 -> 54448.936 | E37: =E34+E35+E36 -> 72773.402 | F37: =F34+F35+F36 -> 81051.899 | G37: =G34+G35+G36 -> 89490.276 | H37: =H34+H35+H36 -> 98082.139 | I37: =I34+I35+I36 -> 106821.35 | J37: =J34+J35+J36 -> 115702.01 | ... BJ37: =BJ34+BJ35+BJ36 -> 190687.01
A39: Cost of sales
A40: Chemicals | C40: =-C28*Inputs!$E$33*(1+Inputs!$E$38)^(C$5-1) -> -2937.7903 | D40: =-D28*Inputs!$E$33*(1+Inputs!$E$38)^(D$5-1) -> -3336.3703 | E40: =-E28*Inputs!$E$33*(1+Inputs!$E$38)^(E$5-1) -> -4637.7842 | F40: =-F28*Inputs!$E$33*(1+Inputs!$E$38)^(F$5-1) -> -5178.2938 | G40: =-G28*Inputs!$E$33*(1+Inputs!$E$38)^(G$5-1) -> -5733.0728 | H40: =-H28*Inputs!$E$33*(1+Inputs!$E$38)^(H$5-1) -> -6301.5503 | I40: =-I28*Inputs!$E$33*(1+Inputs!$E$38)^(I$5-1) -> -6883.1785 | J40: =-J28*Inputs!$E$33*(1+Inputs!$E$38)^(J$5-1) -> -7477.4313 | ... BJ40: =-BJ28*Inputs!$E$33*(1+Inputs!$E$38)^(BJ$5-1) -> -13009.525
A41: Water & sewer | C41: =-C28*Inputs!$E$34/1000*Inputs!$E$35*(1+Inputs!$E$38)^(C$5-1) -> -1244.2406 | D41: =-D28*Inputs!$E$34/1000*Inputs!$E$35*(1+Inputs!$E$38)^(D$5-1) -> -1413.051 | E41: =-E28*Inputs!$E$34/1000*Inputs!$E$35*(1+Inputs!$E$38)^(E$5-1) -> -1964.238 | F41: =-F28*Inputs!$E$34/1000*Inputs!$E$35*(1+Inputs!$E$38)^(F$5-1) -> -2193.1597 | G41: =-G28*Inputs!$E$34/1000*Inputs!$E$35*(1+Inputs!$E$38)^(G$5-1) -> -2428.1249 | H41: =-H28*Inputs!$E$34/1000*Inputs!$E$35*(1+Inputs!$E$38)^(H$5-1) -> -2668.8919 | I41: =-I28*Inputs!$E$34/1000*Inputs!$E$35*(1+Inputs!$E$38)^(I$5-1) -> -2915.2285 | J41: =-J28*Inputs!$E$34/1000*Inputs!$E$35*(1+Inputs!$E$38)^(J$5-1) -> -3166.9121 | ... BJ41: =-BJ28*Inputs!$E$34/1000*Inputs!$E$35*(1+Inputs!$E$38)^(BJ$5-1) -> -5509.9166
A42: Electricity | C42: =-C28*Inputs!$E$36*(1+Inputs!$E$38)^(C$5-1) -> -1451.6141 | D42: =-D28*Inputs!$E$36*(1+Inputs!$E$38)^(D$5-1) -> -1648.5595 | E42: =-E28*Inputs!$E$36*(1+Inputs!$E$38)^(E$5-1) -> -2291.611 | F42: =-F28*Inputs!$E$36*(1+Inputs!$E$38)^(F$5-1) -> -2558.6864 | G42: =-G28*Inputs!$E$36*(1+Inputs!$E$38)^(G$5-1) -> -2832.8124 | H42: =-H28*Inputs!$E$36*(1+Inputs!$E$38)^(H$5-1) -> -3113.7072 | I42: =-I28*Inputs!$E$36*(1+Inputs!$E$38)^(I$5-1) -> -3401.1 | J42: =-J28*Inputs!$E$36*(1+Inputs!$E$38)^(J$5-1) -> -3694.7307 | ... BJ42: =-BJ28*Inputs!$E$36*(1+Inputs!$E$38)^(BJ$5-1) -> -6428.2361
A43: Chemicals, water & electricity | C43: =C40+C41+C42 -> -5633.645 | D43: =D40+D41+D42 -> -6397.9807 | E43: =E40+E41+E42 -> -8893.6332 | F43: =F40+F41+F42 -> -9930.1399 | G43: =G40+G41+G42 -> -10994.01 | H43: =H40+H41+H42 -> -12084.149 | I43: =I40+I41+I42 -> -13199.507 | J43: =J40+J41+J42 -> -14339.074 | ... BJ43: =BJ40+BJ41+BJ42 -> -24947.678
A44: Card processing fees | C44: =-C37*Inputs!$E$37 -> -1438.3007 | D44: =-D37*Inputs!$E$37 -> -1633.4681 | E44: =-E37*Inputs!$E$37 -> -2183.2021 | F44: =-F37*Inputs!$E$37 -> -2431.557 | G44: =-G37*Inputs!$E$37 -> -2684.7083 | H44: =-H37*Inputs!$E$37 -> -2942.4642 | I44: =-I37*Inputs!$E$37 -> -3204.6404 | J44: =-J37*Inputs!$E$37 -> -3471.0603 | ... BJ44: =-BJ37*Inputs!$E$37 -> -5720.6102
A45: Cost of sales | C45: =C43+C44 -> -7071.9457 | D45: =D43+D44 -> -8031.4488 | E45: =E43+E44 -> -11076.835 | F45: =F43+F44 -> -12361.697 | G45: =G43+G44 -> -13678.718 | H45: =H43+H44 -> -15026.614 | I45: =I43+I44 -> -16404.147 | J45: =J43+J44 -> -17810.134 | ... BJ45: =BJ43+BJ44 -> -30668.288
A46: Gross profit | C46: =C37+C45 -> 40871.412 | D46: =D37+D45 -> 46417.487 | E46: =E37+E45 -> 61696.567 | F46: =F37+F45 -> 68690.202 | G46: =G37+G45 -> 75811.558 | H46: =H37+H45 -> 83055.526 | I46: =I37+I45 -> 90417.201 | J46: =J37+J45 -> 97891.875 | ... BJ46: =BJ37+BJ45 -> 160018.72
A48: Operating expenses
A49: Site payroll | C49: =Headcount!C15 -> -36586.667 | D49: =Headcount!D15 -> -36586.667 | E49: =Headcount!E15 -> -36586.667 | F49: =Headcount!F15 -> -36586.667 | G49: =Headcount!G15 -> -36586.667 | H49: =Headcount!H15 -> -36586.667 | I49: =Headcount!I15 -> -36586.667 | J49: =Headcount!J15 -> -36586.667 | ... BJ49: =Headcount!BJ15 -> -41178.616
A50: Site lease or land cost | C50: =-Inputs!$E$41*(1+Inputs!$E$42)^(C$5-1)*1 -> -30000 | D50: =-Inputs!$E$41*(1+Inputs!$E$42)^(D$5-1)*1 -> -30000 | E50: =-Inputs!$E$41*(1+Inputs!$E$42)^(E$5-1)*1 -> -30000 | F50: =-Inputs!$E$41*(1+Inputs!$E$42)^(F$5-1)*1 -> -30000 | G50: =-Inputs!$E$41*(1+Inputs!$E$42)^(G$5-1)*1 -> -30000 | H50: =-Inputs!$E$41*(1+Inputs!$E$42)^(H$5-1)*1 -> -30000 | I50: =-Inputs!$E$41*(1+Inputs!$E$42)^(I$5-1)*1 -> -30000 | J50: =-Inputs!$E$41*(1+Inputs!$E$42)^(J$5-1)*1 -> -30000 | ... BJ50: =-Inputs!$E$41*(1+Inputs!$E$42)^(BJ$5-1)*1 -> -33765.264
A51: Equipment maintenance & repairs | C51: =-Inputs!$E$43*(1+Inputs!$E$38)^(C$5-1)*1 -> -5500 | D51: =-Inputs!$E$43*(1+Inputs!$E$38)^(D$5-1)*1 -> -5500 | E51: =-Inputs!$E$43*(1+Inputs!$E$38)^(E$5-1)*1 -> -5500 | F51: =-Inputs!$E$43*(1+Inputs!$E$38)^(F$5-1)*1 -> -5500 | G51: =-Inputs!$E$43*(1+Inputs!$E$38)^(G$5-1)*1 -> -5500 | H51: =-Inputs!$E$43*(1+Inputs!$E$38)^(H$5-1)*1 -> -5500 | I51: =-Inputs!$E$43*(1+Inputs!$E$38)^(I$5-1)*1 -> -5500 | J51: =-Inputs!$E$43*(1+Inputs!$E$38)^(J$5-1)*1 -> -5500 | ... BJ51: =-Inputs!$E$43*(1+Inputs!$E$38)^(BJ$5-1)*1 -> -6190.2985
A52: Insurance, property tax, software & other | C52: =-Inputs!$E$44*(1+Inputs!$E$38)^(C$5-1)*1 -> -9500 | D52: =-Inputs!$E$44*(1+Inputs!$E$38)^(D$5-1)*1 -> -9500 | E52: =-Inputs!$E$44*(1+Inputs!$E$38)^(E$5-1)*1 -> -9500 | F52: =-Inputs!$E$44*(1+Inputs!$E$38)^(F$5-1)*1 -> -9500 | G52: =-Inputs!$E$44*(1+Inputs!$E$38)^(G$5-1)*1 -> -9500 | H52: =-Inputs!$E$44*(1+Inputs!$E$38)^(H$5-1)*1 -> -9500 | I52: =-Inputs!$E$44*(1+Inputs!$E$38)^(I$5-1)*1 -> -9500 | J52: =-Inputs!$E$44*(1+Inputs!$E$38)^(J$5-1)*1 -> -9500 | ... BJ52: =-Inputs!$E$44*(1+Inputs!$E$38)^(BJ$5-1)*1 -> -10692.334
A53: Marketing | C53: =-Inputs!$E$45*(1+Inputs!$E$46)^(C$5-1)*1 -> -12000 | D53: =-Inputs!$E$45*(1+Inputs!$E$46)^(D$5-1)*1 -> -12000 | E53: =-Inputs!$E$45*(1+Inputs!$E$46)^(E$5-1)*1 -> -12000 | F53: =-Inputs!$E$45*(1+Inputs!$E$46)^(F$5-1)*1 -> -12000 | G53: =-Inputs!$E$45*(1+Inputs!$E$46)^(G$5-1)*1 -> -12000 | H53: =-Inputs!$E$45*(1+Inputs!$E$46)^(H$5-1)*1 -> -12000 | I53: =-Inputs!$E$45*(1+Inputs!$E$46)^(I$5-1)*1 -> -12000 | J53: =-Inputs!$E$45*(1+Inputs!$E$46)^(J$5-1)*1 -> -12000 | ... BJ53: =-Inputs!$E$45*(1+Inputs!$E$46)^(BJ$5-1)*1 -> -4915.2
A54: Total operating expenses | C54: =C49+C50+C51+C52+C53 -> -93586.667 | D54: =D49+D50+D51+D52+D53 -> -93586.667 | E54: =E49+E50+E51+E52+E53 -> -93586.667 | F54: =F49+F50+F51+F52+F53 -> -93586.667 | G54: =G49+G50+G51+G52+G53 -> -93586.667 | H54: =H49+H50+H51+H52+H53 -> -93586.667 | I54: =I49+I50+I51+I52+I53 -> -93586.667 | J54: =J49+J50+J51+J52+J53 -> -93586.667 | ... BJ54: =BJ49+BJ50+BJ51+BJ52+BJ53 -> -96741.712
A55: EBITDA | C55: =C46+C54 -> -52715.254 | D55: =D46+D54 -> -47169.18 | E55: =E46+E54 -> -31890.1 | F55: =F46+F54 -> -24896.465 | G55: =G46+G54 -> -17775.109 | H55: =H46+H54 -> -10531.141 | I55: =I46+I54 -> -3169.4659 | J55: =J46+J54 -> 4305.2082 | ... BJ55: =BJ46+BJ54 -> 63277.007
A57: Profit after depreciation, interest, tax
A58: EBIT | C58: =C55+C73 -> -81187.477 | D58: =D55+D73 -> -75641.402 | E58: =E55+E73 -> -60362.322 | F58: =F55+F73 -> -53368.687 | G58: =G55+G73 -> -46247.331 | H58: =H55+H73 -> -39003.363 | I58: =I55+I73 -> -31641.688 | J58: =J55+J73 -> -24167.014 | ... BJ58: =BJ55+BJ73 -> 33693.673
A59: Interest on loan (average balance after drawdown) | C59: =-(C78+C79+C81)/2*Inputs!$E$69/12 -> -21250 | D59: =-(D78+D79+D81)/2*Inputs!$E$69/12 -> -21161.458 | E59: =-(E78+E79+E81)/2*Inputs!$E$69/12 -> -20984.375 | F59: =-(F78+F79+F81)/2*Inputs!$E$69/12 -> -20807.292 | G59: =-(G78+G79+G81)/2*Inputs!$E$69/12 -> -20630.208 | H59: =-(H78+H79+H81)/2*Inputs!$E$69/12 -> -20453.125 | I59: =-(I78+I79+I81)/2*Inputs!$E$69/12 -> -20276.042 | J59: =-(J78+J79+J81)/2*Inputs!$E$69/12 -> -20098.958 | ... BJ59: =-(BJ78+BJ79+BJ81)/2*Inputs!$E$69/12 -> -10890.625
A60: Pre-tax income | C60: =C58+C59 -> -102437.48 | D60: =D58+D59 -> -96802.86 | E60: =E58+E59 -> -81346.697 | F60: =F58+F59 -> -74175.979 | G60: =G58+G59 -> -66877.539 | H60: =H58+H59 -> -59456.488 | I60: =I58+I59 -> -51917.73 | J60: =J58+J59 -> -44265.972 | ... BJ60: =BJ58+BJ59 -> 22803.048
A61: Helper: cumulative pre-tax income | C61: =C60 -> -102437.48 | D61: =C61+D60 -> -199240.34 | E61: =D61+E60 -> -280587.03 | F61: =E61+F60 -> -354763.01 | G61: =F61+G60 -> -421640.55 | H61: =G61+H60 -> -481097.04 | I61: =H61+I60 -> -533014.77 | J61: =I61+J60 -> -577280.74 | K61: =J61+K60 -> -613786.48 | ... BJ61: =BI61+BJ60 -> -216134.04
A62: Helper: cumulative taxable income (losses carried forward) | C62: =MAX(0,C61) -> 0 | D62: =MAX(C62,D61) -> 0 | E62: =MAX(D62,E61) -> 0 | F62: =MAX(E62,F61) -> 0 | G62: =MAX(F62,G61) -> 0 | H62: =MAX(G62,H61) -> 0 | I62: =MAX(H62,I61) -> 0 | J62: =MAX(I62,J61) -> 0 | K62: =MAX(J62,K61) -> 0 | ... BJ62: =MAX(BI62,BJ61) -> 0
A63: Income tax | C63: =-C62*Inputs!$E$79 -> 0 | D63: =-(D62-C62)*Inputs!$E$79 -> 0 | E63: =-(E62-D62)*Inputs!$E$79 -> 0 | F63: =-(F62-E62)*Inputs!$E$79 -> 0 | G63: =-(G62-F62)*Inputs!$E$79 -> 0 | H63: =-(H62-G62)*Inputs!$E$79 -> 0 | I63: =-(I62-H62)*Inputs!$E$79 -> 0 | J63: =-(J62-I62)*Inputs!$E$79 -> 0 | K63: =-(K62-J62)*Inputs!$E$79 -> 0 | ... BJ63: =-(BJ62-BI62)*Inputs!$E$79 -> 0
A64: Net income | C64: =C60+C63 -> -102437.48 | D64: =D60+D63 -> -96802.86 | E64: =E60+E63 -> -81346.697 | F64: =F60+F63 -> -74175.979 | G64: =G60+G63 -> -66877.539 | H64: =H60+H63 -> -59456.488 | I64: =I60+I63 -> -51917.73 | J64: =J60+J63 -> -44265.972 | ... BJ64: =BJ60+BJ63 -> 22803.048
A66: Fixed assets & capital spending
A67: Tunnel equipment | C67: =IF(C$4=1,Inputs!$E$49,0) -> 1650000 | D67: =IF(D$4=1,Inputs!$E$49,0) -> 0 | E67: =IF(E$4=1,Inputs!$E$49,0) -> 0 | F67: =IF(F$4=1,Inputs!$E$49,0) -> 0 | G67: =IF(G$4=1,Inputs!$E$49,0) -> 0 | H67: =IF(H$4=1,Inputs!$E$49,0) -> 0 | I67: =IF(I$4=1,Inputs!$E$49,0) -> 0 | J67: =IF(J$4=1,Inputs!$E$49,0) -> 0 | ... BJ67: =IF(BJ$4=1,Inputs!$E$49,0) -> 0
A68: Building & site works | C68: =IF(C$4=1,Inputs!$E$50,0) -> 2300000 | D68: =IF(D$4=1,Inputs!$E$50,0) -> 0 | E68: =IF(E$4=1,Inputs!$E$50,0) -> 0 | F68: =IF(F$4=1,Inputs!$E$50,0) -> 0 | G68: =IF(G$4=1,Inputs!$E$50,0) -> 0 | H68: =IF(H$4=1,Inputs!$E$50,0) -> 0 | I68: =IF(I$4=1,Inputs!$E$50,0) -> 0 | J68: =IF(J$4=1,Inputs!$E$50,0) -> 0 | ... BJ68: =IF(BJ$4=1,Inputs!$E$50,0) -> 0
A69: Pay stations, signage & vacuums | C69: =IF(C$4=1,Inputs!$E$51,0) -> 150000 | D69: =IF(D$4=1,Inputs!$E$51,0) -> 0 | E69: =IF(E$4=1,Inputs!$E$51,0) -> 0 | F69: =IF(F$4=1,Inputs!$E$51,0) -> 0 | G69: =IF(G$4=1,Inputs!$E$51,0) -> 0 | H69: =IF(H$4=1,Inputs!$E$51,0) -> 0 | I69: =IF(I$4=1,Inputs!$E$51,0) -> 0 | J69: =IF(J$4=1,Inputs!$E$51,0) -> 0 | ... BJ69: =IF(BJ$4=1,Inputs!$E$51,0) -> 0
A70: Equipment refresh & upgrades (first period of each year from year 2) | C70: =IF(AND(C$5>1,MOD(C$4-1,12)=0),Inputs!$E$52,0) -> 0 | D70: =IF(AND(D$5>1,MOD(D$4-1,12)=0),Inputs!$E$52,0) -> 0 | E70: =IF(AND(E$5>1,MOD(E$4-1,12)=0),Inputs!$E$52,0) -> 0 | F70: =IF(AND(F$5>1,MOD(F$4-1,12)=0),Inputs!$E$52,0) -> 0 | G70: =IF(AND(G$5>1,MOD(G$4-1,12)=0),Inputs!$E$52,0) -> 0 | H70: =IF(AND(H$5>1,MOD(H$4-1,12)=0),Inputs!$E$52,0) -> 0 | I70: =IF(AND(I$5>1,MOD(I$4-1,12)=0),Inputs!$E$52,0) -> 0 | J70: =IF(AND(J$5>1,MOD(J$4-1,12)=0),Inputs!$E$52,0) -> 0 | ... BJ70: =IF(AND(BJ$5>1,MOD(BJ$4-1,12)=0),Inputs!$E$52,0) -> 0
A71: Capital spending | C71: =C67+C68+C69+C70 -> 4100000 | D71: =D67+D68+D69+D70 -> 0 | E71: =E67+E68+E69+E70 -> 0 | F71: =F67+F68+F69+F70 -> 0 | G71: =G67+G68+G69+G70 -> 0 | H71: =H67+H68+H69+H70 -> 0 | I71: =I67+I68+I69+I70 -> 0 | J71: =J67+J68+J69+J70 -> 0 | ... BJ71: =BJ67+BJ68+BJ69+BJ70 -> 0
A72: Fixed assets at cost | C72: =C71 -> 4100000 | D72: =C72+D71 -> 4100000 | E72: =D72+E71 -> 4100000 | F72: =E72+F71 -> 4100000 | G72: =F72+G71 -> 4100000 | H72: =G72+H71 -> 4100000 | I72: =H72+I71 -> 4100000 | J72: =I72+J71 -> 4100000 | K72: =J72+K71 -> 4100000 | ... BJ72: =BI72+BJ71 -> 4260000
A73: Depreciation | C73: =-MIN(C72/MAX(1,Inputs!$E$78*12),C71) -> -28472.222 | D73: =-MIN(D72/MAX(1,Inputs!$E$78*12),C75+D71) -> -28472.222 | E73: =-MIN(E72/MAX(1,Inputs!$E$78*12),D75+E71) -> -28472.222 | F73: =-MIN(F72/MAX(1,Inputs!$E$78*12),E75+F71) -> -28472.222 | G73: =-MIN(G72/MAX(1,Inputs!$E$78*12),F75+G71) -> -28472.222 | H73: =-MIN(H72/MAX(1,Inputs!$E$78*12),G75+H71) -> -28472.222 | I73: =-MIN(I72/MAX(1,Inputs!$E$78*12),H75+I71) -> -28472.222 | J73: =-MIN(J72/MAX(1,Inputs!$E$78*12),I75+J71) -> -28472.222 | K73: =-MIN(K72/MAX(1,Inputs!$E$78*12),J75+K71) -> -28472.222 | ... BJ73: =-MIN(BJ72/MAX(1,Inputs!$E$78*12),BI75+BJ71) -> -29583.333
A74: Accumulated depreciation | C74: =C73 -> -28472.222 | D74: =C74+D73 -> -56944.444 | E74: =D74+E73 -> -85416.667 | F74: =E74+F73 -> -113888.89 | G74: =F74+G73 -> -142361.11 | H74: =G74+H73 -> -170833.33 | I74: =H74+I73 -> -199305.56 | J74: =I74+J73 -> -227777.78 | K74: =J74+K73 -> -256250 | ... BJ74: =BI74+BJ73 -> -1741666.7
A75: Net fixed assets | C75: =C72+C74 -> 4071527.8 | D75: =D72+D74 -> 4043055.6 | E75: =E72+E74 -> 4014583.3 | F75: =F72+F74 -> 3986111.1 | G75: =G72+G74 -> 3957638.9 | H75: =H72+H74 -> 3929166.7 | I75: =I72+I74 -> 3900694.4 | J75: =J72+J74 -> 3872222.2 | ... BJ75: =BJ72+BJ74 -> 2518333.3
A77: Debt
A78: Loan — opening balance | C78: =0 -> 0 | D78: =C81 -> 3000000 | E78: =D81 -> 2975000 | F78: =E81 -> 2950000 | G78: =F81 -> 2925000 | H78: =G81 -> 2900000 | I78: =H81 -> 2875000 | J78: =I81 -> 2850000 | K78: =J81 -> 2825000 | ... BJ78: =BI81 -> 1550000
A79: Loan drawdown | C79: =IF(C$4=1,Inputs!$E$68,0) -> 3000000 | D79: =IF(D$4=1,Inputs!$E$68,0) -> 0 | E79: =IF(E$4=1,Inputs!$E$68,0) -> 0 | F79: =IF(F$4=1,Inputs!$E$68,0) -> 0 | G79: =IF(G$4=1,Inputs!$E$68,0) -> 0 | H79: =IF(H$4=1,Inputs!$E$68,0) -> 0 | I79: =IF(I$4=1,Inputs!$E$68,0) -> 0 | J79: =IF(J$4=1,Inputs!$E$68,0) -> 0 | ... BJ79: =IF(BJ$4=1,Inputs!$E$68,0) -> 0
A80: Loan repayment | C80: =-MIN(C78,Inputs!$E$68/MAX(1,Inputs!$E$70*12)) -> 0 | D80: =-MIN(D78,Inputs!$E$68/MAX(1,Inputs!$E$70*12)) -> -25000 | E80: =-MIN(E78,Inputs!$E$68/MAX(1,Inputs!$E$70*12)) -> -25000 | F80: =-MIN(F78,Inputs!$E$68/MAX(1,Inputs!$E$70*12)) -> -25000 | G80: =-MIN(G78,Inputs!$E$68/MAX(1,Inputs!$E$70*12)) -> -25000 | H80: =-MIN(H78,Inputs!$E$68/MAX(1,Inputs!$E$70*12)) -> -25000 | I80: =-MIN(I78,Inputs!$E$68/MAX(1,Inputs!$E$70*12)) -> -25000 | J80: =-MIN(J78,Inputs!$E$68/MAX(1,Inputs!$E$70*12)) -> -25000 | ... BJ80: =-MIN(BJ78,Inputs!$E$68/MAX(1,Inputs!$E$70*12)) -> -25000
A81: Loan — closing balance | C81: =C78+C79+C80 -> 3000000 | D81: =D78+D79+D80 -> 2975000 | E81: =E78+E79+E80 -> 2950000 | F81: =F78+F79+F80 -> 2925000 | G81: =G78+G79+G80 -> 2900000 | H81: =H78+H79+H80 -> 2875000 | I81: =I78+I79+I80 -> 2850000 | J81: =J78+J79+J80 -> 2825000 | ... BJ81: =BJ78+BJ79+BJ80 -> 1525000
A83: Working capital
A84: Accounts receivable | C84: =C37*Inputs!$E$73/30 -> 3196.2239 | D84: =D37*Inputs!$E$73/30 -> 3629.9291 | E84: =E37*Inputs!$E$73/30 -> 4851.5601 | F84: =F37*Inputs!$E$73/30 -> 5403.4599 | G84: =G37*Inputs!$E$73/30 -> 5966.0184 | H84: =H37*Inputs!$E$73/30 -> 6538.8093 | I84: =I37*Inputs!$E$73/30 -> 7121.4232 | J84: =J37*Inputs!$E$73/30 -> 7713.4673 | ... BJ84: =BJ37*Inputs!$E$73/30 -> 12712.467
A85: Inventory | C85: =-C45*Inputs!$E$74/30 -> 3535.9729 | D85: =-D45*Inputs!$E$74/30 -> 4015.7244 | E85: =-E45*Inputs!$E$74/30 -> 5538.4176 | F85: =-F45*Inputs!$E$74/30 -> 6180.8484 | G85: =-G45*Inputs!$E$74/30 -> 6839.3592 | H85: =-H45*Inputs!$E$74/30 -> 7513.3068 | I85: =-I45*Inputs!$E$74/30 -> 8202.0737 | J85: =-J45*Inputs!$E$74/30 -> 8905.0672 | ... BJ85: =-BJ45*Inputs!$E$74/30 -> 15334.144
A86: Accounts payable | C86: =-C45*Inputs!$E$75/30 -> 5893.2881 | D86: =-D45*Inputs!$E$75/30 -> 6692.874 | E86: =-E45*Inputs!$E$75/30 -> 9230.696 | F86: =-F45*Inputs!$E$75/30 -> 10301.414 | G86: =-G45*Inputs!$E$75/30 -> 11398.932 | H86: =-H45*Inputs!$E$75/30 -> 12522.178 | I86: =-I45*Inputs!$E$75/30 -> 13670.123 | J86: =-J45*Inputs!$E$75/30 -> 14841.779 | ... BJ86: =-BJ45*Inputs!$E$75/30 -> 25556.907
A87: (Increase) / decrease in receivables | C87: =-C84 -> -3196.2239 | D87: =C84-D84 -> -433.70519 | E87: =D84-E84 -> -1221.6311 | F87: =E84-F84 -> -551.8998 | G87: =F84-G84 -> -562.55851 | H87: =G84-H84 -> -572.79086 | I87: =H84-I84 -> -582.61392 | J87: =I84-J84 -> -592.04406 | K87: =J84-K84 -> -601.097 | ... BJ87: =BI84-BJ84 -> 1429.2221
A88: (Increase) / decrease in inventory | C88: =-C85 -> -3535.9729 | D88: =C85-D85 -> -479.75153 | E88: =D85-E85 -> -1522.6932 | F88: =E85-F85 -> -642.43081 | G88: =F85-G85 -> -658.5108 | H88: =G85-H85 -> -673.94759 | I88: =H85-I85 -> -688.7669 | J88: =I85-J85 -> -702.99345 | K88: =J85-K85 -> -716.65093 | ... BJ88: =BI85-BJ85 -> 3220.1603
A89: Increase / (decrease) in payables | C89: =C86 -> 5893.2881 | D89: =D86-C86 -> 799.58588 | E89: =E86-D86 -> 2537.822 | F89: =F86-E86 -> 1070.718 | G89: =G86-F86 -> 1097.518 | H89: =H86-G86 -> 1123.246 | I89: =I86-H86 -> 1147.9448 | J89: =J86-I86 -> 1171.6557 | K89: =K86-J86 -> 1194.4182 | ... BJ89: =BJ86-BI86 -> -5366.9338
A91: Cash flow
A92: Operating cash flow | C92: =C64-C73+C87+C88+C89 -> -74804.163 | D92: =D64-D73+D87+D88+D89 -> -68444.509 | E92: =E64-E73+E87+E88+E89 -> -53080.977 | F92: =F64-F73+F87+F88+F89 -> -45827.369 | G92: =G64-G73+G87+G88+G89 -> -38528.868 | H92: =H64-H73+H87+H88+H89 -> -31107.758 | I92: =I64-I73+I87+I88+I89 -> -23568.944 | J92: =J64-J73+J87+J88+J89 -> -15917.132 | ... BJ92: =BJ64-BJ73+BJ87+BJ88+BJ89 -> 51668.83
A93: Investing cash flow (capex) | C93: =-C71 -> -4100000 | D93: =-D71 -> 0 | E93: =-E71 -> 0 | F93: =-F71 -> 0 | G93: =-G71 -> 0 | H93: =-H71 -> 0 | I93: =-I71 -> 0 | J93: =-J71 -> 0 | ... BJ93: =-BJ71 -> 0
A94: Equity raised | C94: =IF(C$4=1,Inputs!$E$67,0) -> 2100000 | D94: =IF(D$4=1,Inputs!$E$67,0) -> 0 | E94: =IF(E$4=1,Inputs!$E$67,0) -> 0 | F94: =IF(F$4=1,Inputs!$E$67,0) -> 0 | G94: =IF(G$4=1,Inputs!$E$67,0) -> 0 | H94: =IF(H$4=1,Inputs!$E$67,0) -> 0 | I94: =IF(I$4=1,Inputs!$E$67,0) -> 0 | J94: =IF(J$4=1,Inputs!$E$67,0) -> 0 | ... BJ94: =IF(BJ$4=1,Inputs!$E$67,0) -> 0
A95: Financing cash flow | C95: =C94+C79+C80 -> 5100000 | D95: =D94+D79+D80 -> -25000 | E95: =E94+E79+E80 -> -25000 | F95: =F94+F79+F80 -> -25000 | G95: =G94+G79+G80 -> -25000 | H95: =H94+H79+H80 -> -25000 | I95: =I94+I79+I80 -> -25000 | J95: =J94+J79+J80 -> -25000 | ... BJ95: =BJ94+BJ79+BJ80 -> -25000
A96: Net cash flow | C96: =C92+C93+C95 -> 925195.84 | D96: =D92+D93+D95 -> -93444.509 | E96: =E92+E93+E95 -> -78080.977 | F96: =F92+F93+F95 -> -70827.369 | G96: =G92+G93+G95 -> -63528.868 | H96: =H92+H93+H95 -> -56107.758 | I96: =I92+I93+I95 -> -48568.944 | J96: =J92+J93+J95 -> -40917.132 | ... BJ96: =BJ92+BJ93+BJ95 -> 26668.83
A97: Opening cash | C97: =0 -> 0 | D97: =C98 -> 925195.84 | E97: =D98 -> 831751.33 | F97: =E98 -> 753670.35 | G97: =F98 -> 682842.98 | H97: =G98 -> 619314.11 | I97: =H98 -> 563206.36 | J97: =I98 -> 514637.41 | K97: =J98 -> 473720.28 | ... BJ97: =BI98 -> 861374.09
A98: Closing cash | C98: =C97+C96 -> 925195.84 | D98: =D97+D96 -> 831751.33 | E98: =E97+E96 -> 753670.35 | F98: =F97+F96 -> 682842.98 | G98: =G97+G96 -> 619314.11 | H98: =H97+H96 -> 563206.36 | I98: =I97+I96 -> 514637.41 | J98: =J97+J96 -> 473720.28 | ... BJ98: =BJ97+BJ96 -> 888042.92
A99: Helper: EBITDA positive (1/0) | C99: =IF(C55>0,1,0) -> 0 | D99: =IF(D55>0,1,0) -> 0 | E99: =IF(E55>0,1,0) -> 0 | F99: =IF(F55>0,1,0) -> 0 | G99: =IF(G55>0,1,0) -> 0 | H99: =IF(H55>0,1,0) -> 0 | I99: =IF(I55>0,1,0) -> 0 | J99: =IF(J55>0,1,0) -> 1 | ... BJ99: =IF(BJ55>0,1,0) -> 1
A101: Goal modules
A102: Helper: net income positive (1/0) | C102: =IF(C64>0,1,0) -> 0 | D102: =IF(D64>0,1,0) -> 0 | E102: =IF(E64>0,1,0) -> 0 | F102: =IF(F64>0,1,0) -> 0 | G102: =IF(G64>0,1,0) -> 0 | H102: =IF(H64>0,1,0) -> 0 | I102: =IF(I64>0,1,0) -> 0 | J102: =IF(J64>0,1,0) -> 0 | ... BJ102: =IF(BJ64>0,1,0) -> 1
A103: Cash flow before financing (operating + investing) | C103: =C92+C93 -> -4174804.2 | D103: =D92+D93 -> -68444.509 | E103: =E92+E93 -> -53080.977 | F103: =F92+F93 -> -45827.369 | G103: =G92+G93 -> -38528.868 | H103: =H92+H93 -> -31107.758 | I103: =I92+I93 -> -23568.944 | J103: =J92+J93 -> -15917.132 | ... BJ103: =BJ92+BJ93 -> 51668.83
A104: Cumulative cash flow before financing | C104: =C103 -> -4174804.2 | D104: =C104+D103 -> -4243248.7 | E104: =D104+E103 -> -4296329.6 | F104: =E104+F103 -> -4342157 | G104: =F104+G103 -> -4380685.9 | H104: =G104+H103 -> -4411793.6 | I104: =H104+I103 -> -4435362.6 | J104: =I104+J103 -> -4451279.7 | K104: =J104+K103 -> -4459436.6 | ... BJ104: =BI104+BJ103 -> -2736957.1
A105: Helper: lowest cumulative cash flow so far | C105: =C104 -> -4174804.2 | D105: =MIN(C105,D104) -> -4243248.7 | E105: =MIN(D105,E104) -> -4296329.6 | F105: =MIN(E105,F104) -> -4342157 | G105: =MIN(F105,G104) -> -4380685.9 | H105: =MIN(G105,H104) -> -4411793.6 | I105: =MIN(H105,I104) -> -4435362.6 | J105: =MIN(I105,J104) -> -4451279.7 | K105: =MIN(J105,K104) -> -4459436.6 | ... BJ105: =MIN(BI105,BJ104) -> -4524041
A106: Helper: investment paid back (1/0) | C106: =IF(AND(C104>=0,C105<0),1,0) -> 0 | D106: =IF(AND(D104>=0,D105<0),1,0) -> 0 | E106: =IF(AND(E104>=0,E105<0),1,0) -> 0 | F106: =IF(AND(F104>=0,F105<0),1,0) -> 0 | G106: =IF(AND(G104>=0,G105<0),1,0) -> 0 | H106: =IF(AND(H104>=0,H105<0),1,0) -> 0 | I106: =IF(AND(I104>=0,I105<0),1,0) -> 0 | J106: =IF(AND(J104>=0,J105<0),1,0) -> 0 | ... BJ106: =IF(AND(BJ104>=0,BJ105<0),1,0) -> 0
A107: Unlevered free cash flow (operating + after-tax interest − capex) | C107: =C92-C59*(1-Inputs!$E$79)+C93 -> -4158016.7 | D107: =D92-D59*(1-Inputs!$E$79)+D93 -> -51726.957 | E107: =E92-E59*(1-Inputs!$E$79)+E93 -> -36503.321 | F107: =F92-F59*(1-Inputs!$E$79)+F93 -> -29389.609 | G107: =G92-G59*(1-Inputs!$E$79)+G93 -> -22231.004 | H107: =H92-H59*(1-Inputs!$E$79)+H93 -> -14949.79 | I107: =I92-I59*(1-Inputs!$E$79)+I93 -> -7550.8706 | J107: =J92-J59*(1-Inputs!$E$79)+J93 -> -38.954833 | ... BJ107: =BJ92-BJ59*(1-Inputs!$E$79)+BJ93 -> 60272.424
A109: Balance sheet
A110: Paid-in capital | C110: =C94 -> 2100000 | D110: =C110+D94 -> 2100000 | E110: =D110+E94 -> 2100000 | F110: =E110+F94 -> 2100000 | G110: =F110+G94 -> 2100000 | H110: =G110+H94 -> 2100000 | I110: =H110+I94 -> 2100000 | J110: =I110+J94 -> 2100000 | K110: =J110+K94 -> 2100000 | ... BJ110: =BI110+BJ94 -> 2100000
A111: Retained earnings | C111: =C64 -> -102437.48 | D111: =C111+D64 -> -199240.34 | E111: =D111+E64 -> -280587.03 | F111: =E111+F64 -> -354763.01 | G111: =F111+G64 -> -421640.55 | H111: =G111+H64 -> -481097.04 | I111: =H111+I64 -> -533014.77 | J111: =I111+J64 -> -577280.74 | K111: =J111+K64 -> -613786.48 | ... BJ111: =BI111+BJ64 -> -216134.04
A112: Total assets | C112: =C98+C84+C85+C75 -> 5003455.8 | D112: =D98+D84+D85+D75 -> 4882452.5 | E112: =E98+E84+E85+E75 -> 4778643.7 | F112: =F98+F84+F85+F75 -> 4680538.4 | G112: =G98+G84+G85+G75 -> 4589758.4 | H112: =H98+H84+H85+H75 -> 4506425.1 | I112: =I98+I84+I85+I75 -> 4430655.4 | J112: =J98+J84+J85+J75 -> 4362561 | ... BJ112: =BJ98+BJ84+BJ85+BJ75 -> 3434422.9
A113: Total liabilities | C113: =C86+C81 -> 3005893.3 | D113: =D86+D81 -> 2981692.9 | E113: =E86+E81 -> 2959230.7 | F113: =F86+F81 -> 2935301.4 | G113: =G86+G81 -> 2911398.9 | H113: =H86+H81 -> 2887522.2 | I113: =I86+I81 -> 2863670.1 | J113: =J86+J81 -> 2839841.8 | ... BJ113: =BJ86+BJ81 -> 1550556.9
...

Sheet Headcount
A1: Headcount & payroll | D1: =HYPERLINK("#'Cover'!A1","◂ Contents") -> ◂ Contents
A2: $ unless stated; costs shown as negatives. Every period uses the same formula.
A3: Month | C3: M1 | D3: M2 | E3: M3 | F3: M4 | G3: M5 | H3: M6 | I3: M7 | J3: M8 | K3: M9 | L3: M10 | M3: M11 | N3: M12 | O3: M13 | P3: M14 | Q3: M15 | R3: M16 | S3: M17 | T3: M18 | U3: M19 | V3: M20 | W3: M21 | X3: M22 | Y3: M23 | Z3: M24 | AA3: M25 | AB3: M26 | AC3: M27 | AD3: M28 | AE3: M29 | AF3: M30 | AG3: M31 | AH3: M32 | AI3: M33 | AJ3: M34 | AK3: M35 | AL3: M36 | AM3: M37 | AN3: M38 | AO3: M39 | AP3: M40 | AQ3: M41 | AR3: M42 | AS3: M43 | AT3: M44 | AU3: M45 | AV3: M46 | AW3: M47 | AX3: M48 | AY3: M49 | AZ3: M50 | BA3: M51 | BB3: M52 | BC3: M53 | BD3: M54 | BE3: M55 | BF3: M56 | BG3: M57 | BH3: M58 | BI3: M59 | BJ3: M60
A4: Period # | C4: 1 | D4: 2 | E4: 3 | F4: 4 | G4: 5 | H4: 6 | I4: 7 | J4: 8 | K4: 9 | L4: 10 | M4: 11 | N4: 12 | O4: 13 | P4: 14 | Q4: 15 | R4: 16 | S4: 17 | T4: 18 | U4: 19 | V4: 20 | W4: 21 | X4: 22 | Y4: 23 | Z4: 24 | AA4: 25 | AB4: 26 | AC4: 27 | AD4: 28 | AE4: 29 | AF4: 30 | AG4: 31 | AH4: 32 | AI4: 33 | AJ4: 34 | AK4: 35 | AL4: 36 | AM4: 37 | AN4: 38 | AO4: 39 | AP4: 40 | AQ4: 41 | AR4: 42 | AS4: 43 | AT4: 44 | AU4: 45 | AV4: 46 | AW4: 47 | AX4: 48 | AY4: 49 | AZ4: 50 | BA4: 51 | BB4: 52 | BC4: 53 | BD4: 54 | BE4: 55 | BF4: 56 | BG4: 57 | BH4: 58 | BI4: 59 | BJ4: 60
A5: Year # | C5: =ROUNDUP(C4*1/12,0) -> 1 | D5: =ROUNDUP(D4*1/12,0) -> 1 | E5: =ROUNDUP(E4*1/12,0) -> 1 | F5: =ROUNDUP(F4*1/12,0) -> 1 | G5: =ROUNDUP(G4*1/12,0) -> 1 | H5: =ROUNDUP(H4*1/12,0) -> 1 | I5: =ROUNDUP(I4*1/12,0) -> 1 | J5: =ROUNDUP(J4*1/12,0) -> 1 | ... BJ5: =ROUNDUP(BJ4*1/12,0) -> 5
A7: Headcount (FTE)
A8: Site manager — FTE | C8: =Inputs!$E$55*(1+Inputs!$E$57)^(C$5-1)*MAX(0,MIN(1,C$4*1-Inputs!$E$58+1))/1 -> 1 | D8: =Inputs!$E$55*(1+Inputs!$E$57)^(D$5-1)*MAX(0,MIN(1,D$4*1-Inputs!$E$58+1))/1 -> 1 | E8: =Inputs!$E$55*(1+Inputs!$E$57)^(E$5-1)*MAX(0,MIN(1,E$4*1-Inputs!$E$58+1))/1 -> 1 | F8: =Inputs!$E$55*(1+Inputs!$E$57)^(F$5-1)*MAX(0,MIN(1,F$4*1-Inputs!$E$58+1))/1 -> 1 | G8: =Inputs!$E$55*(1+Inputs!$E$57)^(G$5-1)*MAX(0,MIN(1,G$4*1-Inputs!$E$58+1))/1 -> 1 | H8: =Inputs!$E$55*(1+Inputs!$E$57)^(H$5-1)*MAX(0,MIN(1,H$4*1-Inputs!$E$58+1))/1 -> 1 | I8: =Inputs!$E$55*(1+Inputs!$E$57)^(I$5-1)*MAX(0,MIN(1,I$4*1-Inputs!$E$58+1))/1 -> 1 | J8: =Inputs!$E$55*(1+Inputs!$E$57)^(J$5-1)*MAX(0,MIN(1,J$4*1-Inputs!$E$58+1))/1 -> 1 | ... BJ8: =Inputs!$E$55*(1+Inputs!$E$57)^(BJ$5-1)*MAX(0,MIN(1,BJ$4*1-Inputs!$E$58+1))/1 -> 1
A9: Wash attendants & customer service — FTE | C9: =Inputs!$E$59*(1+Inputs!$E$61)^(C$5-1)*MAX(0,MIN(1,C$4*1-Inputs!$E$62+1))/1 -> 10 | D9: =Inputs!$E$59*(1+Inputs!$E$61)^(D$5-1)*MAX(0,MIN(1,D$4*1-Inputs!$E$62+1))/1 -> 10 | E9: =Inputs!$E$59*(1+Inputs!$E$61)^(E$5-1)*MAX(0,MIN(1,E$4*1-Inputs!$E$62+1))/1 -> 10 | F9: =Inputs!$E$59*(1+Inputs!$E$61)^(F$5-1)*MAX(0,MIN(1,F$4*1-Inputs!$E$62+1))/1 -> 10 | G9: =Inputs!$E$59*(1+Inputs!$E$61)^(G$5-1)*MAX(0,MIN(1,G$4*1-Inputs!$E$62+1))/1 -> 10 | H9: =Inputs!$E$59*(1+Inputs!$E$61)^(H$5-1)*MAX(0,MIN(1,H$4*1-Inputs!$E$62+1))/1 -> 10 | I9: =Inputs!$E$59*(1+Inputs!$E$61)^(I$5-1)*MAX(0,MIN(1,I$4*1-Inputs!$E$62+1))/1 -> 10 | J9: =Inputs!$E$59*(1+Inputs!$E$61)^(J$5-1)*MAX(0,MIN(1,J$4*1-Inputs!$E$62+1))/1 -> 10 | ... BJ9: =Inputs!$E$59*(1+Inputs!$E$61)^(BJ$5-1)*MAX(0,MIN(1,BJ$4*1-Inputs!$E$62+1))/1 -> 10
A10: Total FTE | C10: =C8+C9 -> 11 | D10: =D8+D9 -> 11 | E10: =E8+E9 -> 11 | F10: =F8+F9 -> 11 | G10: =G8+G9 -> 11 | H10: =H8+H9 -> 11 | I10: =I8+I9 -> 11 | J10: =J8+J9 -> 11 | ... BJ10: =BJ8+BJ9 -> 11
A12: Payroll cost (salary + taxes & benefits)
A13: Site manager — payroll cost | C13: =-C8*Inputs!$E$56/12*1*(1+Inputs!$E$63)*(1+Inputs!$E$64)^(C$5-1) -> -6720 | D13: =-D8*Inputs!$E$56/12*1*(1+Inputs!$E$63)*(1+Inputs!$E$64)^(D$5-1) -> -6720 | E13: =-E8*Inputs!$E$56/12*1*(1+Inputs!$E$63)*(1+Inputs!$E$64)^(E$5-1) -> -6720 | F13: =-F8*Inputs!$E$56/12*1*(1+Inputs!$E$63)*(1+Inputs!$E$64)^(F$5-1) -> -6720 | G13: =-G8*Inputs!$E$56/12*1*(1+Inputs!$E$63)*(1+Inputs!$E$64)^(G$5-1) -> -6720 | H13: =-H8*Inputs!$E$56/12*1*(1+Inputs!$E$63)*(1+Inputs!$E$64)^(H$5-1) -> -6720 | I13: =-I8*Inputs!$E$56/12*1*(1+Inputs!$E$63)*(1+Inputs!$E$64)^(I$5-1) -> -6720 | J13: =-J8*Inputs!$E$56/12*1*(1+Inputs!$E$63)*(1+Inputs!$E$64)^(J$5-1) -> -6720 | ... BJ13: =-BJ8*Inputs!$E$56/12*1*(1+Inputs!$E$63)*(1+Inputs!$E$64)^(BJ$5-1) -> -7563.4192
A14: Wash attendants & customer service — payroll cost | C14: =-C9*Inputs!$E$60/12*1*(1+Inputs!$E$63)*(1+Inputs!$E$64)^(C$5-1) -> -29866.667 | D14: =-D9*Inputs!$E$60/12*1*(1+Inputs!$E$63)*(1+Inputs!$E$64)^(D$5-1) -> -29866.667 | E14: =-E9*Inputs!$E$60/12*1*(1+Inputs!$E$63)*(1+Inputs!$E$64)^(E$5-1) -> -29866.667 | F14: =-F9*Inputs!$E$60/12*1*(1+Inputs!$E$63)*(1+Inputs!$E$64)^(F$5-1) -> -29866.667 | G14: =-G9*Inputs!$E$60/12*1*(1+Inputs!$E$63)*(1+Inputs!$E$64)^(G$5-1) -> -29866.667 | H14: =-H9*Inputs!$E$60/12*1*(1+Inputs!$E$63)*(1+Inputs!$E$64)^(H$5-1) -> -29866.667 | I14: =-I9*Inputs!$E$60/12*1*(1+Inputs!$E$63)*(1+Inputs!$E$64)^(I$5-1) -> -29866.667 | J14: =-J9*Inputs!$E$60/12*1*(1+Inputs!$E$63)*(1+Inputs!$E$64)^(J$5-1) -> -29866.667 | ... BJ14: =-BJ9*Inputs!$E$60/12*1*(1+Inputs!$E$63)*(1+Inputs!$E$64)^(BJ$5-1) -> -33615.196
A15: Total payroll | C15: =C13+C14 -> -36586.667 | D15: =D13+D14 -> -36586.667 | E15: =E13+E14 -> -36586.667 | F15: =F13+F14 -> -36586.667 | G15: =G13+G14 -> -36586.667 | H15: =H13+H14 -> -36586.667 | I15: =I13+I14 -> -36586.667 | J15: =J13+J14 -> -36586.667 | ... BJ15: =BJ13+BJ14 -> -41178.616

Sheet Scenario calc
A1: Scenario calculation — Low, Base and High side by side | D1: =HYPERLINK("#'Cover'!A1","◂ Contents") -> ◂ Contents
A2: The model's period calculation, copied three times; each copy reads its own Inputs column. Feeds the Scenarios sheet only.
A4: Low scenario — reads Inputs column B
A5: Month | C5: M1 | D5: M2 | E5: M3 | F5: M4 | G5: M5 | H5: M6 | I5: M7 | J5: M8 | K5: M9 | L5: M10 | M5: M11 | N5: M12 | O5: M13 | P5: M14 | Q5: M15 | R5: M16 | S5: M17 | T5: M18 | U5: M19 | V5: M20 | W5: M21 | X5: M22 | Y5: M23 | Z5: M24 | AA5: M25 | AB5: M26 | AC5: M27 | AD5: M28 | AE5: M29 | AF5: M30 | AG5: M31 | AH5: M32 | AI5: M33 | AJ5: M34 | AK5: M35 | AL5: M36 | AM5: M37 | AN5: M38 | AO5: M39 | AP5: M40 | AQ5: M41 | AR5: M42 | AS5: M43 | AT5: M44 | AU5: M45 | AV5: M46 | AW5: M47 | AX5: M48 | AY5: M49 | AZ5: M50 | BA5: M51 | BB5: M52 | BC5: M53 | BD5: M54 | BE5: M55 | BF5: M56 | BG5: M57 | BH5: M58 | BI5: M59 | BJ5: M60
A6: Period # | C6: 1 | D6: 2 | E6: 3 | F6: 4 | G6: 5 | H6: 6 | I6: 7 | J6: 8 | K6: 9 | L6: 10 | M6: 11 | N6: 12 | O6: 13 | P6: 14 | Q6: 15 | R6: 16 | S6: 17 | T6: 18 | U6: 19 | V6: 20 | W6: 21 | X6: 22 | Y6: 23 | Z6: 24 | AA6: 25 | AB6: 26 | AC6: 27 | AD6: 28 | AE6: 29 | AF6: 30 | AG6: 31 | AH6: 32 | AI6: 33 | AJ6: 34 | AK6: 35 | AL6: 36 | AM6: 37 | AN6: 38 | AO6: 39 | AP6: 40 | AQ6: 41 | AR6: 42 | AS6: 43 | AT6: 44 | AU6: 45 | AV6: 46 | AW6: 47 | AX6: 48 | AY6: 49 | AZ6: 50 | BA6: 51 | BB6: 52 | BC6: 53 | BD6: 54 | BE6: 55 | BF6: 56 | BG6: 57 | BH6: 58 | BI6: 59 | BJ6: 60
A7: Year # | C7: =ROUNDUP(C6*1/12,0) -> 1 | D7: =ROUNDUP(D6*1/12,0) -> 1 | E7: =ROUNDUP(E6*1/12,0) -> 1 | F7: =ROUNDUP(F6*1/12,0) -> 1 | G7: =ROUNDUP(G6*1/12,0) -> 1 | H7: =ROUNDUP(H6*1/12,0) -> 1 | I7: =ROUNDUP(I6*1/12,0) -> 1 | J7: =ROUNDUP(J6*1/12,0) -> 1 | ... BJ7: =ROUNDUP(BJ6*1/12,0) -> 5
A9: Volume
A10: Helper: months of the period still on the ramp-up | C10: =MAX(0,MIN(1,Inputs!$B$9-(C$6-1)*1)) -> 1 | D10: =MAX(0,MIN(1,Inputs!$B$9-(D$6-1)*1)) -> 1 | E10: =MAX(0,MIN(1,Inputs!$B$9-(E$6-1)*1)) -> 1 | F10: =MAX(0,MIN(1,Inputs!$B$9-(F$6-1)*1)) -> 1 | G10: =MAX(0,MIN(1,Inputs!$B$9-(G$6-1)*1)) -> 1 | H10: =MAX(0,MIN(1,Inputs!$B$9-(H$6-1)*1)) -> 1 | I10: =MAX(0,MIN(1,Inputs!$B$9-(I$6-1)*1)) -> 1 | J10: =MAX(0,MIN(1,Inputs!$B$9-(J$6-1)*1)) -> 1 | ... BJ10: =MAX(0,MIN(1,Inputs!$B$9-(BJ$6-1)*1)) -> 0
A11: Ramp-up factor (share of mature retail volume) | C11: =IF(Inputs!$B$9<=0,1,(C10*Inputs!$B$10+(1-Inputs!$B$10)/MAX(1,Inputs!$B$9)*(C10*(C$6-1)*1+C10*(C10-1)/2)+1-C10)/1) -> 0.35 | D11: =IF(Inputs!$B$9<=0,1,(D10*Inputs!$B$10+(1-Inputs!$B$10)/MAX(1,Inputs!$B$9)*(D10*(D$6-1)*1+D10*(D10-1)/2)+1-D10)/1) -> 0.40416667 | E11: =IF(Inputs!$B$9<=0,1,(E10*Inputs!$B$10+(1-Inputs!$B$10)/MAX(1,Inputs!$B$9)*(E10*(E$6-1)*1+E10*(E10-1)/2)+1-E10)/1) -> 0.45833333 | F11: =IF(Inputs!$B$9<=0,1,(F10*Inputs!$B$10+(1-Inputs!$B$10)/MAX(1,Inputs!$B$9)*(F10*(F$6-1)*1+F10*(F10-1)/2)+1-F10)/1) -> 0.5125 | G11: =IF(Inputs!$B$9<=0,1,(G10*Inputs!$B$10+(1-Inputs!$B$10)/MAX(1,Inputs!$B$9)*(G10*(G$6-1)*1+G10*(G10-1)/2)+1-G10)/1) -> 0.56666667 | H11: =IF(Inputs!$B$9<=0,1,(H10*Inputs!$B$10+(1-Inputs!$B$10)/MAX(1,Inputs!$B$9)*(H10*(H$6-1)*1+H10*(H10-1)/2)+1-H10)/1) -> 0.62083333 | I11: =IF(Inputs!$B$9<=0,1,(I10*Inputs!$B$10+(1-Inputs!$B$10)/MAX(1,Inputs!$B$9)*(I10*(I$6-1)*1+I10*(I10-1)/2)+1-I10)/1) -> 0.675 | J11: =IF(Inputs!$B$9<=0,1,(J10*Inputs!$B$10+(1-Inputs!$B$10)/MAX(1,Inputs!$B$9)*(J10*(J$6-1)*1+J10*(J10-1)/2)+1-J10)/1) -> 0.72916667 | ... BJ11: =IF(Inputs!$B$9<=0,1,(BJ10*Inputs!$B$10+(1-Inputs!$B$10)/MAX(1,Inputs!$B$9)*(BJ10*(BJ$6-1)*1+BJ10*(BJ10-1)/2)+1-BJ10)/1) -> 1
A12: Season factor (winter dip) | C12: =IF(OR(MOD(C$6-1,12)>=11,MOD(C$6-1,12)<=1),1-Inputs!$B$11,1+Inputs!$B$11/3) -> 0.8 | D12: =IF(OR(MOD(D$6-1,12)>=11,MOD(D$6-1,12)<=1),1-Inputs!$B$11,1+Inputs!$B$11/3) -> 0.8 | E12: =IF(OR(MOD(E$6-1,12)>=11,MOD(E$6-1,12)<=1),1-Inputs!$B$11,1+Inputs!$B$11/3) -> 1.0666667 | F12: =IF(OR(MOD(F$6-1,12)>=11,MOD(F$6-1,12)<=1),1-Inputs!$B$11,1+Inputs!$B$11/3) -> 1.0666667 | G12: =IF(OR(MOD(G$6-1,12)>=11,MOD(G$6-1,12)<=1),1-Inputs!$B$11,1+Inputs!$B$11/3) -> 1.0666667 | H12: =IF(OR(MOD(H$6-1,12)>=11,MOD(H$6-1,12)<=1),1-Inputs!$B$11,1+Inputs!$B$11/3) -> 1.0666667 | I12: =IF(OR(MOD(I$6-1,12)>=11,MOD(I$6-1,12)<=1),1-Inputs!$B$11,1+Inputs!$B$11/3) -> 1.0666667 | J12: =IF(OR(MOD(J$6-1,12)>=11,MOD(J$6-1,12)<=1),1-Inputs!$B$11,1+Inputs!$B$11/3) -> 1.0666667 | ... BJ12: =IF(OR(MOD(BJ$6-1,12)>=11,MOD(BJ$6-1,12)<=1),1-Inputs!$B$11,1+Inputs!$B$11/3) -> 0.8
A13: Retail cars demanded | C13: =Inputs!$B$7*Inputs!$B$8*1*C11*C12 -> 1624 | D13: =Inputs!$B$7*Inputs!$B$8*1*D11*D12 -> 1875.3333 | E13: =Inputs!$B$7*Inputs!$B$8*1*E11*E12 -> 2835.5556 | F13: =Inputs!$B$7*Inputs!$B$8*1*F11*F12 -> 3170.6667 | G13: =Inputs!$B$7*Inputs!$B$8*1*G11*G12 -> 3505.7778 | H13: =Inputs!$B$7*Inputs!$B$8*1*H11*H12 -> 3840.8889 | I13: =Inputs!$B$7*Inputs!$B$8*1*I11*I12 -> 4176 | J13: =Inputs!$B$7*Inputs!$B$8*1*J11*J12 -> 4511.1111 | ... BJ13: =Inputs!$B$7*Inputs!$B$8*1*BJ11*BJ12 -> 4640
A15: Members
A16: New members from retail cars | C16: =C13*Inputs!$B$22 -> 9.744 | D16: =D13*Inputs!$B$22 -> 11.252 | E16: =E13*Inputs!$B$22 -> 17.013333 | F16: =F13*Inputs!$B$22 -> 19.024 | G16: =G13*Inputs!$B$22 -> 21.034667 | H16: =H13*Inputs!$B$22 -> 23.045333 | I16: =I13*Inputs!$B$22 -> 25.056 | J16: =J13*Inputs!$B$22 -> 27.066667 | ... BJ16: =BJ13*Inputs!$B$22 -> 27.84
A17: New members from direct sign-ups | C17: =Inputs!$B$20*(1+Inputs!$B$21)^(C$7-1)*1*C11 -> 14 | D17: =Inputs!$B$20*(1+Inputs!$B$21)^(D$7-1)*1*D11 -> 16.166667 | E17: =Inputs!$B$20*(1+Inputs!$B$21)^(E$7-1)*1*E11 -> 18.333333 | F17: =Inputs!$B$20*(1+Inputs!$B$21)^(F$7-1)*1*F11 -> 20.5 | G17: =Inputs!$B$20*(1+Inputs!$B$21)^(G$7-1)*1*G11 -> 22.666667 | H17: =Inputs!$B$20*(1+Inputs!$B$21)^(H$7-1)*1*H11 -> 24.833333 | I17: =Inputs!$B$20*(1+Inputs!$B$21)^(I$7-1)*1*I11 -> 27 | J17: =Inputs!$B$20*(1+Inputs!$B$21)^(J$7-1)*1*J11 -> 29.166667 | ... BJ17: =Inputs!$B$20*(1+Inputs!$B$21)^(BJ$7-1)*1*BJ11 -> 40
A18: New members - total | C18: =C16+C17 -> 23.744 | D18: =D16+D17 -> 27.418667 | E18: =E16+E17 -> 35.346667 | F18: =F16+F17 -> 39.524 | G18: =G16+G17 -> 43.701333 | H18: =H16+H17 -> 47.878667 | I18: =I16+I17 -> 52.056 | J18: =J16+J17 -> 56.233333 | ... BJ18: =BJ16+BJ17 -> 67.84
A19: Members - opening | C19: =Inputs!$B$19 -> 150 | D19: =C21 -> 166.244 | E19: =D21 -> 185.35047 | F19: =E21 -> 211.42961 | G19: =F21 -> 240.38213 | H19: =G21 -> 272.06436 | I19: =H21 -> 306.33981 | J19: =I21 -> 343.07881 | K19: =J21 -> 382.15821 | ... BJ19: =BI21 -> 1421.0439
A20: Members who cancelled | C20: =C21-C19-C18 -> -7.5 | D20: =D21-D19-D18 -> -8.3122 | E20: =E21-E19-E18 -> -9.2675233 | F20: =F21-F19-F18 -> -10.57148 | G20: =G21-G19-G18 -> -12.019106 | H20: =H21-H19-H18 -> -13.603218 | I20: =I21-I19-I18 -> -15.31699 | J20: =J21-J19-J18 -> -17.153941 | ... BJ20: =BJ21-BJ19-BJ18 -> -71.052197
A21: Members - closing | C21: =C19*(1-Inputs!$B$23)+C18 -> 166.244 | D21: =D19*(1-Inputs!$B$23)+D18 -> 185.35047 | E21: =E19*(1-Inputs!$B$23)+E18 -> 211.42961 | F21: =F19*(1-Inputs!$B$23)+F18 -> 240.38213 | G21: =G19*(1-Inputs!$B$23)+G18 -> 272.06436 | H21: =H19*(1-Inputs!$B$23)+H18 -> 306.33981 | I21: =I19*(1-Inputs!$B$23)+I18 -> 343.07881 | J21: =J19*(1-Inputs!$B$23)+J18 -> 382.15821 | ... BJ21: =BJ19*(1-Inputs!$B$23)+BJ18 -> 1417.8317
A22: Members - average | C22: =(C19+C21)/2 -> 158.122 | D22: =(D19+D21)/2 -> 175.79723 | E22: =(E19+E21)/2 -> 198.39004 | F22: =(F19+F21)/2 -> 225.90587 | G22: =(G19+G21)/2 -> 256.22324 | H22: =(H19+H21)/2 -> 289.20208 | I22: =(I19+I21)/2 -> 324.70931 | J22: =(J19+J21)/2 -> 362.61851 | ... BJ22: =(BJ19+BJ21)/2 -> 1419.4378
A24: Washes
A25: Member washes demanded | C25: =C22*Inputs!$B$24*C12*1 -> 480.69088 | D25: =D22*Inputs!$B$24*D12*1 -> 534.42359 | E25: =E22*Inputs!$B$24*E12*1 -> 804.14096 | F25: =F22*Inputs!$B$24*F12*1 -> 915.67179 | G25: =G22*Inputs!$B$24*G12*1 -> 1038.5582 | H25: =H22*Inputs!$B$24*H12*1 -> 1172.2324 | I25: =I22*Inputs!$B$24*I12*1 -> 1316.1551 | J25: =J22*Inputs!$B$24*J12*1 -> 1469.8137 | ... BJ25: =BJ22*Inputs!$B$24*BJ12*1 -> 4315.091
A26: Tunnel capacity (rated speed × hours × practical share × days) | C26: =Inputs!$B$14*Inputs!$B$15*Inputs!$B$16*Inputs!$B$8*1 -> 24563 | D26: =Inputs!$B$14*Inputs!$B$15*Inputs!$B$16*Inputs!$B$8*1 -> 24563 | E26: =Inputs!$B$14*Inputs!$B$15*Inputs!$B$16*Inputs!$B$8*1 -> 24563 | F26: =Inputs!$B$14*Inputs!$B$15*Inputs!$B$16*Inputs!$B$8*1 -> 24563 | G26: =Inputs!$B$14*Inputs!$B$15*Inputs!$B$16*Inputs!$B$8*1 -> 24563 | H26: =Inputs!$B$14*Inputs!$B$15*Inputs!$B$16*Inputs!$B$8*1 -> 24563 | I26: =Inputs!$B$14*Inputs!$B$15*Inputs!$B$16*Inputs!$B$8*1 -> 24563 | J26: =Inputs!$B$14*Inputs!$B$15*Inputs!$B$16*Inputs!$B$8*1 -> 24563 | ... BJ26: =Inputs!$B$14*Inputs!$B$15*Inputs!$B$16*Inputs!$B$8*1 -> 24563
A27: Share of demand the tunnel can wash | C27: =MIN(1,C26/MAX(1,C13+C25)) -> 1 | D27: =MIN(1,D26/MAX(1,D13+D25)) -> 1 | E27: =MIN(1,E26/MAX(1,E13+E25)) -> 1 | F27: =MIN(1,F26/MAX(1,F13+F25)) -> 1 | G27: =MIN(1,G26/MAX(1,G13+G25)) -> 1 | H27: =MIN(1,H26/MAX(1,H13+H25)) -> 1 | I27: =MIN(1,I26/MAX(1,I13+I25)) -> 1 | J27: =MIN(1,J26/MAX(1,J13+J25)) -> 1 | ... BJ27: =MIN(1,BJ26/MAX(1,BJ13+BJ25)) -> 1
A28: Retail cars washed | C28: =C13*C27 -> 1624 | D28: =D13*D27 -> 1875.3333 | E28: =E13*E27 -> 2835.5556 | F28: =F13*F27 -> 3170.6667 | G28: =G13*G27 -> 3505.7778 | H28: =H13*H27 -> 3840.8889 | I28: =I13*I27 -> 4176 | J28: =J13*J27 -> 4511.1111 | ... BJ28: =BJ13*BJ27 -> 4640
A29: Member washes | C29: =C25*C27 -> 480.69088 | D29: =D25*D27 -> 534.42359 | E29: =E25*E27 -> 804.14096 | F29: =F25*F27 -> 915.67179 | G29: =G25*G27 -> 1038.5582 | H29: =H25*H27 -> 1172.2324 | I29: =I25*I27 -> 1316.1551 | J29: =J25*J27 -> 1469.8137 | ... BJ29: =BJ25*BJ27 -> 4315.091
A30: Washes - total | C30: =C28+C29 -> 2104.6909 | D30: =D28+D29 -> 2409.7569 | E30: =E28+E29 -> 3639.6965 | F30: =F28+F29 -> 4086.3385 | G30: =G28+G29 -> 4544.336 | H30: =H28+H29 -> 5013.1213 | I30: =I28+I29 -> 5492.1551 | J30: =J28+J29 -> 5980.9248 | ... BJ30: =BJ28+BJ29 -> 8955.091
A31: Washes lost to the capacity limit | C31: =C13+C25-C30 -> 0 | D31: =D13+D25-D30 -> 0 | E31: =E13+E25-E30 -> 0 | F31: =F13+F25-F30 -> 0 | G31: =G13+G25-G30 -> 0 | H31: =H13+H25-H30 -> 0 | I31: =I13+I25-I30 -> 0 | J31: =J13+J25-J30 -> 0 | ... BJ31: =BJ13+BJ25-BJ30 -> 0
A33: Revenue
A34: Average price per retail wash | C34: =Inputs!$B$27*(1+Inputs!$B$30)^(C$7-1) -> 12 | D34: =Inputs!$B$27*(1+Inputs!$B$30)^(D$7-1) -> 12 | E34: =Inputs!$B$27*(1+Inputs!$B$30)^(E$7-1) -> 12 | F34: =Inputs!$B$27*(1+Inputs!$B$30)^(F$7-1) -> 12 | G34: =Inputs!$B$27*(1+Inputs!$B$30)^(G$7-1) -> 12 | H34: =Inputs!$B$27*(1+Inputs!$B$30)^(H$7-1) -> 12 | I34: =Inputs!$B$27*(1+Inputs!$B$30)^(I$7-1) -> 12 | J34: =Inputs!$B$27*(1+Inputs!$B$30)^(J$7-1) -> 12 | ... BJ34: =Inputs!$B$27*(1+Inputs!$B$30)^(BJ$7-1) -> 12.487248
A35: Unlimited plan fee per month | C35: =Inputs!$B$29*(1+Inputs!$B$30)^(C$7-1) -> 32 | D35: =Inputs!$B$29*(1+Inputs!$B$30)^(D$7-1) -> 32 | E35: =Inputs!$B$29*(1+Inputs!$B$30)^(E$7-1) -> 32 | F35: =Inputs!$B$29*(1+Inputs!$B$30)^(F$7-1) -> 32 | G35: =Inputs!$B$29*(1+Inputs!$B$30)^(G$7-1) -> 32 | H35: =Inputs!$B$29*(1+Inputs!$B$30)^(H$7-1) -> 32 | I35: =Inputs!$B$29*(1+Inputs!$B$30)^(I$7-1) -> 32 | J35: =Inputs!$B$29*(1+Inputs!$B$30)^(J$7-1) -> 32 | ... BJ35: =Inputs!$B$29*(1+Inputs!$B$30)^(BJ$7-1) -> 33.299328
A36: Retail wash revenue | C36: =C28*C34 -> 19488 | D36: =D28*D34 -> 22504 | E36: =E28*E34 -> 34026.667 | F36: =F28*F34 -> 38048 | G36: =G28*G34 -> 42069.333 | H36: =H28*H34 -> 46090.667 | I36: =I28*I34 -> 50112 | J36: =J28*J34 -> 54133.333 | ... BJ36: =BJ28*BJ34 -> 57940.831
A37: Add-on revenue | C37: =C28*Inputs!$B$28*(1+Inputs!$B$30)^(C$7-1) -> 1948.8 | D37: =D28*Inputs!$B$28*(1+Inputs!$B$30)^(D$7-1) -> 2250.4 | E37: =E28*Inputs!$B$28*(1+Inputs!$B$30)^(E$7-1) -> 3402.6667 | F37: =F28*Inputs!$B$28*(1+Inputs!$B$30)^(F$7-1) -> 3804.8 | G37: =G28*Inputs!$B$28*(1+Inputs!$B$30)^(G$7-1) -> 4206.9333 | H37: =H28*Inputs!$B$28*(1+Inputs!$B$30)^(H$7-1) -> 4609.0667 | I37: =I28*Inputs!$B$28*(1+Inputs!$B$30)^(I$7-1) -> 5011.2 | J37: =J28*Inputs!$B$28*(1+Inputs!$B$30)^(J$7-1) -> 5413.3333 | ... BJ37: =BJ28*Inputs!$B$28*(1+Inputs!$B$30)^(BJ$7-1) -> 5794.0831
A38: Unlimited plan fees | C38: =C22*C35*1 -> 5059.904 | D38: =D22*D35*1 -> 5625.5115 | E38: =E22*E35*1 -> 6348.4812 | F38: =F22*F35*1 -> 7228.9878 | G38: =G22*G35*1 -> 8199.1438 | H38: =H22*H35*1 -> 9254.4666 | I38: =I22*I35*1 -> 10390.698 | J38: =J22*J35*1 -> 11603.792 | ... BJ38: =BJ22*BJ35*1 -> 47266.327
A39: Revenue | C39: =C36+C37+C38 -> 26496.704 | D39: =D36+D37+D38 -> 30379.911 | E39: =E36+E37+E38 -> 43777.815 | F39: =F36+F37+F38 -> 49081.788 | G39: =G36+G37+G38 -> 54475.41 | H39: =H36+H37+H38 -> 59954.2 | I39: =I36+I37+I38 -> 65513.898 | J39: =J36+J37+J38 -> 71150.459 | ... BJ39: =BJ36+BJ37+BJ38 -> 111001.24
A41: Cost of sales
A42: Chemicals | C42: =-C30*Inputs!$B$33*(1+Inputs!$B$38)^(C$7-1) -> -1999.4563 | D42: =-D30*Inputs!$B$33*(1+Inputs!$B$38)^(D$7-1) -> -2289.2691 | E42: =-E30*Inputs!$B$33*(1+Inputs!$B$38)^(E$7-1) -> -3457.7117 | F42: =-F30*Inputs!$B$33*(1+Inputs!$B$38)^(F$7-1) -> -3882.0215 | G42: =-G30*Inputs!$B$33*(1+Inputs!$B$38)^(G$7-1) -> -4317.1192 | H42: =-H30*Inputs!$B$33*(1+Inputs!$B$38)^(H$7-1) -> -4762.4653 | I42: =-I30*Inputs!$B$33*(1+Inputs!$B$38)^(I$7-1) -> -5217.5473 | J42: =-J30*Inputs!$B$33*(1+Inputs!$B$38)^(J$7-1) -> -5681.8786 | ... BJ42: =-BJ30*Inputs!$B$33*(1+Inputs!$B$38)^(BJ$7-1) -> -9952.3804
A43: Water & sewer | C43: =-C30*Inputs!$B$34/1000*Inputs!$B$35*(1+Inputs!$B$38)^(C$7-1) -> -947.1109 | D43: =-D30*Inputs!$B$34/1000*Inputs!$B$35*(1+Inputs!$B$38)^(D$7-1) -> -1084.3906 | E43: =-E30*Inputs!$B$34/1000*Inputs!$B$35*(1+Inputs!$B$38)^(E$7-1) -> -1637.8634 | F43: =-F30*Inputs!$B$34/1000*Inputs!$B$35*(1+Inputs!$B$38)^(F$7-1) -> -1838.8523 | G43: =-G30*Inputs!$B$34/1000*Inputs!$B$35*(1+Inputs!$B$38)^(G$7-1) -> -2044.9512 | H43: =-H30*Inputs!$B$34/1000*Inputs!$B$35*(1+Inputs!$B$38)^(H$7-1) -> -2255.9046 | I43: =-I30*Inputs!$B$34/1000*Inputs!$B$35*(1+Inputs!$B$38)^(I$7-1) -> -2471.4698 | J43: =-J30*Inputs!$B$34/1000*Inputs!$B$35*(1+Inputs!$B$38)^(J$7-1) -> -2691.4162 | ... BJ43: =-BJ30*Inputs!$B$34/1000*Inputs!$B$35*(1+Inputs!$B$38)^(BJ$7-1) -> -4714.2854
A44: Electricity | C44: =-C30*Inputs!$B$36*(1+Inputs!$B$38)^(C$7-1) -> -947.1109 | D44: =-D30*Inputs!$B$36*(1+Inputs!$B$38)^(D$7-1) -> -1084.3906 | E44: =-E30*Inputs!$B$36*(1+Inputs!$B$38)^(E$7-1) -> -1637.8634 | F44: =-F30*Inputs!$B$36*(1+Inputs!$B$38)^(F$7-1) -> -1838.8523 | G44: =-G30*Inputs!$B$36*(1+Inputs!$B$38)^(G$7-1) -> -2044.9512 | H44: =-H30*Inputs!$B$36*(1+Inputs!$B$38)^(H$7-1) -> -2255.9046 | I44: =-I30*Inputs!$B$36*(1+Inputs!$B$38)^(I$7-1) -> -2471.4698 | J44: =-J30*Inputs!$B$36*(1+Inputs!$B$38)^(J$7-1) -> -2691.4162 | ... BJ44: =-BJ30*Inputs!$B$36*(1+Inputs!$B$38)^(BJ$7-1) -> -4714.2854
A45: Chemicals, water & electricity | C45: =C42+C43+C44 -> -3893.6781 | D45: =D42+D43+D44 -> -4458.0503 | E45: =E42+E43+E44 -> -6733.4385 | F45: =F42+F43+F44 -> -7559.7261 | G45: =G42+G43+G44 -> -8407.0216 | H45: =H42+H43+H44 -> -9274.2744 | I45: =I42+I43+I44 -> -10160.487 | J45: =J42+J43+J44 -> -11064.711 | ... BJ45: =BJ42+BJ43+BJ44 -> -19380.951
A46: Card processing fees | C46: =-C39*Inputs!$B$37 -> -847.89453 | D46: =-D39*Inputs!$B$37 -> -972.15717 | E46: =-E39*Inputs!$B$37 -> -1400.8901 | F46: =-F39*Inputs!$B$37 -> -1570.6172 | G46: =-G39*Inputs!$B$37 -> -1743.2131 | H46: =-H39*Inputs!$B$37 -> -1918.5344 | I46: =-I39*Inputs!$B$37 -> -2096.4447 | J46: =-J39*Inputs!$B$37 -> -2276.8147 | ... BJ46: =-BJ39*Inputs!$B$37 -> -3552.0397
A47: Cost of sales | C47: =C45+C46 -> -4741.5727 | D47: =D45+D46 -> -5430.2075 | E47: =E45+E46 -> -8134.3286 | F47: =F45+F46 -> -9130.3434 | G47: =G45+G46 -> -10150.235 | H47: =H45+H46 -> -11192.809 | I47: =I45+I46 -> -12256.932 | J47: =J45+J46 -> -13341.526 | ... BJ47: =BJ45+BJ46 -> -22932.991
A48: Gross profit | C48: =C39+C47 -> 21755.131 | D48: =D39+D47 -> 24949.704 | E48: =E39+E47 -> 35643.486 | F48: =F39+F47 -> 39951.444 | G48: =G39+G47 -> 44325.176 | H48: =H39+H47 -> 48761.391 | I48: =I39+I47 -> 53256.966 | J48: =J39+J47 -> 57808.933 | ... BJ48: =BJ39+BJ47 -> 88068.25
A50: Operating expenses
A51: Site payroll | C51: =C128 -> -36586.667 | D51: =D128 -> -36586.667 | E51: =E128 -> -36586.667 | F51: =F128 -> -36586.667 | G51: =G128 -> -36586.667 | H51: =H128 -> -36586.667 | I51: =I128 -> -36586.667 | J51: =J128 -> -36586.667 | ... BJ51: =BJ128 -> -41178.616
A52: Site lease or land cost | C52: =-Inputs!$B$41*(1+Inputs!$B$42)^(C$7-1)*1 -> -30000 | D52: =-Inputs!$B$41*(1+Inputs!$B$42)^(D$7-1)*1 -> -30000 | E52: =-Inputs!$B$41*(1+Inputs!$B$42)^(E$7-1)*1 -> -30000 | F52: =-Inputs!$B$41*(1+Inputs!$B$42)^(F$7-1)*1 -> -30000 | G52: =-Inputs!$B$41*(1+Inputs!$B$42)^(G$7-1)*1 -> -30000 | H52: =-Inputs!$B$41*(1+Inputs!$B$42)^(H$7-1)*1 -> -30000 | I52: =-Inputs!$B$41*(1+Inputs!$B$42)^(I$7-1)*1 -> -30000 | J52: =-Inputs!$B$41*(1+Inputs!$B$42)^(J$7-1)*1 -> -30000 | ... BJ52: =-Inputs!$B$41*(1+Inputs!$B$42)^(BJ$7-1)*1 -> -33765.264
A53: Equipment maintenance & repairs | C53: =-Inputs!$B$43*(1+Inputs!$B$38)^(C$7-1)*1 -> -5500 | D53: =-Inputs!$B$43*(1+Inputs!$B$38)^(D$7-1)*1 -> -5500 | E53: =-Inputs!$B$43*(1+Inputs!$B$38)^(E$7-1)*1 -> -5500 | F53: =-Inputs!$B$43*(1+Inputs!$B$38)^(F$7-1)*1 -> -5500 | G53: =-Inputs!$B$43*(1+Inputs!$B$38)^(G$7-1)*1 -> -5500 | H53: =-Inputs!$B$43*(1+Inputs!$B$38)^(H$7-1)*1 -> -5500 | I53: =-Inputs!$B$43*(1+Inputs!$B$38)^(I$7-1)*1 -> -5500 | J53: =-Inputs!$B$43*(1+Inputs!$B$38)^(J$7-1)*1 -> -5500 | ... BJ53: =-Inputs!$B$43*(1+Inputs!$B$38)^(BJ$7-1)*1 -> -6434.2221
A54: Insurance, property tax, software & other | C54: =-Inputs!$B$44*(1+Inputs!$B$38)^(C$7-1)*1 -> -9500 | D54: =-Inputs!$B$44*(1+Inputs!$B$38)^(D$7-1)*1 -> -9500 | E54: =-Inputs!$B$44*(1+Inputs!$B$38)^(E$7-1)*1 -> -9500 | F54: =-Inputs!$B$44*(1+Inputs!$B$38)^(F$7-1)*1 -> -9500 | G54: =-Inputs!$B$44*(1+Inputs!$B$38)^(G$7-1)*1 -> -9500 | H54: =-Inputs!$B$44*(1+Inputs!$B$38)^(H$7-1)*1 -> -9500 | I54: =-Inputs!$B$44*(1+Inputs!$B$38)^(I$7-1)*1 -> -9500 | J54: =-Inputs!$B$44*(1+Inputs!$B$38)^(J$7-1)*1 -> -9500 | ... BJ54: =-Inputs!$B$44*(1+Inputs!$B$38)^(BJ$7-1)*1 -> -11113.656
A55: Marketing | C55: =-Inputs!$B$45*(1+Inputs!$B$46)^(C$7-1)*1 -> -12000 | D55: =-Inputs!$B$45*(1+Inputs!$B$46)^(D$7-1)*1 -> -12000 | E55: =-Inputs!$B$45*(1+Inputs!$B$46)^(E$7-1)*1 -> -12000 | F55: =-Inputs!$B$45*(1+Inputs!$B$46)^(F$7-1)*1 -> -12000 | G55: =-Inputs!$B$45*(1+Inputs!$B$46)^(G$7-1)*1 -> -12000 | H55: =-Inputs!$B$45*(1+Inputs!$B$46)^(H$7-1)*1 -> -12000 | I55: =-Inputs!$B$45*(1+Inputs!$B$46)^(I$7-1)*1 -> -12000 | J55: =-Inputs!$B$45*(1+Inputs!$B$46)^(J$7-1)*1 -> -12000 | ... BJ55: =-Inputs!$B$45*(1+Inputs!$B$46)^(BJ$7-1)*1 -> -2881.2
A56: Total operating expenses | C56: =C51+C52+C53+C54+C55 -> -93586.667 | D56: =D51+D52+D53+D54+D55 -> -93586.667 | E56: =E51+E52+E53+E54+E55 -> -93586.667 | F56: =F51+F52+F53+F54+F55 -> -93586.667 | G56: =G51+G52+G53+G54+G55 -> -93586.667 | H56: =H51+H52+H53+H54+H55 -> -93586.667 | I56: =I51+I52+I53+I54+I55 -> -93586.667 | J56: =J51+J52+J53+J54+J55 -> -93586.667 | ... BJ56: =BJ51+BJ52+BJ53+BJ54+BJ55 -> -95372.958
A57: EBITDA | C57: =C48+C56 -> -71831.535 | D57: =D48+D56 -> -68636.963 | E57: =E48+E56 -> -57943.181 | F57: =F48+F56 -> -53635.222 | G57: =G48+G56 -> -49261.491 | H57: =H48+H56 -> -44825.276 | I57: =I48+I56 -> -40329.7 | J57: =J48+J56 -> -35777.733 | ... BJ57: =BJ48+BJ56 -> -7304.7084
A59: Profit after depreciation, interest, tax
A60: EBIT | C60: =C57+C75 -> -100303.76 | D60: =D57+D75 -> -97109.185 | E60: =E57+E75 -> -86415.403 | F60: =F57+F75 -> -82107.444 | G60: =G57+G75 -> -77733.713 | H60: =H57+H75 -> -73297.498 | I60: =I57+I75 -> -68801.923 | J60: =J57+J75 -> -64249.955 | ... BJ60: =BJ57+BJ75 -> -36888.042
A61: Interest on loan (average balance after drawdown) | C61: =-(C80+C81+C83)/2*Inputs!$B$69/12 -> -21250 | D61: =-(D80+D81+D83)/2*Inputs!$B$69/12 -> -21161.458 | E61: =-(E80+E81+E83)/2*Inputs!$B$69/12 -> -20984.375 | F61: =-(F80+F81+F83)/2*Inputs!$B$69/12 -> -20807.292 | G61: =-(G80+G81+G83)/2*Inputs!$B$69/12 -> -20630.208 | H61: =-(H80+H81+H83)/2*Inputs!$B$69/12 -> -20453.125 | I61: =-(I80+I81+I83)/2*Inputs!$B$69/12 -> -20276.042 | J61: =-(J80+J81+J83)/2*Inputs!$B$69/12 -> -20098.958 | ... BJ61: =-(BJ80+BJ81+BJ83)/2*Inputs!$B$69/12 -> -10890.625
A62: Pre-tax income | C62: =C60+C61 -> -121553.76 | D62: =D60+D61 -> -118270.64 | E62: =E60+E61 -> -107399.78 | F62: =F60+F61 -> -102914.74 | G62: =G60+G61 -> -98363.921 | H62: =H60+H61 -> -93750.623 | I62: =I60+I61 -> -89077.964 | J62: =J60+J61 -> -84348.914 | ... BJ62: =BJ60+BJ61 -> -47778.667
A63: Helper: cumulative pre-tax income | C63: =C62 -> -121553.76 | D63: =C63+D62 -> -239824.4 | E63: =D63+E62 -> -347224.18 | F63: =E63+F62 -> -450138.91 | G63: =F63+G62 -> -548502.84 | H63: =G63+H62 -> -642253.46 | I63: =H63+I62 -> -731331.42 | J63: =I63+J62 -> -815680.34 | K63: =J63+K62 -> -895246.63 | ... BJ63: =BI63+BJ62 -> -3340553.2
A64: Helper: cumulative taxable income (losses carried forward) | C64: =MAX(0,C63) -> 0 | D64: =MAX(C64,D63) -> 0 | E64: =MAX(D64,E63) -> 0 | F64: =MAX(E64,F63) -> 0 | G64: =MAX(F64,G63) -> 0 | H64: =MAX(G64,H63) -> 0 | I64: =MAX(H64,I63) -> 0 | J64: =MAX(I64,J63) -> 0 | K64: =MAX(J64,K63) -> 0 | ... BJ64: =MAX(BI64,BJ63) -> 0
A65: Income tax | C65: =-C64*Inputs!$B$79 -> 0 | D65: =-(D64-C64)*Inputs!$B$79 -> 0 | E65: =-(E64-D64)*Inputs!$B$79 -> 0 | F65: =-(F64-E64)*Inputs!$B$79 -> 0 | G65: =-(G64-F64)*Inputs!$B$79 -> 0 | H65: =-(H64-G64)*Inputs!$B$79 -> 0 | I65: =-(I64-H64)*Inputs!$B$79 -> 0 | J65: =-(J64-I64)*Inputs!$B$79 -> 0 | K65: =-(K64-J64)*Inputs!$B$79 -> 0 | ... BJ65: =-(BJ64-BI64)*Inputs!$B$79 -> 0
A66: Net income | C66: =C62+C65 -> -121553.76 | D66: =D62+D65 -> -118270.64 | E66: =E62+E65 -> -107399.78 | F66: =F62+F65 -> -102914.74 | G66: =G62+G65 -> -98363.921 | H66: =H62+H65 -> -93750.623 | I66: =I62+I65 -> -89077.964 | J66: =J62+J65 -> -84348.914 | ... BJ66: =BJ62+BJ65 -> -47778.667
A68: Fixed assets & capital spending
A69: Tunnel equipment | C69: =IF(C$6=1,Inputs!$B$49,0) -> 1650000 | D69: =IF(D$6=1,Inputs!$B$49,0) -> 0 | E69: =IF(E$6=1,Inputs!$B$49,0) -> 0 | F69: =IF(F$6=1,Inputs!$B$49,0) -> 0 | G69: =IF(G$6=1,Inputs!$B$49,0) -> 0 | H69: =IF(H$6=1,Inputs!$B$49,0) -> 0 | I69: =IF(I$6=1,Inputs!$B$49,0) -> 0 | J69: =IF(J$6=1,Inputs!$B$49,0) -> 0 | ... BJ69: =IF(BJ$6=1,Inputs!$B$49,0) -> 0
A70: Building & site works | C70: =IF(C$6=1,Inputs!$B$50,0) -> 2300000 | D70: =IF(D$6=1,Inputs!$B$50,0) -> 0 | E70: =IF(E$6=1,Inputs!$B$50,0) -> 0 | F70: =IF(F$6=1,Inputs!$B$50,0) -> 0 | G70: =IF(G$6=1,Inputs!$B$50,0) -> 0 | H70: =IF(H$6=1,Inputs!$B$50,0) -> 0 | I70: =IF(I$6=1,Inputs!$B$50,0) -> 0 | J70: =IF(J$6=1,Inputs!$B$50,0) -> 0 | ... BJ70: =IF(BJ$6=1,Inputs!$B$50,0) -> 0
A71: Pay stations, signage & vacuums | C71: =IF(C$6=1,Inputs!$B$51,0) -> 150000 | D71: =IF(D$6=1,Inputs!$B$51,0) -> 0 | E71: =IF(E$6=1,Inputs!$B$51,0) -> 0 | F71: =IF(F$6=1,Inputs!$B$51,0) -> 0 | G71: =IF(G$6=1,Inputs!$B$51,0) -> 0 | H71: =IF(H$6=1,Inputs!$B$51,0) -> 0 | I71: =IF(I$6=1,Inputs!$B$51,0) -> 0 | J71: =IF(J$6=1,Inputs!$B$51,0) -> 0 | ... BJ71: =IF(BJ$6=1,Inputs!$B$51,0) -> 0
A72: Equipment refresh & upgrades (first period of each year from year 2) | C72: =IF(AND(C$7>1,MOD(C$6-1,12)=0),Inputs!$B$52,0) -> 0 | D72: =IF(AND(D$7>1,MOD(D$6-1,12)=0),Inputs!$B$52,0) -> 0 | E72: =IF(AND(E$7>1,MOD(E$6-1,12)=0),Inputs!$B$52,0) -> 0 | F72: =IF(AND(F$7>1,MOD(F$6-1,12)=0),Inputs!$B$52,0) -> 0 | G72: =IF(AND(G$7>1,MOD(G$6-1,12)=0),Inputs!$B$52,0) -> 0 | H72: =IF(AND(H$7>1,MOD(H$6-1,12)=0),Inputs!$B$52,0) -> 0 | I72: =IF(AND(I$7>1,MOD(I$6-1,12)=0),Inputs!$B$52,0) -> 0 | J72: =IF(AND(J$7>1,MOD(J$6-1,12)=0),Inputs!$B$52,0) -> 0 | ... BJ72: =IF(AND(BJ$7>1,MOD(BJ$6-1,12)=0),Inputs!$B$52,0) -> 0
A73: Capital spending | C73: =C69+C70+C71+C72 -> 4100000 | D73: =D69+D70+D71+D72 -> 0 | E73: =E69+E70+E71+E72 -> 0 | F73: =F69+F70+F71+F72 -> 0 | G73: =G69+G70+G71+G72 -> 0 | H73: =H69+H70+H71+H72 -> 0 | I73: =I69+I70+I71+I72 -> 0 | J73: =J69+J70+J71+J72 -> 0 | ... BJ73: =BJ69+BJ70+BJ71+BJ72 -> 0
A74: Fixed assets at cost | C74: =C73 -> 4100000 | D74: =C74+D73 -> 4100000 | E74: =D74+E73 -> 4100000 | F74: =E74+F73 -> 4100000 | G74: =F74+G73 -> 4100000 | H74: =G74+H73 -> 4100000 | I74: =H74+I73 -> 4100000 | J74: =I74+J73 -> 4100000 | K74: =J74+K73 -> 4100000 | ... BJ74: =BI74+BJ73 -> 4260000
A75: Depreciation | C75: =-MIN(C74/MAX(1,Inputs!$B$78*12),C73) -> -28472.222 | D75: =-MIN(D74/MAX(1,Inputs!$B$78*12),C77+D73) -> -28472.222 | E75: =-MIN(E74/MAX(1,Inputs!$B$78*12),D77+E73) -> -28472.222 | F75: =-MIN(F74/MAX(1,Inputs!$B$78*12),E77+F73) -> -28472.222 | G75: =-MIN(G74/MAX(1,Inputs!$B$78*12),F77+G73) -> -28472.222 | H75: =-MIN(H74/MAX(1,Inputs!$B$78*12),G77+H73) -> -28472.222 | I75: =-MIN(I74/MAX(1,Inputs!$B$78*12),H77+I73) -> -28472.222 | J75: =-MIN(J74/MAX(1,Inputs!$B$78*12),I77+J73) -> -28472.222 | K75: =-MIN(K74/MAX(1,Inputs!$B$78*12),J77+K73) -> -28472.222 | ... BJ75: =-MIN(BJ74/MAX(1,Inputs!$B$78*12),BI77+BJ73) -> -29583.333
A76: Accumulated depreciation | C76: =C75 -> -28472.222 | D76: =C76+D75 -> -56944.444 | E76: =D76+E75 -> -85416.667 | F76: =E76+F75 -> -113888.89 | G76: =F76+G75 -> -142361.11 | H76: =G76+H75 -> -170833.33 | I76: =H76+I75 -> -199305.56 | J76: =I76+J75 -> -227777.78 | K76: =J76+K75 -> -256250 | ... BJ76: =BI76+BJ75 -> -1741666.7
A77: Net fixed assets | C77: =C74+C76 -> 4071527.8 | D77: =D74+D76 -> 4043055.6 | E77: =E74+E76 -> 4014583.3 | F77: =F74+F76 -> 3986111.1 | G77: =G74+G76 -> 3957638.9 | H77: =H74+H76 -> 3929166.7 | I77: =I74+I76 -> 3900694.4 | J77: =J74+J76 -> 3872222.2 | ... BJ77: =BJ74+BJ76 -> 2518333.3
A79: Debt
A80: Loan — opening balance | C80: =0 -> 0 | D80: =C83 -> 3000000 | E80: =D83 -> 2975000 | F80: =E83 -> 2950000 | G80: =F83 -> 2925000 | H80: =G83 -> 2900000 | I80: =H83 -> 2875000 | J80: =I83 -> 2850000 | K80: =J83 -> 2825000 | ... BJ80: =BI83 -> 1550000
A81: Loan drawdown | C81: =IF(C$6=1,Inputs!$B$68,0) -> 3000000 | D81: =IF(D$6=1,Inputs!$B$68,0) -> 0 | E81: =IF(E$6=1,Inputs!$B$68,0) -> 0 | F81: =IF(F$6=1,Inputs!$B$68,0) -> 0 | G81: =IF(G$6=1,Inputs!$B$68,0) -> 0 | H81: =IF(H$6=1,Inputs!$B$68,0) -> 0 | I81: =IF(I$6=1,Inputs!$B$68,0) -> 0 | J81: =IF(J$6=1,Inputs!$B$68,0) -> 0 | ... BJ81: =IF(BJ$6=1,Inputs!$B$68,0) -> 0
A82: Loan repayment | C82: =-MIN(C80,Inputs!$B$68/MAX(1,Inputs!$B$70*12)) -> 0 | D82: =-MIN(D80,Inputs!$B$68/MAX(1,Inputs!$B$70*12)) -> -25000 | E82: =-MIN(E80,Inputs!$B$68/MAX(1,Inputs!$B$70*12)) -> -25000 | F82: =-MIN(F80,Inputs!$B$68/MAX(1,Inputs!$B$70*12)) -> -25000 | G82: =-MIN(G80,Inputs!$B$68/MAX(1,Inputs!$B$70*12)) -> -25000 | H82: =-MIN(H80,Inputs!$B$68/MAX(1,Inputs!$B$70*12)) -> -25000 | I82: =-MIN(I80,Inputs!$B$68/MAX(1,Inputs!$B$70*12)) -> -25000 | J82: =-MIN(J80,Inputs!$B$68/MAX(1,Inputs!$B$70*12)) -> -25000 | ... BJ82: =-MIN(BJ80,Inputs!$B$68/MAX(1,Inputs!$B$70*12)) -> -25000
A83: Loan — closing balance | C83: =C80+C81+C82 -> 3000000 | D83: =D80+D81+D82 -> 2975000 | E83: =E80+E81+E82 -> 2950000 | F83: =F80+F81+F82 -> 2925000 | G83: =G80+G81+G82 -> 2900000 | H83: =H80+H81+H82 -> 2875000 | I83: =I80+I81+I82 -> 2850000 | J83: =J80+J81+J82 -> 2825000 | ... BJ83: =BJ80+BJ81+BJ82 -> 1525000
A85: Working capital
A86: Accounts receivable | C86: =C39*Inputs!$B$73/30 -> 1766.4469 | D86: =D39*Inputs!$B$73/30 -> 2025.3274 | E86: =E39*Inputs!$B$73/30 -> 2918.521 | F86: =F39*Inputs!$B$73/30 -> 3272.1192 | G86: =G39*Inputs!$B$73/30 -> 3631.694 | H86: =H39*Inputs!$B$73/30 -> 3996.9467 | I86: =I39*Inputs!$B$73/30 -> 4367.5932 | J86: =J39*Inputs!$B$73/30 -> 4743.3639 | ... BJ86: =BJ39*Inputs!$B$73/30 -> 7400.0827
A87: Inventory | C87: =-C47*Inputs!$B$74/30 -> 2370.7863 | D87: =-D47*Inputs!$B$74/30 -> 2715.1037 | E87: =-E47*Inputs!$B$74/30 -> 4067.1643 | F87: =-F47*Inputs!$B$74/30 -> 4565.1717 | G87: =-G47*Inputs!$B$74/30 -> 5075.1174 | H87: =-H47*Inputs!$B$74/30 -> 5596.4044 | I87: =-I47*Inputs!$B$74/30 -> 6128.4658 | J87: =-J47*Inputs!$B$74/30 -> 6670.7628 | ... BJ87: =-BJ47*Inputs!$B$74/30 -> 11466.495
A88: Accounts payable | C88: =-C47*Inputs!$B$75/30 -> 3951.3105 | D88: =-D47*Inputs!$B$75/30 -> 4525.1729 | E88: =-E47*Inputs!$B$75/30 -> 6778.6072 | F88: =-F47*Inputs!$B$75/30 -> 7608.6195 | G88: =-G47*Inputs!$B$75/30 -> 8458.5289 | H88: =-H47*Inputs!$B$75/30 -> 9327.3407 | I88: =-I47*Inputs!$B$75/30 -> 10214.11 | J88: =-J47*Inputs!$B$75/30 -> 11117.938 | ... BJ88: =-BJ47*Inputs!$B$75/30 -> 19110.826
A89: (Increase) / decrease in receivables | C89: =-C86 -> -1766.4469 | D89: =C86-D86 -> -258.8805 | E89: =D86-E86 -> -893.19354 | F89: =E86-F86 -> -353.59822 | G89: =F86-G86 -> -359.57484 | H89: =G86-H86 -> -365.25263 | I89: =H86-I86 -> -370.64653 | J89: =I86-J86 -> -375.77074 | K89: =J86-K86 -> -380.63874 | ... BJ89: =BI86-BJ86 -> 1412.8073
A90: (Increase) / decrease in inventory | C90: =-C87 -> -2370.7863 | D90: =C87-D87 -> -344.31741 | E90: =D87-E87 -> -1352.0606 | F90: =E87-F87 -> -498.00737 | G90: =F87-G87 -> -509.94568 | H90: =G87-H87 -> -521.28707 | I90: =H87-I87 -> -532.06138 | J90: =I87-J87 -> -542.29699 | K90: =J87-K87 -> -552.02081 | ... BJ90: =BI87-BJ87 -> 3562.2693
A91: Increase / (decrease) in payables | C91: =C88 -> 3951.3105 | D91: =D88-C88 -> 573.86235 | E91: =E88-D88 -> 2253.4343 | F91: =F88-E88 -> 830.01229 | G91: =G88-F88 -> 849.90946 | H91: =H88-G88 -> 868.81178 | I91: =I88-H88 -> 886.76897 | J91: =J88-I88 -> 903.82831 | K91: =K88-J88 -> 920.03468 | ... BJ91: =BJ88-BI88 -> -5937.1155
A93: Cash flow
A94: Operating cash flow | C94: =C66-C75+C89+C90+C91 -> -93267.458 | D94: =D66-D75+D89+D90+D91 -> -89827.757 | E94: =E66-E75+E89+E90+E91 -> -78919.376 | F94: =F66-F75+F89+F90+F91 -> -74464.107 | G94: =G66-G75+G89+G90+G91 -> -69911.31 | H94: =H66-H75+H89+H90+H91 -> -65296.129 | I94: =I66-I75+I89+I90+I91 -> -60621.681 | J94: =J66-J75+J89+J90+J91 -> -55890.931 | ... BJ94: =BJ66-BJ75+BJ89+BJ90+BJ91 -> -19157.372
A95: Investing cash flow (capex) | C95: =-C73 -> -4100000 | D95: =-D73 -> 0 | E95: =-E73 -> 0 | F95: =-F73 -> 0 | G95: =-G73 -> 0 | H95: =-H73 -> 0 | I95: =-I73 -> 0 | J95: =-J73 -> 0 | ... BJ95: =-BJ73 -> 0
A96: Equity raised | C96: =IF(C$6=1,Inputs!$B$67,0) -> 2100000 | D96: =IF(D$6=1,Inputs!$B$67,0) -> 0 | E96: =IF(E$6=1,Inputs!$B$67,0) -> 0 | F96: =IF(F$6=1,Inputs!$B$67,0) -> 0 | G96: =IF(G$6=1,Inputs!$B$67,0) -> 0 | H96: =IF(H$6=1,Inputs!$B$67,0) -> 0 | I96: =IF(I$6=1,Inputs!$B$67,0) -> 0 | J96: =IF(J$6=1,Inputs!$B$67,0) -> 0 | ... BJ96: =IF(BJ$6=1,Inputs!$B$67,0) -> 0
A97: Financing cash flow | C97: =C96+C81+C82 -> 5100000 | D97: =D96+D81+D82 -> -25000 | E97: =E96+E81+E82 -> -25000 | F97: =F96+F81+F82 -> -25000 | G97: =G96+G81+G82 -> -25000 | H97: =H96+H81+H82 -> -25000 | I97: =I96+I81+I82 -> -25000 | J97: =J96+J81+J82 -> -25000 | ... BJ97: =BJ96+BJ81+BJ82 -> -25000
A98: Net cash flow | C98: =C94+C95+C97 -> 906732.54 | D98: =D94+D95+D97 -> -114827.76 | E98: =E94+E95+E97 -> -103919.38 | F98: =F94+F95+F97 -> -99464.107 | G98: =G94+G95+G97 -> -94911.31 | H98: =H94+H95+H97 -> -90296.129 | I98: =I94+I95+I97 -> -85621.681 | J98: =J94+J95+J97 -> -80890.931 | ... BJ98: =BJ94+BJ95+BJ97 -> -44157.372
A99: Opening cash | C99: =0 -> 0 | D99: =C100 -> 906732.54 | E99: =D100 -> 791904.79 | F99: =E100 -> 687985.41 | G99: =F100 -> 588521.3 | H99: =G100 -> 493609.99 | I99: =H100 -> 403313.86 | J99: =I100 -> 317692.18 | K99: =J100 -> 236801.25 | ... BJ99: =BI100 -> -2189484.9
A100: Closing cash | C100: =C99+C98 -> 906732.54 | D100: =D99+D98 -> 791904.79 | E100: =E99+E98 -> 687985.41 | F100: =F99+F98 -> 588521.3 | G100: =G99+G98 -> 493609.99 | H100: =H99+H98 -> 403313.86 | I100: =I99+I98 -> 317692.18 | J100: =J99+J98 -> 236801.25 | ... BJ100: =BJ99+BJ98 -> -2233642.3
A101: Helper: EBITDA positive (1/0) | C101: =IF(C57>0,1,0) -> 0 | D101: =IF(D57>0,1,0) -> 0 | E101: =IF(E57>0,1,0) -> 0 | F101: =IF(F57>0,1,0) -> 0 | G101: =IF(G57>0,1,0) -> 0 | H101: =IF(H57>0,1,0) -> 0 | I101: =IF(I57>0,1,0) -> 0 | J101: =IF(J57>0,1,0) -> 0 | ... BJ101: =IF(BJ57>0,1,0) -> 0
A103: Goal modules
A104: Helper: net income positive (1/0) | C104: =IF(C66>0,1,0) -> 0 | D104: =IF(D66>0,1,0) -> 0 | E104: =IF(E66>0,1,0) -> 0 | F104: =IF(F66>0,1,0) -> 0 | G104: =IF(G66>0,1,0) -> 0 | H104: =IF(H66>0,1,0) -> 0 | I104: =IF(I66>0,1,0) -> 0 | J104: =IF(J66>0,1,0) -> 0 | ... BJ104: =IF(BJ66>0,1,0) -> 0
A105: Cash flow before financing (operating + investing) | C105: =C94+C95 -> -4193267.5 | D105: =D94+D95 -> -89827.757 | E105: =E94+E95 -> -78919.376 | F105: =F94+F95 -> -74464.107 | G105: =G94+G95 -> -69911.31 | H105: =H94+H95 -> -65296.129 | I105: =I94+I95 -> -60621.681 | J105: =J94+J95 -> -55890.931 | ... BJ105: =BJ94+BJ95 -> -19157.372
A106: Cumulative cash flow before financing | C106: =C105 -> -4193267.5 | D106: =C106+D105 -> -4283095.2 | E106: =D106+E105 -> -4362014.6 | F106: =E106+F105 -> -4436478.7 | G106: =F106+G105 -> -4506390 | H106: =G106+H105 -> -4571686.1 | I106: =H106+I105 -> -4632307.8 | J106: =I106+J105 -> -4688198.7 | K106: =J106+K105 -> -4739305.4 | ... BJ106: =BI106+BJ105 -> -5858642.3
A107: Helper: lowest cumulative cash flow so far | C107: =C106 -> -4193267.5 | D107: =MIN(C107,D106) -> -4283095.2 | E107: =MIN(D107,E106) -> -4362014.6 | F107: =MIN(E107,F106) -> -4436478.7 | G107: =MIN(F107,G106) -> -4506390 | H107: =MIN(G107,H106) -> -4571686.1 | I107: =MIN(H107,I106) -> -4632307.8 | J107: =MIN(I107,J106) -> -4688198.7 | K107: =MIN(J107,K106) -> -4739305.4 | ... BJ107: =MIN(BI107,BJ106) -> -5858642.3
A108: Helper: investment paid back (1/0) | C108: =IF(AND(C106>=0,C107<0),1,0) -> 0 | D108: =IF(AND(D106>=0,D107<0),1,0) -> 0 | E108: =IF(AND(E106>=0,E107<0),1,0) -> 0 | F108: =IF(AND(F106>=0,F107<0),1,0) -> 0 | G108: =IF(AND(G106>=0,G107<0),1,0) -> 0 | H108: =IF(AND(H106>=0,H107<0),1,0) -> 0 | I108: =IF(AND(I106>=0,I107<0),1,0) -> 0 | J108: =IF(AND(J106>=0,J107<0),1,0) -> 0 | ... BJ108: =IF(AND(BJ106>=0,BJ107<0),1,0) -> 0
A109: Unlevered free cash flow (operating + after-tax interest − capex) | C109: =C94-C61*(1-Inputs!$B$79)+C95 -> -4176480 | D109: =D94-D61*(1-Inputs!$B$79)+D95 -> -73110.204 | E109: =E94-E61*(1-Inputs!$B$79)+E95 -> -62341.719 | F109: =F94-F61*(1-Inputs!$B$79)+F95 -> -58026.347 | G109: =G94-G61*(1-Inputs!$B$79)+G95 -> -53613.446 | H109: =H94-H61*(1-Inputs!$B$79)+H95 -> -49138.16 | I109: =I94-I61*(1-Inputs!$B$79)+I95 -> -44603.608 | J109: =J94-J61*(1-Inputs!$B$79)+J95 -> -40012.754 | ... BJ109: =BJ94-BJ61*(1-Inputs!$B$79)+BJ95 -> -10553.779
A111: Balance sheet
A112: Paid-in capital | C112: =C96 -> 2100000 | D112: =C112+D96 -> 2100000 | E112: =D112+E96 -> 2100000 | F112: =E112+F96 -> 2100000 | G112: =F112+G96 -> 2100000 | H112: =G112+H96 -> 2100000 | I112: =H112+I96 -> 2100000 | J112: =I112+J96 -> 2100000 | K112: =J112+K96 -> 2100000 | ... BJ112: =BI112+BJ96 -> 2100000
A113: Retained earnings | C113: =C66 -> -121553.76 | D113: =C113+D66 -> -239824.4 | E113: =D113+E66 -> -347224.18 | F113: =E113+F66 -> -450138.91 | G113: =F113+G66 -> -548502.84 | H113: =G113+H66 -> -642253.46 | I113: =H113+I66 -> -731331.42 | J113: =I113+J66 -> -815680.34 | K113: =J113+K66 -> -895246.63 | ... BJ113: =BI113+BJ66 -> -3340553.2
A114: Total assets | C114: =C100+C86+C87+C77 -> 4982397.6 | D114: =D100+D86+D87+D77 -> 4839700.8 | E114: =E100+E86+E87+E77 -> 4709554.4 | F114: =F100+F86+F87+F77 -> 4582469.7 | G114: =G100+G86+G87+G77 -> 4459955.7 | H114: =H100+H86+H87+H77 -> 4342073.9 | I114: =I100+I86+I87+I77 -> 4228882.7 | J114: =J100+J86+J87+J77 -> 4120437.6 | ... BJ114: =BJ100+BJ86+BJ87+BJ77 -> 303557.64
...

Sheet Checks
A1: Model checks | E1: =HYPERLINK("#'Cover'!A1","◂ Contents") -> ◂ Contents
A2: Live formulas: they re-run every time an input changes.
A3: Check | B3: Result | C3: What it tests
A4: Annual revenue ties to period detail | B4: =IF(ABS(SUM('P&L'!$B$5:$F$5)-SUM(Monthly!$C$37:$BJ$37))<0.5,"PASS","FAIL") -> PASS | C4: Sum of annual revenue equals the sum of every period
A5: Annual net income ties to period detail | B5: =IF(ABS(SUM('P&L'!$B$22:$F$22)-SUM(Monthly!$C$64:$BJ$64))<0.5,"PASS","FAIL") -> PASS | C5: Sum of annual net income equals the sum of every period
A6: EBITDA reconciliation | B6: =IF(ABS(SUM(Monthly!$C$55:$BJ$55)-SUM(Monthly!$C$46:$BJ$46)-SUM(Monthly!$C$54:$BJ$54))<0.5,"PASS","FAIL") -> PASS | C6: EBITDA = gross profit + operating expenses (costs are negative)
A7: Cash roll-forward | B7: =IF(ABS(INDEX(Monthly!$C$98:$BJ$98,60)-SUM(Monthly!$C$96:$BJ$96))<0.5,"PASS","FAIL") -> PASS | C7: Closing cash = all net cash flows since the start (opening cash is zero)
A8: Scenario selector valid | B8: =IF(AND(ISNUMBER(Dashboard!B4),Dashboard!B4>=1,Dashboard!B4<=3,INT(Dashboard!B4)=Dashboard!B4),"PASS","FAIL") -> PASS | C8: Dashboard!B4 is 1, 2 or 3
A9: Scenario ordering of drivers | B9: =IF(AND(Inputs!$B$7<=Inputs!$C$7,Inputs!$C$7<=Inputs!$D$7,Inputs!$B$9>=Inputs!$C$9,Inputs!$C$9>=Inputs!$D$9,Inputs!$B$10<=Inputs!$C$10,Inputs!$C$10<=Inputs!$D$10,Inputs!$B$11>=Inputs!$C$11,Inputs!$C$11>=Inputs!$D$11,Inputs!$B$19<=Inputs!$C$19,Inputs!$C$19<=Inputs!$D$19,Inputs!$B$20<=Inputs!$C$20,Inputs!$C$20<=Inputs!$D$20,Inputs!$B$21<=Inputs!$C$21,Inputs!$C$21<=Inputs!$D$21,Inputs!$B$22<=Inputs!$C$22,Inputs!$C$22<=Inputs!$D$22,Inputs!$B$23>=Inputs!$C$23,Inputs!$C$23>=Inputs!$D$23,Inputs!$B$24>=Inputs!$C$24,Inputs!$C$24>=Inputs!$D$24,Inputs!$B$27<=Inputs!$C$27,Inputs!$C$27<=Inputs!$D$27,Inputs!$B$28<=Inputs!$C$28,Inputs!$C$28<=Inputs!$D$28,Inputs!$B$29<=Inputs!$C$29,Inputs!$C$29<=Inputs!$D$29,Inputs!$B$30<=Inputs!$C$30,Inputs!$C$30<=Inputs!$D$30,Inputs!$B$33>=Inputs!$C$33,Inputs!$C$33>=Inputs!$D$33,Inputs!$B$34>=Inputs!$C$34,Inputs!$C$34>=Inputs!$D$34,Inputs!$B$35>=Inputs!$C$35,Inputs!$C$35>=Inputs!$D$35,Inputs!$B$36>=Inputs!$C$36,Inputs!$C$36>=Inputs!$D$36,Inputs!$B$37>=Inputs!$C$37,Inputs!$C$37>=Inputs!$D$37,Inputs!$B$38>=Inputs!$C$38,Inputs!$C$38>=Inputs!$D$38,Inputs!$B$46<=Inputs!$C$46,Inputs!$C$46<=Inputs!$D$46,Inputs!$B$55<=Inputs!$C$55,Inputs!$C$55<=Inputs!$D$55,Inputs!$B$57<=Inputs!$C$57,Inputs!$C$57<=Inputs!$D$57,Inputs!$B$59<=Inputs!$C$59,Inputs!$C$59<=Inputs!$D$59,Inputs!$B$61<=Inputs!$C$61,Inputs!$C$61<=Inputs!$D$61,Inputs!$B$85>=Inputs!$C$85,Inputs!$C$85>=Inputs!$D$85,Inputs!$B$86<=Inputs!$C$86,Inputs!$C$86<=Inputs!$D$86,Inputs!$B$87<=Inputs!$C$87,Inputs!$C$87<=Inputs!$D$87),"PASS","FAIL") -> PASS | C9: Low / Base / High ordered the right way for every growth and cost driver
A10: Gross margin within 0–100% | B10: =IF(AND(MIN('P&L'!$B$8:$F$8)>=0,MAX('P&L'!$B$8:$F$8)<=1),"PASS","FAIL") -> PASS | C10: Gross margin never negative or above 100%
A11: Loan balance never negative | B11: =IF(MIN(Monthly!$C$81:$BJ$81)>=-0.5,"PASS","FAIL") -> PASS | C11: Repayments never exceed the loan
A12: Funding table ties to the cash flow | B12: =IF(ABS('Break-even'!B18-('Break-even'!B16-'Break-even'!B10))<0.5,"PASS","FAIL") -> PASS | C12: Lowest cash balance = sources of funds − uses of funds up to that point
A13: Valuation: discounting ties to NPV() | B13: =IF(ABS(Valuation!B23-NPV(Valuation!B6,Valuation!$B$17:$F$17))<0.5,"PASS","FAIL") -> PASS | C13: Sum of discounted free cash flows equals Excel's NPV of the same flows
A14: Valuation: WACC above terminal growth | B14: =IF(Valuation!B6>Valuation!B7,"PASS","FAIL") -> PASS | C14: The perpetual-growth formula needs WACC > g
A15: Valuation: sensitivity centre = enterprise value | B15: =IF(ABS(Valuation!D36-Valuation!B27)<0.5,"PASS","FAIL") -> PASS | C15: The middle of the WACC × growth table reproduces the headline value
A16: Valuation: final-year cash flow positive | B16: =IF(Valuation!$F$17>0,"PASS","WARN") -> PASS | C16: Business warning: a negative final-year cash flow gives a negative terminal value (often a 1-year plan still carrying start-up spending)
A17: Sources & uses balance | B17: =IF(ABS('Sources & Uses'!B21-'Sources & Uses'!B28)<0.5,"PASS","FAIL") -> PASS | C17: Sources of funds = uses of funds (incl. cash at the end) for the Sources & Uses period
A18: No error values | B18: =IF(SUMPRODUCT(--ISERROR(Monthly!$C$4:$BJ$116))+SUMPRODUCT(--ISERROR(Headcount!$C$4:$BJ$15))+SUMPRODUCT(--ISERROR('P&L'!$B$3:$F$23))+SUMPRODUCT(--ISERROR('Cash Flow'!$B$3:$F$18))+SUMPRODUCT(--ISERROR('Balance Sheet'!$B$3:$F$17))+SUMPRODUCT(--ISERROR(KPIs!$B$27:$F$52))+SUMPRODUCT(--ISERROR('Break-even'!$B$26:$F$33))+SUMPRODUCT(--ISERROR(Valuation!$B$14:$F$19))+SUMPRODUCT(--ISERROR('Break-even'!$B$3:$F$35))+SUMPRODUCT(--ISERROR(Valuation!$A$3:$F$40))+SUMPRODUCT(--ISERROR('Sources & Uses'!$B$3:$C$30))+SUMPRODUCT(--ISERROR(Dashboard!$A$6:$W$44))+SUMPRODUCT(--ISERROR(Summary!$A$5:$S$52))+SUMPRODUCT(--ISERROR(KPIs!$A$4:$G$52))+SUMPRODUCT(--ISERROR('Scenario calc'!$C$6:$BJ$128))+SUMPRODUCT(--ISERROR('Scenario calc'!$C$133:$BJ$255))+SUMPRODUCT(--ISERROR('Scenario calc'!$C$260:$BJ$382))+SUMPRODUCT(--ISERROR(Scenarios!$B$5:$F$51))=0,"PASS","FAIL") -> PASS | C18: No error values (divide-by-zero, broken references) on any calculation sheet
A19: Summary ties to statements | B19: =IF(IFERROR(AND(SUMPRODUCT(--(ABS(Summary!$B$7:$F$7-'P&L'!$B$5:$F$5)>0.5))=0,SUMPRODUCT(--(ABS(Summary!$B$19:$F$19-'P&L'!$B$22:$F$22)>0.5))=0,SUMPRODUCT(--(ABS(Summary!$B$31:$F$31-'Cash Flow'!$B$18:$F$18)>0.5))=0,SUMPRODUCT(--(ABS(Summary!$B$41:$F$41-'Balance Sheet'!$B$5:$F$5)>0.5))=0,ABS(SUM(Summary!$H$7:$S$7)-INDEX(Summary!$B$7:$F$7,Summary!$R$2))<0.5,ABS(SUM(Summary!$H$19:$S$19)-INDEX(Summary!$B$19:$F$19,Summary!$R$2))<0.5,ABS(Summary!$S$31-INDEX(Summary!$B$31:$F$31,Summary!$R$2))<0.5),FALSE()),"PASS","FAIL") -> PASS | C19: Summary revenue, net income and closing cash equal the statements every year; the detailed year adds up to its annual figure
A20: DuPont ties to return on equity | B20: =IF(SUMPRODUCT(--(ABS(KPIs!$B$24:$F$24)>0.000000001))>0,"FAIL",IF(SUMPRODUCT(ISNUMBER(KPIs!$B$23:$F$23)*ISNUMBER(KPIs!$B$16:$F$16))=0,"n/a","PASS")) -> PASS | C20: Net margin × asset turnover × equity multiplier equals return on equity every year; n/a = no year where both are defined (a one-sided n/a is a FAIL)
A21: Scenarios: Active = selected scenario | B21: =IF(IFERROR(AND(ABS(Scenarios!E18-INDEX(Scenarios!B18:D18,1,Dashboard!$B$4))<0.5,ABS(Scenarios!E19-INDEX(Scenarios!B19:D19,1,Dashboard!$B$4))<0.5,ABS(Scenarios!E20-INDEX(Scenarios!B20:D20,1,Dashboard!$B$4))<0.5,ABS(Scenarios!E21-INDEX(Scenarios!B21:D21,1,Dashboard!$B$4))<0.000001,ABS(Scenarios!E22-INDEX(Scenarios!B22:D22,1,Dashboard!$B$4))<0.5,ABS(Scenarios!E23-INDEX(Scenarios!B23:D23,1,Dashboard!$B$4))<0.5,ABS(Scenarios!E24-INDEX(Scenarios!B24:D24,1,Dashboard!$B$4))<0.5,ABS(Scenarios!E25-INDEX(Scenarios!B25:D25,1,Dashboard!$B$4))<0.5,ABS(Scenarios!E26-INDEX(Scenarios!B26:D26,1,Dashboard!$B$4))<0.5,ABS(Scenarios!E27-INDEX(Scenarios!B27:D27,1,Dashboard!$B$4))<0.5),FALSE()),"PASS","FAIL") -> PASS | C21: On the Scenarios sheet the live model (Active) equals the Low / Base / High column chosen on the Dashboard for every output
A22: Balance sheet balances every period | B22: =IF(SUMPRODUCT(--(ABS(Monthly!$C$116:$BJ$116)>0.5))=0,"PASS","FAIL") -> PASS | C22: Assets = liabilities + equity in every period
A23: Funding sufficient (cash ≥ 0) | B23: =IF(MIN(Monthly!$C$98:$BJ$98)>=0,"PASS","WARN") -> PASS | C23: Business warning, not an error: cash dips below zero in this scenario
A25: Overall verdict | B25: =IF(COUNTIF(B4:B23,"FAIL")>0,"FAIL",IF(COUNTIF(B4:B23,"WARN")>0,"PASS WITH WARNINGS","PASS")) -> PASS
