Workbook

Sheet Cover
B2: Car wash financial model (planning)
B3: 3-year financial model · monthly detail · Low / Base / High scenarios · US dollars · Full plan
B5: Purpose | D5: Revenue and profit plan
B6: Active scenario | D6: =Dashboard!C4&" (change it on the Dashboard, cell B4)" -> Base (change it on the Dashboard, cell B4)
B7: Model checks | D7: =Checks!B25 -> PASS
B8: Prepared | D8: 21 October 2026
B10: Contents
C11: PRESENTATION
B12: 1 | C12: =HYPERLINK("#Dashboard!A1","Dashboard") -> Dashboard | D12: Scenario switch, key numbers, core financials
B13: 2 | C13: =HYPERLINK("#Summary!A1","Summary") -> Summary | D13: Income statement, cash flow and balance sheet — every year and any year by month
B14: 3 | C14: =HYPERLINK("#Scenarios!A1","Scenarios") -> Scenarios | D14: Low / Base / High side by side: drivers, outputs, charts
B15: 4 | C15: =HYPERLINK("#'Break-even'!A1","Break-even") -> Break-even | D15: Startup costs, funding need, break-even timing and revenue
B16: 5 | C16: =HYPERLINK("#Valuation!A1","Valuation") -> Valuation | D16: Free cash flow, DCF (perpetual growth and exit multiple), WACC × growth sensitivity
B17: 6 | C17: =HYPERLINK("#'Sources & Uses'!A1","Sources & Uses") -> Sources & Uses | D17: Funding structure, sources and uses of cash for the first months
B18: 7 | C18: =HYPERLINK("#KPIs!A1","KPIs") -> KPIs | D18: Financial ratios, DuPont analysis, industry metrics
C19: INPUTS
B20: 8 | C20: =HYPERLINK("#Inputs!A1","Inputs") -> Inputs | D20: Every assumption, Low / Base / High, with units and comments
C21: STATEMENTS
B22: 9 | C22: =HYPERLINK("#'P&L'!A1","P&L") -> P&L | D22: Annual profit & loss
B23: 10 | C23: =HYPERLINK("#'Cash Flow'!A1","Cash Flow") -> Cash Flow | D23: Annual cash flow statement
B24: 11 | C24: =HYPERLINK("#'Balance Sheet'!A1","Balance Sheet") -> Balance Sheet | D24: Balance sheet at year end
C25: CALCULATIONS
B26: 12 | C26: =HYPERLINK("#Monthly!A1","Monthly") -> Monthly | D26: Month-by-month engine of the model
B27: 13 | C27: =HYPERLINK("#Headcount!A1","Headcount") -> Headcount | D27: Team and payroll
B28: 14 | C28: =HYPERLINK("#'Scenario calc'!A1","Scenario calc") -> Scenario calc | D28: Low, Base and High calculated side by side for the Scenarios sheet
C29: CONTROL
B30: 15 | C30: =HYPERLINK("#Checks!A1","Checks") -> Checks | D30: Live integrity checks and the overall verdict
B32: How to read this file
C33: 1000 | D33: Input you can change — yellow cell with a blue figure (Inputs sheet and the view switches)
C34: 1000 | D34: Formula — calculated, do not overwrite
C35: 1000 | D35: Link to another sheet
C36: 1000 | D36: Active value the model uses (follows the scenario)

Sheet Dashboard
A1: Dashboard | W1: =HYPERLINK("#'Cover'!A1","◂ Contents") -> ◂ Contents
A2: Car wash financial model (planning)
A4: Active scenario | B4: 2 | C4: =CHOOSE(B4,"Low","Base","High") -> Base | D4: 1 = Low · 2 = Base · 3 = High — every sheet follows this cell | S4: Model checks | T4: =Checks!B25 -> PASS
A6: REVENUE · YEAR 3 | C6: EBITDA MARGIN · YEAR 3 | H6: NET INCOME · YEAR 3 | L6: LOWEST CASH BALANCE | P6: FUNDING REQUIRED | T6: ENTERPRISE VALUE (DCF)
A7: =D12 -> 2170291.6 | C7: =D17 -> 0.31439407 | H7: =D18 -> 140618.48 | L7: =F39 -> 179017.17 | P7: =F37 -> 5201982.8 | T7: =F44 -> -1510350.7
A8: =IF(AND(B12>0,D12>=0),(D12/B12)^(1/2)-1,"CAGR n/a") -> 0.3560774 | C8: =D16 -> 682326.82 | H8: =D19 -> 0.064792437 | L8: ='Break-even'!B6 -> 26 | P8: =IF(F38>=0,"Covered by funding raised",-F38) -> 101982.83 | T8: Average of 2 methods
A10: Core financials ($'000) — active scenario
B11: 1 | C11: 2 | D11: 3
A12: Revenue | B12: =SUMIF(Monthly!$C$5:$AL$5,B$11,Monthly!$C$37:$AL$37) -> 1180182.4 | C12: =SUMIF(Monthly!$C$5:$AL$5,C$11,Monthly!$C$37:$AL$37) -> 1846649 | D12: =SUMIF(Monthly!$C$5:$AL$5,D$11,Monthly!$C$37:$AL$37) -> 2170291.6
A13: Gross profit | B13: =SUMIF(Monthly!$C$5:$AL$5,B$11,Monthly!$C$46:$AL$46) -> 999760.79 | C13: =SUMIF(Monthly!$C$5:$AL$5,C$11,Monthly!$C$46:$AL$46) -> 1551921 | D13: =SUMIF(Monthly!$C$5:$AL$5,D$11,Monthly!$C$46:$AL$46) -> 1813150.4
A14: Gross margin | B14: =IF(B12=0,0,B13/B12) -> 0.84712397 | C14: =IF(C12=0,0,C13/C12) -> 0.84039848 | D14: =IF(D12=0,0,D13/D12) -> 0.83544089
A15: Operating expenses | B15: =SUMIF(Monthly!$C$5:$AL$5,B$11,Monthly!$C$54:$AL$54) -> -1123040 | C15: =SUMIF(Monthly!$C$5:$AL$5,C$11,Monthly!$C$54:$AL$54) -> -1123611.2 | D15: =SUMIF(Monthly!$C$5:$AL$5,D$11,Monthly!$C$54:$AL$54) -> -1130823.5
A16: EBITDA | B16: =SUMIF(Monthly!$C$5:$AL$5,B$11,Monthly!$C$55:$AL$55) -> -123279.21 | C16: =SUMIF(Monthly!$C$5:$AL$5,C$11,Monthly!$C$55:$AL$55) -> 428309.82 | D16: =SUMIF(Monthly!$C$5:$AL$5,D$11,Monthly!$C$55:$AL$55) -> 682326.82
A17: EBITDA margin | B17: =IF(B12=0,0,B16/B12) -> -0.10445776 | C17: =IF(C12=0,0,C16/C12) -> 0.23193894 | D17: =IF(D12=0,0,D16/D12) -> 0.31439407
A18: Net income | B18: =SUMIF(Monthly!$C$5:$AL$5,B$11,Monthly!$C$64:$AL$64) -> -709232.33 | C18: =SUMIF(Monthly!$C$5:$AL$5,C$11,Monthly!$C$64:$AL$64) -> -135565.18 | D18: =SUMIF(Monthly!$C$5:$AL$5,D$11,Monthly!$C$64:$AL$64) -> 140618.48
A19: Net margin | B19: =IF(B12=0,0,B18/B12) -> -0.60095146 | C19: =IF(C12=0,0,C18/C12) -> -0.073411448 | D19: =IF(D12=0,0,D18/D12) -> 0.064792437
A20: Operating cash flow | B20: =SUMIF(Monthly!$C$5:$AL$5,B$11,Monthly!$C$94:$AL$94) -> -367780.64 | C20: =SUMIF(Monthly!$C$5:$AL$5,C$11,Monthly!$C$94:$AL$94) -> 209654.47 | D20: =SUMIF(Monthly!$C$5:$AL$5,D$11,Monthly!$C$94:$AL$94) -> 489150.48
A21: Investing cash flow | B21: =SUMIF(Monthly!$C$5:$AL$5,B$11,Monthly!$C$95:$AL$95) -> -4100000 | C21: =SUMIF(Monthly!$C$5:$AL$5,C$11,Monthly!$C$95:$AL$95) -> -40000 | D21: =SUMIF(Monthly!$C$5:$AL$5,D$11,Monthly!$C$95:$AL$95) -> -40000
A22: Financing cash flow | B22: =SUMIF(Monthly!$C$5:$AL$5,B$11,Monthly!$C$97:$AL$97) -> 4825000 | C22: =SUMIF(Monthly!$C$5:$AL$5,C$11,Monthly!$C$97:$AL$97) -> -300000 | D22: =SUMIF(Monthly!$C$5:$AL$5,D$11,Monthly!$C$97:$AL$97) -> -300000
A23: Net change in cash | B23: =SUMIF(Monthly!$C$5:$AL$5,B$11,Monthly!$C$98:$AL$98) -> 357219.36 | C23: =SUMIF(Monthly!$C$5:$AL$5,C$11,Monthly!$C$98:$AL$98) -> -130345.53 | D23: =SUMIF(Monthly!$C$5:$AL$5,D$11,Monthly!$C$98:$AL$98) -> 149150.48
A24: Year-end cash | B24: =INDEX(Monthly!$C$100:$AL$100,B$11*12) -> 357219.36 | C24: =INDEX(Monthly!$C$100:$AL$100,C$11*12) -> 226873.84 | D24: =INDEX(Monthly!$C$100:$AL$100,D$11*12) -> 376024.31
A26: Car wash metrics
B27: 1 | C27: 2 | D27: 3
A28: Unlimited members (year end) | B28: =KPIs!B29 -> 972.08918 | C28: =KPIs!C29 -> 1660.5559 | D28: =KPIs!D29 -> 2124.5009
A29: Washes per operating day | B29: =KPIs!B37 -> 255.65215 | C29: =KPIs!C37 -> 409.62871 | D29: =KPIs!D37 -> 485.27721
A30: Tunnel capacity used | B30: =KPIs!B39 -> 0.30183253 | C30: =KPIs!C39 -> 0.48362304 | D30: =KPIs!D39 -> 0.57293649
A31: Revenue per wash | B31: =KPIs!B45 -> 13.265403 | C31: =KPIs!C45 -> 12.954323 | D31: =KPIs!D45 -> 12.851356
A32: Team (FTE, year end) | B32: =INDEX(Headcount!$C$10:$AL$10,B$27*12) -> 11 | C32: =INDEX(Headcount!$C$10:$AL$10,C$27*12) -> 11 | D32: =INDEX(Headcount!$C$10:$AL$10,D$27*12) -> 11
A34: Funding & valuation ($'000) — active scenario
A35: Equity raised | F35: =Inputs!$E$69 -> 2100000
A36: Loan drawn | F36: =Inputs!$E$70 -> 3000000
A37: Funding required (incl. cash buffer) | F37: ='Break-even'!B12 -> 5201982.8
A38: Funding surplus / (shortfall) | F38: ='Break-even'!B17 -> -101982.83
A39: ="Lowest cash balance (month "&'Break-even'!B6&")" -> Lowest cash balance (month 26) | F39: ='Break-even'!B18 -> 179017.17
A40: First month with positive EBITDA | F40: ='Break-even'!B21 -> 8
A41: Cash invested paid back | F41: ='Break-even'!B23 -> Not within horizon
A42: Enterprise value — perpetual growth | F42: =Valuation!B27 -> -1525694.7
A43: Enterprise value — exit multiple | F43: =Valuation!C27 -> -1495006.7
A44: Enterprise value — average | F44: =Valuation!B30 -> -1510350.7

Sheet Summary
A1: Financial statements summary | U1: =HYPERLINK("#'Cover'!A1","◂ Contents") -> ◂ Contents
A2: Car wash financial model (planning) | P2: Select detailed year: | R2: 1
A5: Income statement ($'000) — by year | H5: ="Income statement ($'000) — Year "&$R$2&", by month" -> Income statement ($'000) — Year 1, by month
B6: 1 | C6: 2 | D6: 3 | H6: =INDEX(Monthly!$C$4:$AL$4,($R$2-1)*12+1) -> 1 | I6: =INDEX(Monthly!$C$4:$AL$4,($R$2-1)*12+2) -> 2 | J6: =INDEX(Monthly!$C$4:$AL$4,($R$2-1)*12+3) -> 3 | K6: =INDEX(Monthly!$C$4:$AL$4,($R$2-1)*12+4) -> 4 | L6: =INDEX(Monthly!$C$4:$AL$4,($R$2-1)*12+5) -> 5 | M6: =INDEX(Monthly!$C$4:$AL$4,($R$2-1)*12+6) -> 6 | N6: =INDEX(Monthly!$C$4:$AL$4,($R$2-1)*12+7) -> 7 | O6: =INDEX(Monthly!$C$4:$AL$4,($R$2-1)*12+8) -> 8 | P6: =INDEX(Monthly!$C$4:$AL$4,($R$2-1)*12+9) -> 9 | Q6: =INDEX(Monthly!$C$4:$AL$4,($R$2-1)*12+10) -> 10 | R6: =INDEX(Monthly!$C$4:$AL$4,($R$2-1)*12+11) -> 11 | S6: =INDEX(Monthly!$C$4:$AL$4,($R$2-1)*12+12) -> 12
A7: Revenue | B7: ='P&L'!B5 -> 1180182.4 | C7: ='P&L'!C5 -> 1846649 | D7: ='P&L'!D5 -> 2170291.6 | H7: =INDEX(Monthly!$C$37:$AL$37,($R$2-1)*12+1) -> 47943.358 | I7: =INDEX(Monthly!$C$37:$AL$37,($R$2-1)*12+2) -> 54448.936 | J7: =INDEX(Monthly!$C$37:$AL$37,($R$2-1)*12+3) -> 72773.402 | K7: =INDEX(Monthly!$C$37:$AL$37,($R$2-1)*12+4) -> 81051.899 | L7: =INDEX(Monthly!$C$37:$AL$37,($R$2-1)*12+5) -> 89490.276 | M7: =INDEX(Monthly!$C$37:$AL$37,($R$2-1)*12+6) -> 98082.139 | N7: =INDEX(Monthly!$C$37:$AL$37,($R$2-1)*12+7) -> 106821.35 | O7: =INDEX(Monthly!$C$37:$AL$37,($R$2-1)*12+8) -> 115702.01 | P7: =INDEX(Monthly!$C$37:$AL$37,($R$2-1)*12+9) -> 124718.46 | Q7: =INDEX(Monthly!$C$37:$AL$37,($R$2-1)*12+10) -> 133865.28 | R7: =INDEX(Monthly!$C$37:$AL$37,($R$2-1)*12+11) -> 136545.55 | S7: =INDEX(Monthly!$C$37:$AL$37,($R$2-1)*12+12) -> 118739.73
A8: Cost of sales | B8: ='P&L'!B6 -> -180421.6 | C8: ='P&L'!C6 -> -294728 | D8: ='P&L'!D6 -> -357141.25 | H8: =INDEX(Monthly!$C$45:$AL$45,($R$2-1)*12+1) -> -7071.9457 | I8: =INDEX(Monthly!$C$45:$AL$45,($R$2-1)*12+2) -> -8031.4488 | J8: =INDEX(Monthly!$C$45:$AL$45,($R$2-1)*12+3) -> -11076.835 | K8: =INDEX(Monthly!$C$45:$AL$45,($R$2-1)*12+4) -> -12361.697 | L8: =INDEX(Monthly!$C$45:$AL$45,($R$2-1)*12+5) -> -13678.718 | M8: =INDEX(Monthly!$C$45:$AL$45,($R$2-1)*12+6) -> -15026.614 | N8: =INDEX(Monthly!$C$45:$AL$45,($R$2-1)*12+7) -> -16404.147 | O8: =INDEX(Monthly!$C$45:$AL$45,($R$2-1)*12+8) -> -17810.134 | P8: =INDEX(Monthly!$C$45:$AL$45,($R$2-1)*12+9) -> -19243.436 | Q8: =INDEX(Monthly!$C$45:$AL$45,($R$2-1)*12+10) -> -20702.96 | R8: =INDEX(Monthly!$C$45:$AL$45,($R$2-1)*12+11) -> -21242.097 | S8: =INDEX(Monthly!$C$45:$AL$45,($R$2-1)*12+12) -> -17771.565
A9: Gross profit | B9: ='P&L'!B7 -> 999760.79 | C9: ='P&L'!C7 -> 1551921 | D9: ='P&L'!D7 -> 1813150.4 | H9: =INDEX(Monthly!$C$46:$AL$46,($R$2-1)*12+1) -> 40871.412 | I9: =INDEX(Monthly!$C$46:$AL$46,($R$2-1)*12+2) -> 46417.487 | J9: =INDEX(Monthly!$C$46:$AL$46,($R$2-1)*12+3) -> 61696.567 | K9: =INDEX(Monthly!$C$46:$AL$46,($R$2-1)*12+4) -> 68690.202 | L9: =INDEX(Monthly!$C$46:$AL$46,($R$2-1)*12+5) -> 75811.558 | M9: =INDEX(Monthly!$C$46:$AL$46,($R$2-1)*12+6) -> 83055.526 | N9: =INDEX(Monthly!$C$46:$AL$46,($R$2-1)*12+7) -> 90417.201 | O9: =INDEX(Monthly!$C$46:$AL$46,($R$2-1)*12+8) -> 97891.875 | P9: =INDEX(Monthly!$C$46:$AL$46,($R$2-1)*12+9) -> 105475.03 | Q9: =INDEX(Monthly!$C$46:$AL$46,($R$2-1)*12+10) -> 113162.32 | R9: =INDEX(Monthly!$C$46:$AL$46,($R$2-1)*12+11) -> 115303.45 | S9: =INDEX(Monthly!$C$46:$AL$46,($R$2-1)*12+12) -> 100968.16
A10: Gross margin | B10: ='P&L'!B8 -> 0.84712397 | C10: ='P&L'!C8 -> 0.84039848 | D10: ='P&L'!D8 -> 0.83544089 | H10: =IF(H7=0,0,H9/H7) -> 0.85249373 | I10: =IF(I7=0,0,I9/I7) -> 0.85249576 | J10: =IF(J7=0,0,J9/J7) -> 0.84779006 | K10: =IF(K7=0,0,K9/K7) -> 0.84748418 | L10: =IF(L7=0,0,L9/L7) -> 0.84714855 | M10: =IF(M7=0,0,M9/M7) -> 0.84679562 | N10: =IF(N7=0,0,N9/N7) -> 0.84643381 | O10: =IF(O7=0,0,O9/O7) -> 0.84606893 | ... S10: =IF(S7=0,0,S9/S7) -> 0.85033177
A11: Total operating expenses | B11: ='P&L'!B14 -> -1123040 | C11: ='P&L'!C14 -> -1123611.2 | D11: ='P&L'!D14 -> -1130823.5 | H11: =INDEX(Monthly!$C$54:$AL$54,($R$2-1)*12+1) -> -93586.667 | I11: =INDEX(Monthly!$C$54:$AL$54,($R$2-1)*12+2) -> -93586.667 | J11: =INDEX(Monthly!$C$54:$AL$54,($R$2-1)*12+3) -> -93586.667 | K11: =INDEX(Monthly!$C$54:$AL$54,($R$2-1)*12+4) -> -93586.667 | L11: =INDEX(Monthly!$C$54:$AL$54,($R$2-1)*12+5) -> -93586.667 | M11: =INDEX(Monthly!$C$54:$AL$54,($R$2-1)*12+6) -> -93586.667 | N11: =INDEX(Monthly!$C$54:$AL$54,($R$2-1)*12+7) -> -93586.667 | O11: =INDEX(Monthly!$C$54:$AL$54,($R$2-1)*12+8) -> -93586.667 | P11: =INDEX(Monthly!$C$54:$AL$54,($R$2-1)*12+9) -> -93586.667 | Q11: =INDEX(Monthly!$C$54:$AL$54,($R$2-1)*12+10) -> -93586.667 | R11: =INDEX(Monthly!$C$54:$AL$54,($R$2-1)*12+11) -> -93586.667 | S11: =INDEX(Monthly!$C$54:$AL$54,($R$2-1)*12+12) -> -93586.667
A12: EBITDA | B12: ='P&L'!B15 -> -123279.21 | C12: ='P&L'!C15 -> 428309.82 | D12: ='P&L'!D15 -> 682326.82 | H12: =INDEX(Monthly!$C$55:$AL$55,($R$2-1)*12+1) -> -52715.254 | I12: =INDEX(Monthly!$C$55:$AL$55,($R$2-1)*12+2) -> -47169.18 | J12: =INDEX(Monthly!$C$55:$AL$55,($R$2-1)*12+3) -> -31890.1 | K12: =INDEX(Monthly!$C$55:$AL$55,($R$2-1)*12+4) -> -24896.465 | L12: =INDEX(Monthly!$C$55:$AL$55,($R$2-1)*12+5) -> -17775.109 | M12: =INDEX(Monthly!$C$55:$AL$55,($R$2-1)*12+6) -> -10531.141 | N12: =INDEX(Monthly!$C$55:$AL$55,($R$2-1)*12+7) -> -3169.4659 | O12: =INDEX(Monthly!$C$55:$AL$55,($R$2-1)*12+8) -> 4305.2082 | P12: =INDEX(Monthly!$C$55:$AL$55,($R$2-1)*12+9) -> 11888.361 | Q12: =INDEX(Monthly!$C$55:$AL$55,($R$2-1)*12+10) -> 19575.654 | R12: =INDEX(Monthly!$C$55:$AL$55,($R$2-1)*12+11) -> 21716.787 | S12: =INDEX(Monthly!$C$55:$AL$55,($R$2-1)*12+12) -> 7381.4964
A13: EBITDA margin | B13: ='P&L'!B16 -> -0.10445776 | C13: ='P&L'!C16 -> 0.23193894 | D13: ='P&L'!D16 -> 0.31439407 | H13: =IF(H7=0,0,H12/H7) -> -1.099532 | I13: =IF(I7=0,0,I12/I7) -> -0.86630122 | J13: =IF(J7=0,0,J12/J7) -> -0.43821093 | K13: =IF(K7=0,0,K12/K7) -> -0.30716695 | L13: =IF(L7=0,0,L12/L7) -> -0.19862615 | M13: =IF(M7=0,0,M12/M7) -> -0.10737063 | N13: =IF(N7=0,0,N12/N7) -> -0.029670716 | O13: =IF(O7=0,0,O12/O7) -> 0.03720945 | ... S13: =IF(S7=0,0,S12/S7) -> 0.062165347
A14: Depreciation | B14: ='P&L'!B17 -> -341666.67 | C14: ='P&L'!C17 -> -345000 | D14: ='P&L'!D17 -> -348333.33 | H14: =INDEX(Monthly!$C$75:$AL$75,($R$2-1)*12+1) -> -28472.222 | I14: =INDEX(Monthly!$C$75:$AL$75,($R$2-1)*12+2) -> -28472.222 | J14: =INDEX(Monthly!$C$75:$AL$75,($R$2-1)*12+3) -> -28472.222 | K14: =INDEX(Monthly!$C$75:$AL$75,($R$2-1)*12+4) -> -28472.222 | L14: =INDEX(Monthly!$C$75:$AL$75,($R$2-1)*12+5) -> -28472.222 | M14: =INDEX(Monthly!$C$75:$AL$75,($R$2-1)*12+6) -> -28472.222 | N14: =INDEX(Monthly!$C$75:$AL$75,($R$2-1)*12+7) -> -28472.222 | O14: =INDEX(Monthly!$C$75:$AL$75,($R$2-1)*12+8) -> -28472.222 | P14: =INDEX(Monthly!$C$75:$AL$75,($R$2-1)*12+9) -> -28472.222 | Q14: =INDEX(Monthly!$C$75:$AL$75,($R$2-1)*12+10) -> -28472.222 | R14: =INDEX(Monthly!$C$75:$AL$75,($R$2-1)*12+11) -> -28472.222 | S14: =INDEX(Monthly!$C$75:$AL$75,($R$2-1)*12+12) -> -28472.222
A15: EBIT | B15: ='P&L'!B18 -> -464945.87 | C15: ='P&L'!C18 -> 83309.822 | D15: ='P&L'!D18 -> 333993.48 | H15: =INDEX(Monthly!$C$58:$AL$58,($R$2-1)*12+1) -> -81187.477 | I15: =INDEX(Monthly!$C$58:$AL$58,($R$2-1)*12+2) -> -75641.402 | J15: =INDEX(Monthly!$C$58:$AL$58,($R$2-1)*12+3) -> -60362.322 | K15: =INDEX(Monthly!$C$58:$AL$58,($R$2-1)*12+4) -> -53368.687 | L15: =INDEX(Monthly!$C$58:$AL$58,($R$2-1)*12+5) -> -46247.331 | M15: =INDEX(Monthly!$C$58:$AL$58,($R$2-1)*12+6) -> -39003.363 | N15: =INDEX(Monthly!$C$58:$AL$58,($R$2-1)*12+7) -> -31641.688 | O15: =INDEX(Monthly!$C$58:$AL$58,($R$2-1)*12+8) -> -24167.014 | P15: =INDEX(Monthly!$C$58:$AL$58,($R$2-1)*12+9) -> -16583.861 | Q15: =INDEX(Monthly!$C$58:$AL$58,($R$2-1)*12+10) -> -8896.568 | R15: =INDEX(Monthly!$C$58:$AL$58,($R$2-1)*12+11) -> -6755.4353 | S15: =INDEX(Monthly!$C$58:$AL$58,($R$2-1)*12+12) -> -21090.726
A16: Interest | B16: ='P&L'!B19 -> -244286.46 | C16: ='P&L'!C19 -> -218875 | D16: ='P&L'!D19 -> -193375 | H16: =INDEX(Monthly!$C$59:$AL$59,($R$2-1)*12+1) -> -21250 | I16: =INDEX(Monthly!$C$59:$AL$59,($R$2-1)*12+2) -> -21161.458 | J16: =INDEX(Monthly!$C$59:$AL$59,($R$2-1)*12+3) -> -20984.375 | K16: =INDEX(Monthly!$C$59:$AL$59,($R$2-1)*12+4) -> -20807.292 | L16: =INDEX(Monthly!$C$59:$AL$59,($R$2-1)*12+5) -> -20630.208 | M16: =INDEX(Monthly!$C$59:$AL$59,($R$2-1)*12+6) -> -20453.125 | N16: =INDEX(Monthly!$C$59:$AL$59,($R$2-1)*12+7) -> -20276.042 | O16: =INDEX(Monthly!$C$59:$AL$59,($R$2-1)*12+8) -> -20098.958 | P16: =INDEX(Monthly!$C$59:$AL$59,($R$2-1)*12+9) -> -19921.875 | Q16: =INDEX(Monthly!$C$59:$AL$59,($R$2-1)*12+10) -> -19744.792 | R16: =INDEX(Monthly!$C$59:$AL$59,($R$2-1)*12+11) -> -19567.708 | S16: =INDEX(Monthly!$C$59:$AL$59,($R$2-1)*12+12) -> -19390.625
A17: Pre-tax income | B17: ='P&L'!B20 -> -709232.33 | C17: ='P&L'!C20 -> -135565.18 | D17: ='P&L'!D20 -> 140618.48 | H17: =INDEX(Monthly!$C$60:$AL$60,($R$2-1)*12+1) -> -102437.48 | I17: =INDEX(Monthly!$C$60:$AL$60,($R$2-1)*12+2) -> -96802.86 | J17: =INDEX(Monthly!$C$60:$AL$60,($R$2-1)*12+3) -> -81346.697 | K17: =INDEX(Monthly!$C$60:$AL$60,($R$2-1)*12+4) -> -74175.979 | L17: =INDEX(Monthly!$C$60:$AL$60,($R$2-1)*12+5) -> -66877.539 | M17: =INDEX(Monthly!$C$60:$AL$60,($R$2-1)*12+6) -> -59456.488 | N17: =INDEX(Monthly!$C$60:$AL$60,($R$2-1)*12+7) -> -51917.73 | O17: =INDEX(Monthly!$C$60:$AL$60,($R$2-1)*12+8) -> -44265.972 | P17: =INDEX(Monthly!$C$60:$AL$60,($R$2-1)*12+9) -> -36505.736 | Q17: =INDEX(Monthly!$C$60:$AL$60,($R$2-1)*12+10) -> -28641.36 | R17: =INDEX(Monthly!$C$60:$AL$60,($R$2-1)*12+11) -> -26323.144 | S17: =INDEX(Monthly!$C$60:$AL$60,($R$2-1)*12+12) -> -40481.351
A18: Income tax | B18: ='P&L'!B21 -> 0 | C18: ='P&L'!C21 -> 0 | D18: ='P&L'!D21 -> 0 | H18: =INDEX(Monthly!$C$63:$AL$63,($R$2-1)*12+1) -> 0 | I18: =INDEX(Monthly!$C$63:$AL$63,($R$2-1)*12+2) -> 0 | J18: =INDEX(Monthly!$C$63:$AL$63,($R$2-1)*12+3) -> 0 | K18: =INDEX(Monthly!$C$63:$AL$63,($R$2-1)*12+4) -> 0 | L18: =INDEX(Monthly!$C$63:$AL$63,($R$2-1)*12+5) -> 0 | M18: =INDEX(Monthly!$C$63:$AL$63,($R$2-1)*12+6) -> 0 | N18: =INDEX(Monthly!$C$63:$AL$63,($R$2-1)*12+7) -> 0 | O18: =INDEX(Monthly!$C$63:$AL$63,($R$2-1)*12+8) -> 0 | P18: =INDEX(Monthly!$C$63:$AL$63,($R$2-1)*12+9) -> 0 | Q18: =INDEX(Monthly!$C$63:$AL$63,($R$2-1)*12+10) -> 0 | R18: =INDEX(Monthly!$C$63:$AL$63,($R$2-1)*12+11) -> 0 | S18: =INDEX(Monthly!$C$63:$AL$63,($R$2-1)*12+12) -> 0
A19: Net income | B19: ='P&L'!B22 -> -709232.33 | C19: ='P&L'!C22 -> -135565.18 | D19: ='P&L'!D22 -> 140618.48 | H19: =INDEX(Monthly!$C$64:$AL$64,($R$2-1)*12+1) -> -102437.48 | I19: =INDEX(Monthly!$C$64:$AL$64,($R$2-1)*12+2) -> -96802.86 | J19: =INDEX(Monthly!$C$64:$AL$64,($R$2-1)*12+3) -> -81346.697 | K19: =INDEX(Monthly!$C$64:$AL$64,($R$2-1)*12+4) -> -74175.979 | L19: =INDEX(Monthly!$C$64:$AL$64,($R$2-1)*12+5) -> -66877.539 | M19: =INDEX(Monthly!$C$64:$AL$64,($R$2-1)*12+6) -> -59456.488 | N19: =INDEX(Monthly!$C$64:$AL$64,($R$2-1)*12+7) -> -51917.73 | O19: =INDEX(Monthly!$C$64:$AL$64,($R$2-1)*12+8) -> -44265.972 | P19: =INDEX(Monthly!$C$64:$AL$64,($R$2-1)*12+9) -> -36505.736 | Q19: =INDEX(Monthly!$C$64:$AL$64,($R$2-1)*12+10) -> -28641.36 | R19: =INDEX(Monthly!$C$64:$AL$64,($R$2-1)*12+11) -> -26323.144 | S19: =INDEX(Monthly!$C$64:$AL$64,($R$2-1)*12+12) -> -40481.351
A20: Net margin | B20: ='P&L'!B23 -> -0.60095146 | C20: ='P&L'!C23 -> -0.073411448 | D20: ='P&L'!D23 -> 0.064792437 | H20: =IF(H7=0,0,H19/H7) -> -2.1366354 | I20: =IF(I7=0,0,I19/I7) -> -1.777865 | J20: =IF(J7=0,0,J19/J7) -> -1.1178081 | K20: =IF(K7=0,0,K19/K7) -> -0.91516645 | L20: =IF(L7=0,0,L19/L7) -> -0.74731627 | M20: =IF(M7=0,0,M19/M7) -> -0.60619078 | N20: =IF(N7=0,0,N19/N7) -> -0.48602391 | O20: =IF(O7=0,0,O19/O7) -> -0.38258603 | ... S20: =IF(S7=0,0,S19/S7) -> -0.34092508
A22: Cash flow ($'000) — by year | H22: ="Cash flow ($'000) — Year "&$R$2&", by month" -> Cash flow ($'000) — Year 1, by month
B23: 1 | C23: 2 | D23: 3 | H23: =INDEX(Monthly!$C$4:$AL$4,($R$2-1)*12+1) -> 1 | I23: =INDEX(Monthly!$C$4:$AL$4,($R$2-1)*12+2) -> 2 | J23: =INDEX(Monthly!$C$4:$AL$4,($R$2-1)*12+3) -> 3 | K23: =INDEX(Monthly!$C$4:$AL$4,($R$2-1)*12+4) -> 4 | L23: =INDEX(Monthly!$C$4:$AL$4,($R$2-1)*12+5) -> 5 | M23: =INDEX(Monthly!$C$4:$AL$4,($R$2-1)*12+6) -> 6 | N23: =INDEX(Monthly!$C$4:$AL$4,($R$2-1)*12+7) -> 7 | O23: =INDEX(Monthly!$C$4:$AL$4,($R$2-1)*12+8) -> 8 | P23: =INDEX(Monthly!$C$4:$AL$4,($R$2-1)*12+9) -> 9 | Q23: =INDEX(Monthly!$C$4:$AL$4,($R$2-1)*12+10) -> 10 | R23: =INDEX(Monthly!$C$4:$AL$4,($R$2-1)*12+11) -> 11 | S23: =INDEX(Monthly!$C$4:$AL$4,($R$2-1)*12+12) -> 12
A24: Operating cash flow | B24: ='Cash Flow'!B10 -> -367780.64 | C24: ='Cash Flow'!C10 -> 209654.47 | D24: ='Cash Flow'!D10 -> 489150.48 | H24: =INDEX(Monthly!$C$94:$AL$94,($R$2-1)*12+1) -> -74096.968 | I24: =INDEX(Monthly!$C$94:$AL$94,($R$2-1)*12+2) -> -68348.558 | J24: =INDEX(Monthly!$C$94:$AL$94,($R$2-1)*12+3) -> -52776.439 | K24: =INDEX(Monthly!$C$94:$AL$94,($R$2-1)*12+4) -> -45698.883 | L24: =INDEX(Monthly!$C$94:$AL$94,($R$2-1)*12+5) -> -38397.166 | M24: =INDEX(Monthly!$C$94:$AL$94,($R$2-1)*12+6) -> -30972.969 | N24: =INDEX(Monthly!$C$94:$AL$94,($R$2-1)*12+7) -> -23431.19 | O24: =INDEX(Monthly!$C$94:$AL$94,($R$2-1)*12+8) -> -15776.533 | P24: =INDEX(Monthly!$C$94:$AL$94,($R$2-1)*12+9) -> -8013.5132 | Q24: =INDEX(Monthly!$C$94:$AL$94,($R$2-1)*12+10) -> -146.46471 | R24: =INDEX(Monthly!$C$94:$AL$94,($R$2-1)*12+11) -> 2204.0197 | S24: =INDEX(Monthly!$C$94:$AL$94,($R$2-1)*12+12) -> -12325.971
A25: Capital spending | B25: ='Cash Flow'!B11 -> -4100000 | C25: ='Cash Flow'!C11 -> -40000 | D25: ='Cash Flow'!D11 -> -40000 | H25: =INDEX(Monthly!$C$95:$AL$95,($R$2-1)*12+1) -> -4100000 | I25: =INDEX(Monthly!$C$95:$AL$95,($R$2-1)*12+2) -> 0 | J25: =INDEX(Monthly!$C$95:$AL$95,($R$2-1)*12+3) -> 0 | K25: =INDEX(Monthly!$C$95:$AL$95,($R$2-1)*12+4) -> 0 | L25: =INDEX(Monthly!$C$95:$AL$95,($R$2-1)*12+5) -> 0 | M25: =INDEX(Monthly!$C$95:$AL$95,($R$2-1)*12+6) -> 0 | N25: =INDEX(Monthly!$C$95:$AL$95,($R$2-1)*12+7) -> 0 | O25: =INDEX(Monthly!$C$95:$AL$95,($R$2-1)*12+8) -> 0 | P25: =INDEX(Monthly!$C$95:$AL$95,($R$2-1)*12+9) -> 0 | Q25: =INDEX(Monthly!$C$95:$AL$95,($R$2-1)*12+10) -> 0 | R25: =INDEX(Monthly!$C$95:$AL$95,($R$2-1)*12+11) -> 0 | S25: =INDEX(Monthly!$C$95:$AL$95,($R$2-1)*12+12) -> 0
A26: Equity raised | B26: ='Cash Flow'!B12 -> 2100000 | C26: ='Cash Flow'!C12 -> 0 | D26: ='Cash Flow'!D12 -> 0 | H26: =INDEX(Monthly!$C$96:$AL$96,($R$2-1)*12+1) -> 2100000 | I26: =INDEX(Monthly!$C$96:$AL$96,($R$2-1)*12+2) -> 0 | J26: =INDEX(Monthly!$C$96:$AL$96,($R$2-1)*12+3) -> 0 | K26: =INDEX(Monthly!$C$96:$AL$96,($R$2-1)*12+4) -> 0 | L26: =INDEX(Monthly!$C$96:$AL$96,($R$2-1)*12+5) -> 0 | M26: =INDEX(Monthly!$C$96:$AL$96,($R$2-1)*12+6) -> 0 | N26: =INDEX(Monthly!$C$96:$AL$96,($R$2-1)*12+7) -> 0 | O26: =INDEX(Monthly!$C$96:$AL$96,($R$2-1)*12+8) -> 0 | P26: =INDEX(Monthly!$C$96:$AL$96,($R$2-1)*12+9) -> 0 | Q26: =INDEX(Monthly!$C$96:$AL$96,($R$2-1)*12+10) -> 0 | R26: =INDEX(Monthly!$C$96:$AL$96,($R$2-1)*12+11) -> 0 | S26: =INDEX(Monthly!$C$96:$AL$96,($R$2-1)*12+12) -> 0
A27: Loan drawdown | B27: ='Cash Flow'!B13 -> 3000000 | C27: ='Cash Flow'!C13 -> 0 | D27: ='Cash Flow'!D13 -> 0 | H27: =INDEX(Monthly!$C$81:$AL$81,($R$2-1)*12+1) -> 3000000 | I27: =INDEX(Monthly!$C$81:$AL$81,($R$2-1)*12+2) -> 0 | J27: =INDEX(Monthly!$C$81:$AL$81,($R$2-1)*12+3) -> 0 | K27: =INDEX(Monthly!$C$81:$AL$81,($R$2-1)*12+4) -> 0 | L27: =INDEX(Monthly!$C$81:$AL$81,($R$2-1)*12+5) -> 0 | M27: =INDEX(Monthly!$C$81:$AL$81,($R$2-1)*12+6) -> 0 | N27: =INDEX(Monthly!$C$81:$AL$81,($R$2-1)*12+7) -> 0 | O27: =INDEX(Monthly!$C$81:$AL$81,($R$2-1)*12+8) -> 0 | P27: =INDEX(Monthly!$C$81:$AL$81,($R$2-1)*12+9) -> 0 | Q27: =INDEX(Monthly!$C$81:$AL$81,($R$2-1)*12+10) -> 0 | R27: =INDEX(Monthly!$C$81:$AL$81,($R$2-1)*12+11) -> 0 | S27: =INDEX(Monthly!$C$81:$AL$81,($R$2-1)*12+12) -> 0
A28: Loan repayment | B28: ='Cash Flow'!B14 -> -275000 | C28: ='Cash Flow'!C14 -> -300000 | D28: ='Cash Flow'!D14 -> -300000 | H28: =INDEX(Monthly!$C$82:$AL$82,($R$2-1)*12+1) -> 0 | I28: =INDEX(Monthly!$C$82:$AL$82,($R$2-1)*12+2) -> -25000 | J28: =INDEX(Monthly!$C$82:$AL$82,($R$2-1)*12+3) -> -25000 | K28: =INDEX(Monthly!$C$82:$AL$82,($R$2-1)*12+4) -> -25000 | L28: =INDEX(Monthly!$C$82:$AL$82,($R$2-1)*12+5) -> -25000 | M28: =INDEX(Monthly!$C$82:$AL$82,($R$2-1)*12+6) -> -25000 | N28: =INDEX(Monthly!$C$82:$AL$82,($R$2-1)*12+7) -> -25000 | O28: =INDEX(Monthly!$C$82:$AL$82,($R$2-1)*12+8) -> -25000 | P28: =INDEX(Monthly!$C$82:$AL$82,($R$2-1)*12+9) -> -25000 | Q28: =INDEX(Monthly!$C$82:$AL$82,($R$2-1)*12+10) -> -25000 | R28: =INDEX(Monthly!$C$82:$AL$82,($R$2-1)*12+11) -> -25000 | S28: =INDEX(Monthly!$C$82:$AL$82,($R$2-1)*12+12) -> -25000
A29: Financing cash flow | B29: ='Cash Flow'!B15 -> 4825000 | C29: ='Cash Flow'!C15 -> -300000 | D29: ='Cash Flow'!D15 -> -300000 | H29: =INDEX(Monthly!$C$97:$AL$97,($R$2-1)*12+1) -> 5100000 | I29: =INDEX(Monthly!$C$97:$AL$97,($R$2-1)*12+2) -> -25000 | J29: =INDEX(Monthly!$C$97:$AL$97,($R$2-1)*12+3) -> -25000 | K29: =INDEX(Monthly!$C$97:$AL$97,($R$2-1)*12+4) -> -25000 | L29: =INDEX(Monthly!$C$97:$AL$97,($R$2-1)*12+5) -> -25000 | M29: =INDEX(Monthly!$C$97:$AL$97,($R$2-1)*12+6) -> -25000 | N29: =INDEX(Monthly!$C$97:$AL$97,($R$2-1)*12+7) -> -25000 | O29: =INDEX(Monthly!$C$97:$AL$97,($R$2-1)*12+8) -> -25000 | P29: =INDEX(Monthly!$C$97:$AL$97,($R$2-1)*12+9) -> -25000 | Q29: =INDEX(Monthly!$C$97:$AL$97,($R$2-1)*12+10) -> -25000 | R29: =INDEX(Monthly!$C$97:$AL$97,($R$2-1)*12+11) -> -25000 | S29: =INDEX(Monthly!$C$97:$AL$97,($R$2-1)*12+12) -> -25000
A30: Net change in cash | B30: ='Cash Flow'!B16 -> 357219.36 | C30: ='Cash Flow'!C16 -> -130345.53 | D30: ='Cash Flow'!D16 -> 149150.48 | H30: =INDEX(Monthly!$C$98:$AL$98,($R$2-1)*12+1) -> 925903.03 | I30: =INDEX(Monthly!$C$98:$AL$98,($R$2-1)*12+2) -> -93348.558 | J30: =INDEX(Monthly!$C$98:$AL$98,($R$2-1)*12+3) -> -77776.439 | K30: =INDEX(Monthly!$C$98:$AL$98,($R$2-1)*12+4) -> -70698.883 | L30: =INDEX(Monthly!$C$98:$AL$98,($R$2-1)*12+5) -> -63397.166 | M30: =INDEX(Monthly!$C$98:$AL$98,($R$2-1)*12+6) -> -55972.969 | N30: =INDEX(Monthly!$C$98:$AL$98,($R$2-1)*12+7) -> -48431.19 | O30: =INDEX(Monthly!$C$98:$AL$98,($R$2-1)*12+8) -> -40776.533 | P30: =INDEX(Monthly!$C$98:$AL$98,($R$2-1)*12+9) -> -33013.513 | Q30: =INDEX(Monthly!$C$98:$AL$98,($R$2-1)*12+10) -> -25146.465 | R30: =INDEX(Monthly!$C$98:$AL$98,($R$2-1)*12+11) -> -22795.98 | S30: =INDEX(Monthly!$C$98:$AL$98,($R$2-1)*12+12) -> -37325.971
A31: Closing cash | B31: ='Cash Flow'!B18 -> 357219.36 | C31: ='Cash Flow'!C18 -> 226873.84 | D31: ='Cash Flow'!D18 -> 376024.31 | H31: =INDEX(Monthly!$C$100:$AL$100,($R$2-1)*12+1) -> 925903.03 | I31: =INDEX(Monthly!$C$100:$AL$100,($R$2-1)*12+2) -> 832554.47 | J31: =INDEX(Monthly!$C$100:$AL$100,($R$2-1)*12+3) -> 754778.03 | K31: =INDEX(Monthly!$C$100:$AL$100,($R$2-1)*12+4) -> 684079.15 | L31: =INDEX(Monthly!$C$100:$AL$100,($R$2-1)*12+5) -> 620681.99 | M31: =INDEX(Monthly!$C$100:$AL$100,($R$2-1)*12+6) -> 564709.02 | N31: =INDEX(Monthly!$C$100:$AL$100,($R$2-1)*12+7) -> 516277.83 | O31: =INDEX(Monthly!$C$100:$AL$100,($R$2-1)*12+8) -> 475501.29 | P31: =INDEX(Monthly!$C$100:$AL$100,($R$2-1)*12+9) -> 442487.78 | Q31: =INDEX(Monthly!$C$100:$AL$100,($R$2-1)*12+10) -> 417341.32 | R31: =INDEX(Monthly!$C$100:$AL$100,($R$2-1)*12+11) -> 394545.33 | S31: =INDEX(Monthly!$C$100:$AL$100,($R$2-1)*12+12) -> 357219.36
A39: Balance sheet at year end ($'000) | H39: ="Balance sheet at month end ($'000) — Year "&$R$2 -> Balance sheet at month end ($'000) — Year 1
B40: 1 | C40: 2 | D40: 3 | H40: =INDEX(Monthly!$C$4:$AL$4,($R$2-1)*12+1) -> 1 | I40: =INDEX(Monthly!$C$4:$AL$4,($R$2-1)*12+2) -> 2 | J40: =INDEX(Monthly!$C$4:$AL$4,($R$2-1)*12+3) -> 3 | K40: =INDEX(Monthly!$C$4:$AL$4,($R$2-1)*12+4) -> 4 | L40: =INDEX(Monthly!$C$4:$AL$4,($R$2-1)*12+5) -> 5 | M40: =INDEX(Monthly!$C$4:$AL$4,($R$2-1)*12+6) -> 6 | N40: =INDEX(Monthly!$C$4:$AL$4,($R$2-1)*12+7) -> 7 | O40: =INDEX(Monthly!$C$4:$AL$4,($R$2-1)*12+8) -> 8 | P40: =INDEX(Monthly!$C$4:$AL$4,($R$2-1)*12+9) -> 9 | Q40: =INDEX(Monthly!$C$4:$AL$4,($R$2-1)*12+10) -> 10 | R40: =INDEX(Monthly!$C$4:$AL$4,($R$2-1)*12+11) -> 11 | S40: =INDEX(Monthly!$C$4:$AL$4,($R$2-1)*12+12) -> 12
A41: Cash | B41: ='Balance Sheet'!B5 -> 357219.36 | C41: ='Balance Sheet'!C5 -> 226873.84 | D41: ='Balance Sheet'!D5 -> 376024.31 | H41: =INDEX(Monthly!$C$100:$AL$100,($R$2-1)*12+1) -> 925903.03 | I41: =INDEX(Monthly!$C$100:$AL$100,($R$2-1)*12+2) -> 832554.47 | J41: =INDEX(Monthly!$C$100:$AL$100,($R$2-1)*12+3) -> 754778.03 | K41: =INDEX(Monthly!$C$100:$AL$100,($R$2-1)*12+4) -> 684079.15 | L41: =INDEX(Monthly!$C$100:$AL$100,($R$2-1)*12+5) -> 620681.99 | M41: =INDEX(Monthly!$C$100:$AL$100,($R$2-1)*12+6) -> 564709.02 | N41: =INDEX(Monthly!$C$100:$AL$100,($R$2-1)*12+7) -> 516277.83 | O41: =INDEX(Monthly!$C$100:$AL$100,($R$2-1)*12+8) -> 475501.29 | P41: =INDEX(Monthly!$C$100:$AL$100,($R$2-1)*12+9) -> 442487.78 | Q41: =INDEX(Monthly!$C$100:$AL$100,($R$2-1)*12+10) -> 417341.32 | R41: =INDEX(Monthly!$C$100:$AL$100,($R$2-1)*12+11) -> 394545.33 | S41: =INDEX(Monthly!$C$100:$AL$100,($R$2-1)*12+12) -> 357219.36
A42: Accounts receivable | B42: ='Balance Sheet'!B6 -> 7915.9819 | C42: ='Balance Sheet'!C6 -> 9917.125 | D42: ='Balance Sheet'!D6 -> 11443.887 | H42: =INDEX(Monthly!$C$86:$AL$86,($R$2-1)*12+1) -> 3196.2239 | I42: =INDEX(Monthly!$C$86:$AL$86,($R$2-1)*12+2) -> 3629.9291 | J42: =INDEX(Monthly!$C$86:$AL$86,($R$2-1)*12+3) -> 4851.5601 | K42: =INDEX(Monthly!$C$86:$AL$86,($R$2-1)*12+4) -> 5403.4599 | L42: =INDEX(Monthly!$C$86:$AL$86,($R$2-1)*12+5) -> 5966.0184 | M42: =INDEX(Monthly!$C$86:$AL$86,($R$2-1)*12+6) -> 6538.8093 | N42: =INDEX(Monthly!$C$86:$AL$86,($R$2-1)*12+7) -> 7121.4232 | O42: =INDEX(Monthly!$C$86:$AL$86,($R$2-1)*12+8) -> 7713.4673 | P42: =INDEX(Monthly!$C$86:$AL$86,($R$2-1)*12+9) -> 8314.5643 | Q42: =INDEX(Monthly!$C$86:$AL$86,($R$2-1)*12+10) -> 8924.3521 | R42: =INDEX(Monthly!$C$86:$AL$86,($R$2-1)*12+11) -> 9103.0367 | S42: =INDEX(Monthly!$C$86:$AL$86,($R$2-1)*12+12) -> 7915.9819
A43: Inventory | B43: ='Balance Sheet'!B7 -> 4146.6985 | C43: ='Balance Sheet'!C7 -> 5342.5115 | D43: ='Balance Sheet'!D7 -> 6271.585 | H43: =INDEX(Monthly!$C$87:$AL$87,($R$2-1)*12+1) -> 1650.1207 | I43: =INDEX(Monthly!$C$87:$AL$87,($R$2-1)*12+2) -> 1874.0047 | J43: =INDEX(Monthly!$C$87:$AL$87,($R$2-1)*12+3) -> 2584.5949 | K43: =INDEX(Monthly!$C$87:$AL$87,($R$2-1)*12+4) -> 2884.3959 | L43: =INDEX(Monthly!$C$87:$AL$87,($R$2-1)*12+5) -> 3191.701 | M43: =INDEX(Monthly!$C$87:$AL$87,($R$2-1)*12+6) -> 3506.2099 | N43: =INDEX(Monthly!$C$87:$AL$87,($R$2-1)*12+7) -> 3827.6344 | O43: =INDEX(Monthly!$C$87:$AL$87,($R$2-1)*12+8) -> 4155.698 | P43: =INDEX(Monthly!$C$87:$AL$87,($R$2-1)*12+9) -> 4490.1351 | Q43: =INDEX(Monthly!$C$87:$AL$87,($R$2-1)*12+10) -> 4830.6908 | R43: =INDEX(Monthly!$C$87:$AL$87,($R$2-1)*12+11) -> 4956.4892 | S43: =INDEX(Monthly!$C$87:$AL$87,($R$2-1)*12+12) -> 4146.6985
A44: Net fixed assets | B44: ='Balance Sheet'!B8 -> 3758333.3 | C44: ='Balance Sheet'!C8 -> 3453333.3 | D44: ='Balance Sheet'!D8 -> 3145000 | H44: =INDEX(Monthly!$C$77:$AL$77,($R$2-1)*12+1) -> 4071527.8 | I44: =INDEX(Monthly!$C$77:$AL$77,($R$2-1)*12+2) -> 4043055.6 | J44: =INDEX(Monthly!$C$77:$AL$77,($R$2-1)*12+3) -> 4014583.3 | K44: =INDEX(Monthly!$C$77:$AL$77,($R$2-1)*12+4) -> 3986111.1 | L44: =INDEX(Monthly!$C$77:$AL$77,($R$2-1)*12+5) -> 3957638.9 | M44: =INDEX(Monthly!$C$77:$AL$77,($R$2-1)*12+6) -> 3929166.7 | N44: =INDEX(Monthly!$C$77:$AL$77,($R$2-1)*12+7) -> 3900694.4 | O44: =INDEX(Monthly!$C$77:$AL$77,($R$2-1)*12+8) -> 3872222.2 | P44: =INDEX(Monthly!$C$77:$AL$77,($R$2-1)*12+9) -> 3843750 | Q44: =INDEX(Monthly!$C$77:$AL$77,($R$2-1)*12+10) -> 3815277.8 | R44: =INDEX(Monthly!$C$77:$AL$77,($R$2-1)*12+11) -> 3786805.6 | S44: =INDEX(Monthly!$C$77:$AL$77,($R$2-1)*12+12) -> 3758333.3
A45: Total assets | B45: ='Balance Sheet'!B9 -> 4127615.4 | C45: ='Balance Sheet'!C9 -> 3695466.8 | D45: ='Balance Sheet'!D9 -> 3538739.8 | H45: =INDEX(Monthly!$C$114:$AL$114,($R$2-1)*12+1) -> 5002277.2 | I45: =INDEX(Monthly!$C$114:$AL$114,($R$2-1)*12+2) -> 4881114 | J45: =INDEX(Monthly!$C$114:$AL$114,($R$2-1)*12+3) -> 4776797.5 | K45: =INDEX(Monthly!$C$114:$AL$114,($R$2-1)*12+4) -> 4678478.1 | L45: =INDEX(Monthly!$C$114:$AL$114,($R$2-1)*12+5) -> 4587478.6 | M45: =INDEX(Monthly!$C$114:$AL$114,($R$2-1)*12+6) -> 4503920.7 | N45: =INDEX(Monthly!$C$114:$AL$114,($R$2-1)*12+7) -> 4427921.3 | O45: =INDEX(Monthly!$C$114:$AL$114,($R$2-1)*12+8) -> 4359592.7 | P45: =INDEX(Monthly!$C$114:$AL$114,($R$2-1)*12+9) -> 4299042.5 | Q45: =INDEX(Monthly!$C$114:$AL$114,($R$2-1)*12+10) -> 4246374.1 | R45: =INDEX(Monthly!$C$114:$AL$114,($R$2-1)*12+11) -> 4195410.4 | S45: =INDEX(Monthly!$C$114:$AL$114,($R$2-1)*12+12) -> 4127615.4
A46: Accounts payable | B46: ='Balance Sheet'!B10 -> 11847.71 | C46: ='Balance Sheet'!C10 -> 15264.319 | D46: ='Balance Sheet'!D10 -> 17918.814 | H46: =INDEX(Monthly!$C$88:$AL$88,($R$2-1)*12+1) -> 4714.6305 | I46: =INDEX(Monthly!$C$88:$AL$88,($R$2-1)*12+2) -> 5354.2992 | J46: =INDEX(Monthly!$C$88:$AL$88,($R$2-1)*12+3) -> 7384.5568 | K46: =INDEX(Monthly!$C$88:$AL$88,($R$2-1)*12+4) -> 8241.1313 | L46: =INDEX(Monthly!$C$88:$AL$88,($R$2-1)*12+5) -> 9119.1457 | M46: =INDEX(Monthly!$C$88:$AL$88,($R$2-1)*12+6) -> 10017.742 | N46: =INDEX(Monthly!$C$88:$AL$88,($R$2-1)*12+7) -> 10936.098 | O46: =INDEX(Monthly!$C$88:$AL$88,($R$2-1)*12+8) -> 11873.423 | P46: =INDEX(Monthly!$C$88:$AL$88,($R$2-1)*12+9) -> 12828.957 | Q46: =INDEX(Monthly!$C$88:$AL$88,($R$2-1)*12+10) -> 13801.974 | R46: =INDEX(Monthly!$C$88:$AL$88,($R$2-1)*12+11) -> 14161.398 | S46: =INDEX(Monthly!$C$88:$AL$88,($R$2-1)*12+12) -> 11847.71
A47: Loan | B47: ='Balance Sheet'!B11 -> 2725000 | C47: ='Balance Sheet'!C11 -> 2425000 | D47: ='Balance Sheet'!D11 -> 2125000 | H47: =INDEX(Monthly!$C$83:$AL$83,($R$2-1)*12+1) -> 3000000 | I47: =INDEX(Monthly!$C$83:$AL$83,($R$2-1)*12+2) -> 2975000 | J47: =INDEX(Monthly!$C$83:$AL$83,($R$2-1)*12+3) -> 2950000 | K47: =INDEX(Monthly!$C$83:$AL$83,($R$2-1)*12+4) -> 2925000 | L47: =INDEX(Monthly!$C$83:$AL$83,($R$2-1)*12+5) -> 2900000 | M47: =INDEX(Monthly!$C$83:$AL$83,($R$2-1)*12+6) -> 2875000 | N47: =INDEX(Monthly!$C$83:$AL$83,($R$2-1)*12+7) -> 2850000 | O47: =INDEX(Monthly!$C$83:$AL$83,($R$2-1)*12+8) -> 2825000 | P47: =INDEX(Monthly!$C$83:$AL$83,($R$2-1)*12+9) -> 2800000 | Q47: =INDEX(Monthly!$C$83:$AL$83,($R$2-1)*12+10) -> 2775000 | R47: =INDEX(Monthly!$C$83:$AL$83,($R$2-1)*12+11) -> 2750000 | S47: =INDEX(Monthly!$C$83:$AL$83,($R$2-1)*12+12) -> 2725000
A48: Total liabilities | B48: ='Balance Sheet'!B12 -> 2736847.7 | C48: ='Balance Sheet'!C12 -> 2440264.3 | D48: ='Balance Sheet'!D12 -> 2142918.8 | H48: =INDEX(Monthly!$C$115:$AL$115,($R$2-1)*12+1) -> 3004714.6 | I48: =INDEX(Monthly!$C$115:$AL$115,($R$2-1)*12+2) -> 2980354.3 | J48: =INDEX(Monthly!$C$115:$AL$115,($R$2-1)*12+3) -> 2957384.6 | K48: =INDEX(Monthly!$C$115:$AL$115,($R$2-1)*12+4) -> 2933241.1 | L48: =INDEX(Monthly!$C$115:$AL$115,($R$2-1)*12+5) -> 2909119.1 | M48: =INDEX(Monthly!$C$115:$AL$115,($R$2-1)*12+6) -> 2885017.7 | N48: =INDEX(Monthly!$C$115:$AL$115,($R$2-1)*12+7) -> 2860936.1 | O48: =INDEX(Monthly!$C$115:$AL$115,($R$2-1)*12+8) -> 2836873.4 | P48: =INDEX(Monthly!$C$115:$AL$115,($R$2-1)*12+9) -> 2812829 | Q48: =INDEX(Monthly!$C$115:$AL$115,($R$2-1)*12+10) -> 2788802 | R48: =INDEX(Monthly!$C$115:$AL$115,($R$2-1)*12+11) -> 2764161.4 | S48: =INDEX(Monthly!$C$115:$AL$115,($R$2-1)*12+12) -> 2736847.7
A49: Paid-in capital | B49: ='Balance Sheet'!B13 -> 2100000 | C49: ='Balance Sheet'!C13 -> 2100000 | D49: ='Balance Sheet'!D13 -> 2100000 | H49: =INDEX(Monthly!$C$112:$AL$112,($R$2-1)*12+1) -> 2100000 | I49: =INDEX(Monthly!$C$112:$AL$112,($R$2-1)*12+2) -> 2100000 | J49: =INDEX(Monthly!$C$112:$AL$112,($R$2-1)*12+3) -> 2100000 | K49: =INDEX(Monthly!$C$112:$AL$112,($R$2-1)*12+4) -> 2100000 | L49: =INDEX(Monthly!$C$112:$AL$112,($R$2-1)*12+5) -> 2100000 | M49: =INDEX(Monthly!$C$112:$AL$112,($R$2-1)*12+6) -> 2100000 | N49: =INDEX(Monthly!$C$112:$AL$112,($R$2-1)*12+7) -> 2100000 | O49: =INDEX(Monthly!$C$112:$AL$112,($R$2-1)*12+8) -> 2100000 | P49: =INDEX(Monthly!$C$112:$AL$112,($R$2-1)*12+9) -> 2100000 | Q49: =INDEX(Monthly!$C$112:$AL$112,($R$2-1)*12+10) -> 2100000 | R49: =INDEX(Monthly!$C$112:$AL$112,($R$2-1)*12+11) -> 2100000 | S49: =INDEX(Monthly!$C$112:$AL$112,($R$2-1)*12+12) -> 2100000
A50: Retained earnings | B50: ='Balance Sheet'!B14 -> -709232.33 | C50: ='Balance Sheet'!C14 -> -844797.51 | D50: ='Balance Sheet'!D14 -> -704179.03 | H50: =INDEX(Monthly!$C$113:$AL$113,($R$2-1)*12+1) -> -102437.48 | I50: =INDEX(Monthly!$C$113:$AL$113,($R$2-1)*12+2) -> -199240.34 | J50: =INDEX(Monthly!$C$113:$AL$113,($R$2-1)*12+3) -> -280587.03 | K50: =INDEX(Monthly!$C$113:$AL$113,($R$2-1)*12+4) -> -354763.01 | L50: =INDEX(Monthly!$C$113:$AL$113,($R$2-1)*12+5) -> -421640.55 | M50: =INDEX(Monthly!$C$113:$AL$113,($R$2-1)*12+6) -> -481097.04 | N50: =INDEX(Monthly!$C$113:$AL$113,($R$2-1)*12+7) -> -533014.77 | O50: =INDEX(Monthly!$C$113:$AL$113,($R$2-1)*12+8) -> -577280.74 | P50: =INDEX(Monthly!$C$113:$AL$113,($R$2-1)*12+9) -> -613786.48 | Q50: =INDEX(Monthly!$C$113:$AL$113,($R$2-1)*12+10) -> -642427.84 | R50: =INDEX(Monthly!$C$113:$AL$113,($R$2-1)*12+11) -> -668750.98 | S50: =INDEX(Monthly!$C$113:$AL$113,($R$2-1)*12+12) -> -709232.33
A51: Total equity | B51: ='Balance Sheet'!B15 -> 1390767.7 | C51: ='Balance Sheet'!C15 -> 1255202.5 | D51: ='Balance Sheet'!D15 -> 1395821 | H51: =INDEX(Monthly!$C$116:$AL$116,($R$2-1)*12+1) -> 1997562.5 | I51: =INDEX(Monthly!$C$116:$AL$116,($R$2-1)*12+2) -> 1900759.7 | J51: =INDEX(Monthly!$C$116:$AL$116,($R$2-1)*12+3) -> 1819413 | K51: =INDEX(Monthly!$C$116:$AL$116,($R$2-1)*12+4) -> 1745237 | L51: =INDEX(Monthly!$C$116:$AL$116,($R$2-1)*12+5) -> 1678359.4 | M51: =INDEX(Monthly!$C$116:$AL$116,($R$2-1)*12+6) -> 1618903 | N51: =INDEX(Monthly!$C$116:$AL$116,($R$2-1)*12+7) -> 1566985.2 | O51: =INDEX(Monthly!$C$116:$AL$116,($R$2-1)*12+8) -> 1522719.3 | P51: =INDEX(Monthly!$C$116:$AL$116,($R$2-1)*12+9) -> 1486213.5 | Q51: =INDEX(Monthly!$C$116:$AL$116,($R$2-1)*12+10) -> 1457572.2 | R51: =INDEX(Monthly!$C$116:$AL$116,($R$2-1)*12+11) -> 1431249 | S51: =INDEX(Monthly!$C$116:$AL$116,($R$2-1)*12+12) -> 1390767.7
A52: Total liabilities & equity | B52: ='Balance Sheet'!B16 -> 4127615.4 | C52: ='Balance Sheet'!C16 -> 3695466.8 | D52: ='Balance Sheet'!D16 -> 3538739.8 | H52: =INDEX(Monthly!$C$117:$AL$117,($R$2-1)*12+1) -> 5002277.2 | I52: =INDEX(Monthly!$C$117:$AL$117,($R$2-1)*12+2) -> 4881114 | J52: =INDEX(Monthly!$C$117:$AL$117,($R$2-1)*12+3) -> 4776797.5 | K52: =INDEX(Monthly!$C$117:$AL$117,($R$2-1)*12+4) -> 4678478.1 | L52: =INDEX(Monthly!$C$117:$AL$117,($R$2-1)*12+5) -> 4587478.6 | M52: =INDEX(Monthly!$C$117:$AL$117,($R$2-1)*12+6) -> 4503920.7 | N52: =INDEX(Monthly!$C$117:$AL$117,($R$2-1)*12+7) -> 4427921.3 | O52: =INDEX(Monthly!$C$117:$AL$117,($R$2-1)*12+8) -> 4359592.7 | P52: =INDEX(Monthly!$C$117:$AL$117,($R$2-1)*12+9) -> 4299042.5 | Q52: =INDEX(Monthly!$C$117:$AL$117,($R$2-1)*12+10) -> 4246374.1 | R52: =INDEX(Monthly!$C$117:$AL$117,($R$2-1)*12+11) -> 4195410.4 | S52: =INDEX(Monthly!$C$117:$AL$117,($R$2-1)*12+12) -> 4127615.4

Sheet Scenarios
A1: Scenarios — Low / Base / High | H1: =HYPERLINK("#'Cover'!A1","◂ Contents") -> ◂ Contents
A2: All three scenarios calculated side by side, live: change any input and every column updates. Active = the scenario chosen on the Dashboard.
A5: Key drivers
A6: Driver | B6: Low | C6: Base | D6: High | E6: Active
A7: Retail cars per operating day at maturity (year 1) (cars) | B7: =Inputs!$B$7 -> 200 | C7: =Inputs!$C$7 -> 240 | D7: =Inputs!$D$7 -> 280 | E7: =Inputs!$E$7 -> 240
A8: Average price per retail wash (year 1) ($) | B8: =Inputs!$B$28 -> 12 | C8: =Inputs!$C$28 -> 13 | D8: =Inputs!$D$28 -> 14 | E8: =Inputs!$E$28 -> 13
A9: Unlimited members at start (presale or current base) (#) | B9: =Inputs!$B$20 -> 150 | C9: =Inputs!$C$20 -> 250 | D9: =Inputs!$D$20 -> 350 | E9: =Inputs!$E$20 -> 250
A10: Unlimited plan fee per member per month (year 1) ($) | B10: =Inputs!$B$30 -> 32 | C10: =Inputs!$C$30 -> 35 | D10: =Inputs!$D$30 -> 38 | E10: =Inputs!$E$30 -> 35
A11: Members who cancel per month (%) | B11: =Inputs!$B$24 -> 0.05 | C11: =Inputs!$C$24 -> 0.04 | D11: =Inputs!$D$24 -> 0.032 | E11: =Inputs!$E$24 -> 0.04
A12: Site lease or land cost per month ($) | B12: =Inputs!$B$42 -> 30000 | C12: =Inputs!$C$42 -> 30000 | D12: =Inputs!$D$42 -> 30000 | E12: =Inputs!$E$42 -> 30000
A13: Tunnel equipment (month 1) ($) | B13: =Inputs!$B$50 -> 1650000 | C13: =Inputs!$C$50 -> 1650000 | D13: =Inputs!$D$50 -> 1650000 | E13: =Inputs!$E$50 -> 1650000
A14: Equity raised at start ($) | B14: =Inputs!$B$69 -> 2100000 | C14: =Inputs!$C$69 -> 2100000 | D14: =Inputs!$D$69 -> 2100000 | E14: =Inputs!$E$69 -> 2100000
A16: Results by scenario ($'000)
A17: Output | B17: Low | C17: Base | D17: High | E17: Active
A18: Revenue — final year | B18: =D31 -> 1373352.6 | C18: =D32 -> 2170291.6 | D18: =D33 -> 3275560.9 | E18: ='P&L'!D5 -> 2170291.6
A19: Revenue — whole plan | B19: =SUM(B31:D31) -> 3330663.1 | C19: =SUM(B32:D32) -> 5197123 | D19: =SUM(B33:D33) -> 7627129.2 | E19: =SUM('P&L'!$B$5:$D$5) -> 5197123
A20: EBITDA — final year | B20: =D37 -> -24636.3 | C20: =D38 -> 682326.82 | D20: =D39 -> 1692015.6 | E20: ='P&L'!D15 -> 682326.82
A21: EBITDA margin — final year | B21: =IF(B18=0,0,B20/B18) -> -0.017938802 | C21: =IF(C18=0,0,C20/C18) -> 0.31439407 | D21: =IF(D18=0,0,D20/D18) -> 0.51655752 | E21: =IF(E18=0,0,E20/E18) -> 0.31439407
A22: Net income — final year | B22: =D43 -> -566344.63 | C22: =D44 -> 140618.48 | D22: =D45 -> 908742.73 | E22: ='P&L'!D22 -> 140618.48
A23: Net income — whole plan | B23: =SUM(B43:D43) -> -2370448 | C23: =SUM(B44:D44) -> -704179.03 | D23: =SUM(B45:D45) -> 1211876 | E23: =SUM('P&L'!$B$22:$D$22) -> -704179.03
A24: Cash at the end of the plan | B24: =D49 -> -1288612.1 | C24: =D50 -> 376024.31 | D24: =D51 -> 2288697.8 | E24: ='Balance Sheet'!D5 -> 376024.31
A25: Lowest cash balance | B25: =MIN('Scenario calc'!$C$102:$AL$102) -> -1288612.1 | C25: =MIN('Scenario calc'!$C$231:$AL$231) -> 179017.17 | D25: =MIN('Scenario calc'!$C$360:$AL$360) -> 777911.47 | E25: ='Break-even'!B18 -> 179017.17
A26: Lowest cash point (month #) | B26: =MATCH(MIN('Scenario calc'!$C$102:$AL$102),'Scenario calc'!$C$102:$AL$102,0) -> 36 | C26: =MATCH(MIN('Scenario calc'!$C$231:$AL$231),'Scenario calc'!$C$231:$AL$231,0) -> 26 | D26: =MATCH(MIN('Scenario calc'!$C$360:$AL$360),'Scenario calc'!$C$360:$AL$360,0) -> 7 | E26: ='Break-even'!B6 -> 26
A27: Funding required (incl. cash buffer) | B27: =SUMPRODUCT(--('Scenario calc'!$C$6:$AL$6<=B26),'Scenario calc'!$C$74:$AL$74)-SUMPRODUCT(--('Scenario calc'!$C$6:$AL$6<=B26),'Scenario calc'!$C$96:$AL$96)-SUMPRODUCT(--('Scenario calc'!$C$6:$AL$6<=B26),'Scenario calc'!$C$84:$AL$84)+Inputs!$B$84 -> 6669612.1 | C27: =SUMPRODUCT(--('Scenario calc'!$C$135:$AL$135<=C26),'Scenario calc'!$C$203:$AL$203)-SUMPRODUCT(--('Scenario calc'!$C$135:$AL$135<=C26),'Scenario calc'!$C$225:$AL$225)-SUMPRODUCT(--('Scenario calc'!$C$135:$AL$135<=C26),'Scenario calc'!$C$213:$AL$213)+Inputs!$C$84 -> 5201982.8 | D27: =SUMPRODUCT(--('Scenario calc'!$C$264:$AL$264<=D26),'Scenario calc'!$C$332:$AL$332)-SUMPRODUCT(--('Scenario calc'!$C$264:$AL$264<=D26),'Scenario calc'!$C$354:$AL$354)-SUMPRODUCT(--('Scenario calc'!$C$264:$AL$264<=D26),'Scenario calc'!$C$342:$AL$342)+Inputs!$D$84 -> 4603088.5 | E27: ='Break-even'!B12 -> 5201982.8
A29: Revenue by year ($'000)
A30: Scenario | B30: 1 | C30: 2 | D30: 3
A31: Low | B31: =SUMIF('Scenario calc'!$C$7:$AL$7,B$30,'Scenario calc'!$C$39:$AL$39) -> 723753.78 | C31: =SUMIF('Scenario calc'!$C$7:$AL$7,C$30,'Scenario calc'!$C$39:$AL$39) -> 1233556.7 | D31: =SUMIF('Scenario calc'!$C$7:$AL$7,D$30,'Scenario calc'!$C$39:$AL$39) -> 1373352.6
A32: Base | B32: =SUMIF('Scenario calc'!$C$136:$AL$136,B$30,'Scenario calc'!$C$168:$AL$168) -> 1180182.4 | C32: =SUMIF('Scenario calc'!$C$136:$AL$136,C$30,'Scenario calc'!$C$168:$AL$168) -> 1846649 | D32: =SUMIF('Scenario calc'!$C$136:$AL$136,D$30,'Scenario calc'!$C$168:$AL$168) -> 2170291.6
A33: High | B33: =SUMIF('Scenario calc'!$C$265:$AL$265,B$30,'Scenario calc'!$C$297:$AL$297) -> 1713972.3 | C33: =SUMIF('Scenario calc'!$C$265:$AL$265,C$30,'Scenario calc'!$C$297:$AL$297) -> 2637596 | D33: =SUMIF('Scenario calc'!$C$265:$AL$265,D$30,'Scenario calc'!$C$297:$AL$297) -> 3275560.9
A35: EBITDA by year ($'000)
A36: Scenario | B36: 1 | C36: 2 | D36: 3
A37: Low | B37: =SUMIF('Scenario calc'!$C$7:$AL$7,B$36,'Scenario calc'!$C$57:$AL$57) -> -533892.68 | C37: =SUMIF('Scenario calc'!$C$7:$AL$7,C$36,'Scenario calc'!$C$57:$AL$57) -> -120382.6 | D37: =SUMIF('Scenario calc'!$C$7:$AL$7,D$36,'Scenario calc'!$C$57:$AL$57) -> -24636.3
A38: Base | B38: =SUMIF('Scenario calc'!$C$136:$AL$136,B$36,'Scenario calc'!$C$186:$AL$186) -> -123279.21 | C38: =SUMIF('Scenario calc'!$C$136:$AL$136,C$36,'Scenario calc'!$C$186:$AL$186) -> 428309.82 | D38: =SUMIF('Scenario calc'!$C$136:$AL$136,D$36,'Scenario calc'!$C$186:$AL$186) -> 682326.82
A39: High | B39: =SUMIF('Scenario calc'!$C$265:$AL$265,B$36,'Scenario calc'!$C$315:$AL$315) -> 374729.35 | C39: =SUMIF('Scenario calc'!$C$265:$AL$265,C$36,'Scenario calc'!$C$315:$AL$315) -> 1158811.7 | D39: =SUMIF('Scenario calc'!$C$265:$AL$265,D$36,'Scenario calc'!$C$315:$AL$315) -> 1692015.6
A41: Net income by year ($'000)
A42: Scenario | B42: 1 | C42: 2 | D42: 3
A43: Low | B43: =SUMIF('Scenario calc'!$C$7:$AL$7,B$42,'Scenario calc'!$C$66:$AL$66) -> -1119845.8 | C43: =SUMIF('Scenario calc'!$C$7:$AL$7,C$42,'Scenario calc'!$C$66:$AL$66) -> -684257.6 | D43: =SUMIF('Scenario calc'!$C$7:$AL$7,D$42,'Scenario calc'!$C$66:$AL$66) -> -566344.63
A44: Base | B44: =SUMIF('Scenario calc'!$C$136:$AL$136,B$42,'Scenario calc'!$C$195:$AL$195) -> -709232.33 | C44: =SUMIF('Scenario calc'!$C$136:$AL$136,C$42,'Scenario calc'!$C$195:$AL$195) -> -135565.18 | D44: =SUMIF('Scenario calc'!$C$136:$AL$136,D$42,'Scenario calc'!$C$195:$AL$195) -> 140618.48
A45: High | B45: =SUMIF('Scenario calc'!$C$265:$AL$265,B$42,'Scenario calc'!$C$324:$AL$324) -> -211223.77 | C45: =SUMIF('Scenario calc'!$C$265:$AL$265,C$42,'Scenario calc'!$C$324:$AL$324) -> 514357.01 | D45: =SUMIF('Scenario calc'!$C$265:$AL$265,D$42,'Scenario calc'!$C$324:$AL$324) -> 908742.73
A47: Cash at year end by year ($'000)
A48: Scenario | B48: 1 | C48: 2 | D48: 3
A49: Low | B49: =INDEX('Scenario calc'!$C$102:$AL$102,B$48*12) -> -52322.279 | C49: =INDEX('Scenario calc'!$C$102:$AL$102,C$48*12) -> -731025.65 | D49: =INDEX('Scenario calc'!$C$102:$AL$102,D$48*12) -> -1288612.1
A50: Base | B50: =INDEX('Scenario calc'!$C$231:$AL$231,B$48*12) -> 357219.36 | C50: =INDEX('Scenario calc'!$C$231:$AL$231,C$48*12) -> 226873.84 | D50: =INDEX('Scenario calc'!$C$231:$AL$231,D$48*12) -> 376024.31
A51: High | B51: =INDEX('Scenario calc'!$C$360:$AL$360,B$48*12) -> 853302.31 | C51: =INDEX('Scenario calc'!$C$360:$AL$360,C$48*12) -> 1372134.3 | D51: =INDEX('Scenario calc'!$C$360:$AL$360,D$48*12) -> 2288697.8

Sheet Break-even
A1: Startup costs, funding need and break-even | F1: =HYPERLINK("#'Cover'!A1","◂ Contents") -> ◂ Contents
A2: Live for the selected scenario. Periods are counted in months from the start of the plan.
A3: Scenario shown | B3: =CHOOSE(Dashboard!$B$4,"Low","Base","High") -> Base
A5: Startup costs & funding need (up to the lowest cash point)
A6: Lowest cash point (month #) | B6: =MATCH(MIN(Monthly!$C$100:$AL$100),Monthly!$C$100:$AL$100,0) -> 26
A7: Capital spending up to the lowest cash point | B7: =SUMPRODUCT(--(Monthly!$C$4:$AL$4<=$B$6),Monthly!$C$72:$AL$72) -> 4180000
A8: Operating cash burn up to the lowest cash point | B8: =-SUMPRODUCT(--(Monthly!$C$4:$AL$4<=$B$6),Monthly!$C$94:$AL$94) -> 115982.83 | D8: Losses and working capital before the business funds itself
A9: Loan repayments up to the lowest cash point | B9: =-SUMPRODUCT(--(Monthly!$C$4:$AL$4<=$B$6),Monthly!$C$82:$AL$82) -> 625000
A10: Total uses of funds | B10: =B7+B8+B9 -> 4920982.8
A11: Minimum cash buffer to keep | B11: =Inputs!$E$84 -> 281000 | D11: Input on the Inputs sheet
A12: Funding required (uses + buffer) | B12: =B10+B11 -> 5201982.8
A14: Equity raised | B14: =Inputs!$E$69 -> 2100000
A15: Loan drawn | B15: =Inputs!$E$70 -> 3000000
A16: Total sources of funds | B16: =B14+B15 -> 5100000
A17: Funding surplus / (shortfall) | B17: =B16-B12 -> -101982.83 | D17: Negative = raise at least this much more
A18: Lowest cash balance in the plan | B18: =MIN(Monthly!$C$100:$AL$100) -> 179017.17 | D18: Equals sources minus uses
A20: Break-even timing
A21: First month with positive EBITDA (month #) | B21: =IFERROR(MATCH(1,Monthly!$C$101:$AL$101,0),"Not within horizon") -> 8
A22: First month with positive net income (month #) | B22: =IFERROR(MATCH(1,Monthly!$C$104:$AL$104,0),"Not within horizon") -> 23
A23: Cash invested paid back (month #) | B23: =IF(MIN(Monthly!$C$106:$AL$106)>=0,"No investment to pay back",IFERROR(MATCH(1,Monthly!$C$108:$AL$108,0),"Not within horizon")) -> Not within horizon | D23: Cumulative operating + investing cash flow back to zero
A25: Annual break-even revenue
A26: Year # | B26: 1 | C26: 2 | D26: 3
B27: Year 1 | C27: Year 2 | D27: Year 3
A28: Revenue | B28: =SUMIF(Monthly!$C$5:$AL$5,B$26,Monthly!$C$37:$AL$37) -> 1180182.4 | C28: =SUMIF(Monthly!$C$5:$AL$5,C$26,Monthly!$C$37:$AL$37) -> 1846649 | D28: =SUMIF(Monthly!$C$5:$AL$5,D$26,Monthly!$C$37:$AL$37) -> 2170291.6
A29: Gross profit | B29: =SUMIF(Monthly!$C$5:$AL$5,B$26,Monthly!$C$46:$AL$46) -> 999760.79 | C29: =SUMIF(Monthly!$C$5:$AL$5,C$26,Monthly!$C$46:$AL$46) -> 1551921 | D29: =SUMIF(Monthly!$C$5:$AL$5,D$26,Monthly!$C$46:$AL$46) -> 1813150.4
A30: Gross margin (contribution) | B30: =IF(B28=0,0,B29/B28) -> 0.84712397 | C30: =IF(C28=0,0,C29/C28) -> 0.84039848 | D30: =IF(D28=0,0,D29/D28) -> 0.83544089
A31: Operating expenses (treated as fixed) | B31: =-SUMIF(Monthly!$C$5:$AL$5,B$26,Monthly!$C$54:$AL$54) -> 1123040 | C31: =-SUMIF(Monthly!$C$5:$AL$5,C$26,Monthly!$C$54:$AL$54) -> 1123611.2 | D31: =-SUMIF(Monthly!$C$5:$AL$5,D$26,Monthly!$C$54:$AL$54) -> 1130823.5
A32: Break-even revenue (EBITDA = 0) | B32: =IF(B30>0,B31/B30,"n/a") -> 1325709.2 | C32: =IF(C30>0,C31/C30,"n/a") -> 1336998.1 | D32: =IF(D30>0,D31/D30,"n/a") -> 1353565
A33: Margin of safety (revenue above break-even) | B33: =IF(AND(ISNUMBER(B32),B28>0),(B28-B32)/B28,"n/a") -> -0.1233087 | C33: =IF(AND(ISNUMBER(C32),C28>0),(C28-C32)/C28,"n/a") -> 0.27598687 | D33: =IF(AND(ISNUMBER(D32),D28>0),(D28-D32)/D28,"n/a") -> 0.37632114
A35: Simplification: cost of sales is treated as variable and operating expenses as fixed, so break-even revenue = operating expenses ÷ gross margin.

Sheet Valuation
A1: Discounted cash flow valuation | H1: =HYPERLINK("#'Cover'!A1","◂ Contents") -> ◂ Contents
A2: Enterprise value at the start of the plan, before the funding raised in period 1. Year-end discounting.
A3: Scenario shown | B3: =CHOOSE(Dashboard!$B$4,"Low","Base","High") -> Base
A5: Assumptions (active scenario, from the Inputs sheet)
A6: Discount rate (WACC) | B6: =Inputs!$E$87 -> 0.25
A7: Terminal growth rate | B7: =Inputs!$E$88 -> 0.02
A8: Exit multiple (EV ÷ final-year EBITDA) | B8: =Inputs!$E$89 -> 4
A9: Tax rate (for the interest tax shield) | B9: =Inputs!$E$81 -> 0.21
A10: Sensitivity step: WACC | B10: =Inputs!$E$90 -> 0.01
A11: Sensitivity step: terminal growth | B11: =Inputs!$E$91 -> 0.005
A13: Free cash flow by year
A14: Year # | B14: 1 | C14: 2 | D14: 3
B15: Year 1 | C15: Year 2 | D15: Year 3
A16: EBITDA | B16: =SUMIF(Monthly!$C$5:$AL$5,B$14,Monthly!$C$55:$AL$55) -> -123279.21 | C16: =SUMIF(Monthly!$C$5:$AL$5,C$14,Monthly!$C$55:$AL$55) -> 428309.82 | D16: =SUMIF(Monthly!$C$5:$AL$5,D$14,Monthly!$C$55:$AL$55) -> 682326.82
A17: Unlevered free cash flow | B17: =SUMIF(Monthly!$C$5:$AL$5,B$14,Monthly!$C$109:$AL$109) -> -4274794.3 | C17: =SUMIF(Monthly!$C$5:$AL$5,C$14,Monthly!$C$109:$AL$109) -> 342565.72 | D17: =SUMIF(Monthly!$C$5:$AL$5,D$14,Monthly!$C$109:$AL$109) -> 601916.73
A18: Discount factor | B18: =1/(1+Inputs!$E$87)^B$14 -> 0.8 | C18: =1/(1+Inputs!$E$87)^C$14 -> 0.64 | D18: =1/(1+Inputs!$E$87)^D$14 -> 0.512
A19: Present value of free cash flow | B19: =B17*B18 -> -3419835.5 | C19: =C17*C18 -> 219242.06 | D19: =D17*D18 -> 308181.36
A21: Enterprise value
B22: Perpetual growth | C22: Exit multiple
A23: Present value of the plan's free cash flows | B23: =SUM($B$19:$D$19) -> -2892412 | C23: =B23 -> -2892412
A24: Final-year free cash flow | final-year EBITDA | B24: =$D$17 -> 601916.73 | C24: =$D$16 -> 682326.82
A25: Terminal value at the end of year 3 | B25: =IF($B$6>$B$7,B24*(1+$B$7)/($B$6-$B$7),0) -> 2669369.8 | C25: =C24*$B$8 -> 2729307.3
A26: Present value of the terminal value | B26: =B25/(1+$B$6)^$D$14 -> 1366717.4 | C26: =C25/(1+$B$6)^$D$14 -> 1397405.3
A27: Enterprise value | B27: =B23+B26 -> -1525694.7 | C27: =C23+C26 -> -1495006.7
A28: Terminal value share of enterprise value | B28: =IF(B27<>0,B26/B27,0) -> -0.89580003 | C28: =IF(C27<>0,C26/C27,0) -> -0.93471507
A29: Cross-check: implied exit multiple | implied perpetual growth | B29: =IF(C24>0,B25/C24,"n/a") -> 3.9121573 | C29: =IF(C25+B24<>0,(C25*$B$6-B24)/(C25+B24),"n/a") -> 0.024138302
A30: Enterprise value — average of the two methods | B30: =AVERAGE(B27,C27) -> -1510350.7
A32: Sensitivity: enterprise value (perpetual growth) by WACC and terminal growth
A33: WACC ↓ · terminal growth → | B33: =$B$7+(-2)*$B$11 -> 0.01 | C33: =$B$7+(-1)*$B$11 -> 0.015 | D33: =$B$7+(0)*$B$11 -> 0.02 | E33: =$B$7+(1)*$B$11 -> 0.025 | F33: =$B$7+(2)*$B$11 -> 0.03
A34: =$B$6+(-2)*$B$10 -> 0.23 | B34: =IF($A34>B$33,SUMPRODUCT($B$17:$D$17/(1+$A34)^$B$14:$D$14)+$D$17*(1+B$33)/($A34-B$33)/(1+$A34)^$D$14,"n/a") -> -1440575.2 | C34: =IF($A34>C$33,SUMPRODUCT($B$17:$D$17/(1+$A34)^$B$14:$D$14)+$D$17*(1+C$33)/($A34-C$33)/(1+$A34)^$D$14,"n/a") -> -1398518.5 | D34: =IF($A34>D$33,SUMPRODUCT($B$17:$D$17/(1+$A34)^$B$14:$D$14)+$D$17*(1+D$33)/($A34-D$33)/(1+$A34)^$D$14,"n/a") -> -1354459.1 | E34: =IF($A34>E$33,SUMPRODUCT($B$17:$D$17/(1+$A34)^$B$14:$D$14)+$D$17*(1+E$33)/($A34-E$33)/(1+$A34)^$D$14,"n/a") -> -1308250.5 | F34: =IF($A34>F$33,SUMPRODUCT($B$17:$D$17/(1+$A34)^$B$14:$D$14)+$D$17*(1+F$33)/($A34-F$33)/(1+$A34)^$D$14,"n/a") -> -1259731.4
A35: =$B$6+(-1)*$B$10 -> 0.24 | B35: =IF($A35>B$33,SUMPRODUCT($B$17:$D$17/(1+$A35)^$B$14:$D$14)+$D$17*(1+B$33)/($A35-B$33)/(1+$A35)^$D$14,"n/a") -> -1522600.2 | C35: =IF($A35>C$33,SUMPRODUCT($B$17:$D$17/(1+$A35)^$B$14:$D$14)+$D$17*(1+C$33)/($A35-C$33)/(1+$A35)^$D$14,"n/a") -> -1484777.4 | D35: =IF($A35>D$33,SUMPRODUCT($B$17:$D$17/(1+$A35)^$B$14:$D$14)+$D$17*(1+D$33)/($A35-D$33)/(1+$A35)^$D$14,"n/a") -> -1445235.5 | E35: =IF($A35>E$33,SUMPRODUCT($B$17:$D$17/(1+$A35)^$B$14:$D$14)+$D$17*(1+E$33)/($A35-E$33)/(1+$A35)^$D$14,"n/a") -> -1403854.4 | F35: =IF($A35>F$33,SUMPRODUCT($B$17:$D$17/(1+$A35)^$B$14:$D$14)+$D$17*(1+F$33)/($A35-F$33)/(1+$A35)^$D$14,"n/a") -> -1360502.8
A36: =$B$6+(0)*$B$10 -> 0.25 | B36: =IF($A36>B$33,SUMPRODUCT($B$17:$D$17/(1+$A36)^$B$14:$D$14)+$D$17*(1+B$33)/($A36-B$33)/(1+$A36)^$D$14,"n/a") -> -1595482.1 | C36: =IF($A36>C$33,SUMPRODUCT($B$17:$D$17/(1+$A36)^$B$14:$D$14)+$D$17*(1+C$33)/($A36-C$33)/(1+$A36)^$D$14,"n/a") -> -1561330.8 | D36: =IF($A36>D$33,SUMPRODUCT($B$17:$D$17/(1+$A36)^$B$14:$D$14)+$D$17*(1+D$33)/($A36-D$33)/(1+$A36)^$D$14,"n/a") -> -1525694.7 | E36: =IF($A36>E$33,SUMPRODUCT($B$17:$D$17/(1+$A36)^$B$14:$D$14)+$D$17*(1+E$33)/($A36-E$33)/(1+$A36)^$D$14,"n/a") -> -1488474.7 | F36: =IF($A36>F$33,SUMPRODUCT($B$17:$D$17/(1+$A36)^$B$14:$D$14)+$D$17*(1+F$33)/($A36-F$33)/(1+$A36)^$D$14,"n/a") -> -1449562.9
A37: =$B$6+(1)*$B$10 -> 0.26 | B37: =IF($A37>B$33,SUMPRODUCT($B$17:$D$17/(1+$A37)^$B$14:$D$14)+$D$17*(1+B$33)/($A37-B$33)/(1+$A37)^$D$14,"n/a") -> -1660373 | C37: =IF($A37>C$33,SUMPRODUCT($B$17:$D$17/(1+$A37)^$B$14:$D$14)+$D$17*(1+C$33)/($A37-C$33)/(1+$A37)^$D$14,"n/a") -> -1629423.1 | D37: =IF($A37>D$33,SUMPRODUCT($B$17:$D$17/(1+$A37)^$B$14:$D$14)+$D$17*(1+D$33)/($A37-D$33)/(1+$A37)^$D$14,"n/a") -> -1597183.7 | E37: =IF($A37>E$33,SUMPRODUCT($B$17:$D$17/(1+$A37)^$B$14:$D$14)+$D$17*(1+E$33)/($A37-E$33)/(1+$A37)^$D$14,"n/a") -> -1563572.3 | F37: =IF($A37>F$33,SUMPRODUCT($B$17:$D$17/(1+$A37)^$B$14:$D$14)+$D$17*(1+F$33)/($A37-F$33)/(1+$A37)^$D$14,"n/a") -> -1528499.6
A38: =$B$6+(2)*$B$10 -> 0.27 | B38: =IF($A38>B$33,SUMPRODUCT($B$17:$D$17/(1+$A38)^$B$14:$D$14)+$D$17*(1+B$33)/($A38-B$33)/(1+$A38)^$D$14,"n/a") -> -1718245.9 | C38: =IF($A38>C$33,SUMPRODUCT($B$17:$D$17/(1+$A38)^$B$14:$D$14)+$D$17*(1+C$33)/($A38-C$33)/(1+$A38)^$D$14,"n/a") -> -1690101.9 | D38: =IF($A38>D$33,SUMPRODUCT($B$17:$D$17/(1+$A38)^$B$14:$D$14)+$D$17*(1+D$33)/($A38-D$33)/(1+$A38)^$D$14,"n/a") -> -1660832.2 | E38: =IF($A38>E$33,SUMPRODUCT($B$17:$D$17/(1+$A38)^$B$14:$D$14)+$D$17*(1+E$33)/($A38-E$33)/(1+$A38)^$D$14,"n/a") -> -1630367.7 | F38: =IF($A38>F$33,SUMPRODUCT($B$17:$D$17/(1+$A38)^$B$14:$D$14)+$D$17*(1+F$33)/($A38-F$33)/(1+$A38)^$D$14,"n/a") -> -1598634
A40: Free cash flow = operating cash flow + interest × (1 − tax rate) − capital spending. Cells marked n/a: WACC not above growth.

Sheet Sources & Uses
A1: Sources and uses of funds | E1: =HYPERLINK("#'Cover'!A1","◂ Contents") -> ◂ Contents
A2: Live for the selected scenario. Where the money comes from and where it goes in the period set below.
A3: Scenario shown | B3: =CHOOSE(Dashboard!$B$4,"Low","Base","High") -> Base
A5: Funding structure ($'000) — raised at the start of the plan
B6: Amount | C6: Share
A7: Equity | B7: =Inputs!$E$69 -> 2100000 | C7: =IF($B$9=0,0,B7/$B$9) -> 0.41176471
A8: Debt (loan) | B8: =Inputs!$E$70 -> 3000000 | C8: =IF($B$9=0,0,B8/$B$9) -> 0.58823529
A9: Total funding | B9: =B7+B8 -> 5100000 | C9: =IF(B9=0,0,1) -> 1
A10: Gearing (debt ÷ equity) | B10: =IF(B7<=0,IF(B8>0,"n/a",0),B8/B7) -> 1.4285714 | D10: n/a: debt without positive equity
A11: Funding required by the plan (Break-even sheet) | B11: ='Break-even'!B12 -> 5201982.8
A12: Funding surplus / (shortfall) | B12: ='Break-even'!B17 -> -101982.83
A14: ="Sources and uses of cash in the first "&$B$16&IF($B$16=1," month"," months")&" ($'000)" -> Sources and uses of cash in the first 12 months ($'000)
A15: Period covered (months from the start) | B15: 12 | D15: 1 to 36 (capped)
A16: Months used | B16: =MIN(36,MAX(1,ROUND(B15,0))) -> 12
A17: Sources | B17: Amount | C17: Share
A18: Equity raised | B18: =SUMPRODUCT(--(Monthly!$C$4:$AL$4<=$B$16),Monthly!$C$96:$AL$96) -> 2100000 | C18: =IF($B$21=0,0,B18/$B$21) -> 0.41176471
A19: Loan drawdowns | B19: =SUMPRODUCT(--(Monthly!$C$4:$AL$4<=$B$16),Monthly!$C$81:$AL$81) -> 3000000 | C19: =IF($B$21=0,0,B19/$B$21) -> 0.58823529
A20: Cash generated by operations | B20: =MAX(0,SUMPRODUCT(--(Monthly!$C$4:$AL$4<=$B$16),Monthly!$C$94:$AL$94)) -> 0 | C20: =IF($B$21=0,0,B20/$B$21) -> 0
A21: Total sources | B21: =SUM(B18:B20) -> 5100000 | C21: =IF(B21=0,0,1) -> 1
A23: Uses | B23: Amount | C23: Share
A24: Cash used by operations | B24: =MAX(0,-SUMPRODUCT(--(Monthly!$C$4:$AL$4<=$B$16),Monthly!$C$94:$AL$94)) -> 367780.64 | C24: =IF($B$28=0,0,B24/$B$28) -> 0.07211385
A25: Capital spending | B25: =-SUMPRODUCT(--(Monthly!$C$4:$AL$4<=$B$16),Monthly!$C$95:$AL$95) -> 4100000 | C25: =IF($B$28=0,0,B25/$B$28) -> 0.80392157
A26: Loan repayments | B26: =-SUMPRODUCT(--(Monthly!$C$4:$AL$4<=$B$16),Monthly!$C$82:$AL$82) -> 275000 | C26: =IF($B$28=0,0,B26/$B$28) -> 0.053921569
A27: Cash at the end of the period | B27: =INDEX(Monthly!$C$100:$AL$100,$B$16) -> 357219.36 | C27: =IF($B$28=0,0,B27/$B$28) -> 0.070043013
A28: Total uses | B28: =SUM(B24:B27) -> 5100000 | C28: =IF(B28=0,0,1) -> 1
A29: Sources − uses (must be 0; opening cash is 0) | B29: =B21-B28 -> 0

Sheet KPIs
A1: KPIs & ratios | G1: =HYPERLINK("#'Cover'!A1","◂ Contents") -> ◂ Contents
A2: Car wash financial model (planning) — industry metrics and financial ratios for the active scenario
A4: Financial ratios
B5: 1 | C5: 2 | D5: 3 | E5: Target
A6: Revenue growth | B6: =IF(N('P&L'!A5)<=0,"n/a",'P&L'!B5/'P&L'!A5-1) -> n/a | C6: =IF(N('P&L'!B5)<=0,"n/a",'P&L'!C5/'P&L'!B5-1) -> 0.56471494 | D6: =IF(N('P&L'!C5)<=0,"n/a",'P&L'!D5/'P&L'!C5-1) -> 0.17525939
A7: Gross margin | B7: =IF('P&L'!B5<=0,"n/a",'P&L'!B7/'P&L'!B5) -> 0.84712397 | C7: =IF('P&L'!C5<=0,"n/a",'P&L'!C7/'P&L'!C5) -> 0.84039848 | D7: =IF('P&L'!D5<=0,"n/a",'P&L'!D7/'P&L'!D5) -> 0.83544089
A8: EBITDA margin | B8: =IF('P&L'!B5<=0,"n/a",'P&L'!B15/'P&L'!B5) -> -0.10445776 | C8: =IF('P&L'!C5<=0,"n/a",'P&L'!C15/'P&L'!C5) -> 0.23193894 | D8: =IF('P&L'!D5<=0,"n/a",'P&L'!D15/'P&L'!D5) -> 0.31439407
A9: Net margin | B9: =IF('P&L'!B5<=0,"n/a",'P&L'!B22/'P&L'!B5) -> -0.60095146 | C9: =IF('P&L'!C5<=0,"n/a",'P&L'!C22/'P&L'!C5) -> -0.073411448 | D9: =IF('P&L'!D5<=0,"n/a",'P&L'!D22/'P&L'!D5) -> 0.064792437
A10: Payroll, % of revenue | B10: =IF('P&L'!B5<=0,"n/a",-SUMIF(Headcount!$C$5:$AL$5,B$5,Headcount!$C$15:$AL$15)/'P&L'!B5) -> 0.3720103 | C10: =IF('P&L'!C5<=0,"n/a",-SUMIF(Headcount!$C$5:$AL$5,C$5,Headcount!$C$15:$AL$15)/'P&L'!C5) -> 0.24488205 | D10: =IF('P&L'!D5<=0,"n/a",-SUMIF(Headcount!$C$5:$AL$5,D$5,Headcount!$C$15:$AL$15)/'P&L'!D5) -> 0.21461519
A11: Marketing, % of revenue | B11: =IF('P&L'!B5<=0,"n/a",-'P&L'!B13/'P&L'!B5) -> 0.12201504 | C11: =IF('P&L'!C5<=0,"n/a",-'P&L'!C13/'P&L'!C5) -> 0.062383268 | D11: =IF('P&L'!D5<=0,"n/a",-'P&L'!D13/'P&L'!D5) -> 0.04246434
A12: Operating expenses, % of revenue | B12: =IF('P&L'!B5<=0,"n/a",-'P&L'!B14/'P&L'!B5) -> 0.95158173 | C12: =IF('P&L'!C5<=0,"n/a",-'P&L'!C14/'P&L'!C5) -> 0.60845953 | D12: =IF('P&L'!D5<=0,"n/a",-'P&L'!D14/'P&L'!D5) -> 0.52104682
A13: Current ratio (current assets ÷ current liabilities) | B13: =IF(('Balance Sheet'!B12-'Balance Sheet'!B11)<=0,"n/a",('Balance Sheet'!B5+'Balance Sheet'!B6+'Balance Sheet'!B7)/('Balance Sheet'!B12-'Balance Sheet'!B11)) -> 31.169065 | C13: =IF(('Balance Sheet'!C12-'Balance Sheet'!C11)<=0,"n/a",('Balance Sheet'!C5+'Balance Sheet'!C6+'Balance Sheet'!C7)/('Balance Sheet'!C12-'Balance Sheet'!C11)) -> 15.862711 | D13: =IF(('Balance Sheet'!D12-'Balance Sheet'!D11)<=0,"n/a",('Balance Sheet'!D5+'Balance Sheet'!D6+'Balance Sheet'!D7)/('Balance Sheet'!D12-'Balance Sheet'!D11)) -> 21.97354
A14: Debt ÷ equity (loan ÷ total equity) | B14: =IF('Balance Sheet'!B15<=0,"n/a",'Balance Sheet'!B11/'Balance Sheet'!B15) -> 1.9593495 | C14: =IF('Balance Sheet'!C15<=0,"n/a",'Balance Sheet'!C11/'Balance Sheet'!C15) -> 1.9319592 | D14: =IF('Balance Sheet'!D15<=0,"n/a",'Balance Sheet'!D11/'Balance Sheet'!D15) -> 1.5224015
A15: Return on assets (net income ÷ year-end assets) | B15: =IF('Balance Sheet'!B9<=0,"n/a",'P&L'!B22/'Balance Sheet'!B9) -> -0.17182617 | C15: =IF('Balance Sheet'!C9<=0,"n/a",'P&L'!C22/'Balance Sheet'!C9) -> -0.036684182 | D15: =IF('Balance Sheet'!D9<=0,"n/a",'P&L'!D22/'Balance Sheet'!D9) -> 0.039736881
A16: Return on equity (net income ÷ year-end equity) | B16: =IF('Balance Sheet'!B15<=0,"n/a",'P&L'!B22/'Balance Sheet'!B15) -> -0.50995745 | C16: =IF('Balance Sheet'!C15<=0,"n/a",'P&L'!C22/'Balance Sheet'!C15) -> -0.10800264 | D16: =IF('Balance Sheet'!D15<=0,"n/a",'P&L'!D22/'Balance Sheet'!D15) -> 0.10074249
A18: DuPont analysis — return on equity = net margin × asset turnover × equity multiplier
B19: 1 | C19: 2 | D19: 3
A20: Net margin | B20: =IF('P&L'!B5<=0,"n/a",'P&L'!B22/'P&L'!B5) -> -0.60095146 | C20: =IF('P&L'!C5<=0,"n/a",'P&L'!C22/'P&L'!C5) -> -0.073411448 | D20: =IF('P&L'!D5<=0,"n/a",'P&L'!D22/'P&L'!D5) -> 0.064792437
A21: × Asset turnover (revenue ÷ assets) | B21: =IF('Balance Sheet'!B9<=0,"n/a",'P&L'!B5/'Balance Sheet'!B9) -> 0.28592354 | C21: =IF('Balance Sheet'!C9<=0,"n/a",'P&L'!C5/'Balance Sheet'!C9) -> 0.49970656 | D21: =IF('Balance Sheet'!D9<=0,"n/a",'P&L'!D5/'Balance Sheet'!D9) -> 0.61329505
A22: × Equity multiplier (assets ÷ equity) | B22: =IF('Balance Sheet'!B15<=0,"n/a",'Balance Sheet'!B9/'Balance Sheet'!B15) -> 2.9678684 | C22: =IF('Balance Sheet'!C15<=0,"n/a",'Balance Sheet'!C9/'Balance Sheet'!C15) -> 2.94412 | D22: =IF('Balance Sheet'!D15<=0,"n/a",'Balance Sheet'!D9/'Balance Sheet'!D15) -> 2.535239
A23: Return on equity (product of the three) | B23: =IF(AND(ISNUMBER(B20),ISNUMBER(B21),ISNUMBER(B22)),B20*B21*B22,"n/a") -> -0.50995745 | C23: =IF(AND(ISNUMBER(C20),ISNUMBER(C21),ISNUMBER(C22)),C20*C21*C22,"n/a") -> -0.10800264 | D23: =IF(AND(ISNUMBER(D20),ISNUMBER(D21),ISNUMBER(D22)),D20*D21*D22,"n/a") -> 0.10074249
A24: Check: product − return on equity (must be 0) | B24: =IF(AND(ISNUMBER(B23),ISNUMBER(B16)),B23-B16,IF(ISNUMBER(B23),1,IF(AND(ISNUMBER(B16),ISNUMBER(B20),ISNUMBER(B21)),1,0))) -> 0 | C24: =IF(AND(ISNUMBER(C23),ISNUMBER(C16)),C23-C16,IF(ISNUMBER(C23),1,IF(AND(ISNUMBER(C16),ISNUMBER(C20),ISNUMBER(C21)),1,0))) -> 0 | D24: =IF(AND(ISNUMBER(D23),ISNUMBER(D16)),D23-D16,IF(ISNUMBER(D23),1,IF(AND(ISNUMBER(D16),ISNUMBER(D20),ISNUMBER(D21)),1,0))) -> 0
A26: Car wash metrics ($'000; per-unit rows in $)
A27: Year # | B27: 1 | C27: 2 | D27: 3
B28: Year 1 | C28: Year 2 | D28: Year 3 | E28: Target
A29: Unlimited members (year end) | B29: =INDEX(Monthly!$C$19:$AL$19,B$27*12) -> 972.08918 | C29: =INDEX(Monthly!$C$19:$AL$19,C$27*12) -> 1660.5559 | D29: =INDEX(Monthly!$C$19:$AL$19,D$27*12) -> 2124.5009
A30: New members in the year | B30: =SUMIF(Monthly!$C$5:$AL$5,B$27,Monthly!$C$16:$AL$16) -> 981.45307 | C30: =SUMIF(Monthly!$C$5:$AL$5,C$27,Monthly!$C$16:$AL$16) -> 1318.2048 | D30: =SUMIF(Monthly!$C$5:$AL$5,D$27,Monthly!$C$16:$AL$16) -> 1370.3509
A31: Members who cancelled in the year | B31: =SUMIF(Monthly!$C$5:$AL$5,B$27,Monthly!$C$18:$AL$18) -> -259.36388 | C31: =SUMIF(Monthly!$C$5:$AL$5,C$27,Monthly!$C$18:$AL$18) -> -629.73811 | D31: =SUMIF(Monthly!$C$5:$AL$5,D$27,Monthly!$C$18:$AL$18) -> -906.4059
A32: Members who cancel per month | B32: =Inputs!$E$24 -> 0.04 | C32: =Inputs!$E$24 -> 0.04 | D32: =Inputs!$E$24 -> 0.04
A33: Washes in the year | B33: =SUMIF(Monthly!$C$5:$AL$5,B$27,Monthly!$C$28:$AL$28) -> 88966.949 | C33: =SUMIF(Monthly!$C$5:$AL$5,C$27,Monthly!$C$28:$AL$28) -> 142550.79 | D33: =SUMIF(Monthly!$C$5:$AL$5,D$27,Monthly!$C$28:$AL$28) -> 168876.47
A34: Retail cars washed | B34: =SUMIF(Monthly!$C$5:$AL$5,B$27,Monthly!$C$26:$AL$26) -> 64869.133 | C34: =SUMIF(Monthly!$C$5:$AL$5,C$27,Monthly!$C$26:$AL$26) -> 86025.6 | D34: =SUMIF(Monthly!$C$5:$AL$5,D$27,Monthly!$C$26:$AL$26) -> 88606.368
A35: Member washes | B35: =SUMIF(Monthly!$C$5:$AL$5,B$27,Monthly!$C$27:$AL$27) -> 24097.816 | C35: =SUMIF(Monthly!$C$5:$AL$5,C$27,Monthly!$C$27:$AL$27) -> 56525.192 | D35: =SUMIF(Monthly!$C$5:$AL$5,D$27,Monthly!$C$27:$AL$27) -> 80270.1
A36: Member share of washes | B36: =IF(B33=0,0,B35/B33) -> 0.27086256 | C36: =IF(C33=0,0,C35/C33) -> 0.39652668 | D36: =IF(D33=0,0,D35/D33) -> 0.47531844
A37: Washes per operating day | B37: =IF(Inputs!$E$9=0,0,B33/(Inputs!$E$9*12)) -> 255.65215 | C37: =IF(Inputs!$E$9=0,0,C33/(Inputs!$E$9*12)) -> 409.62871 | D37: =IF(Inputs!$E$9=0,0,D33/(Inputs!$E$9*12)) -> 485.27721
A38: Tunnel capacity (washes) | B38: =SUMIF(Monthly!$C$5:$AL$5,B$27,Monthly!$C$24:$AL$24) -> 294756 | C38: =SUMIF(Monthly!$C$5:$AL$5,C$27,Monthly!$C$24:$AL$24) -> 294756 | D38: =SUMIF(Monthly!$C$5:$AL$5,D$27,Monthly!$C$24:$AL$24) -> 294756
A39: Tunnel capacity used | B39: =IF(B38=0,0,B33/B38) -> 0.30183253 | C39: =IF(C38=0,0,C33/C38) -> 0.48362304 | D39: =IF(D38=0,0,D33/D38) -> 0.57293649
A40: Washes lost to the capacity limit | B40: =SUMIF(Monthly!$C$5:$AL$5,B$27,Monthly!$C$29:$AL$29) -> 0 | C40: =SUMIF(Monthly!$C$5:$AL$5,C$27,Monthly!$C$29:$AL$29) -> 0 | D40: =SUMIF(Monthly!$C$5:$AL$5,D$27,Monthly!$C$29:$AL$29) -> 0
A41: Revenue | B41: =SUMIF(Monthly!$C$5:$AL$5,B$27,Monthly!$C$37:$AL$37) -> 1180182.4 | C41: =SUMIF(Monthly!$C$5:$AL$5,C$27,Monthly!$C$37:$AL$37) -> 1846649 | D41: =SUMIF(Monthly!$C$5:$AL$5,D$27,Monthly!$C$37:$AL$37) -> 2170291.6
A42: Unlimited plan fees | B42: =SUMIF(Monthly!$C$5:$AL$5,B$27,Monthly!$C$36:$AL$36) -> 239579.96 | C42: =SUMIF(Monthly!$C$5:$AL$5,C$27,Monthly!$C$36:$AL$36) -> 574330.39 | D42: =SUMIF(Monthly!$C$5:$AL$5,D$27,Monthly!$C$36:$AL$36) -> 833593.66
A43: Retail wash & add-on revenue | B43: =B41-B42 -> 940602.43 | C43: =C41-C42 -> 1272318.6 | D43: =D41-D42 -> 1336697.9
A44: Plan fees share of revenue | B44: =IF(B41=0,0,B42/B41) -> 0.20300249 | C44: =IF(C41=0,0,C42/C41) -> 0.31101221 | D44: =IF(D41=0,0,D42/D41) -> 0.38409293
A45: Revenue per wash ($) | B45: =IF(B33=0,0,B41/B33) -> 13.265403 | C45: =IF(C33=0,0,C41/C33) -> 12.954323 | D45: =IF(D33=0,0,D41/D33) -> 12.851356
A46: Plan fee revenue per member wash ($) | B46: =IF(B35=0,0,B42/B35) -> 9.9419781 | C46: =IF(C35=0,0,C42/C35) -> 10.160609 | D46: =IF(D35=0,0,D42/D35) -> 10.384859
A47: Chemicals, water & electricity | B47: =SUMIF(Monthly!$C$5:$AL$5,B$27,Monthly!$C$43:$AL$43) -> -145016.13 | C47: =SUMIF(Monthly!$C$5:$AL$5,C$27,Monthly!$C$43:$AL$43) -> -239328.53 | D47: =SUMIF(Monthly!$C$5:$AL$5,D$27,Monthly!$C$43:$AL$43) -> -292032.5
A48: Chemicals, water & electricity per wash ($) | B48: =IF(B33=0,0,-B47/B33) -> 1.63 | C48: =IF(C33=0,0,-C47/C33) -> 1.6789 | D48: =IF(D33=0,0,-D47/D33) -> 1.729267
A49: Gross profit | B49: =SUMIF(Monthly!$C$5:$AL$5,B$27,Monthly!$C$46:$AL$46) -> 999760.79 | C49: =SUMIF(Monthly!$C$5:$AL$5,C$27,Monthly!$C$46:$AL$46) -> 1551921 | D49: =SUMIF(Monthly!$C$5:$AL$5,D$27,Monthly!$C$46:$AL$46) -> 1813150.4
A50: Gross margin | B50: =IF(B41=0,0,B49/B41) -> 0.84712397 | C50: =IF(C41=0,0,C49/C41) -> 0.84039848 | D50: =IF(D41=0,0,D49/D41) -> 0.83544089
A51: EBITDA | B51: =SUMIF(Monthly!$C$5:$AL$5,B$27,Monthly!$C$55:$AL$55) -> -123279.21 | C51: =SUMIF(Monthly!$C$5:$AL$5,C$27,Monthly!$C$55:$AL$55) -> 428309.82 | D51: =SUMIF(Monthly!$C$5:$AL$5,D$27,Monthly!$C$55:$AL$55) -> 682326.82
A52: EBITDA margin | B52: =IF(B41=0,0,B51/B41) -> -0.10445776 | C52: =IF(C41=0,0,C51/C41) -> 0.23193894 | D52: =IF(D41=0,0,D51/D41) -> 0.31439407

Sheet Inputs
A1: Inputs — Low / Base / High | I1: =HYPERLINK("#'Cover'!A1","◂ Contents") -> ◂ Contents
A2: Illustrative assumptions - replace them with your own numbers.
A5: Driver | B5: Low | C5: Base | D5: High | E5: Active | F5: Unit | G5: Source / comment
A6: Retail volume
A7: Retail cars per operating day at maturity (year 1) | B7: 200 | C7: 240 | D7: 280 | E7: =CHOOSE(Dashboard!$B$4,B7,C7,D7) -> 240 | F7: cars | G7: Low ≤ Base ≤ High
A8: Retail cars growth per year | B8: 0 | C8: 0.03 | D8: 0.06 | E8: =CHOOSE(Dashboard!$B$4,B8,C8,D8) -> 0.03 | F8: % | G8: Low ≤ Base ≤ High
A9: Operating days per month | B9: 29 | C9: 29 | D9: 29 | E9: =CHOOSE(Dashboard!$B$4,B9,C9,D9) -> 29 | F9: days
A10: Months to reach mature retail volume (0 = already mature) | B10: 12 | C10: 9 | D10: 7 | E10: =CHOOSE(Dashboard!$B$4,B10,C10,D10) -> 9 | F10: months | G10: Low ≥ Base ≥ High (lower is better)
A11: Retail volume in month 1, % of mature | B11: 0.35 | C11: 0.45 | D11: 0.55 | E11: =CHOOSE(Dashboard!$B$4,B11,C11,D11) -> 0.45 | F11: % | G11: Low ≤ Base ≤ High
A12: Winter volume dip, December-February (monthly models) | B12: 0.2 | C12: 0.15 | D12: 0.1 | E12: =CHOOSE(Dashboard!$B$4,B12,C12,D12) -> 0.15 | F12: % | G12: Low ≥ Base ≥ High (lower is better)
A14: Tunnel capacity
A15: Rated tunnel speed | B15: 140 | C15: 140 | D15: 140 | E15: =CHOOSE(Dashboard!$B$4,B15,C15,D15) -> 140 | F15: cars/hour
A16: Hours open per day | B16: 11 | C16: 11 | D16: 11 | E16: =CHOOSE(Dashboard!$B$4,B16,C16,D16) -> 11 | F16: hours
A17: Practical throughput, % of rated speed over open hours | B17: 0.55 | C17: 0.55 | D17: 0.55 | E17: =CHOOSE(Dashboard!$B$4,B17,C17,D17) -> 0.55 | F17: %
A19: Unlimited members
A20: Unlimited members at start (presale or current base) | B20: 150 | C20: 250 | D20: 350 | E20: =CHOOSE(Dashboard!$B$4,B20,C20,D20) -> 250 | F20: # | G20: Low ≤ Base ≤ High
A21: Direct sign-ups per month at maturity (year 1) | B21: 40 | C21: 50 | D21: 60 | E21: =CHOOSE(Dashboard!$B$4,B21,C21,D21) -> 50 | F21: # | G21: Low ≤ Base ≤ High
A22: Direct sign-ups growth per year | B22: 0 | C22: 0.05 | D22: 0.1 | E22: =CHOOSE(Dashboard!$B$4,B22,C22,D22) -> 0.05 | F22: % | G22: Low ≤ Base ≤ High
A23: Retail cars that sign up for an unlimited plan | B23: 0.006 | C23: 0.008 | D23: 0.01 | E23: =CHOOSE(Dashboard!$B$4,B23,C23,D23) -> 0.008 | F23: % | G23: Low ≤ Base ≤ High
A24: Members who cancel per month | B24: 0.05 | C24: 0.04 | D24: 0.032 | E24: =CHOOSE(Dashboard!$B$4,B24,C24,D24) -> 0.04 | F24: % | G24: Low ≥ Base ≥ High (lower is better)
A25: Washes per member per month | B25: 3.8 | C25: 3.5 | D25: 3.2 | E25: =CHOOSE(Dashboard!$B$4,B25,C25,D25) -> 3.5 | F25: washes | G25: Low ≥ Base ≥ High (lower is better)
A27: Prices
A28: Average price per retail wash (year 1) | B28: 12 | C28: 13 | D28: 14 | E28: =CHOOSE(Dashboard!$B$4,B28,C28,D28) -> 13 | F28: $ | G28: Low ≤ Base ≤ High
A29: Add-on revenue per retail car (wax, ceramic, tire shine) | B29: 1.2 | C29: 1.5 | D29: 1.8 | E29: =CHOOSE(Dashboard!$B$4,B29,C29,D29) -> 1.5 | F29: $ | G29: Low ≤ Base ≤ High
A30: Unlimited plan fee per member per month (year 1) | B30: 32 | C30: 35 | D30: 38 | E30: =CHOOSE(Dashboard!$B$4,B30,C30,D30) -> 35 | F30: $ | G30: Low ≤ Base ≤ High
A31: Price increase per year | B31: 0.01 | C31: 0.02 | D31: 0.03 | E31: =CHOOSE(Dashboard!$B$4,B31,C31,D31) -> 0.02 | F31: % | G31: Low ≤ Base ≤ High
A33: Variable cost per wash
A34: Chemicals per wash | B34: 0.95 | C34: 0.85 | D34: 0.75 | E34: =CHOOSE(Dashboard!$B$4,B34,C34,D34) -> 0.85 | F34: $ | G34: Low ≥ Base ≥ High (lower is better)
A35: Fresh water per wash (after reclaim) | B35: 45 | C35: 40 | D35: 36 | E35: =CHOOSE(Dashboard!$B$4,B35,C35,D35) -> 40 | F35: gallons | G35: Low ≥ Base ≥ High (lower is better)
A36: Water and sewer rate per 1,000 gallons | B36: 10 | C36: 9 | D36: 8 | E36: =CHOOSE(Dashboard!$B$4,B36,C36,D36) -> 9 | F36: $ | G36: Low ≥ Base ≥ High (lower is better)
A37: Electricity per wash | B37: 0.45 | C37: 0.42 | D37: 0.4 | E37: =CHOOSE(Dashboard!$B$4,B37,C37,D37) -> 0.42 | F37: $ | G37: Low ≥ Base ≥ High (lower is better)
A38: Card processing fees, % of revenue | B38: 0.032 | C38: 0.03 | D38: 0.028 | E38: =CHOOSE(Dashboard!$B$4,B38,C38,D38) -> 0.03 | F38: % | G38: Low ≥ Base ≥ High (lower is better)
A39: Cost increase per year (per-wash costs, maintenance, other) | B39: 0.04 | C39: 0.03 | D39: 0.025 | E39: =CHOOSE(Dashboard!$B$4,B39,C39,D39) -> 0.03 | F39: % | G39: Low ≥ Base ≥ High (lower is better)
A41: Site costs
A42: Site lease or land cost per month | B42: 30000 | C42: 30000 | D42: 30000 | E42: =CHOOSE(Dashboard!$B$4,B42,C42,D42) -> 30000 | F42: $
A43: Lease increase per year | B43: 0.03 | C43: 0.03 | D43: 0.03 | E43: =CHOOSE(Dashboard!$B$4,B43,C43,D43) -> 0.03 | F43: %
A44: Equipment maintenance & repairs per month | B44: 5500 | C44: 5500 | D44: 5500 | E44: =CHOOSE(Dashboard!$B$4,B44,C44,D44) -> 5500 | F44: $
A45: Insurance, property tax, software & other G&A per month | B45: 9500 | C45: 9500 | D45: 9500 | E45: =CHOOSE(Dashboard!$B$4,B45,C45,D45) -> 9500 | F45: $
A46: Marketing budget per month (year 1) | B46: 12000 | C46: 12000 | D46: 12000 | E46: =CHOOSE(Dashboard!$B$4,B46,C46,D46) -> 12000 | F46: $
A47: Marketing budget growth per year | B47: -0.3 | C47: -0.2 | D47: -0.1 | E47: =CHOOSE(Dashboard!$B$4,B47,C47,D47) -> -0.2 | F47: % | G47: Low ≤ Base ≤ High
A49: Capital spending
A50: Tunnel equipment (month 1) | B50: 1650000 | C50: 1650000 | D50: 1650000 | E50: =CHOOSE(Dashboard!$B$4,B50,C50,D50) -> 1650000 | F50: $
A51: Building & site works (month 1) | B51: 2300000 | C51: 2300000 | D51: 2300000 | E51: =CHOOSE(Dashboard!$B$4,B51,C51,D51) -> 2300000 | F51: $
A52: Pay stations, signage & vacuums (month 1) | B52: 150000 | C52: 150000 | D52: 150000 | E52: =CHOOSE(Dashboard!$B$4,B52,C52,D52) -> 150000 | F52: $
A53: Land purchase (month 1; never depreciated, 0 = leased site) | B53: 0 | C53: 0 | D53: 0 | E53: =CHOOSE(Dashboard!$B$4,B53,C53,D53) -> 0 | F53: $
A54: Equipment refresh & upgrades per year (from year 2) | B54: 40000 | C54: 40000 | D54: 40000 | E54: =CHOOSE(Dashboard!$B$4,B54,C54,D54) -> 40000 | F54: $
A56: Headcount
A57: Site manager: headcount (FTE) | B57: 1 | C57: 1 | D57: 1 | E57: =CHOOSE(Dashboard!$B$4,B57,C57,D57) -> 1 | F57: FTE | G57: Low ≤ Base ≤ High
A58: Site manager: salary per FTE per year | B58: 72000 | C58: 72000 | D58: 72000 | E58: =CHOOSE(Dashboard!$B$4,B58,C58,D58) -> 72000 | F58: $
A59: Site manager: headcount growth per year | B59: 0 | C59: 0 | D59: 0 | E59: =CHOOSE(Dashboard!$B$4,B59,C59,D59) -> 0 | F59: % | G59: Low ≤ Base ≤ High
A60: Site manager: first month on payroll | B60: 1 | C60: 1 | D60: 1 | E60: =CHOOSE(Dashboard!$B$4,B60,C60,D60) -> 1 | F60: month #
A61: Wash attendants & customer service: headcount (FTE) | B61: 10 | C61: 10 | D61: 10 | E61: =CHOOSE(Dashboard!$B$4,B61,C61,D61) -> 10 | F61: FTE | G61: Low ≤ Base ≤ High
A62: Wash attendants & customer service: salary per FTE per year | B62: 32000 | C62: 32000 | D62: 32000 | E62: =CHOOSE(Dashboard!$B$4,B62,C62,D62) -> 32000 | F62: $
A63: Wash attendants & customer service: headcount growth per year | B63: 0 | C63: 0 | D63: 0 | E63: =CHOOSE(Dashboard!$B$4,B63,C63,D63) -> 0 | F63: % | G63: Low ≤ Base ≤ High
A64: Wash attendants & customer service: first month on payroll | B64: 1 | C64: 1 | D64: 1 | E64: =CHOOSE(Dashboard!$B$4,B64,C64,D64) -> 1 | F64: month #
A65: Payroll taxes & benefits, % of salary | B65: 0.12 | C65: 0.12 | D65: 0.12 | E65: =CHOOSE(Dashboard!$B$4,B65,C65,D65) -> 0.12 | F65: %
A66: Wage growth per year | B66: 0.03 | C66: 0.03 | D66: 0.03 | E66: =CHOOSE(Dashboard!$B$4,B66,C66,D66) -> 0.03 | F66: %
A68: Funding
A69: Equity raised at start | B69: 2100000 | C69: 2100000 | D69: 2100000 | E69: =CHOOSE(Dashboard!$B$4,B69,C69,D69) -> 2100000 | F69: $
A70: Loan drawn at start | B70: 3000000 | C70: 3000000 | D70: 3000000 | E70: =CHOOSE(Dashboard!$B$4,B70,C70,D70) -> 3000000 | F70: $
A71: Loan interest rate per year | B71: 0.085 | C71: 0.085 | D71: 0.085 | E71: =CHOOSE(Dashboard!$B$4,B71,C71,D71) -> 0.085 | F71: %
A72: Loan repayment term | B72: 10 | C72: 10 | D72: 10 | E72: =CHOOSE(Dashboard!$B$4,B72,C72,D72) -> 10 | F72: years
A74: Working capital
A75: Customer payment terms (receivable days) | B75: 2 | C75: 2 | D75: 2 | E75: =CHOOSE(Dashboard!$B$4,B75,C75,D75) -> 2 | F75: days
A76: Inventory held (days of COGS) | B76: 7 | C76: 7 | D76: 7 | E76: =CHOOSE(Dashboard!$B$4,B76,C76,D76) -> 7 | F76: days
A77: Supplier payment terms (payable days) | B77: 20 | C77: 20 | D77: 20 | E77: =CHOOSE(Dashboard!$B$4,B77,C77,D77) -> 20 | F77: days
A79: Tax & depreciation
A80: Depreciation period for capex | B80: 12 | C80: 12 | D80: 12 | E80: =CHOOSE(Dashboard!$B$4,B80,C80,D80) -> 12 | F80: years
A81: Income tax rate | B81: 0.21 | C81: 0.21 | D81: 0.21 | E81: =CHOOSE(Dashboard!$B$4,B81,C81,D81) -> 0.21 | F81: %
A83: Break-even & funding
A84: Minimum cash buffer to keep | B84: 281000 | C84: 281000 | D84: 281000 | E84: =CHOOSE(Dashboard!$B$4,B84,C84,D84) -> 281000 | F84: $ | G84: About 3 months of costs
A86: Valuation
A87: Discount rate (WACC) | B87: 0.3 | C87: 0.25 | D87: 0.2 | E87: =CHOOSE(Dashboard!$B$4,B87,C87,D87) -> 0.25 | F87: % | G87: Low ≥ Base ≥ High (lower is better)
A88: Terminal growth rate (perpetuity) | B88: 0.01 | C88: 0.02 | D88: 0.03 | E88: =CHOOSE(Dashboard!$B$4,B88,C88,D88) -> 0.02 | F88: % | G88: Low ≤ Base ≤ High
A89: Exit multiple (EV ÷ final-year EBITDA) | B89: 3 | C89: 4 | D89: 5 | E89: =CHOOSE(Dashboard!$B$4,B89,C89,D89) -> 4 | F89: x | G89: Low ≤ Base ≤ High
A90: Sensitivity table: WACC step | B90: 0.01 | C90: 0.01 | D90: 0.01 | E90: =CHOOSE(Dashboard!$B$4,B90,C90,D90) -> 0.01 | F90: %
A91: Sensitivity table: growth step | B91: 0.005 | C91: 0.005 | D91: 0.005 | E91: =CHOOSE(Dashboard!$B$4,B91,C91,D91) -> 0.005 | F91: %
A93: Legend: yellow cell with blue figure = input you can change · black = formula · green = link to another sheet · grey = active value (column E follows the scenario on the Dashboard).

Sheet P&L
A1: Annual profit & loss | F1: =HYPERLINK("#'Cover'!A1","◂ Contents") -> ◂ Contents
A2: Rolled up from the period detail (SUMIF on the year row; balances at year end).
A3: Year # | B3: 1 | C3: 2 | D3: 3
B4: Year 1 | C4: Year 2 | D4: Year 3
A5: Revenue | B5: =SUMIF(Monthly!$C$5:$AL$5,B$3,Monthly!$C$37:$AL$37) -> 1180182.4 | C5: =SUMIF(Monthly!$C$5:$AL$5,C$3,Monthly!$C$37:$AL$37) -> 1846649 | D5: =SUMIF(Monthly!$C$5:$AL$5,D$3,Monthly!$C$37:$AL$37) -> 2170291.6
A6: Cost of sales | B6: =SUMIF(Monthly!$C$5:$AL$5,B$3,Monthly!$C$45:$AL$45) -> -180421.6 | C6: =SUMIF(Monthly!$C$5:$AL$5,C$3,Monthly!$C$45:$AL$45) -> -294728 | D6: =SUMIF(Monthly!$C$5:$AL$5,D$3,Monthly!$C$45:$AL$45) -> -357141.25
A7: Gross profit | B7: =SUMIF(Monthly!$C$5:$AL$5,B$3,Monthly!$C$46:$AL$46) -> 999760.79 | C7: =SUMIF(Monthly!$C$5:$AL$5,C$3,Monthly!$C$46:$AL$46) -> 1551921 | D7: =SUMIF(Monthly!$C$5:$AL$5,D$3,Monthly!$C$46:$AL$46) -> 1813150.4
A8: Gross margin | B8: =IF(B5=0,0,B7/B5) -> 0.84712397 | C8: =IF(C5=0,0,C7/C5) -> 0.84039848 | D8: =IF(D5=0,0,D7/D5) -> 0.83544089
A9: Site payroll | B9: =SUMIF(Monthly!$C$5:$AL$5,B$3,Monthly!$C$49:$AL$49) -> -439040 | C9: =SUMIF(Monthly!$C$5:$AL$5,C$3,Monthly!$C$49:$AL$49) -> -452211.2 | D9: =SUMIF(Monthly!$C$5:$AL$5,D$3,Monthly!$C$49:$AL$49) -> -465777.54
A10: Site lease or land cost | B10: =SUMIF(Monthly!$C$5:$AL$5,B$3,Monthly!$C$50:$AL$50) -> -360000 | C10: =SUMIF(Monthly!$C$5:$AL$5,C$3,Monthly!$C$50:$AL$50) -> -370800 | D10: =SUMIF(Monthly!$C$5:$AL$5,D$3,Monthly!$C$50:$AL$50) -> -381924
A11: Equipment maintenance & repairs | B11: =SUMIF(Monthly!$C$5:$AL$5,B$3,Monthly!$C$51:$AL$51) -> -66000 | C11: =SUMIF(Monthly!$C$5:$AL$5,C$3,Monthly!$C$51:$AL$51) -> -67980 | D11: =SUMIF(Monthly!$C$5:$AL$5,D$3,Monthly!$C$51:$AL$51) -> -70019.4
A12: Insurance, property tax, software & other | B12: =SUMIF(Monthly!$C$5:$AL$5,B$3,Monthly!$C$52:$AL$52) -> -114000 | C12: =SUMIF(Monthly!$C$5:$AL$5,C$3,Monthly!$C$52:$AL$52) -> -117420 | D12: =SUMIF(Monthly!$C$5:$AL$5,D$3,Monthly!$C$52:$AL$52) -> -120942.6
A13: Marketing | B13: =SUMIF(Monthly!$C$5:$AL$5,B$3,Monthly!$C$53:$AL$53) -> -144000 | C13: =SUMIF(Monthly!$C$5:$AL$5,C$3,Monthly!$C$53:$AL$53) -> -115200 | D13: =SUMIF(Monthly!$C$5:$AL$5,D$3,Monthly!$C$53:$AL$53) -> -92160
A14: Total operating expenses | B14: =SUMIF(Monthly!$C$5:$AL$5,B$3,Monthly!$C$54:$AL$54) -> -1123040 | C14: =SUMIF(Monthly!$C$5:$AL$5,C$3,Monthly!$C$54:$AL$54) -> -1123611.2 | D14: =SUMIF(Monthly!$C$5:$AL$5,D$3,Monthly!$C$54:$AL$54) -> -1130823.5
A15: EBITDA | B15: =SUMIF(Monthly!$C$5:$AL$5,B$3,Monthly!$C$55:$AL$55) -> -123279.21 | C15: =SUMIF(Monthly!$C$5:$AL$5,C$3,Monthly!$C$55:$AL$55) -> 428309.82 | D15: =SUMIF(Monthly!$C$5:$AL$5,D$3,Monthly!$C$55:$AL$55) -> 682326.82
A16: EBITDA margin | B16: =IF(B5=0,0,B15/B5) -> -0.10445776 | C16: =IF(C5=0,0,C15/C5) -> 0.23193894 | D16: =IF(D5=0,0,D15/D5) -> 0.31439407
A17: Depreciation | B17: =SUMIF(Monthly!$C$5:$AL$5,B$3,Monthly!$C$75:$AL$75) -> -341666.67 | C17: =SUMIF(Monthly!$C$5:$AL$5,C$3,Monthly!$C$75:$AL$75) -> -345000 | D17: =SUMIF(Monthly!$C$5:$AL$5,D$3,Monthly!$C$75:$AL$75) -> -348333.33
A18: EBIT | B18: =SUMIF(Monthly!$C$5:$AL$5,B$3,Monthly!$C$58:$AL$58) -> -464945.87 | C18: =SUMIF(Monthly!$C$5:$AL$5,C$3,Monthly!$C$58:$AL$58) -> 83309.822 | D18: =SUMIF(Monthly!$C$5:$AL$5,D$3,Monthly!$C$58:$AL$58) -> 333993.48
A19: Interest | B19: =SUMIF(Monthly!$C$5:$AL$5,B$3,Monthly!$C$59:$AL$59) -> -244286.46 | C19: =SUMIF(Monthly!$C$5:$AL$5,C$3,Monthly!$C$59:$AL$59) -> -218875 | D19: =SUMIF(Monthly!$C$5:$AL$5,D$3,Monthly!$C$59:$AL$59) -> -193375
A20: Pre-tax income | B20: =SUMIF(Monthly!$C$5:$AL$5,B$3,Monthly!$C$60:$AL$60) -> -709232.33 | C20: =SUMIF(Monthly!$C$5:$AL$5,C$3,Monthly!$C$60:$AL$60) -> -135565.18 | D20: =SUMIF(Monthly!$C$5:$AL$5,D$3,Monthly!$C$60:$AL$60) -> 140618.48
A21: Income tax | B21: =SUMIF(Monthly!$C$5:$AL$5,B$3,Monthly!$C$63:$AL$63) -> 0 | C21: =SUMIF(Monthly!$C$5:$AL$5,C$3,Monthly!$C$63:$AL$63) -> 0 | D21: =SUMIF(Monthly!$C$5:$AL$5,D$3,Monthly!$C$63:$AL$63) -> 0
A22: Net income | B22: =SUMIF(Monthly!$C$5:$AL$5,B$3,Monthly!$C$64:$AL$64) -> -709232.33 | C22: =SUMIF(Monthly!$C$5:$AL$5,C$3,Monthly!$C$64:$AL$64) -> -135565.18 | D22: =SUMIF(Monthly!$C$5:$AL$5,D$3,Monthly!$C$64:$AL$64) -> 140618.48
A23: Net margin | B23: =IF(B5=0,0,B22/B5) -> -0.60095146 | C23: =IF(C5=0,0,C22/C5) -> -0.073411448 | D23: =IF(D5=0,0,D22/D5) -> 0.064792437

Sheet Cash Flow
A1: Annual cash flow statement | F1: =HYPERLINK("#'Cover'!A1","◂ Contents") -> ◂ Contents
A2: Rolled up from the period detail (SUMIF on the year row; balances at year end).
A3: Year # | B3: 1 | C3: 2 | D3: 3
B4: Year 1 | C4: Year 2 | D4: Year 3
A5: Net income | B5: =SUMIF(Monthly!$C$5:$AL$5,B$3,Monthly!$C$64:$AL$64) -> -709232.33 | C5: =SUMIF(Monthly!$C$5:$AL$5,C$3,Monthly!$C$64:$AL$64) -> -135565.18 | D5: =SUMIF(Monthly!$C$5:$AL$5,D$3,Monthly!$C$64:$AL$64) -> 140618.48
A6: Add back depreciation | B6: =-SUMIF(Monthly!$C$5:$AL$5,B$3,Monthly!$C$75:$AL$75) -> 341666.67 | C6: =-SUMIF(Monthly!$C$5:$AL$5,C$3,Monthly!$C$75:$AL$75) -> 345000 | D6: =-SUMIF(Monthly!$C$5:$AL$5,D$3,Monthly!$C$75:$AL$75) -> 348333.33
A7: (Increase) / decrease in receivables | B7: =SUMIF(Monthly!$C$5:$AL$5,B$3,Monthly!$C$89:$AL$89) -> -7915.9819 | C7: =SUMIF(Monthly!$C$5:$AL$5,C$3,Monthly!$C$89:$AL$89) -> -2001.1431 | D7: =SUMIF(Monthly!$C$5:$AL$5,D$3,Monthly!$C$89:$AL$89) -> -1526.7615
A8: (Increase) / decrease in inventory | B8: =SUMIF(Monthly!$C$5:$AL$5,B$3,Monthly!$C$90:$AL$90) -> -4146.6985 | C8: =SUMIF(Monthly!$C$5:$AL$5,C$3,Monthly!$C$90:$AL$90) -> -1195.813 | D8: =SUMIF(Monthly!$C$5:$AL$5,D$3,Monthly!$C$90:$AL$90) -> -929.07353
A9: Increase / (decrease) in payables | B9: =SUMIF(Monthly!$C$5:$AL$5,B$3,Monthly!$C$91:$AL$91) -> 11847.71 | C9: =SUMIF(Monthly!$C$5:$AL$5,C$3,Monthly!$C$91:$AL$91) -> 3416.6085 | D9: =SUMIF(Monthly!$C$5:$AL$5,D$3,Monthly!$C$91:$AL$91) -> 2654.4958
A10: Operating cash flow | B10: =SUMIF(Monthly!$C$5:$AL$5,B$3,Monthly!$C$94:$AL$94) -> -367780.64 | C10: =SUMIF(Monthly!$C$5:$AL$5,C$3,Monthly!$C$94:$AL$94) -> 209654.47 | D10: =SUMIF(Monthly!$C$5:$AL$5,D$3,Monthly!$C$94:$AL$94) -> 489150.48
A11: Capital spending | B11: =SUMIF(Monthly!$C$5:$AL$5,B$3,Monthly!$C$95:$AL$95) -> -4100000 | C11: =SUMIF(Monthly!$C$5:$AL$5,C$3,Monthly!$C$95:$AL$95) -> -40000 | D11: =SUMIF(Monthly!$C$5:$AL$5,D$3,Monthly!$C$95:$AL$95) -> -40000
A12: Equity raised | B12: =SUMIF(Monthly!$C$5:$AL$5,B$3,Monthly!$C$96:$AL$96) -> 2100000 | C12: =SUMIF(Monthly!$C$5:$AL$5,C$3,Monthly!$C$96:$AL$96) -> 0 | D12: =SUMIF(Monthly!$C$5:$AL$5,D$3,Monthly!$C$96:$AL$96) -> 0
A13: Loan drawdown | B13: =SUMIF(Monthly!$C$5:$AL$5,B$3,Monthly!$C$81:$AL$81) -> 3000000 | C13: =SUMIF(Monthly!$C$5:$AL$5,C$3,Monthly!$C$81:$AL$81) -> 0 | D13: =SUMIF(Monthly!$C$5:$AL$5,D$3,Monthly!$C$81:$AL$81) -> 0
A14: Loan repayment | B14: =SUMIF(Monthly!$C$5:$AL$5,B$3,Monthly!$C$82:$AL$82) -> -275000 | C14: =SUMIF(Monthly!$C$5:$AL$5,C$3,Monthly!$C$82:$AL$82) -> -300000 | D14: =SUMIF(Monthly!$C$5:$AL$5,D$3,Monthly!$C$82:$AL$82) -> -300000
A15: Financing cash flow | B15: =SUMIF(Monthly!$C$5:$AL$5,B$3,Monthly!$C$97:$AL$97) -> 4825000 | C15: =SUMIF(Monthly!$C$5:$AL$5,C$3,Monthly!$C$97:$AL$97) -> -300000 | D15: =SUMIF(Monthly!$C$5:$AL$5,D$3,Monthly!$C$97:$AL$97) -> -300000
A16: Net change in cash | B16: =SUMIF(Monthly!$C$5:$AL$5,B$3,Monthly!$C$98:$AL$98) -> 357219.36 | C16: =SUMIF(Monthly!$C$5:$AL$5,C$3,Monthly!$C$98:$AL$98) -> -130345.53 | D16: =SUMIF(Monthly!$C$5:$AL$5,D$3,Monthly!$C$98:$AL$98) -> 149150.48
A17: Opening cash | B17: =INDEX(Monthly!$C$99:$AL$99,(B$3-1)*12+1) -> 0 | C17: =INDEX(Monthly!$C$99:$AL$99,(C$3-1)*12+1) -> 357219.36 | D17: =INDEX(Monthly!$C$99:$AL$99,(D$3-1)*12+1) -> 226873.84
A18: Closing cash | B18: =INDEX(Monthly!$C$100:$AL$100,B$3*12) -> 357219.36 | C18: =INDEX(Monthly!$C$100:$AL$100,C$3*12) -> 226873.84 | D18: =INDEX(Monthly!$C$100:$AL$100,D$3*12) -> 376024.31

Sheet Balance Sheet
A1: Balance sheet at year end | F1: =HYPERLINK("#'Cover'!A1","◂ Contents") -> ◂ Contents
A2: Rolled up from the period detail (SUMIF on the year row; balances at year end).
A3: Year # | B3: 1 | C3: 2 | D3: 3
B4: Year 1 | C4: Year 2 | D4: Year 3
A5: Cash | B5: =INDEX(Monthly!$C$100:$AL$100,B$3*12) -> 357219.36 | C5: =INDEX(Monthly!$C$100:$AL$100,C$3*12) -> 226873.84 | D5: =INDEX(Monthly!$C$100:$AL$100,D$3*12) -> 376024.31
A6: Accounts receivable | B6: =INDEX(Monthly!$C$86:$AL$86,B$3*12) -> 7915.9819 | C6: =INDEX(Monthly!$C$86:$AL$86,C$3*12) -> 9917.125 | D6: =INDEX(Monthly!$C$86:$AL$86,D$3*12) -> 11443.887
A7: Inventory | B7: =INDEX(Monthly!$C$87:$AL$87,B$3*12) -> 4146.6985 | C7: =INDEX(Monthly!$C$87:$AL$87,C$3*12) -> 5342.5115 | D7: =INDEX(Monthly!$C$87:$AL$87,D$3*12) -> 6271.585
A8: Net fixed assets | B8: =INDEX(Monthly!$C$77:$AL$77,B$3*12) -> 3758333.3 | C8: =INDEX(Monthly!$C$77:$AL$77,C$3*12) -> 3453333.3 | D8: =INDEX(Monthly!$C$77:$AL$77,D$3*12) -> 3145000
A9: Total assets | B9: =INDEX(Monthly!$C$114:$AL$114,B$3*12) -> 4127615.4 | C9: =INDEX(Monthly!$C$114:$AL$114,C$3*12) -> 3695466.8 | D9: =INDEX(Monthly!$C$114:$AL$114,D$3*12) -> 3538739.8
A10: Accounts payable | B10: =INDEX(Monthly!$C$88:$AL$88,B$3*12) -> 11847.71 | C10: =INDEX(Monthly!$C$88:$AL$88,C$3*12) -> 15264.319 | D10: =INDEX(Monthly!$C$88:$AL$88,D$3*12) -> 17918.814
A11: Loan | B11: =INDEX(Monthly!$C$83:$AL$83,B$3*12) -> 2725000 | C11: =INDEX(Monthly!$C$83:$AL$83,C$3*12) -> 2425000 | D11: =INDEX(Monthly!$C$83:$AL$83,D$3*12) -> 2125000
A12: Total liabilities | B12: =INDEX(Monthly!$C$115:$AL$115,B$3*12) -> 2736847.7 | C12: =INDEX(Monthly!$C$115:$AL$115,C$3*12) -> 2440264.3 | D12: =INDEX(Monthly!$C$115:$AL$115,D$3*12) -> 2142918.8
A13: Paid-in capital | B13: =INDEX(Monthly!$C$112:$AL$112,B$3*12) -> 2100000 | C13: =INDEX(Monthly!$C$112:$AL$112,C$3*12) -> 2100000 | D13: =INDEX(Monthly!$C$112:$AL$112,D$3*12) -> 2100000
A14: Retained earnings | B14: =INDEX(Monthly!$C$113:$AL$113,B$3*12) -> -709232.33 | C14: =INDEX(Monthly!$C$113:$AL$113,C$3*12) -> -844797.51 | D14: =INDEX(Monthly!$C$113:$AL$113,D$3*12) -> -704179.03
A15: Total equity | B15: =INDEX(Monthly!$C$116:$AL$116,B$3*12) -> 1390767.7 | C15: =INDEX(Monthly!$C$116:$AL$116,C$3*12) -> 1255202.5 | D15: =INDEX(Monthly!$C$116:$AL$116,D$3*12) -> 1395821
A16: Total liabilities & equity | B16: =INDEX(Monthly!$C$117:$AL$117,B$3*12) -> 4127615.4 | C16: =INDEX(Monthly!$C$117:$AL$117,C$3*12) -> 3695466.8 | D16: =INDEX(Monthly!$C$117:$AL$117,D$3*12) -> 3538739.8
A17: Check: assets − liabilities − equity (must be 0) | B17: =INDEX(Monthly!$C$118:$AL$118,B$3*12) -> 0 | C17: =INDEX(Monthly!$C$118:$AL$118,C$3*12) -> 0 | D17: =INDEX(Monthly!$C$118:$AL$118,D$3*12) -> 0

Sheet Monthly
A1: Monthly projection | D1: =HYPERLINK("#'Cover'!A1","◂ Contents") -> ◂ Contents
A2: $ unless stated; costs shown as negatives. Every period uses the same formula.
A3: Month | C3: M1 | D3: M2 | E3: M3 | F3: M4 | G3: M5 | H3: M6 | I3: M7 | J3: M8 | K3: M9 | L3: M10 | M3: M11 | N3: M12 | O3: M13 | P3: M14 | Q3: M15 | R3: M16 | S3: M17 | T3: M18 | U3: M19 | V3: M20 | W3: M21 | X3: M22 | Y3: M23 | Z3: M24 | AA3: M25 | AB3: M26 | AC3: M27 | AD3: M28 | AE3: M29 | AF3: M30 | AG3: M31 | AH3: M32 | AI3: M33 | AJ3: M34 | AK3: M35 | AL3: M36
A4: Period # | C4: 1 | D4: 2 | E4: 3 | F4: 4 | G4: 5 | H4: 6 | I4: 7 | J4: 8 | K4: 9 | L4: 10 | M4: 11 | N4: 12 | O4: 13 | P4: 14 | Q4: 15 | R4: 16 | S4: 17 | T4: 18 | U4: 19 | V4: 20 | W4: 21 | X4: 22 | Y4: 23 | Z4: 24 | AA4: 25 | AB4: 26 | AC4: 27 | AD4: 28 | AE4: 29 | AF4: 30 | AG4: 31 | AH4: 32 | AI4: 33 | AJ4: 34 | AK4: 35 | AL4: 36
A5: Year # | C5: =ROUNDUP(C4*1/12,0) -> 1 | D5: =ROUNDUP(D4*1/12,0) -> 1 | E5: =ROUNDUP(E4*1/12,0) -> 1 | F5: =ROUNDUP(F4*1/12,0) -> 1 | G5: =ROUNDUP(G4*1/12,0) -> 1 | H5: =ROUNDUP(H4*1/12,0) -> 1 | I5: =ROUNDUP(I4*1/12,0) -> 1 | J5: =ROUNDUP(J4*1/12,0) -> 1 | ... AL5: =ROUNDUP(AL4*1/12,0) -> 3
A7: Volume
A8: Helper: months of the period still on the ramp-up | C8: =MAX(0,MIN(1,Inputs!$E$10-(C$4-1)*1)) -> 1 | D8: =MAX(0,MIN(1,Inputs!$E$10-(D$4-1)*1)) -> 1 | E8: =MAX(0,MIN(1,Inputs!$E$10-(E$4-1)*1)) -> 1 | F8: =MAX(0,MIN(1,Inputs!$E$10-(F$4-1)*1)) -> 1 | G8: =MAX(0,MIN(1,Inputs!$E$10-(G$4-1)*1)) -> 1 | H8: =MAX(0,MIN(1,Inputs!$E$10-(H$4-1)*1)) -> 1 | I8: =MAX(0,MIN(1,Inputs!$E$10-(I$4-1)*1)) -> 1 | J8: =MAX(0,MIN(1,Inputs!$E$10-(J$4-1)*1)) -> 1 | ... AL8: =MAX(0,MIN(1,Inputs!$E$10-(AL$4-1)*1)) -> 0
A9: Ramp-up factor (share of mature retail volume) | C9: =IF(Inputs!$E$10<=0,1,(C8*Inputs!$E$11+(1-Inputs!$E$11)/MAX(1,Inputs!$E$10)*(C8*(C$4-1)*1+C8*(C8-1)/2)+1-C8)/1) -> 0.45 | D9: =IF(Inputs!$E$10<=0,1,(D8*Inputs!$E$11+(1-Inputs!$E$11)/MAX(1,Inputs!$E$10)*(D8*(D$4-1)*1+D8*(D8-1)/2)+1-D8)/1) -> 0.51111111 | E9: =IF(Inputs!$E$10<=0,1,(E8*Inputs!$E$11+(1-Inputs!$E$11)/MAX(1,Inputs!$E$10)*(E8*(E$4-1)*1+E8*(E8-1)/2)+1-E8)/1) -> 0.57222222 | F9: =IF(Inputs!$E$10<=0,1,(F8*Inputs!$E$11+(1-Inputs!$E$11)/MAX(1,Inputs!$E$10)*(F8*(F$4-1)*1+F8*(F8-1)/2)+1-F8)/1) -> 0.63333333 | G9: =IF(Inputs!$E$10<=0,1,(G8*Inputs!$E$11+(1-Inputs!$E$11)/MAX(1,Inputs!$E$10)*(G8*(G$4-1)*1+G8*(G8-1)/2)+1-G8)/1) -> 0.69444444 | H9: =IF(Inputs!$E$10<=0,1,(H8*Inputs!$E$11+(1-Inputs!$E$11)/MAX(1,Inputs!$E$10)*(H8*(H$4-1)*1+H8*(H8-1)/2)+1-H8)/1) -> 0.75555556 | I9: =IF(Inputs!$E$10<=0,1,(I8*Inputs!$E$11+(1-Inputs!$E$11)/MAX(1,Inputs!$E$10)*(I8*(I$4-1)*1+I8*(I8-1)/2)+1-I8)/1) -> 0.81666667 | J9: =IF(Inputs!$E$10<=0,1,(J8*Inputs!$E$11+(1-Inputs!$E$11)/MAX(1,Inputs!$E$10)*(J8*(J$4-1)*1+J8*(J8-1)/2)+1-J8)/1) -> 0.87777778 | ... AL9: =IF(Inputs!$E$10<=0,1,(AL8*Inputs!$E$11+(1-Inputs!$E$11)/MAX(1,Inputs!$E$10)*(AL8*(AL$4-1)*1+AL8*(AL8-1)/2)+1-AL8)/1) -> 1
A10: Season factor (winter dip) | C10: =IF(OR(MOD(C$4-1,12)>=11,MOD(C$4-1,12)<=1),1-Inputs!$E$12,1+Inputs!$E$12/3) -> 0.85 | D10: =IF(OR(MOD(D$4-1,12)>=11,MOD(D$4-1,12)<=1),1-Inputs!$E$12,1+Inputs!$E$12/3) -> 0.85 | E10: =IF(OR(MOD(E$4-1,12)>=11,MOD(E$4-1,12)<=1),1-Inputs!$E$12,1+Inputs!$E$12/3) -> 1.05 | F10: =IF(OR(MOD(F$4-1,12)>=11,MOD(F$4-1,12)<=1),1-Inputs!$E$12,1+Inputs!$E$12/3) -> 1.05 | G10: =IF(OR(MOD(G$4-1,12)>=11,MOD(G$4-1,12)<=1),1-Inputs!$E$12,1+Inputs!$E$12/3) -> 1.05 | H10: =IF(OR(MOD(H$4-1,12)>=11,MOD(H$4-1,12)<=1),1-Inputs!$E$12,1+Inputs!$E$12/3) -> 1.05 | I10: =IF(OR(MOD(I$4-1,12)>=11,MOD(I$4-1,12)<=1),1-Inputs!$E$12,1+Inputs!$E$12/3) -> 1.05 | J10: =IF(OR(MOD(J$4-1,12)>=11,MOD(J$4-1,12)<=1),1-Inputs!$E$12,1+Inputs!$E$12/3) -> 1.05 | ... AL10: =IF(OR(MOD(AL$4-1,12)>=11,MOD(AL$4-1,12)<=1),1-Inputs!$E$12,1+Inputs!$E$12/3) -> 0.85
A11: Retail cars demanded | C11: =Inputs!$E$7*(1+Inputs!$E$8)^(C$5-1)*Inputs!$E$9*1*C9*C10 -> 2662.2 | D11: =Inputs!$E$7*(1+Inputs!$E$8)^(D$5-1)*Inputs!$E$9*1*D9*D10 -> 3023.7333 | E11: =Inputs!$E$7*(1+Inputs!$E$8)^(E$5-1)*Inputs!$E$9*1*E9*E10 -> 4181.8 | F11: =Inputs!$E$7*(1+Inputs!$E$8)^(F$5-1)*Inputs!$E$9*1*F9*F10 -> 4628.4 | G11: =Inputs!$E$7*(1+Inputs!$E$8)^(G$5-1)*Inputs!$E$9*1*G9*G10 -> 5075 | H11: =Inputs!$E$7*(1+Inputs!$E$8)^(H$5-1)*Inputs!$E$9*1*H9*H10 -> 5521.6 | I11: =Inputs!$E$7*(1+Inputs!$E$8)^(I$5-1)*Inputs!$E$9*1*I9*I10 -> 5968.2 | J11: =Inputs!$E$7*(1+Inputs!$E$8)^(J$5-1)*Inputs!$E$9*1*J9*J10 -> 6414.8 | ... AL11: =Inputs!$E$7*(1+Inputs!$E$8)^(AL$5-1)*Inputs!$E$9*1*AL9*AL10 -> 6276.2844
A13: Members
A14: New members from retail cars | C14: =C11*Inputs!$E$23 -> 21.2976 | D14: =D11*Inputs!$E$23 -> 24.189867 | E14: =E11*Inputs!$E$23 -> 33.4544 | F14: =F11*Inputs!$E$23 -> 37.0272 | G14: =G11*Inputs!$E$23 -> 40.6 | H14: =H11*Inputs!$E$23 -> 44.1728 | I14: =I11*Inputs!$E$23 -> 47.7456 | J14: =J11*Inputs!$E$23 -> 51.3184 | ... AL14: =AL11*Inputs!$E$23 -> 50.210275
A15: New members from direct sign-ups | C15: =Inputs!$E$21*(1+Inputs!$E$22)^(C$5-1)*1*C9 -> 22.5 | D15: =Inputs!$E$21*(1+Inputs!$E$22)^(D$5-1)*1*D9 -> 25.555556 | E15: =Inputs!$E$21*(1+Inputs!$E$22)^(E$5-1)*1*E9 -> 28.611111 | F15: =Inputs!$E$21*(1+Inputs!$E$22)^(F$5-1)*1*F9 -> 31.666667 | G15: =Inputs!$E$21*(1+Inputs!$E$22)^(G$5-1)*1*G9 -> 34.722222 | H15: =Inputs!$E$21*(1+Inputs!$E$22)^(H$5-1)*1*H9 -> 37.777778 | I15: =Inputs!$E$21*(1+Inputs!$E$22)^(I$5-1)*1*I9 -> 40.833333 | J15: =Inputs!$E$21*(1+Inputs!$E$22)^(J$5-1)*1*J9 -> 43.888889 | ... AL15: =Inputs!$E$21*(1+Inputs!$E$22)^(AL$5-1)*1*AL9 -> 55.125
A16: New members - total | C16: =C14+C15 -> 43.7976 | D16: =D14+D15 -> 49.745422 | E16: =E14+E15 -> 62.065511 | F16: =F14+F15 -> 68.693867 | G16: =G14+G15 -> 75.322222 | H16: =H14+H15 -> 81.950578 | I16: =I14+I15 -> 88.578933 | J16: =J14+J15 -> 95.207289 | ... AL16: =AL14+AL15 -> 105.33528
A17: Members - opening | C17: =Inputs!$E$20 -> 250 | D17: =C19 -> 283.7976 | E17: =D19 -> 322.19112 | F17: =E19 -> 371.36898 | G17: =F19 -> 425.20809 | H17: =G19 -> 483.52199 | I17: =H19 -> 546.13169 | J17: =I19 -> 612.86535 | K17: =J19 -> 683.55803 | ... AL17: =AK19 -> 2103.2975
A18: Members who cancelled | C18: =C19-C17-C16 -> -10 | D18: =D19-D17-D16 -> -11.351904 | E18: =E19-E17-E16 -> -12.887645 | F18: =F19-F17-F16 -> -14.854759 | G18: =G19-G17-G16 -> -17.008324 | H18: =H19-H17-H16 -> -19.34088 | I18: =I19-I17-I16 -> -21.845268 | J18: =J19-J17-J16 -> -24.514614 | ... AL18: =AL19-AL17-AL16 -> -84.131902
A19: Members - closing | C19: =C17*(1-Inputs!$E$24)+C16 -> 283.7976 | D19: =D17*(1-Inputs!$E$24)+D16 -> 322.19112 | E19: =E17*(1-Inputs!$E$24)+E16 -> 371.36898 | F19: =F17*(1-Inputs!$E$24)+F16 -> 425.20809 | G19: =G17*(1-Inputs!$E$24)+G16 -> 483.52199 | H19: =H17*(1-Inputs!$E$24)+H16 -> 546.13169 | I19: =I17*(1-Inputs!$E$24)+I16 -> 612.86535 | J19: =J17*(1-Inputs!$E$24)+J16 -> 683.55803 | ... AL19: =AL17*(1-Inputs!$E$24)+AL16 -> 2124.5009
A20: Members - average | C20: =(C17+C19)/2 -> 266.8988 | D20: =(D17+D19)/2 -> 302.99436 | E20: =(E17+E19)/2 -> 346.78005 | F20: =(F17+F19)/2 -> 398.28854 | G20: =(G17+G19)/2 -> 454.36504 | H20: =(H17+H19)/2 -> 514.82684 | I20: =(I17+I19)/2 -> 579.49852 | J20: =(J17+J19)/2 -> 648.21169 | ... AL20: =(AL17+AL19)/2 -> 2113.8992
A22: Washes
A23: Member washes demanded | C23: =C20*Inputs!$E$25*C10*1 -> 794.02393 | D23: =D20*Inputs!$E$25*D10*1 -> 901.40822 | E23: =E20*Inputs!$E$25*E10*1 -> 1274.4167 | F23: =F20*Inputs!$E$25*F10*1 -> 1463.7104 | G23: =G20*Inputs!$E$25*G10*1 -> 1669.7915 | H23: =H20*Inputs!$E$25*H10*1 -> 1891.9886 | I23: =I20*Inputs!$E$25*I10*1 -> 2129.6571 | J23: =J20*Inputs!$E$25*J10*1 -> 2382.178 | ... AL23: =AL20*Inputs!$E$25*AL10*1 -> 6288.8502
A24: Tunnel capacity (rated speed × hours × practical share × days) | C24: =Inputs!$E$15*Inputs!$E$16*Inputs!$E$17*Inputs!$E$9*1 -> 24563 | D24: =Inputs!$E$15*Inputs!$E$16*Inputs!$E$17*Inputs!$E$9*1 -> 24563 | E24: =Inputs!$E$15*Inputs!$E$16*Inputs!$E$17*Inputs!$E$9*1 -> 24563 | F24: =Inputs!$E$15*Inputs!$E$16*Inputs!$E$17*Inputs!$E$9*1 -> 24563 | G24: =Inputs!$E$15*Inputs!$E$16*Inputs!$E$17*Inputs!$E$9*1 -> 24563 | H24: =Inputs!$E$15*Inputs!$E$16*Inputs!$E$17*Inputs!$E$9*1 -> 24563 | I24: =Inputs!$E$15*Inputs!$E$16*Inputs!$E$17*Inputs!$E$9*1 -> 24563 | J24: =Inputs!$E$15*Inputs!$E$16*Inputs!$E$17*Inputs!$E$9*1 -> 24563 | ... AL24: =Inputs!$E$15*Inputs!$E$16*Inputs!$E$17*Inputs!$E$9*1 -> 24563
A25: Share of demand the tunnel can wash | C25: =MIN(1,C24/MAX(1,C11+C23)) -> 1 | D25: =MIN(1,D24/MAX(1,D11+D23)) -> 1 | E25: =MIN(1,E24/MAX(1,E11+E23)) -> 1 | F25: =MIN(1,F24/MAX(1,F11+F23)) -> 1 | G25: =MIN(1,G24/MAX(1,G11+G23)) -> 1 | H25: =MIN(1,H24/MAX(1,H11+H23)) -> 1 | I25: =MIN(1,I24/MAX(1,I11+I23)) -> 1 | J25: =MIN(1,J24/MAX(1,J11+J23)) -> 1 | ... AL25: =MIN(1,AL24/MAX(1,AL11+AL23)) -> 1
A26: Retail cars washed | C26: =C11*C25 -> 2662.2 | D26: =D11*D25 -> 3023.7333 | E26: =E11*E25 -> 4181.8 | F26: =F11*F25 -> 4628.4 | G26: =G11*G25 -> 5075 | H26: =H11*H25 -> 5521.6 | I26: =I11*I25 -> 5968.2 | J26: =J11*J25 -> 6414.8 | ... AL26: =AL11*AL25 -> 6276.2844
A27: Member washes | C27: =C23*C25 -> 794.02393 | D27: =D23*D25 -> 901.40822 | E27: =E23*E25 -> 1274.4167 | F27: =F23*F25 -> 1463.7104 | G27: =G23*G25 -> 1669.7915 | H27: =H23*H25 -> 1891.9886 | I27: =I23*I25 -> 2129.6571 | J27: =J23*J25 -> 2382.178 | ... AL27: =AL23*AL25 -> 6288.8502
A28: Washes - total | C28: =C26+C27 -> 3456.2239 | D28: =D26+D27 -> 3925.1416 | E28: =E26+E27 -> 5456.2167 | F28: =F26+F27 -> 6092.1104 | G28: =G26+G27 -> 6744.7915 | H28: =H26+H27 -> 7413.5886 | I28: =I26+I27 -> 8097.8571 | J28: =J26+J27 -> 8796.978 | ... AL28: =AL26+AL27 -> 12565.135
A29: Washes lost to the capacity limit | C29: =C11+C23-C28 -> 0 | D29: =D11+D23-D28 -> 0 | E29: =E11+E23-E28 -> 0 | F29: =F11+F23-F28 -> 0 | G29: =G11+G23-G28 -> 0 | H29: =H11+H23-H28 -> 0 | I29: =I11+I23-I28 -> 0 | J29: =J11+J23-J28 -> 0 | ... AL29: =AL11+AL23-AL28 -> 0
A31: Revenue
A32: Average price per retail wash | C32: =Inputs!$E$28*(1+Inputs!$E$31)^(C$5-1) -> 13 | D32: =Inputs!$E$28*(1+Inputs!$E$31)^(D$5-1) -> 13 | E32: =Inputs!$E$28*(1+Inputs!$E$31)^(E$5-1) -> 13 | F32: =Inputs!$E$28*(1+Inputs!$E$31)^(F$5-1) -> 13 | G32: =Inputs!$E$28*(1+Inputs!$E$31)^(G$5-1) -> 13 | H32: =Inputs!$E$28*(1+Inputs!$E$31)^(H$5-1) -> 13 | I32: =Inputs!$E$28*(1+Inputs!$E$31)^(I$5-1) -> 13 | J32: =Inputs!$E$28*(1+Inputs!$E$31)^(J$5-1) -> 13 | ... AL32: =Inputs!$E$28*(1+Inputs!$E$31)^(AL$5-1) -> 13.5252
A33: Unlimited plan fee per month | C33: =Inputs!$E$30*(1+Inputs!$E$31)^(C$5-1) -> 35 | D33: =Inputs!$E$30*(1+Inputs!$E$31)^(D$5-1) -> 35 | E33: =Inputs!$E$30*(1+Inputs!$E$31)^(E$5-1) -> 35 | F33: =Inputs!$E$30*(1+Inputs!$E$31)^(F$5-1) -> 35 | G33: =Inputs!$E$30*(1+Inputs!$E$31)^(G$5-1) -> 35 | H33: =Inputs!$E$30*(1+Inputs!$E$31)^(H$5-1) -> 35 | I33: =Inputs!$E$30*(1+Inputs!$E$31)^(I$5-1) -> 35 | J33: =Inputs!$E$30*(1+Inputs!$E$31)^(J$5-1) -> 35 | ... AL33: =Inputs!$E$30*(1+Inputs!$E$31)^(AL$5-1) -> 36.414
A34: Retail wash revenue | C34: =C26*C32 -> 34608.6 | D34: =D26*D32 -> 39308.533 | E34: =E26*E32 -> 54363.4 | F34: =F26*F32 -> 60169.2 | G34: =G26*G32 -> 65975 | H34: =H26*H32 -> 71780.8 | I34: =I26*I32 -> 77586.6 | J34: =J26*J32 -> 83392.4 | ... AL34: =AL26*AL32 -> 84888.002
A35: Add-on revenue | C35: =C26*Inputs!$E$29*(1+Inputs!$E$31)^(C$5-1) -> 3993.3 | D35: =D26*Inputs!$E$29*(1+Inputs!$E$31)^(D$5-1) -> 4535.6 | E35: =E26*Inputs!$E$29*(1+Inputs!$E$31)^(E$5-1) -> 6272.7 | F35: =F26*Inputs!$E$29*(1+Inputs!$E$31)^(F$5-1) -> 6942.6 | G35: =G26*Inputs!$E$29*(1+Inputs!$E$31)^(G$5-1) -> 7612.5 | H35: =H26*Inputs!$E$29*(1+Inputs!$E$31)^(H$5-1) -> 8282.4 | I35: =I26*Inputs!$E$29*(1+Inputs!$E$31)^(I$5-1) -> 8952.3 | J35: =J26*Inputs!$E$29*(1+Inputs!$E$31)^(J$5-1) -> 9622.2 | ... AL35: =AL26*Inputs!$E$29*(1+Inputs!$E$31)^(AL$5-1) -> 9794.7694
A36: Unlimited plan fees | C36: =C20*C33*1 -> 9341.458 | D36: =D20*D33*1 -> 10604.803 | E36: =E20*E33*1 -> 12137.302 | F36: =F20*F33*1 -> 13940.099 | G36: =G20*G33*1 -> 15902.776 | H36: =H20*H33*1 -> 18018.939 | I36: =I20*I33*1 -> 20282.448 | J36: =J20*J33*1 -> 22687.409 | ... AL36: =AL20*AL33*1 -> 76975.527
A37: Revenue | C37: =C34+C35+C36 -> 47943.358 | D37: =D34+D35+D36 -> 54448.936 | E37: =E34+E35+E36 -> 72773.402 | F37: =F34+F35+F36 -> 81051.899 | G37: =G34+G35+G36 -> 89490.276 | H37: =H34+H35+H36 -> 98082.139 | I37: =I34+I35+I36 -> 106821.35 | J37: =J34+J35+J36 -> 115702.01 | ... AL37: =AL34+AL35+AL36 -> 171658.3
A39: Cost of sales
A40: Chemicals | C40: =-C28*Inputs!$E$34*(1+Inputs!$E$39)^(C$5-1) -> -2937.7903 | D40: =-D28*Inputs!$E$34*(1+Inputs!$E$39)^(D$5-1) -> -3336.3703 | E40: =-E28*Inputs!$E$34*(1+Inputs!$E$39)^(E$5-1) -> -4637.7842 | F40: =-F28*Inputs!$E$34*(1+Inputs!$E$39)^(F$5-1) -> -5178.2938 | G40: =-G28*Inputs!$E$34*(1+Inputs!$E$39)^(G$5-1) -> -5733.0728 | H40: =-H28*Inputs!$E$34*(1+Inputs!$E$39)^(H$5-1) -> -6301.5503 | I40: =-I28*Inputs!$E$34*(1+Inputs!$E$39)^(I$5-1) -> -6883.1785 | J40: =-J28*Inputs!$E$34*(1+Inputs!$E$39)^(J$5-1) -> -7477.4313 | ... AL40: =-AL28*Inputs!$E$34*(1+Inputs!$E$39)^(AL$5-1) -> -11330.799
A41: Water & sewer | C41: =-C28*Inputs!$E$35/1000*Inputs!$E$36*(1+Inputs!$E$39)^(C$5-1) -> -1244.2406 | D41: =-D28*Inputs!$E$35/1000*Inputs!$E$36*(1+Inputs!$E$39)^(D$5-1) -> -1413.051 | E41: =-E28*Inputs!$E$35/1000*Inputs!$E$36*(1+Inputs!$E$39)^(E$5-1) -> -1964.238 | F41: =-F28*Inputs!$E$35/1000*Inputs!$E$36*(1+Inputs!$E$39)^(F$5-1) -> -2193.1597 | G41: =-G28*Inputs!$E$35/1000*Inputs!$E$36*(1+Inputs!$E$39)^(G$5-1) -> -2428.1249 | H41: =-H28*Inputs!$E$35/1000*Inputs!$E$36*(1+Inputs!$E$39)^(H$5-1) -> -2668.8919 | I41: =-I28*Inputs!$E$35/1000*Inputs!$E$36*(1+Inputs!$E$39)^(I$5-1) -> -2915.2285 | J41: =-J28*Inputs!$E$35/1000*Inputs!$E$36*(1+Inputs!$E$39)^(J$5-1) -> -3166.9121 | ... AL41: =-AL28*Inputs!$E$35/1000*Inputs!$E$36*(1+Inputs!$E$39)^(AL$5-1) -> -4798.9265
A42: Electricity | C42: =-C28*Inputs!$E$37*(1+Inputs!$E$39)^(C$5-1) -> -1451.6141 | D42: =-D28*Inputs!$E$37*(1+Inputs!$E$39)^(D$5-1) -> -1648.5595 | E42: =-E28*Inputs!$E$37*(1+Inputs!$E$39)^(E$5-1) -> -2291.611 | F42: =-F28*Inputs!$E$37*(1+Inputs!$E$39)^(F$5-1) -> -2558.6864 | G42: =-G28*Inputs!$E$37*(1+Inputs!$E$39)^(G$5-1) -> -2832.8124 | H42: =-H28*Inputs!$E$37*(1+Inputs!$E$39)^(H$5-1) -> -3113.7072 | I42: =-I28*Inputs!$E$37*(1+Inputs!$E$39)^(I$5-1) -> -3401.1 | J42: =-J28*Inputs!$E$37*(1+Inputs!$E$39)^(J$5-1) -> -3694.7307 | ... AL42: =-AL28*Inputs!$E$37*(1+Inputs!$E$39)^(AL$5-1) -> -5598.7476
A43: Chemicals, water & electricity | C43: =C40+C41+C42 -> -5633.645 | D43: =D40+D41+D42 -> -6397.9807 | E43: =E40+E41+E42 -> -8893.6332 | F43: =F40+F41+F42 -> -9930.1399 | G43: =G40+G41+G42 -> -10994.01 | H43: =H40+H41+H42 -> -12084.149 | I43: =I40+I41+I42 -> -13199.507 | J43: =J40+J41+J42 -> -14339.074 | ... AL43: =AL40+AL41+AL42 -> -21728.473
A44: Card processing fees | C44: =-C37*Inputs!$E$38 -> -1438.3007 | D44: =-D37*Inputs!$E$38 -> -1633.4681 | E44: =-E37*Inputs!$E$38 -> -2183.2021 | F44: =-F37*Inputs!$E$38 -> -2431.557 | G44: =-G37*Inputs!$E$38 -> -2684.7083 | H44: =-H37*Inputs!$E$38 -> -2942.4642 | I44: =-I37*Inputs!$E$38 -> -3204.6404 | J44: =-J37*Inputs!$E$38 -> -3471.0603 | ... AL44: =-AL37*Inputs!$E$38 -> -5149.7489
A45: Cost of sales | C45: =C43+C44 -> -7071.9457 | D45: =D43+D44 -> -8031.4488 | E45: =E43+E44 -> -11076.835 | F45: =F43+F44 -> -12361.697 | G45: =G43+G44 -> -13678.718 | H45: =H43+H44 -> -15026.614 | I45: =I43+I44 -> -16404.147 | J45: =J43+J44 -> -17810.134 | ... AL45: =AL43+AL44 -> -26878.222
A46: Gross profit | C46: =C37+C45 -> 40871.412 | D46: =D37+D45 -> 46417.487 | E46: =E37+E45 -> 61696.567 | F46: =F37+F45 -> 68690.202 | G46: =G37+G45 -> 75811.558 | H46: =H37+H45 -> 83055.526 | I46: =I37+I45 -> 90417.201 | J46: =J37+J45 -> 97891.875 | ... AL46: =AL37+AL45 -> 144780.08
A48: Operating expenses
A49: Site payroll | C49: =Headcount!C15 -> -36586.667 | D49: =Headcount!D15 -> -36586.667 | E49: =Headcount!E15 -> -36586.667 | F49: =Headcount!F15 -> -36586.667 | G49: =Headcount!G15 -> -36586.667 | H49: =Headcount!H15 -> -36586.667 | I49: =Headcount!I15 -> -36586.667 | J49: =Headcount!J15 -> -36586.667 | ... AL49: =Headcount!AL15 -> -38814.795
A50: Site lease or land cost | C50: =-Inputs!$E$42*(1+Inputs!$E$43)^(C$5-1)*1 -> -30000 | D50: =-Inputs!$E$42*(1+Inputs!$E$43)^(D$5-1)*1 -> -30000 | E50: =-Inputs!$E$42*(1+Inputs!$E$43)^(E$5-1)*1 -> -30000 | F50: =-Inputs!$E$42*(1+Inputs!$E$43)^(F$5-1)*1 -> -30000 | G50: =-Inputs!$E$42*(1+Inputs!$E$43)^(G$5-1)*1 -> -30000 | H50: =-Inputs!$E$42*(1+Inputs!$E$43)^(H$5-1)*1 -> -30000 | I50: =-Inputs!$E$42*(1+Inputs!$E$43)^(I$5-1)*1 -> -30000 | J50: =-Inputs!$E$42*(1+Inputs!$E$43)^(J$5-1)*1 -> -30000 | ... AL50: =-Inputs!$E$42*(1+Inputs!$E$43)^(AL$5-1)*1 -> -31827
A51: Equipment maintenance & repairs | C51: =-Inputs!$E$44*(1+Inputs!$E$39)^(C$5-1)*1 -> -5500 | D51: =-Inputs!$E$44*(1+Inputs!$E$39)^(D$5-1)*1 -> -5500 | E51: =-Inputs!$E$44*(1+Inputs!$E$39)^(E$5-1)*1 -> -5500 | F51: =-Inputs!$E$44*(1+Inputs!$E$39)^(F$5-1)*1 -> -5500 | G51: =-Inputs!$E$44*(1+Inputs!$E$39)^(G$5-1)*1 -> -5500 | H51: =-Inputs!$E$44*(1+Inputs!$E$39)^(H$5-1)*1 -> -5500 | I51: =-Inputs!$E$44*(1+Inputs!$E$39)^(I$5-1)*1 -> -5500 | J51: =-Inputs!$E$44*(1+Inputs!$E$39)^(J$5-1)*1 -> -5500 | ... AL51: =-Inputs!$E$44*(1+Inputs!$E$39)^(AL$5-1)*1 -> -5834.95
A52: Insurance, property tax, software & other | C52: =-Inputs!$E$45*(1+Inputs!$E$39)^(C$5-1)*1 -> -9500 | D52: =-Inputs!$E$45*(1+Inputs!$E$39)^(D$5-1)*1 -> -9500 | E52: =-Inputs!$E$45*(1+Inputs!$E$39)^(E$5-1)*1 -> -9500 | F52: =-Inputs!$E$45*(1+Inputs!$E$39)^(F$5-1)*1 -> -9500 | G52: =-Inputs!$E$45*(1+Inputs!$E$39)^(G$5-1)*1 -> -9500 | H52: =-Inputs!$E$45*(1+Inputs!$E$39)^(H$5-1)*1 -> -9500 | I52: =-Inputs!$E$45*(1+Inputs!$E$39)^(I$5-1)*1 -> -9500 | J52: =-Inputs!$E$45*(1+Inputs!$E$39)^(J$5-1)*1 -> -9500 | ... AL52: =-Inputs!$E$45*(1+Inputs!$E$39)^(AL$5-1)*1 -> -10078.55
A53: Marketing | C53: =-Inputs!$E$46*(1+Inputs!$E$47)^(C$5-1)*1 -> -12000 | D53: =-Inputs!$E$46*(1+Inputs!$E$47)^(D$5-1)*1 -> -12000 | E53: =-Inputs!$E$46*(1+Inputs!$E$47)^(E$5-1)*1 -> -12000 | F53: =-Inputs!$E$46*(1+Inputs!$E$47)^(F$5-1)*1 -> -12000 | G53: =-Inputs!$E$46*(1+Inputs!$E$47)^(G$5-1)*1 -> -12000 | H53: =-Inputs!$E$46*(1+Inputs!$E$47)^(H$5-1)*1 -> -12000 | I53: =-Inputs!$E$46*(1+Inputs!$E$47)^(I$5-1)*1 -> -12000 | J53: =-Inputs!$E$46*(1+Inputs!$E$47)^(J$5-1)*1 -> -12000 | ... AL53: =-Inputs!$E$46*(1+Inputs!$E$47)^(AL$5-1)*1 -> -7680
A54: Total operating expenses | C54: =C49+C50+C51+C52+C53 -> -93586.667 | D54: =D49+D50+D51+D52+D53 -> -93586.667 | E54: =E49+E50+E51+E52+E53 -> -93586.667 | F54: =F49+F50+F51+F52+F53 -> -93586.667 | G54: =G49+G50+G51+G52+G53 -> -93586.667 | H54: =H49+H50+H51+H52+H53 -> -93586.667 | I54: =I49+I50+I51+I52+I53 -> -93586.667 | J54: =J49+J50+J51+J52+J53 -> -93586.667 | ... AL54: =AL49+AL50+AL51+AL52+AL53 -> -94235.295
A55: EBITDA | C55: =C46+C54 -> -52715.254 | D55: =D46+D54 -> -47169.18 | E55: =E46+E54 -> -31890.1 | F55: =F46+F54 -> -24896.465 | G55: =G46+G54 -> -17775.109 | H55: =H46+H54 -> -10531.141 | I55: =I46+I54 -> -3169.4659 | J55: =J46+J54 -> 4305.2082 | ... AL55: =AL46+AL54 -> 50544.782
A57: Profit after depreciation, interest, tax
A58: EBIT | C58: =C55+C75 -> -81187.477 | D58: =D55+D75 -> -75641.402 | E58: =E55+E75 -> -60362.322 | F58: =F55+F75 -> -53368.687 | G58: =G55+G75 -> -46247.331 | H58: =H55+H75 -> -39003.363 | I58: =I55+I75 -> -31641.688 | J58: =J55+J75 -> -24167.014 | ... AL58: =AL55+AL75 -> 21517.004
A59: Interest on loan (average balance after drawdown) | C59: =-(C80+C81+C83)/2*Inputs!$E$71/12 -> -21250 | D59: =-(D80+D81+D83)/2*Inputs!$E$71/12 -> -21161.458 | E59: =-(E80+E81+E83)/2*Inputs!$E$71/12 -> -20984.375 | F59: =-(F80+F81+F83)/2*Inputs!$E$71/12 -> -20807.292 | G59: =-(G80+G81+G83)/2*Inputs!$E$71/12 -> -20630.208 | H59: =-(H80+H81+H83)/2*Inputs!$E$71/12 -> -20453.125 | I59: =-(I80+I81+I83)/2*Inputs!$E$71/12 -> -20276.042 | J59: =-(J80+J81+J83)/2*Inputs!$E$71/12 -> -20098.958 | ... AL59: =-(AL80+AL81+AL83)/2*Inputs!$E$71/12 -> -15140.625
A60: Pre-tax income | C60: =C58+C59 -> -102437.48 | D60: =D58+D59 -> -96802.86 | E60: =E58+E59 -> -81346.697 | F60: =F58+F59 -> -74175.979 | G60: =G58+G59 -> -66877.539 | H60: =H58+H59 -> -59456.488 | I60: =I58+I59 -> -51917.73 | J60: =J58+J59 -> -44265.972 | ... AL60: =AL58+AL59 -> 6376.3789
A61: Helper: cumulative pre-tax income | C61: =C60 -> -102437.48 | D61: =C61+D60 -> -199240.34 | E61: =D61+E60 -> -280587.03 | F61: =E61+F60 -> -354763.01 | G61: =F61+G60 -> -421640.55 | H61: =G61+H60 -> -481097.04 | I61: =H61+I60 -> -533014.77 | J61: =I61+J60 -> -577280.74 | K61: =J61+K60 -> -613786.48 | ... AL61: =AK61+AL60 -> -704179.03
A62: Helper: cumulative taxable income (losses carried forward) | C62: =MAX(0,C61) -> 0 | D62: =MAX(C62,D61) -> 0 | E62: =MAX(D62,E61) -> 0 | F62: =MAX(E62,F61) -> 0 | G62: =MAX(F62,G61) -> 0 | H62: =MAX(G62,H61) -> 0 | I62: =MAX(H62,I61) -> 0 | J62: =MAX(I62,J61) -> 0 | K62: =MAX(J62,K61) -> 0 | ... AL62: =MAX(AK62,AL61) -> 0
A63: Income tax | C63: =-C62*Inputs!$E$81 -> 0 | D63: =-(D62-C62)*Inputs!$E$81 -> 0 | E63: =-(E62-D62)*Inputs!$E$81 -> 0 | F63: =-(F62-E62)*Inputs!$E$81 -> 0 | G63: =-(G62-F62)*Inputs!$E$81 -> 0 | H63: =-(H62-G62)*Inputs!$E$81 -> 0 | I63: =-(I62-H62)*Inputs!$E$81 -> 0 | J63: =-(J62-I62)*Inputs!$E$81 -> 0 | K63: =-(K62-J62)*Inputs!$E$81 -> 0 | ... AL63: =-(AL62-AK62)*Inputs!$E$81 -> 0
A64: Net income | C64: =C60+C63 -> -102437.48 | D64: =D60+D63 -> -96802.86 | E64: =E60+E63 -> -81346.697 | F64: =F60+F63 -> -74175.979 | G64: =G60+G63 -> -66877.539 | H64: =H60+H63 -> -59456.488 | I64: =I60+I63 -> -51917.73 | J64: =J60+J63 -> -44265.972 | ... AL64: =AL60+AL63 -> 6376.3789
A66: Fixed assets & capital spending
A67: Tunnel equipment | C67: =IF(C$4=1,Inputs!$E$50,0) -> 1650000 | D67: =IF(D$4=1,Inputs!$E$50,0) -> 0 | E67: =IF(E$4=1,Inputs!$E$50,0) -> 0 | F67: =IF(F$4=1,Inputs!$E$50,0) -> 0 | G67: =IF(G$4=1,Inputs!$E$50,0) -> 0 | H67: =IF(H$4=1,Inputs!$E$50,0) -> 0 | I67: =IF(I$4=1,Inputs!$E$50,0) -> 0 | J67: =IF(J$4=1,Inputs!$E$50,0) -> 0 | ... AL67: =IF(AL$4=1,Inputs!$E$50,0) -> 0
A68: Building & site works | C68: =IF(C$4=1,Inputs!$E$51,0) -> 2300000 | D68: =IF(D$4=1,Inputs!$E$51,0) -> 0 | E68: =IF(E$4=1,Inputs!$E$51,0) -> 0 | F68: =IF(F$4=1,Inputs!$E$51,0) -> 0 | G68: =IF(G$4=1,Inputs!$E$51,0) -> 0 | H68: =IF(H$4=1,Inputs!$E$51,0) -> 0 | I68: =IF(I$4=1,Inputs!$E$51,0) -> 0 | J68: =IF(J$4=1,Inputs!$E$51,0) -> 0 | ... AL68: =IF(AL$4=1,Inputs!$E$51,0) -> 0
A69: Pay stations, signage & vacuums | C69: =IF(C$4=1,Inputs!$E$52,0) -> 150000 | D69: =IF(D$4=1,Inputs!$E$52,0) -> 0 | E69: =IF(E$4=1,Inputs!$E$52,0) -> 0 | F69: =IF(F$4=1,Inputs!$E$52,0) -> 0 | G69: =IF(G$4=1,Inputs!$E$52,0) -> 0 | H69: =IF(H$4=1,Inputs!$E$52,0) -> 0 | I69: =IF(I$4=1,Inputs!$E$52,0) -> 0 | J69: =IF(J$4=1,Inputs!$E$52,0) -> 0 | ... AL69: =IF(AL$4=1,Inputs!$E$52,0) -> 0
A70: Land (not depreciated) | C70: =IF(C$4=1,Inputs!$E$53,0) -> 0 | D70: =IF(D$4=1,Inputs!$E$53,0) -> 0 | E70: =IF(E$4=1,Inputs!$E$53,0) -> 0 | F70: =IF(F$4=1,Inputs!$E$53,0) -> 0 | G70: =IF(G$4=1,Inputs!$E$53,0) -> 0 | H70: =IF(H$4=1,Inputs!$E$53,0) -> 0 | I70: =IF(I$4=1,Inputs!$E$53,0) -> 0 | J70: =IF(J$4=1,Inputs!$E$53,0) -> 0 | ... AL70: =IF(AL$4=1,Inputs!$E$53,0) -> 0
A71: Equipment refresh & upgrades (first period of each year from year 2) | C71: =IF(AND(C$5>1,MOD(C$4-1,12)=0),Inputs!$E$54,0) -> 0 | D71: =IF(AND(D$5>1,MOD(D$4-1,12)=0),Inputs!$E$54,0) -> 0 | E71: =IF(AND(E$5>1,MOD(E$4-1,12)=0),Inputs!$E$54,0) -> 0 | F71: =IF(AND(F$5>1,MOD(F$4-1,12)=0),Inputs!$E$54,0) -> 0 | G71: =IF(AND(G$5>1,MOD(G$4-1,12)=0),Inputs!$E$54,0) -> 0 | H71: =IF(AND(H$5>1,MOD(H$4-1,12)=0),Inputs!$E$54,0) -> 0 | I71: =IF(AND(I$5>1,MOD(I$4-1,12)=0),Inputs!$E$54,0) -> 0 | J71: =IF(AND(J$5>1,MOD(J$4-1,12)=0),Inputs!$E$54,0) -> 0 | ... AL71: =IF(AND(AL$5>1,MOD(AL$4-1,12)=0),Inputs!$E$54,0) -> 0
A72: Capital spending | C72: =C67+C68+C69+C70+C71 -> 4100000 | D72: =D67+D68+D69+D70+D71 -> 0 | E72: =E67+E68+E69+E70+E71 -> 0 | F72: =F67+F68+F69+F70+F71 -> 0 | G72: =G67+G68+G69+G70+G71 -> 0 | H72: =H67+H68+H69+H70+H71 -> 0 | I72: =I67+I68+I69+I70+I71 -> 0 | J72: =J67+J68+J69+J70+J71 -> 0 | ... AL72: =AL67+AL68+AL69+AL70+AL71 -> 0
A73: Fixed assets at cost | C73: =C72 -> 4100000 | D73: =C73+D72 -> 4100000 | E73: =D73+E72 -> 4100000 | F73: =E73+F72 -> 4100000 | G73: =F73+G72 -> 4100000 | H73: =G73+H72 -> 4100000 | I73: =H73+I72 -> 4100000 | J73: =I73+J72 -> 4100000 | K73: =J73+K72 -> 4100000 | ... AL73: =AK73+AL72 -> 4180000
A74: Land at cost (not depreciated) | C74: =C70 -> 0 | D74: =C74+D70 -> 0 | E74: =D74+E70 -> 0 | F74: =E74+F70 -> 0 | G74: =F74+G70 -> 0 | H74: =G74+H70 -> 0 | I74: =H74+I70 -> 0 | J74: =I74+J70 -> 0 | K74: =J74+K70 -> 0 | ... AL74: =AK74+AL70 -> 0
A75: Depreciation | C75: =-MIN((C73-C74)/MAX(1,Inputs!$E$80*12),C72-C74) -> -28472.222 | D75: =-MIN((D73-D74)/MAX(1,Inputs!$E$80*12),C77+D72-D74) -> -28472.222 | E75: =-MIN((E73-E74)/MAX(1,Inputs!$E$80*12),D77+E72-E74) -> -28472.222 | F75: =-MIN((F73-F74)/MAX(1,Inputs!$E$80*12),E77+F72-F74) -> -28472.222 | G75: =-MIN((G73-G74)/MAX(1,Inputs!$E$80*12),F77+G72-G74) -> -28472.222 | H75: =-MIN((H73-H74)/MAX(1,Inputs!$E$80*12),G77+H72-H74) -> -28472.222 | I75: =-MIN((I73-I74)/MAX(1,Inputs!$E$80*12),H77+I72-I74) -> -28472.222 | J75: =-MIN((J73-J74)/MAX(1,Inputs!$E$80*12),I77+J72-J74) -> -28472.222 | K75: =-MIN((K73-K74)/MAX(1,Inputs!$E$80*12),J77+K72-K74) -> -28472.222 | ... AL75: =-MIN((AL73-AL74)/MAX(1,Inputs!$E$80*12),AK77+AL72-AL74) -> -29027.778
A76: Accumulated depreciation | C76: =C75 -> -28472.222 | D76: =C76+D75 -> -56944.444 | E76: =D76+E75 -> -85416.667 | F76: =E76+F75 -> -113888.89 | G76: =F76+G75 -> -142361.11 | H76: =G76+H75 -> -170833.33 | I76: =H76+I75 -> -199305.56 | J76: =I76+J75 -> -227777.78 | K76: =J76+K75 -> -256250 | ... AL76: =AK76+AL75 -> -1035000
A77: Net fixed assets | C77: =C73+C76 -> 4071527.8 | D77: =D73+D76 -> 4043055.6 | E77: =E73+E76 -> 4014583.3 | F77: =F73+F76 -> 3986111.1 | G77: =G73+G76 -> 3957638.9 | H77: =H73+H76 -> 3929166.7 | I77: =I73+I76 -> 3900694.4 | J77: =J73+J76 -> 3872222.2 | ... AL77: =AL73+AL76 -> 3145000
A79: Debt
A80: Loan — opening balance | C80: =0 -> 0 | D80: =C83 -> 3000000 | E80: =D83 -> 2975000 | F80: =E83 -> 2950000 | G80: =F83 -> 2925000 | H80: =G83 -> 2900000 | I80: =H83 -> 2875000 | J80: =I83 -> 2850000 | K80: =J83 -> 2825000 | ... AL80: =AK83 -> 2150000
A81: Loan drawdown | C81: =IF(C$4=1,Inputs!$E$70,0) -> 3000000 | D81: =IF(D$4=1,Inputs!$E$70,0) -> 0 | E81: =IF(E$4=1,Inputs!$E$70,0) -> 0 | F81: =IF(F$4=1,Inputs!$E$70,0) -> 0 | G81: =IF(G$4=1,Inputs!$E$70,0) -> 0 | H81: =IF(H$4=1,Inputs!$E$70,0) -> 0 | I81: =IF(I$4=1,Inputs!$E$70,0) -> 0 | J81: =IF(J$4=1,Inputs!$E$70,0) -> 0 | ... AL81: =IF(AL$4=1,Inputs!$E$70,0) -> 0
A82: Loan repayment | C82: =-MIN(C80,Inputs!$E$70/MAX(1,Inputs!$E$72*12)) -> 0 | D82: =-MIN(D80,Inputs!$E$70/MAX(1,Inputs!$E$72*12)) -> -25000 | E82: =-MIN(E80,Inputs!$E$70/MAX(1,Inputs!$E$72*12)) -> -25000 | F82: =-MIN(F80,Inputs!$E$70/MAX(1,Inputs!$E$72*12)) -> -25000 | G82: =-MIN(G80,Inputs!$E$70/MAX(1,Inputs!$E$72*12)) -> -25000 | H82: =-MIN(H80,Inputs!$E$70/MAX(1,Inputs!$E$72*12)) -> -25000 | I82: =-MIN(I80,Inputs!$E$70/MAX(1,Inputs!$E$72*12)) -> -25000 | J82: =-MIN(J80,Inputs!$E$70/MAX(1,Inputs!$E$72*12)) -> -25000 | ... AL82: =-MIN(AL80,Inputs!$E$70/MAX(1,Inputs!$E$72*12)) -> -25000
A83: Loan — closing balance | C83: =C80+C81+C82 -> 3000000 | D83: =D80+D81+D82 -> 2975000 | E83: =E80+E81+E82 -> 2950000 | F83: =F80+F81+F82 -> 2925000 | G83: =G80+G81+G82 -> 2900000 | H83: =H80+H81+H82 -> 2875000 | I83: =I80+I81+I82 -> 2850000 | J83: =J80+J81+J82 -> 2825000 | ... AL83: =AL80+AL81+AL82 -> 2125000
A85: Working capital
A86: Accounts receivable | C86: =C37*Inputs!$E$75/30 -> 3196.2239 | D86: =D37*Inputs!$E$75/30 -> 3629.9291 | E86: =E37*Inputs!$E$75/30 -> 4851.5601 | F86: =F37*Inputs!$E$75/30 -> 5403.4599 | G86: =G37*Inputs!$E$75/30 -> 5966.0184 | H86: =H37*Inputs!$E$75/30 -> 6538.8093 | I86: =I37*Inputs!$E$75/30 -> 7121.4232 | J86: =J37*Inputs!$E$75/30 -> 7713.4673 | ... AL86: =AL37*Inputs!$E$75/30 -> 11443.887
A87: Inventory | C87: =-C45*Inputs!$E$76/30 -> 1650.1207 | D87: =-D45*Inputs!$E$76/30 -> 1874.0047 | E87: =-E45*Inputs!$E$76/30 -> 2584.5949 | F87: =-F45*Inputs!$E$76/30 -> 2884.3959 | G87: =-G45*Inputs!$E$76/30 -> 3191.701 | H87: =-H45*Inputs!$E$76/30 -> 3506.2099 | I87: =-I45*Inputs!$E$76/30 -> 3827.6344 | J87: =-J45*Inputs!$E$76/30 -> 4155.698 | ... AL87: =-AL45*Inputs!$E$76/30 -> 6271.585
A88: Accounts payable | C88: =-C45*Inputs!$E$77/30 -> 4714.6305 | D88: =-D45*Inputs!$E$77/30 -> 5354.2992 | E88: =-E45*Inputs!$E$77/30 -> 7384.5568 | F88: =-F45*Inputs!$E$77/30 -> 8241.1313 | G88: =-G45*Inputs!$E$77/30 -> 9119.1457 | H88: =-H45*Inputs!$E$77/30 -> 10017.742 | I88: =-I45*Inputs!$E$77/30 -> 10936.098 | J88: =-J45*Inputs!$E$77/30 -> 11873.423 | ... AL88: =-AL45*Inputs!$E$77/30 -> 17918.814
A89: (Increase) / decrease in receivables | C89: =-C86 -> -3196.2239 | D89: =C86-D86 -> -433.70519 | E89: =D86-E86 -> -1221.6311 | F89: =E86-F86 -> -551.8998 | G89: =F86-G86 -> -562.55851 | H89: =G86-H86 -> -572.79086 | I89: =H86-I86 -> -582.61392 | J89: =I86-J86 -> -592.04406 | K89: =J86-K86 -> -601.097 | ... AL89: =AK86-AL86 -> 1417.7367
A90: (Increase) / decrease in inventory | C90: =-C87 -> -1650.1207 | D90: =C87-D87 -> -223.88405 | E90: =D87-E87 -> -710.59017 | F90: =E87-F87 -> -299.80105 | G90: =F87-G87 -> -307.30504 | H90: =G87-H87 -> -314.50887 | I90: =H87-I87 -> -321.42456 | J90: =I87-J87 -> -328.06361 | K90: =J87-K87 -> -334.4371 | ... AL90: =AK87-AL87 -> 1300.5775
A91: Increase / (decrease) in payables | C91: =C88 -> 4714.6305 | D91: =D88-C88 -> 639.66871 | E91: =E88-D88 -> 2030.2576 | F91: =F88-E88 -> 856.57442 | G91: =G88-F88 -> 878.0144 | H91: =H88-G88 -> 898.59678 | I91: =I88-H88 -> 918.35587 | J91: =J88-I88 -> 937.3246 | K91: =K88-J88 -> 955.53457 | ... AL91: =AL88-AK88 -> -3715.9356
A93: Cash flow
A94: Operating cash flow | C94: =C64-C75+C89+C90+C91 -> -74096.968 | D94: =D64-D75+D89+D90+D91 -> -68348.558 | E94: =E64-E75+E89+E90+E91 -> -52776.439 | F94: =F64-F75+F89+F90+F91 -> -45698.883 | G94: =G64-G75+G89+G90+G91 -> -38397.166 | H94: =H64-H75+H89+H90+H91 -> -30972.969 | I94: =I64-I75+I89+I90+I91 -> -23431.19 | J94: =J64-J75+J89+J90+J91 -> -15776.533 | ... AL94: =AL64-AL75+AL89+AL90+AL91 -> 34406.535
A95: Investing cash flow (capex) | C95: =-C72 -> -4100000 | D95: =-D72 -> 0 | E95: =-E72 -> 0 | F95: =-F72 -> 0 | G95: =-G72 -> 0 | H95: =-H72 -> 0 | I95: =-I72 -> 0 | J95: =-J72 -> 0 | ... AL95: =-AL72 -> 0
A96: Equity raised | C96: =IF(C$4=1,Inputs!$E$69,0) -> 2100000 | D96: =IF(D$4=1,Inputs!$E$69,0) -> 0 | E96: =IF(E$4=1,Inputs!$E$69,0) -> 0 | F96: =IF(F$4=1,Inputs!$E$69,0) -> 0 | G96: =IF(G$4=1,Inputs!$E$69,0) -> 0 | H96: =IF(H$4=1,Inputs!$E$69,0) -> 0 | I96: =IF(I$4=1,Inputs!$E$69,0) -> 0 | J96: =IF(J$4=1,Inputs!$E$69,0) -> 0 | ... AL96: =IF(AL$4=1,Inputs!$E$69,0) -> 0
A97: Financing cash flow | C97: =C96+C81+C82 -> 5100000 | D97: =D96+D81+D82 -> -25000 | E97: =E96+E81+E82 -> -25000 | F97: =F96+F81+F82 -> -25000 | G97: =G96+G81+G82 -> -25000 | H97: =H96+H81+H82 -> -25000 | I97: =I96+I81+I82 -> -25000 | J97: =J96+J81+J82 -> -25000 | ... AL97: =AL96+AL81+AL82 -> -25000
A98: Net cash flow | C98: =C94+C95+C97 -> 925903.03 | D98: =D94+D95+D97 -> -93348.558 | E98: =E94+E95+E97 -> -77776.439 | F98: =F94+F95+F97 -> -70698.883 | G98: =G94+G95+G97 -> -63397.166 | H98: =H94+H95+H97 -> -55972.969 | I98: =I94+I95+I97 -> -48431.19 | J98: =J94+J95+J97 -> -40776.533 | ... AL98: =AL94+AL95+AL97 -> 9406.5352
A99: Opening cash | C99: =0 -> 0 | D99: =C100 -> 925903.03 | E99: =D100 -> 832554.47 | F99: =E100 -> 754778.03 | G99: =F100 -> 684079.15 | H99: =G100 -> 620681.99 | I99: =H100 -> 564709.02 | J99: =I100 -> 516277.83 | K99: =J100 -> 475501.29 | ... AL99: =AK100 -> 366617.78
A100: Closing cash | C100: =C99+C98 -> 925903.03 | D100: =D99+D98 -> 832554.47 | E100: =E99+E98 -> 754778.03 | F100: =F99+F98 -> 684079.15 | G100: =G99+G98 -> 620681.99 | H100: =H99+H98 -> 564709.02 | I100: =I99+I98 -> 516277.83 | J100: =J99+J98 -> 475501.29 | ... AL100: =AL99+AL98 -> 376024.31
A101: Helper: EBITDA positive (1/0) | C101: =IF(C55>0,1,0) -> 0 | D101: =IF(D55>0,1,0) -> 0 | E101: =IF(E55>0,1,0) -> 0 | F101: =IF(F55>0,1,0) -> 0 | G101: =IF(G55>0,1,0) -> 0 | H101: =IF(H55>0,1,0) -> 0 | I101: =IF(I55>0,1,0) -> 0 | J101: =IF(J55>0,1,0) -> 1 | ... AL101: =IF(AL55>0,1,0) -> 1
A103: Goal modules
A104: Helper: net income positive (1/0) | C104: =IF(C64>0,1,0) -> 0 | D104: =IF(D64>0,1,0) -> 0 | E104: =IF(E64>0,1,0) -> 0 | F104: =IF(F64>0,1,0) -> 0 | G104: =IF(G64>0,1,0) -> 0 | H104: =IF(H64>0,1,0) -> 0 | I104: =IF(I64>0,1,0) -> 0 | J104: =IF(J64>0,1,0) -> 0 | ... AL104: =IF(AL64>0,1,0) -> 1
A105: Cash flow before financing (operating + investing) | C105: =C94+C95 -> -4174097 | D105: =D94+D95 -> -68348.558 | E105: =E94+E95 -> -52776.439 | F105: =F94+F95 -> -45698.883 | G105: =G94+G95 -> -38397.166 | H105: =H94+H95 -> -30972.969 | I105: =I94+I95 -> -23431.19 | J105: =J94+J95 -> -15776.533 | ... AL105: =AL94+AL95 -> 34406.535
A106: Cumulative cash flow before financing | C106: =C105 -> -4174097 | D106: =C106+D105 -> -4242445.5 | E106: =D106+E105 -> -4295222 | F106: =E106+F105 -> -4340920.8 | G106: =F106+G105 -> -4379318 | H106: =G106+H105 -> -4410291 | I106: =H106+I105 -> -4433722.2 | J106: =I106+J105 -> -4449498.7 | K106: =J106+K105 -> -4457512.2 | ... AL106: =AK106+AL105 -> -3848975.7
A107: Helper: lowest cumulative cash flow so far | C107: =C106 -> -4174097 | D107: =MIN(C107,D106) -> -4242445.5 | E107: =MIN(D107,E106) -> -4295222 | F107: =MIN(E107,F106) -> -4340920.8 | G107: =MIN(F107,G106) -> -4379318 | H107: =MIN(G107,H106) -> -4410291 | I107: =MIN(H107,I106) -> -4433722.2 | J107: =MIN(I107,J106) -> -4449498.7 | K107: =MIN(J107,K106) -> -4457512.2 | ... AL107: =MIN(AK107,AL106) -> -4517572.5
A108: Helper: investment paid back (1/0) | C108: =IF(AND(C106>=0,C107<0),1,0) -> 0 | D108: =IF(AND(D106>=0,D107<0),1,0) -> 0 | E108: =IF(AND(E106>=0,E107<0),1,0) -> 0 | F108: =IF(AND(F106>=0,F107<0),1,0) -> 0 | G108: =IF(AND(G106>=0,G107<0),1,0) -> 0 | H108: =IF(AND(H106>=0,H107<0),1,0) -> 0 | I108: =IF(AND(I106>=0,I107<0),1,0) -> 0 | J108: =IF(AND(J106>=0,J107<0),1,0) -> 0 | ... AL108: =IF(AND(AL106>=0,AL107<0),1,0) -> 0
A109: Unlevered free cash flow (operating + after-tax interest − capex) | C109: =C94-C59*(1-Inputs!$E$81)+C95 -> -4157309.5 | D109: =D94-D59*(1-Inputs!$E$81)+D95 -> -51631.006 | E109: =E94-E59*(1-Inputs!$E$81)+E95 -> -36198.782 | F109: =F94-F59*(1-Inputs!$E$81)+F95 -> -29261.122 | G109: =G94-G59*(1-Inputs!$E$81)+G95 -> -22099.302 | H109: =H94-H59*(1-Inputs!$E$81)+H95 -> -14815 | I109: =I94-I59*(1-Inputs!$E$81)+I95 -> -7413.1172 | J109: =J94-J59*(1-Inputs!$E$81)+J95 -> 101.64386 | ... AL109: =AL94-AL59*(1-Inputs!$E$81)+AL95 -> 46367.629
A111: Balance sheet
A112: Paid-in capital | C112: =C96 -> 2100000 | D112: =C112+D96 -> 2100000 | E112: =D112+E96 -> 2100000 | F112: =E112+F96 -> 2100000 | G112: =F112+G96 -> 2100000 | H112: =G112+H96 -> 2100000 | I112: =H112+I96 -> 2100000 | J112: =I112+J96 -> 2100000 | K112: =J112+K96 -> 2100000 | ... AL112: =AK112+AL96 -> 2100000
A113: Retained earnings | C113: =C64 -> -102437.48 | D113: =C113+D64 -> -199240.34 | E113: =D113+E64 -> -280587.03 | F113: =E113+F64 -> -354763.01 | G113: =F113+G64 -> -421640.55 | H113: =G113+H64 -> -481097.04 | I113: =H113+I64 -> -533014.77 | J113: =I113+J64 -> -577280.74 | K113: =J113+K64 -> -613786.48 | ... AL113: =AK113+AL64 -> -704179.03
...

Sheet Headcount
A1: Headcount & payroll | D1: =HYPERLINK("#'Cover'!A1","◂ Contents") -> ◂ Contents
A2: $ unless stated; costs shown as negatives. Every period uses the same formula.
A3: Month | C3: M1 | D3: M2 | E3: M3 | F3: M4 | G3: M5 | H3: M6 | I3: M7 | J3: M8 | K3: M9 | L3: M10 | M3: M11 | N3: M12 | O3: M13 | P3: M14 | Q3: M15 | R3: M16 | S3: M17 | T3: M18 | U3: M19 | V3: M20 | W3: M21 | X3: M22 | Y3: M23 | Z3: M24 | AA3: M25 | AB3: M26 | AC3: M27 | AD3: M28 | AE3: M29 | AF3: M30 | AG3: M31 | AH3: M32 | AI3: M33 | AJ3: M34 | AK3: M35 | AL3: M36
A4: Period # | C4: 1 | D4: 2 | E4: 3 | F4: 4 | G4: 5 | H4: 6 | I4: 7 | J4: 8 | K4: 9 | L4: 10 | M4: 11 | N4: 12 | O4: 13 | P4: 14 | Q4: 15 | R4: 16 | S4: 17 | T4: 18 | U4: 19 | V4: 20 | W4: 21 | X4: 22 | Y4: 23 | Z4: 24 | AA4: 25 | AB4: 26 | AC4: 27 | AD4: 28 | AE4: 29 | AF4: 30 | AG4: 31 | AH4: 32 | AI4: 33 | AJ4: 34 | AK4: 35 | AL4: 36
A5: Year # | C5: =ROUNDUP(C4*1/12,0) -> 1 | D5: =ROUNDUP(D4*1/12,0) -> 1 | E5: =ROUNDUP(E4*1/12,0) -> 1 | F5: =ROUNDUP(F4*1/12,0) -> 1 | G5: =ROUNDUP(G4*1/12,0) -> 1 | H5: =ROUNDUP(H4*1/12,0) -> 1 | I5: =ROUNDUP(I4*1/12,0) -> 1 | J5: =ROUNDUP(J4*1/12,0) -> 1 | ... AL5: =ROUNDUP(AL4*1/12,0) -> 3
A7: Headcount (FTE)
A8: Site manager — FTE | C8: =Inputs!$E$57*(1+Inputs!$E$59)^(C$5-1)*MAX(0,MIN(1,C$4*1-Inputs!$E$60+1))/1 -> 1 | D8: =Inputs!$E$57*(1+Inputs!$E$59)^(D$5-1)*MAX(0,MIN(1,D$4*1-Inputs!$E$60+1))/1 -> 1 | E8: =Inputs!$E$57*(1+Inputs!$E$59)^(E$5-1)*MAX(0,MIN(1,E$4*1-Inputs!$E$60+1))/1 -> 1 | F8: =Inputs!$E$57*(1+Inputs!$E$59)^(F$5-1)*MAX(0,MIN(1,F$4*1-Inputs!$E$60+1))/1 -> 1 | G8: =Inputs!$E$57*(1+Inputs!$E$59)^(G$5-1)*MAX(0,MIN(1,G$4*1-Inputs!$E$60+1))/1 -> 1 | H8: =Inputs!$E$57*(1+Inputs!$E$59)^(H$5-1)*MAX(0,MIN(1,H$4*1-Inputs!$E$60+1))/1 -> 1 | I8: =Inputs!$E$57*(1+Inputs!$E$59)^(I$5-1)*MAX(0,MIN(1,I$4*1-Inputs!$E$60+1))/1 -> 1 | J8: =Inputs!$E$57*(1+Inputs!$E$59)^(J$5-1)*MAX(0,MIN(1,J$4*1-Inputs!$E$60+1))/1 -> 1 | ... AL8: =Inputs!$E$57*(1+Inputs!$E$59)^(AL$5-1)*MAX(0,MIN(1,AL$4*1-Inputs!$E$60+1))/1 -> 1
A9: Wash attendants & customer service — FTE | C9: =Inputs!$E$61*(1+Inputs!$E$63)^(C$5-1)*MAX(0,MIN(1,C$4*1-Inputs!$E$64+1))/1 -> 10 | D9: =Inputs!$E$61*(1+Inputs!$E$63)^(D$5-1)*MAX(0,MIN(1,D$4*1-Inputs!$E$64+1))/1 -> 10 | E9: =Inputs!$E$61*(1+Inputs!$E$63)^(E$5-1)*MAX(0,MIN(1,E$4*1-Inputs!$E$64+1))/1 -> 10 | F9: =Inputs!$E$61*(1+Inputs!$E$63)^(F$5-1)*MAX(0,MIN(1,F$4*1-Inputs!$E$64+1))/1 -> 10 | G9: =Inputs!$E$61*(1+Inputs!$E$63)^(G$5-1)*MAX(0,MIN(1,G$4*1-Inputs!$E$64+1))/1 -> 10 | H9: =Inputs!$E$61*(1+Inputs!$E$63)^(H$5-1)*MAX(0,MIN(1,H$4*1-Inputs!$E$64+1))/1 -> 10 | I9: =Inputs!$E$61*(1+Inputs!$E$63)^(I$5-1)*MAX(0,MIN(1,I$4*1-Inputs!$E$64+1))/1 -> 10 | J9: =Inputs!$E$61*(1+Inputs!$E$63)^(J$5-1)*MAX(0,MIN(1,J$4*1-Inputs!$E$64+1))/1 -> 10 | ... AL9: =Inputs!$E$61*(1+Inputs!$E$63)^(AL$5-1)*MAX(0,MIN(1,AL$4*1-Inputs!$E$64+1))/1 -> 10
A10: Total FTE | C10: =C8+C9 -> 11 | D10: =D8+D9 -> 11 | E10: =E8+E9 -> 11 | F10: =F8+F9 -> 11 | G10: =G8+G9 -> 11 | H10: =H8+H9 -> 11 | I10: =I8+I9 -> 11 | J10: =J8+J9 -> 11 | ... AL10: =AL8+AL9 -> 11
A12: Payroll cost (salary + taxes & benefits)
A13: Site manager — payroll cost | C13: =-C8*Inputs!$E$58/12*1*(1+Inputs!$E$65)*(1+Inputs!$E$66)^(C$5-1) -> -6720 | D13: =-D8*Inputs!$E$58/12*1*(1+Inputs!$E$65)*(1+Inputs!$E$66)^(D$5-1) -> -6720 | E13: =-E8*Inputs!$E$58/12*1*(1+Inputs!$E$65)*(1+Inputs!$E$66)^(E$5-1) -> -6720 | F13: =-F8*Inputs!$E$58/12*1*(1+Inputs!$E$65)*(1+Inputs!$E$66)^(F$5-1) -> -6720 | G13: =-G8*Inputs!$E$58/12*1*(1+Inputs!$E$65)*(1+Inputs!$E$66)^(G$5-1) -> -6720 | H13: =-H8*Inputs!$E$58/12*1*(1+Inputs!$E$65)*(1+Inputs!$E$66)^(H$5-1) -> -6720 | I13: =-I8*Inputs!$E$58/12*1*(1+Inputs!$E$65)*(1+Inputs!$E$66)^(I$5-1) -> -6720 | J13: =-J8*Inputs!$E$58/12*1*(1+Inputs!$E$65)*(1+Inputs!$E$66)^(J$5-1) -> -6720 | ... AL13: =-AL8*Inputs!$E$58/12*1*(1+Inputs!$E$65)*(1+Inputs!$E$66)^(AL$5-1) -> -7129.248
A14: Wash attendants & customer service — payroll cost | C14: =-C9*Inputs!$E$62/12*1*(1+Inputs!$E$65)*(1+Inputs!$E$66)^(C$5-1) -> -29866.667 | D14: =-D9*Inputs!$E$62/12*1*(1+Inputs!$E$65)*(1+Inputs!$E$66)^(D$5-1) -> -29866.667 | E14: =-E9*Inputs!$E$62/12*1*(1+Inputs!$E$65)*(1+Inputs!$E$66)^(E$5-1) -> -29866.667 | F14: =-F9*Inputs!$E$62/12*1*(1+Inputs!$E$65)*(1+Inputs!$E$66)^(F$5-1) -> -29866.667 | G14: =-G9*Inputs!$E$62/12*1*(1+Inputs!$E$65)*(1+Inputs!$E$66)^(G$5-1) -> -29866.667 | H14: =-H9*Inputs!$E$62/12*1*(1+Inputs!$E$65)*(1+Inputs!$E$66)^(H$5-1) -> -29866.667 | I14: =-I9*Inputs!$E$62/12*1*(1+Inputs!$E$65)*(1+Inputs!$E$66)^(I$5-1) -> -29866.667 | J14: =-J9*Inputs!$E$62/12*1*(1+Inputs!$E$65)*(1+Inputs!$E$66)^(J$5-1) -> -29866.667 | ... AL14: =-AL9*Inputs!$E$62/12*1*(1+Inputs!$E$65)*(1+Inputs!$E$66)^(AL$5-1) -> -31685.547
A15: Total payroll | C15: =C13+C14 -> -36586.667 | D15: =D13+D14 -> -36586.667 | E15: =E13+E14 -> -36586.667 | F15: =F13+F14 -> -36586.667 | G15: =G13+G14 -> -36586.667 | H15: =H13+H14 -> -36586.667 | I15: =I13+I14 -> -36586.667 | J15: =J13+J14 -> -36586.667 | ... AL15: =AL13+AL14 -> -38814.795

Sheet Scenario calc
A1: Scenario calculation — Low, Base and High side by side | D1: =HYPERLINK("#'Cover'!A1","◂ Contents") -> ◂ Contents
A2: The model's period calculation, copied three times; each copy reads its own Inputs column. Feeds the Scenarios sheet only.
A4: Low scenario — reads Inputs column B
A5: Month | C5: M1 | D5: M2 | E5: M3 | F5: M4 | G5: M5 | H5: M6 | I5: M7 | J5: M8 | K5: M9 | L5: M10 | M5: M11 | N5: M12 | O5: M13 | P5: M14 | Q5: M15 | R5: M16 | S5: M17 | T5: M18 | U5: M19 | V5: M20 | W5: M21 | X5: M22 | Y5: M23 | Z5: M24 | AA5: M25 | AB5: M26 | AC5: M27 | AD5: M28 | AE5: M29 | AF5: M30 | AG5: M31 | AH5: M32 | AI5: M33 | AJ5: M34 | AK5: M35 | AL5: M36
A6: Period # | C6: 1 | D6: 2 | E6: 3 | F6: 4 | G6: 5 | H6: 6 | I6: 7 | J6: 8 | K6: 9 | L6: 10 | M6: 11 | N6: 12 | O6: 13 | P6: 14 | Q6: 15 | R6: 16 | S6: 17 | T6: 18 | U6: 19 | V6: 20 | W6: 21 | X6: 22 | Y6: 23 | Z6: 24 | AA6: 25 | AB6: 26 | AC6: 27 | AD6: 28 | AE6: 29 | AF6: 30 | AG6: 31 | AH6: 32 | AI6: 33 | AJ6: 34 | AK6: 35 | AL6: 36
A7: Year # | C7: =ROUNDUP(C6*1/12,0) -> 1 | D7: =ROUNDUP(D6*1/12,0) -> 1 | E7: =ROUNDUP(E6*1/12,0) -> 1 | F7: =ROUNDUP(F6*1/12,0) -> 1 | G7: =ROUNDUP(G6*1/12,0) -> 1 | H7: =ROUNDUP(H6*1/12,0) -> 1 | I7: =ROUNDUP(I6*1/12,0) -> 1 | J7: =ROUNDUP(J6*1/12,0) -> 1 | ... AL7: =ROUNDUP(AL6*1/12,0) -> 3
A9: Volume
A10: Helper: months of the period still on the ramp-up | C10: =MAX(0,MIN(1,Inputs!$B$10-(C$6-1)*1)) -> 1 | D10: =MAX(0,MIN(1,Inputs!$B$10-(D$6-1)*1)) -> 1 | E10: =MAX(0,MIN(1,Inputs!$B$10-(E$6-1)*1)) -> 1 | F10: =MAX(0,MIN(1,Inputs!$B$10-(F$6-1)*1)) -> 1 | G10: =MAX(0,MIN(1,Inputs!$B$10-(G$6-1)*1)) -> 1 | H10: =MAX(0,MIN(1,Inputs!$B$10-(H$6-1)*1)) -> 1 | I10: =MAX(0,MIN(1,Inputs!$B$10-(I$6-1)*1)) -> 1 | J10: =MAX(0,MIN(1,Inputs!$B$10-(J$6-1)*1)) -> 1 | ... AL10: =MAX(0,MIN(1,Inputs!$B$10-(AL$6-1)*1)) -> 0
A11: Ramp-up factor (share of mature retail volume) | C11: =IF(Inputs!$B$10<=0,1,(C10*Inputs!$B$11+(1-Inputs!$B$11)/MAX(1,Inputs!$B$10)*(C10*(C$6-1)*1+C10*(C10-1)/2)+1-C10)/1) -> 0.35 | D11: =IF(Inputs!$B$10<=0,1,(D10*Inputs!$B$11+(1-Inputs!$B$11)/MAX(1,Inputs!$B$10)*(D10*(D$6-1)*1+D10*(D10-1)/2)+1-D10)/1) -> 0.40416667 | E11: =IF(Inputs!$B$10<=0,1,(E10*Inputs!$B$11+(1-Inputs!$B$11)/MAX(1,Inputs!$B$10)*(E10*(E$6-1)*1+E10*(E10-1)/2)+1-E10)/1) -> 0.45833333 | F11: =IF(Inputs!$B$10<=0,1,(F10*Inputs!$B$11+(1-Inputs!$B$11)/MAX(1,Inputs!$B$10)*(F10*(F$6-1)*1+F10*(F10-1)/2)+1-F10)/1) -> 0.5125 | G11: =IF(Inputs!$B$10<=0,1,(G10*Inputs!$B$11+(1-Inputs!$B$11)/MAX(1,Inputs!$B$10)*(G10*(G$6-1)*1+G10*(G10-1)/2)+1-G10)/1) -> 0.56666667 | H11: =IF(Inputs!$B$10<=0,1,(H10*Inputs!$B$11+(1-Inputs!$B$11)/MAX(1,Inputs!$B$10)*(H10*(H$6-1)*1+H10*(H10-1)/2)+1-H10)/1) -> 0.62083333 | I11: =IF(Inputs!$B$10<=0,1,(I10*Inputs!$B$11+(1-Inputs!$B$11)/MAX(1,Inputs!$B$10)*(I10*(I$6-1)*1+I10*(I10-1)/2)+1-I10)/1) -> 0.675 | J11: =IF(Inputs!$B$10<=0,1,(J10*Inputs!$B$11+(1-Inputs!$B$11)/MAX(1,Inputs!$B$10)*(J10*(J$6-1)*1+J10*(J10-1)/2)+1-J10)/1) -> 0.72916667 | ... AL11: =IF(Inputs!$B$10<=0,1,(AL10*Inputs!$B$11+(1-Inputs!$B$11)/MAX(1,Inputs!$B$10)*(AL10*(AL$6-1)*1+AL10*(AL10-1)/2)+1-AL10)/1) -> 1
A12: Season factor (winter dip) | C12: =IF(OR(MOD(C$6-1,12)>=11,MOD(C$6-1,12)<=1),1-Inputs!$B$12,1+Inputs!$B$12/3) -> 0.8 | D12: =IF(OR(MOD(D$6-1,12)>=11,MOD(D$6-1,12)<=1),1-Inputs!$B$12,1+Inputs!$B$12/3) -> 0.8 | E12: =IF(OR(MOD(E$6-1,12)>=11,MOD(E$6-1,12)<=1),1-Inputs!$B$12,1+Inputs!$B$12/3) -> 1.0666667 | F12: =IF(OR(MOD(F$6-1,12)>=11,MOD(F$6-1,12)<=1),1-Inputs!$B$12,1+Inputs!$B$12/3) -> 1.0666667 | G12: =IF(OR(MOD(G$6-1,12)>=11,MOD(G$6-1,12)<=1),1-Inputs!$B$12,1+Inputs!$B$12/3) -> 1.0666667 | H12: =IF(OR(MOD(H$6-1,12)>=11,MOD(H$6-1,12)<=1),1-Inputs!$B$12,1+Inputs!$B$12/3) -> 1.0666667 | I12: =IF(OR(MOD(I$6-1,12)>=11,MOD(I$6-1,12)<=1),1-Inputs!$B$12,1+Inputs!$B$12/3) -> 1.0666667 | J12: =IF(OR(MOD(J$6-1,12)>=11,MOD(J$6-1,12)<=1),1-Inputs!$B$12,1+Inputs!$B$12/3) -> 1.0666667 | ... AL12: =IF(OR(MOD(AL$6-1,12)>=11,MOD(AL$6-1,12)<=1),1-Inputs!$B$12,1+Inputs!$B$12/3) -> 0.8
A13: Retail cars demanded | C13: =Inputs!$B$7*(1+Inputs!$B$8)^(C$7-1)*Inputs!$B$9*1*C11*C12 -> 1624 | D13: =Inputs!$B$7*(1+Inputs!$B$8)^(D$7-1)*Inputs!$B$9*1*D11*D12 -> 1875.3333 | E13: =Inputs!$B$7*(1+Inputs!$B$8)^(E$7-1)*Inputs!$B$9*1*E11*E12 -> 2835.5556 | F13: =Inputs!$B$7*(1+Inputs!$B$8)^(F$7-1)*Inputs!$B$9*1*F11*F12 -> 3170.6667 | G13: =Inputs!$B$7*(1+Inputs!$B$8)^(G$7-1)*Inputs!$B$9*1*G11*G12 -> 3505.7778 | H13: =Inputs!$B$7*(1+Inputs!$B$8)^(H$7-1)*Inputs!$B$9*1*H11*H12 -> 3840.8889 | I13: =Inputs!$B$7*(1+Inputs!$B$8)^(I$7-1)*Inputs!$B$9*1*I11*I12 -> 4176 | J13: =Inputs!$B$7*(1+Inputs!$B$8)^(J$7-1)*Inputs!$B$9*1*J11*J12 -> 4511.1111 | ... AL13: =Inputs!$B$7*(1+Inputs!$B$8)^(AL$7-1)*Inputs!$B$9*1*AL11*AL12 -> 4640
A15: Members
A16: New members from retail cars | C16: =C13*Inputs!$B$23 -> 9.744 | D16: =D13*Inputs!$B$23 -> 11.252 | E16: =E13*Inputs!$B$23 -> 17.013333 | F16: =F13*Inputs!$B$23 -> 19.024 | G16: =G13*Inputs!$B$23 -> 21.034667 | H16: =H13*Inputs!$B$23 -> 23.045333 | I16: =I13*Inputs!$B$23 -> 25.056 | J16: =J13*Inputs!$B$23 -> 27.066667 | ... AL16: =AL13*Inputs!$B$23 -> 27.84
A17: New members from direct sign-ups | C17: =Inputs!$B$21*(1+Inputs!$B$22)^(C$7-1)*1*C11 -> 14 | D17: =Inputs!$B$21*(1+Inputs!$B$22)^(D$7-1)*1*D11 -> 16.166667 | E17: =Inputs!$B$21*(1+Inputs!$B$22)^(E$7-1)*1*E11 -> 18.333333 | F17: =Inputs!$B$21*(1+Inputs!$B$22)^(F$7-1)*1*F11 -> 20.5 | G17: =Inputs!$B$21*(1+Inputs!$B$22)^(G$7-1)*1*G11 -> 22.666667 | H17: =Inputs!$B$21*(1+Inputs!$B$22)^(H$7-1)*1*H11 -> 24.833333 | I17: =Inputs!$B$21*(1+Inputs!$B$22)^(I$7-1)*1*I11 -> 27 | J17: =Inputs!$B$21*(1+Inputs!$B$22)^(J$7-1)*1*J11 -> 29.166667 | ... AL17: =Inputs!$B$21*(1+Inputs!$B$22)^(AL$7-1)*1*AL11 -> 40
A18: New members - total | C18: =C16+C17 -> 23.744 | D18: =D16+D17 -> 27.418667 | E18: =E16+E17 -> 35.346667 | F18: =F16+F17 -> 39.524 | G18: =G16+G17 -> 43.701333 | H18: =H16+H17 -> 47.878667 | I18: =I16+I17 -> 52.056 | J18: =J16+J17 -> 56.233333 | ... AL18: =AL16+AL17 -> 67.84
A19: Members - opening | C19: =Inputs!$B$20 -> 150 | D19: =C21 -> 166.244 | E19: =D21 -> 185.35047 | F19: =E21 -> 211.42961 | G19: =F21 -> 240.38213 | H19: =G21 -> 272.06436 | I19: =H21 -> 306.33981 | J19: =I21 -> 343.07881 | K19: =J21 -> 382.15821 | ... AL19: =AK21 -> 1214.7934
A20: Members who cancelled | C20: =C21-C19-C18 -> -7.5 | D20: =D21-D19-D18 -> -8.3122 | E20: =E21-E19-E18 -> -9.2675233 | F20: =F21-F19-F18 -> -10.57148 | G20: =G21-G19-G18 -> -12.019106 | H20: =H21-H19-H18 -> -13.603218 | I20: =I21-I19-I18 -> -15.31699 | J20: =J21-J19-J18 -> -17.153941 | ... AL20: =AL21-AL19-AL18 -> -60.73967
A21: Members - closing | C21: =C19*(1-Inputs!$B$24)+C18 -> 166.244 | D21: =D19*(1-Inputs!$B$24)+D18 -> 185.35047 | E21: =E19*(1-Inputs!$B$24)+E18 -> 211.42961 | F21: =F19*(1-Inputs!$B$24)+F18 -> 240.38213 | G21: =G19*(1-Inputs!$B$24)+G18 -> 272.06436 | H21: =H19*(1-Inputs!$B$24)+H18 -> 306.33981 | I21: =I19*(1-Inputs!$B$24)+I18 -> 343.07881 | J21: =J19*(1-Inputs!$B$24)+J18 -> 382.15821 | ... AL21: =AL19*(1-Inputs!$B$24)+AL18 -> 1221.8937
A22: Members - average | C22: =(C19+C21)/2 -> 158.122 | D22: =(D19+D21)/2 -> 175.79723 | E22: =(E19+E21)/2 -> 198.39004 | F22: =(F19+F21)/2 -> 225.90587 | G22: =(G19+G21)/2 -> 256.22324 | H22: =(H19+H21)/2 -> 289.20208 | I22: =(I19+I21)/2 -> 324.70931 | J22: =(J19+J21)/2 -> 362.61851 | ... AL22: =(AL19+AL21)/2 -> 1218.3436
A24: Washes
A25: Member washes demanded | C25: =C22*Inputs!$B$25*C12*1 -> 480.69088 | D25: =D22*Inputs!$B$25*D12*1 -> 534.42359 | E25: =E22*Inputs!$B$25*E12*1 -> 804.14096 | F25: =F22*Inputs!$B$25*F12*1 -> 915.67179 | G25: =G22*Inputs!$B$25*G12*1 -> 1038.5582 | H25: =H22*Inputs!$B$25*H12*1 -> 1172.2324 | I25: =I22*Inputs!$B$25*I12*1 -> 1316.1551 | J25: =J22*Inputs!$B$25*J12*1 -> 1469.8137 | ... AL25: =AL22*Inputs!$B$25*AL12*1 -> 3703.7644
A26: Tunnel capacity (rated speed × hours × practical share × days) | C26: =Inputs!$B$15*Inputs!$B$16*Inputs!$B$17*Inputs!$B$9*1 -> 24563 | D26: =Inputs!$B$15*Inputs!$B$16*Inputs!$B$17*Inputs!$B$9*1 -> 24563 | E26: =Inputs!$B$15*Inputs!$B$16*Inputs!$B$17*Inputs!$B$9*1 -> 24563 | F26: =Inputs!$B$15*Inputs!$B$16*Inputs!$B$17*Inputs!$B$9*1 -> 24563 | G26: =Inputs!$B$15*Inputs!$B$16*Inputs!$B$17*Inputs!$B$9*1 -> 24563 | H26: =Inputs!$B$15*Inputs!$B$16*Inputs!$B$17*Inputs!$B$9*1 -> 24563 | I26: =Inputs!$B$15*Inputs!$B$16*Inputs!$B$17*Inputs!$B$9*1 -> 24563 | J26: =Inputs!$B$15*Inputs!$B$16*Inputs!$B$17*Inputs!$B$9*1 -> 24563 | ... AL26: =Inputs!$B$15*Inputs!$B$16*Inputs!$B$17*Inputs!$B$9*1 -> 24563
A27: Share of demand the tunnel can wash | C27: =MIN(1,C26/MAX(1,C13+C25)) -> 1 | D27: =MIN(1,D26/MAX(1,D13+D25)) -> 1 | E27: =MIN(1,E26/MAX(1,E13+E25)) -> 1 | F27: =MIN(1,F26/MAX(1,F13+F25)) -> 1 | G27: =MIN(1,G26/MAX(1,G13+G25)) -> 1 | H27: =MIN(1,H26/MAX(1,H13+H25)) -> 1 | I27: =MIN(1,I26/MAX(1,I13+I25)) -> 1 | J27: =MIN(1,J26/MAX(1,J13+J25)) -> 1 | ... AL27: =MIN(1,AL26/MAX(1,AL13+AL25)) -> 1
A28: Retail cars washed | C28: =C13*C27 -> 1624 | D28: =D13*D27 -> 1875.3333 | E28: =E13*E27 -> 2835.5556 | F28: =F13*F27 -> 3170.6667 | G28: =G13*G27 -> 3505.7778 | H28: =H13*H27 -> 3840.8889 | I28: =I13*I27 -> 4176 | J28: =J13*J27 -> 4511.1111 | ... AL28: =AL13*AL27 -> 4640
A29: Member washes | C29: =C25*C27 -> 480.69088 | D29: =D25*D27 -> 534.42359 | E29: =E25*E27 -> 804.14096 | F29: =F25*F27 -> 915.67179 | G29: =G25*G27 -> 1038.5582 | H29: =H25*H27 -> 1172.2324 | I29: =I25*I27 -> 1316.1551 | J29: =J25*J27 -> 1469.8137 | ... AL29: =AL25*AL27 -> 3703.7644
A30: Washes - total | C30: =C28+C29 -> 2104.6909 | D30: =D28+D29 -> 2409.7569 | E30: =E28+E29 -> 3639.6965 | F30: =F28+F29 -> 4086.3385 | G30: =G28+G29 -> 4544.336 | H30: =H28+H29 -> 5013.1213 | I30: =I28+I29 -> 5492.1551 | J30: =J28+J29 -> 5980.9248 | ... AL30: =AL28+AL29 -> 8343.7644
A31: Washes lost to the capacity limit | C31: =C13+C25-C30 -> 0 | D31: =D13+D25-D30 -> 0 | E31: =E13+E25-E30 -> 0 | F31: =F13+F25-F30 -> 0 | G31: =G13+G25-G30 -> 0 | H31: =H13+H25-H30 -> 0 | I31: =I13+I25-I30 -> 0 | J31: =J13+J25-J30 -> 0 | ... AL31: =AL13+AL25-AL30 -> 0
A33: Revenue
A34: Average price per retail wash | C34: =Inputs!$B$28*(1+Inputs!$B$31)^(C$7-1) -> 12 | D34: =Inputs!$B$28*(1+Inputs!$B$31)^(D$7-1) -> 12 | E34: =Inputs!$B$28*(1+Inputs!$B$31)^(E$7-1) -> 12 | F34: =Inputs!$B$28*(1+Inputs!$B$31)^(F$7-1) -> 12 | G34: =Inputs!$B$28*(1+Inputs!$B$31)^(G$7-1) -> 12 | H34: =Inputs!$B$28*(1+Inputs!$B$31)^(H$7-1) -> 12 | I34: =Inputs!$B$28*(1+Inputs!$B$31)^(I$7-1) -> 12 | J34: =Inputs!$B$28*(1+Inputs!$B$31)^(J$7-1) -> 12 | ... AL34: =Inputs!$B$28*(1+Inputs!$B$31)^(AL$7-1) -> 12.2412
A35: Unlimited plan fee per month | C35: =Inputs!$B$30*(1+Inputs!$B$31)^(C$7-1) -> 32 | D35: =Inputs!$B$30*(1+Inputs!$B$31)^(D$7-1) -> 32 | E35: =Inputs!$B$30*(1+Inputs!$B$31)^(E$7-1) -> 32 | F35: =Inputs!$B$30*(1+Inputs!$B$31)^(F$7-1) -> 32 | G35: =Inputs!$B$30*(1+Inputs!$B$31)^(G$7-1) -> 32 | H35: =Inputs!$B$30*(1+Inputs!$B$31)^(H$7-1) -> 32 | I35: =Inputs!$B$30*(1+Inputs!$B$31)^(I$7-1) -> 32 | J35: =Inputs!$B$30*(1+Inputs!$B$31)^(J$7-1) -> 32 | ... AL35: =Inputs!$B$30*(1+Inputs!$B$31)^(AL$7-1) -> 32.6432
A36: Retail wash revenue | C36: =C28*C34 -> 19488 | D36: =D28*D34 -> 22504 | E36: =E28*E34 -> 34026.667 | F36: =F28*F34 -> 38048 | G36: =G28*G34 -> 42069.333 | H36: =H28*H34 -> 46090.667 | I36: =I28*I34 -> 50112 | J36: =J28*J34 -> 54133.333 | ... AL36: =AL28*AL34 -> 56799.168
A37: Add-on revenue | C37: =C28*Inputs!$B$29*(1+Inputs!$B$31)^(C$7-1) -> 1948.8 | D37: =D28*Inputs!$B$29*(1+Inputs!$B$31)^(D$7-1) -> 2250.4 | E37: =E28*Inputs!$B$29*(1+Inputs!$B$31)^(E$7-1) -> 3402.6667 | F37: =F28*Inputs!$B$29*(1+Inputs!$B$31)^(F$7-1) -> 3804.8 | G37: =G28*Inputs!$B$29*(1+Inputs!$B$31)^(G$7-1) -> 4206.9333 | H37: =H28*Inputs!$B$29*(1+Inputs!$B$31)^(H$7-1) -> 4609.0667 | I37: =I28*Inputs!$B$29*(1+Inputs!$B$31)^(I$7-1) -> 5011.2 | J37: =J28*Inputs!$B$29*(1+Inputs!$B$31)^(J$7-1) -> 5413.3333 | ... AL37: =AL28*Inputs!$B$29*(1+Inputs!$B$31)^(AL$7-1) -> 5679.9168
A38: Unlimited plan fees | C38: =C22*C35*1 -> 5059.904 | D38: =D22*D35*1 -> 5625.5115 | E38: =E22*E35*1 -> 6348.4812 | F38: =F22*F35*1 -> 7228.9878 | G38: =G22*G35*1 -> 8199.1438 | H38: =H22*H35*1 -> 9254.4666 | I38: =I22*I35*1 -> 10390.698 | J38: =J22*J35*1 -> 11603.792 | ... AL38: =AL22*AL35*1 -> 39770.633
A39: Revenue | C39: =C36+C37+C38 -> 26496.704 | D39: =D36+D37+D38 -> 30379.911 | E39: =E36+E37+E38 -> 43777.815 | F39: =F36+F37+F38 -> 49081.788 | G39: =G36+G37+G38 -> 54475.41 | H39: =H36+H37+H38 -> 59954.2 | I39: =I36+I37+I38 -> 65513.898 | J39: =J36+J37+J38 -> 71150.459 | ... AL39: =AL36+AL37+AL38 -> 102249.72
A41: Cost of sales
A42: Chemicals | C42: =-C30*Inputs!$B$34*(1+Inputs!$B$39)^(C$7-1) -> -1999.4563 | D42: =-D30*Inputs!$B$34*(1+Inputs!$B$39)^(D$7-1) -> -2289.2691 | E42: =-E30*Inputs!$B$34*(1+Inputs!$B$39)^(E$7-1) -> -3457.7117 | F42: =-F30*Inputs!$B$34*(1+Inputs!$B$39)^(F$7-1) -> -3882.0215 | G42: =-G30*Inputs!$B$34*(1+Inputs!$B$39)^(G$7-1) -> -4317.1192 | H42: =-H30*Inputs!$B$34*(1+Inputs!$B$39)^(H$7-1) -> -4762.4653 | I42: =-I30*Inputs!$B$34*(1+Inputs!$B$39)^(I$7-1) -> -5217.5473 | J42: =-J30*Inputs!$B$34*(1+Inputs!$B$39)^(J$7-1) -> -5681.8786 | ... AL42: =-AL30*Inputs!$B$34*(1+Inputs!$B$39)^(AL$7-1) -> -8573.3848
A43: Water & sewer | C43: =-C30*Inputs!$B$35/1000*Inputs!$B$36*(1+Inputs!$B$39)^(C$7-1) -> -947.1109 | D43: =-D30*Inputs!$B$35/1000*Inputs!$B$36*(1+Inputs!$B$39)^(D$7-1) -> -1084.3906 | E43: =-E30*Inputs!$B$35/1000*Inputs!$B$36*(1+Inputs!$B$39)^(E$7-1) -> -1637.8634 | F43: =-F30*Inputs!$B$35/1000*Inputs!$B$36*(1+Inputs!$B$39)^(F$7-1) -> -1838.8523 | G43: =-G30*Inputs!$B$35/1000*Inputs!$B$36*(1+Inputs!$B$39)^(G$7-1) -> -2044.9512 | H43: =-H30*Inputs!$B$35/1000*Inputs!$B$36*(1+Inputs!$B$39)^(H$7-1) -> -2255.9046 | I43: =-I30*Inputs!$B$35/1000*Inputs!$B$36*(1+Inputs!$B$39)^(I$7-1) -> -2471.4698 | J43: =-J30*Inputs!$B$35/1000*Inputs!$B$36*(1+Inputs!$B$39)^(J$7-1) -> -2691.4162 | ... AL43: =-AL30*Inputs!$B$35/1000*Inputs!$B$36*(1+Inputs!$B$39)^(AL$7-1) -> -4061.077
A44: Electricity | C44: =-C30*Inputs!$B$37*(1+Inputs!$B$39)^(C$7-1) -> -947.1109 | D44: =-D30*Inputs!$B$37*(1+Inputs!$B$39)^(D$7-1) -> -1084.3906 | E44: =-E30*Inputs!$B$37*(1+Inputs!$B$39)^(E$7-1) -> -1637.8634 | F44: =-F30*Inputs!$B$37*(1+Inputs!$B$39)^(F$7-1) -> -1838.8523 | G44: =-G30*Inputs!$B$37*(1+Inputs!$B$39)^(G$7-1) -> -2044.9512 | H44: =-H30*Inputs!$B$37*(1+Inputs!$B$39)^(H$7-1) -> -2255.9046 | I44: =-I30*Inputs!$B$37*(1+Inputs!$B$39)^(I$7-1) -> -2471.4698 | J44: =-J30*Inputs!$B$37*(1+Inputs!$B$39)^(J$7-1) -> -2691.4162 | ... AL44: =-AL30*Inputs!$B$37*(1+Inputs!$B$39)^(AL$7-1) -> -4061.077
A45: Chemicals, water & electricity | C45: =C42+C43+C44 -> -3893.6781 | D45: =D42+D43+D44 -> -4458.0503 | E45: =E42+E43+E44 -> -6733.4385 | F45: =F42+F43+F44 -> -7559.7261 | G45: =G42+G43+G44 -> -8407.0216 | H45: =H42+H43+H44 -> -9274.2744 | I45: =I42+I43+I44 -> -10160.487 | J45: =J42+J43+J44 -> -11064.711 | ... AL45: =AL42+AL43+AL44 -> -16695.539
A46: Card processing fees | C46: =-C39*Inputs!$B$38 -> -847.89453 | D46: =-D39*Inputs!$B$38 -> -972.15717 | E46: =-E39*Inputs!$B$38 -> -1400.8901 | F46: =-F39*Inputs!$B$38 -> -1570.6172 | G46: =-G39*Inputs!$B$38 -> -1743.2131 | H46: =-H39*Inputs!$B$38 -> -1918.5344 | I46: =-I39*Inputs!$B$38 -> -2096.4447 | J46: =-J39*Inputs!$B$38 -> -2276.8147 | ... AL46: =-AL39*Inputs!$B$38 -> -3271.991
A47: Cost of sales | C47: =C45+C46 -> -4741.5727 | D47: =D45+D46 -> -5430.2075 | E47: =E45+E46 -> -8134.3286 | F47: =F45+F46 -> -9130.3434 | G47: =G45+G46 -> -10150.235 | H47: =H45+H46 -> -11192.809 | I47: =I45+I46 -> -12256.932 | J47: =J45+J46 -> -13341.526 | ... AL47: =AL45+AL46 -> -19967.53
A48: Gross profit | C48: =C39+C47 -> 21755.131 | D48: =D39+D47 -> 24949.704 | E48: =E39+E47 -> 35643.486 | F48: =F39+F47 -> 39951.444 | G48: =G39+G47 -> 44325.176 | H48: =H39+H47 -> 48761.391 | I48: =I39+I47 -> 53256.966 | J48: =J39+J47 -> 57808.933 | ... AL48: =AL39+AL47 -> 82282.187
A50: Operating expenses
A51: Site payroll | C51: =C130 -> -36586.667 | D51: =D130 -> -36586.667 | E51: =E130 -> -36586.667 | F51: =F130 -> -36586.667 | G51: =G130 -> -36586.667 | H51: =H130 -> -36586.667 | I51: =I130 -> -36586.667 | J51: =J130 -> -36586.667 | ... AL51: =AL130 -> -38814.795
A52: Site lease or land cost | C52: =-Inputs!$B$42*(1+Inputs!$B$43)^(C$7-1)*1 -> -30000 | D52: =-Inputs!$B$42*(1+Inputs!$B$43)^(D$7-1)*1 -> -30000 | E52: =-Inputs!$B$42*(1+Inputs!$B$43)^(E$7-1)*1 -> -30000 | F52: =-Inputs!$B$42*(1+Inputs!$B$43)^(F$7-1)*1 -> -30000 | G52: =-Inputs!$B$42*(1+Inputs!$B$43)^(G$7-1)*1 -> -30000 | H52: =-Inputs!$B$42*(1+Inputs!$B$43)^(H$7-1)*1 -> -30000 | I52: =-Inputs!$B$42*(1+Inputs!$B$43)^(I$7-1)*1 -> -30000 | J52: =-Inputs!$B$42*(1+Inputs!$B$43)^(J$7-1)*1 -> -30000 | ... AL52: =-Inputs!$B$42*(1+Inputs!$B$43)^(AL$7-1)*1 -> -31827
A53: Equipment maintenance & repairs | C53: =-Inputs!$B$44*(1+Inputs!$B$39)^(C$7-1)*1 -> -5500 | D53: =-Inputs!$B$44*(1+Inputs!$B$39)^(D$7-1)*1 -> -5500 | E53: =-Inputs!$B$44*(1+Inputs!$B$39)^(E$7-1)*1 -> -5500 | F53: =-Inputs!$B$44*(1+Inputs!$B$39)^(F$7-1)*1 -> -5500 | G53: =-Inputs!$B$44*(1+Inputs!$B$39)^(G$7-1)*1 -> -5500 | H53: =-Inputs!$B$44*(1+Inputs!$B$39)^(H$7-1)*1 -> -5500 | I53: =-Inputs!$B$44*(1+Inputs!$B$39)^(I$7-1)*1 -> -5500 | J53: =-Inputs!$B$44*(1+Inputs!$B$39)^(J$7-1)*1 -> -5500 | ... AL53: =-Inputs!$B$44*(1+Inputs!$B$39)^(AL$7-1)*1 -> -5948.8
A54: Insurance, property tax, software & other | C54: =-Inputs!$B$45*(1+Inputs!$B$39)^(C$7-1)*1 -> -9500 | D54: =-Inputs!$B$45*(1+Inputs!$B$39)^(D$7-1)*1 -> -9500 | E54: =-Inputs!$B$45*(1+Inputs!$B$39)^(E$7-1)*1 -> -9500 | F54: =-Inputs!$B$45*(1+Inputs!$B$39)^(F$7-1)*1 -> -9500 | G54: =-Inputs!$B$45*(1+Inputs!$B$39)^(G$7-1)*1 -> -9500 | H54: =-Inputs!$B$45*(1+Inputs!$B$39)^(H$7-1)*1 -> -9500 | I54: =-Inputs!$B$45*(1+Inputs!$B$39)^(I$7-1)*1 -> -9500 | J54: =-Inputs!$B$45*(1+Inputs!$B$39)^(J$7-1)*1 -> -9500 | ... AL54: =-Inputs!$B$45*(1+Inputs!$B$39)^(AL$7-1)*1 -> -10275.2
A55: Marketing | C55: =-Inputs!$B$46*(1+Inputs!$B$47)^(C$7-1)*1 -> -12000 | D55: =-Inputs!$B$46*(1+Inputs!$B$47)^(D$7-1)*1 -> -12000 | E55: =-Inputs!$B$46*(1+Inputs!$B$47)^(E$7-1)*1 -> -12000 | F55: =-Inputs!$B$46*(1+Inputs!$B$47)^(F$7-1)*1 -> -12000 | G55: =-Inputs!$B$46*(1+Inputs!$B$47)^(G$7-1)*1 -> -12000 | H55: =-Inputs!$B$46*(1+Inputs!$B$47)^(H$7-1)*1 -> -12000 | I55: =-Inputs!$B$46*(1+Inputs!$B$47)^(I$7-1)*1 -> -12000 | J55: =-Inputs!$B$46*(1+Inputs!$B$47)^(J$7-1)*1 -> -12000 | ... AL55: =-Inputs!$B$46*(1+Inputs!$B$47)^(AL$7-1)*1 -> -5880
A56: Total operating expenses | C56: =C51+C52+C53+C54+C55 -> -93586.667 | D56: =D51+D52+D53+D54+D55 -> -93586.667 | E56: =E51+E52+E53+E54+E55 -> -93586.667 | F56: =F51+F52+F53+F54+F55 -> -93586.667 | G56: =G51+G52+G53+G54+G55 -> -93586.667 | H56: =H51+H52+H53+H54+H55 -> -93586.667 | I56: =I51+I52+I53+I54+I55 -> -93586.667 | J56: =J51+J52+J53+J54+J55 -> -93586.667 | ... AL56: =AL51+AL52+AL53+AL54+AL55 -> -92745.795
A57: EBITDA | C57: =C48+C56 -> -71831.535 | D57: =D48+D56 -> -68636.963 | E57: =E48+E56 -> -57943.181 | F57: =F48+F56 -> -53635.222 | G57: =G48+G56 -> -49261.491 | H57: =H48+H56 -> -44825.276 | I57: =I48+I56 -> -40329.7 | J57: =J48+J56 -> -35777.733 | ... AL57: =AL48+AL56 -> -10463.607
A59: Profit after depreciation, interest, tax
A60: EBIT | C60: =C57+C77 -> -100303.76 | D60: =D57+D77 -> -97109.185 | E60: =E57+E77 -> -86415.403 | F60: =F57+F77 -> -82107.444 | G60: =G57+G77 -> -77733.713 | H60: =H57+H77 -> -73297.498 | I60: =I57+I77 -> -68801.923 | J60: =J57+J77 -> -64249.955 | ... AL60: =AL57+AL77 -> -39491.385
A61: Interest on loan (average balance after drawdown) | C61: =-(C82+C83+C85)/2*Inputs!$B$71/12 -> -21250 | D61: =-(D82+D83+D85)/2*Inputs!$B$71/12 -> -21161.458 | E61: =-(E82+E83+E85)/2*Inputs!$B$71/12 -> -20984.375 | F61: =-(F82+F83+F85)/2*Inputs!$B$71/12 -> -20807.292 | G61: =-(G82+G83+G85)/2*Inputs!$B$71/12 -> -20630.208 | H61: =-(H82+H83+H85)/2*Inputs!$B$71/12 -> -20453.125 | I61: =-(I82+I83+I85)/2*Inputs!$B$71/12 -> -20276.042 | J61: =-(J82+J83+J85)/2*Inputs!$B$71/12 -> -20098.958 | ... AL61: =-(AL82+AL83+AL85)/2*Inputs!$B$71/12 -> -15140.625
A62: Pre-tax income | C62: =C60+C61 -> -121553.76 | D62: =D60+D61 -> -118270.64 | E62: =E60+E61 -> -107399.78 | F62: =F60+F61 -> -102914.74 | G62: =G60+G61 -> -98363.921 | H62: =H60+H61 -> -93750.623 | I62: =I60+I61 -> -89077.964 | J62: =J60+J61 -> -84348.914 | ... AL62: =AL60+AL61 -> -54632.01
A63: Helper: cumulative pre-tax income | C63: =C62 -> -121553.76 | D63: =C63+D62 -> -239824.4 | E63: =D63+E62 -> -347224.18 | F63: =E63+F62 -> -450138.91 | G63: =F63+G62 -> -548502.84 | H63: =G63+H62 -> -642253.46 | I63: =H63+I62 -> -731331.42 | J63: =I63+J62 -> -815680.34 | K63: =J63+K62 -> -895246.63 | ... AL63: =AK63+AL62 -> -2370448
A64: Helper: cumulative taxable income (losses carried forward) | C64: =MAX(0,C63) -> 0 | D64: =MAX(C64,D63) -> 0 | E64: =MAX(D64,E63) -> 0 | F64: =MAX(E64,F63) -> 0 | G64: =MAX(F64,G63) -> 0 | H64: =MAX(G64,H63) -> 0 | I64: =MAX(H64,I63) -> 0 | J64: =MAX(I64,J63) -> 0 | K64: =MAX(J64,K63) -> 0 | ... AL64: =MAX(AK64,AL63) -> 0
A65: Income tax | C65: =-C64*Inputs!$B$81 -> 0 | D65: =-(D64-C64)*Inputs!$B$81 -> 0 | E65: =-(E64-D64)*Inputs!$B$81 -> 0 | F65: =-(F64-E64)*Inputs!$B$81 -> 0 | G65: =-(G64-F64)*Inputs!$B$81 -> 0 | H65: =-(H64-G64)*Inputs!$B$81 -> 0 | I65: =-(I64-H64)*Inputs!$B$81 -> 0 | J65: =-(J64-I64)*Inputs!$B$81 -> 0 | K65: =-(K64-J64)*Inputs!$B$81 -> 0 | ... AL65: =-(AL64-AK64)*Inputs!$B$81 -> 0
A66: Net income | C66: =C62+C65 -> -121553.76 | D66: =D62+D65 -> -118270.64 | E66: =E62+E65 -> -107399.78 | F66: =F62+F65 -> -102914.74 | G66: =G62+G65 -> -98363.921 | H66: =H62+H65 -> -93750.623 | I66: =I62+I65 -> -89077.964 | J66: =J62+J65 -> -84348.914 | ... AL66: =AL62+AL65 -> -54632.01
A68: Fixed assets & capital spending
A69: Tunnel equipment | C69: =IF(C$6=1,Inputs!$B$50,0) -> 1650000 | D69: =IF(D$6=1,Inputs!$B$50,0) -> 0 | E69: =IF(E$6=1,Inputs!$B$50,0) -> 0 | F69: =IF(F$6=1,Inputs!$B$50,0) -> 0 | G69: =IF(G$6=1,Inputs!$B$50,0) -> 0 | H69: =IF(H$6=1,Inputs!$B$50,0) -> 0 | I69: =IF(I$6=1,Inputs!$B$50,0) -> 0 | J69: =IF(J$6=1,Inputs!$B$50,0) -> 0 | ... AL69: =IF(AL$6=1,Inputs!$B$50,0) -> 0
A70: Building & site works | C70: =IF(C$6=1,Inputs!$B$51,0) -> 2300000 | D70: =IF(D$6=1,Inputs!$B$51,0) -> 0 | E70: =IF(E$6=1,Inputs!$B$51,0) -> 0 | F70: =IF(F$6=1,Inputs!$B$51,0) -> 0 | G70: =IF(G$6=1,Inputs!$B$51,0) -> 0 | H70: =IF(H$6=1,Inputs!$B$51,0) -> 0 | I70: =IF(I$6=1,Inputs!$B$51,0) -> 0 | J70: =IF(J$6=1,Inputs!$B$51,0) -> 0 | ... AL70: =IF(AL$6=1,Inputs!$B$51,0) -> 0
A71: Pay stations, signage & vacuums | C71: =IF(C$6=1,Inputs!$B$52,0) -> 150000 | D71: =IF(D$6=1,Inputs!$B$52,0) -> 0 | E71: =IF(E$6=1,Inputs!$B$52,0) -> 0 | F71: =IF(F$6=1,Inputs!$B$52,0) -> 0 | G71: =IF(G$6=1,Inputs!$B$52,0) -> 0 | H71: =IF(H$6=1,Inputs!$B$52,0) -> 0 | I71: =IF(I$6=1,Inputs!$B$52,0) -> 0 | J71: =IF(J$6=1,Inputs!$B$52,0) -> 0 | ... AL71: =IF(AL$6=1,Inputs!$B$52,0) -> 0
A72: Land (not depreciated) | C72: =IF(C$6=1,Inputs!$B$53,0) -> 0 | D72: =IF(D$6=1,Inputs!$B$53,0) -> 0 | E72: =IF(E$6=1,Inputs!$B$53,0) -> 0 | F72: =IF(F$6=1,Inputs!$B$53,0) -> 0 | G72: =IF(G$6=1,Inputs!$B$53,0) -> 0 | H72: =IF(H$6=1,Inputs!$B$53,0) -> 0 | I72: =IF(I$6=1,Inputs!$B$53,0) -> 0 | J72: =IF(J$6=1,Inputs!$B$53,0) -> 0 | ... AL72: =IF(AL$6=1,Inputs!$B$53,0) -> 0
A73: Equipment refresh & upgrades (first period of each year from year 2) | C73: =IF(AND(C$7>1,MOD(C$6-1,12)=0),Inputs!$B$54,0) -> 0 | D73: =IF(AND(D$7>1,MOD(D$6-1,12)=0),Inputs!$B$54,0) -> 0 | E73: =IF(AND(E$7>1,MOD(E$6-1,12)=0),Inputs!$B$54,0) -> 0 | F73: =IF(AND(F$7>1,MOD(F$6-1,12)=0),Inputs!$B$54,0) -> 0 | G73: =IF(AND(G$7>1,MOD(G$6-1,12)=0),Inputs!$B$54,0) -> 0 | H73: =IF(AND(H$7>1,MOD(H$6-1,12)=0),Inputs!$B$54,0) -> 0 | I73: =IF(AND(I$7>1,MOD(I$6-1,12)=0),Inputs!$B$54,0) -> 0 | J73: =IF(AND(J$7>1,MOD(J$6-1,12)=0),Inputs!$B$54,0) -> 0 | ... AL73: =IF(AND(AL$7>1,MOD(AL$6-1,12)=0),Inputs!$B$54,0) -> 0
A74: Capital spending | C74: =C69+C70+C71+C72+C73 -> 4100000 | D74: =D69+D70+D71+D72+D73 -> 0 | E74: =E69+E70+E71+E72+E73 -> 0 | F74: =F69+F70+F71+F72+F73 -> 0 | G74: =G69+G70+G71+G72+G73 -> 0 | H74: =H69+H70+H71+H72+H73 -> 0 | I74: =I69+I70+I71+I72+I73 -> 0 | J74: =J69+J70+J71+J72+J73 -> 0 | ... AL74: =AL69+AL70+AL71+AL72+AL73 -> 0
A75: Fixed assets at cost | C75: =C74 -> 4100000 | D75: =C75+D74 -> 4100000 | E75: =D75+E74 -> 4100000 | F75: =E75+F74 -> 4100000 | G75: =F75+G74 -> 4100000 | H75: =G75+H74 -> 4100000 | I75: =H75+I74 -> 4100000 | J75: =I75+J74 -> 4100000 | K75: =J75+K74 -> 4100000 | ... AL75: =AK75+AL74 -> 4180000
A76: Land at cost (not depreciated) | C76: =C72 -> 0 | D76: =C76+D72 -> 0 | E76: =D76+E72 -> 0 | F76: =E76+F72 -> 0 | G76: =F76+G72 -> 0 | H76: =G76+H72 -> 0 | I76: =H76+I72 -> 0 | J76: =I76+J72 -> 0 | K76: =J76+K72 -> 0 | ... AL76: =AK76+AL72 -> 0
A77: Depreciation | C77: =-MIN((C75-C76)/MAX(1,Inputs!$B$80*12),C74-C76) -> -28472.222 | D77: =-MIN((D75-D76)/MAX(1,Inputs!$B$80*12),C79+D74-D76) -> -28472.222 | E77: =-MIN((E75-E76)/MAX(1,Inputs!$B$80*12),D79+E74-E76) -> -28472.222 | F77: =-MIN((F75-F76)/MAX(1,Inputs!$B$80*12),E79+F74-F76) -> -28472.222 | G77: =-MIN((G75-G76)/MAX(1,Inputs!$B$80*12),F79+G74-G76) -> -28472.222 | H77: =-MIN((H75-H76)/MAX(1,Inputs!$B$80*12),G79+H74-H76) -> -28472.222 | I77: =-MIN((I75-I76)/MAX(1,Inputs!$B$80*12),H79+I74-I76) -> -28472.222 | J77: =-MIN((J75-J76)/MAX(1,Inputs!$B$80*12),I79+J74-J76) -> -28472.222 | K77: =-MIN((K75-K76)/MAX(1,Inputs!$B$80*12),J79+K74-K76) -> -28472.222 | ... AL77: =-MIN((AL75-AL76)/MAX(1,Inputs!$B$80*12),AK79+AL74-AL76) -> -29027.778
A78: Accumulated depreciation | C78: =C77 -> -28472.222 | D78: =C78+D77 -> -56944.444 | E78: =D78+E77 -> -85416.667 | F78: =E78+F77 -> -113888.89 | G78: =F78+G77 -> -142361.11 | H78: =G78+H77 -> -170833.33 | I78: =H78+I77 -> -199305.56 | J78: =I78+J77 -> -227777.78 | K78: =J78+K77 -> -256250 | ... AL78: =AK78+AL77 -> -1035000
A79: Net fixed assets | C79: =C75+C78 -> 4071527.8 | D79: =D75+D78 -> 4043055.6 | E79: =E75+E78 -> 4014583.3 | F79: =F75+F78 -> 3986111.1 | G79: =G75+G78 -> 3957638.9 | H79: =H75+H78 -> 3929166.7 | I79: =I75+I78 -> 3900694.4 | J79: =J75+J78 -> 3872222.2 | ... AL79: =AL75+AL78 -> 3145000
A81: Debt
A82: Loan — opening balance | C82: =0 -> 0 | D82: =C85 -> 3000000 | E82: =D85 -> 2975000 | F82: =E85 -> 2950000 | G82: =F85 -> 2925000 | H82: =G85 -> 2900000 | I82: =H85 -> 2875000 | J82: =I85 -> 2850000 | K82: =J85 -> 2825000 | ... AL82: =AK85 -> 2150000
A83: Loan drawdown | C83: =IF(C$6=1,Inputs!$B$70,0) -> 3000000 | D83: =IF(D$6=1,Inputs!$B$70,0) -> 0 | E83: =IF(E$6=1,Inputs!$B$70,0) -> 0 | F83: =IF(F$6=1,Inputs!$B$70,0) -> 0 | G83: =IF(G$6=1,Inputs!$B$70,0) -> 0 | H83: =IF(H$6=1,Inputs!$B$70,0) -> 0 | I83: =IF(I$6=1,Inputs!$B$70,0) -> 0 | J83: =IF(J$6=1,Inputs!$B$70,0) -> 0 | ... AL83: =IF(AL$6=1,Inputs!$B$70,0) -> 0
A84: Loan repayment | C84: =-MIN(C82,Inputs!$B$70/MAX(1,Inputs!$B$72*12)) -> 0 | D84: =-MIN(D82,Inputs!$B$70/MAX(1,Inputs!$B$72*12)) -> -25000 | E84: =-MIN(E82,Inputs!$B$70/MAX(1,Inputs!$B$72*12)) -> -25000 | F84: =-MIN(F82,Inputs!$B$70/MAX(1,Inputs!$B$72*12)) -> -25000 | G84: =-MIN(G82,Inputs!$B$70/MAX(1,Inputs!$B$72*12)) -> -25000 | H84: =-MIN(H82,Inputs!$B$70/MAX(1,Inputs!$B$72*12)) -> -25000 | I84: =-MIN(I82,Inputs!$B$70/MAX(1,Inputs!$B$72*12)) -> -25000 | J84: =-MIN(J82,Inputs!$B$70/MAX(1,Inputs!$B$72*12)) -> -25000 | ... AL84: =-MIN(AL82,Inputs!$B$70/MAX(1,Inputs!$B$72*12)) -> -25000
A85: Loan — closing balance | C85: =C82+C83+C84 -> 3000000 | D85: =D82+D83+D84 -> 2975000 | E85: =E82+E83+E84 -> 2950000 | F85: =F82+F83+F84 -> 2925000 | G85: =G82+G83+G84 -> 2900000 | H85: =H82+H83+H84 -> 2875000 | I85: =I82+I83+I84 -> 2850000 | J85: =J82+J83+J84 -> 2825000 | ... AL85: =AL82+AL83+AL84 -> 2125000
A87: Working capital
A88: Accounts receivable | C88: =C39*Inputs!$B$75/30 -> 1766.4469 | D88: =D39*Inputs!$B$75/30 -> 2025.3274 | E88: =E39*Inputs!$B$75/30 -> 2918.521 | F88: =F39*Inputs!$B$75/30 -> 3272.1192 | G88: =G39*Inputs!$B$75/30 -> 3631.694 | H88: =H39*Inputs!$B$75/30 -> 3996.9467 | I88: =I39*Inputs!$B$75/30 -> 4367.5932 | J88: =J39*Inputs!$B$75/30 -> 4743.3639 | ... AL88: =AL39*Inputs!$B$75/30 -> 6816.6478
A89: Inventory | C89: =-C47*Inputs!$B$76/30 -> 1106.367 | D89: =-D47*Inputs!$B$76/30 -> 1267.0484 | E89: =-E47*Inputs!$B$76/30 -> 1898.01 | F89: =-F47*Inputs!$B$76/30 -> 2130.4135 | G89: =-G47*Inputs!$B$76/30 -> 2368.3881 | H89: =-H47*Inputs!$B$76/30 -> 2611.6554 | I89: =-I47*Inputs!$B$76/30 -> 2859.9507 | J89: =-J47*Inputs!$B$76/30 -> 3113.0226 | ... AL89: =-AL47*Inputs!$B$76/30 -> 4659.0903
A90: Accounts payable | C90: =-C47*Inputs!$B$77/30 -> 3161.0484 | D90: =-D47*Inputs!$B$77/30 -> 3620.1383 | E90: =-E47*Inputs!$B$77/30 -> 5422.8857 | F90: =-F47*Inputs!$B$77/30 -> 6086.8956 | G90: =-G47*Inputs!$B$77/30 -> 6766.8231 | H90: =-H47*Inputs!$B$77/30 -> 7461.8726 | I90: =-I47*Inputs!$B$77/30 -> 8171.2877 | J90: =-J47*Inputs!$B$77/30 -> 8894.3504 | ... AL90: =-AL47*Inputs!$B$77/30 -> 13311.687
A91: (Increase) / decrease in receivables | C91: =-C88 -> -1766.4469 | D91: =C88-D88 -> -258.8805 | E91: =D88-E88 -> -893.19354 | F91: =E88-F88 -> -353.59822 | G91: =F88-G88 -> -359.57484 | H91: =G88-H88 -> -365.25263 | I91: =H88-I88 -> -370.64653 | J91: =I88-J88 -> -375.77074 | K91: =J88-K88 -> -380.63874 | ... AL91: =AK88-AL88 -> 1361.9366
A92: (Increase) / decrease in inventory | C92: =-C89 -> -1106.367 | D92: =C89-D89 -> -160.68146 | E92: =D89-E89 -> -630.9616 | F92: =E89-F89 -> -232.40344 | G92: =F89-G89 -> -237.97465 | H92: =G89-H89 -> -243.2673 | I92: =H89-I89 -> -248.29531 | J92: =I89-J89 -> -253.07193 | K92: =J89-K89 -> -257.60971 | ... AL92: =AK89-AL89 -> 1428.0449
A93: Increase / (decrease) in payables | C93: =C90 -> 3161.0484 | D93: =D90-C90 -> 459.08988 | E93: =E90-D90 -> 1802.7474 | F93: =F90-E90 -> 664.00983 | G93: =G90-F90 -> 679.92757 | H93: =H90-G90 -> 695.04942 | I93: =I90-H90 -> 709.41518 | J93: =J90-I90 -> 723.06265 | K93: =K90-J90 -> 736.02775 | ... AL93: =AL90-AK90 -> -4080.1283
A95: Cash flow
A96: Operating cash flow | C96: =C66-C77+C91+C92+C93 -> -92793.301 | D96: =D66-D77+D91+D92+D93 -> -89758.893 | E96: =E66-E77+E91+E92+E93 -> -78648.963 | F96: =F66-F77+F91+F92+F93 -> -74364.506 | G96: =G66-G77+G91+G92+G93 -> -69809.321 | H96: =H66-H77+H91+H92+H93 -> -65191.871 | I96: =I66-I77+I91+I92+I93 -> -60515.269 | J96: =J66-J77+J91+J92+J93 -> -55782.472 | ... AL96: =AL66-AL77+AL91+AL92+AL93 -> -26894.379
A97: Investing cash flow (capex) | C97: =-C74 -> -4100000 | D97: =-D74 -> 0 | E97: =-E74 -> 0 | F97: =-F74 -> 0 | G97: =-G74 -> 0 | H97: =-H74 -> 0 | I97: =-I74 -> 0 | J97: =-J74 -> 0 | ... AL97: =-AL74 -> 0
A98: Equity raised | C98: =IF(C$6=1,Inputs!$B$69,0) -> 2100000 | D98: =IF(D$6=1,Inputs!$B$69,0) -> 0 | E98: =IF(E$6=1,Inputs!$B$69,0) -> 0 | F98: =IF(F$6=1,Inputs!$B$69,0) -> 0 | G98: =IF(G$6=1,Inputs!$B$69,0) -> 0 | H98: =IF(H$6=1,Inputs!$B$69,0) -> 0 | I98: =IF(I$6=1,Inputs!$B$69,0) -> 0 | J98: =IF(J$6=1,Inputs!$B$69,0) -> 0 | ... AL98: =IF(AL$6=1,Inputs!$B$69,0) -> 0
A99: Financing cash flow | C99: =C98+C83+C84 -> 5100000 | D99: =D98+D83+D84 -> -25000 | E99: =E98+E83+E84 -> -25000 | F99: =F98+F83+F84 -> -25000 | G99: =G98+G83+G84 -> -25000 | H99: =H98+H83+H84 -> -25000 | I99: =I98+I83+I84 -> -25000 | J99: =J98+J83+J84 -> -25000 | ... AL99: =AL98+AL83+AL84 -> -25000
A100: Net cash flow | C100: =C96+C97+C99 -> 907206.7 | D100: =D96+D97+D99 -> -114758.89 | E100: =E96+E97+E99 -> -103648.96 | F100: =F96+F97+F99 -> -99364.506 | G100: =G96+G97+G99 -> -94809.321 | H100: =H96+H97+H99 -> -90191.871 | I100: =I96+I97+I99 -> -85515.269 | J100: =J96+J97+J99 -> -80782.472 | ... AL100: =AL96+AL97+AL99 -> -51894.379
A101: Opening cash | C101: =0 -> 0 | D101: =C102 -> 907206.7 | E101: =D102 -> 792447.81 | F101: =E102 -> 688798.84 | G101: =F102 -> 589434.34 | H101: =G102 -> 494625.02 | I101: =H102 -> 404433.14 | J101: =I102 -> 318917.88 | K101: =J102 -> 238135.4 | ... AL101: =AK102 -> -1236717.7
A102: Closing cash | C102: =C101+C100 -> 907206.7 | D102: =D101+D100 -> 792447.81 | E102: =E101+E100 -> 688798.84 | F102: =F101+F100 -> 589434.34 | G102: =G101+G100 -> 494625.02 | H102: =H101+H100 -> 404433.14 | I102: =I101+I100 -> 318917.88 | J102: =J101+J100 -> 238135.4 | ... AL102: =AL101+AL100 -> -1288612.1
A103: Helper: EBITDA positive (1/0) | C103: =IF(C57>0,1,0) -> 0 | D103: =IF(D57>0,1,0) -> 0 | E103: =IF(E57>0,1,0) -> 0 | F103: =IF(F57>0,1,0) -> 0 | G103: =IF(G57>0,1,0) -> 0 | H103: =IF(H57>0,1,0) -> 0 | I103: =IF(I57>0,1,0) -> 0 | J103: =IF(J57>0,1,0) -> 0 | ... AL103: =IF(AL57>0,1,0) -> 0
A105: Goal modules
A106: Helper: net income positive (1/0) | C106: =IF(C66>0,1,0) -> 0 | D106: =IF(D66>0,1,0) -> 0 | E106: =IF(E66>0,1,0) -> 0 | F106: =IF(F66>0,1,0) -> 0 | G106: =IF(G66>0,1,0) -> 0 | H106: =IF(H66>0,1,0) -> 0 | I106: =IF(I66>0,1,0) -> 0 | J106: =IF(J66>0,1,0) -> 0 | ... AL106: =IF(AL66>0,1,0) -> 0
A107: Cash flow before financing (operating + investing) | C107: =C96+C97 -> -4192793.3 | D107: =D96+D97 -> -89758.893 | E107: =E96+E97 -> -78648.963 | F107: =F96+F97 -> -74364.506 | G107: =G96+G97 -> -69809.321 | H107: =H96+H97 -> -65191.871 | I107: =I96+I97 -> -60515.269 | J107: =J96+J97 -> -55782.472 | ... AL107: =AL96+AL97 -> -26894.379
A108: Cumulative cash flow before financing | C108: =C107 -> -4192793.3 | D108: =C108+D107 -> -4282552.2 | E108: =D108+E107 -> -4361201.2 | F108: =E108+F107 -> -4435565.7 | G108: =F108+G107 -> -4505375 | H108: =G108+H107 -> -4570566.9 | I108: =H108+I107 -> -4631082.1 | J108: =I108+J107 -> -4686864.6 | K108: =J108+K107 -> -4737860.9 | ... AL108: =AK108+AL107 -> -5513612.1
A109: Helper: lowest cumulative cash flow so far | C109: =C108 -> -4192793.3 | D109: =MIN(C109,D108) -> -4282552.2 | E109: =MIN(D109,E108) -> -4361201.2 | F109: =MIN(E109,F108) -> -4435565.7 | G109: =MIN(F109,G108) -> -4505375 | H109: =MIN(G109,H108) -> -4570566.9 | I109: =MIN(H109,I108) -> -4631082.1 | J109: =MIN(I109,J108) -> -4686864.6 | K109: =MIN(J109,K108) -> -4737860.9 | ... AL109: =MIN(AK109,AL108) -> -5513612.1
A110: Helper: investment paid back (1/0) | C110: =IF(AND(C108>=0,C109<0),1,0) -> 0 | D110: =IF(AND(D108>=0,D109<0),1,0) -> 0 | E110: =IF(AND(E108>=0,E109<0),1,0) -> 0 | F110: =IF(AND(F108>=0,F109<0),1,0) -> 0 | G110: =IF(AND(G108>=0,G109<0),1,0) -> 0 | H110: =IF(AND(H108>=0,H109<0),1,0) -> 0 | I110: =IF(AND(I108>=0,I109<0),1,0) -> 0 | J110: =IF(AND(J108>=0,J109<0),1,0) -> 0 | ... AL110: =IF(AND(AL108>=0,AL109<0),1,0) -> 0
A111: Unlevered free cash flow (operating + after-tax interest − capex) | C111: =C96-C61*(1-Inputs!$B$81)+C97 -> -4176005.8 | D111: =D96-D61*(1-Inputs!$B$81)+D97 -> -73041.341 | E111: =E96-E61*(1-Inputs!$B$81)+E97 -> -62071.307 | F111: =F96-F61*(1-Inputs!$B$81)+F97 -> -57926.745 | G111: =G96-G61*(1-Inputs!$B$81)+G97 -> -53511.457 | H111: =H96-H61*(1-Inputs!$B$81)+H97 -> -49033.902 | I111: =I96-I61*(1-Inputs!$B$81)+I97 -> -44497.196 | J111: =J96-J61*(1-Inputs!$B$81)+J97 -> -39904.294 | ... AL111: =AL96-AL61*(1-Inputs!$B$81)+AL97 -> -14933.285
A113: Balance sheet
A114: Paid-in capital | C114: =C98 -> 2100000 | D114: =C114+D98 -> 2100000 | E114: =D114+E98 -> 2100000 | F114: =E114+F98 -> 2100000 | G114: =F114+G98 -> 2100000 | H114: =G114+H98 -> 2100000 | I114: =H114+I98 -> 2100000 | J114: =I114+J98 -> 2100000 | K114: =J114+K98 -> 2100000 | ... AL114: =AK114+AL98 -> 2100000
...

Sheet Checks
A1: Model checks | E1: =HYPERLINK("#'Cover'!A1","◂ Contents") -> ◂ Contents
A2: Live formulas: they re-run every time an input changes.
A3: Check | B3: Result | C3: What it tests
A4: Annual revenue ties to period detail | B4: =IF(ABS(SUM('P&L'!$B$5:$D$5)-SUM(Monthly!$C$37:$AL$37))<0.5,"PASS","FAIL") -> PASS | C4: Sum of annual revenue equals the sum of every period
A5: Annual net income ties to period detail | B5: =IF(ABS(SUM('P&L'!$B$22:$D$22)-SUM(Monthly!$C$64:$AL$64))<0.5,"PASS","FAIL") -> PASS | C5: Sum of annual net income equals the sum of every period
A6: EBITDA reconciliation | B6: =IF(ABS(SUM(Monthly!$C$55:$AL$55)-SUM(Monthly!$C$46:$AL$46)-SUM(Monthly!$C$54:$AL$54))<0.5,"PASS","FAIL") -> PASS | C6: EBITDA = gross profit + operating expenses (costs are negative)
A7: Cash roll-forward | B7: =IF(ABS(INDEX(Monthly!$C$100:$AL$100,36)-SUM(Monthly!$C$98:$AL$98))<0.5,"PASS","FAIL") -> PASS | C7: Closing cash = all net cash flows since the start (opening cash is zero)
A8: Scenario selector valid | B8: =IF(AND(ISNUMBER(Dashboard!B4),Dashboard!B4>=1,Dashboard!B4<=3,INT(Dashboard!B4)=Dashboard!B4),"PASS","FAIL") -> PASS | C8: Dashboard!B4 is 1, 2 or 3
A9: Scenario ordering of drivers | B9: =IF(AND(Inputs!$B$7<=Inputs!$C$7,Inputs!$C$7<=Inputs!$D$7,Inputs!$B$8<=Inputs!$C$8,Inputs!$C$8<=Inputs!$D$8,Inputs!$B$10>=Inputs!$C$10,Inputs!$C$10>=Inputs!$D$10,Inputs!$B$11<=Inputs!$C$11,Inputs!$C$11<=Inputs!$D$11,Inputs!$B$12>=Inputs!$C$12,Inputs!$C$12>=Inputs!$D$12,Inputs!$B$20<=Inputs!$C$20,Inputs!$C$20<=Inputs!$D$20,Inputs!$B$21<=Inputs!$C$21,Inputs!$C$21<=Inputs!$D$21,Inputs!$B$22<=Inputs!$C$22,Inputs!$C$22<=Inputs!$D$22,Inputs!$B$23<=Inputs!$C$23,Inputs!$C$23<=Inputs!$D$23,Inputs!$B$24>=Inputs!$C$24,Inputs!$C$24>=Inputs!$D$24,Inputs!$B$25>=Inputs!$C$25,Inputs!$C$25>=Inputs!$D$25,Inputs!$B$28<=Inputs!$C$28,Inputs!$C$28<=Inputs!$D$28,Inputs!$B$29<=Inputs!$C$29,Inputs!$C$29<=Inputs!$D$29,Inputs!$B$30<=Inputs!$C$30,Inputs!$C$30<=Inputs!$D$30,Inputs!$B$31<=Inputs!$C$31,Inputs!$C$31<=Inputs!$D$31,Inputs!$B$34>=Inputs!$C$34,Inputs!$C$34>=Inputs!$D$34,Inputs!$B$35>=Inputs!$C$35,Inputs!$C$35>=Inputs!$D$35,Inputs!$B$36>=Inputs!$C$36,Inputs!$C$36>=Inputs!$D$36,Inputs!$B$37>=Inputs!$C$37,Inputs!$C$37>=Inputs!$D$37,Inputs!$B$38>=Inputs!$C$38,Inputs!$C$38>=Inputs!$D$38,Inputs!$B$39>=Inputs!$C$39,Inputs!$C$39>=Inputs!$D$39,Inputs!$B$47<=Inputs!$C$47,Inputs!$C$47<=Inputs!$D$47,Inputs!$B$57<=Inputs!$C$57,Inputs!$C$57<=Inputs!$D$57,Inputs!$B$59<=Inputs!$C$59,Inputs!$C$59<=Inputs!$D$59,Inputs!$B$61<=Inputs!$C$61,Inputs!$C$61<=Inputs!$D$61,Inputs!$B$63<=Inputs!$C$63,Inputs!$C$63<=Inputs!$D$63,Inputs!$B$87>=Inputs!$C$87,Inputs!$C$87>=Inputs!$D$87,Inputs!$B$88<=Inputs!$C$88,Inputs!$C$88<=Inputs!$D$88,Inputs!$B$89<=Inputs!$C$89,Inputs!$C$89<=Inputs!$D$89),"PASS","FAIL") -> PASS | C9: Low / Base / High ordered the right way for every growth and cost driver
A10: Gross margin within 0–100% | B10: =IF(AND(MIN('P&L'!$B$8:$D$8)>=0,MAX('P&L'!$B$8:$D$8)<=1),"PASS","FAIL") -> PASS | C10: Gross margin never negative or above 100%
A11: Loan balance never negative | B11: =IF(MIN(Monthly!$C$83:$AL$83)>=-0.5,"PASS","FAIL") -> PASS | C11: Repayments never exceed the loan
A12: Funding table ties to the cash flow | B12: =IF(ABS('Break-even'!B18-('Break-even'!B16-'Break-even'!B10))<0.5,"PASS","FAIL") -> PASS | C12: Lowest cash balance = sources of funds − uses of funds up to that point
A13: Valuation: discounting ties to NPV() | B13: =IF(ABS(Valuation!B23-NPV(Valuation!B6,Valuation!$B$17:$D$17))<0.5,"PASS","FAIL") -> PASS | C13: Sum of discounted free cash flows equals Excel's NPV of the same flows
A14: Valuation: WACC above terminal growth | B14: =IF(Valuation!B6>Valuation!B7,"PASS","FAIL") -> PASS | C14: The perpetual-growth formula needs WACC > g
A15: Valuation: sensitivity centre = enterprise value | B15: =IF(ABS(Valuation!D36-Valuation!B27)<0.5,"PASS","FAIL") -> PASS | C15: The middle of the WACC × growth table reproduces the headline value
A16: Valuation: final-year cash flow positive | B16: =IF(Valuation!$D$17>0,"PASS","WARN") -> PASS | C16: Business warning: a negative final-year cash flow gives a negative terminal value (often a 1-year plan still carrying start-up spending)
A17: Sources & uses balance | B17: =IF(ABS('Sources & Uses'!B21-'Sources & Uses'!B28)<0.5,"PASS","FAIL") -> PASS | C17: Sources of funds = uses of funds (incl. cash at the end) for the Sources & Uses period
A18: No error values | B18: =IF(SUMPRODUCT(--ISERROR(Monthly!$C$4:$AL$118))+SUMPRODUCT(--ISERROR(Headcount!$C$4:$AL$15))+SUMPRODUCT(--ISERROR('P&L'!$B$3:$D$23))+SUMPRODUCT(--ISERROR('Cash Flow'!$B$3:$D$18))+SUMPRODUCT(--ISERROR('Balance Sheet'!$B$3:$D$17))+SUMPRODUCT(--ISERROR(KPIs!$B$27:$D$52))+SUMPRODUCT(--ISERROR('Break-even'!$B$26:$D$33))+SUMPRODUCT(--ISERROR(Valuation!$B$14:$D$19))+SUMPRODUCT(--ISERROR('Break-even'!$B$3:$D$35))+SUMPRODUCT(--ISERROR(Valuation!$A$3:$F$40))+SUMPRODUCT(--ISERROR('Sources & Uses'!$B$3:$C$30))+SUMPRODUCT(--ISERROR(Dashboard!$A$6:$W$44))+SUMPRODUCT(--ISERROR(Summary!$A$5:$S$52))+SUMPRODUCT(--ISERROR(KPIs!$A$4:$E$52))+SUMPRODUCT(--ISERROR('Scenario calc'!$C$6:$AL$130))+SUMPRODUCT(--ISERROR('Scenario calc'!$C$135:$AL$259))+SUMPRODUCT(--ISERROR('Scenario calc'!$C$264:$AL$388))+SUMPRODUCT(--ISERROR(Scenarios!$B$5:$E$51))=0,"PASS","FAIL") -> PASS | C18: No error values (divide-by-zero, broken references) on any calculation sheet
A19: Summary ties to statements | B19: =IF(IFERROR(AND(SUMPRODUCT(--(ABS(Summary!$B$7:$D$7-'P&L'!$B$5:$D$5)>0.5))=0,SUMPRODUCT(--(ABS(Summary!$B$19:$D$19-'P&L'!$B$22:$D$22)>0.5))=0,SUMPRODUCT(--(ABS(Summary!$B$31:$D$31-'Cash Flow'!$B$18:$D$18)>0.5))=0,SUMPRODUCT(--(ABS(Summary!$B$41:$D$41-'Balance Sheet'!$B$5:$D$5)>0.5))=0,ABS(SUM(Summary!$H$7:$S$7)-INDEX(Summary!$B$7:$D$7,Summary!$R$2))<0.5,ABS(SUM(Summary!$H$19:$S$19)-INDEX(Summary!$B$19:$D$19,Summary!$R$2))<0.5,ABS(Summary!$S$31-INDEX(Summary!$B$31:$D$31,Summary!$R$2))<0.5),FALSE()),"PASS","FAIL") -> PASS | C19: Summary revenue, net income and closing cash equal the statements every year; the detailed year adds up to its annual figure
A20: DuPont ties to return on equity | B20: =IF(SUMPRODUCT(--(ABS(KPIs!$B$24:$D$24)>0.000000001))>0,"FAIL",IF(SUMPRODUCT(ISNUMBER(KPIs!$B$23:$D$23)*ISNUMBER(KPIs!$B$16:$D$16))=0,"n/a","PASS")) -> PASS | C20: Net margin × asset turnover × equity multiplier equals return on equity every year; n/a = no year where both are defined (a one-sided n/a is a FAIL)
A21: Scenarios: Active = selected scenario | B21: =IF(IFERROR(AND(ABS(Scenarios!E18-INDEX(Scenarios!B18:D18,1,Dashboard!$B$4))<0.5,ABS(Scenarios!E19-INDEX(Scenarios!B19:D19,1,Dashboard!$B$4))<0.5,ABS(Scenarios!E20-INDEX(Scenarios!B20:D20,1,Dashboard!$B$4))<0.5,ABS(Scenarios!E21-INDEX(Scenarios!B21:D21,1,Dashboard!$B$4))<0.000001,ABS(Scenarios!E22-INDEX(Scenarios!B22:D22,1,Dashboard!$B$4))<0.5,ABS(Scenarios!E23-INDEX(Scenarios!B23:D23,1,Dashboard!$B$4))<0.5,ABS(Scenarios!E24-INDEX(Scenarios!B24:D24,1,Dashboard!$B$4))<0.5,ABS(Scenarios!E25-INDEX(Scenarios!B25:D25,1,Dashboard!$B$4))<0.5,ABS(Scenarios!E26-INDEX(Scenarios!B26:D26,1,Dashboard!$B$4))<0.5,ABS(Scenarios!E27-INDEX(Scenarios!B27:D27,1,Dashboard!$B$4))<0.5),FALSE()),"PASS","FAIL") -> PASS | C21: On the Scenarios sheet the live model (Active) equals the Low / Base / High column chosen on the Dashboard for every output
A22: Balance sheet balances every period | B22: =IF(SUMPRODUCT(--(ABS(Monthly!$C$118:$AL$118)>0.5))=0,"PASS","FAIL") -> PASS | C22: Assets = liabilities + equity in every period
A23: Funding sufficient (cash ≥ 0) | B23: =IF(MIN(Monthly!$C$100:$AL$100)>=0,"PASS","WARN") -> PASS | C23: Business warning, not an error: cash dips below zero in this scenario
A25: Overall verdict | B25: =IF(COUNTIF(B4:B23,"FAIL")>0,"FAIL",IF(COUNTIF(B4:B23,"WARN")>0,"PASS WITH WARNINGS","PASS")) -> PASS
