Workbook

Sheet Cover
B2: Childcare centre financial model (planning)
B3: 5-year financial model · monthly detail · Low / Base / High scenarios · US dollars · Full plan
B5: Purpose | D5: Revenue and profit plan
B6: Active scenario | D6: =Dashboard!C4&" (change it on the Dashboard, cell B4)" -> Base (change it on the Dashboard, cell B4)
B7: Model checks | D7: =Checks!B25 -> PASS
B8: Prepared | D8: 22 October 2026
B10: Contents
C11: PRESENTATION
B12: 1 | C12: =HYPERLINK("#Dashboard!A1","Dashboard") -> Dashboard | D12: Scenario switch, key numbers, core financials
B13: 2 | C13: =HYPERLINK("#Summary!A1","Summary") -> Summary | D13: Income statement, cash flow and balance sheet — every year and any year by month
B14: 3 | C14: =HYPERLINK("#Scenarios!A1","Scenarios") -> Scenarios | D14: Low / Base / High side by side: drivers, outputs, charts
B15: 4 | C15: =HYPERLINK("#'Break-even'!A1","Break-even") -> Break-even | D15: Startup costs, funding need, break-even timing and revenue
B16: 5 | C16: =HYPERLINK("#Valuation!A1","Valuation") -> Valuation | D16: Free cash flow, DCF (perpetual growth and exit multiple), WACC × growth sensitivity
B17: 6 | C17: =HYPERLINK("#'Sources & Uses'!A1","Sources & Uses") -> Sources & Uses | D17: Funding structure, sources and uses of cash for the first months
B18: 7 | C18: =HYPERLINK("#KPIs!A1","KPIs") -> KPIs | D18: Financial ratios, DuPont analysis, industry metrics
C19: INPUTS
B20: 8 | C20: =HYPERLINK("#Inputs!A1","Inputs") -> Inputs | D20: Every assumption, Low / Base / High, with units and comments
C21: STATEMENTS
B22: 9 | C22: =HYPERLINK("#'P&L'!A1","P&L") -> P&L | D22: Annual profit & loss
B23: 10 | C23: =HYPERLINK("#'Cash Flow'!A1","Cash Flow") -> Cash Flow | D23: Annual cash flow statement
B24: 11 | C24: =HYPERLINK("#'Balance Sheet'!A1","Balance Sheet") -> Balance Sheet | D24: Balance sheet at year end
C25: CALCULATIONS
B26: 12 | C26: =HYPERLINK("#Monthly!A1","Monthly") -> Monthly | D26: Month-by-month engine of the model
B27: 13 | C27: =HYPERLINK("#Headcount!A1","Headcount") -> Headcount | D27: Team and payroll
B28: 14 | C28: =HYPERLINK("#'Scenario calc'!A1","Scenario calc") -> Scenario calc | D28: Low, Base and High calculated side by side for the Scenarios sheet
C29: CONTROL
B30: 15 | C30: =HYPERLINK("#Checks!A1","Checks") -> Checks | D30: Live integrity checks and the overall verdict
B32: How to read this file
C33: 1000 | D33: Input you can change — yellow cell with a blue figure (Inputs sheet and the view switches)
C34: 1000 | D34: Formula — calculated, do not overwrite
C35: 1000 | D35: Link to another sheet
C36: 1000 | D36: Active value the model uses (follows the scenario)

Sheet Dashboard
A1: Dashboard | W1: =HYPERLINK("#'Cover'!A1","◂ Contents") -> ◂ Contents
A2: Childcare centre financial model (planning)
A4: Active scenario | B4: 2 | C4: =CHOOSE(B4,"Low","Base","High") -> Base | D4: 1 = Low · 2 = Base · 3 = High — every sheet follows this cell | S4: Model checks | T4: =Checks!B25 -> PASS
A6: REVENUE · YEAR 5 | C6: EBITDA MARGIN · YEAR 5 | H6: NET INCOME · YEAR 5 | L6: LOWEST CASH BALANCE | P6: FUNDING REQUIRED | T6: ENTERPRISE VALUE (DCF)
A7: =F12 -> 792649.71 | C7: =F17 -> 0.08295451 | H7: =F18 -> 6787.2016 | L7: =F38 -> 64092.356 | P7: =F36 -> 709907.64 | T7: =F43 -> -302247.25
A8: =IF(AND(B12>0,F12>=0),(F12/B12)^(1/4)-1,"CAGR n/a") -> 0.17228696 | C8: =F16 -> 65753.868 | H8: =F19 -> 0.0085626746 | L8: ='Break-even'!B6 -> 13 | P8: =IF(F37>=0,"Covered by funding raised",-F37) -> 9907.6437 | T8: Average of 2 methods
A10: Core financials ($'000) — active scenario
B11: 1 | C11: 2 | D11: 3 | E11: 4 | F11: 5
A12: Revenue | B12: =SUMIF(Monthly!$C$5:$BJ$5,B$11,Monthly!$C$32:$BJ$32) -> 419706.38 | C12: =SUMIF(Monthly!$C$5:$BJ$5,C$11,Monthly!$C$32:$BJ$32) -> 725888.9 | D12: =SUMIF(Monthly!$C$5:$BJ$5,D$11,Monthly!$C$32:$BJ$32) -> 747148.37 | E12: =SUMIF(Monthly!$C$5:$BJ$5,E$11,Monthly!$C$32:$BJ$32) -> 769562.82 | F12: =SUMIF(Monthly!$C$5:$BJ$5,F$11,Monthly!$C$32:$BJ$32) -> 792649.71
A13: Gross profit | B13: =SUMIF(Monthly!$C$5:$BJ$5,B$11,Monthly!$C$39:$BJ$39) -> 171077.38 | C13: =SUMIF(Monthly!$C$5:$BJ$5,C$11,Monthly!$C$39:$BJ$39) -> 363320.66 | D13: =SUMIF(Monthly!$C$5:$BJ$5,D$11,Monthly!$C$39:$BJ$39) -> 373703.09 | E13: =SUMIF(Monthly!$C$5:$BJ$5,E$11,Monthly!$C$39:$BJ$39) -> 384914.18 | F13: =SUMIF(Monthly!$C$5:$BJ$5,F$11,Monthly!$C$39:$BJ$39) -> 396461.6
A14: Gross margin | B14: =IF(B12=0,0,B13/B12) -> 0.40761205 | C14: =IF(C12=0,0,C13/C12) -> 0.50051827 | D14: =IF(D12=0,0,D13/D12) -> 0.50017252 | E14: =IF(E12=0,0,E13/E12) -> 0.50017252 | F14: =IF(F12=0,0,F13/F12) -> 0.50017252
A15: Operating expenses | B15: =SUMIF(Monthly!$C$5:$BJ$5,B$11,Monthly!$C$51:$BJ$51) -> -296928.37 | C15: =SUMIF(Monthly!$C$5:$BJ$5,C$11,Monthly!$C$51:$BJ$51) -> -309263.38 | D15: =SUMIF(Monthly!$C$5:$BJ$5,D$11,Monthly!$C$51:$BJ$51) -> -316201.28 | E15: =SUMIF(Monthly!$C$5:$BJ$5,E$11,Monthly!$C$51:$BJ$51) -> -323347.32 | F15: =SUMIF(Monthly!$C$5:$BJ$5,F$11,Monthly!$C$51:$BJ$51) -> -330707.74
A16: EBITDA | B16: =SUMIF(Monthly!$C$5:$BJ$5,B$11,Monthly!$C$52:$BJ$52) -> -125850.99 | C16: =SUMIF(Monthly!$C$5:$BJ$5,C$11,Monthly!$C$52:$BJ$52) -> 54057.278 | D16: =SUMIF(Monthly!$C$5:$BJ$5,D$11,Monthly!$C$52:$BJ$52) -> 57501.808 | E16: =SUMIF(Monthly!$C$5:$BJ$5,E$11,Monthly!$C$52:$BJ$52) -> 61566.862 | F16: =SUMIF(Monthly!$C$5:$BJ$5,F$11,Monthly!$C$52:$BJ$52) -> 65753.868
A17: EBITDA margin | B17: =IF(B12=0,0,B16/B12) -> -0.29985485 | C17: =IF(C12=0,0,C16/C12) -> 0.074470458 | D17: =IF(D12=0,0,D16/D12) -> 0.076961699 | E17: =IF(E12=0,0,E16/E12) -> 0.080002386 | F17: =IF(F12=0,0,F16/F12) -> 0.08295451
A18: Net income | B18: =SUMIF(Monthly!$C$5:$BJ$5,B$11,Monthly!$C$61:$BJ$61) -> -189210.72 | C18: =SUMIF(Monthly!$C$5:$BJ$5,C$11,Monthly!$C$61:$BJ$61) -> -8209.3882 | D18: =SUMIF(Monthly!$C$5:$BJ$5,D$11,Monthly!$C$61:$BJ$61) -> -3664.8586 | E18: =SUMIF(Monthly!$C$5:$BJ$5,E$11,Monthly!$C$61:$BJ$61) -> 1500.1957 | F18: =SUMIF(Monthly!$C$5:$BJ$5,F$11,Monthly!$C$61:$BJ$61) -> 6787.2016
A19: Net margin | B19: =IF(B12=0,0,B18/B12) -> -0.45081687 | C19: =IF(C12=0,0,C18/C12) -> -0.011309428 | D19: =IF(D12=0,0,D18/D12) -> -0.0049051282 | E19: =IF(E12=0,0,E18/E12) -> 0.0019494129 | F19: =IF(F12=0,0,F18/F12) -> 0.0085626746
A20: Operating cash flow | B20: =SUMIF(Monthly!$C$5:$BJ$5,B$11,Monthly!$C$89:$BJ$89) -> -161309.3 | C20: =SUMIF(Monthly!$C$5:$BJ$5,C$11,Monthly!$C$89:$BJ$89) -> 35051.747 | D20: =SUMIF(Monthly!$C$5:$BJ$5,D$11,Monthly!$C$89:$BJ$89) -> 41791.018 | E20: =SUMIF(Monthly!$C$5:$BJ$5,E$11,Monthly!$C$89:$BJ$89) -> 47839.748 | F20: =SUMIF(Monthly!$C$5:$BJ$5,F$11,Monthly!$C$89:$BJ$89) -> 54009.941
A21: Investing cash flow | B21: =SUMIF(Monthly!$C$5:$BJ$5,B$11,Monthly!$C$90:$BJ$90) -> -442000 | C21: =SUMIF(Monthly!$C$5:$BJ$5,C$11,Monthly!$C$90:$BJ$90) -> -9000 | D21: =SUMIF(Monthly!$C$5:$BJ$5,D$11,Monthly!$C$90:$BJ$90) -> -9000 | E21: =SUMIF(Monthly!$C$5:$BJ$5,E$11,Monthly!$C$90:$BJ$90) -> -9000 | F21: =SUMIF(Monthly!$C$5:$BJ$5,F$11,Monthly!$C$90:$BJ$90) -> -9000
A22: Financing cash flow | B22: =SUMIF(Monthly!$C$5:$BJ$5,B$11,Monthly!$C$92:$BJ$92) -> 677083.33 | C22: =SUMIF(Monthly!$C$5:$BJ$5,C$11,Monthly!$C$92:$BJ$92) -> -25000 | D22: =SUMIF(Monthly!$C$5:$BJ$5,D$11,Monthly!$C$92:$BJ$92) -> -25000 | E22: =SUMIF(Monthly!$C$5:$BJ$5,E$11,Monthly!$C$92:$BJ$92) -> -25000 | F22: =SUMIF(Monthly!$C$5:$BJ$5,F$11,Monthly!$C$92:$BJ$92) -> -25000
A23: Net change in cash | B23: =SUMIF(Monthly!$C$5:$BJ$5,B$11,Monthly!$C$93:$BJ$93) -> 73774.032 | C23: =SUMIF(Monthly!$C$5:$BJ$5,C$11,Monthly!$C$93:$BJ$93) -> 1051.747 | D23: =SUMIF(Monthly!$C$5:$BJ$5,D$11,Monthly!$C$93:$BJ$93) -> 7791.0179 | E23: =SUMIF(Monthly!$C$5:$BJ$5,E$11,Monthly!$C$93:$BJ$93) -> 13839.748 | F23: =SUMIF(Monthly!$C$5:$BJ$5,F$11,Monthly!$C$93:$BJ$93) -> 20009.941
A24: Year-end cash | B24: =INDEX(Monthly!$C$95:$BJ$95,B$11*12) -> 73774.032 | C24: =INDEX(Monthly!$C$95:$BJ$95,C$11*12) -> 74825.779 | D24: =INDEX(Monthly!$C$95:$BJ$95,D$11*12) -> 82616.797 | E24: =INDEX(Monthly!$C$95:$BJ$95,E$11*12) -> 96456.545 | F24: =INDEX(Monthly!$C$95:$BJ$95,F$11*12) -> 116466.49
A26: Childcare metrics
B27: 1 | C27: 2 | D27: 3 | E27: 4 | F27: 5
A28: Children enrolled (year end) | B28: =KPIs!B30 -> 47.75 | C28: =KPIs!C30 -> 51 | D28: =KPIs!D30 -> 51 | E28: =KPIs!E30 -> 51 | F28: =KPIs!F30 -> 51
A29: Occupancy (child-months ÷ place-months) | B29: =KPIs!B33 -> 0.49791667 | C29: =KPIs!C33 -> 0.85 | D29: =KPIs!D33 -> 0.85 | E29: =KPIs!E33 -> 0.85 | F29: =KPIs!F33 -> 0.85
A30: Teacher payroll, % of revenue | B30: =KPIs!B43 -> 0.49501273 | C30: =KPIs!C43 -> 0.40048443 | D30: =KPIs!D43 -> 0.40076165 | E30: =KPIs!E43 -> 0.40076165 | F30: =KPIs!F43 -> 0.40076165
A31: Team (FTE, year end) | B31: =INDEX(Headcount!$C$11:$BJ$11,B$27*12) -> 2 | C31: =INDEX(Headcount!$C$11:$BJ$11,C$27*12) -> 2 | D31: =INDEX(Headcount!$C$11:$BJ$11,D$27*12) -> 2 | E31: =INDEX(Headcount!$C$11:$BJ$11,E$27*12) -> 2 | F31: =INDEX(Headcount!$C$11:$BJ$11,F$27*12) -> 2
A33: Funding & valuation ($'000) — active scenario
A34: Equity raised | F34: =Inputs!$E$73 -> 450000
A35: Loan drawn | F35: =Inputs!$E$74 -> 250000
A36: Funding required (incl. cash buffer) | F36: ='Break-even'!B12 -> 709907.64
A37: Funding surplus / (shortfall) | F37: ='Break-even'!B17 -> -9907.6437
A38: ="Lowest cash balance (month "&'Break-even'!B6&")" -> Lowest cash balance (month 13) | F38: ='Break-even'!B18 -> 64092.356
A39: First month with positive EBITDA | F39: ='Break-even'!B21 -> 12
A40: Cash invested paid back | F40: ='Break-even'!B23 -> Not within horizon
A41: Enterprise value — perpetual growth | F41: =Valuation!B27 -> -306225.94
A42: Enterprise value — exit multiple | F42: =Valuation!C27 -> -298268.56
A43: Enterprise value — average | F43: =Valuation!B30 -> -302247.25

Sheet Summary
A1: Financial statements summary | U1: =HYPERLINK("#'Cover'!A1","◂ Contents") -> ◂ Contents
A2: Childcare centre financial model (planning) | P2: Select detailed year: | R2: 1
A5: Income statement ($'000) — by year | H5: ="Income statement ($'000) — Year "&$R$2&", by month" -> Income statement ($'000) — Year 1, by month
B6: 1 | C6: 2 | D6: 3 | E6: 4 | F6: 5 | H6: =INDEX(Monthly!$C$4:$BJ$4,($R$2-1)*12+1) -> 1 | I6: =INDEX(Monthly!$C$4:$BJ$4,($R$2-1)*12+2) -> 2 | J6: =INDEX(Monthly!$C$4:$BJ$4,($R$2-1)*12+3) -> 3 | K6: =INDEX(Monthly!$C$4:$BJ$4,($R$2-1)*12+4) -> 4 | L6: =INDEX(Monthly!$C$4:$BJ$4,($R$2-1)*12+5) -> 5 | M6: =INDEX(Monthly!$C$4:$BJ$4,($R$2-1)*12+6) -> 6 | N6: =INDEX(Monthly!$C$4:$BJ$4,($R$2-1)*12+7) -> 7 | O6: =INDEX(Monthly!$C$4:$BJ$4,($R$2-1)*12+8) -> 8 | P6: =INDEX(Monthly!$C$4:$BJ$4,($R$2-1)*12+9) -> 9 | Q6: =INDEX(Monthly!$C$4:$BJ$4,($R$2-1)*12+10) -> 10 | R6: =INDEX(Monthly!$C$4:$BJ$4,($R$2-1)*12+11) -> 11 | S6: =INDEX(Monthly!$C$4:$BJ$4,($R$2-1)*12+12) -> 12
A7: Revenue | B7: ='P&L'!B5 -> 419706.38 | C7: ='P&L'!C5 -> 725888.9 | D7: ='P&L'!D5 -> 747148.37 | E7: ='P&L'!E5 -> 769562.82 | F7: ='P&L'!F5 -> 792649.71 | H7: =INDEX(Monthly!$C$32:$BJ$32,($R$2-1)*12+1) -> 15609 | I7: =INDEX(Monthly!$C$32:$BJ$32,($R$2-1)*12+2) -> 18036.438 | J7: =INDEX(Monthly!$C$32:$BJ$32,($R$2-1)*12+3) -> 21776.375 | K7: =INDEX(Monthly!$C$32:$BJ$32,($R$2-1)*12+4) -> 25516.312 | L7: =INDEX(Monthly!$C$32:$BJ$32,($R$2-1)*12+5) -> 29256.25 | M7: =INDEX(Monthly!$C$32:$BJ$32,($R$2-1)*12+6) -> 32996.188 | N7: =INDEX(Monthly!$C$32:$BJ$32,($R$2-1)*12+7) -> 36736.125 | O7: =INDEX(Monthly!$C$32:$BJ$32,($R$2-1)*12+8) -> 40476.062 | P7: =INDEX(Monthly!$C$32:$BJ$32,($R$2-1)*12+9) -> 44216 | Q7: =INDEX(Monthly!$C$32:$BJ$32,($R$2-1)*12+10) -> 47955.938 | R7: =INDEX(Monthly!$C$32:$BJ$32,($R$2-1)*12+11) -> 51695.875 | S7: =INDEX(Monthly!$C$32:$BJ$32,($R$2-1)*12+12) -> 55435.812
A8: Cost of sales | B8: ='P&L'!B6 -> -248629 | C8: ='P&L'!C6 -> -362568.24 | D8: ='P&L'!D6 -> -373445.29 | E8: ='P&L'!E6 -> -384648.65 | F8: ='P&L'!F6 -> -396188.11 | H8: =INDEX(Monthly!$C$38:$BJ$38,($R$2-1)*12+1) -> -9208 | I8: =INDEX(Monthly!$C$38:$BJ$38,($R$2-1)*12+2) -> -9578.5 | J8: =INDEX(Monthly!$C$38:$BJ$38,($R$2-1)*12+3) -> -17789 | K8: =INDEX(Monthly!$C$38:$BJ$38,($R$2-1)*12+4) -> -18159.5 | L8: =INDEX(Monthly!$C$38:$BJ$38,($R$2-1)*12+5) -> -18530 | M8: =INDEX(Monthly!$C$38:$BJ$38,($R$2-1)*12+6) -> -18900.5 | N8: =INDEX(Monthly!$C$38:$BJ$38,($R$2-1)*12+7) -> -19271 | O8: =INDEX(Monthly!$C$38:$BJ$38,($R$2-1)*12+8) -> -23561.5 | P8: =INDEX(Monthly!$C$38:$BJ$38,($R$2-1)*12+9) -> -27852 | Q8: =INDEX(Monthly!$C$38:$BJ$38,($R$2-1)*12+10) -> -28222.5 | R8: =INDEX(Monthly!$C$38:$BJ$38,($R$2-1)*12+11) -> -28593 | S8: =INDEX(Monthly!$C$38:$BJ$38,($R$2-1)*12+12) -> -28963.5
A9: Gross profit | B9: ='P&L'!B7 -> 171077.38 | C9: ='P&L'!C7 -> 363320.66 | D9: ='P&L'!D7 -> 373703.09 | E9: ='P&L'!E7 -> 384914.18 | F9: ='P&L'!F7 -> 396461.6 | H9: =INDEX(Monthly!$C$39:$BJ$39,($R$2-1)*12+1) -> 6401 | I9: =INDEX(Monthly!$C$39:$BJ$39,($R$2-1)*12+2) -> 8457.9375 | J9: =INDEX(Monthly!$C$39:$BJ$39,($R$2-1)*12+3) -> 3987.375 | K9: =INDEX(Monthly!$C$39:$BJ$39,($R$2-1)*12+4) -> 7356.8125 | L9: =INDEX(Monthly!$C$39:$BJ$39,($R$2-1)*12+5) -> 10726.25 | M9: =INDEX(Monthly!$C$39:$BJ$39,($R$2-1)*12+6) -> 14095.688 | N9: =INDEX(Monthly!$C$39:$BJ$39,($R$2-1)*12+7) -> 17465.125 | O9: =INDEX(Monthly!$C$39:$BJ$39,($R$2-1)*12+8) -> 16914.562 | P9: =INDEX(Monthly!$C$39:$BJ$39,($R$2-1)*12+9) -> 16364 | Q9: =INDEX(Monthly!$C$39:$BJ$39,($R$2-1)*12+10) -> 19733.438 | R9: =INDEX(Monthly!$C$39:$BJ$39,($R$2-1)*12+11) -> 23102.875 | S9: =INDEX(Monthly!$C$39:$BJ$39,($R$2-1)*12+12) -> 26472.312
A10: Gross margin | B10: ='P&L'!B8 -> 0.40761205 | C10: ='P&L'!C8 -> 0.50051827 | D10: ='P&L'!D8 -> 0.50017252 | E10: ='P&L'!E8 -> 0.50017252 | F10: ='P&L'!F8 -> 0.50017252 | H10: =IF(H7=0,0,H9/H7) -> 0.41008393 | I10: =IF(I7=0,0,I9/I7) -> 0.46893615 | J10: =IF(J7=0,0,J9/J7) -> 0.18310554 | K10: =IF(K7=0,0,K9/K7) -> 0.28831801 | L10: =IF(L7=0,0,L9/L7) -> 0.36663106 | M10: =IF(M7=0,0,M9/M7) -> 0.4271914 | N10: =IF(N7=0,0,N9/N7) -> 0.47542099 | O10: =IF(O7=0,0,O9/O7) -> 0.41789051 | ... S10: =IF(S7=0,0,S9/S7) -> 0.47753088
A11: Total operating expenses | B11: ='P&L'!B18 -> -296928.37 | C11: ='P&L'!C18 -> -309263.38 | D11: ='P&L'!D18 -> -316201.28 | E11: ='P&L'!E18 -> -323347.32 | F11: ='P&L'!F18 -> -330707.74 | H11: =INDEX(Monthly!$C$51:$BJ$51,($R$2-1)*12+1) -> -24349.217 | I11: =INDEX(Monthly!$C$51:$BJ$51,($R$2-1)*12+2) -> -24421.001 | J11: =INDEX(Monthly!$C$51:$BJ$51,($R$2-1)*12+3) -> -24492.785 | K11: =INDEX(Monthly!$C$51:$BJ$51,($R$2-1)*12+4) -> -24564.57 | L11: =INDEX(Monthly!$C$51:$BJ$51,($R$2-1)*12+5) -> -24636.354 | M11: =INDEX(Monthly!$C$51:$BJ$51,($R$2-1)*12+6) -> -24708.139 | N11: =INDEX(Monthly!$C$51:$BJ$51,($R$2-1)*12+7) -> -24779.923 | O11: =INDEX(Monthly!$C$51:$BJ$51,($R$2-1)*12+8) -> -24851.707 | P11: =INDEX(Monthly!$C$51:$BJ$51,($R$2-1)*12+9) -> -24923.492 | Q11: =INDEX(Monthly!$C$51:$BJ$51,($R$2-1)*12+10) -> -24995.276 | R11: =INDEX(Monthly!$C$51:$BJ$51,($R$2-1)*12+11) -> -25067.06 | S11: =INDEX(Monthly!$C$51:$BJ$51,($R$2-1)*12+12) -> -25138.845
A12: EBITDA | B12: ='P&L'!B19 -> -125850.99 | C12: ='P&L'!C19 -> 54057.278 | D12: ='P&L'!D19 -> 57501.808 | E12: ='P&L'!E19 -> 61566.862 | F12: ='P&L'!F19 -> 65753.868 | H12: =INDEX(Monthly!$C$52:$BJ$52,($R$2-1)*12+1) -> -17948.217 | I12: =INDEX(Monthly!$C$52:$BJ$52,($R$2-1)*12+2) -> -15963.064 | J12: =INDEX(Monthly!$C$52:$BJ$52,($R$2-1)*12+3) -> -20505.41 | K12: =INDEX(Monthly!$C$52:$BJ$52,($R$2-1)*12+4) -> -17207.757 | L12: =INDEX(Monthly!$C$52:$BJ$52,($R$2-1)*12+5) -> -13910.104 | M12: =INDEX(Monthly!$C$52:$BJ$52,($R$2-1)*12+6) -> -10612.451 | N12: =INDEX(Monthly!$C$52:$BJ$52,($R$2-1)*12+7) -> -7314.7979 | O12: =INDEX(Monthly!$C$52:$BJ$52,($R$2-1)*12+8) -> -7937.1448 | P12: =INDEX(Monthly!$C$52:$BJ$52,($R$2-1)*12+9) -> -8559.4917 | Q12: =INDEX(Monthly!$C$52:$BJ$52,($R$2-1)*12+10) -> -5261.8385 | R12: =INDEX(Monthly!$C$52:$BJ$52,($R$2-1)*12+11) -> -1964.1854 | S12: =INDEX(Monthly!$C$52:$BJ$52,($R$2-1)*12+12) -> 1333.4677
A13: EBITDA margin | B13: ='P&L'!B20 -> -0.29985485 | C13: ='P&L'!C20 -> 0.074470458 | D13: ='P&L'!D20 -> 0.076961699 | E13: ='P&L'!E20 -> 0.080002386 | F13: ='P&L'!F20 -> 0.08295451 | H13: =IF(H7=0,0,H12/H7) -> -1.1498633 | I13: =IF(I7=0,0,I12/I7) -> -0.88504526 | J13: =IF(J7=0,0,J12/J7) -> -0.94163562 | K13: =IF(K7=0,0,K12/K7) -> -0.6743826 | L13: =IF(L7=0,0,L12/L7) -> -0.47545752 | M13: =IF(M7=0,0,M12/M7) -> -0.32162658 | N13: =IF(N7=0,0,N12/N7) -> -0.1991173 | O13: =IF(O7=0,0,O12/O7) -> -0.19609479 | ... S13: =IF(S7=0,0,S12/S7) -> 0.024054265
A14: Depreciation | B14: ='P&L'!B21 -> -44200 | C14: ='P&L'!C21 -> -45100 | D14: ='P&L'!D21 -> -46000 | E14: ='P&L'!E21 -> -46900 | F14: ='P&L'!F21 -> -47800 | H14: =INDEX(Monthly!$C$70:$BJ$70,($R$2-1)*12+1) -> -3683.3333 | I14: =INDEX(Monthly!$C$70:$BJ$70,($R$2-1)*12+2) -> -3683.3333 | J14: =INDEX(Monthly!$C$70:$BJ$70,($R$2-1)*12+3) -> -3683.3333 | K14: =INDEX(Monthly!$C$70:$BJ$70,($R$2-1)*12+4) -> -3683.3333 | L14: =INDEX(Monthly!$C$70:$BJ$70,($R$2-1)*12+5) -> -3683.3333 | M14: =INDEX(Monthly!$C$70:$BJ$70,($R$2-1)*12+6) -> -3683.3333 | N14: =INDEX(Monthly!$C$70:$BJ$70,($R$2-1)*12+7) -> -3683.3333 | O14: =INDEX(Monthly!$C$70:$BJ$70,($R$2-1)*12+8) -> -3683.3333 | P14: =INDEX(Monthly!$C$70:$BJ$70,($R$2-1)*12+9) -> -3683.3333 | Q14: =INDEX(Monthly!$C$70:$BJ$70,($R$2-1)*12+10) -> -3683.3333 | R14: =INDEX(Monthly!$C$70:$BJ$70,($R$2-1)*12+11) -> -3683.3333 | S14: =INDEX(Monthly!$C$70:$BJ$70,($R$2-1)*12+12) -> -3683.3333
A15: EBIT | B15: ='P&L'!B22 -> -170050.99 | C15: ='P&L'!C22 -> 8957.2785 | D15: ='P&L'!D22 -> 11501.808 | E15: ='P&L'!E22 -> 14666.862 | F15: ='P&L'!F22 -> 17953.868 | H15: =INDEX(Monthly!$C$55:$BJ$55,($R$2-1)*12+1) -> -21631.55 | I15: =INDEX(Monthly!$C$55:$BJ$55,($R$2-1)*12+2) -> -19646.397 | J15: =INDEX(Monthly!$C$55:$BJ$55,($R$2-1)*12+3) -> -24188.744 | K15: =INDEX(Monthly!$C$55:$BJ$55,($R$2-1)*12+4) -> -20891.091 | L15: =INDEX(Monthly!$C$55:$BJ$55,($R$2-1)*12+5) -> -17593.438 | M15: =INDEX(Monthly!$C$55:$BJ$55,($R$2-1)*12+6) -> -14295.784 | N15: =INDEX(Monthly!$C$55:$BJ$55,($R$2-1)*12+7) -> -10998.131 | O15: =INDEX(Monthly!$C$55:$BJ$55,($R$2-1)*12+8) -> -11620.478 | P15: =INDEX(Monthly!$C$55:$BJ$55,($R$2-1)*12+9) -> -12242.825 | Q15: =INDEX(Monthly!$C$55:$BJ$55,($R$2-1)*12+10) -> -8945.1719 | R15: =INDEX(Monthly!$C$55:$BJ$55,($R$2-1)*12+11) -> -5647.5188 | S15: =INDEX(Monthly!$C$55:$BJ$55,($R$2-1)*12+12) -> -2349.8656
A16: Interest | B16: ='P&L'!B23 -> -19159.722 | C16: ='P&L'!C23 -> -17166.667 | D16: ='P&L'!D23 -> -15166.667 | E16: ='P&L'!E23 -> -13166.667 | F16: ='P&L'!F23 -> -11166.667 | H16: =INDEX(Monthly!$C$56:$BJ$56,($R$2-1)*12+1) -> -1666.6667 | I16: =INDEX(Monthly!$C$56:$BJ$56,($R$2-1)*12+2) -> -1659.7222 | J16: =INDEX(Monthly!$C$56:$BJ$56,($R$2-1)*12+3) -> -1645.8333 | K16: =INDEX(Monthly!$C$56:$BJ$56,($R$2-1)*12+4) -> -1631.9444 | L16: =INDEX(Monthly!$C$56:$BJ$56,($R$2-1)*12+5) -> -1618.0556 | M16: =INDEX(Monthly!$C$56:$BJ$56,($R$2-1)*12+6) -> -1604.1667 | N16: =INDEX(Monthly!$C$56:$BJ$56,($R$2-1)*12+7) -> -1590.2778 | O16: =INDEX(Monthly!$C$56:$BJ$56,($R$2-1)*12+8) -> -1576.3889 | P16: =INDEX(Monthly!$C$56:$BJ$56,($R$2-1)*12+9) -> -1562.5 | Q16: =INDEX(Monthly!$C$56:$BJ$56,($R$2-1)*12+10) -> -1548.6111 | R16: =INDEX(Monthly!$C$56:$BJ$56,($R$2-1)*12+11) -> -1534.7222 | S16: =INDEX(Monthly!$C$56:$BJ$56,($R$2-1)*12+12) -> -1520.8333
A17: Pre-tax income | B17: ='P&L'!B24 -> -189210.72 | C17: ='P&L'!C24 -> -8209.3882 | D17: ='P&L'!D24 -> -3664.8586 | E17: ='P&L'!E24 -> 1500.1957 | F17: ='P&L'!F24 -> 6787.2016 | H17: =INDEX(Monthly!$C$57:$BJ$57,($R$2-1)*12+1) -> -23298.217 | I17: =INDEX(Monthly!$C$57:$BJ$57,($R$2-1)*12+2) -> -21306.119 | J17: =INDEX(Monthly!$C$57:$BJ$57,($R$2-1)*12+3) -> -25834.577 | K17: =INDEX(Monthly!$C$57:$BJ$57,($R$2-1)*12+4) -> -22523.035 | L17: =INDEX(Monthly!$C$57:$BJ$57,($R$2-1)*12+5) -> -19211.493 | M17: =INDEX(Monthly!$C$57:$BJ$57,($R$2-1)*12+6) -> -15899.951 | N17: =INDEX(Monthly!$C$57:$BJ$57,($R$2-1)*12+7) -> -12588.409 | O17: =INDEX(Monthly!$C$57:$BJ$57,($R$2-1)*12+8) -> -13196.867 | P17: =INDEX(Monthly!$C$57:$BJ$57,($R$2-1)*12+9) -> -13805.325 | Q17: =INDEX(Monthly!$C$57:$BJ$57,($R$2-1)*12+10) -> -10493.783 | R17: =INDEX(Monthly!$C$57:$BJ$57,($R$2-1)*12+11) -> -7182.241 | S17: =INDEX(Monthly!$C$57:$BJ$57,($R$2-1)*12+12) -> -3870.699
A18: Income tax | B18: ='P&L'!B25 -> 0 | C18: ='P&L'!C25 -> 0 | D18: ='P&L'!D25 -> 0 | E18: ='P&L'!E25 -> 0 | F18: ='P&L'!F25 -> 0 | H18: =INDEX(Monthly!$C$60:$BJ$60,($R$2-1)*12+1) -> 0 | I18: =INDEX(Monthly!$C$60:$BJ$60,($R$2-1)*12+2) -> 0 | J18: =INDEX(Monthly!$C$60:$BJ$60,($R$2-1)*12+3) -> 0 | K18: =INDEX(Monthly!$C$60:$BJ$60,($R$2-1)*12+4) -> 0 | L18: =INDEX(Monthly!$C$60:$BJ$60,($R$2-1)*12+5) -> 0 | M18: =INDEX(Monthly!$C$60:$BJ$60,($R$2-1)*12+6) -> 0 | N18: =INDEX(Monthly!$C$60:$BJ$60,($R$2-1)*12+7) -> 0 | O18: =INDEX(Monthly!$C$60:$BJ$60,($R$2-1)*12+8) -> 0 | P18: =INDEX(Monthly!$C$60:$BJ$60,($R$2-1)*12+9) -> 0 | Q18: =INDEX(Monthly!$C$60:$BJ$60,($R$2-1)*12+10) -> 0 | R18: =INDEX(Monthly!$C$60:$BJ$60,($R$2-1)*12+11) -> 0 | S18: =INDEX(Monthly!$C$60:$BJ$60,($R$2-1)*12+12) -> 0
A19: Net income | B19: ='P&L'!B26 -> -189210.72 | C19: ='P&L'!C26 -> -8209.3882 | D19: ='P&L'!D26 -> -3664.8586 | E19: ='P&L'!E26 -> 1500.1957 | F19: ='P&L'!F26 -> 6787.2016 | H19: =INDEX(Monthly!$C$61:$BJ$61,($R$2-1)*12+1) -> -23298.217 | I19: =INDEX(Monthly!$C$61:$BJ$61,($R$2-1)*12+2) -> -21306.119 | J19: =INDEX(Monthly!$C$61:$BJ$61,($R$2-1)*12+3) -> -25834.577 | K19: =INDEX(Monthly!$C$61:$BJ$61,($R$2-1)*12+4) -> -22523.035 | L19: =INDEX(Monthly!$C$61:$BJ$61,($R$2-1)*12+5) -> -19211.493 | M19: =INDEX(Monthly!$C$61:$BJ$61,($R$2-1)*12+6) -> -15899.951 | N19: =INDEX(Monthly!$C$61:$BJ$61,($R$2-1)*12+7) -> -12588.409 | O19: =INDEX(Monthly!$C$61:$BJ$61,($R$2-1)*12+8) -> -13196.867 | P19: =INDEX(Monthly!$C$61:$BJ$61,($R$2-1)*12+9) -> -13805.325 | Q19: =INDEX(Monthly!$C$61:$BJ$61,($R$2-1)*12+10) -> -10493.783 | R19: =INDEX(Monthly!$C$61:$BJ$61,($R$2-1)*12+11) -> -7182.241 | S19: =INDEX(Monthly!$C$61:$BJ$61,($R$2-1)*12+12) -> -3870.699
A20: Net margin | B20: ='P&L'!B27 -> -0.45081687 | C20: ='P&L'!C27 -> -0.011309428 | D20: ='P&L'!D27 -> -0.0049051282 | E20: ='P&L'!E27 -> 0.0019494129 | F20: ='P&L'!F27 -> 0.0085626746 | H20: =IF(H7=0,0,H19/H7) -> -1.4926143 | I20: =IF(I7=0,0,I19/I7) -> -1.181282 | J20: =IF(J7=0,0,J19/J7) -> -1.186358 | K20: =IF(K7=0,0,K19/K7) -> -0.88269161 | L20: =IF(L7=0,0,L19/L7) -> -0.65666287 | M20: =IF(M7=0,0,M19/M7) -> -0.48187237 | N20: =IF(N7=0,0,N19/N7) -> -0.34267112 | O20: =IF(O7=0,0,O19/O7) -> -0.32604127 | ... S20: =IF(S7=0,0,S19/S7) -> -0.069823076
A22: Cash flow ($'000) — by year | H22: ="Cash flow ($'000) — Year "&$R$2&", by month" -> Cash flow ($'000) — Year 1, by month
B23: 1 | C23: 2 | D23: 3 | E23: 4 | F23: 5 | H23: =INDEX(Monthly!$C$4:$BJ$4,($R$2-1)*12+1) -> 1 | I23: =INDEX(Monthly!$C$4:$BJ$4,($R$2-1)*12+2) -> 2 | J23: =INDEX(Monthly!$C$4:$BJ$4,($R$2-1)*12+3) -> 3 | K23: =INDEX(Monthly!$C$4:$BJ$4,($R$2-1)*12+4) -> 4 | L23: =INDEX(Monthly!$C$4:$BJ$4,($R$2-1)*12+5) -> 5 | M23: =INDEX(Monthly!$C$4:$BJ$4,($R$2-1)*12+6) -> 6 | N23: =INDEX(Monthly!$C$4:$BJ$4,($R$2-1)*12+7) -> 7 | O23: =INDEX(Monthly!$C$4:$BJ$4,($R$2-1)*12+8) -> 8 | P23: =INDEX(Monthly!$C$4:$BJ$4,($R$2-1)*12+9) -> 9 | Q23: =INDEX(Monthly!$C$4:$BJ$4,($R$2-1)*12+10) -> 10 | R23: =INDEX(Monthly!$C$4:$BJ$4,($R$2-1)*12+11) -> 11 | S23: =INDEX(Monthly!$C$4:$BJ$4,($R$2-1)*12+12) -> 12
A24: Operating cash flow | B24: ='Cash Flow'!B10 -> -161309.3 | C24: ='Cash Flow'!C10 -> 35051.747 | D24: ='Cash Flow'!D10 -> 41791.018 | E24: ='Cash Flow'!E10 -> 47839.748 | F24: ='Cash Flow'!F10 -> 54009.941 | H24: =INDEX(Monthly!$C$89:$BJ$89,($R$2-1)*12+1) -> -23923.317 | I24: =INDEX(Monthly!$C$89:$BJ$89,($R$2-1)*12+2) -> -18575.875 | J24: =INDEX(Monthly!$C$89:$BJ$89,($R$2-1)*12+3) -> -21582.417 | K24: =INDEX(Monthly!$C$89:$BJ$89,($R$2-1)*12+4) -> -20361.541 | L24: =INDEX(Monthly!$C$89:$BJ$89,($R$2-1)*12+5) -> -17049.999 | M24: =INDEX(Monthly!$C$89:$BJ$89,($R$2-1)*12+6) -> -13738.457 | N24: =INDEX(Monthly!$C$89:$BJ$89,($R$2-1)*12+7) -> -10426.915 | O24: =INDEX(Monthly!$C$89:$BJ$89,($R$2-1)*12+8) -> -9990.0399 | P24: =INDEX(Monthly!$C$89:$BJ$89,($R$2-1)*12+9) -> -10598.498 | Q24: =INDEX(Monthly!$C$89:$BJ$89,($R$2-1)*12+10) -> -8332.2892 | R24: =INDEX(Monthly!$C$89:$BJ$89,($R$2-1)*12+11) -> -5020.7472 | S24: =INDEX(Monthly!$C$89:$BJ$89,($R$2-1)*12+12) -> -1709.2052
A25: Capital spending | B25: ='Cash Flow'!B11 -> -442000 | C25: ='Cash Flow'!C11 -> -9000 | D25: ='Cash Flow'!D11 -> -9000 | E25: ='Cash Flow'!E11 -> -9000 | F25: ='Cash Flow'!F11 -> -9000 | H25: =INDEX(Monthly!$C$90:$BJ$90,($R$2-1)*12+1) -> -442000 | I25: =INDEX(Monthly!$C$90:$BJ$90,($R$2-1)*12+2) -> 0 | J25: =INDEX(Monthly!$C$90:$BJ$90,($R$2-1)*12+3) -> 0 | K25: =INDEX(Monthly!$C$90:$BJ$90,($R$2-1)*12+4) -> 0 | L25: =INDEX(Monthly!$C$90:$BJ$90,($R$2-1)*12+5) -> 0 | M25: =INDEX(Monthly!$C$90:$BJ$90,($R$2-1)*12+6) -> 0 | N25: =INDEX(Monthly!$C$90:$BJ$90,($R$2-1)*12+7) -> 0 | O25: =INDEX(Monthly!$C$90:$BJ$90,($R$2-1)*12+8) -> 0 | P25: =INDEX(Monthly!$C$90:$BJ$90,($R$2-1)*12+9) -> 0 | Q25: =INDEX(Monthly!$C$90:$BJ$90,($R$2-1)*12+10) -> 0 | R25: =INDEX(Monthly!$C$90:$BJ$90,($R$2-1)*12+11) -> 0 | S25: =INDEX(Monthly!$C$90:$BJ$90,($R$2-1)*12+12) -> 0
A26: Equity raised | B26: ='Cash Flow'!B12 -> 450000 | C26: ='Cash Flow'!C12 -> 0 | D26: ='Cash Flow'!D12 -> 0 | E26: ='Cash Flow'!E12 -> 0 | F26: ='Cash Flow'!F12 -> 0 | H26: =INDEX(Monthly!$C$91:$BJ$91,($R$2-1)*12+1) -> 450000 | I26: =INDEX(Monthly!$C$91:$BJ$91,($R$2-1)*12+2) -> 0 | J26: =INDEX(Monthly!$C$91:$BJ$91,($R$2-1)*12+3) -> 0 | K26: =INDEX(Monthly!$C$91:$BJ$91,($R$2-1)*12+4) -> 0 | L26: =INDEX(Monthly!$C$91:$BJ$91,($R$2-1)*12+5) -> 0 | M26: =INDEX(Monthly!$C$91:$BJ$91,($R$2-1)*12+6) -> 0 | N26: =INDEX(Monthly!$C$91:$BJ$91,($R$2-1)*12+7) -> 0 | O26: =INDEX(Monthly!$C$91:$BJ$91,($R$2-1)*12+8) -> 0 | P26: =INDEX(Monthly!$C$91:$BJ$91,($R$2-1)*12+9) -> 0 | Q26: =INDEX(Monthly!$C$91:$BJ$91,($R$2-1)*12+10) -> 0 | R26: =INDEX(Monthly!$C$91:$BJ$91,($R$2-1)*12+11) -> 0 | S26: =INDEX(Monthly!$C$91:$BJ$91,($R$2-1)*12+12) -> 0
A27: Loan drawdown | B27: ='Cash Flow'!B13 -> 250000 | C27: ='Cash Flow'!C13 -> 0 | D27: ='Cash Flow'!D13 -> 0 | E27: ='Cash Flow'!E13 -> 0 | F27: ='Cash Flow'!F13 -> 0 | H27: =INDEX(Monthly!$C$76:$BJ$76,($R$2-1)*12+1) -> 250000 | I27: =INDEX(Monthly!$C$76:$BJ$76,($R$2-1)*12+2) -> 0 | J27: =INDEX(Monthly!$C$76:$BJ$76,($R$2-1)*12+3) -> 0 | K27: =INDEX(Monthly!$C$76:$BJ$76,($R$2-1)*12+4) -> 0 | L27: =INDEX(Monthly!$C$76:$BJ$76,($R$2-1)*12+5) -> 0 | M27: =INDEX(Monthly!$C$76:$BJ$76,($R$2-1)*12+6) -> 0 | N27: =INDEX(Monthly!$C$76:$BJ$76,($R$2-1)*12+7) -> 0 | O27: =INDEX(Monthly!$C$76:$BJ$76,($R$2-1)*12+8) -> 0 | P27: =INDEX(Monthly!$C$76:$BJ$76,($R$2-1)*12+9) -> 0 | Q27: =INDEX(Monthly!$C$76:$BJ$76,($R$2-1)*12+10) -> 0 | R27: =INDEX(Monthly!$C$76:$BJ$76,($R$2-1)*12+11) -> 0 | S27: =INDEX(Monthly!$C$76:$BJ$76,($R$2-1)*12+12) -> 0
A28: Loan repayment | B28: ='Cash Flow'!B14 -> -22916.667 | C28: ='Cash Flow'!C14 -> -25000 | D28: ='Cash Flow'!D14 -> -25000 | E28: ='Cash Flow'!E14 -> -25000 | F28: ='Cash Flow'!F14 -> -25000 | H28: =INDEX(Monthly!$C$77:$BJ$77,($R$2-1)*12+1) -> 0 | I28: =INDEX(Monthly!$C$77:$BJ$77,($R$2-1)*12+2) -> -2083.3333 | J28: =INDEX(Monthly!$C$77:$BJ$77,($R$2-1)*12+3) -> -2083.3333 | K28: =INDEX(Monthly!$C$77:$BJ$77,($R$2-1)*12+4) -> -2083.3333 | L28: =INDEX(Monthly!$C$77:$BJ$77,($R$2-1)*12+5) -> -2083.3333 | M28: =INDEX(Monthly!$C$77:$BJ$77,($R$2-1)*12+6) -> -2083.3333 | N28: =INDEX(Monthly!$C$77:$BJ$77,($R$2-1)*12+7) -> -2083.3333 | O28: =INDEX(Monthly!$C$77:$BJ$77,($R$2-1)*12+8) -> -2083.3333 | P28: =INDEX(Monthly!$C$77:$BJ$77,($R$2-1)*12+9) -> -2083.3333 | Q28: =INDEX(Monthly!$C$77:$BJ$77,($R$2-1)*12+10) -> -2083.3333 | R28: =INDEX(Monthly!$C$77:$BJ$77,($R$2-1)*12+11) -> -2083.3333 | S28: =INDEX(Monthly!$C$77:$BJ$77,($R$2-1)*12+12) -> -2083.3333
A29: Financing cash flow | B29: ='Cash Flow'!B15 -> 677083.33 | C29: ='Cash Flow'!C15 -> -25000 | D29: ='Cash Flow'!D15 -> -25000 | E29: ='Cash Flow'!E15 -> -25000 | F29: ='Cash Flow'!F15 -> -25000 | H29: =INDEX(Monthly!$C$92:$BJ$92,($R$2-1)*12+1) -> 700000 | I29: =INDEX(Monthly!$C$92:$BJ$92,($R$2-1)*12+2) -> -2083.3333 | J29: =INDEX(Monthly!$C$92:$BJ$92,($R$2-1)*12+3) -> -2083.3333 | K29: =INDEX(Monthly!$C$92:$BJ$92,($R$2-1)*12+4) -> -2083.3333 | L29: =INDEX(Monthly!$C$92:$BJ$92,($R$2-1)*12+5) -> -2083.3333 | M29: =INDEX(Monthly!$C$92:$BJ$92,($R$2-1)*12+6) -> -2083.3333 | N29: =INDEX(Monthly!$C$92:$BJ$92,($R$2-1)*12+7) -> -2083.3333 | O29: =INDEX(Monthly!$C$92:$BJ$92,($R$2-1)*12+8) -> -2083.3333 | P29: =INDEX(Monthly!$C$92:$BJ$92,($R$2-1)*12+9) -> -2083.3333 | Q29: =INDEX(Monthly!$C$92:$BJ$92,($R$2-1)*12+10) -> -2083.3333 | R29: =INDEX(Monthly!$C$92:$BJ$92,($R$2-1)*12+11) -> -2083.3333 | S29: =INDEX(Monthly!$C$92:$BJ$92,($R$2-1)*12+12) -> -2083.3333
A30: Net change in cash | B30: ='Cash Flow'!B16 -> 73774.032 | C30: ='Cash Flow'!C16 -> 1051.747 | D30: ='Cash Flow'!D16 -> 7791.0179 | E30: ='Cash Flow'!E16 -> 13839.748 | F30: ='Cash Flow'!F16 -> 20009.941 | H30: =INDEX(Monthly!$C$93:$BJ$93,($R$2-1)*12+1) -> 234076.68 | I30: =INDEX(Monthly!$C$93:$BJ$93,($R$2-1)*12+2) -> -20659.209 | J30: =INDEX(Monthly!$C$93:$BJ$93,($R$2-1)*12+3) -> -23665.75 | K30: =INDEX(Monthly!$C$93:$BJ$93,($R$2-1)*12+4) -> -22444.875 | L30: =INDEX(Monthly!$C$93:$BJ$93,($R$2-1)*12+5) -> -19133.333 | M30: =INDEX(Monthly!$C$93:$BJ$93,($R$2-1)*12+6) -> -15821.791 | N30: =INDEX(Monthly!$C$93:$BJ$93,($R$2-1)*12+7) -> -12510.249 | O30: =INDEX(Monthly!$C$93:$BJ$93,($R$2-1)*12+8) -> -12073.373 | P30: =INDEX(Monthly!$C$93:$BJ$93,($R$2-1)*12+9) -> -12681.831 | Q30: =INDEX(Monthly!$C$93:$BJ$93,($R$2-1)*12+10) -> -10415.623 | R30: =INDEX(Monthly!$C$93:$BJ$93,($R$2-1)*12+11) -> -7104.0806 | S30: =INDEX(Monthly!$C$93:$BJ$93,($R$2-1)*12+12) -> -3792.5385
A31: Closing cash | B31: ='Cash Flow'!B18 -> 73774.032 | C31: ='Cash Flow'!C18 -> 74825.779 | D31: ='Cash Flow'!D18 -> 82616.797 | E31: ='Cash Flow'!E18 -> 96456.545 | F31: ='Cash Flow'!F18 -> 116466.49 | H31: =INDEX(Monthly!$C$95:$BJ$95,($R$2-1)*12+1) -> 234076.68 | I31: =INDEX(Monthly!$C$95:$BJ$95,($R$2-1)*12+2) -> 213417.47 | J31: =INDEX(Monthly!$C$95:$BJ$95,($R$2-1)*12+3) -> 189751.72 | K31: =INDEX(Monthly!$C$95:$BJ$95,($R$2-1)*12+4) -> 167306.85 | L31: =INDEX(Monthly!$C$95:$BJ$95,($R$2-1)*12+5) -> 148173.52 | M31: =INDEX(Monthly!$C$95:$BJ$95,($R$2-1)*12+6) -> 132351.73 | N31: =INDEX(Monthly!$C$95:$BJ$95,($R$2-1)*12+7) -> 119841.48 | O31: =INDEX(Monthly!$C$95:$BJ$95,($R$2-1)*12+8) -> 107768.1 | P31: =INDEX(Monthly!$C$95:$BJ$95,($R$2-1)*12+9) -> 95086.274 | Q31: =INDEX(Monthly!$C$95:$BJ$95,($R$2-1)*12+10) -> 84670.651 | R31: =INDEX(Monthly!$C$95:$BJ$95,($R$2-1)*12+11) -> 77566.57 | S31: =INDEX(Monthly!$C$95:$BJ$95,($R$2-1)*12+12) -> 73774.032
A39: Balance sheet at year end ($'000) | H39: ="Balance sheet at month end ($'000) — Year "&$R$2 -> Balance sheet at month end ($'000) — Year 1
B40: 1 | C40: 2 | D40: 3 | E40: 4 | F40: 5 | H40: =INDEX(Monthly!$C$4:$BJ$4,($R$2-1)*12+1) -> 1 | I40: =INDEX(Monthly!$C$4:$BJ$4,($R$2-1)*12+2) -> 2 | J40: =INDEX(Monthly!$C$4:$BJ$4,($R$2-1)*12+3) -> 3 | K40: =INDEX(Monthly!$C$4:$BJ$4,($R$2-1)*12+4) -> 4 | L40: =INDEX(Monthly!$C$4:$BJ$4,($R$2-1)*12+5) -> 5 | M40: =INDEX(Monthly!$C$4:$BJ$4,($R$2-1)*12+6) -> 6 | N40: =INDEX(Monthly!$C$4:$BJ$4,($R$2-1)*12+7) -> 7 | O40: =INDEX(Monthly!$C$4:$BJ$4,($R$2-1)*12+8) -> 8 | P40: =INDEX(Monthly!$C$4:$BJ$4,($R$2-1)*12+9) -> 9 | Q40: =INDEX(Monthly!$C$4:$BJ$4,($R$2-1)*12+10) -> 10 | R40: =INDEX(Monthly!$C$4:$BJ$4,($R$2-1)*12+11) -> 11 | S40: =INDEX(Monthly!$C$4:$BJ$4,($R$2-1)*12+12) -> 12
A41: Cash | B41: ='Balance Sheet'!B5 -> 73774.032 | C41: ='Balance Sheet'!C5 -> 74825.779 | D41: ='Balance Sheet'!D5 -> 82616.797 | E41: ='Balance Sheet'!E5 -> 96456.545 | F41: ='Balance Sheet'!F5 -> 116466.49 | H41: =INDEX(Monthly!$C$95:$BJ$95,($R$2-1)*12+1) -> 234076.68 | I41: =INDEX(Monthly!$C$95:$BJ$95,($R$2-1)*12+2) -> 213417.47 | J41: =INDEX(Monthly!$C$95:$BJ$95,($R$2-1)*12+3) -> 189751.72 | K41: =INDEX(Monthly!$C$95:$BJ$95,($R$2-1)*12+4) -> 167306.85 | L41: =INDEX(Monthly!$C$95:$BJ$95,($R$2-1)*12+5) -> 148173.52 | M41: =INDEX(Monthly!$C$95:$BJ$95,($R$2-1)*12+6) -> 132351.73 | N41: =INDEX(Monthly!$C$95:$BJ$95,($R$2-1)*12+7) -> 119841.48 | O41: =INDEX(Monthly!$C$95:$BJ$95,($R$2-1)*12+8) -> 107768.1 | P41: =INDEX(Monthly!$C$95:$BJ$95,($R$2-1)*12+9) -> 95086.274 | Q41: =INDEX(Monthly!$C$95:$BJ$95,($R$2-1)*12+10) -> 84670.651 | R41: =INDEX(Monthly!$C$95:$BJ$95,($R$2-1)*12+11) -> 77566.57 | S41: =INDEX(Monthly!$C$95:$BJ$95,($R$2-1)*12+12) -> 73774.032
A42: Accounts receivable | B42: ='Balance Sheet'!B6 -> 24022.185 | C42: ='Balance Sheet'!C6 -> 26194.522 | D42: ='Balance Sheet'!D6 -> 26980.358 | E42: ='Balance Sheet'!E6 -> 27789.769 | F42: ='Balance Sheet'!F6 -> 28623.462 | H42: =INDEX(Monthly!$C$81:$BJ$81,($R$2-1)*12+1) -> 6763.9 | I42: =INDEX(Monthly!$C$81:$BJ$81,($R$2-1)*12+2) -> 7815.7896 | J42: =INDEX(Monthly!$C$81:$BJ$81,($R$2-1)*12+3) -> 9436.4292 | K42: =INDEX(Monthly!$C$81:$BJ$81,($R$2-1)*12+4) -> 11057.069 | L42: =INDEX(Monthly!$C$81:$BJ$81,($R$2-1)*12+5) -> 12677.708 | M42: =INDEX(Monthly!$C$81:$BJ$81,($R$2-1)*12+6) -> 14298.348 | N42: =INDEX(Monthly!$C$81:$BJ$81,($R$2-1)*12+7) -> 15918.987 | O42: =INDEX(Monthly!$C$81:$BJ$81,($R$2-1)*12+8) -> 17539.627 | P42: =INDEX(Monthly!$C$81:$BJ$81,($R$2-1)*12+9) -> 19160.267 | Q42: =INDEX(Monthly!$C$81:$BJ$81,($R$2-1)*12+10) -> 20780.906 | R42: =INDEX(Monthly!$C$81:$BJ$81,($R$2-1)*12+11) -> 22401.546 | S42: =INDEX(Monthly!$C$81:$BJ$81,($R$2-1)*12+12) -> 24022.185
A43: Inventory | B43: ='Balance Sheet'!B7 -> 2896.35 | C43: ='Balance Sheet'!C7 -> 3021.402 | D43: ='Balance Sheet'!D7 -> 3112.0441 | E43: ='Balance Sheet'!E7 -> 3205.4054 | F43: ='Balance Sheet'!F7 -> 3301.5675 | H43: =INDEX(Monthly!$C$82:$BJ$82,($R$2-1)*12+1) -> 920.8 | I43: =INDEX(Monthly!$C$82:$BJ$82,($R$2-1)*12+2) -> 957.85 | J43: =INDEX(Monthly!$C$82:$BJ$82,($R$2-1)*12+3) -> 1778.9 | K43: =INDEX(Monthly!$C$82:$BJ$82,($R$2-1)*12+4) -> 1815.95 | L43: =INDEX(Monthly!$C$82:$BJ$82,($R$2-1)*12+5) -> 1853 | M43: =INDEX(Monthly!$C$82:$BJ$82,($R$2-1)*12+6) -> 1890.05 | N43: =INDEX(Monthly!$C$82:$BJ$82,($R$2-1)*12+7) -> 1927.1 | O43: =INDEX(Monthly!$C$82:$BJ$82,($R$2-1)*12+8) -> 2356.15 | P43: =INDEX(Monthly!$C$82:$BJ$82,($R$2-1)*12+9) -> 2785.2 | Q43: =INDEX(Monthly!$C$82:$BJ$82,($R$2-1)*12+10) -> 2822.25 | R43: =INDEX(Monthly!$C$82:$BJ$82,($R$2-1)*12+11) -> 2859.3 | S43: =INDEX(Monthly!$C$82:$BJ$82,($R$2-1)*12+12) -> 2896.35
A44: Net fixed assets | B44: ='Balance Sheet'!B8 -> 397800 | C44: ='Balance Sheet'!C8 -> 361700 | D44: ='Balance Sheet'!D8 -> 324700 | E44: ='Balance Sheet'!E8 -> 286800 | F44: ='Balance Sheet'!F8 -> 248000 | H44: =INDEX(Monthly!$C$72:$BJ$72,($R$2-1)*12+1) -> 438316.67 | I44: =INDEX(Monthly!$C$72:$BJ$72,($R$2-1)*12+2) -> 434633.33 | J44: =INDEX(Monthly!$C$72:$BJ$72,($R$2-1)*12+3) -> 430950 | K44: =INDEX(Monthly!$C$72:$BJ$72,($R$2-1)*12+4) -> 427266.67 | L44: =INDEX(Monthly!$C$72:$BJ$72,($R$2-1)*12+5) -> 423583.33 | M44: =INDEX(Monthly!$C$72:$BJ$72,($R$2-1)*12+6) -> 419900 | N44: =INDEX(Monthly!$C$72:$BJ$72,($R$2-1)*12+7) -> 416216.67 | O44: =INDEX(Monthly!$C$72:$BJ$72,($R$2-1)*12+8) -> 412533.33 | P44: =INDEX(Monthly!$C$72:$BJ$72,($R$2-1)*12+9) -> 408850 | Q44: =INDEX(Monthly!$C$72:$BJ$72,($R$2-1)*12+10) -> 405166.67 | R44: =INDEX(Monthly!$C$72:$BJ$72,($R$2-1)*12+11) -> 401483.33 | S44: =INDEX(Monthly!$C$72:$BJ$72,($R$2-1)*12+12) -> 397800
A45: Total assets | B45: ='Balance Sheet'!B9 -> 498492.57 | C45: ='Balance Sheet'!C9 -> 465741.7 | D45: ='Balance Sheet'!D9 -> 437409.2 | E45: ='Balance Sheet'!E9 -> 414251.72 | F45: ='Balance Sheet'!F9 -> 396391.52 | H45: =INDEX(Monthly!$C$109:$BJ$109,($R$2-1)*12+1) -> 680078.05 | I45: =INDEX(Monthly!$C$109:$BJ$109,($R$2-1)*12+2) -> 656824.45 | J45: =INDEX(Monthly!$C$109:$BJ$109,($R$2-1)*12+3) -> 631917.05 | K45: =INDEX(Monthly!$C$109:$BJ$109,($R$2-1)*12+4) -> 607446.54 | L45: =INDEX(Monthly!$C$109:$BJ$109,($R$2-1)*12+5) -> 586287.56 | M45: =INDEX(Monthly!$C$109:$BJ$109,($R$2-1)*12+6) -> 568440.12 | N45: =INDEX(Monthly!$C$109:$BJ$109,($R$2-1)*12+7) -> 553904.23 | O45: =INDEX(Monthly!$C$109:$BJ$109,($R$2-1)*12+8) -> 540197.22 | P45: =INDEX(Monthly!$C$109:$BJ$109,($R$2-1)*12+9) -> 525881.74 | Q45: =INDEX(Monthly!$C$109:$BJ$109,($R$2-1)*12+10) -> 513440.47 | R45: =INDEX(Monthly!$C$109:$BJ$109,($R$2-1)*12+11) -> 504310.75 | S45: =INDEX(Monthly!$C$109:$BJ$109,($R$2-1)*12+12) -> 498492.57
A46: Accounts payable | B46: ='Balance Sheet'!B10 -> 10619.95 | C46: ='Balance Sheet'!C10 -> 11078.474 | D46: ='Balance Sheet'!D10 -> 11410.828 | E46: ='Balance Sheet'!E10 -> 11753.153 | F46: ='Balance Sheet'!F10 -> 12105.748 | H46: =INDEX(Monthly!$C$83:$BJ$83,($R$2-1)*12+1) -> 3376.2667 | I46: =INDEX(Monthly!$C$83:$BJ$83,($R$2-1)*12+2) -> 3512.1167 | J46: =INDEX(Monthly!$C$83:$BJ$83,($R$2-1)*12+3) -> 6522.6333 | K46: =INDEX(Monthly!$C$83:$BJ$83,($R$2-1)*12+4) -> 6658.4833 | L46: =INDEX(Monthly!$C$83:$BJ$83,($R$2-1)*12+5) -> 6794.3333 | M46: =INDEX(Monthly!$C$83:$BJ$83,($R$2-1)*12+6) -> 6930.1833 | N46: =INDEX(Monthly!$C$83:$BJ$83,($R$2-1)*12+7) -> 7066.0333 | O46: =INDEX(Monthly!$C$83:$BJ$83,($R$2-1)*12+8) -> 8639.2167 | P46: =INDEX(Monthly!$C$83:$BJ$83,($R$2-1)*12+9) -> 10212.4 | Q46: =INDEX(Monthly!$C$83:$BJ$83,($R$2-1)*12+10) -> 10348.25 | R46: =INDEX(Monthly!$C$83:$BJ$83,($R$2-1)*12+11) -> 10484.1 | S46: =INDEX(Monthly!$C$83:$BJ$83,($R$2-1)*12+12) -> 10619.95
A47: Loan | B47: ='Balance Sheet'!B11 -> 227083.33 | C47: ='Balance Sheet'!C11 -> 202083.33 | D47: ='Balance Sheet'!D11 -> 177083.33 | E47: ='Balance Sheet'!E11 -> 152083.33 | F47: ='Balance Sheet'!F11 -> 127083.33 | H47: =INDEX(Monthly!$C$78:$BJ$78,($R$2-1)*12+1) -> 250000 | I47: =INDEX(Monthly!$C$78:$BJ$78,($R$2-1)*12+2) -> 247916.67 | J47: =INDEX(Monthly!$C$78:$BJ$78,($R$2-1)*12+3) -> 245833.33 | K47: =INDEX(Monthly!$C$78:$BJ$78,($R$2-1)*12+4) -> 243750 | L47: =INDEX(Monthly!$C$78:$BJ$78,($R$2-1)*12+5) -> 241666.67 | M47: =INDEX(Monthly!$C$78:$BJ$78,($R$2-1)*12+6) -> 239583.33 | N47: =INDEX(Monthly!$C$78:$BJ$78,($R$2-1)*12+7) -> 237500 | O47: =INDEX(Monthly!$C$78:$BJ$78,($R$2-1)*12+8) -> 235416.67 | P47: =INDEX(Monthly!$C$78:$BJ$78,($R$2-1)*12+9) -> 233333.33 | Q47: =INDEX(Monthly!$C$78:$BJ$78,($R$2-1)*12+10) -> 231250 | R47: =INDEX(Monthly!$C$78:$BJ$78,($R$2-1)*12+11) -> 229166.67 | S47: =INDEX(Monthly!$C$78:$BJ$78,($R$2-1)*12+12) -> 227083.33
A48: Total liabilities | B48: ='Balance Sheet'!B12 -> 237703.28 | C48: ='Balance Sheet'!C12 -> 213161.81 | D48: ='Balance Sheet'!D12 -> 188494.16 | E48: ='Balance Sheet'!E12 -> 163836.49 | F48: ='Balance Sheet'!F12 -> 139189.08 | H48: =INDEX(Monthly!$C$110:$BJ$110,($R$2-1)*12+1) -> 253376.27 | I48: =INDEX(Monthly!$C$110:$BJ$110,($R$2-1)*12+2) -> 251428.78 | J48: =INDEX(Monthly!$C$110:$BJ$110,($R$2-1)*12+3) -> 252355.97 | K48: =INDEX(Monthly!$C$110:$BJ$110,($R$2-1)*12+4) -> 250408.48 | L48: =INDEX(Monthly!$C$110:$BJ$110,($R$2-1)*12+5) -> 248461 | M48: =INDEX(Monthly!$C$110:$BJ$110,($R$2-1)*12+6) -> 246513.52 | N48: =INDEX(Monthly!$C$110:$BJ$110,($R$2-1)*12+7) -> 244566.03 | O48: =INDEX(Monthly!$C$110:$BJ$110,($R$2-1)*12+8) -> 244055.88 | P48: =INDEX(Monthly!$C$110:$BJ$110,($R$2-1)*12+9) -> 243545.73 | Q48: =INDEX(Monthly!$C$110:$BJ$110,($R$2-1)*12+10) -> 241598.25 | R48: =INDEX(Monthly!$C$110:$BJ$110,($R$2-1)*12+11) -> 239650.77 | S48: =INDEX(Monthly!$C$110:$BJ$110,($R$2-1)*12+12) -> 237703.28
A49: Paid-in capital | B49: ='Balance Sheet'!B13 -> 450000 | C49: ='Balance Sheet'!C13 -> 450000 | D49: ='Balance Sheet'!D13 -> 450000 | E49: ='Balance Sheet'!E13 -> 450000 | F49: ='Balance Sheet'!F13 -> 450000 | H49: =INDEX(Monthly!$C$107:$BJ$107,($R$2-1)*12+1) -> 450000 | I49: =INDEX(Monthly!$C$107:$BJ$107,($R$2-1)*12+2) -> 450000 | J49: =INDEX(Monthly!$C$107:$BJ$107,($R$2-1)*12+3) -> 450000 | K49: =INDEX(Monthly!$C$107:$BJ$107,($R$2-1)*12+4) -> 450000 | L49: =INDEX(Monthly!$C$107:$BJ$107,($R$2-1)*12+5) -> 450000 | M49: =INDEX(Monthly!$C$107:$BJ$107,($R$2-1)*12+6) -> 450000 | N49: =INDEX(Monthly!$C$107:$BJ$107,($R$2-1)*12+7) -> 450000 | O49: =INDEX(Monthly!$C$107:$BJ$107,($R$2-1)*12+8) -> 450000 | P49: =INDEX(Monthly!$C$107:$BJ$107,($R$2-1)*12+9) -> 450000 | Q49: =INDEX(Monthly!$C$107:$BJ$107,($R$2-1)*12+10) -> 450000 | R49: =INDEX(Monthly!$C$107:$BJ$107,($R$2-1)*12+11) -> 450000 | S49: =INDEX(Monthly!$C$107:$BJ$107,($R$2-1)*12+12) -> 450000
A50: Retained earnings | B50: ='Balance Sheet'!B14 -> -189210.72 | C50: ='Balance Sheet'!C14 -> -197420.1 | D50: ='Balance Sheet'!D14 -> -201084.96 | E50: ='Balance Sheet'!E14 -> -199584.77 | F50: ='Balance Sheet'!F14 -> -192797.57 | H50: =INDEX(Monthly!$C$108:$BJ$108,($R$2-1)*12+1) -> -23298.217 | I50: =INDEX(Monthly!$C$108:$BJ$108,($R$2-1)*12+2) -> -44604.336 | J50: =INDEX(Monthly!$C$108:$BJ$108,($R$2-1)*12+3) -> -70438.913 | K50: =INDEX(Monthly!$C$108:$BJ$108,($R$2-1)*12+4) -> -92961.948 | L50: =INDEX(Monthly!$C$108:$BJ$108,($R$2-1)*12+5) -> -112173.44 | M50: =INDEX(Monthly!$C$108:$BJ$108,($R$2-1)*12+6) -> -128073.39 | N50: =INDEX(Monthly!$C$108:$BJ$108,($R$2-1)*12+7) -> -140661.8 | O50: =INDEX(Monthly!$C$108:$BJ$108,($R$2-1)*12+8) -> -153858.67 | P50: =INDEX(Monthly!$C$108:$BJ$108,($R$2-1)*12+9) -> -167663.99 | Q50: =INDEX(Monthly!$C$108:$BJ$108,($R$2-1)*12+10) -> -178157.78 | R50: =INDEX(Monthly!$C$108:$BJ$108,($R$2-1)*12+11) -> -185340.02 | S50: =INDEX(Monthly!$C$108:$BJ$108,($R$2-1)*12+12) -> -189210.72
A51: Total equity | B51: ='Balance Sheet'!B15 -> 260789.28 | C51: ='Balance Sheet'!C15 -> 252579.9 | D51: ='Balance Sheet'!D15 -> 248915.04 | E51: ='Balance Sheet'!E15 -> 250415.23 | F51: ='Balance Sheet'!F15 -> 257202.43 | H51: =INDEX(Monthly!$C$111:$BJ$111,($R$2-1)*12+1) -> 426701.78 | I51: =INDEX(Monthly!$C$111:$BJ$111,($R$2-1)*12+2) -> 405395.66 | J51: =INDEX(Monthly!$C$111:$BJ$111,($R$2-1)*12+3) -> 379561.09 | K51: =INDEX(Monthly!$C$111:$BJ$111,($R$2-1)*12+4) -> 357038.05 | L51: =INDEX(Monthly!$C$111:$BJ$111,($R$2-1)*12+5) -> 337826.56 | M51: =INDEX(Monthly!$C$111:$BJ$111,($R$2-1)*12+6) -> 321926.61 | N51: =INDEX(Monthly!$C$111:$BJ$111,($R$2-1)*12+7) -> 309338.2 | O51: =INDEX(Monthly!$C$111:$BJ$111,($R$2-1)*12+8) -> 296141.33 | P51: =INDEX(Monthly!$C$111:$BJ$111,($R$2-1)*12+9) -> 282336.01 | Q51: =INDEX(Monthly!$C$111:$BJ$111,($R$2-1)*12+10) -> 271842.22 | R51: =INDEX(Monthly!$C$111:$BJ$111,($R$2-1)*12+11) -> 264659.98 | S51: =INDEX(Monthly!$C$111:$BJ$111,($R$2-1)*12+12) -> 260789.28
A52: Total liabilities & equity | B52: ='Balance Sheet'!B16 -> 498492.57 | C52: ='Balance Sheet'!C16 -> 465741.7 | D52: ='Balance Sheet'!D16 -> 437409.2 | E52: ='Balance Sheet'!E16 -> 414251.72 | F52: ='Balance Sheet'!F16 -> 396391.52 | H52: =INDEX(Monthly!$C$112:$BJ$112,($R$2-1)*12+1) -> 680078.05 | I52: =INDEX(Monthly!$C$112:$BJ$112,($R$2-1)*12+2) -> 656824.45 | J52: =INDEX(Monthly!$C$112:$BJ$112,($R$2-1)*12+3) -> 631917.05 | K52: =INDEX(Monthly!$C$112:$BJ$112,($R$2-1)*12+4) -> 607446.54 | L52: =INDEX(Monthly!$C$112:$BJ$112,($R$2-1)*12+5) -> 586287.56 | M52: =INDEX(Monthly!$C$112:$BJ$112,($R$2-1)*12+6) -> 568440.12 | N52: =INDEX(Monthly!$C$112:$BJ$112,($R$2-1)*12+7) -> 553904.23 | O52: =INDEX(Monthly!$C$112:$BJ$112,($R$2-1)*12+8) -> 540197.22 | P52: =INDEX(Monthly!$C$112:$BJ$112,($R$2-1)*12+9) -> 525881.74 | Q52: =INDEX(Monthly!$C$112:$BJ$112,($R$2-1)*12+10) -> 513440.47 | R52: =INDEX(Monthly!$C$112:$BJ$112,($R$2-1)*12+11) -> 504310.75 | S52: =INDEX(Monthly!$C$112:$BJ$112,($R$2-1)*12+12) -> 498492.57

Sheet Scenarios
A1: Scenarios — Low / Base / High | H1: =HYPERLINK("#'Cover'!A1","◂ Contents") -> ◂ Contents
A2: All three scenarios calculated side by side, live: change any input and every column updates. Active = the scenario chosen on the Dashboard.
A5: Key drivers
A6: Driver | B6: Low | C6: Base | D6: High | E6: Active
A7: Licensed places (children) at start (#) | B7: =Inputs!$B$7 -> 60 | C7: =Inputs!$C$7 -> 60 | D7: =Inputs!$D$7 -> 60 | E7: =Inputs!$E$7 -> 60
A8: Enrolment once full, % of licensed places (%) | B8: =Inputs!$B$10 -> 0.78 | C8: =Inputs!$C$10 -> 0.85 | D8: =Inputs!$D$10 -> 0.9 | E8: =Inputs!$E$10 -> 0.85
A9: Tuition per infant / toddler per month (year 1) ($) | B9: =Inputs!$B$17 -> 1430 | C9: =Inputs!$C$17 -> 1500 | D9: =Inputs!$D$17 -> 1570 | E9: =Inputs!$E$17 -> 1500
A10: Tuition per preschooler per month (year 1) ($) | B10: =Inputs!$B$18 -> 1040 | C10: =Inputs!$C$18 -> 1100 | D10: =Inputs!$D$18 -> 1160 | E10: =Inputs!$E$18 -> 1100
A11: Children paid by subsidy / vouchers, % of enrolled (%) | B11: =Inputs!$B$22 -> 0.25 | C11: =Inputs!$C$22 -> 0.25 | D11: =Inputs!$D$22 -> 0.25 | E11: =Inputs!$E$22 -> 0.25
A12: Rent per square foot per year (year 1) ($) | B12: =Inputs!$B$38 -> 17 | C12: =Inputs!$C$38 -> 16 | D12: =Inputs!$D$38 -> 15 | E12: =Inputs!$E$38 -> 16
A13: Equity raised at start ($) | B13: =Inputs!$B$73 -> 450000 | C13: =Inputs!$C$73 -> 450000 | D13: =Inputs!$D$73 -> 450000 | E13: =Inputs!$E$73 -> 450000
A15: Results by scenario ($'000)
A16: Output | B16: Low | C16: Base | D16: High | E16: Active
A17: Revenue — final year | B17: =F30 -> 665483.7 | C17: =F31 -> 792649.71 | D17: =F32 -> 932012.18 | E17: ='P&L'!F5 -> 792649.71
A18: Revenue — whole plan | B18: =SUM(B30:F30) -> 2787044.2 | C18: =SUM(B31:F31) -> 3454956.2 | D18: =SUM(B32:F32) -> 4086174.7 | E18: =SUM('P&L'!$B$5:$F$5) -> 3454956.2
A19: EBITDA — final year | B19: =F36 -> -92680.594 | C19: =F37 -> 65753.868 | D19: =F38 -> 189614.03 | E19: ='P&L'!F19 -> 65753.868
A20: EBITDA margin — final year | B20: =IF(B17=0,0,B19/B17) -> -0.13926802 | C20: =IF(C17=0,0,C19/C17) -> 0.08295451 | D20: =IF(D17=0,0,D19/D17) -> 0.20344587 | E20: =IF(E17=0,0,E19/E17) -> 0.08295451
A21: Net income — final year | B21: =F42 -> -151647.26 | C21: =F43 -> 6787.2016 | D21: =F44 -> 103211.42 | E21: ='P&L'!F26 -> 6787.2016
A22: Net income — whole plan | B22: =SUM(B42:F42) -> -912098.28 | C22: =SUM(B43:F43) -> -192797.57 | D22: =SUM(B44:F44) -> 285694.57 | E22: =SUM('P&L'!$B$26:$F$26) -> -192797.57
A23: Cash at the end of the plan | B23: =F48 -> -597675.42 | C23: =F49 -> 116466.49 | D23: =F50 -> 590407.17 | E23: ='Balance Sheet'!F5 -> 116466.49
A24: Lowest cash balance | B24: =MIN('Scenario calc'!$C$97:$BJ$97) -> -597675.42 | C24: =MIN('Scenario calc'!$C$223:$BJ$223) -> 64092.356 | D24: =MIN('Scenario calc'!$C$349:$BJ$349) -> 173336.78 | E24: ='Break-even'!B18 -> 64092.356
A25: Lowest cash point (month #) | B25: =MATCH(MIN('Scenario calc'!$C$97:$BJ$97),'Scenario calc'!$C$97:$BJ$97,0) -> 60 | C25: =MATCH(MIN('Scenario calc'!$C$223:$BJ$223),'Scenario calc'!$C$223:$BJ$223,0) -> 13 | D25: =MATCH(MIN('Scenario calc'!$C$349:$BJ$349),'Scenario calc'!$C$349:$BJ$349,0) -> 8 | E25: ='Break-even'!B6 -> 13
A26: Funding required (incl. cash buffer) | B26: =SUMPRODUCT(--('Scenario calc'!$C$6:$BJ$6<=B25),'Scenario calc'!$C$70:$BJ$70)-SUMPRODUCT(--('Scenario calc'!$C$6:$BJ$6<=B25),'Scenario calc'!$C$91:$BJ$91)-SUMPRODUCT(--('Scenario calc'!$C$6:$BJ$6<=B25),'Scenario calc'!$C$79:$BJ$79)+Inputs!$B$88 -> 1371675.4 | C26: =SUMPRODUCT(--('Scenario calc'!$C$132:$BJ$132<=C25),'Scenario calc'!$C$196:$BJ$196)-SUMPRODUCT(--('Scenario calc'!$C$132:$BJ$132<=C25),'Scenario calc'!$C$217:$BJ$217)-SUMPRODUCT(--('Scenario calc'!$C$132:$BJ$132<=C25),'Scenario calc'!$C$205:$BJ$205)+Inputs!$C$88 -> 709907.64 | D26: =SUMPRODUCT(--('Scenario calc'!$C$258:$BJ$258<=D25),'Scenario calc'!$C$322:$BJ$322)-SUMPRODUCT(--('Scenario calc'!$C$258:$BJ$258<=D25),'Scenario calc'!$C$343:$BJ$343)-SUMPRODUCT(--('Scenario calc'!$C$258:$BJ$258<=D25),'Scenario calc'!$C$331:$BJ$331)+Inputs!$D$88 -> 600663.22 | E26: ='Break-even'!B12 -> 709907.64
A28: Revenue by year ($'000)
A29: Scenario | B29: 1 | C29: 2 | D29: 3 | E29: 4 | F29: 5
A30: Low | B30: =SUMIF('Scenario calc'!$C$7:$BJ$7,B$29,'Scenario calc'!$C$34:$BJ$34) -> 267942.91 | C30: =SUMIF('Scenario calc'!$C$7:$BJ$7,C$29,'Scenario calc'!$C$34:$BJ$34) -> 570948.2 | D30: =SUMIF('Scenario calc'!$C$7:$BJ$7,D$29,'Scenario calc'!$C$34:$BJ$34) -> 633416.96 | E30: =SUMIF('Scenario calc'!$C$7:$BJ$7,E$29,'Scenario calc'!$C$34:$BJ$34) -> 649252.39 | F30: =SUMIF('Scenario calc'!$C$7:$BJ$7,F$29,'Scenario calc'!$C$34:$BJ$34) -> 665483.7
A31: Base | B31: =SUMIF('Scenario calc'!$C$133:$BJ$133,B$29,'Scenario calc'!$C$160:$BJ$160) -> 419706.38 | C31: =SUMIF('Scenario calc'!$C$133:$BJ$133,C$29,'Scenario calc'!$C$160:$BJ$160) -> 725888.9 | D31: =SUMIF('Scenario calc'!$C$133:$BJ$133,D$29,'Scenario calc'!$C$160:$BJ$160) -> 747148.37 | E31: =SUMIF('Scenario calc'!$C$133:$BJ$133,E$29,'Scenario calc'!$C$160:$BJ$160) -> 769562.82 | F31: =SUMIF('Scenario calc'!$C$133:$BJ$133,F$29,'Scenario calc'!$C$160:$BJ$160) -> 792649.71
A32: High | B32: =SUMIF('Scenario calc'!$C$259:$BJ$259,B$29,'Scenario calc'!$C$286:$BJ$286) -> 567743.87 | C32: =SUMIF('Scenario calc'!$C$259:$BJ$259,C$29,'Scenario calc'!$C$286:$BJ$286) -> 828555.44 | D32: =SUMIF('Scenario calc'!$C$259:$BJ$259,D$29,'Scenario calc'!$C$286:$BJ$286) -> 861697.65 | E32: =SUMIF('Scenario calc'!$C$259:$BJ$259,E$29,'Scenario calc'!$C$286:$BJ$286) -> 896165.56 | F32: =SUMIF('Scenario calc'!$C$259:$BJ$259,F$29,'Scenario calc'!$C$286:$BJ$286) -> 932012.18
A34: EBITDA by year ($'000)
A35: Scenario | B35: 1 | C35: 2 | D35: 3 | E35: 4 | F35: 5
A36: Low | B36: =SUMIF('Scenario calc'!$C$7:$BJ$7,B$35,'Scenario calc'!$C$54:$BJ$54) -> -228607.08 | C36: =SUMIF('Scenario calc'!$C$7:$BJ$7,C$35,'Scenario calc'!$C$54:$BJ$54) -> -109978.92 | D36: =SUMIF('Scenario calc'!$C$7:$BJ$7,D$35,'Scenario calc'!$C$54:$BJ$54) -> -85835.831 | E36: =SUMIF('Scenario calc'!$C$7:$BJ$7,E$35,'Scenario calc'!$C$54:$BJ$54) -> -89169.476 | F36: =SUMIF('Scenario calc'!$C$7:$BJ$7,F$35,'Scenario calc'!$C$54:$BJ$54) -> -92680.594
A37: Base | B37: =SUMIF('Scenario calc'!$C$133:$BJ$133,B$35,'Scenario calc'!$C$180:$BJ$180) -> -125850.99 | C37: =SUMIF('Scenario calc'!$C$133:$BJ$133,C$35,'Scenario calc'!$C$180:$BJ$180) -> 54057.278 | D37: =SUMIF('Scenario calc'!$C$133:$BJ$133,D$35,'Scenario calc'!$C$180:$BJ$180) -> 57501.808 | E37: =SUMIF('Scenario calc'!$C$133:$BJ$133,E$35,'Scenario calc'!$C$180:$BJ$180) -> 61566.862 | F37: =SUMIF('Scenario calc'!$C$133:$BJ$133,F$35,'Scenario calc'!$C$180:$BJ$180) -> 65753.868
A38: High | B38: =SUMIF('Scenario calc'!$C$259:$BJ$259,B$35,'Scenario calc'!$C$306:$BJ$306) -> 3918.8463 | C38: =SUMIF('Scenario calc'!$C$259:$BJ$259,C$35,'Scenario calc'!$C$306:$BJ$306) -> 142946.24 | D38: =SUMIF('Scenario calc'!$C$259:$BJ$259,D$35,'Scenario calc'!$C$306:$BJ$306) -> 157721.04 | E38: =SUMIF('Scenario calc'!$C$259:$BJ$259,E$35,'Scenario calc'!$C$306:$BJ$306) -> 173264.93 | F38: =SUMIF('Scenario calc'!$C$259:$BJ$259,F$35,'Scenario calc'!$C$306:$BJ$306) -> 189614.03
A40: Net income by year ($'000)
A41: Scenario | B41: 1 | C41: 2 | D41: 3 | E41: 4 | F41: 5
A42: Low | B42: =SUMIF('Scenario calc'!$C$7:$BJ$7,B$41,'Scenario calc'!$C$63:$BJ$63) -> -291966.8 | C42: =SUMIF('Scenario calc'!$C$7:$BJ$7,C$41,'Scenario calc'!$C$63:$BJ$63) -> -172245.58 | D42: =SUMIF('Scenario calc'!$C$7:$BJ$7,D$41,'Scenario calc'!$C$63:$BJ$63) -> -147002.5 | E42: =SUMIF('Scenario calc'!$C$7:$BJ$7,E$41,'Scenario calc'!$C$63:$BJ$63) -> -149236.14 | F42: =SUMIF('Scenario calc'!$C$7:$BJ$7,F$41,'Scenario calc'!$C$63:$BJ$63) -> -151647.26
A43: Base | B43: =SUMIF('Scenario calc'!$C$133:$BJ$133,B$41,'Scenario calc'!$C$189:$BJ$189) -> -189210.72 | C43: =SUMIF('Scenario calc'!$C$133:$BJ$133,C$41,'Scenario calc'!$C$189:$BJ$189) -> -8209.3882 | D43: =SUMIF('Scenario calc'!$C$133:$BJ$133,D$41,'Scenario calc'!$C$189:$BJ$189) -> -3664.8586 | E43: =SUMIF('Scenario calc'!$C$133:$BJ$133,E$41,'Scenario calc'!$C$189:$BJ$189) -> 1500.1957 | F43: =SUMIF('Scenario calc'!$C$133:$BJ$133,F$41,'Scenario calc'!$C$189:$BJ$189) -> 6787.2016
A44: High | B44: =SUMIF('Scenario calc'!$C$259:$BJ$259,B$41,'Scenario calc'!$C$315:$BJ$315) -> -59440.876 | C44: =SUMIF('Scenario calc'!$C$259:$BJ$259,C$41,'Scenario calc'!$C$315:$BJ$315) -> 76219.448 | D44: =SUMIF('Scenario calc'!$C$259:$BJ$259,D$41,'Scenario calc'!$C$315:$BJ$315) -> 76277.952 | E44: =SUMIF('Scenario calc'!$C$259:$BJ$259,E$41,'Scenario calc'!$C$315:$BJ$315) -> 89426.629 | F44: =SUMIF('Scenario calc'!$C$259:$BJ$259,F$41,'Scenario calc'!$C$315:$BJ$315) -> 103211.42
A46: Cash at year end by year ($'000)
A47: Scenario | B47: 1 | C47: 2 | D47: 3 | E47: 4 | F47: 5
A48: Low | B48: =INDEX('Scenario calc'!$C$97:$BJ$97,B$47*12) -> -22127.597 | C48: =INDEX('Scenario calc'!$C$97:$BJ$97,C$47*12) -> -187568.86 | D48: =INDEX('Scenario calc'!$C$97:$BJ$97,D$47*12) -> -322871.98 | E48: =INDEX('Scenario calc'!$C$97:$BJ$97,E$47*12) -> -459514.97 | F48: =INDEX('Scenario calc'!$C$97:$BJ$97,F$47*12) -> -597675.42
A49: Base | B49: =INDEX('Scenario calc'!$C$223:$BJ$223,B$47*12) -> 73774.032 | C49: =INDEX('Scenario calc'!$C$223:$BJ$223,C$47*12) -> 74825.779 | D49: =INDEX('Scenario calc'!$C$223:$BJ$223,D$47*12) -> 82616.797 | E49: =INDEX('Scenario calc'!$C$223:$BJ$223,E$47*12) -> 96456.545 | F49: =INDEX('Scenario calc'!$C$223:$BJ$223,F$47*12) -> 116466.49
A50: High | B50: =INDEX('Scenario calc'!$C$349:$BJ$349,B$47*12) -> 199323 | C50: =INDEX('Scenario calc'!$C$349:$BJ$349,C$47*12) -> 285739.17 | D50: =INDEX('Scenario calc'!$C$349:$BJ$349,D$47*12) -> 373075.24 | E50: =INDEX('Scenario calc'!$C$349:$BJ$349,E$47*12) -> 474419.77 | F50: =INDEX('Scenario calc'!$C$349:$BJ$349,F$47*12) -> 590407.17

Sheet Break-even
A1: Startup costs, funding need and break-even | H1: =HYPERLINK("#'Cover'!A1","◂ Contents") -> ◂ Contents
A2: Live for the selected scenario. Periods are counted in months from the start of the plan.
A3: Scenario shown | B3: =CHOOSE(Dashboard!$B$4,"Low","Base","High") -> Base
A5: Startup costs & funding need (up to the lowest cash point)
A6: Lowest cash point (month #) | B6: =MATCH(MIN(Monthly!$C$95:$BJ$95),Monthly!$C$95:$BJ$95,0) -> 13
A7: Capital spending up to the lowest cash point | B7: =SUMPRODUCT(--(Monthly!$C$4:$BJ$4<=$B$6),Monthly!$C$68:$BJ$68) -> 451000
A8: Operating cash burn up to the lowest cash point | B8: =-SUMPRODUCT(--(Monthly!$C$4:$BJ$4<=$B$6),Monthly!$C$89:$BJ$89) -> 159907.64 | D8: Losses and working capital before the business funds itself
A9: Loan repayments up to the lowest cash point | B9: =-SUMPRODUCT(--(Monthly!$C$4:$BJ$4<=$B$6),Monthly!$C$77:$BJ$77) -> 25000
A10: Total uses of funds | B10: =B7+B8+B9 -> 635907.64
A11: Minimum cash buffer to keep | B11: =Inputs!$E$88 -> 74000 | D11: Input on the Inputs sheet
A12: Funding required (uses + buffer) | B12: =B10+B11 -> 709907.64
A14: Equity raised | B14: =Inputs!$E$73 -> 450000
A15: Loan drawn | B15: =Inputs!$E$74 -> 250000
A16: Total sources of funds | B16: =B14+B15 -> 700000
A17: Funding surplus / (shortfall) | B17: =B16-B12 -> -9907.6437 | D17: Negative = raise at least this much more
A18: Lowest cash balance in the plan | B18: =MIN(Monthly!$C$95:$BJ$95) -> 64092.356 | D18: Equals sources minus uses
A20: Break-even timing
A21: First month with positive EBITDA (month #) | B21: =IFERROR(MATCH(1,Monthly!$C$96:$BJ$96,0),"Not within horizon") -> 12
A22: First month with positive net income (month #) | B22: =IFERROR(MATCH(1,Monthly!$C$99:$BJ$99,0),"Not within horizon") -> 37
A23: Cash invested paid back (month #) | B23: =IF(MIN(Monthly!$C$101:$BJ$101)>=0,"No investment to pay back",IFERROR(MATCH(1,Monthly!$C$103:$BJ$103,0),"Not within horizon")) -> Not within horizon | D23: Cumulative operating + investing cash flow back to zero
A25: Annual break-even revenue
A26: Year # | B26: 1 | C26: 2 | D26: 3 | E26: 4 | F26: 5
B27: Year 1 | C27: Year 2 | D27: Year 3 | E27: Year 4 | F27: Year 5
A28: Revenue | B28: =SUMIF(Monthly!$C$5:$BJ$5,B$26,Monthly!$C$32:$BJ$32) -> 419706.38 | C28: =SUMIF(Monthly!$C$5:$BJ$5,C$26,Monthly!$C$32:$BJ$32) -> 725888.9 | D28: =SUMIF(Monthly!$C$5:$BJ$5,D$26,Monthly!$C$32:$BJ$32) -> 747148.37 | E28: =SUMIF(Monthly!$C$5:$BJ$5,E$26,Monthly!$C$32:$BJ$32) -> 769562.82 | F28: =SUMIF(Monthly!$C$5:$BJ$5,F$26,Monthly!$C$32:$BJ$32) -> 792649.71
A29: Gross profit | B29: =SUMIF(Monthly!$C$5:$BJ$5,B$26,Monthly!$C$39:$BJ$39) -> 171077.38 | C29: =SUMIF(Monthly!$C$5:$BJ$5,C$26,Monthly!$C$39:$BJ$39) -> 363320.66 | D29: =SUMIF(Monthly!$C$5:$BJ$5,D$26,Monthly!$C$39:$BJ$39) -> 373703.09 | E29: =SUMIF(Monthly!$C$5:$BJ$5,E$26,Monthly!$C$39:$BJ$39) -> 384914.18 | F29: =SUMIF(Monthly!$C$5:$BJ$5,F$26,Monthly!$C$39:$BJ$39) -> 396461.6
A30: Gross margin (contribution) | B30: =IF(B28=0,0,B29/B28) -> 0.40761205 | C30: =IF(C28=0,0,C29/C28) -> 0.50051827 | D30: =IF(D28=0,0,D29/D28) -> 0.50017252 | E30: =IF(E28=0,0,E29/E28) -> 0.50017252 | F30: =IF(F28=0,0,F29/F28) -> 0.50017252
A31: Operating expenses (treated as fixed) | B31: =-SUMIF(Monthly!$C$5:$BJ$5,B$26,Monthly!$C$51:$BJ$51) -> 296928.37 | C31: =-SUMIF(Monthly!$C$5:$BJ$5,C$26,Monthly!$C$51:$BJ$51) -> 309263.38 | D31: =-SUMIF(Monthly!$C$5:$BJ$5,D$26,Monthly!$C$51:$BJ$51) -> 316201.28 | E31: =-SUMIF(Monthly!$C$5:$BJ$5,E$26,Monthly!$C$51:$BJ$51) -> 323347.32 | F31: =-SUMIF(Monthly!$C$5:$BJ$5,F$26,Monthly!$C$51:$BJ$51) -> 330707.74
A32: Break-even revenue (EBITDA = 0) | B32: =IF(B30>0,B31/B30,"n/a") -> 728458.27 | C32: =IF(C30>0,C31/C30,"n/a") -> 617886.29 | D32: =IF(D30>0,D31/D30,"n/a") -> 632184.42 | E32: =IF(E30>0,E31/E30,"n/a") -> 646471.57 | F32: =IF(F30>0,F31/F30,"n/a") -> 661187.33
A33: Margin of safety (revenue above break-even) | B33: =IF(AND(ISNUMBER(B32),B28>0),(B28-B32)/B28,"n/a") -> -0.73563786 | C33: =IF(AND(ISNUMBER(C32),C28>0),(C28-C32)/C28,"n/a") -> 0.14878669 | D33: =IF(AND(ISNUMBER(D32),D28>0),(D28-D32)/D28,"n/a") -> 0.15387031 | E33: =IF(AND(ISNUMBER(E32),E28>0),(E28-E32)/E28,"n/a") -> 0.15994958 | F33: =IF(AND(ISNUMBER(F32),F28>0),(F28-F32)/F28,"n/a") -> 0.16585179
A35: Simplification: cost of sales is treated as variable and operating expenses as fixed, so break-even revenue = operating expenses ÷ gross margin.

Sheet Valuation
A1: Discounted cash flow valuation | H1: =HYPERLINK("#'Cover'!A1","◂ Contents") -> ◂ Contents
A2: Enterprise value at the start of the plan, before the funding raised in period 1. Year-end discounting.
A3: Scenario shown | B3: =CHOOSE(Dashboard!$B$4,"Low","Base","High") -> Base
A5: Assumptions (active scenario, from the Inputs sheet)
A6: Discount rate (WACC) | B6: =Inputs!$E$91 -> 0.25
A7: Terminal growth rate | B7: =Inputs!$E$92 -> 0.02
A8: Exit multiple (EV ÷ final-year EBITDA) | B8: =Inputs!$E$93 -> 4
A9: Tax rate (for the interest tax shield) | B9: =Inputs!$E$85 -> 0.21
A10: Sensitivity step: WACC | B10: =Inputs!$E$94 -> 0.01
A11: Sensitivity step: terminal growth | B11: =Inputs!$E$95 -> 0.005
A13: Free cash flow by year
A14: Year # | B14: 1 | C14: 2 | D14: 3 | E14: 4 | F14: 5
B15: Year 1 | C15: Year 2 | D15: Year 3 | E15: Year 4 | F15: Year 5
A16: EBITDA | B16: =SUMIF(Monthly!$C$5:$BJ$5,B$14,Monthly!$C$52:$BJ$52) -> -125850.99 | C16: =SUMIF(Monthly!$C$5:$BJ$5,C$14,Monthly!$C$52:$BJ$52) -> 54057.278 | D16: =SUMIF(Monthly!$C$5:$BJ$5,D$14,Monthly!$C$52:$BJ$52) -> 57501.808 | E16: =SUMIF(Monthly!$C$5:$BJ$5,E$14,Monthly!$C$52:$BJ$52) -> 61566.862 | F16: =SUMIF(Monthly!$C$5:$BJ$5,F$14,Monthly!$C$52:$BJ$52) -> 65753.868
A17: Unlevered free cash flow | B17: =SUMIF(Monthly!$C$5:$BJ$5,B$14,Monthly!$C$104:$BJ$104) -> -588173.12 | C17: =SUMIF(Monthly!$C$5:$BJ$5,C$14,Monthly!$C$104:$BJ$104) -> 39613.414 | D17: =SUMIF(Monthly!$C$5:$BJ$5,D$14,Monthly!$C$104:$BJ$104) -> 44772.685 | E17: =SUMIF(Monthly!$C$5:$BJ$5,E$14,Monthly!$C$104:$BJ$104) -> 49241.415 | F17: =SUMIF(Monthly!$C$5:$BJ$5,F$14,Monthly!$C$104:$BJ$104) -> 53831.608
A18: Discount factor | B18: =1/(1+Inputs!$E$91)^B$14 -> 0.8 | C18: =1/(1+Inputs!$E$91)^C$14 -> 0.64 | D18: =1/(1+Inputs!$E$91)^D$14 -> 0.512 | E18: =1/(1+Inputs!$E$91)^E$14 -> 0.4096 | F18: =1/(1+Inputs!$E$91)^F$14 -> 0.32768
A19: Present value of free cash flow | B19: =B17*B18 -> -470538.5 | C19: =C17*C18 -> 25352.585 | D19: =D17*D18 -> 22923.615 | E19: =E17*E18 -> 20169.284 | F19: =F17*F18 -> 17639.541
A21: Enterprise value
B22: Perpetual growth | C22: Exit multiple
A23: Present value of the plan's free cash flows | B23: =SUM($B$19:$F$19) -> -384453.47 | C23: =B23 -> -384453.47
A24: Final-year free cash flow | final-year EBITDA | B24: =$F$17 -> 53831.608 | C24: =$F$16 -> 65753.868
A25: Terminal value at the end of year 5 | B25: =IF($B$6>$B$7,B24*(1+$B$7)/($B$6-$B$7),0) -> 238731.48 | C25: =C24*$B$8 -> 263015.47
A26: Present value of the terminal value | B26: =B25/(1+$B$6)^$F$14 -> 78227.53 | C26: =C25/(1+$B$6)^$F$14 -> 86184.91
A27: Enterprise value | B27: =B23+B26 -> -306225.94 | C27: =C23+C26 -> -298268.56
A28: Terminal value share of enterprise value | B28: =IF(B27<>0,B26/B27,0) -> -0.2554569 | C28: =IF(C27<>0,C26/C27,0) -> -0.2889507
A29: Cross-check: implied exit multiple | implied perpetual growth | B29: =IF(C24>0,B25/C24,"n/a") -> 3.6306834 | C29: =IF(C25+B24<>0,(C25*$B$6-B24)/(C25+B24),"n/a") -> 0.037627806
A30: Enterprise value — average of the two methods | B30: =AVERAGE(B27,C27) -> -302247.25
A32: Sensitivity: enterprise value (perpetual growth) by WACC and terminal growth
A33: WACC ↓ · terminal growth → | B33: =$B$7+(-2)*$B$11 -> 0.01 | C33: =$B$7+(-1)*$B$11 -> 0.015 | D33: =$B$7+(0)*$B$11 -> 0.02 | E33: =$B$7+(1)*$B$11 -> 0.025 | F33: =$B$7+(2)*$B$11 -> 0.03
A34: =$B$6+(-2)*$B$10 -> 0.23 | B34: =IF($A34>B$33,SUMPRODUCT($B$17:$F$17/(1+$A34)^$B$14:$F$14)+$F$17*(1+B$33)/($A34-B$33)/(1+$A34)^$F$14,"n/a") -> -299528.13 | C34: =IF($A34>C$33,SUMPRODUCT($B$17:$F$17/(1+$A34)^$B$14:$F$14)+$F$17*(1+C$33)/($A34-C$33)/(1+$A34)^$F$14,"n/a") -> -297041.99 | D34: =IF($A34>D$33,SUMPRODUCT($B$17:$F$17/(1+$A34)^$B$14:$F$14)+$F$17*(1+D$33)/($A34-D$33)/(1+$A34)^$F$14,"n/a") -> -294437.46 | E34: =IF($A34>E$33,SUMPRODUCT($B$17:$F$17/(1+$A34)^$B$14:$F$14)+$F$17*(1+E$33)/($A34-E$33)/(1+$A34)^$F$14,"n/a") -> -291705.88 | F34: =IF($A34>F$33,SUMPRODUCT($B$17:$F$17/(1+$A34)^$B$14:$F$14)+$F$17*(1+F$33)/($A34-F$33)/(1+$A34)^$F$14,"n/a") -> -288837.72
A35: =$B$6+(-1)*$B$10 -> 0.24 | B35: =IF($A35>B$33,SUMPRODUCT($B$17:$F$17/(1+$A35)^$B$14:$F$14)+$F$17*(1+B$33)/($A35-B$33)/(1+$A35)^$F$14,"n/a") -> -305262.33 | C35: =IF($A35>C$33,SUMPRODUCT($B$17:$F$17/(1+$A35)^$B$14:$F$14)+$F$17*(1+C$33)/($A35-C$33)/(1+$A35)^$F$14,"n/a") -> -303062.39 | D35: =IF($A35>D$33,SUMPRODUCT($B$17:$F$17/(1+$A35)^$B$14:$F$14)+$F$17*(1+D$33)/($A35-D$33)/(1+$A35)^$F$14,"n/a") -> -300762.45 | E35: =IF($A35>E$33,SUMPRODUCT($B$17:$F$17/(1+$A35)^$B$14:$F$14)+$F$17*(1+E$33)/($A35-E$33)/(1+$A35)^$F$14,"n/a") -> -298355.55 | F35: =IF($A35>F$33,SUMPRODUCT($B$17:$F$17/(1+$A35)^$B$14:$F$14)+$F$17*(1+F$33)/($A35-F$33)/(1+$A35)^$F$14,"n/a") -> -295834.02
A36: =$B$6+(0)*$B$10 -> 0.25 | B36: =IF($A36>B$33,SUMPRODUCT($B$17:$F$17/(1+$A36)^$B$14:$F$14)+$F$17*(1+B$33)/($A36-B$33)/(1+$A36)^$F$14,"n/a") -> -310220.4 | C36: =IF($A36>C$33,SUMPRODUCT($B$17:$F$17/(1+$A36)^$B$14:$F$14)+$F$17*(1+C$33)/($A36-C$33)/(1+$A36)^$F$14,"n/a") -> -308265.67 | D36: =IF($A36>D$33,SUMPRODUCT($B$17:$F$17/(1+$A36)^$B$14:$F$14)+$F$17*(1+D$33)/($A36-D$33)/(1+$A36)^$F$14,"n/a") -> -306225.94 | E36: =IF($A36>E$33,SUMPRODUCT($B$17:$F$17/(1+$A36)^$B$14:$F$14)+$F$17*(1+E$33)/($A36-E$33)/(1+$A36)^$F$14,"n/a") -> -304095.56 | F36: =IF($A36>F$33,SUMPRODUCT($B$17:$F$17/(1+$A36)^$B$14:$F$14)+$F$17*(1+F$33)/($A36-F$33)/(1+$A36)^$F$14,"n/a") -> -301868.35
A37: =$B$6+(1)*$B$10 -> 0.26 | B37: =IF($A37>B$33,SUMPRODUCT($B$17:$F$17/(1+$A37)^$B$14:$F$14)+$F$17*(1+B$33)/($A37-B$33)/(1+$A37)^$F$14,"n/a") -> -314502.66 | C37: =IF($A37>C$33,SUMPRODUCT($B$17:$F$17/(1+$A37)^$B$14:$F$14)+$F$17*(1+C$33)/($A37-C$33)/(1+$A37)^$F$14,"n/a") -> -312759.18 | D37: =IF($A37>D$33,SUMPRODUCT($B$17:$F$17/(1+$A37)^$B$14:$F$14)+$F$17*(1+D$33)/($A37-D$33)/(1+$A37)^$F$14,"n/a") -> -310943.04 | E37: =IF($A37>E$33,SUMPRODUCT($B$17:$F$17/(1+$A37)^$B$14:$F$14)+$F$17*(1+E$33)/($A37-E$33)/(1+$A37)^$F$14,"n/a") -> -309049.63 | F37: =IF($A37>F$33,SUMPRODUCT($B$17:$F$17/(1+$A37)^$B$14:$F$14)+$F$17*(1+F$33)/($A37-F$33)/(1+$A37)^$F$14,"n/a") -> -307073.89
A38: =$B$6+(2)*$B$10 -> 0.27 | B38: =IF($A38>B$33,SUMPRODUCT($B$17:$F$17/(1+$A38)^$B$14:$F$14)+$F$17*(1+B$33)/($A38-B$33)/(1+$A38)^$F$14,"n/a") -> -318193.75 | C38: =IF($A38>C$33,SUMPRODUCT($B$17:$F$17/(1+$A38)^$B$14:$F$14)+$F$17*(1+C$33)/($A38-C$33)/(1+$A38)^$F$14,"n/a") -> -316633.19 | D38: =IF($A38>D$33,SUMPRODUCT($B$17:$F$17/(1+$A38)^$B$14:$F$14)+$F$17*(1+D$33)/($A38-D$33)/(1+$A38)^$F$14,"n/a") -> -315010.21 | E38: =IF($A38>E$33,SUMPRODUCT($B$17:$F$17/(1+$A38)^$B$14:$F$14)+$F$17*(1+E$33)/($A38-E$33)/(1+$A38)^$F$14,"n/a") -> -313320.99 | F38: =IF($A38>F$33,SUMPRODUCT($B$17:$F$17/(1+$A38)^$B$14:$F$14)+$F$17*(1+F$33)/($A38-F$33)/(1+$A38)^$F$14,"n/a") -> -311561.39
A40: Free cash flow = operating cash flow + interest × (1 − tax rate) − capital spending. Cells marked n/a: WACC not above growth.

Sheet Sources & Uses
A1: Sources and uses of funds | E1: =HYPERLINK("#'Cover'!A1","◂ Contents") -> ◂ Contents
A2: Live for the selected scenario. Where the money comes from and where it goes in the period set below.
A3: Scenario shown | B3: =CHOOSE(Dashboard!$B$4,"Low","Base","High") -> Base
A5: Funding structure ($'000) — raised at the start of the plan
B6: Amount | C6: Share
A7: Equity | B7: =Inputs!$E$73 -> 450000 | C7: =IF($B$9=0,0,B7/$B$9) -> 0.64285714
A8: Debt (loan) | B8: =Inputs!$E$74 -> 250000 | C8: =IF($B$9=0,0,B8/$B$9) -> 0.35714286
A9: Total funding | B9: =B7+B8 -> 700000 | C9: =IF(B9=0,0,1) -> 1
A10: Gearing (debt ÷ equity) | B10: =IF(B7<=0,IF(B8>0,"n/a",0),B8/B7) -> 0.55555556 | D10: n/a: debt without positive equity
A11: Funding required by the plan (Break-even sheet) | B11: ='Break-even'!B12 -> 709907.64
A12: Funding surplus / (shortfall) | B12: ='Break-even'!B17 -> -9907.6437
A14: ="Sources and uses of cash in the first "&$B$16&IF($B$16=1," month"," months")&" ($'000)" -> Sources and uses of cash in the first 12 months ($'000)
A15: Period covered (months from the start) | B15: 12 | D15: 1 to 60 (capped)
A16: Months used | B16: =MIN(60,MAX(1,ROUND(B15,0))) -> 12
A17: Sources | B17: Amount | C17: Share
A18: Equity raised | B18: =SUMPRODUCT(--(Monthly!$C$4:$BJ$4<=$B$16),Monthly!$C$91:$BJ$91) -> 450000 | C18: =IF($B$21=0,0,B18/$B$21) -> 0.64285714
A19: Loan drawdowns | B19: =SUMPRODUCT(--(Monthly!$C$4:$BJ$4<=$B$16),Monthly!$C$76:$BJ$76) -> 250000 | C19: =IF($B$21=0,0,B19/$B$21) -> 0.35714286
A20: Cash generated by operations | B20: =MAX(0,SUMPRODUCT(--(Monthly!$C$4:$BJ$4<=$B$16),Monthly!$C$89:$BJ$89)) -> 0 | C20: =IF($B$21=0,0,B20/$B$21) -> 0
A21: Total sources | B21: =SUM(B18:B20) -> 700000 | C21: =IF(B21=0,0,1) -> 1
A23: Uses | B23: Amount | C23: Share
A24: Cash used by operations | B24: =MAX(0,-SUMPRODUCT(--(Monthly!$C$4:$BJ$4<=$B$16),Monthly!$C$89:$BJ$89)) -> 161309.3 | C24: =IF($B$28=0,0,B24/$B$28) -> 0.23044186
A25: Capital spending | B25: =-SUMPRODUCT(--(Monthly!$C$4:$BJ$4<=$B$16),Monthly!$C$90:$BJ$90) -> 442000 | C25: =IF($B$28=0,0,B25/$B$28) -> 0.63142857
A26: Loan repayments | B26: =-SUMPRODUCT(--(Monthly!$C$4:$BJ$4<=$B$16),Monthly!$C$77:$BJ$77) -> 22916.667 | C26: =IF($B$28=0,0,B26/$B$28) -> 0.032738095
A27: Cash at the end of the period | B27: =INDEX(Monthly!$C$95:$BJ$95,$B$16) -> 73774.032 | C27: =IF($B$28=0,0,B27/$B$28) -> 0.10539147
A28: Total uses | B28: =SUM(B24:B27) -> 700000 | C28: =IF(B28=0,0,1) -> 1
A29: Sources − uses (must be 0; opening cash is 0) | B29: =B21-B28 -> 0

Sheet KPIs
A1: KPIs & ratios | I1: =HYPERLINK("#'Cover'!A1","◂ Contents") -> ◂ Contents
A2: Childcare centre financial model (planning) — industry metrics and financial ratios for the active scenario
A4: Financial ratios
B5: 1 | C5: 2 | D5: 3 | E5: 4 | F5: 5 | G5: Target
A6: Revenue growth | B6: =IF(N('P&L'!A5)<=0,"n/a",'P&L'!B5/'P&L'!A5-1) -> n/a | C6: =IF(N('P&L'!B5)<=0,"n/a",'P&L'!C5/'P&L'!B5-1) -> 0.72951601 | D6: =IF(N('P&L'!C5)<=0,"n/a",'P&L'!D5/'P&L'!C5-1) -> 0.02928751 | E6: =IF(N('P&L'!D5)<=0,"n/a",'P&L'!E5/'P&L'!D5-1) -> 0.03 | F6: =IF(N('P&L'!E5)<=0,"n/a",'P&L'!F5/'P&L'!E5-1) -> 0.03
A7: Gross margin | B7: =IF('P&L'!B5<=0,"n/a",'P&L'!B7/'P&L'!B5) -> 0.40761205 | C7: =IF('P&L'!C5<=0,"n/a",'P&L'!C7/'P&L'!C5) -> 0.50051827 | D7: =IF('P&L'!D5<=0,"n/a",'P&L'!D7/'P&L'!D5) -> 0.50017252 | E7: =IF('P&L'!E5<=0,"n/a",'P&L'!E7/'P&L'!E5) -> 0.50017252 | F7: =IF('P&L'!F5<=0,"n/a",'P&L'!F7/'P&L'!F5) -> 0.50017252
A8: EBITDA margin | B8: =IF('P&L'!B5<=0,"n/a",'P&L'!B19/'P&L'!B5) -> -0.29985485 | C8: =IF('P&L'!C5<=0,"n/a",'P&L'!C19/'P&L'!C5) -> 0.074470458 | D8: =IF('P&L'!D5<=0,"n/a",'P&L'!D19/'P&L'!D5) -> 0.076961699 | E8: =IF('P&L'!E5<=0,"n/a",'P&L'!E19/'P&L'!E5) -> 0.080002386 | F8: =IF('P&L'!F5<=0,"n/a",'P&L'!F19/'P&L'!F5) -> 0.08295451
A9: Net margin | B9: =IF('P&L'!B5<=0,"n/a",'P&L'!B26/'P&L'!B5) -> -0.45081687 | C9: =IF('P&L'!C5<=0,"n/a",'P&L'!C26/'P&L'!C5) -> -0.011309428 | D9: =IF('P&L'!D5<=0,"n/a",'P&L'!D26/'P&L'!D5) -> -0.0049051282 | E9: =IF('P&L'!E5<=0,"n/a",'P&L'!E26/'P&L'!E5) -> 0.0019494129 | F9: =IF('P&L'!F5<=0,"n/a",'P&L'!F26/'P&L'!F5) -> 0.0085626746
A10: Payroll, % of revenue | B10: =IF('P&L'!B5<=0,"n/a",-SUMIF(Headcount!$C$5:$BJ$5,B$5,Headcount!$C$17:$BJ$17)/'P&L'!B5) -> 0.26151616 | C10: =IF('P&L'!C5<=0,"n/a",-SUMIF(Headcount!$C$5:$BJ$5,C$5,Headcount!$C$17:$BJ$17)/'P&L'!C5) -> 0.15574394 | D10: =IF('P&L'!D5<=0,"n/a",-SUMIF(Headcount!$C$5:$BJ$5,D$5,Headcount!$C$17:$BJ$17)/'P&L'!D5) -> 0.15585175 | E10: =IF('P&L'!E5<=0,"n/a",-SUMIF(Headcount!$C$5:$BJ$5,E$5,Headcount!$C$17:$BJ$17)/'P&L'!E5) -> 0.15585175 | F10: =IF('P&L'!F5<=0,"n/a",-SUMIF(Headcount!$C$5:$BJ$5,F$5,Headcount!$C$17:$BJ$17)/'P&L'!F5) -> 0.15585175
A11: Marketing, % of revenue | B11: =IF('P&L'!B5<=0,"n/a",-'P&L'!B14/'P&L'!B5) -> 0.071478543 | C11: =IF('P&L'!C5<=0,"n/a",-'P&L'!C14/'P&L'!C5) -> 0.041328639 | D11: =IF('P&L'!D5<=0,"n/a",-'P&L'!D14/'P&L'!D5) -> 0.040152667 | E11: =IF('P&L'!E5<=0,"n/a",-'P&L'!E14/'P&L'!E5) -> 0.038983172 | F11: =IF('P&L'!F5<=0,"n/a",-'P&L'!F14/'P&L'!F5) -> 0.03784774
A12: Operating expenses, % of revenue | B12: =IF('P&L'!B5<=0,"n/a",-'P&L'!B18/'P&L'!B5) -> 0.7074669 | C12: =IF('P&L'!C5<=0,"n/a",-'P&L'!C18/'P&L'!C5) -> 0.42604781 | D12: =IF('P&L'!D5<=0,"n/a",-'P&L'!D18/'P&L'!D5) -> 0.42321082 | E12: =IF('P&L'!E5<=0,"n/a",-'P&L'!E18/'P&L'!E5) -> 0.42017014 | F12: =IF('P&L'!F5<=0,"n/a",-'P&L'!F18/'P&L'!F5) -> 0.41721801
A13: Current ratio (current assets ÷ current liabilities) | B13: =IF(('Balance Sheet'!B12-'Balance Sheet'!B11)<=0,"n/a",('Balance Sheet'!B5+'Balance Sheet'!B6+'Balance Sheet'!B7)/('Balance Sheet'!B12-'Balance Sheet'!B11)) -> 9.481454 | C13: =IF(('Balance Sheet'!C12-'Balance Sheet'!C11)<=0,"n/a",('Balance Sheet'!C5+'Balance Sheet'!C6+'Balance Sheet'!C7)/('Balance Sheet'!C12-'Balance Sheet'!C11)) -> 9.3913388 | D13: =IF(('Balance Sheet'!D12-'Balance Sheet'!D11)<=0,"n/a",('Balance Sheet'!D5+'Balance Sheet'!D6+'Balance Sheet'!D7)/('Balance Sheet'!D12-'Balance Sheet'!D11)) -> 9.8773899 | E13: =IF(('Balance Sheet'!E12-'Balance Sheet'!E11)<=0,"n/a",('Balance Sheet'!E5+'Balance Sheet'!E6+'Balance Sheet'!E7)/('Balance Sheet'!E12-'Balance Sheet'!E11)) -> 10.844045 | F13: =IF(('Balance Sheet'!F12-'Balance Sheet'!F11)<=0,"n/a",('Balance Sheet'!F5+'Balance Sheet'!F6+'Balance Sheet'!F7)/('Balance Sheet'!F12-'Balance Sheet'!F11)) -> 12.257939
A14: Debt ÷ equity (loan ÷ total equity) | B14: =IF('Balance Sheet'!B15<=0,"n/a",'Balance Sheet'!B11/'Balance Sheet'!B15) -> 0.87075408 | C14: =IF('Balance Sheet'!C15<=0,"n/a",'Balance Sheet'!C11/'Balance Sheet'!C15) -> 0.80007687 | D14: =IF('Balance Sheet'!D15<=0,"n/a",'Balance Sheet'!D11/'Balance Sheet'!D15) -> 0.71142079 | E14: =IF('Balance Sheet'!E15<=0,"n/a",'Balance Sheet'!E11/'Balance Sheet'!E15) -> 0.60732461 | F14: =IF('Balance Sheet'!F15<=0,"n/a",'Balance Sheet'!F11/'Balance Sheet'!F15) -> 0.49409849
A15: Return on assets (net income ÷ year-end assets) | B15: =IF('Balance Sheet'!B9<=0,"n/a",'P&L'!B26/'Balance Sheet'!B9) -> -0.37956577 | C15: =IF('Balance Sheet'!C9<=0,"n/a",'P&L'!C26/'Balance Sheet'!C9) -> -0.017626483 | D15: =IF('Balance Sheet'!D9<=0,"n/a",'P&L'!D26/'Balance Sheet'!D9) -> -0.0083785585 | E15: =IF('Balance Sheet'!E9<=0,"n/a",'P&L'!E26/'Balance Sheet'!E9) -> 0.0036214592 | F15: =IF('Balance Sheet'!F9<=0,"n/a",'P&L'!F26/'Balance Sheet'!F9) -> 0.017122469
A16: Return on equity (net income ÷ year-end equity) | B16: =IF('Balance Sheet'!B15<=0,"n/a",'P&L'!B26/'Balance Sheet'!B15) -> -0.72553102 | C16: =IF('Balance Sheet'!C15<=0,"n/a",'P&L'!C26/'Balance Sheet'!C15) -> -0.032502144 | D16: =IF('Balance Sheet'!D15<=0,"n/a",'P&L'!D26/'Balance Sheet'!D15) -> -0.014723331 | E16: =IF('Balance Sheet'!E15<=0,"n/a",'P&L'!E26/'Balance Sheet'!E15) -> 0.0059908324 | F16: =IF('Balance Sheet'!F15<=0,"n/a",'P&L'!F26/'Balance Sheet'!F15) -> 0.026388559
A18: DuPont analysis — return on equity = net margin × asset turnover × equity multiplier
B19: 1 | C19: 2 | D19: 3 | E19: 4 | F19: 5
A20: Net margin | B20: =IF('P&L'!B5<=0,"n/a",'P&L'!B26/'P&L'!B5) -> -0.45081687 | C20: =IF('P&L'!C5<=0,"n/a",'P&L'!C26/'P&L'!C5) -> -0.011309428 | D20: =IF('P&L'!D5<=0,"n/a",'P&L'!D26/'P&L'!D5) -> -0.0049051282 | E20: =IF('P&L'!E5<=0,"n/a",'P&L'!E26/'P&L'!E5) -> 0.0019494129 | F20: =IF('P&L'!F5<=0,"n/a",'P&L'!F26/'P&L'!F5) -> 0.0085626746
A21: × Asset turnover (revenue ÷ assets) | B21: =IF('Balance Sheet'!B9<=0,"n/a",'P&L'!B5/'Balance Sheet'!B9) -> 0.84195112 | C21: =IF('Balance Sheet'!C9<=0,"n/a",'P&L'!C5/'Balance Sheet'!C9) -> 1.5585654 | D21: =IF('Balance Sheet'!D9<=0,"n/a",'P&L'!D5/'Balance Sheet'!D9) -> 1.7081222 | E21: =IF('Balance Sheet'!E9<=0,"n/a",'P&L'!E5/'Balance Sheet'!E9) -> 1.8577179 | F21: =IF('Balance Sheet'!F9<=0,"n/a",'P&L'!F5/'Balance Sheet'!F9) -> 1.9996637
A22: × Equity multiplier (assets ÷ equity) | B22: =IF('Balance Sheet'!B15<=0,"n/a",'Balance Sheet'!B9/'Balance Sheet'!B15) -> 1.9114764 | C22: =IF('Balance Sheet'!C15<=0,"n/a",'Balance Sheet'!C9/'Balance Sheet'!C15) -> 1.8439381 | D22: =IF('Balance Sheet'!D15<=0,"n/a",'Balance Sheet'!D9/'Balance Sheet'!D15) -> 1.7572631 | E22: =IF('Balance Sheet'!E15<=0,"n/a",'Balance Sheet'!E9/'Balance Sheet'!E15) -> 1.6542593 | F22: =IF('Balance Sheet'!F15<=0,"n/a",'Balance Sheet'!F9/'Balance Sheet'!F15) -> 1.5411655
A23: Return on equity (product of the three) | B23: =IF(AND(ISNUMBER(B20),ISNUMBER(B21),ISNUMBER(B22)),B20*B21*B22,"n/a") -> -0.72553102 | C23: =IF(AND(ISNUMBER(C20),ISNUMBER(C21),ISNUMBER(C22)),C20*C21*C22,"n/a") -> -0.032502144 | D23: =IF(AND(ISNUMBER(D20),ISNUMBER(D21),ISNUMBER(D22)),D20*D21*D22,"n/a") -> -0.014723331 | E23: =IF(AND(ISNUMBER(E20),ISNUMBER(E21),ISNUMBER(E22)),E20*E21*E22,"n/a") -> 0.0059908324 | F23: =IF(AND(ISNUMBER(F20),ISNUMBER(F21),ISNUMBER(F22)),F20*F21*F22,"n/a") -> 0.026388559
A24: Check: product − return on equity (must be 0) | B24: =IF(AND(ISNUMBER(B23),ISNUMBER(B16)),B23-B16,IF(ISNUMBER(B23),1,IF(AND(ISNUMBER(B16),ISNUMBER(B20),ISNUMBER(B21)),1,0))) -> 0 | C24: =IF(AND(ISNUMBER(C23),ISNUMBER(C16)),C23-C16,IF(ISNUMBER(C23),1,IF(AND(ISNUMBER(C16),ISNUMBER(C20),ISNUMBER(C21)),1,0))) -> 0 | D24: =IF(AND(ISNUMBER(D23),ISNUMBER(D16)),D23-D16,IF(ISNUMBER(D23),1,IF(AND(ISNUMBER(D16),ISNUMBER(D20),ISNUMBER(D21)),1,0))) -> 0 | E24: =IF(AND(ISNUMBER(E23),ISNUMBER(E16)),E23-E16,IF(ISNUMBER(E23),1,IF(AND(ISNUMBER(E16),ISNUMBER(E20),ISNUMBER(E21)),1,0))) -> 0 | F24: =IF(AND(ISNUMBER(F23),ISNUMBER(F16)),F23-F16,IF(ISNUMBER(F23),1,IF(AND(ISNUMBER(F16),ISNUMBER(F20),ISNUMBER(F21)),1,0))) -> 0
A26: Childcare metrics ($'000; per-unit rows in $)
A27: Year # | B27: 1 | C27: 2 | D27: 3 | E27: 4 | F27: 5
B28: Year 1 | C28: Year 2 | D28: Year 3 | E28: Year 4 | F28: Year 5 | G28: Target
A29: Licensed places (year end) | B29: =INDEX(Monthly!$C$8:$BJ$8,B$27*12) -> 60 | C29: =INDEX(Monthly!$C$8:$BJ$8,C$27*12) -> 60 | D29: =INDEX(Monthly!$C$8:$BJ$8,D$27*12) -> 60 | E29: =INDEX(Monthly!$C$8:$BJ$8,E$27*12) -> 60 | F29: =INDEX(Monthly!$C$8:$BJ$8,F$27*12) -> 60
A30: Children enrolled (year end) | B30: =INDEX(Monthly!$C$18:$BJ$18,B$27*12) -> 47.75 | C30: =INDEX(Monthly!$C$18:$BJ$18,C$27*12) -> 51 | D30: =INDEX(Monthly!$C$18:$BJ$18,D$27*12) -> 51 | E30: =INDEX(Monthly!$C$18:$BJ$18,E$27*12) -> 51 | F30: =INDEX(Monthly!$C$18:$BJ$18,F$27*12) -> 51
A31: Licensed place-months | B31: =SUMIF(Monthly!$C$5:$BJ$5,B$27,Monthly!$C$17:$BJ$17) -> 720 | C31: =SUMIF(Monthly!$C$5:$BJ$5,C$27,Monthly!$C$17:$BJ$17) -> 720 | D31: =SUMIF(Monthly!$C$5:$BJ$5,D$27,Monthly!$C$17:$BJ$17) -> 720 | E31: =SUMIF(Monthly!$C$5:$BJ$5,E$27,Monthly!$C$17:$BJ$17) -> 720 | F31: =SUMIF(Monthly!$C$5:$BJ$5,F$27,Monthly!$C$17:$BJ$17) -> 720
A32: Child-months enrolled | B32: =SUMIF(Monthly!$C$5:$BJ$5,B$27,Monthly!$C$16:$BJ$16) -> 358.5 | C32: =SUMIF(Monthly!$C$5:$BJ$5,C$27,Monthly!$C$16:$BJ$16) -> 612 | D32: =SUMIF(Monthly!$C$5:$BJ$5,D$27,Monthly!$C$16:$BJ$16) -> 612 | E32: =SUMIF(Monthly!$C$5:$BJ$5,E$27,Monthly!$C$16:$BJ$16) -> 612 | F32: =SUMIF(Monthly!$C$5:$BJ$5,F$27,Monthly!$C$16:$BJ$16) -> 612
A33: Occupancy (child-months ÷ licensed place-months) | B33: =IF(B31=0,0,B32/B31) -> 0.49791667 | C33: =IF(C31=0,0,C32/C31) -> 0.85 | D33: =IF(D31=0,0,D32/D31) -> 0.85 | E33: =IF(E31=0,0,E32/E31) -> 0.85 | F33: =IF(F31=0,0,F32/F31) -> 0.85
A34: New children enrolled | B34: =SUMIF(Monthly!$C$5:$BJ$5,B$27,Monthly!$C$19:$BJ$19) -> 56.7125 | C34: =SUMIF(Monthly!$C$5:$BJ$5,C$27,Monthly!$C$19:$BJ$19) -> 18.55 | D34: =SUMIF(Monthly!$C$5:$BJ$5,D$27,Monthly!$C$19:$BJ$19) -> 15.3 | E34: =SUMIF(Monthly!$C$5:$BJ$5,E$27,Monthly!$C$19:$BJ$19) -> 15.3 | F34: =SUMIF(Monthly!$C$5:$BJ$5,F$27,Monthly!$C$19:$BJ$19) -> 15.3
A35: Teachers on the floor (year end) | B35: =INDEX(Monthly!$C$24:$BJ$24,B$27*12) -> 6 | C35: =INDEX(Monthly!$C$24:$BJ$24,C$27*12) -> 6 | D35: =INDEX(Monthly!$C$24:$BJ$24,D$27*12) -> 6 | E35: =INDEX(Monthly!$C$24:$BJ$24,E$27*12) -> 6 | F35: =INDEX(Monthly!$C$24:$BJ$24,F$27*12) -> 6
A36: Revenue | B36: =SUMIF(Monthly!$C$5:$BJ$5,B$27,Monthly!$C$32:$BJ$32) -> 419706.38 | C36: =SUMIF(Monthly!$C$5:$BJ$5,C$27,Monthly!$C$32:$BJ$32) -> 725888.9 | D36: =SUMIF(Monthly!$C$5:$BJ$5,D$27,Monthly!$C$32:$BJ$32) -> 747148.37 | E36: =SUMIF(Monthly!$C$5:$BJ$5,E$27,Monthly!$C$32:$BJ$32) -> 769562.82 | F36: =SUMIF(Monthly!$C$5:$BJ$5,F$27,Monthly!$C$32:$BJ$32) -> 792649.71
A37: Parent-paid tuition | B37: =SUMIF(Monthly!$C$5:$BJ$5,B$27,Monthly!$C$29:$BJ$29) -> 316734.75 | C37: =SUMIF(Monthly!$C$5:$BJ$5,C$27,Monthly!$C$29:$BJ$29) -> 556923.06 | D37: =SUMIF(Monthly!$C$5:$BJ$5,D$27,Monthly!$C$29:$BJ$29) -> 573630.75 | E37: =SUMIF(Monthly!$C$5:$BJ$5,E$27,Monthly!$C$29:$BJ$29) -> 590839.67 | F37: =SUMIF(Monthly!$C$5:$BJ$5,F$27,Monthly!$C$29:$BJ$29) -> 608564.86
A38: Subsidy & voucher payments | B38: =SUMIF(Monthly!$C$5:$BJ$5,B$27,Monthly!$C$30:$BJ$30) -> 94464.75 | C38: =SUMIF(Monthly!$C$5:$BJ$5,C$27,Monthly!$C$30:$BJ$30) -> 166099.86 | D38: =SUMIF(Monthly!$C$5:$BJ$5,D$27,Monthly!$C$30:$BJ$30) -> 171082.86 | E38: =SUMIF(Monthly!$C$5:$BJ$5,E$27,Monthly!$C$30:$BJ$30) -> 176215.34 | F38: =SUMIF(Monthly!$C$5:$BJ$5,F$27,Monthly!$C$30:$BJ$30) -> 181501.8
A39: Subsidy & vouchers, % of tuition revenue | B39: =IF(B37+B38=0,0,B38/(B37+B38)) -> 0.22972973 | C39: =IF(C37+C38=0,0,C38/(C37+C38)) -> 0.22972973 | D39: =IF(D37+D38=0,0,D38/(D37+D38)) -> 0.22972973 | E39: =IF(E37+E38=0,0,E38/(E37+E38)) -> 0.22972973 | F39: =IF(F37+F38=0,0,F38/(F37+F38)) -> 0.22972973
A40: Registration fees | B40: =SUMIF(Monthly!$C$5:$BJ$5,B$27,Monthly!$C$31:$BJ$31) -> 8506.875 | C40: =SUMIF(Monthly!$C$5:$BJ$5,C$27,Monthly!$C$31:$BJ$31) -> 2865.975 | D40: =SUMIF(Monthly!$C$5:$BJ$5,D$27,Monthly!$C$31:$BJ$31) -> 2434.7655 | E40: =SUMIF(Monthly!$C$5:$BJ$5,E$27,Monthly!$C$31:$BJ$31) -> 2507.8085 | F40: =SUMIF(Monthly!$C$5:$BJ$5,F$27,Monthly!$C$31:$BJ$31) -> 2583.0427
A41: Tuition revenue per child-month ($) | B41: =IF(B32=0,0,(B37+B38)/B32) -> 1147 | C41: =IF(C32=0,0,(C37+C38)/C32) -> 1181.41 | D41: =IF(D32=0,0,(D37+D38)/D32) -> 1216.8523 | E41: =IF(E32=0,0,(E37+E38)/E32) -> 1253.3579 | F41: =IF(F32=0,0,(F37+F38)/F32) -> 1290.9586
A42: Teacher payroll (with payroll taxes) | B42: =SUMIF(Monthly!$C$5:$BJ$5,B$27,Monthly!$C$35:$BJ$35) -> -207760 | C42: =SUMIF(Monthly!$C$5:$BJ$5,C$27,Monthly!$C$35:$BJ$35) -> -290707.2 | D42: =SUMIF(Monthly!$C$5:$BJ$5,D$27,Monthly!$C$35:$BJ$35) -> -299428.42 | E42: =SUMIF(Monthly!$C$5:$BJ$5,E$27,Monthly!$C$35:$BJ$35) -> -308411.27 | F42: =SUMIF(Monthly!$C$5:$BJ$5,F$27,Monthly!$C$35:$BJ$35) -> -317663.61
A43: Teacher payroll, % of revenue | B43: =IF(B36=0,0,-B42/B36) -> 0.49501273 | C43: =IF(C36=0,0,-C42/C36) -> 0.40048443 | D43: =IF(D36=0,0,-D42/D36) -> 0.40076165 | E43: =IF(E36=0,0,-E42/E36) -> 0.40076165 | F43: =IF(F36=0,0,-F42/F36) -> 0.40076165
A44: Gross profit | B44: =SUMIF(Monthly!$C$5:$BJ$5,B$27,Monthly!$C$39:$BJ$39) -> 171077.38 | C44: =SUMIF(Monthly!$C$5:$BJ$5,C$27,Monthly!$C$39:$BJ$39) -> 363320.66 | D44: =SUMIF(Monthly!$C$5:$BJ$5,D$27,Monthly!$C$39:$BJ$39) -> 373703.09 | E44: =SUMIF(Monthly!$C$5:$BJ$5,E$27,Monthly!$C$39:$BJ$39) -> 384914.18 | F44: =SUMIF(Monthly!$C$5:$BJ$5,F$27,Monthly!$C$39:$BJ$39) -> 396461.6
A45: Gross margin | B45: =IF(B36=0,0,B44/B36) -> 0.40761205 | C45: =IF(C36=0,0,C44/C36) -> 0.50051827 | D45: =IF(D36=0,0,D44/D36) -> 0.50017252 | E45: =IF(E36=0,0,E44/E36) -> 0.50017252 | F45: =IF(F36=0,0,F44/F36) -> 0.50017252
A46: EBITDA | B46: =SUMIF(Monthly!$C$5:$BJ$5,B$27,Monthly!$C$52:$BJ$52) -> -125850.99 | C46: =SUMIF(Monthly!$C$5:$BJ$5,C$27,Monthly!$C$52:$BJ$52) -> 54057.278 | D46: =SUMIF(Monthly!$C$5:$BJ$5,D$27,Monthly!$C$52:$BJ$52) -> 57501.808 | E46: =SUMIF(Monthly!$C$5:$BJ$5,E$27,Monthly!$C$52:$BJ$52) -> 61566.862 | F46: =SUMIF(Monthly!$C$5:$BJ$5,F$27,Monthly!$C$52:$BJ$52) -> 65753.868
A47: EBITDA margin | B47: =IF(B36=0,0,B46/B36) -> -0.29985485 | C47: =IF(C36=0,0,C46/C36) -> 0.074470458 | D47: =IF(D36=0,0,D46/D36) -> 0.076961699 | E47: =IF(E36=0,0,E46/E36) -> 0.080002386 | F47: =IF(F36=0,0,F46/F36) -> 0.08295451

Sheet Inputs
A1: Inputs — Low / Base / High | I1: =HYPERLINK("#'Cover'!A1","◂ Contents") -> ◂ Contents
A2: Illustrative assumptions — replace them with your own numbers.
A5: Driver | B5: Low | C5: Base | D5: High | E5: Active | F5: Unit | G5: Source / comment
A6: Places & enrolment
A7: Licensed places (children) at start | B7: 60 | C7: 60 | D7: 60 | E7: =CHOOSE(Dashboard!$B$4,B7,C7,D7) -> 60 | F7: #
A8: Licensed places added each year (from year 2) | B8: 0 | C8: 0 | D8: 0 | E8: =CHOOSE(Dashboard!$B$4,B8,C8,D8) -> 0 | F8: # | G8: Low ≤ Base ≤ High
A9: Places for infants & toddlers, % of licensed places | B9: 0.35 | C9: 0.35 | D9: 0.35 | E9: =CHOOSE(Dashboard!$B$4,B9,C9,D9) -> 0.35 | F9: %
A10: Enrolment once full, % of licensed places | B10: 0.78 | C10: 0.85 | D10: 0.9 | E10: =CHOOSE(Dashboard!$B$4,B10,C10,D10) -> 0.85 | F10: % | G10: Low ≤ Base ≤ High
A11: Enrolment in month 1, % of licensed places | B11: 0.15 | C11: 0.2 | D11: 0.25 | E11: =CHOOSE(Dashboard!$B$4,B11,C11,D11) -> 0.2 | F11: % | G11: Low ≤ Base ≤ High
A12: Months to reach full enrolment | B12: 18 | C12: 12 | D12: 9 | E12: =CHOOSE(Dashboard!$B$4,B12,C12,D12) -> 12 | F12: months | G12: Low ≥ Base ≥ High (lower is better)
A13: Operating days per month | B13: 21 | C13: 21 | D13: 21 | E13: =CHOOSE(Dashboard!$B$4,B13,C13,D13) -> 21 | F13: days
A14: Children leaving each year, % of enrolled (replaced by new) | B14: 0.35 | C14: 0.3 | D14: 0.25 | E14: =CHOOSE(Dashboard!$B$4,B14,C14,D14) -> 0.3 | F14: % | G14: Low ≥ Base ≥ High (lower is better)
A16: Tuition & fees
A17: Tuition per infant / toddler per month (year 1) | B17: 1430 | C17: 1500 | D17: 1570 | E17: =CHOOSE(Dashboard!$B$4,B17,C17,D17) -> 1500 | F17: $ | G17: Low ≤ Base ≤ High
A18: Tuition per preschooler per month (year 1) | B18: 1040 | C18: 1100 | D18: 1160 | E18: =CHOOSE(Dashboard!$B$4,B18,C18,D18) -> 1100 | F18: $ | G18: Low ≤ Base ≤ High
A19: Tuition and fee increase per year | B19: 0.025 | C19: 0.03 | D19: 0.04 | E19: =CHOOSE(Dashboard!$B$4,B19,C19,D19) -> 0.03 | F19: % | G19: Low ≤ Base ≤ High
A20: Sibling & staff discounts, % of parent-paid tuition | B20: 0.06 | C20: 0.05 | D20: 0.04 | E20: =CHOOSE(Dashboard!$B$4,B20,C20,D20) -> 0.05 | F20: % | G20: Low ≥ Base ≥ High (lower is better)
A21: Registration fee per new child (year 1) | B21: 100 | C21: 150 | D21: 200 | E21: =CHOOSE(Dashboard!$B$4,B21,C21,D21) -> 150 | F21: $ | G21: Low ≤ Base ≤ High
A22: Children paid by subsidy / vouchers, % of enrolled | B22: 0.25 | C22: 0.25 | D22: 0.25 | E22: =CHOOSE(Dashboard!$B$4,B22,C22,D22) -> 0.25 | F22: %
A23: Subsidy payment, % of the list tuition | B23: 0.82 | C23: 0.85 | D23: 0.88 | E23: =CHOOSE(Dashboard!$B$4,B23,C23,D23) -> 0.85 | F23: % | G23: Low ≤ Base ≤ High
A25: Staffing by ratio
A26: Children per teacher, infants & toddlers | B26: 6 | C26: 6 | D26: 6 | E26: =CHOOSE(Dashboard!$B$4,B26,C26,D26) -> 6 | F26: #
A27: Children per teacher, preschool | B27: 12 | C27: 12 | D27: 12 | E27: =CHOOSE(Dashboard!$B$4,B27,C27,D27) -> 12 | F27: #
A28: Coverage factor (teachers hired per teacher on the floor) | B28: 1.25 | C28: 1.2 | D28: 1.15 | E28: =CHOOSE(Dashboard!$B$4,B28,C28,D28) -> 1.2 | F28: x | G28: Low ≥ Base ≥ High (lower is better)
A29: Teacher salary per FTE per year (year 1) | B29: 36500 | C29: 35000 | D29: 33500 | E29: =CHOOSE(Dashboard!$B$4,B29,C29,D29) -> 35000 | F29: $ | G29: Low ≥ Base ≥ High (lower is better)
A31: Cost of sales
A32: Food per child per operating day (year 1) | B32: 4.2 | C32: 4 | D32: 3.8 | E32: =CHOOSE(Dashboard!$B$4,B32,C32,D32) -> 4 | F32: $ | G32: Low ≥ Base ≥ High (lower is better)
A33: Supplies & activities per child per month (year 1) | B33: 33 | C33: 30 | D33: 27 | E33: =CHOOSE(Dashboard!$B$4,B33,C33,D33) -> 30 | F33: $ | G33: Low ≥ Base ≥ High (lower is better)
A34: Food, supplies & utilities cost increase per year | B34: 0.03 | C34: 0.03 | D34: 0.03 | E34: =CHOOSE(Dashboard!$B$4,B34,C34,D34) -> 0.03 | F34: %
A36: Operating costs
A37: Floor area per licensed place | B37: 75 | C37: 75 | D37: 75 | E37: =CHOOSE(Dashboard!$B$4,B37,C37,D37) -> 75 | F37: sq ft
A38: Rent per square foot per year (year 1) | B38: 17 | C38: 16 | D38: 15 | E38: =CHOOSE(Dashboard!$B$4,B38,C38,D38) -> 16 | F38: $ | G38: Low ≥ Base ≥ High (lower is better)
A39: Rent increase per year | B39: 0.03 | C39: 0.03 | D39: 0.03 | E39: =CHOOSE(Dashboard!$B$4,B39,C39,D39) -> 0.03 | F39: %
A40: Utilities & cleaning per square foot per year (year 1) | B40: 6.8 | C40: 6.5 | D40: 6.2 | E40: =CHOOSE(Dashboard!$B$4,B40,C40,D40) -> 6.5 | F40: $ | G40: Low ≥ Base ≥ High (lower is better)
A41: Insurance per month | B41: 1800 | C41: 1800 | D41: 1800 | E41: =CHOOSE(Dashboard!$B$4,B41,C41,D41) -> 1800 | F41: $
A42: Licensing, background checks & training per month | B42: 600 | C42: 600 | D42: 600 | E42: =CHOOSE(Dashboard!$B$4,B42,C42,D42) -> 600 | F42: $
A43: Marketing budget per month (year 1) | B43: 2500 | C43: 2500 | D43: 2500 | E43: =CHOOSE(Dashboard!$B$4,B43,C43,D43) -> 2500 | F43: $
A44: Marketing budget growth per year | B44: 0 | C44: 0 | D44: 0 | E44: =CHOOSE(Dashboard!$B$4,B44,C44,D44) -> 0 | F44: %
A45: Parent app & management software per month | B45: 400 | C45: 400 | D45: 400 | E45: =CHOOSE(Dashboard!$B$4,B45,C45,D45) -> 400 | F45: $
A46: Card / ACH fees, % of parent-paid tuition | B46: 0.028 | C46: 0.025 | D46: 0.022 | E46: =CHOOSE(Dashboard!$B$4,B46,C46,D46) -> 0.025 | F46: % | G46: Low ≥ Base ≥ High (lower is better)
A47: Other G&A per month (accounting, legal, bank) | B47: 1200 | C47: 1200 | D47: 1200 | E47: =CHOOSE(Dashboard!$B$4,B47,C47,D47) -> 1200 | F47: $
A49: Capex
A50: Build-out per square foot (new places) | B50: 60 | C50: 60 | D50: 60 | E50: =CHOOSE(Dashboard!$B$4,B50,C50,D50) -> 60 | F50: $
A51: Furniture & equipment per licensed place | B51: 2200 | C51: 2200 | D51: 2200 | E51: =CHOOSE(Dashboard!$B$4,B51,C51,D51) -> 2200 | F51: $
A52: Places already built out and equipped at start | B52: 0 | C52: 0 | D52: 0 | E52: =CHOOSE(Dashboard!$B$4,B52,C52,D52) -> 0 | F52: #
A53: Playground & outdoor area (month 1) | B53: 40000 | C53: 40000 | D53: 40000 | E53: =CHOOSE(Dashboard!$B$4,B53,C53,D53) -> 40000 | F53: $
A54: Equipment replacement per licensed place per year (from year 2) | B54: 150 | C54: 150 | D54: 150 | E54: =CHOOSE(Dashboard!$B$4,B54,C54,D54) -> 150 | F54: $
A56: Headcount
A57: Centre director: headcount (FTE) | B57: 1 | C57: 1 | D57: 1 | E57: =CHOOSE(Dashboard!$B$4,B57,C57,D57) -> 1 | F57: FTE | G57: Low ≤ Base ≤ High
A58: Centre director: salary per FTE per year | B58: 62000 | C58: 62000 | D58: 62000 | E58: =CHOOSE(Dashboard!$B$4,B58,C58,D58) -> 62000 | F58: $
A59: Centre director: headcount growth per year | B59: 0 | C59: 0 | D59: 0 | E59: =CHOOSE(Dashboard!$B$4,B59,C59,D59) -> 0 | F59: % | G59: Low ≤ Base ≤ High
A60: Centre director: first month on payroll | B60: 1 | C60: 1 | D60: 1 | E60: =CHOOSE(Dashboard!$B$4,B60,C60,D60) -> 1 | F60: month #
A61: Office & enrolment coordinator: headcount (FTE) | B61: 0.5 | C61: 0.5 | D61: 0.5 | E61: =CHOOSE(Dashboard!$B$4,B61,C61,D61) -> 0.5 | F61: FTE | G61: Low ≤ Base ≤ High
A62: Office & enrolment coordinator: salary per FTE per year | B62: 38000 | C62: 38000 | D62: 38000 | E62: =CHOOSE(Dashboard!$B$4,B62,C62,D62) -> 38000 | F62: $
A63: Office & enrolment coordinator: headcount growth per year | B63: 0 | C63: 0 | D63: 0 | E63: =CHOOSE(Dashboard!$B$4,B63,C63,D63) -> 0 | F63: % | G63: Low ≤ Base ≤ High
A64: Office & enrolment coordinator: first month on payroll | B64: 1 | C64: 1 | D64: 1 | E64: =CHOOSE(Dashboard!$B$4,B64,C64,D64) -> 1 | F64: month #
A65: Cook / kitchen assistant: headcount (FTE) | B65: 0.5 | C65: 0.5 | D65: 0.5 | E65: =CHOOSE(Dashboard!$B$4,B65,C65,D65) -> 0.5 | F65: FTE | G65: Low ≤ Base ≤ High
A66: Cook / kitchen assistant: salary per FTE per year | B66: 34000 | C66: 34000 | D66: 34000 | E66: =CHOOSE(Dashboard!$B$4,B66,C66,D66) -> 34000 | F66: $
A67: Cook / kitchen assistant: headcount growth per year | B67: 0 | C67: 0 | D67: 0 | E67: =CHOOSE(Dashboard!$B$4,B67,C67,D67) -> 0 | F67: % | G67: Low ≤ Base ≤ High
A68: Cook / kitchen assistant: first month on payroll | B68: 1 | C68: 1 | D68: 1 | E68: =CHOOSE(Dashboard!$B$4,B68,C68,D68) -> 1 | F68: month #
A69: Payroll taxes & benefits, % of salary | B69: 0.12 | C69: 0.12 | D69: 0.12 | E69: =CHOOSE(Dashboard!$B$4,B69,C69,D69) -> 0.12 | F69: %
A70: Wage growth per year | B70: 0.03 | C70: 0.03 | D70: 0.03 | E70: =CHOOSE(Dashboard!$B$4,B70,C70,D70) -> 0.03 | F70: %
A72: Funding
A73: Equity raised at start | B73: 450000 | C73: 450000 | D73: 450000 | E73: =CHOOSE(Dashboard!$B$4,B73,C73,D73) -> 450000 | F73: $
A74: Loan drawn at start | B74: 250000 | C74: 250000 | D74: 250000 | E74: =CHOOSE(Dashboard!$B$4,B74,C74,D74) -> 250000 | F74: $
A75: Loan interest rate per year | B75: 0.08 | C75: 0.08 | D75: 0.08 | E75: =CHOOSE(Dashboard!$B$4,B75,C75,D75) -> 0.08 | F75: %
A76: Loan repayment term | B76: 10 | C76: 10 | D76: 10 | E76: =CHOOSE(Dashboard!$B$4,B76,C76,D76) -> 10 | F76: years
A78: Working capital
A79: Customer payment terms (receivable days) | B79: 13 | C79: 13 | D79: 13 | E79: =CHOOSE(Dashboard!$B$4,B79,C79,D79) -> 13 | F79: days
A80: Inventory held (days of COGS) | B80: 3 | C80: 3 | D80: 3 | E80: =CHOOSE(Dashboard!$B$4,B80,C80,D80) -> 3 | F80: days
A81: Supplier payment terms (payable days) | B81: 11 | C81: 11 | D81: 11 | E81: =CHOOSE(Dashboard!$B$4,B81,C81,D81) -> 11 | F81: days
A83: Tax & depreciation
A84: Depreciation period for capex | B84: 10 | C84: 10 | D84: 10 | E84: =CHOOSE(Dashboard!$B$4,B84,C84,D84) -> 10 | F84: years
A85: Income tax rate | B85: 0.21 | C85: 0.21 | D85: 0.21 | E85: =CHOOSE(Dashboard!$B$4,B85,C85,D85) -> 0.21 | F85: %
A87: Break-even & funding
A88: Minimum cash buffer to keep | B88: 74000 | C88: 74000 | D88: 74000 | E88: =CHOOSE(Dashboard!$B$4,B88,C88,D88) -> 74000 | F88: $ | G88: About 3 months of costs
A90: Valuation
A91: Discount rate (WACC) | B91: 0.3 | C91: 0.25 | D91: 0.2 | E91: =CHOOSE(Dashboard!$B$4,B91,C91,D91) -> 0.25 | F91: % | G91: Low ≥ Base ≥ High (lower is better)
A92: Terminal growth rate (perpetuity) | B92: 0.01 | C92: 0.02 | D92: 0.03 | E92: =CHOOSE(Dashboard!$B$4,B92,C92,D92) -> 0.02 | F92: % | G92: Low ≤ Base ≤ High
A93: Exit multiple (EV ÷ final-year EBITDA) | B93: 3 | C93: 4 | D93: 5 | E93: =CHOOSE(Dashboard!$B$4,B93,C93,D93) -> 4 | F93: x | G93: Low ≤ Base ≤ High
A94: Sensitivity table: WACC step | B94: 0.01 | C94: 0.01 | D94: 0.01 | E94: =CHOOSE(Dashboard!$B$4,B94,C94,D94) -> 0.01 | F94: %
A95: Sensitivity table: growth step | B95: 0.005 | C95: 0.005 | D95: 0.005 | E95: =CHOOSE(Dashboard!$B$4,B95,C95,D95) -> 0.005 | F95: %
A97: Legend: yellow cell with blue figure = input you can change · black = formula · green = link to another sheet · grey = active value (column E follows the scenario on the Dashboard).

Sheet P&L
A1: Annual profit & loss | H1: =HYPERLINK("#'Cover'!A1","◂ Contents") -> ◂ Contents
A2: Rolled up from the period detail (SUMIF on the year row; balances at year end).
A3: Year # | B3: 1 | C3: 2 | D3: 3 | E3: 4 | F3: 5
B4: Year 1 | C4: Year 2 | D4: Year 3 | E4: Year 4 | F4: Year 5
A5: Revenue | B5: =SUMIF(Monthly!$C$5:$BJ$5,B$3,Monthly!$C$32:$BJ$32) -> 419706.38 | C5: =SUMIF(Monthly!$C$5:$BJ$5,C$3,Monthly!$C$32:$BJ$32) -> 725888.9 | D5: =SUMIF(Monthly!$C$5:$BJ$5,D$3,Monthly!$C$32:$BJ$32) -> 747148.37 | E5: =SUMIF(Monthly!$C$5:$BJ$5,E$3,Monthly!$C$32:$BJ$32) -> 769562.82 | F5: =SUMIF(Monthly!$C$5:$BJ$5,F$3,Monthly!$C$32:$BJ$32) -> 792649.71
A6: Cost of sales | B6: =SUMIF(Monthly!$C$5:$BJ$5,B$3,Monthly!$C$38:$BJ$38) -> -248629 | C6: =SUMIF(Monthly!$C$5:$BJ$5,C$3,Monthly!$C$38:$BJ$38) -> -362568.24 | D6: =SUMIF(Monthly!$C$5:$BJ$5,D$3,Monthly!$C$38:$BJ$38) -> -373445.29 | E6: =SUMIF(Monthly!$C$5:$BJ$5,E$3,Monthly!$C$38:$BJ$38) -> -384648.65 | F6: =SUMIF(Monthly!$C$5:$BJ$5,F$3,Monthly!$C$38:$BJ$38) -> -396188.11
A7: Gross profit | B7: =SUMIF(Monthly!$C$5:$BJ$5,B$3,Monthly!$C$39:$BJ$39) -> 171077.38 | C7: =SUMIF(Monthly!$C$5:$BJ$5,C$3,Monthly!$C$39:$BJ$39) -> 363320.66 | D7: =SUMIF(Monthly!$C$5:$BJ$5,D$3,Monthly!$C$39:$BJ$39) -> 373703.09 | E7: =SUMIF(Monthly!$C$5:$BJ$5,E$3,Monthly!$C$39:$BJ$39) -> 384914.18 | F7: =SUMIF(Monthly!$C$5:$BJ$5,F$3,Monthly!$C$39:$BJ$39) -> 396461.6
A8: Gross margin | B8: =IF(B5=0,0,B7/B5) -> 0.40761205 | C8: =IF(C5=0,0,C7/C5) -> 0.50051827 | D8: =IF(D5=0,0,D7/D5) -> 0.50017252 | E8: =IF(E5=0,0,E7/E5) -> 0.50017252 | F8: =IF(F5=0,0,F7/F5) -> 0.50017252
A9: Staff payroll (director, office, kitchen) | B9: =SUMIF(Monthly!$C$5:$BJ$5,B$3,Monthly!$C$42:$BJ$42) -> -109760 | C9: =SUMIF(Monthly!$C$5:$BJ$5,C$3,Monthly!$C$42:$BJ$42) -> -113052.8 | D9: =SUMIF(Monthly!$C$5:$BJ$5,D$3,Monthly!$C$42:$BJ$42) -> -116444.38 | E9: =SUMIF(Monthly!$C$5:$BJ$5,E$3,Monthly!$C$42:$BJ$42) -> -119937.72 | F9: =SUMIF(Monthly!$C$5:$BJ$5,F$3,Monthly!$C$42:$BJ$42) -> -123535.85
A10: Rent | B10: =SUMIF(Monthly!$C$5:$BJ$5,B$3,Monthly!$C$43:$BJ$43) -> -72000 | C10: =SUMIF(Monthly!$C$5:$BJ$5,C$3,Monthly!$C$43:$BJ$43) -> -74160 | D10: =SUMIF(Monthly!$C$5:$BJ$5,D$3,Monthly!$C$43:$BJ$43) -> -76384.8 | E10: =SUMIF(Monthly!$C$5:$BJ$5,E$3,Monthly!$C$43:$BJ$43) -> -78676.344 | F10: =SUMIF(Monthly!$C$5:$BJ$5,F$3,Monthly!$C$43:$BJ$43) -> -81036.634
A11: Utilities & cleaning | B11: =SUMIF(Monthly!$C$5:$BJ$5,B$3,Monthly!$C$44:$BJ$44) -> -29250 | C11: =SUMIF(Monthly!$C$5:$BJ$5,C$3,Monthly!$C$44:$BJ$44) -> -30127.5 | D11: =SUMIF(Monthly!$C$5:$BJ$5,D$3,Monthly!$C$44:$BJ$44) -> -31031.325 | E11: =SUMIF(Monthly!$C$5:$BJ$5,E$3,Monthly!$C$44:$BJ$44) -> -31962.265 | F11: =SUMIF(Monthly!$C$5:$BJ$5,F$3,Monthly!$C$44:$BJ$44) -> -32921.133
A12: Insurance | B12: =SUMIF(Monthly!$C$5:$BJ$5,B$3,Monthly!$C$45:$BJ$45) -> -21600 | C12: =SUMIF(Monthly!$C$5:$BJ$5,C$3,Monthly!$C$45:$BJ$45) -> -21600 | D12: =SUMIF(Monthly!$C$5:$BJ$5,D$3,Monthly!$C$45:$BJ$45) -> -21600 | E12: =SUMIF(Monthly!$C$5:$BJ$5,E$3,Monthly!$C$45:$BJ$45) -> -21600 | F12: =SUMIF(Monthly!$C$5:$BJ$5,F$3,Monthly!$C$45:$BJ$45) -> -21600
A13: Licensing, background checks & training | B13: =SUMIF(Monthly!$C$5:$BJ$5,B$3,Monthly!$C$46:$BJ$46) -> -7200 | C13: =SUMIF(Monthly!$C$5:$BJ$5,C$3,Monthly!$C$46:$BJ$46) -> -7200 | D13: =SUMIF(Monthly!$C$5:$BJ$5,D$3,Monthly!$C$46:$BJ$46) -> -7200 | E13: =SUMIF(Monthly!$C$5:$BJ$5,E$3,Monthly!$C$46:$BJ$46) -> -7200 | F13: =SUMIF(Monthly!$C$5:$BJ$5,F$3,Monthly!$C$46:$BJ$46) -> -7200
A14: Marketing | B14: =SUMIF(Monthly!$C$5:$BJ$5,B$3,Monthly!$C$47:$BJ$47) -> -30000 | C14: =SUMIF(Monthly!$C$5:$BJ$5,C$3,Monthly!$C$47:$BJ$47) -> -30000 | D14: =SUMIF(Monthly!$C$5:$BJ$5,D$3,Monthly!$C$47:$BJ$47) -> -30000 | E14: =SUMIF(Monthly!$C$5:$BJ$5,E$3,Monthly!$C$47:$BJ$47) -> -30000 | F14: =SUMIF(Monthly!$C$5:$BJ$5,F$3,Monthly!$C$47:$BJ$47) -> -30000
A15: Parent app & management software | B15: =SUMIF(Monthly!$C$5:$BJ$5,B$3,Monthly!$C$48:$BJ$48) -> -4800 | C15: =SUMIF(Monthly!$C$5:$BJ$5,C$3,Monthly!$C$48:$BJ$48) -> -4800 | D15: =SUMIF(Monthly!$C$5:$BJ$5,D$3,Monthly!$C$48:$BJ$48) -> -4800 | E15: =SUMIF(Monthly!$C$5:$BJ$5,E$3,Monthly!$C$48:$BJ$48) -> -4800 | F15: =SUMIF(Monthly!$C$5:$BJ$5,F$3,Monthly!$C$48:$BJ$48) -> -4800
A16: Card / ACH fees | B16: =SUMIF(Monthly!$C$5:$BJ$5,B$3,Monthly!$C$49:$BJ$49) -> -7918.3687 | C16: =SUMIF(Monthly!$C$5:$BJ$5,C$3,Monthly!$C$49:$BJ$49) -> -13923.076 | D16: =SUMIF(Monthly!$C$5:$BJ$5,D$3,Monthly!$C$49:$BJ$49) -> -14340.769 | E16: =SUMIF(Monthly!$C$5:$BJ$5,E$3,Monthly!$C$49:$BJ$49) -> -14770.992 | F16: =SUMIF(Monthly!$C$5:$BJ$5,F$3,Monthly!$C$49:$BJ$49) -> -15214.122
A17: Other G&A | B17: =SUMIF(Monthly!$C$5:$BJ$5,B$3,Monthly!$C$50:$BJ$50) -> -14400 | C17: =SUMIF(Monthly!$C$5:$BJ$5,C$3,Monthly!$C$50:$BJ$50) -> -14400 | D17: =SUMIF(Monthly!$C$5:$BJ$5,D$3,Monthly!$C$50:$BJ$50) -> -14400 | E17: =SUMIF(Monthly!$C$5:$BJ$5,E$3,Monthly!$C$50:$BJ$50) -> -14400 | F17: =SUMIF(Monthly!$C$5:$BJ$5,F$3,Monthly!$C$50:$BJ$50) -> -14400
A18: Total operating expenses | B18: =SUMIF(Monthly!$C$5:$BJ$5,B$3,Monthly!$C$51:$BJ$51) -> -296928.37 | C18: =SUMIF(Monthly!$C$5:$BJ$5,C$3,Monthly!$C$51:$BJ$51) -> -309263.38 | D18: =SUMIF(Monthly!$C$5:$BJ$5,D$3,Monthly!$C$51:$BJ$51) -> -316201.28 | E18: =SUMIF(Monthly!$C$5:$BJ$5,E$3,Monthly!$C$51:$BJ$51) -> -323347.32 | F18: =SUMIF(Monthly!$C$5:$BJ$5,F$3,Monthly!$C$51:$BJ$51) -> -330707.74
A19: EBITDA | B19: =SUMIF(Monthly!$C$5:$BJ$5,B$3,Monthly!$C$52:$BJ$52) -> -125850.99 | C19: =SUMIF(Monthly!$C$5:$BJ$5,C$3,Monthly!$C$52:$BJ$52) -> 54057.278 | D19: =SUMIF(Monthly!$C$5:$BJ$5,D$3,Monthly!$C$52:$BJ$52) -> 57501.808 | E19: =SUMIF(Monthly!$C$5:$BJ$5,E$3,Monthly!$C$52:$BJ$52) -> 61566.862 | F19: =SUMIF(Monthly!$C$5:$BJ$5,F$3,Monthly!$C$52:$BJ$52) -> 65753.868
A20: EBITDA margin | B20: =IF(B5=0,0,B19/B5) -> -0.29985485 | C20: =IF(C5=0,0,C19/C5) -> 0.074470458 | D20: =IF(D5=0,0,D19/D5) -> 0.076961699 | E20: =IF(E5=0,0,E19/E5) -> 0.080002386 | F20: =IF(F5=0,0,F19/F5) -> 0.08295451
A21: Depreciation | B21: =SUMIF(Monthly!$C$5:$BJ$5,B$3,Monthly!$C$70:$BJ$70) -> -44200 | C21: =SUMIF(Monthly!$C$5:$BJ$5,C$3,Monthly!$C$70:$BJ$70) -> -45100 | D21: =SUMIF(Monthly!$C$5:$BJ$5,D$3,Monthly!$C$70:$BJ$70) -> -46000 | E21: =SUMIF(Monthly!$C$5:$BJ$5,E$3,Monthly!$C$70:$BJ$70) -> -46900 | F21: =SUMIF(Monthly!$C$5:$BJ$5,F$3,Monthly!$C$70:$BJ$70) -> -47800
A22: EBIT | B22: =SUMIF(Monthly!$C$5:$BJ$5,B$3,Monthly!$C$55:$BJ$55) -> -170050.99 | C22: =SUMIF(Monthly!$C$5:$BJ$5,C$3,Monthly!$C$55:$BJ$55) -> 8957.2785 | D22: =SUMIF(Monthly!$C$5:$BJ$5,D$3,Monthly!$C$55:$BJ$55) -> 11501.808 | E22: =SUMIF(Monthly!$C$5:$BJ$5,E$3,Monthly!$C$55:$BJ$55) -> 14666.862 | F22: =SUMIF(Monthly!$C$5:$BJ$5,F$3,Monthly!$C$55:$BJ$55) -> 17953.868
A23: Interest | B23: =SUMIF(Monthly!$C$5:$BJ$5,B$3,Monthly!$C$56:$BJ$56) -> -19159.722 | C23: =SUMIF(Monthly!$C$5:$BJ$5,C$3,Monthly!$C$56:$BJ$56) -> -17166.667 | D23: =SUMIF(Monthly!$C$5:$BJ$5,D$3,Monthly!$C$56:$BJ$56) -> -15166.667 | E23: =SUMIF(Monthly!$C$5:$BJ$5,E$3,Monthly!$C$56:$BJ$56) -> -13166.667 | F23: =SUMIF(Monthly!$C$5:$BJ$5,F$3,Monthly!$C$56:$BJ$56) -> -11166.667
A24: Pre-tax income | B24: =SUMIF(Monthly!$C$5:$BJ$5,B$3,Monthly!$C$57:$BJ$57) -> -189210.72 | C24: =SUMIF(Monthly!$C$5:$BJ$5,C$3,Monthly!$C$57:$BJ$57) -> -8209.3882 | D24: =SUMIF(Monthly!$C$5:$BJ$5,D$3,Monthly!$C$57:$BJ$57) -> -3664.8586 | E24: =SUMIF(Monthly!$C$5:$BJ$5,E$3,Monthly!$C$57:$BJ$57) -> 1500.1957 | F24: =SUMIF(Monthly!$C$5:$BJ$5,F$3,Monthly!$C$57:$BJ$57) -> 6787.2016
A25: Income tax | B25: =SUMIF(Monthly!$C$5:$BJ$5,B$3,Monthly!$C$60:$BJ$60) -> 0 | C25: =SUMIF(Monthly!$C$5:$BJ$5,C$3,Monthly!$C$60:$BJ$60) -> 0 | D25: =SUMIF(Monthly!$C$5:$BJ$5,D$3,Monthly!$C$60:$BJ$60) -> 0 | E25: =SUMIF(Monthly!$C$5:$BJ$5,E$3,Monthly!$C$60:$BJ$60) -> 0 | F25: =SUMIF(Monthly!$C$5:$BJ$5,F$3,Monthly!$C$60:$BJ$60) -> 0
A26: Net income | B26: =SUMIF(Monthly!$C$5:$BJ$5,B$3,Monthly!$C$61:$BJ$61) -> -189210.72 | C26: =SUMIF(Monthly!$C$5:$BJ$5,C$3,Monthly!$C$61:$BJ$61) -> -8209.3882 | D26: =SUMIF(Monthly!$C$5:$BJ$5,D$3,Monthly!$C$61:$BJ$61) -> -3664.8586 | E26: =SUMIF(Monthly!$C$5:$BJ$5,E$3,Monthly!$C$61:$BJ$61) -> 1500.1957 | F26: =SUMIF(Monthly!$C$5:$BJ$5,F$3,Monthly!$C$61:$BJ$61) -> 6787.2016
A27: Net margin | B27: =IF(B5=0,0,B26/B5) -> -0.45081687 | C27: =IF(C5=0,0,C26/C5) -> -0.011309428 | D27: =IF(D5=0,0,D26/D5) -> -0.0049051282 | E27: =IF(E5=0,0,E26/E5) -> 0.0019494129 | F27: =IF(F5=0,0,F26/F5) -> 0.0085626746

Sheet Cash Flow
A1: Annual cash flow statement | H1: =HYPERLINK("#'Cover'!A1","◂ Contents") -> ◂ Contents
A2: Rolled up from the period detail (SUMIF on the year row; balances at year end).
A3: Year # | B3: 1 | C3: 2 | D3: 3 | E3: 4 | F3: 5
B4: Year 1 | C4: Year 2 | D4: Year 3 | E4: Year 4 | F4: Year 5
A5: Net income | B5: =SUMIF(Monthly!$C$5:$BJ$5,B$3,Monthly!$C$61:$BJ$61) -> -189210.72 | C5: =SUMIF(Monthly!$C$5:$BJ$5,C$3,Monthly!$C$61:$BJ$61) -> -8209.3882 | D5: =SUMIF(Monthly!$C$5:$BJ$5,D$3,Monthly!$C$61:$BJ$61) -> -3664.8586 | E5: =SUMIF(Monthly!$C$5:$BJ$5,E$3,Monthly!$C$61:$BJ$61) -> 1500.1957 | F5: =SUMIF(Monthly!$C$5:$BJ$5,F$3,Monthly!$C$61:$BJ$61) -> 6787.2016
A6: Add back depreciation | B6: =-SUMIF(Monthly!$C$5:$BJ$5,B$3,Monthly!$C$70:$BJ$70) -> 44200 | C6: =-SUMIF(Monthly!$C$5:$BJ$5,C$3,Monthly!$C$70:$BJ$70) -> 45100 | D6: =-SUMIF(Monthly!$C$5:$BJ$5,D$3,Monthly!$C$70:$BJ$70) -> 46000 | E6: =-SUMIF(Monthly!$C$5:$BJ$5,E$3,Monthly!$C$70:$BJ$70) -> 46900 | F6: =-SUMIF(Monthly!$C$5:$BJ$5,F$3,Monthly!$C$70:$BJ$70) -> 47800
A7: (Increase) / decrease in receivables | B7: =SUMIF(Monthly!$C$5:$BJ$5,B$3,Monthly!$C$84:$BJ$84) -> -24022.185 | C7: =SUMIF(Monthly!$C$5:$BJ$5,C$3,Monthly!$C$84:$BJ$84) -> -2172.3368 | D7: =SUMIF(Monthly!$C$5:$BJ$5,D$3,Monthly!$C$84:$BJ$84) -> -785.83567 | E7: =SUMIF(Monthly!$C$5:$BJ$5,E$3,Monthly!$C$84:$BJ$84) -> -809.41074 | F7: =SUMIF(Monthly!$C$5:$BJ$5,F$3,Monthly!$C$84:$BJ$84) -> -833.69306
A8: (Increase) / decrease in inventory | B8: =SUMIF(Monthly!$C$5:$BJ$5,B$3,Monthly!$C$85:$BJ$85) -> -2896.35 | C8: =SUMIF(Monthly!$C$5:$BJ$5,C$3,Monthly!$C$85:$BJ$85) -> -125.052 | D8: =SUMIF(Monthly!$C$5:$BJ$5,D$3,Monthly!$C$85:$BJ$85) -> -90.64206 | E8: =SUMIF(Monthly!$C$5:$BJ$5,E$3,Monthly!$C$85:$BJ$85) -> -93.361322 | F8: =SUMIF(Monthly!$C$5:$BJ$5,F$3,Monthly!$C$85:$BJ$85) -> -96.162161
A9: Increase / (decrease) in payables | B9: =SUMIF(Monthly!$C$5:$BJ$5,B$3,Monthly!$C$86:$BJ$86) -> 10619.95 | C9: =SUMIF(Monthly!$C$5:$BJ$5,C$3,Monthly!$C$86:$BJ$86) -> 458.524 | D9: =SUMIF(Monthly!$C$5:$BJ$5,D$3,Monthly!$C$86:$BJ$86) -> 332.35422 | E9: =SUMIF(Monthly!$C$5:$BJ$5,E$3,Monthly!$C$86:$BJ$86) -> 342.32485 | F9: =SUMIF(Monthly!$C$5:$BJ$5,F$3,Monthly!$C$86:$BJ$86) -> 352.59459
A10: Operating cash flow | B10: =SUMIF(Monthly!$C$5:$BJ$5,B$3,Monthly!$C$89:$BJ$89) -> -161309.3 | C10: =SUMIF(Monthly!$C$5:$BJ$5,C$3,Monthly!$C$89:$BJ$89) -> 35051.747 | D10: =SUMIF(Monthly!$C$5:$BJ$5,D$3,Monthly!$C$89:$BJ$89) -> 41791.018 | E10: =SUMIF(Monthly!$C$5:$BJ$5,E$3,Monthly!$C$89:$BJ$89) -> 47839.748 | F10: =SUMIF(Monthly!$C$5:$BJ$5,F$3,Monthly!$C$89:$BJ$89) -> 54009.941
A11: Capital spending | B11: =SUMIF(Monthly!$C$5:$BJ$5,B$3,Monthly!$C$90:$BJ$90) -> -442000 | C11: =SUMIF(Monthly!$C$5:$BJ$5,C$3,Monthly!$C$90:$BJ$90) -> -9000 | D11: =SUMIF(Monthly!$C$5:$BJ$5,D$3,Monthly!$C$90:$BJ$90) -> -9000 | E11: =SUMIF(Monthly!$C$5:$BJ$5,E$3,Monthly!$C$90:$BJ$90) -> -9000 | F11: =SUMIF(Monthly!$C$5:$BJ$5,F$3,Monthly!$C$90:$BJ$90) -> -9000
A12: Equity raised | B12: =SUMIF(Monthly!$C$5:$BJ$5,B$3,Monthly!$C$91:$BJ$91) -> 450000 | C12: =SUMIF(Monthly!$C$5:$BJ$5,C$3,Monthly!$C$91:$BJ$91) -> 0 | D12: =SUMIF(Monthly!$C$5:$BJ$5,D$3,Monthly!$C$91:$BJ$91) -> 0 | E12: =SUMIF(Monthly!$C$5:$BJ$5,E$3,Monthly!$C$91:$BJ$91) -> 0 | F12: =SUMIF(Monthly!$C$5:$BJ$5,F$3,Monthly!$C$91:$BJ$91) -> 0
A13: Loan drawdown | B13: =SUMIF(Monthly!$C$5:$BJ$5,B$3,Monthly!$C$76:$BJ$76) -> 250000 | C13: =SUMIF(Monthly!$C$5:$BJ$5,C$3,Monthly!$C$76:$BJ$76) -> 0 | D13: =SUMIF(Monthly!$C$5:$BJ$5,D$3,Monthly!$C$76:$BJ$76) -> 0 | E13: =SUMIF(Monthly!$C$5:$BJ$5,E$3,Monthly!$C$76:$BJ$76) -> 0 | F13: =SUMIF(Monthly!$C$5:$BJ$5,F$3,Monthly!$C$76:$BJ$76) -> 0
A14: Loan repayment | B14: =SUMIF(Monthly!$C$5:$BJ$5,B$3,Monthly!$C$77:$BJ$77) -> -22916.667 | C14: =SUMIF(Monthly!$C$5:$BJ$5,C$3,Monthly!$C$77:$BJ$77) -> -25000 | D14: =SUMIF(Monthly!$C$5:$BJ$5,D$3,Monthly!$C$77:$BJ$77) -> -25000 | E14: =SUMIF(Monthly!$C$5:$BJ$5,E$3,Monthly!$C$77:$BJ$77) -> -25000 | F14: =SUMIF(Monthly!$C$5:$BJ$5,F$3,Monthly!$C$77:$BJ$77) -> -25000
A15: Financing cash flow | B15: =SUMIF(Monthly!$C$5:$BJ$5,B$3,Monthly!$C$92:$BJ$92) -> 677083.33 | C15: =SUMIF(Monthly!$C$5:$BJ$5,C$3,Monthly!$C$92:$BJ$92) -> -25000 | D15: =SUMIF(Monthly!$C$5:$BJ$5,D$3,Monthly!$C$92:$BJ$92) -> -25000 | E15: =SUMIF(Monthly!$C$5:$BJ$5,E$3,Monthly!$C$92:$BJ$92) -> -25000 | F15: =SUMIF(Monthly!$C$5:$BJ$5,F$3,Monthly!$C$92:$BJ$92) -> -25000
A16: Net change in cash | B16: =SUMIF(Monthly!$C$5:$BJ$5,B$3,Monthly!$C$93:$BJ$93) -> 73774.032 | C16: =SUMIF(Monthly!$C$5:$BJ$5,C$3,Monthly!$C$93:$BJ$93) -> 1051.747 | D16: =SUMIF(Monthly!$C$5:$BJ$5,D$3,Monthly!$C$93:$BJ$93) -> 7791.0179 | E16: =SUMIF(Monthly!$C$5:$BJ$5,E$3,Monthly!$C$93:$BJ$93) -> 13839.748 | F16: =SUMIF(Monthly!$C$5:$BJ$5,F$3,Monthly!$C$93:$BJ$93) -> 20009.941
A17: Opening cash | B17: =INDEX(Monthly!$C$94:$BJ$94,(B$3-1)*12+1) -> 0 | C17: =INDEX(Monthly!$C$94:$BJ$94,(C$3-1)*12+1) -> 73774.032 | D17: =INDEX(Monthly!$C$94:$BJ$94,(D$3-1)*12+1) -> 74825.779 | E17: =INDEX(Monthly!$C$94:$BJ$94,(E$3-1)*12+1) -> 82616.797 | F17: =INDEX(Monthly!$C$94:$BJ$94,(F$3-1)*12+1) -> 96456.545
A18: Closing cash | B18: =INDEX(Monthly!$C$95:$BJ$95,B$3*12) -> 73774.032 | C18: =INDEX(Monthly!$C$95:$BJ$95,C$3*12) -> 74825.779 | D18: =INDEX(Monthly!$C$95:$BJ$95,D$3*12) -> 82616.797 | E18: =INDEX(Monthly!$C$95:$BJ$95,E$3*12) -> 96456.545 | F18: =INDEX(Monthly!$C$95:$BJ$95,F$3*12) -> 116466.49

Sheet Balance Sheet
A1: Balance sheet at year end | H1: =HYPERLINK("#'Cover'!A1","◂ Contents") -> ◂ Contents
A2: Rolled up from the period detail (SUMIF on the year row; balances at year end).
A3: Year # | B3: 1 | C3: 2 | D3: 3 | E3: 4 | F3: 5
B4: Year 1 | C4: Year 2 | D4: Year 3 | E4: Year 4 | F4: Year 5
A5: Cash | B5: =INDEX(Monthly!$C$95:$BJ$95,B$3*12) -> 73774.032 | C5: =INDEX(Monthly!$C$95:$BJ$95,C$3*12) -> 74825.779 | D5: =INDEX(Monthly!$C$95:$BJ$95,D$3*12) -> 82616.797 | E5: =INDEX(Monthly!$C$95:$BJ$95,E$3*12) -> 96456.545 | F5: =INDEX(Monthly!$C$95:$BJ$95,F$3*12) -> 116466.49
A6: Accounts receivable | B6: =INDEX(Monthly!$C$81:$BJ$81,B$3*12) -> 24022.185 | C6: =INDEX(Monthly!$C$81:$BJ$81,C$3*12) -> 26194.522 | D6: =INDEX(Monthly!$C$81:$BJ$81,D$3*12) -> 26980.358 | E6: =INDEX(Monthly!$C$81:$BJ$81,E$3*12) -> 27789.769 | F6: =INDEX(Monthly!$C$81:$BJ$81,F$3*12) -> 28623.462
A7: Inventory | B7: =INDEX(Monthly!$C$82:$BJ$82,B$3*12) -> 2896.35 | C7: =INDEX(Monthly!$C$82:$BJ$82,C$3*12) -> 3021.402 | D7: =INDEX(Monthly!$C$82:$BJ$82,D$3*12) -> 3112.0441 | E7: =INDEX(Monthly!$C$82:$BJ$82,E$3*12) -> 3205.4054 | F7: =INDEX(Monthly!$C$82:$BJ$82,F$3*12) -> 3301.5675
A8: Net fixed assets | B8: =INDEX(Monthly!$C$72:$BJ$72,B$3*12) -> 397800 | C8: =INDEX(Monthly!$C$72:$BJ$72,C$3*12) -> 361700 | D8: =INDEX(Monthly!$C$72:$BJ$72,D$3*12) -> 324700 | E8: =INDEX(Monthly!$C$72:$BJ$72,E$3*12) -> 286800 | F8: =INDEX(Monthly!$C$72:$BJ$72,F$3*12) -> 248000
A9: Total assets | B9: =INDEX(Monthly!$C$109:$BJ$109,B$3*12) -> 498492.57 | C9: =INDEX(Monthly!$C$109:$BJ$109,C$3*12) -> 465741.7 | D9: =INDEX(Monthly!$C$109:$BJ$109,D$3*12) -> 437409.2 | E9: =INDEX(Monthly!$C$109:$BJ$109,E$3*12) -> 414251.72 | F9: =INDEX(Monthly!$C$109:$BJ$109,F$3*12) -> 396391.52
A10: Accounts payable | B10: =INDEX(Monthly!$C$83:$BJ$83,B$3*12) -> 10619.95 | C10: =INDEX(Monthly!$C$83:$BJ$83,C$3*12) -> 11078.474 | D10: =INDEX(Monthly!$C$83:$BJ$83,D$3*12) -> 11410.828 | E10: =INDEX(Monthly!$C$83:$BJ$83,E$3*12) -> 11753.153 | F10: =INDEX(Monthly!$C$83:$BJ$83,F$3*12) -> 12105.748
A11: Loan | B11: =INDEX(Monthly!$C$78:$BJ$78,B$3*12) -> 227083.33 | C11: =INDEX(Monthly!$C$78:$BJ$78,C$3*12) -> 202083.33 | D11: =INDEX(Monthly!$C$78:$BJ$78,D$3*12) -> 177083.33 | E11: =INDEX(Monthly!$C$78:$BJ$78,E$3*12) -> 152083.33 | F11: =INDEX(Monthly!$C$78:$BJ$78,F$3*12) -> 127083.33
A12: Total liabilities | B12: =INDEX(Monthly!$C$110:$BJ$110,B$3*12) -> 237703.28 | C12: =INDEX(Monthly!$C$110:$BJ$110,C$3*12) -> 213161.81 | D12: =INDEX(Monthly!$C$110:$BJ$110,D$3*12) -> 188494.16 | E12: =INDEX(Monthly!$C$110:$BJ$110,E$3*12) -> 163836.49 | F12: =INDEX(Monthly!$C$110:$BJ$110,F$3*12) -> 139189.08
A13: Paid-in capital | B13: =INDEX(Monthly!$C$107:$BJ$107,B$3*12) -> 450000 | C13: =INDEX(Monthly!$C$107:$BJ$107,C$3*12) -> 450000 | D13: =INDEX(Monthly!$C$107:$BJ$107,D$3*12) -> 450000 | E13: =INDEX(Monthly!$C$107:$BJ$107,E$3*12) -> 450000 | F13: =INDEX(Monthly!$C$107:$BJ$107,F$3*12) -> 450000
A14: Retained earnings | B14: =INDEX(Monthly!$C$108:$BJ$108,B$3*12) -> -189210.72 | C14: =INDEX(Monthly!$C$108:$BJ$108,C$3*12) -> -197420.1 | D14: =INDEX(Monthly!$C$108:$BJ$108,D$3*12) -> -201084.96 | E14: =INDEX(Monthly!$C$108:$BJ$108,E$3*12) -> -199584.77 | F14: =INDEX(Monthly!$C$108:$BJ$108,F$3*12) -> -192797.57
A15: Total equity | B15: =INDEX(Monthly!$C$111:$BJ$111,B$3*12) -> 260789.28 | C15: =INDEX(Monthly!$C$111:$BJ$111,C$3*12) -> 252579.9 | D15: =INDEX(Monthly!$C$111:$BJ$111,D$3*12) -> 248915.04 | E15: =INDEX(Monthly!$C$111:$BJ$111,E$3*12) -> 250415.23 | F15: =INDEX(Monthly!$C$111:$BJ$111,F$3*12) -> 257202.43
A16: Total liabilities & equity | B16: =INDEX(Monthly!$C$112:$BJ$112,B$3*12) -> 498492.57 | C16: =INDEX(Monthly!$C$112:$BJ$112,C$3*12) -> 465741.7 | D16: =INDEX(Monthly!$C$112:$BJ$112,D$3*12) -> 437409.2 | E16: =INDEX(Monthly!$C$112:$BJ$112,E$3*12) -> 414251.72 | F16: =INDEX(Monthly!$C$112:$BJ$112,F$3*12) -> 396391.52
A17: Check: assets − liabilities − equity (must be 0) | B17: =INDEX(Monthly!$C$113:$BJ$113,B$3*12) -> 0 | C17: =INDEX(Monthly!$C$113:$BJ$113,C$3*12) -> 0 | D17: =INDEX(Monthly!$C$113:$BJ$113,D$3*12) -> 0 | E17: =INDEX(Monthly!$C$113:$BJ$113,E$3*12) -> 0 | F17: =INDEX(Monthly!$C$113:$BJ$113,F$3*12) -> 0

Sheet Monthly
A1: Monthly projection | D1: =HYPERLINK("#'Cover'!A1","◂ Contents") -> ◂ Contents
A2: $ unless stated; costs shown as negatives. Every period uses the same formula.
A3: Month | C3: M1 | D3: M2 | E3: M3 | F3: M4 | G3: M5 | H3: M6 | I3: M7 | J3: M8 | K3: M9 | L3: M10 | M3: M11 | N3: M12 | O3: M13 | P3: M14 | Q3: M15 | R3: M16 | S3: M17 | T3: M18 | U3: M19 | V3: M20 | W3: M21 | X3: M22 | Y3: M23 | Z3: M24 | AA3: M25 | AB3: M26 | AC3: M27 | AD3: M28 | AE3: M29 | AF3: M30 | AG3: M31 | AH3: M32 | AI3: M33 | AJ3: M34 | AK3: M35 | AL3: M36 | AM3: M37 | AN3: M38 | AO3: M39 | AP3: M40 | AQ3: M41 | AR3: M42 | AS3: M43 | AT3: M44 | AU3: M45 | AV3: M46 | AW3: M47 | AX3: M48 | AY3: M49 | AZ3: M50 | BA3: M51 | BB3: M52 | BC3: M53 | BD3: M54 | BE3: M55 | BF3: M56 | BG3: M57 | BH3: M58 | BI3: M59 | BJ3: M60
A4: Period # | C4: 1 | D4: 2 | E4: 3 | F4: 4 | G4: 5 | H4: 6 | I4: 7 | J4: 8 | K4: 9 | L4: 10 | M4: 11 | N4: 12 | O4: 13 | P4: 14 | Q4: 15 | R4: 16 | S4: 17 | T4: 18 | U4: 19 | V4: 20 | W4: 21 | X4: 22 | Y4: 23 | Z4: 24 | AA4: 25 | AB4: 26 | AC4: 27 | AD4: 28 | AE4: 29 | AF4: 30 | AG4: 31 | AH4: 32 | AI4: 33 | AJ4: 34 | AK4: 35 | AL4: 36 | AM4: 37 | AN4: 38 | AO4: 39 | AP4: 40 | AQ4: 41 | AR4: 42 | AS4: 43 | AT4: 44 | AU4: 45 | AV4: 46 | AW4: 47 | AX4: 48 | AY4: 49 | AZ4: 50 | BA4: 51 | BB4: 52 | BC4: 53 | BD4: 54 | BE4: 55 | BF4: 56 | BG4: 57 | BH4: 58 | BI4: 59 | BJ4: 60
A5: Year # | C5: =ROUNDUP(C4*1/12,0) -> 1 | D5: =ROUNDUP(D4*1/12,0) -> 1 | E5: =ROUNDUP(E4*1/12,0) -> 1 | F5: =ROUNDUP(F4*1/12,0) -> 1 | G5: =ROUNDUP(G4*1/12,0) -> 1 | H5: =ROUNDUP(H4*1/12,0) -> 1 | I5: =ROUNDUP(I4*1/12,0) -> 1 | J5: =ROUNDUP(J4*1/12,0) -> 1 | ... BJ5: =ROUNDUP(BJ4*1/12,0) -> 5
A7: Places & enrolment
A8: Licensed places | C8: =Inputs!$E$7+Inputs!$E$8*(C$5-1) -> 60 | D8: =Inputs!$E$7+Inputs!$E$8*(D$5-1) -> 60 | E8: =Inputs!$E$7+Inputs!$E$8*(E$5-1) -> 60 | F8: =Inputs!$E$7+Inputs!$E$8*(F$5-1) -> 60 | G8: =Inputs!$E$7+Inputs!$E$8*(G$5-1) -> 60 | H8: =Inputs!$E$7+Inputs!$E$8*(H$5-1) -> 60 | I8: =Inputs!$E$7+Inputs!$E$8*(I$5-1) -> 60 | J8: =Inputs!$E$7+Inputs!$E$8*(J$5-1) -> 60 | ... BJ8: =Inputs!$E$7+Inputs!$E$8*(BJ$5-1) -> 60
A9: Enrolment in month 1 (capped at the full level) | C9: =MIN(Inputs!$E$11,Inputs!$E$10) -> 0.2 | D9: =MIN(Inputs!$E$11,Inputs!$E$10) -> 0.2 | E9: =MIN(Inputs!$E$11,Inputs!$E$10) -> 0.2 | F9: =MIN(Inputs!$E$11,Inputs!$E$10) -> 0.2 | G9: =MIN(Inputs!$E$11,Inputs!$E$10) -> 0.2 | H9: =MIN(Inputs!$E$11,Inputs!$E$10) -> 0.2 | I9: =MIN(Inputs!$E$11,Inputs!$E$10) -> 0.2 | J9: =MIN(Inputs!$E$11,Inputs!$E$10) -> 0.2 | ... BJ9: =MIN(Inputs!$E$11,Inputs!$E$10) -> 0.2
A10: Helper: months of the period still on the ramp-up | C10: =MAX(0,MIN(1,Inputs!$E$12-(C$4-1)*1)) -> 1 | D10: =MAX(0,MIN(1,Inputs!$E$12-(D$4-1)*1)) -> 1 | E10: =MAX(0,MIN(1,Inputs!$E$12-(E$4-1)*1)) -> 1 | F10: =MAX(0,MIN(1,Inputs!$E$12-(F$4-1)*1)) -> 1 | G10: =MAX(0,MIN(1,Inputs!$E$12-(G$4-1)*1)) -> 1 | H10: =MAX(0,MIN(1,Inputs!$E$12-(H$4-1)*1)) -> 1 | I10: =MAX(0,MIN(1,Inputs!$E$12-(I$4-1)*1)) -> 1 | J10: =MAX(0,MIN(1,Inputs!$E$12-(J$4-1)*1)) -> 1 | ... BJ10: =MAX(0,MIN(1,Inputs!$E$12-(BJ$4-1)*1)) -> 0
A11: Enrolment, average of the period (% of places) | C11: =(C10*C9+(Inputs!$E$10-C9)/MAX(1,Inputs!$E$12)*(C10*(C$4-1)*1+C10*(C10-1)/2)+(1-C10)*Inputs!$E$10)/1 -> 0.2 | D11: =(D10*D9+(Inputs!$E$10-D9)/MAX(1,Inputs!$E$12)*(D10*(D$4-1)*1+D10*(D10-1)/2)+(1-D10)*Inputs!$E$10)/1 -> 0.25416667 | E11: =(E10*E9+(Inputs!$E$10-E9)/MAX(1,Inputs!$E$12)*(E10*(E$4-1)*1+E10*(E10-1)/2)+(1-E10)*Inputs!$E$10)/1 -> 0.30833333 | F11: =(F10*F9+(Inputs!$E$10-F9)/MAX(1,Inputs!$E$12)*(F10*(F$4-1)*1+F10*(F10-1)/2)+(1-F10)*Inputs!$E$10)/1 -> 0.3625 | G11: =(G10*G9+(Inputs!$E$10-G9)/MAX(1,Inputs!$E$12)*(G10*(G$4-1)*1+G10*(G10-1)/2)+(1-G10)*Inputs!$E$10)/1 -> 0.41666667 | H11: =(H10*H9+(Inputs!$E$10-H9)/MAX(1,Inputs!$E$12)*(H10*(H$4-1)*1+H10*(H10-1)/2)+(1-H10)*Inputs!$E$10)/1 -> 0.47083333 | I11: =(I10*I9+(Inputs!$E$10-I9)/MAX(1,Inputs!$E$12)*(I10*(I$4-1)*1+I10*(I10-1)/2)+(1-I10)*Inputs!$E$10)/1 -> 0.525 | J11: =(J10*J9+(Inputs!$E$10-J9)/MAX(1,Inputs!$E$12)*(J10*(J$4-1)*1+J10*(J10-1)/2)+(1-J10)*Inputs!$E$10)/1 -> 0.57916667 | ... BJ11: =(BJ10*BJ9+(Inputs!$E$10-BJ9)/MAX(1,Inputs!$E$12)*(BJ10*(BJ$4-1)*1+BJ10*(BJ10-1)/2)+(1-BJ10)*Inputs!$E$10)/1 -> 0.85
A12: Enrolment at the end of the period (% of places) | C12: =IF(Inputs!$E$12<=0,Inputs!$E$10,C9+(Inputs!$E$10-C9)*MIN(1,(C$4*1-1)/MAX(1,Inputs!$E$12))) -> 0.2 | D12: =IF(Inputs!$E$12<=0,Inputs!$E$10,D9+(Inputs!$E$10-D9)*MIN(1,(D$4*1-1)/MAX(1,Inputs!$E$12))) -> 0.25416667 | E12: =IF(Inputs!$E$12<=0,Inputs!$E$10,E9+(Inputs!$E$10-E9)*MIN(1,(E$4*1-1)/MAX(1,Inputs!$E$12))) -> 0.30833333 | F12: =IF(Inputs!$E$12<=0,Inputs!$E$10,F9+(Inputs!$E$10-F9)*MIN(1,(F$4*1-1)/MAX(1,Inputs!$E$12))) -> 0.3625 | G12: =IF(Inputs!$E$12<=0,Inputs!$E$10,G9+(Inputs!$E$10-G9)*MIN(1,(G$4*1-1)/MAX(1,Inputs!$E$12))) -> 0.41666667 | H12: =IF(Inputs!$E$12<=0,Inputs!$E$10,H9+(Inputs!$E$10-H9)*MIN(1,(H$4*1-1)/MAX(1,Inputs!$E$12))) -> 0.47083333 | I12: =IF(Inputs!$E$12<=0,Inputs!$E$10,I9+(Inputs!$E$10-I9)*MIN(1,(I$4*1-1)/MAX(1,Inputs!$E$12))) -> 0.525 | J12: =IF(Inputs!$E$12<=0,Inputs!$E$10,J9+(Inputs!$E$10-J9)*MIN(1,(J$4*1-1)/MAX(1,Inputs!$E$12))) -> 0.57916667 | ... BJ12: =IF(Inputs!$E$12<=0,Inputs!$E$10,BJ9+(Inputs!$E$10-BJ9)*MIN(1,(BJ$4*1-1)/MAX(1,Inputs!$E$12))) -> 0.85
A13: Infants & toddlers enrolled (average) | C13: =C8*Inputs!$E$9*C11 -> 4.2 | D13: =D8*Inputs!$E$9*D11 -> 5.3375 | E13: =E8*Inputs!$E$9*E11 -> 6.475 | F13: =F8*Inputs!$E$9*F11 -> 7.6125 | G13: =G8*Inputs!$E$9*G11 -> 8.75 | H13: =H8*Inputs!$E$9*H11 -> 9.8875 | I13: =I8*Inputs!$E$9*I11 -> 11.025 | J13: =J8*Inputs!$E$9*J11 -> 12.1625 | ... BJ13: =BJ8*Inputs!$E$9*BJ11 -> 17.85
A14: Preschoolers enrolled (average) | C14: =C8*(1-Inputs!$E$9)*C11 -> 7.8 | D14: =D8*(1-Inputs!$E$9)*D11 -> 9.9125 | E14: =E8*(1-Inputs!$E$9)*E11 -> 12.025 | F14: =F8*(1-Inputs!$E$9)*F11 -> 14.1375 | G14: =G8*(1-Inputs!$E$9)*G11 -> 16.25 | H14: =H8*(1-Inputs!$E$9)*H11 -> 18.3625 | I14: =I8*(1-Inputs!$E$9)*I11 -> 20.475 | J14: =J8*(1-Inputs!$E$9)*J11 -> 22.5875 | ... BJ14: =BJ8*(1-Inputs!$E$9)*BJ11 -> 33.15
A15: Children enrolled (average) | C15: =C13+C14 -> 12 | D15: =D13+D14 -> 15.25 | E15: =E13+E14 -> 18.5 | F15: =F13+F14 -> 21.75 | G15: =G13+G14 -> 25 | H15: =H13+H14 -> 28.25 | I15: =I13+I14 -> 31.5 | J15: =J13+J14 -> 34.75 | ... BJ15: =BJ13+BJ14 -> 51
A16: Child-months enrolled | C16: =C15*1 -> 12 | D16: =D15*1 -> 15.25 | E16: =E15*1 -> 18.5 | F16: =F15*1 -> 21.75 | G16: =G15*1 -> 25 | H16: =H15*1 -> 28.25 | I16: =I15*1 -> 31.5 | J16: =J15*1 -> 34.75 | ... BJ16: =BJ15*1 -> 51
A17: Licensed place-months | C17: =C8*1 -> 60 | D17: =D8*1 -> 60 | E17: =E8*1 -> 60 | F17: =F8*1 -> 60 | G17: =G8*1 -> 60 | H17: =H8*1 -> 60 | I17: =I8*1 -> 60 | J17: =J8*1 -> 60 | ... BJ17: =BJ8*1 -> 60
A18: Children enrolled at the end of the period | C18: =C8*C12 -> 12 | D18: =D8*D12 -> 15.25 | E18: =E8*E12 -> 18.5 | F18: =F8*F12 -> 21.75 | G18: =G8*G12 -> 25 | H18: =H8*H12 -> 28.25 | I18: =I8*I12 -> 31.5 | J18: =J8*J12 -> 34.75 | ... BJ18: =BJ8*BJ12 -> 51
A19: New children enrolled (fill-up and replacement of leavers) | C19: =MAX(0,C18)+C15*Inputs!$E$14*1/12 -> 12.3 | D19: =MAX(0,D18-C18)+D15*Inputs!$E$14*1/12 -> 3.63125 | E19: =MAX(0,E18-D18)+E15*Inputs!$E$14*1/12 -> 3.7125 | F19: =MAX(0,F18-E18)+F15*Inputs!$E$14*1/12 -> 3.79375 | G19: =MAX(0,G18-F18)+G15*Inputs!$E$14*1/12 -> 3.875 | H19: =MAX(0,H18-G18)+H15*Inputs!$E$14*1/12 -> 3.95625 | I19: =MAX(0,I18-H18)+I15*Inputs!$E$14*1/12 -> 4.0375 | J19: =MAX(0,J18-I18)+J15*Inputs!$E$14*1/12 -> 4.11875 | K19: =MAX(0,K18-J18)+K15*Inputs!$E$14*1/12 -> 4.2 | ... BJ19: =MAX(0,BJ18-BI18)+BJ15*Inputs!$E$14*1/12 -> 1.275
A21: Staffing by ratio
A22: Teachers on the floor, infants & toddlers | C22: =ROUNDUP(ROUND(C13/MAX(1,Inputs!$E$26),6),0) -> 1 | D22: =ROUNDUP(ROUND(D13/MAX(1,Inputs!$E$26),6),0) -> 1 | E22: =ROUNDUP(ROUND(E13/MAX(1,Inputs!$E$26),6),0) -> 2 | F22: =ROUNDUP(ROUND(F13/MAX(1,Inputs!$E$26),6),0) -> 2 | G22: =ROUNDUP(ROUND(G13/MAX(1,Inputs!$E$26),6),0) -> 2 | H22: =ROUNDUP(ROUND(H13/MAX(1,Inputs!$E$26),6),0) -> 2 | I22: =ROUNDUP(ROUND(I13/MAX(1,Inputs!$E$26),6),0) -> 2 | J22: =ROUNDUP(ROUND(J13/MAX(1,Inputs!$E$26),6),0) -> 3 | ... BJ22: =ROUNDUP(ROUND(BJ13/MAX(1,Inputs!$E$26),6),0) -> 3
A23: Teachers on the floor, preschool | C23: =ROUNDUP(ROUND(C14/MAX(1,Inputs!$E$27),6),0) -> 1 | D23: =ROUNDUP(ROUND(D14/MAX(1,Inputs!$E$27),6),0) -> 1 | E23: =ROUNDUP(ROUND(E14/MAX(1,Inputs!$E$27),6),0) -> 2 | F23: =ROUNDUP(ROUND(F14/MAX(1,Inputs!$E$27),6),0) -> 2 | G23: =ROUNDUP(ROUND(G14/MAX(1,Inputs!$E$27),6),0) -> 2 | H23: =ROUNDUP(ROUND(H14/MAX(1,Inputs!$E$27),6),0) -> 2 | I23: =ROUNDUP(ROUND(I14/MAX(1,Inputs!$E$27),6),0) -> 2 | J23: =ROUNDUP(ROUND(J14/MAX(1,Inputs!$E$27),6),0) -> 2 | ... BJ23: =ROUNDUP(ROUND(BJ14/MAX(1,Inputs!$E$27),6),0) -> 3
A24: Teachers on the floor | C24: =C22+C23 -> 2 | D24: =D22+D23 -> 2 | E24: =E22+E23 -> 4 | F24: =F22+F23 -> 4 | G24: =G22+G23 -> 4 | H24: =H22+H23 -> 4 | I24: =I22+I23 -> 4 | J24: =J22+J23 -> 5 | ... BJ24: =BJ22+BJ23 -> 6
A25: Teaching FTE hired (with coverage) | C25: =C24*Inputs!$E$28 -> 2.4 | D25: =D24*Inputs!$E$28 -> 2.4 | E25: =E24*Inputs!$E$28 -> 4.8 | F25: =F24*Inputs!$E$28 -> 4.8 | G25: =G24*Inputs!$E$28 -> 4.8 | H25: =H24*Inputs!$E$28 -> 4.8 | I25: =I24*Inputs!$E$28 -> 4.8 | J25: =J24*Inputs!$E$28 -> 6 | ... BJ25: =BJ24*Inputs!$E$28 -> 7.2
A27: Revenue
A28: Tuition at list price | C28: =(C13*Inputs!$E$17+C14*Inputs!$E$18)*1*(1+Inputs!$E$19)^(C$5-1) -> 14880 | D28: =(D13*Inputs!$E$17+D14*Inputs!$E$18)*1*(1+Inputs!$E$19)^(D$5-1) -> 18910 | E28: =(E13*Inputs!$E$17+E14*Inputs!$E$18)*1*(1+Inputs!$E$19)^(E$5-1) -> 22940 | F28: =(F13*Inputs!$E$17+F14*Inputs!$E$18)*1*(1+Inputs!$E$19)^(F$5-1) -> 26970 | G28: =(G13*Inputs!$E$17+G14*Inputs!$E$18)*1*(1+Inputs!$E$19)^(G$5-1) -> 31000 | H28: =(H13*Inputs!$E$17+H14*Inputs!$E$18)*1*(1+Inputs!$E$19)^(H$5-1) -> 35030 | I28: =(I13*Inputs!$E$17+I14*Inputs!$E$18)*1*(1+Inputs!$E$19)^(I$5-1) -> 39060 | J28: =(J13*Inputs!$E$17+J14*Inputs!$E$18)*1*(1+Inputs!$E$19)^(J$5-1) -> 43090 | ... BJ28: =(BJ13*Inputs!$E$17+BJ14*Inputs!$E$18)*1*(1+Inputs!$E$19)^(BJ$5-1) -> 71177.177
A29: Parent-paid tuition (after sibling & staff discounts) | C29: =C28*(1-Inputs!$E$22)*(1-Inputs!$E$20) -> 10602 | D29: =D28*(1-Inputs!$E$22)*(1-Inputs!$E$20) -> 13473.375 | E29: =E28*(1-Inputs!$E$22)*(1-Inputs!$E$20) -> 16344.75 | F29: =F28*(1-Inputs!$E$22)*(1-Inputs!$E$20) -> 19216.125 | G29: =G28*(1-Inputs!$E$22)*(1-Inputs!$E$20) -> 22087.5 | H29: =H28*(1-Inputs!$E$22)*(1-Inputs!$E$20) -> 24958.875 | I29: =I28*(1-Inputs!$E$22)*(1-Inputs!$E$20) -> 27830.25 | J29: =J28*(1-Inputs!$E$22)*(1-Inputs!$E$20) -> 30701.625 | ... BJ29: =BJ28*(1-Inputs!$E$22)*(1-Inputs!$E$20) -> 50713.739
A30: Subsidy & voucher payments | C30: =C28*Inputs!$E$22*Inputs!$E$23 -> 3162 | D30: =D28*Inputs!$E$22*Inputs!$E$23 -> 4018.375 | E30: =E28*Inputs!$E$22*Inputs!$E$23 -> 4874.75 | F30: =F28*Inputs!$E$22*Inputs!$E$23 -> 5731.125 | G30: =G28*Inputs!$E$22*Inputs!$E$23 -> 6587.5 | H30: =H28*Inputs!$E$22*Inputs!$E$23 -> 7443.875 | I30: =I28*Inputs!$E$22*Inputs!$E$23 -> 8300.25 | J30: =J28*Inputs!$E$22*Inputs!$E$23 -> 9156.625 | ... BJ30: =BJ28*Inputs!$E$22*Inputs!$E$23 -> 15125.15
A31: Registration fees | C31: =C19*Inputs!$E$21*(1+Inputs!$E$19)^(C$5-1) -> 1845 | D31: =D19*Inputs!$E$21*(1+Inputs!$E$19)^(D$5-1) -> 544.6875 | E31: =E19*Inputs!$E$21*(1+Inputs!$E$19)^(E$5-1) -> 556.875 | F31: =F19*Inputs!$E$21*(1+Inputs!$E$19)^(F$5-1) -> 569.0625 | G31: =G19*Inputs!$E$21*(1+Inputs!$E$19)^(G$5-1) -> 581.25 | H31: =H19*Inputs!$E$21*(1+Inputs!$E$19)^(H$5-1) -> 593.4375 | I31: =I19*Inputs!$E$21*(1+Inputs!$E$19)^(I$5-1) -> 605.625 | J31: =J19*Inputs!$E$21*(1+Inputs!$E$19)^(J$5-1) -> 617.8125 | ... BJ31: =BJ19*Inputs!$E$21*(1+Inputs!$E$19)^(BJ$5-1) -> 215.25356
A32: Revenue | C32: =C29+C30+C31 -> 15609 | D32: =D29+D30+D31 -> 18036.438 | E32: =E29+E30+E31 -> 21776.375 | F32: =F29+F30+F31 -> 25516.312 | G32: =G29+G30+G31 -> 29256.25 | H32: =H29+H30+H31 -> 32996.188 | I32: =I29+I30+I31 -> 36736.125 | J32: =J29+J30+J31 -> 40476.062 | ... BJ32: =BJ29+BJ30+BJ31 -> 66054.142
A34: Cost of sales
A35: Teacher payroll (with payroll taxes) | C35: =-C25*Inputs!$E$29/12*1*(1+Inputs!$E$69)*(1+Inputs!$E$70)^(C$5-1) -> -7840 | D35: =-D25*Inputs!$E$29/12*1*(1+Inputs!$E$69)*(1+Inputs!$E$70)^(D$5-1) -> -7840 | E35: =-E25*Inputs!$E$29/12*1*(1+Inputs!$E$69)*(1+Inputs!$E$70)^(E$5-1) -> -15680 | F35: =-F25*Inputs!$E$29/12*1*(1+Inputs!$E$69)*(1+Inputs!$E$70)^(F$5-1) -> -15680 | G35: =-G25*Inputs!$E$29/12*1*(1+Inputs!$E$69)*(1+Inputs!$E$70)^(G$5-1) -> -15680 | H35: =-H25*Inputs!$E$29/12*1*(1+Inputs!$E$69)*(1+Inputs!$E$70)^(H$5-1) -> -15680 | I35: =-I25*Inputs!$E$29/12*1*(1+Inputs!$E$69)*(1+Inputs!$E$70)^(I$5-1) -> -15680 | J35: =-J25*Inputs!$E$29/12*1*(1+Inputs!$E$69)*(1+Inputs!$E$70)^(J$5-1) -> -19600 | ... BJ35: =-BJ25*Inputs!$E$29/12*1*(1+Inputs!$E$69)*(1+Inputs!$E$70)^(BJ$5-1) -> -26471.967
A36: Food | C36: =-C15*Inputs!$E$32*Inputs!$E$13*1*(1+Inputs!$E$34)^(C$5-1) -> -1008 | D36: =-D15*Inputs!$E$32*Inputs!$E$13*1*(1+Inputs!$E$34)^(D$5-1) -> -1281 | E36: =-E15*Inputs!$E$32*Inputs!$E$13*1*(1+Inputs!$E$34)^(E$5-1) -> -1554 | F36: =-F15*Inputs!$E$32*Inputs!$E$13*1*(1+Inputs!$E$34)^(F$5-1) -> -1827 | G36: =-G15*Inputs!$E$32*Inputs!$E$13*1*(1+Inputs!$E$34)^(G$5-1) -> -2100 | H36: =-H15*Inputs!$E$32*Inputs!$E$13*1*(1+Inputs!$E$34)^(H$5-1) -> -2373 | I36: =-I15*Inputs!$E$32*Inputs!$E$13*1*(1+Inputs!$E$34)^(I$5-1) -> -2646 | J36: =-J15*Inputs!$E$32*Inputs!$E$13*1*(1+Inputs!$E$34)^(J$5-1) -> -2919 | ... BJ36: =-BJ15*Inputs!$E$32*Inputs!$E$13*1*(1+Inputs!$E$34)^(BJ$5-1) -> -4821.6797
A37: Supplies & activities | C37: =-C15*Inputs!$E$33*1*(1+Inputs!$E$34)^(C$5-1) -> -360 | D37: =-D15*Inputs!$E$33*1*(1+Inputs!$E$34)^(D$5-1) -> -457.5 | E37: =-E15*Inputs!$E$33*1*(1+Inputs!$E$34)^(E$5-1) -> -555 | F37: =-F15*Inputs!$E$33*1*(1+Inputs!$E$34)^(F$5-1) -> -652.5 | G37: =-G15*Inputs!$E$33*1*(1+Inputs!$E$34)^(G$5-1) -> -750 | H37: =-H15*Inputs!$E$33*1*(1+Inputs!$E$34)^(H$5-1) -> -847.5 | I37: =-I15*Inputs!$E$33*1*(1+Inputs!$E$34)^(I$5-1) -> -945 | J37: =-J15*Inputs!$E$33*1*(1+Inputs!$E$34)^(J$5-1) -> -1042.5 | ... BJ37: =-BJ15*Inputs!$E$33*1*(1+Inputs!$E$34)^(BJ$5-1) -> -1722.0285
A38: Cost of sales | C38: =C35+C36+C37 -> -9208 | D38: =D35+D36+D37 -> -9578.5 | E38: =E35+E36+E37 -> -17789 | F38: =F35+F36+F37 -> -18159.5 | G38: =G35+G36+G37 -> -18530 | H38: =H35+H36+H37 -> -18900.5 | I38: =I35+I36+I37 -> -19271 | J38: =J35+J36+J37 -> -23561.5 | ... BJ38: =BJ35+BJ36+BJ37 -> -33015.675
A39: Gross profit | C39: =C32+C38 -> 6401 | D39: =D32+D38 -> 8457.9375 | E39: =E32+E38 -> 3987.375 | F39: =F32+F38 -> 7356.8125 | G39: =G32+G38 -> 10726.25 | H39: =H32+H38 -> 14095.688 | I39: =I32+I38 -> 17465.125 | J39: =J32+J38 -> 16914.562 | ... BJ39: =BJ32+BJ38 -> 33038.467
A41: Operating expenses
A42: Staff payroll (director, office, kitchen) | C42: =Headcount!C17 -> -9146.6667 | D42: =Headcount!D17 -> -9146.6667 | E42: =Headcount!E17 -> -9146.6667 | F42: =Headcount!F17 -> -9146.6667 | G42: =Headcount!G17 -> -9146.6667 | H42: =Headcount!H17 -> -9146.6667 | I42: =Headcount!I17 -> -9146.6667 | J42: =Headcount!J17 -> -9146.6667 | ... BJ42: =Headcount!BJ17 -> -10294.654
A43: Rent | C43: =-C8*Inputs!$E$37*Inputs!$E$38/12*(1+Inputs!$E$39)^(C$5-1)*1 -> -6000 | D43: =-D8*Inputs!$E$37*Inputs!$E$38/12*(1+Inputs!$E$39)^(D$5-1)*1 -> -6000 | E43: =-E8*Inputs!$E$37*Inputs!$E$38/12*(1+Inputs!$E$39)^(E$5-1)*1 -> -6000 | F43: =-F8*Inputs!$E$37*Inputs!$E$38/12*(1+Inputs!$E$39)^(F$5-1)*1 -> -6000 | G43: =-G8*Inputs!$E$37*Inputs!$E$38/12*(1+Inputs!$E$39)^(G$5-1)*1 -> -6000 | H43: =-H8*Inputs!$E$37*Inputs!$E$38/12*(1+Inputs!$E$39)^(H$5-1)*1 -> -6000 | I43: =-I8*Inputs!$E$37*Inputs!$E$38/12*(1+Inputs!$E$39)^(I$5-1)*1 -> -6000 | J43: =-J8*Inputs!$E$37*Inputs!$E$38/12*(1+Inputs!$E$39)^(J$5-1)*1 -> -6000 | ... BJ43: =-BJ8*Inputs!$E$37*Inputs!$E$38/12*(1+Inputs!$E$39)^(BJ$5-1)*1 -> -6753.0529
A44: Utilities & cleaning | C44: =-C8*Inputs!$E$37*Inputs!$E$40/12*(1+Inputs!$E$34)^(C$5-1)*1 -> -2437.5 | D44: =-D8*Inputs!$E$37*Inputs!$E$40/12*(1+Inputs!$E$34)^(D$5-1)*1 -> -2437.5 | E44: =-E8*Inputs!$E$37*Inputs!$E$40/12*(1+Inputs!$E$34)^(E$5-1)*1 -> -2437.5 | F44: =-F8*Inputs!$E$37*Inputs!$E$40/12*(1+Inputs!$E$34)^(F$5-1)*1 -> -2437.5 | G44: =-G8*Inputs!$E$37*Inputs!$E$40/12*(1+Inputs!$E$34)^(G$5-1)*1 -> -2437.5 | H44: =-H8*Inputs!$E$37*Inputs!$E$40/12*(1+Inputs!$E$34)^(H$5-1)*1 -> -2437.5 | I44: =-I8*Inputs!$E$37*Inputs!$E$40/12*(1+Inputs!$E$34)^(I$5-1)*1 -> -2437.5 | J44: =-J8*Inputs!$E$37*Inputs!$E$40/12*(1+Inputs!$E$34)^(J$5-1)*1 -> -2437.5 | ... BJ44: =-BJ8*Inputs!$E$37*Inputs!$E$40/12*(1+Inputs!$E$34)^(BJ$5-1)*1 -> -2743.4277
A45: Insurance | C45: =-Inputs!$E$41*1 -> -1800 | D45: =-Inputs!$E$41*1 -> -1800 | E45: =-Inputs!$E$41*1 -> -1800 | F45: =-Inputs!$E$41*1 -> -1800 | G45: =-Inputs!$E$41*1 -> -1800 | H45: =-Inputs!$E$41*1 -> -1800 | I45: =-Inputs!$E$41*1 -> -1800 | J45: =-Inputs!$E$41*1 -> -1800 | ... BJ45: =-Inputs!$E$41*1 -> -1800
A46: Licensing, background checks & training | C46: =-Inputs!$E$42*1 -> -600 | D46: =-Inputs!$E$42*1 -> -600 | E46: =-Inputs!$E$42*1 -> -600 | F46: =-Inputs!$E$42*1 -> -600 | G46: =-Inputs!$E$42*1 -> -600 | H46: =-Inputs!$E$42*1 -> -600 | I46: =-Inputs!$E$42*1 -> -600 | J46: =-Inputs!$E$42*1 -> -600 | ... BJ46: =-Inputs!$E$42*1 -> -600
A47: Marketing | C47: =-Inputs!$E$43*(1+Inputs!$E$44)^(C$5-1)*1 -> -2500 | D47: =-Inputs!$E$43*(1+Inputs!$E$44)^(D$5-1)*1 -> -2500 | E47: =-Inputs!$E$43*(1+Inputs!$E$44)^(E$5-1)*1 -> -2500 | F47: =-Inputs!$E$43*(1+Inputs!$E$44)^(F$5-1)*1 -> -2500 | G47: =-Inputs!$E$43*(1+Inputs!$E$44)^(G$5-1)*1 -> -2500 | H47: =-Inputs!$E$43*(1+Inputs!$E$44)^(H$5-1)*1 -> -2500 | I47: =-Inputs!$E$43*(1+Inputs!$E$44)^(I$5-1)*1 -> -2500 | J47: =-Inputs!$E$43*(1+Inputs!$E$44)^(J$5-1)*1 -> -2500 | ... BJ47: =-Inputs!$E$43*(1+Inputs!$E$44)^(BJ$5-1)*1 -> -2500
A48: Parent app & management software | C48: =-Inputs!$E$45*1 -> -400 | D48: =-Inputs!$E$45*1 -> -400 | E48: =-Inputs!$E$45*1 -> -400 | F48: =-Inputs!$E$45*1 -> -400 | G48: =-Inputs!$E$45*1 -> -400 | H48: =-Inputs!$E$45*1 -> -400 | I48: =-Inputs!$E$45*1 -> -400 | J48: =-Inputs!$E$45*1 -> -400 | ... BJ48: =-Inputs!$E$45*1 -> -400
A49: Card / ACH fees | C49: =-C29*Inputs!$E$46 -> -265.05 | D49: =-D29*Inputs!$E$46 -> -336.83438 | E49: =-E29*Inputs!$E$46 -> -408.61875 | F49: =-F29*Inputs!$E$46 -> -480.40312 | G49: =-G29*Inputs!$E$46 -> -552.1875 | H49: =-H29*Inputs!$E$46 -> -623.97187 | I49: =-I29*Inputs!$E$46 -> -695.75625 | J49: =-J29*Inputs!$E$46 -> -767.54062 | ... BJ49: =-BJ29*Inputs!$E$46 -> -1267.8435
A50: Other G&A | C50: =-Inputs!$E$47*1 -> -1200 | D50: =-Inputs!$E$47*1 -> -1200 | E50: =-Inputs!$E$47*1 -> -1200 | F50: =-Inputs!$E$47*1 -> -1200 | G50: =-Inputs!$E$47*1 -> -1200 | H50: =-Inputs!$E$47*1 -> -1200 | I50: =-Inputs!$E$47*1 -> -1200 | J50: =-Inputs!$E$47*1 -> -1200 | ... BJ50: =-Inputs!$E$47*1 -> -1200
A51: Total operating expenses | C51: =C42+C43+C44+C45+C46+C47+C48+C49+C50 -> -24349.217 | D51: =D42+D43+D44+D45+D46+D47+D48+D49+D50 -> -24421.001 | E51: =E42+E43+E44+E45+E46+E47+E48+E49+E50 -> -24492.785 | F51: =F42+F43+F44+F45+F46+F47+F48+F49+F50 -> -24564.57 | G51: =G42+G43+G44+G45+G46+G47+G48+G49+G50 -> -24636.354 | H51: =H42+H43+H44+H45+H46+H47+H48+H49+H50 -> -24708.139 | I51: =I42+I43+I44+I45+I46+I47+I48+I49+I50 -> -24779.923 | J51: =J42+J43+J44+J45+J46+J47+J48+J49+J50 -> -24851.707 | ... BJ51: =BJ42+BJ43+BJ44+BJ45+BJ46+BJ47+BJ48+BJ49+BJ50 -> -27558.978
A52: EBITDA | C52: =C39+C51 -> -17948.217 | D52: =D39+D51 -> -15963.064 | E52: =E39+E51 -> -20505.41 | F52: =F39+F51 -> -17207.757 | G52: =G39+G51 -> -13910.104 | H52: =H39+H51 -> -10612.451 | I52: =I39+I51 -> -7314.7979 | J52: =J39+J51 -> -7937.1448 | ... BJ52: =BJ39+BJ51 -> 5479.489
A54: Profit after depreciation, interest, tax
A55: EBIT | C55: =C52+C70 -> -21631.55 | D55: =D52+D70 -> -19646.397 | E55: =E52+E70 -> -24188.744 | F55: =F52+F70 -> -20891.091 | G55: =G52+G70 -> -17593.438 | H55: =H52+H70 -> -14295.784 | I55: =I52+I70 -> -10998.131 | J55: =J52+J70 -> -11620.478 | ... BJ55: =BJ52+BJ70 -> 1496.1557
A56: Interest on loan (average balance after drawdown) | C56: =-(C75+C76+C78)/2*Inputs!$E$75/12 -> -1666.6667 | D56: =-(D75+D76+D78)/2*Inputs!$E$75/12 -> -1659.7222 | E56: =-(E75+E76+E78)/2*Inputs!$E$75/12 -> -1645.8333 | F56: =-(F75+F76+F78)/2*Inputs!$E$75/12 -> -1631.9444 | G56: =-(G75+G76+G78)/2*Inputs!$E$75/12 -> -1618.0556 | H56: =-(H75+H76+H78)/2*Inputs!$E$75/12 -> -1604.1667 | I56: =-(I75+I76+I78)/2*Inputs!$E$75/12 -> -1590.2778 | J56: =-(J75+J76+J78)/2*Inputs!$E$75/12 -> -1576.3889 | ... BJ56: =-(BJ75+BJ76+BJ78)/2*Inputs!$E$75/12 -> -854.16667
A57: Pre-tax income | C57: =C55+C56 -> -23298.217 | D57: =D55+D56 -> -21306.119 | E57: =E55+E56 -> -25834.577 | F57: =F55+F56 -> -22523.035 | G57: =G55+G56 -> -19211.493 | H57: =H55+H56 -> -15899.951 | I57: =I55+I56 -> -12588.409 | J57: =J55+J56 -> -13196.867 | ... BJ57: =BJ55+BJ56 -> 641.98902
A58: Helper: cumulative pre-tax income | C58: =C57 -> -23298.217 | D58: =C58+D57 -> -44604.336 | E58: =D58+E57 -> -70438.913 | F58: =E58+F57 -> -92961.948 | G58: =F58+G57 -> -112173.44 | H58: =G58+H57 -> -128073.39 | I58: =H58+I57 -> -140661.8 | J58: =I58+J57 -> -153858.67 | K58: =J58+K57 -> -167663.99 | ... BJ58: =BI58+BJ57 -> -192797.57
A59: Helper: cumulative taxable income (losses carried forward) | C59: =MAX(0,C58) -> 0 | D59: =MAX(C59,D58) -> 0 | E59: =MAX(D59,E58) -> 0 | F59: =MAX(E59,F58) -> 0 | G59: =MAX(F59,G58) -> 0 | H59: =MAX(G59,H58) -> 0 | I59: =MAX(H59,I58) -> 0 | J59: =MAX(I59,J58) -> 0 | K59: =MAX(J59,K58) -> 0 | ... BJ59: =MAX(BI59,BJ58) -> 0
A60: Income tax | C60: =-C59*Inputs!$E$85 -> 0 | D60: =-(D59-C59)*Inputs!$E$85 -> 0 | E60: =-(E59-D59)*Inputs!$E$85 -> 0 | F60: =-(F59-E59)*Inputs!$E$85 -> 0 | G60: =-(G59-F59)*Inputs!$E$85 -> 0 | H60: =-(H59-G59)*Inputs!$E$85 -> 0 | I60: =-(I59-H59)*Inputs!$E$85 -> 0 | J60: =-(J59-I59)*Inputs!$E$85 -> 0 | K60: =-(K59-J59)*Inputs!$E$85 -> 0 | ... BJ60: =-(BJ59-BI59)*Inputs!$E$85 -> 0
A61: Net income | C61: =C57+C60 -> -23298.217 | D61: =D57+D60 -> -21306.119 | E61: =E57+E60 -> -25834.577 | F61: =F57+F60 -> -22523.035 | G61: =G57+G60 -> -19211.493 | H61: =H57+H60 -> -15899.951 | I61: =I57+I60 -> -12588.409 | J61: =J57+J60 -> -13196.867 | ... BJ61: =BJ57+BJ60 -> 641.98902
A63: Fixed assets & capital spending
A64: Build-out of new places | C64: =MAX(0,Inputs!$E$7-Inputs!$E$52)*Inputs!$E$37*Inputs!$E$50 -> 270000 | D64: =IF(AND(D$5>1,MOD(D$4-1,12)=0),Inputs!$E$8,0)*Inputs!$E$37*Inputs!$E$50 -> 0 | E64: =IF(AND(E$5>1,MOD(E$4-1,12)=0),Inputs!$E$8,0)*Inputs!$E$37*Inputs!$E$50 -> 0 | F64: =IF(AND(F$5>1,MOD(F$4-1,12)=0),Inputs!$E$8,0)*Inputs!$E$37*Inputs!$E$50 -> 0 | G64: =IF(AND(G$5>1,MOD(G$4-1,12)=0),Inputs!$E$8,0)*Inputs!$E$37*Inputs!$E$50 -> 0 | H64: =IF(AND(H$5>1,MOD(H$4-1,12)=0),Inputs!$E$8,0)*Inputs!$E$37*Inputs!$E$50 -> 0 | I64: =IF(AND(I$5>1,MOD(I$4-1,12)=0),Inputs!$E$8,0)*Inputs!$E$37*Inputs!$E$50 -> 0 | J64: =IF(AND(J$5>1,MOD(J$4-1,12)=0),Inputs!$E$8,0)*Inputs!$E$37*Inputs!$E$50 -> 0 | K64: =IF(AND(K$5>1,MOD(K$4-1,12)=0),Inputs!$E$8,0)*Inputs!$E$37*Inputs!$E$50 -> 0 | ... BJ64: =IF(AND(BJ$5>1,MOD(BJ$4-1,12)=0),Inputs!$E$8,0)*Inputs!$E$37*Inputs!$E$50 -> 0
A65: Furniture & equipment for new places | C65: =MAX(0,Inputs!$E$7-Inputs!$E$52)*Inputs!$E$51 -> 132000 | D65: =IF(AND(D$5>1,MOD(D$4-1,12)=0),Inputs!$E$8,0)*Inputs!$E$51 -> 0 | E65: =IF(AND(E$5>1,MOD(E$4-1,12)=0),Inputs!$E$8,0)*Inputs!$E$51 -> 0 | F65: =IF(AND(F$5>1,MOD(F$4-1,12)=0),Inputs!$E$8,0)*Inputs!$E$51 -> 0 | G65: =IF(AND(G$5>1,MOD(G$4-1,12)=0),Inputs!$E$8,0)*Inputs!$E$51 -> 0 | H65: =IF(AND(H$5>1,MOD(H$4-1,12)=0),Inputs!$E$8,0)*Inputs!$E$51 -> 0 | I65: =IF(AND(I$5>1,MOD(I$4-1,12)=0),Inputs!$E$8,0)*Inputs!$E$51 -> 0 | J65: =IF(AND(J$5>1,MOD(J$4-1,12)=0),Inputs!$E$8,0)*Inputs!$E$51 -> 0 | K65: =IF(AND(K$5>1,MOD(K$4-1,12)=0),Inputs!$E$8,0)*Inputs!$E$51 -> 0 | ... BJ65: =IF(AND(BJ$5>1,MOD(BJ$4-1,12)=0),Inputs!$E$8,0)*Inputs!$E$51 -> 0
A66: Playground & outdoor area | C66: =IF(C$4=1,Inputs!$E$53,0) -> 40000 | D66: =IF(D$4=1,Inputs!$E$53,0) -> 0 | E66: =IF(E$4=1,Inputs!$E$53,0) -> 0 | F66: =IF(F$4=1,Inputs!$E$53,0) -> 0 | G66: =IF(G$4=1,Inputs!$E$53,0) -> 0 | H66: =IF(H$4=1,Inputs!$E$53,0) -> 0 | I66: =IF(I$4=1,Inputs!$E$53,0) -> 0 | J66: =IF(J$4=1,Inputs!$E$53,0) -> 0 | ... BJ66: =IF(BJ$4=1,Inputs!$E$53,0) -> 0
A67: Equipment replacement (first period of each year from year 2) | C67: =IF(AND(C$5>1,MOD(C$4-1,12)=0),C8*Inputs!$E$54,0) -> 0 | D67: =IF(AND(D$5>1,MOD(D$4-1,12)=0),D8*Inputs!$E$54,0) -> 0 | E67: =IF(AND(E$5>1,MOD(E$4-1,12)=0),E8*Inputs!$E$54,0) -> 0 | F67: =IF(AND(F$5>1,MOD(F$4-1,12)=0),F8*Inputs!$E$54,0) -> 0 | G67: =IF(AND(G$5>1,MOD(G$4-1,12)=0),G8*Inputs!$E$54,0) -> 0 | H67: =IF(AND(H$5>1,MOD(H$4-1,12)=0),H8*Inputs!$E$54,0) -> 0 | I67: =IF(AND(I$5>1,MOD(I$4-1,12)=0),I8*Inputs!$E$54,0) -> 0 | J67: =IF(AND(J$5>1,MOD(J$4-1,12)=0),J8*Inputs!$E$54,0) -> 0 | ... BJ67: =IF(AND(BJ$5>1,MOD(BJ$4-1,12)=0),BJ8*Inputs!$E$54,0) -> 0
A68: Capital spending | C68: =C64+C65+C66+C67 -> 442000 | D68: =D64+D65+D66+D67 -> 0 | E68: =E64+E65+E66+E67 -> 0 | F68: =F64+F65+F66+F67 -> 0 | G68: =G64+G65+G66+G67 -> 0 | H68: =H64+H65+H66+H67 -> 0 | I68: =I64+I65+I66+I67 -> 0 | J68: =J64+J65+J66+J67 -> 0 | ... BJ68: =BJ64+BJ65+BJ66+BJ67 -> 0
A69: Fixed assets at cost | C69: =C68 -> 442000 | D69: =C69+D68 -> 442000 | E69: =D69+E68 -> 442000 | F69: =E69+F68 -> 442000 | G69: =F69+G68 -> 442000 | H69: =G69+H68 -> 442000 | I69: =H69+I68 -> 442000 | J69: =I69+J68 -> 442000 | K69: =J69+K68 -> 442000 | ... BJ69: =BI69+BJ68 -> 478000
A70: Depreciation | C70: =-MIN(C69/MAX(1,Inputs!$E$84*12),C68) -> -3683.3333 | D70: =-MIN(D69/MAX(1,Inputs!$E$84*12),C72+D68) -> -3683.3333 | E70: =-MIN(E69/MAX(1,Inputs!$E$84*12),D72+E68) -> -3683.3333 | F70: =-MIN(F69/MAX(1,Inputs!$E$84*12),E72+F68) -> -3683.3333 | G70: =-MIN(G69/MAX(1,Inputs!$E$84*12),F72+G68) -> -3683.3333 | H70: =-MIN(H69/MAX(1,Inputs!$E$84*12),G72+H68) -> -3683.3333 | I70: =-MIN(I69/MAX(1,Inputs!$E$84*12),H72+I68) -> -3683.3333 | J70: =-MIN(J69/MAX(1,Inputs!$E$84*12),I72+J68) -> -3683.3333 | K70: =-MIN(K69/MAX(1,Inputs!$E$84*12),J72+K68) -> -3683.3333 | ... BJ70: =-MIN(BJ69/MAX(1,Inputs!$E$84*12),BI72+BJ68) -> -3983.3333
A71: Accumulated depreciation | C71: =C70 -> -3683.3333 | D71: =C71+D70 -> -7366.6667 | E71: =D71+E70 -> -11050 | F71: =E71+F70 -> -14733.333 | G71: =F71+G70 -> -18416.667 | H71: =G71+H70 -> -22100 | I71: =H71+I70 -> -25783.333 | J71: =I71+J70 -> -29466.667 | K71: =J71+K70 -> -33150 | ... BJ71: =BI71+BJ70 -> -230000
A72: Net fixed assets | C72: =C69+C71 -> 438316.67 | D72: =D69+D71 -> 434633.33 | E72: =E69+E71 -> 430950 | F72: =F69+F71 -> 427266.67 | G72: =G69+G71 -> 423583.33 | H72: =H69+H71 -> 419900 | I72: =I69+I71 -> 416216.67 | J72: =J69+J71 -> 412533.33 | ... BJ72: =BJ69+BJ71 -> 248000
A74: Debt
A75: Loan — opening balance | C75: =0 -> 0 | D75: =C78 -> 250000 | E75: =D78 -> 247916.67 | F75: =E78 -> 245833.33 | G75: =F78 -> 243750 | H75: =G78 -> 241666.67 | I75: =H78 -> 239583.33 | J75: =I78 -> 237500 | K75: =J78 -> 235416.67 | ... BJ75: =BI78 -> 129166.67
A76: Loan drawdown | C76: =IF(C$4=1,Inputs!$E$74,0) -> 250000 | D76: =IF(D$4=1,Inputs!$E$74,0) -> 0 | E76: =IF(E$4=1,Inputs!$E$74,0) -> 0 | F76: =IF(F$4=1,Inputs!$E$74,0) -> 0 | G76: =IF(G$4=1,Inputs!$E$74,0) -> 0 | H76: =IF(H$4=1,Inputs!$E$74,0) -> 0 | I76: =IF(I$4=1,Inputs!$E$74,0) -> 0 | J76: =IF(J$4=1,Inputs!$E$74,0) -> 0 | ... BJ76: =IF(BJ$4=1,Inputs!$E$74,0) -> 0
A77: Loan repayment | C77: =-MIN(C75,Inputs!$E$74/MAX(1,Inputs!$E$76*12)) -> 0 | D77: =-MIN(D75,Inputs!$E$74/MAX(1,Inputs!$E$76*12)) -> -2083.3333 | E77: =-MIN(E75,Inputs!$E$74/MAX(1,Inputs!$E$76*12)) -> -2083.3333 | F77: =-MIN(F75,Inputs!$E$74/MAX(1,Inputs!$E$76*12)) -> -2083.3333 | G77: =-MIN(G75,Inputs!$E$74/MAX(1,Inputs!$E$76*12)) -> -2083.3333 | H77: =-MIN(H75,Inputs!$E$74/MAX(1,Inputs!$E$76*12)) -> -2083.3333 | I77: =-MIN(I75,Inputs!$E$74/MAX(1,Inputs!$E$76*12)) -> -2083.3333 | J77: =-MIN(J75,Inputs!$E$74/MAX(1,Inputs!$E$76*12)) -> -2083.3333 | ... BJ77: =-MIN(BJ75,Inputs!$E$74/MAX(1,Inputs!$E$76*12)) -> -2083.3333
A78: Loan — closing balance | C78: =C75+C76+C77 -> 250000 | D78: =D75+D76+D77 -> 247916.67 | E78: =E75+E76+E77 -> 245833.33 | F78: =F75+F76+F77 -> 243750 | G78: =G75+G76+G77 -> 241666.67 | H78: =H75+H76+H77 -> 239583.33 | I78: =I75+I76+I77 -> 237500 | J78: =J75+J76+J77 -> 235416.67 | ... BJ78: =BJ75+BJ76+BJ77 -> 127083.33
A80: Working capital
A81: Accounts receivable | C81: =C32*Inputs!$E$79/30 -> 6763.9 | D81: =D32*Inputs!$E$79/30 -> 7815.7896 | E81: =E32*Inputs!$E$79/30 -> 9436.4292 | F81: =F32*Inputs!$E$79/30 -> 11057.069 | G81: =G32*Inputs!$E$79/30 -> 12677.708 | H81: =H32*Inputs!$E$79/30 -> 14298.348 | I81: =I32*Inputs!$E$79/30 -> 15918.987 | J81: =J32*Inputs!$E$79/30 -> 17539.627 | ... BJ81: =BJ32*Inputs!$E$79/30 -> 28623.462
A82: Inventory | C82: =-C38*Inputs!$E$80/30 -> 920.8 | D82: =-D38*Inputs!$E$80/30 -> 957.85 | E82: =-E38*Inputs!$E$80/30 -> 1778.9 | F82: =-F38*Inputs!$E$80/30 -> 1815.95 | G82: =-G38*Inputs!$E$80/30 -> 1853 | H82: =-H38*Inputs!$E$80/30 -> 1890.05 | I82: =-I38*Inputs!$E$80/30 -> 1927.1 | J82: =-J38*Inputs!$E$80/30 -> 2356.15 | ... BJ82: =-BJ38*Inputs!$E$80/30 -> 3301.5675
A83: Accounts payable | C83: =-C38*Inputs!$E$81/30 -> 3376.2667 | D83: =-D38*Inputs!$E$81/30 -> 3512.1167 | E83: =-E38*Inputs!$E$81/30 -> 6522.6333 | F83: =-F38*Inputs!$E$81/30 -> 6658.4833 | G83: =-G38*Inputs!$E$81/30 -> 6794.3333 | H83: =-H38*Inputs!$E$81/30 -> 6930.1833 | I83: =-I38*Inputs!$E$81/30 -> 7066.0333 | J83: =-J38*Inputs!$E$81/30 -> 8639.2167 | ... BJ83: =-BJ38*Inputs!$E$81/30 -> 12105.748
A84: (Increase) / decrease in receivables | C84: =-C81 -> -6763.9 | D84: =C81-D81 -> -1051.8896 | E84: =D81-E81 -> -1620.6396 | F84: =E81-F81 -> -1620.6396 | G84: =F81-G81 -> -1620.6396 | H84: =G81-H81 -> -1620.6396 | I84: =H81-I81 -> -1620.6396 | J84: =I81-J81 -> -1620.6396 | K84: =J81-K81 -> -1620.6396 | ... BJ84: =BI81-BJ81 -> 0
A85: (Increase) / decrease in inventory | C85: =-C82 -> -920.8 | D85: =C82-D82 -> -37.05 | E85: =D82-E82 -> -821.05 | F85: =E82-F82 -> -37.05 | G85: =F82-G82 -> -37.05 | H85: =G82-H82 -> -37.05 | I85: =H82-I82 -> -37.05 | J85: =I82-J82 -> -429.05 | K85: =J82-K82 -> -429.05 | ... BJ85: =BI82-BJ82 -> 0
A86: Increase / (decrease) in payables | C86: =C83 -> 3376.2667 | D86: =D83-C83 -> 135.85 | E86: =E83-D83 -> 3010.5167 | F86: =F83-E83 -> 135.85 | G86: =G83-F83 -> 135.85 | H86: =H83-G83 -> 135.85 | I86: =I83-H83 -> 135.85 | J86: =J83-I83 -> 1573.1833 | K86: =K83-J83 -> 1573.1833 | ... BJ86: =BJ83-BI83 -> 0
A88: Cash flow
A89: Operating cash flow | C89: =C61-C70+C84+C85+C86 -> -23923.317 | D89: =D61-D70+D84+D85+D86 -> -18575.875 | E89: =E61-E70+E84+E85+E86 -> -21582.417 | F89: =F61-F70+F84+F85+F86 -> -20361.541 | G89: =G61-G70+G84+G85+G86 -> -17049.999 | H89: =H61-H70+H84+H85+H86 -> -13738.457 | I89: =I61-I70+I84+I85+I86 -> -10426.915 | J89: =J61-J70+J84+J85+J86 -> -9990.0399 | ... BJ89: =BJ61-BJ70+BJ84+BJ85+BJ86 -> 4625.3224
A90: Investing cash flow (capex) | C90: =-C68 -> -442000 | D90: =-D68 -> 0 | E90: =-E68 -> 0 | F90: =-F68 -> 0 | G90: =-G68 -> 0 | H90: =-H68 -> 0 | I90: =-I68 -> 0 | J90: =-J68 -> 0 | ... BJ90: =-BJ68 -> 0
A91: Equity raised | C91: =IF(C$4=1,Inputs!$E$73,0) -> 450000 | D91: =IF(D$4=1,Inputs!$E$73,0) -> 0 | E91: =IF(E$4=1,Inputs!$E$73,0) -> 0 | F91: =IF(F$4=1,Inputs!$E$73,0) -> 0 | G91: =IF(G$4=1,Inputs!$E$73,0) -> 0 | H91: =IF(H$4=1,Inputs!$E$73,0) -> 0 | I91: =IF(I$4=1,Inputs!$E$73,0) -> 0 | J91: =IF(J$4=1,Inputs!$E$73,0) -> 0 | ... BJ91: =IF(BJ$4=1,Inputs!$E$73,0) -> 0
A92: Financing cash flow | C92: =C91+C76+C77 -> 700000 | D92: =D91+D76+D77 -> -2083.3333 | E92: =E91+E76+E77 -> -2083.3333 | F92: =F91+F76+F77 -> -2083.3333 | G92: =G91+G76+G77 -> -2083.3333 | H92: =H91+H76+H77 -> -2083.3333 | I92: =I91+I76+I77 -> -2083.3333 | J92: =J91+J76+J77 -> -2083.3333 | ... BJ92: =BJ91+BJ76+BJ77 -> -2083.3333
A93: Net cash flow | C93: =C89+C90+C92 -> 234076.68 | D93: =D89+D90+D92 -> -20659.209 | E93: =E89+E90+E92 -> -23665.75 | F93: =F89+F90+F92 -> -22444.875 | G93: =G89+G90+G92 -> -19133.333 | H93: =H89+H90+H92 -> -15821.791 | I93: =I89+I90+I92 -> -12510.249 | J93: =J89+J90+J92 -> -12073.373 | ... BJ93: =BJ89+BJ90+BJ92 -> 2541.989
A94: Opening cash | C94: =0 -> 0 | D94: =C95 -> 234076.68 | E94: =D95 -> 213417.47 | F94: =E95 -> 189751.72 | G94: =F95 -> 167306.85 | H94: =G95 -> 148173.52 | I94: =H95 -> 132351.73 | J94: =I95 -> 119841.48 | K94: =J95 -> 107768.1 | ... BJ94: =BI95 -> 113924.5
A95: Closing cash | C95: =C94+C93 -> 234076.68 | D95: =D94+D93 -> 213417.47 | E95: =E94+E93 -> 189751.72 | F95: =F94+F93 -> 167306.85 | G95: =G94+G93 -> 148173.52 | H95: =H94+H93 -> 132351.73 | I95: =I94+I93 -> 119841.48 | J95: =J94+J93 -> 107768.1 | ... BJ95: =BJ94+BJ93 -> 116466.49
A96: Helper: EBITDA positive (1/0) | C96: =IF(C52>0,1,0) -> 0 | D96: =IF(D52>0,1,0) -> 0 | E96: =IF(E52>0,1,0) -> 0 | F96: =IF(F52>0,1,0) -> 0 | G96: =IF(G52>0,1,0) -> 0 | H96: =IF(H52>0,1,0) -> 0 | I96: =IF(I52>0,1,0) -> 0 | J96: =IF(J52>0,1,0) -> 0 | ... BJ96: =IF(BJ52>0,1,0) -> 1
A98: Goal modules
A99: Helper: net income positive (1/0) | C99: =IF(C61>0,1,0) -> 0 | D99: =IF(D61>0,1,0) -> 0 | E99: =IF(E61>0,1,0) -> 0 | F99: =IF(F61>0,1,0) -> 0 | G99: =IF(G61>0,1,0) -> 0 | H99: =IF(H61>0,1,0) -> 0 | I99: =IF(I61>0,1,0) -> 0 | J99: =IF(J61>0,1,0) -> 0 | ... BJ99: =IF(BJ61>0,1,0) -> 1
A100: Cash flow before financing (operating + investing) | C100: =C89+C90 -> -465923.32 | D100: =D89+D90 -> -18575.875 | E100: =E89+E90 -> -21582.417 | F100: =F89+F90 -> -20361.541 | G100: =G89+G90 -> -17049.999 | H100: =H89+H90 -> -13738.457 | I100: =I89+I90 -> -10426.915 | J100: =J89+J90 -> -9990.0399 | ... BJ100: =BJ89+BJ90 -> 4625.3224
A101: Cumulative cash flow before financing | C101: =C100 -> -465923.32 | D101: =C101+D100 -> -484499.19 | E101: =D101+E100 -> -506081.61 | F101: =E101+F100 -> -526443.15 | G101: =F101+G100 -> -543493.15 | H101: =G101+H100 -> -557231.61 | I101: =H101+I100 -> -567658.52 | J101: =I101+J100 -> -577648.56 | K101: =J101+K100 -> -588247.06 | ... BJ101: =BI101+BJ100 -> -460616.85
A102: Helper: lowest cumulative cash flow so far | C102: =C101 -> -465923.32 | D102: =MIN(C102,D101) -> -484499.19 | E102: =MIN(D102,E101) -> -506081.61 | F102: =MIN(E102,F101) -> -526443.15 | G102: =MIN(F102,G101) -> -543493.15 | H102: =MIN(G102,H101) -> -557231.61 | I102: =MIN(H102,I101) -> -567658.52 | J102: =MIN(I102,J101) -> -577648.56 | K102: =MIN(J102,K101) -> -588247.06 | ... BJ102: =MIN(BI102,BJ101) -> -610907.64
A103: Helper: investment paid back (1/0) | C103: =IF(AND(C101>=0,C102<0),1,0) -> 0 | D103: =IF(AND(D101>=0,D102<0),1,0) -> 0 | E103: =IF(AND(E101>=0,E102<0),1,0) -> 0 | F103: =IF(AND(F101>=0,F102<0),1,0) -> 0 | G103: =IF(AND(G101>=0,G102<0),1,0) -> 0 | H103: =IF(AND(H101>=0,H102<0),1,0) -> 0 | I103: =IF(AND(I101>=0,I102<0),1,0) -> 0 | J103: =IF(AND(J101>=0,J102<0),1,0) -> 0 | ... BJ103: =IF(AND(BJ101>=0,BJ102<0),1,0) -> 0
A104: Unlevered free cash flow (operating + after-tax interest − capex) | C104: =C89-C56*(1-Inputs!$E$85)+C90 -> -464606.65 | D104: =D89-D56*(1-Inputs!$E$85)+D90 -> -17264.695 | E104: =E89-E56*(1-Inputs!$E$85)+E90 -> -20282.208 | F104: =F89-F56*(1-Inputs!$E$85)+F90 -> -19072.305 | G104: =G89-G56*(1-Inputs!$E$85)+G90 -> -15771.735 | H104: =H89-H56*(1-Inputs!$E$85)+H90 -> -12471.166 | I104: =I89-I56*(1-Inputs!$E$85)+I90 -> -9170.5958 | J104: =J89-J56*(1-Inputs!$E$85)+J90 -> -8744.6927 | ... BJ104: =BJ89-BJ56*(1-Inputs!$E$85)+BJ90 -> 5300.114
A106: Balance sheet
A107: Paid-in capital | C107: =C91 -> 450000 | D107: =C107+D91 -> 450000 | E107: =D107+E91 -> 450000 | F107: =E107+F91 -> 450000 | G107: =F107+G91 -> 450000 | H107: =G107+H91 -> 450000 | I107: =H107+I91 -> 450000 | J107: =I107+J91 -> 450000 | K107: =J107+K91 -> 450000 | ... BJ107: =BI107+BJ91 -> 450000
A108: Retained earnings | C108: =C61 -> -23298.217 | D108: =C108+D61 -> -44604.336 | E108: =D108+E61 -> -70438.913 | F108: =E108+F61 -> -92961.948 | G108: =F108+G61 -> -112173.44 | H108: =G108+H61 -> -128073.39 | I108: =H108+I61 -> -140661.8 | J108: =I108+J61 -> -153858.67 | K108: =J108+K61 -> -167663.99 | ... BJ108: =BI108+BJ61 -> -192797.57
A109: Total assets | C109: =C95+C81+C82+C72 -> 680078.05 | D109: =D95+D81+D82+D72 -> 656824.45 | E109: =E95+E81+E82+E72 -> 631917.05 | F109: =F95+F81+F82+F72 -> 607446.54 | G109: =G95+G81+G82+G72 -> 586287.56 | H109: =H95+H81+H82+H72 -> 568440.12 | I109: =I95+I81+I82+I72 -> 553904.23 | J109: =J95+J81+J82+J72 -> 540197.22 | ... BJ109: =BJ95+BJ81+BJ82+BJ72 -> 396391.52
A110: Total liabilities | C110: =C83+C78 -> 253376.27 | D110: =D83+D78 -> 251428.78 | E110: =E83+E78 -> 252355.97 | F110: =F83+F78 -> 250408.48 | G110: =G83+G78 -> 248461 | H110: =H83+H78 -> 246513.52 | I110: =I83+I78 -> 244566.03 | J110: =J83+J78 -> 244055.88 | ... BJ110: =BJ83+BJ78 -> 139189.08
A111: Total equity | C111: =C107+C108 -> 426701.78 | D111: =D107+D108 -> 405395.66 | E111: =E107+E108 -> 379561.09 | F111: =F107+F108 -> 357038.05 | G111: =G107+G108 -> 337826.56 | H111: =H107+H108 -> 321926.61 | I111: =I107+I108 -> 309338.2 | J111: =J107+J108 -> 296141.33 | ... BJ111: =BJ107+BJ108 -> 257202.43
A112: Total liabilities & equity | C112: =C110+C111 -> 680078.05 | D112: =D110+D111 -> 656824.45 | E112: =E110+E111 -> 631917.05 | F112: =F110+F111 -> 607446.54 | G112: =G110+G111 -> 586287.56 | H112: =H110+H111 -> 568440.12 | I112: =I110+I111 -> 553904.23 | J112: =J110+J111 -> 540197.22 | ... BJ112: =BJ110+BJ111 -> 396391.52
...

Sheet Headcount
A1: Headcount & payroll | D1: =HYPERLINK("#'Cover'!A1","◂ Contents") -> ◂ Contents
A2: $ unless stated; costs shown as negatives. Every period uses the same formula.
A3: Month | C3: M1 | D3: M2 | E3: M3 | F3: M4 | G3: M5 | H3: M6 | I3: M7 | J3: M8 | K3: M9 | L3: M10 | M3: M11 | N3: M12 | O3: M13 | P3: M14 | Q3: M15 | R3: M16 | S3: M17 | T3: M18 | U3: M19 | V3: M20 | W3: M21 | X3: M22 | Y3: M23 | Z3: M24 | AA3: M25 | AB3: M26 | AC3: M27 | AD3: M28 | AE3: M29 | AF3: M30 | AG3: M31 | AH3: M32 | AI3: M33 | AJ3: M34 | AK3: M35 | AL3: M36 | AM3: M37 | AN3: M38 | AO3: M39 | AP3: M40 | AQ3: M41 | AR3: M42 | AS3: M43 | AT3: M44 | AU3: M45 | AV3: M46 | AW3: M47 | AX3: M48 | AY3: M49 | AZ3: M50 | BA3: M51 | BB3: M52 | BC3: M53 | BD3: M54 | BE3: M55 | BF3: M56 | BG3: M57 | BH3: M58 | BI3: M59 | BJ3: M60
A4: Period # | C4: 1 | D4: 2 | E4: 3 | F4: 4 | G4: 5 | H4: 6 | I4: 7 | J4: 8 | K4: 9 | L4: 10 | M4: 11 | N4: 12 | O4: 13 | P4: 14 | Q4: 15 | R4: 16 | S4: 17 | T4: 18 | U4: 19 | V4: 20 | W4: 21 | X4: 22 | Y4: 23 | Z4: 24 | AA4: 25 | AB4: 26 | AC4: 27 | AD4: 28 | AE4: 29 | AF4: 30 | AG4: 31 | AH4: 32 | AI4: 33 | AJ4: 34 | AK4: 35 | AL4: 36 | AM4: 37 | AN4: 38 | AO4: 39 | AP4: 40 | AQ4: 41 | AR4: 42 | AS4: 43 | AT4: 44 | AU4: 45 | AV4: 46 | AW4: 47 | AX4: 48 | AY4: 49 | AZ4: 50 | BA4: 51 | BB4: 52 | BC4: 53 | BD4: 54 | BE4: 55 | BF4: 56 | BG4: 57 | BH4: 58 | BI4: 59 | BJ4: 60
A5: Year # | C5: =ROUNDUP(C4*1/12,0) -> 1 | D5: =ROUNDUP(D4*1/12,0) -> 1 | E5: =ROUNDUP(E4*1/12,0) -> 1 | F5: =ROUNDUP(F4*1/12,0) -> 1 | G5: =ROUNDUP(G4*1/12,0) -> 1 | H5: =ROUNDUP(H4*1/12,0) -> 1 | I5: =ROUNDUP(I4*1/12,0) -> 1 | J5: =ROUNDUP(J4*1/12,0) -> 1 | ... BJ5: =ROUNDUP(BJ4*1/12,0) -> 5
A7: Headcount (FTE)
A8: Centre director — FTE | C8: =Inputs!$E$57*(1+Inputs!$E$59)^(C$5-1)*MAX(0,MIN(1,C$4*1-Inputs!$E$60+1))/1 -> 1 | D8: =Inputs!$E$57*(1+Inputs!$E$59)^(D$5-1)*MAX(0,MIN(1,D$4*1-Inputs!$E$60+1))/1 -> 1 | E8: =Inputs!$E$57*(1+Inputs!$E$59)^(E$5-1)*MAX(0,MIN(1,E$4*1-Inputs!$E$60+1))/1 -> 1 | F8: =Inputs!$E$57*(1+Inputs!$E$59)^(F$5-1)*MAX(0,MIN(1,F$4*1-Inputs!$E$60+1))/1 -> 1 | G8: =Inputs!$E$57*(1+Inputs!$E$59)^(G$5-1)*MAX(0,MIN(1,G$4*1-Inputs!$E$60+1))/1 -> 1 | H8: =Inputs!$E$57*(1+Inputs!$E$59)^(H$5-1)*MAX(0,MIN(1,H$4*1-Inputs!$E$60+1))/1 -> 1 | I8: =Inputs!$E$57*(1+Inputs!$E$59)^(I$5-1)*MAX(0,MIN(1,I$4*1-Inputs!$E$60+1))/1 -> 1 | J8: =Inputs!$E$57*(1+Inputs!$E$59)^(J$5-1)*MAX(0,MIN(1,J$4*1-Inputs!$E$60+1))/1 -> 1 | ... BJ8: =Inputs!$E$57*(1+Inputs!$E$59)^(BJ$5-1)*MAX(0,MIN(1,BJ$4*1-Inputs!$E$60+1))/1 -> 1
A9: Office & enrolment coordinator — FTE | C9: =Inputs!$E$61*(1+Inputs!$E$63)^(C$5-1)*MAX(0,MIN(1,C$4*1-Inputs!$E$64+1))/1 -> 0.5 | D9: =Inputs!$E$61*(1+Inputs!$E$63)^(D$5-1)*MAX(0,MIN(1,D$4*1-Inputs!$E$64+1))/1 -> 0.5 | E9: =Inputs!$E$61*(1+Inputs!$E$63)^(E$5-1)*MAX(0,MIN(1,E$4*1-Inputs!$E$64+1))/1 -> 0.5 | F9: =Inputs!$E$61*(1+Inputs!$E$63)^(F$5-1)*MAX(0,MIN(1,F$4*1-Inputs!$E$64+1))/1 -> 0.5 | G9: =Inputs!$E$61*(1+Inputs!$E$63)^(G$5-1)*MAX(0,MIN(1,G$4*1-Inputs!$E$64+1))/1 -> 0.5 | H9: =Inputs!$E$61*(1+Inputs!$E$63)^(H$5-1)*MAX(0,MIN(1,H$4*1-Inputs!$E$64+1))/1 -> 0.5 | I9: =Inputs!$E$61*(1+Inputs!$E$63)^(I$5-1)*MAX(0,MIN(1,I$4*1-Inputs!$E$64+1))/1 -> 0.5 | J9: =Inputs!$E$61*(1+Inputs!$E$63)^(J$5-1)*MAX(0,MIN(1,J$4*1-Inputs!$E$64+1))/1 -> 0.5 | ... BJ9: =Inputs!$E$61*(1+Inputs!$E$63)^(BJ$5-1)*MAX(0,MIN(1,BJ$4*1-Inputs!$E$64+1))/1 -> 0.5
A10: Cook / kitchen assistant — FTE | C10: =Inputs!$E$65*(1+Inputs!$E$67)^(C$5-1)*MAX(0,MIN(1,C$4*1-Inputs!$E$68+1))/1 -> 0.5 | D10: =Inputs!$E$65*(1+Inputs!$E$67)^(D$5-1)*MAX(0,MIN(1,D$4*1-Inputs!$E$68+1))/1 -> 0.5 | E10: =Inputs!$E$65*(1+Inputs!$E$67)^(E$5-1)*MAX(0,MIN(1,E$4*1-Inputs!$E$68+1))/1 -> 0.5 | F10: =Inputs!$E$65*(1+Inputs!$E$67)^(F$5-1)*MAX(0,MIN(1,F$4*1-Inputs!$E$68+1))/1 -> 0.5 | G10: =Inputs!$E$65*(1+Inputs!$E$67)^(G$5-1)*MAX(0,MIN(1,G$4*1-Inputs!$E$68+1))/1 -> 0.5 | H10: =Inputs!$E$65*(1+Inputs!$E$67)^(H$5-1)*MAX(0,MIN(1,H$4*1-Inputs!$E$68+1))/1 -> 0.5 | I10: =Inputs!$E$65*(1+Inputs!$E$67)^(I$5-1)*MAX(0,MIN(1,I$4*1-Inputs!$E$68+1))/1 -> 0.5 | J10: =Inputs!$E$65*(1+Inputs!$E$67)^(J$5-1)*MAX(0,MIN(1,J$4*1-Inputs!$E$68+1))/1 -> 0.5 | ... BJ10: =Inputs!$E$65*(1+Inputs!$E$67)^(BJ$5-1)*MAX(0,MIN(1,BJ$4*1-Inputs!$E$68+1))/1 -> 0.5
A11: Total FTE | C11: =C8+C9+C10 -> 2 | D11: =D8+D9+D10 -> 2 | E11: =E8+E9+E10 -> 2 | F11: =F8+F9+F10 -> 2 | G11: =G8+G9+G10 -> 2 | H11: =H8+H9+H10 -> 2 | I11: =I8+I9+I10 -> 2 | J11: =J8+J9+J10 -> 2 | ... BJ11: =BJ8+BJ9+BJ10 -> 2
A13: Payroll cost (salary + taxes & benefits)
A14: Centre director — payroll cost | C14: =-C8*Inputs!$E$58/12*1*(1+Inputs!$E$69)*(1+Inputs!$E$70)^(C$5-1) -> -5786.6667 | D14: =-D8*Inputs!$E$58/12*1*(1+Inputs!$E$69)*(1+Inputs!$E$70)^(D$5-1) -> -5786.6667 | E14: =-E8*Inputs!$E$58/12*1*(1+Inputs!$E$69)*(1+Inputs!$E$70)^(E$5-1) -> -5786.6667 | F14: =-F8*Inputs!$E$58/12*1*(1+Inputs!$E$69)*(1+Inputs!$E$70)^(F$5-1) -> -5786.6667 | G14: =-G8*Inputs!$E$58/12*1*(1+Inputs!$E$69)*(1+Inputs!$E$70)^(G$5-1) -> -5786.6667 | H14: =-H8*Inputs!$E$58/12*1*(1+Inputs!$E$69)*(1+Inputs!$E$70)^(H$5-1) -> -5786.6667 | I14: =-I8*Inputs!$E$58/12*1*(1+Inputs!$E$69)*(1+Inputs!$E$70)^(I$5-1) -> -5786.6667 | J14: =-J8*Inputs!$E$58/12*1*(1+Inputs!$E$69)*(1+Inputs!$E$70)^(J$5-1) -> -5786.6667 | ... BJ14: =-BJ8*Inputs!$E$58/12*1*(1+Inputs!$E$69)*(1+Inputs!$E$70)^(BJ$5-1) -> -6512.9443
A15: Office & enrolment coordinator — payroll cost | C15: =-C9*Inputs!$E$62/12*1*(1+Inputs!$E$69)*(1+Inputs!$E$70)^(C$5-1) -> -1773.3333 | D15: =-D9*Inputs!$E$62/12*1*(1+Inputs!$E$69)*(1+Inputs!$E$70)^(D$5-1) -> -1773.3333 | E15: =-E9*Inputs!$E$62/12*1*(1+Inputs!$E$69)*(1+Inputs!$E$70)^(E$5-1) -> -1773.3333 | F15: =-F9*Inputs!$E$62/12*1*(1+Inputs!$E$69)*(1+Inputs!$E$70)^(F$5-1) -> -1773.3333 | G15: =-G9*Inputs!$E$62/12*1*(1+Inputs!$E$69)*(1+Inputs!$E$70)^(G$5-1) -> -1773.3333 | H15: =-H9*Inputs!$E$62/12*1*(1+Inputs!$E$69)*(1+Inputs!$E$70)^(H$5-1) -> -1773.3333 | I15: =-I9*Inputs!$E$62/12*1*(1+Inputs!$E$69)*(1+Inputs!$E$70)^(I$5-1) -> -1773.3333 | J15: =-J9*Inputs!$E$62/12*1*(1+Inputs!$E$69)*(1+Inputs!$E$70)^(J$5-1) -> -1773.3333 | ... BJ15: =-BJ9*Inputs!$E$62/12*1*(1+Inputs!$E$69)*(1+Inputs!$E$70)^(BJ$5-1) -> -1995.9023
A16: Cook / kitchen assistant — payroll cost | C16: =-C10*Inputs!$E$66/12*1*(1+Inputs!$E$69)*(1+Inputs!$E$70)^(C$5-1) -> -1586.6667 | D16: =-D10*Inputs!$E$66/12*1*(1+Inputs!$E$69)*(1+Inputs!$E$70)^(D$5-1) -> -1586.6667 | E16: =-E10*Inputs!$E$66/12*1*(1+Inputs!$E$69)*(1+Inputs!$E$70)^(E$5-1) -> -1586.6667 | F16: =-F10*Inputs!$E$66/12*1*(1+Inputs!$E$69)*(1+Inputs!$E$70)^(F$5-1) -> -1586.6667 | G16: =-G10*Inputs!$E$66/12*1*(1+Inputs!$E$69)*(1+Inputs!$E$70)^(G$5-1) -> -1586.6667 | H16: =-H10*Inputs!$E$66/12*1*(1+Inputs!$E$69)*(1+Inputs!$E$70)^(H$5-1) -> -1586.6667 | I16: =-I10*Inputs!$E$66/12*1*(1+Inputs!$E$69)*(1+Inputs!$E$70)^(I$5-1) -> -1586.6667 | J16: =-J10*Inputs!$E$66/12*1*(1+Inputs!$E$69)*(1+Inputs!$E$70)^(J$5-1) -> -1586.6667 | ... BJ16: =-BJ10*Inputs!$E$66/12*1*(1+Inputs!$E$69)*(1+Inputs!$E$70)^(BJ$5-1) -> -1785.8073
A17: Total payroll | C17: =C14+C15+C16 -> -9146.6667 | D17: =D14+D15+D16 -> -9146.6667 | E17: =E14+E15+E16 -> -9146.6667 | F17: =F14+F15+F16 -> -9146.6667 | G17: =G14+G15+G16 -> -9146.6667 | H17: =H14+H15+H16 -> -9146.6667 | I17: =I14+I15+I16 -> -9146.6667 | J17: =J14+J15+J16 -> -9146.6667 | ... BJ17: =BJ14+BJ15+BJ16 -> -10294.654

Sheet Scenario calc
A1: Scenario calculation — Low, Base and High side by side | D1: =HYPERLINK("#'Cover'!A1","◂ Contents") -> ◂ Contents
A2: The model's period calculation, copied three times; each copy reads its own Inputs column. Feeds the Scenarios sheet only.
A4: Low scenario — reads Inputs column B
A5: Month | C5: M1 | D5: M2 | E5: M3 | F5: M4 | G5: M5 | H5: M6 | I5: M7 | J5: M8 | K5: M9 | L5: M10 | M5: M11 | N5: M12 | O5: M13 | P5: M14 | Q5: M15 | R5: M16 | S5: M17 | T5: M18 | U5: M19 | V5: M20 | W5: M21 | X5: M22 | Y5: M23 | Z5: M24 | AA5: M25 | AB5: M26 | AC5: M27 | AD5: M28 | AE5: M29 | AF5: M30 | AG5: M31 | AH5: M32 | AI5: M33 | AJ5: M34 | AK5: M35 | AL5: M36 | AM5: M37 | AN5: M38 | AO5: M39 | AP5: M40 | AQ5: M41 | AR5: M42 | AS5: M43 | AT5: M44 | AU5: M45 | AV5: M46 | AW5: M47 | AX5: M48 | AY5: M49 | AZ5: M50 | BA5: M51 | BB5: M52 | BC5: M53 | BD5: M54 | BE5: M55 | BF5: M56 | BG5: M57 | BH5: M58 | BI5: M59 | BJ5: M60
A6: Period # | C6: 1 | D6: 2 | E6: 3 | F6: 4 | G6: 5 | H6: 6 | I6: 7 | J6: 8 | K6: 9 | L6: 10 | M6: 11 | N6: 12 | O6: 13 | P6: 14 | Q6: 15 | R6: 16 | S6: 17 | T6: 18 | U6: 19 | V6: 20 | W6: 21 | X6: 22 | Y6: 23 | Z6: 24 | AA6: 25 | AB6: 26 | AC6: 27 | AD6: 28 | AE6: 29 | AF6: 30 | AG6: 31 | AH6: 32 | AI6: 33 | AJ6: 34 | AK6: 35 | AL6: 36 | AM6: 37 | AN6: 38 | AO6: 39 | AP6: 40 | AQ6: 41 | AR6: 42 | AS6: 43 | AT6: 44 | AU6: 45 | AV6: 46 | AW6: 47 | AX6: 48 | AY6: 49 | AZ6: 50 | BA6: 51 | BB6: 52 | BC6: 53 | BD6: 54 | BE6: 55 | BF6: 56 | BG6: 57 | BH6: 58 | BI6: 59 | BJ6: 60
A7: Year # | C7: =ROUNDUP(C6*1/12,0) -> 1 | D7: =ROUNDUP(D6*1/12,0) -> 1 | E7: =ROUNDUP(E6*1/12,0) -> 1 | F7: =ROUNDUP(F6*1/12,0) -> 1 | G7: =ROUNDUP(G6*1/12,0) -> 1 | H7: =ROUNDUP(H6*1/12,0) -> 1 | I7: =ROUNDUP(I6*1/12,0) -> 1 | J7: =ROUNDUP(J6*1/12,0) -> 1 | ... BJ7: =ROUNDUP(BJ6*1/12,0) -> 5
A9: Places & enrolment
A10: Licensed places | C10: =Inputs!$B$7+Inputs!$B$8*(C$7-1) -> 60 | D10: =Inputs!$B$7+Inputs!$B$8*(D$7-1) -> 60 | E10: =Inputs!$B$7+Inputs!$B$8*(E$7-1) -> 60 | F10: =Inputs!$B$7+Inputs!$B$8*(F$7-1) -> 60 | G10: =Inputs!$B$7+Inputs!$B$8*(G$7-1) -> 60 | H10: =Inputs!$B$7+Inputs!$B$8*(H$7-1) -> 60 | I10: =Inputs!$B$7+Inputs!$B$8*(I$7-1) -> 60 | J10: =Inputs!$B$7+Inputs!$B$8*(J$7-1) -> 60 | ... BJ10: =Inputs!$B$7+Inputs!$B$8*(BJ$7-1) -> 60
A11: Enrolment in month 1 (capped at the full level) | C11: =MIN(Inputs!$B$11,Inputs!$B$10) -> 0.15 | D11: =MIN(Inputs!$B$11,Inputs!$B$10) -> 0.15 | E11: =MIN(Inputs!$B$11,Inputs!$B$10) -> 0.15 | F11: =MIN(Inputs!$B$11,Inputs!$B$10) -> 0.15 | G11: =MIN(Inputs!$B$11,Inputs!$B$10) -> 0.15 | H11: =MIN(Inputs!$B$11,Inputs!$B$10) -> 0.15 | I11: =MIN(Inputs!$B$11,Inputs!$B$10) -> 0.15 | J11: =MIN(Inputs!$B$11,Inputs!$B$10) -> 0.15 | ... BJ11: =MIN(Inputs!$B$11,Inputs!$B$10) -> 0.15
A12: Helper: months of the period still on the ramp-up | C12: =MAX(0,MIN(1,Inputs!$B$12-(C$6-1)*1)) -> 1 | D12: =MAX(0,MIN(1,Inputs!$B$12-(D$6-1)*1)) -> 1 | E12: =MAX(0,MIN(1,Inputs!$B$12-(E$6-1)*1)) -> 1 | F12: =MAX(0,MIN(1,Inputs!$B$12-(F$6-1)*1)) -> 1 | G12: =MAX(0,MIN(1,Inputs!$B$12-(G$6-1)*1)) -> 1 | H12: =MAX(0,MIN(1,Inputs!$B$12-(H$6-1)*1)) -> 1 | I12: =MAX(0,MIN(1,Inputs!$B$12-(I$6-1)*1)) -> 1 | J12: =MAX(0,MIN(1,Inputs!$B$12-(J$6-1)*1)) -> 1 | ... BJ12: =MAX(0,MIN(1,Inputs!$B$12-(BJ$6-1)*1)) -> 0
A13: Enrolment, average of the period (% of places) | C13: =(C12*C11+(Inputs!$B$10-C11)/MAX(1,Inputs!$B$12)*(C12*(C$6-1)*1+C12*(C12-1)/2)+(1-C12)*Inputs!$B$10)/1 -> 0.15 | D13: =(D12*D11+(Inputs!$B$10-D11)/MAX(1,Inputs!$B$12)*(D12*(D$6-1)*1+D12*(D12-1)/2)+(1-D12)*Inputs!$B$10)/1 -> 0.185 | E13: =(E12*E11+(Inputs!$B$10-E11)/MAX(1,Inputs!$B$12)*(E12*(E$6-1)*1+E12*(E12-1)/2)+(1-E12)*Inputs!$B$10)/1 -> 0.22 | F13: =(F12*F11+(Inputs!$B$10-F11)/MAX(1,Inputs!$B$12)*(F12*(F$6-1)*1+F12*(F12-1)/2)+(1-F12)*Inputs!$B$10)/1 -> 0.255 | G13: =(G12*G11+(Inputs!$B$10-G11)/MAX(1,Inputs!$B$12)*(G12*(G$6-1)*1+G12*(G12-1)/2)+(1-G12)*Inputs!$B$10)/1 -> 0.29 | H13: =(H12*H11+(Inputs!$B$10-H11)/MAX(1,Inputs!$B$12)*(H12*(H$6-1)*1+H12*(H12-1)/2)+(1-H12)*Inputs!$B$10)/1 -> 0.325 | I13: =(I12*I11+(Inputs!$B$10-I11)/MAX(1,Inputs!$B$12)*(I12*(I$6-1)*1+I12*(I12-1)/2)+(1-I12)*Inputs!$B$10)/1 -> 0.36 | J13: =(J12*J11+(Inputs!$B$10-J11)/MAX(1,Inputs!$B$12)*(J12*(J$6-1)*1+J12*(J12-1)/2)+(1-J12)*Inputs!$B$10)/1 -> 0.395 | ... BJ13: =(BJ12*BJ11+(Inputs!$B$10-BJ11)/MAX(1,Inputs!$B$12)*(BJ12*(BJ$6-1)*1+BJ12*(BJ12-1)/2)+(1-BJ12)*Inputs!$B$10)/1 -> 0.78
A14: Enrolment at the end of the period (% of places) | C14: =IF(Inputs!$B$12<=0,Inputs!$B$10,C11+(Inputs!$B$10-C11)*MIN(1,(C$6*1-1)/MAX(1,Inputs!$B$12))) -> 0.15 | D14: =IF(Inputs!$B$12<=0,Inputs!$B$10,D11+(Inputs!$B$10-D11)*MIN(1,(D$6*1-1)/MAX(1,Inputs!$B$12))) -> 0.185 | E14: =IF(Inputs!$B$12<=0,Inputs!$B$10,E11+(Inputs!$B$10-E11)*MIN(1,(E$6*1-1)/MAX(1,Inputs!$B$12))) -> 0.22 | F14: =IF(Inputs!$B$12<=0,Inputs!$B$10,F11+(Inputs!$B$10-F11)*MIN(1,(F$6*1-1)/MAX(1,Inputs!$B$12))) -> 0.255 | G14: =IF(Inputs!$B$12<=0,Inputs!$B$10,G11+(Inputs!$B$10-G11)*MIN(1,(G$6*1-1)/MAX(1,Inputs!$B$12))) -> 0.29 | H14: =IF(Inputs!$B$12<=0,Inputs!$B$10,H11+(Inputs!$B$10-H11)*MIN(1,(H$6*1-1)/MAX(1,Inputs!$B$12))) -> 0.325 | I14: =IF(Inputs!$B$12<=0,Inputs!$B$10,I11+(Inputs!$B$10-I11)*MIN(1,(I$6*1-1)/MAX(1,Inputs!$B$12))) -> 0.36 | J14: =IF(Inputs!$B$12<=0,Inputs!$B$10,J11+(Inputs!$B$10-J11)*MIN(1,(J$6*1-1)/MAX(1,Inputs!$B$12))) -> 0.395 | ... BJ14: =IF(Inputs!$B$12<=0,Inputs!$B$10,BJ11+(Inputs!$B$10-BJ11)*MIN(1,(BJ$6*1-1)/MAX(1,Inputs!$B$12))) -> 0.78
A15: Infants & toddlers enrolled (average) | C15: =C10*Inputs!$B$9*C13 -> 3.15 | D15: =D10*Inputs!$B$9*D13 -> 3.885 | E15: =E10*Inputs!$B$9*E13 -> 4.62 | F15: =F10*Inputs!$B$9*F13 -> 5.355 | G15: =G10*Inputs!$B$9*G13 -> 6.09 | H15: =H10*Inputs!$B$9*H13 -> 6.825 | I15: =I10*Inputs!$B$9*I13 -> 7.56 | J15: =J10*Inputs!$B$9*J13 -> 8.295 | ... BJ15: =BJ10*Inputs!$B$9*BJ13 -> 16.38
A16: Preschoolers enrolled (average) | C16: =C10*(1-Inputs!$B$9)*C13 -> 5.85 | D16: =D10*(1-Inputs!$B$9)*D13 -> 7.215 | E16: =E10*(1-Inputs!$B$9)*E13 -> 8.58 | F16: =F10*(1-Inputs!$B$9)*F13 -> 9.945 | G16: =G10*(1-Inputs!$B$9)*G13 -> 11.31 | H16: =H10*(1-Inputs!$B$9)*H13 -> 12.675 | I16: =I10*(1-Inputs!$B$9)*I13 -> 14.04 | J16: =J10*(1-Inputs!$B$9)*J13 -> 15.405 | ... BJ16: =BJ10*(1-Inputs!$B$9)*BJ13 -> 30.42
A17: Children enrolled (average) | C17: =C15+C16 -> 9 | D17: =D15+D16 -> 11.1 | E17: =E15+E16 -> 13.2 | F17: =F15+F16 -> 15.3 | G17: =G15+G16 -> 17.4 | H17: =H15+H16 -> 19.5 | I17: =I15+I16 -> 21.6 | J17: =J15+J16 -> 23.7 | ... BJ17: =BJ15+BJ16 -> 46.8
A18: Child-months enrolled | C18: =C17*1 -> 9 | D18: =D17*1 -> 11.1 | E18: =E17*1 -> 13.2 | F18: =F17*1 -> 15.3 | G18: =G17*1 -> 17.4 | H18: =H17*1 -> 19.5 | I18: =I17*1 -> 21.6 | J18: =J17*1 -> 23.7 | ... BJ18: =BJ17*1 -> 46.8
A19: Licensed place-months | C19: =C10*1 -> 60 | D19: =D10*1 -> 60 | E19: =E10*1 -> 60 | F19: =F10*1 -> 60 | G19: =G10*1 -> 60 | H19: =H10*1 -> 60 | I19: =I10*1 -> 60 | J19: =J10*1 -> 60 | ... BJ19: =BJ10*1 -> 60
A20: Children enrolled at the end of the period | C20: =C10*C14 -> 9 | D20: =D10*D14 -> 11.1 | E20: =E10*E14 -> 13.2 | F20: =F10*F14 -> 15.3 | G20: =G10*G14 -> 17.4 | H20: =H10*H14 -> 19.5 | I20: =I10*I14 -> 21.6 | J20: =J10*J14 -> 23.7 | ... BJ20: =BJ10*BJ14 -> 46.8
A21: New children enrolled (fill-up and replacement of leavers) | C21: =MAX(0,C20)+C17*Inputs!$B$14*1/12 -> 9.2625 | D21: =MAX(0,D20-C20)+D17*Inputs!$B$14*1/12 -> 2.42375 | E21: =MAX(0,E20-D20)+E17*Inputs!$B$14*1/12 -> 2.485 | F21: =MAX(0,F20-E20)+F17*Inputs!$B$14*1/12 -> 2.54625 | G21: =MAX(0,G20-F20)+G17*Inputs!$B$14*1/12 -> 2.6075 | H21: =MAX(0,H20-G20)+H17*Inputs!$B$14*1/12 -> 2.66875 | I21: =MAX(0,I20-H20)+I17*Inputs!$B$14*1/12 -> 2.73 | J21: =MAX(0,J20-I20)+J17*Inputs!$B$14*1/12 -> 2.79125 | K21: =MAX(0,K20-J20)+K17*Inputs!$B$14*1/12 -> 2.8525 | ... BJ21: =MAX(0,BJ20-BI20)+BJ17*Inputs!$B$14*1/12 -> 1.365
A23: Staffing by ratio
A24: Teachers on the floor, infants & toddlers | C24: =ROUNDUP(ROUND(C15/MAX(1,Inputs!$B$26),6),0) -> 1 | D24: =ROUNDUP(ROUND(D15/MAX(1,Inputs!$B$26),6),0) -> 1 | E24: =ROUNDUP(ROUND(E15/MAX(1,Inputs!$B$26),6),0) -> 1 | F24: =ROUNDUP(ROUND(F15/MAX(1,Inputs!$B$26),6),0) -> 1 | G24: =ROUNDUP(ROUND(G15/MAX(1,Inputs!$B$26),6),0) -> 2 | H24: =ROUNDUP(ROUND(H15/MAX(1,Inputs!$B$26),6),0) -> 2 | I24: =ROUNDUP(ROUND(I15/MAX(1,Inputs!$B$26),6),0) -> 2 | J24: =ROUNDUP(ROUND(J15/MAX(1,Inputs!$B$26),6),0) -> 2 | ... BJ24: =ROUNDUP(ROUND(BJ15/MAX(1,Inputs!$B$26),6),0) -> 3
A25: Teachers on the floor, preschool | C25: =ROUNDUP(ROUND(C16/MAX(1,Inputs!$B$27),6),0) -> 1 | D25: =ROUNDUP(ROUND(D16/MAX(1,Inputs!$B$27),6),0) -> 1 | E25: =ROUNDUP(ROUND(E16/MAX(1,Inputs!$B$27),6),0) -> 1 | F25: =ROUNDUP(ROUND(F16/MAX(1,Inputs!$B$27),6),0) -> 1 | G25: =ROUNDUP(ROUND(G16/MAX(1,Inputs!$B$27),6),0) -> 1 | H25: =ROUNDUP(ROUND(H16/MAX(1,Inputs!$B$27),6),0) -> 2 | I25: =ROUNDUP(ROUND(I16/MAX(1,Inputs!$B$27),6),0) -> 2 | J25: =ROUNDUP(ROUND(J16/MAX(1,Inputs!$B$27),6),0) -> 2 | ... BJ25: =ROUNDUP(ROUND(BJ16/MAX(1,Inputs!$B$27),6),0) -> 3
A26: Teachers on the floor | C26: =C24+C25 -> 2 | D26: =D24+D25 -> 2 | E26: =E24+E25 -> 2 | F26: =F24+F25 -> 2 | G26: =G24+G25 -> 3 | H26: =H24+H25 -> 4 | I26: =I24+I25 -> 4 | J26: =J24+J25 -> 4 | ... BJ26: =BJ24+BJ25 -> 6
A27: Teaching FTE hired (with coverage) | C27: =C26*Inputs!$B$28 -> 2.5 | D27: =D26*Inputs!$B$28 -> 2.5 | E27: =E26*Inputs!$B$28 -> 2.5 | F27: =F26*Inputs!$B$28 -> 2.5 | G27: =G26*Inputs!$B$28 -> 3.75 | H27: =H26*Inputs!$B$28 -> 5 | I27: =I26*Inputs!$B$28 -> 5 | J27: =J26*Inputs!$B$28 -> 5 | ... BJ27: =BJ26*Inputs!$B$28 -> 7.5
A29: Revenue
A30: Tuition at list price | C30: =(C15*Inputs!$B$17+C16*Inputs!$B$18)*1*(1+Inputs!$B$19)^(C$7-1) -> 10588.5 | D30: =(D15*Inputs!$B$17+D16*Inputs!$B$18)*1*(1+Inputs!$B$19)^(D$7-1) -> 13059.15 | E30: =(E15*Inputs!$B$17+E16*Inputs!$B$18)*1*(1+Inputs!$B$19)^(E$7-1) -> 15529.8 | F30: =(F15*Inputs!$B$17+F16*Inputs!$B$18)*1*(1+Inputs!$B$19)^(F$7-1) -> 18000.45 | G30: =(G15*Inputs!$B$17+G16*Inputs!$B$18)*1*(1+Inputs!$B$19)^(G$7-1) -> 20471.1 | H30: =(H15*Inputs!$B$17+H16*Inputs!$B$18)*1*(1+Inputs!$B$19)^(H$7-1) -> 22941.75 | I30: =(I15*Inputs!$B$17+I16*Inputs!$B$18)*1*(1+Inputs!$B$19)^(I$7-1) -> 25412.4 | J30: =(J15*Inputs!$B$17+J16*Inputs!$B$18)*1*(1+Inputs!$B$19)^(J$7-1) -> 27883.05 | ... BJ30: =(BJ15*Inputs!$B$17+BJ16*Inputs!$B$18)*1*(1+Inputs!$B$19)^(BJ$7-1) -> 60776.159
A31: Parent-paid tuition (after sibling & staff discounts) | C31: =C30*(1-Inputs!$B$22)*(1-Inputs!$B$20) -> 7464.8925 | D31: =D30*(1-Inputs!$B$22)*(1-Inputs!$B$20) -> 9206.7007 | E31: =E30*(1-Inputs!$B$22)*(1-Inputs!$B$20) -> 10948.509 | F31: =F30*(1-Inputs!$B$22)*(1-Inputs!$B$20) -> 12690.317 | G31: =G30*(1-Inputs!$B$22)*(1-Inputs!$B$20) -> 14432.126 | H31: =H30*(1-Inputs!$B$22)*(1-Inputs!$B$20) -> 16173.934 | I31: =I30*(1-Inputs!$B$22)*(1-Inputs!$B$20) -> 17915.742 | J31: =J30*(1-Inputs!$B$22)*(1-Inputs!$B$20) -> 19657.55 | ... BJ31: =BJ30*(1-Inputs!$B$22)*(1-Inputs!$B$20) -> 42847.192
A32: Subsidy & voucher payments | C32: =C30*Inputs!$B$22*Inputs!$B$23 -> 2170.6425 | D32: =D30*Inputs!$B$22*Inputs!$B$23 -> 2677.1258 | E32: =E30*Inputs!$B$22*Inputs!$B$23 -> 3183.609 | F32: =F30*Inputs!$B$22*Inputs!$B$23 -> 3690.0923 | G32: =G30*Inputs!$B$22*Inputs!$B$23 -> 4196.5755 | H32: =H30*Inputs!$B$22*Inputs!$B$23 -> 4703.0588 | I32: =I30*Inputs!$B$22*Inputs!$B$23 -> 5209.542 | J32: =J30*Inputs!$B$22*Inputs!$B$23 -> 5716.0252 | ... BJ32: =BJ30*Inputs!$B$22*Inputs!$B$23 -> 12459.112
A33: Registration fees | C33: =C21*Inputs!$B$21*(1+Inputs!$B$19)^(C$7-1) -> 926.25 | D33: =D21*Inputs!$B$21*(1+Inputs!$B$19)^(D$7-1) -> 242.375 | E33: =E21*Inputs!$B$21*(1+Inputs!$B$19)^(E$7-1) -> 248.5 | F33: =F21*Inputs!$B$21*(1+Inputs!$B$19)^(F$7-1) -> 254.625 | G33: =G21*Inputs!$B$21*(1+Inputs!$B$19)^(G$7-1) -> 260.75 | H33: =H21*Inputs!$B$21*(1+Inputs!$B$19)^(H$7-1) -> 266.875 | I33: =I21*Inputs!$B$21*(1+Inputs!$B$19)^(I$7-1) -> 273 | J33: =J21*Inputs!$B$21*(1+Inputs!$B$19)^(J$7-1) -> 279.125 | ... BJ33: =BJ21*Inputs!$B$21*(1+Inputs!$B$19)^(BJ$7-1) -> 150.67046
A34: Revenue | C34: =C31+C32+C33 -> 10561.785 | D34: =D31+D32+D33 -> 12126.201 | E34: =E31+E32+E33 -> 14380.618 | F34: =F31+F32+F33 -> 16635.035 | G34: =G31+G32+G33 -> 18889.451 | H34: =H31+H32+H33 -> 21143.868 | I34: =I31+I32+I33 -> 23398.284 | J34: =J31+J32+J33 -> 25652.7 | ... BJ34: =BJ31+BJ32+BJ33 -> 55456.975
A36: Cost of sales
A37: Teacher payroll (with payroll taxes) | C37: =-C27*Inputs!$B$29/12*1*(1+Inputs!$B$69)*(1+Inputs!$B$70)^(C$7-1) -> -8516.6667 | D37: =-D27*Inputs!$B$29/12*1*(1+Inputs!$B$69)*(1+Inputs!$B$70)^(D$7-1) -> -8516.6667 | E37: =-E27*Inputs!$B$29/12*1*(1+Inputs!$B$69)*(1+Inputs!$B$70)^(E$7-1) -> -8516.6667 | F37: =-F27*Inputs!$B$29/12*1*(1+Inputs!$B$69)*(1+Inputs!$B$70)^(F$7-1) -> -8516.6667 | G37: =-G27*Inputs!$B$29/12*1*(1+Inputs!$B$69)*(1+Inputs!$B$70)^(G$7-1) -> -12775 | H37: =-H27*Inputs!$B$29/12*1*(1+Inputs!$B$69)*(1+Inputs!$B$70)^(H$7-1) -> -17033.333 | I37: =-I27*Inputs!$B$29/12*1*(1+Inputs!$B$69)*(1+Inputs!$B$70)^(I$7-1) -> -17033.333 | J37: =-J27*Inputs!$B$29/12*1*(1+Inputs!$B$69)*(1+Inputs!$B$70)^(J$7-1) -> -17033.333 | ... BJ37: =-BJ27*Inputs!$B$29/12*1*(1+Inputs!$B$69)*(1+Inputs!$B$70)^(BJ$7-1) -> -28756.75
A38: Food | C38: =-C17*Inputs!$B$32*Inputs!$B$13*1*(1+Inputs!$B$34)^(C$7-1) -> -793.8 | D38: =-D17*Inputs!$B$32*Inputs!$B$13*1*(1+Inputs!$B$34)^(D$7-1) -> -979.02 | E38: =-E17*Inputs!$B$32*Inputs!$B$13*1*(1+Inputs!$B$34)^(E$7-1) -> -1164.24 | F38: =-F17*Inputs!$B$32*Inputs!$B$13*1*(1+Inputs!$B$34)^(F$7-1) -> -1349.46 | G38: =-G17*Inputs!$B$32*Inputs!$B$13*1*(1+Inputs!$B$34)^(G$7-1) -> -1534.68 | H38: =-H17*Inputs!$B$32*Inputs!$B$13*1*(1+Inputs!$B$34)^(H$7-1) -> -1719.9 | I38: =-I17*Inputs!$B$32*Inputs!$B$13*1*(1+Inputs!$B$34)^(I$7-1) -> -1905.12 | J38: =-J17*Inputs!$B$32*Inputs!$B$13*1*(1+Inputs!$B$34)^(J$7-1) -> -2090.34 | ... BJ38: =-BJ17*Inputs!$B$32*Inputs!$B$13*1*(1+Inputs!$B$34)^(BJ$7-1) -> -4645.8302
A39: Supplies & activities | C39: =-C17*Inputs!$B$33*1*(1+Inputs!$B$34)^(C$7-1) -> -297 | D39: =-D17*Inputs!$B$33*1*(1+Inputs!$B$34)^(D$7-1) -> -366.3 | E39: =-E17*Inputs!$B$33*1*(1+Inputs!$B$34)^(E$7-1) -> -435.6 | F39: =-F17*Inputs!$B$33*1*(1+Inputs!$B$34)^(F$7-1) -> -504.9 | G39: =-G17*Inputs!$B$33*1*(1+Inputs!$B$34)^(G$7-1) -> -574.2 | H39: =-H17*Inputs!$B$33*1*(1+Inputs!$B$34)^(H$7-1) -> -643.5 | I39: =-I17*Inputs!$B$33*1*(1+Inputs!$B$34)^(I$7-1) -> -712.8 | J39: =-J17*Inputs!$B$33*1*(1+Inputs!$B$34)^(J$7-1) -> -782.1 | ... BJ39: =-BJ17*Inputs!$B$33*1*(1+Inputs!$B$34)^(BJ$7-1) -> -1738.2358
A40: Cost of sales | C40: =C37+C38+C39 -> -9607.4667 | D40: =D37+D38+D39 -> -9861.9867 | E40: =E37+E38+E39 -> -10116.507 | F40: =F37+F38+F39 -> -10371.027 | G40: =G37+G38+G39 -> -14883.88 | H40: =H37+H38+H39 -> -19396.733 | I40: =I37+I38+I39 -> -19651.253 | J40: =J37+J38+J39 -> -19905.773 | ... BJ40: =BJ37+BJ38+BJ39 -> -35140.816
A41: Gross profit | C41: =C34+C40 -> 954.31833 | D41: =D34+D40 -> 2264.2148 | E41: =E34+E40 -> 4264.1113 | F41: =F34+F40 -> 6264.0078 | G41: =G34+G40 -> 4005.571 | H41: =H34+H40 -> 1747.1342 | I41: =I34+I40 -> 3747.0307 | J41: =J34+J40 -> 5746.9272 | ... BJ41: =BJ34+BJ40 -> 20316.159
A43: Operating expenses
A44: Staff payroll (director, office, kitchen) | C44: =C127 -> -9146.6667 | D44: =D127 -> -9146.6667 | E44: =E127 -> -9146.6667 | F44: =F127 -> -9146.6667 | G44: =G127 -> -9146.6667 | H44: =H127 -> -9146.6667 | I44: =I127 -> -9146.6667 | J44: =J127 -> -9146.6667 | ... BJ44: =BJ127 -> -10294.654
A45: Rent | C45: =-C10*Inputs!$B$37*Inputs!$B$38/12*(1+Inputs!$B$39)^(C$7-1)*1 -> -6375 | D45: =-D10*Inputs!$B$37*Inputs!$B$38/12*(1+Inputs!$B$39)^(D$7-1)*1 -> -6375 | E45: =-E10*Inputs!$B$37*Inputs!$B$38/12*(1+Inputs!$B$39)^(E$7-1)*1 -> -6375 | F45: =-F10*Inputs!$B$37*Inputs!$B$38/12*(1+Inputs!$B$39)^(F$7-1)*1 -> -6375 | G45: =-G10*Inputs!$B$37*Inputs!$B$38/12*(1+Inputs!$B$39)^(G$7-1)*1 -> -6375 | H45: =-H10*Inputs!$B$37*Inputs!$B$38/12*(1+Inputs!$B$39)^(H$7-1)*1 -> -6375 | I45: =-I10*Inputs!$B$37*Inputs!$B$38/12*(1+Inputs!$B$39)^(I$7-1)*1 -> -6375 | J45: =-J10*Inputs!$B$37*Inputs!$B$38/12*(1+Inputs!$B$39)^(J$7-1)*1 -> -6375 | ... BJ45: =-BJ10*Inputs!$B$37*Inputs!$B$38/12*(1+Inputs!$B$39)^(BJ$7-1)*1 -> -7175.1187
A46: Utilities & cleaning | C46: =-C10*Inputs!$B$37*Inputs!$B$40/12*(1+Inputs!$B$34)^(C$7-1)*1 -> -2550 | D46: =-D10*Inputs!$B$37*Inputs!$B$40/12*(1+Inputs!$B$34)^(D$7-1)*1 -> -2550 | E46: =-E10*Inputs!$B$37*Inputs!$B$40/12*(1+Inputs!$B$34)^(E$7-1)*1 -> -2550 | F46: =-F10*Inputs!$B$37*Inputs!$B$40/12*(1+Inputs!$B$34)^(F$7-1)*1 -> -2550 | G46: =-G10*Inputs!$B$37*Inputs!$B$40/12*(1+Inputs!$B$34)^(G$7-1)*1 -> -2550 | H46: =-H10*Inputs!$B$37*Inputs!$B$40/12*(1+Inputs!$B$34)^(H$7-1)*1 -> -2550 | I46: =-I10*Inputs!$B$37*Inputs!$B$40/12*(1+Inputs!$B$34)^(I$7-1)*1 -> -2550 | J46: =-J10*Inputs!$B$37*Inputs!$B$40/12*(1+Inputs!$B$34)^(J$7-1)*1 -> -2550 | ... BJ46: =-BJ10*Inputs!$B$37*Inputs!$B$40/12*(1+Inputs!$B$34)^(BJ$7-1)*1 -> -2870.0475
A47: Insurance | C47: =-Inputs!$B$41*1 -> -1800 | D47: =-Inputs!$B$41*1 -> -1800 | E47: =-Inputs!$B$41*1 -> -1800 | F47: =-Inputs!$B$41*1 -> -1800 | G47: =-Inputs!$B$41*1 -> -1800 | H47: =-Inputs!$B$41*1 -> -1800 | I47: =-Inputs!$B$41*1 -> -1800 | J47: =-Inputs!$B$41*1 -> -1800 | ... BJ47: =-Inputs!$B$41*1 -> -1800
A48: Licensing, background checks & training | C48: =-Inputs!$B$42*1 -> -600 | D48: =-Inputs!$B$42*1 -> -600 | E48: =-Inputs!$B$42*1 -> -600 | F48: =-Inputs!$B$42*1 -> -600 | G48: =-Inputs!$B$42*1 -> -600 | H48: =-Inputs!$B$42*1 -> -600 | I48: =-Inputs!$B$42*1 -> -600 | J48: =-Inputs!$B$42*1 -> -600 | ... BJ48: =-Inputs!$B$42*1 -> -600
A49: Marketing | C49: =-Inputs!$B$43*(1+Inputs!$B$44)^(C$7-1)*1 -> -2500 | D49: =-Inputs!$B$43*(1+Inputs!$B$44)^(D$7-1)*1 -> -2500 | E49: =-Inputs!$B$43*(1+Inputs!$B$44)^(E$7-1)*1 -> -2500 | F49: =-Inputs!$B$43*(1+Inputs!$B$44)^(F$7-1)*1 -> -2500 | G49: =-Inputs!$B$43*(1+Inputs!$B$44)^(G$7-1)*1 -> -2500 | H49: =-Inputs!$B$43*(1+Inputs!$B$44)^(H$7-1)*1 -> -2500 | I49: =-Inputs!$B$43*(1+Inputs!$B$44)^(I$7-1)*1 -> -2500 | J49: =-Inputs!$B$43*(1+Inputs!$B$44)^(J$7-1)*1 -> -2500 | ... BJ49: =-Inputs!$B$43*(1+Inputs!$B$44)^(BJ$7-1)*1 -> -2500
A50: Parent app & management software | C50: =-Inputs!$B$45*1 -> -400 | D50: =-Inputs!$B$45*1 -> -400 | E50: =-Inputs!$B$45*1 -> -400 | F50: =-Inputs!$B$45*1 -> -400 | G50: =-Inputs!$B$45*1 -> -400 | H50: =-Inputs!$B$45*1 -> -400 | I50: =-Inputs!$B$45*1 -> -400 | J50: =-Inputs!$B$45*1 -> -400 | ... BJ50: =-Inputs!$B$45*1 -> -400
A51: Card / ACH fees | C51: =-C31*Inputs!$B$46 -> -209.01699 | D51: =-D31*Inputs!$B$46 -> -257.78762 | E51: =-E31*Inputs!$B$46 -> -306.55825 | F51: =-F31*Inputs!$B$46 -> -355.32888 | G51: =-G31*Inputs!$B$46 -> -404.09951 | H51: =-H31*Inputs!$B$46 -> -452.87014 | I51: =-I31*Inputs!$B$46 -> -501.64078 | J51: =-J31*Inputs!$B$46 -> -550.41141 | ... BJ51: =-BJ31*Inputs!$B$46 -> -1199.7214
A52: Other G&A | C52: =-Inputs!$B$47*1 -> -1200 | D52: =-Inputs!$B$47*1 -> -1200 | E52: =-Inputs!$B$47*1 -> -1200 | F52: =-Inputs!$B$47*1 -> -1200 | G52: =-Inputs!$B$47*1 -> -1200 | H52: =-Inputs!$B$47*1 -> -1200 | I52: =-Inputs!$B$47*1 -> -1200 | J52: =-Inputs!$B$47*1 -> -1200 | ... BJ52: =-Inputs!$B$47*1 -> -1200
A53: Total operating expenses | C53: =C44+C45+C46+C47+C48+C49+C50+C51+C52 -> -24780.684 | D53: =D44+D45+D46+D47+D48+D49+D50+D51+D52 -> -24829.454 | E53: =E44+E45+E46+E47+E48+E49+E50+E51+E52 -> -24878.225 | F53: =F44+F45+F46+F47+F48+F49+F50+F51+F52 -> -24926.996 | G53: =G44+G45+G46+G47+G48+G49+G50+G51+G52 -> -24975.766 | H53: =H44+H45+H46+H47+H48+H49+H50+H51+H52 -> -25024.537 | I53: =I44+I45+I46+I47+I48+I49+I50+I51+I52 -> -25073.307 | J53: =J44+J45+J46+J47+J48+J49+J50+J51+J52 -> -25122.078 | ... BJ53: =BJ44+BJ45+BJ46+BJ47+BJ48+BJ49+BJ50+BJ51+BJ52 -> -28039.541
A54: EBITDA | C54: =C41+C53 -> -23826.365 | D54: =D41+D53 -> -22565.239 | E54: =E41+E53 -> -20614.114 | F54: =F41+F53 -> -18662.988 | G54: =G41+G53 -> -20970.195 | H54: =H41+H53 -> -23277.403 | I54: =I41+I53 -> -21326.277 | J54: =J41+J53 -> -19375.151 | ... BJ54: =BJ41+BJ53 -> -7723.3828
A56: Profit after depreciation, interest, tax
A57: EBIT | C57: =C54+C72 -> -27509.699 | D57: =D54+D72 -> -26248.573 | E57: =E54+E72 -> -24297.447 | F57: =F54+F72 -> -22346.321 | G57: =G54+G72 -> -24653.529 | H57: =H54+H72 -> -26960.736 | I57: =I54+I72 -> -25009.61 | J57: =J54+J72 -> -23058.484 | ... BJ57: =BJ54+BJ72 -> -11706.716
A58: Interest on loan (average balance after drawdown) | C58: =-(C77+C78+C80)/2*Inputs!$B$75/12 -> -1666.6667 | D58: =-(D77+D78+D80)/2*Inputs!$B$75/12 -> -1659.7222 | E58: =-(E77+E78+E80)/2*Inputs!$B$75/12 -> -1645.8333 | F58: =-(F77+F78+F80)/2*Inputs!$B$75/12 -> -1631.9444 | G58: =-(G77+G78+G80)/2*Inputs!$B$75/12 -> -1618.0556 | H58: =-(H77+H78+H80)/2*Inputs!$B$75/12 -> -1604.1667 | I58: =-(I77+I78+I80)/2*Inputs!$B$75/12 -> -1590.2778 | J58: =-(J77+J78+J80)/2*Inputs!$B$75/12 -> -1576.3889 | ... BJ58: =-(BJ77+BJ78+BJ80)/2*Inputs!$B$75/12 -> -854.16667
A59: Pre-tax income | C59: =C57+C58 -> -29176.365 | D59: =D57+D58 -> -27908.295 | E59: =E57+E58 -> -25943.28 | F59: =F57+F58 -> -23978.265 | G59: =G57+G58 -> -26271.584 | H59: =H57+H58 -> -28564.903 | I59: =I57+I58 -> -26599.888 | J59: =J57+J58 -> -24634.873 | ... BJ59: =BJ57+BJ58 -> -12560.883
A60: Helper: cumulative pre-tax income | C60: =C59 -> -29176.365 | D60: =C60+D59 -> -57084.66 | E60: =D60+E59 -> -83027.941 | F60: =E60+F59 -> -107006.21 | G60: =F60+G59 -> -133277.79 | H60: =G60+H59 -> -161842.69 | I60: =H60+I59 -> -188442.58 | J60: =I60+J59 -> -213077.45 | K60: =J60+K59 -> -235747.31 | ... BJ60: =BI60+BJ59 -> -912098.28
A61: Helper: cumulative taxable income (losses carried forward) | C61: =MAX(0,C60) -> 0 | D61: =MAX(C61,D60) -> 0 | E61: =MAX(D61,E60) -> 0 | F61: =MAX(E61,F60) -> 0 | G61: =MAX(F61,G60) -> 0 | H61: =MAX(G61,H60) -> 0 | I61: =MAX(H61,I60) -> 0 | J61: =MAX(I61,J60) -> 0 | K61: =MAX(J61,K60) -> 0 | ... BJ61: =MAX(BI61,BJ60) -> 0
A62: Income tax | C62: =-C61*Inputs!$B$85 -> 0 | D62: =-(D61-C61)*Inputs!$B$85 -> 0 | E62: =-(E61-D61)*Inputs!$B$85 -> 0 | F62: =-(F61-E61)*Inputs!$B$85 -> 0 | G62: =-(G61-F61)*Inputs!$B$85 -> 0 | H62: =-(H61-G61)*Inputs!$B$85 -> 0 | I62: =-(I61-H61)*Inputs!$B$85 -> 0 | J62: =-(J61-I61)*Inputs!$B$85 -> 0 | K62: =-(K61-J61)*Inputs!$B$85 -> 0 | ... BJ62: =-(BJ61-BI61)*Inputs!$B$85 -> 0
A63: Net income | C63: =C59+C62 -> -29176.365 | D63: =D59+D62 -> -27908.295 | E63: =E59+E62 -> -25943.28 | F63: =F59+F62 -> -23978.265 | G63: =G59+G62 -> -26271.584 | H63: =H59+H62 -> -28564.903 | I63: =I59+I62 -> -26599.888 | J63: =J59+J62 -> -24634.873 | ... BJ63: =BJ59+BJ62 -> -12560.883
A65: Fixed assets & capital spending
A66: Build-out of new places | C66: =MAX(0,Inputs!$B$7-Inputs!$B$52)*Inputs!$B$37*Inputs!$B$50 -> 270000 | D66: =IF(AND(D$7>1,MOD(D$6-1,12)=0),Inputs!$B$8,0)*Inputs!$B$37*Inputs!$B$50 -> 0 | E66: =IF(AND(E$7>1,MOD(E$6-1,12)=0),Inputs!$B$8,0)*Inputs!$B$37*Inputs!$B$50 -> 0 | F66: =IF(AND(F$7>1,MOD(F$6-1,12)=0),Inputs!$B$8,0)*Inputs!$B$37*Inputs!$B$50 -> 0 | G66: =IF(AND(G$7>1,MOD(G$6-1,12)=0),Inputs!$B$8,0)*Inputs!$B$37*Inputs!$B$50 -> 0 | H66: =IF(AND(H$7>1,MOD(H$6-1,12)=0),Inputs!$B$8,0)*Inputs!$B$37*Inputs!$B$50 -> 0 | I66: =IF(AND(I$7>1,MOD(I$6-1,12)=0),Inputs!$B$8,0)*Inputs!$B$37*Inputs!$B$50 -> 0 | J66: =IF(AND(J$7>1,MOD(J$6-1,12)=0),Inputs!$B$8,0)*Inputs!$B$37*Inputs!$B$50 -> 0 | K66: =IF(AND(K$7>1,MOD(K$6-1,12)=0),Inputs!$B$8,0)*Inputs!$B$37*Inputs!$B$50 -> 0 | ... BJ66: =IF(AND(BJ$7>1,MOD(BJ$6-1,12)=0),Inputs!$B$8,0)*Inputs!$B$37*Inputs!$B$50 -> 0
A67: Furniture & equipment for new places | C67: =MAX(0,Inputs!$B$7-Inputs!$B$52)*Inputs!$B$51 -> 132000 | D67: =IF(AND(D$7>1,MOD(D$6-1,12)=0),Inputs!$B$8,0)*Inputs!$B$51 -> 0 | E67: =IF(AND(E$7>1,MOD(E$6-1,12)=0),Inputs!$B$8,0)*Inputs!$B$51 -> 0 | F67: =IF(AND(F$7>1,MOD(F$6-1,12)=0),Inputs!$B$8,0)*Inputs!$B$51 -> 0 | G67: =IF(AND(G$7>1,MOD(G$6-1,12)=0),Inputs!$B$8,0)*Inputs!$B$51 -> 0 | H67: =IF(AND(H$7>1,MOD(H$6-1,12)=0),Inputs!$B$8,0)*Inputs!$B$51 -> 0 | I67: =IF(AND(I$7>1,MOD(I$6-1,12)=0),Inputs!$B$8,0)*Inputs!$B$51 -> 0 | J67: =IF(AND(J$7>1,MOD(J$6-1,12)=0),Inputs!$B$8,0)*Inputs!$B$51 -> 0 | K67: =IF(AND(K$7>1,MOD(K$6-1,12)=0),Inputs!$B$8,0)*Inputs!$B$51 -> 0 | ... BJ67: =IF(AND(BJ$7>1,MOD(BJ$6-1,12)=0),Inputs!$B$8,0)*Inputs!$B$51 -> 0
A68: Playground & outdoor area | C68: =IF(C$6=1,Inputs!$B$53,0) -> 40000 | D68: =IF(D$6=1,Inputs!$B$53,0) -> 0 | E68: =IF(E$6=1,Inputs!$B$53,0) -> 0 | F68: =IF(F$6=1,Inputs!$B$53,0) -> 0 | G68: =IF(G$6=1,Inputs!$B$53,0) -> 0 | H68: =IF(H$6=1,Inputs!$B$53,0) -> 0 | I68: =IF(I$6=1,Inputs!$B$53,0) -> 0 | J68: =IF(J$6=1,Inputs!$B$53,0) -> 0 | ... BJ68: =IF(BJ$6=1,Inputs!$B$53,0) -> 0
A69: Equipment replacement (first period of each year from year 2) | C69: =IF(AND(C$7>1,MOD(C$6-1,12)=0),C10*Inputs!$B$54,0) -> 0 | D69: =IF(AND(D$7>1,MOD(D$6-1,12)=0),D10*Inputs!$B$54,0) -> 0 | E69: =IF(AND(E$7>1,MOD(E$6-1,12)=0),E10*Inputs!$B$54,0) -> 0 | F69: =IF(AND(F$7>1,MOD(F$6-1,12)=0),F10*Inputs!$B$54,0) -> 0 | G69: =IF(AND(G$7>1,MOD(G$6-1,12)=0),G10*Inputs!$B$54,0) -> 0 | H69: =IF(AND(H$7>1,MOD(H$6-1,12)=0),H10*Inputs!$B$54,0) -> 0 | I69: =IF(AND(I$7>1,MOD(I$6-1,12)=0),I10*Inputs!$B$54,0) -> 0 | J69: =IF(AND(J$7>1,MOD(J$6-1,12)=0),J10*Inputs!$B$54,0) -> 0 | ... BJ69: =IF(AND(BJ$7>1,MOD(BJ$6-1,12)=0),BJ10*Inputs!$B$54,0) -> 0
A70: Capital spending | C70: =C66+C67+C68+C69 -> 442000 | D70: =D66+D67+D68+D69 -> 0 | E70: =E66+E67+E68+E69 -> 0 | F70: =F66+F67+F68+F69 -> 0 | G70: =G66+G67+G68+G69 -> 0 | H70: =H66+H67+H68+H69 -> 0 | I70: =I66+I67+I68+I69 -> 0 | J70: =J66+J67+J68+J69 -> 0 | ... BJ70: =BJ66+BJ67+BJ68+BJ69 -> 0
A71: Fixed assets at cost | C71: =C70 -> 442000 | D71: =C71+D70 -> 442000 | E71: =D71+E70 -> 442000 | F71: =E71+F70 -> 442000 | G71: =F71+G70 -> 442000 | H71: =G71+H70 -> 442000 | I71: =H71+I70 -> 442000 | J71: =I71+J70 -> 442000 | K71: =J71+K70 -> 442000 | ... BJ71: =BI71+BJ70 -> 478000
A72: Depreciation | C72: =-MIN(C71/MAX(1,Inputs!$B$84*12),C70) -> -3683.3333 | D72: =-MIN(D71/MAX(1,Inputs!$B$84*12),C74+D70) -> -3683.3333 | E72: =-MIN(E71/MAX(1,Inputs!$B$84*12),D74+E70) -> -3683.3333 | F72: =-MIN(F71/MAX(1,Inputs!$B$84*12),E74+F70) -> -3683.3333 | G72: =-MIN(G71/MAX(1,Inputs!$B$84*12),F74+G70) -> -3683.3333 | H72: =-MIN(H71/MAX(1,Inputs!$B$84*12),G74+H70) -> -3683.3333 | I72: =-MIN(I71/MAX(1,Inputs!$B$84*12),H74+I70) -> -3683.3333 | J72: =-MIN(J71/MAX(1,Inputs!$B$84*12),I74+J70) -> -3683.3333 | K72: =-MIN(K71/MAX(1,Inputs!$B$84*12),J74+K70) -> -3683.3333 | ... BJ72: =-MIN(BJ71/MAX(1,Inputs!$B$84*12),BI74+BJ70) -> -3983.3333
A73: Accumulated depreciation | C73: =C72 -> -3683.3333 | D73: =C73+D72 -> -7366.6667 | E73: =D73+E72 -> -11050 | F73: =E73+F72 -> -14733.333 | G73: =F73+G72 -> -18416.667 | H73: =G73+H72 -> -22100 | I73: =H73+I72 -> -25783.333 | J73: =I73+J72 -> -29466.667 | K73: =J73+K72 -> -33150 | ... BJ73: =BI73+BJ72 -> -230000
A74: Net fixed assets | C74: =C71+C73 -> 438316.67 | D74: =D71+D73 -> 434633.33 | E74: =E71+E73 -> 430950 | F74: =F71+F73 -> 427266.67 | G74: =G71+G73 -> 423583.33 | H74: =H71+H73 -> 419900 | I74: =I71+I73 -> 416216.67 | J74: =J71+J73 -> 412533.33 | ... BJ74: =BJ71+BJ73 -> 248000
A76: Debt
A77: Loan — opening balance | C77: =0 -> 0 | D77: =C80 -> 250000 | E77: =D80 -> 247916.67 | F77: =E80 -> 245833.33 | G77: =F80 -> 243750 | H77: =G80 -> 241666.67 | I77: =H80 -> 239583.33 | J77: =I80 -> 237500 | K77: =J80 -> 235416.67 | ... BJ77: =BI80 -> 129166.67
A78: Loan drawdown | C78: =IF(C$6=1,Inputs!$B$74,0) -> 250000 | D78: =IF(D$6=1,Inputs!$B$74,0) -> 0 | E78: =IF(E$6=1,Inputs!$B$74,0) -> 0 | F78: =IF(F$6=1,Inputs!$B$74,0) -> 0 | G78: =IF(G$6=1,Inputs!$B$74,0) -> 0 | H78: =IF(H$6=1,Inputs!$B$74,0) -> 0 | I78: =IF(I$6=1,Inputs!$B$74,0) -> 0 | J78: =IF(J$6=1,Inputs!$B$74,0) -> 0 | ... BJ78: =IF(BJ$6=1,Inputs!$B$74,0) -> 0
A79: Loan repayment | C79: =-MIN(C77,Inputs!$B$74/MAX(1,Inputs!$B$76*12)) -> 0 | D79: =-MIN(D77,Inputs!$B$74/MAX(1,Inputs!$B$76*12)) -> -2083.3333 | E79: =-MIN(E77,Inputs!$B$74/MAX(1,Inputs!$B$76*12)) -> -2083.3333 | F79: =-MIN(F77,Inputs!$B$74/MAX(1,Inputs!$B$76*12)) -> -2083.3333 | G79: =-MIN(G77,Inputs!$B$74/MAX(1,Inputs!$B$76*12)) -> -2083.3333 | H79: =-MIN(H77,Inputs!$B$74/MAX(1,Inputs!$B$76*12)) -> -2083.3333 | I79: =-MIN(I77,Inputs!$B$74/MAX(1,Inputs!$B$76*12)) -> -2083.3333 | J79: =-MIN(J77,Inputs!$B$74/MAX(1,Inputs!$B$76*12)) -> -2083.3333 | ... BJ79: =-MIN(BJ77,Inputs!$B$74/MAX(1,Inputs!$B$76*12)) -> -2083.3333
A80: Loan — closing balance | C80: =C77+C78+C79 -> 250000 | D80: =D77+D78+D79 -> 247916.67 | E80: =E77+E78+E79 -> 245833.33 | F80: =F77+F78+F79 -> 243750 | G80: =G77+G78+G79 -> 241666.67 | H80: =H77+H78+H79 -> 239583.33 | I80: =I77+I78+I79 -> 237500 | J80: =J77+J78+J79 -> 235416.67 | ... BJ80: =BJ77+BJ78+BJ79 -> 127083.33
A82: Working capital
A83: Accounts receivable | C83: =C34*Inputs!$B$79/30 -> 4576.7735 | D83: =D34*Inputs!$B$79/30 -> 5254.6873 | E83: =E34*Inputs!$B$79/30 -> 6231.6011 | F83: =F34*Inputs!$B$79/30 -> 7208.5149 | G83: =G34*Inputs!$B$79/30 -> 8185.4288 | H83: =H34*Inputs!$B$79/30 -> 9162.3426 | I83: =I34*Inputs!$B$79/30 -> 10139.256 | J83: =J34*Inputs!$B$79/30 -> 11116.17 | ... BJ83: =BJ34*Inputs!$B$79/30 -> 24031.356
A84: Inventory | C84: =-C40*Inputs!$B$80/30 -> 960.74667 | D84: =-D40*Inputs!$B$80/30 -> 986.19867 | E84: =-E40*Inputs!$B$80/30 -> 1011.6507 | F84: =-F40*Inputs!$B$80/30 -> 1037.1027 | G84: =-G40*Inputs!$B$80/30 -> 1488.388 | H84: =-H40*Inputs!$B$80/30 -> 1939.6733 | I84: =-I40*Inputs!$B$80/30 -> 1965.1253 | J84: =-J40*Inputs!$B$80/30 -> 1990.5773 | ... BJ84: =-BJ40*Inputs!$B$80/30 -> 3514.0816
A85: Accounts payable | C85: =-C40*Inputs!$B$81/30 -> 3522.7378 | D85: =-D40*Inputs!$B$81/30 -> 3616.0618 | E85: =-E40*Inputs!$B$81/30 -> 3709.3858 | F85: =-F40*Inputs!$B$81/30 -> 3802.7098 | G85: =-G40*Inputs!$B$81/30 -> 5457.4227 | H85: =-H40*Inputs!$B$81/30 -> 7112.1356 | I85: =-I40*Inputs!$B$81/30 -> 7205.4596 | J85: =-J40*Inputs!$B$81/30 -> 7298.7836 | ... BJ85: =-BJ40*Inputs!$B$81/30 -> 12884.966
A86: (Increase) / decrease in receivables | C86: =-C83 -> -4576.7735 | D86: =C83-D83 -> -677.91382 | E86: =D83-E83 -> -976.91382 | F86: =E83-F83 -> -976.91382 | G86: =F83-G83 -> -976.91382 | H86: =G83-H83 -> -976.91382 | I86: =H83-I83 -> -976.91382 | J86: =I83-J83 -> -976.91382 | K86: =J83-K83 -> -976.91382 | ... BJ86: =BI83-BJ83 -> 0
A87: (Increase) / decrease in inventory | C87: =-C84 -> -960.74667 | D87: =C84-D84 -> -25.452 | E87: =D84-E84 -> -25.452 | F87: =E84-F84 -> -25.452 | G87: =F84-G84 -> -451.28533 | H87: =G84-H84 -> -451.28533 | I87: =H84-I84 -> -25.452 | J87: =I84-J84 -> -25.452 | K87: =J84-K84 -> -25.452 | ... BJ87: =BI84-BJ84 -> 0
A88: Increase / (decrease) in payables | C88: =C85 -> 3522.7378 | D88: =D85-C85 -> 93.324 | E88: =E85-D85 -> 93.324 | F88: =F85-E85 -> 93.324 | G88: =G85-F85 -> 1654.7129 | H88: =H85-G85 -> 1654.7129 | I88: =I85-H85 -> 93.324 | J88: =J85-I85 -> 93.324 | K88: =K85-J85 -> 93.324 | ... BJ88: =BJ85-BI85 -> 0
A90: Cash flow
A91: Operating cash flow | C91: =C63-C72+C86+C87+C88 -> -27507.814 | D91: =D63-D72+D86+D87+D88 -> -24835.003 | E91: =E63-E72+E86+E87+E88 -> -23168.989 | F91: =F63-F72+F86+F87+F88 -> -21203.974 | G91: =G63-G72+G86+G87+G88 -> -22361.737 | H91: =H63-H72+H86+H87+H88 -> -24655.056 | I91: =I63-I72+I86+I87+I88 -> -23825.596 | J91: =J63-J72+J86+J87+J88 -> -21860.582 | ... BJ91: =BJ63-BJ72+BJ86+BJ87+BJ88 -> -8577.5495
A92: Investing cash flow (capex) | C92: =-C70 -> -442000 | D92: =-D70 -> 0 | E92: =-E70 -> 0 | F92: =-F70 -> 0 | G92: =-G70 -> 0 | H92: =-H70 -> 0 | I92: =-I70 -> 0 | J92: =-J70 -> 0 | ... BJ92: =-BJ70 -> 0
A93: Equity raised | C93: =IF(C$6=1,Inputs!$B$73,0) -> 450000 | D93: =IF(D$6=1,Inputs!$B$73,0) -> 0 | E93: =IF(E$6=1,Inputs!$B$73,0) -> 0 | F93: =IF(F$6=1,Inputs!$B$73,0) -> 0 | G93: =IF(G$6=1,Inputs!$B$73,0) -> 0 | H93: =IF(H$6=1,Inputs!$B$73,0) -> 0 | I93: =IF(I$6=1,Inputs!$B$73,0) -> 0 | J93: =IF(J$6=1,Inputs!$B$73,0) -> 0 | ... BJ93: =IF(BJ$6=1,Inputs!$B$73,0) -> 0
A94: Financing cash flow | C94: =C93+C78+C79 -> 700000 | D94: =D93+D78+D79 -> -2083.3333 | E94: =E93+E78+E79 -> -2083.3333 | F94: =F93+F78+F79 -> -2083.3333 | G94: =G93+G78+G79 -> -2083.3333 | H94: =H93+H78+H79 -> -2083.3333 | I94: =I93+I78+I79 -> -2083.3333 | J94: =J93+J78+J79 -> -2083.3333 | ... BJ94: =BJ93+BJ78+BJ79 -> -2083.3333
A95: Net cash flow | C95: =C91+C92+C94 -> 230492.19 | D95: =D91+D92+D94 -> -26918.337 | E95: =E91+E92+E94 -> -25252.322 | F95: =F91+F92+F94 -> -23287.307 | G95: =G91+G92+G94 -> -24445.07 | H95: =H91+H92+H94 -> -26738.389 | I95: =I91+I92+I94 -> -25908.93 | J95: =J91+J92+J94 -> -23943.915 | ... BJ95: =BJ91+BJ92+BJ94 -> -10660.883
A96: Opening cash | C96: =0 -> 0 | D96: =C97 -> 230492.19 | E96: =D97 -> 203573.85 | F96: =E97 -> 178321.53 | G96: =F97 -> 155034.22 | H96: =G97 -> 130589.15 | I96: =H97 -> 103850.76 | J96: =I97 -> 77941.83 | K96: =J97 -> 53997.916 | ... BJ96: =BI97 -> -587014.54
A97: Closing cash | C97: =C96+C95 -> 230492.19 | D97: =D96+D95 -> 203573.85 | E97: =E96+E95 -> 178321.53 | F97: =F96+F95 -> 155034.22 | G97: =G96+G95 -> 130589.15 | H97: =H96+H95 -> 103850.76 | I97: =I96+I95 -> 77941.83 | J97: =J96+J95 -> 53997.916 | ... BJ97: =BJ96+BJ95 -> -597675.42
A98: Helper: EBITDA positive (1/0) | C98: =IF(C54>0,1,0) -> 0 | D98: =IF(D54>0,1,0) -> 0 | E98: =IF(E54>0,1,0) -> 0 | F98: =IF(F54>0,1,0) -> 0 | G98: =IF(G54>0,1,0) -> 0 | H98: =IF(H54>0,1,0) -> 0 | I98: =IF(I54>0,1,0) -> 0 | J98: =IF(J54>0,1,0) -> 0 | ... BJ98: =IF(BJ54>0,1,0) -> 0
A100: Goal modules
A101: Helper: net income positive (1/0) | C101: =IF(C63>0,1,0) -> 0 | D101: =IF(D63>0,1,0) -> 0 | E101: =IF(E63>0,1,0) -> 0 | F101: =IF(F63>0,1,0) -> 0 | G101: =IF(G63>0,1,0) -> 0 | H101: =IF(H63>0,1,0) -> 0 | I101: =IF(I63>0,1,0) -> 0 | J101: =IF(J63>0,1,0) -> 0 | ... BJ101: =IF(BJ63>0,1,0) -> 0
A102: Cash flow before financing (operating + investing) | C102: =C91+C92 -> -469507.81 | D102: =D91+D92 -> -24835.003 | E102: =E91+E92 -> -23168.989 | F102: =F91+F92 -> -21203.974 | G102: =G91+G92 -> -22361.737 | H102: =H91+H92 -> -24655.056 | I102: =I91+I92 -> -23825.596 | J102: =J91+J92 -> -21860.582 | ... BJ102: =BJ91+BJ92 -> -8577.5495
A103: Cumulative cash flow before financing | C103: =C102 -> -469507.81 | D103: =C103+D102 -> -494342.82 | E103: =D103+E102 -> -517511.81 | F103: =E103+F102 -> -538715.78 | G103: =F103+G102 -> -561077.52 | H103: =G103+H102 -> -585732.57 | I103: =H103+I102 -> -609558.17 | J103: =I103+J102 -> -631418.75 | K103: =J103+K102 -> -651314.32 | ... BJ103: =BI103+BJ102 -> -1174758.8
A104: Helper: lowest cumulative cash flow so far | C104: =C103 -> -469507.81 | D104: =MIN(C104,D103) -> -494342.82 | E104: =MIN(D104,E103) -> -517511.81 | F104: =MIN(E104,F103) -> -538715.78 | G104: =MIN(F104,G103) -> -561077.52 | H104: =MIN(G104,H103) -> -585732.57 | I104: =MIN(H104,I103) -> -609558.17 | J104: =MIN(I104,J103) -> -631418.75 | K104: =MIN(J104,K103) -> -651314.32 | ... BJ104: =MIN(BI104,BJ103) -> -1174758.8
A105: Helper: investment paid back (1/0) | C105: =IF(AND(C103>=0,C104<0),1,0) -> 0 | D105: =IF(AND(D103>=0,D104<0),1,0) -> 0 | E105: =IF(AND(E103>=0,E104<0),1,0) -> 0 | F105: =IF(AND(F103>=0,F104<0),1,0) -> 0 | G105: =IF(AND(G103>=0,G104<0),1,0) -> 0 | H105: =IF(AND(H103>=0,H104<0),1,0) -> 0 | I105: =IF(AND(I103>=0,I104<0),1,0) -> 0 | J105: =IF(AND(J103>=0,J104<0),1,0) -> 0 | ... BJ105: =IF(AND(BJ103>=0,BJ104<0),1,0) -> 0
A106: Unlevered free cash flow (operating + after-tax interest − capex) | C106: =C91-C58*(1-Inputs!$B$85)+C92 -> -468191.15 | D106: =D91-D58*(1-Inputs!$B$85)+D92 -> -23523.823 | E106: =E91-E58*(1-Inputs!$B$85)+E92 -> -21868.78 | F106: =F91-F58*(1-Inputs!$B$85)+F92 -> -19914.738 | G106: =G91-G58*(1-Inputs!$B$85)+G92 -> -21083.473 | H106: =H91-H58*(1-Inputs!$B$85)+H92 -> -23387.764 | I106: =I91-I58*(1-Inputs!$B$85)+I92 -> -22569.277 | J106: =J91-J58*(1-Inputs!$B$85)+J92 -> -20615.234 | ... BJ106: =BJ91-BJ58*(1-Inputs!$B$85)+BJ92 -> -7902.7578
A108: Balance sheet
A109: Paid-in capital | C109: =C93 -> 450000 | D109: =C109+D93 -> 450000 | E109: =D109+E93 -> 450000 | F109: =E109+F93 -> 450000 | G109: =F109+G93 -> 450000 | H109: =G109+H93 -> 450000 | I109: =H109+I93 -> 450000 | J109: =I109+J93 -> 450000 | K109: =J109+K93 -> 450000 | ... BJ109: =BI109+BJ93 -> 450000
A110: Retained earnings | C110: =C63 -> -29176.365 | D110: =C110+D63 -> -57084.66 | E110: =D110+E63 -> -83027.941 | F110: =E110+F63 -> -107006.21 | G110: =F110+G63 -> -133277.79 | H110: =G110+H63 -> -161842.69 | I110: =H110+I63 -> -188442.58 | J110: =I110+J63 -> -213077.45 | K110: =J110+K63 -> -235747.31 | ... BJ110: =BI110+BJ63 -> -912098.28
A111: Total assets | C111: =C97+C83+C84+C74 -> 674346.37 | D111: =D97+D83+D84+D74 -> 644448.07 | E111: =E97+E83+E84+E74 -> 616514.78 | F111: =F97+F83+F84+F74 -> 590546.5 | G111: =G97+G83+G84+G74 -> 563846.3 | H111: =H97+H83+H84+H74 -> 534852.78 | I111: =I97+I83+I84+I74 -> 506262.88 | J111: =J97+J83+J84+J74 -> 479638 | ... BJ111: =BJ97+BJ83+BJ84+BJ74 -> -322129.98
A112: Total liabilities | C112: =C85+C80 -> 253522.74 | D112: =D85+D80 -> 251532.73 | E112: =E85+E80 -> 249542.72 | F112: =F85+F80 -> 247552.71 | G112: =G85+G80 -> 247124.09 | H112: =H85+H80 -> 246695.47 | I112: =I85+I80 -> 244705.46 | J112: =J85+J80 -> 242715.45 | ... BJ112: =BJ85+BJ80 -> 139968.3
A113: Total equity | C113: =C109+C110 -> 420823.63 | D113: =D109+D110 -> 392915.34 | E113: =E109+E110 -> 366972.06 | F113: =F109+F110 -> 342993.79 | G113: =G109+G110 -> 316722.21 | H113: =H109+H110 -> 288157.31 | I113: =I109+I110 -> 261557.42 | J113: =J109+J110 -> 236922.55 | ... BJ113: =BJ109+BJ110 -> -462098.28
...

Sheet Checks
A1: Model checks | E1: =HYPERLINK("#'Cover'!A1","◂ Contents") -> ◂ Contents
A2: Live formulas: they re-run every time an input changes.
A3: Check | B3: Result | C3: What it tests
A4: Annual revenue ties to period detail | B4: =IF(ABS(SUM('P&L'!$B$5:$F$5)-SUM(Monthly!$C$32:$BJ$32))<0.5,"PASS","FAIL") -> PASS | C4: Sum of annual revenue equals the sum of every period
A5: Annual net income ties to period detail | B5: =IF(ABS(SUM('P&L'!$B$26:$F$26)-SUM(Monthly!$C$61:$BJ$61))<0.5,"PASS","FAIL") -> PASS | C5: Sum of annual net income equals the sum of every period
A6: EBITDA reconciliation | B6: =IF(ABS(SUM(Monthly!$C$52:$BJ$52)-SUM(Monthly!$C$39:$BJ$39)-SUM(Monthly!$C$51:$BJ$51))<0.5,"PASS","FAIL") -> PASS | C6: EBITDA = gross profit + operating expenses (costs are negative)
A7: Cash roll-forward | B7: =IF(ABS(INDEX(Monthly!$C$95:$BJ$95,60)-SUM(Monthly!$C$93:$BJ$93))<0.5,"PASS","FAIL") -> PASS | C7: Closing cash = all net cash flows since the start (opening cash is zero)
A8: Scenario selector valid | B8: =IF(AND(ISNUMBER(Dashboard!B4),Dashboard!B4>=1,Dashboard!B4<=3,INT(Dashboard!B4)=Dashboard!B4),"PASS","FAIL") -> PASS | C8: Dashboard!B4 is 1, 2 or 3
A9: Scenario ordering of drivers | B9: =IF(AND(Inputs!$B$8<=Inputs!$C$8,Inputs!$C$8<=Inputs!$D$8,Inputs!$B$10<=Inputs!$C$10,Inputs!$C$10<=Inputs!$D$10,Inputs!$B$11<=Inputs!$C$11,Inputs!$C$11<=Inputs!$D$11,Inputs!$B$12>=Inputs!$C$12,Inputs!$C$12>=Inputs!$D$12,Inputs!$B$14>=Inputs!$C$14,Inputs!$C$14>=Inputs!$D$14,Inputs!$B$17<=Inputs!$C$17,Inputs!$C$17<=Inputs!$D$17,Inputs!$B$18<=Inputs!$C$18,Inputs!$C$18<=Inputs!$D$18,Inputs!$B$19<=Inputs!$C$19,Inputs!$C$19<=Inputs!$D$19,Inputs!$B$20>=Inputs!$C$20,Inputs!$C$20>=Inputs!$D$20,Inputs!$B$21<=Inputs!$C$21,Inputs!$C$21<=Inputs!$D$21,Inputs!$B$23<=Inputs!$C$23,Inputs!$C$23<=Inputs!$D$23,Inputs!$B$28>=Inputs!$C$28,Inputs!$C$28>=Inputs!$D$28,Inputs!$B$29>=Inputs!$C$29,Inputs!$C$29>=Inputs!$D$29,Inputs!$B$32>=Inputs!$C$32,Inputs!$C$32>=Inputs!$D$32,Inputs!$B$33>=Inputs!$C$33,Inputs!$C$33>=Inputs!$D$33,Inputs!$B$38>=Inputs!$C$38,Inputs!$C$38>=Inputs!$D$38,Inputs!$B$40>=Inputs!$C$40,Inputs!$C$40>=Inputs!$D$40,Inputs!$B$46>=Inputs!$C$46,Inputs!$C$46>=Inputs!$D$46,Inputs!$B$57<=Inputs!$C$57,Inputs!$C$57<=Inputs!$D$57,Inputs!$B$59<=Inputs!$C$59,Inputs!$C$59<=Inputs!$D$59,Inputs!$B$61<=Inputs!$C$61,Inputs!$C$61<=Inputs!$D$61,Inputs!$B$63<=Inputs!$C$63,Inputs!$C$63<=Inputs!$D$63,Inputs!$B$65<=Inputs!$C$65,Inputs!$C$65<=Inputs!$D$65,Inputs!$B$67<=Inputs!$C$67,Inputs!$C$67<=Inputs!$D$67,Inputs!$B$91>=Inputs!$C$91,Inputs!$C$91>=Inputs!$D$91,Inputs!$B$92<=Inputs!$C$92,Inputs!$C$92<=Inputs!$D$92,Inputs!$B$93<=Inputs!$C$93,Inputs!$C$93<=Inputs!$D$93),"PASS","FAIL") -> PASS | C9: Low / Base / High ordered the right way for every growth and cost driver
A10: Gross margin within 0–100% | B10: =IF(AND(MIN('P&L'!$B$8:$F$8)>=0,MAX('P&L'!$B$8:$F$8)<=1),"PASS","FAIL") -> PASS | C10: Gross margin never negative or above 100%
A11: Loan balance never negative | B11: =IF(MIN(Monthly!$C$78:$BJ$78)>=-0.5,"PASS","FAIL") -> PASS | C11: Repayments never exceed the loan
A12: Funding table ties to the cash flow | B12: =IF(ABS('Break-even'!B18-('Break-even'!B16-'Break-even'!B10))<0.5,"PASS","FAIL") -> PASS | C12: Lowest cash balance = sources of funds − uses of funds up to that point
A13: Valuation: discounting ties to NPV() | B13: =IF(ABS(Valuation!B23-NPV(Valuation!B6,Valuation!$B$17:$F$17))<0.5,"PASS","FAIL") -> PASS | C13: Sum of discounted free cash flows equals Excel's NPV of the same flows
A14: Valuation: WACC above terminal growth | B14: =IF(Valuation!B6>Valuation!B7,"PASS","FAIL") -> PASS | C14: The perpetual-growth formula needs WACC > g
A15: Valuation: sensitivity centre = enterprise value | B15: =IF(ABS(Valuation!D36-Valuation!B27)<0.5,"PASS","FAIL") -> PASS | C15: The middle of the WACC × growth table reproduces the headline value
A16: Valuation: final-year cash flow positive | B16: =IF(Valuation!$F$17>0,"PASS","WARN") -> PASS | C16: Business warning: a negative final-year cash flow gives a negative terminal value (often a 1-year plan still carrying start-up spending)
A17: Sources & uses balance | B17: =IF(ABS('Sources & Uses'!B21-'Sources & Uses'!B28)<0.5,"PASS","FAIL") -> PASS | C17: Sources of funds = uses of funds (incl. cash at the end) for the Sources & Uses period
A18: No error values | B18: =IF(SUMPRODUCT(--ISERROR(Monthly!$C$4:$BJ$113))+SUMPRODUCT(--ISERROR(Headcount!$C$4:$BJ$17))+SUMPRODUCT(--ISERROR('P&L'!$B$3:$F$27))+SUMPRODUCT(--ISERROR('Cash Flow'!$B$3:$F$18))+SUMPRODUCT(--ISERROR('Balance Sheet'!$B$3:$F$17))+SUMPRODUCT(--ISERROR(KPIs!$B$27:$F$47))+SUMPRODUCT(--ISERROR('Break-even'!$B$26:$F$33))+SUMPRODUCT(--ISERROR(Valuation!$B$14:$F$19))+SUMPRODUCT(--ISERROR('Break-even'!$B$3:$F$35))+SUMPRODUCT(--ISERROR(Valuation!$A$3:$F$40))+SUMPRODUCT(--ISERROR('Sources & Uses'!$B$3:$C$30))+SUMPRODUCT(--ISERROR(Dashboard!$A$6:$W$43))+SUMPRODUCT(--ISERROR(Summary!$A$5:$S$52))+SUMPRODUCT(--ISERROR(KPIs!$A$4:$G$47))+SUMPRODUCT(--ISERROR('Scenario calc'!$C$6:$BJ$127))+SUMPRODUCT(--ISERROR('Scenario calc'!$C$132:$BJ$253))+SUMPRODUCT(--ISERROR('Scenario calc'!$C$258:$BJ$379))+SUMPRODUCT(--ISERROR(Scenarios!$B$5:$F$50))=0,"PASS","FAIL") -> PASS | C18: No error values (divide-by-zero, broken references) on any calculation sheet
A19: Summary ties to statements | B19: =IF(IFERROR(AND(SUMPRODUCT(--(ABS(Summary!$B$7:$F$7-'P&L'!$B$5:$F$5)>0.5))=0,SUMPRODUCT(--(ABS(Summary!$B$19:$F$19-'P&L'!$B$26:$F$26)>0.5))=0,SUMPRODUCT(--(ABS(Summary!$B$31:$F$31-'Cash Flow'!$B$18:$F$18)>0.5))=0,SUMPRODUCT(--(ABS(Summary!$B$41:$F$41-'Balance Sheet'!$B$5:$F$5)>0.5))=0,ABS(SUM(Summary!$H$7:$S$7)-INDEX(Summary!$B$7:$F$7,Summary!$R$2))<0.5,ABS(SUM(Summary!$H$19:$S$19)-INDEX(Summary!$B$19:$F$19,Summary!$R$2))<0.5,ABS(Summary!$S$31-INDEX(Summary!$B$31:$F$31,Summary!$R$2))<0.5),FALSE()),"PASS","FAIL") -> PASS | C19: Summary revenue, net income and closing cash equal the statements every year; the detailed year adds up to its annual figure
A20: DuPont ties to return on equity | B20: =IF(SUMPRODUCT(--(ABS(KPIs!$B$24:$F$24)>0.000000001))>0,"FAIL",IF(SUMPRODUCT(ISNUMBER(KPIs!$B$23:$F$23)*ISNUMBER(KPIs!$B$16:$F$16))=0,"n/a","PASS")) -> PASS | C20: Net margin × asset turnover × equity multiplier equals return on equity every year; n/a = no year where both are defined (a one-sided n/a is a FAIL)
A21: Scenarios: Active = selected scenario | B21: =IF(IFERROR(AND(ABS(Scenarios!E17-INDEX(Scenarios!B17:D17,1,Dashboard!$B$4))<0.5,ABS(Scenarios!E18-INDEX(Scenarios!B18:D18,1,Dashboard!$B$4))<0.5,ABS(Scenarios!E19-INDEX(Scenarios!B19:D19,1,Dashboard!$B$4))<0.5,ABS(Scenarios!E20-INDEX(Scenarios!B20:D20,1,Dashboard!$B$4))<0.000001,ABS(Scenarios!E21-INDEX(Scenarios!B21:D21,1,Dashboard!$B$4))<0.5,ABS(Scenarios!E22-INDEX(Scenarios!B22:D22,1,Dashboard!$B$4))<0.5,ABS(Scenarios!E23-INDEX(Scenarios!B23:D23,1,Dashboard!$B$4))<0.5,ABS(Scenarios!E24-INDEX(Scenarios!B24:D24,1,Dashboard!$B$4))<0.5,ABS(Scenarios!E25-INDEX(Scenarios!B25:D25,1,Dashboard!$B$4))<0.5,ABS(Scenarios!E26-INDEX(Scenarios!B26:D26,1,Dashboard!$B$4))<0.5),FALSE()),"PASS","FAIL") -> PASS | C21: On the Scenarios sheet the live model (Active) equals the Low / Base / High column chosen on the Dashboard for every output
A22: Balance sheet balances every period | B22: =IF(SUMPRODUCT(--(ABS(Monthly!$C$113:$BJ$113)>0.5))=0,"PASS","FAIL") -> PASS | C22: Assets = liabilities + equity in every period
A23: Funding sufficient (cash ≥ 0) | B23: =IF(MIN(Monthly!$C$95:$BJ$95)>=0,"PASS","WARN") -> PASS | C23: Business warning, not an error: cash dips below zero in this scenario
A25: Overall verdict | B25: =IF(COUNTIF(B4:B23,"FAIL")>0,"FAIL",IF(COUNTIF(B4:B23,"WARN")>0,"PASS WITH WARNINGS","PASS")) -> PASS
