Workbook

Sheet Cover
B2: Dental practice financial model (growing)
B3: 3-year financial model · monthly detail · Low / Base / High scenarios · US dollars · Full plan
B5: Purpose | D5: Revenue and profit plan
B6: Active scenario | D6: =Dashboard!C4&" (change it on the Dashboard, cell B4)" -> Base (change it on the Dashboard, cell B4)
B7: Model checks | D7: =Checks!B25 -> PASS
B8: Prepared | D8: 22 October 2026
B10: Contents
C11: PRESENTATION
B12: 1 | C12: =HYPERLINK("#Dashboard!A1","Dashboard") -> Dashboard | D12: Scenario switch, key numbers, core financials
B13: 2 | C13: =HYPERLINK("#Summary!A1","Summary") -> Summary | D13: Income statement, cash flow and balance sheet — every year and any year by month
B14: 3 | C14: =HYPERLINK("#Scenarios!A1","Scenarios") -> Scenarios | D14: Low / Base / High side by side: drivers, outputs, charts
B15: 4 | C15: =HYPERLINK("#'Break-even'!A1","Break-even") -> Break-even | D15: Startup costs, funding need, break-even timing and revenue
B16: 5 | C16: =HYPERLINK("#Valuation!A1","Valuation") -> Valuation | D16: Free cash flow, DCF (perpetual growth and exit multiple), WACC × growth sensitivity
B17: 6 | C17: =HYPERLINK("#'Sources & Uses'!A1","Sources & Uses") -> Sources & Uses | D17: Funding structure, sources and uses of cash for the first months
B18: 7 | C18: =HYPERLINK("#KPIs!A1","KPIs") -> KPIs | D18: Financial ratios, DuPont analysis, industry metrics
C19: INPUTS
B20: 8 | C20: =HYPERLINK("#Inputs!A1","Inputs") -> Inputs | D20: Every assumption, Low / Base / High, with units and comments
C21: STATEMENTS
B22: 9 | C22: =HYPERLINK("#'P&L'!A1","P&L") -> P&L | D22: Annual profit & loss
B23: 10 | C23: =HYPERLINK("#'Cash Flow'!A1","Cash Flow") -> Cash Flow | D23: Annual cash flow statement
B24: 11 | C24: =HYPERLINK("#'Balance Sheet'!A1","Balance Sheet") -> Balance Sheet | D24: Balance sheet at year end
C25: CALCULATIONS
B26: 12 | C26: =HYPERLINK("#Monthly!A1","Monthly") -> Monthly | D26: Month-by-month engine of the model
B27: 13 | C27: =HYPERLINK("#Headcount!A1","Headcount") -> Headcount | D27: Team and payroll
B28: 14 | C28: =HYPERLINK("#'Scenario calc'!A1","Scenario calc") -> Scenario calc | D28: Low, Base and High calculated side by side for the Scenarios sheet
C29: CONTROL
B30: 15 | C30: =HYPERLINK("#Checks!A1","Checks") -> Checks | D30: Live integrity checks and the overall verdict
B32: How to read this file
C33: 1000 | D33: Input you can change — yellow cell with a blue figure (Inputs sheet and the view switches)
C34: 1000 | D34: Formula — calculated, do not overwrite
C35: 1000 | D35: Link to another sheet
C36: 1000 | D36: Active value the model uses (follows the scenario)

Sheet Dashboard
A1: Dashboard | W1: =HYPERLINK("#'Cover'!A1","◂ Contents") -> ◂ Contents
A2: Dental practice financial model (growing)
A4: Active scenario | B4: 2 | C4: =CHOOSE(B4,"Low","Base","High") -> Base | D4: 1 = Low · 2 = Base · 3 = High — every sheet follows this cell | S4: Model checks | T4: =Checks!B25 -> PASS
A6: REVENUE · YEAR 3 | C6: EBITDA MARGIN · YEAR 3 | H6: NET INCOME · YEAR 3 | L6: LOWEST CASH BALANCE | P6: FUNDING REQUIRED | T6: ENTERPRISE VALUE (DCF)
A7: =D12 -> 2337329.1 | C7: =D17 -> 0.19248584 | H7: =D18 -> 332947.38 | L7: =F38 -> 123032.22 | P7: =F36 -> 475967.78 | T7: =F43 -> 1983726.8
A8: =IF(AND(B12>0,D12>=0),(D12/B12)^(1/2)-1,"CAGR n/a") -> 0.087785827 | C8: =D16 -> 449902.76 | H8: =D19 -> 0.1424478 | L8: ='Break-even'!B6 -> 1 | P8: =IF(F37>=0,"Covered by funding raised",-F37) -> 225967.78 | T8: Average of 2 methods
A10: Core financials ($'000) — active scenario
B11: 1 | C11: 2 | D11: 3
A12: Revenue | B12: =SUMIF(Monthly!$C$5:$AL$5,B$11,Monthly!$C$31:$AL$31) -> 1975300.1 | C12: =SUMIF(Monthly!$C$5:$AL$5,C$11,Monthly!$C$31:$AL$31) -> 2149133.3 | D12: =SUMIF(Monthly!$C$5:$AL$5,D$11,Monthly!$C$31:$AL$31) -> 2337329.1
A13: Gross profit | B13: =SUMIF(Monthly!$C$5:$AL$5,B$11,Monthly!$C$38:$AL$38) -> 1700585.9 | C13: =SUMIF(Monthly!$C$5:$AL$5,C$11,Monthly!$C$38:$AL$38) -> 1850264.9 | D13: =SUMIF(Monthly!$C$5:$AL$5,D$11,Monthly!$C$38:$AL$38) -> 2012307.8
A14: Gross margin | B14: =IF(B12=0,0,B13/B12) -> 0.86092536 | C14: =IF(C12=0,0,C13/C12) -> 0.86093538 | D14: =IF(D12=0,0,D13/D12) -> 0.86094328
A15: Operating expenses | B15: =SUMIF(Monthly!$C$5:$AL$5,B$11,Monthly!$C$50:$AL$50) -> -1397453.4 | C15: =SUMIF(Monthly!$C$5:$AL$5,C$11,Monthly!$C$50:$AL$50) -> -1476940 | D15: =SUMIF(Monthly!$C$5:$AL$5,D$11,Monthly!$C$50:$AL$50) -> -1562405.1
A16: EBITDA | B16: =SUMIF(Monthly!$C$5:$AL$5,B$11,Monthly!$C$51:$AL$51) -> 303132.53 | C16: =SUMIF(Monthly!$C$5:$AL$5,C$11,Monthly!$C$51:$AL$51) -> 373324.91 | D16: =SUMIF(Monthly!$C$5:$AL$5,D$11,Monthly!$C$51:$AL$51) -> 449902.76
A17: EBITDA margin | B17: =IF(B12=0,0,B16/B12) -> 0.15346151 | C17: =IF(C12=0,0,C16/C12) -> 0.17370952 | D17: =IF(D12=0,0,D16/D12) -> 0.19248584
A18: Net income | B18: =SUMIF(Monthly!$C$5:$AL$5,B$11,Monthly!$C$60:$AL$60) -> 221437.82 | C18: =SUMIF(Monthly!$C$5:$AL$5,C$11,Monthly!$C$60:$AL$60) -> 274821.52 | D18: =SUMIF(Monthly!$C$5:$AL$5,D$11,Monthly!$C$60:$AL$60) -> 332947.38
A19: Net margin | B19: =IF(B12=0,0,B18/B12) -> 0.11210338 | C19: =IF(C12=0,0,C18/C12) -> 0.12787551 | D19: =IF(D12=0,0,D18/D12) -> 0.1424478
A20: Operating cash flow | B20: =SUMIF(Monthly!$C$5:$AL$5,B$11,Monthly!$C$84:$AL$84) -> 147060.42 | C20: =SUMIF(Monthly!$C$5:$AL$5,C$11,Monthly!$C$84:$AL$84) -> 282618.64 | D20: =SUMIF(Monthly!$C$5:$AL$5,D$11,Monthly!$C$84:$AL$84) -> 344946.13
A21: Investing cash flow | B21: =SUMIF(Monthly!$C$5:$AL$5,B$11,Monthly!$C$85:$AL$85) -> -89629.501 | C21: =SUMIF(Monthly!$C$5:$AL$5,C$11,Monthly!$C$85:$AL$85) -> -32237 | D21: =SUMIF(Monthly!$C$5:$AL$5,D$11,Monthly!$C$85:$AL$85) -> -35059.937
A22: Financing cash flow | B22: =SUMIF(Monthly!$C$5:$AL$5,B$11,Monthly!$C$87:$AL$87) -> 230357.14 | C22: =SUMIF(Monthly!$C$5:$AL$5,C$11,Monthly!$C$87:$AL$87) -> -21428.571 | D22: =SUMIF(Monthly!$C$5:$AL$5,D$11,Monthly!$C$87:$AL$87) -> -21428.571
A23: Net change in cash | B23: =SUMIF(Monthly!$C$5:$AL$5,B$11,Monthly!$C$88:$AL$88) -> 287788.06 | C23: =SUMIF(Monthly!$C$5:$AL$5,C$11,Monthly!$C$88:$AL$88) -> 228953.06 | D23: =SUMIF(Monthly!$C$5:$AL$5,D$11,Monthly!$C$88:$AL$88) -> 288457.62
A24: Year-end cash | B24: =INDEX(Monthly!$C$90:$AL$90,B$11*12) -> 287788.06 | C24: =INDEX(Monthly!$C$90:$AL$90,C$11*12) -> 516741.13 | D24: =INDEX(Monthly!$C$90:$AL$90,D$11*12) -> 805198.75
A26: Dental practice metrics
B27: 1 | C27: 2 | D27: 3
A28: Active patients (year end) | B28: =KPIs!B29 -> 3170.4728 | C28: =KPIs!C29 -> 3348.9509 | D28: =KPIs!D29 -> 3536.0755
A29: Doctor chair utilisation | B29: =KPIs!B37 -> 0.81766307 | C29: =KPIs!C37 -> 0.86358429 | D29: =KPIs!D37 -> 0.91174739
A30: Production per visit | B30: =KPIs!B44 -> 262.12257 | C30: =KPIs!C44 -> 269.97414 | D30: =KPIs!D44 -> 278.06352
A31: Team (FTE, year end) | B31: =INDEX(Headcount!$C$13:$AL$13,B$27*12) -> 12.5 | C31: =INDEX(Headcount!$C$13:$AL$13,C$27*12) -> 12.98 | D31: =INDEX(Headcount!$C$13:$AL$13,D$27*12) -> 13.4828
A33: Funding & valuation ($'000) — active scenario
A34: Equity raised | F34: =Inputs!$E$83 -> 100000
A35: Loan drawn | F35: =Inputs!$E$84 -> 150000
A36: Funding required (incl. cash buffer) | F36: ='Break-even'!B12 -> 475967.78
A37: Funding surplus / (shortfall) | F37: ='Break-even'!B17 -> -225967.78
A38: ="Lowest cash balance (month "&'Break-even'!B6&")" -> Lowest cash balance (month 1) | F38: ='Break-even'!B18 -> 123032.22
A39: First month with positive EBITDA | F39: ='Break-even'!B21 -> 1
A40: Cash invested paid back | F40: ='Break-even'!B23 -> 9
A41: Enterprise value — perpetual growth | F41: =Valuation!B27 -> 1929696
A42: Enterprise value — exit multiple | F42: =Valuation!C27 -> 2037757.6
A43: Enterprise value — average | F43: =Valuation!B30 -> 1983726.8

Sheet Summary
A1: Financial statements summary | U1: =HYPERLINK("#'Cover'!A1","◂ Contents") -> ◂ Contents
A2: Dental practice financial model (growing) | P2: Select detailed year: | R2: 1
A5: Income statement ($'000) — by year | H5: ="Income statement ($'000) — Year "&$R$2&", by month" -> Income statement ($'000) — Year 1, by month
B6: 1 | C6: 2 | D6: 3 | H6: =INDEX(Monthly!$C$4:$AL$4,($R$2-1)*12+1) -> 1 | I6: =INDEX(Monthly!$C$4:$AL$4,($R$2-1)*12+2) -> 2 | J6: =INDEX(Monthly!$C$4:$AL$4,($R$2-1)*12+3) -> 3 | K6: =INDEX(Monthly!$C$4:$AL$4,($R$2-1)*12+4) -> 4 | L6: =INDEX(Monthly!$C$4:$AL$4,($R$2-1)*12+5) -> 5 | M6: =INDEX(Monthly!$C$4:$AL$4,($R$2-1)*12+6) -> 6 | N6: =INDEX(Monthly!$C$4:$AL$4,($R$2-1)*12+7) -> 7 | O6: =INDEX(Monthly!$C$4:$AL$4,($R$2-1)*12+8) -> 8 | P6: =INDEX(Monthly!$C$4:$AL$4,($R$2-1)*12+9) -> 9 | Q6: =INDEX(Monthly!$C$4:$AL$4,($R$2-1)*12+10) -> 10 | R6: =INDEX(Monthly!$C$4:$AL$4,($R$2-1)*12+11) -> 11 | S6: =INDEX(Monthly!$C$4:$AL$4,($R$2-1)*12+12) -> 12
A7: Revenue | B7: ='P&L'!B5 -> 1975300.1 | C7: ='P&L'!C5 -> 2149133.3 | D7: ='P&L'!D5 -> 2337329.1 | H7: =INDEX(Monthly!$C$31:$AL$31,($R$2-1)*12+1) -> 160761.97 | I7: =INDEX(Monthly!$C$31:$AL$31,($R$2-1)*12+2) -> 161494.44 | J7: =INDEX(Monthly!$C$31:$AL$31,($R$2-1)*12+3) -> 162216.65 | K7: =INDEX(Monthly!$C$31:$AL$31,($R$2-1)*12+4) -> 162928.76 | L7: =INDEX(Monthly!$C$31:$AL$31,($R$2-1)*12+5) -> 163630.89 | M7: =INDEX(Monthly!$C$31:$AL$31,($R$2-1)*12+6) -> 164323.19 | N7: =INDEX(Monthly!$C$31:$AL$31,($R$2-1)*12+7) -> 165005.81 | O7: =INDEX(Monthly!$C$31:$AL$31,($R$2-1)*12+8) -> 165678.86 | P7: =INDEX(Monthly!$C$31:$AL$31,($R$2-1)*12+9) -> 166342.49 | Q7: =INDEX(Monthly!$C$31:$AL$31,($R$2-1)*12+10) -> 166996.84 | R7: =INDEX(Monthly!$C$31:$AL$31,($R$2-1)*12+11) -> 167642.02 | S7: =INDEX(Monthly!$C$31:$AL$31,($R$2-1)*12+12) -> 168278.17
A8: Cost of sales | B8: ='P&L'!B6 -> -274714.15 | C8: ='P&L'!C6 -> -298868.42 | D8: ='P&L'!D6 -> -325021.31 | H8: =INDEX(Monthly!$C$37:$AL$37,($R$2-1)*12+1) -> -22377.042 | I8: =INDEX(Monthly!$C$37:$AL$37,($R$2-1)*12+2) -> -22475.267 | J8: =INDEX(Monthly!$C$37:$AL$37,($R$2-1)*12+3) -> -22572.117 | K8: =INDEX(Monthly!$C$37:$AL$37,($R$2-1)*12+4) -> -22667.611 | L8: =INDEX(Monthly!$C$37:$AL$37,($R$2-1)*12+5) -> -22761.768 | M8: =INDEX(Monthly!$C$37:$AL$37,($R$2-1)*12+6) -> -22854.608 | N8: =INDEX(Monthly!$C$37:$AL$37,($R$2-1)*12+7) -> -22946.147 | O8: =INDEX(Monthly!$C$37:$AL$37,($R$2-1)*12+8) -> -23036.405 | P8: =INDEX(Monthly!$C$37:$AL$37,($R$2-1)*12+9) -> -23125.399 | Q8: =INDEX(Monthly!$C$37:$AL$37,($R$2-1)*12+10) -> -23213.147 | R8: =INDEX(Monthly!$C$37:$AL$37,($R$2-1)*12+11) -> -23299.667 | S8: =INDEX(Monthly!$C$37:$AL$37,($R$2-1)*12+12) -> -23384.975
A9: Gross profit | B9: ='P&L'!B7 -> 1700585.9 | C9: ='P&L'!C7 -> 1850264.9 | D9: ='P&L'!D7 -> 2012307.8 | H9: =INDEX(Monthly!$C$38:$AL$38,($R$2-1)*12+1) -> 138384.93 | I9: =INDEX(Monthly!$C$38:$AL$38,($R$2-1)*12+2) -> 139019.17 | J9: =INDEX(Monthly!$C$38:$AL$38,($R$2-1)*12+3) -> 139644.54 | K9: =INDEX(Monthly!$C$38:$AL$38,($R$2-1)*12+4) -> 140261.14 | L9: =INDEX(Monthly!$C$38:$AL$38,($R$2-1)*12+5) -> 140869.12 | M9: =INDEX(Monthly!$C$38:$AL$38,($R$2-1)*12+6) -> 141468.59 | N9: =INDEX(Monthly!$C$38:$AL$38,($R$2-1)*12+7) -> 142059.66 | O9: =INDEX(Monthly!$C$38:$AL$38,($R$2-1)*12+8) -> 142642.46 | P9: =INDEX(Monthly!$C$38:$AL$38,($R$2-1)*12+9) -> 143217.1 | Q9: =INDEX(Monthly!$C$38:$AL$38,($R$2-1)*12+10) -> 143783.69 | R9: =INDEX(Monthly!$C$38:$AL$38,($R$2-1)*12+11) -> 144342.35 | S9: =INDEX(Monthly!$C$38:$AL$38,($R$2-1)*12+12) -> 144893.19
A10: Gross margin | B10: ='P&L'!B8 -> 0.86092536 | C10: ='P&L'!C8 -> 0.86093538 | D10: ='P&L'!D8 -> 0.86094328 | H10: =IF(H7=0,0,H9/H7) -> 0.86080637 | I10: =IF(I7=0,0,I9/I7) -> 0.86082947 | J10: =IF(J7=0,0,J9/J7) -> 0.86085204 | K10: =IF(K7=0,0,K9/K7) -> 0.86087409 | L10: =IF(L7=0,0,L9/L7) -> 0.86089565 | M10: =IF(M7=0,0,M9/M7) -> 0.86091673 | N10: =IF(N7=0,0,N9/N7) -> 0.86093734 | O10: =IF(O7=0,0,O9/O7) -> 0.86095749 | ... S10: =IF(S7=0,0,S9/S7) -> 0.86103381
A11: Total operating expenses | B11: ='P&L'!B18 -> -1397453.4 | C11: ='P&L'!C18 -> -1476940 | D11: ='P&L'!D18 -> -1562405.1 | H11: =INDEX(Monthly!$C$50:$AL$50,($R$2-1)*12+1) -> -116196.67 | I11: =INDEX(Monthly!$C$50:$AL$50,($R$2-1)*12+2) -> -116245.76 | J11: =INDEX(Monthly!$C$50:$AL$50,($R$2-1)*12+3) -> -116294.16 | K11: =INDEX(Monthly!$C$50:$AL$50,($R$2-1)*12+4) -> -116341.88 | L11: =INDEX(Monthly!$C$50:$AL$50,($R$2-1)*12+5) -> -116388.94 | M11: =INDEX(Monthly!$C$50:$AL$50,($R$2-1)*12+6) -> -116435.34 | N11: =INDEX(Monthly!$C$50:$AL$50,($R$2-1)*12+7) -> -116481.09 | O11: =INDEX(Monthly!$C$50:$AL$50,($R$2-1)*12+8) -> -116526.2 | P11: =INDEX(Monthly!$C$50:$AL$50,($R$2-1)*12+9) -> -116570.67 | Q11: =INDEX(Monthly!$C$50:$AL$50,($R$2-1)*12+10) -> -116614.53 | R11: =INDEX(Monthly!$C$50:$AL$50,($R$2-1)*12+11) -> -116657.77 | S11: =INDEX(Monthly!$C$50:$AL$50,($R$2-1)*12+12) -> -116700.4
A12: EBITDA | B12: ='P&L'!B19 -> 303132.53 | C12: ='P&L'!C19 -> 373324.91 | D12: ='P&L'!D19 -> 449902.76 | H12: =INDEX(Monthly!$C$51:$AL$51,($R$2-1)*12+1) -> 22188.26 | I12: =INDEX(Monthly!$C$51:$AL$51,($R$2-1)*12+2) -> 22773.414 | J12: =INDEX(Monthly!$C$51:$AL$51,($R$2-1)*12+3) -> 23350.376 | K12: =INDEX(Monthly!$C$51:$AL$51,($R$2-1)*12+4) -> 23919.26 | L12: =INDEX(Monthly!$C$51:$AL$51,($R$2-1)*12+5) -> 24480.18 | M12: =INDEX(Monthly!$C$51:$AL$51,($R$2-1)*12+6) -> 25033.247 | N12: =INDEX(Monthly!$C$51:$AL$51,($R$2-1)*12+7) -> 25578.571 | O12: =INDEX(Monthly!$C$51:$AL$51,($R$2-1)*12+8) -> 26116.261 | P12: =INDEX(Monthly!$C$51:$AL$51,($R$2-1)*12+9) -> 26646.423 | Q12: =INDEX(Monthly!$C$51:$AL$51,($R$2-1)*12+10) -> 27169.162 | R12: =INDEX(Monthly!$C$51:$AL$51,($R$2-1)*12+11) -> 27684.584 | S12: =INDEX(Monthly!$C$51:$AL$51,($R$2-1)*12+12) -> 28192.789
A13: EBITDA margin | B13: ='P&L'!B20 -> 0.15346151 | C13: ='P&L'!C20 -> 0.17370952 | D13: ='P&L'!D20 -> 0.19248584 | H13: =IF(H7=0,0,H12/H7) -> 0.13801933 | I13: =IF(I7=0,0,I12/I7) -> 0.14101671 | J13: =IF(J7=0,0,J12/J7) -> 0.14394561 | K13: =IF(K7=0,0,K12/K7) -> 0.14680809 | L13: =IF(L7=0,0,L12/L7) -> 0.1496061 | M13: =IF(M7=0,0,M12/M7) -> 0.15234153 | N13: =IF(N7=0,0,N12/N7) -> 0.15501619 | O13: =IF(O7=0,0,O12/O7) -> 0.15763182 | ... S13: =IF(S7=0,0,S12/S7) -> 0.16753682
A14: Depreciation | B14: ='P&L'!B21 -> -10846.744 | C14: ='P&L'!C21 -> -15279.934 | D14: ='P&L'!D21 -> -20102.158 | H14: =INDEX(Monthly!$C$65:$AL$65,($R$2-1)*12+1) -> -742.99321 | I14: =INDEX(Monthly!$C$65:$AL$65,($R$2-1)*12+2) -> -771.8315 | J14: =INDEX(Monthly!$C$65:$AL$65,($R$2-1)*12+3) -> -800.79876 | K14: =INDEX(Monthly!$C$65:$AL$65,($R$2-1)*12+4) -> -829.89318 | L14: =INDEX(Monthly!$C$65:$AL$65,($R$2-1)*12+5) -> -859.11298 | M14: =INDEX(Monthly!$C$65:$AL$65,($R$2-1)*12+6) -> -888.45641 | N14: =INDEX(Monthly!$C$65:$AL$65,($R$2-1)*12+7) -> -917.92173 | O14: =INDEX(Monthly!$C$65:$AL$65,($R$2-1)*12+8) -> -947.50724 | P14: =INDEX(Monthly!$C$65:$AL$65,($R$2-1)*12+9) -> -977.21126 | Q14: =INDEX(Monthly!$C$65:$AL$65,($R$2-1)*12+10) -> -1007.0321 | R14: =INDEX(Monthly!$C$65:$AL$65,($R$2-1)*12+11) -> -1036.9682 | S14: =INDEX(Monthly!$C$65:$AL$65,($R$2-1)*12+12) -> -1067.0179
A15: EBIT | B15: ='P&L'!B22 -> 292285.78 | C15: ='P&L'!C22 -> 358044.98 | D15: ='P&L'!D22 -> 429800.6 | H15: =INDEX(Monthly!$C$54:$AL$54,($R$2-1)*12+1) -> 21445.267 | I15: =INDEX(Monthly!$C$54:$AL$54,($R$2-1)*12+2) -> 22001.582 | J15: =INDEX(Monthly!$C$54:$AL$54,($R$2-1)*12+3) -> 22549.577 | K15: =INDEX(Monthly!$C$54:$AL$54,($R$2-1)*12+4) -> 23089.367 | L15: =INDEX(Monthly!$C$54:$AL$54,($R$2-1)*12+5) -> 23621.067 | M15: =INDEX(Monthly!$C$54:$AL$54,($R$2-1)*12+6) -> 24144.791 | N15: =INDEX(Monthly!$C$54:$AL$54,($R$2-1)*12+7) -> 24660.649 | O15: =INDEX(Monthly!$C$54:$AL$54,($R$2-1)*12+8) -> 25168.753 | P15: =INDEX(Monthly!$C$54:$AL$54,($R$2-1)*12+9) -> 25669.211 | Q15: =INDEX(Monthly!$C$54:$AL$54,($R$2-1)*12+10) -> 26162.13 | R15: =INDEX(Monthly!$C$54:$AL$54,($R$2-1)*12+11) -> 26647.615 | S15: =INDEX(Monthly!$C$54:$AL$54,($R$2-1)*12+12) -> 27125.771
A16: Interest | B16: ='P&L'!B23 -> -11984.747 | C16: ='P&L'!C23 -> -10169.643 | D16: ='P&L'!D23 -> -8348.2143 | H16: =INDEX(Monthly!$C$55:$AL$55,($R$2-1)*12+1) -> -1062.5 | I16: =INDEX(Monthly!$C$55:$AL$55,($R$2-1)*12+2) -> -1056.1756 | J16: =INDEX(Monthly!$C$55:$AL$55,($R$2-1)*12+3) -> -1043.5268 | K16: =INDEX(Monthly!$C$55:$AL$55,($R$2-1)*12+4) -> -1030.878 | L16: =INDEX(Monthly!$C$55:$AL$55,($R$2-1)*12+5) -> -1018.2292 | M16: =INDEX(Monthly!$C$55:$AL$55,($R$2-1)*12+6) -> -1005.5804 | N16: =INDEX(Monthly!$C$55:$AL$55,($R$2-1)*12+7) -> -992.93155 | O16: =INDEX(Monthly!$C$55:$AL$55,($R$2-1)*12+8) -> -980.28274 | P16: =INDEX(Monthly!$C$55:$AL$55,($R$2-1)*12+9) -> -967.63393 | Q16: =INDEX(Monthly!$C$55:$AL$55,($R$2-1)*12+10) -> -954.98512 | R16: =INDEX(Monthly!$C$55:$AL$55,($R$2-1)*12+11) -> -942.33631 | S16: =INDEX(Monthly!$C$55:$AL$55,($R$2-1)*12+12) -> -929.6875
A17: Pre-tax income | B17: ='P&L'!B24 -> 280301.03 | C17: ='P&L'!C24 -> 347875.34 | D17: ='P&L'!D24 -> 421452.39 | H17: =INDEX(Monthly!$C$56:$AL$56,($R$2-1)*12+1) -> 20382.767 | I17: =INDEX(Monthly!$C$56:$AL$56,($R$2-1)*12+2) -> 20945.407 | J17: =INDEX(Monthly!$C$56:$AL$56,($R$2-1)*12+3) -> 21506.05 | K17: =INDEX(Monthly!$C$56:$AL$56,($R$2-1)*12+4) -> 22058.489 | L17: =INDEX(Monthly!$C$56:$AL$56,($R$2-1)*12+5) -> 22602.838 | M17: =INDEX(Monthly!$C$56:$AL$56,($R$2-1)*12+6) -> 23139.21 | N17: =INDEX(Monthly!$C$56:$AL$56,($R$2-1)*12+7) -> 23667.718 | O17: =INDEX(Monthly!$C$56:$AL$56,($R$2-1)*12+8) -> 24188.471 | P17: =INDEX(Monthly!$C$56:$AL$56,($R$2-1)*12+9) -> 24701.577 | Q17: =INDEX(Monthly!$C$56:$AL$56,($R$2-1)*12+10) -> 25207.145 | R17: =INDEX(Monthly!$C$56:$AL$56,($R$2-1)*12+11) -> 25705.279 | S17: =INDEX(Monthly!$C$56:$AL$56,($R$2-1)*12+12) -> 26196.084
A18: Income tax | B18: ='P&L'!B25 -> -58863.217 | C18: ='P&L'!C25 -> -73053.821 | D18: ='P&L'!D25 -> -88505.001 | H18: =INDEX(Monthly!$C$59:$AL$59,($R$2-1)*12+1) -> -4280.381 | I18: =INDEX(Monthly!$C$59:$AL$59,($R$2-1)*12+2) -> -4398.5354 | J18: =INDEX(Monthly!$C$59:$AL$59,($R$2-1)*12+3) -> -4516.2705 | K18: =INDEX(Monthly!$C$59:$AL$59,($R$2-1)*12+4) -> -4632.2826 | L18: =INDEX(Monthly!$C$59:$AL$59,($R$2-1)*12+5) -> -4746.5959 | M18: =INDEX(Monthly!$C$59:$AL$59,($R$2-1)*12+6) -> -4859.2341 | N18: =INDEX(Monthly!$C$59:$AL$59,($R$2-1)*12+7) -> -4970.2207 | O18: =INDEX(Monthly!$C$59:$AL$59,($R$2-1)*12+8) -> -5079.5788 | P18: =INDEX(Monthly!$C$59:$AL$59,($R$2-1)*12+9) -> -5187.3313 | Q18: =INDEX(Monthly!$C$59:$AL$59,($R$2-1)*12+10) -> -5293.5005 | R18: =INDEX(Monthly!$C$59:$AL$59,($R$2-1)*12+11) -> -5398.1086 | S18: =INDEX(Monthly!$C$59:$AL$59,($R$2-1)*12+12) -> -5501.1776
A19: Net income | B19: ='P&L'!B26 -> 221437.82 | C19: ='P&L'!C26 -> 274821.52 | D19: ='P&L'!D26 -> 332947.38 | H19: =INDEX(Monthly!$C$60:$AL$60,($R$2-1)*12+1) -> 16102.386 | I19: =INDEX(Monthly!$C$60:$AL$60,($R$2-1)*12+2) -> 16546.871 | J19: =INDEX(Monthly!$C$60:$AL$60,($R$2-1)*12+3) -> 16989.779 | K19: =INDEX(Monthly!$C$60:$AL$60,($R$2-1)*12+4) -> 17426.206 | L19: =INDEX(Monthly!$C$60:$AL$60,($R$2-1)*12+5) -> 17856.242 | M19: =INDEX(Monthly!$C$60:$AL$60,($R$2-1)*12+6) -> 18279.976 | N19: =INDEX(Monthly!$C$60:$AL$60,($R$2-1)*12+7) -> 18697.497 | O19: =INDEX(Monthly!$C$60:$AL$60,($R$2-1)*12+8) -> 19108.892 | P19: =INDEX(Monthly!$C$60:$AL$60,($R$2-1)*12+9) -> 19514.246 | Q19: =INDEX(Monthly!$C$60:$AL$60,($R$2-1)*12+10) -> 19913.645 | R19: =INDEX(Monthly!$C$60:$AL$60,($R$2-1)*12+11) -> 20307.171 | S19: =INDEX(Monthly!$C$60:$AL$60,($R$2-1)*12+12) -> 20694.906
A20: Net margin | B20: ='P&L'!B27 -> 0.11210338 | C20: ='P&L'!C27 -> 0.12787551 | D20: ='P&L'!D27 -> 0.1424478 | H20: =IF(H7=0,0,H19/H7) -> 0.1001629 | I20: =IF(I7=0,0,I19/I7) -> 0.10246094 | J20: =IF(J7=0,0,J19/J7) -> 0.10473511 | K20: =IF(K7=0,0,K19/K7) -> 0.10695599 | L20: =IF(L7=0,0,L19/L7) -> 0.10912513 | M20: =IF(M7=0,0,M19/M7) -> 0.11124404 | N20: =IF(N7=0,0,N19/N7) -> 0.11331418 | O20: =IF(O7=0,0,O19/O7) -> 0.11533693 | ... S20: =IF(S7=0,0,S19/S7) -> 0.12298034
A22: Cash flow ($'000) — by year | H22: ="Cash flow ($'000) — Year "&$R$2&", by month" -> Cash flow ($'000) — Year 1, by month
B23: 1 | C23: 2 | D23: 3 | H23: =INDEX(Monthly!$C$4:$AL$4,($R$2-1)*12+1) -> 1 | I23: =INDEX(Monthly!$C$4:$AL$4,($R$2-1)*12+2) -> 2 | J23: =INDEX(Monthly!$C$4:$AL$4,($R$2-1)*12+3) -> 3 | K23: =INDEX(Monthly!$C$4:$AL$4,($R$2-1)*12+4) -> 4 | L23: =INDEX(Monthly!$C$4:$AL$4,($R$2-1)*12+5) -> 5 | M23: =INDEX(Monthly!$C$4:$AL$4,($R$2-1)*12+6) -> 6 | N23: =INDEX(Monthly!$C$4:$AL$4,($R$2-1)*12+7) -> 7 | O23: =INDEX(Monthly!$C$4:$AL$4,($R$2-1)*12+8) -> 8 | P23: =INDEX(Monthly!$C$4:$AL$4,($R$2-1)*12+9) -> 9 | Q23: =INDEX(Monthly!$C$4:$AL$4,($R$2-1)*12+10) -> 10 | R23: =INDEX(Monthly!$C$4:$AL$4,($R$2-1)*12+11) -> 11 | S23: =INDEX(Monthly!$C$4:$AL$4,($R$2-1)*12+12) -> 12
A24: Operating cash flow | B24: ='Cash Flow'!B10 -> 147060.42 | C24: ='Cash Flow'!C10 -> 282618.64 | D24: ='Cash Flow'!D10 -> 344946.13 | H24: =INDEX(Monthly!$C$84:$AL$84,($R$2-1)*12+1) -> -64556.352 | I24: =INDEX(Monthly!$C$84:$AL$84,($R$2-1)*12+2) -> 16946.201 | J24: =INDEX(Monthly!$C$84:$AL$84,($R$2-1)*12+3) -> 17423.292 | K24: =INDEX(Monthly!$C$84:$AL$84,($R$2-1)*12+4) -> 17893.955 | L24: =INDEX(Monthly!$C$84:$AL$84,($R$2-1)*12+5) -> 18358.28 | M24: =INDEX(Monthly!$C$84:$AL$84,($R$2-1)*12+6) -> 18816.357 | N24: =INDEX(Monthly!$C$84:$AL$84,($R$2-1)*12+7) -> 19268.272 | O24: =INDEX(Monthly!$C$84:$AL$84,($R$2-1)*12+8) -> 19714.113 | P24: =INDEX(Monthly!$C$84:$AL$84,($R$2-1)*12+9) -> 20153.963 | Q24: =INDEX(Monthly!$C$84:$AL$84,($R$2-1)*12+10) -> 20587.907 | R24: =INDEX(Monthly!$C$84:$AL$84,($R$2-1)*12+11) -> 21016.028 | S24: =INDEX(Monthly!$C$84:$AL$84,($R$2-1)*12+12) -> 21438.407
A25: Capital spending | B25: ='Cash Flow'!B11 -> -89629.501 | C25: ='Cash Flow'!C11 -> -32237 | D25: ='Cash Flow'!D11 -> -35059.937 | H25: =INDEX(Monthly!$C$85:$AL$85,($R$2-1)*12+1) -> -62411.43 | I25: =INDEX(Monthly!$C$85:$AL$85,($R$2-1)*12+2) -> -2422.4166 | J25: =INDEX(Monthly!$C$85:$AL$85,($R$2-1)*12+3) -> -2433.2498 | K25: =INDEX(Monthly!$C$85:$AL$85,($R$2-1)*12+4) -> -2443.9313 | L25: =INDEX(Monthly!$C$85:$AL$85,($R$2-1)*12+5) -> -2454.4634 | M25: =INDEX(Monthly!$C$85:$AL$85,($R$2-1)*12+6) -> -2464.8479 | N25: =INDEX(Monthly!$C$85:$AL$85,($R$2-1)*12+7) -> -2475.0871 | O25: =INDEX(Monthly!$C$85:$AL$85,($R$2-1)*12+8) -> -2485.1829 | P25: =INDEX(Monthly!$C$85:$AL$85,($R$2-1)*12+9) -> -2495.1374 | Q25: =INDEX(Monthly!$C$85:$AL$85,($R$2-1)*12+10) -> -2504.9525 | R25: =INDEX(Monthly!$C$85:$AL$85,($R$2-1)*12+11) -> -2514.6303 | S25: =INDEX(Monthly!$C$85:$AL$85,($R$2-1)*12+12) -> -2524.1725
A26: Equity raised | B26: ='Cash Flow'!B12 -> 100000 | C26: ='Cash Flow'!C12 -> 0 | D26: ='Cash Flow'!D12 -> 0 | H26: =INDEX(Monthly!$C$86:$AL$86,($R$2-1)*12+1) -> 100000 | I26: =INDEX(Monthly!$C$86:$AL$86,($R$2-1)*12+2) -> 0 | J26: =INDEX(Monthly!$C$86:$AL$86,($R$2-1)*12+3) -> 0 | K26: =INDEX(Monthly!$C$86:$AL$86,($R$2-1)*12+4) -> 0 | L26: =INDEX(Monthly!$C$86:$AL$86,($R$2-1)*12+5) -> 0 | M26: =INDEX(Monthly!$C$86:$AL$86,($R$2-1)*12+6) -> 0 | N26: =INDEX(Monthly!$C$86:$AL$86,($R$2-1)*12+7) -> 0 | O26: =INDEX(Monthly!$C$86:$AL$86,($R$2-1)*12+8) -> 0 | P26: =INDEX(Monthly!$C$86:$AL$86,($R$2-1)*12+9) -> 0 | Q26: =INDEX(Monthly!$C$86:$AL$86,($R$2-1)*12+10) -> 0 | R26: =INDEX(Monthly!$C$86:$AL$86,($R$2-1)*12+11) -> 0 | S26: =INDEX(Monthly!$C$86:$AL$86,($R$2-1)*12+12) -> 0
A27: Loan drawdown | B27: ='Cash Flow'!B13 -> 150000 | C27: ='Cash Flow'!C13 -> 0 | D27: ='Cash Flow'!D13 -> 0 | H27: =INDEX(Monthly!$C$71:$AL$71,($R$2-1)*12+1) -> 150000 | I27: =INDEX(Monthly!$C$71:$AL$71,($R$2-1)*12+2) -> 0 | J27: =INDEX(Monthly!$C$71:$AL$71,($R$2-1)*12+3) -> 0 | K27: =INDEX(Monthly!$C$71:$AL$71,($R$2-1)*12+4) -> 0 | L27: =INDEX(Monthly!$C$71:$AL$71,($R$2-1)*12+5) -> 0 | M27: =INDEX(Monthly!$C$71:$AL$71,($R$2-1)*12+6) -> 0 | N27: =INDEX(Monthly!$C$71:$AL$71,($R$2-1)*12+7) -> 0 | O27: =INDEX(Monthly!$C$71:$AL$71,($R$2-1)*12+8) -> 0 | P27: =INDEX(Monthly!$C$71:$AL$71,($R$2-1)*12+9) -> 0 | Q27: =INDEX(Monthly!$C$71:$AL$71,($R$2-1)*12+10) -> 0 | R27: =INDEX(Monthly!$C$71:$AL$71,($R$2-1)*12+11) -> 0 | S27: =INDEX(Monthly!$C$71:$AL$71,($R$2-1)*12+12) -> 0
A28: Loan repayment | B28: ='Cash Flow'!B14 -> -19642.857 | C28: ='Cash Flow'!C14 -> -21428.571 | D28: ='Cash Flow'!D14 -> -21428.571 | H28: =INDEX(Monthly!$C$72:$AL$72,($R$2-1)*12+1) -> 0 | I28: =INDEX(Monthly!$C$72:$AL$72,($R$2-1)*12+2) -> -1785.7143 | J28: =INDEX(Monthly!$C$72:$AL$72,($R$2-1)*12+3) -> -1785.7143 | K28: =INDEX(Monthly!$C$72:$AL$72,($R$2-1)*12+4) -> -1785.7143 | L28: =INDEX(Monthly!$C$72:$AL$72,($R$2-1)*12+5) -> -1785.7143 | M28: =INDEX(Monthly!$C$72:$AL$72,($R$2-1)*12+6) -> -1785.7143 | N28: =INDEX(Monthly!$C$72:$AL$72,($R$2-1)*12+7) -> -1785.7143 | O28: =INDEX(Monthly!$C$72:$AL$72,($R$2-1)*12+8) -> -1785.7143 | P28: =INDEX(Monthly!$C$72:$AL$72,($R$2-1)*12+9) -> -1785.7143 | Q28: =INDEX(Monthly!$C$72:$AL$72,($R$2-1)*12+10) -> -1785.7143 | R28: =INDEX(Monthly!$C$72:$AL$72,($R$2-1)*12+11) -> -1785.7143 | S28: =INDEX(Monthly!$C$72:$AL$72,($R$2-1)*12+12) -> -1785.7143
A29: Financing cash flow | B29: ='Cash Flow'!B15 -> 230357.14 | C29: ='Cash Flow'!C15 -> -21428.571 | D29: ='Cash Flow'!D15 -> -21428.571 | H29: =INDEX(Monthly!$C$87:$AL$87,($R$2-1)*12+1) -> 250000 | I29: =INDEX(Monthly!$C$87:$AL$87,($R$2-1)*12+2) -> -1785.7143 | J29: =INDEX(Monthly!$C$87:$AL$87,($R$2-1)*12+3) -> -1785.7143 | K29: =INDEX(Monthly!$C$87:$AL$87,($R$2-1)*12+4) -> -1785.7143 | L29: =INDEX(Monthly!$C$87:$AL$87,($R$2-1)*12+5) -> -1785.7143 | M29: =INDEX(Monthly!$C$87:$AL$87,($R$2-1)*12+6) -> -1785.7143 | N29: =INDEX(Monthly!$C$87:$AL$87,($R$2-1)*12+7) -> -1785.7143 | O29: =INDEX(Monthly!$C$87:$AL$87,($R$2-1)*12+8) -> -1785.7143 | P29: =INDEX(Monthly!$C$87:$AL$87,($R$2-1)*12+9) -> -1785.7143 | Q29: =INDEX(Monthly!$C$87:$AL$87,($R$2-1)*12+10) -> -1785.7143 | R29: =INDEX(Monthly!$C$87:$AL$87,($R$2-1)*12+11) -> -1785.7143 | S29: =INDEX(Monthly!$C$87:$AL$87,($R$2-1)*12+12) -> -1785.7143
A30: Net change in cash | B30: ='Cash Flow'!B16 -> 287788.06 | C30: ='Cash Flow'!C16 -> 228953.06 | D30: ='Cash Flow'!D16 -> 288457.62 | H30: =INDEX(Monthly!$C$88:$AL$88,($R$2-1)*12+1) -> 123032.22 | I30: =INDEX(Monthly!$C$88:$AL$88,($R$2-1)*12+2) -> 12738.07 | J30: =INDEX(Monthly!$C$88:$AL$88,($R$2-1)*12+3) -> 13204.328 | K30: =INDEX(Monthly!$C$88:$AL$88,($R$2-1)*12+4) -> 13664.309 | L30: =INDEX(Monthly!$C$88:$AL$88,($R$2-1)*12+5) -> 14118.103 | M30: =INDEX(Monthly!$C$88:$AL$88,($R$2-1)*12+6) -> 14565.795 | N30: =INDEX(Monthly!$C$88:$AL$88,($R$2-1)*12+7) -> 15007.471 | O30: =INDEX(Monthly!$C$88:$AL$88,($R$2-1)*12+8) -> 15443.215 | P30: =INDEX(Monthly!$C$88:$AL$88,($R$2-1)*12+9) -> 15873.111 | Q30: =INDEX(Monthly!$C$88:$AL$88,($R$2-1)*12+10) -> 16297.24 | R30: =INDEX(Monthly!$C$88:$AL$88,($R$2-1)*12+11) -> 16715.683 | S30: =INDEX(Monthly!$C$88:$AL$88,($R$2-1)*12+12) -> 17128.52
A31: Closing cash | B31: ='Cash Flow'!B18 -> 287788.06 | C31: ='Cash Flow'!C18 -> 516741.13 | D31: ='Cash Flow'!D18 -> 805198.75 | H31: =INDEX(Monthly!$C$90:$AL$90,($R$2-1)*12+1) -> 123032.22 | I31: =INDEX(Monthly!$C$90:$AL$90,($R$2-1)*12+2) -> 135770.29 | J31: =INDEX(Monthly!$C$90:$AL$90,($R$2-1)*12+3) -> 148974.62 | K31: =INDEX(Monthly!$C$90:$AL$90,($R$2-1)*12+4) -> 162638.93 | L31: =INDEX(Monthly!$C$90:$AL$90,($R$2-1)*12+5) -> 176757.03 | M31: =INDEX(Monthly!$C$90:$AL$90,($R$2-1)*12+6) -> 191322.82 | N31: =INDEX(Monthly!$C$90:$AL$90,($R$2-1)*12+7) -> 206330.29 | O31: =INDEX(Monthly!$C$90:$AL$90,($R$2-1)*12+8) -> 221773.51 | P31: =INDEX(Monthly!$C$90:$AL$90,($R$2-1)*12+9) -> 237646.62 | Q31: =INDEX(Monthly!$C$90:$AL$90,($R$2-1)*12+10) -> 253943.86 | R31: =INDEX(Monthly!$C$90:$AL$90,($R$2-1)*12+11) -> 270659.54 | S31: =INDEX(Monthly!$C$90:$AL$90,($R$2-1)*12+12) -> 287788.06
A39: Balance sheet at year end ($'000) | H39: ="Balance sheet at month end ($'000) — Year "&$R$2 -> Balance sheet at month end ($'000) — Year 1
B40: 1 | C40: 2 | D40: 3 | H40: =INDEX(Monthly!$C$4:$AL$4,($R$2-1)*12+1) -> 1 | I40: =INDEX(Monthly!$C$4:$AL$4,($R$2-1)*12+2) -> 2 | J40: =INDEX(Monthly!$C$4:$AL$4,($R$2-1)*12+3) -> 3 | K40: =INDEX(Monthly!$C$4:$AL$4,($R$2-1)*12+4) -> 4 | L40: =INDEX(Monthly!$C$4:$AL$4,($R$2-1)*12+5) -> 5 | M40: =INDEX(Monthly!$C$4:$AL$4,($R$2-1)*12+6) -> 6 | N40: =INDEX(Monthly!$C$4:$AL$4,($R$2-1)*12+7) -> 7 | O40: =INDEX(Monthly!$C$4:$AL$4,($R$2-1)*12+8) -> 8 | P40: =INDEX(Monthly!$C$4:$AL$4,($R$2-1)*12+9) -> 9 | Q40: =INDEX(Monthly!$C$4:$AL$4,($R$2-1)*12+10) -> 10 | R40: =INDEX(Monthly!$C$4:$AL$4,($R$2-1)*12+11) -> 11 | S40: =INDEX(Monthly!$C$4:$AL$4,($R$2-1)*12+12) -> 12
A41: Cash | B41: ='Balance Sheet'!B5 -> 287788.06 | C41: ='Balance Sheet'!C5 -> 516741.13 | D41: ='Balance Sheet'!D5 -> 805198.75 | H41: =INDEX(Monthly!$C$90:$AL$90,($R$2-1)*12+1) -> 123032.22 | I41: =INDEX(Monthly!$C$90:$AL$90,($R$2-1)*12+2) -> 135770.29 | J41: =INDEX(Monthly!$C$90:$AL$90,($R$2-1)*12+3) -> 148974.62 | K41: =INDEX(Monthly!$C$90:$AL$90,($R$2-1)*12+4) -> 162638.93 | L41: =INDEX(Monthly!$C$90:$AL$90,($R$2-1)*12+5) -> 176757.03 | M41: =INDEX(Monthly!$C$90:$AL$90,($R$2-1)*12+6) -> 191322.82 | N41: =INDEX(Monthly!$C$90:$AL$90,($R$2-1)*12+7) -> 206330.29 | O41: =INDEX(Monthly!$C$90:$AL$90,($R$2-1)*12+8) -> 221773.51 | P41: =INDEX(Monthly!$C$90:$AL$90,($R$2-1)*12+9) -> 237646.62 | Q41: =INDEX(Monthly!$C$90:$AL$90,($R$2-1)*12+10) -> 253943.86 | R41: =INDEX(Monthly!$C$90:$AL$90,($R$2-1)*12+11) -> 270659.54 | S41: =INDEX(Monthly!$C$90:$AL$90,($R$2-1)*12+12) -> 287788.06
A42: Accounts receivable | B42: ='Balance Sheet'!B6 -> 95357.627 | C42: ='Balance Sheet'!C6 -> 103729.39 | D42: ='Balance Sheet'!D6 -> 112795.59 | H42: =INDEX(Monthly!$C$76:$AL$76,($R$2-1)*12+1) -> 91098.449 | I42: =INDEX(Monthly!$C$76:$AL$76,($R$2-1)*12+2) -> 91513.515 | J42: =INDEX(Monthly!$C$76:$AL$76,($R$2-1)*12+3) -> 91922.77 | K42: =INDEX(Monthly!$C$76:$AL$76,($R$2-1)*12+4) -> 92326.295 | L42: =INDEX(Monthly!$C$76:$AL$76,($R$2-1)*12+5) -> 92724.171 | M42: =INDEX(Monthly!$C$76:$AL$76,($R$2-1)*12+6) -> 93116.477 | N42: =INDEX(Monthly!$C$76:$AL$76,($R$2-1)*12+7) -> 93503.29 | O42: =INDEX(Monthly!$C$76:$AL$76,($R$2-1)*12+8) -> 93884.688 | P42: =INDEX(Monthly!$C$76:$AL$76,($R$2-1)*12+9) -> 94260.747 | Q42: =INDEX(Monthly!$C$76:$AL$76,($R$2-1)*12+10) -> 94631.541 | R42: =INDEX(Monthly!$C$76:$AL$76,($R$2-1)*12+11) -> 94997.143 | S42: =INDEX(Monthly!$C$76:$AL$76,($R$2-1)*12+12) -> 95357.627
A43: Inventory | B43: ='Balance Sheet'!B7 -> 9353.9901 | C43: ='Balance Sheet'!C7 -> 10174.559 | D43: ='Balance Sheet'!D7 -> 11063.283 | H43: =INDEX(Monthly!$C$77:$AL$77,($R$2-1)*12+1) -> 8950.8167 | I43: =INDEX(Monthly!$C$77:$AL$77,($R$2-1)*12+2) -> 8990.1068 | J43: =INDEX(Monthly!$C$77:$AL$77,($R$2-1)*12+3) -> 9028.8468 | K43: =INDEX(Monthly!$C$77:$AL$77,($R$2-1)*12+4) -> 9067.0445 | L43: =INDEX(Monthly!$C$77:$AL$77,($R$2-1)*12+5) -> 9104.7074 | M43: =INDEX(Monthly!$C$77:$AL$77,($R$2-1)*12+6) -> 9141.843 | N43: =INDEX(Monthly!$C$77:$AL$77,($R$2-1)*12+7) -> 9178.4588 | O43: =INDEX(Monthly!$C$77:$AL$77,($R$2-1)*12+8) -> 9214.5619 | P43: =INDEX(Monthly!$C$77:$AL$77,($R$2-1)*12+9) -> 9250.1595 | Q43: =INDEX(Monthly!$C$77:$AL$77,($R$2-1)*12+10) -> 9285.2588 | R43: =INDEX(Monthly!$C$77:$AL$77,($R$2-1)*12+11) -> 9319.8667 | S43: =INDEX(Monthly!$C$77:$AL$77,($R$2-1)*12+12) -> 9353.9901
A44: Net fixed assets | B44: ='Balance Sheet'!B8 -> 78782.757 | C44: ='Balance Sheet'!C8 -> 95739.823 | D44: ='Balance Sheet'!D8 -> 110697.6 | H44: =INDEX(Monthly!$C$67:$AL$67,($R$2-1)*12+1) -> 61668.436 | I44: =INDEX(Monthly!$C$67:$AL$67,($R$2-1)*12+2) -> 63319.021 | J44: =INDEX(Monthly!$C$67:$AL$67,($R$2-1)*12+3) -> 64951.472 | K44: =INDEX(Monthly!$C$67:$AL$67,($R$2-1)*12+4) -> 66565.511 | L44: =INDEX(Monthly!$C$67:$AL$67,($R$2-1)*12+5) -> 68160.861 | M44: =INDEX(Monthly!$C$67:$AL$67,($R$2-1)*12+6) -> 69737.252 | N44: =INDEX(Monthly!$C$67:$AL$67,($R$2-1)*12+7) -> 71294.418 | O44: =INDEX(Monthly!$C$67:$AL$67,($R$2-1)*12+8) -> 72832.093 | P44: =INDEX(Monthly!$C$67:$AL$67,($R$2-1)*12+9) -> 74350.02 | Q44: =INDEX(Monthly!$C$67:$AL$67,($R$2-1)*12+10) -> 75847.94 | R44: =INDEX(Monthly!$C$67:$AL$67,($R$2-1)*12+11) -> 77325.602 | S44: =INDEX(Monthly!$C$67:$AL$67,($R$2-1)*12+12) -> 78782.757
A45: Total assets | B45: ='Balance Sheet'!B9 -> 471282.44 | C45: ='Balance Sheet'!C9 -> 726384.9 | D45: ='Balance Sheet'!D9 -> 1039755.2 | H45: =INDEX(Monthly!$C$104:$AL$104,($R$2-1)*12+1) -> 284749.92 | I45: =INDEX(Monthly!$C$104:$AL$104,($R$2-1)*12+2) -> 299592.93 | J45: =INDEX(Monthly!$C$104:$AL$104,($R$2-1)*12+3) -> 314877.71 | K45: =INDEX(Monthly!$C$104:$AL$104,($R$2-1)*12+4) -> 330597.78 | L45: =INDEX(Monthly!$C$104:$AL$104,($R$2-1)*12+5) -> 346746.77 | M45: =INDEX(Monthly!$C$104:$AL$104,($R$2-1)*12+6) -> 363318.39 | N45: =INDEX(Monthly!$C$104:$AL$104,($R$2-1)*12+7) -> 380306.46 | O45: =INDEX(Monthly!$C$104:$AL$104,($R$2-1)*12+8) -> 397704.85 | P45: =INDEX(Monthly!$C$104:$AL$104,($R$2-1)*12+9) -> 415507.55 | Q45: =INDEX(Monthly!$C$104:$AL$104,($R$2-1)*12+10) -> 433708.6 | R45: =INDEX(Monthly!$C$104:$AL$104,($R$2-1)*12+11) -> 452302.16 | S45: =INDEX(Monthly!$C$104:$AL$104,($R$2-1)*12+12) -> 471282.44
A46: Accounts payable | B46: ='Balance Sheet'!B10 -> 19487.479 | C46: ='Balance Sheet'!C10 -> 21196.999 | D46: ='Balance Sheet'!D10 -> 23048.507 | H46: =INDEX(Monthly!$C$78:$AL$78,($R$2-1)*12+1) -> 18647.535 | I46: =INDEX(Monthly!$C$78:$AL$78,($R$2-1)*12+2) -> 18729.389 | J46: =INDEX(Monthly!$C$78:$AL$78,($R$2-1)*12+3) -> 18810.098 | K46: =INDEX(Monthly!$C$78:$AL$78,($R$2-1)*12+4) -> 18889.676 | L46: =INDEX(Monthly!$C$78:$AL$78,($R$2-1)*12+5) -> 18968.14 | M46: =INDEX(Monthly!$C$78:$AL$78,($R$2-1)*12+6) -> 19045.506 | N46: =INDEX(Monthly!$C$78:$AL$78,($R$2-1)*12+7) -> 19121.789 | O46: =INDEX(Monthly!$C$78:$AL$78,($R$2-1)*12+8) -> 19197.004 | P46: =INDEX(Monthly!$C$78:$AL$78,($R$2-1)*12+9) -> 19271.166 | Q46: =INDEX(Monthly!$C$78:$AL$78,($R$2-1)*12+10) -> 19344.289 | R46: =INDEX(Monthly!$C$78:$AL$78,($R$2-1)*12+11) -> 19416.389 | S46: =INDEX(Monthly!$C$78:$AL$78,($R$2-1)*12+12) -> 19487.479
A47: Loan | B47: ='Balance Sheet'!B11 -> 130357.14 | C47: ='Balance Sheet'!C11 -> 108928.57 | D47: ='Balance Sheet'!D11 -> 87500 | H47: =INDEX(Monthly!$C$73:$AL$73,($R$2-1)*12+1) -> 150000 | I47: =INDEX(Monthly!$C$73:$AL$73,($R$2-1)*12+2) -> 148214.29 | J47: =INDEX(Monthly!$C$73:$AL$73,($R$2-1)*12+3) -> 146428.57 | K47: =INDEX(Monthly!$C$73:$AL$73,($R$2-1)*12+4) -> 144642.86 | L47: =INDEX(Monthly!$C$73:$AL$73,($R$2-1)*12+5) -> 142857.14 | M47: =INDEX(Monthly!$C$73:$AL$73,($R$2-1)*12+6) -> 141071.43 | N47: =INDEX(Monthly!$C$73:$AL$73,($R$2-1)*12+7) -> 139285.71 | O47: =INDEX(Monthly!$C$73:$AL$73,($R$2-1)*12+8) -> 137500 | P47: =INDEX(Monthly!$C$73:$AL$73,($R$2-1)*12+9) -> 135714.29 | Q47: =INDEX(Monthly!$C$73:$AL$73,($R$2-1)*12+10) -> 133928.57 | R47: =INDEX(Monthly!$C$73:$AL$73,($R$2-1)*12+11) -> 132142.86 | S47: =INDEX(Monthly!$C$73:$AL$73,($R$2-1)*12+12) -> 130357.14
A48: Total liabilities | B48: ='Balance Sheet'!B12 -> 149844.62 | C48: ='Balance Sheet'!C12 -> 130125.57 | D48: ='Balance Sheet'!D12 -> 110548.51 | H48: =INDEX(Monthly!$C$105:$AL$105,($R$2-1)*12+1) -> 168647.53 | I48: =INDEX(Monthly!$C$105:$AL$105,($R$2-1)*12+2) -> 166943.67 | J48: =INDEX(Monthly!$C$105:$AL$105,($R$2-1)*12+3) -> 165238.67 | K48: =INDEX(Monthly!$C$105:$AL$105,($R$2-1)*12+4) -> 163532.53 | L48: =INDEX(Monthly!$C$105:$AL$105,($R$2-1)*12+5) -> 161825.28 | M48: =INDEX(Monthly!$C$105:$AL$105,($R$2-1)*12+6) -> 160116.93 | N48: =INDEX(Monthly!$C$105:$AL$105,($R$2-1)*12+7) -> 158407.5 | O48: =INDEX(Monthly!$C$105:$AL$105,($R$2-1)*12+8) -> 156697 | P48: =INDEX(Monthly!$C$105:$AL$105,($R$2-1)*12+9) -> 154985.45 | Q48: =INDEX(Monthly!$C$105:$AL$105,($R$2-1)*12+10) -> 153272.86 | R48: =INDEX(Monthly!$C$105:$AL$105,($R$2-1)*12+11) -> 151559.25 | S48: =INDEX(Monthly!$C$105:$AL$105,($R$2-1)*12+12) -> 149844.62
A49: Paid-in capital | B49: ='Balance Sheet'!B13 -> 100000 | C49: ='Balance Sheet'!C13 -> 100000 | D49: ='Balance Sheet'!D13 -> 100000 | H49: =INDEX(Monthly!$C$102:$AL$102,($R$2-1)*12+1) -> 100000 | I49: =INDEX(Monthly!$C$102:$AL$102,($R$2-1)*12+2) -> 100000 | J49: =INDEX(Monthly!$C$102:$AL$102,($R$2-1)*12+3) -> 100000 | K49: =INDEX(Monthly!$C$102:$AL$102,($R$2-1)*12+4) -> 100000 | L49: =INDEX(Monthly!$C$102:$AL$102,($R$2-1)*12+5) -> 100000 | M49: =INDEX(Monthly!$C$102:$AL$102,($R$2-1)*12+6) -> 100000 | N49: =INDEX(Monthly!$C$102:$AL$102,($R$2-1)*12+7) -> 100000 | O49: =INDEX(Monthly!$C$102:$AL$102,($R$2-1)*12+8) -> 100000 | P49: =INDEX(Monthly!$C$102:$AL$102,($R$2-1)*12+9) -> 100000 | Q49: =INDEX(Monthly!$C$102:$AL$102,($R$2-1)*12+10) -> 100000 | R49: =INDEX(Monthly!$C$102:$AL$102,($R$2-1)*12+11) -> 100000 | S49: =INDEX(Monthly!$C$102:$AL$102,($R$2-1)*12+12) -> 100000
A50: Retained earnings | B50: ='Balance Sheet'!B14 -> 221437.82 | C50: ='Balance Sheet'!C14 -> 496259.33 | D50: ='Balance Sheet'!D14 -> 829206.72 | H50: =INDEX(Monthly!$C$103:$AL$103,($R$2-1)*12+1) -> 16102.386 | I50: =INDEX(Monthly!$C$103:$AL$103,($R$2-1)*12+2) -> 32649.257 | J50: =INDEX(Monthly!$C$103:$AL$103,($R$2-1)*12+3) -> 49639.036 | K50: =INDEX(Monthly!$C$103:$AL$103,($R$2-1)*12+4) -> 67065.242 | L50: =INDEX(Monthly!$C$103:$AL$103,($R$2-1)*12+5) -> 84921.484 | M50: =INDEX(Monthly!$C$103:$AL$103,($R$2-1)*12+6) -> 103201.46 | N50: =INDEX(Monthly!$C$103:$AL$103,($R$2-1)*12+7) -> 121898.96 | O50: =INDEX(Monthly!$C$103:$AL$103,($R$2-1)*12+8) -> 141007.85 | P50: =INDEX(Monthly!$C$103:$AL$103,($R$2-1)*12+9) -> 160522.1 | Q50: =INDEX(Monthly!$C$103:$AL$103,($R$2-1)*12+10) -> 180435.74 | R50: =INDEX(Monthly!$C$103:$AL$103,($R$2-1)*12+11) -> 200742.91 | S50: =INDEX(Monthly!$C$103:$AL$103,($R$2-1)*12+12) -> 221437.82
A51: Total equity | B51: ='Balance Sheet'!B15 -> 321437.82 | C51: ='Balance Sheet'!C15 -> 596259.33 | D51: ='Balance Sheet'!D15 -> 929206.72 | H51: =INDEX(Monthly!$C$106:$AL$106,($R$2-1)*12+1) -> 116102.39 | I51: =INDEX(Monthly!$C$106:$AL$106,($R$2-1)*12+2) -> 132649.26 | J51: =INDEX(Monthly!$C$106:$AL$106,($R$2-1)*12+3) -> 149639.04 | K51: =INDEX(Monthly!$C$106:$AL$106,($R$2-1)*12+4) -> 167065.24 | L51: =INDEX(Monthly!$C$106:$AL$106,($R$2-1)*12+5) -> 184921.48 | M51: =INDEX(Monthly!$C$106:$AL$106,($R$2-1)*12+6) -> 203201.46 | N51: =INDEX(Monthly!$C$106:$AL$106,($R$2-1)*12+7) -> 221898.96 | O51: =INDEX(Monthly!$C$106:$AL$106,($R$2-1)*12+8) -> 241007.85 | P51: =INDEX(Monthly!$C$106:$AL$106,($R$2-1)*12+9) -> 260522.1 | Q51: =INDEX(Monthly!$C$106:$AL$106,($R$2-1)*12+10) -> 280435.74 | R51: =INDEX(Monthly!$C$106:$AL$106,($R$2-1)*12+11) -> 300742.91 | S51: =INDEX(Monthly!$C$106:$AL$106,($R$2-1)*12+12) -> 321437.82
A52: Total liabilities & equity | B52: ='Balance Sheet'!B16 -> 471282.44 | C52: ='Balance Sheet'!C16 -> 726384.9 | D52: ='Balance Sheet'!D16 -> 1039755.2 | H52: =INDEX(Monthly!$C$107:$AL$107,($R$2-1)*12+1) -> 284749.92 | I52: =INDEX(Monthly!$C$107:$AL$107,($R$2-1)*12+2) -> 299592.93 | J52: =INDEX(Monthly!$C$107:$AL$107,($R$2-1)*12+3) -> 314877.71 | K52: =INDEX(Monthly!$C$107:$AL$107,($R$2-1)*12+4) -> 330597.78 | L52: =INDEX(Monthly!$C$107:$AL$107,($R$2-1)*12+5) -> 346746.77 | M52: =INDEX(Monthly!$C$107:$AL$107,($R$2-1)*12+6) -> 363318.39 | N52: =INDEX(Monthly!$C$107:$AL$107,($R$2-1)*12+7) -> 380306.46 | O52: =INDEX(Monthly!$C$107:$AL$107,($R$2-1)*12+8) -> 397704.85 | P52: =INDEX(Monthly!$C$107:$AL$107,($R$2-1)*12+9) -> 415507.55 | Q52: =INDEX(Monthly!$C$107:$AL$107,($R$2-1)*12+10) -> 433708.6 | R52: =INDEX(Monthly!$C$107:$AL$107,($R$2-1)*12+11) -> 452302.16 | S52: =INDEX(Monthly!$C$107:$AL$107,($R$2-1)*12+12) -> 471282.44

Sheet Scenarios
A1: Scenarios — Low / Base / High | H1: =HYPERLINK("#'Cover'!A1","◂ Contents") -> ◂ Contents
A2: All three scenarios calculated side by side, live: change any input and every column updates. Active = the scenario chosen on the Dashboard.
A5: Key drivers
A6: Driver | B6: Low | C6: Base | D6: High | E6: Active
A7: Active patients at start (#) | B7: =Inputs!$B$14 -> 2700 | C7: =Inputs!$C$14 -> 3000 | D7: =Inputs!$D$14 -> 3300 | E7: =Inputs!$E$14 -> 3000
A8: Doctor operatories (restorative chairs) (#) | B8: =Inputs!$B$7 -> 6 | C8: =Inputs!$C$7 -> 6 | D8: =Inputs!$D$7 -> 6 | E8: =Inputs!$E$7 -> 6
A9: Production per doctor visit, office fees (year 1) ($) | B9: =Inputs!$B$26 -> 320 | C9: =Inputs!$C$26 -> 330 | D9: =Inputs!$D$26 -> 340 | E9: =Inputs!$E$26 -> 330
A10: Hygiene recall visits per active patient per year (visits) | B10: =Inputs!$B$22 -> 1.4 | C10: =Inputs!$C$22 -> 1.5 | D10: =Inputs!$D$22 -> 1.6 | E10: =Inputs!$E$22 -> 1.5
A11: Marketing cost per new patient ($) | B11: =Inputs!$B$19 -> 230 | C11: =Inputs!$C$19 -> 210 | D11: =Inputs!$D$19 -> 190 | E11: =Inputs!$E$19 -> 210
A12: Rent per sq ft per year (incl. CAM) ($) | B12: =Inputs!$B$49 -> 32 | C12: =Inputs!$C$49 -> 30 | D12: =Inputs!$D$49 -> 28 | E12: =Inputs!$E$49 -> 30
A13: Equity raised at start ($) | B13: =Inputs!$B$83 -> 100000 | C13: =Inputs!$C$83 -> 100000 | D13: =Inputs!$D$83 -> 100000 | E13: =Inputs!$E$83 -> 100000
A15: Results by scenario ($'000)
A16: Output | B16: Low | C16: Base | D16: High | E16: Active
A17: Revenue — final year | B17: =D30 -> 1710590.8 | C17: =D31 -> 2337329.1 | D17: =D32 -> 2956070.4 | E17: ='P&L'!D5 -> 2337329.1
A18: Revenue — whole plan | B18: =SUM(B30:D30) -> 4915431.1 | C18: =SUM(B31:D31) -> 6461762.6 | D18: =SUM(B32:D32) -> 8140720.3 | E18: =SUM('P&L'!$B$5:$D$5) -> 6461762.6
A19: EBITDA — final year | B19: =D36 -> -88156.988 | C19: =D37 -> 449902.76 | D19: =D38 -> 1003994.9 | E19: ='P&L'!D19 -> 449902.76
A20: EBITDA margin — final year | B20: =IF(B17=0,0,B19/B17) -> -0.051535988 | C20: =IF(C17=0,0,C19/C17) -> 0.19248584 | D20: =IF(D17=0,0,D19/D17) -> 0.33963835 | E20: =IF(E17=0,0,E19/E17) -> 0.19248584
A21: Net income — final year | B21: =D42 -> -113923.38 | C21: =D43 -> 332947.38 | D21: =D44 -> 768301.97 | E21: ='P&L'!D26 -> 332947.38
A22: Net income — whole plan | B22: =SUM(B42:D42) -> -304541.71 | C22: =SUM(B43:D43) -> 829206.72 | D22: =SUM(B44:D44) -> 2019017.3 | E22: =SUM('P&L'!$B$26:$D$26) -> 829206.72
A23: Cash at the end of the plan | B23: =D48 -> -304710.09 | C23: =D49 -> 805198.75 | D23: =D50 -> 1973944.5 | E23: ='Balance Sheet'!D5 -> 805198.75
A24: Lowest cash balance | B24: =MIN('Scenario calc'!$C$92:$AL$92) -> -304710.09 | C24: =MIN('Scenario calc'!$C$217:$AL$217) -> 123032.22 | D24: =MIN('Scenario calc'!$C$342:$AL$342) -> 149009.98 | E24: ='Break-even'!B18 -> 123032.22
A25: Lowest cash point (month #) | B25: =MATCH(MIN('Scenario calc'!$C$92:$AL$92),'Scenario calc'!$C$92:$AL$92,0) -> 36 | C25: =MATCH(MIN('Scenario calc'!$C$217:$AL$217),'Scenario calc'!$C$217:$AL$217,0) -> 1 | D25: =MATCH(MIN('Scenario calc'!$C$342:$AL$342),'Scenario calc'!$C$342:$AL$342,0) -> 1 | E25: ='Break-even'!B6 -> 1
A26: Funding required (incl. cash buffer) | B26: =SUMPRODUCT(--('Scenario calc'!$C$6:$AL$6<=B25),'Scenario calc'!$C$65:$AL$65)-SUMPRODUCT(--('Scenario calc'!$C$6:$AL$6<=B25),'Scenario calc'!$C$86:$AL$86)-SUMPRODUCT(--('Scenario calc'!$C$6:$AL$6<=B25),'Scenario calc'!$C$74:$AL$74)+Inputs!$B$98 -> 903710.09 | C26: =SUMPRODUCT(--('Scenario calc'!$C$131:$AL$131<=C25),'Scenario calc'!$C$190:$AL$190)-SUMPRODUCT(--('Scenario calc'!$C$131:$AL$131<=C25),'Scenario calc'!$C$211:$AL$211)-SUMPRODUCT(--('Scenario calc'!$C$131:$AL$131<=C25),'Scenario calc'!$C$199:$AL$199)+Inputs!$C$98 -> 475967.78 | D26: =SUMPRODUCT(--('Scenario calc'!$C$256:$AL$256<=D25),'Scenario calc'!$C$315:$AL$315)-SUMPRODUCT(--('Scenario calc'!$C$256:$AL$256<=D25),'Scenario calc'!$C$336:$AL$336)-SUMPRODUCT(--('Scenario calc'!$C$256:$AL$256<=D25),'Scenario calc'!$C$324:$AL$324)+Inputs!$D$98 -> 449990.02 | E26: ='Break-even'!B12 -> 475967.78
A28: Revenue by year ($'000)
A29: Scenario | B29: 1 | C29: 2 | D29: 3
A30: Low | B30: =SUMIF('Scenario calc'!$C$7:$AL$7,B$29,'Scenario calc'!$C$33:$AL$33) -> 1565966.3 | C30: =SUMIF('Scenario calc'!$C$7:$AL$7,C$29,'Scenario calc'!$C$33:$AL$33) -> 1638874 | D30: =SUMIF('Scenario calc'!$C$7:$AL$7,D$29,'Scenario calc'!$C$33:$AL$33) -> 1710590.8
A31: Base | B31: =SUMIF('Scenario calc'!$C$132:$AL$132,B$29,'Scenario calc'!$C$158:$AL$158) -> 1975300.1 | C31: =SUMIF('Scenario calc'!$C$132:$AL$132,C$29,'Scenario calc'!$C$158:$AL$158) -> 2149133.3 | D31: =SUMIF('Scenario calc'!$C$132:$AL$132,D$29,'Scenario calc'!$C$158:$AL$158) -> 2337329.1
A32: High | B32: =SUMIF('Scenario calc'!$C$257:$AL$257,B$29,'Scenario calc'!$C$283:$AL$283) -> 2442863.9 | C32: =SUMIF('Scenario calc'!$C$257:$AL$257,C$29,'Scenario calc'!$C$283:$AL$283) -> 2741786 | D32: =SUMIF('Scenario calc'!$C$257:$AL$257,D$29,'Scenario calc'!$C$283:$AL$283) -> 2956070.4
A34: EBITDA by year ($'000)
A35: Scenario | B35: 1 | C35: 2 | D35: 3
A36: Low | B36: =SUMIF('Scenario calc'!$C$7:$AL$7,B$35,'Scenario calc'!$C$53:$AL$53) -> -68678.961 | C36: =SUMIF('Scenario calc'!$C$7:$AL$7,C$35,'Scenario calc'!$C$53:$AL$53) -> -75580.509 | D36: =SUMIF('Scenario calc'!$C$7:$AL$7,D$35,'Scenario calc'!$C$53:$AL$53) -> -88156.988
A37: Base | B37: =SUMIF('Scenario calc'!$C$132:$AL$132,B$35,'Scenario calc'!$C$178:$AL$178) -> 303132.53 | C37: =SUMIF('Scenario calc'!$C$132:$AL$132,C$35,'Scenario calc'!$C$178:$AL$178) -> 373324.91 | D37: =SUMIF('Scenario calc'!$C$132:$AL$132,D$35,'Scenario calc'!$C$178:$AL$178) -> 449902.76
A38: High | B38: =SUMIF('Scenario calc'!$C$257:$AL$257,B$35,'Scenario calc'!$C$303:$AL$303) -> 732453.68 | C38: =SUMIF('Scenario calc'!$C$257:$AL$257,C$35,'Scenario calc'!$C$303:$AL$303) -> 901235.53 | D38: =SUMIF('Scenario calc'!$C$257:$AL$257,D$35,'Scenario calc'!$C$303:$AL$303) -> 1003994.9
A40: Net income by year ($'000)
A41: Scenario | B41: 1 | C41: 2 | D41: 3
A42: Low | B42: =SUMIF('Scenario calc'!$C$7:$AL$7,B$41,'Scenario calc'!$C$62:$AL$62) -> -91045.538 | C42: =SUMIF('Scenario calc'!$C$7:$AL$7,C$41,'Scenario calc'!$C$62:$AL$62) -> -99572.791 | D42: =SUMIF('Scenario calc'!$C$7:$AL$7,D$41,'Scenario calc'!$C$62:$AL$62) -> -113923.38
A43: Base | B43: =SUMIF('Scenario calc'!$C$132:$AL$132,B$41,'Scenario calc'!$C$187:$AL$187) -> 221437.82 | C43: =SUMIF('Scenario calc'!$C$132:$AL$132,C$41,'Scenario calc'!$C$187:$AL$187) -> 274821.52 | D43: =SUMIF('Scenario calc'!$C$132:$AL$132,D$41,'Scenario calc'!$C$187:$AL$187) -> 332947.38
A44: High | B44: =SUMIF('Scenario calc'!$C$257:$AL$257,B$41,'Scenario calc'!$C$312:$AL$312) -> 560178.81 | C44: =SUMIF('Scenario calc'!$C$257:$AL$257,C$41,'Scenario calc'!$C$312:$AL$312) -> 690536.5 | D44: =SUMIF('Scenario calc'!$C$257:$AL$257,D$41,'Scenario calc'!$C$312:$AL$312) -> 768301.97
A46: Cash at year end by year ($'000)
A47: Scenario | B47: 1 | C47: 2 | D47: 3
A48: Low | B48: =INDEX('Scenario calc'!$C$92:$AL$92,B$47*12) -> -21477.561 | C48: =INDEX('Scenario calc'!$C$92:$AL$92,C$47*12) -> -157203.51 | D48: =INDEX('Scenario calc'!$C$92:$AL$92,D$47*12) -> -304710.09
A49: Base | B49: =INDEX('Scenario calc'!$C$217:$AL$217,B$47*12) -> 287788.06 | C49: =INDEX('Scenario calc'!$C$217:$AL$217,C$47*12) -> 516741.13 | D49: =INDEX('Scenario calc'!$C$217:$AL$217,D$47*12) -> 805198.75
A50: High | B50: =INDEX('Scenario calc'!$C$342:$AL$342,B$47*12) -> 619234.04 | C50: =INDEX('Scenario calc'!$C$342:$AL$342,C$47*12) -> 1254616.9 | D50: =INDEX('Scenario calc'!$C$342:$AL$342,D$47*12) -> 1973944.5

Sheet Break-even
A1: Startup costs, funding need and break-even | F1: =HYPERLINK("#'Cover'!A1","◂ Contents") -> ◂ Contents
A2: Live for the selected scenario. Periods are counted in months from the start of the plan.
A3: Scenario shown | B3: =CHOOSE(Dashboard!$B$4,"Low","Base","High") -> Base
A5: Startup costs & funding need (up to the lowest cash point)
A6: Lowest cash point (month #) | B6: =MATCH(MIN(Monthly!$C$90:$AL$90),Monthly!$C$90:$AL$90,0) -> 1
A7: Capital spending up to the lowest cash point | B7: =SUMPRODUCT(--(Monthly!$C$4:$AL$4<=$B$6),Monthly!$C$63:$AL$63) -> 62411.43
A8: Operating cash burn up to the lowest cash point | B8: =-SUMPRODUCT(--(Monthly!$C$4:$AL$4<=$B$6),Monthly!$C$84:$AL$84) -> 64556.352 | D8: Losses and working capital before the business funds itself
A9: Loan repayments up to the lowest cash point | B9: =-SUMPRODUCT(--(Monthly!$C$4:$AL$4<=$B$6),Monthly!$C$72:$AL$72) -> 0
A10: Total uses of funds | B10: =B7+B8+B9 -> 126967.78
A11: Minimum cash buffer to keep | B11: =Inputs!$E$98 -> 349000 | D11: Input on the Inputs sheet
A12: Funding required (uses + buffer) | B12: =B10+B11 -> 475967.78
A14: Equity raised | B14: =Inputs!$E$83 -> 100000
A15: Loan drawn | B15: =Inputs!$E$84 -> 150000
A16: Total sources of funds | B16: =B14+B15 -> 250000
A17: Funding surplus / (shortfall) | B17: =B16-B12 -> -225967.78 | D17: Negative = raise at least this much more
A18: Lowest cash balance in the plan | B18: =MIN(Monthly!$C$90:$AL$90) -> 123032.22 | D18: Equals sources minus uses
A20: Break-even timing
A21: First month with positive EBITDA (month #) | B21: =IFERROR(MATCH(1,Monthly!$C$91:$AL$91,0),"Not within horizon") -> 1
A22: First month with positive net income (month #) | B22: =IFERROR(MATCH(1,Monthly!$C$94:$AL$94,0),"Not within horizon") -> 1
A23: Cash invested paid back (month #) | B23: =IF(MIN(Monthly!$C$96:$AL$96)>=0,"No investment to pay back",IFERROR(MATCH(1,Monthly!$C$98:$AL$98,0),"Not within horizon")) -> 9 | D23: Cumulative operating + investing cash flow back to zero
A25: Annual break-even revenue
A26: Year # | B26: 1 | C26: 2 | D26: 3
B27: Year 1 | C27: Year 2 | D27: Year 3
A28: Revenue | B28: =SUMIF(Monthly!$C$5:$AL$5,B$26,Monthly!$C$31:$AL$31) -> 1975300.1 | C28: =SUMIF(Monthly!$C$5:$AL$5,C$26,Monthly!$C$31:$AL$31) -> 2149133.3 | D28: =SUMIF(Monthly!$C$5:$AL$5,D$26,Monthly!$C$31:$AL$31) -> 2337329.1
A29: Gross profit | B29: =SUMIF(Monthly!$C$5:$AL$5,B$26,Monthly!$C$38:$AL$38) -> 1700585.9 | C29: =SUMIF(Monthly!$C$5:$AL$5,C$26,Monthly!$C$38:$AL$38) -> 1850264.9 | D29: =SUMIF(Monthly!$C$5:$AL$5,D$26,Monthly!$C$38:$AL$38) -> 2012307.8
A30: Gross margin (contribution) | B30: =IF(B28=0,0,B29/B28) -> 0.86092536 | C30: =IF(C28=0,0,C29/C28) -> 0.86093538 | D30: =IF(D28=0,0,D29/D28) -> 0.86094328
A31: Operating expenses (treated as fixed) | B31: =-SUMIF(Monthly!$C$5:$AL$5,B$26,Monthly!$C$50:$AL$50) -> 1397453.4 | C31: =-SUMIF(Monthly!$C$5:$AL$5,C$26,Monthly!$C$50:$AL$50) -> 1476940 | D31: =-SUMIF(Monthly!$C$5:$AL$5,D$26,Monthly!$C$50:$AL$50) -> 1562405.1
A32: Break-even revenue (EBITDA = 0) | B32: =IF(B30>0,B31/B30,"n/a") -> 1623199.3 | C32: =IF(C30>0,C31/C30,"n/a") -> 1715506.2 | D32: =IF(D30>0,D31/D30,"n/a") -> 1814759.6
A33: Margin of safety (revenue above break-even) | B33: =IF(AND(ISNUMBER(B32),B28>0),(B28-B32)/B28,"n/a") -> 0.17825181 | C33: =IF(AND(ISNUMBER(C32),C28>0),(C28-C32)/C28,"n/a") -> 0.20176836 | D33: =IF(AND(ISNUMBER(D32),D28>0),(D28-D32)/D28,"n/a") -> 0.22357551
A35: Simplification: cost of sales is treated as variable and operating expenses as fixed, so break-even revenue = operating expenses ÷ gross margin.

Sheet Valuation
A1: Discounted cash flow valuation | H1: =HYPERLINK("#'Cover'!A1","◂ Contents") -> ◂ Contents
A2: Enterprise value at the start of the plan, before the funding raised in period 1. Year-end discounting.
A3: Scenario shown | B3: =CHOOSE(Dashboard!$B$4,"Low","Base","High") -> Base
A5: Assumptions (active scenario, from the Inputs sheet)
A6: Discount rate (WACC) | B6: =Inputs!$E$101 -> 0.16
A7: Terminal growth rate | B7: =Inputs!$E$102 -> 0.02
A8: Exit multiple (EV ÷ final-year EBITDA) | B8: =Inputs!$E$103 -> 5.5
A9: Tax rate (for the interest tax shield) | B9: =Inputs!$E$95 -> 0.21
A10: Sensitivity step: WACC | B10: =Inputs!$E$104 -> 0.01
A11: Sensitivity step: terminal growth | B11: =Inputs!$E$105 -> 0.005
A13: Free cash flow by year
A14: Year # | B14: 1 | C14: 2 | D14: 3
B15: Year 1 | C15: Year 2 | D15: Year 3
A16: EBITDA | B16: =SUMIF(Monthly!$C$5:$AL$5,B$14,Monthly!$C$51:$AL$51) -> 303132.53 | C16: =SUMIF(Monthly!$C$5:$AL$5,C$14,Monthly!$C$51:$AL$51) -> 373324.91 | D16: =SUMIF(Monthly!$C$5:$AL$5,D$14,Monthly!$C$51:$AL$51) -> 449902.76
A17: Unlevered free cash flow | B17: =SUMIF(Monthly!$C$5:$AL$5,B$14,Monthly!$C$99:$AL$99) -> 66898.872 | C17: =SUMIF(Monthly!$C$5:$AL$5,C$14,Monthly!$C$99:$AL$99) -> 258415.65 | D17: =SUMIF(Monthly!$C$5:$AL$5,D$14,Monthly!$C$99:$AL$99) -> 316481.28
A18: Discount factor | B18: =1/(1+Inputs!$E$101)^B$14 -> 0.86206897 | C18: =1/(1+Inputs!$E$101)^C$14 -> 0.7431629 | D18: =1/(1+Inputs!$E$101)^D$14 -> 0.64065767
A19: Present value of free cash flow | B19: =B17*B18 -> 57671.441 | C19: =C17*C18 -> 192044.93 | D19: =D17*D18 -> 202756.16
A21: Enterprise value
B22: Perpetual growth | C22: Exit multiple
A23: Present value of the plan's free cash flows | B23: =SUM($B$19:$D$19) -> 452472.53 | C23: =B23 -> 452472.53
A24: Final-year free cash flow | final-year EBITDA | B24: =$D$17 -> 316481.28 | C24: =$D$16 -> 449902.76
A25: Terminal value at the end of year 3 | B25: =IF($B$6>$B$7,B24*(1+$B$7)/($B$6-$B$7),0) -> 2305792.2 | C25: =C24*$B$8 -> 2474465.2
A26: Present value of the terminal value | B26: =B25/(1+$B$6)^$D$14 -> 1477223.5 | C26: =C25/(1+$B$6)^$D$14 -> 1585285.1
A27: Enterprise value | B27: =B23+B26 -> 1929696 | C27: =C23+C26 -> 2037757.6
A28: Terminal value share of enterprise value | B28: =IF(B27<>0,B26/B27,0) -> 0.76552134 | C28: =IF(C27<>0,C26/C27,0) -> 0.77795567
A29: Cross-check: implied exit multiple | implied perpetual growth | B29: =IF(C24>0,B25/C24,"n/a") -> 5.1250901 | C29: =IF(C25+B24<>0,(C25*$B$6-B24)/(C25+B24),"n/a") -> 0.028461007
A30: Enterprise value — average of the two methods | B30: =AVERAGE(B27,C27) -> 1983726.8
A32: Sensitivity: enterprise value (perpetual growth) by WACC and terminal growth
A33: WACC ↓ · terminal growth → | B33: =$B$7+(-2)*$B$11 -> 0.01 | C33: =$B$7+(-1)*$B$11 -> 0.015 | D33: =$B$7+(0)*$B$11 -> 0.02 | E33: =$B$7+(1)*$B$11 -> 0.025 | F33: =$B$7+(2)*$B$11 -> 0.03
A34: =$B$6+(-2)*$B$10 -> 0.14 | B34: =IF($A34>B$33,SUMPRODUCT($B$17:$D$17/(1+$A34)^$B$14:$D$14)+$D$17*(1+B$33)/($A34-B$33)/(1+$A34)^$D$14,"n/a") -> 2130772.4 | C34: =IF($A34>C$33,SUMPRODUCT($B$17:$D$17/(1+$A34)^$B$14:$D$14)+$D$17*(1+C$33)/($A34-C$33)/(1+$A34)^$D$14,"n/a") -> 2205702.2 | D34: =IF($A34>D$33,SUMPRODUCT($B$17:$D$17/(1+$A34)^$B$14:$D$14)+$D$17*(1+D$33)/($A34-D$33)/(1+$A34)^$D$14,"n/a") -> 2286876.2 | E34: =IF($A34>E$33,SUMPRODUCT($B$17:$D$17/(1+$A34)^$B$14:$D$14)+$D$17*(1+E$33)/($A34-E$33)/(1+$A34)^$D$14,"n/a") -> 2375108.9 | F34: =IF($A34>F$33,SUMPRODUCT($B$17:$D$17/(1+$A34)^$B$14:$D$14)+$D$17*(1+F$33)/($A34-F$33)/(1+$A34)^$D$14,"n/a") -> 2471362.7
A35: =$B$6+(-1)*$B$10 -> 0.15 | B35: =IF($A35>B$33,SUMPRODUCT($B$17:$D$17/(1+$A35)^$B$14:$D$14)+$D$17*(1+B$33)/($A35-B$33)/(1+$A35)^$D$14,"n/a") -> 1962896 | C35: =IF($A35>C$33,SUMPRODUCT($B$17:$D$17/(1+$A35)^$B$14:$D$14)+$D$17*(1+C$33)/($A35-C$33)/(1+$A35)^$D$14,"n/a") -> 2026204.3 | D35: =IF($A35>D$33,SUMPRODUCT($B$17:$D$17/(1+$A35)^$B$14:$D$14)+$D$17*(1+D$33)/($A35-D$33)/(1+$A35)^$D$14,"n/a") -> 2094382.4 | E35: =IF($A35>E$33,SUMPRODUCT($B$17:$D$17/(1+$A35)^$B$14:$D$14)+$D$17*(1+E$33)/($A35-E$33)/(1+$A35)^$D$14,"n/a") -> 2168014.8 | F35: =IF($A35>F$33,SUMPRODUCT($B$17:$D$17/(1+$A35)^$B$14:$D$14)+$D$17*(1+F$33)/($A35-F$33)/(1+$A35)^$D$14,"n/a") -> 2247783.3
A36: =$B$6+(0)*$B$10 -> 0.16 | B36: =IF($A36>B$33,SUMPRODUCT($B$17:$D$17/(1+$A36)^$B$14:$D$14)+$D$17*(1+B$33)/($A36-B$33)/(1+$A36)^$D$14,"n/a") -> 1817697.3 | C36: =IF($A36>C$33,SUMPRODUCT($B$17:$D$17/(1+$A36)^$B$14:$D$14)+$D$17*(1+C$33)/($A36-C$33)/(1+$A36)^$D$14,"n/a") -> 1871765.7 | D36: =IF($A36>D$33,SUMPRODUCT($B$17:$D$17/(1+$A36)^$B$14:$D$14)+$D$17*(1+D$33)/($A36-D$33)/(1+$A36)^$D$14,"n/a") -> 1929696 | E36: =IF($A36>E$33,SUMPRODUCT($B$17:$D$17/(1+$A36)^$B$14:$D$14)+$D$17*(1+E$33)/($A36-E$33)/(1+$A36)^$D$14,"n/a") -> 1991917.4 | F36: =IF($A36>F$33,SUMPRODUCT($B$17:$D$17/(1+$A36)^$B$14:$D$14)+$D$17*(1+F$33)/($A36-F$33)/(1+$A36)^$D$14,"n/a") -> 2058925.2
A37: =$B$6+(1)*$B$10 -> 0.17 | B37: =IF($A37>B$33,SUMPRODUCT($B$17:$D$17/(1+$A37)^$B$14:$D$14)+$D$17*(1+B$33)/($A37-B$33)/(1+$A37)^$D$14,"n/a") -> 1690916.3 | C37: =IF($A37>C$33,SUMPRODUCT($B$17:$D$17/(1+$A37)^$B$14:$D$14)+$D$17*(1+C$33)/($A37-C$33)/(1+$A37)^$D$14,"n/a") -> 1737528 | D37: =IF($A37>D$33,SUMPRODUCT($B$17:$D$17/(1+$A37)^$B$14:$D$14)+$D$17*(1+D$33)/($A37-D$33)/(1+$A37)^$D$14,"n/a") -> 1787247.1 | E37: =IF($A37>E$33,SUMPRODUCT($B$17:$D$17/(1+$A37)^$B$14:$D$14)+$D$17*(1+E$33)/($A37-E$33)/(1+$A37)^$D$14,"n/a") -> 1840395.1 | F37: =IF($A37>F$33,SUMPRODUCT($B$17:$D$17/(1+$A37)^$B$14:$D$14)+$D$17*(1+F$33)/($A37-F$33)/(1+$A37)^$D$14,"n/a") -> 1897339.4
A38: =$B$6+(2)*$B$10 -> 0.18 | B38: =IF($A38>B$33,SUMPRODUCT($B$17:$D$17/(1+$A38)^$B$14:$D$14)+$D$17*(1+B$33)/($A38-B$33)/(1+$A38)^$D$14,"n/a") -> 1579295.4 | C38: =IF($A38>C$33,SUMPRODUCT($B$17:$D$17/(1+$A38)^$B$14:$D$14)+$D$17*(1+C$33)/($A38-C$33)/(1+$A38)^$D$14,"n/a") -> 1619810.9 | D38: =IF($A38>D$33,SUMPRODUCT($B$17:$D$17/(1+$A38)^$B$14:$D$14)+$D$17*(1+D$33)/($A38-D$33)/(1+$A38)^$D$14,"n/a") -> 1662858.6 | E38: =IF($A38>E$33,SUMPRODUCT($B$17:$D$17/(1+$A38)^$B$14:$D$14)+$D$17*(1+E$33)/($A38-E$33)/(1+$A38)^$D$14,"n/a") -> 1708683.6 | F38: =IF($A38>F$33,SUMPRODUCT($B$17:$D$17/(1+$A38)^$B$14:$D$14)+$D$17*(1+F$33)/($A38-F$33)/(1+$A38)^$D$14,"n/a") -> 1757563.6
A40: Free cash flow = operating cash flow + interest × (1 − tax rate) − capital spending. Cells marked n/a: WACC not above growth.

Sheet Sources & Uses
A1: Sources and uses of funds | E1: =HYPERLINK("#'Cover'!A1","◂ Contents") -> ◂ Contents
A2: Live for the selected scenario. Where the money comes from and where it goes in the period set below.
A3: Scenario shown | B3: =CHOOSE(Dashboard!$B$4,"Low","Base","High") -> Base
A5: Funding structure ($'000) — raised at the start of the plan
B6: Amount | C6: Share
A7: Equity | B7: =Inputs!$E$83 -> 100000 | C7: =IF($B$9=0,0,B7/$B$9) -> 0.4
A8: Debt (loan) | B8: =Inputs!$E$84 -> 150000 | C8: =IF($B$9=0,0,B8/$B$9) -> 0.6
A9: Total funding | B9: =B7+B8 -> 250000 | C9: =IF(B9=0,0,1) -> 1
A10: Gearing (debt ÷ equity) | B10: =IF(B7<=0,IF(B8>0,"n/a",0),B8/B7) -> 1.5 | D10: n/a: debt without positive equity
A11: Funding required by the plan (Break-even sheet) | B11: ='Break-even'!B12 -> 475967.78
A12: Funding surplus / (shortfall) | B12: ='Break-even'!B17 -> -225967.78
A14: ="Sources and uses of cash in the first "&$B$16&IF($B$16=1," month"," months")&" ($'000)" -> Sources and uses of cash in the first 12 months ($'000)
A15: Period covered (months from the start) | B15: 12 | D15: 1 to 36 (capped)
A16: Months used | B16: =MIN(36,MAX(1,ROUND(B15,0))) -> 12
A17: Sources | B17: Amount | C17: Share
A18: Equity raised | B18: =SUMPRODUCT(--(Monthly!$C$4:$AL$4<=$B$16),Monthly!$C$86:$AL$86) -> 100000 | C18: =IF($B$21=0,0,B18/$B$21) -> 0.25185084
A19: Loan drawdowns | B19: =SUMPRODUCT(--(Monthly!$C$4:$AL$4<=$B$16),Monthly!$C$71:$AL$71) -> 150000 | C19: =IF($B$21=0,0,B19/$B$21) -> 0.37777626
A20: Cash generated by operations | B20: =MAX(0,SUMPRODUCT(--(Monthly!$C$4:$AL$4<=$B$16),Monthly!$C$84:$AL$84)) -> 147060.42 | C20: =IF($B$21=0,0,B20/$B$21) -> 0.37037291
A21: Total sources | B21: =SUM(B18:B20) -> 397060.42 | C21: =IF(B21=0,0,1) -> 1
A23: Uses | B23: Amount | C23: Share
A24: Cash used by operations | B24: =MAX(0,-SUMPRODUCT(--(Monthly!$C$4:$AL$4<=$B$16),Monthly!$C$84:$AL$84)) -> 0 | C24: =IF($B$28=0,0,B24/$B$28) -> 0
A25: Capital spending | B25: =-SUMPRODUCT(--(Monthly!$C$4:$AL$4<=$B$16),Monthly!$C$85:$AL$85) -> 89629.501 | C25: =IF($B$28=0,0,B25/$B$28) -> 0.22573265
A26: Loan repayments | B26: =-SUMPRODUCT(--(Monthly!$C$4:$AL$4<=$B$16),Monthly!$C$72:$AL$72) -> 19642.857 | C26: =IF($B$28=0,0,B26/$B$28) -> 0.0494707
A27: Cash at the end of the period | B27: =INDEX(Monthly!$C$90:$AL$90,$B$16) -> 287788.06 | C27: =IF($B$28=0,0,B27/$B$28) -> 0.72479665
A28: Total uses | B28: =SUM(B24:B27) -> 397060.42 | C28: =IF(B28=0,0,1) -> 1
A29: Sources − uses (must be 0; opening cash is 0) | B29: =B21-B28 -> 0

Sheet KPIs
A1: KPIs & ratios | G1: =HYPERLINK("#'Cover'!A1","◂ Contents") -> ◂ Contents
A2: Dental practice financial model (growing) — industry metrics and financial ratios for the active scenario
A4: Financial ratios
B5: 1 | C5: 2 | D5: 3 | E5: Target
A6: Revenue growth | B6: =IF(N('P&L'!A5)<=0,"n/a",'P&L'!B5/'P&L'!A5-1) -> n/a | C6: =IF(N('P&L'!B5)<=0,"n/a",'P&L'!C5/'P&L'!B5-1) -> 0.088003464 | D6: =IF(N('P&L'!C5)<=0,"n/a",'P&L'!D5/'P&L'!C5-1) -> 0.087568233
A7: Gross margin | B7: =IF('P&L'!B5<=0,"n/a",'P&L'!B7/'P&L'!B5) -> 0.86092536 | C7: =IF('P&L'!C5<=0,"n/a",'P&L'!C7/'P&L'!C5) -> 0.86093538 | D7: =IF('P&L'!D5<=0,"n/a",'P&L'!D7/'P&L'!D5) -> 0.86094328
A8: EBITDA margin | B8: =IF('P&L'!B5<=0,"n/a",'P&L'!B19/'P&L'!B5) -> 0.15346151 | C8: =IF('P&L'!C5<=0,"n/a",'P&L'!C19/'P&L'!C5) -> 0.17370952 | D8: =IF('P&L'!D5<=0,"n/a",'P&L'!D19/'P&L'!D5) -> 0.19248584
A9: Net margin | B9: =IF('P&L'!B5<=0,"n/a",'P&L'!B26/'P&L'!B5) -> 0.11210338 | C9: =IF('P&L'!C5<=0,"n/a",'P&L'!C26/'P&L'!C5) -> 0.12787551 | D9: =IF('P&L'!D5<=0,"n/a",'P&L'!D26/'P&L'!D5) -> 0.1424478
A10: Payroll, % of revenue | B10: =IF('P&L'!B5<=0,"n/a",-SUMIF(Headcount!$C$5:$AL$5,B$5,Headcount!$C$21:$AL$21)/'P&L'!B5) -> 0.47974989 | C10: =IF('P&L'!C5<=0,"n/a",-SUMIF(Headcount!$C$5:$AL$5,C$5,Headcount!$C$21:$AL$21)/'P&L'!C5) -> 0.47014738 | D10: =IF('P&L'!D5<=0,"n/a",-SUMIF(Headcount!$C$5:$AL$5,D$5,Headcount!$C$21:$AL$21)/'P&L'!D5) -> 0.46116705
A11: Marketing, % of revenue | B11: =IF('P&L'!B5<=0,"n/a",-'P&L'!B11/'P&L'!B5) -> 0.042525184 | C11: =IF('P&L'!C5<=0,"n/a",-'P&L'!C11/'P&L'!C5) -> 0.041039799 | D11: =IF('P&L'!D5<=0,"n/a",-'P&L'!D11/'P&L'!D5) -> 0.039622148
A12: Operating expenses, % of revenue | B12: =IF('P&L'!B5<=0,"n/a",-'P&L'!B18/'P&L'!B5) -> 0.70746385 | C12: =IF('P&L'!C5<=0,"n/a",-'P&L'!C18/'P&L'!C5) -> 0.68722586 | D12: =IF('P&L'!D5<=0,"n/a",-'P&L'!D18/'P&L'!D5) -> 0.66845745
A13: Current ratio (current assets ÷ current liabilities) | B13: =IF(('Balance Sheet'!B12-'Balance Sheet'!B11)<=0,"n/a",('Balance Sheet'!B5+'Balance Sheet'!B6+'Balance Sheet'!B7)/('Balance Sheet'!B12-'Balance Sheet'!B11)) -> 20.141121 | C13: =IF(('Balance Sheet'!C12-'Balance Sheet'!C11)<=0,"n/a",('Balance Sheet'!C5+'Balance Sheet'!C6+'Balance Sheet'!C7)/('Balance Sheet'!C12-'Balance Sheet'!C11)) -> 29.751622 | D13: =IF(('Balance Sheet'!D12-'Balance Sheet'!D11)<=0,"n/a",('Balance Sheet'!D5+'Balance Sheet'!D6+'Balance Sheet'!D7)/('Balance Sheet'!D12-'Balance Sheet'!D11)) -> 40.308799
A14: Debt ÷ equity (loan ÷ total equity) | B14: =IF('Balance Sheet'!B15<=0,"n/a",'Balance Sheet'!B11/'Balance Sheet'!B15) -> 0.40554389 | C14: =IF('Balance Sheet'!C15<=0,"n/a",'Balance Sheet'!C11/'Balance Sheet'!C15) -> 0.18268657 | D14: =IF('Balance Sheet'!D15<=0,"n/a",'Balance Sheet'!D11/'Balance Sheet'!D15) -> 0.094166345
A15: Return on assets (net income ÷ year-end assets) | B15: =IF('Balance Sheet'!B9<=0,"n/a",'P&L'!B26/'Balance Sheet'!B9) -> 0.46986223 | C15: =IF('Balance Sheet'!C9<=0,"n/a",'P&L'!C26/'Balance Sheet'!C9) -> 0.37834145 | D15: =IF('Balance Sheet'!D9<=0,"n/a",'P&L'!D26/'Balance Sheet'!D9) -> 0.32021708
A16: Return on equity (net income ÷ year-end equity) | B16: =IF('Balance Sheet'!B15<=0,"n/a",'P&L'!B26/'Balance Sheet'!B15) -> 0.68889784 | C16: =IF('Balance Sheet'!C15<=0,"n/a",'P&L'!C26/'Balance Sheet'!C15) -> 0.46090937 | D16: =IF('Balance Sheet'!D15<=0,"n/a",'P&L'!D26/'Balance Sheet'!D15) -> 0.35831358
A18: DuPont analysis — return on equity = net margin × asset turnover × equity multiplier
B19: 1 | C19: 2 | D19: 3
A20: Net margin | B20: =IF('P&L'!B5<=0,"n/a",'P&L'!B26/'P&L'!B5) -> 0.11210338 | C20: =IF('P&L'!C5<=0,"n/a",'P&L'!C26/'P&L'!C5) -> 0.12787551 | D20: =IF('P&L'!D5<=0,"n/a",'P&L'!D26/'P&L'!D5) -> 0.1424478
A21: × Asset turnover (revenue ÷ assets) | B21: =IF('Balance Sheet'!B9<=0,"n/a",'P&L'!B5/'Balance Sheet'!B9) -> 4.1913297 | C21: =IF('Balance Sheet'!C9<=0,"n/a",'P&L'!C5/'Balance Sheet'!C9) -> 2.9586702 | D21: =IF('Balance Sheet'!D9<=0,"n/a",'P&L'!D5/'Balance Sheet'!D9) -> 2.247961
A22: × Equity multiplier (assets ÷ equity) | B22: =IF('Balance Sheet'!B15<=0,"n/a",'Balance Sheet'!B9/'Balance Sheet'!B15) -> 1.4661699 | C22: =IF('Balance Sheet'!C15<=0,"n/a",'Balance Sheet'!C9/'Balance Sheet'!C15) -> 1.2182365 | D22: =IF('Balance Sheet'!D15<=0,"n/a",'Balance Sheet'!D9/'Balance Sheet'!D15) -> 1.1189708
A23: Return on equity (product of the three) | B23: =IF(AND(ISNUMBER(B20),ISNUMBER(B21),ISNUMBER(B22)),B20*B21*B22,"n/a") -> 0.68889784 | C23: =IF(AND(ISNUMBER(C20),ISNUMBER(C21),ISNUMBER(C22)),C20*C21*C22,"n/a") -> 0.46090937 | D23: =IF(AND(ISNUMBER(D20),ISNUMBER(D21),ISNUMBER(D22)),D20*D21*D22,"n/a") -> 0.35831358
A24: Check: product − return on equity (must be 0) | B24: =IF(AND(ISNUMBER(B23),ISNUMBER(B16)),B23-B16,IF(ISNUMBER(B23),1,IF(AND(ISNUMBER(B16),ISNUMBER(B20),ISNUMBER(B21)),1,0))) -> 0 | C24: =IF(AND(ISNUMBER(C23),ISNUMBER(C16)),C23-C16,IF(ISNUMBER(C23),1,IF(AND(ISNUMBER(C16),ISNUMBER(C20),ISNUMBER(C21)),1,0))) -> 0 | D24: =IF(AND(ISNUMBER(D23),ISNUMBER(D16)),D23-D16,IF(ISNUMBER(D23),1,IF(AND(ISNUMBER(D16),ISNUMBER(D20),ISNUMBER(D21)),1,0))) -> 0
A26: Dental practice metrics ($'000; per-unit rows in $)
A27: Year # | B27: 1 | C27: 2 | D27: 3
B28: Year 1 | C28: Year 2 | D28: Year 3 | E28: Target
A29: Active patients (year end) | B29: =INDEX(Monthly!$C$13:$AL$13,B$27*12) -> 3170.4728 | C29: =INDEX(Monthly!$C$13:$AL$13,C$27*12) -> 3348.9509 | D29: =INDEX(Monthly!$C$13:$AL$13,D$27*12) -> 3536.0755
A30: New patients in the year | B30: =SUMIF(Monthly!$C$5:$AL$5,B$27,Monthly!$C$10:$AL$10) -> 688 | C30: =SUMIF(Monthly!$C$5:$AL$5,C$27,Monthly!$C$10:$AL$10) -> 725.28 | D30: =SUMIF(Monthly!$C$5:$AL$5,D$27,Monthly!$C$10:$AL$10) -> 764.5968
A31: Patients lost in the year | B31: =SUMIF(Monthly!$C$5:$AL$5,B$27,Monthly!$C$12:$AL$12) -> -517.52719 | C31: =SUMIF(Monthly!$C$5:$AL$5,C$27,Monthly!$C$12:$AL$12) -> -546.80186 | D31: =SUMIF(Monthly!$C$5:$AL$5,D$27,Monthly!$C$12:$AL$12) -> -577.47228
A32: Marketing spend | B32: =-SUMIF(Monthly!$C$5:$AL$5,B$27,Monthly!$C$43:$AL$43) -> 84000 | C32: =-SUMIF(Monthly!$C$5:$AL$5,C$27,Monthly!$C$43:$AL$43) -> 88200 | D32: =-SUMIF(Monthly!$C$5:$AL$5,D$27,Monthly!$C$43:$AL$43) -> 92610
A33: New patients from marketing | B33: =SUMIF(Monthly!$C$5:$AL$5,B$27,Monthly!$C$8:$AL$8) -> 400 | C33: =SUMIF(Monthly!$C$5:$AL$5,C$27,Monthly!$C$8:$AL$8) -> 420 | D33: =SUMIF(Monthly!$C$5:$AL$5,D$27,Monthly!$C$8:$AL$8) -> 441
A34: Marketing cost per new patient ($) | B34: =IF(B33=0,0,B32/B33) -> 210 | C34: =IF(C33=0,0,C32/C33) -> 210 | D34: =IF(D33=0,0,D32/D33) -> 210
A35: Doctor visits | B35: =SUMIF(Monthly!$C$5:$AL$5,B$27,Monthly!$C$19:$AL$19) -> 4238.7654 | C35: =SUMIF(Monthly!$C$5:$AL$5,C$27,Monthly!$C$19:$AL$19) -> 4476.821 | D35: =SUMIF(Monthly!$C$5:$AL$5,D$27,Monthly!$C$19:$AL$19) -> 4726.4985
A36: Doctor visit capacity | B36: =SUMIF(Monthly!$C$5:$AL$5,B$27,Monthly!$C$17:$AL$17) -> 5184 | C36: =SUMIF(Monthly!$C$5:$AL$5,C$27,Monthly!$C$17:$AL$17) -> 5184 | D36: =SUMIF(Monthly!$C$5:$AL$5,D$27,Monthly!$C$17:$AL$17) -> 5184
A37: Doctor chair utilisation (visits ÷ capacity) | B37: =IF(B36=0,0,B35/B36) -> 0.81766307 | C37: =IF(C36=0,0,C35/C36) -> 0.86358429 | D37: =IF(D36=0,0,D35/D36) -> 0.91174739
A38: Hygiene visits | B38: =SUMIF(Monthly!$C$5:$AL$5,B$27,Monthly!$C$23:$AL$23) -> 4631.4331 | C38: =SUMIF(Monthly!$C$5:$AL$5,C$27,Monthly!$C$23:$AL$23) -> 4893.3143 | D38: =SUMIF(Monthly!$C$5:$AL$5,D$27,Monthly!$C$23:$AL$23) -> 5167.6978
A39: Hygiene visit capacity | B39: =SUMIF(Monthly!$C$5:$AL$5,B$27,Monthly!$C$21:$AL$21) -> 5184 | C39: =SUMIF(Monthly!$C$5:$AL$5,C$27,Monthly!$C$21:$AL$21) -> 5495.04 | D39: =SUMIF(Monthly!$C$5:$AL$5,D$27,Monthly!$C$21:$AL$21) -> 5824.7424
A40: Hygiene utilisation (visits ÷ capacity) | B40: =IF(B39=0,0,B38/B39) -> 0.89340916 | C40: =IF(C39=0,0,C38/C39) -> 0.89049658 | D40: =IF(D39=0,0,D38/D39) -> 0.88719766
A41: Gross production | B41: =SUMIF(Monthly!$C$5:$AL$5,B$27,Monthly!$C$28:$AL$28) -> 2325079.2 | C41: =SUMIF(Monthly!$C$5:$AL$5,C$27,Monthly!$C$28:$AL$28) -> 2529694.2 | D41: =SUMIF(Monthly!$C$5:$AL$5,D$27,Monthly!$C$28:$AL$28) -> 2751215.1
A42: Hygiene production | B42: =SUMIF(Monthly!$C$5:$AL$5,B$27,Monthly!$C$27:$AL$27) -> 926286.61 | C42: =SUMIF(Monthly!$C$5:$AL$5,C$27,Monthly!$C$27:$AL$27) -> 1008022.8 | D42: =SUMIF(Monthly!$C$5:$AL$5,D$27,Monthly!$C$27:$AL$27) -> 1096482.1
A43: Hygiene share of production | B43: =IF(B41=0,0,B42/B41) -> 0.39838928 | C43: =IF(C41=0,0,C42/C41) -> 0.39847613 | D43: =IF(D41=0,0,D42/D41) -> 0.39854468
A44: Production per visit (doctor and hygiene) ($) | B44: =IF(B35+B38=0,0,B41/(B35+B38)) -> 262.12257 | C44: =IF(C35+C38=0,0,C41/(C35+C38)) -> 269.97414 | D44: =IF(D35+D38=0,0,D41/(D35+D38)) -> 278.06352
A45: Collections (revenue) | B45: =SUMIF(Monthly!$C$5:$AL$5,B$27,Monthly!$C$31:$AL$31) -> 1975300.1 | C45: =SUMIF(Monthly!$C$5:$AL$5,C$27,Monthly!$C$31:$AL$31) -> 2149133.3 | D45: =SUMIF(Monthly!$C$5:$AL$5,D$27,Monthly!$C$31:$AL$31) -> 2337329.1
A46: Collections ÷ gross production | B46: =IF(B41=0,0,B45/B41) -> 0.8495625 | C46: =IF(C41=0,0,C45/C41) -> 0.8495625 | D46: =IF(D41=0,0,D45/D41) -> 0.8495625
A47: Collections per active patient (year-end base) ($) | B47: =IF(B29=0,0,B45/B29) -> 623.03013 | C47: =IF(C29=0,0,C45/C29) -> 641.7333 | D47: =IF(D29=0,0,D45/D29) -> 660.99527
A48: Collections per doctor operatory | B48: =IF(Inputs!$E$7=0,0,B45/Inputs!$E$7) -> 329216.68 | C48: =IF(Inputs!$E$7=0,0,C45/Inputs!$E$7) -> 358188.89 | D48: =IF(Inputs!$E$7=0,0,D45/Inputs!$E$7) -> 389554.86
A49: Gross profit (after supplies, lab and card fees) | B49: =SUMIF(Monthly!$C$5:$AL$5,B$27,Monthly!$C$38:$AL$38) -> 1700585.9 | C49: =SUMIF(Monthly!$C$5:$AL$5,C$27,Monthly!$C$38:$AL$38) -> 1850264.9 | D49: =SUMIF(Monthly!$C$5:$AL$5,D$27,Monthly!$C$38:$AL$38) -> 2012307.8
A50: Gross margin | B50: =IF(B45=0,0,B49/B45) -> 0.86092536 | C50: =IF(C45=0,0,C49/C45) -> 0.86093538 | D50: =IF(D45=0,0,D49/D45) -> 0.86094328
A51: EBITDA (after owner-dentist pay) | B51: =SUMIF(Monthly!$C$5:$AL$5,B$27,Monthly!$C$51:$AL$51) -> 303132.53 | C51: =SUMIF(Monthly!$C$5:$AL$5,C$27,Monthly!$C$51:$AL$51) -> 373324.91 | D51: =SUMIF(Monthly!$C$5:$AL$5,D$27,Monthly!$C$51:$AL$51) -> 449902.76
A52: EBITDA margin | B52: =IF(B45=0,0,B51/B45) -> 0.15346151 | C52: =IF(C45=0,0,C51/C45) -> 0.17370952 | D52: =IF(D45=0,0,D51/D45) -> 0.19248584
A53: Collections per square foot ($) | B53: =IF(Inputs!$E$48=0,0,B45/Inputs!$E$48) -> 493.82502 | C53: =IF(Inputs!$E$48=0,0,C45/Inputs!$E$48) -> 537.28333 | D53: =IF(Inputs!$E$48=0,0,D45/Inputs!$E$48) -> 584.33229

Sheet Inputs
A1: Inputs — Low / Base / High | I1: =HYPERLINK("#'Cover'!A1","◂ Contents") -> ◂ Contents
A2: Illustrative assumptions — replace them with your own numbers.
A5: Driver | B5: Low | C5: Base | D5: High | E5: Active | F5: Unit | G5: Source / comment
A6: Chairs & schedule
A7: Doctor operatories (restorative chairs) | B7: 6 | C7: 6 | D7: 6 | E7: =CHOOSE(Dashboard!$B$4,B7,C7,D7) -> 6 | F7: #
A8: Hygiene operatories | B8: 4 | C8: 4 | D8: 4 | E8: =CHOOSE(Dashboard!$B$4,B8,C8,D8) -> 4 | F8: #
A9: Doctor visits per operatory per working day | B9: 3.8 | C9: 4 | D9: 4.2 | E9: =CHOOSE(Dashboard!$B$4,B9,C9,D9) -> 4 | F9: visits | G9: Low ≤ Base ≤ High
A10: Hygiene visits per hygienist per working day | B10: 7.5 | C10: 8 | D10: 8.5 | E10: =CHOOSE(Dashboard!$B$4,B10,C10,D10) -> 8 | F10: visits | G10: Low ≤ Base ≤ High
A11: Working days per month | B11: 18 | C11: 18 | D11: 18 | E11: =CHOOSE(Dashboard!$B$4,B11,C11,D11) -> 18 | F11: days | G11: Low ≤ Base ≤ High
A13: Patients
A14: Active patients at start | B14: 2700 | C14: 3000 | D14: 3300 | E14: =CHOOSE(Dashboard!$B$4,B14,C14,D14) -> 3000 | F14: # | G14: Low ≤ Base ≤ High
A15: Referral & walk-in new patients per month (year 1) | B15: 20 | C15: 24 | D15: 28 | E15: =CHOOSE(Dashboard!$B$4,B15,C15,D15) -> 24 | F15: # | G15: Low ≤ Base ≤ High
A16: Referral & walk-in new patients growth per year | B16: 0.03 | C16: 0.06 | D16: 0.09 | E16: =CHOOSE(Dashboard!$B$4,B16,C16,D16) -> 0.06 | F16: % | G16: Low ≤ Base ≤ High
A17: Marketing budget per month (year 1) | B17: 7000 | C17: 7000 | D17: 7000 | E17: =CHOOSE(Dashboard!$B$4,B17,C17,D17) -> 7000 | F17: $
A18: Marketing budget growth per year | B18: 0 | C18: 0.05 | D18: 0.1 | E18: =CHOOSE(Dashboard!$B$4,B18,C18,D18) -> 0.05 | F18: % | G18: Low ≤ Base ≤ High
A19: Marketing cost per new patient | B19: 230 | C19: 210 | D19: 190 | E19: =CHOOSE(Dashboard!$B$4,B19,C19,D19) -> 210 | F19: $ | G19: Low ≥ Base ≥ High (lower is better)
A20: Active patients lost per month | B20: 0.016 | C20: 0.014 | D20: 0.012 | E20: =CHOOSE(Dashboard!$B$4,B20,C20,D20) -> 0.014 | F20: % | G20: Low ≥ Base ≥ High (lower is better)
A21: Doctor visits per active patient per year | B21: 1.1 | C21: 1.15 | D21: 1.2 | E21: =CHOOSE(Dashboard!$B$4,B21,C21,D21) -> 1.15 | F21: visits | G21: Low ≤ Base ≤ High
A22: Hygiene recall visits per active patient per year | B22: 1.4 | C22: 1.5 | D22: 1.6 | E22: =CHOOSE(Dashboard!$B$4,B22,C22,D22) -> 1.5 | F22: visits | G22: Low ≤ Base ≤ High
A23: Doctor visits per new patient in the period they join | B23: 1 | C23: 1 | D23: 1 | E23: =CHOOSE(Dashboard!$B$4,B23,C23,D23) -> 1 | F23: visits | G23: Low ≤ Base ≤ High
A25: Fees
A26: Production per doctor visit, office fees (year 1) | B26: 320 | C26: 330 | D26: 340 | E26: =CHOOSE(Dashboard!$B$4,B26,C26,D26) -> 330 | F26: $ | G26: Low ≤ Base ≤ High
A27: Production per hygiene visit, office fees (year 1) | B27: 195 | C27: 200 | D27: 205 | E27: =CHOOSE(Dashboard!$B$4,B27,C27,D27) -> 200 | F27: $ | G27: Low ≤ Base ≤ High
A28: Fee increase per year | B28: 0.02 | C28: 0.03 | D28: 0.04 | E28: =CHOOSE(Dashboard!$B$4,B28,C28,D28) -> 0.03 | F28: % | G28: Low ≤ Base ≤ High
A30: Insurance & collections
A31: Production from in-network insurance (PPO) patients | B31: 0.6 | C31: 0.55 | D31: 0.5 | E31: =CHOOSE(Dashboard!$B$4,B31,C31,D31) -> 0.55 | F31: % | G31: Low ≥ Base ≥ High (lower is better)
A32: PPO fee-schedule write-off, % of PPO production | B32: 0.27 | C32: 0.25 | D32: 0.23 | E32: =CHOOSE(Dashboard!$B$4,B32,C32,D32) -> 0.25 | F32: % | G32: Low ≥ Base ≥ High (lower is better)
A33: Production never collected (bad debt), % of net production | B33: 0.02 | C33: 0.015 | D33: 0.01 | E33: =CHOOSE(Dashboard!$B$4,B33,C33,D33) -> 0.015 | F33: % | G33: Low ≥ Base ≥ High (lower is better)
A35: Costs
A36: Dental supplies, % of gross production | B36: 0.054 | C36: 0.049 | D36: 0.046 | E36: =CHOOSE(Dashboard!$B$4,B36,C36,D36) -> 0.049 | F36: % | G36: Low ≥ Base ≥ High (lower is better)
A37: Lab fees, % of doctor production | B37: 0.108 | C37: 0.098 | D37: 0.088 | E37: =CHOOSE(Dashboard!$B$4,B37,C37,D37) -> 0.098 | F37: % | G37: Low ≥ Base ≥ High (lower is better)
A38: Card & payment processing, % of collections | B38: 0.014 | C38: 0.012 | D38: 0.01 | E38: =CHOOSE(Dashboard!$B$4,B38,C38,D38) -> 0.012 | F38: % | G38: Low ≥ Base ≥ High (lower is better)
A39: Doctor visits seen by associate dentists | B39: 0.4 | C39: 0.4 | D39: 0.4 | E39: =CHOOSE(Dashboard!$B$4,B39,C39,D39) -> 0.4 | F39: %
A40: Associate pay, % of the collections they produce | B40: 0.32 | C40: 0.3 | D40: 0.28 | E40: =CHOOSE(Dashboard!$B$4,B40,C40,D40) -> 0.3 | F40: % | G40: Low ≥ Base ≥ High (lower is better)
A41: Utilities & phone per month | B41: 1800 | C41: 1800 | D41: 1800 | E41: =CHOOSE(Dashboard!$B$4,B41,C41,D41) -> 1800 | F41: $
A42: Practice software & IT per month | B42: 1300 | C42: 1300 | D42: 1300 | E42: =CHOOSE(Dashboard!$B$4,B42,C42,D42) -> 1300 | F42: $
A43: Malpractice & liability insurance per month | B43: 1100 | C43: 1100 | D43: 1100 | E43: =CHOOSE(Dashboard!$B$4,B43,C43,D43) -> 1100 | F43: $
A44: Equipment maintenance, cleaning & compliance per month | B44: 1400 | C44: 1400 | D44: 1400 | E44: =CHOOSE(Dashboard!$B$4,B44,C44,D44) -> 1400 | F44: $
A45: Other G&A per month (accounting, legal, licences, CE) | B45: 3000 | C45: 3000 | D45: 3000 | E45: =CHOOSE(Dashboard!$B$4,B45,C45,D45) -> 3000 | F45: $
A47: Space
A48: Practice size | B48: 4000 | C48: 4000 | D48: 4000 | E48: =CHOOSE(Dashboard!$B$4,B48,C48,D48) -> 4000 | F48: sq ft
A49: Rent per sq ft per year (incl. CAM) | B49: 32 | C49: 30 | D49: 28 | E49: =CHOOSE(Dashboard!$B$4,B49,C49,D49) -> 30 | F49: $ | G49: Low ≥ Base ≥ High (lower is better)
A51: Capex
A52: Fit-out cost per sq ft, net of landlord allowance (month 1) | B52: 0 | C52: 0 | D52: 0 | E52: =CHOOSE(Dashboard!$B$4,B52,C52,D52) -> 0 | F52: $
A53: Equipment per operatory (chair, unit, light, cabinetry) | B53: 45000 | C53: 45000 | D53: 45000 | E53: =CHOOSE(Dashboard!$B$4,B53,C53,D53) -> 45000 | F53: $
A54: Operatories already equipped at start | B54: 10 | C54: 10 | D54: 10 | E54: =CHOOSE(Dashboard!$B$4,B54,C54,D54) -> 10 | F54: #
A55: Imaging & IT (x-ray, panoramic / CBCT, scanner) (month 1) | B55: 60000 | C55: 60000 | D55: 60000 | E55: =CHOOSE(Dashboard!$B$4,B55,C55,D55) -> 60000 | F55: $
A56: Equipment refresh & technology, % of collections | B56: 0.015 | C56: 0.015 | D56: 0.015 | E56: =CHOOSE(Dashboard!$B$4,B56,C56,D56) -> 0.015 | F56: % | G56: Low ≥ Base ≥ High (lower is better)
A58: Headcount
A59: Owner dentist: headcount (FTE) | B59: 1 | C59: 1 | D59: 1 | E59: =CHOOSE(Dashboard!$B$4,B59,C59,D59) -> 1 | F59: FTE | G59: Low ≤ Base ≤ High
A60: Owner dentist: salary per FTE per year | B60: 180000 | C60: 180000 | D60: 180000 | E60: =CHOOSE(Dashboard!$B$4,B60,C60,D60) -> 180000 | F60: $
A61: Owner dentist: headcount growth per year | B61: 0 | C61: 0 | D61: 0 | E61: =CHOOSE(Dashboard!$B$4,B61,C61,D61) -> 0 | F61: % | G61: Low ≤ Base ≤ High
A62: Owner dentist: first month on payroll | B62: 1 | C62: 1 | D62: 1 | E62: =CHOOSE(Dashboard!$B$4,B62,C62,D62) -> 1 | F62: month #
A63: Hygienists: headcount (FTE) | B63: 3 | C63: 3 | D63: 3 | E63: =CHOOSE(Dashboard!$B$4,B63,C63,D63) -> 3 | F63: FTE | G63: Low ≤ Base ≤ High
A64: Hygienists: salary per FTE per year | B64: 96000 | C64: 96000 | D64: 96000 | E64: =CHOOSE(Dashboard!$B$4,B64,C64,D64) -> 96000 | F64: $
A65: Hygienists: headcount growth per year | B65: 0.06 | C65: 0.06 | D65: 0.06 | E65: =CHOOSE(Dashboard!$B$4,B65,C65,D65) -> 0.06 | F65: % | G65: Low ≤ Base ≤ High
A66: Hygienists: first month on payroll | B66: 1 | C66: 1 | D66: 1 | E66: =CHOOSE(Dashboard!$B$4,B66,C66,D66) -> 1 | F66: month #
A67: Dental assistants: headcount (FTE) | B67: 4.5 | C67: 4.5 | D67: 4.5 | E67: =CHOOSE(Dashboard!$B$4,B67,C67,D67) -> 4.5 | F67: FTE | G67: Low ≤ Base ≤ High
A68: Dental assistants: salary per FTE per year | B68: 45000 | C68: 45000 | D68: 45000 | E68: =CHOOSE(Dashboard!$B$4,B68,C68,D68) -> 45000 | F68: $
A69: Dental assistants: headcount growth per year | B69: 0.04 | C69: 0.04 | D69: 0.04 | E69: =CHOOSE(Dashboard!$B$4,B69,C69,D69) -> 0.04 | F69: % | G69: Low ≤ Base ≤ High
A70: Dental assistants: first month on payroll | B70: 1 | C70: 1 | D70: 1 | E70: =CHOOSE(Dashboard!$B$4,B70,C70,D70) -> 1 | F70: month #
A71: Front desk: headcount (FTE) | B71: 3 | C71: 3 | D71: 3 | E71: =CHOOSE(Dashboard!$B$4,B71,C71,D71) -> 3 | F71: FTE | G71: Low ≤ Base ≤ High
A72: Front desk: salary per FTE per year | B72: 41000 | C72: 41000 | D72: 41000 | E72: =CHOOSE(Dashboard!$B$4,B72,C72,D72) -> 41000 | F72: $
A73: Front desk: headcount growth per year | B73: 0.04 | C73: 0.04 | D73: 0.04 | E73: =CHOOSE(Dashboard!$B$4,B73,C73,D73) -> 0.04 | F73: % | G73: Low ≤ Base ≤ High
A74: Front desk: first month on payroll | B74: 1 | C74: 1 | D74: 1 | E74: =CHOOSE(Dashboard!$B$4,B74,C74,D74) -> 1 | F74: month #
A75: Office manager: headcount (FTE) | B75: 1 | C75: 1 | D75: 1 | E75: =CHOOSE(Dashboard!$B$4,B75,C75,D75) -> 1 | F75: FTE | G75: Low ≤ Base ≤ High
A76: Office manager: salary per FTE per year | B76: 68000 | C76: 68000 | D76: 68000 | E76: =CHOOSE(Dashboard!$B$4,B76,C76,D76) -> 68000 | F76: $
A77: Office manager: headcount growth per year | B77: 0 | C77: 0 | D77: 0 | E77: =CHOOSE(Dashboard!$B$4,B77,C77,D77) -> 0 | F77: % | G77: Low ≤ Base ≤ High
A78: Office manager: first month on payroll | B78: 1 | C78: 1 | D78: 1 | E78: =CHOOSE(Dashboard!$B$4,B78,C78,D78) -> 1 | F78: month #
A79: Payroll taxes & benefits, % of salary | B79: 0.1 | C79: 0.1 | D79: 0.1 | E79: =CHOOSE(Dashboard!$B$4,B79,C79,D79) -> 0.1 | F79: %
A80: Wage growth per year | B80: 0.03 | C80: 0.03 | D80: 0.03 | E80: =CHOOSE(Dashboard!$B$4,B80,C80,D80) -> 0.03 | F80: %
A82: Funding
A83: Equity raised at start | B83: 100000 | C83: 100000 | D83: 100000 | E83: =CHOOSE(Dashboard!$B$4,B83,C83,D83) -> 100000 | F83: $
A84: Loan drawn at start | B84: 150000 | C84: 150000 | D84: 150000 | E84: =CHOOSE(Dashboard!$B$4,B84,C84,D84) -> 150000 | F84: $
A85: Loan interest rate per year | B85: 0.085 | C85: 0.085 | D85: 0.085 | E85: =CHOOSE(Dashboard!$B$4,B85,C85,D85) -> 0.085 | F85: %
A86: Loan repayment term | B86: 7 | C86: 7 | D86: 7 | E86: =CHOOSE(Dashboard!$B$4,B86,C86,D86) -> 7 | F86: years
A88: Working capital
A89: Customer payment terms (receivable days) | B89: 22 | C89: 17 | D89: 14 | E89: =CHOOSE(Dashboard!$B$4,B89,C89,D89) -> 17 | F89: days
A90: Inventory held (days of COGS) | B90: 12 | C90: 12 | D90: 12 | E90: =CHOOSE(Dashboard!$B$4,B90,C90,D90) -> 12 | F90: days
A91: Supplier payment terms (payable days) | B91: 25 | C91: 25 | D91: 25 | E91: =CHOOSE(Dashboard!$B$4,B91,C91,D91) -> 25 | F91: days
A93: Tax & depreciation
A94: Depreciation period for capex | B94: 7 | C94: 7 | D94: 7 | E94: =CHOOSE(Dashboard!$B$4,B94,C94,D94) -> 7 | F94: years
A95: Income tax rate | B95: 0.21 | C95: 0.21 | D95: 0.21 | E95: =CHOOSE(Dashboard!$B$4,B95,C95,D95) -> 0.21 | F95: %
A97: Break-even & funding
A98: Minimum cash buffer to keep | B98: 349000 | C98: 349000 | D98: 349000 | E98: =CHOOSE(Dashboard!$B$4,B98,C98,D98) -> 349000 | F98: $ | G98: About 3 months of costs
A100: Valuation
A101: Discount rate (WACC) | B101: 0.2 | C101: 0.16 | D101: 0.13 | E101: =CHOOSE(Dashboard!$B$4,B101,C101,D101) -> 0.16 | F101: % | G101: Low ≥ Base ≥ High (lower is better)
A102: Terminal growth rate (perpetuity) | B102: 0.01 | C102: 0.02 | D102: 0.03 | E102: =CHOOSE(Dashboard!$B$4,B102,C102,D102) -> 0.02 | F102: % | G102: Low ≤ Base ≤ High
A103: Exit multiple (EV ÷ final-year EBITDA) | B103: 4 | C103: 5.5 | D103: 7 | E103: =CHOOSE(Dashboard!$B$4,B103,C103,D103) -> 5.5 | F103: x | G103: Low ≤ Base ≤ High
A104: Sensitivity table: WACC step | B104: 0.01 | C104: 0.01 | D104: 0.01 | E104: =CHOOSE(Dashboard!$B$4,B104,C104,D104) -> 0.01 | F104: %
A105: Sensitivity table: growth step | B105: 0.005 | C105: 0.005 | D105: 0.005 | E105: =CHOOSE(Dashboard!$B$4,B105,C105,D105) -> 0.005 | F105: %
A107: Legend: yellow cell with blue figure = input you can change · black = formula · green = link to another sheet · grey = active value (column E follows the scenario on the Dashboard).

Sheet P&L
A1: Annual profit & loss | F1: =HYPERLINK("#'Cover'!A1","◂ Contents") -> ◂ Contents
A2: Rolled up from the period detail (SUMIF on the year row; balances at year end).
A3: Year # | B3: 1 | C3: 2 | D3: 3
B4: Year 1 | C4: Year 2 | D4: Year 3
A5: Revenue | B5: =SUMIF(Monthly!$C$5:$AL$5,B$3,Monthly!$C$31:$AL$31) -> 1975300.1 | C5: =SUMIF(Monthly!$C$5:$AL$5,C$3,Monthly!$C$31:$AL$31) -> 2149133.3 | D5: =SUMIF(Monthly!$C$5:$AL$5,D$3,Monthly!$C$31:$AL$31) -> 2337329.1
A6: Cost of sales | B6: =SUMIF(Monthly!$C$5:$AL$5,B$3,Monthly!$C$37:$AL$37) -> -274714.15 | C6: =SUMIF(Monthly!$C$5:$AL$5,C$3,Monthly!$C$37:$AL$37) -> -298868.42 | D6: =SUMIF(Monthly!$C$5:$AL$5,D$3,Monthly!$C$37:$AL$37) -> -325021.31
A7: Gross profit | B7: =SUMIF(Monthly!$C$5:$AL$5,B$3,Monthly!$C$38:$AL$38) -> 1700585.9 | C7: =SUMIF(Monthly!$C$5:$AL$5,C$3,Monthly!$C$38:$AL$38) -> 1850264.9 | D7: =SUMIF(Monthly!$C$5:$AL$5,D$3,Monthly!$C$38:$AL$38) -> 2012307.8
A8: Gross margin | B8: =IF(B5=0,0,B7/B5) -> 0.86092536 | C8: =IF(C5=0,0,C7/C5) -> 0.86093538 | D8: =IF(D5=0,0,D7/D5) -> 0.86094328
A9: Staff payroll (owner dentist, hygienists, assistants, front desk, office manager) | B9: =SUMIF(Monthly!$C$5:$AL$5,B$3,Monthly!$C$41:$AL$41) -> -947650 | C9: =SUMIF(Monthly!$C$5:$AL$5,C$3,Monthly!$C$41:$AL$41) -> -1010409.4 | D9: =SUMIF(Monthly!$C$5:$AL$5,D$3,Monthly!$C$41:$AL$41) -> -1077899.2
A10: Associate dentists (% of the collections they produce) | B10: =SUMIF(Monthly!$C$5:$AL$5,B$3,Monthly!$C$42:$AL$42) -> -142603.41 | C10: =SUMIF(Monthly!$C$5:$AL$5,C$3,Monthly!$C$42:$AL$42) -> -155130.6 | D10: =SUMIF(Monthly!$C$5:$AL$5,D$3,Monthly!$C$42:$AL$42) -> -168695.89
A11: Marketing | B11: =SUMIF(Monthly!$C$5:$AL$5,B$3,Monthly!$C$43:$AL$43) -> -84000 | C11: =SUMIF(Monthly!$C$5:$AL$5,C$3,Monthly!$C$43:$AL$43) -> -88200 | D11: =SUMIF(Monthly!$C$5:$AL$5,D$3,Monthly!$C$43:$AL$43) -> -92610
A12: Rent | B12: =SUMIF(Monthly!$C$5:$AL$5,B$3,Monthly!$C$44:$AL$44) -> -120000 | C12: =SUMIF(Monthly!$C$5:$AL$5,C$3,Monthly!$C$44:$AL$44) -> -120000 | D12: =SUMIF(Monthly!$C$5:$AL$5,D$3,Monthly!$C$44:$AL$44) -> -120000
A13: Utilities & phone | B13: =SUMIF(Monthly!$C$5:$AL$5,B$3,Monthly!$C$45:$AL$45) -> -21600 | C13: =SUMIF(Monthly!$C$5:$AL$5,C$3,Monthly!$C$45:$AL$45) -> -21600 | D13: =SUMIF(Monthly!$C$5:$AL$5,D$3,Monthly!$C$45:$AL$45) -> -21600
A14: Practice software & IT | B14: =SUMIF(Monthly!$C$5:$AL$5,B$3,Monthly!$C$46:$AL$46) -> -15600 | C14: =SUMIF(Monthly!$C$5:$AL$5,C$3,Monthly!$C$46:$AL$46) -> -15600 | D14: =SUMIF(Monthly!$C$5:$AL$5,D$3,Monthly!$C$46:$AL$46) -> -15600
A15: Malpractice & liability insurance | B15: =SUMIF(Monthly!$C$5:$AL$5,B$3,Monthly!$C$47:$AL$47) -> -13200 | C15: =SUMIF(Monthly!$C$5:$AL$5,C$3,Monthly!$C$47:$AL$47) -> -13200 | D15: =SUMIF(Monthly!$C$5:$AL$5,D$3,Monthly!$C$47:$AL$47) -> -13200
A16: Equipment maintenance, cleaning & compliance | B16: =SUMIF(Monthly!$C$5:$AL$5,B$3,Monthly!$C$48:$AL$48) -> -16800 | C16: =SUMIF(Monthly!$C$5:$AL$5,C$3,Monthly!$C$48:$AL$48) -> -16800 | D16: =SUMIF(Monthly!$C$5:$AL$5,D$3,Monthly!$C$48:$AL$48) -> -16800
A17: Other G&A | B17: =SUMIF(Monthly!$C$5:$AL$5,B$3,Monthly!$C$49:$AL$49) -> -36000 | C17: =SUMIF(Monthly!$C$5:$AL$5,C$3,Monthly!$C$49:$AL$49) -> -36000 | D17: =SUMIF(Monthly!$C$5:$AL$5,D$3,Monthly!$C$49:$AL$49) -> -36000
A18: Total operating expenses | B18: =SUMIF(Monthly!$C$5:$AL$5,B$3,Monthly!$C$50:$AL$50) -> -1397453.4 | C18: =SUMIF(Monthly!$C$5:$AL$5,C$3,Monthly!$C$50:$AL$50) -> -1476940 | D18: =SUMIF(Monthly!$C$5:$AL$5,D$3,Monthly!$C$50:$AL$50) -> -1562405.1
A19: EBITDA | B19: =SUMIF(Monthly!$C$5:$AL$5,B$3,Monthly!$C$51:$AL$51) -> 303132.53 | C19: =SUMIF(Monthly!$C$5:$AL$5,C$3,Monthly!$C$51:$AL$51) -> 373324.91 | D19: =SUMIF(Monthly!$C$5:$AL$5,D$3,Monthly!$C$51:$AL$51) -> 449902.76
A20: EBITDA margin | B20: =IF(B5=0,0,B19/B5) -> 0.15346151 | C20: =IF(C5=0,0,C19/C5) -> 0.17370952 | D20: =IF(D5=0,0,D19/D5) -> 0.19248584
A21: Depreciation | B21: =SUMIF(Monthly!$C$5:$AL$5,B$3,Monthly!$C$65:$AL$65) -> -10846.744 | C21: =SUMIF(Monthly!$C$5:$AL$5,C$3,Monthly!$C$65:$AL$65) -> -15279.934 | D21: =SUMIF(Monthly!$C$5:$AL$5,D$3,Monthly!$C$65:$AL$65) -> -20102.158
A22: EBIT | B22: =SUMIF(Monthly!$C$5:$AL$5,B$3,Monthly!$C$54:$AL$54) -> 292285.78 | C22: =SUMIF(Monthly!$C$5:$AL$5,C$3,Monthly!$C$54:$AL$54) -> 358044.98 | D22: =SUMIF(Monthly!$C$5:$AL$5,D$3,Monthly!$C$54:$AL$54) -> 429800.6
A23: Interest | B23: =SUMIF(Monthly!$C$5:$AL$5,B$3,Monthly!$C$55:$AL$55) -> -11984.747 | C23: =SUMIF(Monthly!$C$5:$AL$5,C$3,Monthly!$C$55:$AL$55) -> -10169.643 | D23: =SUMIF(Monthly!$C$5:$AL$5,D$3,Monthly!$C$55:$AL$55) -> -8348.2143
A24: Pre-tax income | B24: =SUMIF(Monthly!$C$5:$AL$5,B$3,Monthly!$C$56:$AL$56) -> 280301.03 | C24: =SUMIF(Monthly!$C$5:$AL$5,C$3,Monthly!$C$56:$AL$56) -> 347875.34 | D24: =SUMIF(Monthly!$C$5:$AL$5,D$3,Monthly!$C$56:$AL$56) -> 421452.39
A25: Income tax | B25: =SUMIF(Monthly!$C$5:$AL$5,B$3,Monthly!$C$59:$AL$59) -> -58863.217 | C25: =SUMIF(Monthly!$C$5:$AL$5,C$3,Monthly!$C$59:$AL$59) -> -73053.821 | D25: =SUMIF(Monthly!$C$5:$AL$5,D$3,Monthly!$C$59:$AL$59) -> -88505.001
A26: Net income | B26: =SUMIF(Monthly!$C$5:$AL$5,B$3,Monthly!$C$60:$AL$60) -> 221437.82 | C26: =SUMIF(Monthly!$C$5:$AL$5,C$3,Monthly!$C$60:$AL$60) -> 274821.52 | D26: =SUMIF(Monthly!$C$5:$AL$5,D$3,Monthly!$C$60:$AL$60) -> 332947.38
A27: Net margin | B27: =IF(B5=0,0,B26/B5) -> 0.11210338 | C27: =IF(C5=0,0,C26/C5) -> 0.12787551 | D27: =IF(D5=0,0,D26/D5) -> 0.1424478

Sheet Cash Flow
A1: Annual cash flow statement | F1: =HYPERLINK("#'Cover'!A1","◂ Contents") -> ◂ Contents
A2: Rolled up from the period detail (SUMIF on the year row; balances at year end).
A3: Year # | B3: 1 | C3: 2 | D3: 3
B4: Year 1 | C4: Year 2 | D4: Year 3
A5: Net income | B5: =SUMIF(Monthly!$C$5:$AL$5,B$3,Monthly!$C$60:$AL$60) -> 221437.82 | C5: =SUMIF(Monthly!$C$5:$AL$5,C$3,Monthly!$C$60:$AL$60) -> 274821.52 | D5: =SUMIF(Monthly!$C$5:$AL$5,D$3,Monthly!$C$60:$AL$60) -> 332947.38
A6: Add back depreciation | B6: =-SUMIF(Monthly!$C$5:$AL$5,B$3,Monthly!$C$65:$AL$65) -> 10846.744 | C6: =-SUMIF(Monthly!$C$5:$AL$5,C$3,Monthly!$C$65:$AL$65) -> 15279.934 | D6: =-SUMIF(Monthly!$C$5:$AL$5,D$3,Monthly!$C$65:$AL$65) -> 20102.158
A7: (Increase) / decrease in receivables | B7: =SUMIF(Monthly!$C$5:$AL$5,B$3,Monthly!$C$79:$AL$79) -> -95357.627 | C7: =SUMIF(Monthly!$C$5:$AL$5,C$3,Monthly!$C$79:$AL$79) -> -8371.7648 | D7: =SUMIF(Monthly!$C$5:$AL$5,D$3,Monthly!$C$79:$AL$79) -> -9066.1996
A8: (Increase) / decrease in inventory | B8: =SUMIF(Monthly!$C$5:$AL$5,B$3,Monthly!$C$80:$AL$80) -> -9353.9901 | C8: =SUMIF(Monthly!$C$5:$AL$5,C$3,Monthly!$C$80:$AL$80) -> -820.56915 | D8: =SUMIF(Monthly!$C$5:$AL$5,D$3,Monthly!$C$80:$AL$80) -> -888.72393
A9: Increase / (decrease) in payables | B9: =SUMIF(Monthly!$C$5:$AL$5,B$3,Monthly!$C$81:$AL$81) -> 19487.479 | C9: =SUMIF(Monthly!$C$5:$AL$5,C$3,Monthly!$C$81:$AL$81) -> 1709.5191 | D9: =SUMIF(Monthly!$C$5:$AL$5,D$3,Monthly!$C$81:$AL$81) -> 1851.5082
A10: Operating cash flow | B10: =SUMIF(Monthly!$C$5:$AL$5,B$3,Monthly!$C$84:$AL$84) -> 147060.42 | C10: =SUMIF(Monthly!$C$5:$AL$5,C$3,Monthly!$C$84:$AL$84) -> 282618.64 | D10: =SUMIF(Monthly!$C$5:$AL$5,D$3,Monthly!$C$84:$AL$84) -> 344946.13
A11: Capital spending | B11: =SUMIF(Monthly!$C$5:$AL$5,B$3,Monthly!$C$85:$AL$85) -> -89629.501 | C11: =SUMIF(Monthly!$C$5:$AL$5,C$3,Monthly!$C$85:$AL$85) -> -32237 | D11: =SUMIF(Monthly!$C$5:$AL$5,D$3,Monthly!$C$85:$AL$85) -> -35059.937
A12: Equity raised | B12: =SUMIF(Monthly!$C$5:$AL$5,B$3,Monthly!$C$86:$AL$86) -> 100000 | C12: =SUMIF(Monthly!$C$5:$AL$5,C$3,Monthly!$C$86:$AL$86) -> 0 | D12: =SUMIF(Monthly!$C$5:$AL$5,D$3,Monthly!$C$86:$AL$86) -> 0
A13: Loan drawdown | B13: =SUMIF(Monthly!$C$5:$AL$5,B$3,Monthly!$C$71:$AL$71) -> 150000 | C13: =SUMIF(Monthly!$C$5:$AL$5,C$3,Monthly!$C$71:$AL$71) -> 0 | D13: =SUMIF(Monthly!$C$5:$AL$5,D$3,Monthly!$C$71:$AL$71) -> 0
A14: Loan repayment | B14: =SUMIF(Monthly!$C$5:$AL$5,B$3,Monthly!$C$72:$AL$72) -> -19642.857 | C14: =SUMIF(Monthly!$C$5:$AL$5,C$3,Monthly!$C$72:$AL$72) -> -21428.571 | D14: =SUMIF(Monthly!$C$5:$AL$5,D$3,Monthly!$C$72:$AL$72) -> -21428.571
A15: Financing cash flow | B15: =SUMIF(Monthly!$C$5:$AL$5,B$3,Monthly!$C$87:$AL$87) -> 230357.14 | C15: =SUMIF(Monthly!$C$5:$AL$5,C$3,Monthly!$C$87:$AL$87) -> -21428.571 | D15: =SUMIF(Monthly!$C$5:$AL$5,D$3,Monthly!$C$87:$AL$87) -> -21428.571
A16: Net change in cash | B16: =SUMIF(Monthly!$C$5:$AL$5,B$3,Monthly!$C$88:$AL$88) -> 287788.06 | C16: =SUMIF(Monthly!$C$5:$AL$5,C$3,Monthly!$C$88:$AL$88) -> 228953.06 | D16: =SUMIF(Monthly!$C$5:$AL$5,D$3,Monthly!$C$88:$AL$88) -> 288457.62
A17: Opening cash | B17: =INDEX(Monthly!$C$89:$AL$89,(B$3-1)*12+1) -> 0 | C17: =INDEX(Monthly!$C$89:$AL$89,(C$3-1)*12+1) -> 287788.06 | D17: =INDEX(Monthly!$C$89:$AL$89,(D$3-1)*12+1) -> 516741.13
A18: Closing cash | B18: =INDEX(Monthly!$C$90:$AL$90,B$3*12) -> 287788.06 | C18: =INDEX(Monthly!$C$90:$AL$90,C$3*12) -> 516741.13 | D18: =INDEX(Monthly!$C$90:$AL$90,D$3*12) -> 805198.75

Sheet Balance Sheet
A1: Balance sheet at year end | F1: =HYPERLINK("#'Cover'!A1","◂ Contents") -> ◂ Contents
A2: Rolled up from the period detail (SUMIF on the year row; balances at year end).
A3: Year # | B3: 1 | C3: 2 | D3: 3
B4: Year 1 | C4: Year 2 | D4: Year 3
A5: Cash | B5: =INDEX(Monthly!$C$90:$AL$90,B$3*12) -> 287788.06 | C5: =INDEX(Monthly!$C$90:$AL$90,C$3*12) -> 516741.13 | D5: =INDEX(Monthly!$C$90:$AL$90,D$3*12) -> 805198.75
A6: Accounts receivable | B6: =INDEX(Monthly!$C$76:$AL$76,B$3*12) -> 95357.627 | C6: =INDEX(Monthly!$C$76:$AL$76,C$3*12) -> 103729.39 | D6: =INDEX(Monthly!$C$76:$AL$76,D$3*12) -> 112795.59
A7: Inventory | B7: =INDEX(Monthly!$C$77:$AL$77,B$3*12) -> 9353.9901 | C7: =INDEX(Monthly!$C$77:$AL$77,C$3*12) -> 10174.559 | D7: =INDEX(Monthly!$C$77:$AL$77,D$3*12) -> 11063.283
A8: Net fixed assets | B8: =INDEX(Monthly!$C$67:$AL$67,B$3*12) -> 78782.757 | C8: =INDEX(Monthly!$C$67:$AL$67,C$3*12) -> 95739.823 | D8: =INDEX(Monthly!$C$67:$AL$67,D$3*12) -> 110697.6
A9: Total assets | B9: =INDEX(Monthly!$C$104:$AL$104,B$3*12) -> 471282.44 | C9: =INDEX(Monthly!$C$104:$AL$104,C$3*12) -> 726384.9 | D9: =INDEX(Monthly!$C$104:$AL$104,D$3*12) -> 1039755.2
A10: Accounts payable | B10: =INDEX(Monthly!$C$78:$AL$78,B$3*12) -> 19487.479 | C10: =INDEX(Monthly!$C$78:$AL$78,C$3*12) -> 21196.999 | D10: =INDEX(Monthly!$C$78:$AL$78,D$3*12) -> 23048.507
A11: Loan | B11: =INDEX(Monthly!$C$73:$AL$73,B$3*12) -> 130357.14 | C11: =INDEX(Monthly!$C$73:$AL$73,C$3*12) -> 108928.57 | D11: =INDEX(Monthly!$C$73:$AL$73,D$3*12) -> 87500
A12: Total liabilities | B12: =INDEX(Monthly!$C$105:$AL$105,B$3*12) -> 149844.62 | C12: =INDEX(Monthly!$C$105:$AL$105,C$3*12) -> 130125.57 | D12: =INDEX(Monthly!$C$105:$AL$105,D$3*12) -> 110548.51
A13: Paid-in capital | B13: =INDEX(Monthly!$C$102:$AL$102,B$3*12) -> 100000 | C13: =INDEX(Monthly!$C$102:$AL$102,C$3*12) -> 100000 | D13: =INDEX(Monthly!$C$102:$AL$102,D$3*12) -> 100000
A14: Retained earnings | B14: =INDEX(Monthly!$C$103:$AL$103,B$3*12) -> 221437.82 | C14: =INDEX(Monthly!$C$103:$AL$103,C$3*12) -> 496259.33 | D14: =INDEX(Monthly!$C$103:$AL$103,D$3*12) -> 829206.72
A15: Total equity | B15: =INDEX(Monthly!$C$106:$AL$106,B$3*12) -> 321437.82 | C15: =INDEX(Monthly!$C$106:$AL$106,C$3*12) -> 596259.33 | D15: =INDEX(Monthly!$C$106:$AL$106,D$3*12) -> 929206.72
A16: Total liabilities & equity | B16: =INDEX(Monthly!$C$107:$AL$107,B$3*12) -> 471282.44 | C16: =INDEX(Monthly!$C$107:$AL$107,C$3*12) -> 726384.9 | D16: =INDEX(Monthly!$C$107:$AL$107,D$3*12) -> 1039755.2
A17: Check: assets − liabilities − equity (must be 0) | B17: =INDEX(Monthly!$C$108:$AL$108,B$3*12) -> 0 | C17: =INDEX(Monthly!$C$108:$AL$108,C$3*12) -> 0 | D17: =INDEX(Monthly!$C$108:$AL$108,D$3*12) -> 0

Sheet Monthly
A1: Monthly projection | D1: =HYPERLINK("#'Cover'!A1","◂ Contents") -> ◂ Contents
A2: $ unless stated; costs shown as negatives. Every period uses the same formula.
A3: Month | C3: M1 | D3: M2 | E3: M3 | F3: M4 | G3: M5 | H3: M6 | I3: M7 | J3: M8 | K3: M9 | L3: M10 | M3: M11 | N3: M12 | O3: M13 | P3: M14 | Q3: M15 | R3: M16 | S3: M17 | T3: M18 | U3: M19 | V3: M20 | W3: M21 | X3: M22 | Y3: M23 | Z3: M24 | AA3: M25 | AB3: M26 | AC3: M27 | AD3: M28 | AE3: M29 | AF3: M30 | AG3: M31 | AH3: M32 | AI3: M33 | AJ3: M34 | AK3: M35 | AL3: M36
A4: Period # | C4: 1 | D4: 2 | E4: 3 | F4: 4 | G4: 5 | H4: 6 | I4: 7 | J4: 8 | K4: 9 | L4: 10 | M4: 11 | N4: 12 | O4: 13 | P4: 14 | Q4: 15 | R4: 16 | S4: 17 | T4: 18 | U4: 19 | V4: 20 | W4: 21 | X4: 22 | Y4: 23 | Z4: 24 | AA4: 25 | AB4: 26 | AC4: 27 | AD4: 28 | AE4: 29 | AF4: 30 | AG4: 31 | AH4: 32 | AI4: 33 | AJ4: 34 | AK4: 35 | AL4: 36
A5: Year # | C5: =ROUNDUP(C4*1/12,0) -> 1 | D5: =ROUNDUP(D4*1/12,0) -> 1 | E5: =ROUNDUP(E4*1/12,0) -> 1 | F5: =ROUNDUP(F4*1/12,0) -> 1 | G5: =ROUNDUP(G4*1/12,0) -> 1 | H5: =ROUNDUP(H4*1/12,0) -> 1 | I5: =ROUNDUP(I4*1/12,0) -> 1 | J5: =ROUNDUP(J4*1/12,0) -> 1 | ... AL5: =ROUNDUP(AL4*1/12,0) -> 3
A7: Patients
A8: New patients from marketing | C8: =-C43/MAX(1,Inputs!$E$19) -> 33.333333 | D8: =-D43/MAX(1,Inputs!$E$19) -> 33.333333 | E8: =-E43/MAX(1,Inputs!$E$19) -> 33.333333 | F8: =-F43/MAX(1,Inputs!$E$19) -> 33.333333 | G8: =-G43/MAX(1,Inputs!$E$19) -> 33.333333 | H8: =-H43/MAX(1,Inputs!$E$19) -> 33.333333 | I8: =-I43/MAX(1,Inputs!$E$19) -> 33.333333 | J8: =-J43/MAX(1,Inputs!$E$19) -> 33.333333 | ... AL8: =-AL43/MAX(1,Inputs!$E$19) -> 36.75
A9: New patients from referrals & walk-ins | C9: =Inputs!$E$15*(1+Inputs!$E$16)^(C$5-1)*1 -> 24 | D9: =Inputs!$E$15*(1+Inputs!$E$16)^(D$5-1)*1 -> 24 | E9: =Inputs!$E$15*(1+Inputs!$E$16)^(E$5-1)*1 -> 24 | F9: =Inputs!$E$15*(1+Inputs!$E$16)^(F$5-1)*1 -> 24 | G9: =Inputs!$E$15*(1+Inputs!$E$16)^(G$5-1)*1 -> 24 | H9: =Inputs!$E$15*(1+Inputs!$E$16)^(H$5-1)*1 -> 24 | I9: =Inputs!$E$15*(1+Inputs!$E$16)^(I$5-1)*1 -> 24 | J9: =Inputs!$E$15*(1+Inputs!$E$16)^(J$5-1)*1 -> 24 | ... AL9: =Inputs!$E$15*(1+Inputs!$E$16)^(AL$5-1)*1 -> 26.9664
A10: New patients — total | C10: =C8+C9 -> 57.333333 | D10: =D8+D9 -> 57.333333 | E10: =E8+E9 -> 57.333333 | F10: =F8+F9 -> 57.333333 | G10: =G8+G9 -> 57.333333 | H10: =H8+H9 -> 57.333333 | I10: =I8+I9 -> 57.333333 | J10: =J8+J9 -> 57.333333 | ... AL10: =AL8+AL9 -> 63.7164
A11: Active patients — opening | C11: =Inputs!$E$14 -> 3000 | D11: =C13 -> 3015.3333 | E11: =D13 -> 3030.452 | F11: =E13 -> 3045.359 | G11: =F13 -> 3060.0573 | H11: =G13 -> 3074.5498 | I11: =H13 -> 3088.8395 | J11: =I13 -> 3102.9291 | K11: =J13 -> 3116.8214 | ... AL11: =AK13 -> 3521.6623
A12: Patients lost | C12: =C13-C11-C10 -> -42 | D12: =D13-D11-D10 -> -42.214667 | E12: =E13-E11-E10 -> -42.426328 | F12: =F13-F11-F10 -> -42.635026 | G12: =G13-G11-G10 -> -42.840802 | H12: =H13-H11-H10 -> -43.043698 | I12: =I13-I11-I10 -> -43.243753 | J12: =J13-J11-J10 -> -43.441007 | ... AL12: =AL13-AL11-AL10 -> -49.303273
A13: Active patients — closing | C13: =C11*(1-Inputs!$E$20)+C10 -> 3015.3333 | D13: =D11*(1-Inputs!$E$20)+D10 -> 3030.452 | E13: =E11*(1-Inputs!$E$20)+E10 -> 3045.359 | F13: =F11*(1-Inputs!$E$20)+F10 -> 3060.0573 | G13: =G11*(1-Inputs!$E$20)+G10 -> 3074.5498 | H13: =H11*(1-Inputs!$E$20)+H10 -> 3088.8395 | I13: =I11*(1-Inputs!$E$20)+I10 -> 3102.9291 | J13: =J11*(1-Inputs!$E$20)+J10 -> 3116.8214 | ... AL13: =AL11*(1-Inputs!$E$20)+AL10 -> 3536.0755
A14: Active patients — average | C14: =(C11+C13)/2 -> 3007.6667 | D14: =(D11+D13)/2 -> 3022.8927 | E14: =(E11+E13)/2 -> 3037.9055 | F14: =(F11+F13)/2 -> 3052.7082 | G14: =(G11+G13)/2 -> 3067.3036 | H14: =(H11+H13)/2 -> 3081.6947 | I14: =(I11+I13)/2 -> 3095.8843 | J14: =(J11+J13)/2 -> 3109.8752 | ... AL14: =(AL11+AL13)/2 -> 3528.8689
A16: Visits
A17: Doctor visit capacity (operatories × visits per chair-day × working days) | C17: =Inputs!$E$7*Inputs!$E$9*Inputs!$E$11*1 -> 432 | D17: =Inputs!$E$7*Inputs!$E$9*Inputs!$E$11*1 -> 432 | E17: =Inputs!$E$7*Inputs!$E$9*Inputs!$E$11*1 -> 432 | F17: =Inputs!$E$7*Inputs!$E$9*Inputs!$E$11*1 -> 432 | G17: =Inputs!$E$7*Inputs!$E$9*Inputs!$E$11*1 -> 432 | H17: =Inputs!$E$7*Inputs!$E$9*Inputs!$E$11*1 -> 432 | I17: =Inputs!$E$7*Inputs!$E$9*Inputs!$E$11*1 -> 432 | J17: =Inputs!$E$7*Inputs!$E$9*Inputs!$E$11*1 -> 432 | ... AL17: =Inputs!$E$7*Inputs!$E$9*Inputs!$E$11*1 -> 432
A18: Doctor visits demanded | C18: =C14*Inputs!$E$21/12*1+C10*Inputs!$E$23 -> 345.56806 | D18: =D14*Inputs!$E$21/12*1+D10*Inputs!$E$23 -> 347.02721 | E18: =E14*Inputs!$E$21/12*1+E10*Inputs!$E$23 -> 348.46594 | F18: =F14*Inputs!$E$21/12*1+F10*Inputs!$E$23 -> 349.88453 | G18: =G14*Inputs!$E$21/12*1+G10*Inputs!$E$23 -> 351.28326 | H18: =H14*Inputs!$E$21/12*1+H10*Inputs!$E$23 -> 352.66241 | I18: =I14*Inputs!$E$21/12*1+I10*Inputs!$E$23 -> 354.02224 | J18: =J14*Inputs!$E$21/12*1+J10*Inputs!$E$23 -> 355.36304 | ... AL18: =AL14*Inputs!$E$21/12*1+AL10*Inputs!$E$23 -> 401.89967
A19: Doctor visits (demand capped by chairs) | C19: =MIN(C17,C18) -> 345.56806 | D19: =MIN(D17,D18) -> 347.02721 | E19: =MIN(E17,E18) -> 348.46594 | F19: =MIN(F17,F18) -> 349.88453 | G19: =MIN(G17,G18) -> 351.28326 | H19: =MIN(H17,H18) -> 352.66241 | I19: =MIN(I17,I18) -> 354.02224 | J19: =MIN(J17,J18) -> 355.36304 | ... AL19: =MIN(AL17,AL18) -> 401.89967
A20: Hygienists (FTE) | C20: =Headcount!C9 -> 3 | D20: =Headcount!D9 -> 3 | E20: =Headcount!E9 -> 3 | F20: =Headcount!F9 -> 3 | G20: =Headcount!G9 -> 3 | H20: =Headcount!H9 -> 3 | I20: =Headcount!I9 -> 3 | J20: =Headcount!J9 -> 3 | ... AL20: =Headcount!AL9 -> 3.3708
A21: Hygiene visit capacity (hygienists, up to hygiene rooms, × visits per day × working days) | C21: =MIN(C20,Inputs!$E$8)*Inputs!$E$10*Inputs!$E$11*1 -> 432 | D21: =MIN(D20,Inputs!$E$8)*Inputs!$E$10*Inputs!$E$11*1 -> 432 | E21: =MIN(E20,Inputs!$E$8)*Inputs!$E$10*Inputs!$E$11*1 -> 432 | F21: =MIN(F20,Inputs!$E$8)*Inputs!$E$10*Inputs!$E$11*1 -> 432 | G21: =MIN(G20,Inputs!$E$8)*Inputs!$E$10*Inputs!$E$11*1 -> 432 | H21: =MIN(H20,Inputs!$E$8)*Inputs!$E$10*Inputs!$E$11*1 -> 432 | I21: =MIN(I20,Inputs!$E$8)*Inputs!$E$10*Inputs!$E$11*1 -> 432 | J21: =MIN(J20,Inputs!$E$8)*Inputs!$E$10*Inputs!$E$11*1 -> 432 | ... AL21: =MIN(AL20,Inputs!$E$8)*Inputs!$E$10*Inputs!$E$11*1 -> 485.3952
A22: Hygiene recall visits demanded | C22: =C14*Inputs!$E$22/12*1 -> 375.95833 | D22: =D14*Inputs!$E$22/12*1 -> 377.86158 | E22: =E14*Inputs!$E$22/12*1 -> 379.73819 | F22: =F14*Inputs!$E$22/12*1 -> 381.58852 | G22: =G14*Inputs!$E$22/12*1 -> 383.41295 | H22: =H14*Inputs!$E$22/12*1 -> 385.21183 | I22: =I14*Inputs!$E$22/12*1 -> 386.98553 | J22: =J14*Inputs!$E$22/12*1 -> 388.7344 | ... AL22: =AL14*Inputs!$E$22/12*1 -> 441.10861
A23: Hygiene visits (demand capped by hygienists) | C23: =MIN(C21,C22) -> 375.95833 | D23: =MIN(D21,D22) -> 377.86158 | E23: =MIN(E21,E22) -> 379.73819 | F23: =MIN(F21,F22) -> 381.58852 | G23: =MIN(G21,G22) -> 383.41295 | H23: =MIN(H21,H22) -> 385.21183 | I23: =MIN(I21,I22) -> 386.98553 | J23: =MIN(J21,J22) -> 388.7344 | ... AL23: =MIN(AL21,AL22) -> 441.10861
A25: Production & collections
A26: Doctor production (office fees) | C26: =C19*Inputs!$E$26*(1+Inputs!$E$28)^(C$5-1) -> 114037.46 | D26: =D19*Inputs!$E$26*(1+Inputs!$E$28)^(D$5-1) -> 114518.98 | E26: =E19*Inputs!$E$26*(1+Inputs!$E$28)^(E$5-1) -> 114993.76 | F26: =F19*Inputs!$E$26*(1+Inputs!$E$28)^(F$5-1) -> 115461.9 | G26: =G19*Inputs!$E$26*(1+Inputs!$E$28)^(G$5-1) -> 115923.48 | H26: =H19*Inputs!$E$26*(1+Inputs!$E$28)^(H$5-1) -> 116378.59 | I26: =I19*Inputs!$E$26*(1+Inputs!$E$28)^(I$5-1) -> 116827.34 | J26: =J19*Inputs!$E$26*(1+Inputs!$E$28)^(J$5-1) -> 117269.8 | ... AL26: =AL19*Inputs!$E$26*(1+Inputs!$E$28)^(AL$5-1) -> 140703.87
A27: Hygiene production (office fees) | C27: =C23*Inputs!$E$27*(1+Inputs!$E$28)^(C$5-1) -> 75191.667 | D27: =D23*Inputs!$E$27*(1+Inputs!$E$28)^(D$5-1) -> 75572.317 | E27: =E23*Inputs!$E$27*(1+Inputs!$E$28)^(E$5-1) -> 75947.638 | F27: =F23*Inputs!$E$27*(1+Inputs!$E$28)^(F$5-1) -> 76317.704 | G27: =G23*Inputs!$E$27*(1+Inputs!$E$28)^(G$5-1) -> 76682.589 | H27: =H23*Inputs!$E$27*(1+Inputs!$E$28)^(H$5-1) -> 77042.367 | I27: =I23*Inputs!$E$27*(1+Inputs!$E$28)^(I$5-1) -> 77397.107 | J27: =J23*Inputs!$E$27*(1+Inputs!$E$28)^(J$5-1) -> 77746.881 | ... AL27: =AL23*Inputs!$E$27*(1+Inputs!$E$28)^(AL$5-1) -> 93594.425
A28: Gross production | C28: =C26+C27 -> 189229.12 | D28: =D26+D27 -> 190091.3 | E28: =E26+E27 -> 190941.4 | F28: =F26+F27 -> 191779.6 | G28: =G26+G27 -> 192606.07 | H28: =H26+H27 -> 193420.96 | I28: =I26+I27 -> 194224.45 | J28: =J26+J27 -> 195016.68 | ... AL28: =AL26+AL27 -> 234298.29
A29: PPO fee-schedule write-offs | C29: =-C28*Inputs!$E$31*Inputs!$E$32 -> -26019.005 | D29: =-D28*Inputs!$E$31*Inputs!$E$32 -> -26137.553 | E29: =-E28*Inputs!$E$31*Inputs!$E$32 -> -26254.442 | F29: =-F28*Inputs!$E$31*Inputs!$E$32 -> -26369.695 | G29: =-G28*Inputs!$E$31*Inputs!$E$32 -> -26483.334 | H29: =-H28*Inputs!$E$31*Inputs!$E$32 -> -26595.382 | I29: =-I28*Inputs!$E$31*Inputs!$E$32 -> -26705.861 | J29: =-J28*Inputs!$E$31*Inputs!$E$32 -> -26814.794 | ... AL29: =-AL28*Inputs!$E$31*Inputs!$E$32 -> -32216.015
A30: Bad debt (never collected) | C30: =-(C28+C29)*Inputs!$E$33 -> -2448.1518 | D30: =-(D28+D29)*Inputs!$E$33 -> -2459.3062 | E30: =-(E28+E29)*Inputs!$E$33 -> -2470.3044 | F30: =-(F28+F29)*Inputs!$E$33 -> -2481.1486 | G30: =-(G28+G29)*Inputs!$E$33 -> -2491.841 | H30: =-(H28+H29)*Inputs!$E$33 -> -2502.3837 | I30: =-(I28+I29)*Inputs!$E$33 -> -2512.7788 | J30: =-(J28+J29)*Inputs!$E$33 -> -2523.0284 | ... AL30: =-(AL28+AL29)*Inputs!$E$33 -> -3031.2342
A31: Collections (revenue) | C31: =C28+C29+C30 -> 160761.97 | D31: =D28+D29+D30 -> 161494.44 | E31: =E28+E29+E30 -> 162216.65 | F31: =F28+F29+F30 -> 162928.76 | G31: =G28+G29+G30 -> 163630.89 | H31: =H28+H29+H30 -> 164323.19 | I31: =I28+I29+I30 -> 165005.81 | J31: =J28+J29+J30 -> 165678.86 | ... AL31: =AL28+AL29+AL30 -> 199051.04
A33: Cost of sales
A34: Dental supplies | C34: =-C28*Inputs!$E$36 -> -9272.2271 | D34: =-D28*Inputs!$E$36 -> -9314.4736 | E34: =-E28*Inputs!$E$36 -> -9356.1286 | F34: =-F28*Inputs!$E$36 -> -9397.2004 | G34: =-G28*Inputs!$E$36 -> -9437.6972 | H34: =-H28*Inputs!$E$36 -> -9477.627 | I34: =-I28*Inputs!$E$36 -> -9516.9979 | J34: =-J28*Inputs!$E$36 -> -9555.8175 | ... AL34: =-AL28*Inputs!$E$36 -> -11480.616
A35: Lab fees | C35: =-C26*Inputs!$E$37 -> -11175.671 | D35: =-D26*Inputs!$E$37 -> -11222.86 | E35: =-E26*Inputs!$E$37 -> -11269.389 | F35: =-F26*Inputs!$E$37 -> -11315.266 | G35: =-G26*Inputs!$E$37 -> -11360.501 | H35: =-H26*Inputs!$E$37 -> -11405.102 | I35: =-I26*Inputs!$E$37 -> -11449.079 | J35: =-J26*Inputs!$E$37 -> -11492.441 | ... AL35: =-AL26*Inputs!$E$37 -> -13788.979
A36: Card & payment processing | C36: =-C31*Inputs!$E$38 -> -1929.1436 | D36: =-D31*Inputs!$E$38 -> -1937.9333 | E36: =-E31*Inputs!$E$38 -> -1946.5998 | F36: =-F31*Inputs!$E$38 -> -1955.1451 | G36: =-G31*Inputs!$E$38 -> -1963.5707 | H36: =-H31*Inputs!$E$38 -> -1971.8783 | I36: =-I31*Inputs!$E$38 -> -1980.0697 | J36: =-J31*Inputs!$E$38 -> -1988.1463 | ... AL36: =-AL31*Inputs!$E$38 -> -2388.6125
A37: Cost of sales | C37: =C34+C35+C36 -> -22377.042 | D37: =D34+D35+D36 -> -22475.267 | E37: =E34+E35+E36 -> -22572.117 | F37: =F34+F35+F36 -> -22667.611 | G37: =G34+G35+G36 -> -22761.768 | H37: =H34+H35+H36 -> -22854.608 | I37: =I34+I35+I36 -> -22946.147 | J37: =J34+J35+J36 -> -23036.405 | ... AL37: =AL34+AL35+AL36 -> -27658.208
A38: Gross profit | C38: =C31+C37 -> 138384.93 | D38: =D31+D37 -> 139019.17 | E38: =E31+E37 -> 139644.54 | F38: =F31+F37 -> 140261.14 | G38: =G31+G37 -> 140869.12 | H38: =H31+H37 -> 141468.59 | I38: =I31+I37 -> 142059.66 | J38: =J31+J37 -> 142642.46 | ... AL38: =AL31+AL37 -> 171392.84
A40: Operating expenses
A41: Staff payroll (owner dentist, hygienists, assistants, front desk, office manager) | C41: =Headcount!C21 -> -78970.833 | D41: =Headcount!D21 -> -78970.833 | E41: =Headcount!E21 -> -78970.833 | F41: =Headcount!F21 -> -78970.833 | G41: =Headcount!G21 -> -78970.833 | H41: =Headcount!H21 -> -78970.833 | I41: =Headcount!I21 -> -78970.833 | J41: =Headcount!J21 -> -78970.833 | ... AL41: =Headcount!AL21 -> -89824.932
A42: Associate dentists (% of the collections they produce) | C42: =-C31*C26/MAX(1,C28)*Inputs!$E$39*Inputs!$E$40 -> -11625.834 | D42: =-D31*D26/MAX(1,D28)*Inputs!$E$39*Inputs!$E$40 -> -11674.924 | E42: =-E31*E26/MAX(1,E28)*Inputs!$E$39*Inputs!$E$40 -> -11723.327 | F42: =-F31*F26/MAX(1,F28)*Inputs!$E$39*Inputs!$E$40 -> -11771.052 | G42: =-G31*G26/MAX(1,G28)*Inputs!$E$39*Inputs!$E$40 -> -11818.109 | H42: =-H31*H26/MAX(1,H28)*Inputs!$E$39*Inputs!$E$40 -> -11864.507 | I42: =-I31*I26/MAX(1,I28)*Inputs!$E$39*Inputs!$E$40 -> -11910.255 | J42: =-J31*J26/MAX(1,J28)*Inputs!$E$39*Inputs!$E$40 -> -11955.363 | ... AL42: =-AL31*AL26/MAX(1,AL28)*Inputs!$E$39*Inputs!$E$40 -> -14344.408
A43: Marketing | C43: =-Inputs!$E$17*(1+Inputs!$E$18)^(C$5-1)*1 -> -7000 | D43: =-Inputs!$E$17*(1+Inputs!$E$18)^(D$5-1)*1 -> -7000 | E43: =-Inputs!$E$17*(1+Inputs!$E$18)^(E$5-1)*1 -> -7000 | F43: =-Inputs!$E$17*(1+Inputs!$E$18)^(F$5-1)*1 -> -7000 | G43: =-Inputs!$E$17*(1+Inputs!$E$18)^(G$5-1)*1 -> -7000 | H43: =-Inputs!$E$17*(1+Inputs!$E$18)^(H$5-1)*1 -> -7000 | I43: =-Inputs!$E$17*(1+Inputs!$E$18)^(I$5-1)*1 -> -7000 | J43: =-Inputs!$E$17*(1+Inputs!$E$18)^(J$5-1)*1 -> -7000 | ... AL43: =-Inputs!$E$17*(1+Inputs!$E$18)^(AL$5-1)*1 -> -7717.5
A44: Rent | C44: =-Inputs!$E$48*Inputs!$E$49/12*1 -> -10000 | D44: =-Inputs!$E$48*Inputs!$E$49/12*1 -> -10000 | E44: =-Inputs!$E$48*Inputs!$E$49/12*1 -> -10000 | F44: =-Inputs!$E$48*Inputs!$E$49/12*1 -> -10000 | G44: =-Inputs!$E$48*Inputs!$E$49/12*1 -> -10000 | H44: =-Inputs!$E$48*Inputs!$E$49/12*1 -> -10000 | I44: =-Inputs!$E$48*Inputs!$E$49/12*1 -> -10000 | J44: =-Inputs!$E$48*Inputs!$E$49/12*1 -> -10000 | ... AL44: =-Inputs!$E$48*Inputs!$E$49/12*1 -> -10000
A45: Utilities & phone | C45: =-Inputs!$E$41*1 -> -1800 | D45: =-Inputs!$E$41*1 -> -1800 | E45: =-Inputs!$E$41*1 -> -1800 | F45: =-Inputs!$E$41*1 -> -1800 | G45: =-Inputs!$E$41*1 -> -1800 | H45: =-Inputs!$E$41*1 -> -1800 | I45: =-Inputs!$E$41*1 -> -1800 | J45: =-Inputs!$E$41*1 -> -1800 | ... AL45: =-Inputs!$E$41*1 -> -1800
A46: Practice software & IT | C46: =-Inputs!$E$42*1 -> -1300 | D46: =-Inputs!$E$42*1 -> -1300 | E46: =-Inputs!$E$42*1 -> -1300 | F46: =-Inputs!$E$42*1 -> -1300 | G46: =-Inputs!$E$42*1 -> -1300 | H46: =-Inputs!$E$42*1 -> -1300 | I46: =-Inputs!$E$42*1 -> -1300 | J46: =-Inputs!$E$42*1 -> -1300 | ... AL46: =-Inputs!$E$42*1 -> -1300
A47: Malpractice & liability insurance | C47: =-Inputs!$E$43*1 -> -1100 | D47: =-Inputs!$E$43*1 -> -1100 | E47: =-Inputs!$E$43*1 -> -1100 | F47: =-Inputs!$E$43*1 -> -1100 | G47: =-Inputs!$E$43*1 -> -1100 | H47: =-Inputs!$E$43*1 -> -1100 | I47: =-Inputs!$E$43*1 -> -1100 | J47: =-Inputs!$E$43*1 -> -1100 | ... AL47: =-Inputs!$E$43*1 -> -1100
A48: Equipment maintenance, cleaning & compliance | C48: =-Inputs!$E$44*1 -> -1400 | D48: =-Inputs!$E$44*1 -> -1400 | E48: =-Inputs!$E$44*1 -> -1400 | F48: =-Inputs!$E$44*1 -> -1400 | G48: =-Inputs!$E$44*1 -> -1400 | H48: =-Inputs!$E$44*1 -> -1400 | I48: =-Inputs!$E$44*1 -> -1400 | J48: =-Inputs!$E$44*1 -> -1400 | ... AL48: =-Inputs!$E$44*1 -> -1400
A49: Other G&A | C49: =-Inputs!$E$45*1 -> -3000 | D49: =-Inputs!$E$45*1 -> -3000 | E49: =-Inputs!$E$45*1 -> -3000 | F49: =-Inputs!$E$45*1 -> -3000 | G49: =-Inputs!$E$45*1 -> -3000 | H49: =-Inputs!$E$45*1 -> -3000 | I49: =-Inputs!$E$45*1 -> -3000 | J49: =-Inputs!$E$45*1 -> -3000 | ... AL49: =-Inputs!$E$45*1 -> -3000
A50: Total operating expenses | C50: =C41+C42+C43+C44+C45+C46+C47+C48+C49 -> -116196.67 | D50: =D41+D42+D43+D44+D45+D46+D47+D48+D49 -> -116245.76 | E50: =E41+E42+E43+E44+E45+E46+E47+E48+E49 -> -116294.16 | F50: =F41+F42+F43+F44+F45+F46+F47+F48+F49 -> -116341.88 | G50: =G41+G42+G43+G44+G45+G46+G47+G48+G49 -> -116388.94 | H50: =H41+H42+H43+H44+H45+H46+H47+H48+H49 -> -116435.34 | I50: =I41+I42+I43+I44+I45+I46+I47+I48+I49 -> -116481.09 | J50: =J41+J42+J43+J44+J45+J46+J47+J48+J49 -> -116526.2 | ... AL50: =AL41+AL42+AL43+AL44+AL45+AL46+AL47+AL48+AL49 -> -130486.84
A51: EBITDA | C51: =C38+C50 -> 22188.26 | D51: =D38+D50 -> 22773.414 | E51: =E38+E50 -> 23350.376 | F51: =F38+F50 -> 23919.26 | G51: =G38+G50 -> 24480.18 | H51: =H38+H50 -> 25033.247 | I51: =I38+I50 -> 25578.571 | J51: =J38+J50 -> 26116.261 | ... AL51: =AL38+AL50 -> 40905.997
A53: Profit after depreciation, interest, tax
A54: EBIT | C54: =C51+C65 -> 21445.267 | D54: =D51+D65 -> 22001.582 | E54: =E51+E65 -> 22549.577 | F54: =F51+F65 -> 23089.367 | G54: =G51+G65 -> 23621.067 | H54: =H51+H65 -> 24144.791 | I54: =I51+I65 -> 24660.649 | J54: =J51+J65 -> 25168.753 | ... AL54: =AL51+AL65 -> 39037.825
A55: Interest on loan (average balance after drawdown) | C55: =-(C70+C71+C73)/2*Inputs!$E$85/12 -> -1062.5 | D55: =-(D70+D71+D73)/2*Inputs!$E$85/12 -> -1056.1756 | E55: =-(E70+E71+E73)/2*Inputs!$E$85/12 -> -1043.5268 | F55: =-(F70+F71+F73)/2*Inputs!$E$85/12 -> -1030.878 | G55: =-(G70+G71+G73)/2*Inputs!$E$85/12 -> -1018.2292 | H55: =-(H70+H71+H73)/2*Inputs!$E$85/12 -> -1005.5804 | I55: =-(I70+I71+I73)/2*Inputs!$E$85/12 -> -992.93155 | J55: =-(J70+J71+J73)/2*Inputs!$E$85/12 -> -980.28274 | ... AL55: =-(AL70+AL71+AL73)/2*Inputs!$E$85/12 -> -626.11607
A56: Pre-tax income | C56: =C54+C55 -> 20382.767 | D56: =D54+D55 -> 20945.407 | E56: =E54+E55 -> 21506.05 | F56: =F54+F55 -> 22058.489 | G56: =G54+G55 -> 22602.838 | H56: =H54+H55 -> 23139.21 | I56: =I54+I55 -> 23667.718 | J56: =J54+J55 -> 24188.471 | ... AL56: =AL54+AL55 -> 38411.709
A57: Helper: cumulative pre-tax income | C57: =C56 -> 20382.767 | D57: =C57+D56 -> 41328.173 | E57: =D57+E56 -> 62834.223 | F57: =E57+F56 -> 84892.712 | G57: =F57+G56 -> 107495.55 | H57: =G57+H56 -> 130634.76 | I57: =H57+I56 -> 154302.48 | J57: =I57+J56 -> 178490.95 | K57: =J57+K56 -> 203192.53 | ... AL57: =AK57+AL56 -> 1049628.8
A58: Helper: cumulative taxable income (losses carried forward) | C58: =MAX(0,C57) -> 20382.767 | D58: =MAX(C58,D57) -> 41328.173 | E58: =MAX(D58,E57) -> 62834.223 | F58: =MAX(E58,F57) -> 84892.712 | G58: =MAX(F58,G57) -> 107495.55 | H58: =MAX(G58,H57) -> 130634.76 | I58: =MAX(H58,I57) -> 154302.48 | J58: =MAX(I58,J57) -> 178490.95 | K58: =MAX(J58,K57) -> 203192.53 | ... AL58: =MAX(AK58,AL57) -> 1049628.8
A59: Income tax | C59: =-C58*Inputs!$E$95 -> -4280.381 | D59: =-(D58-C58)*Inputs!$E$95 -> -4398.5354 | E59: =-(E58-D58)*Inputs!$E$95 -> -4516.2705 | F59: =-(F58-E58)*Inputs!$E$95 -> -4632.2826 | G59: =-(G58-F58)*Inputs!$E$95 -> -4746.5959 | H59: =-(H58-G58)*Inputs!$E$95 -> -4859.2341 | I59: =-(I58-H58)*Inputs!$E$95 -> -4970.2207 | J59: =-(J58-I58)*Inputs!$E$95 -> -5079.5788 | K59: =-(K58-J58)*Inputs!$E$95 -> -5187.3313 | ... AL59: =-(AL58-AK58)*Inputs!$E$95 -> -8066.4589
A60: Net income | C60: =C56+C59 -> 16102.386 | D60: =D56+D59 -> 16546.871 | E60: =E56+E59 -> 16989.779 | F60: =F56+F59 -> 17426.206 | G60: =G56+G59 -> 17856.242 | H60: =H56+H59 -> 18279.976 | I60: =I56+I59 -> 18697.497 | J60: =J56+J59 -> 19108.892 | ... AL60: =AL56+AL59 -> 30345.25
A62: Fixed assets & capital spending
A63: Capital spending (fit-out, operatories, imaging at start; then equipment refresh) | C63: =Inputs!$E$52*Inputs!$E$48+MAX(0,Inputs!$E$7+Inputs!$E$8-Inputs!$E$54)*Inputs!$E$53+Inputs!$E$55+C31*Inputs!$E$56 -> 62411.43 | D63: =D31*Inputs!$E$56 -> 2422.4166 | E63: =E31*Inputs!$E$56 -> 2433.2498 | F63: =F31*Inputs!$E$56 -> 2443.9313 | G63: =G31*Inputs!$E$56 -> 2454.4634 | H63: =H31*Inputs!$E$56 -> 2464.8479 | I63: =I31*Inputs!$E$56 -> 2475.0871 | J63: =J31*Inputs!$E$56 -> 2485.1829 | K63: =K31*Inputs!$E$56 -> 2495.1374 | ... AL63: =AL31*Inputs!$E$56 -> 2985.7657
A64: Fixed assets at cost | C64: =C63 -> 62411.43 | D64: =C64+D63 -> 64833.846 | E64: =D64+E63 -> 67267.096 | F64: =E64+F63 -> 69711.027 | G64: =F64+G63 -> 72165.491 | H64: =G64+H63 -> 74630.338 | I64: =H64+I63 -> 77105.426 | J64: =I64+J63 -> 79590.609 | K64: =J64+K63 -> 82085.746 | ... AL64: =AK64+AL63 -> 156926.44
A65: Depreciation | C65: =-MIN(C64/MAX(1,Inputs!$E$94*12),C63) -> -742.99321 | D65: =-MIN(D64/MAX(1,Inputs!$E$94*12),C67+D63) -> -771.8315 | E65: =-MIN(E64/MAX(1,Inputs!$E$94*12),D67+E63) -> -800.79876 | F65: =-MIN(F64/MAX(1,Inputs!$E$94*12),E67+F63) -> -829.89318 | G65: =-MIN(G64/MAX(1,Inputs!$E$94*12),F67+G63) -> -859.11298 | H65: =-MIN(H64/MAX(1,Inputs!$E$94*12),G67+H63) -> -888.45641 | I65: =-MIN(I64/MAX(1,Inputs!$E$94*12),H67+I63) -> -917.92173 | J65: =-MIN(J64/MAX(1,Inputs!$E$94*12),I67+J63) -> -947.50724 | K65: =-MIN(K64/MAX(1,Inputs!$E$94*12),J67+K63) -> -977.21126 | ... AL65: =-MIN(AL64/MAX(1,Inputs!$E$94*12),AK67+AL63) -> -1868.1719
A66: Accumulated depreciation | C66: =C65 -> -742.99321 | D66: =C66+D65 -> -1514.8247 | E66: =D66+E65 -> -2315.6235 | F66: =E66+F65 -> -3145.5167 | G66: =F66+G65 -> -4004.6296 | H66: =G66+H65 -> -4893.086 | I66: =H66+I65 -> -5811.0078 | J66: =I66+J65 -> -6758.515 | K66: =J66+K65 -> -7735.7263 | ... AL66: =AK66+AL65 -> -46228.837
A67: Net fixed assets | C67: =C64+C66 -> 61668.436 | D67: =D64+D66 -> 63319.021 | E67: =E64+E66 -> 64951.472 | F67: =F64+F66 -> 66565.511 | G67: =G64+G66 -> 68160.861 | H67: =H64+H66 -> 69737.252 | I67: =I64+I66 -> 71294.418 | J67: =J64+J66 -> 72832.093 | ... AL67: =AL64+AL66 -> 110697.6
A69: Debt
A70: Loan — opening balance | C70: =0 -> 0 | D70: =C73 -> 150000 | E70: =D73 -> 148214.29 | F70: =E73 -> 146428.57 | G70: =F73 -> 144642.86 | H70: =G73 -> 142857.14 | I70: =H73 -> 141071.43 | J70: =I73 -> 139285.71 | K70: =J73 -> 137500 | ... AL70: =AK73 -> 89285.714
A71: Loan drawdown | C71: =IF(C$4=1,Inputs!$E$84,0) -> 150000 | D71: =IF(D$4=1,Inputs!$E$84,0) -> 0 | E71: =IF(E$4=1,Inputs!$E$84,0) -> 0 | F71: =IF(F$4=1,Inputs!$E$84,0) -> 0 | G71: =IF(G$4=1,Inputs!$E$84,0) -> 0 | H71: =IF(H$4=1,Inputs!$E$84,0) -> 0 | I71: =IF(I$4=1,Inputs!$E$84,0) -> 0 | J71: =IF(J$4=1,Inputs!$E$84,0) -> 0 | ... AL71: =IF(AL$4=1,Inputs!$E$84,0) -> 0
A72: Loan repayment | C72: =-MIN(C70,Inputs!$E$84/MAX(1,Inputs!$E$86*12)) -> 0 | D72: =-MIN(D70,Inputs!$E$84/MAX(1,Inputs!$E$86*12)) -> -1785.7143 | E72: =-MIN(E70,Inputs!$E$84/MAX(1,Inputs!$E$86*12)) -> -1785.7143 | F72: =-MIN(F70,Inputs!$E$84/MAX(1,Inputs!$E$86*12)) -> -1785.7143 | G72: =-MIN(G70,Inputs!$E$84/MAX(1,Inputs!$E$86*12)) -> -1785.7143 | H72: =-MIN(H70,Inputs!$E$84/MAX(1,Inputs!$E$86*12)) -> -1785.7143 | I72: =-MIN(I70,Inputs!$E$84/MAX(1,Inputs!$E$86*12)) -> -1785.7143 | J72: =-MIN(J70,Inputs!$E$84/MAX(1,Inputs!$E$86*12)) -> -1785.7143 | ... AL72: =-MIN(AL70,Inputs!$E$84/MAX(1,Inputs!$E$86*12)) -> -1785.7143
A73: Loan — closing balance | C73: =C70+C71+C72 -> 150000 | D73: =D70+D71+D72 -> 148214.29 | E73: =E70+E71+E72 -> 146428.57 | F73: =F70+F71+F72 -> 144642.86 | G73: =G70+G71+G72 -> 142857.14 | H73: =H70+H71+H72 -> 141071.43 | I73: =I70+I71+I72 -> 139285.71 | J73: =J70+J71+J72 -> 137500 | ... AL73: =AL70+AL71+AL72 -> 87500
A75: Working capital
A76: Accounts receivable | C76: =C31*Inputs!$E$89/30 -> 91098.449 | D76: =D31*Inputs!$E$89/30 -> 91513.515 | E76: =E31*Inputs!$E$89/30 -> 91922.77 | F76: =F31*Inputs!$E$89/30 -> 92326.295 | G76: =G31*Inputs!$E$89/30 -> 92724.171 | H76: =H31*Inputs!$E$89/30 -> 93116.477 | I76: =I31*Inputs!$E$89/30 -> 93503.29 | J76: =J31*Inputs!$E$89/30 -> 93884.688 | ... AL76: =AL31*Inputs!$E$89/30 -> 112795.59
A77: Inventory | C77: =-C37*Inputs!$E$90/30 -> 8950.8167 | D77: =-D37*Inputs!$E$90/30 -> 8990.1068 | E77: =-E37*Inputs!$E$90/30 -> 9028.8468 | F77: =-F37*Inputs!$E$90/30 -> 9067.0445 | G77: =-G37*Inputs!$E$90/30 -> 9104.7074 | H77: =-H37*Inputs!$E$90/30 -> 9141.843 | I77: =-I37*Inputs!$E$90/30 -> 9178.4588 | J77: =-J37*Inputs!$E$90/30 -> 9214.5619 | ... AL77: =-AL37*Inputs!$E$90/30 -> 11063.283
A78: Accounts payable | C78: =-C37*Inputs!$E$91/30 -> 18647.535 | D78: =-D37*Inputs!$E$91/30 -> 18729.389 | E78: =-E37*Inputs!$E$91/30 -> 18810.098 | F78: =-F37*Inputs!$E$91/30 -> 18889.676 | G78: =-G37*Inputs!$E$91/30 -> 18968.14 | H78: =-H37*Inputs!$E$91/30 -> 19045.506 | I78: =-I37*Inputs!$E$91/30 -> 19121.789 | J78: =-J37*Inputs!$E$91/30 -> 19197.004 | ... AL78: =-AL37*Inputs!$E$91/30 -> 23048.507
A79: (Increase) / decrease in receivables | C79: =-C76 -> -91098.449 | D79: =C76-D76 -> -415.06589 | E79: =D76-E76 -> -409.25496 | F79: =E76-F76 -> -403.52539 | G79: =F76-G76 -> -397.87604 | H79: =G76-H76 -> -392.30577 | I79: =H76-I76 -> -386.81349 | J79: =I76-J76 -> -381.39811 | K79: =J76-K76 -> -376.05853 | ... AL79: =AK76-AL76 -> -419.79399
A80: (Increase) / decrease in inventory | C80: =-C77 -> -8950.8167 | D80: =C77-D77 -> -39.290101 | E80: =D77-E77 -> -38.740039 | F80: =E77-F77 -> -38.197679 | G80: =F77-G77 -> -37.662911 | H80: =G77-H77 -> -37.13563 | I80: =H77-I77 -> -36.615731 | J80: =I77-J77 -> -36.103111 | K80: =J77-K77 -> -35.597668 | ... AL80: =AK77-AL77 -> -39.737663
A81: Increase / (decrease) in payables | C81: =C78 -> 18647.535 | D81: =D78-C78 -> 81.854376 | E81: =E78-D78 -> 80.708415 | F81: =F78-E78 -> 79.578497 | G81: =G78-F78 -> 78.464398 | H81: =H78-G78 -> 77.365896 | I81: =I78-H78 -> 76.282774 | J81: =J78-I78 -> 75.214815 | K81: =K78-J78 -> 74.161808 | ... AL81: =AL78-AK78 -> 82.786797
A83: Cash flow
A84: Operating cash flow | C84: =C60-C65+C79+C80+C81 -> -64556.352 | D84: =D60-D65+D79+D80+D81 -> 16946.201 | E84: =E60-E65+E79+E80+E81 -> 17423.292 | F84: =F60-F65+F79+F80+F81 -> 17893.955 | G84: =G60-G65+G79+G80+G81 -> 18358.28 | H84: =H60-H65+H79+H80+H81 -> 18816.357 | I84: =I60-I65+I79+I80+I81 -> 19268.272 | J84: =J60-J65+J79+J80+J81 -> 19714.113 | ... AL84: =AL60-AL65+AL79+AL80+AL81 -> 31836.677
A85: Investing cash flow (capex) | C85: =-C63 -> -62411.43 | D85: =-D63 -> -2422.4166 | E85: =-E63 -> -2433.2498 | F85: =-F63 -> -2443.9313 | G85: =-G63 -> -2454.4634 | H85: =-H63 -> -2464.8479 | I85: =-I63 -> -2475.0871 | J85: =-J63 -> -2485.1829 | ... AL85: =-AL63 -> -2985.7657
A86: Equity raised | C86: =IF(C$4=1,Inputs!$E$83,0) -> 100000 | D86: =IF(D$4=1,Inputs!$E$83,0) -> 0 | E86: =IF(E$4=1,Inputs!$E$83,0) -> 0 | F86: =IF(F$4=1,Inputs!$E$83,0) -> 0 | G86: =IF(G$4=1,Inputs!$E$83,0) -> 0 | H86: =IF(H$4=1,Inputs!$E$83,0) -> 0 | I86: =IF(I$4=1,Inputs!$E$83,0) -> 0 | J86: =IF(J$4=1,Inputs!$E$83,0) -> 0 | ... AL86: =IF(AL$4=1,Inputs!$E$83,0) -> 0
A87: Financing cash flow | C87: =C86+C71+C72 -> 250000 | D87: =D86+D71+D72 -> -1785.7143 | E87: =E86+E71+E72 -> -1785.7143 | F87: =F86+F71+F72 -> -1785.7143 | G87: =G86+G71+G72 -> -1785.7143 | H87: =H86+H71+H72 -> -1785.7143 | I87: =I86+I71+I72 -> -1785.7143 | J87: =J86+J71+J72 -> -1785.7143 | ... AL87: =AL86+AL71+AL72 -> -1785.7143
A88: Net cash flow | C88: =C84+C85+C87 -> 123032.22 | D88: =D84+D85+D87 -> 12738.07 | E88: =E84+E85+E87 -> 13204.328 | F88: =F84+F85+F87 -> 13664.309 | G88: =G84+G85+G87 -> 14118.103 | H88: =H84+H85+H87 -> 14565.795 | I88: =I84+I85+I87 -> 15007.471 | J88: =J84+J85+J87 -> 15443.215 | ... AL88: =AL84+AL85+AL87 -> 27065.197
A89: Opening cash | C89: =0 -> 0 | D89: =C90 -> 123032.22 | E89: =D90 -> 135770.29 | F89: =E90 -> 148974.62 | G89: =F90 -> 162638.93 | H89: =G90 -> 176757.03 | I89: =H90 -> 191322.82 | J89: =I90 -> 206330.29 | K89: =J90 -> 221773.51 | ... AL89: =AK90 -> 778133.55
A90: Closing cash | C90: =C89+C88 -> 123032.22 | D90: =D89+D88 -> 135770.29 | E90: =E89+E88 -> 148974.62 | F90: =F89+F88 -> 162638.93 | G90: =G89+G88 -> 176757.03 | H90: =H89+H88 -> 191322.82 | I90: =I89+I88 -> 206330.29 | J90: =J89+J88 -> 221773.51 | ... AL90: =AL89+AL88 -> 805198.75
A91: Helper: EBITDA positive (1/0) | C91: =IF(C51>0,1,0) -> 1 | D91: =IF(D51>0,1,0) -> 1 | E91: =IF(E51>0,1,0) -> 1 | F91: =IF(F51>0,1,0) -> 1 | G91: =IF(G51>0,1,0) -> 1 | H91: =IF(H51>0,1,0) -> 1 | I91: =IF(I51>0,1,0) -> 1 | J91: =IF(J51>0,1,0) -> 1 | ... AL91: =IF(AL51>0,1,0) -> 1
A93: Goal modules
A94: Helper: net income positive (1/0) | C94: =IF(C60>0,1,0) -> 1 | D94: =IF(D60>0,1,0) -> 1 | E94: =IF(E60>0,1,0) -> 1 | F94: =IF(F60>0,1,0) -> 1 | G94: =IF(G60>0,1,0) -> 1 | H94: =IF(H60>0,1,0) -> 1 | I94: =IF(I60>0,1,0) -> 1 | J94: =IF(J60>0,1,0) -> 1 | ... AL94: =IF(AL60>0,1,0) -> 1
A95: Cash flow before financing (operating + investing) | C95: =C84+C85 -> -126967.78 | D95: =D84+D85 -> 14523.785 | E95: =E84+E85 -> 14990.042 | F95: =F84+F85 -> 15450.023 | G95: =G84+G85 -> 15903.817 | H95: =H84+H85 -> 16351.509 | I95: =I84+I85 -> 16793.185 | J95: =J84+J85 -> 17228.93 | ... AL95: =AL84+AL85 -> 28850.911
A96: Cumulative cash flow before financing | C96: =C95 -> -126967.78 | D96: =C96+D95 -> -112444 | E96: =D96+E95 -> -97453.955 | F96: =E96+F95 -> -82003.932 | G96: =F96+G95 -> -66100.115 | H96: =G96+H95 -> -49748.606 | I96: =H96+I95 -> -32955.421 | J96: =I96+J95 -> -15726.491 | K96: =J96+K95 -> 1932.3347 | ... AL96: =AK96+AL95 -> 617698.75
A97: Helper: lowest cumulative cash flow so far | C97: =C96 -> -126967.78 | D97: =MIN(C97,D96) -> -126967.78 | E97: =MIN(D97,E96) -> -126967.78 | F97: =MIN(E97,F96) -> -126967.78 | G97: =MIN(F97,G96) -> -126967.78 | H97: =MIN(G97,H96) -> -126967.78 | I97: =MIN(H97,I96) -> -126967.78 | J97: =MIN(I97,J96) -> -126967.78 | K97: =MIN(J97,K96) -> -126967.78 | ... AL97: =MIN(AK97,AL96) -> -126967.78
A98: Helper: investment paid back (1/0) | C98: =IF(AND(C96>=0,C97<0),1,0) -> 0 | D98: =IF(AND(D96>=0,D97<0),1,0) -> 0 | E98: =IF(AND(E96>=0,E97<0),1,0) -> 0 | F98: =IF(AND(F96>=0,F97<0),1,0) -> 0 | G98: =IF(AND(G96>=0,G97<0),1,0) -> 0 | H98: =IF(AND(H96>=0,H97<0),1,0) -> 0 | I98: =IF(AND(I96>=0,I97<0),1,0) -> 0 | J98: =IF(AND(J96>=0,J97<0),1,0) -> 0 | ... AL98: =IF(AND(AL96>=0,AL97<0),1,0) -> 1
A99: Unlevered free cash flow (operating + after-tax interest − capex) | C99: =C84-C55*(1-Inputs!$E$95)+C85 -> -126128.41 | D99: =D84-D55*(1-Inputs!$E$95)+D85 -> 15358.163 | E99: =E84-E55*(1-Inputs!$E$95)+E85 -> 15814.428 | F99: =F84-F55*(1-Inputs!$E$95)+F85 -> 16264.417 | G99: =G84-G55*(1-Inputs!$E$95)+G85 -> 16708.218 | H99: =H84-H55*(1-Inputs!$E$95)+H85 -> 17145.917 | I99: =I84-I55*(1-Inputs!$E$95)+I85 -> 17577.601 | J99: =J84-J55*(1-Inputs!$E$95)+J85 -> 18003.353 | ... AL99: =AL84-AL55*(1-Inputs!$E$95)+AL85 -> 29345.543
A101: Balance sheet
A102: Paid-in capital | C102: =C86 -> 100000 | D102: =C102+D86 -> 100000 | E102: =D102+E86 -> 100000 | F102: =E102+F86 -> 100000 | G102: =F102+G86 -> 100000 | H102: =G102+H86 -> 100000 | I102: =H102+I86 -> 100000 | J102: =I102+J86 -> 100000 | K102: =J102+K86 -> 100000 | ... AL102: =AK102+AL86 -> 100000
A103: Retained earnings | C103: =C60 -> 16102.386 | D103: =C103+D60 -> 32649.257 | E103: =D103+E60 -> 49639.036 | F103: =E103+F60 -> 67065.242 | G103: =F103+G60 -> 84921.484 | H103: =G103+H60 -> 103201.46 | I103: =H103+I60 -> 121898.96 | J103: =I103+J60 -> 141007.85 | K103: =J103+K60 -> 160522.1 | ... AL103: =AK103+AL60 -> 829206.72
A104: Total assets | C104: =C90+C76+C77+C67 -> 284749.92 | D104: =D90+D76+D77+D67 -> 299592.93 | E104: =E90+E76+E77+E67 -> 314877.71 | F104: =F90+F76+F77+F67 -> 330597.78 | G104: =G90+G76+G77+G67 -> 346746.77 | H104: =H90+H76+H77+H67 -> 363318.39 | I104: =I90+I76+I77+I67 -> 380306.46 | J104: =J90+J76+J77+J67 -> 397704.85 | ... AL104: =AL90+AL76+AL77+AL67 -> 1039755.2
A105: Total liabilities | C105: =C78+C73 -> 168647.53 | D105: =D78+D73 -> 166943.67 | E105: =E78+E73 -> 165238.67 | F105: =F78+F73 -> 163532.53 | G105: =G78+G73 -> 161825.28 | H105: =H78+H73 -> 160116.93 | I105: =I78+I73 -> 158407.5 | J105: =J78+J73 -> 156697 | ... AL105: =AL78+AL73 -> 110548.51
A106: Total equity | C106: =C102+C103 -> 116102.39 | D106: =D102+D103 -> 132649.26 | E106: =E102+E103 -> 149639.04 | F106: =F102+F103 -> 167065.24 | G106: =G102+G103 -> 184921.48 | H106: =H102+H103 -> 203201.46 | I106: =I102+I103 -> 221898.96 | J106: =J102+J103 -> 241007.85 | ... AL106: =AL102+AL103 -> 929206.72
A107: Total liabilities & equity | C107: =C105+C106 -> 284749.92 | D107: =D105+D106 -> 299592.93 | E107: =E105+E106 -> 314877.71 | F107: =F105+F106 -> 330597.78 | G107: =G105+G106 -> 346746.77 | H107: =H105+H106 -> 363318.39 | I107: =I105+I106 -> 380306.46 | J107: =J105+J106 -> 397704.85 | ... AL107: =AL105+AL106 -> 1039755.2
A108: Check: assets − liabilities − equity | C108: =C104-C107 -> 0 | D108: =D104-D107 -> 0 | E108: =E104-E107 -> 0 | F108: =F104-F107 -> 0 | G108: =G104-G107 -> 0 | H108: =H104-H107 -> 0 | I108: =I104-I107 -> 0 | J108: =J104-J107 -> 0 | ... AL108: =AL104-AL107 -> 0

Sheet Headcount
A1: Headcount & payroll | D1: =HYPERLINK("#'Cover'!A1","◂ Contents") -> ◂ Contents
A2: $ unless stated; costs shown as negatives. Every period uses the same formula.
A3: Month | C3: M1 | D3: M2 | E3: M3 | F3: M4 | G3: M5 | H3: M6 | I3: M7 | J3: M8 | K3: M9 | L3: M10 | M3: M11 | N3: M12 | O3: M13 | P3: M14 | Q3: M15 | R3: M16 | S3: M17 | T3: M18 | U3: M19 | V3: M20 | W3: M21 | X3: M22 | Y3: M23 | Z3: M24 | AA3: M25 | AB3: M26 | AC3: M27 | AD3: M28 | AE3: M29 | AF3: M30 | AG3: M31 | AH3: M32 | AI3: M33 | AJ3: M34 | AK3: M35 | AL3: M36
A4: Period # | C4: 1 | D4: 2 | E4: 3 | F4: 4 | G4: 5 | H4: 6 | I4: 7 | J4: 8 | K4: 9 | L4: 10 | M4: 11 | N4: 12 | O4: 13 | P4: 14 | Q4: 15 | R4: 16 | S4: 17 | T4: 18 | U4: 19 | V4: 20 | W4: 21 | X4: 22 | Y4: 23 | Z4: 24 | AA4: 25 | AB4: 26 | AC4: 27 | AD4: 28 | AE4: 29 | AF4: 30 | AG4: 31 | AH4: 32 | AI4: 33 | AJ4: 34 | AK4: 35 | AL4: 36
A5: Year # | C5: =ROUNDUP(C4*1/12,0) -> 1 | D5: =ROUNDUP(D4*1/12,0) -> 1 | E5: =ROUNDUP(E4*1/12,0) -> 1 | F5: =ROUNDUP(F4*1/12,0) -> 1 | G5: =ROUNDUP(G4*1/12,0) -> 1 | H5: =ROUNDUP(H4*1/12,0) -> 1 | I5: =ROUNDUP(I4*1/12,0) -> 1 | J5: =ROUNDUP(J4*1/12,0) -> 1 | ... AL5: =ROUNDUP(AL4*1/12,0) -> 3
A7: Headcount (FTE)
A8: Owner dentist — FTE | C8: =Inputs!$E$59*(1+Inputs!$E$61)^(C$5-1)*MAX(0,MIN(1,C$4*1-Inputs!$E$62+1))/1 -> 1 | D8: =Inputs!$E$59*(1+Inputs!$E$61)^(D$5-1)*MAX(0,MIN(1,D$4*1-Inputs!$E$62+1))/1 -> 1 | E8: =Inputs!$E$59*(1+Inputs!$E$61)^(E$5-1)*MAX(0,MIN(1,E$4*1-Inputs!$E$62+1))/1 -> 1 | F8: =Inputs!$E$59*(1+Inputs!$E$61)^(F$5-1)*MAX(0,MIN(1,F$4*1-Inputs!$E$62+1))/1 -> 1 | G8: =Inputs!$E$59*(1+Inputs!$E$61)^(G$5-1)*MAX(0,MIN(1,G$4*1-Inputs!$E$62+1))/1 -> 1 | H8: =Inputs!$E$59*(1+Inputs!$E$61)^(H$5-1)*MAX(0,MIN(1,H$4*1-Inputs!$E$62+1))/1 -> 1 | I8: =Inputs!$E$59*(1+Inputs!$E$61)^(I$5-1)*MAX(0,MIN(1,I$4*1-Inputs!$E$62+1))/1 -> 1 | J8: =Inputs!$E$59*(1+Inputs!$E$61)^(J$5-1)*MAX(0,MIN(1,J$4*1-Inputs!$E$62+1))/1 -> 1 | ... AL8: =Inputs!$E$59*(1+Inputs!$E$61)^(AL$5-1)*MAX(0,MIN(1,AL$4*1-Inputs!$E$62+1))/1 -> 1
A9: Hygienists — FTE | C9: =Inputs!$E$63*(1+Inputs!$E$65)^(C$5-1)*MAX(0,MIN(1,C$4*1-Inputs!$E$66+1))/1 -> 3 | D9: =Inputs!$E$63*(1+Inputs!$E$65)^(D$5-1)*MAX(0,MIN(1,D$4*1-Inputs!$E$66+1))/1 -> 3 | E9: =Inputs!$E$63*(1+Inputs!$E$65)^(E$5-1)*MAX(0,MIN(1,E$4*1-Inputs!$E$66+1))/1 -> 3 | F9: =Inputs!$E$63*(1+Inputs!$E$65)^(F$5-1)*MAX(0,MIN(1,F$4*1-Inputs!$E$66+1))/1 -> 3 | G9: =Inputs!$E$63*(1+Inputs!$E$65)^(G$5-1)*MAX(0,MIN(1,G$4*1-Inputs!$E$66+1))/1 -> 3 | H9: =Inputs!$E$63*(1+Inputs!$E$65)^(H$5-1)*MAX(0,MIN(1,H$4*1-Inputs!$E$66+1))/1 -> 3 | I9: =Inputs!$E$63*(1+Inputs!$E$65)^(I$5-1)*MAX(0,MIN(1,I$4*1-Inputs!$E$66+1))/1 -> 3 | J9: =Inputs!$E$63*(1+Inputs!$E$65)^(J$5-1)*MAX(0,MIN(1,J$4*1-Inputs!$E$66+1))/1 -> 3 | ... AL9: =Inputs!$E$63*(1+Inputs!$E$65)^(AL$5-1)*MAX(0,MIN(1,AL$4*1-Inputs!$E$66+1))/1 -> 3.3708
A10: Dental assistants — FTE | C10: =Inputs!$E$67*(1+Inputs!$E$69)^(C$5-1)*MAX(0,MIN(1,C$4*1-Inputs!$E$70+1))/1 -> 4.5 | D10: =Inputs!$E$67*(1+Inputs!$E$69)^(D$5-1)*MAX(0,MIN(1,D$4*1-Inputs!$E$70+1))/1 -> 4.5 | E10: =Inputs!$E$67*(1+Inputs!$E$69)^(E$5-1)*MAX(0,MIN(1,E$4*1-Inputs!$E$70+1))/1 -> 4.5 | F10: =Inputs!$E$67*(1+Inputs!$E$69)^(F$5-1)*MAX(0,MIN(1,F$4*1-Inputs!$E$70+1))/1 -> 4.5 | G10: =Inputs!$E$67*(1+Inputs!$E$69)^(G$5-1)*MAX(0,MIN(1,G$4*1-Inputs!$E$70+1))/1 -> 4.5 | H10: =Inputs!$E$67*(1+Inputs!$E$69)^(H$5-1)*MAX(0,MIN(1,H$4*1-Inputs!$E$70+1))/1 -> 4.5 | I10: =Inputs!$E$67*(1+Inputs!$E$69)^(I$5-1)*MAX(0,MIN(1,I$4*1-Inputs!$E$70+1))/1 -> 4.5 | J10: =Inputs!$E$67*(1+Inputs!$E$69)^(J$5-1)*MAX(0,MIN(1,J$4*1-Inputs!$E$70+1))/1 -> 4.5 | ... AL10: =Inputs!$E$67*(1+Inputs!$E$69)^(AL$5-1)*MAX(0,MIN(1,AL$4*1-Inputs!$E$70+1))/1 -> 4.8672
A11: Front desk — FTE | C11: =Inputs!$E$71*(1+Inputs!$E$73)^(C$5-1)*MAX(0,MIN(1,C$4*1-Inputs!$E$74+1))/1 -> 3 | D11: =Inputs!$E$71*(1+Inputs!$E$73)^(D$5-1)*MAX(0,MIN(1,D$4*1-Inputs!$E$74+1))/1 -> 3 | E11: =Inputs!$E$71*(1+Inputs!$E$73)^(E$5-1)*MAX(0,MIN(1,E$4*1-Inputs!$E$74+1))/1 -> 3 | F11: =Inputs!$E$71*(1+Inputs!$E$73)^(F$5-1)*MAX(0,MIN(1,F$4*1-Inputs!$E$74+1))/1 -> 3 | G11: =Inputs!$E$71*(1+Inputs!$E$73)^(G$5-1)*MAX(0,MIN(1,G$4*1-Inputs!$E$74+1))/1 -> 3 | H11: =Inputs!$E$71*(1+Inputs!$E$73)^(H$5-1)*MAX(0,MIN(1,H$4*1-Inputs!$E$74+1))/1 -> 3 | I11: =Inputs!$E$71*(1+Inputs!$E$73)^(I$5-1)*MAX(0,MIN(1,I$4*1-Inputs!$E$74+1))/1 -> 3 | J11: =Inputs!$E$71*(1+Inputs!$E$73)^(J$5-1)*MAX(0,MIN(1,J$4*1-Inputs!$E$74+1))/1 -> 3 | ... AL11: =Inputs!$E$71*(1+Inputs!$E$73)^(AL$5-1)*MAX(0,MIN(1,AL$4*1-Inputs!$E$74+1))/1 -> 3.2448
A12: Office manager — FTE | C12: =Inputs!$E$75*(1+Inputs!$E$77)^(C$5-1)*MAX(0,MIN(1,C$4*1-Inputs!$E$78+1))/1 -> 1 | D12: =Inputs!$E$75*(1+Inputs!$E$77)^(D$5-1)*MAX(0,MIN(1,D$4*1-Inputs!$E$78+1))/1 -> 1 | E12: =Inputs!$E$75*(1+Inputs!$E$77)^(E$5-1)*MAX(0,MIN(1,E$4*1-Inputs!$E$78+1))/1 -> 1 | F12: =Inputs!$E$75*(1+Inputs!$E$77)^(F$5-1)*MAX(0,MIN(1,F$4*1-Inputs!$E$78+1))/1 -> 1 | G12: =Inputs!$E$75*(1+Inputs!$E$77)^(G$5-1)*MAX(0,MIN(1,G$4*1-Inputs!$E$78+1))/1 -> 1 | H12: =Inputs!$E$75*(1+Inputs!$E$77)^(H$5-1)*MAX(0,MIN(1,H$4*1-Inputs!$E$78+1))/1 -> 1 | I12: =Inputs!$E$75*(1+Inputs!$E$77)^(I$5-1)*MAX(0,MIN(1,I$4*1-Inputs!$E$78+1))/1 -> 1 | J12: =Inputs!$E$75*(1+Inputs!$E$77)^(J$5-1)*MAX(0,MIN(1,J$4*1-Inputs!$E$78+1))/1 -> 1 | ... AL12: =Inputs!$E$75*(1+Inputs!$E$77)^(AL$5-1)*MAX(0,MIN(1,AL$4*1-Inputs!$E$78+1))/1 -> 1
A13: Total FTE | C13: =C8+C9+C10+C11+C12 -> 12.5 | D13: =D8+D9+D10+D11+D12 -> 12.5 | E13: =E8+E9+E10+E11+E12 -> 12.5 | F13: =F8+F9+F10+F11+F12 -> 12.5 | G13: =G8+G9+G10+G11+G12 -> 12.5 | H13: =H8+H9+H10+H11+H12 -> 12.5 | I13: =I8+I9+I10+I11+I12 -> 12.5 | J13: =J8+J9+J10+J11+J12 -> 12.5 | ... AL13: =AL8+AL9+AL10+AL11+AL12 -> 13.4828
A15: Payroll cost (salary + taxes & benefits)
A16: Owner dentist — payroll cost | C16: =-C8*Inputs!$E$60/12*1*(1+Inputs!$E$79)*(1+Inputs!$E$80)^(C$5-1) -> -16500 | D16: =-D8*Inputs!$E$60/12*1*(1+Inputs!$E$79)*(1+Inputs!$E$80)^(D$5-1) -> -16500 | E16: =-E8*Inputs!$E$60/12*1*(1+Inputs!$E$79)*(1+Inputs!$E$80)^(E$5-1) -> -16500 | F16: =-F8*Inputs!$E$60/12*1*(1+Inputs!$E$79)*(1+Inputs!$E$80)^(F$5-1) -> -16500 | G16: =-G8*Inputs!$E$60/12*1*(1+Inputs!$E$79)*(1+Inputs!$E$80)^(G$5-1) -> -16500 | H16: =-H8*Inputs!$E$60/12*1*(1+Inputs!$E$79)*(1+Inputs!$E$80)^(H$5-1) -> -16500 | I16: =-I8*Inputs!$E$60/12*1*(1+Inputs!$E$79)*(1+Inputs!$E$80)^(I$5-1) -> -16500 | J16: =-J8*Inputs!$E$60/12*1*(1+Inputs!$E$79)*(1+Inputs!$E$80)^(J$5-1) -> -16500 | ... AL16: =-AL8*Inputs!$E$60/12*1*(1+Inputs!$E$79)*(1+Inputs!$E$80)^(AL$5-1) -> -17504.85
A17: Hygienists — payroll cost | C17: =-C9*Inputs!$E$64/12*1*(1+Inputs!$E$79)*(1+Inputs!$E$80)^(C$5-1) -> -26400 | D17: =-D9*Inputs!$E$64/12*1*(1+Inputs!$E$79)*(1+Inputs!$E$80)^(D$5-1) -> -26400 | E17: =-E9*Inputs!$E$64/12*1*(1+Inputs!$E$79)*(1+Inputs!$E$80)^(E$5-1) -> -26400 | F17: =-F9*Inputs!$E$64/12*1*(1+Inputs!$E$79)*(1+Inputs!$E$80)^(F$5-1) -> -26400 | G17: =-G9*Inputs!$E$64/12*1*(1+Inputs!$E$79)*(1+Inputs!$E$80)^(G$5-1) -> -26400 | H17: =-H9*Inputs!$E$64/12*1*(1+Inputs!$E$79)*(1+Inputs!$E$80)^(H$5-1) -> -26400 | I17: =-I9*Inputs!$E$64/12*1*(1+Inputs!$E$79)*(1+Inputs!$E$80)^(I$5-1) -> -26400 | J17: =-J9*Inputs!$E$64/12*1*(1+Inputs!$E$79)*(1+Inputs!$E$80)^(J$5-1) -> -26400 | ... AL17: =-AL9*Inputs!$E$64/12*1*(1+Inputs!$E$79)*(1+Inputs!$E$80)^(AL$5-1) -> -31469.519
A18: Dental assistants — payroll cost | C18: =-C10*Inputs!$E$68/12*1*(1+Inputs!$E$79)*(1+Inputs!$E$80)^(C$5-1) -> -18562.5 | D18: =-D10*Inputs!$E$68/12*1*(1+Inputs!$E$79)*(1+Inputs!$E$80)^(D$5-1) -> -18562.5 | E18: =-E10*Inputs!$E$68/12*1*(1+Inputs!$E$79)*(1+Inputs!$E$80)^(E$5-1) -> -18562.5 | F18: =-F10*Inputs!$E$68/12*1*(1+Inputs!$E$79)*(1+Inputs!$E$80)^(F$5-1) -> -18562.5 | G18: =-G10*Inputs!$E$68/12*1*(1+Inputs!$E$79)*(1+Inputs!$E$80)^(G$5-1) -> -18562.5 | H18: =-H10*Inputs!$E$68/12*1*(1+Inputs!$E$79)*(1+Inputs!$E$80)^(H$5-1) -> -18562.5 | I18: =-I10*Inputs!$E$68/12*1*(1+Inputs!$E$79)*(1+Inputs!$E$80)^(I$5-1) -> -18562.5 | J18: =-J10*Inputs!$E$68/12*1*(1+Inputs!$E$79)*(1+Inputs!$E$80)^(J$5-1) -> -18562.5 | ... AL18: =-AL10*Inputs!$E$68/12*1*(1+Inputs!$E$79)*(1+Inputs!$E$80)^(AL$5-1) -> -21299.901
A19: Front desk — payroll cost | C19: =-C11*Inputs!$E$72/12*1*(1+Inputs!$E$79)*(1+Inputs!$E$80)^(C$5-1) -> -11275 | D19: =-D11*Inputs!$E$72/12*1*(1+Inputs!$E$79)*(1+Inputs!$E$80)^(D$5-1) -> -11275 | E19: =-E11*Inputs!$E$72/12*1*(1+Inputs!$E$79)*(1+Inputs!$E$80)^(E$5-1) -> -11275 | F19: =-F11*Inputs!$E$72/12*1*(1+Inputs!$E$79)*(1+Inputs!$E$80)^(F$5-1) -> -11275 | G19: =-G11*Inputs!$E$72/12*1*(1+Inputs!$E$79)*(1+Inputs!$E$80)^(G$5-1) -> -11275 | H19: =-H11*Inputs!$E$72/12*1*(1+Inputs!$E$79)*(1+Inputs!$E$80)^(H$5-1) -> -11275 | I19: =-I11*Inputs!$E$72/12*1*(1+Inputs!$E$79)*(1+Inputs!$E$80)^(I$5-1) -> -11275 | J19: =-J11*Inputs!$E$72/12*1*(1+Inputs!$E$79)*(1+Inputs!$E$80)^(J$5-1) -> -11275 | ... AL19: =-AL11*Inputs!$E$72/12*1*(1+Inputs!$E$79)*(1+Inputs!$E$80)^(AL$5-1) -> -12937.718
A20: Office manager — payroll cost | C20: =-C12*Inputs!$E$76/12*1*(1+Inputs!$E$79)*(1+Inputs!$E$80)^(C$5-1) -> -6233.3333 | D20: =-D12*Inputs!$E$76/12*1*(1+Inputs!$E$79)*(1+Inputs!$E$80)^(D$5-1) -> -6233.3333 | E20: =-E12*Inputs!$E$76/12*1*(1+Inputs!$E$79)*(1+Inputs!$E$80)^(E$5-1) -> -6233.3333 | F20: =-F12*Inputs!$E$76/12*1*(1+Inputs!$E$79)*(1+Inputs!$E$80)^(F$5-1) -> -6233.3333 | G20: =-G12*Inputs!$E$76/12*1*(1+Inputs!$E$79)*(1+Inputs!$E$80)^(G$5-1) -> -6233.3333 | H20: =-H12*Inputs!$E$76/12*1*(1+Inputs!$E$79)*(1+Inputs!$E$80)^(H$5-1) -> -6233.3333 | I20: =-I12*Inputs!$E$76/12*1*(1+Inputs!$E$79)*(1+Inputs!$E$80)^(I$5-1) -> -6233.3333 | J20: =-J12*Inputs!$E$76/12*1*(1+Inputs!$E$79)*(1+Inputs!$E$80)^(J$5-1) -> -6233.3333 | ... AL20: =-AL12*Inputs!$E$76/12*1*(1+Inputs!$E$79)*(1+Inputs!$E$80)^(AL$5-1) -> -6612.9433
A21: Total payroll | C21: =C16+C17+C18+C19+C20 -> -78970.833 | D21: =D16+D17+D18+D19+D20 -> -78970.833 | E21: =E16+E17+E18+E19+E20 -> -78970.833 | F21: =F16+F17+F18+F19+F20 -> -78970.833 | G21: =G16+G17+G18+G19+G20 -> -78970.833 | H21: =H16+H17+H18+H19+H20 -> -78970.833 | I21: =I16+I17+I18+I19+I20 -> -78970.833 | J21: =J16+J17+J18+J19+J20 -> -78970.833 | ... AL21: =AL16+AL17+AL18+AL19+AL20 -> -89824.932

Sheet Scenario calc
A1: Scenario calculation — Low, Base and High side by side | D1: =HYPERLINK("#'Cover'!A1","◂ Contents") -> ◂ Contents
A2: The model's period calculation, copied three times; each copy reads its own Inputs column. Feeds the Scenarios sheet only.
A4: Low scenario — reads Inputs column B
A5: Month | C5: M1 | D5: M2 | E5: M3 | F5: M4 | G5: M5 | H5: M6 | I5: M7 | J5: M8 | K5: M9 | L5: M10 | M5: M11 | N5: M12 | O5: M13 | P5: M14 | Q5: M15 | R5: M16 | S5: M17 | T5: M18 | U5: M19 | V5: M20 | W5: M21 | X5: M22 | Y5: M23 | Z5: M24 | AA5: M25 | AB5: M26 | AC5: M27 | AD5: M28 | AE5: M29 | AF5: M30 | AG5: M31 | AH5: M32 | AI5: M33 | AJ5: M34 | AK5: M35 | AL5: M36
A6: Period # | C6: 1 | D6: 2 | E6: 3 | F6: 4 | G6: 5 | H6: 6 | I6: 7 | J6: 8 | K6: 9 | L6: 10 | M6: 11 | N6: 12 | O6: 13 | P6: 14 | Q6: 15 | R6: 16 | S6: 17 | T6: 18 | U6: 19 | V6: 20 | W6: 21 | X6: 22 | Y6: 23 | Z6: 24 | AA6: 25 | AB6: 26 | AC6: 27 | AD6: 28 | AE6: 29 | AF6: 30 | AG6: 31 | AH6: 32 | AI6: 33 | AJ6: 34 | AK6: 35 | AL6: 36
A7: Year # | C7: =ROUNDUP(C6*1/12,0) -> 1 | D7: =ROUNDUP(D6*1/12,0) -> 1 | E7: =ROUNDUP(E6*1/12,0) -> 1 | F7: =ROUNDUP(F6*1/12,0) -> 1 | G7: =ROUNDUP(G6*1/12,0) -> 1 | H7: =ROUNDUP(H6*1/12,0) -> 1 | I7: =ROUNDUP(I6*1/12,0) -> 1 | J7: =ROUNDUP(J6*1/12,0) -> 1 | ... AL7: =ROUNDUP(AL6*1/12,0) -> 3
A9: Patients
A10: New patients from marketing | C10: =-C45/MAX(1,Inputs!$B$19) -> 30.434783 | D10: =-D45/MAX(1,Inputs!$B$19) -> 30.434783 | E10: =-E45/MAX(1,Inputs!$B$19) -> 30.434783 | F10: =-F45/MAX(1,Inputs!$B$19) -> 30.434783 | G10: =-G45/MAX(1,Inputs!$B$19) -> 30.434783 | H10: =-H45/MAX(1,Inputs!$B$19) -> 30.434783 | I10: =-I45/MAX(1,Inputs!$B$19) -> 30.434783 | J10: =-J45/MAX(1,Inputs!$B$19) -> 30.434783 | ... AL10: =-AL45/MAX(1,Inputs!$B$19) -> 30.434783
A11: New patients from referrals & walk-ins | C11: =Inputs!$B$15*(1+Inputs!$B$16)^(C$7-1)*1 -> 20 | D11: =Inputs!$B$15*(1+Inputs!$B$16)^(D$7-1)*1 -> 20 | E11: =Inputs!$B$15*(1+Inputs!$B$16)^(E$7-1)*1 -> 20 | F11: =Inputs!$B$15*(1+Inputs!$B$16)^(F$7-1)*1 -> 20 | G11: =Inputs!$B$15*(1+Inputs!$B$16)^(G$7-1)*1 -> 20 | H11: =Inputs!$B$15*(1+Inputs!$B$16)^(H$7-1)*1 -> 20 | I11: =Inputs!$B$15*(1+Inputs!$B$16)^(I$7-1)*1 -> 20 | J11: =Inputs!$B$15*(1+Inputs!$B$16)^(J$7-1)*1 -> 20 | ... AL11: =Inputs!$B$15*(1+Inputs!$B$16)^(AL$7-1)*1 -> 21.218
A12: New patients — total | C12: =C10+C11 -> 50.434783 | D12: =D10+D11 -> 50.434783 | E12: =E10+E11 -> 50.434783 | F12: =F10+F11 -> 50.434783 | G12: =G10+G11 -> 50.434783 | H12: =H10+H11 -> 50.434783 | I12: =I10+I11 -> 50.434783 | J12: =J10+J11 -> 50.434783 | ... AL12: =AL10+AL11 -> 51.652783
A13: Active patients — opening | C13: =Inputs!$B$14 -> 2700 | D13: =C15 -> 2707.2348 | E13: =D15 -> 2714.3538 | F13: =E15 -> 2721.3589 | G13: =F15 -> 2728.252 | H13: =G15 -> 2735.0347 | I13: =H15 -> 2741.7089 | J13: =I15 -> 2748.2764 | K13: =J15 -> 2754.7387 | ... AL13: =AK15 -> 2912.9572
A14: Patients lost | C14: =C15-C13-C12 -> -43.2 | D14: =D15-D13-D12 -> -43.315757 | E14: =E15-E13-E12 -> -43.429661 | F14: =F15-F13-F12 -> -43.541743 | G14: =G15-G13-G12 -> -43.652032 | H14: =H15-H13-H12 -> -43.760556 | I14: =I15-I13-I12 -> -43.867343 | J14: =J15-J13-J12 -> -43.972422 | ... AL14: =AL15-AL13-AL12 -> -46.607315
A15: Active patients — closing | C15: =C13*(1-Inputs!$B$20)+C12 -> 2707.2348 | D15: =D13*(1-Inputs!$B$20)+D12 -> 2714.3538 | E15: =E13*(1-Inputs!$B$20)+E12 -> 2721.3589 | F15: =F13*(1-Inputs!$B$20)+F12 -> 2728.252 | G15: =G13*(1-Inputs!$B$20)+G12 -> 2735.0347 | H15: =H13*(1-Inputs!$B$20)+H12 -> 2741.7089 | I15: =I13*(1-Inputs!$B$20)+I12 -> 2748.2764 | J15: =J13*(1-Inputs!$B$20)+J12 -> 2754.7387 | ... AL15: =AL13*(1-Inputs!$B$20)+AL12 -> 2918.0027
A16: Active patients — average | C16: =(C13+C15)/2 -> 2703.6174 | D16: =(D13+D15)/2 -> 2710.7943 | E16: =(E13+E15)/2 -> 2717.8564 | F16: =(F13+F15)/2 -> 2724.8055 | G16: =(G13+G15)/2 -> 2731.6433 | H16: =(H13+H15)/2 -> 2738.3718 | I16: =(I13+I15)/2 -> 2744.9927 | J16: =(J13+J15)/2 -> 2751.5076 | ... AL16: =(AL13+AL15)/2 -> 2915.48
A18: Visits
A19: Doctor visit capacity (operatories × visits per chair-day × working days) | C19: =Inputs!$B$7*Inputs!$B$9*Inputs!$B$11*1 -> 410.4 | D19: =Inputs!$B$7*Inputs!$B$9*Inputs!$B$11*1 -> 410.4 | E19: =Inputs!$B$7*Inputs!$B$9*Inputs!$B$11*1 -> 410.4 | F19: =Inputs!$B$7*Inputs!$B$9*Inputs!$B$11*1 -> 410.4 | G19: =Inputs!$B$7*Inputs!$B$9*Inputs!$B$11*1 -> 410.4 | H19: =Inputs!$B$7*Inputs!$B$9*Inputs!$B$11*1 -> 410.4 | I19: =Inputs!$B$7*Inputs!$B$9*Inputs!$B$11*1 -> 410.4 | J19: =Inputs!$B$7*Inputs!$B$9*Inputs!$B$11*1 -> 410.4 | ... AL19: =Inputs!$B$7*Inputs!$B$9*Inputs!$B$11*1 -> 410.4
A20: Doctor visits demanded | C20: =C16*Inputs!$B$21/12*1+C12*Inputs!$B$23 -> 298.26638 | D20: =D16*Inputs!$B$21/12*1+D12*Inputs!$B$23 -> 298.92426 | E20: =E16*Inputs!$B$21/12*1+E12*Inputs!$B$23 -> 299.57162 | F20: =F16*Inputs!$B$21/12*1+F12*Inputs!$B$23 -> 300.20862 | G20: =G16*Inputs!$B$21/12*1+G12*Inputs!$B$23 -> 300.83542 | H20: =H16*Inputs!$B$21/12*1+H12*Inputs!$B$23 -> 301.4522 | I20: =I16*Inputs!$B$21/12*1+I12*Inputs!$B$23 -> 302.05911 | J20: =J16*Inputs!$B$21/12*1+J12*Inputs!$B$23 -> 302.65631 | ... AL20: =AL16*Inputs!$B$21/12*1+AL12*Inputs!$B$23 -> 318.90511
A21: Doctor visits (demand capped by chairs) | C21: =MIN(C19,C20) -> 298.26638 | D21: =MIN(D19,D20) -> 298.92426 | E21: =MIN(E19,E20) -> 299.57162 | F21: =MIN(F19,F20) -> 300.20862 | G21: =MIN(G19,G20) -> 300.83542 | H21: =MIN(H19,H20) -> 301.4522 | I21: =MIN(I19,I20) -> 302.05911 | J21: =MIN(J19,J20) -> 302.65631 | ... AL21: =MIN(AL19,AL20) -> 318.90511
A22: Hygienists (FTE) | C22: =C114 -> 3 | D22: =D114 -> 3 | E22: =E114 -> 3 | F22: =F114 -> 3 | G22: =G114 -> 3 | H22: =H114 -> 3 | I22: =I114 -> 3 | J22: =J114 -> 3 | ... AL22: =AL114 -> 3.3708
A23: Hygiene visit capacity (hygienists, up to hygiene rooms, × visits per day × working days) | C23: =MIN(C22,Inputs!$B$8)*Inputs!$B$10*Inputs!$B$11*1 -> 405 | D23: =MIN(D22,Inputs!$B$8)*Inputs!$B$10*Inputs!$B$11*1 -> 405 | E23: =MIN(E22,Inputs!$B$8)*Inputs!$B$10*Inputs!$B$11*1 -> 405 | F23: =MIN(F22,Inputs!$B$8)*Inputs!$B$10*Inputs!$B$11*1 -> 405 | G23: =MIN(G22,Inputs!$B$8)*Inputs!$B$10*Inputs!$B$11*1 -> 405 | H23: =MIN(H22,Inputs!$B$8)*Inputs!$B$10*Inputs!$B$11*1 -> 405 | I23: =MIN(I22,Inputs!$B$8)*Inputs!$B$10*Inputs!$B$11*1 -> 405 | J23: =MIN(J22,Inputs!$B$8)*Inputs!$B$10*Inputs!$B$11*1 -> 405 | ... AL23: =MIN(AL22,Inputs!$B$8)*Inputs!$B$10*Inputs!$B$11*1 -> 455.058
A24: Hygiene recall visits demanded | C24: =C16*Inputs!$B$22/12*1 -> 315.42203 | D24: =D16*Inputs!$B$22/12*1 -> 316.25933 | E24: =E16*Inputs!$B$22/12*1 -> 317.08324 | F24: =F16*Inputs!$B$22/12*1 -> 317.89397 | G24: =G16*Inputs!$B$22/12*1 -> 318.69172 | H24: =H16*Inputs!$B$22/12*1 -> 319.47671 | I24: =I16*Inputs!$B$22/12*1 -> 320.24914 | J24: =J16*Inputs!$B$22/12*1 -> 321.00922 | ... AL24: =AL16*Inputs!$B$22/12*1 -> 340.13933
A25: Hygiene visits (demand capped by hygienists) | C25: =MIN(C23,C24) -> 315.42203 | D25: =MIN(D23,D24) -> 316.25933 | E25: =MIN(E23,E24) -> 317.08324 | F25: =MIN(F23,F24) -> 317.89397 | G25: =MIN(G23,G24) -> 318.69172 | H25: =MIN(H23,H24) -> 319.47671 | I25: =MIN(I23,I24) -> 320.24914 | J25: =MIN(J23,J24) -> 321.00922 | ... AL25: =MIN(AL23,AL24) -> 340.13933
A27: Production & collections
A28: Doctor production (office fees) | C28: =C21*Inputs!$B$26*(1+Inputs!$B$28)^(C$7-1) -> 95445.241 | D28: =D21*Inputs!$B$26*(1+Inputs!$B$28)^(D$7-1) -> 95655.763 | E28: =E21*Inputs!$B$26*(1+Inputs!$B$28)^(E$7-1) -> 95862.917 | F28: =F21*Inputs!$B$26*(1+Inputs!$B$28)^(F$7-1) -> 96066.757 | G28: =G21*Inputs!$B$26*(1+Inputs!$B$28)^(G$7-1) -> 96267.335 | H28: =H21*Inputs!$B$26*(1+Inputs!$B$28)^(H$7-1) -> 96464.704 | I28: =I21*Inputs!$B$26*(1+Inputs!$B$28)^(I$7-1) -> 96658.915 | J28: =J21*Inputs!$B$26*(1+Inputs!$B$28)^(J$7-1) -> 96850.019 | ... AL28: =AL21*Inputs!$B$26*(1+Inputs!$B$28)^(AL$7-1) -> 106172.44
A29: Hygiene production (office fees) | C29: =C25*Inputs!$B$27*(1+Inputs!$B$28)^(C$7-1) -> 61507.296 | D29: =D25*Inputs!$B$27*(1+Inputs!$B$28)^(D$7-1) -> 61670.57 | E29: =E25*Inputs!$B$27*(1+Inputs!$B$28)^(E$7-1) -> 61831.232 | F29: =F25*Inputs!$B$27*(1+Inputs!$B$28)^(F$7-1) -> 61989.324 | G29: =G25*Inputs!$B$27*(1+Inputs!$B$28)^(G$7-1) -> 62144.886 | H29: =H25*Inputs!$B$27*(1+Inputs!$B$28)^(H$7-1) -> 62297.959 | I29: =I25*Inputs!$B$27*(1+Inputs!$B$28)^(I$7-1) -> 62448.583 | J29: =J25*Inputs!$B$27*(1+Inputs!$B$28)^(J$7-1) -> 62596.797 | ... AL29: =AL25*Inputs!$B$27*(1+Inputs!$B$28)^(AL$7-1) -> 69006.787
A30: Gross production | C30: =C28+C29 -> 156952.54 | D30: =D28+D29 -> 157326.33 | E30: =E28+E29 -> 157694.15 | F30: =F28+F29 -> 158056.08 | G30: =G28+G29 -> 158412.22 | H30: =H28+H29 -> 158762.66 | I30: =I28+I29 -> 159107.5 | J30: =J28+J29 -> 159446.82 | ... AL30: =AL28+AL29 -> 175179.23
A31: PPO fee-schedule write-offs | C31: =-C30*Inputs!$B$31*Inputs!$B$32 -> -25426.311 | D31: =-D30*Inputs!$B$31*Inputs!$B$32 -> -25486.866 | E31: =-E30*Inputs!$B$31*Inputs!$B$32 -> -25546.452 | F31: =-F30*Inputs!$B$31*Inputs!$B$32 -> -25605.085 | G31: =-G30*Inputs!$B$31*Inputs!$B$32 -> -25662.78 | H31: =-H30*Inputs!$B$31*Inputs!$B$32 -> -25719.551 | I31: =-I30*Inputs!$B$31*Inputs!$B$32 -> -25775.415 | J31: =-J30*Inputs!$B$31*Inputs!$B$32 -> -25830.384 | ... AL31: =-AL30*Inputs!$B$31*Inputs!$B$32 -> -28379.035
A32: Bad debt (never collected) | C32: =-(C30+C31)*Inputs!$B$33 -> -2630.5245 | D32: =-(D30+D31)*Inputs!$B$33 -> -2636.7893 | E32: =-(E30+E31)*Inputs!$B$33 -> -2642.9539 | F32: =-(F30+F31)*Inputs!$B$33 -> -2649.0199 | G32: =-(G30+G31)*Inputs!$B$33 -> -2654.9888 | H32: =-(H30+H31)*Inputs!$B$33 -> -2660.8622 | I32: =-(I30+I31)*Inputs!$B$33 -> -2666.6417 | J32: =-(J30+J31)*Inputs!$B$33 -> -2672.3286 | ... AL32: =-(AL30+AL31)*Inputs!$B$33 -> -2936.0039
A33: Collections (revenue) | C33: =C30+C31+C32 -> 128895.7 | D33: =D30+D31+D32 -> 129202.68 | E33: =E30+E31+E32 -> 129504.74 | F33: =F30+F31+F32 -> 129801.98 | G33: =G30+G31+G32 -> 130094.45 | H33: =H30+H31+H32 -> 130382.25 | I33: =I30+I31+I32 -> 130665.44 | J33: =J30+J31+J32 -> 130944.1 | ... AL33: =AL30+AL31+AL32 -> 143864.19
A35: Cost of sales
A36: Dental supplies | C36: =-C30*Inputs!$B$36 -> -8475.437 | D36: =-D30*Inputs!$B$36 -> -8495.622 | E36: =-E30*Inputs!$B$36 -> -8515.4841 | F36: =-F30*Inputs!$B$36 -> -8535.0284 | G36: =-G30*Inputs!$B$36 -> -8554.26 | H36: =-H30*Inputs!$B$36 -> -8573.1838 | I36: =-I30*Inputs!$B$36 -> -8591.8049 | J36: =-J30*Inputs!$B$36 -> -8610.1281 | ... AL36: =-AL30*Inputs!$B$36 -> -9459.6783
A37: Lab fees | C37: =-C28*Inputs!$B$37 -> -10308.086 | D37: =-D28*Inputs!$B$37 -> -10330.822 | E37: =-E28*Inputs!$B$37 -> -10353.195 | F37: =-F28*Inputs!$B$37 -> -10375.21 | G37: =-G28*Inputs!$B$37 -> -10396.872 | H37: =-H28*Inputs!$B$37 -> -10418.188 | I37: =-I28*Inputs!$B$37 -> -10439.163 | J37: =-J28*Inputs!$B$37 -> -10459.802 | ... AL37: =-AL28*Inputs!$B$37 -> -11466.624
A38: Card & payment processing | C38: =-C33*Inputs!$B$38 -> -1804.5398 | D38: =-D33*Inputs!$B$38 -> -1808.8375 | E38: =-E33*Inputs!$B$38 -> -1813.0664 | F38: =-F33*Inputs!$B$38 -> -1817.2277 | G38: =-G33*Inputs!$B$38 -> -1821.3223 | H38: =-H33*Inputs!$B$38 -> -1825.3515 | I38: =-I33*Inputs!$B$38 -> -1829.3162 | J38: =-J33*Inputs!$B$38 -> -1833.2174 | ... AL38: =-AL33*Inputs!$B$38 -> -2014.0986
A39: Cost of sales | C39: =C36+C37+C38 -> -20588.063 | D39: =D36+D37+D38 -> -20635.282 | E39: =E36+E37+E38 -> -20681.746 | F39: =F36+F37+F38 -> -20727.466 | G39: =G36+G37+G38 -> -20772.454 | H39: =H36+H37+H38 -> -20816.723 | I39: =I36+I37+I38 -> -20860.284 | J39: =J36+J37+J38 -> -20903.148 | ... AL39: =AL36+AL37+AL38 -> -22940.401
A40: Gross profit | C40: =C33+C39 -> 108307.64 | D40: =D33+D39 -> 108567.4 | E40: =E33+E39 -> 108823 | F40: =F33+F39 -> 109074.51 | G40: =G33+G39 -> 109322 | H40: =H33+H39 -> 109565.53 | I40: =I33+I39 -> 109805.16 | J40: =J33+J39 -> 110040.96 | ... AL40: =AL33+AL39 -> 120923.79
A42: Operating expenses
A43: Staff payroll (owner dentist, hygienists, assistants, front desk, office manager) | C43: =C126 -> -78970.833 | D43: =D126 -> -78970.833 | E43: =E126 -> -78970.833 | F43: =F126 -> -78970.833 | G43: =G126 -> -78970.833 | H43: =H126 -> -78970.833 | I43: =I126 -> -78970.833 | J43: =J126 -> -78970.833 | ... AL43: =AL126 -> -89824.932
A44: Associate dentists (% of the collections they produce) | C44: =-C33*C28/MAX(1,C30)*Inputs!$B$39*Inputs!$B$40 -> -10033.082 | D44: =-D33*D28/MAX(1,D30)*Inputs!$B$39*Inputs!$B$40 -> -10055.211 | E44: =-E33*E28/MAX(1,E30)*Inputs!$B$39*Inputs!$B$40 -> -10076.987 | F44: =-F33*F28/MAX(1,F30)*Inputs!$B$39*Inputs!$B$40 -> -10098.415 | G44: =-G33*G28/MAX(1,G30)*Inputs!$B$39*Inputs!$B$40 -> -10119.499 | H44: =-H33*H28/MAX(1,H30)*Inputs!$B$39*Inputs!$B$40 -> -10140.246 | I44: =-I33*I28/MAX(1,I30)*Inputs!$B$39*Inputs!$B$40 -> -10160.661 | J44: =-J33*J28/MAX(1,J30)*Inputs!$B$39*Inputs!$B$40 -> -10180.75 | ... AL44: =-AL33*AL28/MAX(1,AL30)*Inputs!$B$39*Inputs!$B$40 -> -11160.711
A45: Marketing | C45: =-Inputs!$B$17*(1+Inputs!$B$18)^(C$7-1)*1 -> -7000 | D45: =-Inputs!$B$17*(1+Inputs!$B$18)^(D$7-1)*1 -> -7000 | E45: =-Inputs!$B$17*(1+Inputs!$B$18)^(E$7-1)*1 -> -7000 | F45: =-Inputs!$B$17*(1+Inputs!$B$18)^(F$7-1)*1 -> -7000 | G45: =-Inputs!$B$17*(1+Inputs!$B$18)^(G$7-1)*1 -> -7000 | H45: =-Inputs!$B$17*(1+Inputs!$B$18)^(H$7-1)*1 -> -7000 | I45: =-Inputs!$B$17*(1+Inputs!$B$18)^(I$7-1)*1 -> -7000 | J45: =-Inputs!$B$17*(1+Inputs!$B$18)^(J$7-1)*1 -> -7000 | ... AL45: =-Inputs!$B$17*(1+Inputs!$B$18)^(AL$7-1)*1 -> -7000
A46: Rent | C46: =-Inputs!$B$48*Inputs!$B$49/12*1 -> -10666.667 | D46: =-Inputs!$B$48*Inputs!$B$49/12*1 -> -10666.667 | E46: =-Inputs!$B$48*Inputs!$B$49/12*1 -> -10666.667 | F46: =-Inputs!$B$48*Inputs!$B$49/12*1 -> -10666.667 | G46: =-Inputs!$B$48*Inputs!$B$49/12*1 -> -10666.667 | H46: =-Inputs!$B$48*Inputs!$B$49/12*1 -> -10666.667 | I46: =-Inputs!$B$48*Inputs!$B$49/12*1 -> -10666.667 | J46: =-Inputs!$B$48*Inputs!$B$49/12*1 -> -10666.667 | ... AL46: =-Inputs!$B$48*Inputs!$B$49/12*1 -> -10666.667
A47: Utilities & phone | C47: =-Inputs!$B$41*1 -> -1800 | D47: =-Inputs!$B$41*1 -> -1800 | E47: =-Inputs!$B$41*1 -> -1800 | F47: =-Inputs!$B$41*1 -> -1800 | G47: =-Inputs!$B$41*1 -> -1800 | H47: =-Inputs!$B$41*1 -> -1800 | I47: =-Inputs!$B$41*1 -> -1800 | J47: =-Inputs!$B$41*1 -> -1800 | ... AL47: =-Inputs!$B$41*1 -> -1800
A48: Practice software & IT | C48: =-Inputs!$B$42*1 -> -1300 | D48: =-Inputs!$B$42*1 -> -1300 | E48: =-Inputs!$B$42*1 -> -1300 | F48: =-Inputs!$B$42*1 -> -1300 | G48: =-Inputs!$B$42*1 -> -1300 | H48: =-Inputs!$B$42*1 -> -1300 | I48: =-Inputs!$B$42*1 -> -1300 | J48: =-Inputs!$B$42*1 -> -1300 | ... AL48: =-Inputs!$B$42*1 -> -1300
A49: Malpractice & liability insurance | C49: =-Inputs!$B$43*1 -> -1100 | D49: =-Inputs!$B$43*1 -> -1100 | E49: =-Inputs!$B$43*1 -> -1100 | F49: =-Inputs!$B$43*1 -> -1100 | G49: =-Inputs!$B$43*1 -> -1100 | H49: =-Inputs!$B$43*1 -> -1100 | I49: =-Inputs!$B$43*1 -> -1100 | J49: =-Inputs!$B$43*1 -> -1100 | ... AL49: =-Inputs!$B$43*1 -> -1100
A50: Equipment maintenance, cleaning & compliance | C50: =-Inputs!$B$44*1 -> -1400 | D50: =-Inputs!$B$44*1 -> -1400 | E50: =-Inputs!$B$44*1 -> -1400 | F50: =-Inputs!$B$44*1 -> -1400 | G50: =-Inputs!$B$44*1 -> -1400 | H50: =-Inputs!$B$44*1 -> -1400 | I50: =-Inputs!$B$44*1 -> -1400 | J50: =-Inputs!$B$44*1 -> -1400 | ... AL50: =-Inputs!$B$44*1 -> -1400
A51: Other G&A | C51: =-Inputs!$B$45*1 -> -3000 | D51: =-Inputs!$B$45*1 -> -3000 | E51: =-Inputs!$B$45*1 -> -3000 | F51: =-Inputs!$B$45*1 -> -3000 | G51: =-Inputs!$B$45*1 -> -3000 | H51: =-Inputs!$B$45*1 -> -3000 | I51: =-Inputs!$B$45*1 -> -3000 | J51: =-Inputs!$B$45*1 -> -3000 | ... AL51: =-Inputs!$B$45*1 -> -3000
A52: Total operating expenses | C52: =C43+C44+C45+C46+C47+C48+C49+C50+C51 -> -115270.58 | D52: =D43+D44+D45+D46+D47+D48+D49+D50+D51 -> -115292.71 | E52: =E43+E44+E45+E46+E47+E48+E49+E50+E51 -> -115314.49 | F52: =F43+F44+F45+F46+F47+F48+F49+F50+F51 -> -115335.91 | G52: =G43+G44+G45+G46+G47+G48+G49+G50+G51 -> -115357 | H52: =H43+H44+H45+H46+H47+H48+H49+H50+H51 -> -115377.75 | I52: =I43+I44+I45+I46+I47+I48+I49+I50+I51 -> -115398.16 | J52: =J43+J44+J45+J46+J47+J48+J49+J50+J51 -> -115418.25 | ... AL52: =AL43+AL44+AL45+AL46+AL47+AL48+AL49+AL50+AL51 -> -127252.31
A53: EBITDA | C53: =C40+C52 -> -6962.9434 | D53: =D40+D52 -> -6725.3153 | E53: =E40+E52 -> -6491.4892 | F53: =F40+F52 -> -6261.4044 | G53: =G40+G52 -> -6035.0009 | H53: =H40+H52 -> -5812.2199 | I53: =I40+I52 -> -5593.0033 | J53: =J40+J52 -> -5377.2942 | ... AL53: =AL40+AL52 -> -6328.5214
A55: Profit after depreciation, interest, tax
A56: EBIT | C56: =C53+C67 -> -7700.2462 | D56: =D53+D67 -> -7485.69 | E56: =E53+E67 -> -7274.9898 | F56: =F53+F67 -> -7068.0839 | G56: =G53+G67 -> -6864.9115 | H56: =H53+H67 -> -6665.413 | I56: =I53+I67 -> -6469.5296 | J56: =J53+J67 -> -6277.2034 | ... AL56: =AL53+AL67 -> -7920.5627
A57: Interest on loan (average balance after drawdown) | C57: =-(C72+C73+C75)/2*Inputs!$B$85/12 -> -1062.5 | D57: =-(D72+D73+D75)/2*Inputs!$B$85/12 -> -1056.1756 | E57: =-(E72+E73+E75)/2*Inputs!$B$85/12 -> -1043.5268 | F57: =-(F72+F73+F75)/2*Inputs!$B$85/12 -> -1030.878 | G57: =-(G72+G73+G75)/2*Inputs!$B$85/12 -> -1018.2292 | H57: =-(H72+H73+H75)/2*Inputs!$B$85/12 -> -1005.5804 | I57: =-(I72+I73+I75)/2*Inputs!$B$85/12 -> -992.93155 | J57: =-(J72+J73+J75)/2*Inputs!$B$85/12 -> -980.28274 | ... AL57: =-(AL72+AL73+AL75)/2*Inputs!$B$85/12 -> -626.11607
A58: Pre-tax income | C58: =C56+C57 -> -8762.7462 | D58: =D56+D57 -> -8541.8656 | E58: =E56+E57 -> -8318.5166 | F58: =F56+F57 -> -8098.9618 | G58: =G56+G57 -> -7883.1407 | H58: =H56+H57 -> -7670.9934 | I58: =I56+I57 -> -7462.4612 | J58: =J56+J57 -> -7257.4861 | ... AL58: =AL56+AL57 -> -8546.6788
A59: Helper: cumulative pre-tax income | C59: =C58 -> -8762.7462 | D59: =C59+D58 -> -17304.612 | E59: =D59+E58 -> -25623.128 | F59: =E59+F58 -> -33722.09 | G59: =F59+G58 -> -41605.231 | H59: =G59+H58 -> -49276.224 | I59: =H59+I58 -> -56738.685 | J59: =I59+J58 -> -63996.172 | K59: =J59+K58 -> -71052.183 | ... AL59: =AK59+AL58 -> -304541.71
A60: Helper: cumulative taxable income (losses carried forward) | C60: =MAX(0,C59) -> 0 | D60: =MAX(C60,D59) -> 0 | E60: =MAX(D60,E59) -> 0 | F60: =MAX(E60,F59) -> 0 | G60: =MAX(F60,G59) -> 0 | H60: =MAX(G60,H59) -> 0 | I60: =MAX(H60,I59) -> 0 | J60: =MAX(I60,J59) -> 0 | K60: =MAX(J60,K59) -> 0 | ... AL60: =MAX(AK60,AL59) -> 0
A61: Income tax | C61: =-C60*Inputs!$B$95 -> 0 | D61: =-(D60-C60)*Inputs!$B$95 -> 0 | E61: =-(E60-D60)*Inputs!$B$95 -> 0 | F61: =-(F60-E60)*Inputs!$B$95 -> 0 | G61: =-(G60-F60)*Inputs!$B$95 -> 0 | H61: =-(H60-G60)*Inputs!$B$95 -> 0 | I61: =-(I60-H60)*Inputs!$B$95 -> 0 | J61: =-(J60-I60)*Inputs!$B$95 -> 0 | K61: =-(K60-J60)*Inputs!$B$95 -> 0 | ... AL61: =-(AL60-AK60)*Inputs!$B$95 -> 0
A62: Net income | C62: =C58+C61 -> -8762.7462 | D62: =D58+D61 -> -8541.8656 | E62: =E58+E61 -> -8318.5166 | F62: =F58+F61 -> -8098.9618 | G62: =G58+G61 -> -7883.1407 | H62: =H58+H61 -> -7670.9934 | I62: =I58+I61 -> -7462.4612 | J62: =J58+J61 -> -7257.4861 | ... AL62: =AL58+AL61 -> -8546.6788
A64: Fixed assets & capital spending
A65: Capital spending (fit-out, operatories, imaging at start; then equipment refresh) | C65: =Inputs!$B$52*Inputs!$B$48+MAX(0,Inputs!$B$7+Inputs!$B$8-Inputs!$B$54)*Inputs!$B$53+Inputs!$B$55+C33*Inputs!$B$56 -> 61933.436 | D65: =D33*Inputs!$B$56 -> 1938.0402 | E65: =E33*Inputs!$B$56 -> 1942.5712 | F65: =F33*Inputs!$B$56 -> 1947.0296 | G65: =G33*Inputs!$B$56 -> 1951.4168 | H65: =H33*Inputs!$B$56 -> 1955.7337 | I65: =I33*Inputs!$B$56 -> 1959.9816 | J65: =J33*Inputs!$B$56 -> 1964.1616 | K65: =K33*Inputs!$B$56 -> 1968.2746 | ... AL65: =AL33*Inputs!$B$56 -> 2157.9628
A66: Fixed assets at cost | C66: =C65 -> 61933.436 | D66: =C66+D65 -> 63871.476 | E66: =D66+E65 -> 65814.047 | F66: =E66+F65 -> 67761.076 | G66: =F66+G65 -> 69712.493 | H66: =G66+H65 -> 71668.227 | I66: =H66+I65 -> 73628.209 | J66: =I66+J65 -> 75592.37 | K66: =J66+K65 -> 77560.645 | ... AL66: =AK66+AL65 -> 133731.47
A67: Depreciation | C67: =-MIN(C66/MAX(1,Inputs!$B$94*12),C65) -> -737.3028 | D67: =-MIN(D66/MAX(1,Inputs!$B$94*12),C69+D65) -> -760.37471 | E67: =-MIN(E66/MAX(1,Inputs!$B$94*12),D69+E65) -> -783.50056 | F67: =-MIN(F66/MAX(1,Inputs!$B$94*12),E69+F65) -> -806.67948 | G67: =-MIN(G66/MAX(1,Inputs!$B$94*12),F69+G65) -> -829.91063 | H67: =-MIN(H66/MAX(1,Inputs!$B$94*12),G69+H65) -> -853.19318 | I67: =-MIN(I66/MAX(1,Inputs!$B$94*12),H69+I65) -> -876.52629 | J67: =-MIN(J66/MAX(1,Inputs!$B$94*12),I69+J65) -> -899.90917 | K67: =-MIN(K66/MAX(1,Inputs!$B$94*12),J69+K65) -> -923.34101 | ... AL67: =-MIN(AL66/MAX(1,Inputs!$B$94*12),AK69+AL65) -> -1592.0413
A68: Accumulated depreciation | C68: =C67 -> -737.3028 | D68: =C68+D67 -> -1497.6775 | E68: =D68+E67 -> -2281.1781 | F68: =E68+F67 -> -3087.8576 | G68: =F68+G67 -> -3917.7682 | H68: =G68+H67 -> -4770.9614 | I68: =H68+I67 -> -5647.4877 | J68: =I68+J67 -> -6547.3968 | K68: =J68+K67 -> -7470.7378 | ... AL68: =AK68+AL67 -> -41622.648
A69: Net fixed assets | C69: =C66+C68 -> 61196.133 | D69: =D66+D68 -> 62373.798 | E69: =E66+E68 -> 63532.869 | F69: =F66+F68 -> 64673.219 | G69: =G66+G68 -> 65794.725 | H69: =H66+H68 -> 66897.266 | I69: =I66+I68 -> 67980.721 | J69: =J66+J68 -> 69044.973 | ... AL69: =AL66+AL68 -> 92108.818
A71: Debt
A72: Loan — opening balance | C72: =0 -> 0 | D72: =C75 -> 150000 | E72: =D75 -> 148214.29 | F72: =E75 -> 146428.57 | G72: =F75 -> 144642.86 | H72: =G75 -> 142857.14 | I72: =H75 -> 141071.43 | J72: =I75 -> 139285.71 | K72: =J75 -> 137500 | ... AL72: =AK75 -> 89285.714
A73: Loan drawdown | C73: =IF(C$6=1,Inputs!$B$84,0) -> 150000 | D73: =IF(D$6=1,Inputs!$B$84,0) -> 0 | E73: =IF(E$6=1,Inputs!$B$84,0) -> 0 | F73: =IF(F$6=1,Inputs!$B$84,0) -> 0 | G73: =IF(G$6=1,Inputs!$B$84,0) -> 0 | H73: =IF(H$6=1,Inputs!$B$84,0) -> 0 | I73: =IF(I$6=1,Inputs!$B$84,0) -> 0 | J73: =IF(J$6=1,Inputs!$B$84,0) -> 0 | ... AL73: =IF(AL$6=1,Inputs!$B$84,0) -> 0
A74: Loan repayment | C74: =-MIN(C72,Inputs!$B$84/MAX(1,Inputs!$B$86*12)) -> 0 | D74: =-MIN(D72,Inputs!$B$84/MAX(1,Inputs!$B$86*12)) -> -1785.7143 | E74: =-MIN(E72,Inputs!$B$84/MAX(1,Inputs!$B$86*12)) -> -1785.7143 | F74: =-MIN(F72,Inputs!$B$84/MAX(1,Inputs!$B$86*12)) -> -1785.7143 | G74: =-MIN(G72,Inputs!$B$84/MAX(1,Inputs!$B$86*12)) -> -1785.7143 | H74: =-MIN(H72,Inputs!$B$84/MAX(1,Inputs!$B$86*12)) -> -1785.7143 | I74: =-MIN(I72,Inputs!$B$84/MAX(1,Inputs!$B$86*12)) -> -1785.7143 | J74: =-MIN(J72,Inputs!$B$84/MAX(1,Inputs!$B$86*12)) -> -1785.7143 | ... AL74: =-MIN(AL72,Inputs!$B$84/MAX(1,Inputs!$B$86*12)) -> -1785.7143
A75: Loan — closing balance | C75: =C72+C73+C74 -> 150000 | D75: =D72+D73+D74 -> 148214.29 | E75: =E72+E73+E74 -> 146428.57 | F75: =F72+F73+F74 -> 144642.86 | G75: =G72+G73+G74 -> 142857.14 | H75: =H72+H73+H74 -> 141071.43 | I75: =I72+I73+I74 -> 139285.71 | J75: =J72+J73+J74 -> 137500 | ... AL75: =AL72+AL73+AL74 -> 87500
A77: Working capital
A78: Accounts receivable | C78: =C33*Inputs!$B$89/30 -> 94523.514 | D78: =D33*Inputs!$B$89/30 -> 94748.631 | E78: =E33*Inputs!$B$89/30 -> 94970.145 | F78: =F33*Inputs!$B$89/30 -> 95188.116 | G78: =G33*Inputs!$B$89/30 -> 95402.599 | H78: =H33*Inputs!$B$89/30 -> 95613.65 | I78: =I33*Inputs!$B$89/30 -> 95821.324 | J78: =J33*Inputs!$B$89/30 -> 96025.676 | ... AL78: =AL33*Inputs!$B$89/30 -> 105500.41
A79: Inventory | C79: =-C39*Inputs!$B$90/30 -> 8235.2251 | D79: =-D39*Inputs!$B$90/30 -> 8254.1128 | E79: =-E39*Inputs!$B$90/30 -> 8272.6982 | F79: =-F39*Inputs!$B$90/30 -> 8290.9863 | G79: =-G39*Inputs!$B$90/30 -> 8308.9818 | H79: =-H39*Inputs!$B$90/30 -> 8326.6894 | I79: =-I39*Inputs!$B$90/30 -> 8344.1136 | J79: =-J39*Inputs!$B$90/30 -> 8361.259 | ... AL79: =-AL39*Inputs!$B$90/30 -> 9176.1602
A80: Accounts payable | C80: =-C39*Inputs!$B$91/30 -> 17156.719 | D80: =-D39*Inputs!$B$91/30 -> 17196.068 | E80: =-E39*Inputs!$B$91/30 -> 17234.788 | F80: =-F39*Inputs!$B$91/30 -> 17272.888 | G80: =-G39*Inputs!$B$91/30 -> 17310.379 | H80: =-H39*Inputs!$B$91/30 -> 17347.269 | I80: =-I39*Inputs!$B$91/30 -> 17383.57 | J80: =-J39*Inputs!$B$91/30 -> 17419.29 | ... AL80: =-AL39*Inputs!$B$91/30 -> 19117
A81: (Increase) / decrease in receivables | C81: =-C78 -> -94523.514 | D81: =C78-D78 -> -225.11656 | E81: =D78-E78 -> -221.5147 | F81: =E78-F78 -> -217.97046 | G81: =F78-G78 -> -214.48294 | H81: =G78-H78 -> -211.05121 | I81: =H78-I78 -> -207.67439 | J81: =I78-J78 -> -204.3516 | K81: =J78-K78 -> -201.08197 | ... AL81: =AK78-AL78 -> -165.99255
A82: (Increase) / decrease in inventory | C82: =-C79 -> -8235.2251 | D82: =C79-D79 -> -18.887663 | E82: =D79-E79 -> -18.58546 | F82: =E79-F79 -> -18.288093 | G82: =F79-G79 -> -17.995483 | H82: =G79-H79 -> -17.707555 | I82: =H79-I79 -> -17.424234 | J82: =I79-J79 -> -17.145447 | K82: =J79-K79 -> -16.87112 | ... AL82: =AK79-AL79 -> -13.927057
A83: Increase / (decrease) in payables | C83: =C80 -> 17156.719 | D83: =D80-C80 -> 39.349297 | E83: =E80-D80 -> 38.719708 | F83: =F80-E80 -> 38.100193 | G83: =G80-F80 -> 37.49059 | H83: =H80-G80 -> 36.89074 | I83: =I80-H80 -> 36.300488 | J83: =J80-I80 -> 35.719681 | K83: =K80-J80 -> 35.148166 | ... AL83: =AL80-AK80 -> 29.014702
A85: Cash flow
A86: Operating cash flow | C86: =C62-C67+C81+C82+C83 -> -93627.464 | D86: =D62-D67+D81+D82+D83 -> -7986.1458 | E86: =E62-E67+E81+E82+E83 -> -7736.3965 | F86: =F62-F67+F81+F82+F83 -> -7490.4407 | G86: =G62-G67+G81+G82+G83 -> -7248.2179 | H86: =H62-H67+H81+H82+H83 -> -7009.6682 | I86: =I62-I67+I81+I82+I83 -> -6774.733 | J86: =J62-J67+J81+J82+J83 -> -6543.3543 | ... AL86: =AL62-AL67+AL81+AL82+AL83 -> -7105.5424
A87: Investing cash flow (capex) | C87: =-C65 -> -61933.436 | D87: =-D65 -> -1938.0402 | E87: =-E65 -> -1942.5712 | F87: =-F65 -> -1947.0296 | G87: =-G65 -> -1951.4168 | H87: =-H65 -> -1955.7337 | I87: =-I65 -> -1959.9816 | J87: =-J65 -> -1964.1616 | ... AL87: =-AL65 -> -2157.9628
A88: Equity raised | C88: =IF(C$6=1,Inputs!$B$83,0) -> 100000 | D88: =IF(D$6=1,Inputs!$B$83,0) -> 0 | E88: =IF(E$6=1,Inputs!$B$83,0) -> 0 | F88: =IF(F$6=1,Inputs!$B$83,0) -> 0 | G88: =IF(G$6=1,Inputs!$B$83,0) -> 0 | H88: =IF(H$6=1,Inputs!$B$83,0) -> 0 | I88: =IF(I$6=1,Inputs!$B$83,0) -> 0 | J88: =IF(J$6=1,Inputs!$B$83,0) -> 0 | ... AL88: =IF(AL$6=1,Inputs!$B$83,0) -> 0
A89: Financing cash flow | C89: =C88+C73+C74 -> 250000 | D89: =D88+D73+D74 -> -1785.7143 | E89: =E88+E73+E74 -> -1785.7143 | F89: =F88+F73+F74 -> -1785.7143 | G89: =G88+G73+G74 -> -1785.7143 | H89: =H88+H73+H74 -> -1785.7143 | I89: =I88+I73+I74 -> -1785.7143 | J89: =J88+J73+J74 -> -1785.7143 | ... AL89: =AL88+AL73+AL74 -> -1785.7143
A90: Net cash flow | C90: =C86+C87+C89 -> 94439.101 | D90: =D86+D87+D89 -> -11709.9 | E90: =E86+E87+E89 -> -11464.682 | F90: =F86+F87+F89 -> -11223.185 | G90: =G86+G87+G89 -> -10985.349 | H90: =H86+H87+H89 -> -10751.116 | I90: =I86+I87+I89 -> -10520.429 | J90: =J86+J87+J89 -> -10293.23 | ... AL90: =AL86+AL87+AL89 -> -11049.22
A91: Opening cash | C91: =0 -> 0 | D91: =C92 -> 94439.101 | E91: =D92 -> 82729.201 | F91: =E92 -> 71264.519 | G91: =F92 -> 60041.334 | H91: =G92 -> 49055.985 | I91: =H92 -> 38304.869 | J91: =I92 -> 27784.44 | K91: =J92 -> 17491.21 | ... AL91: =AK92 -> -293660.87
A92: Closing cash | C92: =C91+C90 -> 94439.101 | D92: =D91+D90 -> 82729.201 | E92: =E91+E90 -> 71264.519 | F92: =F91+F90 -> 60041.334 | G92: =G91+G90 -> 49055.985 | H92: =H91+H90 -> 38304.869 | I92: =I91+I90 -> 27784.44 | J92: =J91+J90 -> 17491.21 | ... AL92: =AL91+AL90 -> -304710.09
A93: Helper: EBITDA positive (1/0) | C93: =IF(C53>0,1,0) -> 0 | D93: =IF(D53>0,1,0) -> 0 | E93: =IF(E53>0,1,0) -> 0 | F93: =IF(F53>0,1,0) -> 0 | G93: =IF(G53>0,1,0) -> 0 | H93: =IF(H53>0,1,0) -> 0 | I93: =IF(I53>0,1,0) -> 0 | J93: =IF(J53>0,1,0) -> 0 | ... AL93: =IF(AL53>0,1,0) -> 0
A95: Goal modules
A96: Helper: net income positive (1/0) | C96: =IF(C62>0,1,0) -> 0 | D96: =IF(D62>0,1,0) -> 0 | E96: =IF(E62>0,1,0) -> 0 | F96: =IF(F62>0,1,0) -> 0 | G96: =IF(G62>0,1,0) -> 0 | H96: =IF(H62>0,1,0) -> 0 | I96: =IF(I62>0,1,0) -> 0 | J96: =IF(J62>0,1,0) -> 0 | ... AL96: =IF(AL62>0,1,0) -> 0
A97: Cash flow before financing (operating + investing) | C97: =C86+C87 -> -155560.9 | D97: =D86+D87 -> -9924.186 | E97: =E86+E87 -> -9678.9676 | F97: =F86+F87 -> -9437.4704 | G97: =G86+G87 -> -9199.6347 | H97: =H86+H87 -> -8965.402 | I97: =I86+I87 -> -8734.7146 | J97: =J86+J87 -> -8507.5159 | ... AL97: =AL86+AL87 -> -9263.5052
A98: Cumulative cash flow before financing | C98: =C97 -> -155560.9 | D98: =C98+D97 -> -165485.09 | E98: =D98+E97 -> -175164.05 | F98: =E98+F97 -> -184601.52 | G98: =F98+G97 -> -193801.16 | H98: =G98+H97 -> -202766.56 | I98: =H98+I97 -> -211501.27 | J98: =I98+J97 -> -220008.79 | K98: =J98+K97 -> -228292.54 | ... AL98: =AK98+AL97 -> -492210.09
A99: Helper: lowest cumulative cash flow so far | C99: =C98 -> -155560.9 | D99: =MIN(C99,D98) -> -165485.09 | E99: =MIN(D99,E98) -> -175164.05 | F99: =MIN(E99,F98) -> -184601.52 | G99: =MIN(F99,G98) -> -193801.16 | H99: =MIN(G99,H98) -> -202766.56 | I99: =MIN(H99,I98) -> -211501.27 | J99: =MIN(I99,J98) -> -220008.79 | K99: =MIN(J99,K98) -> -228292.54 | ... AL99: =MIN(AK99,AL98) -> -492210.09
A100: Helper: investment paid back (1/0) | C100: =IF(AND(C98>=0,C99<0),1,0) -> 0 | D100: =IF(AND(D98>=0,D99<0),1,0) -> 0 | E100: =IF(AND(E98>=0,E99<0),1,0) -> 0 | F100: =IF(AND(F98>=0,F99<0),1,0) -> 0 | G100: =IF(AND(G98>=0,G99<0),1,0) -> 0 | H100: =IF(AND(H98>=0,H99<0),1,0) -> 0 | I100: =IF(AND(I98>=0,I99<0),1,0) -> 0 | J100: =IF(AND(J98>=0,J99<0),1,0) -> 0 | ... AL100: =IF(AND(AL98>=0,AL99<0),1,0) -> 0
A101: Unlevered free cash flow (operating + after-tax interest − capex) | C101: =C86-C57*(1-Inputs!$B$95)+C87 -> -154721.52 | D101: =D86-D57*(1-Inputs!$B$95)+D87 -> -9089.8073 | E101: =E86-E57*(1-Inputs!$B$95)+E87 -> -8854.5815 | F101: =F86-F57*(1-Inputs!$B$95)+F87 -> -8623.0768 | G101: =G86-G57*(1-Inputs!$B$95)+G87 -> -8395.2336 | H101: =H86-H57*(1-Inputs!$B$95)+H87 -> -8170.9935 | I101: =I86-I57*(1-Inputs!$B$95)+I87 -> -7950.2987 | J101: =J86-J57*(1-Inputs!$B$95)+J87 -> -7733.0925 | ... AL101: =AL86-AL57*(1-Inputs!$B$95)+AL87 -> -8768.8735
A103: Balance sheet
A104: Paid-in capital | C104: =C88 -> 100000 | D104: =C104+D88 -> 100000 | E104: =D104+E88 -> 100000 | F104: =E104+F88 -> 100000 | G104: =F104+G88 -> 100000 | H104: =G104+H88 -> 100000 | I104: =H104+I88 -> 100000 | J104: =I104+J88 -> 100000 | K104: =J104+K88 -> 100000 | ... AL104: =AK104+AL88 -> 100000
A105: Retained earnings | C105: =C62 -> -8762.7462 | D105: =C105+D62 -> -17304.612 | E105: =D105+E62 -> -25623.128 | F105: =E105+F62 -> -33722.09 | G105: =F105+G62 -> -41605.231 | H105: =G105+H62 -> -49276.224 | I105: =H105+I62 -> -56738.685 | J105: =I105+J62 -> -63996.172 | K105: =J105+K62 -> -71052.183 | ... AL105: =AK105+AL62 -> -304541.71
A106: Total assets | C106: =C92+C78+C79+C69 -> 258393.97 | D106: =D92+D78+D79+D69 -> 248105.74 | E106: =E92+E78+E79+E69 -> 238040.23 | F106: =F92+F78+F79+F69 -> 228193.66 | G106: =G92+G78+G79+G69 -> 218562.29 | H106: =H92+H78+H79+H69 -> 209142.47 | I106: =I92+I78+I79+I69 -> 199930.6 | J106: =J92+J78+J79+J69 -> 190923.12 | ... AL106: =AL92+AL78+AL79+AL69 -> -97924.71
A107: Total liabilities | C107: =C80+C75 -> 167156.72 | D107: =D80+D75 -> 165410.35 | E107: =E80+E75 -> 163663.36 | F107: =F80+F75 -> 161915.75 | G107: =G80+G75 -> 160167.52 | H107: =H80+H75 -> 158418.7 | I107: =I80+I75 -> 156669.28 | J107: =J80+J75 -> 154919.29 | ... AL107: =AL80+AL75 -> 106617
A108: Total equity | C108: =C104+C105 -> 91237.254 | D108: =D104+D105 -> 82695.388 | E108: =E104+E105 -> 74376.872 | F108: =F104+F105 -> 66277.91 | G108: =G104+G105 -> 58394.769 | H108: =H104+H105 -> 50723.776 | I108: =I104+I105 -> 43261.315 | J108: =J104+J105 -> 36003.828 | ... AL108: =AL104+AL105 -> -204541.71
A109: Total liabilities & equity | C109: =C107+C108 -> 258393.97 | D109: =D107+D108 -> 248105.74 | E109: =E107+E108 -> 238040.23 | F109: =F107+F108 -> 228193.66 | G109: =G107+G108 -> 218562.29 | H109: =H107+H108 -> 209142.47 | I109: =I107+I108 -> 199930.6 | J109: =J107+J108 -> 190923.12 | ... AL109: =AL107+AL108 -> -97924.71
A110: Check: assets − liabilities − equity | C110: =C106-C109 -> 0 | D110: =D106-D109 -> 0 | E110: =E106-E109 -> 0 | F110: =F106-F109 -> 0 | G110: =G106-G109 -> 0 | H110: =H106-H109 -> 0 | I110: =I106-I109 -> 0 | J110: =J106-J109 -> 0 | ... AL110: =AL106-AL109 -> 0
A112: Headcount (FTE)
A113: Owner dentist — FTE | C113: =Inputs!$B$59*(1+Inputs!$B$61)^(C$7-1)*MAX(0,MIN(1,C$6*1-Inputs!$B$62+1))/1 -> 1 | D113: =Inputs!$B$59*(1+Inputs!$B$61)^(D$7-1)*MAX(0,MIN(1,D$6*1-Inputs!$B$62+1))/1 -> 1 | E113: =Inputs!$B$59*(1+Inputs!$B$61)^(E$7-1)*MAX(0,MIN(1,E$6*1-Inputs!$B$62+1))/1 -> 1 | F113: =Inputs!$B$59*(1+Inputs!$B$61)^(F$7-1)*MAX(0,MIN(1,F$6*1-Inputs!$B$62+1))/1 -> 1 | G113: =Inputs!$B$59*(1+Inputs!$B$61)^(G$7-1)*MAX(0,MIN(1,G$6*1-Inputs!$B$62+1))/1 -> 1 | H113: =Inputs!$B$59*(1+Inputs!$B$61)^(H$7-1)*MAX(0,MIN(1,H$6*1-Inputs!$B$62+1))/1 -> 1 | I113: =Inputs!$B$59*(1+Inputs!$B$61)^(I$7-1)*MAX(0,MIN(1,I$6*1-Inputs!$B$62+1))/1 -> 1 | J113: =Inputs!$B$59*(1+Inputs!$B$61)^(J$7-1)*MAX(0,MIN(1,J$6*1-Inputs!$B$62+1))/1 -> 1 | ... AL113: =Inputs!$B$59*(1+Inputs!$B$61)^(AL$7-1)*MAX(0,MIN(1,AL$6*1-Inputs!$B$62+1))/1 -> 1
A114: Hygienists — FTE | C114: =Inputs!$B$63*(1+Inputs!$B$65)^(C$7-1)*MAX(0,MIN(1,C$6*1-Inputs!$B$66+1))/1 -> 3 | D114: =Inputs!$B$63*(1+Inputs!$B$65)^(D$7-1)*MAX(0,MIN(1,D$6*1-Inputs!$B$66+1))/1 -> 3 | E114: =Inputs!$B$63*(1+Inputs!$B$65)^(E$7-1)*MAX(0,MIN(1,E$6*1-Inputs!$B$66+1))/1 -> 3 | F114: =Inputs!$B$63*(1+Inputs!$B$65)^(F$7-1)*MAX(0,MIN(1,F$6*1-Inputs!$B$66+1))/1 -> 3 | G114: =Inputs!$B$63*(1+Inputs!$B$65)^(G$7-1)*MAX(0,MIN(1,G$6*1-Inputs!$B$66+1))/1 -> 3 | H114: =Inputs!$B$63*(1+Inputs!$B$65)^(H$7-1)*MAX(0,MIN(1,H$6*1-Inputs!$B$66+1))/1 -> 3 | I114: =Inputs!$B$63*(1+Inputs!$B$65)^(I$7-1)*MAX(0,MIN(1,I$6*1-Inputs!$B$66+1))/1 -> 3 | J114: =Inputs!$B$63*(1+Inputs!$B$65)^(J$7-1)*MAX(0,MIN(1,J$6*1-Inputs!$B$66+1))/1 -> 3 | ... AL114: =Inputs!$B$63*(1+Inputs!$B$65)^(AL$7-1)*MAX(0,MIN(1,AL$6*1-Inputs!$B$66+1))/1 -> 3.3708
...

Sheet Checks
A1: Model checks | E1: =HYPERLINK("#'Cover'!A1","◂ Contents") -> ◂ Contents
A2: Live formulas: they re-run every time an input changes.
A3: Check | B3: Result | C3: What it tests
A4: Annual revenue ties to period detail | B4: =IF(ABS(SUM('P&L'!$B$5:$D$5)-SUM(Monthly!$C$31:$AL$31))<0.5,"PASS","FAIL") -> PASS | C4: Sum of annual revenue equals the sum of every period
A5: Annual net income ties to period detail | B5: =IF(ABS(SUM('P&L'!$B$26:$D$26)-SUM(Monthly!$C$60:$AL$60))<0.5,"PASS","FAIL") -> PASS | C5: Sum of annual net income equals the sum of every period
A6: EBITDA reconciliation | B6: =IF(ABS(SUM(Monthly!$C$51:$AL$51)-SUM(Monthly!$C$38:$AL$38)-SUM(Monthly!$C$50:$AL$50))<0.5,"PASS","FAIL") -> PASS | C6: EBITDA = gross profit + operating expenses (costs are negative)
A7: Cash roll-forward | B7: =IF(ABS(INDEX(Monthly!$C$90:$AL$90,36)-SUM(Monthly!$C$88:$AL$88))<0.5,"PASS","FAIL") -> PASS | C7: Closing cash = all net cash flows since the start (opening cash is zero)
A8: Scenario selector valid | B8: =IF(AND(ISNUMBER(Dashboard!B4),Dashboard!B4>=1,Dashboard!B4<=3,INT(Dashboard!B4)=Dashboard!B4),"PASS","FAIL") -> PASS | C8: Dashboard!B4 is 1, 2 or 3
A9: Scenario ordering of drivers | B9: =IF(AND(Inputs!$B$9<=Inputs!$C$9,Inputs!$C$9<=Inputs!$D$9,Inputs!$B$10<=Inputs!$C$10,Inputs!$C$10<=Inputs!$D$10,Inputs!$B$11<=Inputs!$C$11,Inputs!$C$11<=Inputs!$D$11,Inputs!$B$14<=Inputs!$C$14,Inputs!$C$14<=Inputs!$D$14,Inputs!$B$15<=Inputs!$C$15,Inputs!$C$15<=Inputs!$D$15,Inputs!$B$16<=Inputs!$C$16,Inputs!$C$16<=Inputs!$D$16,Inputs!$B$18<=Inputs!$C$18,Inputs!$C$18<=Inputs!$D$18,Inputs!$B$19>=Inputs!$C$19,Inputs!$C$19>=Inputs!$D$19,Inputs!$B$20>=Inputs!$C$20,Inputs!$C$20>=Inputs!$D$20,Inputs!$B$21<=Inputs!$C$21,Inputs!$C$21<=Inputs!$D$21,Inputs!$B$22<=Inputs!$C$22,Inputs!$C$22<=Inputs!$D$22,Inputs!$B$23<=Inputs!$C$23,Inputs!$C$23<=Inputs!$D$23,Inputs!$B$26<=Inputs!$C$26,Inputs!$C$26<=Inputs!$D$26,Inputs!$B$27<=Inputs!$C$27,Inputs!$C$27<=Inputs!$D$27,Inputs!$B$28<=Inputs!$C$28,Inputs!$C$28<=Inputs!$D$28,Inputs!$B$31>=Inputs!$C$31,Inputs!$C$31>=Inputs!$D$31,Inputs!$B$32>=Inputs!$C$32,Inputs!$C$32>=Inputs!$D$32,Inputs!$B$33>=Inputs!$C$33,Inputs!$C$33>=Inputs!$D$33,Inputs!$B$36>=Inputs!$C$36,Inputs!$C$36>=Inputs!$D$36,Inputs!$B$37>=Inputs!$C$37,Inputs!$C$37>=Inputs!$D$37,Inputs!$B$38>=Inputs!$C$38,Inputs!$C$38>=Inputs!$D$38,Inputs!$B$40>=Inputs!$C$40,Inputs!$C$40>=Inputs!$D$40,Inputs!$B$49>=Inputs!$C$49,Inputs!$C$49>=Inputs!$D$49,Inputs!$B$56>=Inputs!$C$56,Inputs!$C$56>=Inputs!$D$56,Inputs!$B$59<=Inputs!$C$59,Inputs!$C$59<=Inputs!$D$59,Inputs!$B$61<=Inputs!$C$61,Inputs!$C$61<=Inputs!$D$61,Inputs!$B$63<=Inputs!$C$63,Inputs!$C$63<=Inputs!$D$63,Inputs!$B$65<=Inputs!$C$65,Inputs!$C$65<=Inputs!$D$65,Inputs!$B$67<=Inputs!$C$67,Inputs!$C$67<=Inputs!$D$67,Inputs!$B$69<=Inputs!$C$69,Inputs!$C$69<=Inputs!$D$69,Inputs!$B$71<=Inputs!$C$71,Inputs!$C$71<=Inputs!$D$71,Inputs!$B$73<=Inputs!$C$73,Inputs!$C$73<=Inputs!$D$73,Inputs!$B$75<=Inputs!$C$75,Inputs!$C$75<=Inputs!$D$75,Inputs!$B$77<=Inputs!$C$77,Inputs!$C$77<=Inputs!$D$77,Inputs!$B$101>=Inputs!$C$101,Inputs!$C$101>=Inputs!$D$101,Inputs!$B$102<=Inputs!$C$102,Inputs!$C$102<=Inputs!$D$102,Inputs!$B$103<=Inputs!$C$103,Inputs!$C$103<=Inputs!$D$103),"PASS","FAIL") -> PASS | C9: Low / Base / High ordered the right way for every growth and cost driver
A10: Gross margin within 0–100% | B10: =IF(AND(MIN('P&L'!$B$8:$D$8)>=0,MAX('P&L'!$B$8:$D$8)<=1),"PASS","FAIL") -> PASS | C10: Gross margin never negative or above 100%
A11: Loan balance never negative | B11: =IF(MIN(Monthly!$C$73:$AL$73)>=-0.5,"PASS","FAIL") -> PASS | C11: Repayments never exceed the loan
A12: Funding table ties to the cash flow | B12: =IF(ABS('Break-even'!B18-('Break-even'!B16-'Break-even'!B10))<0.5,"PASS","FAIL") -> PASS | C12: Lowest cash balance = sources of funds − uses of funds up to that point
A13: Valuation: discounting ties to NPV() | B13: =IF(ABS(Valuation!B23-NPV(Valuation!B6,Valuation!$B$17:$D$17))<0.5,"PASS","FAIL") -> PASS | C13: Sum of discounted free cash flows equals Excel's NPV of the same flows
A14: Valuation: WACC above terminal growth | B14: =IF(Valuation!B6>Valuation!B7,"PASS","FAIL") -> PASS | C14: The perpetual-growth formula needs WACC > g
A15: Valuation: sensitivity centre = enterprise value | B15: =IF(ABS(Valuation!D36-Valuation!B27)<0.5,"PASS","FAIL") -> PASS | C15: The middle of the WACC × growth table reproduces the headline value
A16: Valuation: final-year cash flow positive | B16: =IF(Valuation!$D$17>0,"PASS","WARN") -> PASS | C16: Business warning: a negative final-year cash flow gives a negative terminal value (often a 1-year plan still carrying start-up spending)
A17: Sources & uses balance | B17: =IF(ABS('Sources & Uses'!B21-'Sources & Uses'!B28)<0.5,"PASS","FAIL") -> PASS | C17: Sources of funds = uses of funds (incl. cash at the end) for the Sources & Uses period
A18: No error values | B18: =IF(SUMPRODUCT(--ISERROR(Monthly!$C$4:$AL$108))+SUMPRODUCT(--ISERROR(Headcount!$C$4:$AL$21))+SUMPRODUCT(--ISERROR('P&L'!$B$3:$D$27))+SUMPRODUCT(--ISERROR('Cash Flow'!$B$3:$D$18))+SUMPRODUCT(--ISERROR('Balance Sheet'!$B$3:$D$17))+SUMPRODUCT(--ISERROR(KPIs!$B$27:$D$53))+SUMPRODUCT(--ISERROR('Break-even'!$B$26:$D$33))+SUMPRODUCT(--ISERROR(Valuation!$B$14:$D$19))+SUMPRODUCT(--ISERROR('Break-even'!$B$3:$D$35))+SUMPRODUCT(--ISERROR(Valuation!$A$3:$F$40))+SUMPRODUCT(--ISERROR('Sources & Uses'!$B$3:$C$30))+SUMPRODUCT(--ISERROR(Dashboard!$A$6:$W$43))+SUMPRODUCT(--ISERROR(Summary!$A$5:$S$52))+SUMPRODUCT(--ISERROR(KPIs!$A$4:$E$53))+SUMPRODUCT(--ISERROR('Scenario calc'!$C$6:$AL$126))+SUMPRODUCT(--ISERROR('Scenario calc'!$C$131:$AL$251))+SUMPRODUCT(--ISERROR('Scenario calc'!$C$256:$AL$376))+SUMPRODUCT(--ISERROR(Scenarios!$B$5:$E$50))=0,"PASS","FAIL") -> PASS | C18: No error values (divide-by-zero, broken references) on any calculation sheet
A19: Summary ties to statements | B19: =IF(IFERROR(AND(SUMPRODUCT(--(ABS(Summary!$B$7:$D$7-'P&L'!$B$5:$D$5)>0.5))=0,SUMPRODUCT(--(ABS(Summary!$B$19:$D$19-'P&L'!$B$26:$D$26)>0.5))=0,SUMPRODUCT(--(ABS(Summary!$B$31:$D$31-'Cash Flow'!$B$18:$D$18)>0.5))=0,SUMPRODUCT(--(ABS(Summary!$B$41:$D$41-'Balance Sheet'!$B$5:$D$5)>0.5))=0,ABS(SUM(Summary!$H$7:$S$7)-INDEX(Summary!$B$7:$D$7,Summary!$R$2))<0.5,ABS(SUM(Summary!$H$19:$S$19)-INDEX(Summary!$B$19:$D$19,Summary!$R$2))<0.5,ABS(Summary!$S$31-INDEX(Summary!$B$31:$D$31,Summary!$R$2))<0.5),FALSE()),"PASS","FAIL") -> PASS | C19: Summary revenue, net income and closing cash equal the statements every year; the detailed year adds up to its annual figure
A20: DuPont ties to return on equity | B20: =IF(SUMPRODUCT(--(ABS(KPIs!$B$24:$D$24)>0.000000001))>0,"FAIL",IF(SUMPRODUCT(ISNUMBER(KPIs!$B$23:$D$23)*ISNUMBER(KPIs!$B$16:$D$16))=0,"n/a","PASS")) -> PASS | C20: Net margin × asset turnover × equity multiplier equals return on equity every year; n/a = no year where both are defined (a one-sided n/a is a FAIL)
A21: Scenarios: Active = selected scenario | B21: =IF(IFERROR(AND(ABS(Scenarios!E17-INDEX(Scenarios!B17:D17,1,Dashboard!$B$4))<0.5,ABS(Scenarios!E18-INDEX(Scenarios!B18:D18,1,Dashboard!$B$4))<0.5,ABS(Scenarios!E19-INDEX(Scenarios!B19:D19,1,Dashboard!$B$4))<0.5,ABS(Scenarios!E20-INDEX(Scenarios!B20:D20,1,Dashboard!$B$4))<0.000001,ABS(Scenarios!E21-INDEX(Scenarios!B21:D21,1,Dashboard!$B$4))<0.5,ABS(Scenarios!E22-INDEX(Scenarios!B22:D22,1,Dashboard!$B$4))<0.5,ABS(Scenarios!E23-INDEX(Scenarios!B23:D23,1,Dashboard!$B$4))<0.5,ABS(Scenarios!E24-INDEX(Scenarios!B24:D24,1,Dashboard!$B$4))<0.5,ABS(Scenarios!E25-INDEX(Scenarios!B25:D25,1,Dashboard!$B$4))<0.5,ABS(Scenarios!E26-INDEX(Scenarios!B26:D26,1,Dashboard!$B$4))<0.5),FALSE()),"PASS","FAIL") -> PASS | C21: On the Scenarios sheet the live model (Active) equals the Low / Base / High column chosen on the Dashboard for every output
A22: Balance sheet balances every period | B22: =IF(SUMPRODUCT(--(ABS(Monthly!$C$108:$AL$108)>0.5))=0,"PASS","FAIL") -> PASS | C22: Assets = liabilities + equity in every period
A23: Funding sufficient (cash ≥ 0) | B23: =IF(MIN(Monthly!$C$90:$AL$90)>=0,"PASS","WARN") -> PASS | C23: Business warning, not an error: cash dips below zero in this scenario
A25: Overall verdict | B25: =IF(COUNTIF(B4:B23,"FAIL")>0,"FAIL",IF(COUNTIF(B4:B23,"WARN")>0,"PASS WITH WARNINGS","PASS")) -> PASS
