Workbook

Sheet Cover
B2: Fitness studio financial model (planning)
B3: 3-year financial model · monthly detail · Low / Base / High scenarios · US dollars · Full plan
B5: Purpose | D5: Revenue and profit plan
B6: Active scenario | D6: =Dashboard!C4&" (change it on the Dashboard, cell B4)" -> Base (change it on the Dashboard, cell B4)
B7: Model checks | D7: =Checks!B25 -> PASS
B8: Prepared | D8: 22 October 2026
B10: Contents
C11: PRESENTATION
B12: 1 | C12: =HYPERLINK("#Dashboard!A1","Dashboard") -> Dashboard | D12: Scenario switch, key numbers, core financials
B13: 2 | C13: =HYPERLINK("#Summary!A1","Summary") -> Summary | D13: Income statement, cash flow and balance sheet — every year and any year by month
B14: 3 | C14: =HYPERLINK("#Scenarios!A1","Scenarios") -> Scenarios | D14: Low / Base / High side by side: drivers, outputs, charts
B15: 4 | C15: =HYPERLINK("#'Break-even'!A1","Break-even") -> Break-even | D15: Startup costs, funding need, break-even timing and revenue
B16: 5 | C16: =HYPERLINK("#Valuation!A1","Valuation") -> Valuation | D16: Free cash flow, DCF (perpetual growth and exit multiple), WACC × growth sensitivity
B17: 6 | C17: =HYPERLINK("#'Sources & Uses'!A1","Sources & Uses") -> Sources & Uses | D17: Funding structure, sources and uses of cash for the first months
B18: 7 | C18: =HYPERLINK("#KPIs!A1","KPIs") -> KPIs | D18: Financial ratios, DuPont analysis, industry metrics
C19: INPUTS
B20: 8 | C20: =HYPERLINK("#Inputs!A1","Inputs") -> Inputs | D20: Every assumption, Low / Base / High, with units and comments
C21: STATEMENTS
B22: 9 | C22: =HYPERLINK("#'P&L'!A1","P&L") -> P&L | D22: Annual profit & loss
B23: 10 | C23: =HYPERLINK("#'Cash Flow'!A1","Cash Flow") -> Cash Flow | D23: Annual cash flow statement
B24: 11 | C24: =HYPERLINK("#'Balance Sheet'!A1","Balance Sheet") -> Balance Sheet | D24: Balance sheet at year end
C25: CALCULATIONS
B26: 12 | C26: =HYPERLINK("#Monthly!A1","Monthly") -> Monthly | D26: Month-by-month engine of the model
B27: 13 | C27: =HYPERLINK("#Headcount!A1","Headcount") -> Headcount | D27: Team and payroll
B28: 14 | C28: =HYPERLINK("#'Scenario calc'!A1","Scenario calc") -> Scenario calc | D28: Low, Base and High calculated side by side for the Scenarios sheet
C29: CONTROL
B30: 15 | C30: =HYPERLINK("#Checks!A1","Checks") -> Checks | D30: Live integrity checks and the overall verdict
B32: How to read this file
C33: 1000 | D33: Input you can change — yellow cell with a blue figure (Inputs sheet and the view switches)
C34: 1000 | D34: Formula — calculated, do not overwrite
C35: 1000 | D35: Link to another sheet
C36: 1000 | D36: Active value the model uses (follows the scenario)

Sheet Dashboard
A1: Dashboard | W1: =HYPERLINK("#'Cover'!A1","◂ Contents") -> ◂ Contents
A2: Fitness studio financial model (planning)
A4: Active scenario | B4: 2 | C4: =CHOOSE(B4,"Low","Base","High") -> Base | D4: 1 = Low · 2 = Base · 3 = High — every sheet follows this cell | S4: Model checks | T4: =Checks!B25 -> PASS
A6: REVENUE · YEAR 3 | C6: EBITDA MARGIN · YEAR 3 | H6: NET INCOME · YEAR 3 | L6: LOWEST CASH BALANCE | P6: FUNDING REQUIRED | T6: ENTERPRISE VALUE (DCF)
A7: =D12 -> 722638.4 | C7: =D17 -> 0.11067489 | H7: =D18 -> 36406.5 | L7: =F38 -> 7440.3636 | P7: =F36 -> 583559.64 | T7: =F43 -> -109106.8
A8: =IF(AND(B12>0,D12>=0),(D12/B12)^(1/2)-1,"CAGR n/a") -> 0.35588405 | C8: =D16 -> 79977.928 | H8: =D19 -> 0.050379968 | L8: ='Break-even'!B6 -> 16 | P8: =IF(F37>=0,"Covered by funding raised",-F37) -> 103559.64 | T8: Average of 2 methods
A10: Core financials ($'000) — active scenario
B11: 1 | C11: 2 | D11: 3
A12: Revenue | B12: =SUMIF(Monthly!$C$5:$AL$5,B$11,Monthly!$C$24:$AL$24) -> 393075.46 | C12: =SUMIF(Monthly!$C$5:$AL$5,C$11,Monthly!$C$24:$AL$24) -> 663933.88 | D12: =SUMIF(Monthly!$C$5:$AL$5,D$11,Monthly!$C$24:$AL$24) -> 722638.4
A13: Gross profit | B13: =SUMIF(Monthly!$C$5:$AL$5,B$11,Monthly!$C$31:$AL$31) -> 262844.88 | C13: =SUMIF(Monthly!$C$5:$AL$5,C$11,Monthly!$C$31:$AL$31) -> 504280.12 | D13: =SUMIF(Monthly!$C$5:$AL$5,D$11,Monthly!$C$31:$AL$31) -> 554018.95
A14: Gross margin | B14: =IF(B12=0,0,B13/B12) -> 0.6686881 | C14: =IF(C12=0,0,C13/C12) -> 0.75953364 | D14: =IF(D12=0,0,D13/D12) -> 0.76666138
A15: Operating expenses | B15: =SUMIF(Monthly!$C$5:$AL$5,B$11,Monthly!$C$41:$AL$41) -> -445823.02 | C15: =SUMIF(Monthly!$C$5:$AL$5,C$11,Monthly!$C$41:$AL$41) -> -464040.36 | D15: =SUMIF(Monthly!$C$5:$AL$5,D$11,Monthly!$C$41:$AL$41) -> -474041.03
A16: EBITDA | B16: =SUMIF(Monthly!$C$5:$AL$5,B$11,Monthly!$C$42:$AL$42) -> -182978.13 | C16: =SUMIF(Monthly!$C$5:$AL$5,C$11,Monthly!$C$42:$AL$42) -> 40239.768 | D16: =SUMIF(Monthly!$C$5:$AL$5,D$11,Monthly!$C$42:$AL$42) -> 79977.928
A17: EBITDA margin | B17: =IF(B12=0,0,B16/B12) -> -0.46550384 | C17: =IF(C12=0,0,C16/C12) -> 0.060608094 | D17: =IF(D12=0,0,D16/D12) -> 0.11067489
A18: Net income | B18: =SUMIF(Monthly!$C$5:$AL$5,B$11,Monthly!$C$51:$AL$51) -> -229972.18 | C18: =SUMIF(Monthly!$C$5:$AL$5,C$11,Monthly!$C$51:$AL$51) -> -5045.9468 | D18: =SUMIF(Monthly!$C$5:$AL$5,D$11,Monthly!$C$51:$AL$51) -> 36406.5
A19: Net margin | B19: =IF(B12=0,0,B18/B12) -> -0.58505861 | C19: =IF(C12=0,0,C18/C12) -> -0.0076000742 | D19: =IF(D12=0,0,D18/D12) -> 0.050379968
A20: Operating cash flow | B20: =SUMIF(Monthly!$C$5:$AL$5,B$11,Monthly!$C$75:$AL$75) -> -190250.26 | C20: =SUMIF(Monthly!$C$5:$AL$5,C$11,Monthly!$C$75:$AL$75) -> 31208.152 | D20: =SUMIF(Monthly!$C$5:$AL$5,D$11,Monthly!$C$75:$AL$75) -> 72257.209
A21: Investing cash flow | B21: =SUMIF(Monthly!$C$5:$AL$5,B$11,Monthly!$C$76:$AL$76) -> -250000 | C21: =SUMIF(Monthly!$C$5:$AL$5,C$11,Monthly!$C$76:$AL$76) -> 0 | D21: =SUMIF(Monthly!$C$5:$AL$5,D$11,Monthly!$C$76:$AL$76) -> 0
A22: Financing cash flow | B22: =SUMIF(Monthly!$C$5:$AL$5,B$11,Monthly!$C$78:$AL$78) -> 460357.14 | C22: =SUMIF(Monthly!$C$5:$AL$5,C$11,Monthly!$C$78:$AL$78) -> -21428.571 | D22: =SUMIF(Monthly!$C$5:$AL$5,D$11,Monthly!$C$78:$AL$78) -> -21428.571
A23: Net change in cash | B23: =SUMIF(Monthly!$C$5:$AL$5,B$11,Monthly!$C$79:$AL$79) -> 20106.884 | C23: =SUMIF(Monthly!$C$5:$AL$5,C$11,Monthly!$C$79:$AL$79) -> 9779.5808 | D23: =SUMIF(Monthly!$C$5:$AL$5,D$11,Monthly!$C$79:$AL$79) -> 50828.638
A24: Year-end cash | B24: =INDEX(Monthly!$C$81:$AL$81,B$11*12) -> 20106.884 | C24: =INDEX(Monthly!$C$81:$AL$81,C$11*12) -> 29886.464 | D24: =INDEX(Monthly!$C$81:$AL$81,D$11*12) -> 80715.102
A26: Membership metrics
B27: 1 | C27: 2 | D27: 3
A28: Members (year end) | B28: =KPIs!B29 -> 355.83586 | C28: =KPIs!C29 -> 450 | D28: =KPIs!D29 -> 450
A29: Capacity used (year end) | B29: =KPIs!B33 -> 0.79074635 | C29: =KPIs!C33 -> 1 | D29: =KPIs!D33 -> 1
A30: Membership fees per month (year end) | B30: =KPIs!B34 -> 35227.75 | C30: =KPIs!C34 -> 45886.5 | D30: =KPIs!D34 -> 47263.095
A31: Team (FTE, year end) | B31: =INDEX(Headcount!$C$10:$AL$10,B$27*12) -> 4 | C31: =INDEX(Headcount!$C$10:$AL$10,C$27*12) -> 4 | D31: =INDEX(Headcount!$C$10:$AL$10,D$27*12) -> 4
A33: Funding & valuation ($'000) — active scenario
A34: Equity raised | F34: =Inputs!$E$54 -> 330000
A35: Loan drawn | F35: =Inputs!$E$55 -> 150000
A36: Funding required (incl. cash buffer) | F36: ='Break-even'!B12 -> 583559.64
A37: Funding surplus / (shortfall) | F37: ='Break-even'!B17 -> -103559.64
A38: ="Lowest cash balance (month "&'Break-even'!B6&")" -> Lowest cash balance (month 16) | F38: ='Break-even'!B18 -> 7440.3636
A39: First month with positive EBITDA | F39: ='Break-even'!B21 -> 15
A40: Cash invested paid back | F40: ='Break-even'!B23 -> Not within horizon
A41: Enterprise value — perpetual growth | F41: =Valuation!B27 -> -101923.28
A42: Enterprise value — exit multiple | F42: =Valuation!C27 -> -116290.32
A43: Enterprise value — average | F43: =Valuation!B30 -> -109106.8

Sheet Summary
A1: Financial statements summary | U1: =HYPERLINK("#'Cover'!A1","◂ Contents") -> ◂ Contents
A2: Fitness studio financial model (planning) | P2: Select detailed year: | R2: 1
A5: Income statement ($'000) — by year | H5: ="Income statement ($'000) — Year "&$R$2&", by month" -> Income statement ($'000) — Year 1, by month
B6: 1 | C6: 2 | D6: 3 | H6: =INDEX(Monthly!$C$4:$AL$4,($R$2-1)*12+1) -> 1 | I6: =INDEX(Monthly!$C$4:$AL$4,($R$2-1)*12+2) -> 2 | J6: =INDEX(Monthly!$C$4:$AL$4,($R$2-1)*12+3) -> 3 | K6: =INDEX(Monthly!$C$4:$AL$4,($R$2-1)*12+4) -> 4 | L6: =INDEX(Monthly!$C$4:$AL$4,($R$2-1)*12+5) -> 5 | M6: =INDEX(Monthly!$C$4:$AL$4,($R$2-1)*12+6) -> 6 | N6: =INDEX(Monthly!$C$4:$AL$4,($R$2-1)*12+7) -> 7 | O6: =INDEX(Monthly!$C$4:$AL$4,($R$2-1)*12+8) -> 8 | P6: =INDEX(Monthly!$C$4:$AL$4,($R$2-1)*12+9) -> 9 | Q6: =INDEX(Monthly!$C$4:$AL$4,($R$2-1)*12+10) -> 10 | R6: =INDEX(Monthly!$C$4:$AL$4,($R$2-1)*12+11) -> 11 | S6: =INDEX(Monthly!$C$4:$AL$4,($R$2-1)*12+12) -> 12
A7: Revenue | B7: ='P&L'!B5 -> 393075.46 | C7: ='P&L'!C5 -> 663933.88 | D7: ='P&L'!D5 -> 722638.4 | H7: =INDEX(Monthly!$C$24:$AL$24,($R$2-1)*12+1) -> 18123 | I7: =INDEX(Monthly!$C$24:$AL$24,($R$2-1)*12+2) -> 21349.608 | J7: =INDEX(Monthly!$C$24:$AL$24,($R$2-1)*12+3) -> 24382.62 | K7: =INDEX(Monthly!$C$24:$AL$24,($R$2-1)*12+4) -> 27233.65 | L7: =INDEX(Monthly!$C$24:$AL$24,($R$2-1)*12+5) -> 29913.619 | M7: =INDEX(Monthly!$C$24:$AL$24,($R$2-1)*12+6) -> 32432.79 | N7: =INDEX(Monthly!$C$24:$AL$24,($R$2-1)*12+7) -> 34800.811 | O7: =INDEX(Monthly!$C$24:$AL$24,($R$2-1)*12+8) -> 37026.75 | P7: =INDEX(Monthly!$C$24:$AL$24,($R$2-1)*12+9) -> 39119.133 | Q7: =INDEX(Monthly!$C$24:$AL$24,($R$2-1)*12+10) -> 41085.973 | R7: =INDEX(Monthly!$C$24:$AL$24,($R$2-1)*12+11) -> 42934.803 | S7: =INDEX(Monthly!$C$24:$AL$24,($R$2-1)*12+12) -> 44672.703
A8: Cost of sales | B8: ='P&L'!B6 -> -130230.58 | C8: ='P&L'!C6 -> -159653.76 | D8: ='P&L'!D6 -> -168619.45 | H8: =INDEX(Monthly!$C$30:$AL$30,($R$2-1)*12+1) -> -9415.35 | I8: =INDEX(Monthly!$C$30:$AL$30,($R$2-1)*12+2) -> -9732.249 | J8: =INDEX(Monthly!$C$30:$AL$30,($R$2-1)*12+3) -> -10030.134 | K8: =INDEX(Monthly!$C$30:$AL$30,($R$2-1)*12+4) -> -10310.146 | L8: =INDEX(Monthly!$C$30:$AL$30,($R$2-1)*12+5) -> -10573.357 | M8: =INDEX(Monthly!$C$30:$AL$30,($R$2-1)*12+6) -> -10820.776 | N8: =INDEX(Monthly!$C$30:$AL$30,($R$2-1)*12+7) -> -11053.349 | O8: =INDEX(Monthly!$C$30:$AL$30,($R$2-1)*12+8) -> -11271.968 | P8: =INDEX(Monthly!$C$30:$AL$30,($R$2-1)*12+9) -> -11477.47 | Q8: =INDEX(Monthly!$C$30:$AL$30,($R$2-1)*12+10) -> -11670.642 | R8: =INDEX(Monthly!$C$30:$AL$30,($R$2-1)*12+11) -> -11852.223 | S8: =INDEX(Monthly!$C$30:$AL$30,($R$2-1)*12+12) -> -12022.91
A9: Gross profit | B9: ='P&L'!B7 -> 262844.88 | C9: ='P&L'!C7 -> 504280.12 | D9: ='P&L'!D7 -> 554018.95 | H9: =INDEX(Monthly!$C$31:$AL$31,($R$2-1)*12+1) -> 8707.65 | I9: =INDEX(Monthly!$C$31:$AL$31,($R$2-1)*12+2) -> 11617.359 | J9: =INDEX(Monthly!$C$31:$AL$31,($R$2-1)*12+3) -> 14352.485 | K9: =INDEX(Monthly!$C$31:$AL$31,($R$2-1)*12+4) -> 16923.504 | L9: =INDEX(Monthly!$C$31:$AL$31,($R$2-1)*12+5) -> 19340.262 | M9: =INDEX(Monthly!$C$31:$AL$31,($R$2-1)*12+6) -> 21612.014 | N9: =INDEX(Monthly!$C$31:$AL$31,($R$2-1)*12+7) -> 23747.461 | O9: =INDEX(Monthly!$C$31:$AL$31,($R$2-1)*12+8) -> 25754.782 | P9: =INDEX(Monthly!$C$31:$AL$31,($R$2-1)*12+9) -> 27641.663 | Q9: =INDEX(Monthly!$C$31:$AL$31,($R$2-1)*12+10) -> 29415.331 | R9: =INDEX(Monthly!$C$31:$AL$31,($R$2-1)*12+11) -> 31082.579 | S9: =INDEX(Monthly!$C$31:$AL$31,($R$2-1)*12+12) -> 32649.792
A10: Gross margin | B10: ='P&L'!B8 -> 0.6686881 | C10: ='P&L'!C8 -> 0.75953364 | D10: ='P&L'!D8 -> 0.76666138 | H10: =IF(H7=0,0,H9/H7) -> 0.48047509 | I10: =IF(I7=0,0,I9/I7) -> 0.54414859 | J10: =IF(J7=0,0,J9/J7) -> 0.58863591 | K10: =IF(K7=0,0,K9/K7) -> 0.62141887 | L10: =IF(L7=0,0,L9/L7) -> 0.64653701 | M10: =IF(M7=0,0,M9/M7) -> 0.66636309 | N10: =IF(N7=0,0,N9/N7) -> 0.68238242 | O10: =IF(O7=0,0,O9/O7) -> 0.6955723 | ... S10: =IF(S7=0,0,S9/S7) -> 0.73086674
A11: Total operating expenses | B11: ='P&L'!B16 -> -445823.02 | C11: ='P&L'!C16 -> -464040.36 | D11: ='P&L'!D16 -> -474041.03 | H11: =INDEX(Monthly!$C$41:$AL$41,($R$2-1)*12+1) -> -36566.587 | I11: =INDEX(Monthly!$C$41:$AL$41,($R$2-1)*12+2) -> -36695.651 | J11: =INDEX(Monthly!$C$41:$AL$41,($R$2-1)*12+3) -> -36816.971 | K11: =INDEX(Monthly!$C$41:$AL$41,($R$2-1)*12+4) -> -36931.013 | L11: =INDEX(Monthly!$C$41:$AL$41,($R$2-1)*12+5) -> -37038.211 | M11: =INDEX(Monthly!$C$41:$AL$41,($R$2-1)*12+6) -> -37138.978 | N11: =INDEX(Monthly!$C$41:$AL$41,($R$2-1)*12+7) -> -37233.699 | O11: =INDEX(Monthly!$C$41:$AL$41,($R$2-1)*12+8) -> -37322.737 | P11: =INDEX(Monthly!$C$41:$AL$41,($R$2-1)*12+9) -> -37406.432 | Q11: =INDEX(Monthly!$C$41:$AL$41,($R$2-1)*12+10) -> -37485.106 | R11: =INDEX(Monthly!$C$41:$AL$41,($R$2-1)*12+11) -> -37559.059 | S11: =INDEX(Monthly!$C$41:$AL$41,($R$2-1)*12+12) -> -37628.575
A12: EBITDA | B12: ='P&L'!B17 -> -182978.13 | C12: ='P&L'!C17 -> 40239.768 | D12: ='P&L'!D17 -> 79977.928 | H12: =INDEX(Monthly!$C$42:$AL$42,($R$2-1)*12+1) -> -27858.937 | I12: =INDEX(Monthly!$C$42:$AL$42,($R$2-1)*12+2) -> -25078.292 | J12: =INDEX(Monthly!$C$42:$AL$42,($R$2-1)*12+3) -> -22464.486 | K12: =INDEX(Monthly!$C$42:$AL$42,($R$2-1)*12+4) -> -20007.508 | L12: =INDEX(Monthly!$C$42:$AL$42,($R$2-1)*12+5) -> -17697.949 | M12: =INDEX(Monthly!$C$42:$AL$42,($R$2-1)*12+6) -> -15526.964 | N12: =INDEX(Monthly!$C$42:$AL$42,($R$2-1)*12+7) -> -13486.238 | O12: =INDEX(Monthly!$C$42:$AL$42,($R$2-1)*12+8) -> -11567.955 | P12: =INDEX(Monthly!$C$42:$AL$42,($R$2-1)*12+9) -> -9764.7691 | Q12: =INDEX(Monthly!$C$42:$AL$42,($R$2-1)*12+10) -> -8069.7745 | R12: =INDEX(Monthly!$C$42:$AL$42,($R$2-1)*12+11) -> -6476.4795 | S12: =INDEX(Monthly!$C$42:$AL$42,($R$2-1)*12+12) -> -4978.7823
A13: EBITDA margin | B13: ='P&L'!B18 -> -0.46550384 | C13: ='P&L'!C18 -> 0.060608094 | D13: ='P&L'!D18 -> 0.11067489 | H13: =IF(H7=0,0,H12/H7) -> -1.5372144 | I13: =IF(I7=0,0,I12/I7) -> -1.1746488 | J13: =IF(J7=0,0,J12/J7) -> -0.92133193 | K13: =IF(K7=0,0,K12/K7) -> -0.73466128 | L13: =IF(L7=0,0,L12/L7) -> -0.59163517 | M13: =IF(M7=0,0,M12/M7) -> -0.47874277 | N13: =IF(N7=0,0,N12/N7) -> -0.38752654 | O13: =IF(O7=0,0,O12/O7) -> -0.31242156 | ... S13: =IF(S7=0,0,S12/S7) -> -0.11145021
A14: Depreciation | B14: ='P&L'!B19 -> -35714.286 | C14: ='P&L'!C19 -> -35714.286 | D14: ='P&L'!D19 -> -35714.286 | H14: =INDEX(Monthly!$C$56:$AL$56,($R$2-1)*12+1) -> -2976.1905 | I14: =INDEX(Monthly!$C$56:$AL$56,($R$2-1)*12+2) -> -2976.1905 | J14: =INDEX(Monthly!$C$56:$AL$56,($R$2-1)*12+3) -> -2976.1905 | K14: =INDEX(Monthly!$C$56:$AL$56,($R$2-1)*12+4) -> -2976.1905 | L14: =INDEX(Monthly!$C$56:$AL$56,($R$2-1)*12+5) -> -2976.1905 | M14: =INDEX(Monthly!$C$56:$AL$56,($R$2-1)*12+6) -> -2976.1905 | N14: =INDEX(Monthly!$C$56:$AL$56,($R$2-1)*12+7) -> -2976.1905 | O14: =INDEX(Monthly!$C$56:$AL$56,($R$2-1)*12+8) -> -2976.1905 | P14: =INDEX(Monthly!$C$56:$AL$56,($R$2-1)*12+9) -> -2976.1905 | Q14: =INDEX(Monthly!$C$56:$AL$56,($R$2-1)*12+10) -> -2976.1905 | R14: =INDEX(Monthly!$C$56:$AL$56,($R$2-1)*12+11) -> -2976.1905 | S14: =INDEX(Monthly!$C$56:$AL$56,($R$2-1)*12+12) -> -2976.1905
A15: EBIT | B15: ='P&L'!B20 -> -218692.42 | C15: ='P&L'!C20 -> 4525.4818 | D15: ='P&L'!D20 -> 44263.643 | H15: =INDEX(Monthly!$C$45:$AL$45,($R$2-1)*12+1) -> -30835.127 | I15: =INDEX(Monthly!$C$45:$AL$45,($R$2-1)*12+2) -> -28054.482 | J15: =INDEX(Monthly!$C$45:$AL$45,($R$2-1)*12+3) -> -25440.676 | K15: =INDEX(Monthly!$C$45:$AL$45,($R$2-1)*12+4) -> -22983.699 | L15: =INDEX(Monthly!$C$45:$AL$45,($R$2-1)*12+5) -> -20674.14 | M15: =INDEX(Monthly!$C$45:$AL$45,($R$2-1)*12+6) -> -18503.154 | N15: =INDEX(Monthly!$C$45:$AL$45,($R$2-1)*12+7) -> -16462.428 | O15: =INDEX(Monthly!$C$45:$AL$45,($R$2-1)*12+8) -> -14544.145 | P15: =INDEX(Monthly!$C$45:$AL$45,($R$2-1)*12+9) -> -12740.96 | Q15: =INDEX(Monthly!$C$45:$AL$45,($R$2-1)*12+10) -> -11045.965 | R15: =INDEX(Monthly!$C$45:$AL$45,($R$2-1)*12+11) -> -9452.67 | S15: =INDEX(Monthly!$C$45:$AL$45,($R$2-1)*12+12) -> -7954.9728
A16: Interest | B16: ='P&L'!B21 -> -11279.762 | C16: ='P&L'!C21 -> -9571.4286 | D16: ='P&L'!D21 -> -7857.1429 | H16: =INDEX(Monthly!$C$46:$AL$46,($R$2-1)*12+1) -> -1000 | I16: =INDEX(Monthly!$C$46:$AL$46,($R$2-1)*12+2) -> -994.04762 | J16: =INDEX(Monthly!$C$46:$AL$46,($R$2-1)*12+3) -> -982.14286 | K16: =INDEX(Monthly!$C$46:$AL$46,($R$2-1)*12+4) -> -970.2381 | L16: =INDEX(Monthly!$C$46:$AL$46,($R$2-1)*12+5) -> -958.33333 | M16: =INDEX(Monthly!$C$46:$AL$46,($R$2-1)*12+6) -> -946.42857 | N16: =INDEX(Monthly!$C$46:$AL$46,($R$2-1)*12+7) -> -934.52381 | O16: =INDEX(Monthly!$C$46:$AL$46,($R$2-1)*12+8) -> -922.61905 | P16: =INDEX(Monthly!$C$46:$AL$46,($R$2-1)*12+9) -> -910.71429 | Q16: =INDEX(Monthly!$C$46:$AL$46,($R$2-1)*12+10) -> -898.80952 | R16: =INDEX(Monthly!$C$46:$AL$46,($R$2-1)*12+11) -> -886.90476 | S16: =INDEX(Monthly!$C$46:$AL$46,($R$2-1)*12+12) -> -875
A17: Pre-tax income | B17: ='P&L'!B22 -> -229972.18 | C17: ='P&L'!C22 -> -5045.9468 | D17: ='P&L'!D22 -> 36406.5 | H17: =INDEX(Monthly!$C$47:$AL$47,($R$2-1)*12+1) -> -31835.127 | I17: =INDEX(Monthly!$C$47:$AL$47,($R$2-1)*12+2) -> -29048.53 | J17: =INDEX(Monthly!$C$47:$AL$47,($R$2-1)*12+3) -> -26422.819 | K17: =INDEX(Monthly!$C$47:$AL$47,($R$2-1)*12+4) -> -23953.937 | L17: =INDEX(Monthly!$C$47:$AL$47,($R$2-1)*12+5) -> -21632.473 | M17: =INDEX(Monthly!$C$47:$AL$47,($R$2-1)*12+6) -> -19449.583 | N17: =INDEX(Monthly!$C$47:$AL$47,($R$2-1)*12+7) -> -17396.952 | O17: =INDEX(Monthly!$C$47:$AL$47,($R$2-1)*12+8) -> -15466.764 | P17: =INDEX(Monthly!$C$47:$AL$47,($R$2-1)*12+9) -> -13651.674 | Q17: =INDEX(Monthly!$C$47:$AL$47,($R$2-1)*12+10) -> -11944.774 | R17: =INDEX(Monthly!$C$47:$AL$47,($R$2-1)*12+11) -> -10339.575 | S17: =INDEX(Monthly!$C$47:$AL$47,($R$2-1)*12+12) -> -8829.9728
A18: Income tax | B18: ='P&L'!B23 -> 0 | C18: ='P&L'!C23 -> 0 | D18: ='P&L'!D23 -> 0 | H18: =INDEX(Monthly!$C$50:$AL$50,($R$2-1)*12+1) -> 0 | I18: =INDEX(Monthly!$C$50:$AL$50,($R$2-1)*12+2) -> 0 | J18: =INDEX(Monthly!$C$50:$AL$50,($R$2-1)*12+3) -> 0 | K18: =INDEX(Monthly!$C$50:$AL$50,($R$2-1)*12+4) -> 0 | L18: =INDEX(Monthly!$C$50:$AL$50,($R$2-1)*12+5) -> 0 | M18: =INDEX(Monthly!$C$50:$AL$50,($R$2-1)*12+6) -> 0 | N18: =INDEX(Monthly!$C$50:$AL$50,($R$2-1)*12+7) -> 0 | O18: =INDEX(Monthly!$C$50:$AL$50,($R$2-1)*12+8) -> 0 | P18: =INDEX(Monthly!$C$50:$AL$50,($R$2-1)*12+9) -> 0 | Q18: =INDEX(Monthly!$C$50:$AL$50,($R$2-1)*12+10) -> 0 | R18: =INDEX(Monthly!$C$50:$AL$50,($R$2-1)*12+11) -> 0 | S18: =INDEX(Monthly!$C$50:$AL$50,($R$2-1)*12+12) -> 0
A19: Net income | B19: ='P&L'!B24 -> -229972.18 | C19: ='P&L'!C24 -> -5045.9468 | D19: ='P&L'!D24 -> 36406.5 | H19: =INDEX(Monthly!$C$51:$AL$51,($R$2-1)*12+1) -> -31835.127 | I19: =INDEX(Monthly!$C$51:$AL$51,($R$2-1)*12+2) -> -29048.53 | J19: =INDEX(Monthly!$C$51:$AL$51,($R$2-1)*12+3) -> -26422.819 | K19: =INDEX(Monthly!$C$51:$AL$51,($R$2-1)*12+4) -> -23953.937 | L19: =INDEX(Monthly!$C$51:$AL$51,($R$2-1)*12+5) -> -21632.473 | M19: =INDEX(Monthly!$C$51:$AL$51,($R$2-1)*12+6) -> -19449.583 | N19: =INDEX(Monthly!$C$51:$AL$51,($R$2-1)*12+7) -> -17396.952 | O19: =INDEX(Monthly!$C$51:$AL$51,($R$2-1)*12+8) -> -15466.764 | P19: =INDEX(Monthly!$C$51:$AL$51,($R$2-1)*12+9) -> -13651.674 | Q19: =INDEX(Monthly!$C$51:$AL$51,($R$2-1)*12+10) -> -11944.774 | R19: =INDEX(Monthly!$C$51:$AL$51,($R$2-1)*12+11) -> -10339.575 | S19: =INDEX(Monthly!$C$51:$AL$51,($R$2-1)*12+12) -> -8829.9728
A20: Net margin | B20: ='P&L'!B25 -> -0.58505861 | C20: ='P&L'!C25 -> -0.0076000742 | D20: ='P&L'!D25 -> 0.050379968 | H20: =IF(H7=0,0,H19/H7) -> -1.7566146 | I20: =IF(I7=0,0,I19/I7) -> -1.3606119 | J20: =IF(J7=0,0,J19/J7) -> -1.0836743 | K20: =IF(K7=0,0,K19/K7) -> -0.87957129 | L20: =IF(L7=0,0,L19/L7) -> -0.72316469 | M20: =IF(M7=0,0,M19/M7) -> -0.59968886 | N20: =IF(N7=0,0,N19/N7) -> -0.49990076 | O20: =IF(O7=0,0,O19/O7) -> -0.41771866 | ... S20: =IF(S7=0,0,S19/S7) -> -0.19765925
A22: Cash flow ($'000) — by year | H22: ="Cash flow ($'000) — Year "&$R$2&", by month" -> Cash flow ($'000) — Year 1, by month
B23: 1 | C23: 2 | D23: 3 | H23: =INDEX(Monthly!$C$4:$AL$4,($R$2-1)*12+1) -> 1 | I23: =INDEX(Monthly!$C$4:$AL$4,($R$2-1)*12+2) -> 2 | J23: =INDEX(Monthly!$C$4:$AL$4,($R$2-1)*12+3) -> 3 | K23: =INDEX(Monthly!$C$4:$AL$4,($R$2-1)*12+4) -> 4 | L23: =INDEX(Monthly!$C$4:$AL$4,($R$2-1)*12+5) -> 5 | M23: =INDEX(Monthly!$C$4:$AL$4,($R$2-1)*12+6) -> 6 | N23: =INDEX(Monthly!$C$4:$AL$4,($R$2-1)*12+7) -> 7 | O23: =INDEX(Monthly!$C$4:$AL$4,($R$2-1)*12+8) -> 8 | P23: =INDEX(Monthly!$C$4:$AL$4,($R$2-1)*12+9) -> 9 | Q23: =INDEX(Monthly!$C$4:$AL$4,($R$2-1)*12+10) -> 10 | R23: =INDEX(Monthly!$C$4:$AL$4,($R$2-1)*12+11) -> 11 | S23: =INDEX(Monthly!$C$4:$AL$4,($R$2-1)*12+12) -> 12
A24: Operating cash flow | B24: ='Cash Flow'!B10 -> -190250.26 | C24: ='Cash Flow'!C10 -> 31208.152 | D24: ='Cash Flow'!D10 -> 72257.209 | H24: =INDEX(Monthly!$C$75:$AL$75,($R$2-1)*12+1) -> -25720.487 | I24: =INDEX(Monthly!$C$75:$AL$75,($R$2-1)*12+2) -> -25966.707 | J24: =INDEX(Monthly!$C$75:$AL$75,($R$2-1)*12+3) -> -23347.334 | K24: =INDEX(Monthly!$C$75:$AL$75,($R$2-1)*12+4) -> -20884.409 | L24: =INDEX(Monthly!$C$75:$AL$75,($R$2-1)*12+5) -> -18568.546 | M24: =INDEX(Monthly!$C$75:$AL$75,($R$2-1)*12+6) -> -16390.92 | N24: =INDEX(Monthly!$C$75:$AL$75,($R$2-1)*12+7) -> -14343.237 | O24: =INDEX(Monthly!$C$75:$AL$75,($R$2-1)*12+8) -> -12417.701 | P24: =INDEX(Monthly!$C$75:$AL$75,($R$2-1)*12+9) -> -10606.983 | Q24: =INDEX(Monthly!$C$75:$AL$75,($R$2-1)*12+10) -> -8904.1934 | R24: =INDEX(Monthly!$C$75:$AL$75,($R$2-1)*12+11) -> -7302.8571 | S24: =INDEX(Monthly!$C$75:$AL$75,($R$2-1)*12+12) -> -5796.8867
A25: Capital spending | B25: ='Cash Flow'!B11 -> -250000 | C25: ='Cash Flow'!C11 -> 0 | D25: ='Cash Flow'!D11 -> 0 | H25: =INDEX(Monthly!$C$76:$AL$76,($R$2-1)*12+1) -> -250000 | I25: =INDEX(Monthly!$C$76:$AL$76,($R$2-1)*12+2) -> 0 | J25: =INDEX(Monthly!$C$76:$AL$76,($R$2-1)*12+3) -> 0 | K25: =INDEX(Monthly!$C$76:$AL$76,($R$2-1)*12+4) -> 0 | L25: =INDEX(Monthly!$C$76:$AL$76,($R$2-1)*12+5) -> 0 | M25: =INDEX(Monthly!$C$76:$AL$76,($R$2-1)*12+6) -> 0 | N25: =INDEX(Monthly!$C$76:$AL$76,($R$2-1)*12+7) -> 0 | O25: =INDEX(Monthly!$C$76:$AL$76,($R$2-1)*12+8) -> 0 | P25: =INDEX(Monthly!$C$76:$AL$76,($R$2-1)*12+9) -> 0 | Q25: =INDEX(Monthly!$C$76:$AL$76,($R$2-1)*12+10) -> 0 | R25: =INDEX(Monthly!$C$76:$AL$76,($R$2-1)*12+11) -> 0 | S25: =INDEX(Monthly!$C$76:$AL$76,($R$2-1)*12+12) -> 0
A26: Equity raised | B26: ='Cash Flow'!B12 -> 330000 | C26: ='Cash Flow'!C12 -> 0 | D26: ='Cash Flow'!D12 -> 0 | H26: =INDEX(Monthly!$C$77:$AL$77,($R$2-1)*12+1) -> 330000 | I26: =INDEX(Monthly!$C$77:$AL$77,($R$2-1)*12+2) -> 0 | J26: =INDEX(Monthly!$C$77:$AL$77,($R$2-1)*12+3) -> 0 | K26: =INDEX(Monthly!$C$77:$AL$77,($R$2-1)*12+4) -> 0 | L26: =INDEX(Monthly!$C$77:$AL$77,($R$2-1)*12+5) -> 0 | M26: =INDEX(Monthly!$C$77:$AL$77,($R$2-1)*12+6) -> 0 | N26: =INDEX(Monthly!$C$77:$AL$77,($R$2-1)*12+7) -> 0 | O26: =INDEX(Monthly!$C$77:$AL$77,($R$2-1)*12+8) -> 0 | P26: =INDEX(Monthly!$C$77:$AL$77,($R$2-1)*12+9) -> 0 | Q26: =INDEX(Monthly!$C$77:$AL$77,($R$2-1)*12+10) -> 0 | R26: =INDEX(Monthly!$C$77:$AL$77,($R$2-1)*12+11) -> 0 | S26: =INDEX(Monthly!$C$77:$AL$77,($R$2-1)*12+12) -> 0
A27: Loan drawdown | B27: ='Cash Flow'!B13 -> 150000 | C27: ='Cash Flow'!C13 -> 0 | D27: ='Cash Flow'!D13 -> 0 | H27: =INDEX(Monthly!$C$62:$AL$62,($R$2-1)*12+1) -> 150000 | I27: =INDEX(Monthly!$C$62:$AL$62,($R$2-1)*12+2) -> 0 | J27: =INDEX(Monthly!$C$62:$AL$62,($R$2-1)*12+3) -> 0 | K27: =INDEX(Monthly!$C$62:$AL$62,($R$2-1)*12+4) -> 0 | L27: =INDEX(Monthly!$C$62:$AL$62,($R$2-1)*12+5) -> 0 | M27: =INDEX(Monthly!$C$62:$AL$62,($R$2-1)*12+6) -> 0 | N27: =INDEX(Monthly!$C$62:$AL$62,($R$2-1)*12+7) -> 0 | O27: =INDEX(Monthly!$C$62:$AL$62,($R$2-1)*12+8) -> 0 | P27: =INDEX(Monthly!$C$62:$AL$62,($R$2-1)*12+9) -> 0 | Q27: =INDEX(Monthly!$C$62:$AL$62,($R$2-1)*12+10) -> 0 | R27: =INDEX(Monthly!$C$62:$AL$62,($R$2-1)*12+11) -> 0 | S27: =INDEX(Monthly!$C$62:$AL$62,($R$2-1)*12+12) -> 0
A28: Loan repayment | B28: ='Cash Flow'!B14 -> -19642.857 | C28: ='Cash Flow'!C14 -> -21428.571 | D28: ='Cash Flow'!D14 -> -21428.571 | H28: =INDEX(Monthly!$C$63:$AL$63,($R$2-1)*12+1) -> 0 | I28: =INDEX(Monthly!$C$63:$AL$63,($R$2-1)*12+2) -> -1785.7143 | J28: =INDEX(Monthly!$C$63:$AL$63,($R$2-1)*12+3) -> -1785.7143 | K28: =INDEX(Monthly!$C$63:$AL$63,($R$2-1)*12+4) -> -1785.7143 | L28: =INDEX(Monthly!$C$63:$AL$63,($R$2-1)*12+5) -> -1785.7143 | M28: =INDEX(Monthly!$C$63:$AL$63,($R$2-1)*12+6) -> -1785.7143 | N28: =INDEX(Monthly!$C$63:$AL$63,($R$2-1)*12+7) -> -1785.7143 | O28: =INDEX(Monthly!$C$63:$AL$63,($R$2-1)*12+8) -> -1785.7143 | P28: =INDEX(Monthly!$C$63:$AL$63,($R$2-1)*12+9) -> -1785.7143 | Q28: =INDEX(Monthly!$C$63:$AL$63,($R$2-1)*12+10) -> -1785.7143 | R28: =INDEX(Monthly!$C$63:$AL$63,($R$2-1)*12+11) -> -1785.7143 | S28: =INDEX(Monthly!$C$63:$AL$63,($R$2-1)*12+12) -> -1785.7143
A29: Financing cash flow | B29: ='Cash Flow'!B15 -> 460357.14 | C29: ='Cash Flow'!C15 -> -21428.571 | D29: ='Cash Flow'!D15 -> -21428.571 | H29: =INDEX(Monthly!$C$78:$AL$78,($R$2-1)*12+1) -> 480000 | I29: =INDEX(Monthly!$C$78:$AL$78,($R$2-1)*12+2) -> -1785.7143 | J29: =INDEX(Monthly!$C$78:$AL$78,($R$2-1)*12+3) -> -1785.7143 | K29: =INDEX(Monthly!$C$78:$AL$78,($R$2-1)*12+4) -> -1785.7143 | L29: =INDEX(Monthly!$C$78:$AL$78,($R$2-1)*12+5) -> -1785.7143 | M29: =INDEX(Monthly!$C$78:$AL$78,($R$2-1)*12+6) -> -1785.7143 | N29: =INDEX(Monthly!$C$78:$AL$78,($R$2-1)*12+7) -> -1785.7143 | O29: =INDEX(Monthly!$C$78:$AL$78,($R$2-1)*12+8) -> -1785.7143 | P29: =INDEX(Monthly!$C$78:$AL$78,($R$2-1)*12+9) -> -1785.7143 | Q29: =INDEX(Monthly!$C$78:$AL$78,($R$2-1)*12+10) -> -1785.7143 | R29: =INDEX(Monthly!$C$78:$AL$78,($R$2-1)*12+11) -> -1785.7143 | S29: =INDEX(Monthly!$C$78:$AL$78,($R$2-1)*12+12) -> -1785.7143
A30: Net change in cash | B30: ='Cash Flow'!B16 -> 20106.884 | C30: ='Cash Flow'!C16 -> 9779.5808 | D30: ='Cash Flow'!D16 -> 50828.638 | H30: =INDEX(Monthly!$C$79:$AL$79,($R$2-1)*12+1) -> 204279.51 | I30: =INDEX(Monthly!$C$79:$AL$79,($R$2-1)*12+2) -> -27752.421 | J30: =INDEX(Monthly!$C$79:$AL$79,($R$2-1)*12+3) -> -25133.048 | K30: =INDEX(Monthly!$C$79:$AL$79,($R$2-1)*12+4) -> -22670.123 | L30: =INDEX(Monthly!$C$79:$AL$79,($R$2-1)*12+5) -> -20354.26 | M30: =INDEX(Monthly!$C$79:$AL$79,($R$2-1)*12+6) -> -18176.634 | N30: =INDEX(Monthly!$C$79:$AL$79,($R$2-1)*12+7) -> -16128.951 | O30: =INDEX(Monthly!$C$79:$AL$79,($R$2-1)*12+8) -> -14203.415 | P30: =INDEX(Monthly!$C$79:$AL$79,($R$2-1)*12+9) -> -12392.697 | Q30: =INDEX(Monthly!$C$79:$AL$79,($R$2-1)*12+10) -> -10689.908 | R30: =INDEX(Monthly!$C$79:$AL$79,($R$2-1)*12+11) -> -9088.5714 | S30: =INDEX(Monthly!$C$79:$AL$79,($R$2-1)*12+12) -> -7582.601
A31: Closing cash | B31: ='Cash Flow'!B18 -> 20106.884 | C31: ='Cash Flow'!C18 -> 29886.464 | D31: ='Cash Flow'!D18 -> 80715.102 | H31: =INDEX(Monthly!$C$81:$AL$81,($R$2-1)*12+1) -> 204279.51 | I31: =INDEX(Monthly!$C$81:$AL$81,($R$2-1)*12+2) -> 176527.09 | J31: =INDEX(Monthly!$C$81:$AL$81,($R$2-1)*12+3) -> 151394.04 | K31: =INDEX(Monthly!$C$81:$AL$81,($R$2-1)*12+4) -> 128723.92 | L31: =INDEX(Monthly!$C$81:$AL$81,($R$2-1)*12+5) -> 108369.66 | M31: =INDEX(Monthly!$C$81:$AL$81,($R$2-1)*12+6) -> 90193.027 | N31: =INDEX(Monthly!$C$81:$AL$81,($R$2-1)*12+7) -> 74064.076 | O31: =INDEX(Monthly!$C$81:$AL$81,($R$2-1)*12+8) -> 59860.661 | P31: =INDEX(Monthly!$C$81:$AL$81,($R$2-1)*12+9) -> 47467.964 | Q31: =INDEX(Monthly!$C$81:$AL$81,($R$2-1)*12+10) -> 36778.056 | R31: =INDEX(Monthly!$C$81:$AL$81,($R$2-1)*12+11) -> 27689.485 | S31: =INDEX(Monthly!$C$81:$AL$81,($R$2-1)*12+12) -> 20106.884
A39: Balance sheet at year end ($'000) | H39: ="Balance sheet at month end ($'000) — Year "&$R$2 -> Balance sheet at month end ($'000) — Year 1
B40: 1 | C40: 2 | D40: 3 | H40: =INDEX(Monthly!$C$4:$AL$4,($R$2-1)*12+1) -> 1 | I40: =INDEX(Monthly!$C$4:$AL$4,($R$2-1)*12+2) -> 2 | J40: =INDEX(Monthly!$C$4:$AL$4,($R$2-1)*12+3) -> 3 | K40: =INDEX(Monthly!$C$4:$AL$4,($R$2-1)*12+4) -> 4 | L40: =INDEX(Monthly!$C$4:$AL$4,($R$2-1)*12+5) -> 5 | M40: =INDEX(Monthly!$C$4:$AL$4,($R$2-1)*12+6) -> 6 | N40: =INDEX(Monthly!$C$4:$AL$4,($R$2-1)*12+7) -> 7 | O40: =INDEX(Monthly!$C$4:$AL$4,($R$2-1)*12+8) -> 8 | P40: =INDEX(Monthly!$C$4:$AL$4,($R$2-1)*12+9) -> 9 | Q40: =INDEX(Monthly!$C$4:$AL$4,($R$2-1)*12+10) -> 10 | R40: =INDEX(Monthly!$C$4:$AL$4,($R$2-1)*12+11) -> 11 | S40: =INDEX(Monthly!$C$4:$AL$4,($R$2-1)*12+12) -> 12
A41: Cash | B41: ='Balance Sheet'!B5 -> 20106.884 | C41: ='Balance Sheet'!C5 -> 29886.464 | D41: ='Balance Sheet'!D5 -> 80715.102 | H41: =INDEX(Monthly!$C$81:$AL$81,($R$2-1)*12+1) -> 204279.51 | I41: =INDEX(Monthly!$C$81:$AL$81,($R$2-1)*12+2) -> 176527.09 | J41: =INDEX(Monthly!$C$81:$AL$81,($R$2-1)*12+3) -> 151394.04 | K41: =INDEX(Monthly!$C$81:$AL$81,($R$2-1)*12+4) -> 128723.92 | L41: =INDEX(Monthly!$C$81:$AL$81,($R$2-1)*12+5) -> 108369.66 | M41: =INDEX(Monthly!$C$81:$AL$81,($R$2-1)*12+6) -> 90193.027 | N41: =INDEX(Monthly!$C$81:$AL$81,($R$2-1)*12+7) -> 74064.076 | O41: =INDEX(Monthly!$C$81:$AL$81,($R$2-1)*12+8) -> 59860.661 | P41: =INDEX(Monthly!$C$81:$AL$81,($R$2-1)*12+9) -> 47467.964 | Q41: =INDEX(Monthly!$C$81:$AL$81,($R$2-1)*12+10) -> 36778.056 | R41: =INDEX(Monthly!$C$81:$AL$81,($R$2-1)*12+11) -> 27689.485 | S41: =INDEX(Monthly!$C$81:$AL$81,($R$2-1)*12+12) -> 20106.884
A42: Accounts receivable | B42: ='Balance Sheet'!B6 -> 0 | C42: ='Balance Sheet'!C6 -> 0 | D42: ='Balance Sheet'!D6 -> 0 | H42: =INDEX(Monthly!$C$67:$AL$67,($R$2-1)*12+1) -> 0 | I42: =INDEX(Monthly!$C$67:$AL$67,($R$2-1)*12+2) -> 0 | J42: =INDEX(Monthly!$C$67:$AL$67,($R$2-1)*12+3) -> 0 | K42: =INDEX(Monthly!$C$67:$AL$67,($R$2-1)*12+4) -> 0 | L42: =INDEX(Monthly!$C$67:$AL$67,($R$2-1)*12+5) -> 0 | M42: =INDEX(Monthly!$C$67:$AL$67,($R$2-1)*12+6) -> 0 | N42: =INDEX(Monthly!$C$67:$AL$67,($R$2-1)*12+7) -> 0 | O42: =INDEX(Monthly!$C$67:$AL$67,($R$2-1)*12+8) -> 0 | P42: =INDEX(Monthly!$C$67:$AL$67,($R$2-1)*12+9) -> 0 | Q42: =INDEX(Monthly!$C$67:$AL$67,($R$2-1)*12+10) -> 0 | R42: =INDEX(Monthly!$C$67:$AL$67,($R$2-1)*12+11) -> 0 | S42: =INDEX(Monthly!$C$67:$AL$67,($R$2-1)*12+12) -> 0
A43: Inventory | B43: ='Balance Sheet'!B7 -> 4007.6367 | C43: ='Balance Sheet'!C7 -> 4547.45 | D43: ='Balance Sheet'!D7 -> 4683.8735 | H43: =INDEX(Monthly!$C$68:$AL$68,($R$2-1)*12+1) -> 3138.45 | I43: =INDEX(Monthly!$C$68:$AL$68,($R$2-1)*12+2) -> 3244.083 | J43: =INDEX(Monthly!$C$68:$AL$68,($R$2-1)*12+3) -> 3343.378 | K43: =INDEX(Monthly!$C$68:$AL$68,($R$2-1)*12+4) -> 3436.7153 | L43: =INDEX(Monthly!$C$68:$AL$68,($R$2-1)*12+5) -> 3524.4524 | M43: =INDEX(Monthly!$C$68:$AL$68,($R$2-1)*12+6) -> 3606.9253 | N43: =INDEX(Monthly!$C$68:$AL$68,($R$2-1)*12+7) -> 3684.4498 | O43: =INDEX(Monthly!$C$68:$AL$68,($R$2-1)*12+8) -> 3757.3228 | P43: =INDEX(Monthly!$C$68:$AL$68,($R$2-1)*12+9) -> 3825.8234 | Q43: =INDEX(Monthly!$C$68:$AL$68,($R$2-1)*12+10) -> 3890.214 | R43: =INDEX(Monthly!$C$68:$AL$68,($R$2-1)*12+11) -> 3950.7412 | S43: =INDEX(Monthly!$C$68:$AL$68,($R$2-1)*12+12) -> 4007.6367
A44: Net fixed assets | B44: ='Balance Sheet'!B8 -> 214285.71 | C44: ='Balance Sheet'!C8 -> 178571.43 | D44: ='Balance Sheet'!D8 -> 142857.14 | H44: =INDEX(Monthly!$C$58:$AL$58,($R$2-1)*12+1) -> 247023.81 | I44: =INDEX(Monthly!$C$58:$AL$58,($R$2-1)*12+2) -> 244047.62 | J44: =INDEX(Monthly!$C$58:$AL$58,($R$2-1)*12+3) -> 241071.43 | K44: =INDEX(Monthly!$C$58:$AL$58,($R$2-1)*12+4) -> 238095.24 | L44: =INDEX(Monthly!$C$58:$AL$58,($R$2-1)*12+5) -> 235119.05 | M44: =INDEX(Monthly!$C$58:$AL$58,($R$2-1)*12+6) -> 232142.86 | N44: =INDEX(Monthly!$C$58:$AL$58,($R$2-1)*12+7) -> 229166.67 | O44: =INDEX(Monthly!$C$58:$AL$58,($R$2-1)*12+8) -> 226190.48 | P44: =INDEX(Monthly!$C$58:$AL$58,($R$2-1)*12+9) -> 223214.29 | Q44: =INDEX(Monthly!$C$58:$AL$58,($R$2-1)*12+10) -> 220238.1 | R44: =INDEX(Monthly!$C$58:$AL$58,($R$2-1)*12+11) -> 217261.9 | S44: =INDEX(Monthly!$C$58:$AL$58,($R$2-1)*12+12) -> 214285.71
A45: Total assets | B45: ='Balance Sheet'!B9 -> 238400.23 | C45: ='Balance Sheet'!C9 -> 213005.34 | D45: ='Balance Sheet'!D9 -> 228256.12 | H45: =INDEX(Monthly!$C$95:$AL$95,($R$2-1)*12+1) -> 454441.77 | I45: =INDEX(Monthly!$C$95:$AL$95,($R$2-1)*12+2) -> 423818.79 | J45: =INDEX(Monthly!$C$95:$AL$95,($R$2-1)*12+3) -> 395808.85 | K45: =INDEX(Monthly!$C$95:$AL$95,($R$2-1)*12+4) -> 370255.87 | L45: =INDEX(Monthly!$C$95:$AL$95,($R$2-1)*12+5) -> 347013.16 | M45: =INDEX(Monthly!$C$95:$AL$95,($R$2-1)*12+6) -> 325942.81 | N45: =INDEX(Monthly!$C$95:$AL$95,($R$2-1)*12+7) -> 306915.19 | O45: =INDEX(Monthly!$C$95:$AL$95,($R$2-1)*12+8) -> 289808.46 | P45: =INDEX(Monthly!$C$95:$AL$95,($R$2-1)*12+9) -> 274508.07 | Q45: =INDEX(Monthly!$C$95:$AL$95,($R$2-1)*12+10) -> 260906.37 | R45: =INDEX(Monthly!$C$95:$AL$95,($R$2-1)*12+11) -> 248902.13 | S45: =INDEX(Monthly!$C$95:$AL$95,($R$2-1)*12+12) -> 238400.23
A46: Accounts payable | B46: ='Balance Sheet'!B10 -> 8015.2734 | C46: ='Balance Sheet'!C10 -> 9094.9 | D46: ='Balance Sheet'!D10 -> 9367.747 | H46: =INDEX(Monthly!$C$69:$AL$69,($R$2-1)*12+1) -> 6276.9 | I46: =INDEX(Monthly!$C$69:$AL$69,($R$2-1)*12+2) -> 6488.166 | J46: =INDEX(Monthly!$C$69:$AL$69,($R$2-1)*12+3) -> 6686.756 | K46: =INDEX(Monthly!$C$69:$AL$69,($R$2-1)*12+4) -> 6873.4307 | L46: =INDEX(Monthly!$C$69:$AL$69,($R$2-1)*12+5) -> 7048.9048 | M46: =INDEX(Monthly!$C$69:$AL$69,($R$2-1)*12+6) -> 7213.8505 | N46: =INDEX(Monthly!$C$69:$AL$69,($R$2-1)*12+7) -> 7368.8995 | O46: =INDEX(Monthly!$C$69:$AL$69,($R$2-1)*12+8) -> 7514.6455 | P46: =INDEX(Monthly!$C$69:$AL$69,($R$2-1)*12+9) -> 7651.6468 | Q46: =INDEX(Monthly!$C$69:$AL$69,($R$2-1)*12+10) -> 7780.428 | R46: =INDEX(Monthly!$C$69:$AL$69,($R$2-1)*12+11) -> 7901.4823 | S46: =INDEX(Monthly!$C$69:$AL$69,($R$2-1)*12+12) -> 8015.2734
A47: Loan | B47: ='Balance Sheet'!B11 -> 130357.14 | C47: ='Balance Sheet'!C11 -> 108928.57 | D47: ='Balance Sheet'!D11 -> 87500 | H47: =INDEX(Monthly!$C$64:$AL$64,($R$2-1)*12+1) -> 150000 | I47: =INDEX(Monthly!$C$64:$AL$64,($R$2-1)*12+2) -> 148214.29 | J47: =INDEX(Monthly!$C$64:$AL$64,($R$2-1)*12+3) -> 146428.57 | K47: =INDEX(Monthly!$C$64:$AL$64,($R$2-1)*12+4) -> 144642.86 | L47: =INDEX(Monthly!$C$64:$AL$64,($R$2-1)*12+5) -> 142857.14 | M47: =INDEX(Monthly!$C$64:$AL$64,($R$2-1)*12+6) -> 141071.43 | N47: =INDEX(Monthly!$C$64:$AL$64,($R$2-1)*12+7) -> 139285.71 | O47: =INDEX(Monthly!$C$64:$AL$64,($R$2-1)*12+8) -> 137500 | P47: =INDEX(Monthly!$C$64:$AL$64,($R$2-1)*12+9) -> 135714.29 | Q47: =INDEX(Monthly!$C$64:$AL$64,($R$2-1)*12+10) -> 133928.57 | R47: =INDEX(Monthly!$C$64:$AL$64,($R$2-1)*12+11) -> 132142.86 | S47: =INDEX(Monthly!$C$64:$AL$64,($R$2-1)*12+12) -> 130357.14
A48: Total liabilities | B48: ='Balance Sheet'!B12 -> 138372.42 | C48: ='Balance Sheet'!C12 -> 118023.47 | D48: ='Balance Sheet'!D12 -> 96867.747 | H48: =INDEX(Monthly!$C$96:$AL$96,($R$2-1)*12+1) -> 156276.9 | I48: =INDEX(Monthly!$C$96:$AL$96,($R$2-1)*12+2) -> 154702.45 | J48: =INDEX(Monthly!$C$96:$AL$96,($R$2-1)*12+3) -> 153115.33 | K48: =INDEX(Monthly!$C$96:$AL$96,($R$2-1)*12+4) -> 151516.29 | L48: =INDEX(Monthly!$C$96:$AL$96,($R$2-1)*12+5) -> 149906.05 | M48: =INDEX(Monthly!$C$96:$AL$96,($R$2-1)*12+6) -> 148285.28 | N48: =INDEX(Monthly!$C$96:$AL$96,($R$2-1)*12+7) -> 146654.61 | O48: =INDEX(Monthly!$C$96:$AL$96,($R$2-1)*12+8) -> 145014.65 | P48: =INDEX(Monthly!$C$96:$AL$96,($R$2-1)*12+9) -> 143365.93 | Q48: =INDEX(Monthly!$C$96:$AL$96,($R$2-1)*12+10) -> 141709 | R48: =INDEX(Monthly!$C$96:$AL$96,($R$2-1)*12+11) -> 140044.34 | S48: =INDEX(Monthly!$C$96:$AL$96,($R$2-1)*12+12) -> 138372.42
A49: Paid-in capital | B49: ='Balance Sheet'!B13 -> 330000 | C49: ='Balance Sheet'!C13 -> 330000 | D49: ='Balance Sheet'!D13 -> 330000 | H49: =INDEX(Monthly!$C$93:$AL$93,($R$2-1)*12+1) -> 330000 | I49: =INDEX(Monthly!$C$93:$AL$93,($R$2-1)*12+2) -> 330000 | J49: =INDEX(Monthly!$C$93:$AL$93,($R$2-1)*12+3) -> 330000 | K49: =INDEX(Monthly!$C$93:$AL$93,($R$2-1)*12+4) -> 330000 | L49: =INDEX(Monthly!$C$93:$AL$93,($R$2-1)*12+5) -> 330000 | M49: =INDEX(Monthly!$C$93:$AL$93,($R$2-1)*12+6) -> 330000 | N49: =INDEX(Monthly!$C$93:$AL$93,($R$2-1)*12+7) -> 330000 | O49: =INDEX(Monthly!$C$93:$AL$93,($R$2-1)*12+8) -> 330000 | P49: =INDEX(Monthly!$C$93:$AL$93,($R$2-1)*12+9) -> 330000 | Q49: =INDEX(Monthly!$C$93:$AL$93,($R$2-1)*12+10) -> 330000 | R49: =INDEX(Monthly!$C$93:$AL$93,($R$2-1)*12+11) -> 330000 | S49: =INDEX(Monthly!$C$93:$AL$93,($R$2-1)*12+12) -> 330000
A50: Retained earnings | B50: ='Balance Sheet'!B14 -> -229972.18 | C50: ='Balance Sheet'!C14 -> -235018.13 | D50: ='Balance Sheet'!D14 -> -198611.63 | H50: =INDEX(Monthly!$C$94:$AL$94,($R$2-1)*12+1) -> -31835.127 | I50: =INDEX(Monthly!$C$94:$AL$94,($R$2-1)*12+2) -> -60883.657 | J50: =INDEX(Monthly!$C$94:$AL$94,($R$2-1)*12+3) -> -87306.477 | K50: =INDEX(Monthly!$C$94:$AL$94,($R$2-1)*12+4) -> -111260.41 | L50: =INDEX(Monthly!$C$94:$AL$94,($R$2-1)*12+5) -> -132892.89 | M50: =INDEX(Monthly!$C$94:$AL$94,($R$2-1)*12+6) -> -152342.47 | N50: =INDEX(Monthly!$C$94:$AL$94,($R$2-1)*12+7) -> -169739.42 | O50: =INDEX(Monthly!$C$94:$AL$94,($R$2-1)*12+8) -> -185206.19 | P50: =INDEX(Monthly!$C$94:$AL$94,($R$2-1)*12+9) -> -198857.86 | Q50: =INDEX(Monthly!$C$94:$AL$94,($R$2-1)*12+10) -> -210802.63 | R50: =INDEX(Monthly!$C$94:$AL$94,($R$2-1)*12+11) -> -221142.21 | S50: =INDEX(Monthly!$C$94:$AL$94,($R$2-1)*12+12) -> -229972.18
A51: Total equity | B51: ='Balance Sheet'!B15 -> 100027.82 | C51: ='Balance Sheet'!C15 -> 94981.871 | D51: ='Balance Sheet'!D15 -> 131388.37 | H51: =INDEX(Monthly!$C$97:$AL$97,($R$2-1)*12+1) -> 298164.87 | I51: =INDEX(Monthly!$C$97:$AL$97,($R$2-1)*12+2) -> 269116.34 | J51: =INDEX(Monthly!$C$97:$AL$97,($R$2-1)*12+3) -> 242693.52 | K51: =INDEX(Monthly!$C$97:$AL$97,($R$2-1)*12+4) -> 218739.59 | L51: =INDEX(Monthly!$C$97:$AL$97,($R$2-1)*12+5) -> 197107.11 | M51: =INDEX(Monthly!$C$97:$AL$97,($R$2-1)*12+6) -> 177657.53 | N51: =INDEX(Monthly!$C$97:$AL$97,($R$2-1)*12+7) -> 160260.58 | O51: =INDEX(Monthly!$C$97:$AL$97,($R$2-1)*12+8) -> 144793.81 | P51: =INDEX(Monthly!$C$97:$AL$97,($R$2-1)*12+9) -> 131142.14 | Q51: =INDEX(Monthly!$C$97:$AL$97,($R$2-1)*12+10) -> 119197.37 | R51: =INDEX(Monthly!$C$97:$AL$97,($R$2-1)*12+11) -> 108857.79 | S51: =INDEX(Monthly!$C$97:$AL$97,($R$2-1)*12+12) -> 100027.82
A52: Total liabilities & equity | B52: ='Balance Sheet'!B16 -> 238400.23 | C52: ='Balance Sheet'!C16 -> 213005.34 | D52: ='Balance Sheet'!D16 -> 228256.12 | H52: =INDEX(Monthly!$C$98:$AL$98,($R$2-1)*12+1) -> 454441.77 | I52: =INDEX(Monthly!$C$98:$AL$98,($R$2-1)*12+2) -> 423818.79 | J52: =INDEX(Monthly!$C$98:$AL$98,($R$2-1)*12+3) -> 395808.85 | K52: =INDEX(Monthly!$C$98:$AL$98,($R$2-1)*12+4) -> 370255.87 | L52: =INDEX(Monthly!$C$98:$AL$98,($R$2-1)*12+5) -> 347013.16 | M52: =INDEX(Monthly!$C$98:$AL$98,($R$2-1)*12+6) -> 325942.81 | N52: =INDEX(Monthly!$C$98:$AL$98,($R$2-1)*12+7) -> 306915.19 | O52: =INDEX(Monthly!$C$98:$AL$98,($R$2-1)*12+8) -> 289808.46 | P52: =INDEX(Monthly!$C$98:$AL$98,($R$2-1)*12+9) -> 274508.07 | Q52: =INDEX(Monthly!$C$98:$AL$98,($R$2-1)*12+10) -> 260906.37 | R52: =INDEX(Monthly!$C$98:$AL$98,($R$2-1)*12+11) -> 248902.13 | S52: =INDEX(Monthly!$C$98:$AL$98,($R$2-1)*12+12) -> 238400.23

Sheet Scenarios
A1: Scenarios — Low / Base / High | H1: =HYPERLINK("#'Cover'!A1","◂ Contents") -> ◂ Contents
A2: All three scenarios calculated side by side, live: change any input and every column updates. Active = the scenario chosen on the Dashboard.
A5: Key drivers
A6: Driver | B6: Low | C6: Base | D6: High | E6: Active
A7: Members at start (presale or current base) (#) | B7: =Inputs!$B$7 -> 80 | C7: =Inputs!$C$7 -> 120 | D7: =Inputs!$D$7 -> 160 | E7: =Inputs!$E$7 -> 120
A8: Membership fee per month (year 1) ($) | B8: =Inputs!$B$18 -> 89 | C8: =Inputs!$C$18 -> 99 | D8: =Inputs!$D$18 -> 109 | E8: =Inputs!$E$18 -> 99
A9: Members who cancel per month (%) | B9: =Inputs!$B$15 -> 0.07 | C9: =Inputs!$C$15 -> 0.06 | D9: =Inputs!$D$15 -> 0.05 | E9: =Inputs!$E$15 -> 0.06
A10: Marketing budget per month (year 1) ($) | B10: =Inputs!$B$11 -> 4000 | C10: =Inputs!$C$11 -> 4000 | D10: =Inputs!$D$11 -> 4000 | E10: =Inputs!$E$11 -> 4000
A11: Capacity: most members the studio can hold (#) | B11: =Inputs!$B$8 -> 450 | C11: =Inputs!$C$8 -> 450 | D11: =Inputs!$D$8 -> 450 | E11: =Inputs!$E$8 -> 450
A12: Rent per month ($) | B12: =Inputs!$B$33 -> 12000 | C12: =Inputs!$C$33 -> 12000 | D12: =Inputs!$D$33 -> 12000 | E12: =Inputs!$E$33 -> 12000
A13: Equity raised at start ($) | B13: =Inputs!$B$54 -> 330000 | C13: =Inputs!$C$54 -> 330000 | D13: =Inputs!$D$54 -> 330000 | E13: =Inputs!$E$54 -> 330000
A15: Results by scenario ($'000)
A16: Output | B16: Low | C16: Base | D16: High | E16: Active
A17: Revenue — final year | B17: =D30 -> 515887.22 | C17: =D31 -> 722638.4 | D17: =D32 -> 822654.14 | E17: ='P&L'!D5 -> 722638.4
A18: Revenue — whole plan | B18: =SUM(B30:D30) -> 1201588.4 | C18: =SUM(B31:D31) -> 1779647.7 | D18: =SUM(B32:D32) -> 2184359.1 | E18: =SUM('P&L'!$B$5:$D$5) -> 1779647.7
A19: EBITDA — final year | B19: =D36 -> -106913.55 | C19: =D37 -> 79977.928 | D19: =D38 -> 178027.21 | E19: ='P&L'!D17 -> 79977.928
A20: EBITDA margin — final year | B20: =IF(B17=0,0,B19/B17) -> -0.2072421 | C20: =IF(C17=0,0,C19/C17) -> 0.11067489 | D20: =IF(D17=0,0,D19/D17) -> 0.2164059 | E20: =IF(E17=0,0,E19/E17) -> 0.11067489
A21: Net income — final year | B21: =D42 -> -150484.98 | C21: =D43 -> 36406.5 | D21: =D44 -> 106220.07 | E21: ='P&L'!D24 -> 36406.5
A22: Net income — whole plan | B22: =SUM(B42:D42) -> -728442.32 | C22: =SUM(B43:D43) -> -198611.63 | D22: =SUM(B44:D44) -> 150683.88 | E22: =SUM('P&L'!$B$24:$D$24) -> -198611.63
A23: Cash at the end of the plan | B23: =D48 -> -449313.79 | C23: =D49 -> 80715.102 | D23: =D50 -> 429925.03 | E23: ='Balance Sheet'!D5 -> 80715.102
A24: Lowest cash balance | B24: =MIN('Scenario calc'!$C$83:$AL$83) -> -449313.79 | C24: =MIN('Scenario calc'!$C$193:$AL$193) -> 7440.3636 | D24: =MIN('Scenario calc'!$C$303:$AL$303) -> 155942.75 | E24: ='Break-even'!B18 -> 7440.3636
A25: Lowest cash point (month #) | B25: =MATCH(MIN('Scenario calc'!$C$83:$AL$83),'Scenario calc'!$C$83:$AL$83,0) -> 36 | C25: =MATCH(MIN('Scenario calc'!$C$193:$AL$193),'Scenario calc'!$C$193:$AL$193,0) -> 16 | D25: =MATCH(MIN('Scenario calc'!$C$303:$AL$303),'Scenario calc'!$C$303:$AL$303,0) -> 7 | E25: ='Break-even'!B6 -> 16
A26: Funding required (incl. cash buffer) | B26: =SUMPRODUCT(--('Scenario calc'!$C$6:$AL$6<=B25),'Scenario calc'!$C$56:$AL$56)-SUMPRODUCT(--('Scenario calc'!$C$6:$AL$6<=B25),'Scenario calc'!$C$77:$AL$77)-SUMPRODUCT(--('Scenario calc'!$C$6:$AL$6<=B25),'Scenario calc'!$C$65:$AL$65)+Inputs!$B$69 -> 1040313.8 | C26: =SUMPRODUCT(--('Scenario calc'!$C$116:$AL$116<=C25),'Scenario calc'!$C$166:$AL$166)-SUMPRODUCT(--('Scenario calc'!$C$116:$AL$116<=C25),'Scenario calc'!$C$187:$AL$187)-SUMPRODUCT(--('Scenario calc'!$C$116:$AL$116<=C25),'Scenario calc'!$C$175:$AL$175)+Inputs!$C$69 -> 583559.64 | D26: =SUMPRODUCT(--('Scenario calc'!$C$226:$AL$226<=D25),'Scenario calc'!$C$276:$AL$276)-SUMPRODUCT(--('Scenario calc'!$C$226:$AL$226<=D25),'Scenario calc'!$C$297:$AL$297)-SUMPRODUCT(--('Scenario calc'!$C$226:$AL$226<=D25),'Scenario calc'!$C$285:$AL$285)+Inputs!$D$69 -> 435057.25 | E26: ='Break-even'!B12 -> 583559.64
A28: Revenue by year ($'000)
A29: Scenario | B29: 1 | C29: 2 | D29: 3
A30: Low | B30: =SUMIF('Scenario calc'!$C$7:$AL$7,B$29,'Scenario calc'!$C$26:$AL$26) -> 256826.28 | C30: =SUMIF('Scenario calc'!$C$7:$AL$7,C$29,'Scenario calc'!$C$26:$AL$26) -> 428874.85 | D30: =SUMIF('Scenario calc'!$C$7:$AL$7,D$29,'Scenario calc'!$C$26:$AL$26) -> 515887.22
A31: Base | B31: =SUMIF('Scenario calc'!$C$117:$AL$117,B$29,'Scenario calc'!$C$136:$AL$136) -> 393075.46 | C31: =SUMIF('Scenario calc'!$C$117:$AL$117,C$29,'Scenario calc'!$C$136:$AL$136) -> 663933.88 | D31: =SUMIF('Scenario calc'!$C$117:$AL$117,D$29,'Scenario calc'!$C$136:$AL$136) -> 722638.4
A32: High | B32: =SUMIF('Scenario calc'!$C$227:$AL$227,B$29,'Scenario calc'!$C$246:$AL$246) -> 570691.31 | C32: =SUMIF('Scenario calc'!$C$227:$AL$227,C$29,'Scenario calc'!$C$246:$AL$246) -> 791013.6 | D32: =SUMIF('Scenario calc'!$C$227:$AL$227,D$29,'Scenario calc'!$C$246:$AL$246) -> 822654.14
A34: EBITDA by year ($'000)
A35: Scenario | B35: 1 | C35: 2 | D35: 3
A36: Low | B36: =SUMIF('Scenario calc'!$C$7:$AL$7,B$35,'Scenario calc'!$C$44:$AL$44) -> -312506.71 | C36: =SUMIF('Scenario calc'!$C$7:$AL$7,C$35,'Scenario calc'!$C$44:$AL$44) -> -173170.87 | D36: =SUMIF('Scenario calc'!$C$7:$AL$7,D$35,'Scenario calc'!$C$44:$AL$44) -> -106913.55
A37: Base | B37: =SUMIF('Scenario calc'!$C$117:$AL$117,B$35,'Scenario calc'!$C$154:$AL$154) -> -182978.13 | C37: =SUMIF('Scenario calc'!$C$117:$AL$117,C$35,'Scenario calc'!$C$154:$AL$154) -> 40239.768 | D37: =SUMIF('Scenario calc'!$C$117:$AL$117,D$35,'Scenario calc'!$C$154:$AL$154) -> 79977.928
A38: High | B38: =SUMIF('Scenario calc'!$C$227:$AL$227,B$35,'Scenario calc'!$C$264:$AL$264) -> -14886.38 | C38: =SUMIF('Scenario calc'!$C$227:$AL$227,C$35,'Scenario calc'!$C$264:$AL$264) -> 163449.44 | D38: =SUMIF('Scenario calc'!$C$227:$AL$227,D$35,'Scenario calc'!$C$264:$AL$264) -> 178027.21
A40: Net income by year ($'000)
A41: Scenario | B41: 1 | C41: 2 | D41: 3
A42: Low | B42: =SUMIF('Scenario calc'!$C$7:$AL$7,B$41,'Scenario calc'!$C$53:$AL$53) -> -359500.76 | C42: =SUMIF('Scenario calc'!$C$7:$AL$7,C$41,'Scenario calc'!$C$53:$AL$53) -> -218456.58 | D42: =SUMIF('Scenario calc'!$C$7:$AL$7,D$41,'Scenario calc'!$C$53:$AL$53) -> -150484.98
A43: Base | B43: =SUMIF('Scenario calc'!$C$117:$AL$117,B$41,'Scenario calc'!$C$163:$AL$163) -> -229972.18 | C43: =SUMIF('Scenario calc'!$C$117:$AL$117,C$41,'Scenario calc'!$C$163:$AL$163) -> -5045.9468 | D43: =SUMIF('Scenario calc'!$C$117:$AL$117,D$41,'Scenario calc'!$C$163:$AL$163) -> 36406.5
A44: High | B44: =SUMIF('Scenario calc'!$C$227:$AL$227,B$41,'Scenario calc'!$C$273:$AL$273) -> -61880.427 | C44: =SUMIF('Scenario calc'!$C$227:$AL$227,C$41,'Scenario calc'!$C$273:$AL$273) -> 106344.24 | D44: =SUMIF('Scenario calc'!$C$227:$AL$227,D$41,'Scenario calc'!$C$273:$AL$273) -> 106220.07
A46: Cash at year end by year ($'000)
A47: Scenario | B47: 1 | C47: 2 | D47: 3
A48: Low | B48: =INDEX('Scenario calc'!$C$83:$AL$83,B$47*12) -> -109620.34 | C48: =INDEX('Scenario calc'!$C$83:$AL$83,C$47*12) -> -313379.12 | D48: =INDEX('Scenario calc'!$C$83:$AL$83,D$47*12) -> -449313.79
A49: Base | B49: =INDEX('Scenario calc'!$C$193:$AL$193,B$47*12) -> 20106.884 | C49: =INDEX('Scenario calc'!$C$193:$AL$193,C$47*12) -> 29886.464 | D49: =INDEX('Scenario calc'!$C$193:$AL$193,D$47*12) -> 80715.102
A50: High | B50: =INDEX('Scenario calc'!$C$303:$AL$303,B$47*12) -> 188486.61 | C50: =INDEX('Scenario calc'!$C$303:$AL$303,C$47*12) -> 309265.28 | D50: =INDEX('Scenario calc'!$C$303:$AL$303,D$47*12) -> 429925.03

Sheet Break-even
A1: Startup costs, funding need and break-even | F1: =HYPERLINK("#'Cover'!A1","◂ Contents") -> ◂ Contents
A2: Live for the selected scenario. Periods are counted in months from the start of the plan.
A3: Scenario shown | B3: =CHOOSE(Dashboard!$B$4,"Low","Base","High") -> Base
A5: Startup costs & funding need (up to the lowest cash point)
A6: Lowest cash point (month #) | B6: =MATCH(MIN(Monthly!$C$81:$AL$81),Monthly!$C$81:$AL$81,0) -> 16
A7: Capital spending up to the lowest cash point | B7: =SUMPRODUCT(--(Monthly!$C$4:$AL$4<=$B$6),Monthly!$C$54:$AL$54) -> 250000
A8: Operating cash burn up to the lowest cash point | B8: =-SUMPRODUCT(--(Monthly!$C$4:$AL$4<=$B$6),Monthly!$C$75:$AL$75) -> 195773.92 | D8: Losses and working capital before the business funds itself
A9: Loan repayments up to the lowest cash point | B9: =-SUMPRODUCT(--(Monthly!$C$4:$AL$4<=$B$6),Monthly!$C$63:$AL$63) -> 26785.714
A10: Total uses of funds | B10: =B7+B8+B9 -> 472559.64
A11: Minimum cash buffer to keep | B11: =Inputs!$E$69 -> 111000 | D11: Input on the Inputs sheet
A12: Funding required (uses + buffer) | B12: =B10+B11 -> 583559.64
A14: Equity raised | B14: =Inputs!$E$54 -> 330000
A15: Loan drawn | B15: =Inputs!$E$55 -> 150000
A16: Total sources of funds | B16: =B14+B15 -> 480000
A17: Funding surplus / (shortfall) | B17: =B16-B12 -> -103559.64 | D17: Negative = raise at least this much more
A18: Lowest cash balance in the plan | B18: =MIN(Monthly!$C$81:$AL$81) -> 7440.3636 | D18: Equals sources minus uses
A20: Break-even timing
A21: First month with positive EBITDA (month #) | B21: =IFERROR(MATCH(1,Monthly!$C$82:$AL$82,0),"Not within horizon") -> 15
A22: First month with positive net income (month #) | B22: =IFERROR(MATCH(1,Monthly!$C$85:$AL$85,0),"Not within horizon") -> 18
A23: Cash invested paid back (month #) | B23: =IF(MIN(Monthly!$C$87:$AL$87)>=0,"No investment to pay back",IFERROR(MATCH(1,Monthly!$C$89:$AL$89,0),"Not within horizon")) -> Not within horizon | D23: Cumulative operating + investing cash flow back to zero
A25: Annual break-even revenue
A26: Year # | B26: 1 | C26: 2 | D26: 3
B27: Year 1 | C27: Year 2 | D27: Year 3
A28: Revenue | B28: =SUMIF(Monthly!$C$5:$AL$5,B$26,Monthly!$C$24:$AL$24) -> 393075.46 | C28: =SUMIF(Monthly!$C$5:$AL$5,C$26,Monthly!$C$24:$AL$24) -> 663933.88 | D28: =SUMIF(Monthly!$C$5:$AL$5,D$26,Monthly!$C$24:$AL$24) -> 722638.4
A29: Gross profit | B29: =SUMIF(Monthly!$C$5:$AL$5,B$26,Monthly!$C$31:$AL$31) -> 262844.88 | C29: =SUMIF(Monthly!$C$5:$AL$5,C$26,Monthly!$C$31:$AL$31) -> 504280.12 | D29: =SUMIF(Monthly!$C$5:$AL$5,D$26,Monthly!$C$31:$AL$31) -> 554018.95
A30: Gross margin (contribution) | B30: =IF(B28=0,0,B29/B28) -> 0.6686881 | C30: =IF(C28=0,0,C29/C28) -> 0.75953364 | D30: =IF(D28=0,0,D29/D28) -> 0.76666138
A31: Operating expenses (treated as fixed) | B31: =-SUMIF(Monthly!$C$5:$AL$5,B$26,Monthly!$C$41:$AL$41) -> 445823.02 | C31: =-SUMIF(Monthly!$C$5:$AL$5,C$26,Monthly!$C$41:$AL$41) -> 464040.36 | D31: =-SUMIF(Monthly!$C$5:$AL$5,D$26,Monthly!$C$41:$AL$41) -> 474041.03
A32: Break-even revenue (EBITDA = 0) | B32: =IF(B30>0,B31/B30,"n/a") -> 666712.95 | C32: =IF(C30>0,C31/C30,"n/a") -> 610954.31 | D32: =IF(D30>0,D31/D30,"n/a") -> 618318.64
A33: Margin of safety (revenue above break-even) | B33: =IF(AND(ISNUMBER(B32),B28>0),(B28-B32)/B28,"n/a") -> -0.69614493 | C33: =IF(AND(ISNUMBER(C32),C28>0),(C28-C32)/C28,"n/a") -> 0.079796458 | D33: =IF(AND(ISNUMBER(D32),D28>0),(D28-D32)/D28,"n/a") -> 0.14435955
A35: Simplification: cost of sales is treated as variable and operating expenses as fixed, so break-even revenue = operating expenses ÷ gross margin. In a year with zero or negative gross margin there is no break-even revenue (n/a); the chart line shows 0 there.

Sheet Valuation
A1: Discounted cash flow valuation | H1: =HYPERLINK("#'Cover'!A1","◂ Contents") -> ◂ Contents
A2: Enterprise value at the start of the plan, before the funding raised in period 1. Year-end discounting.
A3: Scenario shown | B3: =CHOOSE(Dashboard!$B$4,"Low","Base","High") -> Base
A5: Assumptions (active scenario, from the Inputs sheet)
A6: Discount rate (WACC) | B6: =Inputs!$E$72 -> 0.25
A7: Terminal growth rate | B7: =Inputs!$E$73 -> 0.02
A8: Exit multiple (EV ÷ final-year EBITDA) | B8: =Inputs!$E$74 -> 4
A9: Tax rate (for the interest tax shield) | B9: =Inputs!$E$66 -> 0.21
A10: Sensitivity step: WACC | B10: =Inputs!$E$75 -> 0.01
A11: Sensitivity step: terminal growth | B11: =Inputs!$E$76 -> 0.005
A13: Free cash flow by year
A14: Year # | B14: 1 | C14: 2 | D14: 3
B15: Year 1 | C15: Year 2 | D15: Year 3
A16: EBITDA | B16: =SUMIF(Monthly!$C$5:$AL$5,B$14,Monthly!$C$42:$AL$42) -> -182978.13 | C16: =SUMIF(Monthly!$C$5:$AL$5,C$14,Monthly!$C$42:$AL$42) -> 40239.768 | D16: =SUMIF(Monthly!$C$5:$AL$5,D$14,Monthly!$C$42:$AL$42) -> 79977.928
A17: Unlevered free cash flow | B17: =SUMIF(Monthly!$C$5:$AL$5,B$14,Monthly!$C$90:$AL$90) -> -431339.25 | C17: =SUMIF(Monthly!$C$5:$AL$5,C$14,Monthly!$C$90:$AL$90) -> 38769.581 | D17: =SUMIF(Monthly!$C$5:$AL$5,D$14,Monthly!$C$90:$AL$90) -> 78464.352
A18: Discount factor | B18: =1/(1+Inputs!$E$72)^B$14 -> 0.8 | C18: =1/(1+Inputs!$E$72)^C$14 -> 0.64 | D18: =1/(1+Inputs!$E$72)^D$14 -> 0.512
A19: Present value of free cash flow | B19: =B17*B18 -> -345071.4 | C19: =C17*C18 -> 24812.532 | D19: =D17*D18 -> 40173.748
A21: Enterprise value
B22: Perpetual growth | C22: Exit multiple
A23: Present value of the plan's free cash flows | B23: =SUM($B$19:$D$19) -> -280085.12 | C23: =B23 -> -280085.12
A24: Final-year free cash flow | final-year EBITDA | B24: =$D$17 -> 78464.352 | C24: =$D$16 -> 79977.928
A25: Terminal value at the end of year 3 | B25: =IF($B$6>$B$7,B24*(1+$B$7)/($B$6-$B$7),0) -> 347972.34 | C25: =C24*$B$8 -> 319911.71
A26: Present value of the terminal value | B26: =B25/(1+$B$6)^$D$14 -> 178161.84 | C26: =C25/(1+$B$6)^$D$14 -> 163794.8
A27: Enterprise value | B27: =B23+B26 -> -101923.28 | C27: =C23+C26 -> -116290.32
A28: Terminal value share of enterprise value | B28: =IF(B27<>0,B26/B27,0) -> -1.7479995 | C28: =IF(C27<>0,C26/C27,0) -> -1.408499
A29: Cross-check: implied exit multiple | implied perpetual growth | B29: =IF(C24>0,B25/C24,"n/a") -> 4.3508547 | C29: =IF(C25+B24<>0,(C25*$B$6-B24)/(C25+B24),"n/a") -> 0.0037993661
A30: Enterprise value — average of the two methods | B30: =AVERAGE(B27,C27) -> -109106.8
A32: Sensitivity: enterprise value (perpetual growth) by WACC and terminal growth
A33: WACC ↓ · terminal growth → | B33: =$B$7+(-2)*$B$11 -> 0.01 | C33: =$B$7+(-1)*$B$11 -> 0.015 | D33: =$B$7+(0)*$B$11 -> 0.02 | E33: =$B$7+(1)*$B$11 -> 0.025 | F33: =$B$7+(2)*$B$11 -> 0.03
A34: =$B$6+(-2)*$B$10 -> 0.23 | B34: =IF($A34>B$33,SUMPRODUCT($B$17:$D$17/(1+$A34)^$B$14:$D$14)+$D$17*(1+B$33)/($A34-B$33)/(1+$A34)^$D$14,"n/a") -> -89312.941 | C34: =IF($A34>C$33,SUMPRODUCT($B$17:$D$17/(1+$A34)^$B$14:$D$14)+$D$17*(1+C$33)/($A34-C$33)/(1+$A34)^$D$14,"n/a") -> -83830.537 | D34: =IF($A34>D$33,SUMPRODUCT($B$17:$D$17/(1+$A34)^$B$14:$D$14)+$D$17*(1+D$33)/($A34-D$33)/(1+$A34)^$D$14,"n/a") -> -78087.066 | E34: =IF($A34>E$33,SUMPRODUCT($B$17:$D$17/(1+$A34)^$B$14:$D$14)+$D$17*(1+E$33)/($A34-E$33)/(1+$A34)^$D$14,"n/a") -> -72063.426 | F34: =IF($A34>F$33,SUMPRODUCT($B$17:$D$17/(1+$A34)^$B$14:$D$14)+$D$17*(1+F$33)/($A34-F$33)/(1+$A34)^$D$14,"n/a") -> -65738.604
A35: =$B$6+(-1)*$B$10 -> 0.24 | B35: =IF($A35>B$33,SUMPRODUCT($B$17:$D$17/(1+$A35)^$B$14:$D$14)+$D$17*(1+B$33)/($A35-B$33)/(1+$A35)^$D$14,"n/a") -> -100768.55 | C35: =IF($A35>C$33,SUMPRODUCT($B$17:$D$17/(1+$A35)^$B$14:$D$14)+$D$17*(1+C$33)/($A35-C$33)/(1+$A35)^$D$14,"n/a") -> -95838.081 | D35: =IF($A35>D$33,SUMPRODUCT($B$17:$D$17/(1+$A35)^$B$14:$D$14)+$D$17*(1+D$33)/($A35-D$33)/(1+$A35)^$D$14,"n/a") -> -90683.494 | E35: =IF($A35>E$33,SUMPRODUCT($B$17:$D$17/(1+$A35)^$B$14:$D$14)+$D$17*(1+E$33)/($A35-E$33)/(1+$A35)^$D$14,"n/a") -> -85289.16 | F35: =IF($A35>F$33,SUMPRODUCT($B$17:$D$17/(1+$A35)^$B$14:$D$14)+$D$17*(1+F$33)/($A35-F$33)/(1+$A35)^$D$14,"n/a") -> -79637.952
A36: =$B$6+(0)*$B$10 -> 0.25 | B36: =IF($A36>B$33,SUMPRODUCT($B$17:$D$17/(1+$A36)^$B$14:$D$14)+$D$17*(1+B$33)/($A36-B$33)/(1+$A36)^$D$14,"n/a") -> -111020.59 | C36: =IF($A36>C$33,SUMPRODUCT($B$17:$D$17/(1+$A36)^$B$14:$D$14)+$D$17*(1+C$33)/($A36-C$33)/(1+$A36)^$D$14,"n/a") -> -106568.72 | D36: =IF($A36>D$33,SUMPRODUCT($B$17:$D$17/(1+$A36)^$B$14:$D$14)+$D$17*(1+D$33)/($A36-D$33)/(1+$A36)^$D$14,"n/a") -> -101923.28 | E36: =IF($A36>E$33,SUMPRODUCT($B$17:$D$17/(1+$A36)^$B$14:$D$14)+$D$17*(1+E$33)/($A36-E$33)/(1+$A36)^$D$14,"n/a") -> -97071.376 | F36: =IF($A36>F$33,SUMPRODUCT($B$17:$D$17/(1+$A36)^$B$14:$D$14)+$D$17*(1+F$33)/($A36-F$33)/(1+$A36)^$D$14,"n/a") -> -91998.933
A37: =$B$6+(1)*$B$10 -> 0.26 | B37: =IF($A37>B$33,SUMPRODUCT($B$17:$D$17/(1+$A37)^$B$14:$D$14)+$D$17*(1+B$33)/($A37-B$33)/(1+$A37)^$D$14,"n/a") -> -120219.49 | C37: =IF($A37>C$33,SUMPRODUCT($B$17:$D$17/(1+$A37)^$B$14:$D$14)+$D$17*(1+C$33)/($A37-C$33)/(1+$A37)^$D$14,"n/a") -> -116184.94 | D37: =IF($A37>D$33,SUMPRODUCT($B$17:$D$17/(1+$A37)^$B$14:$D$14)+$D$17*(1+D$33)/($A37-D$33)/(1+$A37)^$D$14,"n/a") -> -111982.28 | E37: =IF($A37>E$33,SUMPRODUCT($B$17:$D$17/(1+$A37)^$B$14:$D$14)+$D$17*(1+E$33)/($A37-E$33)/(1+$A37)^$D$14,"n/a") -> -107600.79 | F37: =IF($A37>F$33,SUMPRODUCT($B$17:$D$17/(1+$A37)^$B$14:$D$14)+$D$17*(1+F$33)/($A37-F$33)/(1+$A37)^$D$14,"n/a") -> -103028.79
A38: =$B$6+(2)*$B$10 -> 0.27 | B38: =IF($A38>B$33,SUMPRODUCT($B$17:$D$17/(1+$A38)^$B$14:$D$14)+$D$17*(1+B$33)/($A38-B$33)/(1+$A38)^$D$14,"n/a") -> -128492.34 | C38: =IF($A38>C$33,SUMPRODUCT($B$17:$D$17/(1+$A38)^$B$14:$D$14)+$D$17*(1+C$33)/($A38-C$33)/(1+$A38)^$D$14,"n/a") -> -124823.56 | D38: =IF($A38>D$33,SUMPRODUCT($B$17:$D$17/(1+$A38)^$B$14:$D$14)+$D$17*(1+D$33)/($A38-D$33)/(1+$A38)^$D$14,"n/a") -> -121008.03 | E38: =IF($A38>E$33,SUMPRODUCT($B$17:$D$17/(1+$A38)^$B$14:$D$14)+$D$17*(1+E$33)/($A38-E$33)/(1+$A38)^$D$14,"n/a") -> -117036.77 | F38: =IF($A38>F$33,SUMPRODUCT($B$17:$D$17/(1+$A38)^$B$14:$D$14)+$D$17*(1+F$33)/($A38-F$33)/(1+$A38)^$D$14,"n/a") -> -112900.03
A40: Free cash flow = operating cash flow + interest × (1 − tax rate) − capital spending. Cells marked n/a: WACC not above growth.

Sheet Sources & Uses
A1: Sources and uses of funds | E1: =HYPERLINK("#'Cover'!A1","◂ Contents") -> ◂ Contents
A2: Live for the selected scenario. Where the money comes from and where it goes in the period set below.
A3: Scenario shown | B3: =CHOOSE(Dashboard!$B$4,"Low","Base","High") -> Base
A5: Funding structure ($'000) — raised at the start of the plan
B6: Amount | C6: Share
A7: Equity | B7: =Inputs!$E$54 -> 330000 | C7: =IF($B$9=0,0,B7/$B$9) -> 0.6875
A8: Debt (loan) | B8: =Inputs!$E$55 -> 150000 | C8: =IF($B$9=0,0,B8/$B$9) -> 0.3125
A9: Total funding | B9: =B7+B8 -> 480000 | C9: =IF(B9=0,0,1) -> 1
A10: Gearing (debt ÷ equity) | B10: =IF(B7<=0,IF(B8>0,"n/a",0),B8/B7) -> 0.45454545 | D10: n/a: debt without positive equity
A11: Funding required by the plan (Break-even sheet) | B11: ='Break-even'!B12 -> 583559.64
A12: Funding surplus / (shortfall) | B12: ='Break-even'!B17 -> -103559.64
A14: ="Sources and uses of cash in the first "&$B$16&IF($B$16=1," month"," months")&" ($'000)" -> Sources and uses of cash in the first 12 months ($'000)
A15: Period covered (months from the start) | B15: 12 | D15: 1 to 36 (capped)
A16: Months used | B16: =MIN(36,MAX(1,ROUND(B15,0))) -> 12
A17: Sources | B17: Amount | C17: Share
A18: Equity raised | B18: =SUMPRODUCT(--(Monthly!$C$4:$AL$4<=$B$16),Monthly!$C$77:$AL$77) -> 330000 | C18: =IF($B$21=0,0,B18/$B$21) -> 0.6875
A19: Loan drawdowns | B19: =SUMPRODUCT(--(Monthly!$C$4:$AL$4<=$B$16),Monthly!$C$62:$AL$62) -> 150000 | C19: =IF($B$21=0,0,B19/$B$21) -> 0.3125
A20: Cash generated by operations | B20: =MAX(0,SUMPRODUCT(--(Monthly!$C$4:$AL$4<=$B$16),Monthly!$C$75:$AL$75)) -> 0 | C20: =IF($B$21=0,0,B20/$B$21) -> 0
A21: Total sources | B21: =SUM(B18:B20) -> 480000 | C21: =IF(B21=0,0,1) -> 1
A23: Uses | B23: Amount | C23: Share
A24: Cash used by operations | B24: =MAX(0,-SUMPRODUCT(--(Monthly!$C$4:$AL$4<=$B$16),Monthly!$C$75:$AL$75)) -> 190250.26 | C24: =IF($B$28=0,0,B24/$B$28) -> 0.39635471
A25: Capital spending | B25: =-SUMPRODUCT(--(Monthly!$C$4:$AL$4<=$B$16),Monthly!$C$76:$AL$76) -> 250000 | C25: =IF($B$28=0,0,B25/$B$28) -> 0.52083333
A26: Loan repayments | B26: =-SUMPRODUCT(--(Monthly!$C$4:$AL$4<=$B$16),Monthly!$C$63:$AL$63) -> 19642.857 | C26: =IF($B$28=0,0,B26/$B$28) -> 0.040922619
A27: Cash at the end of the period | B27: =INDEX(Monthly!$C$81:$AL$81,$B$16) -> 20106.884 | C27: =IF($B$28=0,0,B27/$B$28) -> 0.041889341
A28: Total uses | B28: =SUM(B24:B27) -> 480000 | C28: =IF(B28=0,0,1) -> 1
A29: Sources − uses (must be 0; opening cash is 0) | B29: =B21-B28 -> 0

Sheet KPIs
A1: KPIs & ratios | G1: =HYPERLINK("#'Cover'!A1","◂ Contents") -> ◂ Contents
A2: Fitness studio financial model (planning) — industry metrics and financial ratios for the active scenario
A4: Financial ratios
B5: 1 | C5: 2 | D5: 3 | E5: Target
A6: Revenue growth | B6: =IF(N('P&L'!A5)<=0,"n/a",'P&L'!B5/'P&L'!A5-1) -> n/a | C6: =IF(N('P&L'!B5)<=0,"n/a",'P&L'!C5/'P&L'!B5-1) -> 0.68907488 | D6: =IF(N('P&L'!C5)<=0,"n/a",'P&L'!D5/'P&L'!C5-1) -> 0.08841922
A7: Gross margin | B7: =IF('P&L'!B5<=0,"n/a",'P&L'!B7/'P&L'!B5) -> 0.6686881 | C7: =IF('P&L'!C5<=0,"n/a",'P&L'!C7/'P&L'!C5) -> 0.75953364 | D7: =IF('P&L'!D5<=0,"n/a",'P&L'!D7/'P&L'!D5) -> 0.76666138
A8: EBITDA margin | B8: =IF('P&L'!B5<=0,"n/a",'P&L'!B17/'P&L'!B5) -> -0.46550384 | C8: =IF('P&L'!C5<=0,"n/a",'P&L'!C17/'P&L'!C5) -> 0.060608094 | D8: =IF('P&L'!D5<=0,"n/a",'P&L'!D17/'P&L'!D5) -> 0.11067489
A9: Net margin | B9: =IF('P&L'!B5<=0,"n/a",'P&L'!B24/'P&L'!B5) -> -0.58505861 | C9: =IF('P&L'!C5<=0,"n/a",'P&L'!C24/'P&L'!C5) -> -0.0076000742 | D9: =IF('P&L'!D5<=0,"n/a",'P&L'!D24/'P&L'!D5) -> 0.050379968
A10: Payroll, % of revenue | B10: =IF('P&L'!B5<=0,"n/a",-SUMIF(Headcount!$C$5:$AL$5,B$5,Headcount!$C$15:$AL$15)/'P&L'!B5) -> 0.42256517 | C10: =IF('P&L'!C5<=0,"n/a",-SUMIF(Headcount!$C$5:$AL$5,C$5,Headcount!$C$15:$AL$15)/'P&L'!C5) -> 0.25768078 | D10: =IF('P&L'!D5<=0,"n/a",-SUMIF(Headcount!$C$5:$AL$5,D$5,Headcount!$C$15:$AL$15)/'P&L'!D5) -> 0.24385016
A11: Marketing, % of revenue | B11: =IF('P&L'!B5<=0,"n/a",-'P&L'!B10/'P&L'!B5) -> 0.12211396 | C11: =IF('P&L'!C5<=0,"n/a",-'P&L'!C10/'P&L'!C5) -> 0.075911173 | D11: =IF('P&L'!D5<=0,"n/a",-'P&L'!D10/'P&L'!D5) -> 0.073231647
A12: Operating expenses, % of revenue | B12: =IF('P&L'!B5<=0,"n/a",-'P&L'!B16/'P&L'!B5) -> 1.1341919 | C12: =IF('P&L'!C5<=0,"n/a",-'P&L'!C16/'P&L'!C5) -> 0.69892555 | D12: =IF('P&L'!D5<=0,"n/a",-'P&L'!D16/'P&L'!D5) -> 0.65598649
A13: Current ratio (current assets ÷ current liabilities) | B13: =IF(('Balance Sheet'!B12-'Balance Sheet'!B11)<=0,"n/a",('Balance Sheet'!B5+'Balance Sheet'!B6+'Balance Sheet'!B7)/('Balance Sheet'!B12-'Balance Sheet'!B11)) -> 3.0085711 | C13: =IF(('Balance Sheet'!C12-'Balance Sheet'!C11)<=0,"n/a",('Balance Sheet'!C5+'Balance Sheet'!C6+'Balance Sheet'!C7)/('Balance Sheet'!C12-'Balance Sheet'!C11)) -> 3.7860685 | D13: =IF(('Balance Sheet'!D12-'Balance Sheet'!D11)<=0,"n/a",('Balance Sheet'!D5+'Balance Sheet'!D6+'Balance Sheet'!D7)/('Balance Sheet'!D12-'Balance Sheet'!D11)) -> 9.1162769
A14: Debt ÷ equity (loan ÷ total equity) | B14: =IF('Balance Sheet'!B15<=0,"n/a",'Balance Sheet'!B11/'Balance Sheet'!B15) -> 1.3032089 | C14: =IF('Balance Sheet'!C15<=0,"n/a",'Balance Sheet'!C11/'Balance Sheet'!C15) -> 1.1468354 | D14: =IF('Balance Sheet'!D15<=0,"n/a",'Balance Sheet'!D11/'Balance Sheet'!D15) -> 0.66596457
A15: Return on assets (net income ÷ year-end assets) | B15: =IF('Balance Sheet'!B9<=0,"n/a",'P&L'!B24/'Balance Sheet'!B9) -> -0.96464746 | C15: =IF('Balance Sheet'!C9<=0,"n/a",'P&L'!C24/'Balance Sheet'!C9) -> -0.023689297 | D15: =IF('Balance Sheet'!D9<=0,"n/a",'P&L'!D24/'Balance Sheet'!D9) -> 0.15949846
A16: Return on equity (net income ÷ year-end equity) | B16: =IF('Balance Sheet'!B15<=0,"n/a",'P&L'!B24/'Balance Sheet'!B15) -> -2.2990823 | C16: =IF('Balance Sheet'!C15<=0,"n/a",'P&L'!C24/'Balance Sheet'!C15) -> -0.053125367 | D16: =IF('Balance Sheet'!D15<=0,"n/a",'P&L'!D24/'Balance Sheet'!D15) -> 0.27709073
A18: DuPont analysis — return on equity = net margin × asset turnover × equity multiplier
B19: 1 | C19: 2 | D19: 3
A20: Net margin | B20: =IF('P&L'!B5<=0,"n/a",'P&L'!B24/'P&L'!B5) -> -0.58505861 | C20: =IF('P&L'!C5<=0,"n/a",'P&L'!C24/'P&L'!C5) -> -0.0076000742 | D20: =IF('P&L'!D5<=0,"n/a",'P&L'!D24/'P&L'!D5) -> 0.050379968
A21: × Asset turnover (revenue ÷ assets) | B21: =IF('Balance Sheet'!B9<=0,"n/a",'P&L'!B5/'Balance Sheet'!B9) -> 1.6488048 | C21: =IF('Balance Sheet'!C9<=0,"n/a",'P&L'!C5/'Balance Sheet'!C9) -> 3.1169823 | D21: =IF('Balance Sheet'!D9<=0,"n/a",'P&L'!D5/'Balance Sheet'!D9) -> 3.1659103
A22: × Equity multiplier (assets ÷ equity) | B22: =IF('Balance Sheet'!B15<=0,"n/a",'Balance Sheet'!B9/'Balance Sheet'!B15) -> 2.3833393 | C22: =IF('Balance Sheet'!C15<=0,"n/a",'Balance Sheet'!C9/'Balance Sheet'!C15) -> 2.2425894 | D22: =IF('Balance Sheet'!D15<=0,"n/a",'Balance Sheet'!D9/'Balance Sheet'!D15) -> 1.7372627
A23: Return on equity (product of the three) | B23: =IF(AND(ISNUMBER(B20),ISNUMBER(B21),ISNUMBER(B22)),B20*B21*B22,"n/a") -> -2.2990823 | C23: =IF(AND(ISNUMBER(C20),ISNUMBER(C21),ISNUMBER(C22)),C20*C21*C22,"n/a") -> -0.053125367 | D23: =IF(AND(ISNUMBER(D20),ISNUMBER(D21),ISNUMBER(D22)),D20*D21*D22,"n/a") -> 0.27709073
A24: Check: product − return on equity (must be 0) | B24: =IF(AND(ISNUMBER(B23),ISNUMBER(B16)),B23-B16,IF(ISNUMBER(B23),1,IF(AND(ISNUMBER(B16),ISNUMBER(B20),ISNUMBER(B21)),1,0))) -> 0 | C24: =IF(AND(ISNUMBER(C23),ISNUMBER(C16)),C23-C16,IF(ISNUMBER(C23),1,IF(AND(ISNUMBER(C16),ISNUMBER(C20),ISNUMBER(C21)),1,0))) -> 0 | D24: =IF(AND(ISNUMBER(D23),ISNUMBER(D16)),D23-D16,IF(ISNUMBER(D23),1,IF(AND(ISNUMBER(D16),ISNUMBER(D20),ISNUMBER(D21)),1,0))) -> 0
A26: Membership metrics ($'000; per-unit rows in $)
A27: Year # | B27: 1 | C27: 2 | D27: 3
B28: Year 1 | C28: Year 2 | D28: Year 3 | E28: Target
A29: Members (year end) | B29: =INDEX(Monthly!$C$14:$AL$14,B$27*12) -> 355.83586 | C29: =INDEX(Monthly!$C$14:$AL$14,C$27*12) -> 450 | D29: =INDEX(Monthly!$C$14:$AL$14,D$27*12) -> 450
A30: New members in the year | B30: =SUMIF(Monthly!$C$5:$AL$5,B$27,Monthly!$C$10:$AL$10) -> 410.4 | C30: =SUMIF(Monthly!$C$5:$AL$5,C$27,Monthly!$C$10:$AL$10) -> 439.92 | D30: =SUMIF(Monthly!$C$5:$AL$5,D$27,Monthly!$C$10:$AL$10) -> 471.816
A31: Members who cancelled in the year | B31: =SUMIF(Monthly!$C$5:$AL$5,B$27,Monthly!$C$12:$AL$12) -> -174.56414 | C31: =SUMIF(Monthly!$C$5:$AL$5,C$27,Monthly!$C$12:$AL$12) -> -301.65599 | D31: =SUMIF(Monthly!$C$5:$AL$5,D$27,Monthly!$C$12:$AL$12) -> -324
A32: Joins lost to the capacity limit | B32: =SUMIF(Monthly!$C$5:$AL$5,B$27,Monthly!$C$15:$AL$15) -> 0 | C32: =SUMIF(Monthly!$C$5:$AL$5,C$27,Monthly!$C$15:$AL$15) -> 44.099865 | D32: =SUMIF(Monthly!$C$5:$AL$5,D$27,Monthly!$C$15:$AL$15) -> 147.816
A33: Capacity used (year-end members ÷ capacity) | B33: =IF(Inputs!$E$8=0,0,B29/Inputs!$E$8) -> 0.79074635 | C33: =IF(Inputs!$E$8=0,0,C29/Inputs!$E$8) -> 1 | D33: =IF(Inputs!$E$8=0,0,D29/Inputs!$E$8) -> 1
A34: Membership fees per month at year end | B34: =B29*B35 -> 35227.75 | C34: =C29*C35 -> 45886.5 | D34: =D29*D35 -> 47263.095
A35: Membership fee per month ($) | B35: =INDEX(Monthly!$C$19:$AL$19,B$27*12) -> 99 | C35: =INDEX(Monthly!$C$19:$AL$19,C$27*12) -> 101.97 | D35: =INDEX(Monthly!$C$19:$AL$19,D$27*12) -> 105.0291
A36: Revenue | B36: =SUMIF(Monthly!$C$5:$AL$5,B$27,Monthly!$C$24:$AL$24) -> 393075.46 | C36: =SUMIF(Monthly!$C$5:$AL$5,C$27,Monthly!$C$24:$AL$24) -> 663933.88 | D36: =SUMIF(Monthly!$C$5:$AL$5,D$27,Monthly!$C$24:$AL$24) -> 722638.4
A37: Membership fees | B37: =SUMIF(Monthly!$C$5:$AL$5,B$27,Monthly!$C$20:$AL$20) -> 299704.71 | C37: =SUMIF(Monthly!$C$5:$AL$5,C$27,Monthly!$C$20:$AL$20) -> 517465.32 | D37: =SUMIF(Monthly!$C$5:$AL$5,D$27,Monthly!$C$20:$AL$20) -> 567157.14
A38: Personal training, retail & joining fees | B38: =B36-B37 -> 93370.751 | C38: =C36-C37 -> 146468.56 | D38: =D36-D37 -> 155481.26
A39: Marketing spend | B39: =-SUMIF(Monthly!$C$5:$AL$5,B$27,Monthly!$C$35:$AL$35) -> 48000 | C39: =-SUMIF(Monthly!$C$5:$AL$5,C$27,Monthly!$C$35:$AL$35) -> 50400 | D39: =-SUMIF(Monthly!$C$5:$AL$5,D$27,Monthly!$C$35:$AL$35) -> 52920
A40: New members from marketing | B40: =SUMIF(Monthly!$C$5:$AL$5,B$27,Monthly!$C$8:$AL$8) -> 230.4 | C40: =SUMIF(Monthly!$C$5:$AL$5,C$27,Monthly!$C$8:$AL$8) -> 241.92 | D40: =SUMIF(Monthly!$C$5:$AL$5,D$27,Monthly!$C$8:$AL$8) -> 254.016
A41: Marketing cost per new member ($) | B41: =IF(B40=0,0,B39/B40) -> 208.33333 | C41: =IF(C40=0,0,C39/C40) -> 208.33333 | D41: =IF(D40=0,0,D39/D40) -> 208.33333
A42: Gross profit | B42: =SUMIF(Monthly!$C$5:$AL$5,B$27,Monthly!$C$31:$AL$31) -> 262844.88 | C42: =SUMIF(Monthly!$C$5:$AL$5,C$27,Monthly!$C$31:$AL$31) -> 504280.12 | D42: =SUMIF(Monthly!$C$5:$AL$5,D$27,Monthly!$C$31:$AL$31) -> 554018.95
A43: Gross margin | B43: =IF(B36=0,0,B42/B36) -> 0.6686881 | C43: =IF(C36=0,0,C42/C36) -> 0.75953364 | D43: =IF(D36=0,0,D42/D36) -> 0.76666138
A44: Members who cancel per month | B44: =Inputs!$E$15 -> 0.06 | C44: =Inputs!$E$15 -> 0.06 | D44: =Inputs!$E$15 -> 0.06
A45: Member lifetime value (fee × gross margin ÷ monthly cancellations) ($) | B45: =IF(B44=0,0,B35*B43/B44) -> 1103.3354 | C45: =IF(C44=0,0,C35*C43/C44) -> 1290.8274 | D45: =IF(D44=0,0,D35*D43/D44) -> 1342.0292
A46: EBITDA | B46: =SUMIF(Monthly!$C$5:$AL$5,B$27,Monthly!$C$42:$AL$42) -> -182978.13 | C46: =SUMIF(Monthly!$C$5:$AL$5,C$27,Monthly!$C$42:$AL$42) -> 40239.768 | D46: =SUMIF(Monthly!$C$5:$AL$5,D$27,Monthly!$C$42:$AL$42) -> 79977.928
A47: EBITDA margin | B47: =IF(B36=0,0,B46/B36) -> -0.46550384 | C47: =IF(C36=0,0,C46/C36) -> 0.060608094 | D47: =IF(D36=0,0,D46/D36) -> 0.11067489
A48: Revenue per square foot ($) | B48: =IF(Inputs!$E$38=0,0,B36/Inputs!$E$38) -> 98.268865 | C48: =IF(Inputs!$E$38=0,0,C36/Inputs!$E$38) -> 165.98347 | D48: =IF(Inputs!$E$38=0,0,D36/Inputs!$E$38) -> 180.6596

Sheet Inputs
A1: Inputs — Low / Base / High | I1: =HYPERLINK("#'Cover'!A1","◂ Contents") -> ◂ Contents
A2: Illustrative assumptions — replace them with your own numbers.
A5: Driver | B5: Low | C5: Base | D5: High | E5: Active | F5: Unit | G5: Source / comment
A6: Members
A7: Members at start (presale or current base) | B7: 80 | C7: 120 | D7: 160 | E7: =CHOOSE(Dashboard!$B$4,B7,C7,D7) -> 120 | F7: # | G7: Low ≤ Base ≤ High
A8: Capacity: most members the studio can hold | B8: 450 | C8: 450 | D8: 450 | E8: =CHOOSE(Dashboard!$B$4,B8,C8,D8) -> 450 | F8: #
A9: Referral & walk-in joins per month (year 1) | B9: 12 | C9: 15 | D9: 18 | E9: =CHOOSE(Dashboard!$B$4,B9,C9,D9) -> 15 | F9: # | G9: Low ≤ Base ≤ High
A10: Referral & walk-in joins growth per year | B10: 0.05 | C10: 0.1 | D10: 0.15 | E10: =CHOOSE(Dashboard!$B$4,B10,C10,D10) -> 0.1 | F10: % | G10: Low ≤ Base ≤ High
A11: Marketing budget per month (year 1) | B11: 4000 | C11: 4000 | D11: 4000 | E11: =CHOOSE(Dashboard!$B$4,B11,C11,D11) -> 4000 | F11: $
A12: Marketing budget growth per year | B12: 0 | C12: 0.05 | D12: 0.1 | E12: =CHOOSE(Dashboard!$B$4,B12,C12,D12) -> 0.05 | F12: % | G12: Low ≤ Base ≤ High
A13: Cost per lead | B13: 28 | C13: 25 | D13: 22 | E13: =CHOOSE(Dashboard!$B$4,B13,C13,D13) -> 25 | F13: $ | G13: Low ≥ Base ≥ High (lower is better)
A14: Leads that join | B14: 0.11 | C14: 0.12 | D14: 0.13 | E14: =CHOOSE(Dashboard!$B$4,B14,C14,D14) -> 0.12 | F14: % | G14: Low ≤ Base ≤ High
A15: Members who cancel per month | B15: 0.07 | C15: 0.06 | D15: 0.05 | E15: =CHOOSE(Dashboard!$B$4,B15,C15,D15) -> 0.06 | F15: % | G15: Low ≥ Base ≥ High (lower is better)
A17: Prices
A18: Membership fee per month (year 1) | B18: 89 | C18: 99 | D18: 109 | E18: =CHOOSE(Dashboard!$B$4,B18,C18,D18) -> 99 | F18: $ | G18: Low ≤ Base ≤ High
A19: Price increase per year | B19: 0.02 | C19: 0.03 | D19: 0.04 | E19: =CHOOSE(Dashboard!$B$4,B19,C19,D19) -> 0.03 | F19: % | G19: Low ≤ Base ≤ High
A20: Joining fee per new member | B20: 49 | C20: 49 | D20: 49 | E20: =CHOOSE(Dashboard!$B$4,B20,C20,D20) -> 49 | F20: $ | G20: Low ≤ Base ≤ High
A22: Personal training & retail
A23: Members buying personal training | B23: 0.07 | C23: 0.08 | D23: 0.09 | E23: =CHOOSE(Dashboard!$B$4,B23,C23,D23) -> 0.08 | F23: % | G23: Low ≤ Base ≤ High
A24: Sessions per personal-training client per month | B24: 4 | C24: 4 | D24: 4 | E24: =CHOOSE(Dashboard!$B$4,B24,C24,D24) -> 4 | F24: # | G24: Low ≤ Base ≤ High
A25: Price per personal-training session | B25: 55 | C25: 60 | D25: 65 | E25: =CHOOSE(Dashboard!$B$4,B25,C25,D25) -> 60 | F25: $ | G25: Low ≤ Base ≤ High
A26: Trainer payout, % of personal-training revenue | B26: 0.55 | C26: 0.5 | D26: 0.45 | E26: =CHOOSE(Dashboard!$B$4,B26,C26,D26) -> 0.5 | F26: % | G26: Low ≥ Base ≥ High (lower is better)
A27: Retail & drinks sales per member per month | B27: 4 | C27: 5 | D27: 6 | E27: =CHOOSE(Dashboard!$B$4,B27,C27,D27) -> 5 | F27: $ | G27: Low ≤ Base ≤ High
A28: Retail & drinks cost, % of sales | B28: 0.55 | C28: 0.5 | D28: 0.45 | E28: =CHOOSE(Dashboard!$B$4,B28,C28,D28) -> 0.5 | F28: % | G28: Low ≥ Base ≥ High (lower is better)
A30: Costs
A31: Group classes per week | B31: 40 | C31: 40 | D31: 40 | E31: =CHOOSE(Dashboard!$B$4,B31,C31,D31) -> 40 | F31: #
A32: Instructor cost per class (year 1) | B32: 50 | C32: 45 | D32: 40 | E32: =CHOOSE(Dashboard!$B$4,B32,C32,D32) -> 45 | F32: $ | G32: Low ≥ Base ≥ High (lower is better)
A33: Rent per month | B33: 12000 | C33: 12000 | D33: 12000 | E33: =CHOOSE(Dashboard!$B$4,B33,C33,D33) -> 12000 | F33: $
A34: Utilities per month | B34: 2200 | C34: 2200 | D34: 2200 | E34: =CHOOSE(Dashboard!$B$4,B34,C34,D34) -> 2200 | F34: $
A35: Equipment maintenance & cleaning per month | B35: 1800 | C35: 1800 | D35: 1800 | E35: =CHOOSE(Dashboard!$B$4,B35,C35,D35) -> 1800 | F35: $
A36: Booking software & payment fees, % of revenue | B36: 0.045 | C36: 0.04 | D36: 0.035 | E36: =CHOOSE(Dashboard!$B$4,B36,C36,D36) -> 0.04 | F36: % | G36: Low ≥ Base ≥ High (lower is better)
A37: Insurance & other G&A per month | B37: 2000 | C37: 2000 | D37: 2000 | E37: =CHOOSE(Dashboard!$B$4,B37,C37,D37) -> 2000 | F37: $
A38: Studio size | B38: 4000 | C38: 4000 | D38: 4000 | E38: =CHOOSE(Dashboard!$B$4,B38,C38,D38) -> 4000 | F38: sq ft
A39: Fit-out & equipment (month 1) | B39: 250000 | C39: 250000 | D39: 250000 | E39: =CHOOSE(Dashboard!$B$4,B39,C39,D39) -> 250000 | F39: $
A41: Headcount
A42: Studio manager: headcount (FTE) | B42: 1 | C42: 1 | D42: 1 | E42: =CHOOSE(Dashboard!$B$4,B42,C42,D42) -> 1 | F42: FTE | G42: Low ≤ Base ≤ High
A43: Studio manager: salary per FTE per year | B43: 55000 | C43: 55000 | D43: 55000 | E43: =CHOOSE(Dashboard!$B$4,B43,C43,D43) -> 55000 | F43: $
A44: Studio manager: headcount growth per year | B44: 0 | C44: 0 | D44: 0 | E44: =CHOOSE(Dashboard!$B$4,B44,C44,D44) -> 0 | F44: % | G44: Low ≤ Base ≤ High
A45: Studio manager: first month on payroll | B45: 1 | C45: 1 | D45: 1 | E45: =CHOOSE(Dashboard!$B$4,B45,C45,D45) -> 1 | F45: month #
A46: Front desk & sales: headcount (FTE) | B46: 3 | C46: 3 | D46: 3 | E46: =CHOOSE(Dashboard!$B$4,B46,C46,D46) -> 3 | F46: FTE | G46: Low ≤ Base ≤ High
A47: Front desk & sales: salary per FTE per year | B47: 32000 | C47: 32000 | D47: 32000 | E47: =CHOOSE(Dashboard!$B$4,B47,C47,D47) -> 32000 | F47: $
A48: Front desk & sales: headcount growth per year | B48: 0 | C48: 0 | D48: 0 | E48: =CHOOSE(Dashboard!$B$4,B48,C48,D48) -> 0 | F48: % | G48: Low ≤ Base ≤ High
A49: Front desk & sales: first month on payroll | B49: 1 | C49: 1 | D49: 1 | E49: =CHOOSE(Dashboard!$B$4,B49,C49,D49) -> 1 | F49: month #
A50: Payroll taxes & benefits, % of salary | B50: 0.1 | C50: 0.1 | D50: 0.1 | E50: =CHOOSE(Dashboard!$B$4,B50,C50,D50) -> 0.1 | F50: %
A51: Wage growth per year | B51: 0.03 | C51: 0.03 | D51: 0.03 | E51: =CHOOSE(Dashboard!$B$4,B51,C51,D51) -> 0.03 | F51: %
A53: Funding
A54: Equity raised at start | B54: 330000 | C54: 330000 | D54: 330000 | E54: =CHOOSE(Dashboard!$B$4,B54,C54,D54) -> 330000 | F54: $
A55: Loan drawn at start | B55: 150000 | C55: 150000 | D55: 150000 | E55: =CHOOSE(Dashboard!$B$4,B55,C55,D55) -> 150000 | F55: $
A56: Loan interest rate per year | B56: 0.08 | C56: 0.08 | D56: 0.08 | E56: =CHOOSE(Dashboard!$B$4,B56,C56,D56) -> 0.08 | F56: %
A57: Loan repayment term | B57: 7 | C57: 7 | D57: 7 | E57: =CHOOSE(Dashboard!$B$4,B57,C57,D57) -> 7 | F57: years
A59: Working capital
A60: Customer payment terms (receivable days) | B60: 0 | C60: 0 | D60: 0 | E60: =CHOOSE(Dashboard!$B$4,B60,C60,D60) -> 0 | F60: days
A61: Inventory held (days of COGS) | B61: 10 | C61: 10 | D61: 10 | E61: =CHOOSE(Dashboard!$B$4,B61,C61,D61) -> 10 | F61: days
A62: Supplier payment terms (payable days) | B62: 20 | C62: 20 | D62: 20 | E62: =CHOOSE(Dashboard!$B$4,B62,C62,D62) -> 20 | F62: days
A64: Tax & depreciation
A65: Depreciation period for capex | B65: 7 | C65: 7 | D65: 7 | E65: =CHOOSE(Dashboard!$B$4,B65,C65,D65) -> 7 | F65: years
A66: Income tax rate | B66: 0.21 | C66: 0.21 | D66: 0.21 | E66: =CHOOSE(Dashboard!$B$4,B66,C66,D66) -> 0.21 | F66: %
A68: Break-even & funding
A69: Minimum cash buffer to keep | B69: 111000 | C69: 111000 | D69: 111000 | E69: =CHOOSE(Dashboard!$B$4,B69,C69,D69) -> 111000 | F69: $ | G69: About 3 months of costs
A71: Valuation
A72: Discount rate (WACC) | B72: 0.3 | C72: 0.25 | D72: 0.2 | E72: =CHOOSE(Dashboard!$B$4,B72,C72,D72) -> 0.25 | F72: % | G72: Low ≥ Base ≥ High (lower is better)
A73: Terminal growth rate (perpetuity) | B73: 0.01 | C73: 0.02 | D73: 0.03 | E73: =CHOOSE(Dashboard!$B$4,B73,C73,D73) -> 0.02 | F73: % | G73: Low ≤ Base ≤ High
A74: Exit multiple (EV ÷ final-year EBITDA) | B74: 3 | C74: 4 | D74: 5 | E74: =CHOOSE(Dashboard!$B$4,B74,C74,D74) -> 4 | F74: x | G74: Low ≤ Base ≤ High
A75: Sensitivity table: WACC step | B75: 0.01 | C75: 0.01 | D75: 0.01 | E75: =CHOOSE(Dashboard!$B$4,B75,C75,D75) -> 0.01 | F75: %
A76: Sensitivity table: growth step | B76: 0.005 | C76: 0.005 | D76: 0.005 | E76: =CHOOSE(Dashboard!$B$4,B76,C76,D76) -> 0.005 | F76: %
A78: Legend: yellow cell with blue figure = input you can change · black = formula · green = link to another sheet · grey = active value (column E follows the scenario on the Dashboard).

Sheet P&L
A1: Annual profit & loss | F1: =HYPERLINK("#'Cover'!A1","◂ Contents") -> ◂ Contents
A2: Rolled up from the period detail (SUMIF on the year row; balances at year end).
A3: Year # | B3: 1 | C3: 2 | D3: 3
B4: Year 1 | C4: Year 2 | D4: Year 3
A5: Revenue | B5: =SUMIF(Monthly!$C$5:$AL$5,B$3,Monthly!$C$24:$AL$24) -> 393075.46 | C5: =SUMIF(Monthly!$C$5:$AL$5,C$3,Monthly!$C$24:$AL$24) -> 663933.88 | D5: =SUMIF(Monthly!$C$5:$AL$5,D$3,Monthly!$C$24:$AL$24) -> 722638.4
A6: Cost of sales | B6: =SUMIF(Monthly!$C$5:$AL$5,B$3,Monthly!$C$30:$AL$30) -> -130230.58 | C6: =SUMIF(Monthly!$C$5:$AL$5,C$3,Monthly!$C$30:$AL$30) -> -159653.76 | D6: =SUMIF(Monthly!$C$5:$AL$5,D$3,Monthly!$C$30:$AL$30) -> -168619.45
A7: Gross profit | B7: =SUMIF(Monthly!$C$5:$AL$5,B$3,Monthly!$C$31:$AL$31) -> 262844.88 | C7: =SUMIF(Monthly!$C$5:$AL$5,C$3,Monthly!$C$31:$AL$31) -> 504280.12 | D7: =SUMIF(Monthly!$C$5:$AL$5,D$3,Monthly!$C$31:$AL$31) -> 554018.95
A8: Gross margin | B8: =IF(B5=0,0,B7/B5) -> 0.6686881 | C8: =IF(C5=0,0,C7/C5) -> 0.75953364 | D8: =IF(D5=0,0,D7/D5) -> 0.76666138
A9: Staff payroll | B9: =SUMIF(Monthly!$C$5:$AL$5,B$3,Monthly!$C$34:$AL$34) -> -166100 | C9: =SUMIF(Monthly!$C$5:$AL$5,C$3,Monthly!$C$34:$AL$34) -> -171083 | D9: =SUMIF(Monthly!$C$5:$AL$5,D$3,Monthly!$C$34:$AL$34) -> -176215.49
A10: Marketing | B10: =SUMIF(Monthly!$C$5:$AL$5,B$3,Monthly!$C$35:$AL$35) -> -48000 | C10: =SUMIF(Monthly!$C$5:$AL$5,C$3,Monthly!$C$35:$AL$35) -> -50400 | D10: =SUMIF(Monthly!$C$5:$AL$5,D$3,Monthly!$C$35:$AL$35) -> -52920
A11: Rent | B11: =SUMIF(Monthly!$C$5:$AL$5,B$3,Monthly!$C$36:$AL$36) -> -144000 | C11: =SUMIF(Monthly!$C$5:$AL$5,C$3,Monthly!$C$36:$AL$36) -> -144000 | D11: =SUMIF(Monthly!$C$5:$AL$5,D$3,Monthly!$C$36:$AL$36) -> -144000
A12: Utilities | B12: =SUMIF(Monthly!$C$5:$AL$5,B$3,Monthly!$C$37:$AL$37) -> -26400 | C12: =SUMIF(Monthly!$C$5:$AL$5,C$3,Monthly!$C$37:$AL$37) -> -26400 | D12: =SUMIF(Monthly!$C$5:$AL$5,D$3,Monthly!$C$37:$AL$37) -> -26400
A13: Equipment maintenance & cleaning | B13: =SUMIF(Monthly!$C$5:$AL$5,B$3,Monthly!$C$38:$AL$38) -> -21600 | C13: =SUMIF(Monthly!$C$5:$AL$5,C$3,Monthly!$C$38:$AL$38) -> -21600 | D13: =SUMIF(Monthly!$C$5:$AL$5,D$3,Monthly!$C$38:$AL$38) -> -21600
A14: Booking software & payment fees | B14: =SUMIF(Monthly!$C$5:$AL$5,B$3,Monthly!$C$39:$AL$39) -> -15723.018 | C14: =SUMIF(Monthly!$C$5:$AL$5,C$3,Monthly!$C$39:$AL$39) -> -26557.355 | D14: =SUMIF(Monthly!$C$5:$AL$5,D$3,Monthly!$C$39:$AL$39) -> -28905.536
A15: Insurance & other G&A | B15: =SUMIF(Monthly!$C$5:$AL$5,B$3,Monthly!$C$40:$AL$40) -> -24000 | C15: =SUMIF(Monthly!$C$5:$AL$5,C$3,Monthly!$C$40:$AL$40) -> -24000 | D15: =SUMIF(Monthly!$C$5:$AL$5,D$3,Monthly!$C$40:$AL$40) -> -24000
A16: Total operating expenses | B16: =SUMIF(Monthly!$C$5:$AL$5,B$3,Monthly!$C$41:$AL$41) -> -445823.02 | C16: =SUMIF(Monthly!$C$5:$AL$5,C$3,Monthly!$C$41:$AL$41) -> -464040.36 | D16: =SUMIF(Monthly!$C$5:$AL$5,D$3,Monthly!$C$41:$AL$41) -> -474041.03
A17: EBITDA | B17: =SUMIF(Monthly!$C$5:$AL$5,B$3,Monthly!$C$42:$AL$42) -> -182978.13 | C17: =SUMIF(Monthly!$C$5:$AL$5,C$3,Monthly!$C$42:$AL$42) -> 40239.768 | D17: =SUMIF(Monthly!$C$5:$AL$5,D$3,Monthly!$C$42:$AL$42) -> 79977.928
A18: EBITDA margin | B18: =IF(B5=0,0,B17/B5) -> -0.46550384 | C18: =IF(C5=0,0,C17/C5) -> 0.060608094 | D18: =IF(D5=0,0,D17/D5) -> 0.11067489
A19: Depreciation | B19: =SUMIF(Monthly!$C$5:$AL$5,B$3,Monthly!$C$56:$AL$56) -> -35714.286 | C19: =SUMIF(Monthly!$C$5:$AL$5,C$3,Monthly!$C$56:$AL$56) -> -35714.286 | D19: =SUMIF(Monthly!$C$5:$AL$5,D$3,Monthly!$C$56:$AL$56) -> -35714.286
A20: EBIT | B20: =SUMIF(Monthly!$C$5:$AL$5,B$3,Monthly!$C$45:$AL$45) -> -218692.42 | C20: =SUMIF(Monthly!$C$5:$AL$5,C$3,Monthly!$C$45:$AL$45) -> 4525.4818 | D20: =SUMIF(Monthly!$C$5:$AL$5,D$3,Monthly!$C$45:$AL$45) -> 44263.643
A21: Interest | B21: =SUMIF(Monthly!$C$5:$AL$5,B$3,Monthly!$C$46:$AL$46) -> -11279.762 | C21: =SUMIF(Monthly!$C$5:$AL$5,C$3,Monthly!$C$46:$AL$46) -> -9571.4286 | D21: =SUMIF(Monthly!$C$5:$AL$5,D$3,Monthly!$C$46:$AL$46) -> -7857.1429
A22: Pre-tax income | B22: =SUMIF(Monthly!$C$5:$AL$5,B$3,Monthly!$C$47:$AL$47) -> -229972.18 | C22: =SUMIF(Monthly!$C$5:$AL$5,C$3,Monthly!$C$47:$AL$47) -> -5045.9468 | D22: =SUMIF(Monthly!$C$5:$AL$5,D$3,Monthly!$C$47:$AL$47) -> 36406.5
A23: Income tax | B23: =SUMIF(Monthly!$C$5:$AL$5,B$3,Monthly!$C$50:$AL$50) -> 0 | C23: =SUMIF(Monthly!$C$5:$AL$5,C$3,Monthly!$C$50:$AL$50) -> 0 | D23: =SUMIF(Monthly!$C$5:$AL$5,D$3,Monthly!$C$50:$AL$50) -> 0
A24: Net income | B24: =SUMIF(Monthly!$C$5:$AL$5,B$3,Monthly!$C$51:$AL$51) -> -229972.18 | C24: =SUMIF(Monthly!$C$5:$AL$5,C$3,Monthly!$C$51:$AL$51) -> -5045.9468 | D24: =SUMIF(Monthly!$C$5:$AL$5,D$3,Monthly!$C$51:$AL$51) -> 36406.5
A25: Net margin | B25: =IF(B5=0,0,B24/B5) -> -0.58505861 | C25: =IF(C5=0,0,C24/C5) -> -0.0076000742 | D25: =IF(D5=0,0,D24/D5) -> 0.050379968

Sheet Cash Flow
A1: Annual cash flow statement | F1: =HYPERLINK("#'Cover'!A1","◂ Contents") -> ◂ Contents
A2: Rolled up from the period detail (SUMIF on the year row; balances at year end).
A3: Year # | B3: 1 | C3: 2 | D3: 3
B4: Year 1 | C4: Year 2 | D4: Year 3
A5: Net income | B5: =SUMIF(Monthly!$C$5:$AL$5,B$3,Monthly!$C$51:$AL$51) -> -229972.18 | C5: =SUMIF(Monthly!$C$5:$AL$5,C$3,Monthly!$C$51:$AL$51) -> -5045.9468 | D5: =SUMIF(Monthly!$C$5:$AL$5,D$3,Monthly!$C$51:$AL$51) -> 36406.5
A6: Add back depreciation | B6: =-SUMIF(Monthly!$C$5:$AL$5,B$3,Monthly!$C$56:$AL$56) -> 35714.286 | C6: =-SUMIF(Monthly!$C$5:$AL$5,C$3,Monthly!$C$56:$AL$56) -> 35714.286 | D6: =-SUMIF(Monthly!$C$5:$AL$5,D$3,Monthly!$C$56:$AL$56) -> 35714.286
A7: (Increase) / decrease in receivables | B7: =SUMIF(Monthly!$C$5:$AL$5,B$3,Monthly!$C$70:$AL$70) -> 0 | C7: =SUMIF(Monthly!$C$5:$AL$5,C$3,Monthly!$C$70:$AL$70) -> 0 | D7: =SUMIF(Monthly!$C$5:$AL$5,D$3,Monthly!$C$70:$AL$70) -> 0
A8: (Increase) / decrease in inventory | B8: =SUMIF(Monthly!$C$5:$AL$5,B$3,Monthly!$C$71:$AL$71) -> -4007.6367 | C8: =SUMIF(Monthly!$C$5:$AL$5,C$3,Monthly!$C$71:$AL$71) -> -539.81331 | D8: =SUMIF(Monthly!$C$5:$AL$5,D$3,Monthly!$C$71:$AL$71) -> -136.4235
A9: Increase / (decrease) in payables | B9: =SUMIF(Monthly!$C$5:$AL$5,B$3,Monthly!$C$72:$AL$72) -> 8015.2734 | C9: =SUMIF(Monthly!$C$5:$AL$5,C$3,Monthly!$C$72:$AL$72) -> 1079.6266 | D9: =SUMIF(Monthly!$C$5:$AL$5,D$3,Monthly!$C$72:$AL$72) -> 272.847
A10: Operating cash flow | B10: =SUMIF(Monthly!$C$5:$AL$5,B$3,Monthly!$C$75:$AL$75) -> -190250.26 | C10: =SUMIF(Monthly!$C$5:$AL$5,C$3,Monthly!$C$75:$AL$75) -> 31208.152 | D10: =SUMIF(Monthly!$C$5:$AL$5,D$3,Monthly!$C$75:$AL$75) -> 72257.209
A11: Capital spending | B11: =SUMIF(Monthly!$C$5:$AL$5,B$3,Monthly!$C$76:$AL$76) -> -250000 | C11: =SUMIF(Monthly!$C$5:$AL$5,C$3,Monthly!$C$76:$AL$76) -> 0 | D11: =SUMIF(Monthly!$C$5:$AL$5,D$3,Monthly!$C$76:$AL$76) -> 0
A12: Equity raised | B12: =SUMIF(Monthly!$C$5:$AL$5,B$3,Monthly!$C$77:$AL$77) -> 330000 | C12: =SUMIF(Monthly!$C$5:$AL$5,C$3,Monthly!$C$77:$AL$77) -> 0 | D12: =SUMIF(Monthly!$C$5:$AL$5,D$3,Monthly!$C$77:$AL$77) -> 0
A13: Loan drawdown | B13: =SUMIF(Monthly!$C$5:$AL$5,B$3,Monthly!$C$62:$AL$62) -> 150000 | C13: =SUMIF(Monthly!$C$5:$AL$5,C$3,Monthly!$C$62:$AL$62) -> 0 | D13: =SUMIF(Monthly!$C$5:$AL$5,D$3,Monthly!$C$62:$AL$62) -> 0
A14: Loan repayment | B14: =SUMIF(Monthly!$C$5:$AL$5,B$3,Monthly!$C$63:$AL$63) -> -19642.857 | C14: =SUMIF(Monthly!$C$5:$AL$5,C$3,Monthly!$C$63:$AL$63) -> -21428.571 | D14: =SUMIF(Monthly!$C$5:$AL$5,D$3,Monthly!$C$63:$AL$63) -> -21428.571
A15: Financing cash flow | B15: =SUMIF(Monthly!$C$5:$AL$5,B$3,Monthly!$C$78:$AL$78) -> 460357.14 | C15: =SUMIF(Monthly!$C$5:$AL$5,C$3,Monthly!$C$78:$AL$78) -> -21428.571 | D15: =SUMIF(Monthly!$C$5:$AL$5,D$3,Monthly!$C$78:$AL$78) -> -21428.571
A16: Net change in cash | B16: =SUMIF(Monthly!$C$5:$AL$5,B$3,Monthly!$C$79:$AL$79) -> 20106.884 | C16: =SUMIF(Monthly!$C$5:$AL$5,C$3,Monthly!$C$79:$AL$79) -> 9779.5808 | D16: =SUMIF(Monthly!$C$5:$AL$5,D$3,Monthly!$C$79:$AL$79) -> 50828.638
A17: Opening cash | B17: =INDEX(Monthly!$C$80:$AL$80,(B$3-1)*12+1) -> 0 | C17: =INDEX(Monthly!$C$80:$AL$80,(C$3-1)*12+1) -> 20106.884 | D17: =INDEX(Monthly!$C$80:$AL$80,(D$3-1)*12+1) -> 29886.464
A18: Closing cash | B18: =INDEX(Monthly!$C$81:$AL$81,B$3*12) -> 20106.884 | C18: =INDEX(Monthly!$C$81:$AL$81,C$3*12) -> 29886.464 | D18: =INDEX(Monthly!$C$81:$AL$81,D$3*12) -> 80715.102

Sheet Balance Sheet
A1: Balance sheet at year end | F1: =HYPERLINK("#'Cover'!A1","◂ Contents") -> ◂ Contents
A2: Rolled up from the period detail (SUMIF on the year row; balances at year end).
A3: Year # | B3: 1 | C3: 2 | D3: 3
B4: Year 1 | C4: Year 2 | D4: Year 3
A5: Cash | B5: =INDEX(Monthly!$C$81:$AL$81,B$3*12) -> 20106.884 | C5: =INDEX(Monthly!$C$81:$AL$81,C$3*12) -> 29886.464 | D5: =INDEX(Monthly!$C$81:$AL$81,D$3*12) -> 80715.102
A6: Accounts receivable | B6: =INDEX(Monthly!$C$67:$AL$67,B$3*12) -> 0 | C6: =INDEX(Monthly!$C$67:$AL$67,C$3*12) -> 0 | D6: =INDEX(Monthly!$C$67:$AL$67,D$3*12) -> 0
A7: Inventory | B7: =INDEX(Monthly!$C$68:$AL$68,B$3*12) -> 4007.6367 | C7: =INDEX(Monthly!$C$68:$AL$68,C$3*12) -> 4547.45 | D7: =INDEX(Monthly!$C$68:$AL$68,D$3*12) -> 4683.8735
A8: Net fixed assets | B8: =INDEX(Monthly!$C$58:$AL$58,B$3*12) -> 214285.71 | C8: =INDEX(Monthly!$C$58:$AL$58,C$3*12) -> 178571.43 | D8: =INDEX(Monthly!$C$58:$AL$58,D$3*12) -> 142857.14
A9: Total assets | B9: =INDEX(Monthly!$C$95:$AL$95,B$3*12) -> 238400.23 | C9: =INDEX(Monthly!$C$95:$AL$95,C$3*12) -> 213005.34 | D9: =INDEX(Monthly!$C$95:$AL$95,D$3*12) -> 228256.12
A10: Accounts payable | B10: =INDEX(Monthly!$C$69:$AL$69,B$3*12) -> 8015.2734 | C10: =INDEX(Monthly!$C$69:$AL$69,C$3*12) -> 9094.9 | D10: =INDEX(Monthly!$C$69:$AL$69,D$3*12) -> 9367.747
A11: Loan | B11: =INDEX(Monthly!$C$64:$AL$64,B$3*12) -> 130357.14 | C11: =INDEX(Monthly!$C$64:$AL$64,C$3*12) -> 108928.57 | D11: =INDEX(Monthly!$C$64:$AL$64,D$3*12) -> 87500
A12: Total liabilities | B12: =INDEX(Monthly!$C$96:$AL$96,B$3*12) -> 138372.42 | C12: =INDEX(Monthly!$C$96:$AL$96,C$3*12) -> 118023.47 | D12: =INDEX(Monthly!$C$96:$AL$96,D$3*12) -> 96867.747
A13: Paid-in capital | B13: =INDEX(Monthly!$C$93:$AL$93,B$3*12) -> 330000 | C13: =INDEX(Monthly!$C$93:$AL$93,C$3*12) -> 330000 | D13: =INDEX(Monthly!$C$93:$AL$93,D$3*12) -> 330000
A14: Retained earnings | B14: =INDEX(Monthly!$C$94:$AL$94,B$3*12) -> -229972.18 | C14: =INDEX(Monthly!$C$94:$AL$94,C$3*12) -> -235018.13 | D14: =INDEX(Monthly!$C$94:$AL$94,D$3*12) -> -198611.63
A15: Total equity | B15: =INDEX(Monthly!$C$97:$AL$97,B$3*12) -> 100027.82 | C15: =INDEX(Monthly!$C$97:$AL$97,C$3*12) -> 94981.871 | D15: =INDEX(Monthly!$C$97:$AL$97,D$3*12) -> 131388.37
A16: Total liabilities & equity | B16: =INDEX(Monthly!$C$98:$AL$98,B$3*12) -> 238400.23 | C16: =INDEX(Monthly!$C$98:$AL$98,C$3*12) -> 213005.34 | D16: =INDEX(Monthly!$C$98:$AL$98,D$3*12) -> 228256.12
A17: Check: assets − liabilities − equity (must be 0) | B17: =INDEX(Monthly!$C$99:$AL$99,B$3*12) -> 0 | C17: =INDEX(Monthly!$C$99:$AL$99,C$3*12) -> 0 | D17: =INDEX(Monthly!$C$99:$AL$99,D$3*12) -> 0

Sheet Monthly
A1: Monthly projection | D1: =HYPERLINK("#'Cover'!A1","◂ Contents") -> ◂ Contents
A2: $ unless stated; costs shown as negatives. Every period uses the same formula.
A3: Month | C3: M1 | D3: M2 | E3: M3 | F3: M4 | G3: M5 | H3: M6 | I3: M7 | J3: M8 | K3: M9 | L3: M10 | M3: M11 | N3: M12 | O3: M13 | P3: M14 | Q3: M15 | R3: M16 | S3: M17 | T3: M18 | U3: M19 | V3: M20 | W3: M21 | X3: M22 | Y3: M23 | Z3: M24 | AA3: M25 | AB3: M26 | AC3: M27 | AD3: M28 | AE3: M29 | AF3: M30 | AG3: M31 | AH3: M32 | AI3: M33 | AJ3: M34 | AK3: M35 | AL3: M36
A4: Period # | C4: 1 | D4: 2 | E4: 3 | F4: 4 | G4: 5 | H4: 6 | I4: 7 | J4: 8 | K4: 9 | L4: 10 | M4: 11 | N4: 12 | O4: 13 | P4: 14 | Q4: 15 | R4: 16 | S4: 17 | T4: 18 | U4: 19 | V4: 20 | W4: 21 | X4: 22 | Y4: 23 | Z4: 24 | AA4: 25 | AB4: 26 | AC4: 27 | AD4: 28 | AE4: 29 | AF4: 30 | AG4: 31 | AH4: 32 | AI4: 33 | AJ4: 34 | AK4: 35 | AL4: 36
A5: Year # | C5: =ROUNDUP(C4*1/12,0) -> 1 | D5: =ROUNDUP(D4*1/12,0) -> 1 | E5: =ROUNDUP(E4*1/12,0) -> 1 | F5: =ROUNDUP(F4*1/12,0) -> 1 | G5: =ROUNDUP(G4*1/12,0) -> 1 | H5: =ROUNDUP(H4*1/12,0) -> 1 | I5: =ROUNDUP(I4*1/12,0) -> 1 | J5: =ROUNDUP(J4*1/12,0) -> 1 | ... AL5: =ROUNDUP(AL4*1/12,0) -> 3
A7: Members
A8: New members from marketing | C8: =-C35/MAX(1,Inputs!$E$13)*Inputs!$E$14 -> 19.2 | D8: =-D35/MAX(1,Inputs!$E$13)*Inputs!$E$14 -> 19.2 | E8: =-E35/MAX(1,Inputs!$E$13)*Inputs!$E$14 -> 19.2 | F8: =-F35/MAX(1,Inputs!$E$13)*Inputs!$E$14 -> 19.2 | G8: =-G35/MAX(1,Inputs!$E$13)*Inputs!$E$14 -> 19.2 | H8: =-H35/MAX(1,Inputs!$E$13)*Inputs!$E$14 -> 19.2 | I8: =-I35/MAX(1,Inputs!$E$13)*Inputs!$E$14 -> 19.2 | J8: =-J35/MAX(1,Inputs!$E$13)*Inputs!$E$14 -> 19.2 | ... AL8: =-AL35/MAX(1,Inputs!$E$13)*Inputs!$E$14 -> 21.168
A9: New members from referrals & walk-ins | C9: =Inputs!$E$9*(1+Inputs!$E$10)^(C$5-1)*1 -> 15 | D9: =Inputs!$E$9*(1+Inputs!$E$10)^(D$5-1)*1 -> 15 | E9: =Inputs!$E$9*(1+Inputs!$E$10)^(E$5-1)*1 -> 15 | F9: =Inputs!$E$9*(1+Inputs!$E$10)^(F$5-1)*1 -> 15 | G9: =Inputs!$E$9*(1+Inputs!$E$10)^(G$5-1)*1 -> 15 | H9: =Inputs!$E$9*(1+Inputs!$E$10)^(H$5-1)*1 -> 15 | I9: =Inputs!$E$9*(1+Inputs!$E$10)^(I$5-1)*1 -> 15 | J9: =Inputs!$E$9*(1+Inputs!$E$10)^(J$5-1)*1 -> 15 | ... AL9: =Inputs!$E$9*(1+Inputs!$E$10)^(AL$5-1)*1 -> 18.15
A10: New members — total | C10: =C8+C9 -> 34.2 | D10: =D8+D9 -> 34.2 | E10: =E8+E9 -> 34.2 | F10: =F8+F9 -> 34.2 | G10: =G8+G9 -> 34.2 | H10: =H8+H9 -> 34.2 | I10: =I8+I9 -> 34.2 | J10: =J8+J9 -> 34.2 | ... AL10: =AL8+AL9 -> 39.318
A11: Members — opening | C11: =Inputs!$E$7 -> 120 | D11: =C14 -> 147 | E11: =D14 -> 172.38 | F11: =E14 -> 196.2372 | G11: =F14 -> 218.66297 | H11: =G14 -> 239.74319 | I11: =H14 -> 259.5586 | J11: =I14 -> 278.18508 | K11: =J14 -> 295.69398 | ... AL11: =AK14 -> 450
A12: Members who cancelled | C12: =-C11*Inputs!$E$15 -> -7.2 | D12: =-D11*Inputs!$E$15 -> -8.82 | E12: =-E11*Inputs!$E$15 -> -10.3428 | F12: =-F11*Inputs!$E$15 -> -11.774232 | G12: =-G11*Inputs!$E$15 -> -13.119778 | H12: =-H11*Inputs!$E$15 -> -14.384591 | I12: =-I11*Inputs!$E$15 -> -15.573516 | J12: =-J11*Inputs!$E$15 -> -16.691105 | ... AL12: =-AL11*Inputs!$E$15 -> -27
A13: Helper: members before the capacity limit | C13: =C11*(1-Inputs!$E$15)+C10 -> 147 | D13: =D11*(1-Inputs!$E$15)+D10 -> 172.38 | E13: =E11*(1-Inputs!$E$15)+E10 -> 196.2372 | F13: =F11*(1-Inputs!$E$15)+F10 -> 218.66297 | G13: =G11*(1-Inputs!$E$15)+G10 -> 239.74319 | H13: =H11*(1-Inputs!$E$15)+H10 -> 259.5586 | I13: =I11*(1-Inputs!$E$15)+I10 -> 278.18508 | J13: =J11*(1-Inputs!$E$15)+J10 -> 295.69398 | ... AL13: =AL11*(1-Inputs!$E$15)+AL10 -> 462.318
A14: Members — closing | C14: =MIN(Inputs!$E$8,C13) -> 147 | D14: =MIN(Inputs!$E$8,D13) -> 172.38 | E14: =MIN(Inputs!$E$8,E13) -> 196.2372 | F14: =MIN(Inputs!$E$8,F13) -> 218.66297 | G14: =MIN(Inputs!$E$8,G13) -> 239.74319 | H14: =MIN(Inputs!$E$8,H13) -> 259.5586 | I14: =MIN(Inputs!$E$8,I13) -> 278.18508 | J14: =MIN(Inputs!$E$8,J13) -> 295.69398 | ... AL14: =MIN(Inputs!$E$8,AL13) -> 450
A15: Joins lost to the capacity limit | C15: =C13-C14 -> 0 | D15: =D13-D14 -> 0 | E15: =E13-E14 -> 0 | F15: =F13-F14 -> 0 | G15: =G13-G14 -> 0 | H15: =H13-H14 -> 0 | I15: =I13-I14 -> 0 | J15: =J13-J14 -> 0 | ... AL15: =AL13-AL14 -> 12.318
A16: Members — average | C16: =(C11+C14)/2 -> 133.5 | D16: =(D11+D14)/2 -> 159.69 | E16: =(E11+E14)/2 -> 184.3086 | F16: =(F11+F14)/2 -> 207.45008 | G16: =(G11+G14)/2 -> 229.20308 | H16: =(H11+H14)/2 -> 249.65089 | I16: =(I11+I14)/2 -> 268.87184 | J16: =(J11+J14)/2 -> 286.93953 | ... AL16: =(AL11+AL14)/2 -> 450
A18: Revenue
A19: Membership fee per month | C19: =Inputs!$E$18*(1+Inputs!$E$19)^(C$5-1) -> 99 | D19: =Inputs!$E$18*(1+Inputs!$E$19)^(D$5-1) -> 99 | E19: =Inputs!$E$18*(1+Inputs!$E$19)^(E$5-1) -> 99 | F19: =Inputs!$E$18*(1+Inputs!$E$19)^(F$5-1) -> 99 | G19: =Inputs!$E$18*(1+Inputs!$E$19)^(G$5-1) -> 99 | H19: =Inputs!$E$18*(1+Inputs!$E$19)^(H$5-1) -> 99 | I19: =Inputs!$E$18*(1+Inputs!$E$19)^(I$5-1) -> 99 | J19: =Inputs!$E$18*(1+Inputs!$E$19)^(J$5-1) -> 99 | ... AL19: =Inputs!$E$18*(1+Inputs!$E$19)^(AL$5-1) -> 105.0291
A20: Membership fees | C20: =C16*C19*1 -> 13216.5 | D20: =D16*D19*1 -> 15809.31 | E20: =E16*E19*1 -> 18246.551 | F20: =F16*F19*1 -> 20537.558 | G20: =G16*G19*1 -> 22691.105 | H20: =H16*H19*1 -> 24715.439 | I20: =I16*I19*1 -> 26618.312 | J20: =J16*J19*1 -> 28407.013 | ... AL20: =AL16*AL19*1 -> 47263.095
A21: Joining fees | C21: =(C10-C15)*Inputs!$E$20*(1+Inputs!$E$19)^(C$5-1) -> 1675.8 | D21: =(D10-D15)*Inputs!$E$20*(1+Inputs!$E$19)^(D$5-1) -> 1675.8 | E21: =(E10-E15)*Inputs!$E$20*(1+Inputs!$E$19)^(E$5-1) -> 1675.8 | F21: =(F10-F15)*Inputs!$E$20*(1+Inputs!$E$19)^(F$5-1) -> 1675.8 | G21: =(G10-G15)*Inputs!$E$20*(1+Inputs!$E$19)^(G$5-1) -> 1675.8 | H21: =(H10-H15)*Inputs!$E$20*(1+Inputs!$E$19)^(H$5-1) -> 1675.8 | I21: =(I10-I15)*Inputs!$E$20*(1+Inputs!$E$19)^(I$5-1) -> 1675.8 | J21: =(J10-J15)*Inputs!$E$20*(1+Inputs!$E$19)^(J$5-1) -> 1675.8 | ... AL21: =(AL10-AL15)*Inputs!$E$20*(1+Inputs!$E$19)^(AL$5-1) -> 1403.5707
A22: Personal training | C22: =C16*Inputs!$E$23*Inputs!$E$24*Inputs!$E$25*(1+Inputs!$E$19)^(C$5-1)*1 -> 2563.2 | D22: =D16*Inputs!$E$23*Inputs!$E$24*Inputs!$E$25*(1+Inputs!$E$19)^(D$5-1)*1 -> 3066.048 | E22: =E16*Inputs!$E$23*Inputs!$E$24*Inputs!$E$25*(1+Inputs!$E$19)^(E$5-1)*1 -> 3538.7251 | F22: =F16*Inputs!$E$23*Inputs!$E$24*Inputs!$E$25*(1+Inputs!$E$19)^(F$5-1)*1 -> 3983.0416 | G22: =G16*Inputs!$E$23*Inputs!$E$24*Inputs!$E$25*(1+Inputs!$E$19)^(G$5-1)*1 -> 4400.6991 | H22: =H16*Inputs!$E$23*Inputs!$E$24*Inputs!$E$25*(1+Inputs!$E$19)^(H$5-1)*1 -> 4793.2972 | I22: =I16*Inputs!$E$23*Inputs!$E$24*Inputs!$E$25*(1+Inputs!$E$19)^(I$5-1)*1 -> 5162.3393 | J22: =J16*Inputs!$E$23*Inputs!$E$24*Inputs!$E$25*(1+Inputs!$E$19)^(J$5-1)*1 -> 5509.239 | ... AL22: =AL16*Inputs!$E$23*Inputs!$E$24*Inputs!$E$25*(1+Inputs!$E$19)^(AL$5-1)*1 -> 9166.176
A23: Retail & drinks | C23: =C16*Inputs!$E$27*(1+Inputs!$E$19)^(C$5-1)*1 -> 667.5 | D23: =D16*Inputs!$E$27*(1+Inputs!$E$19)^(D$5-1)*1 -> 798.45 | E23: =E16*Inputs!$E$27*(1+Inputs!$E$19)^(E$5-1)*1 -> 921.543 | F23: =F16*Inputs!$E$27*(1+Inputs!$E$19)^(F$5-1)*1 -> 1037.2504 | G23: =G16*Inputs!$E$27*(1+Inputs!$E$19)^(G$5-1)*1 -> 1146.0154 | H23: =H16*Inputs!$E$27*(1+Inputs!$E$19)^(H$5-1)*1 -> 1248.2545 | I23: =I16*Inputs!$E$27*(1+Inputs!$E$19)^(I$5-1)*1 -> 1344.3592 | J23: =J16*Inputs!$E$27*(1+Inputs!$E$19)^(J$5-1)*1 -> 1434.6977 | ... AL23: =AL16*Inputs!$E$27*(1+Inputs!$E$19)^(AL$5-1)*1 -> 2387.025
A24: Revenue | C24: =C20+C21+C22+C23 -> 18123 | D24: =D20+D21+D22+D23 -> 21349.608 | E24: =E20+E21+E22+E23 -> 24382.62 | F24: =F20+F21+F22+F23 -> 27233.65 | G24: =G20+G21+G22+G23 -> 29913.619 | H24: =H20+H21+H22+H23 -> 32432.79 | I24: =I20+I21+I22+I23 -> 34800.811 | J24: =J20+J21+J22+J23 -> 37026.75 | ... AL24: =AL20+AL21+AL22+AL23 -> 60219.867
A26: Cost of sales
A27: Group-class instructors | C27: =-Inputs!$E$31*52/12*Inputs!$E$32*(1+Inputs!$E$51)^(C$5-1)*1 -> -7800 | D27: =-Inputs!$E$31*52/12*Inputs!$E$32*(1+Inputs!$E$51)^(D$5-1)*1 -> -7800 | E27: =-Inputs!$E$31*52/12*Inputs!$E$32*(1+Inputs!$E$51)^(E$5-1)*1 -> -7800 | F27: =-Inputs!$E$31*52/12*Inputs!$E$32*(1+Inputs!$E$51)^(F$5-1)*1 -> -7800 | G27: =-Inputs!$E$31*52/12*Inputs!$E$32*(1+Inputs!$E$51)^(G$5-1)*1 -> -7800 | H27: =-Inputs!$E$31*52/12*Inputs!$E$32*(1+Inputs!$E$51)^(H$5-1)*1 -> -7800 | I27: =-Inputs!$E$31*52/12*Inputs!$E$32*(1+Inputs!$E$51)^(I$5-1)*1 -> -7800 | J27: =-Inputs!$E$31*52/12*Inputs!$E$32*(1+Inputs!$E$51)^(J$5-1)*1 -> -7800 | ... AL27: =-Inputs!$E$31*52/12*Inputs!$E$32*(1+Inputs!$E$51)^(AL$5-1)*1 -> -8275.02
A28: Trainer payouts | C28: =-C22*Inputs!$E$26 -> -1281.6 | D28: =-D22*Inputs!$E$26 -> -1533.024 | E28: =-E22*Inputs!$E$26 -> -1769.3626 | F28: =-F22*Inputs!$E$26 -> -1991.5208 | G28: =-G22*Inputs!$E$26 -> -2200.3496 | H28: =-H22*Inputs!$E$26 -> -2396.6486 | I28: =-I22*Inputs!$E$26 -> -2581.1697 | J28: =-J22*Inputs!$E$26 -> -2754.6195 | ... AL28: =-AL22*Inputs!$E$26 -> -4583.088
A29: Retail & drinks cost | C29: =-C23*Inputs!$E$28 -> -333.75 | D29: =-D23*Inputs!$E$28 -> -399.225 | E29: =-E23*Inputs!$E$28 -> -460.7715 | F29: =-F23*Inputs!$E$28 -> -518.62521 | G29: =-G23*Inputs!$E$28 -> -573.0077 | H29: =-H23*Inputs!$E$28 -> -624.12724 | I29: =-I23*Inputs!$E$28 -> -672.1796 | J29: =-J23*Inputs!$E$28 -> -717.34883 | ... AL29: =-AL23*Inputs!$E$28 -> -1193.5125
A30: Cost of sales | C30: =C27+C28+C29 -> -9415.35 | D30: =D27+D28+D29 -> -9732.249 | E30: =E27+E28+E29 -> -10030.134 | F30: =F27+F28+F29 -> -10310.146 | G30: =G27+G28+G29 -> -10573.357 | H30: =H27+H28+H29 -> -10820.776 | I30: =I27+I28+I29 -> -11053.349 | J30: =J27+J28+J29 -> -11271.968 | ... AL30: =AL27+AL28+AL29 -> -14051.621
A31: Gross profit | C31: =C24+C30 -> 8707.65 | D31: =D24+D30 -> 11617.359 | E31: =E24+E30 -> 14352.485 | F31: =F24+F30 -> 16923.504 | G31: =G24+G30 -> 19340.262 | H31: =H24+H30 -> 21612.014 | I31: =I24+I30 -> 23747.461 | J31: =J24+J30 -> 25754.782 | ... AL31: =AL24+AL30 -> 46168.246
A33: Operating expenses
A34: Staff payroll | C34: =Headcount!C15 -> -13841.667 | D34: =Headcount!D15 -> -13841.667 | E34: =Headcount!E15 -> -13841.667 | F34: =Headcount!F15 -> -13841.667 | G34: =Headcount!G15 -> -13841.667 | H34: =Headcount!H15 -> -13841.667 | I34: =Headcount!I15 -> -13841.667 | J34: =Headcount!J15 -> -13841.667 | ... AL34: =Headcount!AL15 -> -14684.624
A35: Marketing | C35: =-Inputs!$E$11*(1+Inputs!$E$12)^(C$5-1)*1 -> -4000 | D35: =-Inputs!$E$11*(1+Inputs!$E$12)^(D$5-1)*1 -> -4000 | E35: =-Inputs!$E$11*(1+Inputs!$E$12)^(E$5-1)*1 -> -4000 | F35: =-Inputs!$E$11*(1+Inputs!$E$12)^(F$5-1)*1 -> -4000 | G35: =-Inputs!$E$11*(1+Inputs!$E$12)^(G$5-1)*1 -> -4000 | H35: =-Inputs!$E$11*(1+Inputs!$E$12)^(H$5-1)*1 -> -4000 | I35: =-Inputs!$E$11*(1+Inputs!$E$12)^(I$5-1)*1 -> -4000 | J35: =-Inputs!$E$11*(1+Inputs!$E$12)^(J$5-1)*1 -> -4000 | ... AL35: =-Inputs!$E$11*(1+Inputs!$E$12)^(AL$5-1)*1 -> -4410
A36: Rent | C36: =-Inputs!$E$33*1 -> -12000 | D36: =-Inputs!$E$33*1 -> -12000 | E36: =-Inputs!$E$33*1 -> -12000 | F36: =-Inputs!$E$33*1 -> -12000 | G36: =-Inputs!$E$33*1 -> -12000 | H36: =-Inputs!$E$33*1 -> -12000 | I36: =-Inputs!$E$33*1 -> -12000 | J36: =-Inputs!$E$33*1 -> -12000 | ... AL36: =-Inputs!$E$33*1 -> -12000
A37: Utilities | C37: =-Inputs!$E$34*1 -> -2200 | D37: =-Inputs!$E$34*1 -> -2200 | E37: =-Inputs!$E$34*1 -> -2200 | F37: =-Inputs!$E$34*1 -> -2200 | G37: =-Inputs!$E$34*1 -> -2200 | H37: =-Inputs!$E$34*1 -> -2200 | I37: =-Inputs!$E$34*1 -> -2200 | J37: =-Inputs!$E$34*1 -> -2200 | ... AL37: =-Inputs!$E$34*1 -> -2200
A38: Equipment maintenance & cleaning | C38: =-Inputs!$E$35*1 -> -1800 | D38: =-Inputs!$E$35*1 -> -1800 | E38: =-Inputs!$E$35*1 -> -1800 | F38: =-Inputs!$E$35*1 -> -1800 | G38: =-Inputs!$E$35*1 -> -1800 | H38: =-Inputs!$E$35*1 -> -1800 | I38: =-Inputs!$E$35*1 -> -1800 | J38: =-Inputs!$E$35*1 -> -1800 | ... AL38: =-Inputs!$E$35*1 -> -1800
A39: Booking software & payment fees | C39: =-C24*Inputs!$E$36 -> -724.92 | D39: =-D24*Inputs!$E$36 -> -853.98432 | E39: =-E24*Inputs!$E$36 -> -975.30478 | F39: =-F24*Inputs!$E$36 -> -1089.346 | G39: =-G24*Inputs!$E$36 -> -1196.5448 | H39: =-H24*Inputs!$E$36 -> -1297.3116 | I39: =-I24*Inputs!$E$36 -> -1392.0324 | J39: =-J24*Inputs!$E$36 -> -1481.07 | ... AL39: =-AL24*Inputs!$E$36 -> -2408.7947
A40: Insurance & other G&A | C40: =-Inputs!$E$37*1 -> -2000 | D40: =-Inputs!$E$37*1 -> -2000 | E40: =-Inputs!$E$37*1 -> -2000 | F40: =-Inputs!$E$37*1 -> -2000 | G40: =-Inputs!$E$37*1 -> -2000 | H40: =-Inputs!$E$37*1 -> -2000 | I40: =-Inputs!$E$37*1 -> -2000 | J40: =-Inputs!$E$37*1 -> -2000 | ... AL40: =-Inputs!$E$37*1 -> -2000
A41: Total operating expenses | C41: =C34+C35+C36+C37+C38+C39+C40 -> -36566.587 | D41: =D34+D35+D36+D37+D38+D39+D40 -> -36695.651 | E41: =E34+E35+E36+E37+E38+E39+E40 -> -36816.971 | F41: =F34+F35+F36+F37+F38+F39+F40 -> -36931.013 | G41: =G34+G35+G36+G37+G38+G39+G40 -> -37038.211 | H41: =H34+H35+H36+H37+H38+H39+H40 -> -37138.978 | I41: =I34+I35+I36+I37+I38+I39+I40 -> -37233.699 | J41: =J34+J35+J36+J37+J38+J39+J40 -> -37322.737 | ... AL41: =AL34+AL35+AL36+AL37+AL38+AL39+AL40 -> -39503.419
A42: EBITDA | C42: =C31+C41 -> -27858.937 | D42: =D31+D41 -> -25078.292 | E42: =E31+E41 -> -22464.486 | F42: =F31+F41 -> -20007.508 | G42: =G31+G41 -> -17697.949 | H42: =H31+H41 -> -15526.964 | I42: =I31+I41 -> -13486.238 | J42: =J31+J41 -> -11567.955 | ... AL42: =AL31+AL41 -> 6664.8274
A44: Profit after depreciation, interest, tax
A45: EBIT | C45: =C42+C56 -> -30835.127 | D45: =D42+D56 -> -28054.482 | E45: =E42+E56 -> -25440.676 | F45: =F42+F56 -> -22983.699 | G45: =G42+G56 -> -20674.14 | H45: =H42+H56 -> -18503.154 | I45: =I42+I56 -> -16462.428 | J45: =J42+J56 -> -14544.145 | ... AL45: =AL42+AL56 -> 3688.6369
A46: Interest on loan (average balance after drawdown) | C46: =-(C61+C62+C64)/2*Inputs!$E$56/12 -> -1000 | D46: =-(D61+D62+D64)/2*Inputs!$E$56/12 -> -994.04762 | E46: =-(E61+E62+E64)/2*Inputs!$E$56/12 -> -982.14286 | F46: =-(F61+F62+F64)/2*Inputs!$E$56/12 -> -970.2381 | G46: =-(G61+G62+G64)/2*Inputs!$E$56/12 -> -958.33333 | H46: =-(H61+H62+H64)/2*Inputs!$E$56/12 -> -946.42857 | I46: =-(I61+I62+I64)/2*Inputs!$E$56/12 -> -934.52381 | J46: =-(J61+J62+J64)/2*Inputs!$E$56/12 -> -922.61905 | ... AL46: =-(AL61+AL62+AL64)/2*Inputs!$E$56/12 -> -589.28571
A47: Pre-tax income | C47: =C45+C46 -> -31835.127 | D47: =D45+D46 -> -29048.53 | E47: =E45+E46 -> -26422.819 | F47: =F45+F46 -> -23953.937 | G47: =G45+G46 -> -21632.473 | H47: =H45+H46 -> -19449.583 | I47: =I45+I46 -> -17396.952 | J47: =J45+J46 -> -15466.764 | ... AL47: =AL45+AL46 -> 3099.3512
A48: Helper: cumulative pre-tax income | C48: =C47 -> -31835.127 | D48: =C48+D47 -> -60883.657 | E48: =D48+E47 -> -87306.477 | F48: =E48+F47 -> -111260.41 | G48: =F48+G47 -> -132892.89 | H48: =G48+H47 -> -152342.47 | I48: =H48+I47 -> -169739.42 | J48: =I48+J47 -> -185206.19 | K48: =J48+K47 -> -198857.86 | ... AL48: =AK48+AL47 -> -198611.63
A49: Helper: cumulative taxable income (losses carried forward) | C49: =MAX(0,C48) -> 0 | D49: =MAX(C49,D48) -> 0 | E49: =MAX(D49,E48) -> 0 | F49: =MAX(E49,F48) -> 0 | G49: =MAX(F49,G48) -> 0 | H49: =MAX(G49,H48) -> 0 | I49: =MAX(H49,I48) -> 0 | J49: =MAX(I49,J48) -> 0 | K49: =MAX(J49,K48) -> 0 | ... AL49: =MAX(AK49,AL48) -> 0
A50: Income tax | C50: =-C49*Inputs!$E$66 -> 0 | D50: =-(D49-C49)*Inputs!$E$66 -> 0 | E50: =-(E49-D49)*Inputs!$E$66 -> 0 | F50: =-(F49-E49)*Inputs!$E$66 -> 0 | G50: =-(G49-F49)*Inputs!$E$66 -> 0 | H50: =-(H49-G49)*Inputs!$E$66 -> 0 | I50: =-(I49-H49)*Inputs!$E$66 -> 0 | J50: =-(J49-I49)*Inputs!$E$66 -> 0 | K50: =-(K49-J49)*Inputs!$E$66 -> 0 | ... AL50: =-(AL49-AK49)*Inputs!$E$66 -> 0
A51: Net income | C51: =C47+C50 -> -31835.127 | D51: =D47+D50 -> -29048.53 | E51: =E47+E50 -> -26422.819 | F51: =F47+F50 -> -23953.937 | G51: =G47+G50 -> -21632.473 | H51: =H47+H50 -> -19449.583 | I51: =I47+I50 -> -17396.952 | J51: =J47+J50 -> -15466.764 | ... AL51: =AL47+AL50 -> 3099.3512
A53: Fixed assets & capital spending
A54: Capital spending (fit-out & equipment) | C54: =IF(C$4=1,Inputs!$E$39,0) -> 250000 | D54: =IF(D$4=1,Inputs!$E$39,0) -> 0 | E54: =IF(E$4=1,Inputs!$E$39,0) -> 0 | F54: =IF(F$4=1,Inputs!$E$39,0) -> 0 | G54: =IF(G$4=1,Inputs!$E$39,0) -> 0 | H54: =IF(H$4=1,Inputs!$E$39,0) -> 0 | I54: =IF(I$4=1,Inputs!$E$39,0) -> 0 | J54: =IF(J$4=1,Inputs!$E$39,0) -> 0 | ... AL54: =IF(AL$4=1,Inputs!$E$39,0) -> 0
A55: Fixed assets at cost | C55: =C54 -> 250000 | D55: =C55+D54 -> 250000 | E55: =D55+E54 -> 250000 | F55: =E55+F54 -> 250000 | G55: =F55+G54 -> 250000 | H55: =G55+H54 -> 250000 | I55: =H55+I54 -> 250000 | J55: =I55+J54 -> 250000 | K55: =J55+K54 -> 250000 | ... AL55: =AK55+AL54 -> 250000
A56: Depreciation | C56: =-MIN(C55/MAX(1,Inputs!$E$65*12),C54) -> -2976.1905 | D56: =-MIN(D55/MAX(1,Inputs!$E$65*12),C58+D54) -> -2976.1905 | E56: =-MIN(E55/MAX(1,Inputs!$E$65*12),D58+E54) -> -2976.1905 | F56: =-MIN(F55/MAX(1,Inputs!$E$65*12),E58+F54) -> -2976.1905 | G56: =-MIN(G55/MAX(1,Inputs!$E$65*12),F58+G54) -> -2976.1905 | H56: =-MIN(H55/MAX(1,Inputs!$E$65*12),G58+H54) -> -2976.1905 | I56: =-MIN(I55/MAX(1,Inputs!$E$65*12),H58+I54) -> -2976.1905 | J56: =-MIN(J55/MAX(1,Inputs!$E$65*12),I58+J54) -> -2976.1905 | K56: =-MIN(K55/MAX(1,Inputs!$E$65*12),J58+K54) -> -2976.1905 | ... AL56: =-MIN(AL55/MAX(1,Inputs!$E$65*12),AK58+AL54) -> -2976.1905
A57: Accumulated depreciation | C57: =C56 -> -2976.1905 | D57: =C57+D56 -> -5952.381 | E57: =D57+E56 -> -8928.5714 | F57: =E57+F56 -> -11904.762 | G57: =F57+G56 -> -14880.952 | H57: =G57+H56 -> -17857.143 | I57: =H57+I56 -> -20833.333 | J57: =I57+J56 -> -23809.524 | K57: =J57+K56 -> -26785.714 | ... AL57: =AK57+AL56 -> -107142.86
A58: Net fixed assets | C58: =C55+C57 -> 247023.81 | D58: =D55+D57 -> 244047.62 | E58: =E55+E57 -> 241071.43 | F58: =F55+F57 -> 238095.24 | G58: =G55+G57 -> 235119.05 | H58: =H55+H57 -> 232142.86 | I58: =I55+I57 -> 229166.67 | J58: =J55+J57 -> 226190.48 | ... AL58: =AL55+AL57 -> 142857.14
A60: Debt
A61: Loan — opening balance | C61: =0 -> 0 | D61: =C64 -> 150000 | E61: =D64 -> 148214.29 | F61: =E64 -> 146428.57 | G61: =F64 -> 144642.86 | H61: =G64 -> 142857.14 | I61: =H64 -> 141071.43 | J61: =I64 -> 139285.71 | K61: =J64 -> 137500 | ... AL61: =AK64 -> 89285.714
A62: Loan drawdown | C62: =IF(C$4=1,Inputs!$E$55,0) -> 150000 | D62: =IF(D$4=1,Inputs!$E$55,0) -> 0 | E62: =IF(E$4=1,Inputs!$E$55,0) -> 0 | F62: =IF(F$4=1,Inputs!$E$55,0) -> 0 | G62: =IF(G$4=1,Inputs!$E$55,0) -> 0 | H62: =IF(H$4=1,Inputs!$E$55,0) -> 0 | I62: =IF(I$4=1,Inputs!$E$55,0) -> 0 | J62: =IF(J$4=1,Inputs!$E$55,0) -> 0 | ... AL62: =IF(AL$4=1,Inputs!$E$55,0) -> 0
A63: Loan repayment | C63: =-MIN(C61,Inputs!$E$55/MAX(1,Inputs!$E$57*12)) -> 0 | D63: =-MIN(D61,Inputs!$E$55/MAX(1,Inputs!$E$57*12)) -> -1785.7143 | E63: =-MIN(E61,Inputs!$E$55/MAX(1,Inputs!$E$57*12)) -> -1785.7143 | F63: =-MIN(F61,Inputs!$E$55/MAX(1,Inputs!$E$57*12)) -> -1785.7143 | G63: =-MIN(G61,Inputs!$E$55/MAX(1,Inputs!$E$57*12)) -> -1785.7143 | H63: =-MIN(H61,Inputs!$E$55/MAX(1,Inputs!$E$57*12)) -> -1785.7143 | I63: =-MIN(I61,Inputs!$E$55/MAX(1,Inputs!$E$57*12)) -> -1785.7143 | J63: =-MIN(J61,Inputs!$E$55/MAX(1,Inputs!$E$57*12)) -> -1785.7143 | ... AL63: =-MIN(AL61,Inputs!$E$55/MAX(1,Inputs!$E$57*12)) -> -1785.7143
A64: Loan — closing balance | C64: =C61+C62+C63 -> 150000 | D64: =D61+D62+D63 -> 148214.29 | E64: =E61+E62+E63 -> 146428.57 | F64: =F61+F62+F63 -> 144642.86 | G64: =G61+G62+G63 -> 142857.14 | H64: =H61+H62+H63 -> 141071.43 | I64: =I61+I62+I63 -> 139285.71 | J64: =J61+J62+J63 -> 137500 | ... AL64: =AL61+AL62+AL63 -> 87500
A66: Working capital
A67: Accounts receivable | C67: =C24*Inputs!$E$60/30 -> 0 | D67: =D24*Inputs!$E$60/30 -> 0 | E67: =E24*Inputs!$E$60/30 -> 0 | F67: =F24*Inputs!$E$60/30 -> 0 | G67: =G24*Inputs!$E$60/30 -> 0 | H67: =H24*Inputs!$E$60/30 -> 0 | I67: =I24*Inputs!$E$60/30 -> 0 | J67: =J24*Inputs!$E$60/30 -> 0 | ... AL67: =AL24*Inputs!$E$60/30 -> 0
A68: Inventory | C68: =-C30*Inputs!$E$61/30 -> 3138.45 | D68: =-D30*Inputs!$E$61/30 -> 3244.083 | E68: =-E30*Inputs!$E$61/30 -> 3343.378 | F68: =-F30*Inputs!$E$61/30 -> 3436.7153 | G68: =-G30*Inputs!$E$61/30 -> 3524.4524 | H68: =-H30*Inputs!$E$61/30 -> 3606.9253 | I68: =-I30*Inputs!$E$61/30 -> 3684.4498 | J68: =-J30*Inputs!$E$61/30 -> 3757.3228 | ... AL68: =-AL30*Inputs!$E$61/30 -> 4683.8735
A69: Accounts payable | C69: =-C30*Inputs!$E$62/30 -> 6276.9 | D69: =-D30*Inputs!$E$62/30 -> 6488.166 | E69: =-E30*Inputs!$E$62/30 -> 6686.756 | F69: =-F30*Inputs!$E$62/30 -> 6873.4307 | G69: =-G30*Inputs!$E$62/30 -> 7048.9048 | H69: =-H30*Inputs!$E$62/30 -> 7213.8505 | I69: =-I30*Inputs!$E$62/30 -> 7368.8995 | J69: =-J30*Inputs!$E$62/30 -> 7514.6455 | ... AL69: =-AL30*Inputs!$E$62/30 -> 9367.747
A70: (Increase) / decrease in receivables | C70: =-C67 -> 0 | D70: =C67-D67 -> 0 | E70: =D67-E67 -> 0 | F70: =E67-F67 -> 0 | G70: =F67-G67 -> 0 | H70: =G67-H67 -> 0 | I70: =H67-I67 -> 0 | J70: =I67-J67 -> 0 | K70: =J67-K67 -> 0 | ... AL70: =AK67-AL67 -> 0
A71: (Increase) / decrease in inventory | C71: =-C68 -> -3138.45 | D71: =C68-D68 -> -105.633 | E71: =D68-E68 -> -99.29502 | F71: =E68-F68 -> -93.337319 | G71: =F68-G68 -> -87.73708 | H71: =G68-H68 -> -82.472855 | I71: =H68-I68 -> -77.524484 | J71: =I68-J68 -> -72.873015 | K71: =J68-K68 -> -68.500634 | ... AL71: =AK68-AL68 -> 0
A72: Increase / (decrease) in payables | C72: =C69 -> 6276.9 | D72: =D69-C69 -> 211.266 | E72: =E69-D69 -> 198.59004 | F72: =F69-E69 -> 186.67464 | G72: =G69-F69 -> 175.47416 | H72: =H69-G69 -> 164.94571 | I72: =I69-H69 -> 155.04897 | J72: =J69-I69 -> 145.74603 | K72: =K69-J69 -> 137.00127 | ... AL72: =AL69-AK69 -> 0
A74: Cash flow
A75: Operating cash flow | C75: =C51-C56+C70+C71+C72 -> -25720.487 | D75: =D51-D56+D70+D71+D72 -> -25966.707 | E75: =E51-E56+E70+E71+E72 -> -23347.334 | F75: =F51-F56+F70+F71+F72 -> -20884.409 | G75: =G51-G56+G70+G71+G72 -> -18568.546 | H75: =H51-H56+H70+H71+H72 -> -16390.92 | I75: =I51-I56+I70+I71+I72 -> -14343.237 | J75: =J51-J56+J70+J71+J72 -> -12417.701 | ... AL75: =AL51-AL56+AL70+AL71+AL72 -> 6075.5417
A76: Investing cash flow (capex) | C76: =-C54 -> -250000 | D76: =-D54 -> 0 | E76: =-E54 -> 0 | F76: =-F54 -> 0 | G76: =-G54 -> 0 | H76: =-H54 -> 0 | I76: =-I54 -> 0 | J76: =-J54 -> 0 | ... AL76: =-AL54 -> 0
A77: Equity raised | C77: =IF(C$4=1,Inputs!$E$54,0) -> 330000 | D77: =IF(D$4=1,Inputs!$E$54,0) -> 0 | E77: =IF(E$4=1,Inputs!$E$54,0) -> 0 | F77: =IF(F$4=1,Inputs!$E$54,0) -> 0 | G77: =IF(G$4=1,Inputs!$E$54,0) -> 0 | H77: =IF(H$4=1,Inputs!$E$54,0) -> 0 | I77: =IF(I$4=1,Inputs!$E$54,0) -> 0 | J77: =IF(J$4=1,Inputs!$E$54,0) -> 0 | ... AL77: =IF(AL$4=1,Inputs!$E$54,0) -> 0
A78: Financing cash flow | C78: =C77+C62+C63 -> 480000 | D78: =D77+D62+D63 -> -1785.7143 | E78: =E77+E62+E63 -> -1785.7143 | F78: =F77+F62+F63 -> -1785.7143 | G78: =G77+G62+G63 -> -1785.7143 | H78: =H77+H62+H63 -> -1785.7143 | I78: =I77+I62+I63 -> -1785.7143 | J78: =J77+J62+J63 -> -1785.7143 | ... AL78: =AL77+AL62+AL63 -> -1785.7143
A79: Net cash flow | C79: =C75+C76+C78 -> 204279.51 | D79: =D75+D76+D78 -> -27752.421 | E79: =E75+E76+E78 -> -25133.048 | F79: =F75+F76+F78 -> -22670.123 | G79: =G75+G76+G78 -> -20354.26 | H79: =H75+H76+H78 -> -18176.634 | I79: =I75+I76+I78 -> -16128.951 | J79: =J75+J76+J78 -> -14203.415 | ... AL79: =AL75+AL76+AL78 -> 4289.8274
A80: Opening cash | C80: =0 -> 0 | D80: =C81 -> 204279.51 | E80: =D81 -> 176527.09 | F80: =E81 -> 151394.04 | G80: =F81 -> 128723.92 | H80: =G81 -> 108369.66 | I80: =H81 -> 90193.027 | J80: =I81 -> 74064.076 | K80: =J81 -> 59860.661 | ... AL80: =AK81 -> 76425.275
A81: Closing cash | C81: =C80+C79 -> 204279.51 | D81: =D80+D79 -> 176527.09 | E81: =E80+E79 -> 151394.04 | F81: =F80+F79 -> 128723.92 | G81: =G80+G79 -> 108369.66 | H81: =H80+H79 -> 90193.027 | I81: =I80+I79 -> 74064.076 | J81: =J80+J79 -> 59860.661 | ... AL81: =AL80+AL79 -> 80715.102
A82: Helper: EBITDA positive (1/0) | C82: =IF(C42>0,1,0) -> 0 | D82: =IF(D42>0,1,0) -> 0 | E82: =IF(E42>0,1,0) -> 0 | F82: =IF(F42>0,1,0) -> 0 | G82: =IF(G42>0,1,0) -> 0 | H82: =IF(H42>0,1,0) -> 0 | I82: =IF(I42>0,1,0) -> 0 | J82: =IF(J42>0,1,0) -> 0 | ... AL82: =IF(AL42>0,1,0) -> 1
A84: Goal modules
A85: Helper: net income positive (1/0) | C85: =IF(C51>0,1,0) -> 0 | D85: =IF(D51>0,1,0) -> 0 | E85: =IF(E51>0,1,0) -> 0 | F85: =IF(F51>0,1,0) -> 0 | G85: =IF(G51>0,1,0) -> 0 | H85: =IF(H51>0,1,0) -> 0 | I85: =IF(I51>0,1,0) -> 0 | J85: =IF(J51>0,1,0) -> 0 | ... AL85: =IF(AL51>0,1,0) -> 1
A86: Cash flow before financing (operating + investing) | C86: =C75+C76 -> -275720.49 | D86: =D75+D76 -> -25966.707 | E86: =E75+E76 -> -23347.334 | F86: =F75+F76 -> -20884.409 | G86: =G75+G76 -> -18568.546 | H86: =H75+H76 -> -16390.92 | I86: =I75+I76 -> -14343.237 | J86: =J75+J76 -> -12417.701 | ... AL86: =AL75+AL76 -> 6075.5417
A87: Cumulative cash flow before financing | C87: =C86 -> -275720.49 | D87: =C87+D86 -> -301687.19 | E87: =D87+E86 -> -325034.53 | F87: =E87+F86 -> -345918.94 | G87: =F87+G86 -> -364487.48 | H87: =G87+H86 -> -380878.4 | I87: =H87+I86 -> -395221.64 | J87: =I87+J86 -> -407639.34 | K87: =J87+K86 -> -418246.32 | ... AL87: =AK87+AL86 -> -336784.9
A88: Helper: lowest cumulative cash flow so far | C88: =C87 -> -275720.49 | D88: =MIN(C88,D87) -> -301687.19 | E88: =MIN(D88,E87) -> -325034.53 | F88: =MIN(E88,F87) -> -345918.94 | G88: =MIN(F88,G87) -> -364487.48 | H88: =MIN(G88,H87) -> -380878.4 | I88: =MIN(H88,I87) -> -395221.64 | J88: =MIN(I88,J87) -> -407639.34 | K88: =MIN(J88,K87) -> -418246.32 | ... AL88: =MIN(AK88,AL87) -> -446622.24
A89: Helper: investment paid back (1/0) | C89: =IF(AND(C87>=0,C88<0),1,0) -> 0 | D89: =IF(AND(D87>=0,D88<0),1,0) -> 0 | E89: =IF(AND(E87>=0,E88<0),1,0) -> 0 | F89: =IF(AND(F87>=0,F88<0),1,0) -> 0 | G89: =IF(AND(G87>=0,G88<0),1,0) -> 0 | H89: =IF(AND(H87>=0,H88<0),1,0) -> 0 | I89: =IF(AND(I87>=0,I88<0),1,0) -> 0 | J89: =IF(AND(J87>=0,J88<0),1,0) -> 0 | ... AL89: =IF(AND(AL87>=0,AL88<0),1,0) -> 0
A90: Unlevered free cash flow (operating + after-tax interest − capex) | C90: =C75-C46*(1-Inputs!$E$66)+C76 -> -274930.49 | D90: =D75-D46*(1-Inputs!$E$66)+D76 -> -25181.409 | E90: =E75-E46*(1-Inputs!$E$66)+E76 -> -22571.441 | F90: =F75-F46*(1-Inputs!$E$66)+F76 -> -20117.921 | G90: =G75-G46*(1-Inputs!$E$66)+G76 -> -17811.462 | H90: =H75-H46*(1-Inputs!$E$66)+H76 -> -15643.241 | I90: =I75-I46*(1-Inputs!$E$66)+I76 -> -13604.963 | J90: =J75-J46*(1-Inputs!$E$66)+J76 -> -11688.832 | ... AL90: =AL75-AL46*(1-Inputs!$E$66)+AL76 -> 6541.0774
A92: Balance sheet
A93: Paid-in capital | C93: =C77 -> 330000 | D93: =C93+D77 -> 330000 | E93: =D93+E77 -> 330000 | F93: =E93+F77 -> 330000 | G93: =F93+G77 -> 330000 | H93: =G93+H77 -> 330000 | I93: =H93+I77 -> 330000 | J93: =I93+J77 -> 330000 | K93: =J93+K77 -> 330000 | ... AL93: =AK93+AL77 -> 330000
A94: Retained earnings | C94: =C51 -> -31835.127 | D94: =C94+D51 -> -60883.657 | E94: =D94+E51 -> -87306.477 | F94: =E94+F51 -> -111260.41 | G94: =F94+G51 -> -132892.89 | H94: =G94+H51 -> -152342.47 | I94: =H94+I51 -> -169739.42 | J94: =I94+J51 -> -185206.19 | K94: =J94+K51 -> -198857.86 | ... AL94: =AK94+AL51 -> -198611.63
A95: Total assets | C95: =C81+C67+C68+C58 -> 454441.77 | D95: =D81+D67+D68+D58 -> 423818.79 | E95: =E81+E67+E68+E58 -> 395808.85 | F95: =F81+F67+F68+F58 -> 370255.87 | G95: =G81+G67+G68+G58 -> 347013.16 | H95: =H81+H67+H68+H58 -> 325942.81 | I95: =I81+I67+I68+I58 -> 306915.19 | J95: =J81+J67+J68+J58 -> 289808.46 | ... AL95: =AL81+AL67+AL68+AL58 -> 228256.12
A96: Total liabilities | C96: =C69+C64 -> 156276.9 | D96: =D69+D64 -> 154702.45 | E96: =E69+E64 -> 153115.33 | F96: =F69+F64 -> 151516.29 | G96: =G69+G64 -> 149906.05 | H96: =H69+H64 -> 148285.28 | I96: =I69+I64 -> 146654.61 | J96: =J69+J64 -> 145014.65 | ... AL96: =AL69+AL64 -> 96867.747
A97: Total equity | C97: =C93+C94 -> 298164.87 | D97: =D93+D94 -> 269116.34 | E97: =E93+E94 -> 242693.52 | F97: =F93+F94 -> 218739.59 | G97: =G93+G94 -> 197107.11 | H97: =H93+H94 -> 177657.53 | I97: =I93+I94 -> 160260.58 | J97: =J93+J94 -> 144793.81 | ... AL97: =AL93+AL94 -> 131388.37
A98: Total liabilities & equity | C98: =C96+C97 -> 454441.77 | D98: =D96+D97 -> 423818.79 | E98: =E96+E97 -> 395808.85 | F98: =F96+F97 -> 370255.87 | G98: =G96+G97 -> 347013.16 | H98: =H96+H97 -> 325942.81 | I98: =I96+I97 -> 306915.19 | J98: =J96+J97 -> 289808.46 | ... AL98: =AL96+AL97 -> 228256.12
A99: Check: assets − liabilities − equity | C99: =C95-C98 -> 0 | D99: =D95-D98 -> 0 | E99: =E95-E98 -> 0 | F99: =F95-F98 -> 0 | G99: =G95-G98 -> 0 | H99: =H95-H98 -> 0 | I99: =I95-I98 -> 0 | J99: =J95-J98 -> 0 | ... AL99: =AL95-AL98 -> 0

Sheet Headcount
A1: Headcount & payroll | D1: =HYPERLINK("#'Cover'!A1","◂ Contents") -> ◂ Contents
A2: $ unless stated; costs shown as negatives. Every period uses the same formula.
A3: Month | C3: M1 | D3: M2 | E3: M3 | F3: M4 | G3: M5 | H3: M6 | I3: M7 | J3: M8 | K3: M9 | L3: M10 | M3: M11 | N3: M12 | O3: M13 | P3: M14 | Q3: M15 | R3: M16 | S3: M17 | T3: M18 | U3: M19 | V3: M20 | W3: M21 | X3: M22 | Y3: M23 | Z3: M24 | AA3: M25 | AB3: M26 | AC3: M27 | AD3: M28 | AE3: M29 | AF3: M30 | AG3: M31 | AH3: M32 | AI3: M33 | AJ3: M34 | AK3: M35 | AL3: M36
A4: Period # | C4: 1 | D4: 2 | E4: 3 | F4: 4 | G4: 5 | H4: 6 | I4: 7 | J4: 8 | K4: 9 | L4: 10 | M4: 11 | N4: 12 | O4: 13 | P4: 14 | Q4: 15 | R4: 16 | S4: 17 | T4: 18 | U4: 19 | V4: 20 | W4: 21 | X4: 22 | Y4: 23 | Z4: 24 | AA4: 25 | AB4: 26 | AC4: 27 | AD4: 28 | AE4: 29 | AF4: 30 | AG4: 31 | AH4: 32 | AI4: 33 | AJ4: 34 | AK4: 35 | AL4: 36
A5: Year # | C5: =ROUNDUP(C4*1/12,0) -> 1 | D5: =ROUNDUP(D4*1/12,0) -> 1 | E5: =ROUNDUP(E4*1/12,0) -> 1 | F5: =ROUNDUP(F4*1/12,0) -> 1 | G5: =ROUNDUP(G4*1/12,0) -> 1 | H5: =ROUNDUP(H4*1/12,0) -> 1 | I5: =ROUNDUP(I4*1/12,0) -> 1 | J5: =ROUNDUP(J4*1/12,0) -> 1 | ... AL5: =ROUNDUP(AL4*1/12,0) -> 3
A7: Headcount (FTE)
A8: Studio manager — FTE | C8: =Inputs!$E$42*(1+Inputs!$E$44)^(C$5-1)*MAX(0,MIN(1,C$4*1-Inputs!$E$45+1))/1 -> 1 | D8: =Inputs!$E$42*(1+Inputs!$E$44)^(D$5-1)*MAX(0,MIN(1,D$4*1-Inputs!$E$45+1))/1 -> 1 | E8: =Inputs!$E$42*(1+Inputs!$E$44)^(E$5-1)*MAX(0,MIN(1,E$4*1-Inputs!$E$45+1))/1 -> 1 | F8: =Inputs!$E$42*(1+Inputs!$E$44)^(F$5-1)*MAX(0,MIN(1,F$4*1-Inputs!$E$45+1))/1 -> 1 | G8: =Inputs!$E$42*(1+Inputs!$E$44)^(G$5-1)*MAX(0,MIN(1,G$4*1-Inputs!$E$45+1))/1 -> 1 | H8: =Inputs!$E$42*(1+Inputs!$E$44)^(H$5-1)*MAX(0,MIN(1,H$4*1-Inputs!$E$45+1))/1 -> 1 | I8: =Inputs!$E$42*(1+Inputs!$E$44)^(I$5-1)*MAX(0,MIN(1,I$4*1-Inputs!$E$45+1))/1 -> 1 | J8: =Inputs!$E$42*(1+Inputs!$E$44)^(J$5-1)*MAX(0,MIN(1,J$4*1-Inputs!$E$45+1))/1 -> 1 | ... AL8: =Inputs!$E$42*(1+Inputs!$E$44)^(AL$5-1)*MAX(0,MIN(1,AL$4*1-Inputs!$E$45+1))/1 -> 1
A9: Front desk & sales — FTE | C9: =Inputs!$E$46*(1+Inputs!$E$48)^(C$5-1)*MAX(0,MIN(1,C$4*1-Inputs!$E$49+1))/1 -> 3 | D9: =Inputs!$E$46*(1+Inputs!$E$48)^(D$5-1)*MAX(0,MIN(1,D$4*1-Inputs!$E$49+1))/1 -> 3 | E9: =Inputs!$E$46*(1+Inputs!$E$48)^(E$5-1)*MAX(0,MIN(1,E$4*1-Inputs!$E$49+1))/1 -> 3 | F9: =Inputs!$E$46*(1+Inputs!$E$48)^(F$5-1)*MAX(0,MIN(1,F$4*1-Inputs!$E$49+1))/1 -> 3 | G9: =Inputs!$E$46*(1+Inputs!$E$48)^(G$5-1)*MAX(0,MIN(1,G$4*1-Inputs!$E$49+1))/1 -> 3 | H9: =Inputs!$E$46*(1+Inputs!$E$48)^(H$5-1)*MAX(0,MIN(1,H$4*1-Inputs!$E$49+1))/1 -> 3 | I9: =Inputs!$E$46*(1+Inputs!$E$48)^(I$5-1)*MAX(0,MIN(1,I$4*1-Inputs!$E$49+1))/1 -> 3 | J9: =Inputs!$E$46*(1+Inputs!$E$48)^(J$5-1)*MAX(0,MIN(1,J$4*1-Inputs!$E$49+1))/1 -> 3 | ... AL9: =Inputs!$E$46*(1+Inputs!$E$48)^(AL$5-1)*MAX(0,MIN(1,AL$4*1-Inputs!$E$49+1))/1 -> 3
A10: Total FTE | C10: =C8+C9 -> 4 | D10: =D8+D9 -> 4 | E10: =E8+E9 -> 4 | F10: =F8+F9 -> 4 | G10: =G8+G9 -> 4 | H10: =H8+H9 -> 4 | I10: =I8+I9 -> 4 | J10: =J8+J9 -> 4 | ... AL10: =AL8+AL9 -> 4
A12: Payroll cost (salary + taxes & benefits)
A13: Studio manager — payroll cost | C13: =-C8*Inputs!$E$43/12*1*(1+Inputs!$E$50)*(1+Inputs!$E$51)^(C$5-1) -> -5041.6667 | D13: =-D8*Inputs!$E$43/12*1*(1+Inputs!$E$50)*(1+Inputs!$E$51)^(D$5-1) -> -5041.6667 | E13: =-E8*Inputs!$E$43/12*1*(1+Inputs!$E$50)*(1+Inputs!$E$51)^(E$5-1) -> -5041.6667 | F13: =-F8*Inputs!$E$43/12*1*(1+Inputs!$E$50)*(1+Inputs!$E$51)^(F$5-1) -> -5041.6667 | G13: =-G8*Inputs!$E$43/12*1*(1+Inputs!$E$50)*(1+Inputs!$E$51)^(G$5-1) -> -5041.6667 | H13: =-H8*Inputs!$E$43/12*1*(1+Inputs!$E$50)*(1+Inputs!$E$51)^(H$5-1) -> -5041.6667 | I13: =-I8*Inputs!$E$43/12*1*(1+Inputs!$E$50)*(1+Inputs!$E$51)^(I$5-1) -> -5041.6667 | J13: =-J8*Inputs!$E$43/12*1*(1+Inputs!$E$50)*(1+Inputs!$E$51)^(J$5-1) -> -5041.6667 | ... AL13: =-AL8*Inputs!$E$43/12*1*(1+Inputs!$E$50)*(1+Inputs!$E$51)^(AL$5-1) -> -5348.7042
A14: Front desk & sales — payroll cost | C14: =-C9*Inputs!$E$47/12*1*(1+Inputs!$E$50)*(1+Inputs!$E$51)^(C$5-1) -> -8800 | D14: =-D9*Inputs!$E$47/12*1*(1+Inputs!$E$50)*(1+Inputs!$E$51)^(D$5-1) -> -8800 | E14: =-E9*Inputs!$E$47/12*1*(1+Inputs!$E$50)*(1+Inputs!$E$51)^(E$5-1) -> -8800 | F14: =-F9*Inputs!$E$47/12*1*(1+Inputs!$E$50)*(1+Inputs!$E$51)^(F$5-1) -> -8800 | G14: =-G9*Inputs!$E$47/12*1*(1+Inputs!$E$50)*(1+Inputs!$E$51)^(G$5-1) -> -8800 | H14: =-H9*Inputs!$E$47/12*1*(1+Inputs!$E$50)*(1+Inputs!$E$51)^(H$5-1) -> -8800 | I14: =-I9*Inputs!$E$47/12*1*(1+Inputs!$E$50)*(1+Inputs!$E$51)^(I$5-1) -> -8800 | J14: =-J9*Inputs!$E$47/12*1*(1+Inputs!$E$50)*(1+Inputs!$E$51)^(J$5-1) -> -8800 | ... AL14: =-AL9*Inputs!$E$47/12*1*(1+Inputs!$E$50)*(1+Inputs!$E$51)^(AL$5-1) -> -9335.92
A15: Total payroll | C15: =C13+C14 -> -13841.667 | D15: =D13+D14 -> -13841.667 | E15: =E13+E14 -> -13841.667 | F15: =F13+F14 -> -13841.667 | G15: =G13+G14 -> -13841.667 | H15: =H13+H14 -> -13841.667 | I15: =I13+I14 -> -13841.667 | J15: =J13+J14 -> -13841.667 | ... AL15: =AL13+AL14 -> -14684.624

Sheet Scenario calc
A1: Scenario calculation — Low, Base and High side by side | D1: =HYPERLINK("#'Cover'!A1","◂ Contents") -> ◂ Contents
A2: The model's period calculation, copied three times; each copy reads its own Inputs column. Feeds the Scenarios sheet only.
A4: Low scenario — reads Inputs column B
A5: Month | C5: M1 | D5: M2 | E5: M3 | F5: M4 | G5: M5 | H5: M6 | I5: M7 | J5: M8 | K5: M9 | L5: M10 | M5: M11 | N5: M12 | O5: M13 | P5: M14 | Q5: M15 | R5: M16 | S5: M17 | T5: M18 | U5: M19 | V5: M20 | W5: M21 | X5: M22 | Y5: M23 | Z5: M24 | AA5: M25 | AB5: M26 | AC5: M27 | AD5: M28 | AE5: M29 | AF5: M30 | AG5: M31 | AH5: M32 | AI5: M33 | AJ5: M34 | AK5: M35 | AL5: M36
A6: Period # | C6: 1 | D6: 2 | E6: 3 | F6: 4 | G6: 5 | H6: 6 | I6: 7 | J6: 8 | K6: 9 | L6: 10 | M6: 11 | N6: 12 | O6: 13 | P6: 14 | Q6: 15 | R6: 16 | S6: 17 | T6: 18 | U6: 19 | V6: 20 | W6: 21 | X6: 22 | Y6: 23 | Z6: 24 | AA6: 25 | AB6: 26 | AC6: 27 | AD6: 28 | AE6: 29 | AF6: 30 | AG6: 31 | AH6: 32 | AI6: 33 | AJ6: 34 | AK6: 35 | AL6: 36
A7: Year # | C7: =ROUNDUP(C6*1/12,0) -> 1 | D7: =ROUNDUP(D6*1/12,0) -> 1 | E7: =ROUNDUP(E6*1/12,0) -> 1 | F7: =ROUNDUP(F6*1/12,0) -> 1 | G7: =ROUNDUP(G6*1/12,0) -> 1 | H7: =ROUNDUP(H6*1/12,0) -> 1 | I7: =ROUNDUP(I6*1/12,0) -> 1 | J7: =ROUNDUP(J6*1/12,0) -> 1 | ... AL7: =ROUNDUP(AL6*1/12,0) -> 3
A9: Members
A10: New members from marketing | C10: =-C37/MAX(1,Inputs!$B$13)*Inputs!$B$14 -> 15.714286 | D10: =-D37/MAX(1,Inputs!$B$13)*Inputs!$B$14 -> 15.714286 | E10: =-E37/MAX(1,Inputs!$B$13)*Inputs!$B$14 -> 15.714286 | F10: =-F37/MAX(1,Inputs!$B$13)*Inputs!$B$14 -> 15.714286 | G10: =-G37/MAX(1,Inputs!$B$13)*Inputs!$B$14 -> 15.714286 | H10: =-H37/MAX(1,Inputs!$B$13)*Inputs!$B$14 -> 15.714286 | I10: =-I37/MAX(1,Inputs!$B$13)*Inputs!$B$14 -> 15.714286 | J10: =-J37/MAX(1,Inputs!$B$13)*Inputs!$B$14 -> 15.714286 | ... AL10: =-AL37/MAX(1,Inputs!$B$13)*Inputs!$B$14 -> 15.714286
A11: New members from referrals & walk-ins | C11: =Inputs!$B$9*(1+Inputs!$B$10)^(C$7-1)*1 -> 12 | D11: =Inputs!$B$9*(1+Inputs!$B$10)^(D$7-1)*1 -> 12 | E11: =Inputs!$B$9*(1+Inputs!$B$10)^(E$7-1)*1 -> 12 | F11: =Inputs!$B$9*(1+Inputs!$B$10)^(F$7-1)*1 -> 12 | G11: =Inputs!$B$9*(1+Inputs!$B$10)^(G$7-1)*1 -> 12 | H11: =Inputs!$B$9*(1+Inputs!$B$10)^(H$7-1)*1 -> 12 | I11: =Inputs!$B$9*(1+Inputs!$B$10)^(I$7-1)*1 -> 12 | J11: =Inputs!$B$9*(1+Inputs!$B$10)^(J$7-1)*1 -> 12 | ... AL11: =Inputs!$B$9*(1+Inputs!$B$10)^(AL$7-1)*1 -> 13.23
A12: New members — total | C12: =C10+C11 -> 27.714286 | D12: =D10+D11 -> 27.714286 | E12: =E10+E11 -> 27.714286 | F12: =F10+F11 -> 27.714286 | G12: =G10+G11 -> 27.714286 | H12: =H10+H11 -> 27.714286 | I12: =I10+I11 -> 27.714286 | J12: =J10+J11 -> 27.714286 | ... AL12: =AL10+AL11 -> 28.944286
A13: Members — opening | C13: =Inputs!$B$7 -> 80 | D13: =C16 -> 102.11429 | E13: =D16 -> 122.68057 | F13: =E16 -> 141.80722 | G13: =F16 -> 159.595 | H13: =G16 -> 176.13763 | I13: =H16 -> 191.52228 | J13: =I16 -> 205.83001 | K13: =J16 -> 219.1362 | ... AL13: =AK16 -> 382.90792
A14: Members who cancelled | C14: =-C13*Inputs!$B$15 -> -5.6 | D14: =-D13*Inputs!$B$15 -> -7.148 | E14: =-E13*Inputs!$B$15 -> -8.58764 | F14: =-F13*Inputs!$B$15 -> -9.9265052 | G14: =-G13*Inputs!$B$15 -> -11.17165 | H14: =-H13*Inputs!$B$15 -> -12.329634 | I14: =-I13*Inputs!$B$15 -> -13.40656 | J14: =-J13*Inputs!$B$15 -> -14.408101 | ... AL14: =-AL13*Inputs!$B$15 -> -26.803554
A15: Helper: members before the capacity limit | C15: =C13*(1-Inputs!$B$15)+C12 -> 102.11429 | D15: =D13*(1-Inputs!$B$15)+D12 -> 122.68057 | E15: =E13*(1-Inputs!$B$15)+E12 -> 141.80722 | F15: =F13*(1-Inputs!$B$15)+F12 -> 159.595 | G15: =G13*(1-Inputs!$B$15)+G12 -> 176.13763 | H15: =H13*(1-Inputs!$B$15)+H12 -> 191.52228 | I15: =I13*(1-Inputs!$B$15)+I12 -> 205.83001 | J15: =J13*(1-Inputs!$B$15)+J12 -> 219.1362 | ... AL15: =AL13*(1-Inputs!$B$15)+AL12 -> 385.04865
A16: Members — closing | C16: =MIN(Inputs!$B$8,C15) -> 102.11429 | D16: =MIN(Inputs!$B$8,D15) -> 122.68057 | E16: =MIN(Inputs!$B$8,E15) -> 141.80722 | F16: =MIN(Inputs!$B$8,F15) -> 159.595 | G16: =MIN(Inputs!$B$8,G15) -> 176.13763 | H16: =MIN(Inputs!$B$8,H15) -> 191.52228 | I16: =MIN(Inputs!$B$8,I15) -> 205.83001 | J16: =MIN(Inputs!$B$8,J15) -> 219.1362 | ... AL16: =MIN(Inputs!$B$8,AL15) -> 385.04865
A17: Joins lost to the capacity limit | C17: =C15-C16 -> 0 | D17: =D15-D16 -> 0 | E17: =E15-E16 -> 0 | F17: =F15-F16 -> 0 | G17: =G15-G16 -> 0 | H17: =H15-H16 -> 0 | I17: =I15-I16 -> 0 | J17: =J15-J16 -> 0 | ... AL17: =AL15-AL16 -> 0
A18: Members — average | C18: =(C13+C16)/2 -> 91.057143 | D18: =(D13+D16)/2 -> 112.39743 | E18: =(E13+E16)/2 -> 132.24389 | F18: =(F13+F16)/2 -> 150.70111 | G18: =(G13+G16)/2 -> 167.86632 | H18: =(H13+H16)/2 -> 183.82996 | I18: =(I13+I16)/2 -> 198.67615 | J18: =(J13+J16)/2 -> 212.4831 | ... AL18: =(AL13+AL16)/2 -> 383.97829
A20: Revenue
A21: Membership fee per month | C21: =Inputs!$B$18*(1+Inputs!$B$19)^(C$7-1) -> 89 | D21: =Inputs!$B$18*(1+Inputs!$B$19)^(D$7-1) -> 89 | E21: =Inputs!$B$18*(1+Inputs!$B$19)^(E$7-1) -> 89 | F21: =Inputs!$B$18*(1+Inputs!$B$19)^(F$7-1) -> 89 | G21: =Inputs!$B$18*(1+Inputs!$B$19)^(G$7-1) -> 89 | H21: =Inputs!$B$18*(1+Inputs!$B$19)^(H$7-1) -> 89 | I21: =Inputs!$B$18*(1+Inputs!$B$19)^(I$7-1) -> 89 | J21: =Inputs!$B$18*(1+Inputs!$B$19)^(J$7-1) -> 89 | ... AL21: =Inputs!$B$18*(1+Inputs!$B$19)^(AL$7-1) -> 92.5956
A22: Membership fees | C22: =C18*C21*1 -> 8104.0857 | D22: =D18*D21*1 -> 10003.371 | E22: =E18*E21*1 -> 11769.707 | F22: =F18*F21*1 -> 13412.399 | G22: =G18*G21*1 -> 14940.102 | H22: =H18*H21*1 -> 16360.866 | I22: =I18*I21*1 -> 17682.177 | J22: =J18*J21*1 -> 18910.996 | ... AL22: =AL18*AL21*1 -> 35554.7
A23: Joining fees | C23: =(C12-C17)*Inputs!$B$20*(1+Inputs!$B$19)^(C$7-1) -> 1358 | D23: =(D12-D17)*Inputs!$B$20*(1+Inputs!$B$19)^(D$7-1) -> 1358 | E23: =(E12-E17)*Inputs!$B$20*(1+Inputs!$B$19)^(E$7-1) -> 1358 | F23: =(F12-F17)*Inputs!$B$20*(1+Inputs!$B$19)^(F$7-1) -> 1358 | G23: =(G12-G17)*Inputs!$B$20*(1+Inputs!$B$19)^(G$7-1) -> 1358 | H23: =(H12-H17)*Inputs!$B$20*(1+Inputs!$B$19)^(H$7-1) -> 1358 | I23: =(I12-I17)*Inputs!$B$20*(1+Inputs!$B$19)^(I$7-1) -> 1358 | J23: =(J12-J17)*Inputs!$B$20*(1+Inputs!$B$19)^(J$7-1) -> 1358 | ... AL23: =(AL12-AL17)*Inputs!$B$20*(1+Inputs!$B$19)^(AL$7-1) -> 1475.5681
A24: Personal training | C24: =C18*Inputs!$B$23*Inputs!$B$24*Inputs!$B$25*(1+Inputs!$B$19)^(C$7-1)*1 -> 1402.28 | D24: =D18*Inputs!$B$23*Inputs!$B$24*Inputs!$B$25*(1+Inputs!$B$19)^(D$7-1)*1 -> 1730.9204 | E24: =E18*Inputs!$B$23*Inputs!$B$24*Inputs!$B$25*(1+Inputs!$B$19)^(E$7-1)*1 -> 2036.556 | F24: =F18*Inputs!$B$23*Inputs!$B$24*Inputs!$B$25*(1+Inputs!$B$19)^(F$7-1)*1 -> 2320.7971 | G24: =G18*Inputs!$B$23*Inputs!$B$24*Inputs!$B$25*(1+Inputs!$B$19)^(G$7-1)*1 -> 2585.1413 | H24: =H18*Inputs!$B$23*Inputs!$B$24*Inputs!$B$25*(1+Inputs!$B$19)^(H$7-1)*1 -> 2830.9814 | I24: =I18*Inputs!$B$23*Inputs!$B$24*Inputs!$B$25*(1+Inputs!$B$19)^(I$7-1)*1 -> 3059.6127 | J24: =J18*Inputs!$B$23*Inputs!$B$24*Inputs!$B$25*(1+Inputs!$B$19)^(J$7-1)*1 -> 3272.2398 | ... AL24: =AL18*Inputs!$B$23*Inputs!$B$24*Inputs!$B$25*(1+Inputs!$B$19)^(AL$7-1)*1 -> 6152.1615
A25: Retail & drinks | C25: =C18*Inputs!$B$27*(1+Inputs!$B$19)^(C$7-1)*1 -> 364.22857 | D25: =D18*Inputs!$B$27*(1+Inputs!$B$19)^(D$7-1)*1 -> 449.58971 | E25: =E18*Inputs!$B$27*(1+Inputs!$B$19)^(E$7-1)*1 -> 528.97558 | F25: =F18*Inputs!$B$27*(1+Inputs!$B$19)^(F$7-1)*1 -> 602.80443 | G25: =G18*Inputs!$B$27*(1+Inputs!$B$19)^(G$7-1)*1 -> 671.46526 | H25: =H18*Inputs!$B$27*(1+Inputs!$B$19)^(H$7-1)*1 -> 735.31984 | I25: =I18*Inputs!$B$27*(1+Inputs!$B$19)^(I$7-1)*1 -> 794.70459 | J25: =J18*Inputs!$B$27*(1+Inputs!$B$19)^(J$7-1)*1 -> 849.93241 | ... AL25: =AL18*Inputs!$B$27*(1+Inputs!$B$19)^(AL$7-1)*1 -> 1597.964
A26: Revenue | C26: =C22+C23+C24+C25 -> 11228.594 | D26: =D22+D23+D24+D25 -> 13541.881 | E26: =E22+E23+E24+E25 -> 15693.238 | F26: =F22+F23+F24+F25 -> 17694 | G26: =G22+G23+G24+G25 -> 19554.709 | H26: =H22+H23+H24+H25 -> 21285.168 | I26: =I22+I23+I24+I25 -> 22894.494 | J26: =J22+J23+J24+J25 -> 24391.168 | ... AL26: =AL22+AL23+AL24+AL25 -> 44780.394
A28: Cost of sales
A29: Group-class instructors | C29: =-Inputs!$B$31*52/12*Inputs!$B$32*(1+Inputs!$B$51)^(C$7-1)*1 -> -8666.6667 | D29: =-Inputs!$B$31*52/12*Inputs!$B$32*(1+Inputs!$B$51)^(D$7-1)*1 -> -8666.6667 | E29: =-Inputs!$B$31*52/12*Inputs!$B$32*(1+Inputs!$B$51)^(E$7-1)*1 -> -8666.6667 | F29: =-Inputs!$B$31*52/12*Inputs!$B$32*(1+Inputs!$B$51)^(F$7-1)*1 -> -8666.6667 | G29: =-Inputs!$B$31*52/12*Inputs!$B$32*(1+Inputs!$B$51)^(G$7-1)*1 -> -8666.6667 | H29: =-Inputs!$B$31*52/12*Inputs!$B$32*(1+Inputs!$B$51)^(H$7-1)*1 -> -8666.6667 | I29: =-Inputs!$B$31*52/12*Inputs!$B$32*(1+Inputs!$B$51)^(I$7-1)*1 -> -8666.6667 | J29: =-Inputs!$B$31*52/12*Inputs!$B$32*(1+Inputs!$B$51)^(J$7-1)*1 -> -8666.6667 | ... AL29: =-Inputs!$B$31*52/12*Inputs!$B$32*(1+Inputs!$B$51)^(AL$7-1)*1 -> -9194.4667
A30: Trainer payouts | C30: =-C24*Inputs!$B$26 -> -771.254 | D30: =-D24*Inputs!$B$26 -> -952.00622 | E30: =-E24*Inputs!$B$26 -> -1120.1058 | F30: =-F24*Inputs!$B$26 -> -1276.4384 | G30: =-G24*Inputs!$B$26 -> -1421.8277 | H30: =-H24*Inputs!$B$26 -> -1557.0398 | I30: =-I24*Inputs!$B$26 -> -1682.787 | J30: =-J24*Inputs!$B$26 -> -1799.7319 | ... AL30: =-AL24*Inputs!$B$26 -> -3383.6888
A31: Retail & drinks cost | C31: =-C25*Inputs!$B$28 -> -200.32571 | D31: =-D25*Inputs!$B$28 -> -247.27434 | E31: =-E25*Inputs!$B$28 -> -290.93657 | F31: =-F25*Inputs!$B$28 -> -331.54244 | G31: =-G25*Inputs!$B$28 -> -369.30589 | H31: =-H25*Inputs!$B$28 -> -404.42591 | I31: =-I25*Inputs!$B$28 -> -437.08753 | J31: =-J25*Inputs!$B$28 -> -467.46283 | ... AL31: =-AL25*Inputs!$B$28 -> -878.88022
A32: Cost of sales | C32: =C29+C30+C31 -> -9638.2464 | D32: =D29+D30+D31 -> -9865.9472 | E32: =E29+E30+E31 -> -10077.709 | F32: =F29+F30+F31 -> -10274.647 | G32: =G29+G30+G31 -> -10457.8 | H32: =H29+H30+H31 -> -10628.132 | I32: =I29+I30+I31 -> -10786.541 | J32: =J29+J30+J31 -> -10933.861 | ... AL32: =AL29+AL30+AL31 -> -13457.036
A33: Gross profit | C33: =C26+C32 -> 1590.3479 | D33: =D26+D32 -> 3675.934 | E33: =E26+E32 -> 5615.5291 | F33: =F26+F32 -> 7419.3526 | G33: =G26+G32 -> 9096.9084 | H33: =H26+H32 -> 10657.035 | I33: =I26+I32 -> 12107.953 | J33: =J26+J32 -> 13457.307 | ... AL33: =AL26+AL32 -> 31323.358
A35: Operating expenses
A36: Staff payroll | C36: =C111 -> -13841.667 | D36: =D111 -> -13841.667 | E36: =E111 -> -13841.667 | F36: =F111 -> -13841.667 | G36: =G111 -> -13841.667 | H36: =H111 -> -13841.667 | I36: =I111 -> -13841.667 | J36: =J111 -> -13841.667 | ... AL36: =AL111 -> -14684.624
A37: Marketing | C37: =-Inputs!$B$11*(1+Inputs!$B$12)^(C$7-1)*1 -> -4000 | D37: =-Inputs!$B$11*(1+Inputs!$B$12)^(D$7-1)*1 -> -4000 | E37: =-Inputs!$B$11*(1+Inputs!$B$12)^(E$7-1)*1 -> -4000 | F37: =-Inputs!$B$11*(1+Inputs!$B$12)^(F$7-1)*1 -> -4000 | G37: =-Inputs!$B$11*(1+Inputs!$B$12)^(G$7-1)*1 -> -4000 | H37: =-Inputs!$B$11*(1+Inputs!$B$12)^(H$7-1)*1 -> -4000 | I37: =-Inputs!$B$11*(1+Inputs!$B$12)^(I$7-1)*1 -> -4000 | J37: =-Inputs!$B$11*(1+Inputs!$B$12)^(J$7-1)*1 -> -4000 | ... AL37: =-Inputs!$B$11*(1+Inputs!$B$12)^(AL$7-1)*1 -> -4000
A38: Rent | C38: =-Inputs!$B$33*1 -> -12000 | D38: =-Inputs!$B$33*1 -> -12000 | E38: =-Inputs!$B$33*1 -> -12000 | F38: =-Inputs!$B$33*1 -> -12000 | G38: =-Inputs!$B$33*1 -> -12000 | H38: =-Inputs!$B$33*1 -> -12000 | I38: =-Inputs!$B$33*1 -> -12000 | J38: =-Inputs!$B$33*1 -> -12000 | ... AL38: =-Inputs!$B$33*1 -> -12000
A39: Utilities | C39: =-Inputs!$B$34*1 -> -2200 | D39: =-Inputs!$B$34*1 -> -2200 | E39: =-Inputs!$B$34*1 -> -2200 | F39: =-Inputs!$B$34*1 -> -2200 | G39: =-Inputs!$B$34*1 -> -2200 | H39: =-Inputs!$B$34*1 -> -2200 | I39: =-Inputs!$B$34*1 -> -2200 | J39: =-Inputs!$B$34*1 -> -2200 | ... AL39: =-Inputs!$B$34*1 -> -2200
A40: Equipment maintenance & cleaning | C40: =-Inputs!$B$35*1 -> -1800 | D40: =-Inputs!$B$35*1 -> -1800 | E40: =-Inputs!$B$35*1 -> -1800 | F40: =-Inputs!$B$35*1 -> -1800 | G40: =-Inputs!$B$35*1 -> -1800 | H40: =-Inputs!$B$35*1 -> -1800 | I40: =-Inputs!$B$35*1 -> -1800 | J40: =-Inputs!$B$35*1 -> -1800 | ... AL40: =-Inputs!$B$35*1 -> -1800
A41: Booking software & payment fees | C41: =-C26*Inputs!$B$36 -> -505.28674 | D41: =-D26*Inputs!$B$36 -> -609.38466 | E41: =-E26*Inputs!$B$36 -> -706.19572 | F41: =-F26*Inputs!$B$36 -> -796.23 | G41: =-G26*Inputs!$B$36 -> -879.96189 | H41: =-H26*Inputs!$B$36 -> -957.83254 | I41: =-I26*Inputs!$B$36 -> -1030.2522 | J41: =-J26*Inputs!$B$36 -> -1097.6026 | ... AL41: =-AL26*Inputs!$B$36 -> -2015.1177
A42: Insurance & other G&A | C42: =-Inputs!$B$37*1 -> -2000 | D42: =-Inputs!$B$37*1 -> -2000 | E42: =-Inputs!$B$37*1 -> -2000 | F42: =-Inputs!$B$37*1 -> -2000 | G42: =-Inputs!$B$37*1 -> -2000 | H42: =-Inputs!$B$37*1 -> -2000 | I42: =-Inputs!$B$37*1 -> -2000 | J42: =-Inputs!$B$37*1 -> -2000 | ... AL42: =-Inputs!$B$37*1 -> -2000
A43: Total operating expenses | C43: =C36+C37+C38+C39+C40+C41+C42 -> -36346.953 | D43: =D36+D37+D38+D39+D40+D41+D42 -> -36451.051 | E43: =E36+E37+E38+E39+E40+E41+E42 -> -36547.862 | F43: =F36+F37+F38+F39+F40+F41+F42 -> -36637.897 | G43: =G36+G37+G38+G39+G40+G41+G42 -> -36721.629 | H43: =H36+H37+H38+H39+H40+H41+H42 -> -36799.499 | I43: =I36+I37+I38+I39+I40+I41+I42 -> -36871.919 | J43: =J36+J37+J38+J39+J40+J41+J42 -> -36939.269 | ... AL43: =AL36+AL37+AL38+AL39+AL40+AL41+AL42 -> -38699.742
A44: EBITDA | C44: =C33+C43 -> -34756.606 | D44: =D33+D43 -> -32775.117 | E44: =E33+E43 -> -30932.333 | F44: =F33+F43 -> -29218.544 | G44: =G33+G43 -> -27624.72 | H44: =H33+H43 -> -26142.464 | I44: =I33+I43 -> -24763.966 | J44: =J33+J43 -> -23481.962 | ... AL44: =AL33+AL43 -> -7376.3841
A46: Profit after depreciation, interest, tax
A47: EBIT | C47: =C44+C58 -> -37732.796 | D47: =D44+D58 -> -35751.308 | E47: =E44+E58 -> -33908.524 | F47: =F44+F58 -> -32194.735 | G47: =G44+G58 -> -30600.911 | H47: =H44+H58 -> -29118.654 | I47: =I44+I58 -> -27740.156 | J47: =J44+J58 -> -26458.153 | ... AL47: =AL44+AL58 -> -10352.575
A48: Interest on loan (average balance after drawdown) | C48: =-(C63+C64+C66)/2*Inputs!$B$56/12 -> -1000 | D48: =-(D63+D64+D66)/2*Inputs!$B$56/12 -> -994.04762 | E48: =-(E63+E64+E66)/2*Inputs!$B$56/12 -> -982.14286 | F48: =-(F63+F64+F66)/2*Inputs!$B$56/12 -> -970.2381 | G48: =-(G63+G64+G66)/2*Inputs!$B$56/12 -> -958.33333 | H48: =-(H63+H64+H66)/2*Inputs!$B$56/12 -> -946.42857 | I48: =-(I63+I64+I66)/2*Inputs!$B$56/12 -> -934.52381 | J48: =-(J63+J64+J66)/2*Inputs!$B$56/12 -> -922.61905 | ... AL48: =-(AL63+AL64+AL66)/2*Inputs!$B$56/12 -> -589.28571
A49: Pre-tax income | C49: =C47+C48 -> -38732.796 | D49: =D47+D48 -> -36745.355 | E49: =E47+E48 -> -34890.667 | F49: =F47+F48 -> -33164.973 | G49: =G47+G48 -> -31559.244 | H49: =H47+H48 -> -30065.083 | I49: =I47+I48 -> -28674.68 | J49: =J47+J48 -> -27380.772 | ... AL49: =AL47+AL48 -> -10941.86
A50: Helper: cumulative pre-tax income | C50: =C49 -> -38732.796 | D50: =C50+D49 -> -75478.151 | E50: =D50+E49 -> -110368.82 | F50: =E50+F49 -> -143533.79 | G50: =F50+G49 -> -175093.03 | H50: =G50+H49 -> -205158.12 | I50: =H50+I49 -> -233832.8 | J50: =I50+J49 -> -261213.57 | K50: =J50+K49 -> -287390.17 | ... AL50: =AK50+AL49 -> -728442.32
A51: Helper: cumulative taxable income (losses carried forward) | C51: =MAX(0,C50) -> 0 | D51: =MAX(C51,D50) -> 0 | E51: =MAX(D51,E50) -> 0 | F51: =MAX(E51,F50) -> 0 | G51: =MAX(F51,G50) -> 0 | H51: =MAX(G51,H50) -> 0 | I51: =MAX(H51,I50) -> 0 | J51: =MAX(I51,J50) -> 0 | K51: =MAX(J51,K50) -> 0 | ... AL51: =MAX(AK51,AL50) -> 0
A52: Income tax | C52: =-C51*Inputs!$B$66 -> 0 | D52: =-(D51-C51)*Inputs!$B$66 -> 0 | E52: =-(E51-D51)*Inputs!$B$66 -> 0 | F52: =-(F51-E51)*Inputs!$B$66 -> 0 | G52: =-(G51-F51)*Inputs!$B$66 -> 0 | H52: =-(H51-G51)*Inputs!$B$66 -> 0 | I52: =-(I51-H51)*Inputs!$B$66 -> 0 | J52: =-(J51-I51)*Inputs!$B$66 -> 0 | K52: =-(K51-J51)*Inputs!$B$66 -> 0 | ... AL52: =-(AL51-AK51)*Inputs!$B$66 -> 0
A53: Net income | C53: =C49+C52 -> -38732.796 | D53: =D49+D52 -> -36745.355 | E53: =E49+E52 -> -34890.667 | F53: =F49+F52 -> -33164.973 | G53: =G49+G52 -> -31559.244 | H53: =H49+H52 -> -30065.083 | I53: =I49+I52 -> -28674.68 | J53: =J49+J52 -> -27380.772 | ... AL53: =AL49+AL52 -> -10941.86
A55: Fixed assets & capital spending
A56: Capital spending (fit-out & equipment) | C56: =IF(C$6=1,Inputs!$B$39,0) -> 250000 | D56: =IF(D$6=1,Inputs!$B$39,0) -> 0 | E56: =IF(E$6=1,Inputs!$B$39,0) -> 0 | F56: =IF(F$6=1,Inputs!$B$39,0) -> 0 | G56: =IF(G$6=1,Inputs!$B$39,0) -> 0 | H56: =IF(H$6=1,Inputs!$B$39,0) -> 0 | I56: =IF(I$6=1,Inputs!$B$39,0) -> 0 | J56: =IF(J$6=1,Inputs!$B$39,0) -> 0 | ... AL56: =IF(AL$6=1,Inputs!$B$39,0) -> 0
A57: Fixed assets at cost | C57: =C56 -> 250000 | D57: =C57+D56 -> 250000 | E57: =D57+E56 -> 250000 | F57: =E57+F56 -> 250000 | G57: =F57+G56 -> 250000 | H57: =G57+H56 -> 250000 | I57: =H57+I56 -> 250000 | J57: =I57+J56 -> 250000 | K57: =J57+K56 -> 250000 | ... AL57: =AK57+AL56 -> 250000
A58: Depreciation | C58: =-MIN(C57/MAX(1,Inputs!$B$65*12),C56) -> -2976.1905 | D58: =-MIN(D57/MAX(1,Inputs!$B$65*12),C60+D56) -> -2976.1905 | E58: =-MIN(E57/MAX(1,Inputs!$B$65*12),D60+E56) -> -2976.1905 | F58: =-MIN(F57/MAX(1,Inputs!$B$65*12),E60+F56) -> -2976.1905 | G58: =-MIN(G57/MAX(1,Inputs!$B$65*12),F60+G56) -> -2976.1905 | H58: =-MIN(H57/MAX(1,Inputs!$B$65*12),G60+H56) -> -2976.1905 | I58: =-MIN(I57/MAX(1,Inputs!$B$65*12),H60+I56) -> -2976.1905 | J58: =-MIN(J57/MAX(1,Inputs!$B$65*12),I60+J56) -> -2976.1905 | K58: =-MIN(K57/MAX(1,Inputs!$B$65*12),J60+K56) -> -2976.1905 | ... AL58: =-MIN(AL57/MAX(1,Inputs!$B$65*12),AK60+AL56) -> -2976.1905
A59: Accumulated depreciation | C59: =C58 -> -2976.1905 | D59: =C59+D58 -> -5952.381 | E59: =D59+E58 -> -8928.5714 | F59: =E59+F58 -> -11904.762 | G59: =F59+G58 -> -14880.952 | H59: =G59+H58 -> -17857.143 | I59: =H59+I58 -> -20833.333 | J59: =I59+J58 -> -23809.524 | K59: =J59+K58 -> -26785.714 | ... AL59: =AK59+AL58 -> -107142.86
A60: Net fixed assets | C60: =C57+C59 -> 247023.81 | D60: =D57+D59 -> 244047.62 | E60: =E57+E59 -> 241071.43 | F60: =F57+F59 -> 238095.24 | G60: =G57+G59 -> 235119.05 | H60: =H57+H59 -> 232142.86 | I60: =I57+I59 -> 229166.67 | J60: =J57+J59 -> 226190.48 | ... AL60: =AL57+AL59 -> 142857.14
A62: Debt
A63: Loan — opening balance | C63: =0 -> 0 | D63: =C66 -> 150000 | E63: =D66 -> 148214.29 | F63: =E66 -> 146428.57 | G63: =F66 -> 144642.86 | H63: =G66 -> 142857.14 | I63: =H66 -> 141071.43 | J63: =I66 -> 139285.71 | K63: =J66 -> 137500 | ... AL63: =AK66 -> 89285.714
A64: Loan drawdown | C64: =IF(C$6=1,Inputs!$B$55,0) -> 150000 | D64: =IF(D$6=1,Inputs!$B$55,0) -> 0 | E64: =IF(E$6=1,Inputs!$B$55,0) -> 0 | F64: =IF(F$6=1,Inputs!$B$55,0) -> 0 | G64: =IF(G$6=1,Inputs!$B$55,0) -> 0 | H64: =IF(H$6=1,Inputs!$B$55,0) -> 0 | I64: =IF(I$6=1,Inputs!$B$55,0) -> 0 | J64: =IF(J$6=1,Inputs!$B$55,0) -> 0 | ... AL64: =IF(AL$6=1,Inputs!$B$55,0) -> 0
A65: Loan repayment | C65: =-MIN(C63,Inputs!$B$55/MAX(1,Inputs!$B$57*12)) -> 0 | D65: =-MIN(D63,Inputs!$B$55/MAX(1,Inputs!$B$57*12)) -> -1785.7143 | E65: =-MIN(E63,Inputs!$B$55/MAX(1,Inputs!$B$57*12)) -> -1785.7143 | F65: =-MIN(F63,Inputs!$B$55/MAX(1,Inputs!$B$57*12)) -> -1785.7143 | G65: =-MIN(G63,Inputs!$B$55/MAX(1,Inputs!$B$57*12)) -> -1785.7143 | H65: =-MIN(H63,Inputs!$B$55/MAX(1,Inputs!$B$57*12)) -> -1785.7143 | I65: =-MIN(I63,Inputs!$B$55/MAX(1,Inputs!$B$57*12)) -> -1785.7143 | J65: =-MIN(J63,Inputs!$B$55/MAX(1,Inputs!$B$57*12)) -> -1785.7143 | ... AL65: =-MIN(AL63,Inputs!$B$55/MAX(1,Inputs!$B$57*12)) -> -1785.7143
A66: Loan — closing balance | C66: =C63+C64+C65 -> 150000 | D66: =D63+D64+D65 -> 148214.29 | E66: =E63+E64+E65 -> 146428.57 | F66: =F63+F64+F65 -> 144642.86 | G66: =G63+G64+G65 -> 142857.14 | H66: =H63+H64+H65 -> 141071.43 | I66: =I63+I64+I65 -> 139285.71 | J66: =J63+J64+J65 -> 137500 | ... AL66: =AL63+AL64+AL65 -> 87500
A68: Working capital
A69: Accounts receivable | C69: =C26*Inputs!$B$60/30 -> 0 | D69: =D26*Inputs!$B$60/30 -> 0 | E69: =E26*Inputs!$B$60/30 -> 0 | F69: =F26*Inputs!$B$60/30 -> 0 | G69: =G26*Inputs!$B$60/30 -> 0 | H69: =H26*Inputs!$B$60/30 -> 0 | I69: =I26*Inputs!$B$60/30 -> 0 | J69: =J26*Inputs!$B$60/30 -> 0 | ... AL69: =AL26*Inputs!$B$60/30 -> 0
A70: Inventory | C70: =-C32*Inputs!$B$61/30 -> 3212.7488 | D70: =-D32*Inputs!$B$61/30 -> 3288.6491 | E70: =-E32*Inputs!$B$61/30 -> 3359.2363 | F70: =-F32*Inputs!$B$61/30 -> 3424.8825 | G70: =-G32*Inputs!$B$61/30 -> 3485.9334 | H70: =-H32*Inputs!$B$61/30 -> 3542.7108 | I70: =-I32*Inputs!$B$61/30 -> 3595.5137 | J70: =-J32*Inputs!$B$61/30 -> 3644.6205 | ... AL70: =-AL32*Inputs!$B$61/30 -> 4485.6786
A71: Accounts payable | C71: =-C32*Inputs!$B$62/30 -> 6425.4976 | D71: =-D32*Inputs!$B$62/30 -> 6577.2982 | E71: =-E32*Inputs!$B$62/30 -> 6718.4727 | F71: =-F32*Inputs!$B$62/30 -> 6849.765 | G71: =-G32*Inputs!$B$62/30 -> 6971.8668 | H71: =-H32*Inputs!$B$62/30 -> 7085.4216 | I71: =-I32*Inputs!$B$62/30 -> 7191.0274 | J71: =-J32*Inputs!$B$62/30 -> 7289.2409 | ... AL71: =-AL32*Inputs!$B$62/30 -> 8971.3572
A72: (Increase) / decrease in receivables | C72: =-C69 -> 0 | D72: =C69-D69 -> 0 | E72: =D69-E69 -> 0 | F72: =E69-F69 -> 0 | G72: =F69-G69 -> 0 | H72: =G69-H69 -> 0 | I72: =H69-I69 -> 0 | J72: =I69-J69 -> 0 | K72: =J69-K69 -> 0 | ... AL72: =AK69-AL69 -> 0
A73: (Increase) / decrease in inventory | C73: =-C70 -> -3212.7488 | D73: =C70-D70 -> -75.900283 | E73: =D70-E70 -> -70.587263 | F73: =E70-F70 -> -65.646155 | G73: =F70-G70 -> -61.050924 | H73: =G70-H70 -> -56.777359 | I73: =H70-I70 -> -52.802944 | J73: =I70-J70 -> -49.106738 | K73: =J70-K70 -> -45.669266 | ... AL73: =AK70-AL70 -> -8.2195875
A74: Increase / (decrease) in payables | C74: =C71 -> 6425.4976 | D74: =D71-C71 -> 151.80057 | E74: =E71-D71 -> 141.17453 | F74: =F71-E71 -> 131.29231 | G74: =G71-F71 -> 122.10185 | H74: =H71-G71 -> 113.55472 | I74: =I71-H71 -> 105.60589 | J74: =J71-I71 -> 98.213476 | K74: =K71-J71 -> 91.338533 | ... AL74: =AL71-AK71 -> 16.439175
A76: Cash flow
A77: Operating cash flow | C77: =C53-C58+C72+C73+C74 -> -32543.857 | D77: =D53-D58+D72+D73+D74 -> -33693.265 | E77: =E53-E58+E72+E73+E74 -> -31843.889 | F77: =F53-F58+F72+F73+F74 -> -30123.136 | G77: =G53-G58+G72+G73+G74 -> -28522.003 | H77: =H53-H58+H72+H73+H74 -> -27032.115 | I77: =I53-I58+I72+I73+I74 -> -25645.687 | J77: =J53-J58+J72+J73+J74 -> -24355.475 | ... AL77: =AL53-AL58+AL72+AL73+AL74 -> -7957.4502
A78: Investing cash flow (capex) | C78: =-C56 -> -250000 | D78: =-D56 -> 0 | E78: =-E56 -> 0 | F78: =-F56 -> 0 | G78: =-G56 -> 0 | H78: =-H56 -> 0 | I78: =-I56 -> 0 | J78: =-J56 -> 0 | ... AL78: =-AL56 -> 0
A79: Equity raised | C79: =IF(C$6=1,Inputs!$B$54,0) -> 330000 | D79: =IF(D$6=1,Inputs!$B$54,0) -> 0 | E79: =IF(E$6=1,Inputs!$B$54,0) -> 0 | F79: =IF(F$6=1,Inputs!$B$54,0) -> 0 | G79: =IF(G$6=1,Inputs!$B$54,0) -> 0 | H79: =IF(H$6=1,Inputs!$B$54,0) -> 0 | I79: =IF(I$6=1,Inputs!$B$54,0) -> 0 | J79: =IF(J$6=1,Inputs!$B$54,0) -> 0 | ... AL79: =IF(AL$6=1,Inputs!$B$54,0) -> 0
A80: Financing cash flow | C80: =C79+C64+C65 -> 480000 | D80: =D79+D64+D65 -> -1785.7143 | E80: =E79+E64+E65 -> -1785.7143 | F80: =F79+F64+F65 -> -1785.7143 | G80: =G79+G64+G65 -> -1785.7143 | H80: =H79+H64+H65 -> -1785.7143 | I80: =I79+I64+I65 -> -1785.7143 | J80: =J79+J64+J65 -> -1785.7143 | ... AL80: =AL79+AL64+AL65 -> -1785.7143
A81: Net cash flow | C81: =C77+C78+C80 -> 197456.14 | D81: =D77+D78+D80 -> -35478.979 | E81: =E77+E78+E80 -> -33629.603 | F81: =F77+F78+F80 -> -31908.85 | G81: =G77+G78+G80 -> -30307.717 | H81: =H77+H78+H80 -> -28817.829 | I81: =I77+I78+I80 -> -27431.401 | J81: =J77+J78+J80 -> -26141.189 | ... AL81: =AL77+AL78+AL80 -> -9743.1645
A82: Opening cash | C82: =0 -> 0 | D82: =C83 -> 197456.14 | E82: =D83 -> 161977.16 | F82: =E83 -> 128347.56 | G82: =F83 -> 96438.711 | H82: =G83 -> 66130.994 | I82: =H83 -> 37313.165 | J82: =I83 -> 9881.7637 | K82: =J83 -> -16259.425 | ... AL82: =AK83 -> -439570.62
A83: Closing cash | C83: =C82+C81 -> 197456.14 | D83: =D82+D81 -> 161977.16 | E83: =E82+E81 -> 128347.56 | F83: =F82+F81 -> 96438.711 | G83: =G82+G81 -> 66130.994 | H83: =H82+H81 -> 37313.165 | I83: =I82+I81 -> 9881.7637 | J83: =J82+J81 -> -16259.425 | ... AL83: =AL82+AL81 -> -449313.79
A84: Helper: EBITDA positive (1/0) | C84: =IF(C44>0,1,0) -> 0 | D84: =IF(D44>0,1,0) -> 0 | E84: =IF(E44>0,1,0) -> 0 | F84: =IF(F44>0,1,0) -> 0 | G84: =IF(G44>0,1,0) -> 0 | H84: =IF(H44>0,1,0) -> 0 | I84: =IF(I44>0,1,0) -> 0 | J84: =IF(J44>0,1,0) -> 0 | ... AL84: =IF(AL44>0,1,0) -> 0
A86: Goal modules
A87: Helper: net income positive (1/0) | C87: =IF(C53>0,1,0) -> 0 | D87: =IF(D53>0,1,0) -> 0 | E87: =IF(E53>0,1,0) -> 0 | F87: =IF(F53>0,1,0) -> 0 | G87: =IF(G53>0,1,0) -> 0 | H87: =IF(H53>0,1,0) -> 0 | I87: =IF(I53>0,1,0) -> 0 | J87: =IF(J53>0,1,0) -> 0 | ... AL87: =IF(AL53>0,1,0) -> 0
A88: Cash flow before financing (operating + investing) | C88: =C77+C78 -> -282543.86 | D88: =D77+D78 -> -33693.265 | E88: =E77+E78 -> -31843.889 | F88: =F77+F78 -> -30123.136 | G88: =G77+G78 -> -28522.003 | H88: =H77+H78 -> -27032.115 | I88: =I77+I78 -> -25645.687 | J88: =J77+J78 -> -24355.475 | ... AL88: =AL77+AL78 -> -7957.4502
A89: Cumulative cash flow before financing | C89: =C88 -> -282543.86 | D89: =C89+D88 -> -316237.12 | E89: =D89+E88 -> -348081.01 | F89: =E89+F88 -> -378204.15 | G89: =F89+G88 -> -406726.15 | H89: =G89+H88 -> -433758.26 | I89: =H89+I88 -> -459403.95 | J89: =I89+J88 -> -483759.43 | K89: =J89+K88 -> -506914.17 | ... AL89: =AK89+AL88 -> -866813.79
A90: Helper: lowest cumulative cash flow so far | C90: =C89 -> -282543.86 | D90: =MIN(C90,D89) -> -316237.12 | E90: =MIN(D90,E89) -> -348081.01 | F90: =MIN(E90,F89) -> -378204.15 | G90: =MIN(F90,G89) -> -406726.15 | H90: =MIN(G90,H89) -> -433758.26 | I90: =MIN(H90,I89) -> -459403.95 | J90: =MIN(I90,J89) -> -483759.43 | K90: =MIN(J90,K89) -> -506914.17 | ... AL90: =MIN(AK90,AL89) -> -866813.79
A91: Helper: investment paid back (1/0) | C91: =IF(AND(C89>=0,C90<0),1,0) -> 0 | D91: =IF(AND(D89>=0,D90<0),1,0) -> 0 | E91: =IF(AND(E89>=0,E90<0),1,0) -> 0 | F91: =IF(AND(F89>=0,F90<0),1,0) -> 0 | G91: =IF(AND(G89>=0,G90<0),1,0) -> 0 | H91: =IF(AND(H89>=0,H90<0),1,0) -> 0 | I91: =IF(AND(I89>=0,I90<0),1,0) -> 0 | J91: =IF(AND(J89>=0,J90<0),1,0) -> 0 | ... AL91: =IF(AND(AL89>=0,AL90<0),1,0) -> 0
A92: Unlevered free cash flow (operating + after-tax interest − capex) | C92: =C77-C48*(1-Inputs!$B$66)+C78 -> -281753.86 | D92: =D77-D48*(1-Inputs!$B$66)+D78 -> -32907.967 | E92: =E77-E48*(1-Inputs!$B$66)+E78 -> -31067.996 | F92: =F77-F48*(1-Inputs!$B$66)+F78 -> -29356.648 | G92: =G77-G48*(1-Inputs!$B$66)+G78 -> -27764.919 | H92: =H77-H48*(1-Inputs!$B$66)+H78 -> -26284.437 | I92: =I77-I48*(1-Inputs!$B$66)+I78 -> -24907.413 | J92: =J77-J48*(1-Inputs!$B$66)+J78 -> -23626.606 | ... AL92: =AL77-AL48*(1-Inputs!$B$66)+AL78 -> -7491.9145
A94: Balance sheet
A95: Paid-in capital | C95: =C79 -> 330000 | D95: =C95+D79 -> 330000 | E95: =D95+E79 -> 330000 | F95: =E95+F79 -> 330000 | G95: =F95+G79 -> 330000 | H95: =G95+H79 -> 330000 | I95: =H95+I79 -> 330000 | J95: =I95+J79 -> 330000 | K95: =J95+K79 -> 330000 | ... AL95: =AK95+AL79 -> 330000
A96: Retained earnings | C96: =C53 -> -38732.796 | D96: =C96+D53 -> -75478.151 | E96: =D96+E53 -> -110368.82 | F96: =E96+F53 -> -143533.79 | G96: =F96+G53 -> -175093.03 | H96: =G96+H53 -> -205158.12 | I96: =H96+I53 -> -233832.8 | J96: =I96+J53 -> -261213.57 | K96: =J96+K53 -> -287390.17 | ... AL96: =AK96+AL53 -> -728442.32
A97: Total assets | C97: =C83+C69+C70+C60 -> 447692.7 | D97: =D83+D69+D70+D60 -> 409313.43 | E97: =E83+E69+E70+E60 -> 372778.23 | F97: =F83+F69+F70+F60 -> 337958.83 | G97: =G83+G69+G70+G60 -> 304735.98 | H97: =H83+H69+H70+H60 -> 272998.73 | I97: =I83+I69+I70+I60 -> 242643.94 | J97: =J83+J69+J70+J60 -> 213575.67 | ... AL97: =AL83+AL69+AL70+AL60 -> -301970.97
A98: Total liabilities | C98: =C71+C66 -> 156425.5 | D98: =D71+D66 -> 154791.58 | E98: =E71+E66 -> 153147.04 | F98: =F71+F66 -> 151492.62 | G98: =G71+G66 -> 149829.01 | H98: =H71+H66 -> 148156.85 | I98: =I71+I66 -> 146476.74 | J98: =J71+J66 -> 144789.24 | ... AL98: =AL71+AL66 -> 96471.357
A99: Total equity | C99: =C95+C96 -> 291267.2 | D99: =D95+D96 -> 254521.85 | E99: =E95+E96 -> 219631.18 | F99: =F95+F96 -> 186466.21 | G99: =G95+G96 -> 154906.97 | H99: =H95+H96 -> 124841.88 | I99: =I95+I96 -> 96167.202 | J99: =J95+J96 -> 68786.431 | ... AL99: =AL95+AL96 -> -398442.32
A100: Total liabilities & equity | C100: =C98+C99 -> 447692.7 | D100: =D98+D99 -> 409313.43 | E100: =E98+E99 -> 372778.23 | F100: =F98+F99 -> 337958.83 | G100: =G98+G99 -> 304735.98 | H100: =H98+H99 -> 272998.73 | I100: =I98+I99 -> 242643.94 | J100: =J98+J99 -> 213575.67 | ... AL100: =AL98+AL99 -> -301970.97
A101: Check: assets − liabilities − equity | C101: =C97-C100 -> 0 | D101: =D97-D100 -> 0 | E101: =E97-E100 -> 0 | F101: =F97-F100 -> 0 | G101: =G97-G100 -> 0 | H101: =H97-H100 -> 0 | I101: =I97-I100 -> 0 | J101: =J97-J100 -> 0 | ... AL101: =AL97-AL100 -> 0
A103: Headcount (FTE)
A104: Studio manager — FTE | C104: =Inputs!$B$42*(1+Inputs!$B$44)^(C$7-1)*MAX(0,MIN(1,C$6*1-Inputs!$B$45+1))/1 -> 1 | D104: =Inputs!$B$42*(1+Inputs!$B$44)^(D$7-1)*MAX(0,MIN(1,D$6*1-Inputs!$B$45+1))/1 -> 1 | E104: =Inputs!$B$42*(1+Inputs!$B$44)^(E$7-1)*MAX(0,MIN(1,E$6*1-Inputs!$B$45+1))/1 -> 1 | F104: =Inputs!$B$42*(1+Inputs!$B$44)^(F$7-1)*MAX(0,MIN(1,F$6*1-Inputs!$B$45+1))/1 -> 1 | G104: =Inputs!$B$42*(1+Inputs!$B$44)^(G$7-1)*MAX(0,MIN(1,G$6*1-Inputs!$B$45+1))/1 -> 1 | H104: =Inputs!$B$42*(1+Inputs!$B$44)^(H$7-1)*MAX(0,MIN(1,H$6*1-Inputs!$B$45+1))/1 -> 1 | I104: =Inputs!$B$42*(1+Inputs!$B$44)^(I$7-1)*MAX(0,MIN(1,I$6*1-Inputs!$B$45+1))/1 -> 1 | J104: =Inputs!$B$42*(1+Inputs!$B$44)^(J$7-1)*MAX(0,MIN(1,J$6*1-Inputs!$B$45+1))/1 -> 1 | ... AL104: =Inputs!$B$42*(1+Inputs!$B$44)^(AL$7-1)*MAX(0,MIN(1,AL$6*1-Inputs!$B$45+1))/1 -> 1
A105: Front desk & sales — FTE | C105: =Inputs!$B$46*(1+Inputs!$B$48)^(C$7-1)*MAX(0,MIN(1,C$6*1-Inputs!$B$49+1))/1 -> 3 | D105: =Inputs!$B$46*(1+Inputs!$B$48)^(D$7-1)*MAX(0,MIN(1,D$6*1-Inputs!$B$49+1))/1 -> 3 | E105: =Inputs!$B$46*(1+Inputs!$B$48)^(E$7-1)*MAX(0,MIN(1,E$6*1-Inputs!$B$49+1))/1 -> 3 | F105: =Inputs!$B$46*(1+Inputs!$B$48)^(F$7-1)*MAX(0,MIN(1,F$6*1-Inputs!$B$49+1))/1 -> 3 | G105: =Inputs!$B$46*(1+Inputs!$B$48)^(G$7-1)*MAX(0,MIN(1,G$6*1-Inputs!$B$49+1))/1 -> 3 | H105: =Inputs!$B$46*(1+Inputs!$B$48)^(H$7-1)*MAX(0,MIN(1,H$6*1-Inputs!$B$49+1))/1 -> 3 | I105: =Inputs!$B$46*(1+Inputs!$B$48)^(I$7-1)*MAX(0,MIN(1,I$6*1-Inputs!$B$49+1))/1 -> 3 | J105: =Inputs!$B$46*(1+Inputs!$B$48)^(J$7-1)*MAX(0,MIN(1,J$6*1-Inputs!$B$49+1))/1 -> 3 | ... AL105: =Inputs!$B$46*(1+Inputs!$B$48)^(AL$7-1)*MAX(0,MIN(1,AL$6*1-Inputs!$B$49+1))/1 -> 3
A106: Total FTE | C106: =C104+C105 -> 4 | D106: =D104+D105 -> 4 | E106: =E104+E105 -> 4 | F106: =F104+F105 -> 4 | G106: =G104+G105 -> 4 | H106: =H104+H105 -> 4 | I106: =I104+I105 -> 4 | J106: =J104+J105 -> 4 | ... AL106: =AL104+AL105 -> 4
A108: Payroll cost (salary + taxes & benefits)
A109: Studio manager — payroll cost | C109: =-C104*Inputs!$B$43/12*1*(1+Inputs!$B$50)*(1+Inputs!$B$51)^(C$7-1) -> -5041.6667 | D109: =-D104*Inputs!$B$43/12*1*(1+Inputs!$B$50)*(1+Inputs!$B$51)^(D$7-1) -> -5041.6667 | E109: =-E104*Inputs!$B$43/12*1*(1+Inputs!$B$50)*(1+Inputs!$B$51)^(E$7-1) -> -5041.6667 | F109: =-F104*Inputs!$B$43/12*1*(1+Inputs!$B$50)*(1+Inputs!$B$51)^(F$7-1) -> -5041.6667 | G109: =-G104*Inputs!$B$43/12*1*(1+Inputs!$B$50)*(1+Inputs!$B$51)^(G$7-1) -> -5041.6667 | H109: =-H104*Inputs!$B$43/12*1*(1+Inputs!$B$50)*(1+Inputs!$B$51)^(H$7-1) -> -5041.6667 | I109: =-I104*Inputs!$B$43/12*1*(1+Inputs!$B$50)*(1+Inputs!$B$51)^(I$7-1) -> -5041.6667 | J109: =-J104*Inputs!$B$43/12*1*(1+Inputs!$B$50)*(1+Inputs!$B$51)^(J$7-1) -> -5041.6667 | ... AL109: =-AL104*Inputs!$B$43/12*1*(1+Inputs!$B$50)*(1+Inputs!$B$51)^(AL$7-1) -> -5348.7042
A110: Front desk & sales — payroll cost | C110: =-C105*Inputs!$B$47/12*1*(1+Inputs!$B$50)*(1+Inputs!$B$51)^(C$7-1) -> -8800 | D110: =-D105*Inputs!$B$47/12*1*(1+Inputs!$B$50)*(1+Inputs!$B$51)^(D$7-1) -> -8800 | E110: =-E105*Inputs!$B$47/12*1*(1+Inputs!$B$50)*(1+Inputs!$B$51)^(E$7-1) -> -8800 | F110: =-F105*Inputs!$B$47/12*1*(1+Inputs!$B$50)*(1+Inputs!$B$51)^(F$7-1) -> -8800 | G110: =-G105*Inputs!$B$47/12*1*(1+Inputs!$B$50)*(1+Inputs!$B$51)^(G$7-1) -> -8800 | H110: =-H105*Inputs!$B$47/12*1*(1+Inputs!$B$50)*(1+Inputs!$B$51)^(H$7-1) -> -8800 | I110: =-I105*Inputs!$B$47/12*1*(1+Inputs!$B$50)*(1+Inputs!$B$51)^(I$7-1) -> -8800 | J110: =-J105*Inputs!$B$47/12*1*(1+Inputs!$B$50)*(1+Inputs!$B$51)^(J$7-1) -> -8800 | ... AL110: =-AL105*Inputs!$B$47/12*1*(1+Inputs!$B$50)*(1+Inputs!$B$51)^(AL$7-1) -> -9335.92
A111: Total payroll | C111: =C109+C110 -> -13841.667 | D111: =D109+D110 -> -13841.667 | E111: =E109+E110 -> -13841.667 | F111: =F109+F110 -> -13841.667 | G111: =G109+G110 -> -13841.667 | H111: =H109+H110 -> -13841.667 | I111: =I109+I110 -> -13841.667 | J111: =J109+J110 -> -13841.667 | ... AL111: =AL109+AL110 -> -14684.624
A114: Base scenario — reads Inputs column C
A115: Month | C115: M1 | D115: M2 | E115: M3 | F115: M4 | G115: M5 | H115: M6 | I115: M7 | J115: M8 | K115: M9 | L115: M10 | M115: M11 | N115: M12 | O115: M13 | P115: M14 | Q115: M15 | R115: M16 | S115: M17 | T115: M18 | U115: M19 | V115: M20 | W115: M21 | X115: M22 | Y115: M23 | Z115: M24 | AA115: M25 | AB115: M26 | AC115: M27 | AD115: M28 | AE115: M29 | AF115: M30 | AG115: M31 | AH115: M32 | AI115: M33 | AJ115: M34 | AK115: M35 | AL115: M36
A116: Period # | C116: 1 | D116: 2 | E116: 3 | F116: 4 | G116: 5 | H116: 6 | I116: 7 | J116: 8 | K116: 9 | L116: 10 | M116: 11 | N116: 12 | O116: 13 | P116: 14 | Q116: 15 | R116: 16 | S116: 17 | T116: 18 | U116: 19 | V116: 20 | W116: 21 | X116: 22 | Y116: 23 | Z116: 24 | AA116: 25 | AB116: 26 | AC116: 27 | AD116: 28 | AE116: 29 | AF116: 30 | AG116: 31 | AH116: 32 | AI116: 33 | AJ116: 34 | AK116: 35 | AL116: 36
...

Sheet Checks
A1: Model checks | E1: =HYPERLINK("#'Cover'!A1","◂ Contents") -> ◂ Contents
A2: Live formulas: they re-run every time an input changes.
A3: Check | B3: Result | C3: What it tests
A4: Annual revenue ties to period detail | B4: =IF(ABS(SUM('P&L'!$B$5:$D$5)-SUM(Monthly!$C$24:$AL$24))<0.5,"PASS","FAIL") -> PASS | C4: Sum of annual revenue equals the sum of every period
A5: Annual net income ties to period detail | B5: =IF(ABS(SUM('P&L'!$B$24:$D$24)-SUM(Monthly!$C$51:$AL$51))<0.5,"PASS","FAIL") -> PASS | C5: Sum of annual net income equals the sum of every period
A6: EBITDA reconciliation | B6: =IF(ABS(SUM(Monthly!$C$42:$AL$42)-SUM(Monthly!$C$31:$AL$31)-SUM(Monthly!$C$41:$AL$41))<0.5,"PASS","FAIL") -> PASS | C6: EBITDA = gross profit + operating expenses (costs are negative)
A7: Cash roll-forward | B7: =IF(ABS(INDEX(Monthly!$C$81:$AL$81,36)-SUM(Monthly!$C$79:$AL$79))<0.5,"PASS","FAIL") -> PASS | C7: Closing cash = all net cash flows since the start (opening cash is zero)
A8: Scenario selector valid | B8: =IF(AND(ISNUMBER(Dashboard!B4),Dashboard!B4>=1,Dashboard!B4<=3,INT(Dashboard!B4)=Dashboard!B4),"PASS","FAIL") -> PASS | C8: Dashboard!B4 is 1, 2 or 3
A9: Scenario ordering of drivers | B9: =IF(AND(Inputs!$B$7<=Inputs!$C$7,Inputs!$C$7<=Inputs!$D$7,Inputs!$B$9<=Inputs!$C$9,Inputs!$C$9<=Inputs!$D$9,Inputs!$B$10<=Inputs!$C$10,Inputs!$C$10<=Inputs!$D$10,Inputs!$B$12<=Inputs!$C$12,Inputs!$C$12<=Inputs!$D$12,Inputs!$B$13>=Inputs!$C$13,Inputs!$C$13>=Inputs!$D$13,Inputs!$B$14<=Inputs!$C$14,Inputs!$C$14<=Inputs!$D$14,Inputs!$B$15>=Inputs!$C$15,Inputs!$C$15>=Inputs!$D$15,Inputs!$B$18<=Inputs!$C$18,Inputs!$C$18<=Inputs!$D$18,Inputs!$B$19<=Inputs!$C$19,Inputs!$C$19<=Inputs!$D$19,Inputs!$B$20<=Inputs!$C$20,Inputs!$C$20<=Inputs!$D$20,Inputs!$B$23<=Inputs!$C$23,Inputs!$C$23<=Inputs!$D$23,Inputs!$B$24<=Inputs!$C$24,Inputs!$C$24<=Inputs!$D$24,Inputs!$B$25<=Inputs!$C$25,Inputs!$C$25<=Inputs!$D$25,Inputs!$B$26>=Inputs!$C$26,Inputs!$C$26>=Inputs!$D$26,Inputs!$B$27<=Inputs!$C$27,Inputs!$C$27<=Inputs!$D$27,Inputs!$B$28>=Inputs!$C$28,Inputs!$C$28>=Inputs!$D$28,Inputs!$B$32>=Inputs!$C$32,Inputs!$C$32>=Inputs!$D$32,Inputs!$B$36>=Inputs!$C$36,Inputs!$C$36>=Inputs!$D$36,Inputs!$B$42<=Inputs!$C$42,Inputs!$C$42<=Inputs!$D$42,Inputs!$B$44<=Inputs!$C$44,Inputs!$C$44<=Inputs!$D$44,Inputs!$B$46<=Inputs!$C$46,Inputs!$C$46<=Inputs!$D$46,Inputs!$B$48<=Inputs!$C$48,Inputs!$C$48<=Inputs!$D$48,Inputs!$B$72>=Inputs!$C$72,Inputs!$C$72>=Inputs!$D$72,Inputs!$B$73<=Inputs!$C$73,Inputs!$C$73<=Inputs!$D$73,Inputs!$B$74<=Inputs!$C$74,Inputs!$C$74<=Inputs!$D$74),"PASS","FAIL") -> PASS | C9: Low / Base / High ordered the right way for every growth and cost driver
A10: Gross margin within 0–100% | B10: =IF(AND(MIN('P&L'!$B$8:$D$8)>=0,MAX('P&L'!$B$8:$D$8)<=1),"PASS","FAIL") -> PASS | C10: Gross margin never negative or above 100%
A11: Loan balance never negative | B11: =IF(MIN(Monthly!$C$64:$AL$64)>=-0.5,"PASS","FAIL") -> PASS | C11: Repayments never exceed the loan
A12: Funding table ties to the cash flow | B12: =IF(ABS('Break-even'!B18-('Break-even'!B16-'Break-even'!B10))<0.5,"PASS","FAIL") -> PASS | C12: Lowest cash balance = sources of funds − uses of funds up to that point
A13: Valuation: discounting ties to NPV() | B13: =IF(ABS(Valuation!B23-NPV(Valuation!B6,Valuation!$B$17:$D$17))<0.5,"PASS","FAIL") -> PASS | C13: Sum of discounted free cash flows equals Excel's NPV of the same flows
A14: Valuation: WACC above terminal growth | B14: =IF(Valuation!B6>Valuation!B7,"PASS","FAIL") -> PASS | C14: The perpetual-growth formula needs WACC > g
A15: Valuation: sensitivity centre = enterprise value | B15: =IF(ABS(Valuation!D36-Valuation!B27)<0.5,"PASS","FAIL") -> PASS | C15: The middle of the WACC × growth table reproduces the headline value
A16: Valuation: final-year cash flow positive | B16: =IF(Valuation!$D$17>0,"PASS","WARN") -> PASS | C16: Business warning: a negative final-year cash flow gives a negative terminal value (often a 1-year plan still carrying start-up spending)
A17: Sources & uses balance | B17: =IF(ABS('Sources & Uses'!B21-'Sources & Uses'!B28)<0.5,"PASS","FAIL") -> PASS | C17: Sources of funds = uses of funds (incl. cash at the end) for the Sources & Uses period
A18: No error values | B18: =IF(SUMPRODUCT(--ISERROR(Monthly!$C$4:$AL$99))+SUMPRODUCT(--ISERROR(Headcount!$C$4:$AL$15))+SUMPRODUCT(--ISERROR('P&L'!$B$3:$D$25))+SUMPRODUCT(--ISERROR('Cash Flow'!$B$3:$D$18))+SUMPRODUCT(--ISERROR('Balance Sheet'!$B$3:$D$17))+SUMPRODUCT(--ISERROR(KPIs!$B$27:$D$48))+SUMPRODUCT(--ISERROR('Break-even'!$B$26:$D$33))+SUMPRODUCT(--ISERROR(Valuation!$B$14:$D$19))+SUMPRODUCT(--ISERROR('Break-even'!$B$3:$D$35))+SUMPRODUCT(--ISERROR(Valuation!$A$3:$F$40))+SUMPRODUCT(--ISERROR('Sources & Uses'!$B$3:$C$30))+SUMPRODUCT(--ISERROR(Dashboard!$A$6:$W$43))+SUMPRODUCT(--ISERROR(Summary!$A$5:$S$52))+SUMPRODUCT(--ISERROR(KPIs!$A$4:$E$48))+SUMPRODUCT(--ISERROR('Scenario calc'!$C$6:$AL$111))+SUMPRODUCT(--ISERROR('Scenario calc'!$C$116:$AL$221))+SUMPRODUCT(--ISERROR('Scenario calc'!$C$226:$AL$331))+SUMPRODUCT(--ISERROR(Scenarios!$B$5:$E$50))=0,"PASS","FAIL") -> PASS | C18: No error values (divide-by-zero, broken references) on any calculation sheet
A19: Summary ties to statements | B19: =IF(IFERROR(AND(SUMPRODUCT(--(ABS(Summary!$B$7:$D$7-'P&L'!$B$5:$D$5)>0.5))=0,SUMPRODUCT(--(ABS(Summary!$B$19:$D$19-'P&L'!$B$24:$D$24)>0.5))=0,SUMPRODUCT(--(ABS(Summary!$B$31:$D$31-'Cash Flow'!$B$18:$D$18)>0.5))=0,SUMPRODUCT(--(ABS(Summary!$B$41:$D$41-'Balance Sheet'!$B$5:$D$5)>0.5))=0,ABS(SUM(Summary!$H$7:$S$7)-INDEX(Summary!$B$7:$D$7,Summary!$R$2))<0.5,ABS(SUM(Summary!$H$19:$S$19)-INDEX(Summary!$B$19:$D$19,Summary!$R$2))<0.5,ABS(Summary!$S$31-INDEX(Summary!$B$31:$D$31,Summary!$R$2))<0.5),FALSE()),"PASS","FAIL") -> PASS | C19: Summary revenue, net income and closing cash equal the statements every year; the detailed year adds up to its annual figure
A20: DuPont ties to return on equity | B20: =IF(SUMPRODUCT(--(ABS(KPIs!$B$24:$D$24)>0.000000001))>0,"FAIL",IF(SUMPRODUCT(ISNUMBER(KPIs!$B$23:$D$23)*ISNUMBER(KPIs!$B$16:$D$16))=0,"n/a","PASS")) -> PASS | C20: Net margin × asset turnover × equity multiplier equals return on equity every year; n/a = no year where both are defined (a one-sided n/a is a FAIL)
A21: Scenarios: Active = selected scenario | B21: =IF(IFERROR(AND(ABS(Scenarios!E17-INDEX(Scenarios!B17:D17,1,Dashboard!$B$4))<0.5,ABS(Scenarios!E18-INDEX(Scenarios!B18:D18,1,Dashboard!$B$4))<0.5,ABS(Scenarios!E19-INDEX(Scenarios!B19:D19,1,Dashboard!$B$4))<0.5,ABS(Scenarios!E20-INDEX(Scenarios!B20:D20,1,Dashboard!$B$4))<0.000001,ABS(Scenarios!E21-INDEX(Scenarios!B21:D21,1,Dashboard!$B$4))<0.5,ABS(Scenarios!E22-INDEX(Scenarios!B22:D22,1,Dashboard!$B$4))<0.5,ABS(Scenarios!E23-INDEX(Scenarios!B23:D23,1,Dashboard!$B$4))<0.5,ABS(Scenarios!E24-INDEX(Scenarios!B24:D24,1,Dashboard!$B$4))<0.5,ABS(Scenarios!E25-INDEX(Scenarios!B25:D25,1,Dashboard!$B$4))<0.5,ABS(Scenarios!E26-INDEX(Scenarios!B26:D26,1,Dashboard!$B$4))<0.5),FALSE()),"PASS","FAIL") -> PASS | C21: On the Scenarios sheet the live model (Active) equals the Low / Base / High column chosen on the Dashboard for every output
A22: Balance sheet balances every period | B22: =IF(SUMPRODUCT(--(ABS(Monthly!$C$99:$AL$99)>0.5))=0,"PASS","FAIL") -> PASS | C22: Assets = liabilities + equity in every period
A23: Funding sufficient (cash ≥ 0) | B23: =IF(MIN(Monthly!$C$81:$AL$81)>=0,"PASS","WARN") -> PASS | C23: Business warning, not an error: cash dips below zero in this scenario
A25: Overall verdict | B25: =IF(COUNTIF(B4:B23,"FAIL")>0,"FAIL",IF(COUNTIF(B4:B23,"WARN")>0,"PASS WITH WARNINGS","PASS")) -> PASS
