Workbook

Sheet Cover
B2: Food truck financial model (planning)
B3: 5-year financial model · monthly detail · Low / Base / High scenarios · US dollars · Full plan
B5: Purpose | D5: Revenue and profit plan
B6: Active scenario | D6: =Dashboard!C4&" (change it on the Dashboard, cell B4)" -> Base (change it on the Dashboard, cell B4)
B7: Model checks | D7: =Checks!B25 -> PASS
B8: Prepared | D8: 22 October 2026
B10: Contents
C11: PRESENTATION
B12: 1 | C12: =HYPERLINK("#Dashboard!A1","Dashboard") -> Dashboard | D12: Scenario switch, key numbers, core financials
B13: 2 | C13: =HYPERLINK("#Summary!A1","Summary") -> Summary | D13: Income statement, cash flow and balance sheet — every year and any year by month
B14: 3 | C14: =HYPERLINK("#Scenarios!A1","Scenarios") -> Scenarios | D14: Low / Base / High side by side: drivers, outputs, charts
B15: 4 | C15: =HYPERLINK("#'Break-even'!A1","Break-even") -> Break-even | D15: Startup costs, funding need, break-even timing and revenue
B16: 5 | C16: =HYPERLINK("#Valuation!A1","Valuation") -> Valuation | D16: Free cash flow, DCF (perpetual growth and exit multiple), WACC × growth sensitivity
B17: 6 | C17: =HYPERLINK("#'Sources & Uses'!A1","Sources & Uses") -> Sources & Uses | D17: Funding structure, sources and uses of cash for the first months
B18: 7 | C18: =HYPERLINK("#KPIs!A1","KPIs") -> KPIs | D18: Financial ratios, DuPont analysis, industry metrics
C19: INPUTS
B20: 8 | C20: =HYPERLINK("#Inputs!A1","Inputs") -> Inputs | D20: Every assumption, Low / Base / High, with units and comments
C21: STATEMENTS
B22: 9 | C22: =HYPERLINK("#'P&L'!A1","P&L") -> P&L | D22: Annual profit & loss
B23: 10 | C23: =HYPERLINK("#'Cash Flow'!A1","Cash Flow") -> Cash Flow | D23: Annual cash flow statement
B24: 11 | C24: =HYPERLINK("#'Balance Sheet'!A1","Balance Sheet") -> Balance Sheet | D24: Balance sheet at year end
C25: CALCULATIONS
B26: 12 | C26: =HYPERLINK("#Monthly!A1","Monthly") -> Monthly | D26: Month-by-month engine of the model
B27: 13 | C27: =HYPERLINK("#Headcount!A1","Headcount") -> Headcount | D27: Team and payroll
B28: 14 | C28: =HYPERLINK("#'Scenario calc'!A1","Scenario calc") -> Scenario calc | D28: Low, Base and High calculated side by side for the Scenarios sheet
C29: CONTROL
B30: 15 | C30: =HYPERLINK("#Checks!A1","Checks") -> Checks | D30: Live integrity checks and the overall verdict
B32: How to read this file
C33: 1000 | D33: Input you can change — yellow cell with a blue figure (Inputs sheet and the view switches)
C34: 1000 | D34: Formula — calculated, do not overwrite
C35: 1000 | D35: Link to another sheet
C36: 1000 | D36: Active value the model uses (follows the scenario)

Sheet Dashboard
A1: Dashboard | W1: =HYPERLINK("#'Cover'!A1","◂ Contents") -> ◂ Contents
A2: Food truck financial model (planning)
A4: Active scenario | B4: 2 | C4: =CHOOSE(B4,"Low","Base","High") -> Base | D4: 1 = Low · 2 = Base · 3 = High — every sheet follows this cell | S4: Model checks | T4: =Checks!B25 -> PASS
A6: REVENUE · YEAR 5 | C6: EBITDA MARGIN · YEAR 5 | H6: NET INCOME · YEAR 5 | L6: LOWEST CASH BALANCE | P6: FUNDING REQUIRED | T6: ENTERPRISE VALUE (DCF)
A7: =F12 -> 406053.09 | C7: =F17 -> 0.12196808 | H7: =F18 -> 23592.293 | L7: =F39 -> 9872.4151 | P7: =F37 -> 222127.58 | T7: =F44 -> 2883.7108
A8: =IF(AND(B12>0,F12>=0),(F12/B12)^(1/4)-1,"CAGR n/a") -> 0.10344142 | C8: =F16 -> 49525.516 | H8: =F19 -> 0.058101498 | L8: ='Break-even'!B6 -> 26 | P8: =IF(F38>=0,"Covered by funding raised",-F38) -> 32127.585 | T8: Average of 2 methods
A10: Core financials ($'000) — active scenario
B11: 1 | C11: 2 | D11: 3 | E11: 4 | F11: 5
A12: Revenue | B12: =SUMIF(Monthly!$C$5:$BJ$5,B$11,Monthly!$C$24:$BJ$24) -> 273896 | C12: =SUMIF(Monthly!$C$5:$BJ$5,C$11,Monthly!$C$24:$BJ$24) -> 336825.82 | D12: =SUMIF(Monthly!$C$5:$BJ$5,D$11,Monthly!$C$24:$BJ$24) -> 358461.37 | E12: =SUMIF(Monthly!$C$5:$BJ$5,E$11,Monthly!$C$24:$BJ$24) -> 381506.04 | F12: =SUMIF(Monthly!$C$5:$BJ$5,F$11,Monthly!$C$24:$BJ$24) -> 406053.09
A13: Gross profit | B13: =SUMIF(Monthly!$C$5:$BJ$5,B$11,Monthly!$C$33:$BJ$33) -> 161966.54 | C13: =SUMIF(Monthly!$C$5:$BJ$5,C$11,Monthly!$C$33:$BJ$33) -> 199005.1 | D13: =SUMIF(Monthly!$C$5:$BJ$5,D$11,Monthly!$C$33:$BJ$33) -> 211683.05 | E13: =SUMIF(Monthly!$C$5:$BJ$5,E$11,Monthly!$C$33:$BJ$33) -> 225178.61 | F13: =SUMIF(Monthly!$C$5:$BJ$5,F$11,Monthly!$C$33:$BJ$33) -> 239545.29
A14: Gross margin | B14: =IF(B12=0,0,B13/B12) -> 0.5913432 | C14: =IF(C12=0,0,C13/C12) -> 0.59082496 | D14: =IF(D12=0,0,D13/D12) -> 0.5905324 | E14: =IF(E12=0,0,E13/E12) -> 0.59023605 | F14: =IF(F12=0,0,F13/F12) -> 0.58993587
A15: Operating expenses | B15: =SUMIF(Monthly!$C$5:$BJ$5,B$11,Monthly!$C$45:$BJ$45) -> -169272.5 | C15: =SUMIF(Monthly!$C$5:$BJ$5,C$11,Monthly!$C$45:$BJ$45) -> -174374.61 | D15: =SUMIF(Monthly!$C$5:$BJ$5,D$11,Monthly!$C$45:$BJ$45) -> -179430.04 | E15: =SUMIF(Monthly!$C$5:$BJ$5,E$11,Monthly!$C$45:$BJ$45) -> -184643.35 | F15: =SUMIF(Monthly!$C$5:$BJ$5,F$11,Monthly!$C$45:$BJ$45) -> -190019.77
A16: EBITDA | B16: =SUMIF(Monthly!$C$5:$BJ$5,B$11,Monthly!$C$46:$BJ$46) -> -7305.964 | C16: =SUMIF(Monthly!$C$5:$BJ$5,C$11,Monthly!$C$46:$BJ$46) -> 24630.491 | D16: =SUMIF(Monthly!$C$5:$BJ$5,D$11,Monthly!$C$46:$BJ$46) -> 32253.01 | E16: =SUMIF(Monthly!$C$5:$BJ$5,E$11,Monthly!$C$46:$BJ$46) -> 40535.265 | F16: =SUMIF(Monthly!$C$5:$BJ$5,F$11,Monthly!$C$46:$BJ$46) -> 49525.516
A17: EBITDA margin | B17: =IF(B12=0,0,B16/B12) -> -0.026674227 | C17: =IF(C12=0,0,C16/C12) -> 0.073125305 | D17: =IF(D12=0,0,D16/D12) -> 0.089976252 | E17: =IF(E12=0,0,E16/E12) -> 0.10625065 | F17: =IF(F12=0,0,F16/F12) -> 0.12196808
A18: Net income | B18: =SUMIF(Monthly!$C$5:$BJ$5,B$11,Monthly!$C$55:$BJ$55) -> -34439.625 | C18: =SUMIF(Monthly!$C$5:$BJ$5,C$11,Monthly!$C$55:$BJ$55) -> -1245.9377 | D18: =SUMIF(Monthly!$C$5:$BJ$5,D$11,Monthly!$C$55:$BJ$55) -> 7639.439 | E18: =SUMIF(Monthly!$C$5:$BJ$5,E$11,Monthly!$C$55:$BJ$55) -> 17184.551 | F18: =SUMIF(Monthly!$C$5:$BJ$5,F$11,Monthly!$C$55:$BJ$55) -> 23592.293
A19: Net margin | B19: =IF(B12=0,0,B18/B12) -> -0.12573979 | C19: =IF(C12=0,0,C18/C12) -> -0.0036990563 | D19: =IF(D12=0,0,D18/D12) -> 0.02131175 | E19: =IF(E12=0,0,E18/E12) -> 0.045043982 | F19: =IF(F12=0,0,F18/F12) -> 0.058101498
A20: Operating cash flow | B20: =SUMIF(Monthly!$C$5:$BJ$5,B$11,Monthly!$C$83:$BJ$83) -> -15659.701 | C20: =SUMIF(Monthly!$C$5:$BJ$5,C$11,Monthly!$C$83:$BJ$83) -> 18765.734 | D20: =SUMIF(Monthly!$C$5:$BJ$5,D$11,Monthly!$C$83:$BJ$83) -> 28004.382 | E20: =SUMIF(Monthly!$C$5:$BJ$5,E$11,Monthly!$C$83:$BJ$83) -> 37902.51 | F20: =SUMIF(Monthly!$C$5:$BJ$5,F$11,Monthly!$C$83:$BJ$83) -> 44662.997
A21: Investing cash flow | B21: =SUMIF(Monthly!$C$5:$BJ$5,B$11,Monthly!$C$84:$BJ$84) -> -138000 | C21: =SUMIF(Monthly!$C$5:$BJ$5,C$11,Monthly!$C$84:$BJ$84) -> -2500 | D21: =SUMIF(Monthly!$C$5:$BJ$5,D$11,Monthly!$C$84:$BJ$84) -> -2500 | E21: =SUMIF(Monthly!$C$5:$BJ$5,E$11,Monthly!$C$84:$BJ$84) -> -2500 | F21: =SUMIF(Monthly!$C$5:$BJ$5,F$11,Monthly!$C$84:$BJ$84) -> -2500
A22: Financing cash flow | B22: =SUMIF(Monthly!$C$5:$BJ$5,B$11,Monthly!$C$86:$BJ$86) -> 173500 | C22: =SUMIF(Monthly!$C$5:$BJ$5,C$11,Monthly!$C$86:$BJ$86) -> -18000 | D22: =SUMIF(Monthly!$C$5:$BJ$5,D$11,Monthly!$C$86:$BJ$86) -> -18000 | E22: =SUMIF(Monthly!$C$5:$BJ$5,E$11,Monthly!$C$86:$BJ$86) -> -18000 | F22: =SUMIF(Monthly!$C$5:$BJ$5,F$11,Monthly!$C$86:$BJ$86) -> -18000
A23: Net change in cash | B23: =SUMIF(Monthly!$C$5:$BJ$5,B$11,Monthly!$C$87:$BJ$87) -> 19840.299 | C23: =SUMIF(Monthly!$C$5:$BJ$5,C$11,Monthly!$C$87:$BJ$87) -> -1734.2661 | D23: =SUMIF(Monthly!$C$5:$BJ$5,D$11,Monthly!$C$87:$BJ$87) -> 7504.3816 | E23: =SUMIF(Monthly!$C$5:$BJ$5,E$11,Monthly!$C$87:$BJ$87) -> 17402.51 | F23: =SUMIF(Monthly!$C$5:$BJ$5,F$11,Monthly!$C$87:$BJ$87) -> 24162.997
A24: Year-end cash | B24: =INDEX(Monthly!$C$89:$BJ$89,B$11*12) -> 19840.299 | C24: =INDEX(Monthly!$C$89:$BJ$89,C$11*12) -> 18106.033 | D24: =INDEX(Monthly!$C$89:$BJ$89,D$11*12) -> 25610.415 | E24: =INDEX(Monthly!$C$89:$BJ$89,E$11*12) -> 43012.925 | F24: =INDEX(Monthly!$C$89:$BJ$89,F$11*12) -> 67175.922
A26: Food truck metrics
B27: 1 | C27: 2 | D27: 3 | E27: 4 | F27: 5
A28: Meals served | B28: =KPIs!B31 -> 19564 | C28: =KPIs!C31 -> 23358.24 | D28: =KPIs!D31 -> 24134.587 | E28: =KPIs!E31 -> 24938.005 | F28: =KPIs!F31 -> 25769.494
A29: Revenue per service day | B29: =KPIs!B38 -> 1110.0142 | C29: =KPIs!C38 -> 1327.1309 | D29: =KPIs!D38 -> 1401.9374 | E29: =KPIs!E38 -> 1480.5735 | F29: =KPIs!F38 -> 1563.1963
A30: Events & catering, % of revenue | B30: =KPIs!B36 -> 0.15717645 | C30: =KPIs!C36 -> 0.16182726 | D30: =KPIs!D36 -> 0.16445278 | E30: =KPIs!E36 -> 0.16711241 | F30: =KPIs!F36 -> 0.1698063
A31: Prime cost (food, packaging, payroll), % of revenue | B31: =KPIs!B43 -> 0.79477422 | C31: =KPIs!C43 -> 0.72449893 | D31: =KPIs!D43 -> 0.71284287 | E31: =KPIs!E43 -> 0.70154451 | F31: =KPIs!F43 -> 0.69059323
A32: Team (FTE, year end) | B32: =INDEX(Headcount!$C$11:$BJ$11,B$27*12) -> 3.2 | C32: =INDEX(Headcount!$C$11:$BJ$11,C$27*12) -> 3.2 | D32: =INDEX(Headcount!$C$11:$BJ$11,D$27*12) -> 3.2 | E32: =INDEX(Headcount!$C$11:$BJ$11,E$27*12) -> 3.2 | F32: =INDEX(Headcount!$C$11:$BJ$11,F$27*12) -> 3.2
A34: Funding & valuation ($'000) — active scenario
A35: Equity raised | F35: =Inputs!$E$71 -> 100000
A36: Loan drawn | F36: =Inputs!$E$72 -> 90000
A37: Funding required (incl. cash buffer) | F37: ='Break-even'!B12 -> 222127.58
A38: Funding surplus / (shortfall) | F38: ='Break-even'!B17 -> -32127.585
A39: ="Lowest cash balance (month "&'Break-even'!B6&")" -> Lowest cash balance (month 26) | F39: ='Break-even'!B18 -> 9872.4151
A40: First month with positive EBITDA | F40: ='Break-even'!B21 -> 6
A41: Cash invested paid back | F41: ='Break-even'!B23 -> Not within horizon
A42: Enterprise value — perpetual growth | F42: =Valuation!B27 -> 1604.5212
A43: Enterprise value — exit multiple | F43: =Valuation!C27 -> 4162.9003
A44: Enterprise value — average | F44: =Valuation!B30 -> 2883.7108

Sheet Summary
A1: Financial statements summary | U1: =HYPERLINK("#'Cover'!A1","◂ Contents") -> ◂ Contents
A2: Food truck financial model (planning) | P2: Select detailed year: | R2: 1
A5: Income statement ($'000) — by year | H5: ="Income statement ($'000) — Year "&$R$2&", by month" -> Income statement ($'000) — Year 1, by month
B6: 1 | C6: 2 | D6: 3 | E6: 4 | F6: 5 | H6: =INDEX(Monthly!$C$4:$BJ$4,($R$2-1)*12+1) -> 1 | I6: =INDEX(Monthly!$C$4:$BJ$4,($R$2-1)*12+2) -> 2 | J6: =INDEX(Monthly!$C$4:$BJ$4,($R$2-1)*12+3) -> 3 | K6: =INDEX(Monthly!$C$4:$BJ$4,($R$2-1)*12+4) -> 4 | L6: =INDEX(Monthly!$C$4:$BJ$4,($R$2-1)*12+5) -> 5 | M6: =INDEX(Monthly!$C$4:$BJ$4,($R$2-1)*12+6) -> 6 | N6: =INDEX(Monthly!$C$4:$BJ$4,($R$2-1)*12+7) -> 7 | O6: =INDEX(Monthly!$C$4:$BJ$4,($R$2-1)*12+8) -> 8 | P6: =INDEX(Monthly!$C$4:$BJ$4,($R$2-1)*12+9) -> 9 | Q6: =INDEX(Monthly!$C$4:$BJ$4,($R$2-1)*12+10) -> 10 | R6: =INDEX(Monthly!$C$4:$BJ$4,($R$2-1)*12+11) -> 11 | S6: =INDEX(Monthly!$C$4:$BJ$4,($R$2-1)*12+12) -> 12
A7: Revenue | B7: ='P&L'!B5 -> 273896 | C7: ='P&L'!C5 -> 336825.82 | D7: ='P&L'!D5 -> 358461.37 | E7: ='P&L'!E5 -> 381506.04 | F7: ='P&L'!F5 -> 406053.09 | H7: =INDEX(Monthly!$C$24:$BJ$24,($R$2-1)*12+1) -> 10416 | I7: =INDEX(Monthly!$C$24:$BJ$24,($R$2-1)*12+2) -> 12152 | J7: =INDEX(Monthly!$C$24:$BJ$24,($R$2-1)*12+3) -> 18816 | K7: =INDEX(Monthly!$C$24:$BJ$24,($R$2-1)*12+4) -> 21168 | L7: =INDEX(Monthly!$C$24:$BJ$24,($R$2-1)*12+5) -> 23520 | M7: =INDEX(Monthly!$C$24:$BJ$24,($R$2-1)*12+6) -> 25872 | N7: =INDEX(Monthly!$C$24:$BJ$24,($R$2-1)*12+7) -> 28224 | O7: =INDEX(Monthly!$C$24:$BJ$24,($R$2-1)*12+8) -> 28224 | P7: =INDEX(Monthly!$C$24:$BJ$24,($R$2-1)*12+9) -> 28224 | Q7: =INDEX(Monthly!$C$24:$BJ$24,($R$2-1)*12+10) -> 28224 | R7: =INDEX(Monthly!$C$24:$BJ$24,($R$2-1)*12+11) -> 28224 | S7: =INDEX(Monthly!$C$24:$BJ$24,($R$2-1)*12+12) -> 20832
A8: Cost of sales | B8: ='P&L'!B6 -> -111929.46 | C8: ='P&L'!C6 -> -137820.72 | D8: ='P&L'!D6 -> -146778.32 | E8: ='P&L'!E6 -> -156327.42 | F8: ='P&L'!F6 -> -166507.81 | H8: =INDEX(Monthly!$C$32:$BJ$32,($R$2-1)*12+1) -> -4308.144 | I8: =INDEX(Monthly!$C$32:$BJ$32,($R$2-1)*12+2) -> -5026.168 | J8: =INDEX(Monthly!$C$32:$BJ$32,($R$2-1)*12+3) -> -7671.744 | K8: =INDEX(Monthly!$C$32:$BJ$32,($R$2-1)*12+4) -> -8630.712 | L8: =INDEX(Monthly!$C$32:$BJ$32,($R$2-1)*12+5) -> -9589.68 | M8: =INDEX(Monthly!$C$32:$BJ$32,($R$2-1)*12+6) -> -10548.648 | N8: =INDEX(Monthly!$C$32:$BJ$32,($R$2-1)*12+7) -> -11507.616 | O8: =INDEX(Monthly!$C$32:$BJ$32,($R$2-1)*12+8) -> -11507.616 | P8: =INDEX(Monthly!$C$32:$BJ$32,($R$2-1)*12+9) -> -11507.616 | Q8: =INDEX(Monthly!$C$32:$BJ$32,($R$2-1)*12+10) -> -11507.616 | R8: =INDEX(Monthly!$C$32:$BJ$32,($R$2-1)*12+11) -> -11507.616 | S8: =INDEX(Monthly!$C$32:$BJ$32,($R$2-1)*12+12) -> -8616.288
A9: Gross profit | B9: ='P&L'!B7 -> 161966.54 | C9: ='P&L'!C7 -> 199005.1 | D9: ='P&L'!D7 -> 211683.05 | E9: ='P&L'!E7 -> 225178.61 | F9: ='P&L'!F7 -> 239545.29 | H9: =INDEX(Monthly!$C$33:$BJ$33,($R$2-1)*12+1) -> 6107.856 | I9: =INDEX(Monthly!$C$33:$BJ$33,($R$2-1)*12+2) -> 7125.832 | J9: =INDEX(Monthly!$C$33:$BJ$33,($R$2-1)*12+3) -> 11144.256 | K9: =INDEX(Monthly!$C$33:$BJ$33,($R$2-1)*12+4) -> 12537.288 | L9: =INDEX(Monthly!$C$33:$BJ$33,($R$2-1)*12+5) -> 13930.32 | M9: =INDEX(Monthly!$C$33:$BJ$33,($R$2-1)*12+6) -> 15323.352 | N9: =INDEX(Monthly!$C$33:$BJ$33,($R$2-1)*12+7) -> 16716.384 | O9: =INDEX(Monthly!$C$33:$BJ$33,($R$2-1)*12+8) -> 16716.384 | P9: =INDEX(Monthly!$C$33:$BJ$33,($R$2-1)*12+9) -> 16716.384 | Q9: =INDEX(Monthly!$C$33:$BJ$33,($R$2-1)*12+10) -> 16716.384 | R9: =INDEX(Monthly!$C$33:$BJ$33,($R$2-1)*12+11) -> 16716.384 | S9: =INDEX(Monthly!$C$33:$BJ$33,($R$2-1)*12+12) -> 12215.712
A10: Gross margin | B10: ='P&L'!B8 -> 0.5913432 | C10: ='P&L'!C8 -> 0.59082496 | D10: ='P&L'!D8 -> 0.5905324 | E10: ='P&L'!E8 -> 0.59023605 | F10: ='P&L'!F8 -> 0.58993587 | H10: =IF(H7=0,0,H9/H7) -> 0.58639171 | I10: =IF(I7=0,0,I9/I7) -> 0.58639171 | J10: =IF(J7=0,0,J9/J7) -> 0.59227551 | K10: =IF(K7=0,0,K9/K7) -> 0.59227551 | L10: =IF(L7=0,0,L9/L7) -> 0.59227551 | M10: =IF(M7=0,0,M9/M7) -> 0.59227551 | N10: =IF(N7=0,0,N9/N7) -> 0.59227551 | O10: =IF(O7=0,0,O9/O7) -> 0.59227551 | ... S10: =IF(S7=0,0,S9/S7) -> 0.58639171
A11: Total operating expenses | B11: ='P&L'!B18 -> -169272.5 | C11: ='P&L'!C18 -> -174374.61 | D11: ='P&L'!D18 -> -179430.04 | E11: ='P&L'!E18 -> -184643.35 | F11: ='P&L'!F18 -> -190019.77 | H11: =INDEX(Monthly!$C$45:$BJ$45,($R$2-1)*12+1) -> -13894.667 | I11: =INDEX(Monthly!$C$45:$BJ$45,($R$2-1)*12+2) -> -13904.167 | J11: =INDEX(Monthly!$C$45:$BJ$45,($R$2-1)*12+3) -> -14141.667 | K11: =INDEX(Monthly!$C$45:$BJ$45,($R$2-1)*12+4) -> -14151.167 | L11: =INDEX(Monthly!$C$45:$BJ$45,($R$2-1)*12+5) -> -14160.667 | M11: =INDEX(Monthly!$C$45:$BJ$45,($R$2-1)*12+6) -> -14170.167 | N11: =INDEX(Monthly!$C$45:$BJ$45,($R$2-1)*12+7) -> -14179.667 | O11: =INDEX(Monthly!$C$45:$BJ$45,($R$2-1)*12+8) -> -14179.667 | P11: =INDEX(Monthly!$C$45:$BJ$45,($R$2-1)*12+9) -> -14179.667 | Q11: =INDEX(Monthly!$C$45:$BJ$45,($R$2-1)*12+10) -> -14179.667 | R11: =INDEX(Monthly!$C$45:$BJ$45,($R$2-1)*12+11) -> -14179.667 | S11: =INDEX(Monthly!$C$45:$BJ$45,($R$2-1)*12+12) -> -13951.667
A12: EBITDA | B12: ='P&L'!B19 -> -7305.964 | C12: ='P&L'!C19 -> 24630.491 | D12: ='P&L'!D19 -> 32253.01 | E12: ='P&L'!E19 -> 40535.265 | F12: ='P&L'!F19 -> 49525.516 | H12: =INDEX(Monthly!$C$46:$BJ$46,($R$2-1)*12+1) -> -7786.8107 | I12: =INDEX(Monthly!$C$46:$BJ$46,($R$2-1)*12+2) -> -6778.3347 | J12: =INDEX(Monthly!$C$46:$BJ$46,($R$2-1)*12+3) -> -2997.4107 | K12: =INDEX(Monthly!$C$46:$BJ$46,($R$2-1)*12+4) -> -1613.8787 | L12: =INDEX(Monthly!$C$46:$BJ$46,($R$2-1)*12+5) -> -230.34667 | M12: =INDEX(Monthly!$C$46:$BJ$46,($R$2-1)*12+6) -> 1153.1853 | N12: =INDEX(Monthly!$C$46:$BJ$46,($R$2-1)*12+7) -> 2536.7173 | O12: =INDEX(Monthly!$C$46:$BJ$46,($R$2-1)*12+8) -> 2536.7173 | P12: =INDEX(Monthly!$C$46:$BJ$46,($R$2-1)*12+9) -> 2536.7173 | Q12: =INDEX(Monthly!$C$46:$BJ$46,($R$2-1)*12+10) -> 2536.7173 | R12: =INDEX(Monthly!$C$46:$BJ$46,($R$2-1)*12+11) -> 2536.7173 | S12: =INDEX(Monthly!$C$46:$BJ$46,($R$2-1)*12+12) -> -1735.9547
A13: EBITDA margin | B13: ='P&L'!B20 -> -0.026674227 | C13: ='P&L'!C20 -> 0.073125305 | D13: ='P&L'!D20 -> 0.089976252 | E13: ='P&L'!E20 -> 0.10625065 | F13: ='P&L'!F20 -> 0.12196808 | H13: =IF(H7=0,0,H12/H7) -> -0.74758167 | I13: =IF(I7=0,0,I12/I7) -> -0.55779581 | J13: =IF(J7=0,0,J12/J7) -> -0.15930116 | K13: =IF(K7=0,0,K12/K7) -> -0.076241434 | L13: =IF(L7=0,0,L12/L7) -> -0.0097936508 | M13: =IF(M7=0,0,M12/M7) -> 0.044572717 | N13: =IF(N7=0,0,N12/N7) -> 0.089878023 | O13: =IF(O7=0,0,O12/O7) -> 0.089878023 | ... S13: =IF(S7=0,0,S12/S7) -> -0.083331157
A14: Depreciation | B14: ='P&L'!B21 -> -19714.286 | C14: ='P&L'!C21 -> -20071.429 | D14: ='P&L'!D21 -> -20428.571 | E14: ='P&L'!E21 -> -20785.714 | F14: ='P&L'!F21 -> -21142.857 | H14: =INDEX(Monthly!$C$64:$BJ$64,($R$2-1)*12+1) -> -1642.8571 | I14: =INDEX(Monthly!$C$64:$BJ$64,($R$2-1)*12+2) -> -1642.8571 | J14: =INDEX(Monthly!$C$64:$BJ$64,($R$2-1)*12+3) -> -1642.8571 | K14: =INDEX(Monthly!$C$64:$BJ$64,($R$2-1)*12+4) -> -1642.8571 | L14: =INDEX(Monthly!$C$64:$BJ$64,($R$2-1)*12+5) -> -1642.8571 | M14: =INDEX(Monthly!$C$64:$BJ$64,($R$2-1)*12+6) -> -1642.8571 | N14: =INDEX(Monthly!$C$64:$BJ$64,($R$2-1)*12+7) -> -1642.8571 | O14: =INDEX(Monthly!$C$64:$BJ$64,($R$2-1)*12+8) -> -1642.8571 | P14: =INDEX(Monthly!$C$64:$BJ$64,($R$2-1)*12+9) -> -1642.8571 | Q14: =INDEX(Monthly!$C$64:$BJ$64,($R$2-1)*12+10) -> -1642.8571 | R14: =INDEX(Monthly!$C$64:$BJ$64,($R$2-1)*12+11) -> -1642.8571 | S14: =INDEX(Monthly!$C$64:$BJ$64,($R$2-1)*12+12) -> -1642.8571
A15: EBIT | B15: ='P&L'!B22 -> -27020.25 | C15: ='P&L'!C22 -> 4559.0623 | D15: ='P&L'!D22 -> 11824.439 | E15: ='P&L'!E22 -> 19749.551 | F15: ='P&L'!F22 -> 28382.659 | H15: =INDEX(Monthly!$C$49:$BJ$49,($R$2-1)*12+1) -> -9429.6678 | I15: =INDEX(Monthly!$C$49:$BJ$49,($R$2-1)*12+2) -> -8421.1918 | J15: =INDEX(Monthly!$C$49:$BJ$49,($R$2-1)*12+3) -> -4640.2678 | K15: =INDEX(Monthly!$C$49:$BJ$49,($R$2-1)*12+4) -> -3256.7358 | L15: =INDEX(Monthly!$C$49:$BJ$49,($R$2-1)*12+5) -> -1873.2038 | M15: =INDEX(Monthly!$C$49:$BJ$49,($R$2-1)*12+6) -> -489.67181 | N15: =INDEX(Monthly!$C$49:$BJ$49,($R$2-1)*12+7) -> 893.86019 | O15: =INDEX(Monthly!$C$49:$BJ$49,($R$2-1)*12+8) -> 893.86019 | P15: =INDEX(Monthly!$C$49:$BJ$49,($R$2-1)*12+9) -> 893.86019 | Q15: =INDEX(Monthly!$C$49:$BJ$49,($R$2-1)*12+10) -> 893.86019 | R15: =INDEX(Monthly!$C$49:$BJ$49,($R$2-1)*12+11) -> 893.86019 | S15: =INDEX(Monthly!$C$49:$BJ$49,($R$2-1)*12+12) -> -3378.8118
A16: Interest | B16: ='P&L'!B23 -> -7419.375 | C16: ='P&L'!C23 -> -5805 | D16: ='P&L'!D23 -> -4185 | E16: ='P&L'!E23 -> -2565 | F16: ='P&L'!F23 -> -945 | H16: =INDEX(Monthly!$C$50:$BJ$50,($R$2-1)*12+1) -> -675 | I16: =INDEX(Monthly!$C$50:$BJ$50,($R$2-1)*12+2) -> -669.375 | J16: =INDEX(Monthly!$C$50:$BJ$50,($R$2-1)*12+3) -> -658.125 | K16: =INDEX(Monthly!$C$50:$BJ$50,($R$2-1)*12+4) -> -646.875 | L16: =INDEX(Monthly!$C$50:$BJ$50,($R$2-1)*12+5) -> -635.625 | M16: =INDEX(Monthly!$C$50:$BJ$50,($R$2-1)*12+6) -> -624.375 | N16: =INDEX(Monthly!$C$50:$BJ$50,($R$2-1)*12+7) -> -613.125 | O16: =INDEX(Monthly!$C$50:$BJ$50,($R$2-1)*12+8) -> -601.875 | P16: =INDEX(Monthly!$C$50:$BJ$50,($R$2-1)*12+9) -> -590.625 | Q16: =INDEX(Monthly!$C$50:$BJ$50,($R$2-1)*12+10) -> -579.375 | R16: =INDEX(Monthly!$C$50:$BJ$50,($R$2-1)*12+11) -> -568.125 | S16: =INDEX(Monthly!$C$50:$BJ$50,($R$2-1)*12+12) -> -556.875
A17: Pre-tax income | B17: ='P&L'!B24 -> -34439.625 | C17: ='P&L'!C24 -> -1245.9377 | D17: ='P&L'!D24 -> 7639.439 | E17: ='P&L'!E24 -> 17184.551 | F17: ='P&L'!F24 -> 27437.659 | H17: =INDEX(Monthly!$C$51:$BJ$51,($R$2-1)*12+1) -> -10104.668 | I17: =INDEX(Monthly!$C$51:$BJ$51,($R$2-1)*12+2) -> -9090.5668 | J17: =INDEX(Monthly!$C$51:$BJ$51,($R$2-1)*12+3) -> -5298.3928 | K17: =INDEX(Monthly!$C$51:$BJ$51,($R$2-1)*12+4) -> -3903.6108 | L17: =INDEX(Monthly!$C$51:$BJ$51,($R$2-1)*12+5) -> -2508.8288 | M17: =INDEX(Monthly!$C$51:$BJ$51,($R$2-1)*12+6) -> -1114.0468 | N17: =INDEX(Monthly!$C$51:$BJ$51,($R$2-1)*12+7) -> 280.73519 | O17: =INDEX(Monthly!$C$51:$BJ$51,($R$2-1)*12+8) -> 291.98519 | P17: =INDEX(Monthly!$C$51:$BJ$51,($R$2-1)*12+9) -> 303.23519 | Q17: =INDEX(Monthly!$C$51:$BJ$51,($R$2-1)*12+10) -> 314.48519 | R17: =INDEX(Monthly!$C$51:$BJ$51,($R$2-1)*12+11) -> 325.73519 | S17: =INDEX(Monthly!$C$51:$BJ$51,($R$2-1)*12+12) -> -3935.6868
A18: Income tax | B18: ='P&L'!B25 -> 0 | C18: ='P&L'!C25 -> 0 | D18: ='P&L'!D25 -> 0 | E18: ='P&L'!E25 -> 0 | F18: ='P&L'!F25 -> -3845.3658 | H18: =INDEX(Monthly!$C$54:$BJ$54,($R$2-1)*12+1) -> 0 | I18: =INDEX(Monthly!$C$54:$BJ$54,($R$2-1)*12+2) -> 0 | J18: =INDEX(Monthly!$C$54:$BJ$54,($R$2-1)*12+3) -> 0 | K18: =INDEX(Monthly!$C$54:$BJ$54,($R$2-1)*12+4) -> 0 | L18: =INDEX(Monthly!$C$54:$BJ$54,($R$2-1)*12+5) -> 0 | M18: =INDEX(Monthly!$C$54:$BJ$54,($R$2-1)*12+6) -> 0 | N18: =INDEX(Monthly!$C$54:$BJ$54,($R$2-1)*12+7) -> 0 | O18: =INDEX(Monthly!$C$54:$BJ$54,($R$2-1)*12+8) -> 0 | P18: =INDEX(Monthly!$C$54:$BJ$54,($R$2-1)*12+9) -> 0 | Q18: =INDEX(Monthly!$C$54:$BJ$54,($R$2-1)*12+10) -> 0 | R18: =INDEX(Monthly!$C$54:$BJ$54,($R$2-1)*12+11) -> 0 | S18: =INDEX(Monthly!$C$54:$BJ$54,($R$2-1)*12+12) -> 0
A19: Net income | B19: ='P&L'!B26 -> -34439.625 | C19: ='P&L'!C26 -> -1245.9377 | D19: ='P&L'!D26 -> 7639.439 | E19: ='P&L'!E26 -> 17184.551 | F19: ='P&L'!F26 -> 23592.293 | H19: =INDEX(Monthly!$C$55:$BJ$55,($R$2-1)*12+1) -> -10104.668 | I19: =INDEX(Monthly!$C$55:$BJ$55,($R$2-1)*12+2) -> -9090.5668 | J19: =INDEX(Monthly!$C$55:$BJ$55,($R$2-1)*12+3) -> -5298.3928 | K19: =INDEX(Monthly!$C$55:$BJ$55,($R$2-1)*12+4) -> -3903.6108 | L19: =INDEX(Monthly!$C$55:$BJ$55,($R$2-1)*12+5) -> -2508.8288 | M19: =INDEX(Monthly!$C$55:$BJ$55,($R$2-1)*12+6) -> -1114.0468 | N19: =INDEX(Monthly!$C$55:$BJ$55,($R$2-1)*12+7) -> 280.73519 | O19: =INDEX(Monthly!$C$55:$BJ$55,($R$2-1)*12+8) -> 291.98519 | P19: =INDEX(Monthly!$C$55:$BJ$55,($R$2-1)*12+9) -> 303.23519 | Q19: =INDEX(Monthly!$C$55:$BJ$55,($R$2-1)*12+10) -> 314.48519 | R19: =INDEX(Monthly!$C$55:$BJ$55,($R$2-1)*12+11) -> 325.73519 | S19: =INDEX(Monthly!$C$55:$BJ$55,($R$2-1)*12+12) -> -3935.6868
A20: Net margin | B20: ='P&L'!B27 -> -0.12573979 | C20: ='P&L'!C27 -> -0.0036990563 | D20: ='P&L'!D27 -> 0.02131175 | E20: ='P&L'!E27 -> 0.045043982 | F20: ='P&L'!F27 -> 0.058101498 | H20: =IF(H7=0,0,H19/H7) -> -0.9701102 | I20: =IF(I7=0,0,I19/I7) -> -0.74807166 | J20: =IF(J7=0,0,J19/J7) -> -0.28158975 | K20: =IF(K7=0,0,K19/K7) -> -0.18441094 | L20: =IF(L7=0,0,L19/L7) -> -0.10666789 | M20: =IF(M7=0,0,M19/M7) -> -0.043059942 | N20: =IF(N7=0,0,N19/N7) -> 0.0099466833 | O20: =IF(O7=0,0,O19/O7) -> 0.01034528 | ... S20: =IF(S7=0,0,S19/S7) -> -0.18892506
A22: Cash flow ($'000) — by year | H22: ="Cash flow ($'000) — Year "&$R$2&", by month" -> Cash flow ($'000) — Year 1, by month
B23: 1 | C23: 2 | D23: 3 | E23: 4 | F23: 5 | H23: =INDEX(Monthly!$C$4:$BJ$4,($R$2-1)*12+1) -> 1 | I23: =INDEX(Monthly!$C$4:$BJ$4,($R$2-1)*12+2) -> 2 | J23: =INDEX(Monthly!$C$4:$BJ$4,($R$2-1)*12+3) -> 3 | K23: =INDEX(Monthly!$C$4:$BJ$4,($R$2-1)*12+4) -> 4 | L23: =INDEX(Monthly!$C$4:$BJ$4,($R$2-1)*12+5) -> 5 | M23: =INDEX(Monthly!$C$4:$BJ$4,($R$2-1)*12+6) -> 6 | N23: =INDEX(Monthly!$C$4:$BJ$4,($R$2-1)*12+7) -> 7 | O23: =INDEX(Monthly!$C$4:$BJ$4,($R$2-1)*12+8) -> 8 | P23: =INDEX(Monthly!$C$4:$BJ$4,($R$2-1)*12+9) -> 9 | Q23: =INDEX(Monthly!$C$4:$BJ$4,($R$2-1)*12+10) -> 10 | R23: =INDEX(Monthly!$C$4:$BJ$4,($R$2-1)*12+11) -> 11 | S23: =INDEX(Monthly!$C$4:$BJ$4,($R$2-1)*12+12) -> 12
A24: Operating cash flow | B24: ='Cash Flow'!B10 -> -15659.701 | C24: ='Cash Flow'!C10 -> 18765.734 | D24: ='Cash Flow'!D10 -> 28004.382 | E24: ='Cash Flow'!E10 -> 37902.51 | F24: ='Cash Flow'!F10 -> 44662.997 | H24: =INDEX(Monthly!$C$83:$BJ$83,($R$2-1)*12+1) -> -8928.9915 | I24: =INDEX(Monthly!$C$83:$BJ$83,($R$2-1)*12+2) -> -7525.5731 | J24: =INDEX(Monthly!$C$83:$BJ$83,($R$2-1)*12+3) -> -3969.1922 | K24: =INDEX(Monthly!$C$83:$BJ$83,($R$2-1)*12+4) -> -2368.0913 | L24: =INDEX(Monthly!$C$83:$BJ$83,($R$2-1)*12+5) -> -973.30927 | M24: =INDEX(Monthly!$C$83:$BJ$83,($R$2-1)*12+6) -> 421.47273 | N24: =INDEX(Monthly!$C$83:$BJ$83,($R$2-1)*12+7) -> 1816.2547 | O24: =INDEX(Monthly!$C$83:$BJ$83,($R$2-1)*12+8) -> 1934.8423 | P24: =INDEX(Monthly!$C$83:$BJ$83,($R$2-1)*12+9) -> 1946.0923 | Q24: =INDEX(Monthly!$C$83:$BJ$83,($R$2-1)*12+10) -> 1957.3423 | R24: =INDEX(Monthly!$C$83:$BJ$83,($R$2-1)*12+11) -> 1968.5923 | S24: =INDEX(Monthly!$C$83:$BJ$83,($R$2-1)*12+12) -> -1939.1401
A25: Capital spending | B25: ='Cash Flow'!B11 -> -138000 | C25: ='Cash Flow'!C11 -> -2500 | D25: ='Cash Flow'!D11 -> -2500 | E25: ='Cash Flow'!E11 -> -2500 | F25: ='Cash Flow'!F11 -> -2500 | H25: =INDEX(Monthly!$C$84:$BJ$84,($R$2-1)*12+1) -> -138000 | I25: =INDEX(Monthly!$C$84:$BJ$84,($R$2-1)*12+2) -> 0 | J25: =INDEX(Monthly!$C$84:$BJ$84,($R$2-1)*12+3) -> 0 | K25: =INDEX(Monthly!$C$84:$BJ$84,($R$2-1)*12+4) -> 0 | L25: =INDEX(Monthly!$C$84:$BJ$84,($R$2-1)*12+5) -> 0 | M25: =INDEX(Monthly!$C$84:$BJ$84,($R$2-1)*12+6) -> 0 | N25: =INDEX(Monthly!$C$84:$BJ$84,($R$2-1)*12+7) -> 0 | O25: =INDEX(Monthly!$C$84:$BJ$84,($R$2-1)*12+8) -> 0 | P25: =INDEX(Monthly!$C$84:$BJ$84,($R$2-1)*12+9) -> 0 | Q25: =INDEX(Monthly!$C$84:$BJ$84,($R$2-1)*12+10) -> 0 | R25: =INDEX(Monthly!$C$84:$BJ$84,($R$2-1)*12+11) -> 0 | S25: =INDEX(Monthly!$C$84:$BJ$84,($R$2-1)*12+12) -> 0
A26: Equity raised | B26: ='Cash Flow'!B12 -> 100000 | C26: ='Cash Flow'!C12 -> 0 | D26: ='Cash Flow'!D12 -> 0 | E26: ='Cash Flow'!E12 -> 0 | F26: ='Cash Flow'!F12 -> 0 | H26: =INDEX(Monthly!$C$85:$BJ$85,($R$2-1)*12+1) -> 100000 | I26: =INDEX(Monthly!$C$85:$BJ$85,($R$2-1)*12+2) -> 0 | J26: =INDEX(Monthly!$C$85:$BJ$85,($R$2-1)*12+3) -> 0 | K26: =INDEX(Monthly!$C$85:$BJ$85,($R$2-1)*12+4) -> 0 | L26: =INDEX(Monthly!$C$85:$BJ$85,($R$2-1)*12+5) -> 0 | M26: =INDEX(Monthly!$C$85:$BJ$85,($R$2-1)*12+6) -> 0 | N26: =INDEX(Monthly!$C$85:$BJ$85,($R$2-1)*12+7) -> 0 | O26: =INDEX(Monthly!$C$85:$BJ$85,($R$2-1)*12+8) -> 0 | P26: =INDEX(Monthly!$C$85:$BJ$85,($R$2-1)*12+9) -> 0 | Q26: =INDEX(Monthly!$C$85:$BJ$85,($R$2-1)*12+10) -> 0 | R26: =INDEX(Monthly!$C$85:$BJ$85,($R$2-1)*12+11) -> 0 | S26: =INDEX(Monthly!$C$85:$BJ$85,($R$2-1)*12+12) -> 0
A27: Loan drawdown | B27: ='Cash Flow'!B13 -> 90000 | C27: ='Cash Flow'!C13 -> 0 | D27: ='Cash Flow'!D13 -> 0 | E27: ='Cash Flow'!E13 -> 0 | F27: ='Cash Flow'!F13 -> 0 | H27: =INDEX(Monthly!$C$70:$BJ$70,($R$2-1)*12+1) -> 90000 | I27: =INDEX(Monthly!$C$70:$BJ$70,($R$2-1)*12+2) -> 0 | J27: =INDEX(Monthly!$C$70:$BJ$70,($R$2-1)*12+3) -> 0 | K27: =INDEX(Monthly!$C$70:$BJ$70,($R$2-1)*12+4) -> 0 | L27: =INDEX(Monthly!$C$70:$BJ$70,($R$2-1)*12+5) -> 0 | M27: =INDEX(Monthly!$C$70:$BJ$70,($R$2-1)*12+6) -> 0 | N27: =INDEX(Monthly!$C$70:$BJ$70,($R$2-1)*12+7) -> 0 | O27: =INDEX(Monthly!$C$70:$BJ$70,($R$2-1)*12+8) -> 0 | P27: =INDEX(Monthly!$C$70:$BJ$70,($R$2-1)*12+9) -> 0 | Q27: =INDEX(Monthly!$C$70:$BJ$70,($R$2-1)*12+10) -> 0 | R27: =INDEX(Monthly!$C$70:$BJ$70,($R$2-1)*12+11) -> 0 | S27: =INDEX(Monthly!$C$70:$BJ$70,($R$2-1)*12+12) -> 0
A28: Loan repayment | B28: ='Cash Flow'!B14 -> -16500 | C28: ='Cash Flow'!C14 -> -18000 | D28: ='Cash Flow'!D14 -> -18000 | E28: ='Cash Flow'!E14 -> -18000 | F28: ='Cash Flow'!F14 -> -18000 | H28: =INDEX(Monthly!$C$71:$BJ$71,($R$2-1)*12+1) -> 0 | I28: =INDEX(Monthly!$C$71:$BJ$71,($R$2-1)*12+2) -> -1500 | J28: =INDEX(Monthly!$C$71:$BJ$71,($R$2-1)*12+3) -> -1500 | K28: =INDEX(Monthly!$C$71:$BJ$71,($R$2-1)*12+4) -> -1500 | L28: =INDEX(Monthly!$C$71:$BJ$71,($R$2-1)*12+5) -> -1500 | M28: =INDEX(Monthly!$C$71:$BJ$71,($R$2-1)*12+6) -> -1500 | N28: =INDEX(Monthly!$C$71:$BJ$71,($R$2-1)*12+7) -> -1500 | O28: =INDEX(Monthly!$C$71:$BJ$71,($R$2-1)*12+8) -> -1500 | P28: =INDEX(Monthly!$C$71:$BJ$71,($R$2-1)*12+9) -> -1500 | Q28: =INDEX(Monthly!$C$71:$BJ$71,($R$2-1)*12+10) -> -1500 | R28: =INDEX(Monthly!$C$71:$BJ$71,($R$2-1)*12+11) -> -1500 | S28: =INDEX(Monthly!$C$71:$BJ$71,($R$2-1)*12+12) -> -1500
A29: Financing cash flow | B29: ='Cash Flow'!B15 -> 173500 | C29: ='Cash Flow'!C15 -> -18000 | D29: ='Cash Flow'!D15 -> -18000 | E29: ='Cash Flow'!E15 -> -18000 | F29: ='Cash Flow'!F15 -> -18000 | H29: =INDEX(Monthly!$C$86:$BJ$86,($R$2-1)*12+1) -> 190000 | I29: =INDEX(Monthly!$C$86:$BJ$86,($R$2-1)*12+2) -> -1500 | J29: =INDEX(Monthly!$C$86:$BJ$86,($R$2-1)*12+3) -> -1500 | K29: =INDEX(Monthly!$C$86:$BJ$86,($R$2-1)*12+4) -> -1500 | L29: =INDEX(Monthly!$C$86:$BJ$86,($R$2-1)*12+5) -> -1500 | M29: =INDEX(Monthly!$C$86:$BJ$86,($R$2-1)*12+6) -> -1500 | N29: =INDEX(Monthly!$C$86:$BJ$86,($R$2-1)*12+7) -> -1500 | O29: =INDEX(Monthly!$C$86:$BJ$86,($R$2-1)*12+8) -> -1500 | P29: =INDEX(Monthly!$C$86:$BJ$86,($R$2-1)*12+9) -> -1500 | Q29: =INDEX(Monthly!$C$86:$BJ$86,($R$2-1)*12+10) -> -1500 | R29: =INDEX(Monthly!$C$86:$BJ$86,($R$2-1)*12+11) -> -1500 | S29: =INDEX(Monthly!$C$86:$BJ$86,($R$2-1)*12+12) -> -1500
A30: Net change in cash | B30: ='Cash Flow'!B16 -> 19840.299 | C30: ='Cash Flow'!C16 -> -1734.2661 | D30: ='Cash Flow'!D16 -> 7504.3816 | E30: ='Cash Flow'!E16 -> 17402.51 | F30: ='Cash Flow'!F16 -> 24162.997 | H30: =INDEX(Monthly!$C$87:$BJ$87,($R$2-1)*12+1) -> 43071.009 | I30: =INDEX(Monthly!$C$87:$BJ$87,($R$2-1)*12+2) -> -9025.5731 | J30: =INDEX(Monthly!$C$87:$BJ$87,($R$2-1)*12+3) -> -5469.1922 | K30: =INDEX(Monthly!$C$87:$BJ$87,($R$2-1)*12+4) -> -3868.0913 | L30: =INDEX(Monthly!$C$87:$BJ$87,($R$2-1)*12+5) -> -2473.3093 | M30: =INDEX(Monthly!$C$87:$BJ$87,($R$2-1)*12+6) -> -1078.5273 | N30: =INDEX(Monthly!$C$87:$BJ$87,($R$2-1)*12+7) -> 316.25473 | O30: =INDEX(Monthly!$C$87:$BJ$87,($R$2-1)*12+8) -> 434.84233 | P30: =INDEX(Monthly!$C$87:$BJ$87,($R$2-1)*12+9) -> 446.09233 | Q30: =INDEX(Monthly!$C$87:$BJ$87,($R$2-1)*12+10) -> 457.34233 | R30: =INDEX(Monthly!$C$87:$BJ$87,($R$2-1)*12+11) -> 468.59233 | S30: =INDEX(Monthly!$C$87:$BJ$87,($R$2-1)*12+12) -> -3439.1401
A31: Closing cash | B31: ='Cash Flow'!B18 -> 19840.299 | C31: ='Cash Flow'!C18 -> 18106.033 | D31: ='Cash Flow'!D18 -> 25610.415 | E31: ='Cash Flow'!E18 -> 43012.925 | F31: ='Cash Flow'!F18 -> 67175.922 | H31: =INDEX(Monthly!$C$89:$BJ$89,($R$2-1)*12+1) -> 43071.009 | I31: =INDEX(Monthly!$C$89:$BJ$89,($R$2-1)*12+2) -> 34045.435 | J31: =INDEX(Monthly!$C$89:$BJ$89,($R$2-1)*12+3) -> 28576.243 | K31: =INDEX(Monthly!$C$89:$BJ$89,($R$2-1)*12+4) -> 24708.152 | L31: =INDEX(Monthly!$C$89:$BJ$89,($R$2-1)*12+5) -> 22234.843 | M31: =INDEX(Monthly!$C$89:$BJ$89,($R$2-1)*12+6) -> 21156.315 | N31: =INDEX(Monthly!$C$89:$BJ$89,($R$2-1)*12+7) -> 21472.57 | O31: =INDEX(Monthly!$C$89:$BJ$89,($R$2-1)*12+8) -> 21907.412 | P31: =INDEX(Monthly!$C$89:$BJ$89,($R$2-1)*12+9) -> 22353.505 | Q31: =INDEX(Monthly!$C$89:$BJ$89,($R$2-1)*12+10) -> 22810.847 | R31: =INDEX(Monthly!$C$89:$BJ$89,($R$2-1)*12+11) -> 23279.439 | S31: =INDEX(Monthly!$C$89:$BJ$89,($R$2-1)*12+12) -> 19840.299
A39: Balance sheet at year end ($'000) | H39: ="Balance sheet at month end ($'000) — Year "&$R$2 -> Balance sheet at month end ($'000) — Year 1
B40: 1 | C40: 2 | D40: 3 | E40: 4 | F40: 5 | H40: =INDEX(Monthly!$C$4:$BJ$4,($R$2-1)*12+1) -> 1 | I40: =INDEX(Monthly!$C$4:$BJ$4,($R$2-1)*12+2) -> 2 | J40: =INDEX(Monthly!$C$4:$BJ$4,($R$2-1)*12+3) -> 3 | K40: =INDEX(Monthly!$C$4:$BJ$4,($R$2-1)*12+4) -> 4 | L40: =INDEX(Monthly!$C$4:$BJ$4,($R$2-1)*12+5) -> 5 | M40: =INDEX(Monthly!$C$4:$BJ$4,($R$2-1)*12+6) -> 6 | N40: =INDEX(Monthly!$C$4:$BJ$4,($R$2-1)*12+7) -> 7 | O40: =INDEX(Monthly!$C$4:$BJ$4,($R$2-1)*12+8) -> 8 | P40: =INDEX(Monthly!$C$4:$BJ$4,($R$2-1)*12+9) -> 9 | Q40: =INDEX(Monthly!$C$4:$BJ$4,($R$2-1)*12+10) -> 10 | R40: =INDEX(Monthly!$C$4:$BJ$4,($R$2-1)*12+11) -> 11 | S40: =INDEX(Monthly!$C$4:$BJ$4,($R$2-1)*12+12) -> 12
A41: Cash | B41: ='Balance Sheet'!B5 -> 19840.299 | C41: ='Balance Sheet'!C5 -> 18106.033 | D41: ='Balance Sheet'!D5 -> 25610.415 | E41: ='Balance Sheet'!E5 -> 43012.925 | F41: ='Balance Sheet'!F5 -> 67175.922 | H41: =INDEX(Monthly!$C$89:$BJ$89,($R$2-1)*12+1) -> 43071.009 | I41: =INDEX(Monthly!$C$89:$BJ$89,($R$2-1)*12+2) -> 34045.435 | J41: =INDEX(Monthly!$C$89:$BJ$89,($R$2-1)*12+3) -> 28576.243 | K41: =INDEX(Monthly!$C$89:$BJ$89,($R$2-1)*12+4) -> 24708.152 | L41: =INDEX(Monthly!$C$89:$BJ$89,($R$2-1)*12+5) -> 22234.843 | M41: =INDEX(Monthly!$C$89:$BJ$89,($R$2-1)*12+6) -> 21156.315 | N41: =INDEX(Monthly!$C$89:$BJ$89,($R$2-1)*12+7) -> 21472.57 | O41: =INDEX(Monthly!$C$89:$BJ$89,($R$2-1)*12+8) -> 21907.412 | P41: =INDEX(Monthly!$C$89:$BJ$89,($R$2-1)*12+9) -> 22353.505 | Q41: =INDEX(Monthly!$C$89:$BJ$89,($R$2-1)*12+10) -> 22810.847 | R41: =INDEX(Monthly!$C$89:$BJ$89,($R$2-1)*12+11) -> 23279.439 | S41: =INDEX(Monthly!$C$89:$BJ$89,($R$2-1)*12+12) -> 19840.299
A42: Accounts receivable | B42: ='Balance Sheet'!B6 -> 2083.2 | C42: ='Balance Sheet'!C6 -> 2218.7189 | D42: ='Balance Sheet'!D6 -> 2363.196 | E42: ='Balance Sheet'!E6 -> 2517.2344 | F42: ='Balance Sheet'!F6 -> 2681.4785 | H42: =INDEX(Monthly!$C$75:$BJ$75,($R$2-1)*12+1) -> 1041.6 | I42: =INDEX(Monthly!$C$75:$BJ$75,($R$2-1)*12+2) -> 1215.2 | J42: =INDEX(Monthly!$C$75:$BJ$75,($R$2-1)*12+3) -> 1881.6 | K42: =INDEX(Monthly!$C$75:$BJ$75,($R$2-1)*12+4) -> 2116.8 | L42: =INDEX(Monthly!$C$75:$BJ$75,($R$2-1)*12+5) -> 2352 | M42: =INDEX(Monthly!$C$75:$BJ$75,($R$2-1)*12+6) -> 2587.2 | N42: =INDEX(Monthly!$C$75:$BJ$75,($R$2-1)*12+7) -> 2822.4 | O42: =INDEX(Monthly!$C$75:$BJ$75,($R$2-1)*12+8) -> 2822.4 | P42: =INDEX(Monthly!$C$75:$BJ$75,($R$2-1)*12+9) -> 2822.4 | Q42: =INDEX(Monthly!$C$75:$BJ$75,($R$2-1)*12+10) -> 2822.4 | R42: =INDEX(Monthly!$C$75:$BJ$75,($R$2-1)*12+11) -> 2822.4 | S42: =INDEX(Monthly!$C$75:$BJ$75,($R$2-1)*12+12) -> 2083.2
A43: Inventory | B43: ='Balance Sheet'!B7 -> 861.6288 | C43: ='Balance Sheet'!C7 -> 918.45024 | D43: ='Balance Sheet'!D7 -> 979.08649 | E43: ='Balance Sheet'!E7 -> 1043.7988 | F43: ='Balance Sheet'!F7 -> 1112.8665 | H43: =INDEX(Monthly!$C$76:$BJ$76,($R$2-1)*12+1) -> 430.8144 | I43: =INDEX(Monthly!$C$76:$BJ$76,($R$2-1)*12+2) -> 502.6168 | J43: =INDEX(Monthly!$C$76:$BJ$76,($R$2-1)*12+3) -> 767.1744 | K43: =INDEX(Monthly!$C$76:$BJ$76,($R$2-1)*12+4) -> 863.0712 | L43: =INDEX(Monthly!$C$76:$BJ$76,($R$2-1)*12+5) -> 958.968 | M43: =INDEX(Monthly!$C$76:$BJ$76,($R$2-1)*12+6) -> 1054.8648 | N43: =INDEX(Monthly!$C$76:$BJ$76,($R$2-1)*12+7) -> 1150.7616 | O43: =INDEX(Monthly!$C$76:$BJ$76,($R$2-1)*12+8) -> 1150.7616 | P43: =INDEX(Monthly!$C$76:$BJ$76,($R$2-1)*12+9) -> 1150.7616 | Q43: =INDEX(Monthly!$C$76:$BJ$76,($R$2-1)*12+10) -> 1150.7616 | R43: =INDEX(Monthly!$C$76:$BJ$76,($R$2-1)*12+11) -> 1150.7616 | S43: =INDEX(Monthly!$C$76:$BJ$76,($R$2-1)*12+12) -> 861.6288
A44: Net fixed assets | B44: ='Balance Sheet'!B8 -> 118285.71 | C44: ='Balance Sheet'!C8 -> 100714.29 | D44: ='Balance Sheet'!D8 -> 82785.714 | E44: ='Balance Sheet'!E8 -> 64500 | F44: ='Balance Sheet'!F8 -> 45857.143 | H44: =INDEX(Monthly!$C$66:$BJ$66,($R$2-1)*12+1) -> 136357.14 | I44: =INDEX(Monthly!$C$66:$BJ$66,($R$2-1)*12+2) -> 134714.29 | J44: =INDEX(Monthly!$C$66:$BJ$66,($R$2-1)*12+3) -> 133071.43 | K44: =INDEX(Monthly!$C$66:$BJ$66,($R$2-1)*12+4) -> 131428.57 | L44: =INDEX(Monthly!$C$66:$BJ$66,($R$2-1)*12+5) -> 129785.71 | M44: =INDEX(Monthly!$C$66:$BJ$66,($R$2-1)*12+6) -> 128142.86 | N44: =INDEX(Monthly!$C$66:$BJ$66,($R$2-1)*12+7) -> 126500 | O44: =INDEX(Monthly!$C$66:$BJ$66,($R$2-1)*12+8) -> 124857.14 | P44: =INDEX(Monthly!$C$66:$BJ$66,($R$2-1)*12+9) -> 123214.29 | Q44: =INDEX(Monthly!$C$66:$BJ$66,($R$2-1)*12+10) -> 121571.43 | R44: =INDEX(Monthly!$C$66:$BJ$66,($R$2-1)*12+11) -> 119928.57 | S44: =INDEX(Monthly!$C$66:$BJ$66,($R$2-1)*12+12) -> 118285.71
A45: Total assets | B45: ='Balance Sheet'!B9 -> 141070.84 | C45: ='Balance Sheet'!C9 -> 121957.49 | D45: ='Balance Sheet'!D9 -> 111738.41 | E45: ='Balance Sheet'!E9 -> 111073.96 | F45: ='Balance Sheet'!F9 -> 116827.41 | H45: =INDEX(Monthly!$C$103:$BJ$103,($R$2-1)*12+1) -> 180900.57 | I45: =INDEX(Monthly!$C$103:$BJ$103,($R$2-1)*12+2) -> 170477.54 | J45: =INDEX(Monthly!$C$103:$BJ$103,($R$2-1)*12+3) -> 164296.45 | K45: =INDEX(Monthly!$C$103:$BJ$103,($R$2-1)*12+4) -> 159116.59 | L45: =INDEX(Monthly!$C$103:$BJ$103,($R$2-1)*12+5) -> 155331.52 | M45: =INDEX(Monthly!$C$103:$BJ$103,($R$2-1)*12+6) -> 152941.24 | N45: =INDEX(Monthly!$C$103:$BJ$103,($R$2-1)*12+7) -> 151945.73 | O45: =INDEX(Monthly!$C$103:$BJ$103,($R$2-1)*12+8) -> 150737.72 | P45: =INDEX(Monthly!$C$103:$BJ$103,($R$2-1)*12+9) -> 149540.95 | Q45: =INDEX(Monthly!$C$103:$BJ$103,($R$2-1)*12+10) -> 148355.44 | R45: =INDEX(Monthly!$C$103:$BJ$103,($R$2-1)*12+11) -> 147181.17 | S45: =INDEX(Monthly!$C$103:$BJ$103,($R$2-1)*12+12) -> 141070.84
A46: Accounts payable | B46: ='Balance Sheet'!B10 -> 2010.4672 | C46: ='Balance Sheet'!C10 -> 2143.0506 | D46: ='Balance Sheet'!D10 -> 2284.5351 | E46: ='Balance Sheet'!E10 -> 2435.5304 | F46: ='Balance Sheet'!F10 -> 2596.6885 | H46: =INDEX(Monthly!$C$77:$BJ$77,($R$2-1)*12+1) -> 1005.2336 | I46: =INDEX(Monthly!$C$77:$BJ$77,($R$2-1)*12+2) -> 1172.7725 | J46: =INDEX(Monthly!$C$77:$BJ$77,($R$2-1)*12+3) -> 1790.0736 | K46: =INDEX(Monthly!$C$77:$BJ$77,($R$2-1)*12+4) -> 2013.8328 | L46: =INDEX(Monthly!$C$77:$BJ$77,($R$2-1)*12+5) -> 2237.592 | M46: =INDEX(Monthly!$C$77:$BJ$77,($R$2-1)*12+6) -> 2461.3512 | N46: =INDEX(Monthly!$C$77:$BJ$77,($R$2-1)*12+7) -> 2685.1104 | O46: =INDEX(Monthly!$C$77:$BJ$77,($R$2-1)*12+8) -> 2685.1104 | P46: =INDEX(Monthly!$C$77:$BJ$77,($R$2-1)*12+9) -> 2685.1104 | Q46: =INDEX(Monthly!$C$77:$BJ$77,($R$2-1)*12+10) -> 2685.1104 | R46: =INDEX(Monthly!$C$77:$BJ$77,($R$2-1)*12+11) -> 2685.1104 | S46: =INDEX(Monthly!$C$77:$BJ$77,($R$2-1)*12+12) -> 2010.4672
A47: Loan | B47: ='Balance Sheet'!B11 -> 73500 | C47: ='Balance Sheet'!C11 -> 55500 | D47: ='Balance Sheet'!D11 -> 37500 | E47: ='Balance Sheet'!E11 -> 19500 | F47: ='Balance Sheet'!F11 -> 1500 | H47: =INDEX(Monthly!$C$72:$BJ$72,($R$2-1)*12+1) -> 90000 | I47: =INDEX(Monthly!$C$72:$BJ$72,($R$2-1)*12+2) -> 88500 | J47: =INDEX(Monthly!$C$72:$BJ$72,($R$2-1)*12+3) -> 87000 | K47: =INDEX(Monthly!$C$72:$BJ$72,($R$2-1)*12+4) -> 85500 | L47: =INDEX(Monthly!$C$72:$BJ$72,($R$2-1)*12+5) -> 84000 | M47: =INDEX(Monthly!$C$72:$BJ$72,($R$2-1)*12+6) -> 82500 | N47: =INDEX(Monthly!$C$72:$BJ$72,($R$2-1)*12+7) -> 81000 | O47: =INDEX(Monthly!$C$72:$BJ$72,($R$2-1)*12+8) -> 79500 | P47: =INDEX(Monthly!$C$72:$BJ$72,($R$2-1)*12+9) -> 78000 | Q47: =INDEX(Monthly!$C$72:$BJ$72,($R$2-1)*12+10) -> 76500 | R47: =INDEX(Monthly!$C$72:$BJ$72,($R$2-1)*12+11) -> 75000 | S47: =INDEX(Monthly!$C$72:$BJ$72,($R$2-1)*12+12) -> 73500
A48: Total liabilities | B48: ='Balance Sheet'!B12 -> 75510.467 | C48: ='Balance Sheet'!C12 -> 57643.051 | D48: ='Balance Sheet'!D12 -> 39784.535 | E48: ='Balance Sheet'!E12 -> 21935.53 | F48: ='Balance Sheet'!F12 -> 4096.6885 | H48: =INDEX(Monthly!$C$104:$BJ$104,($R$2-1)*12+1) -> 91005.234 | I48: =INDEX(Monthly!$C$104:$BJ$104,($R$2-1)*12+2) -> 89672.773 | J48: =INDEX(Monthly!$C$104:$BJ$104,($R$2-1)*12+3) -> 88790.074 | K48: =INDEX(Monthly!$C$104:$BJ$104,($R$2-1)*12+4) -> 87513.833 | L48: =INDEX(Monthly!$C$104:$BJ$104,($R$2-1)*12+5) -> 86237.592 | M48: =INDEX(Monthly!$C$104:$BJ$104,($R$2-1)*12+6) -> 84961.351 | N48: =INDEX(Monthly!$C$104:$BJ$104,($R$2-1)*12+7) -> 83685.11 | O48: =INDEX(Monthly!$C$104:$BJ$104,($R$2-1)*12+8) -> 82185.11 | P48: =INDEX(Monthly!$C$104:$BJ$104,($R$2-1)*12+9) -> 80685.11 | Q48: =INDEX(Monthly!$C$104:$BJ$104,($R$2-1)*12+10) -> 79185.11 | R48: =INDEX(Monthly!$C$104:$BJ$104,($R$2-1)*12+11) -> 77685.11 | S48: =INDEX(Monthly!$C$104:$BJ$104,($R$2-1)*12+12) -> 75510.467
A49: Paid-in capital | B49: ='Balance Sheet'!B13 -> 100000 | C49: ='Balance Sheet'!C13 -> 100000 | D49: ='Balance Sheet'!D13 -> 100000 | E49: ='Balance Sheet'!E13 -> 100000 | F49: ='Balance Sheet'!F13 -> 100000 | H49: =INDEX(Monthly!$C$101:$BJ$101,($R$2-1)*12+1) -> 100000 | I49: =INDEX(Monthly!$C$101:$BJ$101,($R$2-1)*12+2) -> 100000 | J49: =INDEX(Monthly!$C$101:$BJ$101,($R$2-1)*12+3) -> 100000 | K49: =INDEX(Monthly!$C$101:$BJ$101,($R$2-1)*12+4) -> 100000 | L49: =INDEX(Monthly!$C$101:$BJ$101,($R$2-1)*12+5) -> 100000 | M49: =INDEX(Monthly!$C$101:$BJ$101,($R$2-1)*12+6) -> 100000 | N49: =INDEX(Monthly!$C$101:$BJ$101,($R$2-1)*12+7) -> 100000 | O49: =INDEX(Monthly!$C$101:$BJ$101,($R$2-1)*12+8) -> 100000 | P49: =INDEX(Monthly!$C$101:$BJ$101,($R$2-1)*12+9) -> 100000 | Q49: =INDEX(Monthly!$C$101:$BJ$101,($R$2-1)*12+10) -> 100000 | R49: =INDEX(Monthly!$C$101:$BJ$101,($R$2-1)*12+11) -> 100000 | S49: =INDEX(Monthly!$C$101:$BJ$101,($R$2-1)*12+12) -> 100000
A50: Retained earnings | B50: ='Balance Sheet'!B14 -> -34439.625 | C50: ='Balance Sheet'!C14 -> -35685.562 | D50: ='Balance Sheet'!D14 -> -28046.123 | E50: ='Balance Sheet'!E14 -> -10861.572 | F50: ='Balance Sheet'!F14 -> 12730.721 | H50: =INDEX(Monthly!$C$102:$BJ$102,($R$2-1)*12+1) -> -10104.668 | I50: =INDEX(Monthly!$C$102:$BJ$102,($R$2-1)*12+2) -> -19195.235 | J50: =INDEX(Monthly!$C$102:$BJ$102,($R$2-1)*12+3) -> -24493.627 | K50: =INDEX(Monthly!$C$102:$BJ$102,($R$2-1)*12+4) -> -28397.238 | L50: =INDEX(Monthly!$C$102:$BJ$102,($R$2-1)*12+5) -> -30906.067 | M50: =INDEX(Monthly!$C$102:$BJ$102,($R$2-1)*12+6) -> -32020.114 | N50: =INDEX(Monthly!$C$102:$BJ$102,($R$2-1)*12+7) -> -31739.379 | O50: =INDEX(Monthly!$C$102:$BJ$102,($R$2-1)*12+8) -> -31447.393 | P50: =INDEX(Monthly!$C$102:$BJ$102,($R$2-1)*12+9) -> -31144.158 | Q50: =INDEX(Monthly!$C$102:$BJ$102,($R$2-1)*12+10) -> -30829.673 | R50: =INDEX(Monthly!$C$102:$BJ$102,($R$2-1)*12+11) -> -30503.938 | S50: =INDEX(Monthly!$C$102:$BJ$102,($R$2-1)*12+12) -> -34439.625
A51: Total equity | B51: ='Balance Sheet'!B15 -> 65560.375 | C51: ='Balance Sheet'!C15 -> 64314.438 | D51: ='Balance Sheet'!D15 -> 71953.877 | E51: ='Balance Sheet'!E15 -> 89138.428 | F51: ='Balance Sheet'!F15 -> 112730.72 | H51: =INDEX(Monthly!$C$105:$BJ$105,($R$2-1)*12+1) -> 89895.332 | I51: =INDEX(Monthly!$C$105:$BJ$105,($R$2-1)*12+2) -> 80804.765 | J51: =INDEX(Monthly!$C$105:$BJ$105,($R$2-1)*12+3) -> 75506.373 | K51: =INDEX(Monthly!$C$105:$BJ$105,($R$2-1)*12+4) -> 71602.762 | L51: =INDEX(Monthly!$C$105:$BJ$105,($R$2-1)*12+5) -> 69093.933 | M51: =INDEX(Monthly!$C$105:$BJ$105,($R$2-1)*12+6) -> 67979.886 | N51: =INDEX(Monthly!$C$105:$BJ$105,($R$2-1)*12+7) -> 68260.621 | O51: =INDEX(Monthly!$C$105:$BJ$105,($R$2-1)*12+8) -> 68552.607 | P51: =INDEX(Monthly!$C$105:$BJ$105,($R$2-1)*12+9) -> 68855.842 | Q51: =INDEX(Monthly!$C$105:$BJ$105,($R$2-1)*12+10) -> 69170.327 | R51: =INDEX(Monthly!$C$105:$BJ$105,($R$2-1)*12+11) -> 69496.062 | S51: =INDEX(Monthly!$C$105:$BJ$105,($R$2-1)*12+12) -> 65560.375
A52: Total liabilities & equity | B52: ='Balance Sheet'!B16 -> 141070.84 | C52: ='Balance Sheet'!C16 -> 121957.49 | D52: ='Balance Sheet'!D16 -> 111738.41 | E52: ='Balance Sheet'!E16 -> 111073.96 | F52: ='Balance Sheet'!F16 -> 116827.41 | H52: =INDEX(Monthly!$C$106:$BJ$106,($R$2-1)*12+1) -> 180900.57 | I52: =INDEX(Monthly!$C$106:$BJ$106,($R$2-1)*12+2) -> 170477.54 | J52: =INDEX(Monthly!$C$106:$BJ$106,($R$2-1)*12+3) -> 164296.45 | K52: =INDEX(Monthly!$C$106:$BJ$106,($R$2-1)*12+4) -> 159116.59 | L52: =INDEX(Monthly!$C$106:$BJ$106,($R$2-1)*12+5) -> 155331.52 | M52: =INDEX(Monthly!$C$106:$BJ$106,($R$2-1)*12+6) -> 152941.24 | N52: =INDEX(Monthly!$C$106:$BJ$106,($R$2-1)*12+7) -> 151945.73 | O52: =INDEX(Monthly!$C$106:$BJ$106,($R$2-1)*12+8) -> 150737.72 | P52: =INDEX(Monthly!$C$106:$BJ$106,($R$2-1)*12+9) -> 149540.95 | Q52: =INDEX(Monthly!$C$106:$BJ$106,($R$2-1)*12+10) -> 148355.44 | R52: =INDEX(Monthly!$C$106:$BJ$106,($R$2-1)*12+11) -> 147181.17 | S52: =INDEX(Monthly!$C$106:$BJ$106,($R$2-1)*12+12) -> 141070.84

Sheet Scenarios
A1: Scenarios — Low / Base / High | H1: =HYPERLINK("#'Cover'!A1","◂ Contents") -> ◂ Contents
A2: All three scenarios calculated side by side, live: change any input and every column updates. Active = the scenario chosen on the Dashboard.
A5: Key drivers
A6: Driver | B6: Low | C6: Base | D6: High | E6: Active
A7: Street service days per truck per month (year average) (days) | B7: =Inputs!$B$9 -> 17 | C7: =Inputs!$C$9 -> 18 | D7: =Inputs!$D$9 -> 19 | E7: =Inputs!$E$9 -> 18
A8: Meals per street service day at maturity (year 1) (meals) | B8: =Inputs!$B$17 -> 78 | C8: =Inputs!$C$17 -> 88 | D8: =Inputs!$D$17 -> 98 | E8: =Inputs!$E$17 -> 88
A9: Average ticket per meal (year 1) ($) | B9: =Inputs!$B$19 -> 13 | C9: =Inputs!$C$19 -> 14 | D9: =Inputs!$D$19 -> 15 | E9: =Inputs!$E$19 -> 14
A10: Event and catering days per truck per month (year 1) (days) | B10: =Inputs!$B$23 -> 2.5 | C10: =Inputs!$C$23 -> 3 | D10: =Inputs!$D$23 -> 3.5 | E10: =Inputs!$E$23 -> 3
A11: Food cost, % of sales (%) | B11: =Inputs!$B$29 -> 0.345 | C11: =Inputs!$C$29 -> 0.33 | D11: =Inputs!$D$29 -> 0.315 | E11: =Inputs!$E$29 -> 0.33
A12: Truck purchase, each ($) | B12: =Inputs!$B$49 -> 95000 | C12: =Inputs!$C$49 -> 95000 | D12: =Inputs!$D$49 -> 95000 | E12: =Inputs!$E$49 -> 95000
A13: Equity raised at start ($) | B13: =Inputs!$B$71 -> 100000 | C13: =Inputs!$C$71 -> 100000 | D13: =Inputs!$D$71 -> 100000 | E13: =Inputs!$E$71 -> 100000
A15: Results by scenario ($'000)
A16: Output | B16: Low | C16: Base | D16: High | E16: Active
A17: Revenue — final year | B17: =F30 -> 264498.79 | C17: =F31 -> 406053.09 | D17: =F32 -> 588090.22 | E17: ='P&L'!F5 -> 406053.09
A18: Revenue — whole plan | B18: =SUM(B30:F30) -> 1208322.1 | C18: =SUM(B31:F31) -> 1756742.3 | D18: =SUM(B32:F32) -> 2417583.7 | E18: =SUM('P&L'!$B$5:$F$5) -> 1756742.3
A19: EBITDA — final year | B19: =F36 -> -48078.489 | C19: =F37 -> 49525.516 | D19: =F38 -> 178096.69 | E19: ='P&L'!F19 -> 49525.516
A20: EBITDA margin — final year | B20: =IF(B17=0,0,B19/B17) -> -0.18177205 | C20: =IF(C17=0,0,C19/C17) -> 0.12196808 | D20: =IF(D17=0,0,D19/D17) -> 0.30283905 | E20: =IF(E17=0,0,E19/E17) -> 0.12196808
A21: Net income — final year | B21: =F42 -> -70166.346 | C21: =F43 -> 23592.293 | D21: =F44 -> 123246.97 | E21: ='P&L'!F26 -> 23592.293
A22: Net income — whole plan | B22: =SUM(B42:F42) -> -367104.45 | C22: =SUM(B43:F43) -> 12730.721 | D22: =SUM(B44:F44) -> 390953.02 | E22: =SUM('P&L'!$B$26:$F$26) -> 12730.721
A23: Cash at the end of the plan | B23: =F48 -> -312120.36 | C23: =F49 -> 67175.922 | D23: =F50 -> 444596.24 | E23: ='Balance Sheet'!F5 -> 67175.922
A24: Lowest cash balance | B24: =MIN('Scenario calc'!$C$91:$BJ$91) -> -312120.36 | C24: =MIN('Scenario calc'!$C$211:$BJ$211) -> 9872.4151 | D24: =MIN('Scenario calc'!$C$331:$BJ$331) -> 43192.085 | E24: ='Break-even'!B18 -> 9872.4151
A25: Lowest cash point (month #) | B25: =MATCH(MIN('Scenario calc'!$C$91:$BJ$91),'Scenario calc'!$C$91:$BJ$91,0) -> 60 | C25: =MATCH(MIN('Scenario calc'!$C$211:$BJ$211),'Scenario calc'!$C$211:$BJ$211,0) -> 26 | D25: =MATCH(MIN('Scenario calc'!$C$331:$BJ$331),'Scenario calc'!$C$331:$BJ$331,0) -> 2 | E25: ='Break-even'!B6 -> 26
A26: Funding required (incl. cash buffer) | B26: =SUMPRODUCT(--('Scenario calc'!$C$6:$BJ$6<=B25),'Scenario calc'!$C$64:$BJ$64)-SUMPRODUCT(--('Scenario calc'!$C$6:$BJ$6<=B25),'Scenario calc'!$C$85:$BJ$85)-SUMPRODUCT(--('Scenario calc'!$C$6:$BJ$6<=B25),'Scenario calc'!$C$73:$BJ$73)+Inputs!$B$86 -> 544120.36 | C26: =SUMPRODUCT(--('Scenario calc'!$C$126:$BJ$126<=C25),'Scenario calc'!$C$184:$BJ$184)-SUMPRODUCT(--('Scenario calc'!$C$126:$BJ$126<=C25),'Scenario calc'!$C$205:$BJ$205)-SUMPRODUCT(--('Scenario calc'!$C$126:$BJ$126<=C25),'Scenario calc'!$C$193:$BJ$193)+Inputs!$C$86 -> 222127.58 | D26: =SUMPRODUCT(--('Scenario calc'!$C$246:$BJ$246<=D25),'Scenario calc'!$C$304:$BJ$304)-SUMPRODUCT(--('Scenario calc'!$C$246:$BJ$246<=D25),'Scenario calc'!$C$325:$BJ$325)-SUMPRODUCT(--('Scenario calc'!$C$246:$BJ$246<=D25),'Scenario calc'!$C$313:$BJ$313)+Inputs!$D$86 -> 188807.91 | E26: ='Break-even'!B12 -> 222127.58
A28: Revenue by year ($'000)
A29: Scenario | B29: 1 | C29: 2 | D29: 3 | E29: 4 | F29: 5
A30: Low | B30: =SUMIF('Scenario calc'!$C$7:$BJ$7,B$29,'Scenario calc'!$C$26:$BJ$26) -> 181039.67 | C30: =SUMIF('Scenario calc'!$C$7:$BJ$7,C$29,'Scenario calc'!$C$26:$BJ$26) -> 249243.12 | D30: =SUMIF('Scenario calc'!$C$7:$BJ$7,D$29,'Scenario calc'!$C$26:$BJ$26) -> 254227.98 | E30: =SUMIF('Scenario calc'!$C$7:$BJ$7,E$29,'Scenario calc'!$C$26:$BJ$26) -> 259312.54 | F30: =SUMIF('Scenario calc'!$C$7:$BJ$7,F$29,'Scenario calc'!$C$26:$BJ$26) -> 264498.79
A31: Base | B31: =SUMIF('Scenario calc'!$C$127:$BJ$127,B$29,'Scenario calc'!$C$146:$BJ$146) -> 273896 | C31: =SUMIF('Scenario calc'!$C$127:$BJ$127,C$29,'Scenario calc'!$C$146:$BJ$146) -> 336825.82 | D31: =SUMIF('Scenario calc'!$C$127:$BJ$127,D$29,'Scenario calc'!$C$146:$BJ$146) -> 358461.37 | E31: =SUMIF('Scenario calc'!$C$127:$BJ$127,E$29,'Scenario calc'!$C$146:$BJ$146) -> 381506.04 | F31: =SUMIF('Scenario calc'!$C$127:$BJ$127,F$29,'Scenario calc'!$C$146:$BJ$146) -> 406053.09
A32: High | B32: =SUMIF('Scenario calc'!$C$247:$BJ$247,B$29,'Scenario calc'!$C$266:$BJ$266) -> 370256.6 | C32: =SUMIF('Scenario calc'!$C$247:$BJ$247,C$29,'Scenario calc'!$C$266:$BJ$266) -> 440469.12 | D32: =SUMIF('Scenario calc'!$C$247:$BJ$247,D$29,'Scenario calc'!$C$266:$BJ$266) -> 484864.95 | E32: =SUMIF('Scenario calc'!$C$247:$BJ$247,E$29,'Scenario calc'!$C$266:$BJ$266) -> 533902.86 | F32: =SUMIF('Scenario calc'!$C$247:$BJ$247,F$29,'Scenario calc'!$C$266:$BJ$266) -> 588090.22
A34: EBITDA by year ($'000)
A35: Scenario | B35: 1 | C35: 2 | D35: 3 | E35: 4 | F35: 5
A36: Low | B36: =SUMIF('Scenario calc'!$C$7:$BJ$7,B$35,'Scenario calc'!$C$48:$BJ$48) -> -70979.563 | C36: =SUMIF('Scenario calc'!$C$7:$BJ$7,C$35,'Scenario calc'!$C$48:$BJ$48) -> -38601.113 | D36: =SUMIF('Scenario calc'!$C$7:$BJ$7,D$35,'Scenario calc'!$C$48:$BJ$48) -> -41612.953 | E36: =SUMIF('Scenario calc'!$C$7:$BJ$7,E$35,'Scenario calc'!$C$48:$BJ$48) -> -44770.097 | F36: =SUMIF('Scenario calc'!$C$7:$BJ$7,F$35,'Scenario calc'!$C$48:$BJ$48) -> -48078.489
A37: Base | B37: =SUMIF('Scenario calc'!$C$127:$BJ$127,B$35,'Scenario calc'!$C$168:$BJ$168) -> -7305.964 | C37: =SUMIF('Scenario calc'!$C$127:$BJ$127,C$35,'Scenario calc'!$C$168:$BJ$168) -> 24630.491 | D37: =SUMIF('Scenario calc'!$C$127:$BJ$127,D$35,'Scenario calc'!$C$168:$BJ$168) -> 32253.01 | E37: =SUMIF('Scenario calc'!$C$127:$BJ$127,E$35,'Scenario calc'!$C$168:$BJ$168) -> 40535.265 | F37: =SUMIF('Scenario calc'!$C$127:$BJ$127,F$35,'Scenario calc'!$C$168:$BJ$168) -> 49525.516
A38: High | B38: =SUMIF('Scenario calc'!$C$247:$BJ$247,B$35,'Scenario calc'!$C$288:$BJ$288) -> 63466.417 | C38: =SUMIF('Scenario calc'!$C$247:$BJ$247,C$35,'Scenario calc'!$C$288:$BJ$288) -> 101989.4 | D38: =SUMIF('Scenario calc'!$C$247:$BJ$247,D$35,'Scenario calc'!$C$288:$BJ$288) -> 124559.56 | E38: =SUMIF('Scenario calc'!$C$247:$BJ$247,E$35,'Scenario calc'!$C$288:$BJ$288) -> 149827.42 | F38: =SUMIF('Scenario calc'!$C$247:$BJ$247,F$35,'Scenario calc'!$C$288:$BJ$288) -> 178096.69
A40: Net income by year ($'000)
A41: Scenario | B41: 1 | C41: 2 | D41: 3 | E41: 4 | F41: 5
A42: Low | B42: =SUMIF('Scenario calc'!$C$7:$BJ$7,B$41,'Scenario calc'!$C$57:$BJ$57) -> -98113.224 | C42: =SUMIF('Scenario calc'!$C$7:$BJ$7,C$41,'Scenario calc'!$C$57:$BJ$57) -> -64477.542 | D42: =SUMIF('Scenario calc'!$C$7:$BJ$7,D$41,'Scenario calc'!$C$57:$BJ$57) -> -66226.524 | E42: =SUMIF('Scenario calc'!$C$7:$BJ$7,E$41,'Scenario calc'!$C$57:$BJ$57) -> -68120.812 | F42: =SUMIF('Scenario calc'!$C$7:$BJ$7,F$41,'Scenario calc'!$C$57:$BJ$57) -> -70166.346
A43: Base | B43: =SUMIF('Scenario calc'!$C$127:$BJ$127,B$41,'Scenario calc'!$C$177:$BJ$177) -> -34439.625 | C43: =SUMIF('Scenario calc'!$C$127:$BJ$127,C$41,'Scenario calc'!$C$177:$BJ$177) -> -1245.9377 | D43: =SUMIF('Scenario calc'!$C$127:$BJ$127,D$41,'Scenario calc'!$C$177:$BJ$177) -> 7639.439 | E43: =SUMIF('Scenario calc'!$C$127:$BJ$127,E$41,'Scenario calc'!$C$177:$BJ$177) -> 17184.551 | F43: =SUMIF('Scenario calc'!$C$127:$BJ$127,F$41,'Scenario calc'!$C$177:$BJ$177) -> 23592.293
A44: High | B44: =SUMIF('Scenario calc'!$C$247:$BJ$247,B$41,'Scenario calc'!$C$297:$BJ$297) -> 28702.877 | C44: =SUMIF('Scenario calc'!$C$247:$BJ$247,C$41,'Scenario calc'!$C$297:$BJ$297) -> 60129.245 | D44: =SUMIF('Scenario calc'!$C$247:$BJ$247,D$41,'Scenario calc'!$C$297:$BJ$297) -> 78957.328 | E44: =SUMIF('Scenario calc'!$C$247:$BJ$247,E$41,'Scenario calc'!$C$297:$BJ$297) -> 99916.598 | F44: =SUMIF('Scenario calc'!$C$247:$BJ$247,F$41,'Scenario calc'!$C$297:$BJ$297) -> 123246.97
A46: Cash at year end by year ($'000)
A47: Scenario | B47: 1 | C47: 2 | D47: 3 | E47: 4 | F47: 5
A48: Low | B48: =INDEX('Scenario calc'!$C$91:$BJ$91,B$47*12) -> -43517.112 | C48: =INDEX('Scenario calc'!$C$91:$BJ$91,C$47*12) -> -108433.22 | D48: =INDEX('Scenario calc'!$C$91:$BJ$91,D$47*12) -> -174741.27 | E48: =INDEX('Scenario calc'!$C$91:$BJ$91,E$47*12) -> -242586.57 | F48: =INDEX('Scenario calc'!$C$91:$BJ$91,F$47*12) -> -312120.36
A49: Base | B49: =INDEX('Scenario calc'!$C$211:$BJ$211,B$47*12) -> 19840.299 | C49: =INDEX('Scenario calc'!$C$211:$BJ$211,C$47*12) -> 18106.033 | D49: =INDEX('Scenario calc'!$C$211:$BJ$211,D$47*12) -> 25610.415 | E49: =INDEX('Scenario calc'!$C$211:$BJ$211,E$47*12) -> 43012.925 | F49: =INDEX('Scenario calc'!$C$211:$BJ$211,F$47*12) -> 67175.922
A50: High | B50: =INDEX('Scenario calc'!$C$331:$BJ$331,B$47*12) -> 82563.675 | C50: =INDEX('Scenario calc'!$C$331:$BJ$331,C$47*12) -> 142126.35 | D50: =INDEX('Scenario calc'!$C$331:$BJ$331,D$47*12) -> 220859.66 | E50: =INDEX('Scenario calc'!$C$331:$BJ$331,E$47*12) -> 320893.19 | F50: =INDEX('Scenario calc'!$C$331:$BJ$331,F$47*12) -> 444596.24

Sheet Break-even
A1: Startup costs, funding need and break-even | H1: =HYPERLINK("#'Cover'!A1","◂ Contents") -> ◂ Contents
A2: Live for the selected scenario. Periods are counted in months from the start of the plan.
A3: Scenario shown | B3: =CHOOSE(Dashboard!$B$4,"Low","Base","High") -> Base
A5: Startup costs & funding need (up to the lowest cash point)
A6: Lowest cash point (month #) | B6: =MATCH(MIN(Monthly!$C$89:$BJ$89),Monthly!$C$89:$BJ$89,0) -> 26
A7: Capital spending up to the lowest cash point | B7: =SUMPRODUCT(--(Monthly!$C$4:$BJ$4<=$B$6),Monthly!$C$62:$BJ$62) -> 143000
A8: Operating cash burn up to the lowest cash point | B8: =-SUMPRODUCT(--(Monthly!$C$4:$BJ$4<=$B$6),Monthly!$C$83:$BJ$83) -> -372.4151 | D8: Losses and working capital before the business funds itself
A9: Loan repayments up to the lowest cash point | B9: =-SUMPRODUCT(--(Monthly!$C$4:$BJ$4<=$B$6),Monthly!$C$71:$BJ$71) -> 37500
A10: Total uses of funds | B10: =B7+B8+B9 -> 180127.58
A11: Minimum cash buffer to keep | B11: =Inputs!$E$86 -> 42000 | D11: Input on the Inputs sheet
A12: Funding required (uses + buffer) | B12: =B10+B11 -> 222127.58
A14: Equity raised | B14: =Inputs!$E$71 -> 100000
A15: Loan drawn | B15: =Inputs!$E$72 -> 90000
A16: Total sources of funds | B16: =B14+B15 -> 190000
A17: Funding surplus / (shortfall) | B17: =B16-B12 -> -32127.585 | D17: Negative = raise at least this much more
A18: Lowest cash balance in the plan | B18: =MIN(Monthly!$C$89:$BJ$89) -> 9872.4151 | D18: Equals sources minus uses
A20: Break-even timing
A21: First month with positive EBITDA (month #) | B21: =IFERROR(MATCH(1,Monthly!$C$90:$BJ$90,0),"Not within horizon") -> 6
A22: First month with positive net income (month #) | B22: =IFERROR(MATCH(1,Monthly!$C$93:$BJ$93,0),"Not within horizon") -> 7
A23: Cash invested paid back (month #) | B23: =IF(MIN(Monthly!$C$95:$BJ$95)>=0,"No investment to pay back",IFERROR(MATCH(1,Monthly!$C$97:$BJ$97,0),"Not within horizon")) -> Not within horizon | D23: Cumulative operating + investing cash flow back to zero
A25: Annual break-even revenue
A26: Year # | B26: 1 | C26: 2 | D26: 3 | E26: 4 | F26: 5
B27: Year 1 | C27: Year 2 | D27: Year 3 | E27: Year 4 | F27: Year 5
A28: Revenue | B28: =SUMIF(Monthly!$C$5:$BJ$5,B$26,Monthly!$C$24:$BJ$24) -> 273896 | C28: =SUMIF(Monthly!$C$5:$BJ$5,C$26,Monthly!$C$24:$BJ$24) -> 336825.82 | D28: =SUMIF(Monthly!$C$5:$BJ$5,D$26,Monthly!$C$24:$BJ$24) -> 358461.37 | E28: =SUMIF(Monthly!$C$5:$BJ$5,E$26,Monthly!$C$24:$BJ$24) -> 381506.04 | F28: =SUMIF(Monthly!$C$5:$BJ$5,F$26,Monthly!$C$24:$BJ$24) -> 406053.09
A29: Gross profit | B29: =SUMIF(Monthly!$C$5:$BJ$5,B$26,Monthly!$C$33:$BJ$33) -> 161966.54 | C29: =SUMIF(Monthly!$C$5:$BJ$5,C$26,Monthly!$C$33:$BJ$33) -> 199005.1 | D29: =SUMIF(Monthly!$C$5:$BJ$5,D$26,Monthly!$C$33:$BJ$33) -> 211683.05 | E29: =SUMIF(Monthly!$C$5:$BJ$5,E$26,Monthly!$C$33:$BJ$33) -> 225178.61 | F29: =SUMIF(Monthly!$C$5:$BJ$5,F$26,Monthly!$C$33:$BJ$33) -> 239545.29
A30: Gross margin (contribution) | B30: =IF(B28=0,0,B29/B28) -> 0.5913432 | C30: =IF(C28=0,0,C29/C28) -> 0.59082496 | D30: =IF(D28=0,0,D29/D28) -> 0.5905324 | E30: =IF(E28=0,0,E29/E28) -> 0.59023605 | F30: =IF(F28=0,0,F29/F28) -> 0.58993587
A31: Operating expenses (treated as fixed) | B31: =-SUMIF(Monthly!$C$5:$BJ$5,B$26,Monthly!$C$45:$BJ$45) -> 169272.5 | C31: =-SUMIF(Monthly!$C$5:$BJ$5,C$26,Monthly!$C$45:$BJ$45) -> 174374.61 | D31: =-SUMIF(Monthly!$C$5:$BJ$5,D$26,Monthly!$C$45:$BJ$45) -> 179430.04 | E31: =-SUMIF(Monthly!$C$5:$BJ$5,E$26,Monthly!$C$45:$BJ$45) -> 184643.35 | F31: =-SUMIF(Monthly!$C$5:$BJ$5,F$26,Monthly!$C$45:$BJ$45) -> 190019.77
A32: Break-even revenue (EBITDA = 0) | B32: =IF(B30>0,B31/B30,"n/a") -> 286250.86 | C32: =IF(C30>0,C31/C30,"n/a") -> 295137.52 | D32: =IF(D30>0,D31/D30,"n/a") -> 303844.54 | E32: =IF(E30>0,E31/E30,"n/a") -> 312829.67 | F32: =IF(F30>0,F31/F30,"n/a") -> 322102.42
A33: Margin of safety (revenue above break-even) | B33: =IF(AND(ISNUMBER(B32),B28>0),(B28-B32)/B28,"n/a") -> -0.045107861 | C33: =IF(AND(ISNUMBER(C32),C28>0),(C28-C32)/C28,"n/a") -> 0.12376814 | D33: =IF(AND(ISNUMBER(D32),D28>0),(D28-D32)/D28,"n/a") -> 0.15236463 | E33: =IF(AND(ISNUMBER(E32),E28>0),(E28-E32)/E28,"n/a") -> 0.18001383 | F33: =IF(AND(ISNUMBER(F32),F28>0),(F28-F32)/F28,"n/a") -> 0.20674803
A35: Simplification: cost of sales is treated as variable and operating expenses as fixed, so break-even revenue = operating expenses ÷ gross margin.

Sheet Valuation
A1: Discounted cash flow valuation | H1: =HYPERLINK("#'Cover'!A1","◂ Contents") -> ◂ Contents
A2: Enterprise value at the start of the plan, before the funding raised in period 1. Year-end discounting.
A3: Scenario shown | B3: =CHOOSE(Dashboard!$B$4,"Low","Base","High") -> Base
A5: Assumptions (active scenario, from the Inputs sheet)
A6: Discount rate (WACC) | B6: =Inputs!$E$89 -> 0.25
A7: Terminal growth rate | B7: =Inputs!$E$90 -> 0.02
A8: Exit multiple (EV ÷ final-year EBITDA) | B8: =Inputs!$E$91 -> 4
A9: Tax rate (for the interest tax shield) | B9: =Inputs!$E$83 -> 0.21
A10: Sensitivity step: WACC | B10: =Inputs!$E$92 -> 0.01
A11: Sensitivity step: terminal growth | B11: =Inputs!$E$93 -> 0.005
A13: Free cash flow by year
A14: Year # | B14: 1 | C14: 2 | D14: 3 | E14: 4 | F14: 5
B15: Year 1 | C15: Year 2 | D15: Year 3 | E15: Year 4 | F15: Year 5
A16: EBITDA | B16: =SUMIF(Monthly!$C$5:$BJ$5,B$14,Monthly!$C$46:$BJ$46) -> -7305.964 | C16: =SUMIF(Monthly!$C$5:$BJ$5,C$14,Monthly!$C$46:$BJ$46) -> 24630.491 | D16: =SUMIF(Monthly!$C$5:$BJ$5,D$14,Monthly!$C$46:$BJ$46) -> 32253.01 | E16: =SUMIF(Monthly!$C$5:$BJ$5,E$14,Monthly!$C$46:$BJ$46) -> 40535.265 | F16: =SUMIF(Monthly!$C$5:$BJ$5,F$14,Monthly!$C$46:$BJ$46) -> 49525.516
A17: Unlevered free cash flow | B17: =SUMIF(Monthly!$C$5:$BJ$5,B$14,Monthly!$C$98:$BJ$98) -> -147798.39 | C17: =SUMIF(Monthly!$C$5:$BJ$5,C$14,Monthly!$C$98:$BJ$98) -> 20851.684 | D17: =SUMIF(Monthly!$C$5:$BJ$5,D$14,Monthly!$C$98:$BJ$98) -> 28810.532 | E17: =SUMIF(Monthly!$C$5:$BJ$5,E$14,Monthly!$C$98:$BJ$98) -> 37428.86 | F17: =SUMIF(Monthly!$C$5:$BJ$5,F$14,Monthly!$C$98:$BJ$98) -> 42909.547
A18: Discount factor | B18: =1/(1+Inputs!$E$89)^B$14 -> 0.8 | C18: =1/(1+Inputs!$E$89)^C$14 -> 0.64 | D18: =1/(1+Inputs!$E$89)^D$14 -> 0.512 | E18: =1/(1+Inputs!$E$89)^E$14 -> 0.4096 | F18: =1/(1+Inputs!$E$89)^F$14 -> 0.32768
A19: Present value of free cash flow | B19: =B17*B18 -> -118238.72 | C19: =C17*C18 -> 13345.078 | D19: =D17*D18 -> 14750.992 | E19: =E17*E18 -> 15330.861 | F19: =F17*F18 -> 14060.6
A21: Enterprise value
B22: Perpetual growth | C22: Exit multiple
A23: Present value of the plan's free cash flows | B23: =SUM($B$19:$F$19) -> -60751.184 | C23: =B23 -> -60751.184
A24: Final-year free cash flow | final-year EBITDA | B24: =$F$17 -> 42909.547 | C24: =$F$16 -> 49525.516
A25: Terminal value at the end of year 5 | B25: =IF($B$6>$B$7,B24*(1+$B$7)/($B$6-$B$7),0) -> 190294.51 | C25: =C24*$B$8 -> 198102.06
A26: Present value of the terminal value | B26: =B25/(1+$B$6)^$F$14 -> 62355.705 | C26: =C25/(1+$B$6)^$F$14 -> 64914.085
A27: Enterprise value | B27: =B23+B26 -> 1604.5212 | C27: =C23+C26 -> 4162.9003
A28: Terminal value share of enterprise value | B28: =IF(B27<>0,B26/B27,0) -> 38.862501 | C28: =IF(C27<>0,C26/C27,0) -> 15.593476
A29: Cross-check: implied exit multiple | implied perpetual growth | B29: =IF(C24>0,B25/C24,"n/a") -> 3.8423529 | C29: =IF(C25+B24<>0,(C25*$B$6-B24)/(C25+B24),"n/a") -> 0.027450833
A30: Enterprise value — average of the two methods | B30: =AVERAGE(B27,C27) -> 2883.7108
A32: Sensitivity: enterprise value (perpetual growth) by WACC and terminal growth
A33: WACC ↓ · terminal growth → | B33: =$B$7+(-2)*$B$11 -> 0.01 | C33: =$B$7+(-1)*$B$11 -> 0.015 | D33: =$B$7+(0)*$B$11 -> 0.02 | E33: =$B$7+(1)*$B$11 -> 0.025 | F33: =$B$7+(2)*$B$11 -> 0.03
A34: =$B$6+(-2)*$B$10 -> 0.23 | B34: =IF($A34>B$33,SUMPRODUCT($B$17:$F$17/(1+$A34)^$B$14:$F$14)+$F$17*(1+B$33)/($A34-B$33)/(1+$A34)^$F$14,"n/a") -> 10670.158 | C34: =IF($A34>C$33,SUMPRODUCT($B$17:$F$17/(1+$A34)^$B$14:$F$14)+$F$17*(1+C$33)/($A34-C$33)/(1+$A34)^$F$14,"n/a") -> 12651.878 | D34: =IF($A34>D$33,SUMPRODUCT($B$17:$F$17/(1+$A34)^$B$14:$F$14)+$F$17*(1+D$33)/($A34-D$33)/(1+$A34)^$F$14,"n/a") -> 14727.966 | E34: =IF($A34>E$33,SUMPRODUCT($B$17:$F$17/(1+$A34)^$B$14:$F$14)+$F$17*(1+E$33)/($A34-E$33)/(1+$A34)^$F$14,"n/a") -> 16905.326 | F34: =IF($A34>F$33,SUMPRODUCT($B$17:$F$17/(1+$A34)^$B$14:$F$14)+$F$17*(1+F$33)/($A34-F$33)/(1+$A34)^$F$14,"n/a") -> 19191.555
A35: =$B$6+(-1)*$B$10 -> 0.24 | B35: =IF($A35>B$33,SUMPRODUCT($B$17:$F$17/(1+$A35)^$B$14:$F$14)+$F$17*(1+B$33)/($A35-B$33)/(1+$A35)^$F$14,"n/a") -> 4222.4392 | C35: =IF($A35>C$33,SUMPRODUCT($B$17:$F$17/(1+$A35)^$B$14:$F$14)+$F$17*(1+C$33)/($A35-C$33)/(1+$A35)^$F$14,"n/a") -> 5976.0243 | D35: =IF($A35>D$33,SUMPRODUCT($B$17:$F$17/(1+$A35)^$B$14:$F$14)+$F$17*(1+D$33)/($A35-D$33)/(1+$A35)^$F$14,"n/a") -> 7809.3177 | E35: =IF($A35>E$33,SUMPRODUCT($B$17:$F$17/(1+$A35)^$B$14:$F$14)+$F$17*(1+E$33)/($A35-E$33)/(1+$A35)^$F$14,"n/a") -> 9727.8807 | F35: =IF($A35>F$33,SUMPRODUCT($B$17:$F$17/(1+$A35)^$B$14:$F$14)+$F$17*(1+F$33)/($A35-F$33)/(1+$A35)^$F$14,"n/a") -> 11737.804
A36: =$B$6+(0)*$B$10 -> 0.25 | B36: =IF($A36>B$33,SUMPRODUCT($B$17:$F$17/(1+$A36)^$B$14:$F$14)+$F$17*(1+B$33)/($A36-B$33)/(1+$A36)^$F$14,"n/a") -> -1579.4916 | C36: =IF($A36>C$33,SUMPRODUCT($B$17:$F$17/(1+$A36)^$B$14:$F$14)+$F$17*(1+C$33)/($A36-C$33)/(1+$A36)^$F$14,"n/a") -> -21.357674 | D36: =IF($A36>D$33,SUMPRODUCT($B$17:$F$17/(1+$A36)^$B$14:$F$14)+$F$17*(1+D$33)/($A36-D$33)/(1+$A36)^$F$14,"n/a") -> 1604.5212 | E36: =IF($A36>E$33,SUMPRODUCT($B$17:$F$17/(1+$A36)^$B$14:$F$14)+$F$17*(1+E$33)/($A36-E$33)/(1+$A36)^$F$14,"n/a") -> 3302.6613 | F36: =IF($A36>F$33,SUMPRODUCT($B$17:$F$17/(1+$A36)^$B$14:$F$14)+$F$17*(1+F$33)/($A36-F$33)/(1+$A36)^$F$14,"n/a") -> 5077.9896
A37: =$B$6+(1)*$B$10 -> 0.26 | B37: =IF($A37>B$33,SUMPRODUCT($B$17:$F$17/(1+$A37)^$B$14:$F$14)+$F$17*(1+B$33)/($A37-B$33)/(1+$A37)^$F$14,"n/a") -> -6816.1436 | C37: =IF($A37>C$33,SUMPRODUCT($B$17:$F$17/(1+$A37)^$B$14:$F$14)+$F$17*(1+C$33)/($A37-C$33)/(1+$A37)^$F$14,"n/a") -> -5426.3969 | D37: =IF($A37>D$33,SUMPRODUCT($B$17:$F$17/(1+$A37)^$B$14:$F$14)+$F$17*(1+D$33)/($A37-D$33)/(1+$A37)^$F$14,"n/a") -> -3978.744 | E37: =IF($A37>E$33,SUMPRODUCT($B$17:$F$17/(1+$A37)^$B$14:$F$14)+$F$17*(1+E$33)/($A37-E$33)/(1+$A37)^$F$14,"n/a") -> -2469.489 | F37: =IF($A37>F$33,SUMPRODUCT($B$17:$F$17/(1+$A37)^$B$14:$F$14)+$F$17*(1+F$33)/($A37-F$33)/(1+$A37)^$F$14,"n/a") -> -894.61409
A38: =$B$6+(2)*$B$10 -> 0.27 | B38: =IF($A38>B$33,SUMPRODUCT($B$17:$F$17/(1+$A38)^$B$14:$F$14)+$F$17*(1+B$33)/($A38-B$33)/(1+$A38)^$F$14,"n/a") -> -11555.527 | C38: =IF($A38>C$33,SUMPRODUCT($B$17:$F$17/(1+$A38)^$B$14:$F$14)+$F$17*(1+C$33)/($A38-C$33)/(1+$A38)^$F$14,"n/a") -> -10311.598 | D38: =IF($A38>D$33,SUMPRODUCT($B$17:$F$17/(1+$A38)^$B$14:$F$14)+$F$17*(1+D$33)/($A38-D$33)/(1+$A38)^$F$14,"n/a") -> -9017.9123 | E38: =IF($A38>E$33,SUMPRODUCT($B$17:$F$17/(1+$A38)^$B$14:$F$14)+$F$17*(1+E$33)/($A38-E$33)/(1+$A38)^$F$14,"n/a") -> -7671.4229 | F38: =IF($A38>F$33,SUMPRODUCT($B$17:$F$17/(1+$A38)^$B$14:$F$14)+$F$17*(1+F$33)/($A38-F$33)/(1+$A38)^$F$14,"n/a") -> -6268.8297
A40: Free cash flow = operating cash flow + interest × (1 − tax rate) − capital spending. Cells marked n/a: WACC not above growth.

Sheet Sources & Uses
A1: Sources and uses of funds | E1: =HYPERLINK("#'Cover'!A1","◂ Contents") -> ◂ Contents
A2: Live for the selected scenario. Where the money comes from and where it goes in the period set below.
A3: Scenario shown | B3: =CHOOSE(Dashboard!$B$4,"Low","Base","High") -> Base
A5: Funding structure ($'000) — raised at the start of the plan
B6: Amount | C6: Share
A7: Equity | B7: =Inputs!$E$71 -> 100000 | C7: =IF($B$9=0,0,B7/$B$9) -> 0.52631579
A8: Debt (loan) | B8: =Inputs!$E$72 -> 90000 | C8: =IF($B$9=0,0,B8/$B$9) -> 0.47368421
A9: Total funding | B9: =B7+B8 -> 190000 | C9: =IF(B9=0,0,1) -> 1
A10: Gearing (debt ÷ equity) | B10: =IF(B7<=0,IF(B8>0,"n/a",0),B8/B7) -> 0.9 | D10: n/a: debt without positive equity
A11: Funding required by the plan (Break-even sheet) | B11: ='Break-even'!B12 -> 222127.58
A12: Funding surplus / (shortfall) | B12: ='Break-even'!B17 -> -32127.585
A14: ="Sources and uses of cash in the first "&$B$16&IF($B$16=1," month"," months")&" ($'000)" -> Sources and uses of cash in the first 12 months ($'000)
A15: Period covered (months from the start) | B15: 12 | D15: 1 to 60 (capped)
A16: Months used | B16: =MIN(60,MAX(1,ROUND(B15,0))) -> 12
A17: Sources | B17: Amount | C17: Share
A18: Equity raised | B18: =SUMPRODUCT(--(Monthly!$C$4:$BJ$4<=$B$16),Monthly!$C$85:$BJ$85) -> 100000 | C18: =IF($B$21=0,0,B18/$B$21) -> 0.52631579
A19: Loan drawdowns | B19: =SUMPRODUCT(--(Monthly!$C$4:$BJ$4<=$B$16),Monthly!$C$70:$BJ$70) -> 90000 | C19: =IF($B$21=0,0,B19/$B$21) -> 0.47368421
A20: Cash generated by operations | B20: =MAX(0,SUMPRODUCT(--(Monthly!$C$4:$BJ$4<=$B$16),Monthly!$C$83:$BJ$83)) -> 0 | C20: =IF($B$21=0,0,B20/$B$21) -> 0
A21: Total sources | B21: =SUM(B18:B20) -> 190000 | C21: =IF(B21=0,0,1) -> 1
A23: Uses | B23: Amount | C23: Share
A24: Cash used by operations | B24: =MAX(0,-SUMPRODUCT(--(Monthly!$C$4:$BJ$4<=$B$16),Monthly!$C$83:$BJ$83)) -> 15659.701 | C24: =IF($B$28=0,0,B24/$B$28) -> 0.082419477
A25: Capital spending | B25: =-SUMPRODUCT(--(Monthly!$C$4:$BJ$4<=$B$16),Monthly!$C$84:$BJ$84) -> 138000 | C25: =IF($B$28=0,0,B25/$B$28) -> 0.72631579
A26: Loan repayments | B26: =-SUMPRODUCT(--(Monthly!$C$4:$BJ$4<=$B$16),Monthly!$C$71:$BJ$71) -> 16500 | C26: =IF($B$28=0,0,B26/$B$28) -> 0.086842105
A27: Cash at the end of the period | B27: =INDEX(Monthly!$C$89:$BJ$89,$B$16) -> 19840.299 | C27: =IF($B$28=0,0,B27/$B$28) -> 0.10442263
A28: Total uses | B28: =SUM(B24:B27) -> 190000 | C28: =IF(B28=0,0,1) -> 1
A29: Sources − uses (must be 0; opening cash is 0) | B29: =B21-B28 -> 0

Sheet KPIs
A1: KPIs & ratios | I1: =HYPERLINK("#'Cover'!A1","◂ Contents") -> ◂ Contents
A2: Food truck financial model (planning) — industry metrics and financial ratios for the active scenario
A4: Financial ratios
B5: 1 | C5: 2 | D5: 3 | E5: 4 | F5: 5 | G5: Target
A6: Revenue growth | B6: =IF(N('P&L'!A5)<=0,"n/a",'P&L'!B5/'P&L'!A5-1) -> n/a | C6: =IF(N('P&L'!B5)<=0,"n/a",'P&L'!C5/'P&L'!B5-1) -> 0.22975809 | D6: =IF(N('P&L'!C5)<=0,"n/a",'P&L'!D5/'P&L'!C5-1) -> 0.064233642 | E6: =IF(N('P&L'!D5)<=0,"n/a",'P&L'!E5/'P&L'!D5-1) -> 0.064287727 | F6: =IF(N('P&L'!E5)<=0,"n/a",'P&L'!F5/'P&L'!E5-1) -> 0.064342516
A7: Gross margin | B7: =IF('P&L'!B5<=0,"n/a",'P&L'!B7/'P&L'!B5) -> 0.5913432 | C7: =IF('P&L'!C5<=0,"n/a",'P&L'!C7/'P&L'!C5) -> 0.59082496 | D7: =IF('P&L'!D5<=0,"n/a",'P&L'!D7/'P&L'!D5) -> 0.5905324 | E7: =IF('P&L'!E5<=0,"n/a",'P&L'!E7/'P&L'!E5) -> 0.59023605 | F7: =IF('P&L'!F5<=0,"n/a",'P&L'!F7/'P&L'!F5) -> 0.58993587
A8: EBITDA margin | B8: =IF('P&L'!B5<=0,"n/a",'P&L'!B19/'P&L'!B5) -> -0.026674227 | C8: =IF('P&L'!C5<=0,"n/a",'P&L'!C19/'P&L'!C5) -> 0.073125305 | D8: =IF('P&L'!D5<=0,"n/a",'P&L'!D19/'P&L'!D5) -> 0.089976252 | E8: =IF('P&L'!E5<=0,"n/a",'P&L'!E19/'P&L'!E5) -> 0.10625065 | F8: =IF('P&L'!F5<=0,"n/a",'P&L'!F19/'P&L'!F5) -> 0.12196808
A9: Net margin | B9: =IF('P&L'!B5<=0,"n/a",'P&L'!B26/'P&L'!B5) -> -0.12573979 | C9: =IF('P&L'!C5<=0,"n/a",'P&L'!C26/'P&L'!C5) -> -0.0036990563 | D9: =IF('P&L'!D5<=0,"n/a",'P&L'!D26/'P&L'!D5) -> 0.02131175 | E9: =IF('P&L'!E5<=0,"n/a",'P&L'!E26/'P&L'!E5) -> 0.045043982 | F9: =IF('P&L'!F5<=0,"n/a",'P&L'!F26/'P&L'!F5) -> 0.058101498
A10: Payroll, % of revenue | B10: =IF('P&L'!B5<=0,"n/a",-SUMIF(Headcount!$C$5:$BJ$5,B$5,Headcount!$C$17:$BJ$17)/'P&L'!B5) -> 0.43263136 | C10: =IF('P&L'!C5<=0,"n/a",-SUMIF(Headcount!$C$5:$BJ$5,C$5,Headcount!$C$17:$BJ$17)/'P&L'!C5) -> 0.36235607 | D10: =IF('P&L'!D5<=0,"n/a",-SUMIF(Headcount!$C$5:$BJ$5,D$5,Headcount!$C$17:$BJ$17)/'P&L'!D5) -> 0.35070001 | E10: =IF('P&L'!E5<=0,"n/a",-SUMIF(Headcount!$C$5:$BJ$5,E$5,Headcount!$C$17:$BJ$17)/'P&L'!E5) -> 0.33940165 | F10: =IF('P&L'!F5<=0,"n/a",-SUMIF(Headcount!$C$5:$BJ$5,F$5,Headcount!$C$17:$BJ$17)/'P&L'!F5) -> 0.32845038
A11: Marketing, % of revenue | B11: =IF('P&L'!B5<=0,"n/a",-'P&L'!B16/'P&L'!B5) -> 0.030668575 | C11: =IF('P&L'!C5<=0,"n/a",-'P&L'!C16/'P&L'!C5) -> 0.024938706 | D11: =IF('P&L'!D5<=0,"n/a",-'P&L'!D16/'P&L'!D5) -> 0.023433487 | E11: =IF('P&L'!E5<=0,"n/a",-'P&L'!E16/'P&L'!E5) -> 0.022018 | F11: =IF('P&L'!F5<=0,"n/a",-'P&L'!F16/'P&L'!F5) -> 0.02068695
A12: Operating expenses, % of revenue | B12: =IF('P&L'!B5<=0,"n/a",-'P&L'!B18/'P&L'!B5) -> 0.61801742 | C12: =IF('P&L'!C5<=0,"n/a",-'P&L'!C18/'P&L'!C5) -> 0.51769966 | D12: =IF('P&L'!D5<=0,"n/a",-'P&L'!D18/'P&L'!D5) -> 0.50055615 | E12: =IF('P&L'!E5<=0,"n/a",-'P&L'!E18/'P&L'!E5) -> 0.48398539 | F12: =IF('P&L'!F5<=0,"n/a",-'P&L'!F18/'P&L'!F5) -> 0.46796779
A13: Current ratio (current assets ÷ current liabilities) | B13: =IF(('Balance Sheet'!B12-'Balance Sheet'!B11)<=0,"n/a",('Balance Sheet'!B5+'Balance Sheet'!B6+'Balance Sheet'!B7)/('Balance Sheet'!B12-'Balance Sheet'!B11)) -> 11.33325 | C13: =IF(('Balance Sheet'!C12-'Balance Sheet'!C11)<=0,"n/a",('Balance Sheet'!C5+'Balance Sheet'!C6+'Balance Sheet'!C7)/('Balance Sheet'!C12-'Balance Sheet'!C11)) -> 9.9125997 | D13: =IF(('Balance Sheet'!D12-'Balance Sheet'!D11)<=0,"n/a",('Balance Sheet'!D5+'Balance Sheet'!D6+'Balance Sheet'!D7)/('Balance Sheet'!D12-'Balance Sheet'!D11)) -> 12.673343 | E13: =IF(('Balance Sheet'!E12-'Balance Sheet'!E11)<=0,"n/a",('Balance Sheet'!E5+'Balance Sheet'!E6+'Balance Sheet'!E7)/('Balance Sheet'!E12-'Balance Sheet'!E11)) -> 19.122717 | F13: =IF(('Balance Sheet'!F12-'Balance Sheet'!F11)<=0,"n/a",('Balance Sheet'!F5+'Balance Sheet'!F6+'Balance Sheet'!F7)/('Balance Sheet'!F12-'Balance Sheet'!F11)) -> 27.331067
A14: Debt ÷ equity (loan ÷ total equity) | B14: =IF('Balance Sheet'!B15<=0,"n/a",'Balance Sheet'!B11/'Balance Sheet'!B15) -> 1.121104 | C14: =IF('Balance Sheet'!C15<=0,"n/a",'Balance Sheet'!C11/'Balance Sheet'!C15) -> 0.86294776 | D14: =IF('Balance Sheet'!D15<=0,"n/a",'Balance Sheet'!D11/'Balance Sheet'!D15) -> 0.52116719 | E14: =IF('Balance Sheet'!E15<=0,"n/a",'Balance Sheet'!E11/'Balance Sheet'!E15) -> 0.21876087 | F14: =IF('Balance Sheet'!F15<=0,"n/a",'Balance Sheet'!F11/'Balance Sheet'!F15) -> 0.013306045
A15: Return on assets (net income ÷ year-end assets) | B15: =IF('Balance Sheet'!B9<=0,"n/a",'P&L'!B26/'Balance Sheet'!B9) -> -0.24413 | C15: =IF('Balance Sheet'!C9<=0,"n/a",'P&L'!C26/'Balance Sheet'!C9) -> -0.010216164 | D15: =IF('Balance Sheet'!D9<=0,"n/a",'P&L'!D26/'Balance Sheet'!D9) -> 0.06836896 | E15: =IF('Balance Sheet'!E9<=0,"n/a",'P&L'!E26/'Balance Sheet'!E9) -> 0.15471269 | F15: =IF('Balance Sheet'!F9<=0,"n/a",'P&L'!F26/'Balance Sheet'!F9) -> 0.20194142
A16: Return on equity (net income ÷ year-end equity) | B16: =IF('Balance Sheet'!B15<=0,"n/a",'P&L'!B26/'Balance Sheet'!B15) -> -0.52531159 | C16: =IF('Balance Sheet'!C15<=0,"n/a",'P&L'!C26/'Balance Sheet'!C15) -> -0.019372597 | D16: =IF('Balance Sheet'!D15<=0,"n/a",'P&L'!D26/'Balance Sheet'!D15) -> 0.10617133 | E16: =IF('Balance Sheet'!E15<=0,"n/a",'P&L'!E26/'Balance Sheet'!E15) -> 0.19278499 | F16: =IF('Balance Sheet'!F15<=0,"n/a",'P&L'!F26/'Balance Sheet'!F15) -> 0.20928007
A18: DuPont analysis — return on equity = net margin × asset turnover × equity multiplier
B19: 1 | C19: 2 | D19: 3 | E19: 4 | F19: 5
A20: Net margin | B20: =IF('P&L'!B5<=0,"n/a",'P&L'!B26/'P&L'!B5) -> -0.12573979 | C20: =IF('P&L'!C5<=0,"n/a",'P&L'!C26/'P&L'!C5) -> -0.0036990563 | D20: =IF('P&L'!D5<=0,"n/a",'P&L'!D26/'P&L'!D5) -> 0.02131175 | E20: =IF('P&L'!E5<=0,"n/a",'P&L'!E26/'P&L'!E5) -> 0.045043982 | F20: =IF('P&L'!F5<=0,"n/a",'P&L'!F26/'P&L'!F5) -> 0.058101498
A21: × Asset turnover (revenue ÷ assets) | B21: =IF('Balance Sheet'!B9<=0,"n/a",'P&L'!B5/'Balance Sheet'!B9) -> 1.9415493 | C21: =IF('Balance Sheet'!C9<=0,"n/a",'P&L'!C5/'Balance Sheet'!C9) -> 2.7618298 | D21: =IF('Balance Sheet'!D9<=0,"n/a",'P&L'!D5/'Balance Sheet'!D9) -> 3.2080407 | E21: =IF('Balance Sheet'!E9<=0,"n/a",'P&L'!E5/'Balance Sheet'!E9) -> 3.4347028 | F21: =IF('Balance Sheet'!F9<=0,"n/a",'P&L'!F5/'Balance Sheet'!F9) -> 3.4756663
A22: × Equity multiplier (assets ÷ equity) | B22: =IF('Balance Sheet'!B15<=0,"n/a",'Balance Sheet'!B9/'Balance Sheet'!B15) -> 2.1517699 | C22: =IF('Balance Sheet'!C15<=0,"n/a",'Balance Sheet'!C9/'Balance Sheet'!C15) -> 1.8962692 | D22: =IF('Balance Sheet'!D15<=0,"n/a",'Balance Sheet'!D9/'Balance Sheet'!D15) -> 1.5529172 | E22: =IF('Balance Sheet'!E15<=0,"n/a",'Balance Sheet'!E9/'Balance Sheet'!E15) -> 1.2460839 | F22: =IF('Balance Sheet'!F15<=0,"n/a",'Balance Sheet'!F9/'Balance Sheet'!F15) -> 1.0363405
A23: Return on equity (product of the three) | B23: =IF(AND(ISNUMBER(B20),ISNUMBER(B21),ISNUMBER(B22)),B20*B21*B22,"n/a") -> -0.52531159 | C23: =IF(AND(ISNUMBER(C20),ISNUMBER(C21),ISNUMBER(C22)),C20*C21*C22,"n/a") -> -0.019372597 | D23: =IF(AND(ISNUMBER(D20),ISNUMBER(D21),ISNUMBER(D22)),D20*D21*D22,"n/a") -> 0.10617133 | E23: =IF(AND(ISNUMBER(E20),ISNUMBER(E21),ISNUMBER(E22)),E20*E21*E22,"n/a") -> 0.19278499 | F23: =IF(AND(ISNUMBER(F20),ISNUMBER(F21),ISNUMBER(F22)),F20*F21*F22,"n/a") -> 0.20928007
A24: Check: product − return on equity (must be 0) | B24: =IF(AND(ISNUMBER(B23),ISNUMBER(B16)),B23-B16,IF(ISNUMBER(B23),1,IF(AND(ISNUMBER(B16),ISNUMBER(B20),ISNUMBER(B21)),1,0))) -> 0 | C24: =IF(AND(ISNUMBER(C23),ISNUMBER(C16)),C23-C16,IF(ISNUMBER(C23),1,IF(AND(ISNUMBER(C16),ISNUMBER(C20),ISNUMBER(C21)),1,0))) -> 0 | D24: =IF(AND(ISNUMBER(D23),ISNUMBER(D16)),D23-D16,IF(ISNUMBER(D23),1,IF(AND(ISNUMBER(D16),ISNUMBER(D20),ISNUMBER(D21)),1,0))) -> 0 | E24: =IF(AND(ISNUMBER(E23),ISNUMBER(E16)),E23-E16,IF(ISNUMBER(E23),1,IF(AND(ISNUMBER(E16),ISNUMBER(E20),ISNUMBER(E21)),1,0))) -> 0 | F24: =IF(AND(ISNUMBER(F23),ISNUMBER(F16)),F23-F16,IF(ISNUMBER(F23),1,IF(AND(ISNUMBER(F16),ISNUMBER(F20),ISNUMBER(F21)),1,0))) -> 0
A26: Food truck metrics ($'000; per-unit rows in $)
A27: Year # | B27: 1 | C27: 2 | D27: 3 | E27: 4 | F27: 5
B28: Year 1 | C28: Year 2 | D28: Year 3 | E28: Year 4 | F28: Year 5 | G28: Target
A29: Trucks in operation (year end) | B29: =INDEX(Monthly!$C$8:$BJ$8,B$27*12) -> 1 | C29: =INDEX(Monthly!$C$8:$BJ$8,C$27*12) -> 1 | D29: =INDEX(Monthly!$C$8:$BJ$8,D$27*12) -> 1 | E29: =INDEX(Monthly!$C$8:$BJ$8,E$27*12) -> 1 | F29: =INDEX(Monthly!$C$8:$BJ$8,F$27*12) -> 1
A30: Service days (street and events) | B30: =SUMIF(Monthly!$C$5:$BJ$5,B$27,Monthly!$C$14:$BJ$14) -> 246.75 | C30: =SUMIF(Monthly!$C$5:$BJ$5,C$27,Monthly!$C$14:$BJ$14) -> 253.8 | D30: =SUMIF(Monthly!$C$5:$BJ$5,D$27,Monthly!$C$14:$BJ$14) -> 255.69 | E30: =SUMIF(Monthly!$C$5:$BJ$5,E$27,Monthly!$C$14:$BJ$14) -> 257.6745 | F30: =SUMIF(Monthly!$C$5:$BJ$5,F$27,Monthly!$C$14:$BJ$14) -> 259.75822
A31: Meals served | B31: =SUMIF(Monthly!$C$5:$BJ$5,B$27,Monthly!$C$17:$BJ$17) -> 19564 | C31: =SUMIF(Monthly!$C$5:$BJ$5,C$27,Monthly!$C$17:$BJ$17) -> 23358.24 | D31: =SUMIF(Monthly!$C$5:$BJ$5,D$27,Monthly!$C$17:$BJ$17) -> 24134.587 | E31: =SUMIF(Monthly!$C$5:$BJ$5,E$27,Monthly!$C$17:$BJ$17) -> 24938.005 | F31: =SUMIF(Monthly!$C$5:$BJ$5,F$27,Monthly!$C$17:$BJ$17) -> 25769.494
A32: Meals per service day | B32: =IF(B30=0,0,B31/B30) -> 79.286727 | C32: =IF(C30=0,0,C31/C30) -> 92.034043 | D32: =IF(D30=0,0,D31/D30) -> 94.390032 | E32: =IF(E30=0,0,E31/E30) -> 96.781035 | F32: =IF(F30=0,0,F31/F30) -> 99.20569
A33: Revenue | B33: =SUMIF(Monthly!$C$5:$BJ$5,B$27,Monthly!$C$24:$BJ$24) -> 273896 | C33: =SUMIF(Monthly!$C$5:$BJ$5,C$27,Monthly!$C$24:$BJ$24) -> 336825.82 | D33: =SUMIF(Monthly!$C$5:$BJ$5,D$27,Monthly!$C$24:$BJ$24) -> 358461.37 | E33: =SUMIF(Monthly!$C$5:$BJ$5,E$27,Monthly!$C$24:$BJ$24) -> 381506.04 | F33: =SUMIF(Monthly!$C$5:$BJ$5,F$27,Monthly!$C$24:$BJ$24) -> 406053.09
A34: Street sales | B34: =SUMIF(Monthly!$C$5:$BJ$5,B$27,Monthly!$C$22:$BJ$22) -> 230846 | C34: =SUMIF(Monthly!$C$5:$BJ$5,C$27,Monthly!$C$22:$BJ$22) -> 282318.22 | D34: =SUMIF(Monthly!$C$5:$BJ$5,D$27,Monthly!$C$22:$BJ$22) -> 299511.4 | E34: =SUMIF(Monthly!$C$5:$BJ$5,E$27,Monthly!$C$22:$BJ$22) -> 317751.64 | F34: =SUMIF(Monthly!$C$5:$BJ$5,F$27,Monthly!$C$22:$BJ$22) -> 337102.72
A35: Events & catering | B35: =SUMIF(Monthly!$C$5:$BJ$5,B$27,Monthly!$C$23:$BJ$23) -> 43050 | C35: =SUMIF(Monthly!$C$5:$BJ$5,C$27,Monthly!$C$23:$BJ$23) -> 54507.6 | D35: =SUMIF(Monthly!$C$5:$BJ$5,D$27,Monthly!$C$23:$BJ$23) -> 58949.969 | E35: =SUMIF(Monthly!$C$5:$BJ$5,E$27,Monthly!$C$23:$BJ$23) -> 63754.392 | F35: =SUMIF(Monthly!$C$5:$BJ$5,F$27,Monthly!$C$23:$BJ$23) -> 68950.375
A36: Events & catering, % of revenue | B36: =IF(B33=0,0,B35/B33) -> 0.15717645 | C36: =IF(C33=0,0,C35/C33) -> 0.16182726 | D36: =IF(D33=0,0,D35/D33) -> 0.16445278 | E36: =IF(E33=0,0,E35/E33) -> 0.16711241 | F36: =IF(F33=0,0,F35/F33) -> 0.1698063
A37: Revenue per meal ($) | B37: =IF(B31=0,0,B33/B31) -> 14 | C37: =IF(C31=0,0,C33/C31) -> 14.42 | D37: =IF(D31=0,0,D33/D31) -> 14.8526 | E37: =IF(E31=0,0,E33/E31) -> 15.298178 | F37: =IF(F31=0,0,F33/F31) -> 15.757123
A38: Revenue per service day ($) | B38: =IF(B30=0,0,B33/B30) -> 1110.0142 | C38: =IF(C30=0,0,C33/C30) -> 1327.1309 | D38: =IF(D30=0,0,D33/D30) -> 1401.9374 | E38: =IF(E30=0,0,E33/E30) -> 1480.5735 | F38: =IF(F30=0,0,F33/F30) -> 1563.1963
A39: Revenue per truck (year-end fleet) | B39: =IF(B29=0,0,B33/B29) -> 273896 | C39: =IF(C29=0,0,C33/C29) -> 336825.82 | D39: =IF(D29=0,0,D33/D29) -> 358461.37 | E39: =IF(E29=0,0,E33/E29) -> 381506.04 | F39: =IF(F29=0,0,F33/F29) -> 406053.09
A40: Food & packaging | B40: =SUMIF(Monthly!$C$5:$BJ$5,B$27,Monthly!$C$29:$BJ$29) -> -99189.48 | C40: =SUMIF(Monthly!$C$5:$BJ$5,C$27,Monthly!$C$29:$BJ$29) -> -121979.07 | D40: =SUMIF(Monthly!$C$5:$BJ$5,D$27,Monthly!$C$29:$BJ$29) -> -129814.22 | E40: =SUMIF(Monthly!$C$5:$BJ$5,E$27,Monthly!$C$29:$BJ$29) -> -138159.69 | F40: =SUMIF(Monthly!$C$5:$BJ$5,F$27,Monthly!$C$29:$BJ$29) -> -147049.23
A41: Food & packaging, % of revenue | B41: =IF(B33=0,0,-B40/B33) -> 0.36214286 | C41: =IF(C33=0,0,-C40/C33) -> 0.36214286 | D41: =IF(D33=0,0,-D40/D33) -> 0.36214286 | E41: =IF(E33=0,0,-E40/E33) -> 0.36214286 | F41: =IF(F33=0,0,-F40/F33) -> 0.36214286
A42: Payroll | B42: =SUMIF(Headcount!$C$5:$BJ$5,B$27,Headcount!$C$17:$BJ$17) -> -118496 | C42: =SUMIF(Headcount!$C$5:$BJ$5,C$27,Headcount!$C$17:$BJ$17) -> -122050.88 | D42: =SUMIF(Headcount!$C$5:$BJ$5,D$27,Headcount!$C$17:$BJ$17) -> -125712.41 | E42: =SUMIF(Headcount!$C$5:$BJ$5,E$27,Headcount!$C$17:$BJ$17) -> -129483.78 | F42: =SUMIF(Headcount!$C$5:$BJ$5,F$27,Headcount!$C$17:$BJ$17) -> -133368.29
A43: Prime cost (food, packaging, payroll), % of revenue | B43: =IF(B33=0,0,-(B40+B42)/B33) -> 0.79477422 | C43: =IF(C33=0,0,-(C40+C42)/C33) -> 0.72449893 | D43: =IF(D33=0,0,-(D40+D42)/D33) -> 0.71284287 | E43: =IF(E33=0,0,-(E40+E42)/E33) -> 0.70154451 | F43: =IF(F33=0,0,-(F40+F42)/F33) -> 0.69059323
A44: Gross profit | B44: =SUMIF(Monthly!$C$5:$BJ$5,B$27,Monthly!$C$33:$BJ$33) -> 161966.54 | C44: =SUMIF(Monthly!$C$5:$BJ$5,C$27,Monthly!$C$33:$BJ$33) -> 199005.1 | D44: =SUMIF(Monthly!$C$5:$BJ$5,D$27,Monthly!$C$33:$BJ$33) -> 211683.05 | E44: =SUMIF(Monthly!$C$5:$BJ$5,E$27,Monthly!$C$33:$BJ$33) -> 225178.61 | F44: =SUMIF(Monthly!$C$5:$BJ$5,F$27,Monthly!$C$33:$BJ$33) -> 239545.29
A45: Gross margin | B45: =IF(B33=0,0,B44/B33) -> 0.5913432 | C45: =IF(C33=0,0,C44/C33) -> 0.59082496 | D45: =IF(D33=0,0,D44/D33) -> 0.5905324 | E45: =IF(E33=0,0,E44/E33) -> 0.59023605 | F45: =IF(F33=0,0,F44/F33) -> 0.58993587
A46: EBITDA | B46: =SUMIF(Monthly!$C$5:$BJ$5,B$27,Monthly!$C$46:$BJ$46) -> -7305.964 | C46: =SUMIF(Monthly!$C$5:$BJ$5,C$27,Monthly!$C$46:$BJ$46) -> 24630.491 | D46: =SUMIF(Monthly!$C$5:$BJ$5,D$27,Monthly!$C$46:$BJ$46) -> 32253.01 | E46: =SUMIF(Monthly!$C$5:$BJ$5,E$27,Monthly!$C$46:$BJ$46) -> 40535.265 | F46: =SUMIF(Monthly!$C$5:$BJ$5,F$27,Monthly!$C$46:$BJ$46) -> 49525.516
A47: EBITDA margin | B47: =IF(B33=0,0,B46/B33) -> -0.026674227 | C47: =IF(C33=0,0,C46/C33) -> 0.073125305 | D47: =IF(D33=0,0,D46/D33) -> 0.089976252 | E47: =IF(E33=0,0,E46/E33) -> 0.10625065 | F47: =IF(F33=0,0,F46/F33) -> 0.12196808

Sheet Inputs
A1: Inputs — Low / Base / High | I1: =HYPERLINK("#'Cover'!A1","◂ Contents") -> ◂ Contents
A2: Illustrative assumptions - replace them with your own numbers.
A5: Driver | B5: Low | C5: Base | D5: High | E5: Active | F5: Unit | G5: Source / comment
A6: Fleet & service days
A7: Food trucks in operation at start | B7: 1 | C7: 1 | D7: 1 | E7: =CHOOSE(Dashboard!$B$4,B7,C7,D7) -> 1 | F7: #
A8: Trucks added each year (from year 2; raise headcount to match) | B8: 0 | C8: 0 | D8: 0 | E8: =CHOOSE(Dashboard!$B$4,B8,C8,D8) -> 0 | F8: #
A9: Street service days per truck per month (year average) | B9: 17 | C9: 18 | D9: 19 | E9: =CHOOSE(Dashboard!$B$4,B9,C9,D9) -> 18 | F9: days | G9: Low ≤ Base ≤ High
A10: Winter dip in street service days, December-February (monthly models) | B10: 0.3 | C10: 0.25 | D10: 0.2 | E10: =CHOOSE(Dashboard!$B$4,B10,C10,D10) -> 0.25 | F10: % | G10: Low ≥ Base ≥ High (lower is better)
A12: Ramp-up
A13: Months to reach mature volume (0 = already mature) | B13: 9 | C13: 6 | D13: 4 | E13: =CHOOSE(Dashboard!$B$4,B13,C13,D13) -> 6 | F13: months | G13: Low ≥ Base ≥ High (lower is better)
A14: Volume in month 1, % of mature | B14: 0.35 | C14: 0.5 | D14: 0.6 | E14: =CHOOSE(Dashboard!$B$4,B14,C14,D14) -> 0.5 | F14: % | G14: Low ≤ Base ≤ High
A16: Street sales
A17: Meals per street service day at maturity (year 1) | B17: 78 | C17: 88 | D17: 98 | E17: =CHOOSE(Dashboard!$B$4,B17,C17,D17) -> 88 | F17: meals | G17: Low ≤ Base ≤ High
A18: Meals per day growth per year | B18: 0 | C18: 0.03 | D18: 0.05 | E18: =CHOOSE(Dashboard!$B$4,B18,C18,D18) -> 0.03 | F18: % | G18: Low ≤ Base ≤ High
A19: Average ticket per meal (year 1) | B19: 13 | C19: 14 | D19: 15 | E19: =CHOOSE(Dashboard!$B$4,B19,C19,D19) -> 14 | F19: $ | G19: Low ≤ Base ≤ High
A20: Price increase per year | B20: 0.02 | C20: 0.03 | D20: 0.04 | E20: =CHOOSE(Dashboard!$B$4,B20,C20,D20) -> 0.03 | F20: % | G20: Low ≤ Base ≤ High
A22: Events & catering
A23: Event and catering days per truck per month (year 1) | B23: 2.5 | C23: 3 | D23: 3.5 | E23: =CHOOSE(Dashboard!$B$4,B23,C23,D23) -> 3 | F23: days | G23: Low ≤ Base ≤ High
A24: Event days growth per year | B24: 0 | C24: 0.05 | D24: 0.1 | E24: =CHOOSE(Dashboard!$B$4,B24,C24,D24) -> 0.05 | F24: % | G24: Low ≤ Base ≤ High
A25: Revenue per event or catering day (year 1) | B25: 1250 | C25: 1400 | D25: 1550 | E25: =CHOOSE(Dashboard!$B$4,B25,C25,D25) -> 1400 | F25: $ | G25: Low ≤ Base ≤ High
A26: Meals served per event or catering day | B26: 100 | C26: 100 | D26: 100 | E26: =CHOOSE(Dashboard!$B$4,B26,C26,D26) -> 100 | F26: meals
A28: Cost of sales
A29: Food cost, % of sales | B29: 0.345 | C29: 0.33 | D29: 0.315 | E29: =CHOOSE(Dashboard!$B$4,B29,C29,D29) -> 0.33 | F29: % | G29: Low ≥ Base ≥ High (lower is better)
A30: Packaging & disposables per meal (year 1) | B30: 0.5 | C30: 0.45 | D30: 0.4 | E30: =CHOOSE(Dashboard!$B$4,B30,C30,D30) -> 0.45 | F30: $ | G30: Low ≥ Base ≥ High (lower is better)
A31: Card & POS processing fees, % of revenue | B31: 0.031 | C31: 0.029 | D31: 0.027 | E31: =CHOOSE(Dashboard!$B$4,B31,C31,D31) -> 0.029 | F31: % | G31: Low ≥ Base ≥ High (lower is better)
A32: Event & festival fees, % of event revenue | B32: 0.05 | C32: 0.04 | D32: 0.03 | E32: =CHOOSE(Dashboard!$B$4,B32,C32,D32) -> 0.04 | F32: % | G32: Low ≥ Base ≥ High (lower is better)
A33: Event booth or vendor fee per event day (year 1) | B33: 120 | C33: 100 | D33: 80 | E33: =CHOOSE(Dashboard!$B$4,B33,C33,D33) -> 100 | F33: $ | G33: Low ≥ Base ≥ High (lower is better)
A34: Cost increase per year (packaging, fuel, fixed costs) | B34: 0.04 | C34: 0.03 | D34: 0.025 | E34: =CHOOSE(Dashboard!$B$4,B34,C34,D34) -> 0.03 | F34: % | G34: Low ≥ Base ≥ High (lower is better)
A36: Operating costs
A37: Commissary kitchen rent per truck per month | B37: 1050 | C37: 950 | D37: 850 | E37: =CHOOSE(Dashboard!$B$4,B37,C37,D37) -> 950 | F37: $
A38: Permits & licences per truck per month (annual fees ÷ 12) | B38: 400 | C38: 380 | D38: 360 | E38: =CHOOSE(Dashboard!$B$4,B38,C38,D38) -> 380 | F38: $
A39: Insurance per truck per month | B39: 480 | C39: 450 | D39: 420 | E39: =CHOOSE(Dashboard!$B$4,B39,C39,D39) -> 450 | F39: $
A40: Fuel, propane & generator per service day | B40: 40 | C40: 38 | D40: 36 | E40: =CHOOSE(Dashboard!$B$4,B40,C40,D40) -> 38 | F40: $
A41: Truck maintenance & repairs per truck per month | B41: 550 | C41: 500 | D41: 450 | E41: =CHOOSE(Dashboard!$B$4,B41,C41,D41) -> 500 | F41: $
A42: POS & ordering software per month | B42: 125 | C42: 120 | D42: 115 | E42: =CHOOSE(Dashboard!$B$4,B42,C42,D42) -> 120 | F42: $
A43: Marketing budget per month (year 1) | B43: 800 | C43: 700 | D43: 600 | E43: =CHOOSE(Dashboard!$B$4,B43,C43,D43) -> 700 | F43: $
A44: Marketing budget growth per year | B44: 0 | C44: 0 | D44: 0 | E44: =CHOOSE(Dashboard!$B$4,B44,C44,D44) -> 0 | F44: %
A45: Accounting, bank fees & other G&A per month | B45: 380 | C45: 350 | D45: 320 | E45: =CHOOSE(Dashboard!$B$4,B45,C45,D45) -> 350 | F45: $
A47: Capital spending
A48: Trucks to buy and build out in month 1 | B48: 1 | C48: 1 | D48: 1 | E48: =CHOOSE(Dashboard!$B$4,B48,C48,D48) -> 1 | F48: #
A49: Truck purchase, each | B49: 95000 | C49: 95000 | D49: 95000 | E49: =CHOOSE(Dashboard!$B$4,B49,C49,D49) -> 95000 | F49: $
A50: Kitchen build-out, equipment & wrap, per truck | B50: 40000 | C50: 40000 | D50: 40000 | E50: =CHOOSE(Dashboard!$B$4,B50,C50,D50) -> 40000 | F50: $
A51: POS hardware & smallwares (month 1) | B51: 3000 | C51: 3000 | D51: 3000 | E51: =CHOOSE(Dashboard!$B$4,B51,C51,D51) -> 3000 | F51: $
A52: Equipment refresh per truck per year (from year 2) | B52: 2500 | C52: 2500 | D52: 2500 | E52: =CHOOSE(Dashboard!$B$4,B52,C52,D52) -> 2500 | F52: $
A54: Headcount
A55: Owner-operator (salary optional): headcount (FTE) | B55: 1 | C55: 1 | D55: 1 | E55: =CHOOSE(Dashboard!$B$4,B55,C55,D55) -> 1 | F55: FTE | G55: Low ≤ Base ≤ High
A56: Owner-operator (salary optional): salary per FTE per year | B56: 36000 | C56: 36000 | D56: 36000 | E56: =CHOOSE(Dashboard!$B$4,B56,C56,D56) -> 36000 | F56: $
A57: Owner-operator (salary optional): headcount growth per year | B57: 0 | C57: 0 | D57: 0 | E57: =CHOOSE(Dashboard!$B$4,B57,C57,D57) -> 0 | F57: % | G57: Low ≤ Base ≤ High
A58: Owner-operator (salary optional): first month on payroll | B58: 1 | C58: 1 | D58: 1 | E58: =CHOOSE(Dashboard!$B$4,B58,C58,D58) -> 1 | F58: month #
A59: Cooks: headcount (FTE) | B59: 1.2 | C59: 1.2 | D59: 1.2 | E59: =CHOOSE(Dashboard!$B$4,B59,C59,D59) -> 1.2 | F59: FTE | G59: Low ≤ Base ≤ High
A60: Cooks: salary per FTE per year | B60: 34000 | C60: 34000 | D60: 34000 | E60: =CHOOSE(Dashboard!$B$4,B60,C60,D60) -> 34000 | F60: $
A61: Cooks: headcount growth per year | B61: 0 | C61: 0 | D61: 0 | E61: =CHOOSE(Dashboard!$B$4,B61,C61,D61) -> 0 | F61: % | G61: Low ≤ Base ≤ High
A62: Cooks: first month on payroll | B62: 1 | C62: 1 | D62: 1 | E62: =CHOOSE(Dashboard!$B$4,B62,C62,D62) -> 1 | F62: month #
A63: Cashiers & service staff: headcount (FTE) | B63: 1 | C63: 1 | D63: 1 | E63: =CHOOSE(Dashboard!$B$4,B63,C63,D63) -> 1 | F63: FTE | G63: Low ≤ Base ≤ High
A64: Cashiers & service staff: salary per FTE per year | B64: 29000 | C64: 29000 | D64: 29000 | E64: =CHOOSE(Dashboard!$B$4,B64,C64,D64) -> 29000 | F64: $
A65: Cashiers & service staff: headcount growth per year | B65: 0 | C65: 0 | D65: 0 | E65: =CHOOSE(Dashboard!$B$4,B65,C65,D65) -> 0 | F65: % | G65: Low ≤ Base ≤ High
A66: Cashiers & service staff: first month on payroll | B66: 1 | C66: 1 | D66: 1 | E66: =CHOOSE(Dashboard!$B$4,B66,C66,D66) -> 1 | F66: month #
A67: Payroll taxes & benefits, % of salary | B67: 0.12 | C67: 0.12 | D67: 0.12 | E67: =CHOOSE(Dashboard!$B$4,B67,C67,D67) -> 0.12 | F67: %
A68: Wage growth per year | B68: 0.03 | C68: 0.03 | D68: 0.03 | E68: =CHOOSE(Dashboard!$B$4,B68,C68,D68) -> 0.03 | F68: %
A70: Funding
A71: Equity raised at start | B71: 100000 | C71: 100000 | D71: 100000 | E71: =CHOOSE(Dashboard!$B$4,B71,C71,D71) -> 100000 | F71: $
A72: Loan drawn at start | B72: 90000 | C72: 90000 | D72: 90000 | E72: =CHOOSE(Dashboard!$B$4,B72,C72,D72) -> 90000 | F72: $
A73: Loan interest rate per year | B73: 0.09 | C73: 0.09 | D73: 0.09 | E73: =CHOOSE(Dashboard!$B$4,B73,C73,D73) -> 0.09 | F73: %
A74: Loan repayment term | B74: 5 | C74: 5 | D74: 5 | E74: =CHOOSE(Dashboard!$B$4,B74,C74,D74) -> 5 | F74: years
A76: Working capital
A77: Customer payment terms (receivable days) | B77: 3 | C77: 3 | D77: 3 | E77: =CHOOSE(Dashboard!$B$4,B77,C77,D77) -> 3 | F77: days
A78: Inventory held (days of COGS) | B78: 3 | C78: 3 | D78: 3 | E78: =CHOOSE(Dashboard!$B$4,B78,C78,D78) -> 3 | F78: days
A79: Supplier payment terms (payable days) | B79: 7 | C79: 7 | D79: 7 | E79: =CHOOSE(Dashboard!$B$4,B79,C79,D79) -> 7 | F79: days
A81: Tax & depreciation
A82: Depreciation period for capex | B82: 7 | C82: 7 | D82: 7 | E82: =CHOOSE(Dashboard!$B$4,B82,C82,D82) -> 7 | F82: years
A83: Income tax rate | B83: 0.21 | C83: 0.21 | D83: 0.21 | E83: =CHOOSE(Dashboard!$B$4,B83,C83,D83) -> 0.21 | F83: %
A85: Break-even & funding
A86: Minimum cash buffer to keep | B86: 42000 | C86: 42000 | D86: 42000 | E86: =CHOOSE(Dashboard!$B$4,B86,C86,D86) -> 42000 | F86: $ | G86: About 3 months of costs
A88: Valuation
A89: Discount rate (WACC) | B89: 0.3 | C89: 0.25 | D89: 0.2 | E89: =CHOOSE(Dashboard!$B$4,B89,C89,D89) -> 0.25 | F89: % | G89: Low ≥ Base ≥ High (lower is better)
A90: Terminal growth rate (perpetuity) | B90: 0.01 | C90: 0.02 | D90: 0.03 | E90: =CHOOSE(Dashboard!$B$4,B90,C90,D90) -> 0.02 | F90: % | G90: Low ≤ Base ≤ High
A91: Exit multiple (EV ÷ final-year EBITDA) | B91: 3 | C91: 4 | D91: 5 | E91: =CHOOSE(Dashboard!$B$4,B91,C91,D91) -> 4 | F91: x | G91: Low ≤ Base ≤ High
A92: Sensitivity table: WACC step | B92: 0.01 | C92: 0.01 | D92: 0.01 | E92: =CHOOSE(Dashboard!$B$4,B92,C92,D92) -> 0.01 | F92: %
A93: Sensitivity table: growth step | B93: 0.005 | C93: 0.005 | D93: 0.005 | E93: =CHOOSE(Dashboard!$B$4,B93,C93,D93) -> 0.005 | F93: %
A95: Legend: yellow cell with blue figure = input you can change · black = formula · green = link to another sheet · grey = active value (column E follows the scenario on the Dashboard).

Sheet P&L
A1: Annual profit & loss | H1: =HYPERLINK("#'Cover'!A1","◂ Contents") -> ◂ Contents
A2: Rolled up from the period detail (SUMIF on the year row; balances at year end).
A3: Year # | B3: 1 | C3: 2 | D3: 3 | E3: 4 | F3: 5
B4: Year 1 | C4: Year 2 | D4: Year 3 | E4: Year 4 | F4: Year 5
A5: Revenue | B5: =SUMIF(Monthly!$C$5:$BJ$5,B$3,Monthly!$C$24:$BJ$24) -> 273896 | C5: =SUMIF(Monthly!$C$5:$BJ$5,C$3,Monthly!$C$24:$BJ$24) -> 336825.82 | D5: =SUMIF(Monthly!$C$5:$BJ$5,D$3,Monthly!$C$24:$BJ$24) -> 358461.37 | E5: =SUMIF(Monthly!$C$5:$BJ$5,E$3,Monthly!$C$24:$BJ$24) -> 381506.04 | F5: =SUMIF(Monthly!$C$5:$BJ$5,F$3,Monthly!$C$24:$BJ$24) -> 406053.09
A6: Cost of sales | B6: =SUMIF(Monthly!$C$5:$BJ$5,B$3,Monthly!$C$32:$BJ$32) -> -111929.46 | C6: =SUMIF(Monthly!$C$5:$BJ$5,C$3,Monthly!$C$32:$BJ$32) -> -137820.72 | D6: =SUMIF(Monthly!$C$5:$BJ$5,D$3,Monthly!$C$32:$BJ$32) -> -146778.32 | E6: =SUMIF(Monthly!$C$5:$BJ$5,E$3,Monthly!$C$32:$BJ$32) -> -156327.42 | F6: =SUMIF(Monthly!$C$5:$BJ$5,F$3,Monthly!$C$32:$BJ$32) -> -166507.81
A7: Gross profit | B7: =SUMIF(Monthly!$C$5:$BJ$5,B$3,Monthly!$C$33:$BJ$33) -> 161966.54 | C7: =SUMIF(Monthly!$C$5:$BJ$5,C$3,Monthly!$C$33:$BJ$33) -> 199005.1 | D7: =SUMIF(Monthly!$C$5:$BJ$5,D$3,Monthly!$C$33:$BJ$33) -> 211683.05 | E7: =SUMIF(Monthly!$C$5:$BJ$5,E$3,Monthly!$C$33:$BJ$33) -> 225178.61 | F7: =SUMIF(Monthly!$C$5:$BJ$5,F$3,Monthly!$C$33:$BJ$33) -> 239545.29
A8: Gross margin | B8: =IF(B5=0,0,B7/B5) -> 0.5913432 | C8: =IF(C5=0,0,C7/C5) -> 0.59082496 | D8: =IF(D5=0,0,D7/D5) -> 0.5905324 | E8: =IF(E5=0,0,E7/E5) -> 0.59023605 | F8: =IF(F5=0,0,F7/F5) -> 0.58993587
A9: Payroll (owner-operator, cooks, cashiers) | B9: =SUMIF(Monthly!$C$5:$BJ$5,B$3,Monthly!$C$36:$BJ$36) -> -118496 | C9: =SUMIF(Monthly!$C$5:$BJ$5,C$3,Monthly!$C$36:$BJ$36) -> -122050.88 | D9: =SUMIF(Monthly!$C$5:$BJ$5,D$3,Monthly!$C$36:$BJ$36) -> -125712.41 | E9: =SUMIF(Monthly!$C$5:$BJ$5,E$3,Monthly!$C$36:$BJ$36) -> -129483.78 | F9: =SUMIF(Monthly!$C$5:$BJ$5,F$3,Monthly!$C$36:$BJ$36) -> -133368.29
A10: Commissary kitchen | B10: =SUMIF(Monthly!$C$5:$BJ$5,B$3,Monthly!$C$37:$BJ$37) -> -11400 | C10: =SUMIF(Monthly!$C$5:$BJ$5,C$3,Monthly!$C$37:$BJ$37) -> -11742 | D10: =SUMIF(Monthly!$C$5:$BJ$5,D$3,Monthly!$C$37:$BJ$37) -> -12094.26 | E10: =SUMIF(Monthly!$C$5:$BJ$5,E$3,Monthly!$C$37:$BJ$37) -> -12457.088 | F10: =SUMIF(Monthly!$C$5:$BJ$5,F$3,Monthly!$C$37:$BJ$37) -> -12830.8
A11: Permits & licences | B11: =SUMIF(Monthly!$C$5:$BJ$5,B$3,Monthly!$C$38:$BJ$38) -> -4560 | C11: =SUMIF(Monthly!$C$5:$BJ$5,C$3,Monthly!$C$38:$BJ$38) -> -4696.8 | D11: =SUMIF(Monthly!$C$5:$BJ$5,D$3,Monthly!$C$38:$BJ$38) -> -4837.704 | E11: =SUMIF(Monthly!$C$5:$BJ$5,E$3,Monthly!$C$38:$BJ$38) -> -4982.8351 | F11: =SUMIF(Monthly!$C$5:$BJ$5,F$3,Monthly!$C$38:$BJ$38) -> -5132.3202
A12: Insurance | B12: =SUMIF(Monthly!$C$5:$BJ$5,B$3,Monthly!$C$39:$BJ$39) -> -5400 | C12: =SUMIF(Monthly!$C$5:$BJ$5,C$3,Monthly!$C$39:$BJ$39) -> -5562 | D12: =SUMIF(Monthly!$C$5:$BJ$5,D$3,Monthly!$C$39:$BJ$39) -> -5728.86 | E12: =SUMIF(Monthly!$C$5:$BJ$5,E$3,Monthly!$C$39:$BJ$39) -> -5900.7258 | F12: =SUMIF(Monthly!$C$5:$BJ$5,F$3,Monthly!$C$39:$BJ$39) -> -6077.7476
A13: Fuel, propane & generator | B13: =SUMIF(Monthly!$C$5:$BJ$5,B$3,Monthly!$C$40:$BJ$40) -> -9376.5 | C13: =SUMIF(Monthly!$C$5:$BJ$5,C$3,Monthly!$C$40:$BJ$40) -> -9933.732 | D13: =SUMIF(Monthly!$C$5:$BJ$5,D$3,Monthly!$C$40:$BJ$40) -> -10307.938 | E13: =SUMIF(Monthly!$C$5:$BJ$5,E$3,Monthly!$C$40:$BJ$40) -> -10699.58 | F13: =SUMIF(Monthly!$C$5:$BJ$5,F$3,Monthly!$C$40:$BJ$40) -> -11109.686
A14: Truck maintenance & repairs | B14: =SUMIF(Monthly!$C$5:$BJ$5,B$3,Monthly!$C$41:$BJ$41) -> -6000 | C14: =SUMIF(Monthly!$C$5:$BJ$5,C$3,Monthly!$C$41:$BJ$41) -> -6180 | D14: =SUMIF(Monthly!$C$5:$BJ$5,D$3,Monthly!$C$41:$BJ$41) -> -6365.4 | E14: =SUMIF(Monthly!$C$5:$BJ$5,E$3,Monthly!$C$41:$BJ$41) -> -6556.362 | F14: =SUMIF(Monthly!$C$5:$BJ$5,F$3,Monthly!$C$41:$BJ$41) -> -6753.0529
A15: POS & ordering software | B15: =SUMIF(Monthly!$C$5:$BJ$5,B$3,Monthly!$C$42:$BJ$42) -> -1440 | C15: =SUMIF(Monthly!$C$5:$BJ$5,C$3,Monthly!$C$42:$BJ$42) -> -1483.2 | D15: =SUMIF(Monthly!$C$5:$BJ$5,D$3,Monthly!$C$42:$BJ$42) -> -1527.696 | E15: =SUMIF(Monthly!$C$5:$BJ$5,E$3,Monthly!$C$42:$BJ$42) -> -1573.5269 | F15: =SUMIF(Monthly!$C$5:$BJ$5,F$3,Monthly!$C$42:$BJ$42) -> -1620.7327
A16: Marketing | B16: =SUMIF(Monthly!$C$5:$BJ$5,B$3,Monthly!$C$43:$BJ$43) -> -8400 | C16: =SUMIF(Monthly!$C$5:$BJ$5,C$3,Monthly!$C$43:$BJ$43) -> -8400 | D16: =SUMIF(Monthly!$C$5:$BJ$5,D$3,Monthly!$C$43:$BJ$43) -> -8400 | E16: =SUMIF(Monthly!$C$5:$BJ$5,E$3,Monthly!$C$43:$BJ$43) -> -8400 | F16: =SUMIF(Monthly!$C$5:$BJ$5,F$3,Monthly!$C$43:$BJ$43) -> -8400
A17: Accounting, bank fees & other G&A | B17: =SUMIF(Monthly!$C$5:$BJ$5,B$3,Monthly!$C$44:$BJ$44) -> -4200 | C17: =SUMIF(Monthly!$C$5:$BJ$5,C$3,Monthly!$C$44:$BJ$44) -> -4326 | D17: =SUMIF(Monthly!$C$5:$BJ$5,D$3,Monthly!$C$44:$BJ$44) -> -4455.78 | E17: =SUMIF(Monthly!$C$5:$BJ$5,E$3,Monthly!$C$44:$BJ$44) -> -4589.4534 | F17: =SUMIF(Monthly!$C$5:$BJ$5,F$3,Monthly!$C$44:$BJ$44) -> -4727.137
A18: Total operating expenses | B18: =SUMIF(Monthly!$C$5:$BJ$5,B$3,Monthly!$C$45:$BJ$45) -> -169272.5 | C18: =SUMIF(Monthly!$C$5:$BJ$5,C$3,Monthly!$C$45:$BJ$45) -> -174374.61 | D18: =SUMIF(Monthly!$C$5:$BJ$5,D$3,Monthly!$C$45:$BJ$45) -> -179430.04 | E18: =SUMIF(Monthly!$C$5:$BJ$5,E$3,Monthly!$C$45:$BJ$45) -> -184643.35 | F18: =SUMIF(Monthly!$C$5:$BJ$5,F$3,Monthly!$C$45:$BJ$45) -> -190019.77
A19: EBITDA | B19: =SUMIF(Monthly!$C$5:$BJ$5,B$3,Monthly!$C$46:$BJ$46) -> -7305.964 | C19: =SUMIF(Monthly!$C$5:$BJ$5,C$3,Monthly!$C$46:$BJ$46) -> 24630.491 | D19: =SUMIF(Monthly!$C$5:$BJ$5,D$3,Monthly!$C$46:$BJ$46) -> 32253.01 | E19: =SUMIF(Monthly!$C$5:$BJ$5,E$3,Monthly!$C$46:$BJ$46) -> 40535.265 | F19: =SUMIF(Monthly!$C$5:$BJ$5,F$3,Monthly!$C$46:$BJ$46) -> 49525.516
A20: EBITDA margin | B20: =IF(B5=0,0,B19/B5) -> -0.026674227 | C20: =IF(C5=0,0,C19/C5) -> 0.073125305 | D20: =IF(D5=0,0,D19/D5) -> 0.089976252 | E20: =IF(E5=0,0,E19/E5) -> 0.10625065 | F20: =IF(F5=0,0,F19/F5) -> 0.12196808
A21: Depreciation | B21: =SUMIF(Monthly!$C$5:$BJ$5,B$3,Monthly!$C$64:$BJ$64) -> -19714.286 | C21: =SUMIF(Monthly!$C$5:$BJ$5,C$3,Monthly!$C$64:$BJ$64) -> -20071.429 | D21: =SUMIF(Monthly!$C$5:$BJ$5,D$3,Monthly!$C$64:$BJ$64) -> -20428.571 | E21: =SUMIF(Monthly!$C$5:$BJ$5,E$3,Monthly!$C$64:$BJ$64) -> -20785.714 | F21: =SUMIF(Monthly!$C$5:$BJ$5,F$3,Monthly!$C$64:$BJ$64) -> -21142.857
A22: EBIT | B22: =SUMIF(Monthly!$C$5:$BJ$5,B$3,Monthly!$C$49:$BJ$49) -> -27020.25 | C22: =SUMIF(Monthly!$C$5:$BJ$5,C$3,Monthly!$C$49:$BJ$49) -> 4559.0623 | D22: =SUMIF(Monthly!$C$5:$BJ$5,D$3,Monthly!$C$49:$BJ$49) -> 11824.439 | E22: =SUMIF(Monthly!$C$5:$BJ$5,E$3,Monthly!$C$49:$BJ$49) -> 19749.551 | F22: =SUMIF(Monthly!$C$5:$BJ$5,F$3,Monthly!$C$49:$BJ$49) -> 28382.659
A23: Interest | B23: =SUMIF(Monthly!$C$5:$BJ$5,B$3,Monthly!$C$50:$BJ$50) -> -7419.375 | C23: =SUMIF(Monthly!$C$5:$BJ$5,C$3,Monthly!$C$50:$BJ$50) -> -5805 | D23: =SUMIF(Monthly!$C$5:$BJ$5,D$3,Monthly!$C$50:$BJ$50) -> -4185 | E23: =SUMIF(Monthly!$C$5:$BJ$5,E$3,Monthly!$C$50:$BJ$50) -> -2565 | F23: =SUMIF(Monthly!$C$5:$BJ$5,F$3,Monthly!$C$50:$BJ$50) -> -945
A24: Pre-tax income | B24: =SUMIF(Monthly!$C$5:$BJ$5,B$3,Monthly!$C$51:$BJ$51) -> -34439.625 | C24: =SUMIF(Monthly!$C$5:$BJ$5,C$3,Monthly!$C$51:$BJ$51) -> -1245.9377 | D24: =SUMIF(Monthly!$C$5:$BJ$5,D$3,Monthly!$C$51:$BJ$51) -> 7639.439 | E24: =SUMIF(Monthly!$C$5:$BJ$5,E$3,Monthly!$C$51:$BJ$51) -> 17184.551 | F24: =SUMIF(Monthly!$C$5:$BJ$5,F$3,Monthly!$C$51:$BJ$51) -> 27437.659
A25: Income tax | B25: =SUMIF(Monthly!$C$5:$BJ$5,B$3,Monthly!$C$54:$BJ$54) -> 0 | C25: =SUMIF(Monthly!$C$5:$BJ$5,C$3,Monthly!$C$54:$BJ$54) -> 0 | D25: =SUMIF(Monthly!$C$5:$BJ$5,D$3,Monthly!$C$54:$BJ$54) -> 0 | E25: =SUMIF(Monthly!$C$5:$BJ$5,E$3,Monthly!$C$54:$BJ$54) -> 0 | F25: =SUMIF(Monthly!$C$5:$BJ$5,F$3,Monthly!$C$54:$BJ$54) -> -3845.3658
A26: Net income | B26: =SUMIF(Monthly!$C$5:$BJ$5,B$3,Monthly!$C$55:$BJ$55) -> -34439.625 | C26: =SUMIF(Monthly!$C$5:$BJ$5,C$3,Monthly!$C$55:$BJ$55) -> -1245.9377 | D26: =SUMIF(Monthly!$C$5:$BJ$5,D$3,Monthly!$C$55:$BJ$55) -> 7639.439 | E26: =SUMIF(Monthly!$C$5:$BJ$5,E$3,Monthly!$C$55:$BJ$55) -> 17184.551 | F26: =SUMIF(Monthly!$C$5:$BJ$5,F$3,Monthly!$C$55:$BJ$55) -> 23592.293
A27: Net margin | B27: =IF(B5=0,0,B26/B5) -> -0.12573979 | C27: =IF(C5=0,0,C26/C5) -> -0.0036990563 | D27: =IF(D5=0,0,D26/D5) -> 0.02131175 | E27: =IF(E5=0,0,E26/E5) -> 0.045043982 | F27: =IF(F5=0,0,F26/F5) -> 0.058101498

Sheet Cash Flow
A1: Annual cash flow statement | H1: =HYPERLINK("#'Cover'!A1","◂ Contents") -> ◂ Contents
A2: Rolled up from the period detail (SUMIF on the year row; balances at year end).
A3: Year # | B3: 1 | C3: 2 | D3: 3 | E3: 4 | F3: 5
B4: Year 1 | C4: Year 2 | D4: Year 3 | E4: Year 4 | F4: Year 5
A5: Net income | B5: =SUMIF(Monthly!$C$5:$BJ$5,B$3,Monthly!$C$55:$BJ$55) -> -34439.625 | C5: =SUMIF(Monthly!$C$5:$BJ$5,C$3,Monthly!$C$55:$BJ$55) -> -1245.9377 | D5: =SUMIF(Monthly!$C$5:$BJ$5,D$3,Monthly!$C$55:$BJ$55) -> 7639.439 | E5: =SUMIF(Monthly!$C$5:$BJ$5,E$3,Monthly!$C$55:$BJ$55) -> 17184.551 | F5: =SUMIF(Monthly!$C$5:$BJ$5,F$3,Monthly!$C$55:$BJ$55) -> 23592.293
A6: Add back depreciation | B6: =-SUMIF(Monthly!$C$5:$BJ$5,B$3,Monthly!$C$64:$BJ$64) -> 19714.286 | C6: =-SUMIF(Monthly!$C$5:$BJ$5,C$3,Monthly!$C$64:$BJ$64) -> 20071.429 | D6: =-SUMIF(Monthly!$C$5:$BJ$5,D$3,Monthly!$C$64:$BJ$64) -> 20428.571 | E6: =-SUMIF(Monthly!$C$5:$BJ$5,E$3,Monthly!$C$64:$BJ$64) -> 20785.714 | F6: =-SUMIF(Monthly!$C$5:$BJ$5,F$3,Monthly!$C$64:$BJ$64) -> 21142.857
A7: (Increase) / decrease in receivables | B7: =SUMIF(Monthly!$C$5:$BJ$5,B$3,Monthly!$C$78:$BJ$78) -> -2083.2 | C7: =SUMIF(Monthly!$C$5:$BJ$5,C$3,Monthly!$C$78:$BJ$78) -> -135.51888 | D7: =SUMIF(Monthly!$C$5:$BJ$5,D$3,Monthly!$C$78:$BJ$78) -> -144.47712 | E7: =SUMIF(Monthly!$C$5:$BJ$5,E$3,Monthly!$C$78:$BJ$78) -> -154.03838 | F7: =SUMIF(Monthly!$C$5:$BJ$5,F$3,Monthly!$C$78:$BJ$78) -> -164.24408
A8: (Increase) / decrease in inventory | B8: =SUMIF(Monthly!$C$5:$BJ$5,B$3,Monthly!$C$79:$BJ$79) -> -861.6288 | C8: =SUMIF(Monthly!$C$5:$BJ$5,C$3,Monthly!$C$79:$BJ$79) -> -56.821442 | D8: =SUMIF(Monthly!$C$5:$BJ$5,D$3,Monthly!$C$79:$BJ$79) -> -60.63625 | E8: =SUMIF(Monthly!$C$5:$BJ$5,E$3,Monthly!$C$79:$BJ$79) -> -64.712262 | F8: =SUMIF(Monthly!$C$5:$BJ$5,F$3,Monthly!$C$79:$BJ$79) -> -69.067739
A9: Increase / (decrease) in payables | B9: =SUMIF(Monthly!$C$5:$BJ$5,B$3,Monthly!$C$80:$BJ$80) -> 2010.4672 | C9: =SUMIF(Monthly!$C$5:$BJ$5,C$3,Monthly!$C$80:$BJ$80) -> 132.58336 | D9: =SUMIF(Monthly!$C$5:$BJ$5,D$3,Monthly!$C$80:$BJ$80) -> 141.48458 | E9: =SUMIF(Monthly!$C$5:$BJ$5,E$3,Monthly!$C$80:$BJ$80) -> 150.99528 | F9: =SUMIF(Monthly!$C$5:$BJ$5,F$3,Monthly!$C$80:$BJ$80) -> 161.15806
A10: Operating cash flow | B10: =SUMIF(Monthly!$C$5:$BJ$5,B$3,Monthly!$C$83:$BJ$83) -> -15659.701 | C10: =SUMIF(Monthly!$C$5:$BJ$5,C$3,Monthly!$C$83:$BJ$83) -> 18765.734 | D10: =SUMIF(Monthly!$C$5:$BJ$5,D$3,Monthly!$C$83:$BJ$83) -> 28004.382 | E10: =SUMIF(Monthly!$C$5:$BJ$5,E$3,Monthly!$C$83:$BJ$83) -> 37902.51 | F10: =SUMIF(Monthly!$C$5:$BJ$5,F$3,Monthly!$C$83:$BJ$83) -> 44662.997
A11: Capital spending | B11: =SUMIF(Monthly!$C$5:$BJ$5,B$3,Monthly!$C$84:$BJ$84) -> -138000 | C11: =SUMIF(Monthly!$C$5:$BJ$5,C$3,Monthly!$C$84:$BJ$84) -> -2500 | D11: =SUMIF(Monthly!$C$5:$BJ$5,D$3,Monthly!$C$84:$BJ$84) -> -2500 | E11: =SUMIF(Monthly!$C$5:$BJ$5,E$3,Monthly!$C$84:$BJ$84) -> -2500 | F11: =SUMIF(Monthly!$C$5:$BJ$5,F$3,Monthly!$C$84:$BJ$84) -> -2500
A12: Equity raised | B12: =SUMIF(Monthly!$C$5:$BJ$5,B$3,Monthly!$C$85:$BJ$85) -> 100000 | C12: =SUMIF(Monthly!$C$5:$BJ$5,C$3,Monthly!$C$85:$BJ$85) -> 0 | D12: =SUMIF(Monthly!$C$5:$BJ$5,D$3,Monthly!$C$85:$BJ$85) -> 0 | E12: =SUMIF(Monthly!$C$5:$BJ$5,E$3,Monthly!$C$85:$BJ$85) -> 0 | F12: =SUMIF(Monthly!$C$5:$BJ$5,F$3,Monthly!$C$85:$BJ$85) -> 0
A13: Loan drawdown | B13: =SUMIF(Monthly!$C$5:$BJ$5,B$3,Monthly!$C$70:$BJ$70) -> 90000 | C13: =SUMIF(Monthly!$C$5:$BJ$5,C$3,Monthly!$C$70:$BJ$70) -> 0 | D13: =SUMIF(Monthly!$C$5:$BJ$5,D$3,Monthly!$C$70:$BJ$70) -> 0 | E13: =SUMIF(Monthly!$C$5:$BJ$5,E$3,Monthly!$C$70:$BJ$70) -> 0 | F13: =SUMIF(Monthly!$C$5:$BJ$5,F$3,Monthly!$C$70:$BJ$70) -> 0
A14: Loan repayment | B14: =SUMIF(Monthly!$C$5:$BJ$5,B$3,Monthly!$C$71:$BJ$71) -> -16500 | C14: =SUMIF(Monthly!$C$5:$BJ$5,C$3,Monthly!$C$71:$BJ$71) -> -18000 | D14: =SUMIF(Monthly!$C$5:$BJ$5,D$3,Monthly!$C$71:$BJ$71) -> -18000 | E14: =SUMIF(Monthly!$C$5:$BJ$5,E$3,Monthly!$C$71:$BJ$71) -> -18000 | F14: =SUMIF(Monthly!$C$5:$BJ$5,F$3,Monthly!$C$71:$BJ$71) -> -18000
A15: Financing cash flow | B15: =SUMIF(Monthly!$C$5:$BJ$5,B$3,Monthly!$C$86:$BJ$86) -> 173500 | C15: =SUMIF(Monthly!$C$5:$BJ$5,C$3,Monthly!$C$86:$BJ$86) -> -18000 | D15: =SUMIF(Monthly!$C$5:$BJ$5,D$3,Monthly!$C$86:$BJ$86) -> -18000 | E15: =SUMIF(Monthly!$C$5:$BJ$5,E$3,Monthly!$C$86:$BJ$86) -> -18000 | F15: =SUMIF(Monthly!$C$5:$BJ$5,F$3,Monthly!$C$86:$BJ$86) -> -18000
A16: Net change in cash | B16: =SUMIF(Monthly!$C$5:$BJ$5,B$3,Monthly!$C$87:$BJ$87) -> 19840.299 | C16: =SUMIF(Monthly!$C$5:$BJ$5,C$3,Monthly!$C$87:$BJ$87) -> -1734.2661 | D16: =SUMIF(Monthly!$C$5:$BJ$5,D$3,Monthly!$C$87:$BJ$87) -> 7504.3816 | E16: =SUMIF(Monthly!$C$5:$BJ$5,E$3,Monthly!$C$87:$BJ$87) -> 17402.51 | F16: =SUMIF(Monthly!$C$5:$BJ$5,F$3,Monthly!$C$87:$BJ$87) -> 24162.997
A17: Opening cash | B17: =INDEX(Monthly!$C$88:$BJ$88,(B$3-1)*12+1) -> 0 | C17: =INDEX(Monthly!$C$88:$BJ$88,(C$3-1)*12+1) -> 19840.299 | D17: =INDEX(Monthly!$C$88:$BJ$88,(D$3-1)*12+1) -> 18106.033 | E17: =INDEX(Monthly!$C$88:$BJ$88,(E$3-1)*12+1) -> 25610.415 | F17: =INDEX(Monthly!$C$88:$BJ$88,(F$3-1)*12+1) -> 43012.925
A18: Closing cash | B18: =INDEX(Monthly!$C$89:$BJ$89,B$3*12) -> 19840.299 | C18: =INDEX(Monthly!$C$89:$BJ$89,C$3*12) -> 18106.033 | D18: =INDEX(Monthly!$C$89:$BJ$89,D$3*12) -> 25610.415 | E18: =INDEX(Monthly!$C$89:$BJ$89,E$3*12) -> 43012.925 | F18: =INDEX(Monthly!$C$89:$BJ$89,F$3*12) -> 67175.922

Sheet Balance Sheet
A1: Balance sheet at year end | H1: =HYPERLINK("#'Cover'!A1","◂ Contents") -> ◂ Contents
A2: Rolled up from the period detail (SUMIF on the year row; balances at year end).
A3: Year # | B3: 1 | C3: 2 | D3: 3 | E3: 4 | F3: 5
B4: Year 1 | C4: Year 2 | D4: Year 3 | E4: Year 4 | F4: Year 5
A5: Cash | B5: =INDEX(Monthly!$C$89:$BJ$89,B$3*12) -> 19840.299 | C5: =INDEX(Monthly!$C$89:$BJ$89,C$3*12) -> 18106.033 | D5: =INDEX(Monthly!$C$89:$BJ$89,D$3*12) -> 25610.415 | E5: =INDEX(Monthly!$C$89:$BJ$89,E$3*12) -> 43012.925 | F5: =INDEX(Monthly!$C$89:$BJ$89,F$3*12) -> 67175.922
A6: Accounts receivable | B6: =INDEX(Monthly!$C$75:$BJ$75,B$3*12) -> 2083.2 | C6: =INDEX(Monthly!$C$75:$BJ$75,C$3*12) -> 2218.7189 | D6: =INDEX(Monthly!$C$75:$BJ$75,D$3*12) -> 2363.196 | E6: =INDEX(Monthly!$C$75:$BJ$75,E$3*12) -> 2517.2344 | F6: =INDEX(Monthly!$C$75:$BJ$75,F$3*12) -> 2681.4785
A7: Inventory | B7: =INDEX(Monthly!$C$76:$BJ$76,B$3*12) -> 861.6288 | C7: =INDEX(Monthly!$C$76:$BJ$76,C$3*12) -> 918.45024 | D7: =INDEX(Monthly!$C$76:$BJ$76,D$3*12) -> 979.08649 | E7: =INDEX(Monthly!$C$76:$BJ$76,E$3*12) -> 1043.7988 | F7: =INDEX(Monthly!$C$76:$BJ$76,F$3*12) -> 1112.8665
A8: Net fixed assets | B8: =INDEX(Monthly!$C$66:$BJ$66,B$3*12) -> 118285.71 | C8: =INDEX(Monthly!$C$66:$BJ$66,C$3*12) -> 100714.29 | D8: =INDEX(Monthly!$C$66:$BJ$66,D$3*12) -> 82785.714 | E8: =INDEX(Monthly!$C$66:$BJ$66,E$3*12) -> 64500 | F8: =INDEX(Monthly!$C$66:$BJ$66,F$3*12) -> 45857.143
A9: Total assets | B9: =INDEX(Monthly!$C$103:$BJ$103,B$3*12) -> 141070.84 | C9: =INDEX(Monthly!$C$103:$BJ$103,C$3*12) -> 121957.49 | D9: =INDEX(Monthly!$C$103:$BJ$103,D$3*12) -> 111738.41 | E9: =INDEX(Monthly!$C$103:$BJ$103,E$3*12) -> 111073.96 | F9: =INDEX(Monthly!$C$103:$BJ$103,F$3*12) -> 116827.41
A10: Accounts payable | B10: =INDEX(Monthly!$C$77:$BJ$77,B$3*12) -> 2010.4672 | C10: =INDEX(Monthly!$C$77:$BJ$77,C$3*12) -> 2143.0506 | D10: =INDEX(Monthly!$C$77:$BJ$77,D$3*12) -> 2284.5351 | E10: =INDEX(Monthly!$C$77:$BJ$77,E$3*12) -> 2435.5304 | F10: =INDEX(Monthly!$C$77:$BJ$77,F$3*12) -> 2596.6885
A11: Loan | B11: =INDEX(Monthly!$C$72:$BJ$72,B$3*12) -> 73500 | C11: =INDEX(Monthly!$C$72:$BJ$72,C$3*12) -> 55500 | D11: =INDEX(Monthly!$C$72:$BJ$72,D$3*12) -> 37500 | E11: =INDEX(Monthly!$C$72:$BJ$72,E$3*12) -> 19500 | F11: =INDEX(Monthly!$C$72:$BJ$72,F$3*12) -> 1500
A12: Total liabilities | B12: =INDEX(Monthly!$C$104:$BJ$104,B$3*12) -> 75510.467 | C12: =INDEX(Monthly!$C$104:$BJ$104,C$3*12) -> 57643.051 | D12: =INDEX(Monthly!$C$104:$BJ$104,D$3*12) -> 39784.535 | E12: =INDEX(Monthly!$C$104:$BJ$104,E$3*12) -> 21935.53 | F12: =INDEX(Monthly!$C$104:$BJ$104,F$3*12) -> 4096.6885
A13: Paid-in capital | B13: =INDEX(Monthly!$C$101:$BJ$101,B$3*12) -> 100000 | C13: =INDEX(Monthly!$C$101:$BJ$101,C$3*12) -> 100000 | D13: =INDEX(Monthly!$C$101:$BJ$101,D$3*12) -> 100000 | E13: =INDEX(Monthly!$C$101:$BJ$101,E$3*12) -> 100000 | F13: =INDEX(Monthly!$C$101:$BJ$101,F$3*12) -> 100000
A14: Retained earnings | B14: =INDEX(Monthly!$C$102:$BJ$102,B$3*12) -> -34439.625 | C14: =INDEX(Monthly!$C$102:$BJ$102,C$3*12) -> -35685.562 | D14: =INDEX(Monthly!$C$102:$BJ$102,D$3*12) -> -28046.123 | E14: =INDEX(Monthly!$C$102:$BJ$102,E$3*12) -> -10861.572 | F14: =INDEX(Monthly!$C$102:$BJ$102,F$3*12) -> 12730.721
A15: Total equity | B15: =INDEX(Monthly!$C$105:$BJ$105,B$3*12) -> 65560.375 | C15: =INDEX(Monthly!$C$105:$BJ$105,C$3*12) -> 64314.438 | D15: =INDEX(Monthly!$C$105:$BJ$105,D$3*12) -> 71953.877 | E15: =INDEX(Monthly!$C$105:$BJ$105,E$3*12) -> 89138.428 | F15: =INDEX(Monthly!$C$105:$BJ$105,F$3*12) -> 112730.72
A16: Total liabilities & equity | B16: =INDEX(Monthly!$C$106:$BJ$106,B$3*12) -> 141070.84 | C16: =INDEX(Monthly!$C$106:$BJ$106,C$3*12) -> 121957.49 | D16: =INDEX(Monthly!$C$106:$BJ$106,D$3*12) -> 111738.41 | E16: =INDEX(Monthly!$C$106:$BJ$106,E$3*12) -> 111073.96 | F16: =INDEX(Monthly!$C$106:$BJ$106,F$3*12) -> 116827.41
A17: Check: assets − liabilities − equity (must be 0) | B17: =INDEX(Monthly!$C$107:$BJ$107,B$3*12) -> 0 | C17: =INDEX(Monthly!$C$107:$BJ$107,C$3*12) -> 0 | D17: =INDEX(Monthly!$C$107:$BJ$107,D$3*12) -> 0 | E17: =INDEX(Monthly!$C$107:$BJ$107,E$3*12) -> 0 | F17: =INDEX(Monthly!$C$107:$BJ$107,F$3*12) -> 0

Sheet Monthly
A1: Monthly projection | D1: =HYPERLINK("#'Cover'!A1","◂ Contents") -> ◂ Contents
A2: $ unless stated; costs shown as negatives. Every period uses the same formula.
A3: Month | C3: M1 | D3: M2 | E3: M3 | F3: M4 | G3: M5 | H3: M6 | I3: M7 | J3: M8 | K3: M9 | L3: M10 | M3: M11 | N3: M12 | O3: M13 | P3: M14 | Q3: M15 | R3: M16 | S3: M17 | T3: M18 | U3: M19 | V3: M20 | W3: M21 | X3: M22 | Y3: M23 | Z3: M24 | AA3: M25 | AB3: M26 | AC3: M27 | AD3: M28 | AE3: M29 | AF3: M30 | AG3: M31 | AH3: M32 | AI3: M33 | AJ3: M34 | AK3: M35 | AL3: M36 | AM3: M37 | AN3: M38 | AO3: M39 | AP3: M40 | AQ3: M41 | AR3: M42 | AS3: M43 | AT3: M44 | AU3: M45 | AV3: M46 | AW3: M47 | AX3: M48 | AY3: M49 | AZ3: M50 | BA3: M51 | BB3: M52 | BC3: M53 | BD3: M54 | BE3: M55 | BF3: M56 | BG3: M57 | BH3: M58 | BI3: M59 | BJ3: M60
A4: Period # | C4: 1 | D4: 2 | E4: 3 | F4: 4 | G4: 5 | H4: 6 | I4: 7 | J4: 8 | K4: 9 | L4: 10 | M4: 11 | N4: 12 | O4: 13 | P4: 14 | Q4: 15 | R4: 16 | S4: 17 | T4: 18 | U4: 19 | V4: 20 | W4: 21 | X4: 22 | Y4: 23 | Z4: 24 | AA4: 25 | AB4: 26 | AC4: 27 | AD4: 28 | AE4: 29 | AF4: 30 | AG4: 31 | AH4: 32 | AI4: 33 | AJ4: 34 | AK4: 35 | AL4: 36 | AM4: 37 | AN4: 38 | AO4: 39 | AP4: 40 | AQ4: 41 | AR4: 42 | AS4: 43 | AT4: 44 | AU4: 45 | AV4: 46 | AW4: 47 | AX4: 48 | AY4: 49 | AZ4: 50 | BA4: 51 | BB4: 52 | BC4: 53 | BD4: 54 | BE4: 55 | BF4: 56 | BG4: 57 | BH4: 58 | BI4: 59 | BJ4: 60
A5: Year # | C5: =ROUNDUP(C4*1/12,0) -> 1 | D5: =ROUNDUP(D4*1/12,0) -> 1 | E5: =ROUNDUP(E4*1/12,0) -> 1 | F5: =ROUNDUP(F4*1/12,0) -> 1 | G5: =ROUNDUP(G4*1/12,0) -> 1 | H5: =ROUNDUP(H4*1/12,0) -> 1 | I5: =ROUNDUP(I4*1/12,0) -> 1 | J5: =ROUNDUP(J4*1/12,0) -> 1 | ... BJ5: =ROUNDUP(BJ4*1/12,0) -> 5
A7: Fleet & volume
A8: Trucks in operation | C8: =Inputs!$E$7+Inputs!$E$8*(C$5-1) -> 1 | D8: =Inputs!$E$7+Inputs!$E$8*(D$5-1) -> 1 | E8: =Inputs!$E$7+Inputs!$E$8*(E$5-1) -> 1 | F8: =Inputs!$E$7+Inputs!$E$8*(F$5-1) -> 1 | G8: =Inputs!$E$7+Inputs!$E$8*(G$5-1) -> 1 | H8: =Inputs!$E$7+Inputs!$E$8*(H$5-1) -> 1 | I8: =Inputs!$E$7+Inputs!$E$8*(I$5-1) -> 1 | J8: =Inputs!$E$7+Inputs!$E$8*(J$5-1) -> 1 | ... BJ8: =Inputs!$E$7+Inputs!$E$8*(BJ$5-1) -> 1
A9: Helper: months of the period still on the ramp-up | C9: =MAX(0,MIN(1,Inputs!$E$13-(C$4-1)*1)) -> 1 | D9: =MAX(0,MIN(1,Inputs!$E$13-(D$4-1)*1)) -> 1 | E9: =MAX(0,MIN(1,Inputs!$E$13-(E$4-1)*1)) -> 1 | F9: =MAX(0,MIN(1,Inputs!$E$13-(F$4-1)*1)) -> 1 | G9: =MAX(0,MIN(1,Inputs!$E$13-(G$4-1)*1)) -> 1 | H9: =MAX(0,MIN(1,Inputs!$E$13-(H$4-1)*1)) -> 1 | I9: =MAX(0,MIN(1,Inputs!$E$13-(I$4-1)*1)) -> 0 | J9: =MAX(0,MIN(1,Inputs!$E$13-(J$4-1)*1)) -> 0 | ... BJ9: =MAX(0,MIN(1,Inputs!$E$13-(BJ$4-1)*1)) -> 0
A10: Ramp-up factor (share of mature volume) | C10: =IF(Inputs!$E$13<=0,1,(C9*Inputs!$E$14+(1-Inputs!$E$14)/MAX(1,Inputs!$E$13)*(C9*(C$4-1)*1+C9*(C9-1)/2)+1-C9)/1) -> 0.5 | D10: =IF(Inputs!$E$13<=0,1,(D9*Inputs!$E$14+(1-Inputs!$E$14)/MAX(1,Inputs!$E$13)*(D9*(D$4-1)*1+D9*(D9-1)/2)+1-D9)/1) -> 0.58333333 | E10: =IF(Inputs!$E$13<=0,1,(E9*Inputs!$E$14+(1-Inputs!$E$14)/MAX(1,Inputs!$E$13)*(E9*(E$4-1)*1+E9*(E9-1)/2)+1-E9)/1) -> 0.66666667 | F10: =IF(Inputs!$E$13<=0,1,(F9*Inputs!$E$14+(1-Inputs!$E$14)/MAX(1,Inputs!$E$13)*(F9*(F$4-1)*1+F9*(F9-1)/2)+1-F9)/1) -> 0.75 | G10: =IF(Inputs!$E$13<=0,1,(G9*Inputs!$E$14+(1-Inputs!$E$14)/MAX(1,Inputs!$E$13)*(G9*(G$4-1)*1+G9*(G9-1)/2)+1-G9)/1) -> 0.83333333 | H10: =IF(Inputs!$E$13<=0,1,(H9*Inputs!$E$14+(1-Inputs!$E$14)/MAX(1,Inputs!$E$13)*(H9*(H$4-1)*1+H9*(H9-1)/2)+1-H9)/1) -> 0.91666667 | I10: =IF(Inputs!$E$13<=0,1,(I9*Inputs!$E$14+(1-Inputs!$E$14)/MAX(1,Inputs!$E$13)*(I9*(I$4-1)*1+I9*(I9-1)/2)+1-I9)/1) -> 1 | J10: =IF(Inputs!$E$13<=0,1,(J9*Inputs!$E$14+(1-Inputs!$E$14)/MAX(1,Inputs!$E$13)*(J9*(J$4-1)*1+J9*(J9-1)/2)+1-J9)/1) -> 1 | ... BJ10: =IF(Inputs!$E$13<=0,1,(BJ9*Inputs!$E$14+(1-Inputs!$E$14)/MAX(1,Inputs!$E$13)*(BJ9*(BJ$4-1)*1+BJ9*(BJ9-1)/2)+1-BJ9)/1) -> 1
A11: Season factor (winter dip in street days) | C11: =IF(OR(MOD(C$4-1,12)>=11,MOD(C$4-1,12)<=1),1-Inputs!$E$10,1+Inputs!$E$10/3) -> 0.75 | D11: =IF(OR(MOD(D$4-1,12)>=11,MOD(D$4-1,12)<=1),1-Inputs!$E$10,1+Inputs!$E$10/3) -> 0.75 | E11: =IF(OR(MOD(E$4-1,12)>=11,MOD(E$4-1,12)<=1),1-Inputs!$E$10,1+Inputs!$E$10/3) -> 1.0833333 | F11: =IF(OR(MOD(F$4-1,12)>=11,MOD(F$4-1,12)<=1),1-Inputs!$E$10,1+Inputs!$E$10/3) -> 1.0833333 | G11: =IF(OR(MOD(G$4-1,12)>=11,MOD(G$4-1,12)<=1),1-Inputs!$E$10,1+Inputs!$E$10/3) -> 1.0833333 | H11: =IF(OR(MOD(H$4-1,12)>=11,MOD(H$4-1,12)<=1),1-Inputs!$E$10,1+Inputs!$E$10/3) -> 1.0833333 | I11: =IF(OR(MOD(I$4-1,12)>=11,MOD(I$4-1,12)<=1),1-Inputs!$E$10,1+Inputs!$E$10/3) -> 1.0833333 | J11: =IF(OR(MOD(J$4-1,12)>=11,MOD(J$4-1,12)<=1),1-Inputs!$E$10,1+Inputs!$E$10/3) -> 1.0833333 | ... BJ11: =IF(OR(MOD(BJ$4-1,12)>=11,MOD(BJ$4-1,12)<=1),1-Inputs!$E$10,1+Inputs!$E$10/3) -> 0.75
A12: Street service days | C12: =C8*Inputs!$E$9*1*C11 -> 13.5 | D12: =D8*Inputs!$E$9*1*D11 -> 13.5 | E12: =E8*Inputs!$E$9*1*E11 -> 19.5 | F12: =F8*Inputs!$E$9*1*F11 -> 19.5 | G12: =G8*Inputs!$E$9*1*G11 -> 19.5 | H12: =H8*Inputs!$E$9*1*H11 -> 19.5 | I12: =I8*Inputs!$E$9*1*I11 -> 19.5 | J12: =J8*Inputs!$E$9*1*J11 -> 19.5 | ... BJ12: =BJ8*Inputs!$E$9*1*BJ11 -> 13.5
A13: Event and catering days | C13: =C8*Inputs!$E$23*(1+Inputs!$E$24)^(C$5-1)*1*C10 -> 1.5 | D13: =D8*Inputs!$E$23*(1+Inputs!$E$24)^(D$5-1)*1*D10 -> 1.75 | E13: =E8*Inputs!$E$23*(1+Inputs!$E$24)^(E$5-1)*1*E10 -> 2 | F13: =F8*Inputs!$E$23*(1+Inputs!$E$24)^(F$5-1)*1*F10 -> 2.25 | G13: =G8*Inputs!$E$23*(1+Inputs!$E$24)^(G$5-1)*1*G10 -> 2.5 | H13: =H8*Inputs!$E$23*(1+Inputs!$E$24)^(H$5-1)*1*H10 -> 2.75 | I13: =I8*Inputs!$E$23*(1+Inputs!$E$24)^(I$5-1)*1*I10 -> 3 | J13: =J8*Inputs!$E$23*(1+Inputs!$E$24)^(J$5-1)*1*J10 -> 3 | ... BJ13: =BJ8*Inputs!$E$23*(1+Inputs!$E$24)^(BJ$5-1)*1*BJ10 -> 3.6465187
A14: Service days - total | C14: =C12+C13 -> 15 | D14: =D12+D13 -> 15.25 | E14: =E12+E13 -> 21.5 | F14: =F12+F13 -> 21.75 | G14: =G12+G13 -> 22 | H14: =H12+H13 -> 22.25 | I14: =I12+I13 -> 22.5 | J14: =J12+J13 -> 22.5 | ... BJ14: =BJ12+BJ13 -> 17.146519
A15: Meals sold on the street | C15: =C12*Inputs!$E$17*(1+Inputs!$E$18)^(C$5-1)*C10 -> 594 | D15: =D12*Inputs!$E$17*(1+Inputs!$E$18)^(D$5-1)*D10 -> 693 | E15: =E12*Inputs!$E$17*(1+Inputs!$E$18)^(E$5-1)*E10 -> 1144 | F15: =F12*Inputs!$E$17*(1+Inputs!$E$18)^(F$5-1)*F10 -> 1287 | G15: =G12*Inputs!$E$17*(1+Inputs!$E$18)^(G$5-1)*G10 -> 1430 | H15: =H12*Inputs!$E$17*(1+Inputs!$E$18)^(H$5-1)*H10 -> 1573 | I15: =I12*Inputs!$E$17*(1+Inputs!$E$18)^(I$5-1)*I10 -> 1716 | J15: =J12*Inputs!$E$17*(1+Inputs!$E$18)^(J$5-1)*J10 -> 1716 | ... BJ15: =BJ12*Inputs!$E$17*(1+Inputs!$E$18)^(BJ$5-1)*BJ10 -> 1337.1045
A16: Meals served at events | C16: =C13*Inputs!$E$26 -> 150 | D16: =D13*Inputs!$E$26 -> 175 | E16: =E13*Inputs!$E$26 -> 200 | F16: =F13*Inputs!$E$26 -> 225 | G16: =G13*Inputs!$E$26 -> 250 | H16: =H13*Inputs!$E$26 -> 275 | I16: =I13*Inputs!$E$26 -> 300 | J16: =J13*Inputs!$E$26 -> 300 | ... BJ16: =BJ13*Inputs!$E$26 -> 364.65188
A17: Meals - total | C17: =C15+C16 -> 744 | D17: =D15+D16 -> 868 | E17: =E15+E16 -> 1344 | F17: =F15+F16 -> 1512 | G17: =G15+G16 -> 1680 | H17: =H15+H16 -> 1848 | I17: =I15+I16 -> 2016 | J17: =J15+J16 -> 2016 | ... BJ17: =BJ15+BJ16 -> 1701.7563
A19: Revenue
A20: Average ticket per street meal | C20: =Inputs!$E$19*(1+Inputs!$E$20)^(C$5-1) -> 14 | D20: =Inputs!$E$19*(1+Inputs!$E$20)^(D$5-1) -> 14 | E20: =Inputs!$E$19*(1+Inputs!$E$20)^(E$5-1) -> 14 | F20: =Inputs!$E$19*(1+Inputs!$E$20)^(F$5-1) -> 14 | G20: =Inputs!$E$19*(1+Inputs!$E$20)^(G$5-1) -> 14 | H20: =Inputs!$E$19*(1+Inputs!$E$20)^(H$5-1) -> 14 | I20: =Inputs!$E$19*(1+Inputs!$E$20)^(I$5-1) -> 14 | J20: =Inputs!$E$19*(1+Inputs!$E$20)^(J$5-1) -> 14 | ... BJ20: =Inputs!$E$19*(1+Inputs!$E$20)^(BJ$5-1) -> 15.757123
A21: Revenue per event day | C21: =Inputs!$E$25*(1+Inputs!$E$20)^(C$5-1) -> 1400 | D21: =Inputs!$E$25*(1+Inputs!$E$20)^(D$5-1) -> 1400 | E21: =Inputs!$E$25*(1+Inputs!$E$20)^(E$5-1) -> 1400 | F21: =Inputs!$E$25*(1+Inputs!$E$20)^(F$5-1) -> 1400 | G21: =Inputs!$E$25*(1+Inputs!$E$20)^(G$5-1) -> 1400 | H21: =Inputs!$E$25*(1+Inputs!$E$20)^(H$5-1) -> 1400 | I21: =Inputs!$E$25*(1+Inputs!$E$20)^(I$5-1) -> 1400 | J21: =Inputs!$E$25*(1+Inputs!$E$20)^(J$5-1) -> 1400 | ... BJ21: =Inputs!$E$25*(1+Inputs!$E$20)^(BJ$5-1) -> 1575.7123
A22: Street sales | C22: =C15*C20 -> 8316 | D22: =D15*D20 -> 9702 | E22: =E15*E20 -> 16016 | F22: =F15*F20 -> 18018 | G22: =G15*G20 -> 20020 | H22: =H15*H20 -> 22022 | I22: =I15*I20 -> 24024 | J22: =J15*J20 -> 24024 | ... BJ22: =BJ15*BJ20 -> 21068.92
A23: Events & catering | C23: =C13*C21 -> 2100 | D23: =D13*D21 -> 2450 | E23: =E13*E21 -> 2800 | F23: =F13*F21 -> 3150 | G23: =G13*G21 -> 3500 | H23: =H13*H21 -> 3850 | I23: =I13*I21 -> 4200 | J23: =J13*J21 -> 4200 | ... BJ23: =BJ13*BJ21 -> 5745.8646
A24: Revenue | C24: =C22+C23 -> 10416 | D24: =D22+D23 -> 12152 | E24: =E22+E23 -> 18816 | F24: =F22+F23 -> 21168 | G24: =G22+G23 -> 23520 | H24: =H22+H23 -> 25872 | I24: =I22+I23 -> 28224 | J24: =J22+J23 -> 28224 | ... BJ24: =BJ22+BJ23 -> 26814.785
A26: Cost of sales
A27: Food cost | C27: =-C24*Inputs!$E$29 -> -3437.28 | D27: =-D24*Inputs!$E$29 -> -4010.16 | E27: =-E24*Inputs!$E$29 -> -6209.28 | F27: =-F24*Inputs!$E$29 -> -6985.44 | G27: =-G24*Inputs!$E$29 -> -7761.6 | H27: =-H24*Inputs!$E$29 -> -8537.76 | I27: =-I24*Inputs!$E$29 -> -9313.92 | J27: =-J24*Inputs!$E$29 -> -9313.92 | ... BJ27: =-BJ24*Inputs!$E$29 -> -8848.8789
A28: Packaging & disposables | C28: =-C17*Inputs!$E$30*(1+Inputs!$E$34)^(C$5-1) -> -334.8 | D28: =-D17*Inputs!$E$30*(1+Inputs!$E$34)^(D$5-1) -> -390.6 | E28: =-E17*Inputs!$E$30*(1+Inputs!$E$34)^(E$5-1) -> -604.8 | F28: =-F17*Inputs!$E$30*(1+Inputs!$E$34)^(F$5-1) -> -680.4 | G28: =-G17*Inputs!$E$30*(1+Inputs!$E$34)^(G$5-1) -> -756 | H28: =-H17*Inputs!$E$30*(1+Inputs!$E$34)^(H$5-1) -> -831.6 | I28: =-I17*Inputs!$E$30*(1+Inputs!$E$34)^(I$5-1) -> -907.2 | J28: =-J17*Inputs!$E$30*(1+Inputs!$E$34)^(J$5-1) -> -907.2 | ... BJ28: =-BJ17*Inputs!$E$30*(1+Inputs!$E$34)^(BJ$5-1) -> -861.90379
A29: Food & packaging | C29: =C27+C28 -> -3772.08 | D29: =D27+D28 -> -4400.76 | E29: =E27+E28 -> -6814.08 | F29: =F27+F28 -> -7665.84 | G29: =G27+G28 -> -8517.6 | H29: =H27+H28 -> -9369.36 | I29: =I27+I28 -> -10221.12 | J29: =J27+J28 -> -10221.12 | ... BJ29: =BJ27+BJ28 -> -9710.7827
A30: Card & POS processing fees | C30: =-C24*Inputs!$E$31 -> -302.064 | D30: =-D24*Inputs!$E$31 -> -352.408 | E30: =-E24*Inputs!$E$31 -> -545.664 | F30: =-F24*Inputs!$E$31 -> -613.872 | G30: =-G24*Inputs!$E$31 -> -682.08 | H30: =-H24*Inputs!$E$31 -> -750.288 | I30: =-I24*Inputs!$E$31 -> -818.496 | J30: =-J24*Inputs!$E$31 -> -818.496 | ... BJ30: =-BJ24*Inputs!$E$31 -> -777.62875
A31: Event & festival fees | C31: =-C23*Inputs!$E$32-C13*Inputs!$E$33*(1+Inputs!$E$34)^(C$5-1) -> -234 | D31: =-D23*Inputs!$E$32-D13*Inputs!$E$33*(1+Inputs!$E$34)^(D$5-1) -> -273 | E31: =-E23*Inputs!$E$32-E13*Inputs!$E$33*(1+Inputs!$E$34)^(E$5-1) -> -312 | F31: =-F23*Inputs!$E$32-F13*Inputs!$E$33*(1+Inputs!$E$34)^(F$5-1) -> -351 | G31: =-G23*Inputs!$E$32-G13*Inputs!$E$33*(1+Inputs!$E$34)^(G$5-1) -> -390 | H31: =-H23*Inputs!$E$32-H13*Inputs!$E$33*(1+Inputs!$E$34)^(H$5-1) -> -429 | I31: =-I23*Inputs!$E$32-I13*Inputs!$E$33*(1+Inputs!$E$34)^(I$5-1) -> -468 | J31: =-J23*Inputs!$E$32-J13*Inputs!$E$33*(1+Inputs!$E$34)^(J$5-1) -> -468 | ... BJ31: =-BJ23*Inputs!$E$32-BJ13*Inputs!$E$33*(1+Inputs!$E$34)^(BJ$5-1) -> -640.25348
A32: Cost of sales | C32: =C29+C30+C31 -> -4308.144 | D32: =D29+D30+D31 -> -5026.168 | E32: =E29+E30+E31 -> -7671.744 | F32: =F29+F30+F31 -> -8630.712 | G32: =G29+G30+G31 -> -9589.68 | H32: =H29+H30+H31 -> -10548.648 | I32: =I29+I30+I31 -> -11507.616 | J32: =J29+J30+J31 -> -11507.616 | ... BJ32: =BJ29+BJ30+BJ31 -> -11128.665
A33: Gross profit | C33: =C24+C32 -> 6107.856 | D33: =D24+D32 -> 7125.832 | E33: =E24+E32 -> 11144.256 | F33: =F24+F32 -> 12537.288 | G33: =G24+G32 -> 13930.32 | H33: =H24+H32 -> 15323.352 | I33: =I24+I32 -> 16716.384 | J33: =J24+J32 -> 16716.384 | ... BJ33: =BJ24+BJ32 -> 15686.12
A35: Operating expenses
A36: Payroll (owner-operator, cooks, cashiers) | C36: =Headcount!C17 -> -9874.6667 | D36: =Headcount!D17 -> -9874.6667 | E36: =Headcount!E17 -> -9874.6667 | F36: =Headcount!F17 -> -9874.6667 | G36: =Headcount!G17 -> -9874.6667 | H36: =Headcount!H17 -> -9874.6667 | I36: =Headcount!I17 -> -9874.6667 | J36: =Headcount!J17 -> -9874.6667 | ... BJ36: =Headcount!BJ17 -> -11114.024
A37: Commissary kitchen | C37: =-Inputs!$E$37*C8*(1+Inputs!$E$34)^(C$5-1)*1 -> -950 | D37: =-Inputs!$E$37*D8*(1+Inputs!$E$34)^(D$5-1)*1 -> -950 | E37: =-Inputs!$E$37*E8*(1+Inputs!$E$34)^(E$5-1)*1 -> -950 | F37: =-Inputs!$E$37*F8*(1+Inputs!$E$34)^(F$5-1)*1 -> -950 | G37: =-Inputs!$E$37*G8*(1+Inputs!$E$34)^(G$5-1)*1 -> -950 | H37: =-Inputs!$E$37*H8*(1+Inputs!$E$34)^(H$5-1)*1 -> -950 | I37: =-Inputs!$E$37*I8*(1+Inputs!$E$34)^(I$5-1)*1 -> -950 | J37: =-Inputs!$E$37*J8*(1+Inputs!$E$34)^(J$5-1)*1 -> -950 | ... BJ37: =-Inputs!$E$37*BJ8*(1+Inputs!$E$34)^(BJ$5-1)*1 -> -1069.2334
A38: Permits & licences | C38: =-Inputs!$E$38*C8*(1+Inputs!$E$34)^(C$5-1)*1 -> -380 | D38: =-Inputs!$E$38*D8*(1+Inputs!$E$34)^(D$5-1)*1 -> -380 | E38: =-Inputs!$E$38*E8*(1+Inputs!$E$34)^(E$5-1)*1 -> -380 | F38: =-Inputs!$E$38*F8*(1+Inputs!$E$34)^(F$5-1)*1 -> -380 | G38: =-Inputs!$E$38*G8*(1+Inputs!$E$34)^(G$5-1)*1 -> -380 | H38: =-Inputs!$E$38*H8*(1+Inputs!$E$34)^(H$5-1)*1 -> -380 | I38: =-Inputs!$E$38*I8*(1+Inputs!$E$34)^(I$5-1)*1 -> -380 | J38: =-Inputs!$E$38*J8*(1+Inputs!$E$34)^(J$5-1)*1 -> -380 | ... BJ38: =-Inputs!$E$38*BJ8*(1+Inputs!$E$34)^(BJ$5-1)*1 -> -427.69335
A39: Insurance | C39: =-Inputs!$E$39*C8*(1+Inputs!$E$34)^(C$5-1)*1 -> -450 | D39: =-Inputs!$E$39*D8*(1+Inputs!$E$34)^(D$5-1)*1 -> -450 | E39: =-Inputs!$E$39*E8*(1+Inputs!$E$34)^(E$5-1)*1 -> -450 | F39: =-Inputs!$E$39*F8*(1+Inputs!$E$34)^(F$5-1)*1 -> -450 | G39: =-Inputs!$E$39*G8*(1+Inputs!$E$34)^(G$5-1)*1 -> -450 | H39: =-Inputs!$E$39*H8*(1+Inputs!$E$34)^(H$5-1)*1 -> -450 | I39: =-Inputs!$E$39*I8*(1+Inputs!$E$34)^(I$5-1)*1 -> -450 | J39: =-Inputs!$E$39*J8*(1+Inputs!$E$34)^(J$5-1)*1 -> -450 | ... BJ39: =-Inputs!$E$39*BJ8*(1+Inputs!$E$34)^(BJ$5-1)*1 -> -506.47896
A40: Fuel, propane & generator | C40: =-Inputs!$E$40*C14*(1+Inputs!$E$34)^(C$5-1) -> -570 | D40: =-Inputs!$E$40*D14*(1+Inputs!$E$34)^(D$5-1) -> -579.5 | E40: =-Inputs!$E$40*E14*(1+Inputs!$E$34)^(E$5-1) -> -817 | F40: =-Inputs!$E$40*F14*(1+Inputs!$E$34)^(F$5-1) -> -826.5 | G40: =-Inputs!$E$40*G14*(1+Inputs!$E$34)^(G$5-1) -> -836 | H40: =-Inputs!$E$40*H14*(1+Inputs!$E$34)^(H$5-1) -> -845.5 | I40: =-Inputs!$E$40*I14*(1+Inputs!$E$34)^(I$5-1) -> -855 | J40: =-Inputs!$E$40*J14*(1+Inputs!$E$34)^(J$5-1) -> -855 | ... BJ40: =-Inputs!$E$40*BJ14*(1+Inputs!$E$34)^(BJ$5-1) -> -733.3452
A41: Truck maintenance & repairs | C41: =-Inputs!$E$41*C8*(1+Inputs!$E$34)^(C$5-1)*1 -> -500 | D41: =-Inputs!$E$41*D8*(1+Inputs!$E$34)^(D$5-1)*1 -> -500 | E41: =-Inputs!$E$41*E8*(1+Inputs!$E$34)^(E$5-1)*1 -> -500 | F41: =-Inputs!$E$41*F8*(1+Inputs!$E$34)^(F$5-1)*1 -> -500 | G41: =-Inputs!$E$41*G8*(1+Inputs!$E$34)^(G$5-1)*1 -> -500 | H41: =-Inputs!$E$41*H8*(1+Inputs!$E$34)^(H$5-1)*1 -> -500 | I41: =-Inputs!$E$41*I8*(1+Inputs!$E$34)^(I$5-1)*1 -> -500 | J41: =-Inputs!$E$41*J8*(1+Inputs!$E$34)^(J$5-1)*1 -> -500 | ... BJ41: =-Inputs!$E$41*BJ8*(1+Inputs!$E$34)^(BJ$5-1)*1 -> -562.75441
A42: POS & ordering software | C42: =-Inputs!$E$42*(1+Inputs!$E$34)^(C$5-1)*1 -> -120 | D42: =-Inputs!$E$42*(1+Inputs!$E$34)^(D$5-1)*1 -> -120 | E42: =-Inputs!$E$42*(1+Inputs!$E$34)^(E$5-1)*1 -> -120 | F42: =-Inputs!$E$42*(1+Inputs!$E$34)^(F$5-1)*1 -> -120 | G42: =-Inputs!$E$42*(1+Inputs!$E$34)^(G$5-1)*1 -> -120 | H42: =-Inputs!$E$42*(1+Inputs!$E$34)^(H$5-1)*1 -> -120 | I42: =-Inputs!$E$42*(1+Inputs!$E$34)^(I$5-1)*1 -> -120 | J42: =-Inputs!$E$42*(1+Inputs!$E$34)^(J$5-1)*1 -> -120 | ... BJ42: =-Inputs!$E$42*(1+Inputs!$E$34)^(BJ$5-1)*1 -> -135.06106
A43: Marketing | C43: =-Inputs!$E$43*(1+Inputs!$E$44)^(C$5-1)*1 -> -700 | D43: =-Inputs!$E$43*(1+Inputs!$E$44)^(D$5-1)*1 -> -700 | E43: =-Inputs!$E$43*(1+Inputs!$E$44)^(E$5-1)*1 -> -700 | F43: =-Inputs!$E$43*(1+Inputs!$E$44)^(F$5-1)*1 -> -700 | G43: =-Inputs!$E$43*(1+Inputs!$E$44)^(G$5-1)*1 -> -700 | H43: =-Inputs!$E$43*(1+Inputs!$E$44)^(H$5-1)*1 -> -700 | I43: =-Inputs!$E$43*(1+Inputs!$E$44)^(I$5-1)*1 -> -700 | J43: =-Inputs!$E$43*(1+Inputs!$E$44)^(J$5-1)*1 -> -700 | ... BJ43: =-Inputs!$E$43*(1+Inputs!$E$44)^(BJ$5-1)*1 -> -700
A44: Accounting, bank fees & other G&A | C44: =-Inputs!$E$45*(1+Inputs!$E$34)^(C$5-1)*1 -> -350 | D44: =-Inputs!$E$45*(1+Inputs!$E$34)^(D$5-1)*1 -> -350 | E44: =-Inputs!$E$45*(1+Inputs!$E$34)^(E$5-1)*1 -> -350 | F44: =-Inputs!$E$45*(1+Inputs!$E$34)^(F$5-1)*1 -> -350 | G44: =-Inputs!$E$45*(1+Inputs!$E$34)^(G$5-1)*1 -> -350 | H44: =-Inputs!$E$45*(1+Inputs!$E$34)^(H$5-1)*1 -> -350 | I44: =-Inputs!$E$45*(1+Inputs!$E$34)^(I$5-1)*1 -> -350 | J44: =-Inputs!$E$45*(1+Inputs!$E$34)^(J$5-1)*1 -> -350 | ... BJ44: =-Inputs!$E$45*(1+Inputs!$E$34)^(BJ$5-1)*1 -> -393.92808
A45: Total operating expenses | C45: =C36+C37+C38+C39+C40+C41+C42+C43+C44 -> -13894.667 | D45: =D36+D37+D38+D39+D40+D41+D42+D43+D44 -> -13904.167 | E45: =E36+E37+E38+E39+E40+E41+E42+E43+E44 -> -14141.667 | F45: =F36+F37+F38+F39+F40+F41+F42+F43+F44 -> -14151.167 | G45: =G36+G37+G38+G39+G40+G41+G42+G43+G44 -> -14160.667 | H45: =H36+H37+H38+H39+H40+H41+H42+H43+H44 -> -14170.167 | I45: =I36+I37+I38+I39+I40+I41+I42+I43+I44 -> -14179.667 | J45: =J36+J37+J38+J39+J40+J41+J42+J43+J44 -> -14179.667 | ... BJ45: =BJ36+BJ37+BJ38+BJ39+BJ40+BJ41+BJ42+BJ43+BJ44 -> -15642.519
A46: EBITDA | C46: =C33+C45 -> -7786.8107 | D46: =D33+D45 -> -6778.3347 | E46: =E33+E45 -> -2997.4107 | F46: =F33+F45 -> -1613.8787 | G46: =G33+G45 -> -230.34667 | H46: =H33+H45 -> 1153.1853 | I46: =I33+I45 -> 2536.7173 | J46: =J33+J45 -> 2536.7173 | ... BJ46: =BJ33+BJ45 -> 43.600878
A48: Profit after depreciation, interest, tax
A49: EBIT | C49: =C46+C64 -> -9429.6678 | D49: =D46+D64 -> -8421.1918 | E49: =E46+E64 -> -4640.2678 | F49: =F46+F64 -> -3256.7358 | G49: =G46+G64 -> -1873.2038 | H49: =H46+H64 -> -489.67181 | I49: =I46+I64 -> 893.86019 | J49: =J46+J64 -> 893.86019 | ... BJ49: =BJ46+BJ64 -> -1718.3039
A50: Interest on loan (average balance after drawdown) | C50: =-(C69+C70+C72)/2*Inputs!$E$73/12 -> -675 | D50: =-(D69+D70+D72)/2*Inputs!$E$73/12 -> -669.375 | E50: =-(E69+E70+E72)/2*Inputs!$E$73/12 -> -658.125 | F50: =-(F69+F70+F72)/2*Inputs!$E$73/12 -> -646.875 | G50: =-(G69+G70+G72)/2*Inputs!$E$73/12 -> -635.625 | H50: =-(H69+H70+H72)/2*Inputs!$E$73/12 -> -624.375 | I50: =-(I69+I70+I72)/2*Inputs!$E$73/12 -> -613.125 | J50: =-(J69+J70+J72)/2*Inputs!$E$73/12 -> -601.875 | ... BJ50: =-(BJ69+BJ70+BJ72)/2*Inputs!$E$73/12 -> -16.875
A51: Pre-tax income | C51: =C49+C50 -> -10104.668 | D51: =D49+D50 -> -9090.5668 | E51: =E49+E50 -> -5298.3928 | F51: =F49+F50 -> -3903.6108 | G51: =G49+G50 -> -2508.8288 | H51: =H49+H50 -> -1114.0468 | I51: =I49+I50 -> 280.73519 | J51: =J49+J50 -> 291.98519 | ... BJ51: =BJ49+BJ50 -> -1735.1789
A52: Helper: cumulative pre-tax income | C52: =C51 -> -10104.668 | D52: =C52+D51 -> -19195.235 | E52: =D52+E51 -> -24493.627 | F52: =E52+F51 -> -28397.238 | G52: =F52+G51 -> -30906.067 | H52: =G52+H51 -> -32020.114 | I52: =H52+I51 -> -31739.379 | J52: =I52+J51 -> -31447.393 | K52: =J52+K51 -> -31144.158 | ... BJ52: =BI52+BJ51 -> 16576.087
A53: Helper: cumulative taxable income (losses carried forward) | C53: =MAX(0,C52) -> 0 | D53: =MAX(C53,D52) -> 0 | E53: =MAX(D53,E52) -> 0 | F53: =MAX(E53,F52) -> 0 | G53: =MAX(F53,G52) -> 0 | H53: =MAX(G53,H52) -> 0 | I53: =MAX(H53,I52) -> 0 | J53: =MAX(I53,J52) -> 0 | K53: =MAX(J53,K52) -> 0 | ... BJ53: =MAX(BI53,BJ52) -> 18311.266
A54: Income tax | C54: =-C53*Inputs!$E$83 -> 0 | D54: =-(D53-C53)*Inputs!$E$83 -> 0 | E54: =-(E53-D53)*Inputs!$E$83 -> 0 | F54: =-(F53-E53)*Inputs!$E$83 -> 0 | G54: =-(G53-F53)*Inputs!$E$83 -> 0 | H54: =-(H53-G53)*Inputs!$E$83 -> 0 | I54: =-(I53-H53)*Inputs!$E$83 -> 0 | J54: =-(J53-I53)*Inputs!$E$83 -> 0 | K54: =-(K53-J53)*Inputs!$E$83 -> 0 | ... BJ54: =-(BJ53-BI53)*Inputs!$E$83 -> 0
A55: Net income | C55: =C51+C54 -> -10104.668 | D55: =D51+D54 -> -9090.5668 | E55: =E51+E54 -> -5298.3928 | F55: =F51+F54 -> -3903.6108 | G55: =G51+G54 -> -2508.8288 | H55: =H51+H54 -> -1114.0468 | I55: =I51+I54 -> 280.73519 | J55: =J51+J54 -> 291.98519 | ... BJ55: =BJ51+BJ54 -> -1735.1789
A57: Fixed assets & capital spending
A58: Truck purchase (month 1; trucks added from year 2) | C58: =Inputs!$E$48*Inputs!$E$49 -> 95000 | D58: =IF(AND(D$5>1,MOD(D$4-1,12)=0),Inputs!$E$8*Inputs!$E$49,0) -> 0 | E58: =IF(AND(E$5>1,MOD(E$4-1,12)=0),Inputs!$E$8*Inputs!$E$49,0) -> 0 | F58: =IF(AND(F$5>1,MOD(F$4-1,12)=0),Inputs!$E$8*Inputs!$E$49,0) -> 0 | G58: =IF(AND(G$5>1,MOD(G$4-1,12)=0),Inputs!$E$8*Inputs!$E$49,0) -> 0 | H58: =IF(AND(H$5>1,MOD(H$4-1,12)=0),Inputs!$E$8*Inputs!$E$49,0) -> 0 | I58: =IF(AND(I$5>1,MOD(I$4-1,12)=0),Inputs!$E$8*Inputs!$E$49,0) -> 0 | J58: =IF(AND(J$5>1,MOD(J$4-1,12)=0),Inputs!$E$8*Inputs!$E$49,0) -> 0 | K58: =IF(AND(K$5>1,MOD(K$4-1,12)=0),Inputs!$E$8*Inputs!$E$49,0) -> 0 | ... BJ58: =IF(AND(BJ$5>1,MOD(BJ$4-1,12)=0),Inputs!$E$8*Inputs!$E$49,0) -> 0
A59: Kitchen build-out, equipment & wrap | C59: =Inputs!$E$48*Inputs!$E$50 -> 40000 | D59: =IF(AND(D$5>1,MOD(D$4-1,12)=0),Inputs!$E$8*Inputs!$E$50,0) -> 0 | E59: =IF(AND(E$5>1,MOD(E$4-1,12)=0),Inputs!$E$8*Inputs!$E$50,0) -> 0 | F59: =IF(AND(F$5>1,MOD(F$4-1,12)=0),Inputs!$E$8*Inputs!$E$50,0) -> 0 | G59: =IF(AND(G$5>1,MOD(G$4-1,12)=0),Inputs!$E$8*Inputs!$E$50,0) -> 0 | H59: =IF(AND(H$5>1,MOD(H$4-1,12)=0),Inputs!$E$8*Inputs!$E$50,0) -> 0 | I59: =IF(AND(I$5>1,MOD(I$4-1,12)=0),Inputs!$E$8*Inputs!$E$50,0) -> 0 | J59: =IF(AND(J$5>1,MOD(J$4-1,12)=0),Inputs!$E$8*Inputs!$E$50,0) -> 0 | K59: =IF(AND(K$5>1,MOD(K$4-1,12)=0),Inputs!$E$8*Inputs!$E$50,0) -> 0 | ... BJ59: =IF(AND(BJ$5>1,MOD(BJ$4-1,12)=0),Inputs!$E$8*Inputs!$E$50,0) -> 0
A60: POS hardware & smallwares | C60: =IF(C$4=1,Inputs!$E$51,0) -> 3000 | D60: =IF(D$4=1,Inputs!$E$51,0) -> 0 | E60: =IF(E$4=1,Inputs!$E$51,0) -> 0 | F60: =IF(F$4=1,Inputs!$E$51,0) -> 0 | G60: =IF(G$4=1,Inputs!$E$51,0) -> 0 | H60: =IF(H$4=1,Inputs!$E$51,0) -> 0 | I60: =IF(I$4=1,Inputs!$E$51,0) -> 0 | J60: =IF(J$4=1,Inputs!$E$51,0) -> 0 | ... BJ60: =IF(BJ$4=1,Inputs!$E$51,0) -> 0
A61: Equipment refresh (first period of each year from year 2) | C61: =IF(AND(C$5>1,MOD(C$4-1,12)=0),Inputs!$E$52*C8,0) -> 0 | D61: =IF(AND(D$5>1,MOD(D$4-1,12)=0),Inputs!$E$52*D8,0) -> 0 | E61: =IF(AND(E$5>1,MOD(E$4-1,12)=0),Inputs!$E$52*E8,0) -> 0 | F61: =IF(AND(F$5>1,MOD(F$4-1,12)=0),Inputs!$E$52*F8,0) -> 0 | G61: =IF(AND(G$5>1,MOD(G$4-1,12)=0),Inputs!$E$52*G8,0) -> 0 | H61: =IF(AND(H$5>1,MOD(H$4-1,12)=0),Inputs!$E$52*H8,0) -> 0 | I61: =IF(AND(I$5>1,MOD(I$4-1,12)=0),Inputs!$E$52*I8,0) -> 0 | J61: =IF(AND(J$5>1,MOD(J$4-1,12)=0),Inputs!$E$52*J8,0) -> 0 | ... BJ61: =IF(AND(BJ$5>1,MOD(BJ$4-1,12)=0),Inputs!$E$52*BJ8,0) -> 0
A62: Capital spending | C62: =C58+C59+C60+C61 -> 138000 | D62: =D58+D59+D60+D61 -> 0 | E62: =E58+E59+E60+E61 -> 0 | F62: =F58+F59+F60+F61 -> 0 | G62: =G58+G59+G60+G61 -> 0 | H62: =H58+H59+H60+H61 -> 0 | I62: =I58+I59+I60+I61 -> 0 | J62: =J58+J59+J60+J61 -> 0 | ... BJ62: =BJ58+BJ59+BJ60+BJ61 -> 0
A63: Fixed assets at cost | C63: =C62 -> 138000 | D63: =C63+D62 -> 138000 | E63: =D63+E62 -> 138000 | F63: =E63+F62 -> 138000 | G63: =F63+G62 -> 138000 | H63: =G63+H62 -> 138000 | I63: =H63+I62 -> 138000 | J63: =I63+J62 -> 138000 | K63: =J63+K62 -> 138000 | ... BJ63: =BI63+BJ62 -> 148000
A64: Depreciation | C64: =-MIN(C63/MAX(1,Inputs!$E$82*12),C62) -> -1642.8571 | D64: =-MIN(D63/MAX(1,Inputs!$E$82*12),C66+D62) -> -1642.8571 | E64: =-MIN(E63/MAX(1,Inputs!$E$82*12),D66+E62) -> -1642.8571 | F64: =-MIN(F63/MAX(1,Inputs!$E$82*12),E66+F62) -> -1642.8571 | G64: =-MIN(G63/MAX(1,Inputs!$E$82*12),F66+G62) -> -1642.8571 | H64: =-MIN(H63/MAX(1,Inputs!$E$82*12),G66+H62) -> -1642.8571 | I64: =-MIN(I63/MAX(1,Inputs!$E$82*12),H66+I62) -> -1642.8571 | J64: =-MIN(J63/MAX(1,Inputs!$E$82*12),I66+J62) -> -1642.8571 | K64: =-MIN(K63/MAX(1,Inputs!$E$82*12),J66+K62) -> -1642.8571 | ... BJ64: =-MIN(BJ63/MAX(1,Inputs!$E$82*12),BI66+BJ62) -> -1761.9048
A65: Accumulated depreciation | C65: =C64 -> -1642.8571 | D65: =C65+D64 -> -3285.7143 | E65: =D65+E64 -> -4928.5714 | F65: =E65+F64 -> -6571.4286 | G65: =F65+G64 -> -8214.2857 | H65: =G65+H64 -> -9857.1429 | I65: =H65+I64 -> -11500 | J65: =I65+J64 -> -13142.857 | K65: =J65+K64 -> -14785.714 | ... BJ65: =BI65+BJ64 -> -102142.86
A66: Net fixed assets | C66: =C63+C65 -> 136357.14 | D66: =D63+D65 -> 134714.29 | E66: =E63+E65 -> 133071.43 | F66: =F63+F65 -> 131428.57 | G66: =G63+G65 -> 129785.71 | H66: =H63+H65 -> 128142.86 | I66: =I63+I65 -> 126500 | J66: =J63+J65 -> 124857.14 | ... BJ66: =BJ63+BJ65 -> 45857.143
A68: Debt
A69: Loan — opening balance | C69: =0 -> 0 | D69: =C72 -> 90000 | E69: =D72 -> 88500 | F69: =E72 -> 87000 | G69: =F72 -> 85500 | H69: =G72 -> 84000 | I69: =H72 -> 82500 | J69: =I72 -> 81000 | K69: =J72 -> 79500 | ... BJ69: =BI72 -> 3000
A70: Loan drawdown | C70: =IF(C$4=1,Inputs!$E$72,0) -> 90000 | D70: =IF(D$4=1,Inputs!$E$72,0) -> 0 | E70: =IF(E$4=1,Inputs!$E$72,0) -> 0 | F70: =IF(F$4=1,Inputs!$E$72,0) -> 0 | G70: =IF(G$4=1,Inputs!$E$72,0) -> 0 | H70: =IF(H$4=1,Inputs!$E$72,0) -> 0 | I70: =IF(I$4=1,Inputs!$E$72,0) -> 0 | J70: =IF(J$4=1,Inputs!$E$72,0) -> 0 | ... BJ70: =IF(BJ$4=1,Inputs!$E$72,0) -> 0
A71: Loan repayment | C71: =-MIN(C69,Inputs!$E$72/MAX(1,Inputs!$E$74*12)) -> 0 | D71: =-MIN(D69,Inputs!$E$72/MAX(1,Inputs!$E$74*12)) -> -1500 | E71: =-MIN(E69,Inputs!$E$72/MAX(1,Inputs!$E$74*12)) -> -1500 | F71: =-MIN(F69,Inputs!$E$72/MAX(1,Inputs!$E$74*12)) -> -1500 | G71: =-MIN(G69,Inputs!$E$72/MAX(1,Inputs!$E$74*12)) -> -1500 | H71: =-MIN(H69,Inputs!$E$72/MAX(1,Inputs!$E$74*12)) -> -1500 | I71: =-MIN(I69,Inputs!$E$72/MAX(1,Inputs!$E$74*12)) -> -1500 | J71: =-MIN(J69,Inputs!$E$72/MAX(1,Inputs!$E$74*12)) -> -1500 | ... BJ71: =-MIN(BJ69,Inputs!$E$72/MAX(1,Inputs!$E$74*12)) -> -1500
A72: Loan — closing balance | C72: =C69+C70+C71 -> 90000 | D72: =D69+D70+D71 -> 88500 | E72: =E69+E70+E71 -> 87000 | F72: =F69+F70+F71 -> 85500 | G72: =G69+G70+G71 -> 84000 | H72: =H69+H70+H71 -> 82500 | I72: =I69+I70+I71 -> 81000 | J72: =J69+J70+J71 -> 79500 | ... BJ72: =BJ69+BJ70+BJ71 -> 1500
A74: Working capital
A75: Accounts receivable | C75: =C24*Inputs!$E$77/30 -> 1041.6 | D75: =D24*Inputs!$E$77/30 -> 1215.2 | E75: =E24*Inputs!$E$77/30 -> 1881.6 | F75: =F24*Inputs!$E$77/30 -> 2116.8 | G75: =G24*Inputs!$E$77/30 -> 2352 | H75: =H24*Inputs!$E$77/30 -> 2587.2 | I75: =I24*Inputs!$E$77/30 -> 2822.4 | J75: =J24*Inputs!$E$77/30 -> 2822.4 | ... BJ75: =BJ24*Inputs!$E$77/30 -> 2681.4785
A76: Inventory | C76: =-C32*Inputs!$E$78/30 -> 430.8144 | D76: =-D32*Inputs!$E$78/30 -> 502.6168 | E76: =-E32*Inputs!$E$78/30 -> 767.1744 | F76: =-F32*Inputs!$E$78/30 -> 863.0712 | G76: =-G32*Inputs!$E$78/30 -> 958.968 | H76: =-H32*Inputs!$E$78/30 -> 1054.8648 | I76: =-I32*Inputs!$E$78/30 -> 1150.7616 | J76: =-J32*Inputs!$E$78/30 -> 1150.7616 | ... BJ76: =-BJ32*Inputs!$E$78/30 -> 1112.8665
A77: Accounts payable | C77: =-C32*Inputs!$E$79/30 -> 1005.2336 | D77: =-D32*Inputs!$E$79/30 -> 1172.7725 | E77: =-E32*Inputs!$E$79/30 -> 1790.0736 | F77: =-F32*Inputs!$E$79/30 -> 2013.8328 | G77: =-G32*Inputs!$E$79/30 -> 2237.592 | H77: =-H32*Inputs!$E$79/30 -> 2461.3512 | I77: =-I32*Inputs!$E$79/30 -> 2685.1104 | J77: =-J32*Inputs!$E$79/30 -> 2685.1104 | ... BJ77: =-BJ32*Inputs!$E$79/30 -> 2596.6885
A78: (Increase) / decrease in receivables | C78: =-C75 -> -1041.6 | D78: =C75-D75 -> -173.6 | E78: =D75-E75 -> -666.4 | F78: =E75-F75 -> -235.2 | G78: =F75-G75 -> -235.2 | H78: =G75-H75 -> -235.2 | I78: =H75-I75 -> -235.2 | J78: =I75-J75 -> 0 | K78: =J75-K75 -> 0 | ... BJ78: =BI75-BJ75 -> 936.39644
A79: (Increase) / decrease in inventory | C79: =-C76 -> -430.8144 | D79: =C76-D76 -> -71.8024 | E79: =D76-E76 -> -264.5576 | F79: =E76-F76 -> -95.8968 | G79: =F76-G76 -> -95.8968 | H79: =G76-H76 -> -95.8968 | I79: =H76-I76 -> -95.8968 | J79: =I76-J76 -> 0 | K79: =J76-K76 -> 0 | ... BJ79: =BI76-BJ76 -> 366.26478
A80: Increase / (decrease) in payables | C80: =C77 -> 1005.2336 | D80: =D77-C77 -> 167.53893 | E80: =E77-D77 -> 617.30107 | F80: =F77-E77 -> 223.7592 | G80: =G77-F77 -> 223.7592 | H80: =H77-G77 -> 223.7592 | I80: =I77-H77 -> 223.7592 | J80: =J77-I77 -> 0 | K80: =K77-J77 -> 0 | ... BJ80: =BJ77-BI77 -> -854.61782
A82: Cash flow
A83: Operating cash flow | C83: =C55-C64+C78+C79+C80 -> -8928.9915 | D83: =D55-D64+D78+D79+D80 -> -7525.5731 | E83: =E55-E64+E78+E79+E80 -> -3969.1922 | F83: =F55-F64+F78+F79+F80 -> -2368.0913 | G83: =G55-G64+G78+G79+G80 -> -973.30927 | H83: =H55-H64+H78+H79+H80 -> 421.47273 | I83: =I55-I64+I78+I79+I80 -> 1816.2547 | J83: =J55-J64+J78+J79+J80 -> 1934.8423 | ... BJ83: =BJ55-BJ64+BJ78+BJ79+BJ80 -> 474.76928
A84: Investing cash flow (capex) | C84: =-C62 -> -138000 | D84: =-D62 -> 0 | E84: =-E62 -> 0 | F84: =-F62 -> 0 | G84: =-G62 -> 0 | H84: =-H62 -> 0 | I84: =-I62 -> 0 | J84: =-J62 -> 0 | ... BJ84: =-BJ62 -> 0
A85: Equity raised | C85: =IF(C$4=1,Inputs!$E$71,0) -> 100000 | D85: =IF(D$4=1,Inputs!$E$71,0) -> 0 | E85: =IF(E$4=1,Inputs!$E$71,0) -> 0 | F85: =IF(F$4=1,Inputs!$E$71,0) -> 0 | G85: =IF(G$4=1,Inputs!$E$71,0) -> 0 | H85: =IF(H$4=1,Inputs!$E$71,0) -> 0 | I85: =IF(I$4=1,Inputs!$E$71,0) -> 0 | J85: =IF(J$4=1,Inputs!$E$71,0) -> 0 | ... BJ85: =IF(BJ$4=1,Inputs!$E$71,0) -> 0
A86: Financing cash flow | C86: =C85+C70+C71 -> 190000 | D86: =D85+D70+D71 -> -1500 | E86: =E85+E70+E71 -> -1500 | F86: =F85+F70+F71 -> -1500 | G86: =G85+G70+G71 -> -1500 | H86: =H85+H70+H71 -> -1500 | I86: =I85+I70+I71 -> -1500 | J86: =J85+J70+J71 -> -1500 | ... BJ86: =BJ85+BJ70+BJ71 -> -1500
A87: Net cash flow | C87: =C83+C84+C86 -> 43071.009 | D87: =D83+D84+D86 -> -9025.5731 | E87: =E83+E84+E86 -> -5469.1922 | F87: =F83+F84+F86 -> -3868.0913 | G87: =G83+G84+G86 -> -2473.3093 | H87: =H83+H84+H86 -> -1078.5273 | I87: =I83+I84+I86 -> 316.25473 | J87: =J83+J84+J86 -> 434.84233 | ... BJ87: =BJ83+BJ84+BJ86 -> -1025.2307
A88: Opening cash | C88: =0 -> 0 | D88: =C89 -> 43071.009 | E88: =D89 -> 34045.435 | F88: =E89 -> 28576.243 | G88: =F89 -> 24708.152 | H88: =G89 -> 22234.843 | I88: =H89 -> 21156.315 | J88: =I89 -> 21472.57 | K88: =J89 -> 21907.412 | ... BJ88: =BI89 -> 68201.152
A89: Closing cash | C89: =C88+C87 -> 43071.009 | D89: =D88+D87 -> 34045.435 | E89: =E88+E87 -> 28576.243 | F89: =F88+F87 -> 24708.152 | G89: =G88+G87 -> 22234.843 | H89: =H88+H87 -> 21156.315 | I89: =I88+I87 -> 21472.57 | J89: =J88+J87 -> 21907.412 | ... BJ89: =BJ88+BJ87 -> 67175.922
A90: Helper: EBITDA positive (1/0) | C90: =IF(C46>0,1,0) -> 0 | D90: =IF(D46>0,1,0) -> 0 | E90: =IF(E46>0,1,0) -> 0 | F90: =IF(F46>0,1,0) -> 0 | G90: =IF(G46>0,1,0) -> 0 | H90: =IF(H46>0,1,0) -> 1 | I90: =IF(I46>0,1,0) -> 1 | J90: =IF(J46>0,1,0) -> 1 | ... BJ90: =IF(BJ46>0,1,0) -> 1
A92: Goal modules
A93: Helper: net income positive (1/0) | C93: =IF(C55>0,1,0) -> 0 | D93: =IF(D55>0,1,0) -> 0 | E93: =IF(E55>0,1,0) -> 0 | F93: =IF(F55>0,1,0) -> 0 | G93: =IF(G55>0,1,0) -> 0 | H93: =IF(H55>0,1,0) -> 0 | I93: =IF(I55>0,1,0) -> 1 | J93: =IF(J55>0,1,0) -> 1 | ... BJ93: =IF(BJ55>0,1,0) -> 0
A94: Cash flow before financing (operating + investing) | C94: =C83+C84 -> -146928.99 | D94: =D83+D84 -> -7525.5731 | E94: =E83+E84 -> -3969.1922 | F94: =F83+F84 -> -2368.0913 | G94: =G83+G84 -> -973.30927 | H94: =H83+H84 -> 421.47273 | I94: =I83+I84 -> 1816.2547 | J94: =J83+J84 -> 1934.8423 | ... BJ94: =BJ83+BJ84 -> 474.76928
A95: Cumulative cash flow before financing | C95: =C94 -> -146928.99 | D95: =C95+D94 -> -154454.56 | E95: =D95+E94 -> -158423.76 | F95: =E95+F94 -> -160791.85 | G95: =F95+G94 -> -161765.16 | H95: =G95+H94 -> -161343.68 | I95: =H95+I94 -> -159527.43 | J95: =I95+J94 -> -157592.59 | K95: =J95+K94 -> -155646.5 | ... BJ95: =BI95+BJ94 -> -34324.078
A96: Helper: lowest cumulative cash flow so far | C96: =C95 -> -146928.99 | D96: =MIN(C96,D95) -> -154454.56 | E96: =MIN(D96,E95) -> -158423.76 | F96: =MIN(E96,F95) -> -160791.85 | G96: =MIN(F96,G95) -> -161765.16 | H96: =MIN(G96,H95) -> -161765.16 | I96: =MIN(H96,I95) -> -161765.16 | J96: =MIN(I96,J95) -> -161765.16 | K96: =MIN(J96,K95) -> -161765.16 | ... BJ96: =MIN(BI96,BJ95) -> -161765.16
A97: Helper: investment paid back (1/0) | C97: =IF(AND(C95>=0,C96<0),1,0) -> 0 | D97: =IF(AND(D95>=0,D96<0),1,0) -> 0 | E97: =IF(AND(E95>=0,E96<0),1,0) -> 0 | F97: =IF(AND(F95>=0,F96<0),1,0) -> 0 | G97: =IF(AND(G95>=0,G96<0),1,0) -> 0 | H97: =IF(AND(H95>=0,H96<0),1,0) -> 0 | I97: =IF(AND(I95>=0,I96<0),1,0) -> 0 | J97: =IF(AND(J95>=0,J96<0),1,0) -> 0 | ... BJ97: =IF(AND(BJ95>=0,BJ96<0),1,0) -> 0
A98: Unlevered free cash flow (operating + after-tax interest − capex) | C98: =C83-C50*(1-Inputs!$E$83)+C84 -> -146395.74 | D98: =D83-D50*(1-Inputs!$E$83)+D84 -> -6996.7669 | E98: =E83-E50*(1-Inputs!$E$83)+E84 -> -3449.2735 | F98: =F83-F50*(1-Inputs!$E$83)+F84 -> -1857.06 | G98: =G83-G50*(1-Inputs!$E$83)+G84 -> -471.16552 | H98: =H83-H50*(1-Inputs!$E$83)+H84 -> 914.72898 | I98: =I83-I50*(1-Inputs!$E$83)+I84 -> 2300.6235 | J98: =J83-J50*(1-Inputs!$E$83)+J84 -> 2410.3236 | ... BJ98: =BJ83-BJ50*(1-Inputs!$E$83)+BJ84 -> 488.10053
A100: Balance sheet
A101: Paid-in capital | C101: =C85 -> 100000 | D101: =C101+D85 -> 100000 | E101: =D101+E85 -> 100000 | F101: =E101+F85 -> 100000 | G101: =F101+G85 -> 100000 | H101: =G101+H85 -> 100000 | I101: =H101+I85 -> 100000 | J101: =I101+J85 -> 100000 | K101: =J101+K85 -> 100000 | ... BJ101: =BI101+BJ85 -> 100000
A102: Retained earnings | C102: =C55 -> -10104.668 | D102: =C102+D55 -> -19195.235 | E102: =D102+E55 -> -24493.627 | F102: =E102+F55 -> -28397.238 | G102: =F102+G55 -> -30906.067 | H102: =G102+H55 -> -32020.114 | I102: =H102+I55 -> -31739.379 | J102: =I102+J55 -> -31447.393 | K102: =J102+K55 -> -31144.158 | ... BJ102: =BI102+BJ55 -> 12730.721
A103: Total assets | C103: =C89+C75+C76+C66 -> 180900.57 | D103: =D89+D75+D76+D66 -> 170477.54 | E103: =E89+E75+E76+E66 -> 164296.45 | F103: =F89+F75+F76+F66 -> 159116.59 | G103: =G89+G75+G76+G66 -> 155331.52 | H103: =H89+H75+H76+H66 -> 152941.24 | I103: =I89+I75+I76+I66 -> 151945.73 | J103: =J89+J75+J76+J66 -> 150737.72 | ... BJ103: =BJ89+BJ75+BJ76+BJ66 -> 116827.41
A104: Total liabilities | C104: =C77+C72 -> 91005.234 | D104: =D77+D72 -> 89672.773 | E104: =E77+E72 -> 88790.074 | F104: =F77+F72 -> 87513.833 | G104: =G77+G72 -> 86237.592 | H104: =H77+H72 -> 84961.351 | I104: =I77+I72 -> 83685.11 | J104: =J77+J72 -> 82185.11 | ... BJ104: =BJ77+BJ72 -> 4096.6885
A105: Total equity | C105: =C101+C102 -> 89895.332 | D105: =D101+D102 -> 80804.765 | E105: =E101+E102 -> 75506.373 | F105: =F101+F102 -> 71602.762 | G105: =G101+G102 -> 69093.933 | H105: =H101+H102 -> 67979.886 | I105: =I101+I102 -> 68260.621 | J105: =J101+J102 -> 68552.607 | ... BJ105: =BJ101+BJ102 -> 112730.72
A106: Total liabilities & equity | C106: =C104+C105 -> 180900.57 | D106: =D104+D105 -> 170477.54 | E106: =E104+E105 -> 164296.45 | F106: =F104+F105 -> 159116.59 | G106: =G104+G105 -> 155331.52 | H106: =H104+H105 -> 152941.24 | I106: =I104+I105 -> 151945.73 | J106: =J104+J105 -> 150737.72 | ... BJ106: =BJ104+BJ105 -> 116827.41
A107: Check: assets − liabilities − equity | C107: =C103-C106 -> 0 | D107: =D103-D106 -> 0 | E107: =E103-E106 -> 0 | F107: =F103-F106 -> 0 | G107: =G103-G106 -> 0 | H107: =H103-H106 -> 0 | I107: =I103-I106 -> 0 | J107: =J103-J106 -> 0 | ... BJ107: =BJ103-BJ106 -> 0

Sheet Headcount
A1: Headcount & payroll | D1: =HYPERLINK("#'Cover'!A1","◂ Contents") -> ◂ Contents
A2: $ unless stated; costs shown as negatives. Every period uses the same formula.
A3: Month | C3: M1 | D3: M2 | E3: M3 | F3: M4 | G3: M5 | H3: M6 | I3: M7 | J3: M8 | K3: M9 | L3: M10 | M3: M11 | N3: M12 | O3: M13 | P3: M14 | Q3: M15 | R3: M16 | S3: M17 | T3: M18 | U3: M19 | V3: M20 | W3: M21 | X3: M22 | Y3: M23 | Z3: M24 | AA3: M25 | AB3: M26 | AC3: M27 | AD3: M28 | AE3: M29 | AF3: M30 | AG3: M31 | AH3: M32 | AI3: M33 | AJ3: M34 | AK3: M35 | AL3: M36 | AM3: M37 | AN3: M38 | AO3: M39 | AP3: M40 | AQ3: M41 | AR3: M42 | AS3: M43 | AT3: M44 | AU3: M45 | AV3: M46 | AW3: M47 | AX3: M48 | AY3: M49 | AZ3: M50 | BA3: M51 | BB3: M52 | BC3: M53 | BD3: M54 | BE3: M55 | BF3: M56 | BG3: M57 | BH3: M58 | BI3: M59 | BJ3: M60
A4: Period # | C4: 1 | D4: 2 | E4: 3 | F4: 4 | G4: 5 | H4: 6 | I4: 7 | J4: 8 | K4: 9 | L4: 10 | M4: 11 | N4: 12 | O4: 13 | P4: 14 | Q4: 15 | R4: 16 | S4: 17 | T4: 18 | U4: 19 | V4: 20 | W4: 21 | X4: 22 | Y4: 23 | Z4: 24 | AA4: 25 | AB4: 26 | AC4: 27 | AD4: 28 | AE4: 29 | AF4: 30 | AG4: 31 | AH4: 32 | AI4: 33 | AJ4: 34 | AK4: 35 | AL4: 36 | AM4: 37 | AN4: 38 | AO4: 39 | AP4: 40 | AQ4: 41 | AR4: 42 | AS4: 43 | AT4: 44 | AU4: 45 | AV4: 46 | AW4: 47 | AX4: 48 | AY4: 49 | AZ4: 50 | BA4: 51 | BB4: 52 | BC4: 53 | BD4: 54 | BE4: 55 | BF4: 56 | BG4: 57 | BH4: 58 | BI4: 59 | BJ4: 60
A5: Year # | C5: =ROUNDUP(C4*1/12,0) -> 1 | D5: =ROUNDUP(D4*1/12,0) -> 1 | E5: =ROUNDUP(E4*1/12,0) -> 1 | F5: =ROUNDUP(F4*1/12,0) -> 1 | G5: =ROUNDUP(G4*1/12,0) -> 1 | H5: =ROUNDUP(H4*1/12,0) -> 1 | I5: =ROUNDUP(I4*1/12,0) -> 1 | J5: =ROUNDUP(J4*1/12,0) -> 1 | ... BJ5: =ROUNDUP(BJ4*1/12,0) -> 5
A7: Headcount (FTE)
A8: Owner-operator (salary optional) — FTE | C8: =Inputs!$E$55*(1+Inputs!$E$57)^(C$5-1)*MAX(0,MIN(1,C$4*1-Inputs!$E$58+1))/1 -> 1 | D8: =Inputs!$E$55*(1+Inputs!$E$57)^(D$5-1)*MAX(0,MIN(1,D$4*1-Inputs!$E$58+1))/1 -> 1 | E8: =Inputs!$E$55*(1+Inputs!$E$57)^(E$5-1)*MAX(0,MIN(1,E$4*1-Inputs!$E$58+1))/1 -> 1 | F8: =Inputs!$E$55*(1+Inputs!$E$57)^(F$5-1)*MAX(0,MIN(1,F$4*1-Inputs!$E$58+1))/1 -> 1 | G8: =Inputs!$E$55*(1+Inputs!$E$57)^(G$5-1)*MAX(0,MIN(1,G$4*1-Inputs!$E$58+1))/1 -> 1 | H8: =Inputs!$E$55*(1+Inputs!$E$57)^(H$5-1)*MAX(0,MIN(1,H$4*1-Inputs!$E$58+1))/1 -> 1 | I8: =Inputs!$E$55*(1+Inputs!$E$57)^(I$5-1)*MAX(0,MIN(1,I$4*1-Inputs!$E$58+1))/1 -> 1 | J8: =Inputs!$E$55*(1+Inputs!$E$57)^(J$5-1)*MAX(0,MIN(1,J$4*1-Inputs!$E$58+1))/1 -> 1 | ... BJ8: =Inputs!$E$55*(1+Inputs!$E$57)^(BJ$5-1)*MAX(0,MIN(1,BJ$4*1-Inputs!$E$58+1))/1 -> 1
A9: Cooks — FTE | C9: =Inputs!$E$59*(1+Inputs!$E$61)^(C$5-1)*MAX(0,MIN(1,C$4*1-Inputs!$E$62+1))/1 -> 1.2 | D9: =Inputs!$E$59*(1+Inputs!$E$61)^(D$5-1)*MAX(0,MIN(1,D$4*1-Inputs!$E$62+1))/1 -> 1.2 | E9: =Inputs!$E$59*(1+Inputs!$E$61)^(E$5-1)*MAX(0,MIN(1,E$4*1-Inputs!$E$62+1))/1 -> 1.2 | F9: =Inputs!$E$59*(1+Inputs!$E$61)^(F$5-1)*MAX(0,MIN(1,F$4*1-Inputs!$E$62+1))/1 -> 1.2 | G9: =Inputs!$E$59*(1+Inputs!$E$61)^(G$5-1)*MAX(0,MIN(1,G$4*1-Inputs!$E$62+1))/1 -> 1.2 | H9: =Inputs!$E$59*(1+Inputs!$E$61)^(H$5-1)*MAX(0,MIN(1,H$4*1-Inputs!$E$62+1))/1 -> 1.2 | I9: =Inputs!$E$59*(1+Inputs!$E$61)^(I$5-1)*MAX(0,MIN(1,I$4*1-Inputs!$E$62+1))/1 -> 1.2 | J9: =Inputs!$E$59*(1+Inputs!$E$61)^(J$5-1)*MAX(0,MIN(1,J$4*1-Inputs!$E$62+1))/1 -> 1.2 | ... BJ9: =Inputs!$E$59*(1+Inputs!$E$61)^(BJ$5-1)*MAX(0,MIN(1,BJ$4*1-Inputs!$E$62+1))/1 -> 1.2
A10: Cashiers & service staff — FTE | C10: =Inputs!$E$63*(1+Inputs!$E$65)^(C$5-1)*MAX(0,MIN(1,C$4*1-Inputs!$E$66+1))/1 -> 1 | D10: =Inputs!$E$63*(1+Inputs!$E$65)^(D$5-1)*MAX(0,MIN(1,D$4*1-Inputs!$E$66+1))/1 -> 1 | E10: =Inputs!$E$63*(1+Inputs!$E$65)^(E$5-1)*MAX(0,MIN(1,E$4*1-Inputs!$E$66+1))/1 -> 1 | F10: =Inputs!$E$63*(1+Inputs!$E$65)^(F$5-1)*MAX(0,MIN(1,F$4*1-Inputs!$E$66+1))/1 -> 1 | G10: =Inputs!$E$63*(1+Inputs!$E$65)^(G$5-1)*MAX(0,MIN(1,G$4*1-Inputs!$E$66+1))/1 -> 1 | H10: =Inputs!$E$63*(1+Inputs!$E$65)^(H$5-1)*MAX(0,MIN(1,H$4*1-Inputs!$E$66+1))/1 -> 1 | I10: =Inputs!$E$63*(1+Inputs!$E$65)^(I$5-1)*MAX(0,MIN(1,I$4*1-Inputs!$E$66+1))/1 -> 1 | J10: =Inputs!$E$63*(1+Inputs!$E$65)^(J$5-1)*MAX(0,MIN(1,J$4*1-Inputs!$E$66+1))/1 -> 1 | ... BJ10: =Inputs!$E$63*(1+Inputs!$E$65)^(BJ$5-1)*MAX(0,MIN(1,BJ$4*1-Inputs!$E$66+1))/1 -> 1
A11: Total FTE | C11: =C8+C9+C10 -> 3.2 | D11: =D8+D9+D10 -> 3.2 | E11: =E8+E9+E10 -> 3.2 | F11: =F8+F9+F10 -> 3.2 | G11: =G8+G9+G10 -> 3.2 | H11: =H8+H9+H10 -> 3.2 | I11: =I8+I9+I10 -> 3.2 | J11: =J8+J9+J10 -> 3.2 | ... BJ11: =BJ8+BJ9+BJ10 -> 3.2
A13: Payroll cost (salary + taxes & benefits)
A14: Owner-operator (salary optional) — payroll cost | C14: =-C8*Inputs!$E$56/12*1*(1+Inputs!$E$67)*(1+Inputs!$E$68)^(C$5-1) -> -3360 | D14: =-D8*Inputs!$E$56/12*1*(1+Inputs!$E$67)*(1+Inputs!$E$68)^(D$5-1) -> -3360 | E14: =-E8*Inputs!$E$56/12*1*(1+Inputs!$E$67)*(1+Inputs!$E$68)^(E$5-1) -> -3360 | F14: =-F8*Inputs!$E$56/12*1*(1+Inputs!$E$67)*(1+Inputs!$E$68)^(F$5-1) -> -3360 | G14: =-G8*Inputs!$E$56/12*1*(1+Inputs!$E$67)*(1+Inputs!$E$68)^(G$5-1) -> -3360 | H14: =-H8*Inputs!$E$56/12*1*(1+Inputs!$E$67)*(1+Inputs!$E$68)^(H$5-1) -> -3360 | I14: =-I8*Inputs!$E$56/12*1*(1+Inputs!$E$67)*(1+Inputs!$E$68)^(I$5-1) -> -3360 | J14: =-J8*Inputs!$E$56/12*1*(1+Inputs!$E$67)*(1+Inputs!$E$68)^(J$5-1) -> -3360 | ... BJ14: =-BJ8*Inputs!$E$56/12*1*(1+Inputs!$E$67)*(1+Inputs!$E$68)^(BJ$5-1) -> -3781.7096
A15: Cooks — payroll cost | C15: =-C9*Inputs!$E$60/12*1*(1+Inputs!$E$67)*(1+Inputs!$E$68)^(C$5-1) -> -3808 | D15: =-D9*Inputs!$E$60/12*1*(1+Inputs!$E$67)*(1+Inputs!$E$68)^(D$5-1) -> -3808 | E15: =-E9*Inputs!$E$60/12*1*(1+Inputs!$E$67)*(1+Inputs!$E$68)^(E$5-1) -> -3808 | F15: =-F9*Inputs!$E$60/12*1*(1+Inputs!$E$67)*(1+Inputs!$E$68)^(F$5-1) -> -3808 | G15: =-G9*Inputs!$E$60/12*1*(1+Inputs!$E$67)*(1+Inputs!$E$68)^(G$5-1) -> -3808 | H15: =-H9*Inputs!$E$60/12*1*(1+Inputs!$E$67)*(1+Inputs!$E$68)^(H$5-1) -> -3808 | I15: =-I9*Inputs!$E$60/12*1*(1+Inputs!$E$67)*(1+Inputs!$E$68)^(I$5-1) -> -3808 | J15: =-J9*Inputs!$E$60/12*1*(1+Inputs!$E$67)*(1+Inputs!$E$68)^(J$5-1) -> -3808 | ... BJ15: =-BJ9*Inputs!$E$60/12*1*(1+Inputs!$E$67)*(1+Inputs!$E$68)^(BJ$5-1) -> -4285.9375
A16: Cashiers & service staff — payroll cost | C16: =-C10*Inputs!$E$64/12*1*(1+Inputs!$E$67)*(1+Inputs!$E$68)^(C$5-1) -> -2706.6667 | D16: =-D10*Inputs!$E$64/12*1*(1+Inputs!$E$67)*(1+Inputs!$E$68)^(D$5-1) -> -2706.6667 | E16: =-E10*Inputs!$E$64/12*1*(1+Inputs!$E$67)*(1+Inputs!$E$68)^(E$5-1) -> -2706.6667 | F16: =-F10*Inputs!$E$64/12*1*(1+Inputs!$E$67)*(1+Inputs!$E$68)^(F$5-1) -> -2706.6667 | G16: =-G10*Inputs!$E$64/12*1*(1+Inputs!$E$67)*(1+Inputs!$E$68)^(G$5-1) -> -2706.6667 | H16: =-H10*Inputs!$E$64/12*1*(1+Inputs!$E$67)*(1+Inputs!$E$68)^(H$5-1) -> -2706.6667 | I16: =-I10*Inputs!$E$64/12*1*(1+Inputs!$E$67)*(1+Inputs!$E$68)^(I$5-1) -> -2706.6667 | J16: =-J10*Inputs!$E$64/12*1*(1+Inputs!$E$67)*(1+Inputs!$E$68)^(J$5-1) -> -2706.6667 | ... BJ16: =-BJ10*Inputs!$E$64/12*1*(1+Inputs!$E$67)*(1+Inputs!$E$68)^(BJ$5-1) -> -3046.3772
A17: Total payroll | C17: =C14+C15+C16 -> -9874.6667 | D17: =D14+D15+D16 -> -9874.6667 | E17: =E14+E15+E16 -> -9874.6667 | F17: =F14+F15+F16 -> -9874.6667 | G17: =G14+G15+G16 -> -9874.6667 | H17: =H14+H15+H16 -> -9874.6667 | I17: =I14+I15+I16 -> -9874.6667 | J17: =J14+J15+J16 -> -9874.6667 | ... BJ17: =BJ14+BJ15+BJ16 -> -11114.024

Sheet Scenario calc
A1: Scenario calculation — Low, Base and High side by side | D1: =HYPERLINK("#'Cover'!A1","◂ Contents") -> ◂ Contents
A2: The model's period calculation, copied three times; each copy reads its own Inputs column. Feeds the Scenarios sheet only.
A4: Low scenario — reads Inputs column B
A5: Month | C5: M1 | D5: M2 | E5: M3 | F5: M4 | G5: M5 | H5: M6 | I5: M7 | J5: M8 | K5: M9 | L5: M10 | M5: M11 | N5: M12 | O5: M13 | P5: M14 | Q5: M15 | R5: M16 | S5: M17 | T5: M18 | U5: M19 | V5: M20 | W5: M21 | X5: M22 | Y5: M23 | Z5: M24 | AA5: M25 | AB5: M26 | AC5: M27 | AD5: M28 | AE5: M29 | AF5: M30 | AG5: M31 | AH5: M32 | AI5: M33 | AJ5: M34 | AK5: M35 | AL5: M36 | AM5: M37 | AN5: M38 | AO5: M39 | AP5: M40 | AQ5: M41 | AR5: M42 | AS5: M43 | AT5: M44 | AU5: M45 | AV5: M46 | AW5: M47 | AX5: M48 | AY5: M49 | AZ5: M50 | BA5: M51 | BB5: M52 | BC5: M53 | BD5: M54 | BE5: M55 | BF5: M56 | BG5: M57 | BH5: M58 | BI5: M59 | BJ5: M60
A6: Period # | C6: 1 | D6: 2 | E6: 3 | F6: 4 | G6: 5 | H6: 6 | I6: 7 | J6: 8 | K6: 9 | L6: 10 | M6: 11 | N6: 12 | O6: 13 | P6: 14 | Q6: 15 | R6: 16 | S6: 17 | T6: 18 | U6: 19 | V6: 20 | W6: 21 | X6: 22 | Y6: 23 | Z6: 24 | AA6: 25 | AB6: 26 | AC6: 27 | AD6: 28 | AE6: 29 | AF6: 30 | AG6: 31 | AH6: 32 | AI6: 33 | AJ6: 34 | AK6: 35 | AL6: 36 | AM6: 37 | AN6: 38 | AO6: 39 | AP6: 40 | AQ6: 41 | AR6: 42 | AS6: 43 | AT6: 44 | AU6: 45 | AV6: 46 | AW6: 47 | AX6: 48 | AY6: 49 | AZ6: 50 | BA6: 51 | BB6: 52 | BC6: 53 | BD6: 54 | BE6: 55 | BF6: 56 | BG6: 57 | BH6: 58 | BI6: 59 | BJ6: 60
A7: Year # | C7: =ROUNDUP(C6*1/12,0) -> 1 | D7: =ROUNDUP(D6*1/12,0) -> 1 | E7: =ROUNDUP(E6*1/12,0) -> 1 | F7: =ROUNDUP(F6*1/12,0) -> 1 | G7: =ROUNDUP(G6*1/12,0) -> 1 | H7: =ROUNDUP(H6*1/12,0) -> 1 | I7: =ROUNDUP(I6*1/12,0) -> 1 | J7: =ROUNDUP(J6*1/12,0) -> 1 | ... BJ7: =ROUNDUP(BJ6*1/12,0) -> 5
A9: Fleet & volume
A10: Trucks in operation | C10: =Inputs!$B$7+Inputs!$B$8*(C$7-1) -> 1 | D10: =Inputs!$B$7+Inputs!$B$8*(D$7-1) -> 1 | E10: =Inputs!$B$7+Inputs!$B$8*(E$7-1) -> 1 | F10: =Inputs!$B$7+Inputs!$B$8*(F$7-1) -> 1 | G10: =Inputs!$B$7+Inputs!$B$8*(G$7-1) -> 1 | H10: =Inputs!$B$7+Inputs!$B$8*(H$7-1) -> 1 | I10: =Inputs!$B$7+Inputs!$B$8*(I$7-1) -> 1 | J10: =Inputs!$B$7+Inputs!$B$8*(J$7-1) -> 1 | ... BJ10: =Inputs!$B$7+Inputs!$B$8*(BJ$7-1) -> 1
A11: Helper: months of the period still on the ramp-up | C11: =MAX(0,MIN(1,Inputs!$B$13-(C$6-1)*1)) -> 1 | D11: =MAX(0,MIN(1,Inputs!$B$13-(D$6-1)*1)) -> 1 | E11: =MAX(0,MIN(1,Inputs!$B$13-(E$6-1)*1)) -> 1 | F11: =MAX(0,MIN(1,Inputs!$B$13-(F$6-1)*1)) -> 1 | G11: =MAX(0,MIN(1,Inputs!$B$13-(G$6-1)*1)) -> 1 | H11: =MAX(0,MIN(1,Inputs!$B$13-(H$6-1)*1)) -> 1 | I11: =MAX(0,MIN(1,Inputs!$B$13-(I$6-1)*1)) -> 1 | J11: =MAX(0,MIN(1,Inputs!$B$13-(J$6-1)*1)) -> 1 | ... BJ11: =MAX(0,MIN(1,Inputs!$B$13-(BJ$6-1)*1)) -> 0
A12: Ramp-up factor (share of mature volume) | C12: =IF(Inputs!$B$13<=0,1,(C11*Inputs!$B$14+(1-Inputs!$B$14)/MAX(1,Inputs!$B$13)*(C11*(C$6-1)*1+C11*(C11-1)/2)+1-C11)/1) -> 0.35 | D12: =IF(Inputs!$B$13<=0,1,(D11*Inputs!$B$14+(1-Inputs!$B$14)/MAX(1,Inputs!$B$13)*(D11*(D$6-1)*1+D11*(D11-1)/2)+1-D11)/1) -> 0.42222222 | E12: =IF(Inputs!$B$13<=0,1,(E11*Inputs!$B$14+(1-Inputs!$B$14)/MAX(1,Inputs!$B$13)*(E11*(E$6-1)*1+E11*(E11-1)/2)+1-E11)/1) -> 0.49444444 | F12: =IF(Inputs!$B$13<=0,1,(F11*Inputs!$B$14+(1-Inputs!$B$14)/MAX(1,Inputs!$B$13)*(F11*(F$6-1)*1+F11*(F11-1)/2)+1-F11)/1) -> 0.56666667 | G12: =IF(Inputs!$B$13<=0,1,(G11*Inputs!$B$14+(1-Inputs!$B$14)/MAX(1,Inputs!$B$13)*(G11*(G$6-1)*1+G11*(G11-1)/2)+1-G11)/1) -> 0.63888889 | H12: =IF(Inputs!$B$13<=0,1,(H11*Inputs!$B$14+(1-Inputs!$B$14)/MAX(1,Inputs!$B$13)*(H11*(H$6-1)*1+H11*(H11-1)/2)+1-H11)/1) -> 0.71111111 | I12: =IF(Inputs!$B$13<=0,1,(I11*Inputs!$B$14+(1-Inputs!$B$14)/MAX(1,Inputs!$B$13)*(I11*(I$6-1)*1+I11*(I11-1)/2)+1-I11)/1) -> 0.78333333 | J12: =IF(Inputs!$B$13<=0,1,(J11*Inputs!$B$14+(1-Inputs!$B$14)/MAX(1,Inputs!$B$13)*(J11*(J$6-1)*1+J11*(J11-1)/2)+1-J11)/1) -> 0.85555556 | ... BJ12: =IF(Inputs!$B$13<=0,1,(BJ11*Inputs!$B$14+(1-Inputs!$B$14)/MAX(1,Inputs!$B$13)*(BJ11*(BJ$6-1)*1+BJ11*(BJ11-1)/2)+1-BJ11)/1) -> 1
A13: Season factor (winter dip in street days) | C13: =IF(OR(MOD(C$6-1,12)>=11,MOD(C$6-1,12)<=1),1-Inputs!$B$10,1+Inputs!$B$10/3) -> 0.7 | D13: =IF(OR(MOD(D$6-1,12)>=11,MOD(D$6-1,12)<=1),1-Inputs!$B$10,1+Inputs!$B$10/3) -> 0.7 | E13: =IF(OR(MOD(E$6-1,12)>=11,MOD(E$6-1,12)<=1),1-Inputs!$B$10,1+Inputs!$B$10/3) -> 1.1 | F13: =IF(OR(MOD(F$6-1,12)>=11,MOD(F$6-1,12)<=1),1-Inputs!$B$10,1+Inputs!$B$10/3) -> 1.1 | G13: =IF(OR(MOD(G$6-1,12)>=11,MOD(G$6-1,12)<=1),1-Inputs!$B$10,1+Inputs!$B$10/3) -> 1.1 | H13: =IF(OR(MOD(H$6-1,12)>=11,MOD(H$6-1,12)<=1),1-Inputs!$B$10,1+Inputs!$B$10/3) -> 1.1 | I13: =IF(OR(MOD(I$6-1,12)>=11,MOD(I$6-1,12)<=1),1-Inputs!$B$10,1+Inputs!$B$10/3) -> 1.1 | J13: =IF(OR(MOD(J$6-1,12)>=11,MOD(J$6-1,12)<=1),1-Inputs!$B$10,1+Inputs!$B$10/3) -> 1.1 | ... BJ13: =IF(OR(MOD(BJ$6-1,12)>=11,MOD(BJ$6-1,12)<=1),1-Inputs!$B$10,1+Inputs!$B$10/3) -> 0.7
A14: Street service days | C14: =C10*Inputs!$B$9*1*C13 -> 11.9 | D14: =D10*Inputs!$B$9*1*D13 -> 11.9 | E14: =E10*Inputs!$B$9*1*E13 -> 18.7 | F14: =F10*Inputs!$B$9*1*F13 -> 18.7 | G14: =G10*Inputs!$B$9*1*G13 -> 18.7 | H14: =H10*Inputs!$B$9*1*H13 -> 18.7 | I14: =I10*Inputs!$B$9*1*I13 -> 18.7 | J14: =J10*Inputs!$B$9*1*J13 -> 18.7 | ... BJ14: =BJ10*Inputs!$B$9*1*BJ13 -> 11.9
A15: Event and catering days | C15: =C10*Inputs!$B$23*(1+Inputs!$B$24)^(C$7-1)*1*C12 -> 0.875 | D15: =D10*Inputs!$B$23*(1+Inputs!$B$24)^(D$7-1)*1*D12 -> 1.0555556 | E15: =E10*Inputs!$B$23*(1+Inputs!$B$24)^(E$7-1)*1*E12 -> 1.2361111 | F15: =F10*Inputs!$B$23*(1+Inputs!$B$24)^(F$7-1)*1*F12 -> 1.4166667 | G15: =G10*Inputs!$B$23*(1+Inputs!$B$24)^(G$7-1)*1*G12 -> 1.5972222 | H15: =H10*Inputs!$B$23*(1+Inputs!$B$24)^(H$7-1)*1*H12 -> 1.7777778 | I15: =I10*Inputs!$B$23*(1+Inputs!$B$24)^(I$7-1)*1*I12 -> 1.9583333 | J15: =J10*Inputs!$B$23*(1+Inputs!$B$24)^(J$7-1)*1*J12 -> 2.1388889 | ... BJ15: =BJ10*Inputs!$B$23*(1+Inputs!$B$24)^(BJ$7-1)*1*BJ12 -> 2.5
A16: Service days - total | C16: =C14+C15 -> 12.775 | D16: =D14+D15 -> 12.955556 | E16: =E14+E15 -> 19.936111 | F16: =F14+F15 -> 20.116667 | G16: =G14+G15 -> 20.297222 | H16: =H14+H15 -> 20.477778 | I16: =I14+I15 -> 20.658333 | J16: =J14+J15 -> 20.838889 | ... BJ16: =BJ14+BJ15 -> 14.4
A17: Meals sold on the street | C17: =C14*Inputs!$B$17*(1+Inputs!$B$18)^(C$7-1)*C12 -> 324.87 | D17: =D14*Inputs!$B$17*(1+Inputs!$B$18)^(D$7-1)*D12 -> 391.90667 | E17: =E14*Inputs!$B$17*(1+Inputs!$B$18)^(E$7-1)*E12 -> 721.19667 | F17: =F14*Inputs!$B$17*(1+Inputs!$B$18)^(F$7-1)*F12 -> 826.54 | G17: =G14*Inputs!$B$17*(1+Inputs!$B$18)^(G$7-1)*G12 -> 931.88333 | H17: =H14*Inputs!$B$17*(1+Inputs!$B$18)^(H$7-1)*H12 -> 1037.2267 | I17: =I14*Inputs!$B$17*(1+Inputs!$B$18)^(I$7-1)*I12 -> 1142.57 | J17: =J14*Inputs!$B$17*(1+Inputs!$B$18)^(J$7-1)*J12 -> 1247.9133 | ... BJ17: =BJ14*Inputs!$B$17*(1+Inputs!$B$18)^(BJ$7-1)*BJ12 -> 928.2
A18: Meals served at events | C18: =C15*Inputs!$B$26 -> 87.5 | D18: =D15*Inputs!$B$26 -> 105.55556 | E18: =E15*Inputs!$B$26 -> 123.61111 | F18: =F15*Inputs!$B$26 -> 141.66667 | G18: =G15*Inputs!$B$26 -> 159.72222 | H18: =H15*Inputs!$B$26 -> 177.77778 | I18: =I15*Inputs!$B$26 -> 195.83333 | J18: =J15*Inputs!$B$26 -> 213.88889 | ... BJ18: =BJ15*Inputs!$B$26 -> 250
A19: Meals - total | C19: =C17+C18 -> 412.37 | D19: =D17+D18 -> 497.46222 | E19: =E17+E18 -> 844.80778 | F19: =F17+F18 -> 968.20667 | G19: =G17+G18 -> 1091.6056 | H19: =H17+H18 -> 1215.0044 | I19: =I17+I18 -> 1338.4033 | J19: =J17+J18 -> 1461.8022 | ... BJ19: =BJ17+BJ18 -> 1178.2
A21: Revenue
A22: Average ticket per street meal | C22: =Inputs!$B$19*(1+Inputs!$B$20)^(C$7-1) -> 13 | D22: =Inputs!$B$19*(1+Inputs!$B$20)^(D$7-1) -> 13 | E22: =Inputs!$B$19*(1+Inputs!$B$20)^(E$7-1) -> 13 | F22: =Inputs!$B$19*(1+Inputs!$B$20)^(F$7-1) -> 13 | G22: =Inputs!$B$19*(1+Inputs!$B$20)^(G$7-1) -> 13 | H22: =Inputs!$B$19*(1+Inputs!$B$20)^(H$7-1) -> 13 | I22: =Inputs!$B$19*(1+Inputs!$B$20)^(I$7-1) -> 13 | J22: =Inputs!$B$19*(1+Inputs!$B$20)^(J$7-1) -> 13 | ... BJ22: =Inputs!$B$19*(1+Inputs!$B$20)^(BJ$7-1) -> 14.071618
A23: Revenue per event day | C23: =Inputs!$B$25*(1+Inputs!$B$20)^(C$7-1) -> 1250 | D23: =Inputs!$B$25*(1+Inputs!$B$20)^(D$7-1) -> 1250 | E23: =Inputs!$B$25*(1+Inputs!$B$20)^(E$7-1) -> 1250 | F23: =Inputs!$B$25*(1+Inputs!$B$20)^(F$7-1) -> 1250 | G23: =Inputs!$B$25*(1+Inputs!$B$20)^(G$7-1) -> 1250 | H23: =Inputs!$B$25*(1+Inputs!$B$20)^(H$7-1) -> 1250 | I23: =Inputs!$B$25*(1+Inputs!$B$20)^(I$7-1) -> 1250 | J23: =Inputs!$B$25*(1+Inputs!$B$20)^(J$7-1) -> 1250 | ... BJ23: =Inputs!$B$25*(1+Inputs!$B$20)^(BJ$7-1) -> 1353.0402
A24: Street sales | C24: =C17*C22 -> 4223.31 | D24: =D17*D22 -> 5094.7867 | E24: =E17*E22 -> 9375.5567 | F24: =F17*F22 -> 10745.02 | G24: =G17*G22 -> 12114.483 | H24: =H17*H22 -> 13483.947 | I24: =I17*I22 -> 14853.41 | J24: =J17*J22 -> 16222.873 | ... BJ24: =BJ17*BJ22 -> 13061.276
A25: Events & catering | C25: =C15*C23 -> 1093.75 | D25: =D15*D23 -> 1319.4444 | E25: =E15*E23 -> 1545.1389 | F25: =F15*F23 -> 1770.8333 | G25: =G15*G23 -> 1996.5278 | H25: =H15*H23 -> 2222.2222 | I25: =I15*I23 -> 2447.9167 | J25: =J15*J23 -> 2673.6111 | ... BJ25: =BJ15*BJ23 -> 3382.6005
A26: Revenue | C26: =C24+C25 -> 5317.06 | D26: =D24+D25 -> 6414.2311 | E26: =E24+E25 -> 10920.696 | F26: =F24+F25 -> 12515.853 | G26: =G24+G25 -> 14111.011 | H26: =H24+H25 -> 15706.169 | I26: =I24+I25 -> 17301.327 | J26: =J24+J25 -> 18896.484 | ... BJ26: =BJ24+BJ25 -> 16443.876
A28: Cost of sales
A29: Food cost | C29: =-C26*Inputs!$B$29 -> -1834.3857 | D29: =-D26*Inputs!$B$29 -> -2212.9097 | E29: =-E26*Inputs!$B$29 -> -3767.64 | F29: =-F26*Inputs!$B$29 -> -4317.9694 | G29: =-G26*Inputs!$B$29 -> -4868.2988 | H29: =-H26*Inputs!$B$29 -> -5418.6283 | I29: =-I26*Inputs!$B$29 -> -5968.9577 | J29: =-J26*Inputs!$B$29 -> -6519.2871 | ... BJ29: =-BJ26*Inputs!$B$29 -> -5673.1374
A30: Packaging & disposables | C30: =-C19*Inputs!$B$30*(1+Inputs!$B$34)^(C$7-1) -> -206.185 | D30: =-D19*Inputs!$B$30*(1+Inputs!$B$34)^(D$7-1) -> -248.73111 | E30: =-E19*Inputs!$B$30*(1+Inputs!$B$34)^(E$7-1) -> -422.40389 | F30: =-F19*Inputs!$B$30*(1+Inputs!$B$34)^(F$7-1) -> -484.10333 | G30: =-G19*Inputs!$B$30*(1+Inputs!$B$34)^(G$7-1) -> -545.80278 | H30: =-H19*Inputs!$B$30*(1+Inputs!$B$34)^(H$7-1) -> -607.50222 | I30: =-I19*Inputs!$B$30*(1+Inputs!$B$34)^(I$7-1) -> -669.20167 | J30: =-J19*Inputs!$B$30*(1+Inputs!$B$34)^(J$7-1) -> -730.90111 | ... BJ30: =-BJ19*Inputs!$B$30*(1+Inputs!$B$34)^(BJ$7-1) -> -689.16368
A31: Food & packaging | C31: =C29+C30 -> -2040.5707 | D31: =D29+D30 -> -2461.6408 | E31: =E29+E30 -> -4190.0439 | F31: =F29+F30 -> -4802.0727 | G31: =G29+G30 -> -5414.1016 | H31: =H29+H30 -> -6026.1305 | I31: =I29+I30 -> -6638.1594 | J31: =J29+J30 -> -7250.1882 | ... BJ31: =BJ29+BJ30 -> -6362.301
A32: Card & POS processing fees | C32: =-C26*Inputs!$B$31 -> -164.82886 | D32: =-D26*Inputs!$B$31 -> -198.84116 | E32: =-E26*Inputs!$B$31 -> -338.54156 | F32: =-F26*Inputs!$B$31 -> -387.99145 | G32: =-G26*Inputs!$B$31 -> -437.44134 | H32: =-H26*Inputs!$B$31 -> -486.89124 | I32: =-I26*Inputs!$B$31 -> -536.34113 | J32: =-J26*Inputs!$B$31 -> -585.79102 | ... BJ32: =-BJ26*Inputs!$B$31 -> -509.76017
A33: Event & festival fees | C33: =-C25*Inputs!$B$32-C15*Inputs!$B$33*(1+Inputs!$B$34)^(C$7-1) -> -159.6875 | D33: =-D25*Inputs!$B$32-D15*Inputs!$B$33*(1+Inputs!$B$34)^(D$7-1) -> -192.63889 | E33: =-E25*Inputs!$B$32-E15*Inputs!$B$33*(1+Inputs!$B$34)^(E$7-1) -> -225.59028 | F33: =-F25*Inputs!$B$32-F15*Inputs!$B$33*(1+Inputs!$B$34)^(F$7-1) -> -258.54167 | G33: =-G25*Inputs!$B$32-G15*Inputs!$B$33*(1+Inputs!$B$34)^(G$7-1) -> -291.49306 | H33: =-H25*Inputs!$B$32-H15*Inputs!$B$33*(1+Inputs!$B$34)^(H$7-1) -> -324.44444 | I33: =-I25*Inputs!$B$32-I15*Inputs!$B$33*(1+Inputs!$B$34)^(I$7-1) -> -357.39583 | J33: =-J25*Inputs!$B$32-J15*Inputs!$B$33*(1+Inputs!$B$34)^(J$7-1) -> -390.34722 | ... BJ33: =-BJ25*Inputs!$B$32-BJ15*Inputs!$B$33*(1+Inputs!$B$34)^(BJ$7-1) -> -520.08759
A34: Cost of sales | C34: =C31+C32+C33 -> -2365.0871 | D34: =D31+D32+D33 -> -2853.1209 | E34: =E31+E32+E33 -> -4754.1757 | F34: =F31+F32+F33 -> -5448.6059 | G34: =G31+G32+G33 -> -6143.036 | H34: =H31+H32+H33 -> -6837.4662 | I34: =I31+I32+I33 -> -7531.8963 | J34: =J31+J32+J33 -> -8226.3265 | ... BJ34: =BJ31+BJ32+BJ33 -> -7392.1488
A35: Gross profit | C35: =C26+C34 -> 2951.9729 | D35: =D26+D34 -> 3561.1102 | E35: =E26+E34 -> 6166.5199 | F35: =F26+F34 -> 7067.2475 | G35: =G26+G34 -> 7967.9751 | H35: =H26+H34 -> 8868.7027 | I35: =I26+I34 -> 9769.4303 | J35: =J26+J34 -> 10670.158 | ... BJ35: =BJ26+BJ34 -> 9051.7276
A37: Operating expenses
A38: Payroll (owner-operator, cooks, cashiers) | C38: =C121 -> -9874.6667 | D38: =D121 -> -9874.6667 | E38: =E121 -> -9874.6667 | F38: =F121 -> -9874.6667 | G38: =G121 -> -9874.6667 | H38: =H121 -> -9874.6667 | I38: =I121 -> -9874.6667 | J38: =J121 -> -9874.6667 | ... BJ38: =BJ121 -> -11114.024
A39: Commissary kitchen | C39: =-Inputs!$B$37*C10*(1+Inputs!$B$34)^(C$7-1)*1 -> -1050 | D39: =-Inputs!$B$37*D10*(1+Inputs!$B$34)^(D$7-1)*1 -> -1050 | E39: =-Inputs!$B$37*E10*(1+Inputs!$B$34)^(E$7-1)*1 -> -1050 | F39: =-Inputs!$B$37*F10*(1+Inputs!$B$34)^(F$7-1)*1 -> -1050 | G39: =-Inputs!$B$37*G10*(1+Inputs!$B$34)^(G$7-1)*1 -> -1050 | H39: =-Inputs!$B$37*H10*(1+Inputs!$B$34)^(H$7-1)*1 -> -1050 | I39: =-Inputs!$B$37*I10*(1+Inputs!$B$34)^(I$7-1)*1 -> -1050 | J39: =-Inputs!$B$37*J10*(1+Inputs!$B$34)^(J$7-1)*1 -> -1050 | ... BJ39: =-Inputs!$B$37*BJ10*(1+Inputs!$B$34)^(BJ$7-1)*1 -> -1228.3515
A40: Permits & licences | C40: =-Inputs!$B$38*C10*(1+Inputs!$B$34)^(C$7-1)*1 -> -400 | D40: =-Inputs!$B$38*D10*(1+Inputs!$B$34)^(D$7-1)*1 -> -400 | E40: =-Inputs!$B$38*E10*(1+Inputs!$B$34)^(E$7-1)*1 -> -400 | F40: =-Inputs!$B$38*F10*(1+Inputs!$B$34)^(F$7-1)*1 -> -400 | G40: =-Inputs!$B$38*G10*(1+Inputs!$B$34)^(G$7-1)*1 -> -400 | H40: =-Inputs!$B$38*H10*(1+Inputs!$B$34)^(H$7-1)*1 -> -400 | I40: =-Inputs!$B$38*I10*(1+Inputs!$B$34)^(I$7-1)*1 -> -400 | J40: =-Inputs!$B$38*J10*(1+Inputs!$B$34)^(J$7-1)*1 -> -400 | ... BJ40: =-Inputs!$B$38*BJ10*(1+Inputs!$B$34)^(BJ$7-1)*1 -> -467.94342
A41: Insurance | C41: =-Inputs!$B$39*C10*(1+Inputs!$B$34)^(C$7-1)*1 -> -480 | D41: =-Inputs!$B$39*D10*(1+Inputs!$B$34)^(D$7-1)*1 -> -480 | E41: =-Inputs!$B$39*E10*(1+Inputs!$B$34)^(E$7-1)*1 -> -480 | F41: =-Inputs!$B$39*F10*(1+Inputs!$B$34)^(F$7-1)*1 -> -480 | G41: =-Inputs!$B$39*G10*(1+Inputs!$B$34)^(G$7-1)*1 -> -480 | H41: =-Inputs!$B$39*H10*(1+Inputs!$B$34)^(H$7-1)*1 -> -480 | I41: =-Inputs!$B$39*I10*(1+Inputs!$B$34)^(I$7-1)*1 -> -480 | J41: =-Inputs!$B$39*J10*(1+Inputs!$B$34)^(J$7-1)*1 -> -480 | ... BJ41: =-Inputs!$B$39*BJ10*(1+Inputs!$B$34)^(BJ$7-1)*1 -> -561.53211
A42: Fuel, propane & generator | C42: =-Inputs!$B$40*C16*(1+Inputs!$B$34)^(C$7-1) -> -511 | D42: =-Inputs!$B$40*D16*(1+Inputs!$B$34)^(D$7-1) -> -518.22222 | E42: =-Inputs!$B$40*E16*(1+Inputs!$B$34)^(E$7-1) -> -797.44444 | F42: =-Inputs!$B$40*F16*(1+Inputs!$B$34)^(F$7-1) -> -804.66667 | G42: =-Inputs!$B$40*G16*(1+Inputs!$B$34)^(G$7-1) -> -811.88889 | H42: =-Inputs!$B$40*H16*(1+Inputs!$B$34)^(H$7-1) -> -819.11111 | I42: =-Inputs!$B$40*I16*(1+Inputs!$B$34)^(I$7-1) -> -826.33333 | J42: =-Inputs!$B$40*J16*(1+Inputs!$B$34)^(J$7-1) -> -833.55556 | ... BJ42: =-Inputs!$B$40*BJ16*(1+Inputs!$B$34)^(BJ$7-1) -> -673.83853
A43: Truck maintenance & repairs | C43: =-Inputs!$B$41*C10*(1+Inputs!$B$34)^(C$7-1)*1 -> -550 | D43: =-Inputs!$B$41*D10*(1+Inputs!$B$34)^(D$7-1)*1 -> -550 | E43: =-Inputs!$B$41*E10*(1+Inputs!$B$34)^(E$7-1)*1 -> -550 | F43: =-Inputs!$B$41*F10*(1+Inputs!$B$34)^(F$7-1)*1 -> -550 | G43: =-Inputs!$B$41*G10*(1+Inputs!$B$34)^(G$7-1)*1 -> -550 | H43: =-Inputs!$B$41*H10*(1+Inputs!$B$34)^(H$7-1)*1 -> -550 | I43: =-Inputs!$B$41*I10*(1+Inputs!$B$34)^(I$7-1)*1 -> -550 | J43: =-Inputs!$B$41*J10*(1+Inputs!$B$34)^(J$7-1)*1 -> -550 | ... BJ43: =-Inputs!$B$41*BJ10*(1+Inputs!$B$34)^(BJ$7-1)*1 -> -643.42221
A44: POS & ordering software | C44: =-Inputs!$B$42*(1+Inputs!$B$34)^(C$7-1)*1 -> -125 | D44: =-Inputs!$B$42*(1+Inputs!$B$34)^(D$7-1)*1 -> -125 | E44: =-Inputs!$B$42*(1+Inputs!$B$34)^(E$7-1)*1 -> -125 | F44: =-Inputs!$B$42*(1+Inputs!$B$34)^(F$7-1)*1 -> -125 | G44: =-Inputs!$B$42*(1+Inputs!$B$34)^(G$7-1)*1 -> -125 | H44: =-Inputs!$B$42*(1+Inputs!$B$34)^(H$7-1)*1 -> -125 | I44: =-Inputs!$B$42*(1+Inputs!$B$34)^(I$7-1)*1 -> -125 | J44: =-Inputs!$B$42*(1+Inputs!$B$34)^(J$7-1)*1 -> -125 | ... BJ44: =-Inputs!$B$42*(1+Inputs!$B$34)^(BJ$7-1)*1 -> -146.23232
A45: Marketing | C45: =-Inputs!$B$43*(1+Inputs!$B$44)^(C$7-1)*1 -> -800 | D45: =-Inputs!$B$43*(1+Inputs!$B$44)^(D$7-1)*1 -> -800 | E45: =-Inputs!$B$43*(1+Inputs!$B$44)^(E$7-1)*1 -> -800 | F45: =-Inputs!$B$43*(1+Inputs!$B$44)^(F$7-1)*1 -> -800 | G45: =-Inputs!$B$43*(1+Inputs!$B$44)^(G$7-1)*1 -> -800 | H45: =-Inputs!$B$43*(1+Inputs!$B$44)^(H$7-1)*1 -> -800 | I45: =-Inputs!$B$43*(1+Inputs!$B$44)^(I$7-1)*1 -> -800 | J45: =-Inputs!$B$43*(1+Inputs!$B$44)^(J$7-1)*1 -> -800 | ... BJ45: =-Inputs!$B$43*(1+Inputs!$B$44)^(BJ$7-1)*1 -> -800
A46: Accounting, bank fees & other G&A | C46: =-Inputs!$B$45*(1+Inputs!$B$34)^(C$7-1)*1 -> -380 | D46: =-Inputs!$B$45*(1+Inputs!$B$34)^(D$7-1)*1 -> -380 | E46: =-Inputs!$B$45*(1+Inputs!$B$34)^(E$7-1)*1 -> -380 | F46: =-Inputs!$B$45*(1+Inputs!$B$34)^(F$7-1)*1 -> -380 | G46: =-Inputs!$B$45*(1+Inputs!$B$34)^(G$7-1)*1 -> -380 | H46: =-Inputs!$B$45*(1+Inputs!$B$34)^(H$7-1)*1 -> -380 | I46: =-Inputs!$B$45*(1+Inputs!$B$34)^(I$7-1)*1 -> -380 | J46: =-Inputs!$B$45*(1+Inputs!$B$34)^(J$7-1)*1 -> -380 | ... BJ46: =-Inputs!$B$45*(1+Inputs!$B$34)^(BJ$7-1)*1 -> -444.54625
A47: Total operating expenses | C47: =C38+C39+C40+C41+C42+C43+C44+C45+C46 -> -14170.667 | D47: =D38+D39+D40+D41+D42+D43+D44+D45+D46 -> -14177.889 | E47: =E38+E39+E40+E41+E42+E43+E44+E45+E46 -> -14457.111 | F47: =F38+F39+F40+F41+F42+F43+F44+F45+F46 -> -14464.333 | G47: =G38+G39+G40+G41+G42+G43+G44+G45+G46 -> -14471.556 | H47: =H38+H39+H40+H41+H42+H43+H44+H45+H46 -> -14478.778 | I47: =I38+I39+I40+I41+I42+I43+I44+I45+I46 -> -14486 | J47: =J38+J39+J40+J41+J42+J43+J44+J45+J46 -> -14493.222 | ... BJ47: =BJ38+BJ39+BJ40+BJ41+BJ42+BJ43+BJ44+BJ45+BJ46 -> -16079.891
A48: EBITDA | C48: =C35+C47 -> -11218.694 | D48: =D35+D47 -> -10616.779 | E48: =E35+E47 -> -8290.5913 | F48: =F35+F47 -> -7397.0859 | G48: =G35+G47 -> -6503.5805 | H48: =H35+H47 -> -5610.0751 | I48: =I35+I47 -> -4716.5697 | J48: =J35+J47 -> -3823.0643 | ... BJ48: =BJ35+BJ47 -> -7028.1631
A50: Profit after depreciation, interest, tax
A51: EBIT | C51: =C48+C66 -> -12861.551 | D51: =D48+D66 -> -12259.636 | E51: =E48+E66 -> -9933.4484 | F51: =F48+F66 -> -9039.943 | G51: =G48+G66 -> -8146.4376 | H51: =H48+H66 -> -7252.9322 | I51: =I48+I66 -> -6359.4268 | J51: =J48+J66 -> -5465.9214 | ... BJ51: =BJ48+BJ66 -> -8790.0678
A52: Interest on loan (average balance after drawdown) | C52: =-(C71+C72+C74)/2*Inputs!$B$73/12 -> -675 | D52: =-(D71+D72+D74)/2*Inputs!$B$73/12 -> -669.375 | E52: =-(E71+E72+E74)/2*Inputs!$B$73/12 -> -658.125 | F52: =-(F71+F72+F74)/2*Inputs!$B$73/12 -> -646.875 | G52: =-(G71+G72+G74)/2*Inputs!$B$73/12 -> -635.625 | H52: =-(H71+H72+H74)/2*Inputs!$B$73/12 -> -624.375 | I52: =-(I71+I72+I74)/2*Inputs!$B$73/12 -> -613.125 | J52: =-(J71+J72+J74)/2*Inputs!$B$73/12 -> -601.875 | ... BJ52: =-(BJ71+BJ72+BJ74)/2*Inputs!$B$73/12 -> -16.875
A53: Pre-tax income | C53: =C51+C52 -> -13536.551 | D53: =D51+D52 -> -12929.011 | E53: =E51+E52 -> -10591.573 | F53: =F51+F52 -> -9686.818 | G53: =G51+G52 -> -8782.0626 | H53: =H51+H52 -> -7877.3072 | I53: =I51+I52 -> -6972.5518 | J53: =J51+J52 -> -6067.7964 | ... BJ53: =BJ51+BJ52 -> -8806.9428
A54: Helper: cumulative pre-tax income | C54: =C53 -> -13536.551 | D54: =C54+D53 -> -26465.562 | E54: =D54+E53 -> -37057.135 | F54: =E54+F53 -> -46743.953 | G54: =F54+G53 -> -55526.016 | H54: =G54+H53 -> -63403.323 | I54: =H54+I53 -> -70375.875 | J54: =I54+J53 -> -76443.671 | K54: =J54+K53 -> -81606.712 | ... BJ54: =BI54+BJ53 -> -367104.45
A55: Helper: cumulative taxable income (losses carried forward) | C55: =MAX(0,C54) -> 0 | D55: =MAX(C55,D54) -> 0 | E55: =MAX(D55,E54) -> 0 | F55: =MAX(E55,F54) -> 0 | G55: =MAX(F55,G54) -> 0 | H55: =MAX(G55,H54) -> 0 | I55: =MAX(H55,I54) -> 0 | J55: =MAX(I55,J54) -> 0 | K55: =MAX(J55,K54) -> 0 | ... BJ55: =MAX(BI55,BJ54) -> 0
A56: Income tax | C56: =-C55*Inputs!$B$83 -> 0 | D56: =-(D55-C55)*Inputs!$B$83 -> 0 | E56: =-(E55-D55)*Inputs!$B$83 -> 0 | F56: =-(F55-E55)*Inputs!$B$83 -> 0 | G56: =-(G55-F55)*Inputs!$B$83 -> 0 | H56: =-(H55-G55)*Inputs!$B$83 -> 0 | I56: =-(I55-H55)*Inputs!$B$83 -> 0 | J56: =-(J55-I55)*Inputs!$B$83 -> 0 | K56: =-(K55-J55)*Inputs!$B$83 -> 0 | ... BJ56: =-(BJ55-BI55)*Inputs!$B$83 -> 0
A57: Net income | C57: =C53+C56 -> -13536.551 | D57: =D53+D56 -> -12929.011 | E57: =E53+E56 -> -10591.573 | F57: =F53+F56 -> -9686.818 | G57: =G53+G56 -> -8782.0626 | H57: =H53+H56 -> -7877.3072 | I57: =I53+I56 -> -6972.5518 | J57: =J53+J56 -> -6067.7964 | ... BJ57: =BJ53+BJ56 -> -8806.9428
A59: Fixed assets & capital spending
A60: Truck purchase (month 1; trucks added from year 2) | C60: =Inputs!$B$48*Inputs!$B$49 -> 95000 | D60: =IF(AND(D$7>1,MOD(D$6-1,12)=0),Inputs!$B$8*Inputs!$B$49,0) -> 0 | E60: =IF(AND(E$7>1,MOD(E$6-1,12)=0),Inputs!$B$8*Inputs!$B$49,0) -> 0 | F60: =IF(AND(F$7>1,MOD(F$6-1,12)=0),Inputs!$B$8*Inputs!$B$49,0) -> 0 | G60: =IF(AND(G$7>1,MOD(G$6-1,12)=0),Inputs!$B$8*Inputs!$B$49,0) -> 0 | H60: =IF(AND(H$7>1,MOD(H$6-1,12)=0),Inputs!$B$8*Inputs!$B$49,0) -> 0 | I60: =IF(AND(I$7>1,MOD(I$6-1,12)=0),Inputs!$B$8*Inputs!$B$49,0) -> 0 | J60: =IF(AND(J$7>1,MOD(J$6-1,12)=0),Inputs!$B$8*Inputs!$B$49,0) -> 0 | K60: =IF(AND(K$7>1,MOD(K$6-1,12)=0),Inputs!$B$8*Inputs!$B$49,0) -> 0 | ... BJ60: =IF(AND(BJ$7>1,MOD(BJ$6-1,12)=0),Inputs!$B$8*Inputs!$B$49,0) -> 0
A61: Kitchen build-out, equipment & wrap | C61: =Inputs!$B$48*Inputs!$B$50 -> 40000 | D61: =IF(AND(D$7>1,MOD(D$6-1,12)=0),Inputs!$B$8*Inputs!$B$50,0) -> 0 | E61: =IF(AND(E$7>1,MOD(E$6-1,12)=0),Inputs!$B$8*Inputs!$B$50,0) -> 0 | F61: =IF(AND(F$7>1,MOD(F$6-1,12)=0),Inputs!$B$8*Inputs!$B$50,0) -> 0 | G61: =IF(AND(G$7>1,MOD(G$6-1,12)=0),Inputs!$B$8*Inputs!$B$50,0) -> 0 | H61: =IF(AND(H$7>1,MOD(H$6-1,12)=0),Inputs!$B$8*Inputs!$B$50,0) -> 0 | I61: =IF(AND(I$7>1,MOD(I$6-1,12)=0),Inputs!$B$8*Inputs!$B$50,0) -> 0 | J61: =IF(AND(J$7>1,MOD(J$6-1,12)=0),Inputs!$B$8*Inputs!$B$50,0) -> 0 | K61: =IF(AND(K$7>1,MOD(K$6-1,12)=0),Inputs!$B$8*Inputs!$B$50,0) -> 0 | ... BJ61: =IF(AND(BJ$7>1,MOD(BJ$6-1,12)=0),Inputs!$B$8*Inputs!$B$50,0) -> 0
A62: POS hardware & smallwares | C62: =IF(C$6=1,Inputs!$B$51,0) -> 3000 | D62: =IF(D$6=1,Inputs!$B$51,0) -> 0 | E62: =IF(E$6=1,Inputs!$B$51,0) -> 0 | F62: =IF(F$6=1,Inputs!$B$51,0) -> 0 | G62: =IF(G$6=1,Inputs!$B$51,0) -> 0 | H62: =IF(H$6=1,Inputs!$B$51,0) -> 0 | I62: =IF(I$6=1,Inputs!$B$51,0) -> 0 | J62: =IF(J$6=1,Inputs!$B$51,0) -> 0 | ... BJ62: =IF(BJ$6=1,Inputs!$B$51,0) -> 0
A63: Equipment refresh (first period of each year from year 2) | C63: =IF(AND(C$7>1,MOD(C$6-1,12)=0),Inputs!$B$52*C10,0) -> 0 | D63: =IF(AND(D$7>1,MOD(D$6-1,12)=0),Inputs!$B$52*D10,0) -> 0 | E63: =IF(AND(E$7>1,MOD(E$6-1,12)=0),Inputs!$B$52*E10,0) -> 0 | F63: =IF(AND(F$7>1,MOD(F$6-1,12)=0),Inputs!$B$52*F10,0) -> 0 | G63: =IF(AND(G$7>1,MOD(G$6-1,12)=0),Inputs!$B$52*G10,0) -> 0 | H63: =IF(AND(H$7>1,MOD(H$6-1,12)=0),Inputs!$B$52*H10,0) -> 0 | I63: =IF(AND(I$7>1,MOD(I$6-1,12)=0),Inputs!$B$52*I10,0) -> 0 | J63: =IF(AND(J$7>1,MOD(J$6-1,12)=0),Inputs!$B$52*J10,0) -> 0 | ... BJ63: =IF(AND(BJ$7>1,MOD(BJ$6-1,12)=0),Inputs!$B$52*BJ10,0) -> 0
A64: Capital spending | C64: =C60+C61+C62+C63 -> 138000 | D64: =D60+D61+D62+D63 -> 0 | E64: =E60+E61+E62+E63 -> 0 | F64: =F60+F61+F62+F63 -> 0 | G64: =G60+G61+G62+G63 -> 0 | H64: =H60+H61+H62+H63 -> 0 | I64: =I60+I61+I62+I63 -> 0 | J64: =J60+J61+J62+J63 -> 0 | ... BJ64: =BJ60+BJ61+BJ62+BJ63 -> 0
A65: Fixed assets at cost | C65: =C64 -> 138000 | D65: =C65+D64 -> 138000 | E65: =D65+E64 -> 138000 | F65: =E65+F64 -> 138000 | G65: =F65+G64 -> 138000 | H65: =G65+H64 -> 138000 | I65: =H65+I64 -> 138000 | J65: =I65+J64 -> 138000 | K65: =J65+K64 -> 138000 | ... BJ65: =BI65+BJ64 -> 148000
A66: Depreciation | C66: =-MIN(C65/MAX(1,Inputs!$B$82*12),C64) -> -1642.8571 | D66: =-MIN(D65/MAX(1,Inputs!$B$82*12),C68+D64) -> -1642.8571 | E66: =-MIN(E65/MAX(1,Inputs!$B$82*12),D68+E64) -> -1642.8571 | F66: =-MIN(F65/MAX(1,Inputs!$B$82*12),E68+F64) -> -1642.8571 | G66: =-MIN(G65/MAX(1,Inputs!$B$82*12),F68+G64) -> -1642.8571 | H66: =-MIN(H65/MAX(1,Inputs!$B$82*12),G68+H64) -> -1642.8571 | I66: =-MIN(I65/MAX(1,Inputs!$B$82*12),H68+I64) -> -1642.8571 | J66: =-MIN(J65/MAX(1,Inputs!$B$82*12),I68+J64) -> -1642.8571 | K66: =-MIN(K65/MAX(1,Inputs!$B$82*12),J68+K64) -> -1642.8571 | ... BJ66: =-MIN(BJ65/MAX(1,Inputs!$B$82*12),BI68+BJ64) -> -1761.9048
A67: Accumulated depreciation | C67: =C66 -> -1642.8571 | D67: =C67+D66 -> -3285.7143 | E67: =D67+E66 -> -4928.5714 | F67: =E67+F66 -> -6571.4286 | G67: =F67+G66 -> -8214.2857 | H67: =G67+H66 -> -9857.1429 | I67: =H67+I66 -> -11500 | J67: =I67+J66 -> -13142.857 | K67: =J67+K66 -> -14785.714 | ... BJ67: =BI67+BJ66 -> -102142.86
A68: Net fixed assets | C68: =C65+C67 -> 136357.14 | D68: =D65+D67 -> 134714.29 | E68: =E65+E67 -> 133071.43 | F68: =F65+F67 -> 131428.57 | G68: =G65+G67 -> 129785.71 | H68: =H65+H67 -> 128142.86 | I68: =I65+I67 -> 126500 | J68: =J65+J67 -> 124857.14 | ... BJ68: =BJ65+BJ67 -> 45857.143
A70: Debt
A71: Loan — opening balance | C71: =0 -> 0 | D71: =C74 -> 90000 | E71: =D74 -> 88500 | F71: =E74 -> 87000 | G71: =F74 -> 85500 | H71: =G74 -> 84000 | I71: =H74 -> 82500 | J71: =I74 -> 81000 | K71: =J74 -> 79500 | ... BJ71: =BI74 -> 3000
A72: Loan drawdown | C72: =IF(C$6=1,Inputs!$B$72,0) -> 90000 | D72: =IF(D$6=1,Inputs!$B$72,0) -> 0 | E72: =IF(E$6=1,Inputs!$B$72,0) -> 0 | F72: =IF(F$6=1,Inputs!$B$72,0) -> 0 | G72: =IF(G$6=1,Inputs!$B$72,0) -> 0 | H72: =IF(H$6=1,Inputs!$B$72,0) -> 0 | I72: =IF(I$6=1,Inputs!$B$72,0) -> 0 | J72: =IF(J$6=1,Inputs!$B$72,0) -> 0 | ... BJ72: =IF(BJ$6=1,Inputs!$B$72,0) -> 0
A73: Loan repayment | C73: =-MIN(C71,Inputs!$B$72/MAX(1,Inputs!$B$74*12)) -> 0 | D73: =-MIN(D71,Inputs!$B$72/MAX(1,Inputs!$B$74*12)) -> -1500 | E73: =-MIN(E71,Inputs!$B$72/MAX(1,Inputs!$B$74*12)) -> -1500 | F73: =-MIN(F71,Inputs!$B$72/MAX(1,Inputs!$B$74*12)) -> -1500 | G73: =-MIN(G71,Inputs!$B$72/MAX(1,Inputs!$B$74*12)) -> -1500 | H73: =-MIN(H71,Inputs!$B$72/MAX(1,Inputs!$B$74*12)) -> -1500 | I73: =-MIN(I71,Inputs!$B$72/MAX(1,Inputs!$B$74*12)) -> -1500 | J73: =-MIN(J71,Inputs!$B$72/MAX(1,Inputs!$B$74*12)) -> -1500 | ... BJ73: =-MIN(BJ71,Inputs!$B$72/MAX(1,Inputs!$B$74*12)) -> -1500
A74: Loan — closing balance | C74: =C71+C72+C73 -> 90000 | D74: =D71+D72+D73 -> 88500 | E74: =E71+E72+E73 -> 87000 | F74: =F71+F72+F73 -> 85500 | G74: =G71+G72+G73 -> 84000 | H74: =H71+H72+H73 -> 82500 | I74: =I71+I72+I73 -> 81000 | J74: =J71+J72+J73 -> 79500 | ... BJ74: =BJ71+BJ72+BJ73 -> 1500
A76: Working capital
A77: Accounts receivable | C77: =C26*Inputs!$B$77/30 -> 531.706 | D77: =D26*Inputs!$B$77/30 -> 641.42311 | E77: =E26*Inputs!$B$77/30 -> 1092.0696 | F77: =F26*Inputs!$B$77/30 -> 1251.5853 | G77: =G26*Inputs!$B$77/30 -> 1411.1011 | H77: =H26*Inputs!$B$77/30 -> 1570.6169 | I77: =I26*Inputs!$B$77/30 -> 1730.1327 | J77: =J26*Inputs!$B$77/30 -> 1889.6484 | ... BJ77: =BJ26*Inputs!$B$77/30 -> 1644.3876
A78: Inventory | C78: =-C34*Inputs!$B$78/30 -> 236.50871 | D78: =-D34*Inputs!$B$78/30 -> 285.31209 | E78: =-E34*Inputs!$B$78/30 -> 475.41757 | F78: =-F34*Inputs!$B$78/30 -> 544.86059 | G78: =-G34*Inputs!$B$78/30 -> 614.3036 | H78: =-H34*Inputs!$B$78/30 -> 683.74662 | I78: =-I34*Inputs!$B$78/30 -> 753.18963 | J78: =-J34*Inputs!$B$78/30 -> 822.63265 | ... BJ78: =-BJ34*Inputs!$B$78/30 -> 739.21488
A79: Accounts payable | C79: =-C34*Inputs!$B$79/30 -> 551.85365 | D79: =-D34*Inputs!$B$79/30 -> 665.72821 | E79: =-E34*Inputs!$B$79/30 -> 1109.3077 | F79: =-F34*Inputs!$B$79/30 -> 1271.3414 | G79: =-G34*Inputs!$B$79/30 -> 1433.3751 | H79: =-H34*Inputs!$B$79/30 -> 1595.4088 | I79: =-I34*Inputs!$B$79/30 -> 1757.4425 | J79: =-J34*Inputs!$B$79/30 -> 1919.4762 | ... BJ79: =-BJ34*Inputs!$B$79/30 -> 1724.8347
A80: (Increase) / decrease in receivables | C80: =-C77 -> -531.706 | D80: =C77-D77 -> -109.71711 | E80: =D77-E77 -> -450.64644 | F80: =E77-F77 -> -159.51578 | G80: =F77-G77 -> -159.51578 | H80: =G77-H77 -> -159.51578 | I80: =H77-I77 -> -159.51578 | J80: =I77-J77 -> -159.51578 | K80: =J77-K77 -> -159.51578 | ... BJ80: =BI77-BJ77 -> 746.35862
A81: (Increase) / decrease in inventory | C81: =-C78 -> -236.50871 | D81: =C78-D78 -> -48.803384 | E81: =D78-E78 -> -190.10548 | F81: =E78-F78 -> -69.443016 | G81: =F78-G78 -> -69.443016 | H81: =G78-H78 -> -69.443016 | I81: =H78-I78 -> -69.443016 | J81: =I78-J78 -> -69.443016 | K81: =J78-K78 -> -69.443016 | ... BJ81: =BI78-BJ78 -> 311.65549
A82: Increase / (decrease) in payables | C82: =C79 -> 551.85365 | D82: =D79-C79 -> 113.87456 | E82: =E79-D79 -> 443.57945 | F82: =F79-E79 -> 162.0337 | G82: =G79-F79 -> 162.0337 | H82: =H79-G79 -> 162.0337 | I82: =I79-H79 -> 162.0337 | J82: =J79-I79 -> 162.0337 | K82: =K79-J79 -> 162.0337 | ... BJ82: =BJ79-BI79 -> -727.19615
A84: Cash flow
A85: Operating cash flow | C85: =C57-C66+C80+C81+C82 -> -12110.055 | D85: =D57-D66+D80+D81+D82 -> -11330.8 | E85: =E57-E66+E80+E81+E82 -> -9145.8887 | F85: =F57-F66+F80+F81+F82 -> -8110.8859 | G85: =G57-G66+G80+G81+G82 -> -7206.1305 | H85: =H57-H66+H80+H81+H82 -> -6301.3751 | I85: =I57-I66+I80+I81+I82 -> -5396.6198 | J85: =J57-J66+J80+J81+J82 -> -4491.8644 | ... BJ85: =BJ57-BJ66+BJ80+BJ81+BJ82 -> -6714.2201
A86: Investing cash flow (capex) | C86: =-C64 -> -138000 | D86: =-D64 -> 0 | E86: =-E64 -> 0 | F86: =-F64 -> 0 | G86: =-G64 -> 0 | H86: =-H64 -> 0 | I86: =-I64 -> 0 | J86: =-J64 -> 0 | ... BJ86: =-BJ64 -> 0
A87: Equity raised | C87: =IF(C$6=1,Inputs!$B$71,0) -> 100000 | D87: =IF(D$6=1,Inputs!$B$71,0) -> 0 | E87: =IF(E$6=1,Inputs!$B$71,0) -> 0 | F87: =IF(F$6=1,Inputs!$B$71,0) -> 0 | G87: =IF(G$6=1,Inputs!$B$71,0) -> 0 | H87: =IF(H$6=1,Inputs!$B$71,0) -> 0 | I87: =IF(I$6=1,Inputs!$B$71,0) -> 0 | J87: =IF(J$6=1,Inputs!$B$71,0) -> 0 | ... BJ87: =IF(BJ$6=1,Inputs!$B$71,0) -> 0
A88: Financing cash flow | C88: =C87+C72+C73 -> 190000 | D88: =D87+D72+D73 -> -1500 | E88: =E87+E72+E73 -> -1500 | F88: =F87+F72+F73 -> -1500 | G88: =G87+G72+G73 -> -1500 | H88: =H87+H72+H73 -> -1500 | I88: =I87+I72+I73 -> -1500 | J88: =J87+J72+J73 -> -1500 | ... BJ88: =BJ87+BJ72+BJ73 -> -1500
A89: Net cash flow | C89: =C85+C86+C88 -> 39889.945 | D89: =D85+D86+D88 -> -12830.8 | E89: =E85+E86+E88 -> -10645.889 | F89: =F85+F86+F88 -> -9610.8859 | G89: =G85+G86+G88 -> -8706.1305 | H89: =H85+H86+H88 -> -7801.3751 | I89: =I85+I86+I88 -> -6896.6198 | J89: =J85+J86+J88 -> -5991.8644 | ... BJ89: =BJ85+BJ86+BJ88 -> -8214.2201
A90: Opening cash | C90: =0 -> 0 | D90: =C91 -> 39889.945 | E90: =D91 -> 27059.146 | F90: =E91 -> 16413.257 | G90: =F91 -> 6802.3709 | H90: =G91 -> -1903.7596 | I90: =H91 -> -9705.1348 | J90: =I91 -> -16601.755 | K90: =J91 -> -22593.619 | ... BJ90: =BI91 -> -303906.14
A91: Closing cash | C91: =C90+C89 -> 39889.945 | D91: =D90+D89 -> 27059.146 | E91: =E90+E89 -> 16413.257 | F91: =F90+F89 -> 6802.3709 | G91: =G90+G89 -> -1903.7596 | H91: =H90+H89 -> -9705.1348 | I91: =I90+I89 -> -16601.755 | J91: =J90+J89 -> -22593.619 | ... BJ91: =BJ90+BJ89 -> -312120.36
A92: Helper: EBITDA positive (1/0) | C92: =IF(C48>0,1,0) -> 0 | D92: =IF(D48>0,1,0) -> 0 | E92: =IF(E48>0,1,0) -> 0 | F92: =IF(F48>0,1,0) -> 0 | G92: =IF(G48>0,1,0) -> 0 | H92: =IF(H48>0,1,0) -> 0 | I92: =IF(I48>0,1,0) -> 0 | J92: =IF(J48>0,1,0) -> 0 | ... BJ92: =IF(BJ48>0,1,0) -> 0
A94: Goal modules
A95: Helper: net income positive (1/0) | C95: =IF(C57>0,1,0) -> 0 | D95: =IF(D57>0,1,0) -> 0 | E95: =IF(E57>0,1,0) -> 0 | F95: =IF(F57>0,1,0) -> 0 | G95: =IF(G57>0,1,0) -> 0 | H95: =IF(H57>0,1,0) -> 0 | I95: =IF(I57>0,1,0) -> 0 | J95: =IF(J57>0,1,0) -> 0 | ... BJ95: =IF(BJ57>0,1,0) -> 0
A96: Cash flow before financing (operating + investing) | C96: =C85+C86 -> -150110.05 | D96: =D85+D86 -> -11330.8 | E96: =E85+E86 -> -9145.8887 | F96: =F85+F86 -> -8110.8859 | G96: =G85+G86 -> -7206.1305 | H96: =H85+H86 -> -6301.3751 | I96: =I85+I86 -> -5396.6198 | J96: =J85+J86 -> -4491.8644 | ... BJ96: =BJ85+BJ86 -> -6714.2201
A97: Cumulative cash flow before financing | C97: =C96 -> -150110.05 | D97: =C97+D96 -> -161440.85 | E97: =D97+E96 -> -170586.74 | F97: =E97+F96 -> -178697.63 | G97: =F97+G96 -> -185903.76 | H97: =G97+H96 -> -192205.13 | I97: =H97+I96 -> -197601.75 | J97: =I97+J96 -> -202093.62 | K97: =J97+K96 -> -205680.73 | ... BJ97: =BI97+BJ96 -> -413620.36
A98: Helper: lowest cumulative cash flow so far | C98: =C97 -> -150110.05 | D98: =MIN(C98,D97) -> -161440.85 | E98: =MIN(D98,E97) -> -170586.74 | F98: =MIN(E98,F97) -> -178697.63 | G98: =MIN(F98,G97) -> -185903.76 | H98: =MIN(G98,H97) -> -192205.13 | I98: =MIN(H98,I97) -> -197601.75 | J98: =MIN(I98,J97) -> -202093.62 | K98: =MIN(J98,K97) -> -205680.73 | ... BJ98: =MIN(BI98,BJ97) -> -413620.36
A99: Helper: investment paid back (1/0) | C99: =IF(AND(C97>=0,C98<0),1,0) -> 0 | D99: =IF(AND(D97>=0,D98<0),1,0) -> 0 | E99: =IF(AND(E97>=0,E98<0),1,0) -> 0 | F99: =IF(AND(F97>=0,F98<0),1,0) -> 0 | G99: =IF(AND(G97>=0,G98<0),1,0) -> 0 | H99: =IF(AND(H97>=0,H98<0),1,0) -> 0 | I99: =IF(AND(I97>=0,I98<0),1,0) -> 0 | J99: =IF(AND(J97>=0,J98<0),1,0) -> 0 | ... BJ99: =IF(AND(BJ97>=0,BJ98<0),1,0) -> 0
A100: Unlevered free cash flow (operating + after-tax interest − capex) | C100: =C85-C52*(1-Inputs!$B$83)+C86 -> -149576.8 | D100: =D85-D52*(1-Inputs!$B$83)+D86 -> -10801.993 | E100: =E85-E52*(1-Inputs!$B$83)+E86 -> -8625.97 | F100: =F85-F52*(1-Inputs!$B$83)+F86 -> -7599.8547 | G100: =G85-G52*(1-Inputs!$B$83)+G86 -> -6703.9868 | H100: =H85-H52*(1-Inputs!$B$83)+H86 -> -5808.1189 | I100: =I85-I52*(1-Inputs!$B$83)+I86 -> -4912.251 | J100: =J85-J52*(1-Inputs!$B$83)+J86 -> -4016.3831 | ... BJ100: =BJ85-BJ52*(1-Inputs!$B$83)+BJ86 -> -6700.8888
A102: Balance sheet
A103: Paid-in capital | C103: =C87 -> 100000 | D103: =C103+D87 -> 100000 | E103: =D103+E87 -> 100000 | F103: =E103+F87 -> 100000 | G103: =F103+G87 -> 100000 | H103: =G103+H87 -> 100000 | I103: =H103+I87 -> 100000 | J103: =I103+J87 -> 100000 | K103: =J103+K87 -> 100000 | ... BJ103: =BI103+BJ87 -> 100000
A104: Retained earnings | C104: =C57 -> -13536.551 | D104: =C104+D57 -> -26465.562 | E104: =D104+E57 -> -37057.135 | F104: =E104+F57 -> -46743.953 | G104: =F104+G57 -> -55526.016 | H104: =G104+H57 -> -63403.323 | I104: =H104+I57 -> -70375.875 | J104: =I104+J57 -> -76443.671 | K104: =J104+K57 -> -81606.712 | ... BJ104: =BI104+BJ57 -> -367104.45
A105: Total assets | C105: =C91+C77+C78+C68 -> 177015.3 | D105: =D91+D77+D78+D68 -> 162700.17 | E105: =E91+E77+E78+E68 -> 151052.17 | F105: =F91+F77+F78+F68 -> 140027.39 | G105: =G91+G77+G78+G68 -> 129907.36 | H105: =H91+H77+H78+H68 -> 120692.09 | I105: =I91+I77+I78+I68 -> 112381.57 | J105: =J91+J77+J78+J68 -> 104975.81 | ... BJ105: =BJ91+BJ77+BJ78+BJ68 -> -263879.61
A106: Total liabilities | C106: =C79+C74 -> 90551.854 | D106: =D79+D74 -> 89165.728 | E106: =E79+E74 -> 88109.308 | F106: =F79+F74 -> 86771.341 | G106: =G79+G74 -> 85433.375 | H106: =H79+H74 -> 84095.409 | I106: =I79+I74 -> 82757.442 | J106: =J79+J74 -> 81419.476 | ... BJ106: =BJ79+BJ74 -> 3224.8347
A107: Total equity | C107: =C103+C104 -> 86463.449 | D107: =D103+D104 -> 73534.438 | E107: =E103+E104 -> 62942.865 | F107: =F103+F104 -> 53256.047 | G107: =G103+G104 -> 44473.984 | H107: =H103+H104 -> 36596.677 | I107: =I103+I104 -> 29624.125 | J107: =J103+J104 -> 23556.329 | ... BJ107: =BJ103+BJ104 -> -267104.45
A108: Total liabilities & equity | C108: =C106+C107 -> 177015.3 | D108: =D106+D107 -> 162700.17 | E108: =E106+E107 -> 151052.17 | F108: =F106+F107 -> 140027.39 | G108: =G106+G107 -> 129907.36 | H108: =H106+H107 -> 120692.09 | I108: =I106+I107 -> 112381.57 | J108: =J106+J107 -> 104975.81 | ... BJ108: =BJ106+BJ107 -> -263879.61
A109: Check: assets − liabilities − equity | C109: =C105-C108 -> 0 | D109: =D105-D108 -> 0 | E109: =E105-E108 -> 0 | F109: =F105-F108 -> 0 | G109: =G105-G108 -> 0 | H109: =H105-H108 -> 0 | I109: =I105-I108 -> 0 | J109: =J105-J108 -> 0 | ... BJ109: =BJ105-BJ108 -> 0
A111: Headcount (FTE)
A112: Owner-operator (salary optional) — FTE | C112: =Inputs!$B$55*(1+Inputs!$B$57)^(C$7-1)*MAX(0,MIN(1,C$6*1-Inputs!$B$58+1))/1 -> 1 | D112: =Inputs!$B$55*(1+Inputs!$B$57)^(D$7-1)*MAX(0,MIN(1,D$6*1-Inputs!$B$58+1))/1 -> 1 | E112: =Inputs!$B$55*(1+Inputs!$B$57)^(E$7-1)*MAX(0,MIN(1,E$6*1-Inputs!$B$58+1))/1 -> 1 | F112: =Inputs!$B$55*(1+Inputs!$B$57)^(F$7-1)*MAX(0,MIN(1,F$6*1-Inputs!$B$58+1))/1 -> 1 | G112: =Inputs!$B$55*(1+Inputs!$B$57)^(G$7-1)*MAX(0,MIN(1,G$6*1-Inputs!$B$58+1))/1 -> 1 | H112: =Inputs!$B$55*(1+Inputs!$B$57)^(H$7-1)*MAX(0,MIN(1,H$6*1-Inputs!$B$58+1))/1 -> 1 | I112: =Inputs!$B$55*(1+Inputs!$B$57)^(I$7-1)*MAX(0,MIN(1,I$6*1-Inputs!$B$58+1))/1 -> 1 | J112: =Inputs!$B$55*(1+Inputs!$B$57)^(J$7-1)*MAX(0,MIN(1,J$6*1-Inputs!$B$58+1))/1 -> 1 | ... BJ112: =Inputs!$B$55*(1+Inputs!$B$57)^(BJ$7-1)*MAX(0,MIN(1,BJ$6*1-Inputs!$B$58+1))/1 -> 1
A113: Cooks — FTE | C113: =Inputs!$B$59*(1+Inputs!$B$61)^(C$7-1)*MAX(0,MIN(1,C$6*1-Inputs!$B$62+1))/1 -> 1.2 | D113: =Inputs!$B$59*(1+Inputs!$B$61)^(D$7-1)*MAX(0,MIN(1,D$6*1-Inputs!$B$62+1))/1 -> 1.2 | E113: =Inputs!$B$59*(1+Inputs!$B$61)^(E$7-1)*MAX(0,MIN(1,E$6*1-Inputs!$B$62+1))/1 -> 1.2 | F113: =Inputs!$B$59*(1+Inputs!$B$61)^(F$7-1)*MAX(0,MIN(1,F$6*1-Inputs!$B$62+1))/1 -> 1.2 | G113: =Inputs!$B$59*(1+Inputs!$B$61)^(G$7-1)*MAX(0,MIN(1,G$6*1-Inputs!$B$62+1))/1 -> 1.2 | H113: =Inputs!$B$59*(1+Inputs!$B$61)^(H$7-1)*MAX(0,MIN(1,H$6*1-Inputs!$B$62+1))/1 -> 1.2 | I113: =Inputs!$B$59*(1+Inputs!$B$61)^(I$7-1)*MAX(0,MIN(1,I$6*1-Inputs!$B$62+1))/1 -> 1.2 | J113: =Inputs!$B$59*(1+Inputs!$B$61)^(J$7-1)*MAX(0,MIN(1,J$6*1-Inputs!$B$62+1))/1 -> 1.2 | ... BJ113: =Inputs!$B$59*(1+Inputs!$B$61)^(BJ$7-1)*MAX(0,MIN(1,BJ$6*1-Inputs!$B$62+1))/1 -> 1.2
...

Sheet Checks
A1: Model checks | E1: =HYPERLINK("#'Cover'!A1","◂ Contents") -> ◂ Contents
A2: Live formulas: they re-run every time an input changes.
A3: Check | B3: Result | C3: What it tests
A4: Annual revenue ties to period detail | B4: =IF(ABS(SUM('P&L'!$B$5:$F$5)-SUM(Monthly!$C$24:$BJ$24))<0.5,"PASS","FAIL") -> PASS | C4: Sum of annual revenue equals the sum of every period
A5: Annual net income ties to period detail | B5: =IF(ABS(SUM('P&L'!$B$26:$F$26)-SUM(Monthly!$C$55:$BJ$55))<0.5,"PASS","FAIL") -> PASS | C5: Sum of annual net income equals the sum of every period
A6: EBITDA reconciliation | B6: =IF(ABS(SUM(Monthly!$C$46:$BJ$46)-SUM(Monthly!$C$33:$BJ$33)-SUM(Monthly!$C$45:$BJ$45))<0.5,"PASS","FAIL") -> PASS | C6: EBITDA = gross profit + operating expenses (costs are negative)
A7: Cash roll-forward | B7: =IF(ABS(INDEX(Monthly!$C$89:$BJ$89,60)-SUM(Monthly!$C$87:$BJ$87))<0.5,"PASS","FAIL") -> PASS | C7: Closing cash = all net cash flows since the start (opening cash is zero)
A8: Scenario selector valid | B8: =IF(AND(ISNUMBER(Dashboard!B4),Dashboard!B4>=1,Dashboard!B4<=3,INT(Dashboard!B4)=Dashboard!B4),"PASS","FAIL") -> PASS | C8: Dashboard!B4 is 1, 2 or 3
A9: Scenario ordering of drivers | B9: =IF(AND(Inputs!$B$9<=Inputs!$C$9,Inputs!$C$9<=Inputs!$D$9,Inputs!$B$10>=Inputs!$C$10,Inputs!$C$10>=Inputs!$D$10,Inputs!$B$13>=Inputs!$C$13,Inputs!$C$13>=Inputs!$D$13,Inputs!$B$14<=Inputs!$C$14,Inputs!$C$14<=Inputs!$D$14,Inputs!$B$17<=Inputs!$C$17,Inputs!$C$17<=Inputs!$D$17,Inputs!$B$18<=Inputs!$C$18,Inputs!$C$18<=Inputs!$D$18,Inputs!$B$19<=Inputs!$C$19,Inputs!$C$19<=Inputs!$D$19,Inputs!$B$20<=Inputs!$C$20,Inputs!$C$20<=Inputs!$D$20,Inputs!$B$23<=Inputs!$C$23,Inputs!$C$23<=Inputs!$D$23,Inputs!$B$24<=Inputs!$C$24,Inputs!$C$24<=Inputs!$D$24,Inputs!$B$25<=Inputs!$C$25,Inputs!$C$25<=Inputs!$D$25,Inputs!$B$29>=Inputs!$C$29,Inputs!$C$29>=Inputs!$D$29,Inputs!$B$30>=Inputs!$C$30,Inputs!$C$30>=Inputs!$D$30,Inputs!$B$31>=Inputs!$C$31,Inputs!$C$31>=Inputs!$D$31,Inputs!$B$32>=Inputs!$C$32,Inputs!$C$32>=Inputs!$D$32,Inputs!$B$33>=Inputs!$C$33,Inputs!$C$33>=Inputs!$D$33,Inputs!$B$34>=Inputs!$C$34,Inputs!$C$34>=Inputs!$D$34,Inputs!$B$55<=Inputs!$C$55,Inputs!$C$55<=Inputs!$D$55,Inputs!$B$57<=Inputs!$C$57,Inputs!$C$57<=Inputs!$D$57,Inputs!$B$59<=Inputs!$C$59,Inputs!$C$59<=Inputs!$D$59,Inputs!$B$61<=Inputs!$C$61,Inputs!$C$61<=Inputs!$D$61,Inputs!$B$63<=Inputs!$C$63,Inputs!$C$63<=Inputs!$D$63,Inputs!$B$65<=Inputs!$C$65,Inputs!$C$65<=Inputs!$D$65,Inputs!$B$89>=Inputs!$C$89,Inputs!$C$89>=Inputs!$D$89,Inputs!$B$90<=Inputs!$C$90,Inputs!$C$90<=Inputs!$D$90,Inputs!$B$91<=Inputs!$C$91,Inputs!$C$91<=Inputs!$D$91),"PASS","FAIL") -> PASS | C9: Low / Base / High ordered the right way for every growth and cost driver
A10: Gross margin within 0–100% | B10: =IF(AND(MIN('P&L'!$B$8:$F$8)>=0,MAX('P&L'!$B$8:$F$8)<=1),"PASS","FAIL") -> PASS | C10: Gross margin never negative or above 100%
A11: Loan balance never negative | B11: =IF(MIN(Monthly!$C$72:$BJ$72)>=-0.5,"PASS","FAIL") -> PASS | C11: Repayments never exceed the loan
A12: Funding table ties to the cash flow | B12: =IF(ABS('Break-even'!B18-('Break-even'!B16-'Break-even'!B10))<0.5,"PASS","FAIL") -> PASS | C12: Lowest cash balance = sources of funds − uses of funds up to that point
A13: Valuation: discounting ties to NPV() | B13: =IF(ABS(Valuation!B23-NPV(Valuation!B6,Valuation!$B$17:$F$17))<0.5,"PASS","FAIL") -> PASS | C13: Sum of discounted free cash flows equals Excel's NPV of the same flows
A14: Valuation: WACC above terminal growth | B14: =IF(Valuation!B6>Valuation!B7,"PASS","FAIL") -> PASS | C14: The perpetual-growth formula needs WACC > g
A15: Valuation: sensitivity centre = enterprise value | B15: =IF(ABS(Valuation!D36-Valuation!B27)<0.5,"PASS","FAIL") -> PASS | C15: The middle of the WACC × growth table reproduces the headline value
A16: Valuation: final-year cash flow positive | B16: =IF(Valuation!$F$17>0,"PASS","WARN") -> PASS | C16: Business warning: a negative final-year cash flow gives a negative terminal value (often a 1-year plan still carrying start-up spending)
A17: Sources & uses balance | B17: =IF(ABS('Sources & Uses'!B21-'Sources & Uses'!B28)<0.5,"PASS","FAIL") -> PASS | C17: Sources of funds = uses of funds (incl. cash at the end) for the Sources & Uses period
A18: No error values | B18: =IF(SUMPRODUCT(--ISERROR(Monthly!$C$4:$BJ$107))+SUMPRODUCT(--ISERROR(Headcount!$C$4:$BJ$17))+SUMPRODUCT(--ISERROR('P&L'!$B$3:$F$27))+SUMPRODUCT(--ISERROR('Cash Flow'!$B$3:$F$18))+SUMPRODUCT(--ISERROR('Balance Sheet'!$B$3:$F$17))+SUMPRODUCT(--ISERROR(KPIs!$B$27:$F$47))+SUMPRODUCT(--ISERROR('Break-even'!$B$26:$F$33))+SUMPRODUCT(--ISERROR(Valuation!$B$14:$F$19))+SUMPRODUCT(--ISERROR('Break-even'!$B$3:$F$35))+SUMPRODUCT(--ISERROR(Valuation!$A$3:$F$40))+SUMPRODUCT(--ISERROR('Sources & Uses'!$B$3:$C$30))+SUMPRODUCT(--ISERROR(Dashboard!$A$6:$W$44))+SUMPRODUCT(--ISERROR(Summary!$A$5:$S$52))+SUMPRODUCT(--ISERROR(KPIs!$A$4:$G$47))+SUMPRODUCT(--ISERROR('Scenario calc'!$C$6:$BJ$121))+SUMPRODUCT(--ISERROR('Scenario calc'!$C$126:$BJ$241))+SUMPRODUCT(--ISERROR('Scenario calc'!$C$246:$BJ$361))+SUMPRODUCT(--ISERROR(Scenarios!$B$5:$F$50))=0,"PASS","FAIL") -> PASS | C18: No error values (divide-by-zero, broken references) on any calculation sheet
A19: Summary ties to statements | B19: =IF(IFERROR(AND(SUMPRODUCT(--(ABS(Summary!$B$7:$F$7-'P&L'!$B$5:$F$5)>0.5))=0,SUMPRODUCT(--(ABS(Summary!$B$19:$F$19-'P&L'!$B$26:$F$26)>0.5))=0,SUMPRODUCT(--(ABS(Summary!$B$31:$F$31-'Cash Flow'!$B$18:$F$18)>0.5))=0,SUMPRODUCT(--(ABS(Summary!$B$41:$F$41-'Balance Sheet'!$B$5:$F$5)>0.5))=0,ABS(SUM(Summary!$H$7:$S$7)-INDEX(Summary!$B$7:$F$7,Summary!$R$2))<0.5,ABS(SUM(Summary!$H$19:$S$19)-INDEX(Summary!$B$19:$F$19,Summary!$R$2))<0.5,ABS(Summary!$S$31-INDEX(Summary!$B$31:$F$31,Summary!$R$2))<0.5),FALSE()),"PASS","FAIL") -> PASS | C19: Summary revenue, net income and closing cash equal the statements every year; the detailed year adds up to its annual figure
A20: DuPont ties to return on equity | B20: =IF(SUMPRODUCT(--(ABS(KPIs!$B$24:$F$24)>0.000000001))>0,"FAIL",IF(SUMPRODUCT(ISNUMBER(KPIs!$B$23:$F$23)*ISNUMBER(KPIs!$B$16:$F$16))=0,"n/a","PASS")) -> PASS | C20: Net margin × asset turnover × equity multiplier equals return on equity every year; n/a = no year where both are defined (a one-sided n/a is a FAIL)
A21: Scenarios: Active = selected scenario | B21: =IF(IFERROR(AND(ABS(Scenarios!E17-INDEX(Scenarios!B17:D17,1,Dashboard!$B$4))<0.5,ABS(Scenarios!E18-INDEX(Scenarios!B18:D18,1,Dashboard!$B$4))<0.5,ABS(Scenarios!E19-INDEX(Scenarios!B19:D19,1,Dashboard!$B$4))<0.5,ABS(Scenarios!E20-INDEX(Scenarios!B20:D20,1,Dashboard!$B$4))<0.000001,ABS(Scenarios!E21-INDEX(Scenarios!B21:D21,1,Dashboard!$B$4))<0.5,ABS(Scenarios!E22-INDEX(Scenarios!B22:D22,1,Dashboard!$B$4))<0.5,ABS(Scenarios!E23-INDEX(Scenarios!B23:D23,1,Dashboard!$B$4))<0.5,ABS(Scenarios!E24-INDEX(Scenarios!B24:D24,1,Dashboard!$B$4))<0.5,ABS(Scenarios!E25-INDEX(Scenarios!B25:D25,1,Dashboard!$B$4))<0.5,ABS(Scenarios!E26-INDEX(Scenarios!B26:D26,1,Dashboard!$B$4))<0.5),FALSE()),"PASS","FAIL") -> PASS | C21: On the Scenarios sheet the live model (Active) equals the Low / Base / High column chosen on the Dashboard for every output
A22: Balance sheet balances every period | B22: =IF(SUMPRODUCT(--(ABS(Monthly!$C$107:$BJ$107)>0.5))=0,"PASS","FAIL") -> PASS | C22: Assets = liabilities + equity in every period
A23: Funding sufficient (cash ≥ 0) | B23: =IF(MIN(Monthly!$C$89:$BJ$89)>=0,"PASS","WARN") -> PASS | C23: Business warning, not an error: cash dips below zero in this scenario
A25: Overall verdict | B25: =IF(COUNTIF(B4:B23,"FAIL")>0,"FAIL",IF(COUNTIF(B4:B23,"WARN")>0,"PASS WITH WARNINGS","PASS")) -> PASS
