Workbook

Sheet Cover
B2: Guest house financial model (planning)
B3: 5-year financial model · monthly detail · Low / Base / High scenarios · US dollars · Full plan
B5: Purpose | D5: Revenue and profit plan
B6: Active scenario | D6: =Dashboard!C4&" (change it on the Dashboard, cell B4)" -> Base (change it on the Dashboard, cell B4)
B7: Model checks | D7: =Checks!B25 -> PASS
B8: Prepared | D8: 22 October 2026
B10: Contents
C11: PRESENTATION
B12: 1 | C12: =HYPERLINK("#Dashboard!A1","Dashboard") -> Dashboard | D12: Scenario switch, key numbers, core financials
B13: 2 | C13: =HYPERLINK("#Summary!A1","Summary") -> Summary | D13: Income statement, cash flow and balance sheet — every year and any year by month
B14: 3 | C14: =HYPERLINK("#Scenarios!A1","Scenarios") -> Scenarios | D14: Low / Base / High side by side: drivers, outputs, charts
B15: 4 | C15: =HYPERLINK("#'Break-even'!A1","Break-even") -> Break-even | D15: Startup costs, funding need, break-even timing and revenue
B16: 5 | C16: =HYPERLINK("#Valuation!A1","Valuation") -> Valuation | D16: Free cash flow, DCF (perpetual growth and exit multiple), WACC × growth sensitivity
B17: 6 | C17: =HYPERLINK("#'Sources & Uses'!A1","Sources & Uses") -> Sources & Uses | D17: Funding structure, sources and uses of cash for the first months
B18: 7 | C18: =HYPERLINK("#KPIs!A1","KPIs") -> KPIs | D18: Financial ratios, DuPont analysis, industry metrics
C19: INPUTS
B20: 8 | C20: =HYPERLINK("#Inputs!A1","Inputs") -> Inputs | D20: Every assumption, Low / Base / High, with units and comments
C21: STATEMENTS
B22: 9 | C22: =HYPERLINK("#'P&L'!A1","P&L") -> P&L | D22: Annual profit & loss
B23: 10 | C23: =HYPERLINK("#'Cash Flow'!A1","Cash Flow") -> Cash Flow | D23: Annual cash flow statement
B24: 11 | C24: =HYPERLINK("#'Balance Sheet'!A1","Balance Sheet") -> Balance Sheet | D24: Balance sheet at year end
C25: CALCULATIONS
B26: 12 | C26: =HYPERLINK("#Monthly!A1","Monthly") -> Monthly | D26: Month-by-month engine of the model
B27: 13 | C27: =HYPERLINK("#Headcount!A1","Headcount") -> Headcount | D27: Team and payroll
B28: 14 | C28: =HYPERLINK("#'Scenario calc'!A1","Scenario calc") -> Scenario calc | D28: Low, Base and High calculated side by side for the Scenarios sheet
C29: CONTROL
B30: 15 | C30: =HYPERLINK("#Checks!A1","Checks") -> Checks | D30: Live integrity checks and the overall verdict
B32: How to read this file
C33: 1000 | D33: Input you can change — yellow cell with a blue figure (Inputs sheet and the view switches)
C34: 1000 | D34: Formula — calculated, do not overwrite
C35: 1000 | D35: Link to another sheet
C36: 1000 | D36: Active value the model uses (follows the scenario)

Sheet Dashboard
A1: Dashboard | W1: =HYPERLINK("#'Cover'!A1","◂ Contents") -> ◂ Contents
A2: Guest house financial model (planning)
A4: Active scenario | B4: 2 | C4: =CHOOSE(B4,"Low","Base","High") -> Base | D4: 1 = Low · 2 = Base · 3 = High — every sheet follows this cell | S4: Model checks | T4: =Checks!B25 -> PASS
A6: REVENUE · YEAR 5 | C6: EBITDA MARGIN · YEAR 5 | H6: NET INCOME · YEAR 5 | L6: LOWEST CASH BALANCE | P6: FUNDING REQUIRED | T6: ENTERPRISE VALUE (DCF)
A7: =F12 -> 460163.93 | C7: =F17 -> 0.29432751 | H7: =F18 -> 43135.578 | L7: =F39 -> 22904.403 | P7: =F37 -> 946095.6 | T7: =F44 -> -348552.33
A8: =IF(AND(B12>0,F12>=0),(F12/B12)^(1/4)-1,"CAGR n/a") -> 0.13740984 | C8: =F16 -> 135438.9 | H8: =F19 -> 0.09373959 | L8: ='Break-even'!B6 -> 5 | P8: =IF(F38>=0,"Covered by funding raised",-F38) -> 16095.597 | T8: Average of 2 methods
A10: Core financials ($'000) — active scenario
B11: 1 | C11: 2 | D11: 3 | E11: 4 | F11: 5
A12: Revenue | B12: =SUMIF(Monthly!$C$5:$BJ$5,B$11,Monthly!$C$20:$BJ$20) -> 274944.26 | C12: =SUMIF(Monthly!$C$5:$BJ$5,C$11,Monthly!$C$20:$BJ$20) -> 396826.24 | D12: =SUMIF(Monthly!$C$5:$BJ$5,D$11,Monthly!$C$20:$BJ$20) -> 416905.65 | E12: =SUMIF(Monthly!$C$5:$BJ$5,E$11,Monthly!$C$20:$BJ$20) -> 438001.08 | F12: =SUMIF(Monthly!$C$5:$BJ$5,F$11,Monthly!$C$20:$BJ$20) -> 460163.93
A13: Gross profit | B13: =SUMIF(Monthly!$C$5:$BJ$5,B$11,Monthly!$C$29:$BJ$29) -> 165763.81 | C13: =SUMIF(Monthly!$C$5:$BJ$5,C$11,Monthly!$C$29:$BJ$29) -> 262060.42 | D13: =SUMIF(Monthly!$C$5:$BJ$5,D$11,Monthly!$C$29:$BJ$29) -> 276491.91 | E13: =SUMIF(Monthly!$C$5:$BJ$5,E$11,Monthly!$C$29:$BJ$29) -> 291688.77 | F13: =SUMIF(Monthly!$C$5:$BJ$5,F$11,Monthly!$C$29:$BJ$29) -> 307690.79
A14: Gross margin | B14: =IF(B12=0,0,B13/B12) -> 0.6028997 | C14: =IF(C12=0,0,C13/C12) -> 0.66039085 | D14: =IF(D12=0,0,D13/D12) -> 0.6632002 | E14: =IF(E12=0,0,E13/E12) -> 0.66595446 | F14: =IF(F12=0,0,F13/F12) -> 0.66865472
A15: Operating expenses | B15: =SUMIF(Monthly!$C$5:$BJ$5,B$11,Monthly!$C$41:$BJ$41) -> -155521.27 | C15: =SUMIF(Monthly!$C$5:$BJ$5,C$11,Monthly!$C$41:$BJ$41) -> -163660.36 | D15: =SUMIF(Monthly!$C$5:$BJ$5,D$11,Monthly!$C$41:$BJ$41) -> -165805.87 | E15: =SUMIF(Monthly!$C$5:$BJ$5,E$11,Monthly!$C$41:$BJ$41) -> -168705.86 | F15: =SUMIF(Monthly!$C$5:$BJ$5,F$11,Monthly!$C$41:$BJ$41) -> -172251.88
A16: EBITDA | B16: =SUMIF(Monthly!$C$5:$BJ$5,B$11,Monthly!$C$42:$BJ$42) -> 10242.544 | C16: =SUMIF(Monthly!$C$5:$BJ$5,C$11,Monthly!$C$42:$BJ$42) -> 98400.063 | D16: =SUMIF(Monthly!$C$5:$BJ$5,D$11,Monthly!$C$42:$BJ$42) -> 110686.04 | E16: =SUMIF(Monthly!$C$5:$BJ$5,E$11,Monthly!$C$42:$BJ$42) -> 122982.92 | F16: =SUMIF(Monthly!$C$5:$BJ$5,F$11,Monthly!$C$42:$BJ$42) -> 135438.9
A17: EBITDA margin | B17: =IF(B12=0,0,B16/B12) -> 0.037253166 | C17: =IF(C12=0,0,C16/C12) -> 0.24796763 | D17: =IF(D12=0,0,D16/D12) -> 0.26549423 | E17: =IF(E12=0,0,E16/E12) -> 0.28078222 | F17: =IF(F12=0,0,F16/F12) -> 0.29432751
A18: Net income | B18: =SUMIF(Monthly!$C$5:$BJ$5,B$11,Monthly!$C$51:$BJ$51) -> -70506.807 | C18: =SUMIF(Monthly!$C$5:$BJ$5,C$11,Monthly!$C$51:$BJ$51) -> 17593.913 | D18: =SUMIF(Monthly!$C$5:$BJ$5,D$11,Monthly!$C$51:$BJ$51) -> 29844.776 | E18: =SUMIF(Monthly!$C$5:$BJ$5,E$11,Monthly!$C$51:$BJ$51) -> 38127.44 | F18: =SUMIF(Monthly!$C$5:$BJ$5,F$11,Monthly!$C$51:$BJ$51) -> 43135.578
A19: Net margin | B19: =IF(B12=0,0,B18/B12) -> -0.25644037 | C19: =IF(C12=0,0,C18/C12) -> 0.044336566 | D19: =IF(D12=0,0,D18/D12) -> 0.071586402 | E19: =IF(E12=0,0,E18/E12) -> 0.087048736 | F19: =IF(F12=0,0,F18/F12) -> 0.09373959
A20: Operating cash flow | B20: =SUMIF(Monthly!$C$5:$BJ$5,B$11,Monthly!$C$83:$BJ$83) -> -19872.931 | C20: =SUMIF(Monthly!$C$5:$BJ$5,C$11,Monthly!$C$83:$BJ$83) -> 64360.735 | D20: =SUMIF(Monthly!$C$5:$BJ$5,D$11,Monthly!$C$83:$BJ$83) -> 77245.925 | E20: =SUMIF(Monthly!$C$5:$BJ$5,E$11,Monthly!$C$83:$BJ$83) -> 86182.013 | F20: =SUMIF(Monthly!$C$5:$BJ$5,F$11,Monthly!$C$83:$BJ$83) -> 91863.248
A21: Investing cash flow | B21: =SUMIF(Monthly!$C$5:$BJ$5,B$11,Monthly!$C$84:$BJ$84) -> -874000 | C21: =SUMIF(Monthly!$C$5:$BJ$5,C$11,Monthly!$C$84:$BJ$84) -> -9270 | D21: =SUMIF(Monthly!$C$5:$BJ$5,D$11,Monthly!$C$84:$BJ$84) -> -9548.1 | E21: =SUMIF(Monthly!$C$5:$BJ$5,E$11,Monthly!$C$84:$BJ$84) -> -9834.543 | F21: =SUMIF(Monthly!$C$5:$BJ$5,F$11,Monthly!$C$84:$BJ$84) -> -10129.579
A22: Financing cash flow | B22: =SUMIF(Monthly!$C$5:$BJ$5,B$11,Monthly!$C$86:$BJ$86) -> 922350.93 | C22: =SUMIF(Monthly!$C$5:$BJ$5,C$11,Monthly!$C$86:$BJ$86) -> -8202.0187 | D22: =SUMIF(Monthly!$C$5:$BJ$5,D$11,Monthly!$C$86:$BJ$86) -> -8794.9433 | E22: =SUMIF(Monthly!$C$5:$BJ$5,E$11,Monthly!$C$86:$BJ$86) -> -9430.7304 | F22: =SUMIF(Monthly!$C$5:$BJ$5,F$11,Monthly!$C$86:$BJ$86) -> -10112.479
A23: Net change in cash | B23: =SUMIF(Monthly!$C$5:$BJ$5,B$11,Monthly!$C$87:$BJ$87) -> 28478.002 | C23: =SUMIF(Monthly!$C$5:$BJ$5,C$11,Monthly!$C$87:$BJ$87) -> 46888.716 | D23: =SUMIF(Monthly!$C$5:$BJ$5,D$11,Monthly!$C$87:$BJ$87) -> 58902.881 | E23: =SUMIF(Monthly!$C$5:$BJ$5,E$11,Monthly!$C$87:$BJ$87) -> 66916.74 | F23: =SUMIF(Monthly!$C$5:$BJ$5,F$11,Monthly!$C$87:$BJ$87) -> 71621.19
A24: Year-end cash | B24: =INDEX(Monthly!$C$89:$BJ$89,B$11*12) -> 28478.002 | C24: =INDEX(Monthly!$C$89:$BJ$89,C$11*12) -> 75366.718 | D24: =INDEX(Monthly!$C$89:$BJ$89,D$11*12) -> 134269.6 | E24: =INDEX(Monthly!$C$89:$BJ$89,E$11*12) -> 201186.34 | F24: =INDEX(Monthly!$C$89:$BJ$89,F$11*12) -> 272807.53
A26: Guest house metrics
B27: 1 | C27: 2 | D27: 3 | E27: 4 | F27: 5
A28: Occupancy | B28: =KPIs!B31 -> 0.45130833 | C28: =KPIs!C31 -> 0.6324 | D28: =KPIs!D31 -> 0.645048 | E28: =KPIs!E31 -> 0.65794896 | F28: =KPIs!F31 -> 0.67110794
A29: Average daily rate | B29: =KPIs!B37 -> 155 | C29: =KPIs!C37 -> 159.65 | D29: =KPIs!D37 -> 164.4395 | E29: =KPIs!E37 -> 169.37268 | F29: =KPIs!F37 -> 174.45387
A30: RevPAR (room revenue per available room-night) | B30: =KPIs!B38 -> 69.952792 | C30: =KPIs!C38 -> 100.96266 | D30: =KPIs!D38 -> 106.07137 | E30: =KPIs!E38 -> 111.43858 | F30: =KPIs!F38 -> 117.07737
A31: Guest stays | B31: =KPIs!B32 -> 748.35127 | C31: =KPIs!C32 -> 1048.6342 | D31: =KPIs!D32 -> 1069.6069 | E31: =KPIs!E32 -> 1090.999 | F31: =KPIs!F32 -> 1112.819
A32: Team (FTE, year end) | B32: =INDEX(Headcount!$C$11:$BJ$11,B$27*12) -> 3.1 | C32: =INDEX(Headcount!$C$11:$BJ$11,C$27*12) -> 3.1 | D32: =INDEX(Headcount!$C$11:$BJ$11,D$27*12) -> 3.1 | E32: =INDEX(Headcount!$C$11:$BJ$11,E$27*12) -> 3.1 | F32: =INDEX(Headcount!$C$11:$BJ$11,F$27*12) -> 3.1
A34: Funding & valuation ($'000) — active scenario
A35: Equity raised | F35: =Inputs!$E$65 -> 430000
A36: Loan drawn | F36: =Inputs!$E$66 -> 500000
A37: Funding required (incl. cash buffer) | F37: ='Break-even'!B12 -> 946095.6
A38: Funding surplus / (shortfall) | F38: ='Break-even'!B17 -> -16095.597
A39: ="Lowest cash balance (month "&'Break-even'!B6&")" -> Lowest cash balance (month 5) | F39: ='Break-even'!B18 -> 22904.403
A40: First month with positive EBITDA | F40: ='Break-even'!B21 -> 6
A41: Cash invested paid back | F41: ='Break-even'!B23 -> Not within horizon
A42: Enterprise value — perpetual growth | F42: =Valuation!B27 -> -359389.08
A43: Enterprise value — exit multiple | F43: =Valuation!C27 -> -337715.58
A44: Enterprise value — average | F44: =Valuation!B30 -> -348552.33

Sheet Summary
A1: Financial statements summary | U1: =HYPERLINK("#'Cover'!A1","◂ Contents") -> ◂ Contents
A2: Guest house financial model (planning) | P2: Select detailed year: | R2: 1
A5: Income statement ($'000) — by year | H5: ="Income statement ($'000) — Year "&$R$2&", by month" -> Income statement ($'000) — Year 1, by month
B6: 1 | C6: 2 | D6: 3 | E6: 4 | F6: 5 | H6: =INDEX(Monthly!$C$4:$BJ$4,($R$2-1)*12+1) -> 1 | I6: =INDEX(Monthly!$C$4:$BJ$4,($R$2-1)*12+2) -> 2 | J6: =INDEX(Monthly!$C$4:$BJ$4,($R$2-1)*12+3) -> 3 | K6: =INDEX(Monthly!$C$4:$BJ$4,($R$2-1)*12+4) -> 4 | L6: =INDEX(Monthly!$C$4:$BJ$4,($R$2-1)*12+5) -> 5 | M6: =INDEX(Monthly!$C$4:$BJ$4,($R$2-1)*12+6) -> 6 | N6: =INDEX(Monthly!$C$4:$BJ$4,($R$2-1)*12+7) -> 7 | O6: =INDEX(Monthly!$C$4:$BJ$4,($R$2-1)*12+8) -> 8 | P6: =INDEX(Monthly!$C$4:$BJ$4,($R$2-1)*12+9) -> 9 | Q6: =INDEX(Monthly!$C$4:$BJ$4,($R$2-1)*12+10) -> 10 | R6: =INDEX(Monthly!$C$4:$BJ$4,($R$2-1)*12+11) -> 11 | S6: =INDEX(Monthly!$C$4:$BJ$4,($R$2-1)*12+12) -> 12
A7: Revenue | B7: ='P&L'!B5 -> 274944.26 | C7: ='P&L'!C5 -> 396826.24 | D7: ='P&L'!D5 -> 416905.65 | E7: ='P&L'!E5 -> 438001.08 | F7: ='P&L'!F5 -> 460163.93 | H7: =INDEX(Monthly!$C$20:$BJ$20,($R$2-1)*12+1) -> 11541.259 | I7: =INDEX(Monthly!$C$20:$BJ$20,($R$2-1)*12+2) -> 13272.447 | J7: =INDEX(Monthly!$C$20:$BJ$20,($R$2-1)*12+3) -> 15003.636 | K7: =INDEX(Monthly!$C$20:$BJ$20,($R$2-1)*12+4) -> 16734.825 | L7: =INDEX(Monthly!$C$20:$BJ$20,($R$2-1)*12+5) -> 18466.014 | M7: =INDEX(Monthly!$C$20:$BJ$20,($R$2-1)*12+6) -> 27541.64 | N7: =INDEX(Monthly!$C$20:$BJ$20,($R$2-1)*12+7) -> 29902.352 | O7: =INDEX(Monthly!$C$20:$BJ$20,($R$2-1)*12+8) -> 32263.064 | P7: =INDEX(Monthly!$C$20:$BJ$20,($R$2-1)*12+9) -> 25390.769 | Q7: =INDEX(Monthly!$C$20:$BJ$20,($R$2-1)*12+10) -> 27121.958 | R7: =INDEX(Monthly!$C$20:$BJ$20,($R$2-1)*12+11) -> 28853.147 | S7: =INDEX(Monthly!$C$20:$BJ$20,($R$2-1)*12+12) -> 28853.147
A8: Cost of sales | B8: ='P&L'!B6 -> -109180.45 | C8: ='P&L'!C6 -> -134765.82 | D8: ='P&L'!D6 -> -140413.74 | E8: ='P&L'!E6 -> -146312.3 | F8: ='P&L'!F6 -> -152473.15 | H8: =INDEX(Monthly!$C$28:$BJ$28,($R$2-1)*12+1) -> -6865.9223 | I8: =INDEX(Monthly!$C$28:$BJ$28,($R$2-1)*12+2) -> -7205.8106 | J8: =INDEX(Monthly!$C$28:$BJ$28,($R$2-1)*12+3) -> -7545.6989 | K8: =INDEX(Monthly!$C$28:$BJ$28,($R$2-1)*12+4) -> -7885.5873 | L8: =INDEX(Monthly!$C$28:$BJ$28,($R$2-1)*12+5) -> -8225.4756 | M8: =INDEX(Monthly!$C$28:$BJ$28,($R$2-1)*12+6) -> -10007.315 | N8: =INDEX(Monthly!$C$28:$BJ$28,($R$2-1)*12+7) -> -10470.799 | O8: =INDEX(Monthly!$C$28:$BJ$28,($R$2-1)*12+8) -> -10934.283 | P8: =INDEX(Monthly!$C$28:$BJ$28,($R$2-1)*12+9) -> -9585.029 | Q8: =INDEX(Monthly!$C$28:$BJ$28,($R$2-1)*12+10) -> -9924.9173 | R8: =INDEX(Monthly!$C$28:$BJ$28,($R$2-1)*12+11) -> -10264.806 | S8: =INDEX(Monthly!$C$28:$BJ$28,($R$2-1)*12+12) -> -10264.806
A9: Gross profit | B9: ='P&L'!B7 -> 165763.81 | C9: ='P&L'!C7 -> 262060.42 | D9: ='P&L'!D7 -> 276491.91 | E9: ='P&L'!E7 -> 291688.77 | F9: ='P&L'!F7 -> 307690.79 | H9: =INDEX(Monthly!$C$29:$BJ$29,($R$2-1)*12+1) -> 4675.3364 | I9: =INDEX(Monthly!$C$29:$BJ$29,($R$2-1)*12+2) -> 6066.6369 | J9: =INDEX(Monthly!$C$29:$BJ$29,($R$2-1)*12+3) -> 7457.9373 | K9: =INDEX(Monthly!$C$29:$BJ$29,($R$2-1)*12+4) -> 8849.2378 | L9: =INDEX(Monthly!$C$29:$BJ$29,($R$2-1)*12+5) -> 10240.538 | M9: =INDEX(Monthly!$C$29:$BJ$29,($R$2-1)*12+6) -> 17534.325 | N9: =INDEX(Monthly!$C$29:$BJ$29,($R$2-1)*12+7) -> 19431.553 | O9: =INDEX(Monthly!$C$29:$BJ$29,($R$2-1)*12+8) -> 21328.781 | P9: =INDEX(Monthly!$C$29:$BJ$29,($R$2-1)*12+9) -> 15805.74 | Q9: =INDEX(Monthly!$C$29:$BJ$29,($R$2-1)*12+10) -> 17197.041 | R9: =INDEX(Monthly!$C$29:$BJ$29,($R$2-1)*12+11) -> 18588.341 | S9: =INDEX(Monthly!$C$29:$BJ$29,($R$2-1)*12+12) -> 18588.341
A10: Gross margin | B10: ='P&L'!B8 -> 0.6028997 | C10: ='P&L'!C8 -> 0.66039085 | D10: ='P&L'!D8 -> 0.6632002 | E10: ='P&L'!E8 -> 0.66595446 | F10: ='P&L'!F8 -> 0.66865472 | H10: =IF(H7=0,0,H9/H7) -> 0.40509762 | I10: =IF(I7=0,0,I9/I7) -> 0.45708502 | J10: =IF(J7=0,0,J9/J7) -> 0.49707532 | K10: =IF(K7=0,0,K9/K7) -> 0.52879177 | L10: =IF(L7=0,0,L9/L7) -> 0.55456139 | M10: =IF(M7=0,0,M9/M7) -> 0.63664784 | N10: =IF(N7=0,0,N9/N7) -> 0.64983361 | O10: =IF(O7=0,0,O9/O7) -> 0.66108976 | ... S10: =IF(S7=0,0,S9/S7) -> 0.64423965
A11: Total operating expenses | B11: ='P&L'!B18 -> -155521.27 | C11: ='P&L'!C18 -> -163660.36 | D11: ='P&L'!D18 -> -165805.87 | E11: ='P&L'!E18 -> -168705.86 | F11: ='P&L'!F18 -> -172251.88 | H11: =INDEX(Monthly!$C$41:$BJ$41,($R$2-1)*12+1) -> -12198.264 | I11: =INDEX(Monthly!$C$41:$BJ$41,($R$2-1)*12+2) -> -12314.254 | J11: =INDEX(Monthly!$C$41:$BJ$41,($R$2-1)*12+3) -> -12430.244 | K11: =INDEX(Monthly!$C$41:$BJ$41,($R$2-1)*12+4) -> -12546.233 | L11: =INDEX(Monthly!$C$41:$BJ$41,($R$2-1)*12+5) -> -12662.223 | M11: =INDEX(Monthly!$C$41:$BJ$41,($R$2-1)*12+6) -> -13270.29 | N11: =INDEX(Monthly!$C$41:$BJ$41,($R$2-1)*12+7) -> -13428.458 | O11: =INDEX(Monthly!$C$41:$BJ$41,($R$2-1)*12+8) -> -13586.625 | P11: =INDEX(Monthly!$C$41:$BJ$41,($R$2-1)*12+9) -> -13126.182 | Q11: =INDEX(Monthly!$C$41:$BJ$41,($R$2-1)*12+10) -> -13242.171 | R11: =INDEX(Monthly!$C$41:$BJ$41,($R$2-1)*12+11) -> -13358.161 | S11: =INDEX(Monthly!$C$41:$BJ$41,($R$2-1)*12+12) -> -13358.161
A12: EBITDA | B12: ='P&L'!B19 -> 10242.544 | C12: ='P&L'!C19 -> 98400.063 | D12: ='P&L'!D19 -> 110686.04 | E12: ='P&L'!E19 -> 122982.92 | F12: ='P&L'!F19 -> 135438.9 | H12: =INDEX(Monthly!$C$42:$BJ$42,($R$2-1)*12+1) -> -7522.9279 | I12: =INDEX(Monthly!$C$42:$BJ$42,($R$2-1)*12+2) -> -6247.6171 | J12: =INDEX(Monthly!$C$42:$BJ$42,($R$2-1)*12+3) -> -4972.3063 | K12: =INDEX(Monthly!$C$42:$BJ$42,($R$2-1)*12+4) -> -3696.9955 | L12: =INDEX(Monthly!$C$42:$BJ$42,($R$2-1)*12+5) -> -2421.6847 | M12: =INDEX(Monthly!$C$42:$BJ$42,($R$2-1)*12+6) -> 4264.0356 | N12: =INDEX(Monthly!$C$42:$BJ$42,($R$2-1)*12+7) -> 6003.0958 | O12: =INDEX(Monthly!$C$42:$BJ$42,($R$2-1)*12+8) -> 7742.156 | P12: =INDEX(Monthly!$C$42:$BJ$42,($R$2-1)*12+9) -> 2679.5586 | Q12: =INDEX(Monthly!$C$42:$BJ$42,($R$2-1)*12+10) -> 3954.8694 | R12: =INDEX(Monthly!$C$42:$BJ$42,($R$2-1)*12+11) -> 5230.1802 | S12: =INDEX(Monthly!$C$42:$BJ$42,($R$2-1)*12+12) -> 5230.1802
A13: EBITDA margin | B13: ='P&L'!B20 -> 0.037253166 | C13: ='P&L'!C20 -> 0.24796763 | D13: ='P&L'!D20 -> 0.26549423 | E13: ='P&L'!E20 -> 0.28078222 | F13: ='P&L'!F20 -> 0.29432751 | H13: =IF(H7=0,0,H12/H7) -> -0.65182907 | I13: =IF(I7=0,0,I12/I7) -> -0.4707208 | J13: =IF(J7=0,0,J12/J7) -> -0.33140675 | K13: =IF(K7=0,0,K12/K7) -> -0.22091629 | L13: =IF(L7=0,0,L12/L7) -> -0.1311428 | M13: =IF(M7=0,0,M12/M7) -> 0.15482141 | N13: =IF(N7=0,0,N12/N7) -> 0.20075664 | O13: =IF(O7=0,0,O12/O7) -> 0.23996964 | ... S13: =IF(S7=0,0,S12/S7) -> 0.18126897
A14: Depreciation | B14: ='P&L'!B21 -> -45991.667 | C14: ='P&L'!C21 -> -46601.417 | D14: ='P&L'!D21 -> -47229.459 | E14: ='P&L'!E21 -> -47876.343 | F14: ='P&L'!F21 -> -48542.633 | H14: =INDEX(Monthly!$C$62:$BJ$62,($R$2-1)*12+1) -> -3809.7222 | I14: =INDEX(Monthly!$C$62:$BJ$62,($R$2-1)*12+2) -> -3813.8889 | J14: =INDEX(Monthly!$C$62:$BJ$62,($R$2-1)*12+3) -> -3818.0556 | K14: =INDEX(Monthly!$C$62:$BJ$62,($R$2-1)*12+4) -> -3822.2222 | L14: =INDEX(Monthly!$C$62:$BJ$62,($R$2-1)*12+5) -> -3826.3889 | M14: =INDEX(Monthly!$C$62:$BJ$62,($R$2-1)*12+6) -> -3830.5556 | N14: =INDEX(Monthly!$C$62:$BJ$62,($R$2-1)*12+7) -> -3834.7222 | O14: =INDEX(Monthly!$C$62:$BJ$62,($R$2-1)*12+8) -> -3838.8889 | P14: =INDEX(Monthly!$C$62:$BJ$62,($R$2-1)*12+9) -> -3843.0556 | Q14: =INDEX(Monthly!$C$62:$BJ$62,($R$2-1)*12+10) -> -3847.2222 | R14: =INDEX(Monthly!$C$62:$BJ$62,($R$2-1)*12+11) -> -3851.3889 | S14: =INDEX(Monthly!$C$62:$BJ$62,($R$2-1)*12+12) -> -3855.5556
A15: EBIT | B15: ='P&L'!B22 -> -35749.123 | C15: ='P&L'!C22 -> 51798.646 | D15: ='P&L'!D22 -> 63456.584 | E15: ='P&L'!E22 -> 75106.572 | F15: ='P&L'!F22 -> 86896.271 | H15: =INDEX(Monthly!$C$45:$BJ$45,($R$2-1)*12+1) -> -11332.65 | I15: =INDEX(Monthly!$C$45:$BJ$45,($R$2-1)*12+2) -> -10061.506 | J15: =INDEX(Monthly!$C$45:$BJ$45,($R$2-1)*12+3) -> -8790.3619 | K15: =INDEX(Monthly!$C$45:$BJ$45,($R$2-1)*12+4) -> -7519.2177 | L15: =INDEX(Monthly!$C$45:$BJ$45,($R$2-1)*12+5) -> -6248.0736 | M15: =INDEX(Monthly!$C$45:$BJ$45,($R$2-1)*12+6) -> 433.48006 | N15: =INDEX(Monthly!$C$45:$BJ$45,($R$2-1)*12+7) -> 2168.3736 | O15: =INDEX(Monthly!$C$45:$BJ$45,($R$2-1)*12+8) -> 3903.2671 | P15: =INDEX(Monthly!$C$45:$BJ$45,($R$2-1)*12+9) -> -1163.497 | Q15: =INDEX(Monthly!$C$45:$BJ$45,($R$2-1)*12+10) -> 107.64714 | R15: =INDEX(Monthly!$C$45:$BJ$45,($R$2-1)*12+11) -> 1378.7913 | S15: =INDEX(Monthly!$C$45:$BJ$45,($R$2-1)*12+12) -> 1374.6246
A16: Interest | B16: ='P&L'!B23 -> -34757.685 | C16: ='P&L'!C23 -> -34204.733 | D16: ='P&L'!D23 -> -33611.809 | E16: ='P&L'!E23 -> -32976.021 | F16: ='P&L'!F23 -> -32294.273 | H16: =INDEX(Monthly!$C$46:$BJ$46,($R$2-1)*12+1) -> -2916.6667 | I16: =INDEX(Monthly!$C$46:$BJ$46,($R$2-1)*12+2) -> -2913.0662 | J16: =INDEX(Monthly!$C$46:$BJ$46,($R$2-1)*12+3) -> -2909.4447 | K16: =INDEX(Monthly!$C$46:$BJ$46,($R$2-1)*12+4) -> -2905.802 | L16: =INDEX(Monthly!$C$46:$BJ$46,($R$2-1)*12+5) -> -2902.1381 | M16: =INDEX(Monthly!$C$46:$BJ$46,($R$2-1)*12+6) -> -2898.4529 | N16: =INDEX(Monthly!$C$46:$BJ$46,($R$2-1)*12+7) -> -2894.7461 | O16: =INDEX(Monthly!$C$46:$BJ$46,($R$2-1)*12+8) -> -2891.0178 | P16: =INDEX(Monthly!$C$46:$BJ$46,($R$2-1)*12+9) -> -2887.2676 | Q16: =INDEX(Monthly!$C$46:$BJ$46,($R$2-1)*12+10) -> -2883.4956 | R16: =INDEX(Monthly!$C$46:$BJ$46,($R$2-1)*12+11) -> -2879.7016 | S16: =INDEX(Monthly!$C$46:$BJ$46,($R$2-1)*12+12) -> -2875.8855
A17: Pre-tax income | B17: ='P&L'!B24 -> -70506.807 | C17: ='P&L'!C24 -> 17593.913 | D17: ='P&L'!D24 -> 29844.776 | E17: ='P&L'!E24 -> 42130.551 | F17: ='P&L'!F24 -> 54601.998 | H17: =INDEX(Monthly!$C$47:$BJ$47,($R$2-1)*12+1) -> -14249.317 | I17: =INDEX(Monthly!$C$47:$BJ$47,($R$2-1)*12+2) -> -12974.572 | J17: =INDEX(Monthly!$C$47:$BJ$47,($R$2-1)*12+3) -> -11699.807 | K17: =INDEX(Monthly!$C$47:$BJ$47,($R$2-1)*12+4) -> -10425.02 | L17: =INDEX(Monthly!$C$47:$BJ$47,($R$2-1)*12+5) -> -9150.2117 | M17: =INDEX(Monthly!$C$47:$BJ$47,($R$2-1)*12+6) -> -2464.9728 | N17: =INDEX(Monthly!$C$47:$BJ$47,($R$2-1)*12+7) -> -726.37254 | O17: =INDEX(Monthly!$C$47:$BJ$47,($R$2-1)*12+8) -> 1012.2494 | P17: =INDEX(Monthly!$C$47:$BJ$47,($R$2-1)*12+9) -> -4050.7646 | Q17: =INDEX(Monthly!$C$47:$BJ$47,($R$2-1)*12+10) -> -2775.8485 | R17: =INDEX(Monthly!$C$47:$BJ$47,($R$2-1)*12+11) -> -1500.9104 | S17: =INDEX(Monthly!$C$47:$BJ$47,($R$2-1)*12+12) -> -1501.2609
A18: Income tax | B18: ='P&L'!B25 -> 0 | C18: ='P&L'!C25 -> 0 | D18: ='P&L'!D25 -> 0 | E18: ='P&L'!E25 -> -4003.1107 | F18: ='P&L'!F25 -> -11466.42 | H18: =INDEX(Monthly!$C$50:$BJ$50,($R$2-1)*12+1) -> 0 | I18: =INDEX(Monthly!$C$50:$BJ$50,($R$2-1)*12+2) -> 0 | J18: =INDEX(Monthly!$C$50:$BJ$50,($R$2-1)*12+3) -> 0 | K18: =INDEX(Monthly!$C$50:$BJ$50,($R$2-1)*12+4) -> 0 | L18: =INDEX(Monthly!$C$50:$BJ$50,($R$2-1)*12+5) -> 0 | M18: =INDEX(Monthly!$C$50:$BJ$50,($R$2-1)*12+6) -> 0 | N18: =INDEX(Monthly!$C$50:$BJ$50,($R$2-1)*12+7) -> 0 | O18: =INDEX(Monthly!$C$50:$BJ$50,($R$2-1)*12+8) -> 0 | P18: =INDEX(Monthly!$C$50:$BJ$50,($R$2-1)*12+9) -> 0 | Q18: =INDEX(Monthly!$C$50:$BJ$50,($R$2-1)*12+10) -> 0 | R18: =INDEX(Monthly!$C$50:$BJ$50,($R$2-1)*12+11) -> 0 | S18: =INDEX(Monthly!$C$50:$BJ$50,($R$2-1)*12+12) -> 0
A19: Net income | B19: ='P&L'!B26 -> -70506.807 | C19: ='P&L'!C26 -> 17593.913 | D19: ='P&L'!D26 -> 29844.776 | E19: ='P&L'!E26 -> 38127.44 | F19: ='P&L'!F26 -> 43135.578 | H19: =INDEX(Monthly!$C$51:$BJ$51,($R$2-1)*12+1) -> -14249.317 | I19: =INDEX(Monthly!$C$51:$BJ$51,($R$2-1)*12+2) -> -12974.572 | J19: =INDEX(Monthly!$C$51:$BJ$51,($R$2-1)*12+3) -> -11699.807 | K19: =INDEX(Monthly!$C$51:$BJ$51,($R$2-1)*12+4) -> -10425.02 | L19: =INDEX(Monthly!$C$51:$BJ$51,($R$2-1)*12+5) -> -9150.2117 | M19: =INDEX(Monthly!$C$51:$BJ$51,($R$2-1)*12+6) -> -2464.9728 | N19: =INDEX(Monthly!$C$51:$BJ$51,($R$2-1)*12+7) -> -726.37254 | O19: =INDEX(Monthly!$C$51:$BJ$51,($R$2-1)*12+8) -> 1012.2494 | P19: =INDEX(Monthly!$C$51:$BJ$51,($R$2-1)*12+9) -> -4050.7646 | Q19: =INDEX(Monthly!$C$51:$BJ$51,($R$2-1)*12+10) -> -2775.8485 | R19: =INDEX(Monthly!$C$51:$BJ$51,($R$2-1)*12+11) -> -1500.9104 | S19: =INDEX(Monthly!$C$51:$BJ$51,($R$2-1)*12+12) -> -1501.2609
A20: Net margin | B20: ='P&L'!B27 -> -0.25644037 | C20: ='P&L'!C27 -> 0.044336566 | D20: ='P&L'!D27 -> 0.071586402 | E20: ='P&L'!E27 -> 0.087048736 | F20: ='P&L'!F27 -> 0.09373959 | H20: =IF(H7=0,0,H19/H7) -> -1.2346415 | I20: =IF(I7=0,0,I19/I7) -> -0.97755687 | J20: =IF(J7=0,0,J19/J7) -> -0.77979806 | K20: =IF(K7=0,0,K19/K7) -> -0.62295361 | L20: =IF(L7=0,0,L19/L7) -> -0.49551635 | M20: =IF(M7=0,0,M19/M7) -> -0.089499856 | N20: =IF(N7=0,0,N19/N7) -> -0.024291485 | O20: =IF(O7=0,0,O19/O7) -> 0.031374868 | ... S20: =IF(S7=0,0,S19/S7) -> -0.052031097
A22: Cash flow ($'000) — by year | H22: ="Cash flow ($'000) — Year "&$R$2&", by month" -> Cash flow ($'000) — Year 1, by month
B23: 1 | C23: 2 | D23: 3 | E23: 4 | F23: 5 | H23: =INDEX(Monthly!$C$4:$BJ$4,($R$2-1)*12+1) -> 1 | I23: =INDEX(Monthly!$C$4:$BJ$4,($R$2-1)*12+2) -> 2 | J23: =INDEX(Monthly!$C$4:$BJ$4,($R$2-1)*12+3) -> 3 | K23: =INDEX(Monthly!$C$4:$BJ$4,($R$2-1)*12+4) -> 4 | L23: =INDEX(Monthly!$C$4:$BJ$4,($R$2-1)*12+5) -> 5 | M23: =INDEX(Monthly!$C$4:$BJ$4,($R$2-1)*12+6) -> 6 | N23: =INDEX(Monthly!$C$4:$BJ$4,($R$2-1)*12+7) -> 7 | O23: =INDEX(Monthly!$C$4:$BJ$4,($R$2-1)*12+8) -> 8 | P23: =INDEX(Monthly!$C$4:$BJ$4,($R$2-1)*12+9) -> 9 | Q23: =INDEX(Monthly!$C$4:$BJ$4,($R$2-1)*12+10) -> 10 | R23: =INDEX(Monthly!$C$4:$BJ$4,($R$2-1)*12+11) -> 11 | S23: =INDEX(Monthly!$C$4:$BJ$4,($R$2-1)*12+12) -> 12
A24: Operating cash flow | B24: ='Cash Flow'!B10 -> -19872.931 | C24: ='Cash Flow'!C10 -> 64360.735 | D24: ='Cash Flow'!D10 -> 77245.925 | E24: ='Cash Flow'!E10 -> 86182.013 | F24: ='Cash Flow'!F10 -> 91863.248 | H24: =INDEX(Monthly!$C$83:$BJ$83,($R$2-1)*12+1) -> -6558.7108 | I24: =INDEX(Monthly!$C$83:$BJ$83,($R$2-1)*12+2) -> -9084.5507 | J24: =INDEX(Monthly!$C$83:$BJ$83,($R$2-1)*12+3) -> -7805.6184 | K24: =INDEX(Monthly!$C$83:$BJ$83,($R$2-1)*12+4) -> -6526.665 | L24: =INDEX(Monthly!$C$83:$BJ$83,($R$2-1)*12+5) -> -5247.6903 | M24: =INDEX(Monthly!$C$83:$BJ$83,($R$2-1)*12+6) -> 1764.702 | N24: =INDEX(Monthly!$C$83:$BJ$83,($R$2-1)*12+7) -> 3212.1668 | O24: =INDEX(Monthly!$C$83:$BJ$83,($R$2-1)*12+8) -> 4954.9554 | P24: =INDEX(Monthly!$C$83:$BJ$83,($R$2-1)*12+9) -> -509.93232 | Q24: =INDEX(Monthly!$C$83:$BJ$83,($R$2-1)*12+10) -> 1147.5063 | R24: =INDEX(Monthly!$C$83:$BJ$83,($R$2-1)*12+11) -> 2426.6111 | S24: =INDEX(Monthly!$C$83:$BJ$83,($R$2-1)*12+12) -> 2354.2947
A25: Capital spending | B25: ='Cash Flow'!B11 -> -874000 | C25: ='Cash Flow'!C11 -> -9270 | D25: ='Cash Flow'!D11 -> -9548.1 | E25: ='Cash Flow'!E11 -> -9834.543 | F25: ='Cash Flow'!F11 -> -10129.579 | H25: =INDEX(Monthly!$C$84:$BJ$84,($R$2-1)*12+1) -> -865750 | I25: =INDEX(Monthly!$C$84:$BJ$84,($R$2-1)*12+2) -> -750 | J25: =INDEX(Monthly!$C$84:$BJ$84,($R$2-1)*12+3) -> -750 | K25: =INDEX(Monthly!$C$84:$BJ$84,($R$2-1)*12+4) -> -750 | L25: =INDEX(Monthly!$C$84:$BJ$84,($R$2-1)*12+5) -> -750 | M25: =INDEX(Monthly!$C$84:$BJ$84,($R$2-1)*12+6) -> -750 | N25: =INDEX(Monthly!$C$84:$BJ$84,($R$2-1)*12+7) -> -750 | O25: =INDEX(Monthly!$C$84:$BJ$84,($R$2-1)*12+8) -> -750 | P25: =INDEX(Monthly!$C$84:$BJ$84,($R$2-1)*12+9) -> -750 | Q25: =INDEX(Monthly!$C$84:$BJ$84,($R$2-1)*12+10) -> -750 | R25: =INDEX(Monthly!$C$84:$BJ$84,($R$2-1)*12+11) -> -750 | S25: =INDEX(Monthly!$C$84:$BJ$84,($R$2-1)*12+12) -> -750
A26: Equity raised | B26: ='Cash Flow'!B12 -> 430000 | C26: ='Cash Flow'!C12 -> 0 | D26: ='Cash Flow'!D12 -> 0 | E26: ='Cash Flow'!E12 -> 0 | F26: ='Cash Flow'!F12 -> 0 | H26: =INDEX(Monthly!$C$85:$BJ$85,($R$2-1)*12+1) -> 430000 | I26: =INDEX(Monthly!$C$85:$BJ$85,($R$2-1)*12+2) -> 0 | J26: =INDEX(Monthly!$C$85:$BJ$85,($R$2-1)*12+3) -> 0 | K26: =INDEX(Monthly!$C$85:$BJ$85,($R$2-1)*12+4) -> 0 | L26: =INDEX(Monthly!$C$85:$BJ$85,($R$2-1)*12+5) -> 0 | M26: =INDEX(Monthly!$C$85:$BJ$85,($R$2-1)*12+6) -> 0 | N26: =INDEX(Monthly!$C$85:$BJ$85,($R$2-1)*12+7) -> 0 | O26: =INDEX(Monthly!$C$85:$BJ$85,($R$2-1)*12+8) -> 0 | P26: =INDEX(Monthly!$C$85:$BJ$85,($R$2-1)*12+9) -> 0 | Q26: =INDEX(Monthly!$C$85:$BJ$85,($R$2-1)*12+10) -> 0 | R26: =INDEX(Monthly!$C$85:$BJ$85,($R$2-1)*12+11) -> 0 | S26: =INDEX(Monthly!$C$85:$BJ$85,($R$2-1)*12+12) -> 0
A27: Loan drawdown | B27: ='Cash Flow'!B13 -> 500000 | C27: ='Cash Flow'!C13 -> 0 | D27: ='Cash Flow'!D13 -> 0 | E27: ='Cash Flow'!E13 -> 0 | F27: ='Cash Flow'!F13 -> 0 | H27: =INDEX(Monthly!$C$68:$BJ$68,($R$2-1)*12+1) -> 500000 | I27: =INDEX(Monthly!$C$68:$BJ$68,($R$2-1)*12+2) -> 0 | J27: =INDEX(Monthly!$C$68:$BJ$68,($R$2-1)*12+3) -> 0 | K27: =INDEX(Monthly!$C$68:$BJ$68,($R$2-1)*12+4) -> 0 | L27: =INDEX(Monthly!$C$68:$BJ$68,($R$2-1)*12+5) -> 0 | M27: =INDEX(Monthly!$C$68:$BJ$68,($R$2-1)*12+6) -> 0 | N27: =INDEX(Monthly!$C$68:$BJ$68,($R$2-1)*12+7) -> 0 | O27: =INDEX(Monthly!$C$68:$BJ$68,($R$2-1)*12+8) -> 0 | P27: =INDEX(Monthly!$C$68:$BJ$68,($R$2-1)*12+9) -> 0 | Q27: =INDEX(Monthly!$C$68:$BJ$68,($R$2-1)*12+10) -> 0 | R27: =INDEX(Monthly!$C$68:$BJ$68,($R$2-1)*12+11) -> 0 | S27: =INDEX(Monthly!$C$68:$BJ$68,($R$2-1)*12+12) -> 0
A28: Loan repayment | B28: ='Cash Flow'!B14 -> -7649.067 | C28: ='Cash Flow'!C14 -> -8202.0187 | D28: ='Cash Flow'!D14 -> -8794.9433 | E28: ='Cash Flow'!E14 -> -9430.7304 | F28: ='Cash Flow'!F14 -> -10112.479 | H28: =INDEX(Monthly!$C$70:$BJ$70,($R$2-1)*12+1) -> -617.22932 | I28: =INDEX(Monthly!$C$70:$BJ$70,($R$2-1)*12+2) -> -620.82982 | J28: =INDEX(Monthly!$C$70:$BJ$70,($R$2-1)*12+3) -> -624.45133 | K28: =INDEX(Monthly!$C$70:$BJ$70,($R$2-1)*12+4) -> -628.09396 | L28: =INDEX(Monthly!$C$70:$BJ$70,($R$2-1)*12+5) -> -631.75785 | M28: =INDEX(Monthly!$C$70:$BJ$70,($R$2-1)*12+6) -> -635.4431 | N28: =INDEX(Monthly!$C$70:$BJ$70,($R$2-1)*12+7) -> -639.14985 | O28: =INDEX(Monthly!$C$70:$BJ$70,($R$2-1)*12+8) -> -642.87823 | P28: =INDEX(Monthly!$C$70:$BJ$70,($R$2-1)*12+9) -> -646.62835 | Q28: =INDEX(Monthly!$C$70:$BJ$70,($R$2-1)*12+10) -> -650.40035 | R28: =INDEX(Monthly!$C$70:$BJ$70,($R$2-1)*12+11) -> -654.19435 | S28: =INDEX(Monthly!$C$70:$BJ$70,($R$2-1)*12+12) -> -658.01048
A29: Financing cash flow | B29: ='Cash Flow'!B15 -> 922350.93 | C29: ='Cash Flow'!C15 -> -8202.0187 | D29: ='Cash Flow'!D15 -> -8794.9433 | E29: ='Cash Flow'!E15 -> -9430.7304 | F29: ='Cash Flow'!F15 -> -10112.479 | H29: =INDEX(Monthly!$C$86:$BJ$86,($R$2-1)*12+1) -> 929382.77 | I29: =INDEX(Monthly!$C$86:$BJ$86,($R$2-1)*12+2) -> -620.82982 | J29: =INDEX(Monthly!$C$86:$BJ$86,($R$2-1)*12+3) -> -624.45133 | K29: =INDEX(Monthly!$C$86:$BJ$86,($R$2-1)*12+4) -> -628.09396 | L29: =INDEX(Monthly!$C$86:$BJ$86,($R$2-1)*12+5) -> -631.75785 | M29: =INDEX(Monthly!$C$86:$BJ$86,($R$2-1)*12+6) -> -635.4431 | N29: =INDEX(Monthly!$C$86:$BJ$86,($R$2-1)*12+7) -> -639.14985 | O29: =INDEX(Monthly!$C$86:$BJ$86,($R$2-1)*12+8) -> -642.87823 | P29: =INDEX(Monthly!$C$86:$BJ$86,($R$2-1)*12+9) -> -646.62835 | Q29: =INDEX(Monthly!$C$86:$BJ$86,($R$2-1)*12+10) -> -650.40035 | R29: =INDEX(Monthly!$C$86:$BJ$86,($R$2-1)*12+11) -> -654.19435 | S29: =INDEX(Monthly!$C$86:$BJ$86,($R$2-1)*12+12) -> -658.01048
A30: Net change in cash | B30: ='Cash Flow'!B16 -> 28478.002 | C30: ='Cash Flow'!C16 -> 46888.716 | D30: ='Cash Flow'!D16 -> 58902.881 | E30: ='Cash Flow'!E16 -> 66916.74 | F30: ='Cash Flow'!F16 -> 71621.19 | H30: =INDEX(Monthly!$C$87:$BJ$87,($R$2-1)*12+1) -> 57074.06 | I30: =INDEX(Monthly!$C$87:$BJ$87,($R$2-1)*12+2) -> -10455.381 | J30: =INDEX(Monthly!$C$87:$BJ$87,($R$2-1)*12+3) -> -9180.0697 | K30: =INDEX(Monthly!$C$87:$BJ$87,($R$2-1)*12+4) -> -7904.7589 | L30: =INDEX(Monthly!$C$87:$BJ$87,($R$2-1)*12+5) -> -6629.4481 | M30: =INDEX(Monthly!$C$87:$BJ$87,($R$2-1)*12+6) -> 379.25886 | N30: =INDEX(Monthly!$C$87:$BJ$87,($R$2-1)*12+7) -> 1823.017 | O30: =INDEX(Monthly!$C$87:$BJ$87,($R$2-1)*12+8) -> 3562.0772 | P30: =INDEX(Monthly!$C$87:$BJ$87,($R$2-1)*12+9) -> -1906.5607 | Q30: =INDEX(Monthly!$C$87:$BJ$87,($R$2-1)*12+10) -> -252.89405 | R30: =INDEX(Monthly!$C$87:$BJ$87,($R$2-1)*12+11) -> 1022.4168 | S30: =INDEX(Monthly!$C$87:$BJ$87,($R$2-1)*12+12) -> 946.28419
A31: Closing cash | B31: ='Cash Flow'!B18 -> 28478.002 | C31: ='Cash Flow'!C18 -> 75366.718 | D31: ='Cash Flow'!D18 -> 134269.6 | E31: ='Cash Flow'!E18 -> 201186.34 | F31: ='Cash Flow'!F18 -> 272807.53 | H31: =INDEX(Monthly!$C$89:$BJ$89,($R$2-1)*12+1) -> 57074.06 | I31: =INDEX(Monthly!$C$89:$BJ$89,($R$2-1)*12+2) -> 46618.679 | J31: =INDEX(Monthly!$C$89:$BJ$89,($R$2-1)*12+3) -> 37438.61 | K31: =INDEX(Monthly!$C$89:$BJ$89,($R$2-1)*12+4) -> 29533.851 | L31: =INDEX(Monthly!$C$89:$BJ$89,($R$2-1)*12+5) -> 22904.403 | M31: =INDEX(Monthly!$C$89:$BJ$89,($R$2-1)*12+6) -> 23283.661 | N31: =INDEX(Monthly!$C$89:$BJ$89,($R$2-1)*12+7) -> 25106.678 | O31: =INDEX(Monthly!$C$89:$BJ$89,($R$2-1)*12+8) -> 28668.756 | P31: =INDEX(Monthly!$C$89:$BJ$89,($R$2-1)*12+9) -> 26762.195 | Q31: =INDEX(Monthly!$C$89:$BJ$89,($R$2-1)*12+10) -> 26509.301 | R31: =INDEX(Monthly!$C$89:$BJ$89,($R$2-1)*12+11) -> 27531.718 | S31: =INDEX(Monthly!$C$89:$BJ$89,($R$2-1)*12+12) -> 28478.002
A39: Balance sheet at year end ($'000) | H39: ="Balance sheet at month end ($'000) — Year "&$R$2 -> Balance sheet at month end ($'000) — Year 1
B40: 1 | C40: 2 | D40: 3 | E40: 4 | F40: 5 | H40: =INDEX(Monthly!$C$4:$BJ$4,($R$2-1)*12+1) -> 1 | I40: =INDEX(Monthly!$C$4:$BJ$4,($R$2-1)*12+2) -> 2 | J40: =INDEX(Monthly!$C$4:$BJ$4,($R$2-1)*12+3) -> 3 | K40: =INDEX(Monthly!$C$4:$BJ$4,($R$2-1)*12+4) -> 4 | L40: =INDEX(Monthly!$C$4:$BJ$4,($R$2-1)*12+5) -> 5 | M40: =INDEX(Monthly!$C$4:$BJ$4,($R$2-1)*12+6) -> 6 | N40: =INDEX(Monthly!$C$4:$BJ$4,($R$2-1)*12+7) -> 7 | O40: =INDEX(Monthly!$C$4:$BJ$4,($R$2-1)*12+8) -> 8 | P40: =INDEX(Monthly!$C$4:$BJ$4,($R$2-1)*12+9) -> 9 | Q40: =INDEX(Monthly!$C$4:$BJ$4,($R$2-1)*12+10) -> 10 | R40: =INDEX(Monthly!$C$4:$BJ$4,($R$2-1)*12+11) -> 11 | S40: =INDEX(Monthly!$C$4:$BJ$4,($R$2-1)*12+12) -> 12
A41: Cash | B41: ='Balance Sheet'!B5 -> 28478.002 | C41: ='Balance Sheet'!C5 -> 75366.718 | D41: ='Balance Sheet'!D5 -> 134269.6 | E41: ='Balance Sheet'!E5 -> 201186.34 | F41: ='Balance Sheet'!F5 -> 272807.53 | H41: =INDEX(Monthly!$C$89:$BJ$89,($R$2-1)*12+1) -> 57074.06 | I41: =INDEX(Monthly!$C$89:$BJ$89,($R$2-1)*12+2) -> 46618.679 | J41: =INDEX(Monthly!$C$89:$BJ$89,($R$2-1)*12+3) -> 37438.61 | K41: =INDEX(Monthly!$C$89:$BJ$89,($R$2-1)*12+4) -> 29533.851 | L41: =INDEX(Monthly!$C$89:$BJ$89,($R$2-1)*12+5) -> 22904.403 | M41: =INDEX(Monthly!$C$89:$BJ$89,($R$2-1)*12+6) -> 23283.661 | N41: =INDEX(Monthly!$C$89:$BJ$89,($R$2-1)*12+7) -> 25106.678 | O41: =INDEX(Monthly!$C$89:$BJ$89,($R$2-1)*12+8) -> 28668.756 | P41: =INDEX(Monthly!$C$89:$BJ$89,($R$2-1)*12+9) -> 26762.195 | Q41: =INDEX(Monthly!$C$89:$BJ$89,($R$2-1)*12+10) -> 26509.301 | R41: =INDEX(Monthly!$C$89:$BJ$89,($R$2-1)*12+11) -> 27531.718 | S41: =INDEX(Monthly!$C$89:$BJ$89,($R$2-1)*12+12) -> 28478.002
A42: Accounts receivable | B42: ='Balance Sheet'!B6 -> 2885.3147 | C42: ='Balance Sheet'!C6 -> 3031.3116 | D42: ='Balance Sheet'!D6 -> 3184.696 | E42: ='Balance Sheet'!E6 -> 3345.8416 | F42: ='Balance Sheet'!F6 -> 3515.1412 | H42: =INDEX(Monthly!$C$75:$BJ$75,($R$2-1)*12+1) -> 1154.1259 | I42: =INDEX(Monthly!$C$75:$BJ$75,($R$2-1)*12+2) -> 1327.2447 | J42: =INDEX(Monthly!$C$75:$BJ$75,($R$2-1)*12+3) -> 1500.3636 | K42: =INDEX(Monthly!$C$75:$BJ$75,($R$2-1)*12+4) -> 1673.4825 | L42: =INDEX(Monthly!$C$75:$BJ$75,($R$2-1)*12+5) -> 1846.6014 | M42: =INDEX(Monthly!$C$75:$BJ$75,($R$2-1)*12+6) -> 2754.164 | N42: =INDEX(Monthly!$C$75:$BJ$75,($R$2-1)*12+7) -> 2990.2352 | O42: =INDEX(Monthly!$C$75:$BJ$75,($R$2-1)*12+8) -> 3226.3064 | P42: =INDEX(Monthly!$C$75:$BJ$75,($R$2-1)*12+9) -> 2539.0769 | Q42: =INDEX(Monthly!$C$75:$BJ$75,($R$2-1)*12+10) -> 2712.1958 | R42: =INDEX(Monthly!$C$75:$BJ$75,($R$2-1)*12+11) -> 2885.3147 | S42: =INDEX(Monthly!$C$75:$BJ$75,($R$2-1)*12+12) -> 2885.3147
A43: Inventory | B43: ='Balance Sheet'!B7 -> 1026.4806 | C43: ='Balance Sheet'!C7 -> 1068.9445 | D43: ='Balance Sheet'!D7 -> 1113.2728 | E43: ='Balance Sheet'!E7 -> 1159.5513 | F43: ='Balance Sheet'!F7 -> 1207.8699 | H43: =INDEX(Monthly!$C$76:$BJ$76,($R$2-1)*12+1) -> 686.59223 | I43: =INDEX(Monthly!$C$76:$BJ$76,($R$2-1)*12+2) -> 720.58106 | J43: =INDEX(Monthly!$C$76:$BJ$76,($R$2-1)*12+3) -> 754.56989 | K43: =INDEX(Monthly!$C$76:$BJ$76,($R$2-1)*12+4) -> 788.55873 | L43: =INDEX(Monthly!$C$76:$BJ$76,($R$2-1)*12+5) -> 822.54756 | M43: =INDEX(Monthly!$C$76:$BJ$76,($R$2-1)*12+6) -> 1000.7314 | N43: =INDEX(Monthly!$C$76:$BJ$76,($R$2-1)*12+7) -> 1047.0799 | O43: =INDEX(Monthly!$C$76:$BJ$76,($R$2-1)*12+8) -> 1093.4283 | P43: =INDEX(Monthly!$C$76:$BJ$76,($R$2-1)*12+9) -> 958.5029 | Q43: =INDEX(Monthly!$C$76:$BJ$76,($R$2-1)*12+10) -> 992.49173 | R43: =INDEX(Monthly!$C$76:$BJ$76,($R$2-1)*12+11) -> 1026.4806 | S43: =INDEX(Monthly!$C$76:$BJ$76,($R$2-1)*12+12) -> 1026.4806
A44: Net fixed assets | B44: ='Balance Sheet'!B8 -> 828008.33 | C44: ='Balance Sheet'!C8 -> 790676.92 | D44: ='Balance Sheet'!D8 -> 752995.56 | E44: ='Balance Sheet'!E8 -> 714953.76 | F44: ='Balance Sheet'!F8 -> 676540.7 | H44: =INDEX(Monthly!$C$64:$BJ$64,($R$2-1)*12+1) -> 861940.28 | I44: =INDEX(Monthly!$C$64:$BJ$64,($R$2-1)*12+2) -> 858876.39 | J44: =INDEX(Monthly!$C$64:$BJ$64,($R$2-1)*12+3) -> 855808.33 | K44: =INDEX(Monthly!$C$64:$BJ$64,($R$2-1)*12+4) -> 852736.11 | L44: =INDEX(Monthly!$C$64:$BJ$64,($R$2-1)*12+5) -> 849659.72 | M44: =INDEX(Monthly!$C$64:$BJ$64,($R$2-1)*12+6) -> 846579.17 | N44: =INDEX(Monthly!$C$64:$BJ$64,($R$2-1)*12+7) -> 843494.44 | O44: =INDEX(Monthly!$C$64:$BJ$64,($R$2-1)*12+8) -> 840405.56 | P44: =INDEX(Monthly!$C$64:$BJ$64,($R$2-1)*12+9) -> 837312.5 | Q44: =INDEX(Monthly!$C$64:$BJ$64,($R$2-1)*12+10) -> 834215.28 | R44: =INDEX(Monthly!$C$64:$BJ$64,($R$2-1)*12+11) -> 831113.89 | S44: =INDEX(Monthly!$C$64:$BJ$64,($R$2-1)*12+12) -> 828008.33
A45: Total assets | B45: ='Balance Sheet'!B9 -> 860398.13 | C45: ='Balance Sheet'!C9 -> 870143.89 | D45: ='Balance Sheet'!D9 -> 891563.13 | E45: ='Balance Sheet'!E9 -> 920645.49 | F45: ='Balance Sheet'!F9 -> 954071.24 | H45: =INDEX(Monthly!$C$103:$BJ$103,($R$2-1)*12+1) -> 920855.06 | I45: =INDEX(Monthly!$C$103:$BJ$103,($R$2-1)*12+2) -> 907542.89 | J45: =INDEX(Monthly!$C$103:$BJ$103,($R$2-1)*12+3) -> 895501.88 | K45: =INDEX(Monthly!$C$103:$BJ$103,($R$2-1)*12+4) -> 884732 | L45: =INDEX(Monthly!$C$103:$BJ$103,($R$2-1)*12+5) -> 875233.27 | M45: =INDEX(Monthly!$C$103:$BJ$103,($R$2-1)*12+6) -> 873617.72 | N45: =INDEX(Monthly!$C$103:$BJ$103,($R$2-1)*12+7) -> 872638.44 | O45: =INDEX(Monthly!$C$103:$BJ$103,($R$2-1)*12+8) -> 873394.05 | P45: =INDEX(Monthly!$C$103:$BJ$103,($R$2-1)*12+9) -> 867572.27 | Q45: =INDEX(Monthly!$C$103:$BJ$103,($R$2-1)*12+10) -> 864429.27 | R45: =INDEX(Monthly!$C$103:$BJ$103,($R$2-1)*12+11) -> 862557.4 | S45: =INDEX(Monthly!$C$103:$BJ$103,($R$2-1)*12+12) -> 860398.13
A46: Accounts payable | B46: ='Balance Sheet'!B10 -> 8554.0047 | C46: ='Balance Sheet'!C10 -> 8907.8707 | D46: ='Balance Sheet'!D10 -> 9277.2733 | E46: ='Balance Sheet'!E10 -> 9662.9276 | F46: ='Balance Sheet'!F10 -> 10065.583 | H46: =INDEX(Monthly!$C$77:$BJ$77,($R$2-1)*12+1) -> 5721.6019 | I46: =INDEX(Monthly!$C$77:$BJ$77,($R$2-1)*12+2) -> 6004.8422 | J46: =INDEX(Monthly!$C$77:$BJ$77,($R$2-1)*12+3) -> 6288.0825 | K46: =INDEX(Monthly!$C$77:$BJ$77,($R$2-1)*12+4) -> 6571.3227 | L46: =INDEX(Monthly!$C$77:$BJ$77,($R$2-1)*12+5) -> 6854.563 | M46: =INDEX(Monthly!$C$77:$BJ$77,($R$2-1)*12+6) -> 8339.4287 | N46: =INDEX(Monthly!$C$77:$BJ$77,($R$2-1)*12+7) -> 8725.6655 | O46: =INDEX(Monthly!$C$77:$BJ$77,($R$2-1)*12+8) -> 9111.9022 | P46: =INDEX(Monthly!$C$77:$BJ$77,($R$2-1)*12+9) -> 7987.5242 | Q46: =INDEX(Monthly!$C$77:$BJ$77,($R$2-1)*12+10) -> 8270.7644 | R46: =INDEX(Monthly!$C$77:$BJ$77,($R$2-1)*12+11) -> 8554.0047 | S46: =INDEX(Monthly!$C$77:$BJ$77,($R$2-1)*12+12) -> 8554.0047
A47: Loan | B47: ='Balance Sheet'!B11 -> 492350.93 | C47: ='Balance Sheet'!C11 -> 484148.91 | D47: ='Balance Sheet'!D11 -> 475353.97 | E47: ='Balance Sheet'!E11 -> 465923.24 | F47: ='Balance Sheet'!F11 -> 455810.76 | H47: =INDEX(Monthly!$C$72:$BJ$72,($R$2-1)*12+1) -> 499382.77 | I47: =INDEX(Monthly!$C$72:$BJ$72,($R$2-1)*12+2) -> 498761.94 | J47: =INDEX(Monthly!$C$72:$BJ$72,($R$2-1)*12+3) -> 498137.49 | K47: =INDEX(Monthly!$C$72:$BJ$72,($R$2-1)*12+4) -> 497509.4 | L47: =INDEX(Monthly!$C$72:$BJ$72,($R$2-1)*12+5) -> 496877.64 | M47: =INDEX(Monthly!$C$72:$BJ$72,($R$2-1)*12+6) -> 496242.19 | N47: =INDEX(Monthly!$C$72:$BJ$72,($R$2-1)*12+7) -> 495603.04 | O47: =INDEX(Monthly!$C$72:$BJ$72,($R$2-1)*12+8) -> 494960.17 | P47: =INDEX(Monthly!$C$72:$BJ$72,($R$2-1)*12+9) -> 494313.54 | Q47: =INDEX(Monthly!$C$72:$BJ$72,($R$2-1)*12+10) -> 493663.14 | R47: =INDEX(Monthly!$C$72:$BJ$72,($R$2-1)*12+11) -> 493008.94 | S47: =INDEX(Monthly!$C$72:$BJ$72,($R$2-1)*12+12) -> 492350.93
A48: Total liabilities | B48: ='Balance Sheet'!B12 -> 500904.94 | C48: ='Balance Sheet'!C12 -> 493056.79 | D48: ='Balance Sheet'!D12 -> 484631.24 | E48: ='Balance Sheet'!E12 -> 475586.17 | F48: ='Balance Sheet'!F12 -> 465876.34 | H48: =INDEX(Monthly!$C$104:$BJ$104,($R$2-1)*12+1) -> 505104.37 | I48: =INDEX(Monthly!$C$104:$BJ$104,($R$2-1)*12+2) -> 504766.78 | J48: =INDEX(Monthly!$C$104:$BJ$104,($R$2-1)*12+3) -> 504425.57 | K48: =INDEX(Monthly!$C$104:$BJ$104,($R$2-1)*12+4) -> 504080.72 | L48: =INDEX(Monthly!$C$104:$BJ$104,($R$2-1)*12+5) -> 503732.2 | M48: =INDEX(Monthly!$C$104:$BJ$104,($R$2-1)*12+6) -> 504581.62 | N48: =INDEX(Monthly!$C$104:$BJ$104,($R$2-1)*12+7) -> 504328.71 | O48: =INDEX(Monthly!$C$104:$BJ$104,($R$2-1)*12+8) -> 504072.07 | P48: =INDEX(Monthly!$C$104:$BJ$104,($R$2-1)*12+9) -> 502301.06 | Q48: =INDEX(Monthly!$C$104:$BJ$104,($R$2-1)*12+10) -> 501933.9 | R48: =INDEX(Monthly!$C$104:$BJ$104,($R$2-1)*12+11) -> 501562.95 | S48: =INDEX(Monthly!$C$104:$BJ$104,($R$2-1)*12+12) -> 500904.94
A49: Paid-in capital | B49: ='Balance Sheet'!B13 -> 430000 | C49: ='Balance Sheet'!C13 -> 430000 | D49: ='Balance Sheet'!D13 -> 430000 | E49: ='Balance Sheet'!E13 -> 430000 | F49: ='Balance Sheet'!F13 -> 430000 | H49: =INDEX(Monthly!$C$101:$BJ$101,($R$2-1)*12+1) -> 430000 | I49: =INDEX(Monthly!$C$101:$BJ$101,($R$2-1)*12+2) -> 430000 | J49: =INDEX(Monthly!$C$101:$BJ$101,($R$2-1)*12+3) -> 430000 | K49: =INDEX(Monthly!$C$101:$BJ$101,($R$2-1)*12+4) -> 430000 | L49: =INDEX(Monthly!$C$101:$BJ$101,($R$2-1)*12+5) -> 430000 | M49: =INDEX(Monthly!$C$101:$BJ$101,($R$2-1)*12+6) -> 430000 | N49: =INDEX(Monthly!$C$101:$BJ$101,($R$2-1)*12+7) -> 430000 | O49: =INDEX(Monthly!$C$101:$BJ$101,($R$2-1)*12+8) -> 430000 | P49: =INDEX(Monthly!$C$101:$BJ$101,($R$2-1)*12+9) -> 430000 | Q49: =INDEX(Monthly!$C$101:$BJ$101,($R$2-1)*12+10) -> 430000 | R49: =INDEX(Monthly!$C$101:$BJ$101,($R$2-1)*12+11) -> 430000 | S49: =INDEX(Monthly!$C$101:$BJ$101,($R$2-1)*12+12) -> 430000
A50: Retained earnings | B50: ='Balance Sheet'!B14 -> -70506.807 | C50: ='Balance Sheet'!C14 -> -52912.894 | D50: ='Balance Sheet'!D14 -> -23068.119 | E50: ='Balance Sheet'!E14 -> 15059.321 | F50: ='Balance Sheet'!F14 -> 58194.9 | H50: =INDEX(Monthly!$C$102:$BJ$102,($R$2-1)*12+1) -> -14249.317 | I50: =INDEX(Monthly!$C$102:$BJ$102,($R$2-1)*12+2) -> -27223.889 | J50: =INDEX(Monthly!$C$102:$BJ$102,($R$2-1)*12+3) -> -38923.696 | K50: =INDEX(Monthly!$C$102:$BJ$102,($R$2-1)*12+4) -> -49348.715 | L50: =INDEX(Monthly!$C$102:$BJ$102,($R$2-1)*12+5) -> -58498.927 | M50: =INDEX(Monthly!$C$102:$BJ$102,($R$2-1)*12+6) -> -60963.9 | N50: =INDEX(Monthly!$C$102:$BJ$102,($R$2-1)*12+7) -> -61690.272 | O50: =INDEX(Monthly!$C$102:$BJ$102,($R$2-1)*12+8) -> -60678.023 | P50: =INDEX(Monthly!$C$102:$BJ$102,($R$2-1)*12+9) -> -64728.788 | Q50: =INDEX(Monthly!$C$102:$BJ$102,($R$2-1)*12+10) -> -67504.636 | R50: =INDEX(Monthly!$C$102:$BJ$102,($R$2-1)*12+11) -> -69005.546 | S50: =INDEX(Monthly!$C$102:$BJ$102,($R$2-1)*12+12) -> -70506.807
A51: Total equity | B51: ='Balance Sheet'!B15 -> 359493.19 | C51: ='Balance Sheet'!C15 -> 377087.11 | D51: ='Balance Sheet'!D15 -> 406931.88 | E51: ='Balance Sheet'!E15 -> 445059.32 | F51: ='Balance Sheet'!F15 -> 488194.9 | H51: =INDEX(Monthly!$C$105:$BJ$105,($R$2-1)*12+1) -> 415750.68 | I51: =INDEX(Monthly!$C$105:$BJ$105,($R$2-1)*12+2) -> 402776.11 | J51: =INDEX(Monthly!$C$105:$BJ$105,($R$2-1)*12+3) -> 391076.3 | K51: =INDEX(Monthly!$C$105:$BJ$105,($R$2-1)*12+4) -> 380651.28 | L51: =INDEX(Monthly!$C$105:$BJ$105,($R$2-1)*12+5) -> 371501.07 | M51: =INDEX(Monthly!$C$105:$BJ$105,($R$2-1)*12+6) -> 369036.1 | N51: =INDEX(Monthly!$C$105:$BJ$105,($R$2-1)*12+7) -> 368309.73 | O51: =INDEX(Monthly!$C$105:$BJ$105,($R$2-1)*12+8) -> 369321.98 | P51: =INDEX(Monthly!$C$105:$BJ$105,($R$2-1)*12+9) -> 365271.21 | Q51: =INDEX(Monthly!$C$105:$BJ$105,($R$2-1)*12+10) -> 362495.36 | R51: =INDEX(Monthly!$C$105:$BJ$105,($R$2-1)*12+11) -> 360994.45 | S51: =INDEX(Monthly!$C$105:$BJ$105,($R$2-1)*12+12) -> 359493.19
A52: Total liabilities & equity | B52: ='Balance Sheet'!B16 -> 860398.13 | C52: ='Balance Sheet'!C16 -> 870143.89 | D52: ='Balance Sheet'!D16 -> 891563.13 | E52: ='Balance Sheet'!E16 -> 920645.49 | F52: ='Balance Sheet'!F16 -> 954071.24 | H52: =INDEX(Monthly!$C$106:$BJ$106,($R$2-1)*12+1) -> 920855.06 | I52: =INDEX(Monthly!$C$106:$BJ$106,($R$2-1)*12+2) -> 907542.89 | J52: =INDEX(Monthly!$C$106:$BJ$106,($R$2-1)*12+3) -> 895501.88 | K52: =INDEX(Monthly!$C$106:$BJ$106,($R$2-1)*12+4) -> 884732 | L52: =INDEX(Monthly!$C$106:$BJ$106,($R$2-1)*12+5) -> 875233.27 | M52: =INDEX(Monthly!$C$106:$BJ$106,($R$2-1)*12+6) -> 873617.72 | N52: =INDEX(Monthly!$C$106:$BJ$106,($R$2-1)*12+7) -> 872638.44 | O52: =INDEX(Monthly!$C$106:$BJ$106,($R$2-1)*12+8) -> 873394.05 | P52: =INDEX(Monthly!$C$106:$BJ$106,($R$2-1)*12+9) -> 867572.27 | Q52: =INDEX(Monthly!$C$106:$BJ$106,($R$2-1)*12+10) -> 864429.27 | R52: =INDEX(Monthly!$C$106:$BJ$106,($R$2-1)*12+11) -> 862557.4 | S52: =INDEX(Monthly!$C$106:$BJ$106,($R$2-1)*12+12) -> 860398.13

Sheet Scenarios
A1: Scenarios — Low / Base / High | H1: =HYPERLINK("#'Cover'!A1","◂ Contents") -> ◂ Contents
A2: All three scenarios calculated side by side, live: change any input and every column updates. Active = the scenario chosen on the Dashboard.
A5: Key drivers
A6: Driver | B6: Low | C6: Base | D6: High | E6: Active
A7: Lettable rooms (rooms) | B7: =Inputs!$B$7 -> 10 | C7: =Inputs!$C$7 -> 10 | D7: =Inputs!$D$7 -> 10 | E7: =Inputs!$E$7 -> 10
A8: Average daily rate per occupied room (year 1) ($) | B8: =Inputs!$B$17 -> 135 | C8: =Inputs!$C$17 -> 155 | D8: =Inputs!$D$17 -> 170 | E8: =Inputs!$E$17 -> 155
A9: Average occupancy at maturity, % of room-nights (year 1) (%) | B9: =Inputs!$B$8 -> 0.5 | C9: =Inputs!$C$8 -> 0.62 | D9: =Inputs!$D$8 -> 0.7 | E9: =Inputs!$E$8 -> 0.62
A10: Property purchase (month 1; 0 = leased building) ($) | B10: =Inputs!$B$42 -> 720000 | C10: =Inputs!$C$42 -> 720000 | D10: =Inputs!$D$42 -> 720000 | E10: =Inputs!$E$42 -> 720000
A11: Loan drawn at start ($) | B11: =Inputs!$B$66 -> 500000 | C11: =Inputs!$C$66 -> 500000 | D11: =Inputs!$D$66 -> 500000 | E11: =Inputs!$E$66 -> 500000
A12: Loan interest rate per year (%) | B12: =Inputs!$B$67 -> 0.07 | C12: =Inputs!$C$67 -> 0.07 | D12: =Inputs!$D$67 -> 0.07 | E12: =Inputs!$E$67 -> 0.07
A13: Equity raised at start ($) | B13: =Inputs!$B$65 -> 430000 | C13: =Inputs!$C$65 -> 430000 | D13: =Inputs!$D$65 -> 430000 | E13: =Inputs!$E$65 -> 430000
A15: Results by scenario ($'000)
A16: Output | B16: Low | C16: Base | D16: High | E16: Active
A17: Revenue — final year | B17: =F30 -> 273320.89 | C17: =F31 -> 460163.93 | D17: =F32 -> 622023.59 | E17: ='P&L'!F5 -> 460163.93
A18: Revenue — whole plan | B18: =SUM(B30:F30) -> 1225688.3 | C18: =SUM(B31:F31) -> 1986841.2 | D18: =SUM(B32:F32) -> 2637136.3 | E18: =SUM('P&L'!$B$5:$F$5) -> 1986841.2
A19: EBITDA — final year | B19: =F36 -> -35973.656 | C19: =F37 -> 135438.9 | D19: =F38 -> 284860.42 | E19: ='P&L'!F19 -> 135438.9
A20: EBITDA margin — final year | B20: =IF(B17=0,0,B19/B17) -> -0.13161693 | C20: =IF(C17=0,0,C19/C17) -> 0.29432751 | D20: =IF(D17=0,0,D19/D17) -> 0.45795758 | E20: =IF(E17=0,0,E19/E17) -> 0.29432751
A21: Net income — final year | B21: =F42 -> -116862.68 | C21: =F43 -> 43135.578 | D21: =F44 -> 161198.89 | E21: ='P&L'!F26 -> 43135.578
A22: Net income — whole plan | B22: =SUM(B42:F42) -> -616314.1 | C22: =SUM(B43:F43) -> 58194.9 | D22: =SUM(B44:F44) -> 537535.4 | E22: =SUM('P&L'!$B$26:$F$26) -> 58194.9
A23: Cash at the end of the plan | B23: =F48 -> -401616.61 | C23: =F49 -> 272807.53 | D23: =F50 -> 751487.19 | E23: ='Balance Sheet'!F5 -> 272807.53
A24: Lowest cash balance | B24: =MIN('Scenario calc'!$C$91:$BJ$91) -> -401616.61 | C24: =MIN('Scenario calc'!$C$211:$BJ$211) -> 22904.403 | D24: =MIN('Scenario calc'!$C$331:$BJ$331) -> 54905.784 | E24: ='Break-even'!B18 -> 22904.403
A25: Lowest cash point (month #) | B25: =MATCH(MIN('Scenario calc'!$C$91:$BJ$91),'Scenario calc'!$C$91:$BJ$91,0) -> 60 | C25: =MATCH(MIN('Scenario calc'!$C$211:$BJ$211),'Scenario calc'!$C$211:$BJ$211,0) -> 5 | D25: =MATCH(MIN('Scenario calc'!$C$331:$BJ$331),'Scenario calc'!$C$331:$BJ$331,0) -> 4 | E25: ='Break-even'!B6 -> 5
A26: Funding required (incl. cash buffer) | B26: =SUMPRODUCT(--('Scenario calc'!$C$6:$BJ$6<=B25),'Scenario calc'!$C$61:$BJ$61)-SUMPRODUCT(--('Scenario calc'!$C$6:$BJ$6<=B25),'Scenario calc'!$C$85:$BJ$85)-SUMPRODUCT(--('Scenario calc'!$C$6:$BJ$6<=B25),'Scenario calc'!$C$72:$BJ$72)+Inputs!$B$80 -> 1370616.6 | C26: =SUMPRODUCT(--('Scenario calc'!$C$126:$BJ$126<=C25),'Scenario calc'!$C$181:$BJ$181)-SUMPRODUCT(--('Scenario calc'!$C$126:$BJ$126<=C25),'Scenario calc'!$C$205:$BJ$205)-SUMPRODUCT(--('Scenario calc'!$C$126:$BJ$126<=C25),'Scenario calc'!$C$192:$BJ$192)+Inputs!$C$80 -> 946095.6 | D26: =SUMPRODUCT(--('Scenario calc'!$C$246:$BJ$246<=D25),'Scenario calc'!$C$301:$BJ$301)-SUMPRODUCT(--('Scenario calc'!$C$246:$BJ$246<=D25),'Scenario calc'!$C$325:$BJ$325)-SUMPRODUCT(--('Scenario calc'!$C$246:$BJ$246<=D25),'Scenario calc'!$C$312:$BJ$312)+Inputs!$D$80 -> 914094.22 | E26: ='Break-even'!B12 -> 946095.6
A28: Revenue by year ($'000)
A29: Scenario | B29: 1 | C29: 2 | D29: 3 | E29: 4 | F29: 5
A30: Low | B30: =SUMIF('Scenario calc'!$C$7:$BJ$7,B$29,'Scenario calc'!$C$22:$BJ$22) -> 151574.4 | C30: =SUMIF('Scenario calc'!$C$7:$BJ$7,C$29,'Scenario calc'!$C$22:$BJ$22) -> 262242.86 | D30: =SUMIF('Scenario calc'!$C$7:$BJ$7,D$29,'Scenario calc'!$C$22:$BJ$22) -> 267935.39 | E30: =SUMIF('Scenario calc'!$C$7:$BJ$7,E$29,'Scenario calc'!$C$22:$BJ$22) -> 270614.74 | F30: =SUMIF('Scenario calc'!$C$7:$BJ$7,F$29,'Scenario calc'!$C$22:$BJ$22) -> 273320.89
A31: Base | B31: =SUMIF('Scenario calc'!$C$127:$BJ$127,B$29,'Scenario calc'!$C$142:$BJ$142) -> 274944.26 | C31: =SUMIF('Scenario calc'!$C$127:$BJ$127,C$29,'Scenario calc'!$C$142:$BJ$142) -> 396826.24 | D31: =SUMIF('Scenario calc'!$C$127:$BJ$127,D$29,'Scenario calc'!$C$142:$BJ$142) -> 416905.65 | E31: =SUMIF('Scenario calc'!$C$127:$BJ$127,E$29,'Scenario calc'!$C$142:$BJ$142) -> 438001.08 | F31: =SUMIF('Scenario calc'!$C$127:$BJ$127,F$29,'Scenario calc'!$C$142:$BJ$142) -> 460163.93
A32: High | B32: =SUMIF('Scenario calc'!$C$247:$BJ$247,B$29,'Scenario calc'!$C$262:$BJ$262) -> 386298.5 | C32: =SUMIF('Scenario calc'!$C$247:$BJ$247,C$29,'Scenario calc'!$C$262:$BJ$262) -> 506052.02 | D32: =SUMIF('Scenario calc'!$C$247:$BJ$247,D$29,'Scenario calc'!$C$262:$BJ$262) -> 542082.92 | E32: =SUMIF('Scenario calc'!$C$247:$BJ$247,E$29,'Scenario calc'!$C$262:$BJ$262) -> 580679.23 | F32: =SUMIF('Scenario calc'!$C$247:$BJ$247,F$29,'Scenario calc'!$C$262:$BJ$262) -> 622023.59
A34: EBITDA by year ($'000)
A35: Scenario | B35: 1 | C35: 2 | D35: 3 | E35: 4 | F35: 5
A36: Low | B36: =SUMIF('Scenario calc'!$C$7:$BJ$7,B$35,'Scenario calc'!$C$44:$BJ$44) -> -94231.305 | C36: =SUMIF('Scenario calc'!$C$7:$BJ$7,C$35,'Scenario calc'!$C$44:$BJ$44) -> -25252.574 | D36: =SUMIF('Scenario calc'!$C$7:$BJ$7,D$35,'Scenario calc'!$C$44:$BJ$44) -> -26169.782 | E36: =SUMIF('Scenario calc'!$C$7:$BJ$7,E$35,'Scenario calc'!$C$44:$BJ$44) -> -30503.789 | F36: =SUMIF('Scenario calc'!$C$7:$BJ$7,F$35,'Scenario calc'!$C$44:$BJ$44) -> -35973.656
A37: Base | B37: =SUMIF('Scenario calc'!$C$127:$BJ$127,B$35,'Scenario calc'!$C$164:$BJ$164) -> 10242.544 | C37: =SUMIF('Scenario calc'!$C$127:$BJ$127,C$35,'Scenario calc'!$C$164:$BJ$164) -> 98400.063 | D37: =SUMIF('Scenario calc'!$C$127:$BJ$127,D$35,'Scenario calc'!$C$164:$BJ$164) -> 110686.04 | E37: =SUMIF('Scenario calc'!$C$127:$BJ$127,E$35,'Scenario calc'!$C$164:$BJ$164) -> 122982.92 | F37: =SUMIF('Scenario calc'!$C$127:$BJ$127,F$35,'Scenario calc'!$C$164:$BJ$164) -> 135438.9
A38: High | B38: =SUMIF('Scenario calc'!$C$247:$BJ$247,B$35,'Scenario calc'!$C$284:$BJ$284) -> 111794.82 | C38: =SUMIF('Scenario calc'!$C$247:$BJ$247,C$35,'Scenario calc'!$C$284:$BJ$284) -> 203324.39 | D38: =SUMIF('Scenario calc'!$C$247:$BJ$247,D$35,'Scenario calc'!$C$284:$BJ$284) -> 228679.04 | E38: =SUMIF('Scenario calc'!$C$247:$BJ$247,E$35,'Scenario calc'!$C$284:$BJ$284) -> 255803.93 | F38: =SUMIF('Scenario calc'!$C$247:$BJ$247,F$35,'Scenario calc'!$C$284:$BJ$284) -> 284860.42
A40: Net income by year ($'000)
A41: Scenario | B41: 1 | C41: 2 | D41: 3 | E41: 4 | F41: 5
A42: Low | B42: =SUMIF('Scenario calc'!$C$7:$BJ$7,B$41,'Scenario calc'!$C$53:$BJ$53) -> -174980.66 | C42: =SUMIF('Scenario calc'!$C$7:$BJ$7,C$41,'Scenario calc'!$C$53:$BJ$53) -> -106061.97 | D42: =SUMIF('Scenario calc'!$C$7:$BJ$7,D$41,'Scenario calc'!$C$53:$BJ$53) -> -107023.78 | E42: =SUMIF('Scenario calc'!$C$7:$BJ$7,E$41,'Scenario calc'!$C$53:$BJ$53) -> -111385.02 | F42: =SUMIF('Scenario calc'!$C$7:$BJ$7,F$41,'Scenario calc'!$C$53:$BJ$53) -> -116862.68
A43: Base | B43: =SUMIF('Scenario calc'!$C$127:$BJ$127,B$41,'Scenario calc'!$C$173:$BJ$173) -> -70506.807 | C43: =SUMIF('Scenario calc'!$C$127:$BJ$127,C$41,'Scenario calc'!$C$173:$BJ$173) -> 17593.913 | D43: =SUMIF('Scenario calc'!$C$127:$BJ$127,D$41,'Scenario calc'!$C$173:$BJ$173) -> 29844.776 | E43: =SUMIF('Scenario calc'!$C$127:$BJ$127,E$41,'Scenario calc'!$C$173:$BJ$173) -> 38127.44 | F43: =SUMIF('Scenario calc'!$C$127:$BJ$127,F$41,'Scenario calc'!$C$173:$BJ$173) -> 43135.578
A44: High | B44: =SUMIF('Scenario calc'!$C$247:$BJ$247,B$41,'Scenario calc'!$C$293:$BJ$293) -> 24525.921 | C44: =SUMIF('Scenario calc'!$C$247:$BJ$247,C$41,'Scenario calc'!$C$293:$BJ$293) -> 96790.692 | D44: =SUMIF('Scenario calc'!$C$247:$BJ$247,D$41,'Scenario calc'!$C$293:$BJ$293) -> 116796.85 | E44: =SUMIF('Scenario calc'!$C$247:$BJ$247,E$41,'Scenario calc'!$C$293:$BJ$293) -> 138223.04 | F44: =SUMIF('Scenario calc'!$C$247:$BJ$247,F$41,'Scenario calc'!$C$293:$BJ$293) -> 161198.89
A46: Cash at year end by year ($'000)
A47: Scenario | B47: 1 | C47: 2 | D47: 3 | E47: 4 | F47: 5
A48: Low | B48: =INDEX('Scenario calc'!$C$91:$BJ$91,B$47*12) -> -75555.877 | C48: =INDEX('Scenario calc'!$C$91:$BJ$91,C$47*12) -> -152059 | D48: =INDEX('Scenario calc'!$C$91:$BJ$91,D$47*12) -> -230146.72 | E48: =INDEX('Scenario calc'!$C$91:$BJ$91,E$47*12) -> -312948.89 | F48: =INDEX('Scenario calc'!$C$91:$BJ$91,F$47*12) -> -401616.61
A49: Base | B49: =INDEX('Scenario calc'!$C$211:$BJ$211,B$47*12) -> 28478.002 | C49: =INDEX('Scenario calc'!$C$211:$BJ$211,C$47*12) -> 75366.718 | D49: =INDEX('Scenario calc'!$C$211:$BJ$211,D$47*12) -> 134269.6 | E49: =INDEX('Scenario calc'!$C$211:$BJ$211,E$47*12) -> 201186.34 | F49: =INDEX('Scenario calc'!$C$211:$BJ$211,F$47*12) -> 272807.53
A50: High | B50: =INDEX('Scenario calc'!$C$331:$BJ$331,B$47*12) -> 122676.78 | C50: =INDEX('Scenario calc'!$C$331:$BJ$331,C$47*12) -> 248748.53 | D50: =INDEX('Scenario calc'!$C$331:$BJ$331,D$47*12) -> 394628.42 | E50: =INDEX('Scenario calc'!$C$331:$BJ$331,E$47*12) -> 561703.4 | F50: =INDEX('Scenario calc'!$C$331:$BJ$331,F$47*12) -> 751487.19

Sheet Break-even
A1: Startup costs, funding need and break-even | H1: =HYPERLINK("#'Cover'!A1","◂ Contents") -> ◂ Contents
A2: Live for the selected scenario. Periods are counted in months from the start of the plan.
A3: Scenario shown | B3: =CHOOSE(Dashboard!$B$4,"Low","Base","High") -> Base
A5: Startup costs & funding need (up to the lowest cash point)
A6: Lowest cash point (month #) | B6: =MATCH(MIN(Monthly!$C$89:$BJ$89),Monthly!$C$89:$BJ$89,0) -> 5
A7: Capital spending up to the lowest cash point | B7: =SUMPRODUCT(--(Monthly!$C$4:$BJ$4<=$B$6),Monthly!$C$59:$BJ$59) -> 868750
A8: Operating cash burn up to the lowest cash point | B8: =-SUMPRODUCT(--(Monthly!$C$4:$BJ$4<=$B$6),Monthly!$C$83:$BJ$83) -> 35223.235 | D8: Losses and working capital before the business funds itself
A9: Loan repayments up to the lowest cash point | B9: =-SUMPRODUCT(--(Monthly!$C$4:$BJ$4<=$B$6),Monthly!$C$70:$BJ$70) -> 3122.3623
A10: Total uses of funds | B10: =B7+B8+B9 -> 907095.6
A11: Minimum cash buffer to keep | B11: =Inputs!$E$80 -> 39000 | D11: Input on the Inputs sheet
A12: Funding required (uses + buffer) | B12: =B10+B11 -> 946095.6
A14: Equity raised | B14: =Inputs!$E$65 -> 430000
A15: Loan drawn | B15: =Inputs!$E$66 -> 500000
A16: Total sources of funds | B16: =B14+B15 -> 930000
A17: Funding surplus / (shortfall) | B17: =B16-B12 -> -16095.597 | D17: Negative = raise at least this much more
A18: Lowest cash balance in the plan | B18: =MIN(Monthly!$C$89:$BJ$89) -> 22904.403 | D18: Equals sources minus uses
A20: Break-even timing
A21: First month with positive EBITDA (month #) | B21: =IFERROR(MATCH(1,Monthly!$C$90:$BJ$90,0),"Not within horizon") -> 6
A22: First month with positive net income (month #) | B22: =IFERROR(MATCH(1,Monthly!$C$93:$BJ$93,0),"Not within horizon") -> 8
A23: Cash invested paid back (month #) | B23: =IF(MIN(Monthly!$C$95:$BJ$95)>=0,"No investment to pay back",IFERROR(MATCH(1,Monthly!$C$97:$BJ$97,0),"Not within horizon")) -> Not within horizon | D23: Cumulative operating + investing cash flow back to zero
A25: Annual break-even revenue
A26: Year # | B26: 1 | C26: 2 | D26: 3 | E26: 4 | F26: 5
B27: Year 1 | C27: Year 2 | D27: Year 3 | E27: Year 4 | F27: Year 5
A28: Revenue | B28: =SUMIF(Monthly!$C$5:$BJ$5,B$26,Monthly!$C$20:$BJ$20) -> 274944.26 | C28: =SUMIF(Monthly!$C$5:$BJ$5,C$26,Monthly!$C$20:$BJ$20) -> 396826.24 | D28: =SUMIF(Monthly!$C$5:$BJ$5,D$26,Monthly!$C$20:$BJ$20) -> 416905.65 | E28: =SUMIF(Monthly!$C$5:$BJ$5,E$26,Monthly!$C$20:$BJ$20) -> 438001.08 | F28: =SUMIF(Monthly!$C$5:$BJ$5,F$26,Monthly!$C$20:$BJ$20) -> 460163.93
A29: Gross profit | B29: =SUMIF(Monthly!$C$5:$BJ$5,B$26,Monthly!$C$29:$BJ$29) -> 165763.81 | C29: =SUMIF(Monthly!$C$5:$BJ$5,C$26,Monthly!$C$29:$BJ$29) -> 262060.42 | D29: =SUMIF(Monthly!$C$5:$BJ$5,D$26,Monthly!$C$29:$BJ$29) -> 276491.91 | E29: =SUMIF(Monthly!$C$5:$BJ$5,E$26,Monthly!$C$29:$BJ$29) -> 291688.77 | F29: =SUMIF(Monthly!$C$5:$BJ$5,F$26,Monthly!$C$29:$BJ$29) -> 307690.79
A30: Gross margin (contribution) | B30: =IF(B28=0,0,B29/B28) -> 0.6028997 | C30: =IF(C28=0,0,C29/C28) -> 0.66039085 | D30: =IF(D28=0,0,D29/D28) -> 0.6632002 | E30: =IF(E28=0,0,E29/E28) -> 0.66595446 | F30: =IF(F28=0,0,F29/F28) -> 0.66865472
A31: Operating expenses (treated as fixed) | B31: =-SUMIF(Monthly!$C$5:$BJ$5,B$26,Monthly!$C$41:$BJ$41) -> 155521.27 | C31: =-SUMIF(Monthly!$C$5:$BJ$5,C$26,Monthly!$C$41:$BJ$41) -> 163660.36 | D31: =-SUMIF(Monthly!$C$5:$BJ$5,D$26,Monthly!$C$41:$BJ$41) -> 165805.87 | E31: =-SUMIF(Monthly!$C$5:$BJ$5,E$26,Monthly!$C$41:$BJ$41) -> 168705.86 | F31: =-SUMIF(Monthly!$C$5:$BJ$5,F$26,Monthly!$C$41:$BJ$41) -> 172251.88
A32: Break-even revenue (EBITDA = 0) | B32: =IF(B30>0,B31/B30,"n/a") -> 257955.45 | C32: =IF(C30>0,C31/C30,"n/a") -> 247823.48 | D32: =IF(D30>0,D31/D30,"n/a") -> 250008.77 | E32: =IF(E30>0,E31/E30,"n/a") -> 253329.42 | F32: =IF(F30>0,F31/F30,"n/a") -> 257609.61
A33: Margin of safety (revenue above break-even) | B33: =IF(AND(ISNUMBER(B32),B28>0),(B28-B32)/B28,"n/a") -> 0.06178999 | C33: =IF(AND(ISNUMBER(C32),C28>0),(C28-C32)/C28,"n/a") -> 0.37548617 | D33: =IF(AND(ISNUMBER(D32),D28>0),(D28-D32)/D28,"n/a") -> 0.4003229 | E33: =IF(AND(ISNUMBER(E32),E28>0),(E28-E32)/E28,"n/a") -> 0.42162375 | F33: =IF(AND(ISNUMBER(F32),F28>0),(F28-F32)/F28,"n/a") -> 0.44017861
A35: Simplification: cost of sales is treated as variable and operating expenses as fixed, so break-even revenue = operating expenses ÷ gross margin.

Sheet Valuation
A1: Discounted cash flow valuation | H1: =HYPERLINK("#'Cover'!A1","◂ Contents") -> ◂ Contents
A2: Enterprise value at the start of the plan, before the funding raised in period 1. Year-end discounting.
A3: Scenario shown | B3: =CHOOSE(Dashboard!$B$4,"Low","Base","High") -> Base
A5: Assumptions (active scenario, from the Inputs sheet)
A6: Discount rate (WACC) | B6: =Inputs!$E$83 -> 0.25
A7: Terminal growth rate | B7: =Inputs!$E$84 -> 0.02
A8: Exit multiple (EV ÷ final-year EBITDA) | B8: =Inputs!$E$85 -> 4
A9: Tax rate (for the interest tax shield) | B9: =Inputs!$E$77 -> 0.21
A10: Sensitivity step: WACC | B10: =Inputs!$E$86 -> 0.01
A11: Sensitivity step: terminal growth | B11: =Inputs!$E$87 -> 0.005
A13: Free cash flow by year
A14: Year # | B14: 1 | C14: 2 | D14: 3 | E14: 4 | F14: 5
B15: Year 1 | C15: Year 2 | D15: Year 3 | E15: Year 4 | F15: Year 5
A16: EBITDA | B16: =SUMIF(Monthly!$C$5:$BJ$5,B$14,Monthly!$C$42:$BJ$42) -> 10242.544 | C16: =SUMIF(Monthly!$C$5:$BJ$5,C$14,Monthly!$C$42:$BJ$42) -> 98400.063 | D16: =SUMIF(Monthly!$C$5:$BJ$5,D$14,Monthly!$C$42:$BJ$42) -> 110686.04 | E16: =SUMIF(Monthly!$C$5:$BJ$5,E$14,Monthly!$C$42:$BJ$42) -> 122982.92 | F16: =SUMIF(Monthly!$C$5:$BJ$5,F$14,Monthly!$C$42:$BJ$42) -> 135438.9
A17: Unlevered free cash flow | B17: =SUMIF(Monthly!$C$5:$BJ$5,B$14,Monthly!$C$98:$BJ$98) -> -866414.36 | C17: =SUMIF(Monthly!$C$5:$BJ$5,C$14,Monthly!$C$98:$BJ$98) -> 82112.474 | D17: =SUMIF(Monthly!$C$5:$BJ$5,D$14,Monthly!$C$98:$BJ$98) -> 94251.153 | E17: =SUMIF(Monthly!$C$5:$BJ$5,E$14,Monthly!$C$98:$BJ$98) -> 102398.53 | F17: =SUMIF(Monthly!$C$5:$BJ$5,F$14,Monthly!$C$98:$BJ$98) -> 107246.14
A18: Discount factor | B18: =1/(1+Inputs!$E$83)^B$14 -> 0.8 | C18: =1/(1+Inputs!$E$83)^C$14 -> 0.64 | D18: =1/(1+Inputs!$E$83)^D$14 -> 0.512 | E18: =1/(1+Inputs!$E$83)^E$14 -> 0.4096 | F18: =1/(1+Inputs!$E$83)^F$14 -> 0.32768
A19: Present value of free cash flow | B19: =B17*B18 -> -693131.49 | C19: =C17*C18 -> 52551.983 | D19: =D17*D18 -> 48256.591 | E19: =E17*E18 -> 41942.437 | F19: =F17*F18 -> 35142.417
A21: Enterprise value
B22: Perpetual growth | C22: Exit multiple
A23: Present value of the plan's free cash flows | B23: =SUM($B$19:$F$19) -> -515238.06 | C23: =B23 -> -515238.06
A24: Final-year free cash flow | final-year EBITDA | B24: =$F$17 -> 107246.14 | C24: =$F$16 -> 135438.9
A25: Terminal value at the end of year 5 | B25: =IF($B$6>$B$7,B24*(1+$B$7)/($B$6-$B$7),0) -> 475613.34 | C25: =C24*$B$8 -> 541755.62
A26: Present value of the terminal value | B26: =B25/(1+$B$6)^$F$14 -> 155848.98 | C26: =C25/(1+$B$6)^$F$14 -> 177522.48
A27: Enterprise value | B27: =B23+B26 -> -359389.08 | C27: =C23+C26 -> -337715.58
A28: Terminal value share of enterprise value | B28: =IF(B27<>0,B26/B27,0) -> -0.43364973 | C28: =IF(C27<>0,C26/C27,0) -> -0.52565677
A29: Cross-check: implied exit multiple | implied perpetual growth | B29: =IF(C24>0,B25/C24,"n/a") -> 3.5116449 | C29: =IF(C25+B24<>0,(C25*$B$6-B24)/(C25+B24),"n/a") -> 0.043440189
A30: Enterprise value — average of the two methods | B30: =AVERAGE(B27,C27) -> -348552.33
A32: Sensitivity: enterprise value (perpetual growth) by WACC and terminal growth
A33: WACC ↓ · terminal growth → | B33: =$B$7+(-2)*$B$11 -> 0.01 | C33: =$B$7+(-1)*$B$11 -> 0.015 | D33: =$B$7+(0)*$B$11 -> 0.02 | E33: =$B$7+(1)*$B$11 -> 0.025 | F33: =$B$7+(2)*$B$11 -> 0.03
A34: =$B$6+(-2)*$B$10 -> 0.23 | B34: =IF($A34>B$33,SUMPRODUCT($B$17:$F$17/(1+$A34)^$B$14:$F$14)+$F$17*(1+B$33)/($A34-B$33)/(1+$A34)^$F$14,"n/a") -> -341760.45 | C34: =IF($A34>C$33,SUMPRODUCT($B$17:$F$17/(1+$A34)^$B$14:$F$14)+$F$17*(1+C$33)/($A34-C$33)/(1+$A34)^$F$14,"n/a") -> -336807.43 | D34: =IF($A34>D$33,SUMPRODUCT($B$17:$F$17/(1+$A34)^$B$14:$F$14)+$F$17*(1+D$33)/($A34-D$33)/(1+$A34)^$F$14,"n/a") -> -331618.55 | E34: =IF($A34>E$33,SUMPRODUCT($B$17:$F$17/(1+$A34)^$B$14:$F$14)+$F$17*(1+E$33)/($A34-E$33)/(1+$A34)^$F$14,"n/a") -> -326176.55 | F34: =IF($A34>F$33,SUMPRODUCT($B$17:$F$17/(1+$A34)^$B$14:$F$14)+$F$17*(1+F$33)/($A34-F$33)/(1+$A34)^$F$14,"n/a") -> -320462.46
A35: =$B$6+(-1)*$B$10 -> 0.24 | B35: =IF($A35>B$33,SUMPRODUCT($B$17:$F$17/(1+$A35)^$B$14:$F$14)+$F$17*(1+B$33)/($A35-B$33)/(1+$A35)^$F$14,"n/a") -> -355345.5 | C35: =IF($A35>C$33,SUMPRODUCT($B$17:$F$17/(1+$A35)^$B$14:$F$14)+$F$17*(1+C$33)/($A35-C$33)/(1+$A35)^$F$14,"n/a") -> -350962.67 | D35: =IF($A35>D$33,SUMPRODUCT($B$17:$F$17/(1+$A35)^$B$14:$F$14)+$F$17*(1+D$33)/($A35-D$33)/(1+$A35)^$F$14,"n/a") -> -346380.62 | E35: =IF($A35>E$33,SUMPRODUCT($B$17:$F$17/(1+$A35)^$B$14:$F$14)+$F$17*(1+E$33)/($A35-E$33)/(1+$A35)^$F$14,"n/a") -> -341585.46 | F35: =IF($A35>F$33,SUMPRODUCT($B$17:$F$17/(1+$A35)^$B$14:$F$14)+$F$17*(1+F$33)/($A35-F$33)/(1+$A35)^$F$14,"n/a") -> -336561.95
A36: =$B$6+(0)*$B$10 -> 0.25 | B36: =IF($A36>B$33,SUMPRODUCT($B$17:$F$17/(1+$A36)^$B$14:$F$14)+$F$17*(1+B$33)/($A36-B$33)/(1+$A36)^$F$14,"n/a") -> -367347.06 | C36: =IF($A36>C$33,SUMPRODUCT($B$17:$F$17/(1+$A36)^$B$14:$F$14)+$F$17*(1+C$33)/($A36-C$33)/(1+$A36)^$F$14,"n/a") -> -363452.73 | D36: =IF($A36>D$33,SUMPRODUCT($B$17:$F$17/(1+$A36)^$B$14:$F$14)+$F$17*(1+D$33)/($A36-D$33)/(1+$A36)^$F$14,"n/a") -> -359389.08 | E36: =IF($A36>E$33,SUMPRODUCT($B$17:$F$17/(1+$A36)^$B$14:$F$14)+$F$17*(1+E$33)/($A36-E$33)/(1+$A36)^$F$14,"n/a") -> -355144.83 | F36: =IF($A36>F$33,SUMPRODUCT($B$17:$F$17/(1+$A36)^$B$14:$F$14)+$F$17*(1+F$33)/($A36-F$33)/(1+$A36)^$F$14,"n/a") -> -350707.65
A37: =$B$6+(1)*$B$10 -> 0.26 | B37: =IF($A37>B$33,SUMPRODUCT($B$17:$F$17/(1+$A37)^$B$14:$F$14)+$F$17*(1+B$33)/($A37-B$33)/(1+$A37)^$F$14,"n/a") -> -377965.91 | C37: =IF($A37>C$33,SUMPRODUCT($B$17:$F$17/(1+$A37)^$B$14:$F$14)+$F$17*(1+C$33)/($A37-C$33)/(1+$A37)^$F$14,"n/a") -> -374492.44 | D37: =IF($A37>D$33,SUMPRODUCT($B$17:$F$17/(1+$A37)^$B$14:$F$14)+$F$17*(1+D$33)/($A37-D$33)/(1+$A37)^$F$14,"n/a") -> -370874.25 | E37: =IF($A37>E$33,SUMPRODUCT($B$17:$F$17/(1+$A37)^$B$14:$F$14)+$F$17*(1+E$33)/($A37-E$33)/(1+$A37)^$F$14,"n/a") -> -367102.09 | F37: =IF($A37>F$33,SUMPRODUCT($B$17:$F$17/(1+$A37)^$B$14:$F$14)+$F$17*(1+F$33)/($A37-F$33)/(1+$A37)^$F$14,"n/a") -> -363165.92
A38: =$B$6+(2)*$B$10 -> 0.27 | B38: =IF($A38>B$33,SUMPRODUCT($B$17:$F$17/(1+$A38)^$B$14:$F$14)+$F$17*(1+B$33)/($A38-B$33)/(1+$A38)^$F$14,"n/a") -> -387371.64 | C38: =IF($A38>C$33,SUMPRODUCT($B$17:$F$17/(1+$A38)^$B$14:$F$14)+$F$17*(1+C$33)/($A38-C$33)/(1+$A38)^$F$14,"n/a") -> -384262.63 | D38: =IF($A38>D$33,SUMPRODUCT($B$17:$F$17/(1+$A38)^$B$14:$F$14)+$F$17*(1+D$33)/($A38-D$33)/(1+$A38)^$F$14,"n/a") -> -381029.25 | E38: =IF($A38>E$33,SUMPRODUCT($B$17:$F$17/(1+$A38)^$B$14:$F$14)+$F$17*(1+E$33)/($A38-E$33)/(1+$A38)^$F$14,"n/a") -> -377663.89 | F38: =IF($A38>F$33,SUMPRODUCT($B$17:$F$17/(1+$A38)^$B$14:$F$14)+$F$17*(1+F$33)/($A38-F$33)/(1+$A38)^$F$14,"n/a") -> -374158.32
A40: Free cash flow = operating cash flow + interest × (1 − tax rate) − capital spending. Cells marked n/a: WACC not above growth.

Sheet Sources & Uses
A1: Sources and uses of funds | E1: =HYPERLINK("#'Cover'!A1","◂ Contents") -> ◂ Contents
A2: Live for the selected scenario. Where the money comes from and where it goes in the period set below.
A3: Scenario shown | B3: =CHOOSE(Dashboard!$B$4,"Low","Base","High") -> Base
A5: Funding structure ($'000) — raised at the start of the plan
B6: Amount | C6: Share
A7: Equity | B7: =Inputs!$E$65 -> 430000 | C7: =IF($B$9=0,0,B7/$B$9) -> 0.46236559
A8: Debt (loan) | B8: =Inputs!$E$66 -> 500000 | C8: =IF($B$9=0,0,B8/$B$9) -> 0.53763441
A9: Total funding | B9: =B7+B8 -> 930000 | C9: =IF(B9=0,0,1) -> 1
A10: Gearing (debt ÷ equity) | B10: =IF(B7<=0,IF(B8>0,"n/a",0),B8/B7) -> 1.1627907 | D10: n/a: debt without positive equity
A11: Funding required by the plan (Break-even sheet) | B11: ='Break-even'!B12 -> 946095.6
A12: Funding surplus / (shortfall) | B12: ='Break-even'!B17 -> -16095.597
A14: ="Sources and uses of cash in the first "&$B$16&IF($B$16=1," month"," months")&" ($'000)" -> Sources and uses of cash in the first 12 months ($'000)
A15: Period covered (months from the start) | B15: 12 | D15: 1 to 60 (capped)
A16: Months used | B16: =MIN(60,MAX(1,ROUND(B15,0))) -> 12
A17: Sources | B17: Amount | C17: Share
A18: Equity raised | B18: =SUMPRODUCT(--(Monthly!$C$4:$BJ$4<=$B$16),Monthly!$C$85:$BJ$85) -> 430000 | C18: =IF($B$21=0,0,B18/$B$21) -> 0.46236559
A19: Loan drawdowns | B19: =SUMPRODUCT(--(Monthly!$C$4:$BJ$4<=$B$16),Monthly!$C$68:$BJ$68) -> 500000 | C19: =IF($B$21=0,0,B19/$B$21) -> 0.53763441
A20: Cash generated by operations | B20: =MAX(0,SUMPRODUCT(--(Monthly!$C$4:$BJ$4<=$B$16),Monthly!$C$83:$BJ$83)) -> 0 | C20: =IF($B$21=0,0,B20/$B$21) -> 0
A21: Total sources | B21: =SUM(B18:B20) -> 930000 | C21: =IF(B21=0,0,1) -> 1
A23: Uses | B23: Amount | C23: Share
A24: Cash used by operations | B24: =MAX(0,-SUMPRODUCT(--(Monthly!$C$4:$BJ$4<=$B$16),Monthly!$C$83:$BJ$83)) -> 19872.931 | C24: =IF($B$28=0,0,B24/$B$28) -> 0.021368743
A25: Capital spending | B25: =-SUMPRODUCT(--(Monthly!$C$4:$BJ$4<=$B$16),Monthly!$C$84:$BJ$84) -> 874000 | C25: =IF($B$28=0,0,B25/$B$28) -> 0.93978495
A26: Loan repayments | B26: =-SUMPRODUCT(--(Monthly!$C$4:$BJ$4<=$B$16),Monthly!$C$70:$BJ$70) -> 7649.067 | C26: =IF($B$28=0,0,B26/$B$28) -> 0.0082248032
A27: Cash at the end of the period | B27: =INDEX(Monthly!$C$89:$BJ$89,$B$16) -> 28478.002 | C27: =IF($B$28=0,0,B27/$B$28) -> 0.030621507
A28: Total uses | B28: =SUM(B24:B27) -> 930000 | C28: =IF(B28=0,0,1) -> 1
A29: Sources − uses (must be 0; opening cash is 0) | B29: =B21-B28 -> 0

Sheet KPIs
A1: KPIs & ratios | I1: =HYPERLINK("#'Cover'!A1","◂ Contents") -> ◂ Contents
A2: Guest house financial model (planning) — industry metrics and financial ratios for the active scenario
A4: Financial ratios
B5: 1 | C5: 2 | D5: 3 | E5: 4 | F5: 5 | G5: Target
A6: Revenue growth | B6: =IF(N('P&L'!A5)<=0,"n/a",'P&L'!B5/'P&L'!A5-1) -> n/a | C6: =IF(N('P&L'!B5)<=0,"n/a",'P&L'!C5/'P&L'!B5-1) -> 0.44329708 | D6: =IF(N('P&L'!C5)<=0,"n/a",'P&L'!D5/'P&L'!C5-1) -> 0.0506 | E6: =IF(N('P&L'!D5)<=0,"n/a",'P&L'!E5/'P&L'!D5-1) -> 0.0506 | F6: =IF(N('P&L'!E5)<=0,"n/a",'P&L'!F5/'P&L'!E5-1) -> 0.0506
A7: Gross margin | B7: =IF('P&L'!B5<=0,"n/a",'P&L'!B7/'P&L'!B5) -> 0.6028997 | C7: =IF('P&L'!C5<=0,"n/a",'P&L'!C7/'P&L'!C5) -> 0.66039085 | D7: =IF('P&L'!D5<=0,"n/a",'P&L'!D7/'P&L'!D5) -> 0.6632002 | E7: =IF('P&L'!E5<=0,"n/a",'P&L'!E7/'P&L'!E5) -> 0.66595446 | F7: =IF('P&L'!F5<=0,"n/a",'P&L'!F7/'P&L'!F5) -> 0.66865472
A8: EBITDA margin | B8: =IF('P&L'!B5<=0,"n/a",'P&L'!B19/'P&L'!B5) -> 0.037253166 | C8: =IF('P&L'!C5<=0,"n/a",'P&L'!C19/'P&L'!C5) -> 0.24796763 | D8: =IF('P&L'!D5<=0,"n/a",'P&L'!D19/'P&L'!D5) -> 0.26549423 | E8: =IF('P&L'!E5<=0,"n/a",'P&L'!E19/'P&L'!E5) -> 0.28078222 | F8: =IF('P&L'!F5<=0,"n/a",'P&L'!F19/'P&L'!F5) -> 0.29432751
A9: Net margin | B9: =IF('P&L'!B5<=0,"n/a",'P&L'!B26/'P&L'!B5) -> -0.25644037 | C9: =IF('P&L'!C5<=0,"n/a",'P&L'!C26/'P&L'!C5) -> 0.044336566 | D9: =IF('P&L'!D5<=0,"n/a",'P&L'!D26/'P&L'!D5) -> 0.071586402 | E9: =IF('P&L'!E5<=0,"n/a",'P&L'!E26/'P&L'!E5) -> 0.087048736 | F9: =IF('P&L'!F5<=0,"n/a",'P&L'!F26/'P&L'!F5) -> 0.09373959
A10: Payroll, % of revenue | B10: =IF('P&L'!B5<=0,"n/a",-SUMIF(Headcount!$C$5:$BJ$5,B$5,Headcount!$C$17:$BJ$17)/'P&L'!B5) -> 0.4433626 | C10: =IF('P&L'!C5<=0,"n/a",-SUMIF(Headcount!$C$5:$BJ$5,C$5,Headcount!$C$17:$BJ$17)/'P&L'!C5) -> 0.31640296 | D10: =IF('P&L'!D5<=0,"n/a",-SUMIF(Headcount!$C$5:$BJ$5,D$5,Headcount!$C$17:$BJ$17)/'P&L'!D5) -> 0.31019898 | E10: =IF('P&L'!E5<=0,"n/a",-SUMIF(Headcount!$C$5:$BJ$5,E$5,Headcount!$C$17:$BJ$17)/'P&L'!E5) -> 0.30411665 | F10: =IF('P&L'!F5<=0,"n/a",-SUMIF(Headcount!$C$5:$BJ$5,F$5,Headcount!$C$17:$BJ$17)/'P&L'!F5) -> 0.29815358
A11: Marketing, % of revenue | B11: =IF('P&L'!B5<=0,"n/a",-'P&L'!B15/'P&L'!B5) -> 0.065467816 | C11: =IF('P&L'!C5<=0,"n/a",-'P&L'!C15/'P&L'!C5) -> 0.036287922 | D11: =IF('P&L'!D5<=0,"n/a",-'P&L'!D15/'P&L'!D5) -> 0.027632151 | E11: =IF('P&L'!E5<=0,"n/a",-'P&L'!E15/'P&L'!E5) -> 0.021041044 | F11: =IF('P&L'!F5<=0,"n/a",-'P&L'!F15/'P&L'!F5) -> 0.016022116
A12: Operating expenses, % of revenue | B12: =IF('P&L'!B5<=0,"n/a",-'P&L'!B18/'P&L'!B5) -> 0.56564653 | C12: =IF('P&L'!C5<=0,"n/a",-'P&L'!C18/'P&L'!C5) -> 0.41242322 | D12: =IF('P&L'!D5<=0,"n/a",-'P&L'!D18/'P&L'!D5) -> 0.39770597 | E12: =IF('P&L'!E5<=0,"n/a",-'P&L'!E18/'P&L'!E5) -> 0.38517224 | F12: =IF('P&L'!F5<=0,"n/a",-'P&L'!F18/'P&L'!F5) -> 0.37432721
A13: Current ratio (current assets ÷ current liabilities) | B13: =IF(('Balance Sheet'!B12-'Balance Sheet'!B11)<=0,"n/a",('Balance Sheet'!B5+'Balance Sheet'!B6+'Balance Sheet'!B7)/('Balance Sheet'!B12-'Balance Sheet'!B11)) -> 3.7865068 | C13: =IF(('Balance Sheet'!C12-'Balance Sheet'!C11)<=0,"n/a",('Balance Sheet'!C5+'Balance Sheet'!C6+'Balance Sheet'!C7)/('Balance Sheet'!C12-'Balance Sheet'!C11)) -> 8.9209842 | D13: =IF(('Balance Sheet'!D12-'Balance Sheet'!D11)<=0,"n/a",('Balance Sheet'!D5+'Balance Sheet'!D6+'Balance Sheet'!D7)/('Balance Sheet'!D12-'Balance Sheet'!D11)) -> 14.936239 | E13: =IF(('Balance Sheet'!E12-'Balance Sheet'!E11)<=0,"n/a",('Balance Sheet'!E5+'Balance Sheet'!E6+'Balance Sheet'!E7)/('Balance Sheet'!E12-'Balance Sheet'!E11)) -> 21.286689 | F13: =IF(('Balance Sheet'!F12-'Balance Sheet'!F11)<=0,"n/a",('Balance Sheet'!F5+'Balance Sheet'!F6+'Balance Sheet'!F7)/('Balance Sheet'!F12-'Balance Sheet'!F11)) -> 27.572228
A14: Debt ÷ equity (loan ÷ total equity) | B14: =IF('Balance Sheet'!B15<=0,"n/a",'Balance Sheet'!B11/'Balance Sheet'!B15) -> 1.3695696 | C14: =IF('Balance Sheet'!C15<=0,"n/a",'Balance Sheet'!C11/'Balance Sheet'!C15) -> 1.283918 | D14: =IF('Balance Sheet'!D15<=0,"n/a",'Balance Sheet'!D11/'Balance Sheet'!D15) -> 1.1681414 | E14: =IF('Balance Sheet'!E15<=0,"n/a",'Balance Sheet'!E11/'Balance Sheet'!E15) -> 1.046879 | F14: =IF('Balance Sheet'!F15<=0,"n/a",'Balance Sheet'!F11/'Balance Sheet'!F15) -> 0.93366556
A15: Return on assets (net income ÷ year-end assets) | B15: =IF('Balance Sheet'!B9<=0,"n/a",'P&L'!B26/'Balance Sheet'!B9) -> -0.081946723 | C15: =IF('Balance Sheet'!C9<=0,"n/a",'P&L'!C26/'Balance Sheet'!C9) -> 0.020219544 | D15: =IF('Balance Sheet'!D9<=0,"n/a",'P&L'!D26/'Balance Sheet'!D9) -> 0.033474663 | E15: =IF('Balance Sheet'!E9<=0,"n/a",'P&L'!E26/'Balance Sheet'!E9) -> 0.041413813 | F15: =IF('Balance Sheet'!F9<=0,"n/a",'P&L'!F26/'Balance Sheet'!F9) -> 0.045212114
A16: Return on equity (net income ÷ year-end equity) | B16: =IF('Balance Sheet'!B15<=0,"n/a",'P&L'!B26/'Balance Sheet'!B15) -> -0.19612835 | C16: =IF('Balance Sheet'!C15<=0,"n/a",'P&L'!C26/'Balance Sheet'!C15) -> 0.046657424 | D16: =IF('Balance Sheet'!D15<=0,"n/a",'P&L'!D26/'Balance Sheet'!D15) -> 0.073340962 | E16: =IF('Balance Sheet'!E15<=0,"n/a",'P&L'!E26/'Balance Sheet'!E15) -> 0.085668221 | F16: =IF('Balance Sheet'!F15<=0,"n/a",'P&L'!F26/'Balance Sheet'!F15) -> 0.08835729
A18: DuPont analysis — return on equity = net margin × asset turnover × equity multiplier
B19: 1 | C19: 2 | D19: 3 | E19: 4 | F19: 5
A20: Net margin | B20: =IF('P&L'!B5<=0,"n/a",'P&L'!B26/'P&L'!B5) -> -0.25644037 | C20: =IF('P&L'!C5<=0,"n/a",'P&L'!C26/'P&L'!C5) -> 0.044336566 | D20: =IF('P&L'!D5<=0,"n/a",'P&L'!D26/'P&L'!D5) -> 0.071586402 | E20: =IF('P&L'!E5<=0,"n/a",'P&L'!E26/'P&L'!E5) -> 0.087048736 | F20: =IF('P&L'!F5<=0,"n/a",'P&L'!F26/'P&L'!F5) -> 0.09373959
A21: × Asset turnover (revenue ÷ assets) | B21: =IF('Balance Sheet'!B9<=0,"n/a",'P&L'!B5/'Balance Sheet'!B9) -> 0.31955469 | C21: =IF('Balance Sheet'!C9<=0,"n/a",'P&L'!C5/'Balance Sheet'!C9) -> 0.45604669 | D21: =IF('Balance Sheet'!D9<=0,"n/a",'P&L'!D5/'Balance Sheet'!D9) -> 0.46761204 | E21: =IF('Balance Sheet'!E9<=0,"n/a",'P&L'!E5/'Balance Sheet'!E9) -> 0.47575433 | F21: =IF('Balance Sheet'!F9<=0,"n/a",'P&L'!F5/'Balance Sheet'!F9) -> 0.48231611
A22: × Equity multiplier (assets ÷ equity) | B22: =IF('Balance Sheet'!B15<=0,"n/a",'Balance Sheet'!B9/'Balance Sheet'!B15) -> 2.3933642 | C22: =IF('Balance Sheet'!C15<=0,"n/a",'Balance Sheet'!C9/'Balance Sheet'!C15) -> 2.3075408 | D22: =IF('Balance Sheet'!D15<=0,"n/a",'Balance Sheet'!D9/'Balance Sheet'!D15) -> 2.1909395 | E22: =IF('Balance Sheet'!E15<=0,"n/a",'Balance Sheet'!E9/'Balance Sheet'!E15) -> 2.0685905 | F22: =IF('Balance Sheet'!F15<=0,"n/a",'Balance Sheet'!F9/'Balance Sheet'!F15) -> 1.9542835
A23: Return on equity (product of the three) | B23: =IF(AND(ISNUMBER(B20),ISNUMBER(B21),ISNUMBER(B22)),B20*B21*B22,"n/a") -> -0.19612835 | C23: =IF(AND(ISNUMBER(C20),ISNUMBER(C21),ISNUMBER(C22)),C20*C21*C22,"n/a") -> 0.046657424 | D23: =IF(AND(ISNUMBER(D20),ISNUMBER(D21),ISNUMBER(D22)),D20*D21*D22,"n/a") -> 0.073340962 | E23: =IF(AND(ISNUMBER(E20),ISNUMBER(E21),ISNUMBER(E22)),E20*E21*E22,"n/a") -> 0.085668221 | F23: =IF(AND(ISNUMBER(F20),ISNUMBER(F21),ISNUMBER(F22)),F20*F21*F22,"n/a") -> 0.08835729
A24: Check: product − return on equity (must be 0) | B24: =IF(AND(ISNUMBER(B23),ISNUMBER(B16)),B23-B16,IF(ISNUMBER(B23),1,IF(AND(ISNUMBER(B16),ISNUMBER(B20),ISNUMBER(B21)),1,0))) -> 0 | C24: =IF(AND(ISNUMBER(C23),ISNUMBER(C16)),C23-C16,IF(ISNUMBER(C23),1,IF(AND(ISNUMBER(C16),ISNUMBER(C20),ISNUMBER(C21)),1,0))) -> 0 | D24: =IF(AND(ISNUMBER(D23),ISNUMBER(D16)),D23-D16,IF(ISNUMBER(D23),1,IF(AND(ISNUMBER(D16),ISNUMBER(D20),ISNUMBER(D21)),1,0))) -> 0 | E24: =IF(AND(ISNUMBER(E23),ISNUMBER(E16)),E23-E16,IF(ISNUMBER(E23),1,IF(AND(ISNUMBER(E16),ISNUMBER(E20),ISNUMBER(E21)),1,0))) -> 0 | F24: =IF(AND(ISNUMBER(F23),ISNUMBER(F16)),F23-F16,IF(ISNUMBER(F23),1,IF(AND(ISNUMBER(F16),ISNUMBER(F20),ISNUMBER(F21)),1,0))) -> 0
A26: Guest house metrics ($'000; per-unit rows in $)
A27: Year # | B27: 1 | C27: 2 | D27: 3 | E27: 4 | F27: 5
B28: Year 1 | C28: Year 2 | D28: Year 3 | E28: Year 4 | F28: Year 5 | G28: Target
A29: Available room-nights | B29: =SUMIF(Monthly!$C$5:$BJ$5,B$27,Monthly!$C$11:$BJ$11) -> 3648 | C29: =SUMIF(Monthly!$C$5:$BJ$5,C$27,Monthly!$C$11:$BJ$11) -> 3648 | D29: =SUMIF(Monthly!$C$5:$BJ$5,D$27,Monthly!$C$11:$BJ$11) -> 3648 | E29: =SUMIF(Monthly!$C$5:$BJ$5,E$27,Monthly!$C$11:$BJ$11) -> 3648 | F29: =SUMIF(Monthly!$C$5:$BJ$5,F$27,Monthly!$C$11:$BJ$11) -> 3648
A30: Occupied room-nights | B30: =SUMIF(Monthly!$C$5:$BJ$5,B$27,Monthly!$C$13:$BJ$13) -> 1646.3728 | C30: =SUMIF(Monthly!$C$5:$BJ$5,C$27,Monthly!$C$13:$BJ$13) -> 2306.9952 | D30: =SUMIF(Monthly!$C$5:$BJ$5,D$27,Monthly!$C$13:$BJ$13) -> 2353.1351 | E30: =SUMIF(Monthly!$C$5:$BJ$5,E$27,Monthly!$C$13:$BJ$13) -> 2400.1978 | F30: =SUMIF(Monthly!$C$5:$BJ$5,F$27,Monthly!$C$13:$BJ$13) -> 2448.2018
A31: Occupancy | B31: =IF(B29=0,0,B30/B29) -> 0.45130833 | C31: =IF(C29=0,0,C30/C29) -> 0.6324 | D31: =IF(D29=0,0,D30/D29) -> 0.645048 | E31: =IF(E29=0,0,E30/E29) -> 0.65794896 | F31: =IF(F29=0,0,F30/F29) -> 0.67110794
A32: Guest stays | B32: =SUMIF(Monthly!$C$5:$BJ$5,B$27,Monthly!$C$14:$BJ$14) -> 748.35127 | C32: =SUMIF(Monthly!$C$5:$BJ$5,C$27,Monthly!$C$14:$BJ$14) -> 1048.6342 | D32: =SUMIF(Monthly!$C$5:$BJ$5,D$27,Monthly!$C$14:$BJ$14) -> 1069.6069 | E32: =SUMIF(Monthly!$C$5:$BJ$5,E$27,Monthly!$C$14:$BJ$14) -> 1090.999 | F32: =SUMIF(Monthly!$C$5:$BJ$5,F$27,Monthly!$C$14:$BJ$14) -> 1112.819
A33: Revenue | B33: =SUMIF(Monthly!$C$5:$BJ$5,B$27,Monthly!$C$20:$BJ$20) -> 274944.26 | C33: =SUMIF(Monthly!$C$5:$BJ$5,C$27,Monthly!$C$20:$BJ$20) -> 396826.24 | D33: =SUMIF(Monthly!$C$5:$BJ$5,D$27,Monthly!$C$20:$BJ$20) -> 416905.65 | E33: =SUMIF(Monthly!$C$5:$BJ$5,E$27,Monthly!$C$20:$BJ$20) -> 438001.08 | F33: =SUMIF(Monthly!$C$5:$BJ$5,F$27,Monthly!$C$20:$BJ$20) -> 460163.93
A34: Room revenue | B34: =SUMIF(Monthly!$C$5:$BJ$5,B$27,Monthly!$C$18:$BJ$18) -> 255187.78 | C34: =SUMIF(Monthly!$C$5:$BJ$5,C$27,Monthly!$C$18:$BJ$18) -> 368311.78 | D34: =SUMIF(Monthly!$C$5:$BJ$5,D$27,Monthly!$C$18:$BJ$18) -> 386948.36 | E34: =SUMIF(Monthly!$C$5:$BJ$5,E$27,Monthly!$C$18:$BJ$18) -> 406527.95 | F34: =SUMIF(Monthly!$C$5:$BJ$5,F$27,Monthly!$C$18:$BJ$18) -> 427098.26
A35: Breakfast & extras revenue | B35: =SUMIF(Monthly!$C$5:$BJ$5,B$27,Monthly!$C$19:$BJ$19) -> 19756.474 | C35: =SUMIF(Monthly!$C$5:$BJ$5,C$27,Monthly!$C$19:$BJ$19) -> 28514.461 | D35: =SUMIF(Monthly!$C$5:$BJ$5,D$27,Monthly!$C$19:$BJ$19) -> 29957.292 | E35: =SUMIF(Monthly!$C$5:$BJ$5,E$27,Monthly!$C$19:$BJ$19) -> 31473.131 | F35: =SUMIF(Monthly!$C$5:$BJ$5,F$27,Monthly!$C$19:$BJ$19) -> 33065.672
A36: Extras share of revenue | B36: =IF(B33=0,0,B35/B33) -> 0.071856287 | C36: =IF(C33=0,0,C35/C33) -> 0.071856287 | D36: =IF(D33=0,0,D35/D33) -> 0.071856287 | E36: =IF(E33=0,0,E35/E33) -> 0.071856287 | F36: =IF(F33=0,0,F35/F33) -> 0.071856287
A37: Average daily rate (room revenue ÷ occupied room-nights) ($) | B37: =IF(B30=0,0,B34/B30) -> 155 | C37: =IF(C30=0,0,C34/C30) -> 159.65 | D37: =IF(D30=0,0,D34/D30) -> 164.4395 | E37: =IF(E30=0,0,E34/E30) -> 169.37268 | F37: =IF(F30=0,0,F34/F30) -> 174.45387
A38: RevPAR (room revenue ÷ available room-nights) ($) | B38: =IF(B29=0,0,B34/B29) -> 69.952792 | C38: =IF(C29=0,0,C34/C29) -> 100.96266 | D38: =IF(D29=0,0,D34/D29) -> 106.07137 | E38: =IF(E29=0,0,E34/E29) -> 111.43858 | F38: =IF(F29=0,0,F34/F29) -> 117.07737
A39: Total revenue per available room-night ($) | B39: =IF(B29=0,0,B33/B29) -> 75.368492 | C39: =IF(C29=0,0,C33/C29) -> 108.77912 | D39: =IF(D29=0,0,D33/D29) -> 114.28335 | E39: =IF(E29=0,0,E33/E29) -> 120.06609 | F39: =IF(F29=0,0,F33/F29) -> 126.14143
A40: Revenue per stay ($) | B40: =IF(B32=0,0,B33/B32) -> 367.4 | C40: =IF(C32=0,0,C33/C32) -> 378.422 | D40: =IF(D32=0,0,D33/D32) -> 389.77466 | E40: =IF(E32=0,0,E33/E32) -> 401.4679 | F40: =IF(F32=0,0,F33/F32) -> 413.51194
A41: Gross profit | B41: =SUMIF(Monthly!$C$5:$BJ$5,B$27,Monthly!$C$29:$BJ$29) -> 165763.81 | C41: =SUMIF(Monthly!$C$5:$BJ$5,C$27,Monthly!$C$29:$BJ$29) -> 262060.42 | D41: =SUMIF(Monthly!$C$5:$BJ$5,D$27,Monthly!$C$29:$BJ$29) -> 276491.91 | E41: =SUMIF(Monthly!$C$5:$BJ$5,E$27,Monthly!$C$29:$BJ$29) -> 291688.77 | F41: =SUMIF(Monthly!$C$5:$BJ$5,F$27,Monthly!$C$29:$BJ$29) -> 307690.79
A42: Gross margin | B42: =IF(B33=0,0,B41/B33) -> 0.6028997 | C42: =IF(C33=0,0,C41/C33) -> 0.66039085 | D42: =IF(D33=0,0,D41/D33) -> 0.6632002 | E42: =IF(E33=0,0,E41/E33) -> 0.66595446 | F42: =IF(F33=0,0,F41/F33) -> 0.66865472
A43: EBITDA | B43: =SUMIF(Monthly!$C$5:$BJ$5,B$27,Monthly!$C$42:$BJ$42) -> 10242.544 | C43: =SUMIF(Monthly!$C$5:$BJ$5,C$27,Monthly!$C$42:$BJ$42) -> 98400.063 | D43: =SUMIF(Monthly!$C$5:$BJ$5,D$27,Monthly!$C$42:$BJ$42) -> 110686.04 | E43: =SUMIF(Monthly!$C$5:$BJ$5,E$27,Monthly!$C$42:$BJ$42) -> 122982.92 | F43: =SUMIF(Monthly!$C$5:$BJ$5,F$27,Monthly!$C$42:$BJ$42) -> 135438.9
A44: EBITDA margin | B44: =IF(B33=0,0,B43/B33) -> 0.037253166 | C44: =IF(C33=0,0,C43/C33) -> 0.24796763 | D44: =IF(D33=0,0,D43/D33) -> 0.26549423 | E44: =IF(E33=0,0,E43/E33) -> 0.28078222 | F44: =IF(F33=0,0,F43/F33) -> 0.29432751

Sheet Inputs
A1: Inputs — Low / Base / High | I1: =HYPERLINK("#'Cover'!A1","◂ Contents") -> ◂ Contents
A2: Illustrative assumptions - replace them with your own numbers.
A5: Driver | B5: Low | C5: Base | D5: High | E5: Active | F5: Unit | G5: Source / comment
A6: Rooms & occupancy
A7: Lettable rooms | B7: 10 | C7: 10 | D7: 10 | E7: =CHOOSE(Dashboard!$B$4,B7,C7,D7) -> 10 | F7: rooms
A8: Average occupancy at maturity, % of room-nights (year 1) | B8: 0.5 | C8: 0.62 | D8: 0.7 | E8: =CHOOSE(Dashboard!$B$4,B8,C8,D8) -> 0.62 | F8: % | G8: Low ≤ Base ≤ High
A9: Occupancy growth per year (capped at 100%) | B9: 0 | C9: 0.02 | D9: 0.03 | E9: =CHOOSE(Dashboard!$B$4,B9,C9,D9) -> 0.02 | F9: % | G9: Low ≤ Base ≤ High
A10: Months to reach mature occupancy (0 = already mature) | B10: 14 | C10: 10 | D10: 8 | E10: =CHOOSE(Dashboard!$B$4,B10,C10,D10) -> 10 | F10: months | G10: Low ≥ Base ≥ High (lower is better)
A11: Occupancy in month 1, % of mature | B11: 0.3 | C11: 0.4 | D11: 0.5 | E11: =CHOOSE(Dashboard!$B$4,B11,C11,D11) -> 0.4 | F11: % | G11: Low ≤ Base ≤ High
A12: Peak-season uplift, June-August (monthly models) | B12: 0.25 | C12: 0.25 | D12: 0.25 | E12: =CHOOSE(Dashboard!$B$4,B12,C12,D12) -> 0.25 | F12: %
A13: Calendar nights per month | B13: 30.4 | C13: 30.4 | D13: 30.4 | E13: =CHOOSE(Dashboard!$B$4,B13,C13,D13) -> 30.4 | F13: nights
A14: Average length of stay | B14: 1.8 | C14: 2.2 | D14: 2.6 | E14: =CHOOSE(Dashboard!$B$4,B14,C14,D14) -> 2.2 | F14: nights | G14: Low ≤ Base ≤ High
A16: Rates & extras
A17: Average daily rate per occupied room (year 1) | B17: 135 | C17: 155 | D17: 170 | E17: =CHOOSE(Dashboard!$B$4,B17,C17,D17) -> 155 | F17: $ | G17: Low ≤ Base ≤ High
A18: Rate increase per year (rooms and extras) | B18: 0.01 | C18: 0.03 | D18: 0.04 | E18: =CHOOSE(Dashboard!$B$4,B18,C18,D18) -> 0.03 | F18: % | G18: Low ≤ Base ≤ High
A19: Breakfast & extras revenue per occupied room-night (year 1) | B19: 9 | C19: 12 | D19: 15 | E19: =CHOOSE(Dashboard!$B$4,B19,C19,D19) -> 12 | F19: $ | G19: Low ≤ Base ≤ High
A21: Cost of sales
A22: Breakfast & extras cost, % of that revenue | B22: 0.55 | C22: 0.5 | D22: 0.45 | E22: =CHOOSE(Dashboard!$B$4,B22,C22,D22) -> 0.5 | F22: % | G22: Low ≥ Base ≥ High (lower is better)
A23: Cleaning & linen per stay (year 1) | B23: 26 | C23: 22 | D23: 19 | E23: =CHOOSE(Dashboard!$B$4,B23,C23,D23) -> 22 | F23: $ | G23: Low ≥ Base ≥ High (lower is better)
A24: Guest supplies per occupied room-night (year 1) | B24: 5 | C24: 4 | D24: 3.5 | E24: =CHOOSE(Dashboard!$B$4,B24,C24,D24) -> 4 | F24: $ | G24: Low ≥ Base ≥ High (lower is better)
A25: Share of room revenue booked through OTAs | B25: 0.65 | C25: 0.55 | D25: 0.45 | E25: =CHOOSE(Dashboard!$B$4,B25,C25,D25) -> 0.55 | F25: % | G25: Low ≥ Base ≥ High (lower is better)
A26: OTA / booking commission, % of OTA room revenue | B26: 0.17 | C26: 0.15 | D26: 0.14 | E26: =CHOOSE(Dashboard!$B$4,B26,C26,D26) -> 0.15 | F26: % | G26: Low ≥ Base ≥ High (lower is better)
A28: Property costs
A29: Building rent per month (0 = owned property) | B29: 0 | C29: 0 | D29: 0 | E29: =CHOOSE(Dashboard!$B$4,B29,C29,D29) -> 0 | F29: $
A30: Rent increase per year | B30: 0.03 | C30: 0.03 | D30: 0.03 | E30: =CHOOSE(Dashboard!$B$4,B30,C30,D30) -> 0.03 | F30: %
A31: Property tax per year (0 if leased or included in rent) | B31: 8000 | C31: 8000 | D31: 8000 | E31: =CHOOSE(Dashboard!$B$4,B31,C31,D31) -> 8000 | F31: $
A32: Insurance (property, liability) per month | B32: 700 | C32: 700 | D32: 700 | E32: =CHOOSE(Dashboard!$B$4,B32,C32,D32) -> 700 | F32: $
A33: Utilities per month | B33: 1800 | C33: 1800 | D33: 1800 | E33: =CHOOSE(Dashboard!$B$4,B33,C33,D33) -> 1800 | F33: $
A34: Repairs & maintenance, % of revenue | B34: 0.05 | C34: 0.04 | D34: 0.035 | E34: =CHOOSE(Dashboard!$B$4,B34,C34,D34) -> 0.04 | F34: % | G34: Low ≥ Base ≥ High (lower is better)
A35: Software, accounting & other G&A per month | B35: 1200 | C35: 1200 | D35: 1200 | E35: =CHOOSE(Dashboard!$B$4,B35,C35,D35) -> 1200 | F35: $
A36: Marketing budget per month (year 1) | B36: 1500 | C36: 1500 | D36: 1500 | E36: =CHOOSE(Dashboard!$B$4,B36,C36,D36) -> 1500 | F36: $
A37: Marketing budget growth per year | B37: -0.3 | C37: -0.2 | D37: -0.1 | E37: =CHOOSE(Dashboard!$B$4,B37,C37,D37) -> -0.2 | F37: % | G37: Low ≤ Base ≤ High
A38: Card processing fees, % of revenue | B38: 0.03 | C38: 0.027 | D38: 0.025 | E38: =CHOOSE(Dashboard!$B$4,B38,C38,D38) -> 0.027 | F38: % | G38: Low ≥ Base ≥ High (lower is better)
A39: Cost increase per year (insurance, utilities, supplies, cleaning, tax) | B39: 0.04 | C39: 0.03 | D39: 0.025 | E39: =CHOOSE(Dashboard!$B$4,B39,C39,D39) -> 0.03 | F39: % | G39: Low ≥ Base ≥ High (lower is better)
A41: Capital spending
A42: Property purchase (month 1; 0 = leased building) | B42: 720000 | C42: 720000 | D42: 720000 | E42: =CHOOSE(Dashboard!$B$4,B42,C42,D42) -> 720000 | F42: $
A43: Land share of the property purchase (never depreciated) | B43: 0.25 | C43: 0.25 | D43: 0.25 | E43: =CHOOSE(Dashboard!$B$4,B43,C43,D43) -> 0.25 | F43: %
A44: Furnishing & bathroom fit-out per room (month 1) | B44: 7500 | C44: 7500 | D44: 7500 | E44: =CHOOSE(Dashboard!$B$4,B44,C44,D44) -> 7500 | F44: $
A45: Building works, kitchen, signage & systems (month 1) | B45: 70000 | C45: 70000 | D45: 70000 | E45: =CHOOSE(Dashboard!$B$4,B45,C45,D45) -> 70000 | F45: $
A46: FF&E replacement per room per year | B46: 900 | C46: 900 | D46: 900 | E46: =CHOOSE(Dashboard!$B$4,B46,C46,D46) -> 900 | F46: $
A48: Headcount
A49: Housekeeping staff: headcount (FTE) | B49: 1.5 | C49: 1.5 | D49: 1.5 | E49: =CHOOSE(Dashboard!$B$4,B49,C49,D49) -> 1.5 | F49: FTE | G49: Low ≤ Base ≤ High
A50: Housekeeping staff: salary per FTE per year | B50: 32000 | C50: 32000 | D50: 32000 | E50: =CHOOSE(Dashboard!$B$4,B50,C50,D50) -> 32000 | F50: $
A51: Housekeeping staff: headcount growth per year | B51: 0 | C51: 0 | D51: 0 | E51: =CHOOSE(Dashboard!$B$4,B51,C51,D51) -> 0 | F51: % | G51: Low ≤ Base ≤ High
A52: Housekeeping staff: first month on payroll | B52: 1 | C52: 1 | D52: 1 | E52: =CHOOSE(Dashboard!$B$4,B52,C52,D52) -> 1 | F52: month #
A53: Host, manager & front desk: headcount (FTE) | B53: 1 | C53: 1 | D53: 1 | E53: =CHOOSE(Dashboard!$B$4,B53,C53,D53) -> 1 | F53: FTE | G53: Low ≤ Base ≤ High
A54: Host, manager & front desk: salary per FTE per year | B54: 40000 | C54: 40000 | D54: 40000 | E54: =CHOOSE(Dashboard!$B$4,B54,C54,D54) -> 40000 | F54: $
A55: Host, manager & front desk: headcount growth per year | B55: 0 | C55: 0 | D55: 0 | E55: =CHOOSE(Dashboard!$B$4,B55,C55,D55) -> 0 | F55: % | G55: Low ≤ Base ≤ High
A56: Host, manager & front desk: first month on payroll | B56: 1 | C56: 1 | D56: 1 | E56: =CHOOSE(Dashboard!$B$4,B56,C56,D56) -> 1 | F56: month #
A57: Breakfast kitchen & maintenance: headcount (FTE) | B57: 0.6 | C57: 0.6 | D57: 0.6 | E57: =CHOOSE(Dashboard!$B$4,B57,C57,D57) -> 0.6 | F57: FTE | G57: Low ≤ Base ≤ High
A58: Breakfast kitchen & maintenance: salary per FTE per year | B58: 30000 | C58: 30000 | D58: 30000 | E58: =CHOOSE(Dashboard!$B$4,B58,C58,D58) -> 30000 | F58: $
A59: Breakfast kitchen & maintenance: headcount growth per year | B59: 0 | C59: 0 | D59: 0 | E59: =CHOOSE(Dashboard!$B$4,B59,C59,D59) -> 0 | F59: % | G59: Low ≤ Base ≤ High
A60: Breakfast kitchen & maintenance: first month on payroll | B60: 1 | C60: 1 | D60: 1 | E60: =CHOOSE(Dashboard!$B$4,B60,C60,D60) -> 1 | F60: month #
A61: Payroll taxes & benefits, % of salary | B61: 0.15 | C61: 0.15 | D61: 0.15 | E61: =CHOOSE(Dashboard!$B$4,B61,C61,D61) -> 0.15 | F61: %
A62: Wage growth per year | B62: 0.04 | C62: 0.03 | D62: 0.03 | E62: =CHOOSE(Dashboard!$B$4,B62,C62,D62) -> 0.03 | F62: %
A64: Funding
A65: Equity raised at start | B65: 430000 | C65: 430000 | D65: 430000 | E65: =CHOOSE(Dashboard!$B$4,B65,C65,D65) -> 430000 | F65: $
A66: Loan drawn at start | B66: 500000 | C66: 500000 | D66: 500000 | E66: =CHOOSE(Dashboard!$B$4,B66,C66,D66) -> 500000 | F66: $
A67: Loan interest rate per year | B67: 0.07 | C67: 0.07 | D67: 0.07 | E67: =CHOOSE(Dashboard!$B$4,B67,C67,D67) -> 0.07 | F67: %
A68: Loan repayment term | B68: 25 | C68: 25 | D68: 25 | E68: =CHOOSE(Dashboard!$B$4,B68,C68,D68) -> 25 | F68: years
A70: Working capital
A71: Customer payment terms (receivable days) | B71: 3 | C71: 3 | D71: 3 | E71: =CHOOSE(Dashboard!$B$4,B71,C71,D71) -> 3 | F71: days
A72: Inventory held (days of COGS) | B72: 3 | C72: 3 | D72: 3 | E72: =CHOOSE(Dashboard!$B$4,B72,C72,D72) -> 3 | F72: days
A73: Supplier payment terms (payable days) | B73: 25 | C73: 25 | D73: 25 | E73: =CHOOSE(Dashboard!$B$4,B73,C73,D73) -> 25 | F73: days
A75: Tax & depreciation
A76: Depreciation period for capex | B76: 15 | C76: 15 | D76: 15 | E76: =CHOOSE(Dashboard!$B$4,B76,C76,D76) -> 15 | F76: years
A77: Income tax rate | B77: 0.21 | C77: 0.21 | D77: 0.21 | E77: =CHOOSE(Dashboard!$B$4,B77,C77,D77) -> 0.21 | F77: %
A79: Break-even & funding
A80: Minimum cash buffer to keep | B80: 39000 | C80: 39000 | D80: 39000 | E80: =CHOOSE(Dashboard!$B$4,B80,C80,D80) -> 39000 | F80: $ | G80: About 3 months of costs
A82: Valuation
A83: Discount rate (WACC) | B83: 0.3 | C83: 0.25 | D83: 0.2 | E83: =CHOOSE(Dashboard!$B$4,B83,C83,D83) -> 0.25 | F83: % | G83: Low ≥ Base ≥ High (lower is better)
A84: Terminal growth rate (perpetuity) | B84: 0.01 | C84: 0.02 | D84: 0.03 | E84: =CHOOSE(Dashboard!$B$4,B84,C84,D84) -> 0.02 | F84: % | G84: Low ≤ Base ≤ High
A85: Exit multiple (EV ÷ final-year EBITDA) | B85: 3 | C85: 4 | D85: 5 | E85: =CHOOSE(Dashboard!$B$4,B85,C85,D85) -> 4 | F85: x | G85: Low ≤ Base ≤ High
A86: Sensitivity table: WACC step | B86: 0.01 | C86: 0.01 | D86: 0.01 | E86: =CHOOSE(Dashboard!$B$4,B86,C86,D86) -> 0.01 | F86: %
A87: Sensitivity table: growth step | B87: 0.005 | C87: 0.005 | D87: 0.005 | E87: =CHOOSE(Dashboard!$B$4,B87,C87,D87) -> 0.005 | F87: %
A89: Legend: yellow cell with blue figure = input you can change · black = formula · green = link to another sheet · grey = active value (column E follows the scenario on the Dashboard).

Sheet P&L
A1: Annual profit & loss | H1: =HYPERLINK("#'Cover'!A1","◂ Contents") -> ◂ Contents
A2: Rolled up from the period detail (SUMIF on the year row; balances at year end).
A3: Year # | B3: 1 | C3: 2 | D3: 3 | E3: 4 | F3: 5
B4: Year 1 | C4: Year 2 | D4: Year 3 | E4: Year 4 | F4: Year 5
A5: Revenue | B5: =SUMIF(Monthly!$C$5:$BJ$5,B$3,Monthly!$C$20:$BJ$20) -> 274944.26 | C5: =SUMIF(Monthly!$C$5:$BJ$5,C$3,Monthly!$C$20:$BJ$20) -> 396826.24 | D5: =SUMIF(Monthly!$C$5:$BJ$5,D$3,Monthly!$C$20:$BJ$20) -> 416905.65 | E5: =SUMIF(Monthly!$C$5:$BJ$5,E$3,Monthly!$C$20:$BJ$20) -> 438001.08 | F5: =SUMIF(Monthly!$C$5:$BJ$5,F$3,Monthly!$C$20:$BJ$20) -> 460163.93
A6: Cost of sales | B6: =SUMIF(Monthly!$C$5:$BJ$5,B$3,Monthly!$C$28:$BJ$28) -> -109180.45 | C6: =SUMIF(Monthly!$C$5:$BJ$5,C$3,Monthly!$C$28:$BJ$28) -> -134765.82 | D6: =SUMIF(Monthly!$C$5:$BJ$5,D$3,Monthly!$C$28:$BJ$28) -> -140413.74 | E6: =SUMIF(Monthly!$C$5:$BJ$5,E$3,Monthly!$C$28:$BJ$28) -> -146312.3 | F6: =SUMIF(Monthly!$C$5:$BJ$5,F$3,Monthly!$C$28:$BJ$28) -> -152473.15
A7: Gross profit | B7: =SUMIF(Monthly!$C$5:$BJ$5,B$3,Monthly!$C$29:$BJ$29) -> 165763.81 | C7: =SUMIF(Monthly!$C$5:$BJ$5,C$3,Monthly!$C$29:$BJ$29) -> 262060.42 | D7: =SUMIF(Monthly!$C$5:$BJ$5,D$3,Monthly!$C$29:$BJ$29) -> 276491.91 | E7: =SUMIF(Monthly!$C$5:$BJ$5,E$3,Monthly!$C$29:$BJ$29) -> 291688.77 | F7: =SUMIF(Monthly!$C$5:$BJ$5,F$3,Monthly!$C$29:$BJ$29) -> 307690.79
A8: Gross margin | B8: =IF(B5=0,0,B7/B5) -> 0.6028997 | C8: =IF(C5=0,0,C7/C5) -> 0.66039085 | D8: =IF(D5=0,0,D7/D5) -> 0.6632002 | E8: =IF(E5=0,0,E7/E5) -> 0.66595446 | F8: =IF(F5=0,0,F7/F5) -> 0.66865472
A9: Host, front desk, kitchen & maintenance payroll | B9: =SUMIF(Monthly!$C$5:$BJ$5,B$3,Monthly!$C$32:$BJ$32) -> -66700 | C9: =SUMIF(Monthly!$C$5:$BJ$5,C$3,Monthly!$C$32:$BJ$32) -> -68701 | D9: =SUMIF(Monthly!$C$5:$BJ$5,D$3,Monthly!$C$32:$BJ$32) -> -70762.03 | E9: =SUMIF(Monthly!$C$5:$BJ$5,E$3,Monthly!$C$32:$BJ$32) -> -72884.891 | F9: =SUMIF(Monthly!$C$5:$BJ$5,F$3,Monthly!$C$32:$BJ$32) -> -75071.438
A10: Building rent | B10: =SUMIF(Monthly!$C$5:$BJ$5,B$3,Monthly!$C$33:$BJ$33) -> 0 | C10: =SUMIF(Monthly!$C$5:$BJ$5,C$3,Monthly!$C$33:$BJ$33) -> 0 | D10: =SUMIF(Monthly!$C$5:$BJ$5,D$3,Monthly!$C$33:$BJ$33) -> 0 | E10: =SUMIF(Monthly!$C$5:$BJ$5,E$3,Monthly!$C$33:$BJ$33) -> 0 | F10: =SUMIF(Monthly!$C$5:$BJ$5,F$3,Monthly!$C$33:$BJ$33) -> 0
A11: Property tax | B11: =SUMIF(Monthly!$C$5:$BJ$5,B$3,Monthly!$C$34:$BJ$34) -> -8000 | C11: =SUMIF(Monthly!$C$5:$BJ$5,C$3,Monthly!$C$34:$BJ$34) -> -8240 | D11: =SUMIF(Monthly!$C$5:$BJ$5,D$3,Monthly!$C$34:$BJ$34) -> -8487.2 | E11: =SUMIF(Monthly!$C$5:$BJ$5,E$3,Monthly!$C$34:$BJ$34) -> -8741.816 | F11: =SUMIF(Monthly!$C$5:$BJ$5,F$3,Monthly!$C$34:$BJ$34) -> -9004.0705
A12: Insurance | B12: =SUMIF(Monthly!$C$5:$BJ$5,B$3,Monthly!$C$35:$BJ$35) -> -8400 | C12: =SUMIF(Monthly!$C$5:$BJ$5,C$3,Monthly!$C$35:$BJ$35) -> -8652 | D12: =SUMIF(Monthly!$C$5:$BJ$5,D$3,Monthly!$C$35:$BJ$35) -> -8911.56 | E12: =SUMIF(Monthly!$C$5:$BJ$5,E$3,Monthly!$C$35:$BJ$35) -> -9178.9068 | F12: =SUMIF(Monthly!$C$5:$BJ$5,F$3,Monthly!$C$35:$BJ$35) -> -9454.274
A13: Utilities | B13: =SUMIF(Monthly!$C$5:$BJ$5,B$3,Monthly!$C$36:$BJ$36) -> -21600 | C13: =SUMIF(Monthly!$C$5:$BJ$5,C$3,Monthly!$C$36:$BJ$36) -> -22248 | D13: =SUMIF(Monthly!$C$5:$BJ$5,D$3,Monthly!$C$36:$BJ$36) -> -22915.44 | E13: =SUMIF(Monthly!$C$5:$BJ$5,E$3,Monthly!$C$36:$BJ$36) -> -23602.903 | F13: =SUMIF(Monthly!$C$5:$BJ$5,F$3,Monthly!$C$36:$BJ$36) -> -24310.99
A14: Repairs & maintenance | B14: =SUMIF(Monthly!$C$5:$BJ$5,B$3,Monthly!$C$37:$BJ$37) -> -10997.77 | C14: =SUMIF(Monthly!$C$5:$BJ$5,C$3,Monthly!$C$37:$BJ$37) -> -15873.05 | D14: =SUMIF(Monthly!$C$5:$BJ$5,D$3,Monthly!$C$37:$BJ$37) -> -16676.226 | E14: =SUMIF(Monthly!$C$5:$BJ$5,E$3,Monthly!$C$37:$BJ$37) -> -17520.043 | F14: =SUMIF(Monthly!$C$5:$BJ$5,F$3,Monthly!$C$37:$BJ$37) -> -18406.557
A15: Marketing | B15: =SUMIF(Monthly!$C$5:$BJ$5,B$3,Monthly!$C$38:$BJ$38) -> -18000 | C15: =SUMIF(Monthly!$C$5:$BJ$5,C$3,Monthly!$C$38:$BJ$38) -> -14400 | D15: =SUMIF(Monthly!$C$5:$BJ$5,D$3,Monthly!$C$38:$BJ$38) -> -11520 | E15: =SUMIF(Monthly!$C$5:$BJ$5,E$3,Monthly!$C$38:$BJ$38) -> -9216 | F15: =SUMIF(Monthly!$C$5:$BJ$5,F$3,Monthly!$C$38:$BJ$38) -> -7372.8
A16: Software, accounting & other G&A | B16: =SUMIF(Monthly!$C$5:$BJ$5,B$3,Monthly!$C$39:$BJ$39) -> -14400 | C16: =SUMIF(Monthly!$C$5:$BJ$5,C$3,Monthly!$C$39:$BJ$39) -> -14832 | D16: =SUMIF(Monthly!$C$5:$BJ$5,D$3,Monthly!$C$39:$BJ$39) -> -15276.96 | E16: =SUMIF(Monthly!$C$5:$BJ$5,E$3,Monthly!$C$39:$BJ$39) -> -15735.269 | F16: =SUMIF(Monthly!$C$5:$BJ$5,F$3,Monthly!$C$39:$BJ$39) -> -16207.327
A17: Card processing fees | B17: =SUMIF(Monthly!$C$5:$BJ$5,B$3,Monthly!$C$40:$BJ$40) -> -7423.495 | C17: =SUMIF(Monthly!$C$5:$BJ$5,C$3,Monthly!$C$40:$BJ$40) -> -10714.309 | D17: =SUMIF(Monthly!$C$5:$BJ$5,D$3,Monthly!$C$40:$BJ$40) -> -11256.453 | E17: =SUMIF(Monthly!$C$5:$BJ$5,E$3,Monthly!$C$40:$BJ$40) -> -11826.029 | F17: =SUMIF(Monthly!$C$5:$BJ$5,F$3,Monthly!$C$40:$BJ$40) -> -12424.426
A18: Total operating expenses | B18: =SUMIF(Monthly!$C$5:$BJ$5,B$3,Monthly!$C$41:$BJ$41) -> -155521.27 | C18: =SUMIF(Monthly!$C$5:$BJ$5,C$3,Monthly!$C$41:$BJ$41) -> -163660.36 | D18: =SUMIF(Monthly!$C$5:$BJ$5,D$3,Monthly!$C$41:$BJ$41) -> -165805.87 | E18: =SUMIF(Monthly!$C$5:$BJ$5,E$3,Monthly!$C$41:$BJ$41) -> -168705.86 | F18: =SUMIF(Monthly!$C$5:$BJ$5,F$3,Monthly!$C$41:$BJ$41) -> -172251.88
A19: EBITDA | B19: =SUMIF(Monthly!$C$5:$BJ$5,B$3,Monthly!$C$42:$BJ$42) -> 10242.544 | C19: =SUMIF(Monthly!$C$5:$BJ$5,C$3,Monthly!$C$42:$BJ$42) -> 98400.063 | D19: =SUMIF(Monthly!$C$5:$BJ$5,D$3,Monthly!$C$42:$BJ$42) -> 110686.04 | E19: =SUMIF(Monthly!$C$5:$BJ$5,E$3,Monthly!$C$42:$BJ$42) -> 122982.92 | F19: =SUMIF(Monthly!$C$5:$BJ$5,F$3,Monthly!$C$42:$BJ$42) -> 135438.9
A20: EBITDA margin | B20: =IF(B5=0,0,B19/B5) -> 0.037253166 | C20: =IF(C5=0,0,C19/C5) -> 0.24796763 | D20: =IF(D5=0,0,D19/D5) -> 0.26549423 | E20: =IF(E5=0,0,E19/E5) -> 0.28078222 | F20: =IF(F5=0,0,F19/F5) -> 0.29432751
A21: Depreciation | B21: =SUMIF(Monthly!$C$5:$BJ$5,B$3,Monthly!$C$62:$BJ$62) -> -45991.667 | C21: =SUMIF(Monthly!$C$5:$BJ$5,C$3,Monthly!$C$62:$BJ$62) -> -46601.417 | D21: =SUMIF(Monthly!$C$5:$BJ$5,D$3,Monthly!$C$62:$BJ$62) -> -47229.459 | E21: =SUMIF(Monthly!$C$5:$BJ$5,E$3,Monthly!$C$62:$BJ$62) -> -47876.343 | F21: =SUMIF(Monthly!$C$5:$BJ$5,F$3,Monthly!$C$62:$BJ$62) -> -48542.633
A22: EBIT | B22: =SUMIF(Monthly!$C$5:$BJ$5,B$3,Monthly!$C$45:$BJ$45) -> -35749.123 | C22: =SUMIF(Monthly!$C$5:$BJ$5,C$3,Monthly!$C$45:$BJ$45) -> 51798.646 | D22: =SUMIF(Monthly!$C$5:$BJ$5,D$3,Monthly!$C$45:$BJ$45) -> 63456.584 | E22: =SUMIF(Monthly!$C$5:$BJ$5,E$3,Monthly!$C$45:$BJ$45) -> 75106.572 | F22: =SUMIF(Monthly!$C$5:$BJ$5,F$3,Monthly!$C$45:$BJ$45) -> 86896.271
A23: Interest | B23: =SUMIF(Monthly!$C$5:$BJ$5,B$3,Monthly!$C$46:$BJ$46) -> -34757.685 | C23: =SUMIF(Monthly!$C$5:$BJ$5,C$3,Monthly!$C$46:$BJ$46) -> -34204.733 | D23: =SUMIF(Monthly!$C$5:$BJ$5,D$3,Monthly!$C$46:$BJ$46) -> -33611.809 | E23: =SUMIF(Monthly!$C$5:$BJ$5,E$3,Monthly!$C$46:$BJ$46) -> -32976.021 | F23: =SUMIF(Monthly!$C$5:$BJ$5,F$3,Monthly!$C$46:$BJ$46) -> -32294.273
A24: Pre-tax income | B24: =SUMIF(Monthly!$C$5:$BJ$5,B$3,Monthly!$C$47:$BJ$47) -> -70506.807 | C24: =SUMIF(Monthly!$C$5:$BJ$5,C$3,Monthly!$C$47:$BJ$47) -> 17593.913 | D24: =SUMIF(Monthly!$C$5:$BJ$5,D$3,Monthly!$C$47:$BJ$47) -> 29844.776 | E24: =SUMIF(Monthly!$C$5:$BJ$5,E$3,Monthly!$C$47:$BJ$47) -> 42130.551 | F24: =SUMIF(Monthly!$C$5:$BJ$5,F$3,Monthly!$C$47:$BJ$47) -> 54601.998
A25: Income tax | B25: =SUMIF(Monthly!$C$5:$BJ$5,B$3,Monthly!$C$50:$BJ$50) -> 0 | C25: =SUMIF(Monthly!$C$5:$BJ$5,C$3,Monthly!$C$50:$BJ$50) -> 0 | D25: =SUMIF(Monthly!$C$5:$BJ$5,D$3,Monthly!$C$50:$BJ$50) -> 0 | E25: =SUMIF(Monthly!$C$5:$BJ$5,E$3,Monthly!$C$50:$BJ$50) -> -4003.1107 | F25: =SUMIF(Monthly!$C$5:$BJ$5,F$3,Monthly!$C$50:$BJ$50) -> -11466.42
A26: Net income | B26: =SUMIF(Monthly!$C$5:$BJ$5,B$3,Monthly!$C$51:$BJ$51) -> -70506.807 | C26: =SUMIF(Monthly!$C$5:$BJ$5,C$3,Monthly!$C$51:$BJ$51) -> 17593.913 | D26: =SUMIF(Monthly!$C$5:$BJ$5,D$3,Monthly!$C$51:$BJ$51) -> 29844.776 | E26: =SUMIF(Monthly!$C$5:$BJ$5,E$3,Monthly!$C$51:$BJ$51) -> 38127.44 | F26: =SUMIF(Monthly!$C$5:$BJ$5,F$3,Monthly!$C$51:$BJ$51) -> 43135.578
A27: Net margin | B27: =IF(B5=0,0,B26/B5) -> -0.25644037 | C27: =IF(C5=0,0,C26/C5) -> 0.044336566 | D27: =IF(D5=0,0,D26/D5) -> 0.071586402 | E27: =IF(E5=0,0,E26/E5) -> 0.087048736 | F27: =IF(F5=0,0,F26/F5) -> 0.09373959

Sheet Cash Flow
A1: Annual cash flow statement | H1: =HYPERLINK("#'Cover'!A1","◂ Contents") -> ◂ Contents
A2: Rolled up from the period detail (SUMIF on the year row; balances at year end).
A3: Year # | B3: 1 | C3: 2 | D3: 3 | E3: 4 | F3: 5
B4: Year 1 | C4: Year 2 | D4: Year 3 | E4: Year 4 | F4: Year 5
A5: Net income | B5: =SUMIF(Monthly!$C$5:$BJ$5,B$3,Monthly!$C$51:$BJ$51) -> -70506.807 | C5: =SUMIF(Monthly!$C$5:$BJ$5,C$3,Monthly!$C$51:$BJ$51) -> 17593.913 | D5: =SUMIF(Monthly!$C$5:$BJ$5,D$3,Monthly!$C$51:$BJ$51) -> 29844.776 | E5: =SUMIF(Monthly!$C$5:$BJ$5,E$3,Monthly!$C$51:$BJ$51) -> 38127.44 | F5: =SUMIF(Monthly!$C$5:$BJ$5,F$3,Monthly!$C$51:$BJ$51) -> 43135.578
A6: Add back depreciation | B6: =-SUMIF(Monthly!$C$5:$BJ$5,B$3,Monthly!$C$62:$BJ$62) -> 45991.667 | C6: =-SUMIF(Monthly!$C$5:$BJ$5,C$3,Monthly!$C$62:$BJ$62) -> 46601.417 | D6: =-SUMIF(Monthly!$C$5:$BJ$5,D$3,Monthly!$C$62:$BJ$62) -> 47229.459 | E6: =-SUMIF(Monthly!$C$5:$BJ$5,E$3,Monthly!$C$62:$BJ$62) -> 47876.343 | F6: =-SUMIF(Monthly!$C$5:$BJ$5,F$3,Monthly!$C$62:$BJ$62) -> 48542.633
A7: (Increase) / decrease in receivables | B7: =SUMIF(Monthly!$C$5:$BJ$5,B$3,Monthly!$C$78:$BJ$78) -> -2885.3147 | C7: =SUMIF(Monthly!$C$5:$BJ$5,C$3,Monthly!$C$78:$BJ$78) -> -145.99692 | D7: =SUMIF(Monthly!$C$5:$BJ$5,D$3,Monthly!$C$78:$BJ$78) -> -153.38437 | E7: =SUMIF(Monthly!$C$5:$BJ$5,E$3,Monthly!$C$78:$BJ$78) -> -161.14562 | F7: =SUMIF(Monthly!$C$5:$BJ$5,F$3,Monthly!$C$78:$BJ$78) -> -169.29958
A8: (Increase) / decrease in inventory | B8: =SUMIF(Monthly!$C$5:$BJ$5,B$3,Monthly!$C$79:$BJ$79) -> -1026.4806 | C8: =SUMIF(Monthly!$C$5:$BJ$5,C$3,Monthly!$C$79:$BJ$79) -> -42.463917 | D8: =SUMIF(Monthly!$C$5:$BJ$5,D$3,Monthly!$C$79:$BJ$79) -> -44.328311 | E8: =SUMIF(Monthly!$C$5:$BJ$5,E$3,Monthly!$C$79:$BJ$79) -> -46.278515 | F8: =SUMIF(Monthly!$C$5:$BJ$5,F$3,Monthly!$C$79:$BJ$79) -> -48.318615
A9: Increase / (decrease) in payables | B9: =SUMIF(Monthly!$C$5:$BJ$5,B$3,Monthly!$C$80:$BJ$80) -> 8554.0047 | C9: =SUMIF(Monthly!$C$5:$BJ$5,C$3,Monthly!$C$80:$BJ$80) -> 353.86597 | D9: =SUMIF(Monthly!$C$5:$BJ$5,D$3,Monthly!$C$80:$BJ$80) -> 369.40259 | E9: =SUMIF(Monthly!$C$5:$BJ$5,E$3,Monthly!$C$80:$BJ$80) -> 385.65429 | F9: =SUMIF(Monthly!$C$5:$BJ$5,F$3,Monthly!$C$80:$BJ$80) -> 402.65513
A10: Operating cash flow | B10: =SUMIF(Monthly!$C$5:$BJ$5,B$3,Monthly!$C$83:$BJ$83) -> -19872.931 | C10: =SUMIF(Monthly!$C$5:$BJ$5,C$3,Monthly!$C$83:$BJ$83) -> 64360.735 | D10: =SUMIF(Monthly!$C$5:$BJ$5,D$3,Monthly!$C$83:$BJ$83) -> 77245.925 | E10: =SUMIF(Monthly!$C$5:$BJ$5,E$3,Monthly!$C$83:$BJ$83) -> 86182.013 | F10: =SUMIF(Monthly!$C$5:$BJ$5,F$3,Monthly!$C$83:$BJ$83) -> 91863.248
A11: Capital spending | B11: =SUMIF(Monthly!$C$5:$BJ$5,B$3,Monthly!$C$84:$BJ$84) -> -874000 | C11: =SUMIF(Monthly!$C$5:$BJ$5,C$3,Monthly!$C$84:$BJ$84) -> -9270 | D11: =SUMIF(Monthly!$C$5:$BJ$5,D$3,Monthly!$C$84:$BJ$84) -> -9548.1 | E11: =SUMIF(Monthly!$C$5:$BJ$5,E$3,Monthly!$C$84:$BJ$84) -> -9834.543 | F11: =SUMIF(Monthly!$C$5:$BJ$5,F$3,Monthly!$C$84:$BJ$84) -> -10129.579
A12: Equity raised | B12: =SUMIF(Monthly!$C$5:$BJ$5,B$3,Monthly!$C$85:$BJ$85) -> 430000 | C12: =SUMIF(Monthly!$C$5:$BJ$5,C$3,Monthly!$C$85:$BJ$85) -> 0 | D12: =SUMIF(Monthly!$C$5:$BJ$5,D$3,Monthly!$C$85:$BJ$85) -> 0 | E12: =SUMIF(Monthly!$C$5:$BJ$5,E$3,Monthly!$C$85:$BJ$85) -> 0 | F12: =SUMIF(Monthly!$C$5:$BJ$5,F$3,Monthly!$C$85:$BJ$85) -> 0
A13: Loan drawdown | B13: =SUMIF(Monthly!$C$5:$BJ$5,B$3,Monthly!$C$68:$BJ$68) -> 500000 | C13: =SUMIF(Monthly!$C$5:$BJ$5,C$3,Monthly!$C$68:$BJ$68) -> 0 | D13: =SUMIF(Monthly!$C$5:$BJ$5,D$3,Monthly!$C$68:$BJ$68) -> 0 | E13: =SUMIF(Monthly!$C$5:$BJ$5,E$3,Monthly!$C$68:$BJ$68) -> 0 | F13: =SUMIF(Monthly!$C$5:$BJ$5,F$3,Monthly!$C$68:$BJ$68) -> 0
A14: Loan repayment | B14: =SUMIF(Monthly!$C$5:$BJ$5,B$3,Monthly!$C$70:$BJ$70) -> -7649.067 | C14: =SUMIF(Monthly!$C$5:$BJ$5,C$3,Monthly!$C$70:$BJ$70) -> -8202.0187 | D14: =SUMIF(Monthly!$C$5:$BJ$5,D$3,Monthly!$C$70:$BJ$70) -> -8794.9433 | E14: =SUMIF(Monthly!$C$5:$BJ$5,E$3,Monthly!$C$70:$BJ$70) -> -9430.7304 | F14: =SUMIF(Monthly!$C$5:$BJ$5,F$3,Monthly!$C$70:$BJ$70) -> -10112.479
A15: Financing cash flow | B15: =SUMIF(Monthly!$C$5:$BJ$5,B$3,Monthly!$C$86:$BJ$86) -> 922350.93 | C15: =SUMIF(Monthly!$C$5:$BJ$5,C$3,Monthly!$C$86:$BJ$86) -> -8202.0187 | D15: =SUMIF(Monthly!$C$5:$BJ$5,D$3,Monthly!$C$86:$BJ$86) -> -8794.9433 | E15: =SUMIF(Monthly!$C$5:$BJ$5,E$3,Monthly!$C$86:$BJ$86) -> -9430.7304 | F15: =SUMIF(Monthly!$C$5:$BJ$5,F$3,Monthly!$C$86:$BJ$86) -> -10112.479
A16: Net change in cash | B16: =SUMIF(Monthly!$C$5:$BJ$5,B$3,Monthly!$C$87:$BJ$87) -> 28478.002 | C16: =SUMIF(Monthly!$C$5:$BJ$5,C$3,Monthly!$C$87:$BJ$87) -> 46888.716 | D16: =SUMIF(Monthly!$C$5:$BJ$5,D$3,Monthly!$C$87:$BJ$87) -> 58902.881 | E16: =SUMIF(Monthly!$C$5:$BJ$5,E$3,Monthly!$C$87:$BJ$87) -> 66916.74 | F16: =SUMIF(Monthly!$C$5:$BJ$5,F$3,Monthly!$C$87:$BJ$87) -> 71621.19
A17: Opening cash | B17: =INDEX(Monthly!$C$88:$BJ$88,(B$3-1)*12+1) -> 0 | C17: =INDEX(Monthly!$C$88:$BJ$88,(C$3-1)*12+1) -> 28478.002 | D17: =INDEX(Monthly!$C$88:$BJ$88,(D$3-1)*12+1) -> 75366.718 | E17: =INDEX(Monthly!$C$88:$BJ$88,(E$3-1)*12+1) -> 134269.6 | F17: =INDEX(Monthly!$C$88:$BJ$88,(F$3-1)*12+1) -> 201186.34
A18: Closing cash | B18: =INDEX(Monthly!$C$89:$BJ$89,B$3*12) -> 28478.002 | C18: =INDEX(Monthly!$C$89:$BJ$89,C$3*12) -> 75366.718 | D18: =INDEX(Monthly!$C$89:$BJ$89,D$3*12) -> 134269.6 | E18: =INDEX(Monthly!$C$89:$BJ$89,E$3*12) -> 201186.34 | F18: =INDEX(Monthly!$C$89:$BJ$89,F$3*12) -> 272807.53

Sheet Balance Sheet
A1: Balance sheet at year end | H1: =HYPERLINK("#'Cover'!A1","◂ Contents") -> ◂ Contents
A2: Rolled up from the period detail (SUMIF on the year row; balances at year end).
A3: Year # | B3: 1 | C3: 2 | D3: 3 | E3: 4 | F3: 5
B4: Year 1 | C4: Year 2 | D4: Year 3 | E4: Year 4 | F4: Year 5
A5: Cash | B5: =INDEX(Monthly!$C$89:$BJ$89,B$3*12) -> 28478.002 | C5: =INDEX(Monthly!$C$89:$BJ$89,C$3*12) -> 75366.718 | D5: =INDEX(Monthly!$C$89:$BJ$89,D$3*12) -> 134269.6 | E5: =INDEX(Monthly!$C$89:$BJ$89,E$3*12) -> 201186.34 | F5: =INDEX(Monthly!$C$89:$BJ$89,F$3*12) -> 272807.53
A6: Accounts receivable | B6: =INDEX(Monthly!$C$75:$BJ$75,B$3*12) -> 2885.3147 | C6: =INDEX(Monthly!$C$75:$BJ$75,C$3*12) -> 3031.3116 | D6: =INDEX(Monthly!$C$75:$BJ$75,D$3*12) -> 3184.696 | E6: =INDEX(Monthly!$C$75:$BJ$75,E$3*12) -> 3345.8416 | F6: =INDEX(Monthly!$C$75:$BJ$75,F$3*12) -> 3515.1412
A7: Inventory | B7: =INDEX(Monthly!$C$76:$BJ$76,B$3*12) -> 1026.4806 | C7: =INDEX(Monthly!$C$76:$BJ$76,C$3*12) -> 1068.9445 | D7: =INDEX(Monthly!$C$76:$BJ$76,D$3*12) -> 1113.2728 | E7: =INDEX(Monthly!$C$76:$BJ$76,E$3*12) -> 1159.5513 | F7: =INDEX(Monthly!$C$76:$BJ$76,F$3*12) -> 1207.8699
A8: Net fixed assets | B8: =INDEX(Monthly!$C$64:$BJ$64,B$3*12) -> 828008.33 | C8: =INDEX(Monthly!$C$64:$BJ$64,C$3*12) -> 790676.92 | D8: =INDEX(Monthly!$C$64:$BJ$64,D$3*12) -> 752995.56 | E8: =INDEX(Monthly!$C$64:$BJ$64,E$3*12) -> 714953.76 | F8: =INDEX(Monthly!$C$64:$BJ$64,F$3*12) -> 676540.7
A9: Total assets | B9: =INDEX(Monthly!$C$103:$BJ$103,B$3*12) -> 860398.13 | C9: =INDEX(Monthly!$C$103:$BJ$103,C$3*12) -> 870143.89 | D9: =INDEX(Monthly!$C$103:$BJ$103,D$3*12) -> 891563.13 | E9: =INDEX(Monthly!$C$103:$BJ$103,E$3*12) -> 920645.49 | F9: =INDEX(Monthly!$C$103:$BJ$103,F$3*12) -> 954071.24
A10: Accounts payable | B10: =INDEX(Monthly!$C$77:$BJ$77,B$3*12) -> 8554.0047 | C10: =INDEX(Monthly!$C$77:$BJ$77,C$3*12) -> 8907.8707 | D10: =INDEX(Monthly!$C$77:$BJ$77,D$3*12) -> 9277.2733 | E10: =INDEX(Monthly!$C$77:$BJ$77,E$3*12) -> 9662.9276 | F10: =INDEX(Monthly!$C$77:$BJ$77,F$3*12) -> 10065.583
A11: Loan | B11: =INDEX(Monthly!$C$72:$BJ$72,B$3*12) -> 492350.93 | C11: =INDEX(Monthly!$C$72:$BJ$72,C$3*12) -> 484148.91 | D11: =INDEX(Monthly!$C$72:$BJ$72,D$3*12) -> 475353.97 | E11: =INDEX(Monthly!$C$72:$BJ$72,E$3*12) -> 465923.24 | F11: =INDEX(Monthly!$C$72:$BJ$72,F$3*12) -> 455810.76
A12: Total liabilities | B12: =INDEX(Monthly!$C$104:$BJ$104,B$3*12) -> 500904.94 | C12: =INDEX(Monthly!$C$104:$BJ$104,C$3*12) -> 493056.79 | D12: =INDEX(Monthly!$C$104:$BJ$104,D$3*12) -> 484631.24 | E12: =INDEX(Monthly!$C$104:$BJ$104,E$3*12) -> 475586.17 | F12: =INDEX(Monthly!$C$104:$BJ$104,F$3*12) -> 465876.34
A13: Paid-in capital | B13: =INDEX(Monthly!$C$101:$BJ$101,B$3*12) -> 430000 | C13: =INDEX(Monthly!$C$101:$BJ$101,C$3*12) -> 430000 | D13: =INDEX(Monthly!$C$101:$BJ$101,D$3*12) -> 430000 | E13: =INDEX(Monthly!$C$101:$BJ$101,E$3*12) -> 430000 | F13: =INDEX(Monthly!$C$101:$BJ$101,F$3*12) -> 430000
A14: Retained earnings | B14: =INDEX(Monthly!$C$102:$BJ$102,B$3*12) -> -70506.807 | C14: =INDEX(Monthly!$C$102:$BJ$102,C$3*12) -> -52912.894 | D14: =INDEX(Monthly!$C$102:$BJ$102,D$3*12) -> -23068.119 | E14: =INDEX(Monthly!$C$102:$BJ$102,E$3*12) -> 15059.321 | F14: =INDEX(Monthly!$C$102:$BJ$102,F$3*12) -> 58194.9
A15: Total equity | B15: =INDEX(Monthly!$C$105:$BJ$105,B$3*12) -> 359493.19 | C15: =INDEX(Monthly!$C$105:$BJ$105,C$3*12) -> 377087.11 | D15: =INDEX(Monthly!$C$105:$BJ$105,D$3*12) -> 406931.88 | E15: =INDEX(Monthly!$C$105:$BJ$105,E$3*12) -> 445059.32 | F15: =INDEX(Monthly!$C$105:$BJ$105,F$3*12) -> 488194.9
A16: Total liabilities & equity | B16: =INDEX(Monthly!$C$106:$BJ$106,B$3*12) -> 860398.13 | C16: =INDEX(Monthly!$C$106:$BJ$106,C$3*12) -> 870143.89 | D16: =INDEX(Monthly!$C$106:$BJ$106,D$3*12) -> 891563.13 | E16: =INDEX(Monthly!$C$106:$BJ$106,E$3*12) -> 920645.49 | F16: =INDEX(Monthly!$C$106:$BJ$106,F$3*12) -> 954071.24
A17: Check: assets − liabilities − equity (must be 0) | B17: =INDEX(Monthly!$C$107:$BJ$107,B$3*12) -> 0 | C17: =INDEX(Monthly!$C$107:$BJ$107,C$3*12) -> 0 | D17: =INDEX(Monthly!$C$107:$BJ$107,D$3*12) -> 0 | E17: =INDEX(Monthly!$C$107:$BJ$107,E$3*12) -> 0 | F17: =INDEX(Monthly!$C$107:$BJ$107,F$3*12) -> 0

Sheet Monthly
A1: Monthly projection | D1: =HYPERLINK("#'Cover'!A1","◂ Contents") -> ◂ Contents
A2: $ unless stated; costs shown as negatives. Every period uses the same formula.
A3: Month | C3: M1 | D3: M2 | E3: M3 | F3: M4 | G3: M5 | H3: M6 | I3: M7 | J3: M8 | K3: M9 | L3: M10 | M3: M11 | N3: M12 | O3: M13 | P3: M14 | Q3: M15 | R3: M16 | S3: M17 | T3: M18 | U3: M19 | V3: M20 | W3: M21 | X3: M22 | Y3: M23 | Z3: M24 | AA3: M25 | AB3: M26 | AC3: M27 | AD3: M28 | AE3: M29 | AF3: M30 | AG3: M31 | AH3: M32 | AI3: M33 | AJ3: M34 | AK3: M35 | AL3: M36 | AM3: M37 | AN3: M38 | AO3: M39 | AP3: M40 | AQ3: M41 | AR3: M42 | AS3: M43 | AT3: M44 | AU3: M45 | AV3: M46 | AW3: M47 | AX3: M48 | AY3: M49 | AZ3: M50 | BA3: M51 | BB3: M52 | BC3: M53 | BD3: M54 | BE3: M55 | BF3: M56 | BG3: M57 | BH3: M58 | BI3: M59 | BJ3: M60
A4: Period # | C4: 1 | D4: 2 | E4: 3 | F4: 4 | G4: 5 | H4: 6 | I4: 7 | J4: 8 | K4: 9 | L4: 10 | M4: 11 | N4: 12 | O4: 13 | P4: 14 | Q4: 15 | R4: 16 | S4: 17 | T4: 18 | U4: 19 | V4: 20 | W4: 21 | X4: 22 | Y4: 23 | Z4: 24 | AA4: 25 | AB4: 26 | AC4: 27 | AD4: 28 | AE4: 29 | AF4: 30 | AG4: 31 | AH4: 32 | AI4: 33 | AJ4: 34 | AK4: 35 | AL4: 36 | AM4: 37 | AN4: 38 | AO4: 39 | AP4: 40 | AQ4: 41 | AR4: 42 | AS4: 43 | AT4: 44 | AU4: 45 | AV4: 46 | AW4: 47 | AX4: 48 | AY4: 49 | AZ4: 50 | BA4: 51 | BB4: 52 | BC4: 53 | BD4: 54 | BE4: 55 | BF4: 56 | BG4: 57 | BH4: 58 | BI4: 59 | BJ4: 60
A5: Year # | C5: =ROUNDUP(C4*1/12,0) -> 1 | D5: =ROUNDUP(D4*1/12,0) -> 1 | E5: =ROUNDUP(E4*1/12,0) -> 1 | F5: =ROUNDUP(F4*1/12,0) -> 1 | G5: =ROUNDUP(G4*1/12,0) -> 1 | H5: =ROUNDUP(H4*1/12,0) -> 1 | I5: =ROUNDUP(I4*1/12,0) -> 1 | J5: =ROUNDUP(J4*1/12,0) -> 1 | ... BJ5: =ROUNDUP(BJ4*1/12,0) -> 5
A7: Rooms & occupancy
A8: Helper: months of the period still on the opening ramp | C8: =MAX(0,MIN(1,Inputs!$E$10-(C$4-1)*1)) -> 1 | D8: =MAX(0,MIN(1,Inputs!$E$10-(D$4-1)*1)) -> 1 | E8: =MAX(0,MIN(1,Inputs!$E$10-(E$4-1)*1)) -> 1 | F8: =MAX(0,MIN(1,Inputs!$E$10-(F$4-1)*1)) -> 1 | G8: =MAX(0,MIN(1,Inputs!$E$10-(G$4-1)*1)) -> 1 | H8: =MAX(0,MIN(1,Inputs!$E$10-(H$4-1)*1)) -> 1 | I8: =MAX(0,MIN(1,Inputs!$E$10-(I$4-1)*1)) -> 1 | J8: =MAX(0,MIN(1,Inputs!$E$10-(J$4-1)*1)) -> 1 | ... BJ8: =MAX(0,MIN(1,Inputs!$E$10-(BJ$4-1)*1)) -> 0
A9: Opening ramp factor (share of mature occupancy) | C9: =IF(Inputs!$E$10<=0,1,(C8*Inputs!$E$11+(1-Inputs!$E$11)/MAX(1,Inputs!$E$10)*(C8*(C$4-1)*1+C8*(C8-1)/2)+1-C8)/1) -> 0.4 | D9: =IF(Inputs!$E$10<=0,1,(D8*Inputs!$E$11+(1-Inputs!$E$11)/MAX(1,Inputs!$E$10)*(D8*(D$4-1)*1+D8*(D8-1)/2)+1-D8)/1) -> 0.46 | E9: =IF(Inputs!$E$10<=0,1,(E8*Inputs!$E$11+(1-Inputs!$E$11)/MAX(1,Inputs!$E$10)*(E8*(E$4-1)*1+E8*(E8-1)/2)+1-E8)/1) -> 0.52 | F9: =IF(Inputs!$E$10<=0,1,(F8*Inputs!$E$11+(1-Inputs!$E$11)/MAX(1,Inputs!$E$10)*(F8*(F$4-1)*1+F8*(F8-1)/2)+1-F8)/1) -> 0.58 | G9: =IF(Inputs!$E$10<=0,1,(G8*Inputs!$E$11+(1-Inputs!$E$11)/MAX(1,Inputs!$E$10)*(G8*(G$4-1)*1+G8*(G8-1)/2)+1-G8)/1) -> 0.64 | H9: =IF(Inputs!$E$10<=0,1,(H8*Inputs!$E$11+(1-Inputs!$E$11)/MAX(1,Inputs!$E$10)*(H8*(H$4-1)*1+H8*(H8-1)/2)+1-H8)/1) -> 0.7 | I9: =IF(Inputs!$E$10<=0,1,(I8*Inputs!$E$11+(1-Inputs!$E$11)/MAX(1,Inputs!$E$10)*(I8*(I$4-1)*1+I8*(I8-1)/2)+1-I8)/1) -> 0.76 | J9: =IF(Inputs!$E$10<=0,1,(J8*Inputs!$E$11+(1-Inputs!$E$11)/MAX(1,Inputs!$E$10)*(J8*(J$4-1)*1+J8*(J8-1)/2)+1-J8)/1) -> 0.82 | ... BJ9: =IF(Inputs!$E$10<=0,1,(BJ8*Inputs!$E$11+(1-Inputs!$E$11)/MAX(1,Inputs!$E$10)*(BJ8*(BJ$4-1)*1+BJ8*(BJ8-1)/2)+1-BJ8)/1) -> 1
A10: Season factor (June-August) | C10: =IF(AND(MOD(C$4-1,12)>=5,MOD(C$4-1,12)<=7),1+Inputs!$E$12,1-Inputs!$E$12/3) -> 0.91666667 | D10: =IF(AND(MOD(D$4-1,12)>=5,MOD(D$4-1,12)<=7),1+Inputs!$E$12,1-Inputs!$E$12/3) -> 0.91666667 | E10: =IF(AND(MOD(E$4-1,12)>=5,MOD(E$4-1,12)<=7),1+Inputs!$E$12,1-Inputs!$E$12/3) -> 0.91666667 | F10: =IF(AND(MOD(F$4-1,12)>=5,MOD(F$4-1,12)<=7),1+Inputs!$E$12,1-Inputs!$E$12/3) -> 0.91666667 | G10: =IF(AND(MOD(G$4-1,12)>=5,MOD(G$4-1,12)<=7),1+Inputs!$E$12,1-Inputs!$E$12/3) -> 0.91666667 | H10: =IF(AND(MOD(H$4-1,12)>=5,MOD(H$4-1,12)<=7),1+Inputs!$E$12,1-Inputs!$E$12/3) -> 1.25 | I10: =IF(AND(MOD(I$4-1,12)>=5,MOD(I$4-1,12)<=7),1+Inputs!$E$12,1-Inputs!$E$12/3) -> 1.25 | J10: =IF(AND(MOD(J$4-1,12)>=5,MOD(J$4-1,12)<=7),1+Inputs!$E$12,1-Inputs!$E$12/3) -> 1.25 | ... BJ10: =IF(AND(MOD(BJ$4-1,12)>=5,MOD(BJ$4-1,12)<=7),1+Inputs!$E$12,1-Inputs!$E$12/3) -> 0.91666667
A11: Available room-nights (rooms × calendar nights) | C11: =Inputs!$E$7*Inputs!$E$13*1 -> 304 | D11: =Inputs!$E$7*Inputs!$E$13*1 -> 304 | E11: =Inputs!$E$7*Inputs!$E$13*1 -> 304 | F11: =Inputs!$E$7*Inputs!$E$13*1 -> 304 | G11: =Inputs!$E$7*Inputs!$E$13*1 -> 304 | H11: =Inputs!$E$7*Inputs!$E$13*1 -> 304 | I11: =Inputs!$E$7*Inputs!$E$13*1 -> 304 | J11: =Inputs!$E$7*Inputs!$E$13*1 -> 304 | ... BJ11: =Inputs!$E$7*Inputs!$E$13*1 -> 304
A12: Occupancy (maturity × growth × ramp × season, capped at 100%) | C12: =MIN(1,Inputs!$E$8*(1+Inputs!$E$9)^(C$5-1)*C9*C10) -> 0.22733333 | D12: =MIN(1,Inputs!$E$8*(1+Inputs!$E$9)^(D$5-1)*D9*D10) -> 0.26143333 | E12: =MIN(1,Inputs!$E$8*(1+Inputs!$E$9)^(E$5-1)*E9*E10) -> 0.29553333 | F12: =MIN(1,Inputs!$E$8*(1+Inputs!$E$9)^(F$5-1)*F9*F10) -> 0.32963333 | G12: =MIN(1,Inputs!$E$8*(1+Inputs!$E$9)^(G$5-1)*G9*G10) -> 0.36373333 | H12: =MIN(1,Inputs!$E$8*(1+Inputs!$E$9)^(H$5-1)*H9*H10) -> 0.5425 | I12: =MIN(1,Inputs!$E$8*(1+Inputs!$E$9)^(I$5-1)*I9*I10) -> 0.589 | J12: =MIN(1,Inputs!$E$8*(1+Inputs!$E$9)^(J$5-1)*J9*J10) -> 0.6355 | ... BJ12: =MIN(1,Inputs!$E$8*(1+Inputs!$E$9)^(BJ$5-1)*BJ9*BJ10) -> 0.61518228
A13: Occupied room-nights | C13: =C11*C12 -> 69.109333 | D13: =D11*D12 -> 79.475733 | E13: =E11*E12 -> 89.842133 | F13: =F11*F12 -> 100.20853 | G13: =G11*G12 -> 110.57493 | H13: =H11*H12 -> 164.92 | I13: =I11*I12 -> 179.056 | J13: =J11*J12 -> 193.192 | ... BJ13: =BJ11*BJ12 -> 187.01541
A14: Guest stays (room-nights ÷ average length of stay) | C14: =IF(Inputs!$E$14<=0,0,C13/Inputs!$E$14) -> 31.413333 | D14: =IF(Inputs!$E$14<=0,0,D13/Inputs!$E$14) -> 36.125333 | E14: =IF(Inputs!$E$14<=0,0,E13/Inputs!$E$14) -> 40.837333 | F14: =IF(Inputs!$E$14<=0,0,F13/Inputs!$E$14) -> 45.549333 | G14: =IF(Inputs!$E$14<=0,0,G13/Inputs!$E$14) -> 50.261333 | H14: =IF(Inputs!$E$14<=0,0,H13/Inputs!$E$14) -> 74.963636 | I14: =IF(Inputs!$E$14<=0,0,I13/Inputs!$E$14) -> 81.389091 | J14: =IF(Inputs!$E$14<=0,0,J13/Inputs!$E$14) -> 87.814545 | ... BJ14: =IF(Inputs!$E$14<=0,0,BJ13/Inputs!$E$14) -> 85.007006
A16: Revenue
A17: Average daily rate | C17: =Inputs!$E$17*(1+Inputs!$E$18)^(C$5-1) -> 155 | D17: =Inputs!$E$17*(1+Inputs!$E$18)^(D$5-1) -> 155 | E17: =Inputs!$E$17*(1+Inputs!$E$18)^(E$5-1) -> 155 | F17: =Inputs!$E$17*(1+Inputs!$E$18)^(F$5-1) -> 155 | G17: =Inputs!$E$17*(1+Inputs!$E$18)^(G$5-1) -> 155 | H17: =Inputs!$E$17*(1+Inputs!$E$18)^(H$5-1) -> 155 | I17: =Inputs!$E$17*(1+Inputs!$E$18)^(I$5-1) -> 155 | J17: =Inputs!$E$17*(1+Inputs!$E$18)^(J$5-1) -> 155 | ... BJ17: =Inputs!$E$17*(1+Inputs!$E$18)^(BJ$5-1) -> 174.45387
A18: Room revenue | C18: =C13*C17 -> 10711.947 | D18: =D13*D17 -> 12318.739 | E18: =E13*E17 -> 13925.531 | F18: =F13*F17 -> 15532.323 | G18: =G13*G17 -> 17139.115 | H18: =H13*H17 -> 25562.6 | I18: =I13*I17 -> 27753.68 | J18: =J13*J17 -> 29944.76 | ... BJ18: =BJ13*BJ17 -> 32625.562
A19: Breakfast & extras revenue | C19: =C13*Inputs!$E$19*(1+Inputs!$E$18)^(C$5-1) -> 829.312 | D19: =D13*Inputs!$E$19*(1+Inputs!$E$18)^(D$5-1) -> 953.7088 | E19: =E13*Inputs!$E$19*(1+Inputs!$E$18)^(E$5-1) -> 1078.1056 | F19: =F13*Inputs!$E$19*(1+Inputs!$E$18)^(F$5-1) -> 1202.5024 | G19: =G13*Inputs!$E$19*(1+Inputs!$E$18)^(G$5-1) -> 1326.8992 | H19: =H13*Inputs!$E$19*(1+Inputs!$E$18)^(H$5-1) -> 1979.04 | I19: =I13*Inputs!$E$19*(1+Inputs!$E$18)^(I$5-1) -> 2148.672 | J19: =J13*Inputs!$E$19*(1+Inputs!$E$18)^(J$5-1) -> 2318.304 | ... BJ19: =BJ13*Inputs!$E$19*(1+Inputs!$E$18)^(BJ$5-1) -> 2525.8499
A20: Revenue | C20: =C18+C19 -> 11541.259 | D20: =D18+D19 -> 13272.447 | E20: =E18+E19 -> 15003.636 | F20: =F18+F19 -> 16734.825 | G20: =G18+G19 -> 18466.014 | H20: =H18+H19 -> 27541.64 | I20: =I18+I19 -> 29902.352 | J20: =J18+J19 -> 32263.064 | ... BJ20: =BJ18+BJ19 -> 35151.412
A22: Cost of sales
A23: Housekeeping payroll | C23: =Headcount!C14 -> -4600 | D23: =Headcount!D14 -> -4600 | E23: =Headcount!E14 -> -4600 | F23: =Headcount!F14 -> -4600 | G23: =Headcount!G14 -> -4600 | H23: =Headcount!H14 -> -4600 | I23: =Headcount!I14 -> -4600 | J23: =Headcount!J14 -> -4600 | ... BJ23: =Headcount!BJ14 -> -5177.3405
A24: OTA / booking commission | C24: =-C18*Inputs!$E$25*Inputs!$E$26 -> -883.7356 | D24: =-D18*Inputs!$E$25*Inputs!$E$26 -> -1016.2959 | E24: =-E18*Inputs!$E$25*Inputs!$E$26 -> -1148.8563 | F24: =-F18*Inputs!$E$25*Inputs!$E$26 -> -1281.4166 | G24: =-G18*Inputs!$E$25*Inputs!$E$26 -> -1413.977 | H24: =-H18*Inputs!$E$25*Inputs!$E$26 -> -2108.9145 | I24: =-I18*Inputs!$E$25*Inputs!$E$26 -> -2289.6786 | J24: =-J18*Inputs!$E$25*Inputs!$E$26 -> -2470.4427 | ... BJ24: =-BJ18*Inputs!$E$25*Inputs!$E$26 -> -2691.6088
A25: Breakfast & extras cost | C25: =-C19*Inputs!$E$22 -> -414.656 | D25: =-D19*Inputs!$E$22 -> -476.8544 | E25: =-E19*Inputs!$E$22 -> -539.0528 | F25: =-F19*Inputs!$E$22 -> -601.2512 | G25: =-G19*Inputs!$E$22 -> -663.4496 | H25: =-H19*Inputs!$E$22 -> -989.52 | I25: =-I19*Inputs!$E$22 -> -1074.336 | J25: =-J19*Inputs!$E$22 -> -1159.152 | ... BJ25: =-BJ19*Inputs!$E$22 -> -1262.925
A26: Cleaning & linen (per stay) | C26: =-C14*Inputs!$E$23*(1+Inputs!$E$39)^(C$5-1) -> -691.09333 | D26: =-D14*Inputs!$E$23*(1+Inputs!$E$39)^(D$5-1) -> -794.75733 | E26: =-E14*Inputs!$E$23*(1+Inputs!$E$39)^(E$5-1) -> -898.42133 | F26: =-F14*Inputs!$E$23*(1+Inputs!$E$39)^(F$5-1) -> -1002.0853 | G26: =-G14*Inputs!$E$23*(1+Inputs!$E$39)^(G$5-1) -> -1105.7493 | H26: =-H14*Inputs!$E$23*(1+Inputs!$E$39)^(H$5-1) -> -1649.2 | I26: =-I14*Inputs!$E$23*(1+Inputs!$E$39)^(I$5-1) -> -1790.56 | J26: =-J14*Inputs!$E$23*(1+Inputs!$E$39)^(J$5-1) -> -1931.92 | ... BJ26: =-BJ14*Inputs!$E$23*(1+Inputs!$E$39)^(BJ$5-1) -> -2104.8749
A27: Guest supplies | C27: =-C13*Inputs!$E$24*(1+Inputs!$E$39)^(C$5-1) -> -276.43733 | D27: =-D13*Inputs!$E$24*(1+Inputs!$E$39)^(D$5-1) -> -317.90293 | E27: =-E13*Inputs!$E$24*(1+Inputs!$E$39)^(E$5-1) -> -359.36853 | F27: =-F13*Inputs!$E$24*(1+Inputs!$E$39)^(F$5-1) -> -400.83413 | G27: =-G13*Inputs!$E$24*(1+Inputs!$E$39)^(G$5-1) -> -442.29973 | H27: =-H13*Inputs!$E$24*(1+Inputs!$E$39)^(H$5-1) -> -659.68 | I27: =-I13*Inputs!$E$24*(1+Inputs!$E$39)^(I$5-1) -> -716.224 | J27: =-J13*Inputs!$E$24*(1+Inputs!$E$39)^(J$5-1) -> -772.768 | ... BJ27: =-BJ13*Inputs!$E$24*(1+Inputs!$E$39)^(BJ$5-1) -> -841.94998
A28: Cost of sales | C28: =C23+C24+C25+C26+C27 -> -6865.9223 | D28: =D23+D24+D25+D26+D27 -> -7205.8106 | E28: =E23+E24+E25+E26+E27 -> -7545.6989 | F28: =F23+F24+F25+F26+F27 -> -7885.5873 | G28: =G23+G24+G25+G26+G27 -> -8225.4756 | H28: =H23+H24+H25+H26+H27 -> -10007.315 | I28: =I23+I24+I25+I26+I27 -> -10470.799 | J28: =J23+J24+J25+J26+J27 -> -10934.283 | ... BJ28: =BJ23+BJ24+BJ25+BJ26+BJ27 -> -12078.699
A29: Gross profit | C29: =C20+C28 -> 4675.3364 | D29: =D20+D28 -> 6066.6369 | E29: =E20+E28 -> 7457.9373 | F29: =F20+F28 -> 8849.2378 | G29: =G20+G28 -> 10240.538 | H29: =H20+H28 -> 17534.325 | I29: =I20+I28 -> 19431.553 | J29: =J20+J28 -> 21328.781 | ... BJ29: =BJ20+BJ28 -> 23072.712
A31: Operating expenses
A32: Host, front desk, kitchen & maintenance payroll | C32: =Headcount!C17-Headcount!C14 -> -5558.3333 | D32: =Headcount!D17-Headcount!D14 -> -5558.3333 | E32: =Headcount!E17-Headcount!E14 -> -5558.3333 | F32: =Headcount!F17-Headcount!F14 -> -5558.3333 | G32: =Headcount!G17-Headcount!G14 -> -5558.3333 | H32: =Headcount!H17-Headcount!H14 -> -5558.3333 | I32: =Headcount!I17-Headcount!I14 -> -5558.3333 | J32: =Headcount!J17-Headcount!J14 -> -5558.3333 | ... BJ32: =Headcount!BJ17-Headcount!BJ14 -> -6255.9531
A33: Building rent | C33: =-Inputs!$E$29*(1+Inputs!$E$30)^(C$5-1)*1 -> 0 | D33: =-Inputs!$E$29*(1+Inputs!$E$30)^(D$5-1)*1 -> 0 | E33: =-Inputs!$E$29*(1+Inputs!$E$30)^(E$5-1)*1 -> 0 | F33: =-Inputs!$E$29*(1+Inputs!$E$30)^(F$5-1)*1 -> 0 | G33: =-Inputs!$E$29*(1+Inputs!$E$30)^(G$5-1)*1 -> 0 | H33: =-Inputs!$E$29*(1+Inputs!$E$30)^(H$5-1)*1 -> 0 | I33: =-Inputs!$E$29*(1+Inputs!$E$30)^(I$5-1)*1 -> 0 | J33: =-Inputs!$E$29*(1+Inputs!$E$30)^(J$5-1)*1 -> 0 | ... BJ33: =-Inputs!$E$29*(1+Inputs!$E$30)^(BJ$5-1)*1 -> 0
A34: Property tax | C34: =-Inputs!$E$31/12*(1+Inputs!$E$39)^(C$5-1)*1 -> -666.66667 | D34: =-Inputs!$E$31/12*(1+Inputs!$E$39)^(D$5-1)*1 -> -666.66667 | E34: =-Inputs!$E$31/12*(1+Inputs!$E$39)^(E$5-1)*1 -> -666.66667 | F34: =-Inputs!$E$31/12*(1+Inputs!$E$39)^(F$5-1)*1 -> -666.66667 | G34: =-Inputs!$E$31/12*(1+Inputs!$E$39)^(G$5-1)*1 -> -666.66667 | H34: =-Inputs!$E$31/12*(1+Inputs!$E$39)^(H$5-1)*1 -> -666.66667 | I34: =-Inputs!$E$31/12*(1+Inputs!$E$39)^(I$5-1)*1 -> -666.66667 | J34: =-Inputs!$E$31/12*(1+Inputs!$E$39)^(J$5-1)*1 -> -666.66667 | ... BJ34: =-Inputs!$E$31/12*(1+Inputs!$E$39)^(BJ$5-1)*1 -> -750.33921
A35: Insurance | C35: =-Inputs!$E$32*(1+Inputs!$E$39)^(C$5-1)*1 -> -700 | D35: =-Inputs!$E$32*(1+Inputs!$E$39)^(D$5-1)*1 -> -700 | E35: =-Inputs!$E$32*(1+Inputs!$E$39)^(E$5-1)*1 -> -700 | F35: =-Inputs!$E$32*(1+Inputs!$E$39)^(F$5-1)*1 -> -700 | G35: =-Inputs!$E$32*(1+Inputs!$E$39)^(G$5-1)*1 -> -700 | H35: =-Inputs!$E$32*(1+Inputs!$E$39)^(H$5-1)*1 -> -700 | I35: =-Inputs!$E$32*(1+Inputs!$E$39)^(I$5-1)*1 -> -700 | J35: =-Inputs!$E$32*(1+Inputs!$E$39)^(J$5-1)*1 -> -700 | ... BJ35: =-Inputs!$E$32*(1+Inputs!$E$39)^(BJ$5-1)*1 -> -787.85617
A36: Utilities | C36: =-Inputs!$E$33*(1+Inputs!$E$39)^(C$5-1)*1 -> -1800 | D36: =-Inputs!$E$33*(1+Inputs!$E$39)^(D$5-1)*1 -> -1800 | E36: =-Inputs!$E$33*(1+Inputs!$E$39)^(E$5-1)*1 -> -1800 | F36: =-Inputs!$E$33*(1+Inputs!$E$39)^(F$5-1)*1 -> -1800 | G36: =-Inputs!$E$33*(1+Inputs!$E$39)^(G$5-1)*1 -> -1800 | H36: =-Inputs!$E$33*(1+Inputs!$E$39)^(H$5-1)*1 -> -1800 | I36: =-Inputs!$E$33*(1+Inputs!$E$39)^(I$5-1)*1 -> -1800 | J36: =-Inputs!$E$33*(1+Inputs!$E$39)^(J$5-1)*1 -> -1800 | ... BJ36: =-Inputs!$E$33*(1+Inputs!$E$39)^(BJ$5-1)*1 -> -2025.9159
A37: Repairs & maintenance | C37: =-C20*Inputs!$E$34 -> -461.65035 | D37: =-D20*Inputs!$E$34 -> -530.8979 | E37: =-E20*Inputs!$E$34 -> -600.14545 | F37: =-F20*Inputs!$E$34 -> -669.393 | G37: =-G20*Inputs!$E$34 -> -738.64055 | H37: =-H20*Inputs!$E$34 -> -1101.6656 | I37: =-I20*Inputs!$E$34 -> -1196.0941 | J37: =-J20*Inputs!$E$34 -> -1290.5226 | ... BJ37: =-BJ20*Inputs!$E$34 -> -1406.0565
A38: Marketing | C38: =-Inputs!$E$36*(1+Inputs!$E$37)^(C$5-1)*1 -> -1500 | D38: =-Inputs!$E$36*(1+Inputs!$E$37)^(D$5-1)*1 -> -1500 | E38: =-Inputs!$E$36*(1+Inputs!$E$37)^(E$5-1)*1 -> -1500 | F38: =-Inputs!$E$36*(1+Inputs!$E$37)^(F$5-1)*1 -> -1500 | G38: =-Inputs!$E$36*(1+Inputs!$E$37)^(G$5-1)*1 -> -1500 | H38: =-Inputs!$E$36*(1+Inputs!$E$37)^(H$5-1)*1 -> -1500 | I38: =-Inputs!$E$36*(1+Inputs!$E$37)^(I$5-1)*1 -> -1500 | J38: =-Inputs!$E$36*(1+Inputs!$E$37)^(J$5-1)*1 -> -1500 | ... BJ38: =-Inputs!$E$36*(1+Inputs!$E$37)^(BJ$5-1)*1 -> -614.4
A39: Software, accounting & other G&A | C39: =-Inputs!$E$35*(1+Inputs!$E$39)^(C$5-1)*1 -> -1200 | D39: =-Inputs!$E$35*(1+Inputs!$E$39)^(D$5-1)*1 -> -1200 | E39: =-Inputs!$E$35*(1+Inputs!$E$39)^(E$5-1)*1 -> -1200 | F39: =-Inputs!$E$35*(1+Inputs!$E$39)^(F$5-1)*1 -> -1200 | G39: =-Inputs!$E$35*(1+Inputs!$E$39)^(G$5-1)*1 -> -1200 | H39: =-Inputs!$E$35*(1+Inputs!$E$39)^(H$5-1)*1 -> -1200 | I39: =-Inputs!$E$35*(1+Inputs!$E$39)^(I$5-1)*1 -> -1200 | J39: =-Inputs!$E$35*(1+Inputs!$E$39)^(J$5-1)*1 -> -1200 | ... BJ39: =-Inputs!$E$35*(1+Inputs!$E$39)^(BJ$5-1)*1 -> -1350.6106
A40: Card processing fees | C40: =-C20*Inputs!$E$38 -> -311.61398 | D40: =-D20*Inputs!$E$38 -> -358.35608 | E40: =-E20*Inputs!$E$38 -> -405.09818 | F40: =-F20*Inputs!$E$38 -> -451.84028 | G40: =-G20*Inputs!$E$38 -> -498.58237 | H40: =-H20*Inputs!$E$38 -> -743.62428 | I40: =-I20*Inputs!$E$38 -> -807.3635 | J40: =-J20*Inputs!$E$38 -> -871.10273 | ... BJ40: =-BJ20*Inputs!$E$38 -> -949.08811
A41: Total operating expenses | C41: =C32+C33+C34+C35+C36+C37+C38+C39+C40 -> -12198.264 | D41: =D32+D33+D34+D35+D36+D37+D38+D39+D40 -> -12314.254 | E41: =E32+E33+E34+E35+E36+E37+E38+E39+E40 -> -12430.244 | F41: =F32+F33+F34+F35+F36+F37+F38+F39+F40 -> -12546.233 | G41: =G32+G33+G34+G35+G36+G37+G38+G39+G40 -> -12662.223 | H41: =H32+H33+H34+H35+H36+H37+H38+H39+H40 -> -13270.29 | I41: =I32+I33+I34+I35+I36+I37+I38+I39+I40 -> -13428.458 | J41: =J32+J33+J34+J35+J36+J37+J38+J39+J40 -> -13586.625 | ... BJ41: =BJ32+BJ33+BJ34+BJ35+BJ36+BJ37+BJ38+BJ39+BJ40 -> -14140.22
A42: EBITDA | C42: =C29+C41 -> -7522.9279 | D42: =D29+D41 -> -6247.6171 | E42: =E29+E41 -> -4972.3063 | F42: =F29+F41 -> -3696.9955 | G42: =G29+G41 -> -2421.6847 | H42: =H29+H41 -> 4264.0356 | I42: =I29+I41 -> 6003.0958 | J42: =J29+J41 -> 7742.156 | ... BJ42: =BJ29+BJ41 -> 8932.4928
A44: Profit after depreciation, interest, tax
A45: EBIT | C45: =C42+C62 -> -11332.65 | D45: =D42+D62 -> -10061.506 | E45: =E42+E62 -> -8790.3619 | F45: =F42+F62 -> -7519.2177 | G45: =G42+G62 -> -6248.0736 | H45: =H42+H62 -> 433.48006 | I45: =I42+I62 -> 2168.3736 | J45: =J42+J62 -> 3903.2671 | ... BJ45: =BJ42+BJ62 -> 4861.4804
A46: Interest on loan (balance after drawdown, start of period) | C46: =-(C67+C68)*Inputs!$E$67/12 -> -2916.6667 | D46: =-(D67+D68)*Inputs!$E$67/12 -> -2913.0662 | E46: =-(E67+E68)*Inputs!$E$67/12 -> -2909.4447 | F46: =-(F67+F68)*Inputs!$E$67/12 -> -2905.802 | G46: =-(G67+G68)*Inputs!$E$67/12 -> -2902.1381 | H46: =-(H67+H68)*Inputs!$E$67/12 -> -2898.4529 | I46: =-(I67+I68)*Inputs!$E$67/12 -> -2894.7461 | J46: =-(J67+J68)*Inputs!$E$67/12 -> -2891.0178 | ... BJ46: =-(BJ67+BJ68)*Inputs!$E$67/12 -> -2663.9707
A47: Pre-tax income | C47: =C45+C46 -> -14249.317 | D47: =D45+D46 -> -12974.572 | E47: =E45+E46 -> -11699.807 | F47: =F45+F46 -> -10425.02 | G47: =G45+G46 -> -9150.2117 | H47: =H45+H46 -> -2464.9728 | I47: =I45+I46 -> -726.37254 | J47: =J45+J46 -> 1012.2494 | ... BJ47: =BJ45+BJ46 -> 2197.5098
A48: Helper: cumulative pre-tax income | C48: =C47 -> -14249.317 | D48: =C48+D47 -> -27223.889 | E48: =D48+E47 -> -38923.696 | F48: =E48+F47 -> -49348.715 | G48: =F48+G47 -> -58498.927 | H48: =G48+H47 -> -60963.9 | I48: =H48+I47 -> -61690.272 | J48: =I48+J47 -> -60678.023 | K48: =J48+K47 -> -64728.788 | ... BJ48: =BI48+BJ47 -> 73664.43
A49: Helper: cumulative taxable income (losses carried forward) | C49: =MAX(0,C48) -> 0 | D49: =MAX(C49,D48) -> 0 | E49: =MAX(D49,E48) -> 0 | F49: =MAX(E49,F48) -> 0 | G49: =MAX(F49,G48) -> 0 | H49: =MAX(G49,H48) -> 0 | I49: =MAX(H49,I48) -> 0 | J49: =MAX(I49,J48) -> 0 | K49: =MAX(J49,K48) -> 0 | ... BJ49: =MAX(BI49,BJ48) -> 73664.43
A50: Income tax | C50: =-C49*Inputs!$E$77 -> 0 | D50: =-(D49-C49)*Inputs!$E$77 -> 0 | E50: =-(E49-D49)*Inputs!$E$77 -> 0 | F50: =-(F49-E49)*Inputs!$E$77 -> 0 | G50: =-(G49-F49)*Inputs!$E$77 -> 0 | H50: =-(H49-G49)*Inputs!$E$77 -> 0 | I50: =-(I49-H49)*Inputs!$E$77 -> 0 | J50: =-(J49-I49)*Inputs!$E$77 -> 0 | K50: =-(K49-J49)*Inputs!$E$77 -> 0 | ... BJ50: =-(BJ49-BI49)*Inputs!$E$77 -> -461.47705
A51: Net income | C51: =C47+C50 -> -14249.317 | D51: =D47+D50 -> -12974.572 | E51: =E47+E50 -> -11699.807 | F51: =F47+F50 -> -10425.02 | G51: =G47+G50 -> -9150.2117 | H51: =H47+H50 -> -2464.9728 | I51: =I47+I50 -> -726.37254 | J51: =J47+J50 -> 1012.2494 | ... BJ51: =BJ47+BJ50 -> 1736.0327
A53: Fixed assets & capital spending
A54: Property purchase | C54: =IF(C$4=1,Inputs!$E$42,0) -> 720000 | D54: =IF(D$4=1,Inputs!$E$42,0) -> 0 | E54: =IF(E$4=1,Inputs!$E$42,0) -> 0 | F54: =IF(F$4=1,Inputs!$E$42,0) -> 0 | G54: =IF(G$4=1,Inputs!$E$42,0) -> 0 | H54: =IF(H$4=1,Inputs!$E$42,0) -> 0 | I54: =IF(I$4=1,Inputs!$E$42,0) -> 0 | J54: =IF(J$4=1,Inputs!$E$42,0) -> 0 | ... BJ54: =IF(BJ$4=1,Inputs!$E$42,0) -> 0
A55: of which land (not depreciated) | C55: =IF(C$4=1,Inputs!$E$42*Inputs!$E$43,0) -> 180000 | D55: =IF(D$4=1,Inputs!$E$42*Inputs!$E$43,0) -> 0 | E55: =IF(E$4=1,Inputs!$E$42*Inputs!$E$43,0) -> 0 | F55: =IF(F$4=1,Inputs!$E$42*Inputs!$E$43,0) -> 0 | G55: =IF(G$4=1,Inputs!$E$42*Inputs!$E$43,0) -> 0 | H55: =IF(H$4=1,Inputs!$E$42*Inputs!$E$43,0) -> 0 | I55: =IF(I$4=1,Inputs!$E$42*Inputs!$E$43,0) -> 0 | J55: =IF(J$4=1,Inputs!$E$42*Inputs!$E$43,0) -> 0 | ... BJ55: =IF(BJ$4=1,Inputs!$E$42*Inputs!$E$43,0) -> 0
A56: Room furnishing & fit-out | C56: =IF(C$4=1,Inputs!$E$7*Inputs!$E$44,0) -> 75000 | D56: =IF(D$4=1,Inputs!$E$7*Inputs!$E$44,0) -> 0 | E56: =IF(E$4=1,Inputs!$E$7*Inputs!$E$44,0) -> 0 | F56: =IF(F$4=1,Inputs!$E$7*Inputs!$E$44,0) -> 0 | G56: =IF(G$4=1,Inputs!$E$7*Inputs!$E$44,0) -> 0 | H56: =IF(H$4=1,Inputs!$E$7*Inputs!$E$44,0) -> 0 | I56: =IF(I$4=1,Inputs!$E$7*Inputs!$E$44,0) -> 0 | J56: =IF(J$4=1,Inputs!$E$7*Inputs!$E$44,0) -> 0 | ... BJ56: =IF(BJ$4=1,Inputs!$E$7*Inputs!$E$44,0) -> 0
A57: Building works, kitchen & signage | C57: =IF(C$4=1,Inputs!$E$45,0) -> 70000 | D57: =IF(D$4=1,Inputs!$E$45,0) -> 0 | E57: =IF(E$4=1,Inputs!$E$45,0) -> 0 | F57: =IF(F$4=1,Inputs!$E$45,0) -> 0 | G57: =IF(G$4=1,Inputs!$E$45,0) -> 0 | H57: =IF(H$4=1,Inputs!$E$45,0) -> 0 | I57: =IF(I$4=1,Inputs!$E$45,0) -> 0 | J57: =IF(J$4=1,Inputs!$E$45,0) -> 0 | ... BJ57: =IF(BJ$4=1,Inputs!$E$45,0) -> 0
A58: FF&E replacement | C58: =Inputs!$E$7*Inputs!$E$46/12*(1+Inputs!$E$39)^(C$5-1)*1 -> 750 | D58: =Inputs!$E$7*Inputs!$E$46/12*(1+Inputs!$E$39)^(D$5-1)*1 -> 750 | E58: =Inputs!$E$7*Inputs!$E$46/12*(1+Inputs!$E$39)^(E$5-1)*1 -> 750 | F58: =Inputs!$E$7*Inputs!$E$46/12*(1+Inputs!$E$39)^(F$5-1)*1 -> 750 | G58: =Inputs!$E$7*Inputs!$E$46/12*(1+Inputs!$E$39)^(G$5-1)*1 -> 750 | H58: =Inputs!$E$7*Inputs!$E$46/12*(1+Inputs!$E$39)^(H$5-1)*1 -> 750 | I58: =Inputs!$E$7*Inputs!$E$46/12*(1+Inputs!$E$39)^(I$5-1)*1 -> 750 | J58: =Inputs!$E$7*Inputs!$E$46/12*(1+Inputs!$E$39)^(J$5-1)*1 -> 750 | ... BJ58: =Inputs!$E$7*Inputs!$E$46/12*(1+Inputs!$E$39)^(BJ$5-1)*1 -> 844.13161
A59: Capital spending | C59: =C54+C56+C57+C58 -> 865750 | D59: =D54+D56+D57+D58 -> 750 | E59: =E54+E56+E57+E58 -> 750 | F59: =F54+F56+F57+F58 -> 750 | G59: =G54+G56+G57+G58 -> 750 | H59: =H54+H56+H57+H58 -> 750 | I59: =I54+I56+I57+I58 -> 750 | J59: =J54+J56+J57+J58 -> 750 | ... BJ59: =BJ54+BJ56+BJ57+BJ58 -> 844.13161
A60: Fixed assets at cost | C60: =C59 -> 865750 | D60: =C60+D59 -> 866500 | E60: =D60+E59 -> 867250 | F60: =E60+F59 -> 868000 | G60: =F60+G59 -> 868750 | H60: =G60+H59 -> 869500 | I60: =H60+I59 -> 870250 | J60: =I60+J59 -> 871000 | K60: =J60+K59 -> 871750 | ... BJ60: =BI60+BJ59 -> 912782.22
A61: Land at cost (not depreciated) | C61: =C55 -> 180000 | D61: =C61+D55 -> 180000 | E61: =D61+E55 -> 180000 | F61: =E61+F55 -> 180000 | G61: =F61+G55 -> 180000 | H61: =G61+H55 -> 180000 | I61: =H61+I55 -> 180000 | J61: =I61+J55 -> 180000 | K61: =J61+K55 -> 180000 | ... BJ61: =BI61+BJ55 -> 180000
A62: Depreciation | C62: =-MIN((C60-C61)/MAX(1,Inputs!$E$76*12),C59-C61) -> -3809.7222 | D62: =-MIN((D60-D61)/MAX(1,Inputs!$E$76*12),C64+D59-D61) -> -3813.8889 | E62: =-MIN((E60-E61)/MAX(1,Inputs!$E$76*12),D64+E59-E61) -> -3818.0556 | F62: =-MIN((F60-F61)/MAX(1,Inputs!$E$76*12),E64+F59-F61) -> -3822.2222 | G62: =-MIN((G60-G61)/MAX(1,Inputs!$E$76*12),F64+G59-G61) -> -3826.3889 | H62: =-MIN((H60-H61)/MAX(1,Inputs!$E$76*12),G64+H59-H61) -> -3830.5556 | I62: =-MIN((I60-I61)/MAX(1,Inputs!$E$76*12),H64+I59-I61) -> -3834.7222 | J62: =-MIN((J60-J61)/MAX(1,Inputs!$E$76*12),I64+J59-J61) -> -3838.8889 | K62: =-MIN((K60-K61)/MAX(1,Inputs!$E$76*12),J64+K59-K61) -> -3843.0556 | ... BJ62: =-MIN((BJ60-BJ61)/MAX(1,Inputs!$E$76*12),BI64+BJ59-BJ61) -> -4071.0123
A63: Accumulated depreciation | C63: =C62 -> -3809.7222 | D63: =C63+D62 -> -7623.6111 | E63: =D63+E62 -> -11441.667 | F63: =E63+F62 -> -15263.889 | G63: =F63+G62 -> -19090.278 | H63: =G63+H62 -> -22920.833 | I63: =H63+I62 -> -26755.556 | J63: =I63+J62 -> -30594.444 | K63: =J63+K62 -> -34437.5 | ... BJ63: =BI63+BJ62 -> -236241.52
A64: Net fixed assets | C64: =C60+C63 -> 861940.28 | D64: =D60+D63 -> 858876.39 | E64: =E60+E63 -> 855808.33 | F64: =F60+F63 -> 852736.11 | G64: =G60+G63 -> 849659.72 | H64: =H60+H63 -> 846579.17 | I64: =I60+I63 -> 843494.44 | J64: =J60+J63 -> 840405.56 | ... BJ64: =BJ60+BJ63 -> 676540.7
A66: Debt
A67: Loan — opening balance | C67: =0 -> 0 | D67: =C72 -> 499382.77 | E67: =D72 -> 498761.94 | F67: =E72 -> 498137.49 | G67: =F72 -> 497509.4 | H67: =G72 -> 496877.64 | I67: =H72 -> 496242.19 | J67: =I72 -> 495603.04 | K67: =J72 -> 494960.17 | ... BJ67: =BI72 -> 456680.69
A68: Loan drawdown | C68: =IF(C$4=1,Inputs!$E$66,0) -> 500000 | D68: =IF(D$4=1,Inputs!$E$66,0) -> 0 | E68: =IF(E$4=1,Inputs!$E$66,0) -> 0 | F68: =IF(F$4=1,Inputs!$E$66,0) -> 0 | G68: =IF(G$4=1,Inputs!$E$66,0) -> 0 | H68: =IF(H$4=1,Inputs!$E$66,0) -> 0 | I68: =IF(I$4=1,Inputs!$E$66,0) -> 0 | J68: =IF(J$4=1,Inputs!$E$66,0) -> 0 | ... BJ68: =IF(BJ$4=1,Inputs!$E$66,0) -> 0
A69: Scheduled loan payment (principal + interest, level) | C69: =-PMT(Inputs!$E$67/12,MAX(1,Inputs!$E$68*12),Inputs!$E$66) -> 3533.896 | D69: =-PMT(Inputs!$E$67/12,MAX(1,Inputs!$E$68*12),Inputs!$E$66) -> 3533.896 | E69: =-PMT(Inputs!$E$67/12,MAX(1,Inputs!$E$68*12),Inputs!$E$66) -> 3533.896 | F69: =-PMT(Inputs!$E$67/12,MAX(1,Inputs!$E$68*12),Inputs!$E$66) -> 3533.896 | G69: =-PMT(Inputs!$E$67/12,MAX(1,Inputs!$E$68*12),Inputs!$E$66) -> 3533.896 | H69: =-PMT(Inputs!$E$67/12,MAX(1,Inputs!$E$68*12),Inputs!$E$66) -> 3533.896 | I69: =-PMT(Inputs!$E$67/12,MAX(1,Inputs!$E$68*12),Inputs!$E$66) -> 3533.896 | J69: =-PMT(Inputs!$E$67/12,MAX(1,Inputs!$E$68*12),Inputs!$E$66) -> 3533.896 | ... BJ69: =-PMT(Inputs!$E$67/12,MAX(1,Inputs!$E$68*12),Inputs!$E$66) -> 3533.896
A70: Loan repayment (principal) | C70: =-MIN(C67+C68,C69+C46) -> -617.22932 | D70: =-MIN(D67+D68,D69+D46) -> -620.82982 | E70: =-MIN(E67+E68,E69+E46) -> -624.45133 | F70: =-MIN(F67+F68,F69+F46) -> -628.09396 | G70: =-MIN(G67+G68,G69+G46) -> -631.75785 | H70: =-MIN(H67+H68,H69+H46) -> -635.4431 | I70: =-MIN(I67+I68,I69+I46) -> -639.14985 | J70: =-MIN(J67+J68,J69+J46) -> -642.87823 | ... BJ70: =-MIN(BJ67+BJ68,BJ69+BJ46) -> -869.92531
A71: Debt service (interest + principal) | C71: =C46+C70 -> -3533.896 | D71: =D46+D70 -> -3533.896 | E71: =E46+E70 -> -3533.896 | F71: =F46+F70 -> -3533.896 | G71: =G46+G70 -> -3533.896 | H71: =H46+H70 -> -3533.896 | I71: =I46+I70 -> -3533.896 | J71: =J46+J70 -> -3533.896 | ... BJ71: =BJ46+BJ70 -> -3533.896
A72: Loan — closing balance | C72: =C67+C68+C70 -> 499382.77 | D72: =D67+D68+D70 -> 498761.94 | E72: =E67+E68+E70 -> 498137.49 | F72: =F67+F68+F70 -> 497509.4 | G72: =G67+G68+G70 -> 496877.64 | H72: =H67+H68+H70 -> 496242.19 | I72: =I67+I68+I70 -> 495603.04 | J72: =J67+J68+J70 -> 494960.17 | ... BJ72: =BJ67+BJ68+BJ70 -> 455810.76
A74: Working capital
A75: Accounts receivable | C75: =C20*Inputs!$E$71/30 -> 1154.1259 | D75: =D20*Inputs!$E$71/30 -> 1327.2447 | E75: =E20*Inputs!$E$71/30 -> 1500.3636 | F75: =F20*Inputs!$E$71/30 -> 1673.4825 | G75: =G20*Inputs!$E$71/30 -> 1846.6014 | H75: =H20*Inputs!$E$71/30 -> 2754.164 | I75: =I20*Inputs!$E$71/30 -> 2990.2352 | J75: =J20*Inputs!$E$71/30 -> 3226.3064 | ... BJ75: =BJ20*Inputs!$E$71/30 -> 3515.1412
A76: Inventory | C76: =-C28*Inputs!$E$72/30 -> 686.59223 | D76: =-D28*Inputs!$E$72/30 -> 720.58106 | E76: =-E28*Inputs!$E$72/30 -> 754.56989 | F76: =-F28*Inputs!$E$72/30 -> 788.55873 | G76: =-G28*Inputs!$E$72/30 -> 822.54756 | H76: =-H28*Inputs!$E$72/30 -> 1000.7314 | I76: =-I28*Inputs!$E$72/30 -> 1047.0799 | J76: =-J28*Inputs!$E$72/30 -> 1093.4283 | ... BJ76: =-BJ28*Inputs!$E$72/30 -> 1207.8699
A77: Accounts payable | C77: =-C28*Inputs!$E$73/30 -> 5721.6019 | D77: =-D28*Inputs!$E$73/30 -> 6004.8422 | E77: =-E28*Inputs!$E$73/30 -> 6288.0825 | F77: =-F28*Inputs!$E$73/30 -> 6571.3227 | G77: =-G28*Inputs!$E$73/30 -> 6854.563 | H77: =-H28*Inputs!$E$73/30 -> 8339.4287 | I77: =-I28*Inputs!$E$73/30 -> 8725.6655 | J77: =-J28*Inputs!$E$73/30 -> 9111.9022 | ... BJ77: =-BJ28*Inputs!$E$73/30 -> 10065.583
A78: (Increase) / decrease in receivables | C78: =-C75 -> -1154.1259 | D78: =C75-D75 -> -173.11888 | E78: =D75-E75 -> -173.11888 | F78: =E75-F75 -> -173.11888 | G78: =F75-G75 -> -173.11888 | H78: =G75-H75 -> -907.56261 | I78: =H75-I75 -> -236.0712 | J78: =I75-J75 -> -236.0712 | K78: =J75-K75 -> 687.22949 | ... BJ78: =BI75-BJ75 -> 0
A79: (Increase) / decrease in inventory | C79: =-C76 -> -686.59223 | D79: =C76-D76 -> -33.988834 | E79: =D76-E76 -> -33.988834 | F79: =E76-F76 -> -33.988834 | G79: =F76-G76 -> -33.988834 | H79: =G76-H76 -> -178.18389 | I79: =H76-I76 -> -46.34841 | J79: =I76-J76 -> -46.34841 | K79: =J76-K76 -> 134.92537 | ... BJ79: =BI76-BJ76 -> 0
A80: Increase / (decrease) in payables | C80: =C77 -> 5721.6019 | D80: =D77-C77 -> 283.24028 | E80: =E77-D77 -> 283.24028 | F80: =F77-E77 -> 283.24028 | G80: =G77-F77 -> 283.24028 | H80: =H77-G77 -> 1484.8657 | I80: =I77-H77 -> 386.23675 | J80: =J77-I77 -> 386.23675 | K80: =K77-J77 -> -1124.3781 | ... BJ80: =BJ77-BI77 -> 0
A82: Cash flow
A83: Operating cash flow | C83: =C51-C62+C78+C79+C80 -> -6558.7108 | D83: =D51-D62+D78+D79+D80 -> -9084.5507 | E83: =E51-E62+E78+E79+E80 -> -7805.6184 | F83: =F51-F62+F78+F79+F80 -> -6526.665 | G83: =G51-G62+G78+G79+G80 -> -5247.6903 | H83: =H51-H62+H78+H79+H80 -> 1764.702 | I83: =I51-I62+I78+I79+I80 -> 3212.1668 | J83: =J51-J62+J78+J79+J80 -> 4954.9554 | ... BJ83: =BJ51-BJ62+BJ78+BJ79+BJ80 -> 5807.0451
A84: Investing cash flow (capex) | C84: =-C59 -> -865750 | D84: =-D59 -> -750 | E84: =-E59 -> -750 | F84: =-F59 -> -750 | G84: =-G59 -> -750 | H84: =-H59 -> -750 | I84: =-I59 -> -750 | J84: =-J59 -> -750 | ... BJ84: =-BJ59 -> -844.13161
A85: Equity raised | C85: =IF(C$4=1,Inputs!$E$65,0) -> 430000 | D85: =IF(D$4=1,Inputs!$E$65,0) -> 0 | E85: =IF(E$4=1,Inputs!$E$65,0) -> 0 | F85: =IF(F$4=1,Inputs!$E$65,0) -> 0 | G85: =IF(G$4=1,Inputs!$E$65,0) -> 0 | H85: =IF(H$4=1,Inputs!$E$65,0) -> 0 | I85: =IF(I$4=1,Inputs!$E$65,0) -> 0 | J85: =IF(J$4=1,Inputs!$E$65,0) -> 0 | ... BJ85: =IF(BJ$4=1,Inputs!$E$65,0) -> 0
A86: Financing cash flow | C86: =C85+C68+C70 -> 929382.77 | D86: =D85+D68+D70 -> -620.82982 | E86: =E85+E68+E70 -> -624.45133 | F86: =F85+F68+F70 -> -628.09396 | G86: =G85+G68+G70 -> -631.75785 | H86: =H85+H68+H70 -> -635.4431 | I86: =I85+I68+I70 -> -639.14985 | J86: =J85+J68+J70 -> -642.87823 | ... BJ86: =BJ85+BJ68+BJ70 -> -869.92531
A87: Net cash flow | C87: =C83+C84+C86 -> 57074.06 | D87: =D83+D84+D86 -> -10455.381 | E87: =E83+E84+E86 -> -9180.0697 | F87: =F83+F84+F86 -> -7904.7589 | G87: =G83+G84+G86 -> -6629.4481 | H87: =H83+H84+H86 -> 379.25886 | I87: =I83+I84+I86 -> 1823.017 | J87: =J83+J84+J86 -> 3562.0772 | ... BJ87: =BJ83+BJ84+BJ86 -> 4092.9881
A88: Opening cash | C88: =0 -> 0 | D88: =C89 -> 57074.06 | E88: =D89 -> 46618.679 | F88: =E89 -> 37438.61 | G88: =F89 -> 29533.851 | H88: =G89 -> 22904.403 | I88: =H89 -> 23283.661 | J88: =I89 -> 25106.678 | K88: =J89 -> 28668.756 | ... BJ88: =BI89 -> 268714.54
A89: Closing cash | C89: =C88+C87 -> 57074.06 | D89: =D88+D87 -> 46618.679 | E89: =E88+E87 -> 37438.61 | F89: =F88+F87 -> 29533.851 | G89: =G88+G87 -> 22904.403 | H89: =H88+H87 -> 23283.661 | I89: =I88+I87 -> 25106.678 | J89: =J88+J87 -> 28668.756 | ... BJ89: =BJ88+BJ87 -> 272807.53
A90: Helper: EBITDA positive (1/0) | C90: =IF(C42>0,1,0) -> 0 | D90: =IF(D42>0,1,0) -> 0 | E90: =IF(E42>0,1,0) -> 0 | F90: =IF(F42>0,1,0) -> 0 | G90: =IF(G42>0,1,0) -> 0 | H90: =IF(H42>0,1,0) -> 1 | I90: =IF(I42>0,1,0) -> 1 | J90: =IF(J42>0,1,0) -> 1 | ... BJ90: =IF(BJ42>0,1,0) -> 1
A92: Goal modules
A93: Helper: net income positive (1/0) | C93: =IF(C51>0,1,0) -> 0 | D93: =IF(D51>0,1,0) -> 0 | E93: =IF(E51>0,1,0) -> 0 | F93: =IF(F51>0,1,0) -> 0 | G93: =IF(G51>0,1,0) -> 0 | H93: =IF(H51>0,1,0) -> 0 | I93: =IF(I51>0,1,0) -> 0 | J93: =IF(J51>0,1,0) -> 1 | ... BJ93: =IF(BJ51>0,1,0) -> 1
A94: Cash flow before financing (operating + investing) | C94: =C83+C84 -> -872308.71 | D94: =D83+D84 -> -9834.5507 | E94: =E83+E84 -> -8555.6184 | F94: =F83+F84 -> -7276.665 | G94: =G83+G84 -> -5997.6903 | H94: =H83+H84 -> 1014.702 | I94: =I83+I84 -> 2462.1668 | J94: =J83+J84 -> 4204.9554 | ... BJ94: =BJ83+BJ84 -> 4962.9135
A95: Cumulative cash flow before financing | C95: =C94 -> -872308.71 | D95: =C95+D94 -> -882143.26 | E95: =D95+E94 -> -890698.88 | F95: =E95+F94 -> -897975.54 | G95: =F95+G94 -> -903973.24 | H95: =G95+H94 -> -902958.53 | I95: =H95+I94 -> -900496.37 | J95: =I95+J94 -> -896291.41 | K95: =J95+K94 -> -897551.34 | ... BJ95: =BI95+BJ94 -> -613003.23
A96: Helper: lowest cumulative cash flow so far | C96: =C95 -> -872308.71 | D96: =MIN(C96,D95) -> -882143.26 | E96: =MIN(D96,E95) -> -890698.88 | F96: =MIN(E96,F95) -> -897975.54 | G96: =MIN(F96,G95) -> -903973.24 | H96: =MIN(G96,H95) -> -903973.24 | I96: =MIN(H96,I95) -> -903973.24 | J96: =MIN(I96,J95) -> -903973.24 | K96: =MIN(J96,K95) -> -903973.24 | ... BJ96: =MIN(BI96,BJ95) -> -903973.24
A97: Helper: investment paid back (1/0) | C97: =IF(AND(C95>=0,C96<0),1,0) -> 0 | D97: =IF(AND(D95>=0,D96<0),1,0) -> 0 | E97: =IF(AND(E95>=0,E96<0),1,0) -> 0 | F97: =IF(AND(F95>=0,F96<0),1,0) -> 0 | G97: =IF(AND(G95>=0,G96<0),1,0) -> 0 | H97: =IF(AND(H95>=0,H96<0),1,0) -> 0 | I97: =IF(AND(I95>=0,I96<0),1,0) -> 0 | J97: =IF(AND(J95>=0,J96<0),1,0) -> 0 | ... BJ97: =IF(AND(BJ95>=0,BJ96<0),1,0) -> 0
A98: Unlevered free cash flow (operating + after-tax interest − capex) | C98: =C83-C46*(1-Inputs!$E$77)+C84 -> -870004.54 | D98: =D83-D46*(1-Inputs!$E$77)+D84 -> -7533.2284 | E98: =E83-E46*(1-Inputs!$E$77)+E84 -> -6257.1571 | F98: =F83-F46*(1-Inputs!$E$77)+F84 -> -4981.0814 | G98: =G83-G46*(1-Inputs!$E$77)+G84 -> -3705.0011 | H98: =H83-H46*(1-Inputs!$E$77)+H84 -> 3304.4797 | I98: =I83-I46*(1-Inputs!$E$77)+I84 -> 4749.0163 | J98: =J83-J46*(1-Inputs!$E$77)+J84 -> 6488.8594 | ... BJ98: =BJ83-BJ46*(1-Inputs!$E$77)+BJ84 -> 7067.4503
A100: Balance sheet
A101: Paid-in capital | C101: =C85 -> 430000 | D101: =C101+D85 -> 430000 | E101: =D101+E85 -> 430000 | F101: =E101+F85 -> 430000 | G101: =F101+G85 -> 430000 | H101: =G101+H85 -> 430000 | I101: =H101+I85 -> 430000 | J101: =I101+J85 -> 430000 | K101: =J101+K85 -> 430000 | ... BJ101: =BI101+BJ85 -> 430000
A102: Retained earnings | C102: =C51 -> -14249.317 | D102: =C102+D51 -> -27223.889 | E102: =D102+E51 -> -38923.696 | F102: =E102+F51 -> -49348.715 | G102: =F102+G51 -> -58498.927 | H102: =G102+H51 -> -60963.9 | I102: =H102+I51 -> -61690.272 | J102: =I102+J51 -> -60678.023 | K102: =J102+K51 -> -64728.788 | ... BJ102: =BI102+BJ51 -> 58194.9
A103: Total assets | C103: =C89+C75+C76+C64 -> 920855.06 | D103: =D89+D75+D76+D64 -> 907542.89 | E103: =E89+E75+E76+E64 -> 895501.88 | F103: =F89+F75+F76+F64 -> 884732 | G103: =G89+G75+G76+G64 -> 875233.27 | H103: =H89+H75+H76+H64 -> 873617.72 | I103: =I89+I75+I76+I64 -> 872638.44 | J103: =J89+J75+J76+J64 -> 873394.05 | ... BJ103: =BJ89+BJ75+BJ76+BJ64 -> 954071.24
A104: Total liabilities | C104: =C77+C72 -> 505104.37 | D104: =D77+D72 -> 504766.78 | E104: =E77+E72 -> 504425.57 | F104: =F77+F72 -> 504080.72 | G104: =G77+G72 -> 503732.2 | H104: =H77+H72 -> 504581.62 | I104: =I77+I72 -> 504328.71 | J104: =J77+J72 -> 504072.07 | ... BJ104: =BJ77+BJ72 -> 465876.34
A105: Total equity | C105: =C101+C102 -> 415750.68 | D105: =D101+D102 -> 402776.11 | E105: =E101+E102 -> 391076.3 | F105: =F101+F102 -> 380651.28 | G105: =G101+G102 -> 371501.07 | H105: =H101+H102 -> 369036.1 | I105: =I101+I102 -> 368309.73 | J105: =J101+J102 -> 369321.98 | ... BJ105: =BJ101+BJ102 -> 488194.9
A106: Total liabilities & equity | C106: =C104+C105 -> 920855.06 | D106: =D104+D105 -> 907542.89 | E106: =E104+E105 -> 895501.88 | F106: =F104+F105 -> 884732 | G106: =G104+G105 -> 875233.27 | H106: =H104+H105 -> 873617.72 | I106: =I104+I105 -> 872638.44 | J106: =J104+J105 -> 873394.05 | ... BJ106: =BJ104+BJ105 -> 954071.24
A107: Check: assets − liabilities − equity | C107: =C103-C106 -> 0 | D107: =D103-D106 -> 0 | E107: =E103-E106 -> 0 | F107: =F103-F106 -> 0 | G107: =G103-G106 -> 0 | H107: =H103-H106 -> 0 | I107: =I103-I106 -> 0 | J107: =J103-J106 -> 0 | ... BJ107: =BJ103-BJ106 -> 0

Sheet Headcount
A1: Headcount & payroll | D1: =HYPERLINK("#'Cover'!A1","◂ Contents") -> ◂ Contents
A2: $ unless stated; costs shown as negatives. Every period uses the same formula.
A3: Month | C3: M1 | D3: M2 | E3: M3 | F3: M4 | G3: M5 | H3: M6 | I3: M7 | J3: M8 | K3: M9 | L3: M10 | M3: M11 | N3: M12 | O3: M13 | P3: M14 | Q3: M15 | R3: M16 | S3: M17 | T3: M18 | U3: M19 | V3: M20 | W3: M21 | X3: M22 | Y3: M23 | Z3: M24 | AA3: M25 | AB3: M26 | AC3: M27 | AD3: M28 | AE3: M29 | AF3: M30 | AG3: M31 | AH3: M32 | AI3: M33 | AJ3: M34 | AK3: M35 | AL3: M36 | AM3: M37 | AN3: M38 | AO3: M39 | AP3: M40 | AQ3: M41 | AR3: M42 | AS3: M43 | AT3: M44 | AU3: M45 | AV3: M46 | AW3: M47 | AX3: M48 | AY3: M49 | AZ3: M50 | BA3: M51 | BB3: M52 | BC3: M53 | BD3: M54 | BE3: M55 | BF3: M56 | BG3: M57 | BH3: M58 | BI3: M59 | BJ3: M60
A4: Period # | C4: 1 | D4: 2 | E4: 3 | F4: 4 | G4: 5 | H4: 6 | I4: 7 | J4: 8 | K4: 9 | L4: 10 | M4: 11 | N4: 12 | O4: 13 | P4: 14 | Q4: 15 | R4: 16 | S4: 17 | T4: 18 | U4: 19 | V4: 20 | W4: 21 | X4: 22 | Y4: 23 | Z4: 24 | AA4: 25 | AB4: 26 | AC4: 27 | AD4: 28 | AE4: 29 | AF4: 30 | AG4: 31 | AH4: 32 | AI4: 33 | AJ4: 34 | AK4: 35 | AL4: 36 | AM4: 37 | AN4: 38 | AO4: 39 | AP4: 40 | AQ4: 41 | AR4: 42 | AS4: 43 | AT4: 44 | AU4: 45 | AV4: 46 | AW4: 47 | AX4: 48 | AY4: 49 | AZ4: 50 | BA4: 51 | BB4: 52 | BC4: 53 | BD4: 54 | BE4: 55 | BF4: 56 | BG4: 57 | BH4: 58 | BI4: 59 | BJ4: 60
A5: Year # | C5: =ROUNDUP(C4*1/12,0) -> 1 | D5: =ROUNDUP(D4*1/12,0) -> 1 | E5: =ROUNDUP(E4*1/12,0) -> 1 | F5: =ROUNDUP(F4*1/12,0) -> 1 | G5: =ROUNDUP(G4*1/12,0) -> 1 | H5: =ROUNDUP(H4*1/12,0) -> 1 | I5: =ROUNDUP(I4*1/12,0) -> 1 | J5: =ROUNDUP(J4*1/12,0) -> 1 | ... BJ5: =ROUNDUP(BJ4*1/12,0) -> 5
A7: Headcount (FTE)
A8: Housekeeping staff — FTE | C8: =Inputs!$E$49*(1+Inputs!$E$51)^(C$5-1)*MAX(0,MIN(1,C$4*1-Inputs!$E$52+1))/1 -> 1.5 | D8: =Inputs!$E$49*(1+Inputs!$E$51)^(D$5-1)*MAX(0,MIN(1,D$4*1-Inputs!$E$52+1))/1 -> 1.5 | E8: =Inputs!$E$49*(1+Inputs!$E$51)^(E$5-1)*MAX(0,MIN(1,E$4*1-Inputs!$E$52+1))/1 -> 1.5 | F8: =Inputs!$E$49*(1+Inputs!$E$51)^(F$5-1)*MAX(0,MIN(1,F$4*1-Inputs!$E$52+1))/1 -> 1.5 | G8: =Inputs!$E$49*(1+Inputs!$E$51)^(G$5-1)*MAX(0,MIN(1,G$4*1-Inputs!$E$52+1))/1 -> 1.5 | H8: =Inputs!$E$49*(1+Inputs!$E$51)^(H$5-1)*MAX(0,MIN(1,H$4*1-Inputs!$E$52+1))/1 -> 1.5 | I8: =Inputs!$E$49*(1+Inputs!$E$51)^(I$5-1)*MAX(0,MIN(1,I$4*1-Inputs!$E$52+1))/1 -> 1.5 | J8: =Inputs!$E$49*(1+Inputs!$E$51)^(J$5-1)*MAX(0,MIN(1,J$4*1-Inputs!$E$52+1))/1 -> 1.5 | ... BJ8: =Inputs!$E$49*(1+Inputs!$E$51)^(BJ$5-1)*MAX(0,MIN(1,BJ$4*1-Inputs!$E$52+1))/1 -> 1.5
A9: Host, manager & front desk — FTE | C9: =Inputs!$E$53*(1+Inputs!$E$55)^(C$5-1)*MAX(0,MIN(1,C$4*1-Inputs!$E$56+1))/1 -> 1 | D9: =Inputs!$E$53*(1+Inputs!$E$55)^(D$5-1)*MAX(0,MIN(1,D$4*1-Inputs!$E$56+1))/1 -> 1 | E9: =Inputs!$E$53*(1+Inputs!$E$55)^(E$5-1)*MAX(0,MIN(1,E$4*1-Inputs!$E$56+1))/1 -> 1 | F9: =Inputs!$E$53*(1+Inputs!$E$55)^(F$5-1)*MAX(0,MIN(1,F$4*1-Inputs!$E$56+1))/1 -> 1 | G9: =Inputs!$E$53*(1+Inputs!$E$55)^(G$5-1)*MAX(0,MIN(1,G$4*1-Inputs!$E$56+1))/1 -> 1 | H9: =Inputs!$E$53*(1+Inputs!$E$55)^(H$5-1)*MAX(0,MIN(1,H$4*1-Inputs!$E$56+1))/1 -> 1 | I9: =Inputs!$E$53*(1+Inputs!$E$55)^(I$5-1)*MAX(0,MIN(1,I$4*1-Inputs!$E$56+1))/1 -> 1 | J9: =Inputs!$E$53*(1+Inputs!$E$55)^(J$5-1)*MAX(0,MIN(1,J$4*1-Inputs!$E$56+1))/1 -> 1 | ... BJ9: =Inputs!$E$53*(1+Inputs!$E$55)^(BJ$5-1)*MAX(0,MIN(1,BJ$4*1-Inputs!$E$56+1))/1 -> 1
A10: Breakfast kitchen & maintenance — FTE | C10: =Inputs!$E$57*(1+Inputs!$E$59)^(C$5-1)*MAX(0,MIN(1,C$4*1-Inputs!$E$60+1))/1 -> 0.6 | D10: =Inputs!$E$57*(1+Inputs!$E$59)^(D$5-1)*MAX(0,MIN(1,D$4*1-Inputs!$E$60+1))/1 -> 0.6 | E10: =Inputs!$E$57*(1+Inputs!$E$59)^(E$5-1)*MAX(0,MIN(1,E$4*1-Inputs!$E$60+1))/1 -> 0.6 | F10: =Inputs!$E$57*(1+Inputs!$E$59)^(F$5-1)*MAX(0,MIN(1,F$4*1-Inputs!$E$60+1))/1 -> 0.6 | G10: =Inputs!$E$57*(1+Inputs!$E$59)^(G$5-1)*MAX(0,MIN(1,G$4*1-Inputs!$E$60+1))/1 -> 0.6 | H10: =Inputs!$E$57*(1+Inputs!$E$59)^(H$5-1)*MAX(0,MIN(1,H$4*1-Inputs!$E$60+1))/1 -> 0.6 | I10: =Inputs!$E$57*(1+Inputs!$E$59)^(I$5-1)*MAX(0,MIN(1,I$4*1-Inputs!$E$60+1))/1 -> 0.6 | J10: =Inputs!$E$57*(1+Inputs!$E$59)^(J$5-1)*MAX(0,MIN(1,J$4*1-Inputs!$E$60+1))/1 -> 0.6 | ... BJ10: =Inputs!$E$57*(1+Inputs!$E$59)^(BJ$5-1)*MAX(0,MIN(1,BJ$4*1-Inputs!$E$60+1))/1 -> 0.6
A11: Total FTE | C11: =C8+C9+C10 -> 3.1 | D11: =D8+D9+D10 -> 3.1 | E11: =E8+E9+E10 -> 3.1 | F11: =F8+F9+F10 -> 3.1 | G11: =G8+G9+G10 -> 3.1 | H11: =H8+H9+H10 -> 3.1 | I11: =I8+I9+I10 -> 3.1 | J11: =J8+J9+J10 -> 3.1 | ... BJ11: =BJ8+BJ9+BJ10 -> 3.1
A13: Payroll cost (salary + taxes & benefits)
A14: Housekeeping staff — payroll cost | C14: =-C8*Inputs!$E$50/12*1*(1+Inputs!$E$61)*(1+Inputs!$E$62)^(C$5-1) -> -4600 | D14: =-D8*Inputs!$E$50/12*1*(1+Inputs!$E$61)*(1+Inputs!$E$62)^(D$5-1) -> -4600 | E14: =-E8*Inputs!$E$50/12*1*(1+Inputs!$E$61)*(1+Inputs!$E$62)^(E$5-1) -> -4600 | F14: =-F8*Inputs!$E$50/12*1*(1+Inputs!$E$61)*(1+Inputs!$E$62)^(F$5-1) -> -4600 | G14: =-G8*Inputs!$E$50/12*1*(1+Inputs!$E$61)*(1+Inputs!$E$62)^(G$5-1) -> -4600 | H14: =-H8*Inputs!$E$50/12*1*(1+Inputs!$E$61)*(1+Inputs!$E$62)^(H$5-1) -> -4600 | I14: =-I8*Inputs!$E$50/12*1*(1+Inputs!$E$61)*(1+Inputs!$E$62)^(I$5-1) -> -4600 | J14: =-J8*Inputs!$E$50/12*1*(1+Inputs!$E$61)*(1+Inputs!$E$62)^(J$5-1) -> -4600 | ... BJ14: =-BJ8*Inputs!$E$50/12*1*(1+Inputs!$E$61)*(1+Inputs!$E$62)^(BJ$5-1) -> -5177.3405
A15: Host, manager & front desk — payroll cost | C15: =-C9*Inputs!$E$54/12*1*(1+Inputs!$E$61)*(1+Inputs!$E$62)^(C$5-1) -> -3833.3333 | D15: =-D9*Inputs!$E$54/12*1*(1+Inputs!$E$61)*(1+Inputs!$E$62)^(D$5-1) -> -3833.3333 | E15: =-E9*Inputs!$E$54/12*1*(1+Inputs!$E$61)*(1+Inputs!$E$62)^(E$5-1) -> -3833.3333 | F15: =-F9*Inputs!$E$54/12*1*(1+Inputs!$E$61)*(1+Inputs!$E$62)^(F$5-1) -> -3833.3333 | G15: =-G9*Inputs!$E$54/12*1*(1+Inputs!$E$61)*(1+Inputs!$E$62)^(G$5-1) -> -3833.3333 | H15: =-H9*Inputs!$E$54/12*1*(1+Inputs!$E$61)*(1+Inputs!$E$62)^(H$5-1) -> -3833.3333 | I15: =-I9*Inputs!$E$54/12*1*(1+Inputs!$E$61)*(1+Inputs!$E$62)^(I$5-1) -> -3833.3333 | J15: =-J9*Inputs!$E$54/12*1*(1+Inputs!$E$61)*(1+Inputs!$E$62)^(J$5-1) -> -3833.3333 | ... BJ15: =-BJ9*Inputs!$E$54/12*1*(1+Inputs!$E$61)*(1+Inputs!$E$62)^(BJ$5-1) -> -4314.4504
A16: Breakfast kitchen & maintenance — payroll cost | C16: =-C10*Inputs!$E$58/12*1*(1+Inputs!$E$61)*(1+Inputs!$E$62)^(C$5-1) -> -1725 | D16: =-D10*Inputs!$E$58/12*1*(1+Inputs!$E$61)*(1+Inputs!$E$62)^(D$5-1) -> -1725 | E16: =-E10*Inputs!$E$58/12*1*(1+Inputs!$E$61)*(1+Inputs!$E$62)^(E$5-1) -> -1725 | F16: =-F10*Inputs!$E$58/12*1*(1+Inputs!$E$61)*(1+Inputs!$E$62)^(F$5-1) -> -1725 | G16: =-G10*Inputs!$E$58/12*1*(1+Inputs!$E$61)*(1+Inputs!$E$62)^(G$5-1) -> -1725 | H16: =-H10*Inputs!$E$58/12*1*(1+Inputs!$E$61)*(1+Inputs!$E$62)^(H$5-1) -> -1725 | I16: =-I10*Inputs!$E$58/12*1*(1+Inputs!$E$61)*(1+Inputs!$E$62)^(I$5-1) -> -1725 | J16: =-J10*Inputs!$E$58/12*1*(1+Inputs!$E$61)*(1+Inputs!$E$62)^(J$5-1) -> -1725 | ... BJ16: =-BJ10*Inputs!$E$58/12*1*(1+Inputs!$E$61)*(1+Inputs!$E$62)^(BJ$5-1) -> -1941.5027
A17: Total payroll | C17: =C14+C15+C16 -> -10158.333 | D17: =D14+D15+D16 -> -10158.333 | E17: =E14+E15+E16 -> -10158.333 | F17: =F14+F15+F16 -> -10158.333 | G17: =G14+G15+G16 -> -10158.333 | H17: =H14+H15+H16 -> -10158.333 | I17: =I14+I15+I16 -> -10158.333 | J17: =J14+J15+J16 -> -10158.333 | ... BJ17: =BJ14+BJ15+BJ16 -> -11433.294

Sheet Scenario calc
A1: Scenario calculation — Low, Base and High side by side | D1: =HYPERLINK("#'Cover'!A1","◂ Contents") -> ◂ Contents
A2: The model's period calculation, copied three times; each copy reads its own Inputs column. Feeds the Scenarios sheet only.
A4: Low scenario — reads Inputs column B
A5: Month | C5: M1 | D5: M2 | E5: M3 | F5: M4 | G5: M5 | H5: M6 | I5: M7 | J5: M8 | K5: M9 | L5: M10 | M5: M11 | N5: M12 | O5: M13 | P5: M14 | Q5: M15 | R5: M16 | S5: M17 | T5: M18 | U5: M19 | V5: M20 | W5: M21 | X5: M22 | Y5: M23 | Z5: M24 | AA5: M25 | AB5: M26 | AC5: M27 | AD5: M28 | AE5: M29 | AF5: M30 | AG5: M31 | AH5: M32 | AI5: M33 | AJ5: M34 | AK5: M35 | AL5: M36 | AM5: M37 | AN5: M38 | AO5: M39 | AP5: M40 | AQ5: M41 | AR5: M42 | AS5: M43 | AT5: M44 | AU5: M45 | AV5: M46 | AW5: M47 | AX5: M48 | AY5: M49 | AZ5: M50 | BA5: M51 | BB5: M52 | BC5: M53 | BD5: M54 | BE5: M55 | BF5: M56 | BG5: M57 | BH5: M58 | BI5: M59 | BJ5: M60
A6: Period # | C6: 1 | D6: 2 | E6: 3 | F6: 4 | G6: 5 | H6: 6 | I6: 7 | J6: 8 | K6: 9 | L6: 10 | M6: 11 | N6: 12 | O6: 13 | P6: 14 | Q6: 15 | R6: 16 | S6: 17 | T6: 18 | U6: 19 | V6: 20 | W6: 21 | X6: 22 | Y6: 23 | Z6: 24 | AA6: 25 | AB6: 26 | AC6: 27 | AD6: 28 | AE6: 29 | AF6: 30 | AG6: 31 | AH6: 32 | AI6: 33 | AJ6: 34 | AK6: 35 | AL6: 36 | AM6: 37 | AN6: 38 | AO6: 39 | AP6: 40 | AQ6: 41 | AR6: 42 | AS6: 43 | AT6: 44 | AU6: 45 | AV6: 46 | AW6: 47 | AX6: 48 | AY6: 49 | AZ6: 50 | BA6: 51 | BB6: 52 | BC6: 53 | BD6: 54 | BE6: 55 | BF6: 56 | BG6: 57 | BH6: 58 | BI6: 59 | BJ6: 60
A7: Year # | C7: =ROUNDUP(C6*1/12,0) -> 1 | D7: =ROUNDUP(D6*1/12,0) -> 1 | E7: =ROUNDUP(E6*1/12,0) -> 1 | F7: =ROUNDUP(F6*1/12,0) -> 1 | G7: =ROUNDUP(G6*1/12,0) -> 1 | H7: =ROUNDUP(H6*1/12,0) -> 1 | I7: =ROUNDUP(I6*1/12,0) -> 1 | J7: =ROUNDUP(J6*1/12,0) -> 1 | ... BJ7: =ROUNDUP(BJ6*1/12,0) -> 5
A9: Rooms & occupancy
A10: Helper: months of the period still on the opening ramp | C10: =MAX(0,MIN(1,Inputs!$B$10-(C$6-1)*1)) -> 1 | D10: =MAX(0,MIN(1,Inputs!$B$10-(D$6-1)*1)) -> 1 | E10: =MAX(0,MIN(1,Inputs!$B$10-(E$6-1)*1)) -> 1 | F10: =MAX(0,MIN(1,Inputs!$B$10-(F$6-1)*1)) -> 1 | G10: =MAX(0,MIN(1,Inputs!$B$10-(G$6-1)*1)) -> 1 | H10: =MAX(0,MIN(1,Inputs!$B$10-(H$6-1)*1)) -> 1 | I10: =MAX(0,MIN(1,Inputs!$B$10-(I$6-1)*1)) -> 1 | J10: =MAX(0,MIN(1,Inputs!$B$10-(J$6-1)*1)) -> 1 | ... BJ10: =MAX(0,MIN(1,Inputs!$B$10-(BJ$6-1)*1)) -> 0
A11: Opening ramp factor (share of mature occupancy) | C11: =IF(Inputs!$B$10<=0,1,(C10*Inputs!$B$11+(1-Inputs!$B$11)/MAX(1,Inputs!$B$10)*(C10*(C$6-1)*1+C10*(C10-1)/2)+1-C10)/1) -> 0.3 | D11: =IF(Inputs!$B$10<=0,1,(D10*Inputs!$B$11+(1-Inputs!$B$11)/MAX(1,Inputs!$B$10)*(D10*(D$6-1)*1+D10*(D10-1)/2)+1-D10)/1) -> 0.35 | E11: =IF(Inputs!$B$10<=0,1,(E10*Inputs!$B$11+(1-Inputs!$B$11)/MAX(1,Inputs!$B$10)*(E10*(E$6-1)*1+E10*(E10-1)/2)+1-E10)/1) -> 0.4 | F11: =IF(Inputs!$B$10<=0,1,(F10*Inputs!$B$11+(1-Inputs!$B$11)/MAX(1,Inputs!$B$10)*(F10*(F$6-1)*1+F10*(F10-1)/2)+1-F10)/1) -> 0.45 | G11: =IF(Inputs!$B$10<=0,1,(G10*Inputs!$B$11+(1-Inputs!$B$11)/MAX(1,Inputs!$B$10)*(G10*(G$6-1)*1+G10*(G10-1)/2)+1-G10)/1) -> 0.5 | H11: =IF(Inputs!$B$10<=0,1,(H10*Inputs!$B$11+(1-Inputs!$B$11)/MAX(1,Inputs!$B$10)*(H10*(H$6-1)*1+H10*(H10-1)/2)+1-H10)/1) -> 0.55 | I11: =IF(Inputs!$B$10<=0,1,(I10*Inputs!$B$11+(1-Inputs!$B$11)/MAX(1,Inputs!$B$10)*(I10*(I$6-1)*1+I10*(I10-1)/2)+1-I10)/1) -> 0.6 | J11: =IF(Inputs!$B$10<=0,1,(J10*Inputs!$B$11+(1-Inputs!$B$11)/MAX(1,Inputs!$B$10)*(J10*(J$6-1)*1+J10*(J10-1)/2)+1-J10)/1) -> 0.65 | ... BJ11: =IF(Inputs!$B$10<=0,1,(BJ10*Inputs!$B$11+(1-Inputs!$B$11)/MAX(1,Inputs!$B$10)*(BJ10*(BJ$6-1)*1+BJ10*(BJ10-1)/2)+1-BJ10)/1) -> 1
A12: Season factor (June-August) | C12: =IF(AND(MOD(C$6-1,12)>=5,MOD(C$6-1,12)<=7),1+Inputs!$B$12,1-Inputs!$B$12/3) -> 0.91666667 | D12: =IF(AND(MOD(D$6-1,12)>=5,MOD(D$6-1,12)<=7),1+Inputs!$B$12,1-Inputs!$B$12/3) -> 0.91666667 | E12: =IF(AND(MOD(E$6-1,12)>=5,MOD(E$6-1,12)<=7),1+Inputs!$B$12,1-Inputs!$B$12/3) -> 0.91666667 | F12: =IF(AND(MOD(F$6-1,12)>=5,MOD(F$6-1,12)<=7),1+Inputs!$B$12,1-Inputs!$B$12/3) -> 0.91666667 | G12: =IF(AND(MOD(G$6-1,12)>=5,MOD(G$6-1,12)<=7),1+Inputs!$B$12,1-Inputs!$B$12/3) -> 0.91666667 | H12: =IF(AND(MOD(H$6-1,12)>=5,MOD(H$6-1,12)<=7),1+Inputs!$B$12,1-Inputs!$B$12/3) -> 1.25 | I12: =IF(AND(MOD(I$6-1,12)>=5,MOD(I$6-1,12)<=7),1+Inputs!$B$12,1-Inputs!$B$12/3) -> 1.25 | J12: =IF(AND(MOD(J$6-1,12)>=5,MOD(J$6-1,12)<=7),1+Inputs!$B$12,1-Inputs!$B$12/3) -> 1.25 | ... BJ12: =IF(AND(MOD(BJ$6-1,12)>=5,MOD(BJ$6-1,12)<=7),1+Inputs!$B$12,1-Inputs!$B$12/3) -> 0.91666667
A13: Available room-nights (rooms × calendar nights) | C13: =Inputs!$B$7*Inputs!$B$13*1 -> 304 | D13: =Inputs!$B$7*Inputs!$B$13*1 -> 304 | E13: =Inputs!$B$7*Inputs!$B$13*1 -> 304 | F13: =Inputs!$B$7*Inputs!$B$13*1 -> 304 | G13: =Inputs!$B$7*Inputs!$B$13*1 -> 304 | H13: =Inputs!$B$7*Inputs!$B$13*1 -> 304 | I13: =Inputs!$B$7*Inputs!$B$13*1 -> 304 | J13: =Inputs!$B$7*Inputs!$B$13*1 -> 304 | ... BJ13: =Inputs!$B$7*Inputs!$B$13*1 -> 304
A14: Occupancy (maturity × growth × ramp × season, capped at 100%) | C14: =MIN(1,Inputs!$B$8*(1+Inputs!$B$9)^(C$7-1)*C11*C12) -> 0.1375 | D14: =MIN(1,Inputs!$B$8*(1+Inputs!$B$9)^(D$7-1)*D11*D12) -> 0.16041667 | E14: =MIN(1,Inputs!$B$8*(1+Inputs!$B$9)^(E$7-1)*E11*E12) -> 0.18333333 | F14: =MIN(1,Inputs!$B$8*(1+Inputs!$B$9)^(F$7-1)*F11*F12) -> 0.20625 | G14: =MIN(1,Inputs!$B$8*(1+Inputs!$B$9)^(G$7-1)*G11*G12) -> 0.22916667 | H14: =MIN(1,Inputs!$B$8*(1+Inputs!$B$9)^(H$7-1)*H11*H12) -> 0.34375 | I14: =MIN(1,Inputs!$B$8*(1+Inputs!$B$9)^(I$7-1)*I11*I12) -> 0.375 | J14: =MIN(1,Inputs!$B$8*(1+Inputs!$B$9)^(J$7-1)*J11*J12) -> 0.40625 | ... BJ14: =MIN(1,Inputs!$B$8*(1+Inputs!$B$9)^(BJ$7-1)*BJ11*BJ12) -> 0.45833333
A15: Occupied room-nights | C15: =C13*C14 -> 41.8 | D15: =D13*D14 -> 48.766667 | E15: =E13*E14 -> 55.733333 | F15: =F13*F14 -> 62.7 | G15: =G13*G14 -> 69.666667 | H15: =H13*H14 -> 104.5 | I15: =I13*I14 -> 114 | J15: =J13*J14 -> 123.5 | ... BJ15: =BJ13*BJ14 -> 139.33333
A16: Guest stays (room-nights ÷ average length of stay) | C16: =IF(Inputs!$B$14<=0,0,C15/Inputs!$B$14) -> 23.222222 | D16: =IF(Inputs!$B$14<=0,0,D15/Inputs!$B$14) -> 27.092593 | E16: =IF(Inputs!$B$14<=0,0,E15/Inputs!$B$14) -> 30.962963 | F16: =IF(Inputs!$B$14<=0,0,F15/Inputs!$B$14) -> 34.833333 | G16: =IF(Inputs!$B$14<=0,0,G15/Inputs!$B$14) -> 38.703704 | H16: =IF(Inputs!$B$14<=0,0,H15/Inputs!$B$14) -> 58.055556 | I16: =IF(Inputs!$B$14<=0,0,I15/Inputs!$B$14) -> 63.333333 | J16: =IF(Inputs!$B$14<=0,0,J15/Inputs!$B$14) -> 68.611111 | ... BJ16: =IF(Inputs!$B$14<=0,0,BJ15/Inputs!$B$14) -> 77.407407
A18: Revenue
A19: Average daily rate | C19: =Inputs!$B$17*(1+Inputs!$B$18)^(C$7-1) -> 135 | D19: =Inputs!$B$17*(1+Inputs!$B$18)^(D$7-1) -> 135 | E19: =Inputs!$B$17*(1+Inputs!$B$18)^(E$7-1) -> 135 | F19: =Inputs!$B$17*(1+Inputs!$B$18)^(F$7-1) -> 135 | G19: =Inputs!$B$17*(1+Inputs!$B$18)^(G$7-1) -> 135 | H19: =Inputs!$B$17*(1+Inputs!$B$18)^(H$7-1) -> 135 | I19: =Inputs!$B$17*(1+Inputs!$B$18)^(I$7-1) -> 135 | J19: =Inputs!$B$17*(1+Inputs!$B$18)^(J$7-1) -> 135 | ... BJ19: =Inputs!$B$17*(1+Inputs!$B$18)^(BJ$7-1) -> 140.48154
A20: Room revenue | C20: =C15*C19 -> 5643 | D20: =D15*D19 -> 6583.5 | E20: =E15*E19 -> 7524 | F20: =F15*F19 -> 8464.5 | G20: =G15*G19 -> 9405 | H20: =H15*H19 -> 14107.5 | I20: =I15*I19 -> 15390 | J20: =J15*J19 -> 16672.5 | ... BJ20: =BJ15*BJ19 -> 19573.761
A21: Breakfast & extras revenue | C21: =C15*Inputs!$B$19*(1+Inputs!$B$18)^(C$7-1) -> 376.2 | D21: =D15*Inputs!$B$19*(1+Inputs!$B$18)^(D$7-1) -> 438.9 | E21: =E15*Inputs!$B$19*(1+Inputs!$B$18)^(E$7-1) -> 501.6 | F21: =F15*Inputs!$B$19*(1+Inputs!$B$18)^(F$7-1) -> 564.3 | G21: =G15*Inputs!$B$19*(1+Inputs!$B$18)^(G$7-1) -> 627 | H21: =H15*Inputs!$B$19*(1+Inputs!$B$18)^(H$7-1) -> 940.5 | I21: =I15*Inputs!$B$19*(1+Inputs!$B$18)^(I$7-1) -> 1026 | J21: =J15*Inputs!$B$19*(1+Inputs!$B$18)^(J$7-1) -> 1111.5 | ... BJ21: =BJ15*Inputs!$B$19*(1+Inputs!$B$18)^(BJ$7-1) -> 1304.9174
A22: Revenue | C22: =C20+C21 -> 6019.2 | D22: =D20+D21 -> 7022.4 | E22: =E20+E21 -> 8025.6 | F22: =F20+F21 -> 9028.8 | G22: =G20+G21 -> 10032 | H22: =H20+H21 -> 15048 | I22: =I20+I21 -> 16416 | J22: =J20+J21 -> 17784 | ... BJ22: =BJ20+BJ21 -> 20878.679
A24: Cost of sales
A25: Housekeeping payroll | C25: =C118 -> -4600 | D25: =D118 -> -4600 | E25: =E118 -> -4600 | F25: =F118 -> -4600 | G25: =G118 -> -4600 | H25: =H118 -> -4600 | I25: =I118 -> -4600 | J25: =J118 -> -4600 | ... BJ25: =BJ118 -> -5381.3494
A26: OTA / booking commission | C26: =-C20*Inputs!$B$25*Inputs!$B$26 -> -623.5515 | D26: =-D20*Inputs!$B$25*Inputs!$B$26 -> -727.47675 | E26: =-E20*Inputs!$B$25*Inputs!$B$26 -> -831.402 | F26: =-F20*Inputs!$B$25*Inputs!$B$26 -> -935.32725 | G26: =-G20*Inputs!$B$25*Inputs!$B$26 -> -1039.2525 | H26: =-H20*Inputs!$B$25*Inputs!$B$26 -> -1558.8788 | I26: =-I20*Inputs!$B$25*Inputs!$B$26 -> -1700.595 | J26: =-J20*Inputs!$B$25*Inputs!$B$26 -> -1842.3112 | ... BJ26: =-BJ20*Inputs!$B$25*Inputs!$B$26 -> -2162.9006
A27: Breakfast & extras cost | C27: =-C21*Inputs!$B$22 -> -206.91 | D27: =-D21*Inputs!$B$22 -> -241.395 | E27: =-E21*Inputs!$B$22 -> -275.88 | F27: =-F21*Inputs!$B$22 -> -310.365 | G27: =-G21*Inputs!$B$22 -> -344.85 | H27: =-H21*Inputs!$B$22 -> -517.275 | I27: =-I21*Inputs!$B$22 -> -564.3 | J27: =-J21*Inputs!$B$22 -> -611.325 | ... BJ27: =-BJ21*Inputs!$B$22 -> -717.70459
A28: Cleaning & linen (per stay) | C28: =-C16*Inputs!$B$23*(1+Inputs!$B$39)^(C$7-1) -> -603.77778 | D28: =-D16*Inputs!$B$23*(1+Inputs!$B$39)^(D$7-1) -> -704.40741 | E28: =-E16*Inputs!$B$23*(1+Inputs!$B$39)^(E$7-1) -> -805.03704 | F28: =-F16*Inputs!$B$23*(1+Inputs!$B$39)^(F$7-1) -> -905.66667 | G28: =-G16*Inputs!$B$23*(1+Inputs!$B$39)^(G$7-1) -> -1006.2963 | H28: =-H16*Inputs!$B$23*(1+Inputs!$B$39)^(H$7-1) -> -1509.4444 | I28: =-I16*Inputs!$B$23*(1+Inputs!$B$39)^(I$7-1) -> -1646.6667 | J28: =-J16*Inputs!$B$23*(1+Inputs!$B$39)^(J$7-1) -> -1783.8889 | ... BJ28: =-BJ16*Inputs!$B$23*(1+Inputs!$B$39)^(BJ$7-1) -> -2354.4487
A29: Guest supplies | C29: =-C15*Inputs!$B$24*(1+Inputs!$B$39)^(C$7-1) -> -209 | D29: =-D15*Inputs!$B$24*(1+Inputs!$B$39)^(D$7-1) -> -243.83333 | E29: =-E15*Inputs!$B$24*(1+Inputs!$B$39)^(E$7-1) -> -278.66667 | F29: =-F15*Inputs!$B$24*(1+Inputs!$B$39)^(F$7-1) -> -313.5 | G29: =-G15*Inputs!$B$24*(1+Inputs!$B$39)^(G$7-1) -> -348.33333 | H29: =-H15*Inputs!$B$24*(1+Inputs!$B$39)^(H$7-1) -> -522.5 | I29: =-I15*Inputs!$B$24*(1+Inputs!$B$39)^(I$7-1) -> -570 | J29: =-J15*Inputs!$B$24*(1+Inputs!$B$39)^(J$7-1) -> -617.5 | ... BJ29: =-BJ15*Inputs!$B$24*(1+Inputs!$B$39)^(BJ$7-1) -> -815.00146
A30: Cost of sales | C30: =C25+C26+C27+C28+C29 -> -6243.2393 | D30: =D25+D26+D27+D28+D29 -> -6517.1125 | E30: =E25+E26+E27+E28+E29 -> -6790.9857 | F30: =F25+F26+F27+F28+F29 -> -7064.8589 | G30: =G25+G26+G27+G28+G29 -> -7338.7321 | H30: =H25+H26+H27+H28+H29 -> -8708.0982 | I30: =I25+I26+I27+I28+I29 -> -9081.5617 | J30: =J25+J26+J27+J28+J29 -> -9455.0251 | ... BJ30: =BJ25+BJ26+BJ27+BJ28+BJ29 -> -11431.405
A31: Gross profit | C31: =C22+C30 -> -224.03928 | D31: =D22+D30 -> 505.28751 | E31: =E22+E30 -> 1234.6143 | F31: =F22+F30 -> 1963.9411 | G31: =G22+G30 -> 2693.2679 | H31: =H22+H30 -> 6339.9018 | I31: =I22+I30 -> 7334.4383 | J31: =J22+J30 -> 8328.9749 | ... BJ31: =BJ22+BJ30 -> 9447.2741
A33: Operating expenses
A34: Host, front desk, kitchen & maintenance payroll | C34: =C121-C118 -> -5558.3333 | D34: =D121-D118 -> -5558.3333 | E34: =E121-E118 -> -5558.3333 | F34: =F121-F118 -> -5558.3333 | G34: =G121-G118 -> -5558.3333 | H34: =H121-H118 -> -5558.3333 | I34: =I121-I118 -> -5558.3333 | J34: =J121-J118 -> -5558.3333 | ... BJ34: =BJ121-BJ118 -> -6502.4638
A35: Building rent | C35: =-Inputs!$B$29*(1+Inputs!$B$30)^(C$7-1)*1 -> 0 | D35: =-Inputs!$B$29*(1+Inputs!$B$30)^(D$7-1)*1 -> 0 | E35: =-Inputs!$B$29*(1+Inputs!$B$30)^(E$7-1)*1 -> 0 | F35: =-Inputs!$B$29*(1+Inputs!$B$30)^(F$7-1)*1 -> 0 | G35: =-Inputs!$B$29*(1+Inputs!$B$30)^(G$7-1)*1 -> 0 | H35: =-Inputs!$B$29*(1+Inputs!$B$30)^(H$7-1)*1 -> 0 | I35: =-Inputs!$B$29*(1+Inputs!$B$30)^(I$7-1)*1 -> 0 | J35: =-Inputs!$B$29*(1+Inputs!$B$30)^(J$7-1)*1 -> 0 | ... BJ35: =-Inputs!$B$29*(1+Inputs!$B$30)^(BJ$7-1)*1 -> 0
A36: Property tax | C36: =-Inputs!$B$31/12*(1+Inputs!$B$39)^(C$7-1)*1 -> -666.66667 | D36: =-Inputs!$B$31/12*(1+Inputs!$B$39)^(D$7-1)*1 -> -666.66667 | E36: =-Inputs!$B$31/12*(1+Inputs!$B$39)^(E$7-1)*1 -> -666.66667 | F36: =-Inputs!$B$31/12*(1+Inputs!$B$39)^(F$7-1)*1 -> -666.66667 | G36: =-Inputs!$B$31/12*(1+Inputs!$B$39)^(G$7-1)*1 -> -666.66667 | H36: =-Inputs!$B$31/12*(1+Inputs!$B$39)^(H$7-1)*1 -> -666.66667 | I36: =-Inputs!$B$31/12*(1+Inputs!$B$39)^(I$7-1)*1 -> -666.66667 | J36: =-Inputs!$B$31/12*(1+Inputs!$B$39)^(J$7-1)*1 -> -666.66667 | ... BJ36: =-Inputs!$B$31/12*(1+Inputs!$B$39)^(BJ$7-1)*1 -> -779.90571
A37: Insurance | C37: =-Inputs!$B$32*(1+Inputs!$B$39)^(C$7-1)*1 -> -700 | D37: =-Inputs!$B$32*(1+Inputs!$B$39)^(D$7-1)*1 -> -700 | E37: =-Inputs!$B$32*(1+Inputs!$B$39)^(E$7-1)*1 -> -700 | F37: =-Inputs!$B$32*(1+Inputs!$B$39)^(F$7-1)*1 -> -700 | G37: =-Inputs!$B$32*(1+Inputs!$B$39)^(G$7-1)*1 -> -700 | H37: =-Inputs!$B$32*(1+Inputs!$B$39)^(H$7-1)*1 -> -700 | I37: =-Inputs!$B$32*(1+Inputs!$B$39)^(I$7-1)*1 -> -700 | J37: =-Inputs!$B$32*(1+Inputs!$B$39)^(J$7-1)*1 -> -700 | ... BJ37: =-Inputs!$B$32*(1+Inputs!$B$39)^(BJ$7-1)*1 -> -818.90099
A38: Utilities | C38: =-Inputs!$B$33*(1+Inputs!$B$39)^(C$7-1)*1 -> -1800 | D38: =-Inputs!$B$33*(1+Inputs!$B$39)^(D$7-1)*1 -> -1800 | E38: =-Inputs!$B$33*(1+Inputs!$B$39)^(E$7-1)*1 -> -1800 | F38: =-Inputs!$B$33*(1+Inputs!$B$39)^(F$7-1)*1 -> -1800 | G38: =-Inputs!$B$33*(1+Inputs!$B$39)^(G$7-1)*1 -> -1800 | H38: =-Inputs!$B$33*(1+Inputs!$B$39)^(H$7-1)*1 -> -1800 | I38: =-Inputs!$B$33*(1+Inputs!$B$39)^(I$7-1)*1 -> -1800 | J38: =-Inputs!$B$33*(1+Inputs!$B$39)^(J$7-1)*1 -> -1800 | ... BJ38: =-Inputs!$B$33*(1+Inputs!$B$39)^(BJ$7-1)*1 -> -2105.7454
A39: Repairs & maintenance | C39: =-C22*Inputs!$B$34 -> -300.96 | D39: =-D22*Inputs!$B$34 -> -351.12 | E39: =-E22*Inputs!$B$34 -> -401.28 | F39: =-F22*Inputs!$B$34 -> -451.44 | G39: =-G22*Inputs!$B$34 -> -501.6 | H39: =-H22*Inputs!$B$34 -> -752.4 | I39: =-I22*Inputs!$B$34 -> -820.8 | J39: =-J22*Inputs!$B$34 -> -889.2 | ... BJ39: =-BJ22*Inputs!$B$34 -> -1043.9339
A40: Marketing | C40: =-Inputs!$B$36*(1+Inputs!$B$37)^(C$7-1)*1 -> -1500 | D40: =-Inputs!$B$36*(1+Inputs!$B$37)^(D$7-1)*1 -> -1500 | E40: =-Inputs!$B$36*(1+Inputs!$B$37)^(E$7-1)*1 -> -1500 | F40: =-Inputs!$B$36*(1+Inputs!$B$37)^(F$7-1)*1 -> -1500 | G40: =-Inputs!$B$36*(1+Inputs!$B$37)^(G$7-1)*1 -> -1500 | H40: =-Inputs!$B$36*(1+Inputs!$B$37)^(H$7-1)*1 -> -1500 | I40: =-Inputs!$B$36*(1+Inputs!$B$37)^(I$7-1)*1 -> -1500 | J40: =-Inputs!$B$36*(1+Inputs!$B$37)^(J$7-1)*1 -> -1500 | ... BJ40: =-Inputs!$B$36*(1+Inputs!$B$37)^(BJ$7-1)*1 -> -360.15
A41: Software, accounting & other G&A | C41: =-Inputs!$B$35*(1+Inputs!$B$39)^(C$7-1)*1 -> -1200 | D41: =-Inputs!$B$35*(1+Inputs!$B$39)^(D$7-1)*1 -> -1200 | E41: =-Inputs!$B$35*(1+Inputs!$B$39)^(E$7-1)*1 -> -1200 | F41: =-Inputs!$B$35*(1+Inputs!$B$39)^(F$7-1)*1 -> -1200 | G41: =-Inputs!$B$35*(1+Inputs!$B$39)^(G$7-1)*1 -> -1200 | H41: =-Inputs!$B$35*(1+Inputs!$B$39)^(H$7-1)*1 -> -1200 | I41: =-Inputs!$B$35*(1+Inputs!$B$39)^(I$7-1)*1 -> -1200 | J41: =-Inputs!$B$35*(1+Inputs!$B$39)^(J$7-1)*1 -> -1200 | ... BJ41: =-Inputs!$B$35*(1+Inputs!$B$39)^(BJ$7-1)*1 -> -1403.8303
A42: Card processing fees | C42: =-C22*Inputs!$B$38 -> -180.576 | D42: =-D22*Inputs!$B$38 -> -210.672 | E42: =-E22*Inputs!$B$38 -> -240.768 | F42: =-F22*Inputs!$B$38 -> -270.864 | G42: =-G22*Inputs!$B$38 -> -300.96 | H42: =-H22*Inputs!$B$38 -> -451.44 | I42: =-I22*Inputs!$B$38 -> -492.48 | J42: =-J22*Inputs!$B$38 -> -533.52 | ... BJ42: =-BJ22*Inputs!$B$38 -> -626.36037
A43: Total operating expenses | C43: =C34+C35+C36+C37+C38+C39+C40+C41+C42 -> -11906.536 | D43: =D34+D35+D36+D37+D38+D39+D40+D41+D42 -> -11986.792 | E43: =E34+E35+E36+E37+E38+E39+E40+E41+E42 -> -12067.048 | F43: =F34+F35+F36+F37+F38+F39+F40+F41+F42 -> -12147.304 | G43: =G34+G35+G36+G37+G38+G39+G40+G41+G42 -> -12227.56 | H43: =H34+H35+H36+H37+H38+H39+H40+H41+H42 -> -12628.84 | I43: =I34+I35+I36+I37+I38+I39+I40+I41+I42 -> -12738.28 | J43: =J34+J35+J36+J37+J38+J39+J40+J41+J42 -> -12847.72 | ... BJ43: =BJ34+BJ35+BJ36+BJ37+BJ38+BJ39+BJ40+BJ41+BJ42 -> -13641.291
A44: EBITDA | C44: =C31+C43 -> -12130.575 | D44: =D31+D43 -> -11481.504 | E44: =E31+E43 -> -10832.434 | F44: =F31+F43 -> -10183.363 | G44: =G31+G43 -> -9534.2921 | H44: =H31+H43 -> -6288.9382 | I44: =I31+I43 -> -5403.8417 | J44: =J31+J43 -> -4518.7451 | ... BJ44: =BJ31+BJ43 -> -4194.0164
A46: Profit after depreciation, interest, tax
A47: EBIT | C47: =C44+C64 -> -15940.298 | D47: =D44+D64 -> -15295.393 | E47: =E44+E64 -> -14650.489 | F47: =F44+F64 -> -14005.585 | G47: =G44+G64 -> -13360.681 | H47: =H44+H64 -> -10119.494 | I47: =I44+I64 -> -9238.5639 | J47: =J44+J64 -> -8357.634 | ... BJ47: =BJ44+BJ64 -> -8270.3881
A48: Interest on loan (balance after drawdown, start of period) | C48: =-(C69+C70)*Inputs!$B$67/12 -> -2916.6667 | D48: =-(D69+D70)*Inputs!$B$67/12 -> -2913.0662 | E48: =-(E69+E70)*Inputs!$B$67/12 -> -2909.4447 | F48: =-(F69+F70)*Inputs!$B$67/12 -> -2905.802 | G48: =-(G69+G70)*Inputs!$B$67/12 -> -2902.1381 | H48: =-(H69+H70)*Inputs!$B$67/12 -> -2898.4529 | I48: =-(I69+I70)*Inputs!$B$67/12 -> -2894.7461 | J48: =-(J69+J70)*Inputs!$B$67/12 -> -2891.0178 | ... BJ48: =-(BJ69+BJ70)*Inputs!$B$67/12 -> -2663.9707
A49: Pre-tax income | C49: =C47+C48 -> -18856.964 | D49: =D47+D48 -> -18208.46 | E49: =E47+E48 -> -17559.934 | F49: =F47+F48 -> -16911.387 | G49: =G47+G48 -> -16262.819 | H49: =H47+H48 -> -13017.947 | I49: =I47+I48 -> -12133.31 | J49: =J47+J48 -> -11248.652 | ... BJ49: =BJ47+BJ48 -> -10934.359
A50: Helper: cumulative pre-tax income | C50: =C49 -> -18856.964 | D50: =C50+D49 -> -37065.424 | E50: =D50+E49 -> -54625.358 | F50: =E50+F49 -> -71536.745 | G50: =F50+G49 -> -87799.564 | H50: =G50+H49 -> -100817.51 | I50: =H50+I49 -> -112950.82 | J50: =I50+J49 -> -124199.47 | K50: =J50+K49 -> -137867.8 | ... BJ50: =BI50+BJ49 -> -616314.1
A51: Helper: cumulative taxable income (losses carried forward) | C51: =MAX(0,C50) -> 0 | D51: =MAX(C51,D50) -> 0 | E51: =MAX(D51,E50) -> 0 | F51: =MAX(E51,F50) -> 0 | G51: =MAX(F51,G50) -> 0 | H51: =MAX(G51,H50) -> 0 | I51: =MAX(H51,I50) -> 0 | J51: =MAX(I51,J50) -> 0 | K51: =MAX(J51,K50) -> 0 | ... BJ51: =MAX(BI51,BJ50) -> 0
A52: Income tax | C52: =-C51*Inputs!$B$77 -> 0 | D52: =-(D51-C51)*Inputs!$B$77 -> 0 | E52: =-(E51-D51)*Inputs!$B$77 -> 0 | F52: =-(F51-E51)*Inputs!$B$77 -> 0 | G52: =-(G51-F51)*Inputs!$B$77 -> 0 | H52: =-(H51-G51)*Inputs!$B$77 -> 0 | I52: =-(I51-H51)*Inputs!$B$77 -> 0 | J52: =-(J51-I51)*Inputs!$B$77 -> 0 | K52: =-(K51-J51)*Inputs!$B$77 -> 0 | ... BJ52: =-(BJ51-BI51)*Inputs!$B$77 -> 0
A53: Net income | C53: =C49+C52 -> -18856.964 | D53: =D49+D52 -> -18208.46 | E53: =E49+E52 -> -17559.934 | F53: =F49+F52 -> -16911.387 | G53: =G49+G52 -> -16262.819 | H53: =H49+H52 -> -13017.947 | I53: =I49+I52 -> -12133.31 | J53: =J49+J52 -> -11248.652 | ... BJ53: =BJ49+BJ52 -> -10934.359
A55: Fixed assets & capital spending
A56: Property purchase | C56: =IF(C$6=1,Inputs!$B$42,0) -> 720000 | D56: =IF(D$6=1,Inputs!$B$42,0) -> 0 | E56: =IF(E$6=1,Inputs!$B$42,0) -> 0 | F56: =IF(F$6=1,Inputs!$B$42,0) -> 0 | G56: =IF(G$6=1,Inputs!$B$42,0) -> 0 | H56: =IF(H$6=1,Inputs!$B$42,0) -> 0 | I56: =IF(I$6=1,Inputs!$B$42,0) -> 0 | J56: =IF(J$6=1,Inputs!$B$42,0) -> 0 | ... BJ56: =IF(BJ$6=1,Inputs!$B$42,0) -> 0
A57: of which land (not depreciated) | C57: =IF(C$6=1,Inputs!$B$42*Inputs!$B$43,0) -> 180000 | D57: =IF(D$6=1,Inputs!$B$42*Inputs!$B$43,0) -> 0 | E57: =IF(E$6=1,Inputs!$B$42*Inputs!$B$43,0) -> 0 | F57: =IF(F$6=1,Inputs!$B$42*Inputs!$B$43,0) -> 0 | G57: =IF(G$6=1,Inputs!$B$42*Inputs!$B$43,0) -> 0 | H57: =IF(H$6=1,Inputs!$B$42*Inputs!$B$43,0) -> 0 | I57: =IF(I$6=1,Inputs!$B$42*Inputs!$B$43,0) -> 0 | J57: =IF(J$6=1,Inputs!$B$42*Inputs!$B$43,0) -> 0 | ... BJ57: =IF(BJ$6=1,Inputs!$B$42*Inputs!$B$43,0) -> 0
A58: Room furnishing & fit-out | C58: =IF(C$6=1,Inputs!$B$7*Inputs!$B$44,0) -> 75000 | D58: =IF(D$6=1,Inputs!$B$7*Inputs!$B$44,0) -> 0 | E58: =IF(E$6=1,Inputs!$B$7*Inputs!$B$44,0) -> 0 | F58: =IF(F$6=1,Inputs!$B$7*Inputs!$B$44,0) -> 0 | G58: =IF(G$6=1,Inputs!$B$7*Inputs!$B$44,0) -> 0 | H58: =IF(H$6=1,Inputs!$B$7*Inputs!$B$44,0) -> 0 | I58: =IF(I$6=1,Inputs!$B$7*Inputs!$B$44,0) -> 0 | J58: =IF(J$6=1,Inputs!$B$7*Inputs!$B$44,0) -> 0 | ... BJ58: =IF(BJ$6=1,Inputs!$B$7*Inputs!$B$44,0) -> 0
A59: Building works, kitchen & signage | C59: =IF(C$6=1,Inputs!$B$45,0) -> 70000 | D59: =IF(D$6=1,Inputs!$B$45,0) -> 0 | E59: =IF(E$6=1,Inputs!$B$45,0) -> 0 | F59: =IF(F$6=1,Inputs!$B$45,0) -> 0 | G59: =IF(G$6=1,Inputs!$B$45,0) -> 0 | H59: =IF(H$6=1,Inputs!$B$45,0) -> 0 | I59: =IF(I$6=1,Inputs!$B$45,0) -> 0 | J59: =IF(J$6=1,Inputs!$B$45,0) -> 0 | ... BJ59: =IF(BJ$6=1,Inputs!$B$45,0) -> 0
A60: FF&E replacement | C60: =Inputs!$B$7*Inputs!$B$46/12*(1+Inputs!$B$39)^(C$7-1)*1 -> 750 | D60: =Inputs!$B$7*Inputs!$B$46/12*(1+Inputs!$B$39)^(D$7-1)*1 -> 750 | E60: =Inputs!$B$7*Inputs!$B$46/12*(1+Inputs!$B$39)^(E$7-1)*1 -> 750 | F60: =Inputs!$B$7*Inputs!$B$46/12*(1+Inputs!$B$39)^(F$7-1)*1 -> 750 | G60: =Inputs!$B$7*Inputs!$B$46/12*(1+Inputs!$B$39)^(G$7-1)*1 -> 750 | H60: =Inputs!$B$7*Inputs!$B$46/12*(1+Inputs!$B$39)^(H$7-1)*1 -> 750 | I60: =Inputs!$B$7*Inputs!$B$46/12*(1+Inputs!$B$39)^(I$7-1)*1 -> 750 | J60: =Inputs!$B$7*Inputs!$B$46/12*(1+Inputs!$B$39)^(J$7-1)*1 -> 750 | ... BJ60: =Inputs!$B$7*Inputs!$B$46/12*(1+Inputs!$B$39)^(BJ$7-1)*1 -> 877.39392
A61: Capital spending | C61: =C56+C58+C59+C60 -> 865750 | D61: =D56+D58+D59+D60 -> 750 | E61: =E56+E58+E59+E60 -> 750 | F61: =F56+F58+F59+F60 -> 750 | G61: =G56+G58+G59+G60 -> 750 | H61: =H56+H58+H59+H60 -> 750 | I61: =I56+I58+I59+I60 -> 750 | J61: =J56+J58+J59+J60 -> 750 | ... BJ61: =BJ56+BJ58+BJ59+BJ60 -> 877.39392
A62: Fixed assets at cost | C62: =C61 -> 865750 | D62: =C62+D61 -> 866500 | E62: =D62+E61 -> 867250 | F62: =E62+F61 -> 868000 | G62: =F62+G61 -> 868750 | H62: =G62+H61 -> 869500 | I62: =H62+I61 -> 870250 | J62: =I62+J61 -> 871000 | K62: =J62+K61 -> 871750 | ... BJ62: =BI62+BJ61 -> 913746.9
A63: Land at cost (not depreciated) | C63: =C57 -> 180000 | D63: =C63+D57 -> 180000 | E63: =D63+E57 -> 180000 | F63: =E63+F57 -> 180000 | G63: =F63+G57 -> 180000 | H63: =G63+H57 -> 180000 | I63: =H63+I57 -> 180000 | J63: =I63+J57 -> 180000 | K63: =J63+K57 -> 180000 | ... BJ63: =BI63+BJ57 -> 180000
A64: Depreciation | C64: =-MIN((C62-C63)/MAX(1,Inputs!$B$76*12),C61-C63) -> -3809.7222 | D64: =-MIN((D62-D63)/MAX(1,Inputs!$B$76*12),C66+D61-D63) -> -3813.8889 | E64: =-MIN((E62-E63)/MAX(1,Inputs!$B$76*12),D66+E61-E63) -> -3818.0556 | F64: =-MIN((F62-F63)/MAX(1,Inputs!$B$76*12),E66+F61-F63) -> -3822.2222 | G64: =-MIN((G62-G63)/MAX(1,Inputs!$B$76*12),F66+G61-G63) -> -3826.3889 | H64: =-MIN((H62-H63)/MAX(1,Inputs!$B$76*12),G66+H61-H63) -> -3830.5556 | I64: =-MIN((I62-I63)/MAX(1,Inputs!$B$76*12),H66+I61-I63) -> -3834.7222 | J64: =-MIN((J62-J63)/MAX(1,Inputs!$B$76*12),I66+J61-J63) -> -3838.8889 | K64: =-MIN((K62-K63)/MAX(1,Inputs!$B$76*12),J66+K61-K63) -> -3843.0556 | ... BJ64: =-MIN((BJ62-BJ63)/MAX(1,Inputs!$B$76*12),BI66+BJ61-BJ63) -> -4076.3717
A65: Accumulated depreciation | C65: =C64 -> -3809.7222 | D65: =C65+D64 -> -7623.6111 | E65: =D65+E64 -> -11441.667 | F65: =E65+F64 -> -15263.889 | G65: =F65+G64 -> -19090.278 | H65: =G65+H64 -> -22920.833 | I65: =H65+I64 -> -26755.556 | J65: =I65+J64 -> -30594.444 | K65: =J65+K64 -> -34437.5 | ... BJ65: =BI65+BJ64 -> -236338.48
A66: Net fixed assets | C66: =C62+C65 -> 861940.28 | D66: =D62+D65 -> 858876.39 | E66: =E62+E65 -> 855808.33 | F66: =F62+F65 -> 852736.11 | G66: =G62+G65 -> 849659.72 | H66: =H62+H65 -> 846579.17 | I66: =I62+I65 -> 843494.44 | J66: =J62+J65 -> 840405.56 | ... BJ66: =BJ62+BJ65 -> 677408.43
A68: Debt
A69: Loan — opening balance | C69: =0 -> 0 | D69: =C74 -> 499382.77 | E69: =D74 -> 498761.94 | F69: =E74 -> 498137.49 | G69: =F74 -> 497509.4 | H69: =G74 -> 496877.64 | I69: =H74 -> 496242.19 | J69: =I74 -> 495603.04 | K69: =J74 -> 494960.17 | ... BJ69: =BI74 -> 456680.69
A70: Loan drawdown | C70: =IF(C$6=1,Inputs!$B$66,0) -> 500000 | D70: =IF(D$6=1,Inputs!$B$66,0) -> 0 | E70: =IF(E$6=1,Inputs!$B$66,0) -> 0 | F70: =IF(F$6=1,Inputs!$B$66,0) -> 0 | G70: =IF(G$6=1,Inputs!$B$66,0) -> 0 | H70: =IF(H$6=1,Inputs!$B$66,0) -> 0 | I70: =IF(I$6=1,Inputs!$B$66,0) -> 0 | J70: =IF(J$6=1,Inputs!$B$66,0) -> 0 | ... BJ70: =IF(BJ$6=1,Inputs!$B$66,0) -> 0
A71: Scheduled loan payment (principal + interest, level) | C71: =-PMT(Inputs!$B$67/12,MAX(1,Inputs!$B$68*12),Inputs!$B$66) -> 3533.896 | D71: =-PMT(Inputs!$B$67/12,MAX(1,Inputs!$B$68*12),Inputs!$B$66) -> 3533.896 | E71: =-PMT(Inputs!$B$67/12,MAX(1,Inputs!$B$68*12),Inputs!$B$66) -> 3533.896 | F71: =-PMT(Inputs!$B$67/12,MAX(1,Inputs!$B$68*12),Inputs!$B$66) -> 3533.896 | G71: =-PMT(Inputs!$B$67/12,MAX(1,Inputs!$B$68*12),Inputs!$B$66) -> 3533.896 | H71: =-PMT(Inputs!$B$67/12,MAX(1,Inputs!$B$68*12),Inputs!$B$66) -> 3533.896 | I71: =-PMT(Inputs!$B$67/12,MAX(1,Inputs!$B$68*12),Inputs!$B$66) -> 3533.896 | J71: =-PMT(Inputs!$B$67/12,MAX(1,Inputs!$B$68*12),Inputs!$B$66) -> 3533.896 | ... BJ71: =-PMT(Inputs!$B$67/12,MAX(1,Inputs!$B$68*12),Inputs!$B$66) -> 3533.896
A72: Loan repayment (principal) | C72: =-MIN(C69+C70,C71+C48) -> -617.22932 | D72: =-MIN(D69+D70,D71+D48) -> -620.82982 | E72: =-MIN(E69+E70,E71+E48) -> -624.45133 | F72: =-MIN(F69+F70,F71+F48) -> -628.09396 | G72: =-MIN(G69+G70,G71+G48) -> -631.75785 | H72: =-MIN(H69+H70,H71+H48) -> -635.4431 | I72: =-MIN(I69+I70,I71+I48) -> -639.14985 | J72: =-MIN(J69+J70,J71+J48) -> -642.87823 | ... BJ72: =-MIN(BJ69+BJ70,BJ71+BJ48) -> -869.92531
A73: Debt service (interest + principal) | C73: =C48+C72 -> -3533.896 | D73: =D48+D72 -> -3533.896 | E73: =E48+E72 -> -3533.896 | F73: =F48+F72 -> -3533.896 | G73: =G48+G72 -> -3533.896 | H73: =H48+H72 -> -3533.896 | I73: =I48+I72 -> -3533.896 | J73: =J48+J72 -> -3533.896 | ... BJ73: =BJ48+BJ72 -> -3533.896
A74: Loan — closing balance | C74: =C69+C70+C72 -> 499382.77 | D74: =D69+D70+D72 -> 498761.94 | E74: =E69+E70+E72 -> 498137.49 | F74: =F69+F70+F72 -> 497509.4 | G74: =G69+G70+G72 -> 496877.64 | H74: =H69+H70+H72 -> 496242.19 | I74: =I69+I70+I72 -> 495603.04 | J74: =J69+J70+J72 -> 494960.17 | ... BJ74: =BJ69+BJ70+BJ72 -> 455810.76
A76: Working capital
A77: Accounts receivable | C77: =C22*Inputs!$B$71/30 -> 601.92 | D77: =D22*Inputs!$B$71/30 -> 702.24 | E77: =E22*Inputs!$B$71/30 -> 802.56 | F77: =F22*Inputs!$B$71/30 -> 902.88 | G77: =G22*Inputs!$B$71/30 -> 1003.2 | H77: =H22*Inputs!$B$71/30 -> 1504.8 | I77: =I22*Inputs!$B$71/30 -> 1641.6 | J77: =J22*Inputs!$B$71/30 -> 1778.4 | ... BJ77: =BJ22*Inputs!$B$71/30 -> 2087.8679
A78: Inventory | C78: =-C30*Inputs!$B$72/30 -> 624.32393 | D78: =-D30*Inputs!$B$72/30 -> 651.71125 | E78: =-E30*Inputs!$B$72/30 -> 679.09857 | F78: =-F30*Inputs!$B$72/30 -> 706.48589 | G78: =-G30*Inputs!$B$72/30 -> 733.87321 | H78: =-H30*Inputs!$B$72/30 -> 870.80982 | I78: =-I30*Inputs!$B$72/30 -> 908.15617 | J78: =-J30*Inputs!$B$72/30 -> 945.50251 | ... BJ78: =-BJ30*Inputs!$B$72/30 -> 1143.1405
A79: Accounts payable | C79: =-C30*Inputs!$B$73/30 -> 5202.6994 | D79: =-D30*Inputs!$B$73/30 -> 5430.9271 | E79: =-E30*Inputs!$B$73/30 -> 5659.1548 | F79: =-F30*Inputs!$B$73/30 -> 5887.3824 | G79: =-G30*Inputs!$B$73/30 -> 6115.6101 | H79: =-H30*Inputs!$B$73/30 -> 7256.7485 | I79: =-I30*Inputs!$B$73/30 -> 7567.9681 | J79: =-J30*Inputs!$B$73/30 -> 7879.1876 | ... BJ79: =-BJ30*Inputs!$B$73/30 -> 9526.1706
A80: (Increase) / decrease in receivables | C80: =-C77 -> -601.92 | D80: =C77-D77 -> -100.32 | E80: =D77-E77 -> -100.32 | F80: =E77-F77 -> -100.32 | G80: =F77-G77 -> -100.32 | H80: =G77-H77 -> -501.6 | I80: =H77-I77 -> -136.8 | J80: =I77-J77 -> -136.8 | K80: =J77-K77 -> 373.92 | ... BJ80: =BI77-BJ77 -> 0
A81: (Increase) / decrease in inventory | C81: =-C78 -> -624.32393 | D81: =C78-D78 -> -27.387321 | E81: =D78-E78 -> -27.387321 | F81: =E78-F78 -> -27.387321 | G81: =F78-G78 -> -27.387321 | H81: =G78-H78 -> -136.93661 | I81: =H78-I78 -> -37.346347 | J81: =I78-J78 -> -37.346347 | K81: =J78-K78 -> 102.08002 | ... BJ81: =BI78-BJ78 -> 0
A82: Increase / (decrease) in payables | C82: =C79 -> 5202.6994 | D82: =D79-C79 -> 228.22768 | E82: =E79-D79 -> 228.22768 | F82: =F79-E79 -> 228.22768 | G82: =G79-F79 -> 228.22768 | H82: =H79-G79 -> 1141.1384 | I82: =I79-H79 -> 311.21956 | J82: =J79-I79 -> 311.21956 | K82: =K79-J79 -> -850.6668 | ... BJ82: =BJ79-BI79 -> 0
A84: Cash flow
A85: Operating cash flow | C85: =C53-C64+C80+C81+C82 -> -11070.786 | D85: =D53-D64+D80+D81+D82 -> -14294.05 | E85: =E53-E64+E80+E81+E82 -> -13641.358 | F85: =F53-F64+F80+F81+F82 -> -12988.645 | G85: =G53-G64+G80+G81+G82 -> -12335.91 | H85: =H53-H64+H80+H81+H82 -> -8684.7893 | I85: =I53-I64+I80+I81+I82 -> -8161.5146 | J85: =J53-J64+J80+J81+J82 -> -7272.6897 | ... BJ85: =BJ53-BJ64+BJ80+BJ81+BJ82 -> -6857.9871
A86: Investing cash flow (capex) | C86: =-C61 -> -865750 | D86: =-D61 -> -750 | E86: =-E61 -> -750 | F86: =-F61 -> -750 | G86: =-G61 -> -750 | H86: =-H61 -> -750 | I86: =-I61 -> -750 | J86: =-J61 -> -750 | ... BJ86: =-BJ61 -> -877.39392
A87: Equity raised | C87: =IF(C$6=1,Inputs!$B$65,0) -> 430000 | D87: =IF(D$6=1,Inputs!$B$65,0) -> 0 | E87: =IF(E$6=1,Inputs!$B$65,0) -> 0 | F87: =IF(F$6=1,Inputs!$B$65,0) -> 0 | G87: =IF(G$6=1,Inputs!$B$65,0) -> 0 | H87: =IF(H$6=1,Inputs!$B$65,0) -> 0 | I87: =IF(I$6=1,Inputs!$B$65,0) -> 0 | J87: =IF(J$6=1,Inputs!$B$65,0) -> 0 | ... BJ87: =IF(BJ$6=1,Inputs!$B$65,0) -> 0
A88: Financing cash flow | C88: =C87+C70+C72 -> 929382.77 | D88: =D87+D70+D72 -> -620.82982 | E88: =E87+E70+E72 -> -624.45133 | F88: =F87+F70+F72 -> -628.09396 | G88: =G87+G70+G72 -> -631.75785 | H88: =H87+H70+H72 -> -635.4431 | I88: =I87+I70+I72 -> -639.14985 | J88: =J87+J70+J72 -> -642.87823 | ... BJ88: =BJ87+BJ70+BJ72 -> -869.92531
A89: Net cash flow | C89: =C85+C86+C88 -> 52561.984 | D89: =D85+D86+D88 -> -15664.88 | E89: =E85+E86+E88 -> -15015.809 | F89: =F85+F86+F88 -> -14366.739 | G89: =G85+G86+G88 -> -13717.668 | H89: =H85+H86+H88 -> -10070.232 | I89: =I85+I86+I88 -> -9550.6644 | J89: =J85+J86+J88 -> -8665.5679 | ... BJ89: =BJ85+BJ86+BJ88 -> -8605.3063
A90: Opening cash | C90: =0 -> 0 | D90: =C91 -> 52561.984 | E90: =D91 -> 36897.104 | F90: =E91 -> 21881.295 | G90: =F91 -> 7514.5562 | H90: =G91 -> -6203.1116 | I90: =H91 -> -16273.344 | J90: =I91 -> -25824.008 | K90: =J91 -> -34489.576 | ... BJ90: =BI91 -> -393011.3
A91: Closing cash | C91: =C90+C89 -> 52561.984 | D91: =D90+D89 -> 36897.104 | E91: =E90+E89 -> 21881.295 | F91: =F90+F89 -> 7514.5562 | G91: =G90+G89 -> -6203.1116 | H91: =H90+H89 -> -16273.344 | I91: =I90+I89 -> -25824.008 | J91: =J90+J89 -> -34489.576 | ... BJ91: =BJ90+BJ89 -> -401616.61
A92: Helper: EBITDA positive (1/0) | C92: =IF(C44>0,1,0) -> 0 | D92: =IF(D44>0,1,0) -> 0 | E92: =IF(E44>0,1,0) -> 0 | F92: =IF(F44>0,1,0) -> 0 | G92: =IF(G44>0,1,0) -> 0 | H92: =IF(H44>0,1,0) -> 0 | I92: =IF(I44>0,1,0) -> 0 | J92: =IF(J44>0,1,0) -> 0 | ... BJ92: =IF(BJ44>0,1,0) -> 0
A94: Goal modules
A95: Helper: net income positive (1/0) | C95: =IF(C53>0,1,0) -> 0 | D95: =IF(D53>0,1,0) -> 0 | E95: =IF(E53>0,1,0) -> 0 | F95: =IF(F53>0,1,0) -> 0 | G95: =IF(G53>0,1,0) -> 0 | H95: =IF(H53>0,1,0) -> 0 | I95: =IF(I53>0,1,0) -> 0 | J95: =IF(J53>0,1,0) -> 0 | ... BJ95: =IF(BJ53>0,1,0) -> 0
A96: Cash flow before financing (operating + investing) | C96: =C85+C86 -> -876820.79 | D96: =D85+D86 -> -15044.05 | E96: =E85+E86 -> -14391.358 | F96: =F85+F86 -> -13738.645 | G96: =G85+G86 -> -13085.91 | H96: =H85+H86 -> -9434.7893 | I96: =I85+I86 -> -8911.5146 | J96: =J85+J86 -> -8022.6897 | ... BJ96: =BJ85+BJ86 -> -7735.381
A97: Cumulative cash flow before financing | C97: =C96 -> -876820.79 | D97: =C97+D96 -> -891864.84 | E97: =D97+E96 -> -906256.19 | F97: =E97+F96 -> -919994.84 | G97: =F97+G96 -> -933080.75 | H97: =G97+H96 -> -942515.54 | I97: =H97+I96 -> -951427.05 | J97: =I97+J96 -> -959449.74 | K97: =J97+K96 -> -970399.69 | ... BJ97: =BI97+BJ96 -> -1287427.4
A98: Helper: lowest cumulative cash flow so far | C98: =C97 -> -876820.79 | D98: =MIN(C98,D97) -> -891864.84 | E98: =MIN(D98,E97) -> -906256.19 | F98: =MIN(E98,F97) -> -919994.84 | G98: =MIN(F98,G97) -> -933080.75 | H98: =MIN(G98,H97) -> -942515.54 | I98: =MIN(H98,I97) -> -951427.05 | J98: =MIN(I98,J97) -> -959449.74 | K98: =MIN(J98,K97) -> -970399.69 | ... BJ98: =MIN(BI98,BJ97) -> -1287427.4
A99: Helper: investment paid back (1/0) | C99: =IF(AND(C97>=0,C98<0),1,0) -> 0 | D99: =IF(AND(D97>=0,D98<0),1,0) -> 0 | E99: =IF(AND(E97>=0,E98<0),1,0) -> 0 | F99: =IF(AND(F97>=0,F98<0),1,0) -> 0 | G99: =IF(AND(G97>=0,G98<0),1,0) -> 0 | H99: =IF(AND(H97>=0,H98<0),1,0) -> 0 | I99: =IF(AND(I97>=0,I98<0),1,0) -> 0 | J99: =IF(AND(J97>=0,J98<0),1,0) -> 0 | ... BJ99: =IF(AND(BJ97>=0,BJ98<0),1,0) -> 0
A100: Unlevered free cash flow (operating + after-tax interest − capex) | C100: =C85-C48*(1-Inputs!$B$77)+C86 -> -874516.62 | D100: =D85-D48*(1-Inputs!$B$77)+D86 -> -12742.728 | E100: =E85-E48*(1-Inputs!$B$77)+E86 -> -12092.897 | F100: =F85-F48*(1-Inputs!$B$77)+F86 -> -11443.061 | G100: =G85-G48*(1-Inputs!$B$77)+G86 -> -10793.221 | H100: =H85-H48*(1-Inputs!$B$77)+H86 -> -7145.0115 | I100: =I85-I48*(1-Inputs!$B$77)+I86 -> -6624.6651 | J100: =J85-J48*(1-Inputs!$B$77)+J86 -> -5738.7857 | ... BJ100: =BJ85-BJ48*(1-Inputs!$B$77)+BJ86 -> -5630.8442
A102: Balance sheet
A103: Paid-in capital | C103: =C87 -> 430000 | D103: =C103+D87 -> 430000 | E103: =D103+E87 -> 430000 | F103: =E103+F87 -> 430000 | G103: =F103+G87 -> 430000 | H103: =G103+H87 -> 430000 | I103: =H103+I87 -> 430000 | J103: =I103+J87 -> 430000 | K103: =J103+K87 -> 430000 | ... BJ103: =BI103+BJ87 -> 430000
A104: Retained earnings | C104: =C53 -> -18856.964 | D104: =C104+D53 -> -37065.424 | E104: =D104+E53 -> -54625.358 | F104: =E104+F53 -> -71536.745 | G104: =F104+G53 -> -87799.564 | H104: =G104+H53 -> -100817.51 | I104: =H104+I53 -> -112950.82 | J104: =I104+J53 -> -124199.47 | K104: =J104+K53 -> -137867.8 | ... BJ104: =BI104+BJ53 -> -616314.1
A105: Total assets | C105: =C91+C77+C78+C66 -> 915728.51 | D105: =D91+D77+D78+D66 -> 897127.44 | E105: =E91+E77+E78+E66 -> 879171.29 | F105: =F91+F77+F78+F66 -> 861860.03 | G105: =G91+G77+G78+G66 -> 845193.68 | H105: =H91+H77+H78+H66 -> 832681.43 | I105: =I91+I77+I78+I66 -> 820220.19 | J105: =J91+J77+J78+J66 -> 808639.88 | ... BJ105: =BJ91+BJ77+BJ78+BJ66 -> 279022.83
A106: Total liabilities | C106: =C79+C74 -> 504585.47 | D106: =D79+D74 -> 504192.87 | E106: =E79+E74 -> 503796.64 | F106: =F79+F74 -> 503396.78 | G106: =G79+G74 -> 502993.25 | H106: =H79+H74 -> 503498.94 | I106: =I79+I74 -> 503171.01 | J106: =J79+J74 -> 502839.35 | ... BJ106: =BJ79+BJ74 -> 465336.93
A107: Total equity | C107: =C103+C104 -> 411143.04 | D107: =D103+D104 -> 392934.58 | E107: =E103+E104 -> 375374.64 | F107: =F103+F104 -> 358463.26 | G107: =G103+G104 -> 342200.44 | H107: =H103+H104 -> 329182.49 | I107: =I103+I104 -> 317049.18 | J107: =J103+J104 -> 305800.53 | ... BJ107: =BJ103+BJ104 -> -186314.1
A108: Total liabilities & equity | C108: =C106+C107 -> 915728.51 | D108: =D106+D107 -> 897127.44 | E108: =E106+E107 -> 879171.29 | F108: =F106+F107 -> 861860.03 | G108: =G106+G107 -> 845193.68 | H108: =H106+H107 -> 832681.43 | I108: =I106+I107 -> 820220.19 | J108: =J106+J107 -> 808639.88 | ... BJ108: =BJ106+BJ107 -> 279022.83
A109: Check: assets − liabilities − equity | C109: =C105-C108 -> 0 | D109: =D105-D108 -> 0 | E109: =E105-E108 -> 0 | F109: =F105-F108 -> 0 | G109: =G105-G108 -> 0 | H109: =H105-H108 -> 0 | I109: =I105-I108 -> 0 | J109: =J105-J108 -> 0 | ... BJ109: =BJ105-BJ108 -> 0
A111: Headcount (FTE)
A112: Housekeeping staff — FTE | C112: =Inputs!$B$49*(1+Inputs!$B$51)^(C$7-1)*MAX(0,MIN(1,C$6*1-Inputs!$B$52+1))/1 -> 1.5 | D112: =Inputs!$B$49*(1+Inputs!$B$51)^(D$7-1)*MAX(0,MIN(1,D$6*1-Inputs!$B$52+1))/1 -> 1.5 | E112: =Inputs!$B$49*(1+Inputs!$B$51)^(E$7-1)*MAX(0,MIN(1,E$6*1-Inputs!$B$52+1))/1 -> 1.5 | F112: =Inputs!$B$49*(1+Inputs!$B$51)^(F$7-1)*MAX(0,MIN(1,F$6*1-Inputs!$B$52+1))/1 -> 1.5 | G112: =Inputs!$B$49*(1+Inputs!$B$51)^(G$7-1)*MAX(0,MIN(1,G$6*1-Inputs!$B$52+1))/1 -> 1.5 | H112: =Inputs!$B$49*(1+Inputs!$B$51)^(H$7-1)*MAX(0,MIN(1,H$6*1-Inputs!$B$52+1))/1 -> 1.5 | I112: =Inputs!$B$49*(1+Inputs!$B$51)^(I$7-1)*MAX(0,MIN(1,I$6*1-Inputs!$B$52+1))/1 -> 1.5 | J112: =Inputs!$B$49*(1+Inputs!$B$51)^(J$7-1)*MAX(0,MIN(1,J$6*1-Inputs!$B$52+1))/1 -> 1.5 | ... BJ112: =Inputs!$B$49*(1+Inputs!$B$51)^(BJ$7-1)*MAX(0,MIN(1,BJ$6*1-Inputs!$B$52+1))/1 -> 1.5
A113: Host, manager & front desk — FTE | C113: =Inputs!$B$53*(1+Inputs!$B$55)^(C$7-1)*MAX(0,MIN(1,C$6*1-Inputs!$B$56+1))/1 -> 1 | D113: =Inputs!$B$53*(1+Inputs!$B$55)^(D$7-1)*MAX(0,MIN(1,D$6*1-Inputs!$B$56+1))/1 -> 1 | E113: =Inputs!$B$53*(1+Inputs!$B$55)^(E$7-1)*MAX(0,MIN(1,E$6*1-Inputs!$B$56+1))/1 -> 1 | F113: =Inputs!$B$53*(1+Inputs!$B$55)^(F$7-1)*MAX(0,MIN(1,F$6*1-Inputs!$B$56+1))/1 -> 1 | G113: =Inputs!$B$53*(1+Inputs!$B$55)^(G$7-1)*MAX(0,MIN(1,G$6*1-Inputs!$B$56+1))/1 -> 1 | H113: =Inputs!$B$53*(1+Inputs!$B$55)^(H$7-1)*MAX(0,MIN(1,H$6*1-Inputs!$B$56+1))/1 -> 1 | I113: =Inputs!$B$53*(1+Inputs!$B$55)^(I$7-1)*MAX(0,MIN(1,I$6*1-Inputs!$B$56+1))/1 -> 1 | J113: =Inputs!$B$53*(1+Inputs!$B$55)^(J$7-1)*MAX(0,MIN(1,J$6*1-Inputs!$B$56+1))/1 -> 1 | ... BJ113: =Inputs!$B$53*(1+Inputs!$B$55)^(BJ$7-1)*MAX(0,MIN(1,BJ$6*1-Inputs!$B$56+1))/1 -> 1
...

Sheet Checks
A1: Model checks | E1: =HYPERLINK("#'Cover'!A1","◂ Contents") -> ◂ Contents
A2: Live formulas: they re-run every time an input changes.
A3: Check | B3: Result | C3: What it tests
A4: Annual revenue ties to period detail | B4: =IF(ABS(SUM('P&L'!$B$5:$F$5)-SUM(Monthly!$C$20:$BJ$20))<0.5,"PASS","FAIL") -> PASS | C4: Sum of annual revenue equals the sum of every period
A5: Annual net income ties to period detail | B5: =IF(ABS(SUM('P&L'!$B$26:$F$26)-SUM(Monthly!$C$51:$BJ$51))<0.5,"PASS","FAIL") -> PASS | C5: Sum of annual net income equals the sum of every period
A6: EBITDA reconciliation | B6: =IF(ABS(SUM(Monthly!$C$42:$BJ$42)-SUM(Monthly!$C$29:$BJ$29)-SUM(Monthly!$C$41:$BJ$41))<0.5,"PASS","FAIL") -> PASS | C6: EBITDA = gross profit + operating expenses (costs are negative)
A7: Cash roll-forward | B7: =IF(ABS(INDEX(Monthly!$C$89:$BJ$89,60)-SUM(Monthly!$C$87:$BJ$87))<0.5,"PASS","FAIL") -> PASS | C7: Closing cash = all net cash flows since the start (opening cash is zero)
A8: Scenario selector valid | B8: =IF(AND(ISNUMBER(Dashboard!B4),Dashboard!B4>=1,Dashboard!B4<=3,INT(Dashboard!B4)=Dashboard!B4),"PASS","FAIL") -> PASS | C8: Dashboard!B4 is 1, 2 or 3
A9: Scenario ordering of drivers | B9: =IF(AND(Inputs!$B$8<=Inputs!$C$8,Inputs!$C$8<=Inputs!$D$8,Inputs!$B$9<=Inputs!$C$9,Inputs!$C$9<=Inputs!$D$9,Inputs!$B$10>=Inputs!$C$10,Inputs!$C$10>=Inputs!$D$10,Inputs!$B$11<=Inputs!$C$11,Inputs!$C$11<=Inputs!$D$11,Inputs!$B$14<=Inputs!$C$14,Inputs!$C$14<=Inputs!$D$14,Inputs!$B$17<=Inputs!$C$17,Inputs!$C$17<=Inputs!$D$17,Inputs!$B$18<=Inputs!$C$18,Inputs!$C$18<=Inputs!$D$18,Inputs!$B$19<=Inputs!$C$19,Inputs!$C$19<=Inputs!$D$19,Inputs!$B$22>=Inputs!$C$22,Inputs!$C$22>=Inputs!$D$22,Inputs!$B$23>=Inputs!$C$23,Inputs!$C$23>=Inputs!$D$23,Inputs!$B$24>=Inputs!$C$24,Inputs!$C$24>=Inputs!$D$24,Inputs!$B$25>=Inputs!$C$25,Inputs!$C$25>=Inputs!$D$25,Inputs!$B$26>=Inputs!$C$26,Inputs!$C$26>=Inputs!$D$26,Inputs!$B$34>=Inputs!$C$34,Inputs!$C$34>=Inputs!$D$34,Inputs!$B$37<=Inputs!$C$37,Inputs!$C$37<=Inputs!$D$37,Inputs!$B$38>=Inputs!$C$38,Inputs!$C$38>=Inputs!$D$38,Inputs!$B$39>=Inputs!$C$39,Inputs!$C$39>=Inputs!$D$39,Inputs!$B$49<=Inputs!$C$49,Inputs!$C$49<=Inputs!$D$49,Inputs!$B$51<=Inputs!$C$51,Inputs!$C$51<=Inputs!$D$51,Inputs!$B$53<=Inputs!$C$53,Inputs!$C$53<=Inputs!$D$53,Inputs!$B$55<=Inputs!$C$55,Inputs!$C$55<=Inputs!$D$55,Inputs!$B$57<=Inputs!$C$57,Inputs!$C$57<=Inputs!$D$57,Inputs!$B$59<=Inputs!$C$59,Inputs!$C$59<=Inputs!$D$59,Inputs!$B$83>=Inputs!$C$83,Inputs!$C$83>=Inputs!$D$83,Inputs!$B$84<=Inputs!$C$84,Inputs!$C$84<=Inputs!$D$84,Inputs!$B$85<=Inputs!$C$85,Inputs!$C$85<=Inputs!$D$85),"PASS","FAIL") -> PASS | C9: Low / Base / High ordered the right way for every growth and cost driver
A10: Gross margin within 0–100% | B10: =IF(AND(MIN('P&L'!$B$8:$F$8)>=0,MAX('P&L'!$B$8:$F$8)<=1),"PASS","FAIL") -> PASS | C10: Gross margin never negative or above 100%
A11: Loan balance never negative | B11: =IF(MIN(Monthly!$C$72:$BJ$72)>=-0.5,"PASS","FAIL") -> PASS | C11: Repayments never exceed the loan
A12: Funding table ties to the cash flow | B12: =IF(ABS('Break-even'!B18-('Break-even'!B16-'Break-even'!B10))<0.5,"PASS","FAIL") -> PASS | C12: Lowest cash balance = sources of funds − uses of funds up to that point
A13: Valuation: discounting ties to NPV() | B13: =IF(ABS(Valuation!B23-NPV(Valuation!B6,Valuation!$B$17:$F$17))<0.5,"PASS","FAIL") -> PASS | C13: Sum of discounted free cash flows equals Excel's NPV of the same flows
A14: Valuation: WACC above terminal growth | B14: =IF(Valuation!B6>Valuation!B7,"PASS","FAIL") -> PASS | C14: The perpetual-growth formula needs WACC > g
A15: Valuation: sensitivity centre = enterprise value | B15: =IF(ABS(Valuation!D36-Valuation!B27)<0.5,"PASS","FAIL") -> PASS | C15: The middle of the WACC × growth table reproduces the headline value
A16: Valuation: final-year cash flow positive | B16: =IF(Valuation!$F$17>0,"PASS","WARN") -> PASS | C16: Business warning: a negative final-year cash flow gives a negative terminal value (often a 1-year plan still carrying start-up spending)
A17: Sources & uses balance | B17: =IF(ABS('Sources & Uses'!B21-'Sources & Uses'!B28)<0.5,"PASS","FAIL") -> PASS | C17: Sources of funds = uses of funds (incl. cash at the end) for the Sources & Uses period
A18: No error values | B18: =IF(SUMPRODUCT(--ISERROR(Monthly!$C$4:$BJ$107))+SUMPRODUCT(--ISERROR(Headcount!$C$4:$BJ$17))+SUMPRODUCT(--ISERROR('P&L'!$B$3:$F$27))+SUMPRODUCT(--ISERROR('Cash Flow'!$B$3:$F$18))+SUMPRODUCT(--ISERROR('Balance Sheet'!$B$3:$F$17))+SUMPRODUCT(--ISERROR(KPIs!$B$27:$F$44))+SUMPRODUCT(--ISERROR('Break-even'!$B$26:$F$33))+SUMPRODUCT(--ISERROR(Valuation!$B$14:$F$19))+SUMPRODUCT(--ISERROR('Break-even'!$B$3:$F$35))+SUMPRODUCT(--ISERROR(Valuation!$A$3:$F$40))+SUMPRODUCT(--ISERROR('Sources & Uses'!$B$3:$C$30))+SUMPRODUCT(--ISERROR(Dashboard!$A$6:$W$44))+SUMPRODUCT(--ISERROR(Summary!$A$5:$S$52))+SUMPRODUCT(--ISERROR(KPIs!$A$4:$G$44))+SUMPRODUCT(--ISERROR('Scenario calc'!$C$6:$BJ$121))+SUMPRODUCT(--ISERROR('Scenario calc'!$C$126:$BJ$241))+SUMPRODUCT(--ISERROR('Scenario calc'!$C$246:$BJ$361))+SUMPRODUCT(--ISERROR(Scenarios!$B$5:$F$50))=0,"PASS","FAIL") -> PASS | C18: No error values (divide-by-zero, broken references) on any calculation sheet
A19: Summary ties to statements | B19: =IF(IFERROR(AND(SUMPRODUCT(--(ABS(Summary!$B$7:$F$7-'P&L'!$B$5:$F$5)>0.5))=0,SUMPRODUCT(--(ABS(Summary!$B$19:$F$19-'P&L'!$B$26:$F$26)>0.5))=0,SUMPRODUCT(--(ABS(Summary!$B$31:$F$31-'Cash Flow'!$B$18:$F$18)>0.5))=0,SUMPRODUCT(--(ABS(Summary!$B$41:$F$41-'Balance Sheet'!$B$5:$F$5)>0.5))=0,ABS(SUM(Summary!$H$7:$S$7)-INDEX(Summary!$B$7:$F$7,Summary!$R$2))<0.5,ABS(SUM(Summary!$H$19:$S$19)-INDEX(Summary!$B$19:$F$19,Summary!$R$2))<0.5,ABS(Summary!$S$31-INDEX(Summary!$B$31:$F$31,Summary!$R$2))<0.5),FALSE()),"PASS","FAIL") -> PASS | C19: Summary revenue, net income and closing cash equal the statements every year; the detailed year adds up to its annual figure
A20: DuPont ties to return on equity | B20: =IF(SUMPRODUCT(--(ABS(KPIs!$B$24:$F$24)>0.000000001))>0,"FAIL",IF(SUMPRODUCT(ISNUMBER(KPIs!$B$23:$F$23)*ISNUMBER(KPIs!$B$16:$F$16))=0,"n/a","PASS")) -> PASS | C20: Net margin × asset turnover × equity multiplier equals return on equity every year; n/a = no year where both are defined (a one-sided n/a is a FAIL)
A21: Scenarios: Active = selected scenario | B21: =IF(IFERROR(AND(ABS(Scenarios!E17-INDEX(Scenarios!B17:D17,1,Dashboard!$B$4))<0.5,ABS(Scenarios!E18-INDEX(Scenarios!B18:D18,1,Dashboard!$B$4))<0.5,ABS(Scenarios!E19-INDEX(Scenarios!B19:D19,1,Dashboard!$B$4))<0.5,ABS(Scenarios!E20-INDEX(Scenarios!B20:D20,1,Dashboard!$B$4))<0.000001,ABS(Scenarios!E21-INDEX(Scenarios!B21:D21,1,Dashboard!$B$4))<0.5,ABS(Scenarios!E22-INDEX(Scenarios!B22:D22,1,Dashboard!$B$4))<0.5,ABS(Scenarios!E23-INDEX(Scenarios!B23:D23,1,Dashboard!$B$4))<0.5,ABS(Scenarios!E24-INDEX(Scenarios!B24:D24,1,Dashboard!$B$4))<0.5,ABS(Scenarios!E25-INDEX(Scenarios!B25:D25,1,Dashboard!$B$4))<0.5,ABS(Scenarios!E26-INDEX(Scenarios!B26:D26,1,Dashboard!$B$4))<0.5),FALSE()),"PASS","FAIL") -> PASS | C21: On the Scenarios sheet the live model (Active) equals the Low / Base / High column chosen on the Dashboard for every output
A22: Balance sheet balances every period | B22: =IF(SUMPRODUCT(--(ABS(Monthly!$C$107:$BJ$107)>0.5))=0,"PASS","FAIL") -> PASS | C22: Assets = liabilities + equity in every period
A23: Funding sufficient (cash ≥ 0) | B23: =IF(MIN(Monthly!$C$89:$BJ$89)>=0,"PASS","WARN") -> PASS | C23: Business warning, not an error: cash dips below zero in this scenario
A25: Overall verdict | B25: =IF(COUNTIF(B4:B23,"FAIL")>0,"FAIL",IF(COUNTIF(B4:B23,"WARN")>0,"PASS WITH WARNINGS","PASS")) -> PASS
