Workbook

Sheet Cover
B2: Home services financial model (growing)
B3: 3-year financial model · monthly detail · Low / Base / High scenarios · US dollars · Full plan
B5: Purpose | D5: Revenue and profit plan
B6: Active scenario | D6: =Dashboard!C4&" (change it on the Dashboard, cell B4)" -> Base (change it on the Dashboard, cell B4)
B7: Model checks | D7: =Checks!B25 -> PASS
B8: Prepared | D8: 22 October 2026
B10: Contents
C11: PRESENTATION
B12: 1 | C12: =HYPERLINK("#Dashboard!A1","Dashboard") -> Dashboard | D12: Scenario switch, key numbers, core financials
B13: 2 | C13: =HYPERLINK("#Summary!A1","Summary") -> Summary | D13: Income statement, cash flow and balance sheet — every year and any year by month
B14: 3 | C14: =HYPERLINK("#Scenarios!A1","Scenarios") -> Scenarios | D14: Low / Base / High side by side: drivers, outputs, charts
B15: 4 | C15: =HYPERLINK("#'Break-even'!A1","Break-even") -> Break-even | D15: Startup costs, funding need, break-even timing and revenue
B16: 5 | C16: =HYPERLINK("#Valuation!A1","Valuation") -> Valuation | D16: Free cash flow, DCF (perpetual growth and exit multiple), WACC × growth sensitivity
B17: 6 | C17: =HYPERLINK("#'Sources & Uses'!A1","Sources & Uses") -> Sources & Uses | D17: Funding structure, sources and uses of cash for the first months
B18: 7 | C18: =HYPERLINK("#KPIs!A1","KPIs") -> KPIs | D18: Financial ratios, DuPont analysis, industry metrics
C19: INPUTS
B20: 8 | C20: =HYPERLINK("#Inputs!A1","Inputs") -> Inputs | D20: Every assumption, Low / Base / High, with units and comments
C21: STATEMENTS
B22: 9 | C22: =HYPERLINK("#'P&L'!A1","P&L") -> P&L | D22: Annual profit & loss
B23: 10 | C23: =HYPERLINK("#'Cash Flow'!A1","Cash Flow") -> Cash Flow | D23: Annual cash flow statement
B24: 11 | C24: =HYPERLINK("#'Balance Sheet'!A1","Balance Sheet") -> Balance Sheet | D24: Balance sheet at year end
C25: CALCULATIONS
B26: 12 | C26: =HYPERLINK("#Monthly!A1","Monthly") -> Monthly | D26: Month-by-month engine of the model
B27: 13 | C27: =HYPERLINK("#Headcount!A1","Headcount") -> Headcount | D27: Team and payroll
B28: 14 | C28: =HYPERLINK("#'Scenario calc'!A1","Scenario calc") -> Scenario calc | D28: Low, Base and High calculated side by side for the Scenarios sheet
C29: CONTROL
B30: 15 | C30: =HYPERLINK("#Checks!A1","Checks") -> Checks | D30: Live integrity checks and the overall verdict
B32: How to read this file
C33: 1000 | D33: Input you can change — yellow cell with a blue figure (Inputs sheet and the view switches)
C34: 1000 | D34: Formula — calculated, do not overwrite
C35: 1000 | D35: Link to another sheet
C36: 1000 | D36: Active value the model uses (follows the scenario)

Sheet Dashboard
A1: Dashboard | W1: =HYPERLINK("#'Cover'!A1","◂ Contents") -> ◂ Contents
A2: Home services financial model (growing)
A4: Active scenario | B4: 2 | C4: =CHOOSE(B4,"Low","Base","High") -> Base | D4: 1 = Low · 2 = Base · 3 = High — every sheet follows this cell | S4: Model checks | T4: =Checks!B25 -> PASS
A6: REVENUE · YEAR 3 | C6: EBITDA MARGIN · YEAR 3 | H6: NET INCOME · YEAR 3 | L6: LOWEST CASH BALANCE | P6: FUNDING REQUIRED | T6: ENTERPRISE VALUE (DCF)
A7: =D12 -> 2376160.7 | C7: =D17 -> 0.2021959 | H7: =D18 -> 355570.65 | L7: =F38 -> 339238.12 | P7: =F36 -> 108761.88 | T7: =F43 -> 2205569.6
A8: =IF(AND(B12>0,D12>=0),(D12/B12)^(1/2)-1,"CAGR n/a") -> 0.17878891 | C8: =D16 -> 480449.96 | H8: =D19 -> 0.14964082 | L8: ='Break-even'!B6 -> 1 | P8: =IF(F37>=0,"Covered by funding raised",-F37) -> Covered by funding raised | T8: Average of 2 methods
A10: Core financials ($'000) — active scenario
B11: 1 | C11: 2 | D11: 3
A12: Revenue | B12: =SUMIF(Monthly!$C$5:$AL$5,B$11,Monthly!$C$22:$AL$22) -> 1710030 | C12: =SUMIF(Monthly!$C$5:$AL$5,C$11,Monthly!$C$22:$AL$22) -> 2015484.9 | D12: =SUMIF(Monthly!$C$5:$AL$5,D$11,Monthly!$C$22:$AL$22) -> 2376160.7
A13: Gross profit | B13: =SUMIF(Monthly!$C$5:$AL$5,B$11,Monthly!$C$30:$AL$30) -> 659822.5 | C13: =SUMIF(Monthly!$C$5:$AL$5,C$11,Monthly!$C$30:$AL$30) -> 795749.55 | D13: =SUMIF(Monthly!$C$5:$AL$5,D$11,Monthly!$C$30:$AL$30) -> 958942.46
A14: Gross margin | B14: =IF(B12=0,0,B13/B12) -> 0.38585434 | C14: =IF(C12=0,0,C13/C12) -> 0.39481791 | D14: =IF(D12=0,0,D13/D12) -> 0.40356802
A15: Operating expenses | B15: =SUMIF(Monthly!$C$5:$AL$5,B$11,Monthly!$C$40:$AL$40) -> -393750.81 | C15: =SUMIF(Monthly!$C$5:$AL$5,C$11,Monthly!$C$40:$AL$40) -> -433173.19 | D15: =SUMIF(Monthly!$C$5:$AL$5,D$11,Monthly!$C$40:$AL$40) -> -478492.5
A16: EBITDA | B16: =SUMIF(Monthly!$C$5:$AL$5,B$11,Monthly!$C$41:$AL$41) -> 266071.69 | C16: =SUMIF(Monthly!$C$5:$AL$5,C$11,Monthly!$C$41:$AL$41) -> 362576.36 | D16: =SUMIF(Monthly!$C$5:$AL$5,D$11,Monthly!$C$41:$AL$41) -> 480449.96
A17: EBITDA margin | B17: =IF(B12=0,0,B16/B12) -> 0.15559475 | C17: =IF(C12=0,0,C16/C12) -> 0.17989534 | D17: =IF(D12=0,0,D16/D12) -> 0.2021959
A18: Net income | B18: =SUMIF(Monthly!$C$5:$AL$5,B$11,Monthly!$C$50:$AL$50) -> 192564.27 | C18: =SUMIF(Monthly!$C$5:$AL$5,C$11,Monthly!$C$50:$AL$50) -> 265979.59 | D18: =SUMIF(Monthly!$C$5:$AL$5,D$11,Monthly!$C$50:$AL$50) -> 355570.65
A19: Net margin | B19: =IF(B12=0,0,B18/B12) -> 0.11260871 | C19: =IF(C12=0,0,C18/C12) -> 0.13196803 | D19: =IF(D12=0,0,D18/D12) -> 0.14964082
A20: Operating cash flow | B20: =SUMIF(Monthly!$C$5:$AL$5,B$11,Monthly!$C$74:$AL$74) -> 194710.8 | C20: =SUMIF(Monthly!$C$5:$AL$5,C$11,Monthly!$C$74:$AL$74) -> 276206.62 | D20: =SUMIF(Monthly!$C$5:$AL$5,D$11,Monthly!$C$74:$AL$74) -> 373872.07
A21: Investing cash flow | B21: =SUMIF(Monthly!$C$5:$AL$5,B$11,Monthly!$C$75:$AL$75) -> -20000 | C21: =SUMIF(Monthly!$C$5:$AL$5,C$11,Monthly!$C$75:$AL$75) -> -37800 | D21: =SUMIF(Monthly!$C$5:$AL$5,D$11,Monthly!$C$75:$AL$75) -> -42336
A22: Financing cash flow | B22: =SUMIF(Monthly!$C$5:$AL$5,B$11,Monthly!$C$77:$AL$77) -> 304166.67 | C22: =SUMIF(Monthly!$C$5:$AL$5,C$11,Monthly!$C$77:$AL$77) -> -50000 | D22: =SUMIF(Monthly!$C$5:$AL$5,D$11,Monthly!$C$77:$AL$77) -> -50000
A23: Net change in cash | B23: =SUMIF(Monthly!$C$5:$AL$5,B$11,Monthly!$C$78:$AL$78) -> 478877.47 | C23: =SUMIF(Monthly!$C$5:$AL$5,C$11,Monthly!$C$78:$AL$78) -> 188406.62 | D23: =SUMIF(Monthly!$C$5:$AL$5,D$11,Monthly!$C$78:$AL$78) -> 281536.07
A24: Year-end cash | B24: =INDEX(Monthly!$C$80:$AL$80,B$11*12) -> 478877.47 | C24: =INDEX(Monthly!$C$80:$AL$80,C$11*12) -> 667284.09 | D24: =INDEX(Monthly!$C$80:$AL$80,D$11*12) -> 948820.16
A26: Home services metrics
B27: 1 | C27: 2 | D27: 3
A28: Jobs completed | B28: =KPIs!B32 -> 3668.25 | C28: =KPIs!C32 -> 4185.4125 | D28: =KPIs!D32 -> 4776.1804
A29: Technician utilisation | B29: =KPIs!B33 -> 0.83180272 | C29: =KPIs!C33 -> 0.84738672 | D29: =KPIs!D33 -> 0.86338815
A30: Average revenue per job | B30: =KPIs!B40 -> 440 | C30: =KPIs!C40 -> 453.2 | D30: =KPIs!D40 -> 466.796
A31: Team (FTE, year end) | B31: =INDEX(Headcount!$C$10:$AL$10,B$27*12) -> 9 | C31: =INDEX(Headcount!$C$10:$AL$10,C$27*12) -> 10.04 | D31: =INDEX(Headcount!$C$10:$AL$10,D$27*12) -> 11.2008
A33: Funding & valuation ($'000) — active scenario
A34: Equity raised | F34: =Inputs!$E$54 -> 100000
A35: Loan drawn | F35: =Inputs!$E$55 -> 250000
A36: Funding required (incl. cash buffer) | F36: ='Break-even'!B12 -> 108761.88
A37: Funding surplus / (shortfall) | F37: ='Break-even'!B17 -> 241238.12
A38: ="Lowest cash balance (month "&'Break-even'!B6&")" -> Lowest cash balance (month 1) | F38: ='Break-even'!B18 -> 339238.12
A39: First month with positive EBITDA | F39: ='Break-even'!B21 -> 1
A40: Cash invested paid back | F40: ='Break-even'!B23 -> 2
A41: Enterprise value — perpetual growth | F41: =Valuation!B27 -> 2151907.5
A42: Enterprise value — exit multiple | F42: =Valuation!C27 -> 2259231.7
A43: Enterprise value — average | F43: =Valuation!B30 -> 2205569.6

Sheet Summary
A1: Financial statements summary | U1: =HYPERLINK("#'Cover'!A1","◂ Contents") -> ◂ Contents
A2: Home services financial model (growing) | P2: Select detailed year: | R2: 1
A5: Income statement ($'000) — by year | H5: ="Income statement ($'000) — Year "&$R$2&", by month" -> Income statement ($'000) — Year 1, by month
B6: 1 | C6: 2 | D6: 3 | H6: =INDEX(Monthly!$C$4:$AL$4,($R$2-1)*12+1) -> 1 | I6: =INDEX(Monthly!$C$4:$AL$4,($R$2-1)*12+2) -> 2 | J6: =INDEX(Monthly!$C$4:$AL$4,($R$2-1)*12+3) -> 3 | K6: =INDEX(Monthly!$C$4:$AL$4,($R$2-1)*12+4) -> 4 | L6: =INDEX(Monthly!$C$4:$AL$4,($R$2-1)*12+5) -> 5 | M6: =INDEX(Monthly!$C$4:$AL$4,($R$2-1)*12+6) -> 6 | N6: =INDEX(Monthly!$C$4:$AL$4,($R$2-1)*12+7) -> 7 | O6: =INDEX(Monthly!$C$4:$AL$4,($R$2-1)*12+8) -> 8 | P6: =INDEX(Monthly!$C$4:$AL$4,($R$2-1)*12+9) -> 9 | Q6: =INDEX(Monthly!$C$4:$AL$4,($R$2-1)*12+10) -> 10 | R6: =INDEX(Monthly!$C$4:$AL$4,($R$2-1)*12+11) -> 11 | S6: =INDEX(Monthly!$C$4:$AL$4,($R$2-1)*12+12) -> 12
A7: Revenue | B7: ='P&L'!B5 -> 1710030 | C7: ='P&L'!C5 -> 2015484.9 | D7: ='P&L'!D5 -> 2376160.7 | H7: =INDEX(Monthly!$C$22:$AL$22,($R$2-1)*12+1) -> 133436.67 | I7: =INDEX(Monthly!$C$22:$AL$22,($R$2-1)*12+2) -> 133436.67 | J7: =INDEX(Monthly!$C$22:$AL$22,($R$2-1)*12+3) -> 133436.67 | K7: =INDEX(Monthly!$C$22:$AL$22,($R$2-1)*12+4) -> 133436.67 | L7: =INDEX(Monthly!$C$22:$AL$22,($R$2-1)*12+5) -> 133436.67 | M7: =INDEX(Monthly!$C$22:$AL$22,($R$2-1)*12+6) -> 169700 | N7: =INDEX(Monthly!$C$22:$AL$22,($R$2-1)*12+7) -> 169700 | O7: =INDEX(Monthly!$C$22:$AL$22,($R$2-1)*12+8) -> 169700 | P7: =INDEX(Monthly!$C$22:$AL$22,($R$2-1)*12+9) -> 133436.67 | Q7: =INDEX(Monthly!$C$22:$AL$22,($R$2-1)*12+10) -> 133436.67 | R7: =INDEX(Monthly!$C$22:$AL$22,($R$2-1)*12+11) -> 133436.67 | S7: =INDEX(Monthly!$C$22:$AL$22,($R$2-1)*12+12) -> 133436.67
A8: Cost of delivery | B8: ='P&L'!B6 -> -1050207.5 | C8: ='P&L'!C6 -> -1219735.4 | D8: ='P&L'!D6 -> -1417218.2 | H8: =INDEX(Monthly!$C$29:$AL$29,($R$2-1)*12+1) -> -85250.833 | I8: =INDEX(Monthly!$C$29:$AL$29,($R$2-1)*12+2) -> -85250.833 | J8: =INDEX(Monthly!$C$29:$AL$29,($R$2-1)*12+3) -> -85250.833 | K8: =INDEX(Monthly!$C$29:$AL$29,($R$2-1)*12+4) -> -85250.833 | L8: =INDEX(Monthly!$C$29:$AL$29,($R$2-1)*12+5) -> -85250.833 | M8: =INDEX(Monthly!$C$29:$AL$29,($R$2-1)*12+6) -> -94316.667 | N8: =INDEX(Monthly!$C$29:$AL$29,($R$2-1)*12+7) -> -94316.667 | O8: =INDEX(Monthly!$C$29:$AL$29,($R$2-1)*12+8) -> -94316.667 | P8: =INDEX(Monthly!$C$29:$AL$29,($R$2-1)*12+9) -> -85250.833 | Q8: =INDEX(Monthly!$C$29:$AL$29,($R$2-1)*12+10) -> -85250.833 | R8: =INDEX(Monthly!$C$29:$AL$29,($R$2-1)*12+11) -> -85250.833 | S8: =INDEX(Monthly!$C$29:$AL$29,($R$2-1)*12+12) -> -85250.833
A9: Gross profit | B9: ='P&L'!B7 -> 659822.5 | C9: ='P&L'!C7 -> 795749.55 | D9: ='P&L'!D7 -> 958942.46 | H9: =INDEX(Monthly!$C$30:$AL$30,($R$2-1)*12+1) -> 48185.833 | I9: =INDEX(Monthly!$C$30:$AL$30,($R$2-1)*12+2) -> 48185.833 | J9: =INDEX(Monthly!$C$30:$AL$30,($R$2-1)*12+3) -> 48185.833 | K9: =INDEX(Monthly!$C$30:$AL$30,($R$2-1)*12+4) -> 48185.833 | L9: =INDEX(Monthly!$C$30:$AL$30,($R$2-1)*12+5) -> 48185.833 | M9: =INDEX(Monthly!$C$30:$AL$30,($R$2-1)*12+6) -> 75383.333 | N9: =INDEX(Monthly!$C$30:$AL$30,($R$2-1)*12+7) -> 75383.333 | O9: =INDEX(Monthly!$C$30:$AL$30,($R$2-1)*12+8) -> 75383.333 | P9: =INDEX(Monthly!$C$30:$AL$30,($R$2-1)*12+9) -> 48185.833 | Q9: =INDEX(Monthly!$C$30:$AL$30,($R$2-1)*12+10) -> 48185.833 | R9: =INDEX(Monthly!$C$30:$AL$30,($R$2-1)*12+11) -> 48185.833 | S9: =INDEX(Monthly!$C$30:$AL$30,($R$2-1)*12+12) -> 48185.833
A10: Gross margin | B10: ='P&L'!B8 -> 0.38585434 | C10: ='P&L'!C8 -> 0.39481791 | D10: ='P&L'!D8 -> 0.40356802 | H10: =IF(H7=0,0,H9/H7) -> 0.36111389 | I10: =IF(I7=0,0,I9/I7) -> 0.36111389 | J10: =IF(J7=0,0,J9/J7) -> 0.36111389 | K10: =IF(K7=0,0,K9/K7) -> 0.36111389 | L10: =IF(L7=0,0,L9/L7) -> 0.36111389 | M10: =IF(M7=0,0,M9/M7) -> 0.44421528 | N10: =IF(N7=0,0,N9/N7) -> 0.44421528 | O10: =IF(O7=0,0,O9/O7) -> 0.44421528 | ... S10: =IF(S7=0,0,S9/S7) -> 0.36111389
A11: Total operating expenses | B11: ='P&L'!B16 -> -393750.81 | C11: ='P&L'!C16 -> -433173.19 | D11: ='P&L'!D16 -> -478492.5 | H11: =INDEX(Monthly!$C$40:$AL$40,($R$2-1)*12+1) -> -32567.79 | I11: =INDEX(Monthly!$C$40:$AL$40,($R$2-1)*12+2) -> -32567.79 | J11: =INDEX(Monthly!$C$40:$AL$40,($R$2-1)*12+3) -> -32567.79 | K11: =INDEX(Monthly!$C$40:$AL$40,($R$2-1)*12+4) -> -32567.79 | L11: =INDEX(Monthly!$C$40:$AL$40,($R$2-1)*12+5) -> -32567.79 | M11: =INDEX(Monthly!$C$40:$AL$40,($R$2-1)*12+6) -> -33546.9 | N11: =INDEX(Monthly!$C$40:$AL$40,($R$2-1)*12+7) -> -33546.9 | O11: =INDEX(Monthly!$C$40:$AL$40,($R$2-1)*12+8) -> -33546.9 | P11: =INDEX(Monthly!$C$40:$AL$40,($R$2-1)*12+9) -> -32567.79 | Q11: =INDEX(Monthly!$C$40:$AL$40,($R$2-1)*12+10) -> -32567.79 | R11: =INDEX(Monthly!$C$40:$AL$40,($R$2-1)*12+11) -> -32567.79 | S11: =INDEX(Monthly!$C$40:$AL$40,($R$2-1)*12+12) -> -32567.79
A12: EBITDA | B12: ='P&L'!B17 -> 266071.69 | C12: ='P&L'!C17 -> 362576.36 | D12: ='P&L'!D17 -> 480449.96 | H12: =INDEX(Monthly!$C$41:$AL$41,($R$2-1)*12+1) -> 15618.043 | I12: =INDEX(Monthly!$C$41:$AL$41,($R$2-1)*12+2) -> 15618.043 | J12: =INDEX(Monthly!$C$41:$AL$41,($R$2-1)*12+3) -> 15618.043 | K12: =INDEX(Monthly!$C$41:$AL$41,($R$2-1)*12+4) -> 15618.043 | L12: =INDEX(Monthly!$C$41:$AL$41,($R$2-1)*12+5) -> 15618.043 | M12: =INDEX(Monthly!$C$41:$AL$41,($R$2-1)*12+6) -> 41836.433 | N12: =INDEX(Monthly!$C$41:$AL$41,($R$2-1)*12+7) -> 41836.433 | O12: =INDEX(Monthly!$C$41:$AL$41,($R$2-1)*12+8) -> 41836.433 | P12: =INDEX(Monthly!$C$41:$AL$41,($R$2-1)*12+9) -> 15618.043 | Q12: =INDEX(Monthly!$C$41:$AL$41,($R$2-1)*12+10) -> 15618.043 | R12: =INDEX(Monthly!$C$41:$AL$41,($R$2-1)*12+11) -> 15618.043 | S12: =INDEX(Monthly!$C$41:$AL$41,($R$2-1)*12+12) -> 15618.043
A13: EBITDA margin | B13: ='P&L'!B18 -> 0.15559475 | C13: ='P&L'!C18 -> 0.17989534 | D13: ='P&L'!D18 -> 0.2021959 | H13: =IF(H7=0,0,H12/H7) -> 0.11704462 | I13: =IF(I7=0,0,I12/I7) -> 0.11704462 | J13: =IF(J7=0,0,J12/J7) -> 0.11704462 | K13: =IF(K7=0,0,K12/K7) -> 0.11704462 | L13: =IF(L7=0,0,L12/L7) -> 0.11704462 | M13: =IF(M7=0,0,M12/M7) -> 0.24653172 | N13: =IF(N7=0,0,N12/N7) -> 0.24653172 | O13: =IF(O7=0,0,O12/O7) -> 0.24653172 | ... S13: =IF(S7=0,0,S12/S7) -> 0.11704462
A14: Depreciation | B14: ='P&L'!B19 -> -4000 | C14: ='P&L'!C19 -> -11560 | D14: ='P&L'!D19 -> -20027.2 | H14: =INDEX(Monthly!$C$55:$AL$55,($R$2-1)*12+1) -> -333.33333 | I14: =INDEX(Monthly!$C$55:$AL$55,($R$2-1)*12+2) -> -333.33333 | J14: =INDEX(Monthly!$C$55:$AL$55,($R$2-1)*12+3) -> -333.33333 | K14: =INDEX(Monthly!$C$55:$AL$55,($R$2-1)*12+4) -> -333.33333 | L14: =INDEX(Monthly!$C$55:$AL$55,($R$2-1)*12+5) -> -333.33333 | M14: =INDEX(Monthly!$C$55:$AL$55,($R$2-1)*12+6) -> -333.33333 | N14: =INDEX(Monthly!$C$55:$AL$55,($R$2-1)*12+7) -> -333.33333 | O14: =INDEX(Monthly!$C$55:$AL$55,($R$2-1)*12+8) -> -333.33333 | P14: =INDEX(Monthly!$C$55:$AL$55,($R$2-1)*12+9) -> -333.33333 | Q14: =INDEX(Monthly!$C$55:$AL$55,($R$2-1)*12+10) -> -333.33333 | R14: =INDEX(Monthly!$C$55:$AL$55,($R$2-1)*12+11) -> -333.33333 | S14: =INDEX(Monthly!$C$55:$AL$55,($R$2-1)*12+12) -> -333.33333
A15: EBIT | B15: ='P&L'!B20 -> 262071.69 | C15: ='P&L'!C20 -> 351016.36 | D15: ='P&L'!D20 -> 460422.76 | H15: =INDEX(Monthly!$C$44:$AL$44,($R$2-1)*12+1) -> 15284.71 | I15: =INDEX(Monthly!$C$44:$AL$44,($R$2-1)*12+2) -> 15284.71 | J15: =INDEX(Monthly!$C$44:$AL$44,($R$2-1)*12+3) -> 15284.71 | K15: =INDEX(Monthly!$C$44:$AL$44,($R$2-1)*12+4) -> 15284.71 | L15: =INDEX(Monthly!$C$44:$AL$44,($R$2-1)*12+5) -> 15284.71 | M15: =INDEX(Monthly!$C$44:$AL$44,($R$2-1)*12+6) -> 41503.1 | N15: =INDEX(Monthly!$C$44:$AL$44,($R$2-1)*12+7) -> 41503.1 | O15: =INDEX(Monthly!$C$44:$AL$44,($R$2-1)*12+8) -> 41503.1 | P15: =INDEX(Monthly!$C$44:$AL$44,($R$2-1)*12+9) -> 15284.71 | Q15: =INDEX(Monthly!$C$44:$AL$44,($R$2-1)*12+10) -> 15284.71 | R15: =INDEX(Monthly!$C$44:$AL$44,($R$2-1)*12+11) -> 15284.71 | S15: =INDEX(Monthly!$C$44:$AL$44,($R$2-1)*12+12) -> 15284.71
A16: Interest | B16: ='P&L'!B21 -> -18319.444 | C16: ='P&L'!C21 -> -14333.333 | D16: ='P&L'!D21 -> -10333.333 | H16: =INDEX(Monthly!$C$45:$AL$45,($R$2-1)*12+1) -> -1666.6667 | I16: =INDEX(Monthly!$C$45:$AL$45,($R$2-1)*12+2) -> -1652.7778 | J16: =INDEX(Monthly!$C$45:$AL$45,($R$2-1)*12+3) -> -1625 | K16: =INDEX(Monthly!$C$45:$AL$45,($R$2-1)*12+4) -> -1597.2222 | L16: =INDEX(Monthly!$C$45:$AL$45,($R$2-1)*12+5) -> -1569.4444 | M16: =INDEX(Monthly!$C$45:$AL$45,($R$2-1)*12+6) -> -1541.6667 | N16: =INDEX(Monthly!$C$45:$AL$45,($R$2-1)*12+7) -> -1513.8889 | O16: =INDEX(Monthly!$C$45:$AL$45,($R$2-1)*12+8) -> -1486.1111 | P16: =INDEX(Monthly!$C$45:$AL$45,($R$2-1)*12+9) -> -1458.3333 | Q16: =INDEX(Monthly!$C$45:$AL$45,($R$2-1)*12+10) -> -1430.5556 | R16: =INDEX(Monthly!$C$45:$AL$45,($R$2-1)*12+11) -> -1402.7778 | S16: =INDEX(Monthly!$C$45:$AL$45,($R$2-1)*12+12) -> -1375
A17: Pre-tax income | B17: ='P&L'!B22 -> 243752.25 | C17: ='P&L'!C22 -> 336683.02 | D17: ='P&L'!D22 -> 450089.43 | H17: =INDEX(Monthly!$C$46:$AL$46,($R$2-1)*12+1) -> 13618.043 | I17: =INDEX(Monthly!$C$46:$AL$46,($R$2-1)*12+2) -> 13631.932 | J17: =INDEX(Monthly!$C$46:$AL$46,($R$2-1)*12+3) -> 13659.71 | K17: =INDEX(Monthly!$C$46:$AL$46,($R$2-1)*12+4) -> 13687.488 | L17: =INDEX(Monthly!$C$46:$AL$46,($R$2-1)*12+5) -> 13715.266 | M17: =INDEX(Monthly!$C$46:$AL$46,($R$2-1)*12+6) -> 39961.433 | N17: =INDEX(Monthly!$C$46:$AL$46,($R$2-1)*12+7) -> 39989.211 | O17: =INDEX(Monthly!$C$46:$AL$46,($R$2-1)*12+8) -> 40016.989 | P17: =INDEX(Monthly!$C$46:$AL$46,($R$2-1)*12+9) -> 13826.377 | Q17: =INDEX(Monthly!$C$46:$AL$46,($R$2-1)*12+10) -> 13854.154 | R17: =INDEX(Monthly!$C$46:$AL$46,($R$2-1)*12+11) -> 13881.932 | S17: =INDEX(Monthly!$C$46:$AL$46,($R$2-1)*12+12) -> 13909.71
A18: Income tax | B18: ='P&L'!B23 -> -51187.972 | C18: ='P&L'!C23 -> -70703.435 | D18: ='P&L'!D23 -> -94518.78 | H18: =INDEX(Monthly!$C$49:$AL$49,($R$2-1)*12+1) -> -2859.7891 | I18: =INDEX(Monthly!$C$49:$AL$49,($R$2-1)*12+2) -> -2862.7058 | J18: =INDEX(Monthly!$C$49:$AL$49,($R$2-1)*12+3) -> -2868.5391 | K18: =INDEX(Monthly!$C$49:$AL$49,($R$2-1)*12+4) -> -2874.3724 | L18: =INDEX(Monthly!$C$49:$AL$49,($R$2-1)*12+5) -> -2880.2058 | M18: =INDEX(Monthly!$C$49:$AL$49,($R$2-1)*12+6) -> -8391.901 | N18: =INDEX(Monthly!$C$49:$AL$49,($R$2-1)*12+7) -> -8397.7343 | O18: =INDEX(Monthly!$C$49:$AL$49,($R$2-1)*12+8) -> -8403.5677 | P18: =INDEX(Monthly!$C$49:$AL$49,($R$2-1)*12+9) -> -2903.5391 | Q18: =INDEX(Monthly!$C$49:$AL$49,($R$2-1)*12+10) -> -2909.3724 | R18: =INDEX(Monthly!$C$49:$AL$49,($R$2-1)*12+11) -> -2915.2058 | S18: =INDEX(Monthly!$C$49:$AL$49,($R$2-1)*12+12) -> -2921.0391
A19: Net income | B19: ='P&L'!B24 -> 192564.27 | C19: ='P&L'!C24 -> 265979.59 | D19: ='P&L'!D24 -> 355570.65 | H19: =INDEX(Monthly!$C$50:$AL$50,($R$2-1)*12+1) -> 10758.254 | I19: =INDEX(Monthly!$C$50:$AL$50,($R$2-1)*12+2) -> 10769.226 | J19: =INDEX(Monthly!$C$50:$AL$50,($R$2-1)*12+3) -> 10791.171 | K19: =INDEX(Monthly!$C$50:$AL$50,($R$2-1)*12+4) -> 10813.115 | L19: =INDEX(Monthly!$C$50:$AL$50,($R$2-1)*12+5) -> 10835.06 | M19: =INDEX(Monthly!$C$50:$AL$50,($R$2-1)*12+6) -> 31569.532 | N19: =INDEX(Monthly!$C$50:$AL$50,($R$2-1)*12+7) -> 31591.477 | O19: =INDEX(Monthly!$C$50:$AL$50,($R$2-1)*12+8) -> 31613.421 | P19: =INDEX(Monthly!$C$50:$AL$50,($R$2-1)*12+9) -> 10922.838 | Q19: =INDEX(Monthly!$C$50:$AL$50,($R$2-1)*12+10) -> 10944.782 | R19: =INDEX(Monthly!$C$50:$AL$50,($R$2-1)*12+11) -> 10966.726 | S19: =INDEX(Monthly!$C$50:$AL$50,($R$2-1)*12+12) -> 10988.671
A20: Net margin | B20: ='P&L'!B25 -> 0.11260871 | C20: ='P&L'!C25 -> 0.13196803 | D20: ='P&L'!D25 -> 0.14964082 | H20: =IF(H7=0,0,H19/H7) -> 0.080624423 | I20: =IF(I7=0,0,I19/I7) -> 0.080706651 | J20: =IF(J7=0,0,J19/J7) -> 0.080871107 | K20: =IF(K7=0,0,K19/K7) -> 0.081035563 | L20: =IF(L7=0,0,L19/L7) -> 0.081200018 | M20: =IF(M7=0,0,M19/M7) -> 0.18603142 | N20: =IF(N7=0,0,N19/N7) -> 0.18616074 | O20: =IF(O7=0,0,O19/O7) -> 0.18629005 | ... S20: =IF(S7=0,0,S19/S7) -> 0.08235121
A22: Cash flow ($'000) — by year | H22: ="Cash flow ($'000) — Year "&$R$2&", by month" -> Cash flow ($'000) — Year 1, by month
B23: 1 | C23: 2 | D23: 3 | H23: =INDEX(Monthly!$C$4:$AL$4,($R$2-1)*12+1) -> 1 | I23: =INDEX(Monthly!$C$4:$AL$4,($R$2-1)*12+2) -> 2 | J23: =INDEX(Monthly!$C$4:$AL$4,($R$2-1)*12+3) -> 3 | K23: =INDEX(Monthly!$C$4:$AL$4,($R$2-1)*12+4) -> 4 | L23: =INDEX(Monthly!$C$4:$AL$4,($R$2-1)*12+5) -> 5 | M23: =INDEX(Monthly!$C$4:$AL$4,($R$2-1)*12+6) -> 6 | N23: =INDEX(Monthly!$C$4:$AL$4,($R$2-1)*12+7) -> 7 | O23: =INDEX(Monthly!$C$4:$AL$4,($R$2-1)*12+8) -> 8 | P23: =INDEX(Monthly!$C$4:$AL$4,($R$2-1)*12+9) -> 9 | Q23: =INDEX(Monthly!$C$4:$AL$4,($R$2-1)*12+10) -> 10 | R23: =INDEX(Monthly!$C$4:$AL$4,($R$2-1)*12+11) -> 11 | S23: =INDEX(Monthly!$C$4:$AL$4,($R$2-1)*12+12) -> 12
A24: Operating cash flow | B24: ='Cash Flow'!B10 -> 194710.8 | C24: ='Cash Flow'!C10 -> 276206.62 | D24: ='Cash Flow'!D10 -> 373872.07 | H24: =INDEX(Monthly!$C$74:$AL$74,($R$2-1)*12+1) -> 9238.1153 | I24: =INDEX(Monthly!$C$74:$AL$74,($R$2-1)*12+2) -> 11102.56 | J24: =INDEX(Monthly!$C$74:$AL$74,($R$2-1)*12+3) -> 11124.504 | K24: =INDEX(Monthly!$C$74:$AL$74,($R$2-1)*12+4) -> 11146.449 | L24: =INDEX(Monthly!$C$74:$AL$74,($R$2-1)*12+5) -> 11168.393 | M24: =INDEX(Monthly!$C$74:$AL$74,($R$2-1)*12+6) -> 24348.005 | N24: =INDEX(Monthly!$C$74:$AL$74,($R$2-1)*12+7) -> 31924.81 | O24: =INDEX(Monthly!$C$74:$AL$74,($R$2-1)*12+8) -> 31946.755 | P24: =INDEX(Monthly!$C$74:$AL$74,($R$2-1)*12+9) -> 18811.032 | Q24: =INDEX(Monthly!$C$74:$AL$74,($R$2-1)*12+10) -> 11278.115 | R24: =INDEX(Monthly!$C$74:$AL$74,($R$2-1)*12+11) -> 11300.06 | S24: =INDEX(Monthly!$C$74:$AL$74,($R$2-1)*12+12) -> 11322.004
A25: Capital spending | B25: ='Cash Flow'!B11 -> -20000 | C25: ='Cash Flow'!C11 -> -37800 | D25: ='Cash Flow'!D11 -> -42336 | H25: =INDEX(Monthly!$C$75:$AL$75,($R$2-1)*12+1) -> -20000 | I25: =INDEX(Monthly!$C$75:$AL$75,($R$2-1)*12+2) -> 0 | J25: =INDEX(Monthly!$C$75:$AL$75,($R$2-1)*12+3) -> 0 | K25: =INDEX(Monthly!$C$75:$AL$75,($R$2-1)*12+4) -> 0 | L25: =INDEX(Monthly!$C$75:$AL$75,($R$2-1)*12+5) -> 0 | M25: =INDEX(Monthly!$C$75:$AL$75,($R$2-1)*12+6) -> 0 | N25: =INDEX(Monthly!$C$75:$AL$75,($R$2-1)*12+7) -> 0 | O25: =INDEX(Monthly!$C$75:$AL$75,($R$2-1)*12+8) -> 0 | P25: =INDEX(Monthly!$C$75:$AL$75,($R$2-1)*12+9) -> 0 | Q25: =INDEX(Monthly!$C$75:$AL$75,($R$2-1)*12+10) -> 0 | R25: =INDEX(Monthly!$C$75:$AL$75,($R$2-1)*12+11) -> 0 | S25: =INDEX(Monthly!$C$75:$AL$75,($R$2-1)*12+12) -> 0
A26: Equity raised | B26: ='Cash Flow'!B12 -> 100000 | C26: ='Cash Flow'!C12 -> 0 | D26: ='Cash Flow'!D12 -> 0 | H26: =INDEX(Monthly!$C$76:$AL$76,($R$2-1)*12+1) -> 100000 | I26: =INDEX(Monthly!$C$76:$AL$76,($R$2-1)*12+2) -> 0 | J26: =INDEX(Monthly!$C$76:$AL$76,($R$2-1)*12+3) -> 0 | K26: =INDEX(Monthly!$C$76:$AL$76,($R$2-1)*12+4) -> 0 | L26: =INDEX(Monthly!$C$76:$AL$76,($R$2-1)*12+5) -> 0 | M26: =INDEX(Monthly!$C$76:$AL$76,($R$2-1)*12+6) -> 0 | N26: =INDEX(Monthly!$C$76:$AL$76,($R$2-1)*12+7) -> 0 | O26: =INDEX(Monthly!$C$76:$AL$76,($R$2-1)*12+8) -> 0 | P26: =INDEX(Monthly!$C$76:$AL$76,($R$2-1)*12+9) -> 0 | Q26: =INDEX(Monthly!$C$76:$AL$76,($R$2-1)*12+10) -> 0 | R26: =INDEX(Monthly!$C$76:$AL$76,($R$2-1)*12+11) -> 0 | S26: =INDEX(Monthly!$C$76:$AL$76,($R$2-1)*12+12) -> 0
A27: Loan drawdown | B27: ='Cash Flow'!B13 -> 250000 | C27: ='Cash Flow'!C13 -> 0 | D27: ='Cash Flow'!D13 -> 0 | H27: =INDEX(Monthly!$C$61:$AL$61,($R$2-1)*12+1) -> 250000 | I27: =INDEX(Monthly!$C$61:$AL$61,($R$2-1)*12+2) -> 0 | J27: =INDEX(Monthly!$C$61:$AL$61,($R$2-1)*12+3) -> 0 | K27: =INDEX(Monthly!$C$61:$AL$61,($R$2-1)*12+4) -> 0 | L27: =INDEX(Monthly!$C$61:$AL$61,($R$2-1)*12+5) -> 0 | M27: =INDEX(Monthly!$C$61:$AL$61,($R$2-1)*12+6) -> 0 | N27: =INDEX(Monthly!$C$61:$AL$61,($R$2-1)*12+7) -> 0 | O27: =INDEX(Monthly!$C$61:$AL$61,($R$2-1)*12+8) -> 0 | P27: =INDEX(Monthly!$C$61:$AL$61,($R$2-1)*12+9) -> 0 | Q27: =INDEX(Monthly!$C$61:$AL$61,($R$2-1)*12+10) -> 0 | R27: =INDEX(Monthly!$C$61:$AL$61,($R$2-1)*12+11) -> 0 | S27: =INDEX(Monthly!$C$61:$AL$61,($R$2-1)*12+12) -> 0
A28: Loan repayment | B28: ='Cash Flow'!B14 -> -45833.333 | C28: ='Cash Flow'!C14 -> -50000 | D28: ='Cash Flow'!D14 -> -50000 | H28: =INDEX(Monthly!$C$62:$AL$62,($R$2-1)*12+1) -> 0 | I28: =INDEX(Monthly!$C$62:$AL$62,($R$2-1)*12+2) -> -4166.6667 | J28: =INDEX(Monthly!$C$62:$AL$62,($R$2-1)*12+3) -> -4166.6667 | K28: =INDEX(Monthly!$C$62:$AL$62,($R$2-1)*12+4) -> -4166.6667 | L28: =INDEX(Monthly!$C$62:$AL$62,($R$2-1)*12+5) -> -4166.6667 | M28: =INDEX(Monthly!$C$62:$AL$62,($R$2-1)*12+6) -> -4166.6667 | N28: =INDEX(Monthly!$C$62:$AL$62,($R$2-1)*12+7) -> -4166.6667 | O28: =INDEX(Monthly!$C$62:$AL$62,($R$2-1)*12+8) -> -4166.6667 | P28: =INDEX(Monthly!$C$62:$AL$62,($R$2-1)*12+9) -> -4166.6667 | Q28: =INDEX(Monthly!$C$62:$AL$62,($R$2-1)*12+10) -> -4166.6667 | R28: =INDEX(Monthly!$C$62:$AL$62,($R$2-1)*12+11) -> -4166.6667 | S28: =INDEX(Monthly!$C$62:$AL$62,($R$2-1)*12+12) -> -4166.6667
A29: Financing cash flow | B29: ='Cash Flow'!B15 -> 304166.67 | C29: ='Cash Flow'!C15 -> -50000 | D29: ='Cash Flow'!D15 -> -50000 | H29: =INDEX(Monthly!$C$77:$AL$77,($R$2-1)*12+1) -> 350000 | I29: =INDEX(Monthly!$C$77:$AL$77,($R$2-1)*12+2) -> -4166.6667 | J29: =INDEX(Monthly!$C$77:$AL$77,($R$2-1)*12+3) -> -4166.6667 | K29: =INDEX(Monthly!$C$77:$AL$77,($R$2-1)*12+4) -> -4166.6667 | L29: =INDEX(Monthly!$C$77:$AL$77,($R$2-1)*12+5) -> -4166.6667 | M29: =INDEX(Monthly!$C$77:$AL$77,($R$2-1)*12+6) -> -4166.6667 | N29: =INDEX(Monthly!$C$77:$AL$77,($R$2-1)*12+7) -> -4166.6667 | O29: =INDEX(Monthly!$C$77:$AL$77,($R$2-1)*12+8) -> -4166.6667 | P29: =INDEX(Monthly!$C$77:$AL$77,($R$2-1)*12+9) -> -4166.6667 | Q29: =INDEX(Monthly!$C$77:$AL$77,($R$2-1)*12+10) -> -4166.6667 | R29: =INDEX(Monthly!$C$77:$AL$77,($R$2-1)*12+11) -> -4166.6667 | S29: =INDEX(Monthly!$C$77:$AL$77,($R$2-1)*12+12) -> -4166.6667
A30: Net change in cash | B30: ='Cash Flow'!B16 -> 478877.47 | C30: ='Cash Flow'!C16 -> 188406.62 | D30: ='Cash Flow'!D16 -> 281536.07 | H30: =INDEX(Monthly!$C$78:$AL$78,($R$2-1)*12+1) -> 339238.12 | I30: =INDEX(Monthly!$C$78:$AL$78,($R$2-1)*12+2) -> 6935.8931 | J30: =INDEX(Monthly!$C$78:$AL$78,($R$2-1)*12+3) -> 6957.8376 | K30: =INDEX(Monthly!$C$78:$AL$78,($R$2-1)*12+4) -> 6979.782 | L30: =INDEX(Monthly!$C$78:$AL$78,($R$2-1)*12+5) -> 7001.7265 | M30: =INDEX(Monthly!$C$78:$AL$78,($R$2-1)*12+6) -> 20181.338 | N30: =INDEX(Monthly!$C$78:$AL$78,($R$2-1)*12+7) -> 27758.143 | O30: =INDEX(Monthly!$C$78:$AL$78,($R$2-1)*12+8) -> 27780.088 | P30: =INDEX(Monthly!$C$78:$AL$78,($R$2-1)*12+9) -> 14644.365 | Q30: =INDEX(Monthly!$C$78:$AL$78,($R$2-1)*12+10) -> 7111.4487 | R30: =INDEX(Monthly!$C$78:$AL$78,($R$2-1)*12+11) -> 7133.3931 | S30: =INDEX(Monthly!$C$78:$AL$78,($R$2-1)*12+12) -> 7155.3376
A31: Closing cash | B31: ='Cash Flow'!B18 -> 478877.47 | C31: ='Cash Flow'!C18 -> 667284.09 | D31: ='Cash Flow'!D18 -> 948820.16 | H31: =INDEX(Monthly!$C$80:$AL$80,($R$2-1)*12+1) -> 339238.12 | I31: =INDEX(Monthly!$C$80:$AL$80,($R$2-1)*12+2) -> 346174.01 | J31: =INDEX(Monthly!$C$80:$AL$80,($R$2-1)*12+3) -> 353131.85 | K31: =INDEX(Monthly!$C$80:$AL$80,($R$2-1)*12+4) -> 360111.63 | L31: =INDEX(Monthly!$C$80:$AL$80,($R$2-1)*12+5) -> 367113.35 | M31: =INDEX(Monthly!$C$80:$AL$80,($R$2-1)*12+6) -> 387294.69 | N31: =INDEX(Monthly!$C$80:$AL$80,($R$2-1)*12+7) -> 415052.84 | O31: =INDEX(Monthly!$C$80:$AL$80,($R$2-1)*12+8) -> 442832.92 | P31: =INDEX(Monthly!$C$80:$AL$80,($R$2-1)*12+9) -> 457477.29 | Q31: =INDEX(Monthly!$C$80:$AL$80,($R$2-1)*12+10) -> 464588.74 | R31: =INDEX(Monthly!$C$80:$AL$80,($R$2-1)*12+11) -> 471722.13 | S31: =INDEX(Monthly!$C$80:$AL$80,($R$2-1)*12+12) -> 478877.47
A39: Balance sheet at year end ($'000) | H39: ="Balance sheet at month end ($'000) — Year "&$R$2 -> Balance sheet at month end ($'000) — Year 1
B40: 1 | C40: 2 | D40: 3 | H40: =INDEX(Monthly!$C$4:$AL$4,($R$2-1)*12+1) -> 1 | I40: =INDEX(Monthly!$C$4:$AL$4,($R$2-1)*12+2) -> 2 | J40: =INDEX(Monthly!$C$4:$AL$4,($R$2-1)*12+3) -> 3 | K40: =INDEX(Monthly!$C$4:$AL$4,($R$2-1)*12+4) -> 4 | L40: =INDEX(Monthly!$C$4:$AL$4,($R$2-1)*12+5) -> 5 | M40: =INDEX(Monthly!$C$4:$AL$4,($R$2-1)*12+6) -> 6 | N40: =INDEX(Monthly!$C$4:$AL$4,($R$2-1)*12+7) -> 7 | O40: =INDEX(Monthly!$C$4:$AL$4,($R$2-1)*12+8) -> 8 | P40: =INDEX(Monthly!$C$4:$AL$4,($R$2-1)*12+9) -> 9 | Q40: =INDEX(Monthly!$C$4:$AL$4,($R$2-1)*12+10) -> 10 | R40: =INDEX(Monthly!$C$4:$AL$4,($R$2-1)*12+11) -> 11 | S40: =INDEX(Monthly!$C$4:$AL$4,($R$2-1)*12+12) -> 12
A41: Cash | B41: ='Balance Sheet'!B5 -> 478877.47 | C41: ='Balance Sheet'!C5 -> 667284.09 | D41: ='Balance Sheet'!D5 -> 948820.16 | H41: =INDEX(Monthly!$C$80:$AL$80,($R$2-1)*12+1) -> 339238.12 | I41: =INDEX(Monthly!$C$80:$AL$80,($R$2-1)*12+2) -> 346174.01 | J41: =INDEX(Monthly!$C$80:$AL$80,($R$2-1)*12+3) -> 353131.85 | K41: =INDEX(Monthly!$C$80:$AL$80,($R$2-1)*12+4) -> 360111.63 | L41: =INDEX(Monthly!$C$80:$AL$80,($R$2-1)*12+5) -> 367113.35 | M41: =INDEX(Monthly!$C$80:$AL$80,($R$2-1)*12+6) -> 387294.69 | N41: =INDEX(Monthly!$C$80:$AL$80,($R$2-1)*12+7) -> 415052.84 | O41: =INDEX(Monthly!$C$80:$AL$80,($R$2-1)*12+8) -> 442832.92 | P41: =INDEX(Monthly!$C$80:$AL$80,($R$2-1)*12+9) -> 457477.29 | Q41: =INDEX(Monthly!$C$80:$AL$80,($R$2-1)*12+10) -> 464588.74 | R41: =INDEX(Monthly!$C$80:$AL$80,($R$2-1)*12+11) -> 471722.13 | S41: =INDEX(Monthly!$C$80:$AL$80,($R$2-1)*12+12) -> 478877.47
A42: Accounts receivable | B42: ='Balance Sheet'!B6 -> 44478.889 | C42: ='Balance Sheet'!C6 -> 52822.577 | D42: ='Balance Sheet'!D6 -> 62738.087 | H42: =INDEX(Monthly!$C$66:$AL$66,($R$2-1)*12+1) -> 44478.889 | I42: =INDEX(Monthly!$C$66:$AL$66,($R$2-1)*12+2) -> 44478.889 | J42: =INDEX(Monthly!$C$66:$AL$66,($R$2-1)*12+3) -> 44478.889 | K42: =INDEX(Monthly!$C$66:$AL$66,($R$2-1)*12+4) -> 44478.889 | L42: =INDEX(Monthly!$C$66:$AL$66,($R$2-1)*12+5) -> 44478.889 | M42: =INDEX(Monthly!$C$66:$AL$66,($R$2-1)*12+6) -> 56566.667 | N42: =INDEX(Monthly!$C$66:$AL$66,($R$2-1)*12+7) -> 56566.667 | O42: =INDEX(Monthly!$C$66:$AL$66,($R$2-1)*12+8) -> 56566.667 | P42: =INDEX(Monthly!$C$66:$AL$66,($R$2-1)*12+9) -> 44478.889 | Q42: =INDEX(Monthly!$C$66:$AL$66,($R$2-1)*12+10) -> 44478.889 | R42: =INDEX(Monthly!$C$66:$AL$66,($R$2-1)*12+11) -> 44478.889 | S42: =INDEX(Monthly!$C$66:$AL$66,($R$2-1)*12+12) -> 44478.889
A43: Inventory | B43: ='Balance Sheet'!B7 -> 14208.472 | C43: ='Balance Sheet'!C7 -> 16545.38 | D43: ='Balance Sheet'!D7 -> 19275.29 | H43: =INDEX(Monthly!$C$67:$AL$67,($R$2-1)*12+1) -> 14208.472 | I43: =INDEX(Monthly!$C$67:$AL$67,($R$2-1)*12+2) -> 14208.472 | J43: =INDEX(Monthly!$C$67:$AL$67,($R$2-1)*12+3) -> 14208.472 | K43: =INDEX(Monthly!$C$67:$AL$67,($R$2-1)*12+4) -> 14208.472 | L43: =INDEX(Monthly!$C$67:$AL$67,($R$2-1)*12+5) -> 14208.472 | M43: =INDEX(Monthly!$C$67:$AL$67,($R$2-1)*12+6) -> 15719.444 | N43: =INDEX(Monthly!$C$67:$AL$67,($R$2-1)*12+7) -> 15719.444 | O43: =INDEX(Monthly!$C$67:$AL$67,($R$2-1)*12+8) -> 15719.444 | P43: =INDEX(Monthly!$C$67:$AL$67,($R$2-1)*12+9) -> 14208.472 | Q43: =INDEX(Monthly!$C$67:$AL$67,($R$2-1)*12+10) -> 14208.472 | R43: =INDEX(Monthly!$C$67:$AL$67,($R$2-1)*12+11) -> 14208.472 | S43: =INDEX(Monthly!$C$67:$AL$67,($R$2-1)*12+12) -> 14208.472
A44: Net fixed assets | B44: ='Balance Sheet'!B8 -> 16000 | C44: ='Balance Sheet'!C8 -> 42240 | D44: ='Balance Sheet'!D8 -> 64548.8 | H44: =INDEX(Monthly!$C$57:$AL$57,($R$2-1)*12+1) -> 19666.667 | I44: =INDEX(Monthly!$C$57:$AL$57,($R$2-1)*12+2) -> 19333.333 | J44: =INDEX(Monthly!$C$57:$AL$57,($R$2-1)*12+3) -> 19000 | K44: =INDEX(Monthly!$C$57:$AL$57,($R$2-1)*12+4) -> 18666.667 | L44: =INDEX(Monthly!$C$57:$AL$57,($R$2-1)*12+5) -> 18333.333 | M44: =INDEX(Monthly!$C$57:$AL$57,($R$2-1)*12+6) -> 18000 | N44: =INDEX(Monthly!$C$57:$AL$57,($R$2-1)*12+7) -> 17666.667 | O44: =INDEX(Monthly!$C$57:$AL$57,($R$2-1)*12+8) -> 17333.333 | P44: =INDEX(Monthly!$C$57:$AL$57,($R$2-1)*12+9) -> 17000 | Q44: =INDEX(Monthly!$C$57:$AL$57,($R$2-1)*12+10) -> 16666.667 | R44: =INDEX(Monthly!$C$57:$AL$57,($R$2-1)*12+11) -> 16333.333 | S44: =INDEX(Monthly!$C$57:$AL$57,($R$2-1)*12+12) -> 16000
A45: Total assets | B45: ='Balance Sheet'!B9 -> 553564.83 | C45: ='Balance Sheet'!C9 -> 778892.05 | D45: ='Balance Sheet'!D9 -> 1095382.3 | H45: =INDEX(Monthly!$C$94:$AL$94,($R$2-1)*12+1) -> 417592.14 | I45: =INDEX(Monthly!$C$94:$AL$94,($R$2-1)*12+2) -> 424194.7 | J45: =INDEX(Monthly!$C$94:$AL$94,($R$2-1)*12+3) -> 430819.21 | K45: =INDEX(Monthly!$C$94:$AL$94,($R$2-1)*12+4) -> 437465.66 | L45: =INDEX(Monthly!$C$94:$AL$94,($R$2-1)*12+5) -> 444134.05 | M45: =INDEX(Monthly!$C$94:$AL$94,($R$2-1)*12+6) -> 477580.8 | N45: =INDEX(Monthly!$C$94:$AL$94,($R$2-1)*12+7) -> 505005.61 | O45: =INDEX(Monthly!$C$94:$AL$94,($R$2-1)*12+8) -> 532452.37 | P45: =INDEX(Monthly!$C$94:$AL$94,($R$2-1)*12+9) -> 533164.65 | Q45: =INDEX(Monthly!$C$94:$AL$94,($R$2-1)*12+10) -> 539942.77 | R45: =INDEX(Monthly!$C$94:$AL$94,($R$2-1)*12+11) -> 546742.83 | S45: =INDEX(Monthly!$C$94:$AL$94,($R$2-1)*12+12) -> 553564.83
A46: Accounts payable | B46: ='Balance Sheet'!B10 -> 56833.889 | C46: ='Balance Sheet'!C10 -> 66181.52 | D46: ='Balance Sheet'!D10 -> 77101.158 | H46: =INDEX(Monthly!$C$68:$AL$68,($R$2-1)*12+1) -> 56833.889 | I46: =INDEX(Monthly!$C$68:$AL$68,($R$2-1)*12+2) -> 56833.889 | J46: =INDEX(Monthly!$C$68:$AL$68,($R$2-1)*12+3) -> 56833.889 | K46: =INDEX(Monthly!$C$68:$AL$68,($R$2-1)*12+4) -> 56833.889 | L46: =INDEX(Monthly!$C$68:$AL$68,($R$2-1)*12+5) -> 56833.889 | M46: =INDEX(Monthly!$C$68:$AL$68,($R$2-1)*12+6) -> 62877.778 | N46: =INDEX(Monthly!$C$68:$AL$68,($R$2-1)*12+7) -> 62877.778 | O46: =INDEX(Monthly!$C$68:$AL$68,($R$2-1)*12+8) -> 62877.778 | P46: =INDEX(Monthly!$C$68:$AL$68,($R$2-1)*12+9) -> 56833.889 | Q46: =INDEX(Monthly!$C$68:$AL$68,($R$2-1)*12+10) -> 56833.889 | R46: =INDEX(Monthly!$C$68:$AL$68,($R$2-1)*12+11) -> 56833.889 | S46: =INDEX(Monthly!$C$68:$AL$68,($R$2-1)*12+12) -> 56833.889
A47: Loan | B47: ='Balance Sheet'!B11 -> 204166.67 | C47: ='Balance Sheet'!C11 -> 154166.67 | D47: ='Balance Sheet'!D11 -> 104166.67 | H47: =INDEX(Monthly!$C$63:$AL$63,($R$2-1)*12+1) -> 250000 | I47: =INDEX(Monthly!$C$63:$AL$63,($R$2-1)*12+2) -> 245833.33 | J47: =INDEX(Monthly!$C$63:$AL$63,($R$2-1)*12+3) -> 241666.67 | K47: =INDEX(Monthly!$C$63:$AL$63,($R$2-1)*12+4) -> 237500 | L47: =INDEX(Monthly!$C$63:$AL$63,($R$2-1)*12+5) -> 233333.33 | M47: =INDEX(Monthly!$C$63:$AL$63,($R$2-1)*12+6) -> 229166.67 | N47: =INDEX(Monthly!$C$63:$AL$63,($R$2-1)*12+7) -> 225000 | O47: =INDEX(Monthly!$C$63:$AL$63,($R$2-1)*12+8) -> 220833.33 | P47: =INDEX(Monthly!$C$63:$AL$63,($R$2-1)*12+9) -> 216666.67 | Q47: =INDEX(Monthly!$C$63:$AL$63,($R$2-1)*12+10) -> 212500 | R47: =INDEX(Monthly!$C$63:$AL$63,($R$2-1)*12+11) -> 208333.33 | S47: =INDEX(Monthly!$C$63:$AL$63,($R$2-1)*12+12) -> 204166.67
A48: Total liabilities | B48: ='Balance Sheet'!B12 -> 261000.56 | C48: ='Balance Sheet'!C12 -> 220348.19 | D48: ='Balance Sheet'!D12 -> 181267.82 | H48: =INDEX(Monthly!$C$95:$AL$95,($R$2-1)*12+1) -> 306833.89 | I48: =INDEX(Monthly!$C$95:$AL$95,($R$2-1)*12+2) -> 302667.22 | J48: =INDEX(Monthly!$C$95:$AL$95,($R$2-1)*12+3) -> 298500.56 | K48: =INDEX(Monthly!$C$95:$AL$95,($R$2-1)*12+4) -> 294333.89 | L48: =INDEX(Monthly!$C$95:$AL$95,($R$2-1)*12+5) -> 290167.22 | M48: =INDEX(Monthly!$C$95:$AL$95,($R$2-1)*12+6) -> 292044.44 | N48: =INDEX(Monthly!$C$95:$AL$95,($R$2-1)*12+7) -> 287877.78 | O48: =INDEX(Monthly!$C$95:$AL$95,($R$2-1)*12+8) -> 283711.11 | P48: =INDEX(Monthly!$C$95:$AL$95,($R$2-1)*12+9) -> 273500.56 | Q48: =INDEX(Monthly!$C$95:$AL$95,($R$2-1)*12+10) -> 269333.89 | R48: =INDEX(Monthly!$C$95:$AL$95,($R$2-1)*12+11) -> 265167.22 | S48: =INDEX(Monthly!$C$95:$AL$95,($R$2-1)*12+12) -> 261000.56
A49: Paid-in capital | B49: ='Balance Sheet'!B13 -> 100000 | C49: ='Balance Sheet'!C13 -> 100000 | D49: ='Balance Sheet'!D13 -> 100000 | H49: =INDEX(Monthly!$C$92:$AL$92,($R$2-1)*12+1) -> 100000 | I49: =INDEX(Monthly!$C$92:$AL$92,($R$2-1)*12+2) -> 100000 | J49: =INDEX(Monthly!$C$92:$AL$92,($R$2-1)*12+3) -> 100000 | K49: =INDEX(Monthly!$C$92:$AL$92,($R$2-1)*12+4) -> 100000 | L49: =INDEX(Monthly!$C$92:$AL$92,($R$2-1)*12+5) -> 100000 | M49: =INDEX(Monthly!$C$92:$AL$92,($R$2-1)*12+6) -> 100000 | N49: =INDEX(Monthly!$C$92:$AL$92,($R$2-1)*12+7) -> 100000 | O49: =INDEX(Monthly!$C$92:$AL$92,($R$2-1)*12+8) -> 100000 | P49: =INDEX(Monthly!$C$92:$AL$92,($R$2-1)*12+9) -> 100000 | Q49: =INDEX(Monthly!$C$92:$AL$92,($R$2-1)*12+10) -> 100000 | R49: =INDEX(Monthly!$C$92:$AL$92,($R$2-1)*12+11) -> 100000 | S49: =INDEX(Monthly!$C$92:$AL$92,($R$2-1)*12+12) -> 100000
A50: Retained earnings | B50: ='Balance Sheet'!B14 -> 192564.27 | C50: ='Balance Sheet'!C14 -> 458543.86 | D50: ='Balance Sheet'!D14 -> 814114.51 | H50: =INDEX(Monthly!$C$93:$AL$93,($R$2-1)*12+1) -> 10758.254 | I50: =INDEX(Monthly!$C$93:$AL$93,($R$2-1)*12+2) -> 21527.481 | J50: =INDEX(Monthly!$C$93:$AL$93,($R$2-1)*12+3) -> 32318.652 | K50: =INDEX(Monthly!$C$93:$AL$93,($R$2-1)*12+4) -> 43131.767 | L50: =INDEX(Monthly!$C$93:$AL$93,($R$2-1)*12+5) -> 53966.827 | M50: =INDEX(Monthly!$C$93:$AL$93,($R$2-1)*12+6) -> 85536.359 | N50: =INDEX(Monthly!$C$93:$AL$93,($R$2-1)*12+7) -> 117127.84 | O50: =INDEX(Monthly!$C$93:$AL$93,($R$2-1)*12+8) -> 148741.26 | P50: =INDEX(Monthly!$C$93:$AL$93,($R$2-1)*12+9) -> 159664.09 | Q50: =INDEX(Monthly!$C$93:$AL$93,($R$2-1)*12+10) -> 170608.88 | R50: =INDEX(Monthly!$C$93:$AL$93,($R$2-1)*12+11) -> 181575.6 | S50: =INDEX(Monthly!$C$93:$AL$93,($R$2-1)*12+12) -> 192564.27
A51: Total equity | B51: ='Balance Sheet'!B15 -> 292564.27 | C51: ='Balance Sheet'!C15 -> 558543.86 | D51: ='Balance Sheet'!D15 -> 914114.51 | H51: =INDEX(Monthly!$C$96:$AL$96,($R$2-1)*12+1) -> 110758.25 | I51: =INDEX(Monthly!$C$96:$AL$96,($R$2-1)*12+2) -> 121527.48 | J51: =INDEX(Monthly!$C$96:$AL$96,($R$2-1)*12+3) -> 132318.65 | K51: =INDEX(Monthly!$C$96:$AL$96,($R$2-1)*12+4) -> 143131.77 | L51: =INDEX(Monthly!$C$96:$AL$96,($R$2-1)*12+5) -> 153966.83 | M51: =INDEX(Monthly!$C$96:$AL$96,($R$2-1)*12+6) -> 185536.36 | N51: =INDEX(Monthly!$C$96:$AL$96,($R$2-1)*12+7) -> 217127.84 | O51: =INDEX(Monthly!$C$96:$AL$96,($R$2-1)*12+8) -> 248741.26 | P51: =INDEX(Monthly!$C$96:$AL$96,($R$2-1)*12+9) -> 259664.09 | Q51: =INDEX(Monthly!$C$96:$AL$96,($R$2-1)*12+10) -> 270608.88 | R51: =INDEX(Monthly!$C$96:$AL$96,($R$2-1)*12+11) -> 281575.6 | S51: =INDEX(Monthly!$C$96:$AL$96,($R$2-1)*12+12) -> 292564.27
A52: Total liabilities & equity | B52: ='Balance Sheet'!B16 -> 553564.83 | C52: ='Balance Sheet'!C16 -> 778892.05 | D52: ='Balance Sheet'!D16 -> 1095382.3 | H52: =INDEX(Monthly!$C$97:$AL$97,($R$2-1)*12+1) -> 417592.14 | I52: =INDEX(Monthly!$C$97:$AL$97,($R$2-1)*12+2) -> 424194.7 | J52: =INDEX(Monthly!$C$97:$AL$97,($R$2-1)*12+3) -> 430819.21 | K52: =INDEX(Monthly!$C$97:$AL$97,($R$2-1)*12+4) -> 437465.66 | L52: =INDEX(Monthly!$C$97:$AL$97,($R$2-1)*12+5) -> 444134.05 | M52: =INDEX(Monthly!$C$97:$AL$97,($R$2-1)*12+6) -> 477580.8 | N52: =INDEX(Monthly!$C$97:$AL$97,($R$2-1)*12+7) -> 505005.61 | O52: =INDEX(Monthly!$C$97:$AL$97,($R$2-1)*12+8) -> 532452.37 | P52: =INDEX(Monthly!$C$97:$AL$97,($R$2-1)*12+9) -> 533164.65 | Q52: =INDEX(Monthly!$C$97:$AL$97,($R$2-1)*12+10) -> 539942.77 | R52: =INDEX(Monthly!$C$97:$AL$97,($R$2-1)*12+11) -> 546742.83 | S52: =INDEX(Monthly!$C$97:$AL$97,($R$2-1)*12+12) -> 553564.83

Sheet Scenarios
A1: Scenarios — Low / Base / High | H1: =HYPERLINK("#'Cover'!A1","◂ Contents") -> ◂ Contents
A2: All three scenarios calculated side by side, live: change any input and every column updates. Active = the scenario chosen on the Dashboard.
A5: Key drivers
A6: Driver | B6: Low | C6: Base | D6: High | E6: Active
A7: Average revenue per job (year 1) ($) | B7: =Inputs!$B$20 -> 415 | C7: =Inputs!$C$20 -> 440 | D7: =Inputs!$D$20 -> 465 | E7: =Inputs!$E$20 -> 440
A8: Jobs per technician per working day (jobs) | B8: =Inputs!$B$7 -> 2.35 | C8: =Inputs!$C$7 -> 2.5 | D8: =Inputs!$D$7 -> 2.65 | E8: =Inputs!$E$7 -> 2.5
A9: Marketing budget per month ($) | B9: =Inputs!$B$11 -> 9000 | C9: =Inputs!$C$11 -> 9000 | D9: =Inputs!$D$11 -> 9000 | E9: =Inputs!$E$11 -> 9000
A10: Cost per lead ($) | B10: =Inputs!$B$13 -> 52 | C10: =Inputs!$C$13 -> 50 | D10: =Inputs!$D$13 -> 48 | E10: =Inputs!$E$13 -> 50
A11: Leads booked as jobs (%) | B11: =Inputs!$B$14 -> 0.42 | C11: =Inputs!$C$14 -> 0.45 | D11: =Inputs!$D$14 -> 0.48 | E11: =Inputs!$E$14 -> 0.45
A12: Materials & parts, % of job revenue (%) | B12: =Inputs!$B$30 -> 0.26 | C12: =Inputs!$C$30 -> 0.25 | D12: =Inputs!$D$30 -> 0.24 | E12: =Inputs!$E$30 -> 0.25
A13: Equity raised at start ($) | B13: =Inputs!$B$54 -> 100000 | C13: =Inputs!$C$54 -> 100000 | D13: =Inputs!$D$54 -> 100000 | E13: =Inputs!$E$54 -> 100000
A15: Results by scenario ($'000)
A16: Output | B16: Low | C16: Base | D16: High | E16: Active
A17: Revenue — final year | B17: =D30 -> 1796473 | C17: =D31 -> 2376160.7 | D17: =D32 -> 3040261.8 | E17: ='P&L'!D5 -> 2376160.7
A18: Revenue — whole plan | B18: =SUM(B30:D30) -> 4739987.5 | C18: =SUM(B31:D31) -> 6101675.7 | D18: =SUM(B32:D32) -> 7596136.8 | E18: =SUM('P&L'!$B$5:$D$5) -> 6101675.7
A19: EBITDA — final year | B19: =D36 -> 49597.556 | C19: =D37 -> 480449.96 | D19: =D38 -> 985565.06 | E19: ='P&L'!D17 -> 480449.96
A20: EBITDA margin — final year | B20: =IF(B17=0,0,B19/B17) -> 0.027608295 | C20: =IF(C17=0,0,C19/C17) -> 0.2021959 | D20: =IF(D17=0,0,D19/D17) -> 0.32417112 | E20: =IF(E17=0,0,E19/E17) -> 0.2021959
A21: Net income — final year | B21: =D42 -> 15445.606 | C21: =D43 -> 355570.65 | D21: =D44 -> 755174.31 | E21: ='P&L'!D24 -> 355570.65
A22: Net income — whole plan | B22: =SUM(B42:D42) -> -4174.0176 | C22: =SUM(B43:D43) -> 814114.51 | D22: =SUM(B44:D44) -> 1727783.2 | E22: =SUM('P&L'!$B$24:$D$24) -> 814114.51
A23: Cash at the end of the plan | B23: =D48 -> 139097.51 | C23: =D49 -> 948820.16 | D23: =D50 -> 1851111.7 | E23: ='Balance Sheet'!D5 -> 948820.16
A24: Lowest cash balance | B24: =MIN('Scenario calc'!$C$82:$AL$82) -> 105803.75 | C24: =MIN('Scenario calc'!$C$191:$AL$191) -> 339238.12 | D24: =MIN('Scenario calc'!$C$300:$AL$300) -> 351230.53 | E24: ='Break-even'!B18 -> 339238.12
A25: Lowest cash point (month #) | B25: =MATCH(MIN('Scenario calc'!$C$82:$AL$82),'Scenario calc'!$C$82:$AL$82,0) -> 29 | C25: =MATCH(MIN('Scenario calc'!$C$191:$AL$191),'Scenario calc'!$C$191:$AL$191,0) -> 1 | D25: =MATCH(MIN('Scenario calc'!$C$300:$AL$300),'Scenario calc'!$C$300:$AL$300,0) -> 1 | E25: ='Break-even'!B6 -> 1
A26: Funding required (incl. cash buffer) | B26: =SUMPRODUCT(--('Scenario calc'!$C$6:$AL$6<=B25),'Scenario calc'!$C$55:$AL$55)-SUMPRODUCT(--('Scenario calc'!$C$6:$AL$6<=B25),'Scenario calc'!$C$76:$AL$76)-SUMPRODUCT(--('Scenario calc'!$C$6:$AL$6<=B25),'Scenario calc'!$C$64:$AL$64)+Inputs!$B$69 -> 342196.25 | C26: =SUMPRODUCT(--('Scenario calc'!$C$115:$AL$115<=C25),'Scenario calc'!$C$164:$AL$164)-SUMPRODUCT(--('Scenario calc'!$C$115:$AL$115<=C25),'Scenario calc'!$C$185:$AL$185)-SUMPRODUCT(--('Scenario calc'!$C$115:$AL$115<=C25),'Scenario calc'!$C$173:$AL$173)+Inputs!$C$69 -> 108761.88 | D26: =SUMPRODUCT(--('Scenario calc'!$C$224:$AL$224<=D25),'Scenario calc'!$C$273:$AL$273)-SUMPRODUCT(--('Scenario calc'!$C$224:$AL$224<=D25),'Scenario calc'!$C$294:$AL$294)-SUMPRODUCT(--('Scenario calc'!$C$224:$AL$224<=D25),'Scenario calc'!$C$282:$AL$282)+Inputs!$D$69 -> 96769.474 | E26: ='Break-even'!B12 -> 108761.88
A28: Revenue by year ($'000)
A29: Scenario | B29: 1 | C29: 2 | D29: 3
A30: Low | B30: =SUMIF('Scenario calc'!$C$7:$AL$7,B$29,'Scenario calc'!$C$24:$AL$24) -> 1373007.7 | C30: =SUMIF('Scenario calc'!$C$7:$AL$7,C$29,'Scenario calc'!$C$24:$AL$24) -> 1570506.9 | D30: =SUMIF('Scenario calc'!$C$7:$AL$7,D$29,'Scenario calc'!$C$24:$AL$24) -> 1796473
A31: Base | B31: =SUMIF('Scenario calc'!$C$116:$AL$116,B$29,'Scenario calc'!$C$133:$AL$133) -> 1710030 | C31: =SUMIF('Scenario calc'!$C$116:$AL$116,C$29,'Scenario calc'!$C$133:$AL$133) -> 2015484.9 | D31: =SUMIF('Scenario calc'!$C$116:$AL$116,D$29,'Scenario calc'!$C$133:$AL$133) -> 2376160.7
A32: High | B32: =SUMIF('Scenario calc'!$C$225:$AL$225,B$29,'Scenario calc'!$C$242:$AL$242) -> 2056472.2 | C32: =SUMIF('Scenario calc'!$C$225:$AL$225,C$29,'Scenario calc'!$C$242:$AL$242) -> 2499402.8 | D32: =SUMIF('Scenario calc'!$C$225:$AL$225,D$29,'Scenario calc'!$C$242:$AL$242) -> 3040261.8
A34: EBITDA by year ($'000)
A35: Scenario | B35: 1 | C35: 2 | D35: 3
A36: Low | B36: =SUMIF('Scenario calc'!$C$7:$AL$7,B$35,'Scenario calc'!$C$43:$AL$43) -> 5760.4692 | C36: =SUMIF('Scenario calc'!$C$7:$AL$7,C$35,'Scenario calc'!$C$43:$AL$43) -> 26183.859 | D36: =SUMIF('Scenario calc'!$C$7:$AL$7,D$35,'Scenario calc'!$C$43:$AL$43) -> 49597.556
A37: Base | B37: =SUMIF('Scenario calc'!$C$116:$AL$116,B$35,'Scenario calc'!$C$152:$AL$152) -> 266071.69 | C37: =SUMIF('Scenario calc'!$C$116:$AL$116,C$35,'Scenario calc'!$C$152:$AL$152) -> 362576.36 | D37: =SUMIF('Scenario calc'!$C$116:$AL$116,D$35,'Scenario calc'!$C$152:$AL$152) -> 480449.96
A38: High | B38: =SUMIF('Scenario calc'!$C$225:$AL$225,B$35,'Scenario calc'!$C$261:$AL$261) -> 541347.1 | C38: =SUMIF('Scenario calc'!$C$225:$AL$225,C$35,'Scenario calc'!$C$261:$AL$261) -> 737680.2 | D38: =SUMIF('Scenario calc'!$C$225:$AL$225,D$35,'Scenario calc'!$C$261:$AL$261) -> 985565.06
A40: Net income by year ($'000)
A41: Scenario | B41: 1 | C41: 2 | D41: 3
A42: Low | B42: =SUMIF('Scenario calc'!$C$7:$AL$7,B$41,'Scenario calc'!$C$52:$AL$52) -> -19574.149 | C42: =SUMIF('Scenario calc'!$C$7:$AL$7,C$41,'Scenario calc'!$C$52:$AL$52) -> -45.474404 | D42: =SUMIF('Scenario calc'!$C$7:$AL$7,D$41,'Scenario calc'!$C$52:$AL$52) -> 15445.606
A43: Base | B43: =SUMIF('Scenario calc'!$C$116:$AL$116,B$41,'Scenario calc'!$C$161:$AL$161) -> 192564.27 | C43: =SUMIF('Scenario calc'!$C$116:$AL$116,C$41,'Scenario calc'!$C$161:$AL$161) -> 265979.59 | D43: =SUMIF('Scenario calc'!$C$116:$AL$116,D$41,'Scenario calc'!$C$161:$AL$161) -> 355570.65
A44: High | B44: =SUMIF('Scenario calc'!$C$225:$AL$225,B$41,'Scenario calc'!$C$270:$AL$270) -> 410031.85 | C44: =SUMIF('Scenario calc'!$C$225:$AL$225,C$41,'Scenario calc'!$C$270:$AL$270) -> 562577.06 | D44: =SUMIF('Scenario calc'!$C$225:$AL$225,D$41,'Scenario calc'!$C$270:$AL$270) -> 755174.31
A46: Cash at year end by year ($'000)
A47: Scenario | B47: 1 | C47: 2 | D47: 3
A48: Low | B48: =INDEX('Scenario calc'!$C$82:$AL$82,B$47*12) -> 273127.74 | C48: =INDEX('Scenario calc'!$C$82:$AL$82,C$47*12) -> 196250.77 | D48: =INDEX('Scenario calc'!$C$82:$AL$82,D$47*12) -> 139097.51
A49: Base | B49: =INDEX('Scenario calc'!$C$191:$AL$191,B$47*12) -> 478877.47 | C49: =INDEX('Scenario calc'!$C$191:$AL$191,C$47*12) -> 667284.09 | D49: =INDEX('Scenario calc'!$C$191:$AL$191,D$47*12) -> 948820.16
A50: High | B50: =INDEX('Scenario calc'!$C$300:$AL$300,B$47*12) -> 689056.68 | C50: =INDEX('Scenario calc'!$C$300:$AL$300,C$47*12) -> 1172546.4 | D50: =INDEX('Scenario calc'!$C$300:$AL$300,D$47*12) -> 1851111.7

Sheet Break-even
A1: Startup costs, funding need and break-even | F1: =HYPERLINK("#'Cover'!A1","◂ Contents") -> ◂ Contents
A2: Live for the selected scenario. Periods are counted in months from the start of the plan.
A3: Scenario shown | B3: =CHOOSE(Dashboard!$B$4,"Low","Base","High") -> Base
A5: Startup costs & funding need (up to the lowest cash point)
A6: Lowest cash point (month #) | B6: =MATCH(MIN(Monthly!$C$80:$AL$80),Monthly!$C$80:$AL$80,0) -> 1
A7: Capital spending up to the lowest cash point | B7: =SUMPRODUCT(--(Monthly!$C$4:$AL$4<=$B$6),Monthly!$C$53:$AL$53) -> 20000
A8: Operating cash burn up to the lowest cash point | B8: =-SUMPRODUCT(--(Monthly!$C$4:$AL$4<=$B$6),Monthly!$C$74:$AL$74) -> -9238.1153 | D8: Losses and working capital before the business funds itself
A9: Loan repayments up to the lowest cash point | B9: =-SUMPRODUCT(--(Monthly!$C$4:$AL$4<=$B$6),Monthly!$C$62:$AL$62) -> 0
A10: Total uses of funds | B10: =B7+B8+B9 -> 10761.885
A11: Minimum cash buffer to keep | B11: =Inputs!$E$69 -> 98000 | D11: Input on the Inputs sheet
A12: Funding required (uses + buffer) | B12: =B10+B11 -> 108761.88
A14: Equity raised | B14: =Inputs!$E$54 -> 100000
A15: Loan drawn | B15: =Inputs!$E$55 -> 250000
A16: Total sources of funds | B16: =B14+B15 -> 350000
A17: Funding surplus / (shortfall) | B17: =B16-B12 -> 241238.12 | D17: Negative = raise at least this much more
A18: Lowest cash balance in the plan | B18: =MIN(Monthly!$C$80:$AL$80) -> 339238.12 | D18: Equals sources minus uses
A20: Break-even timing
A21: First month with positive EBITDA (month #) | B21: =IFERROR(MATCH(1,Monthly!$C$81:$AL$81,0),"Not within horizon") -> 1
A22: First month with positive net income (month #) | B22: =IFERROR(MATCH(1,Monthly!$C$84:$AL$84,0),"Not within horizon") -> 1
A23: Cash invested paid back (month #) | B23: =IF(MIN(Monthly!$C$86:$AL$86)>=0,"No investment to pay back",IFERROR(MATCH(1,Monthly!$C$88:$AL$88,0),"Not within horizon")) -> 2 | D23: Cumulative operating + investing cash flow back to zero
A25: Annual break-even revenue
A26: Year # | B26: 1 | C26: 2 | D26: 3
B27: Year 1 | C27: Year 2 | D27: Year 3
A28: Revenue | B28: =SUMIF(Monthly!$C$5:$AL$5,B$26,Monthly!$C$22:$AL$22) -> 1710030 | C28: =SUMIF(Monthly!$C$5:$AL$5,C$26,Monthly!$C$22:$AL$22) -> 2015484.9 | D28: =SUMIF(Monthly!$C$5:$AL$5,D$26,Monthly!$C$22:$AL$22) -> 2376160.7
A29: Gross profit | B29: =SUMIF(Monthly!$C$5:$AL$5,B$26,Monthly!$C$30:$AL$30) -> 659822.5 | C29: =SUMIF(Monthly!$C$5:$AL$5,C$26,Monthly!$C$30:$AL$30) -> 795749.55 | D29: =SUMIF(Monthly!$C$5:$AL$5,D$26,Monthly!$C$30:$AL$30) -> 958942.46
A30: Gross margin (contribution) | B30: =IF(B28=0,0,B29/B28) -> 0.38585434 | C30: =IF(C28=0,0,C29/C28) -> 0.39481791 | D30: =IF(D28=0,0,D29/D28) -> 0.40356802
A31: Operating expenses (treated as fixed) | B31: =-SUMIF(Monthly!$C$5:$AL$5,B$26,Monthly!$C$40:$AL$40) -> 393750.81 | C31: =-SUMIF(Monthly!$C$5:$AL$5,C$26,Monthly!$C$40:$AL$40) -> 433173.19 | D31: =-SUMIF(Monthly!$C$5:$AL$5,D$26,Monthly!$C$40:$AL$40) -> 478492.5
A32: Break-even revenue (EBITDA = 0) | B32: =IF(B30>0,B31/B30,"n/a") -> 1020464.9 | C32: =IF(C30>0,C31/C30,"n/a") -> 1097146.8 | D32: =IF(D30>0,D31/D30,"n/a") -> 1185655.2
A33: Margin of safety (revenue above break-even) | B33: =IF(AND(ISNUMBER(B32),B28>0),(B28-B32)/B28,"n/a") -> 0.40324737 | C33: =IF(AND(ISNUMBER(C32),C28>0),(C28-C32)/C28,"n/a") -> 0.4556413 | D33: =IF(AND(ISNUMBER(D32),D28>0),(D28-D32)/D28,"n/a") -> 0.50102063
A35: Simplification: cost of sales is treated as variable and operating expenses as fixed, so break-even revenue = operating expenses ÷ gross margin. In a year with zero or negative gross margin there is no break-even revenue (n/a); the chart line shows 0 there.

Sheet Valuation
A1: Discounted cash flow valuation | H1: =HYPERLINK("#'Cover'!A1","◂ Contents") -> ◂ Contents
A2: Enterprise value at the start of the plan, before the funding raised in period 1. Year-end discounting.
A3: Scenario shown | B3: =CHOOSE(Dashboard!$B$4,"Low","Base","High") -> Base
A5: Assumptions (active scenario, from the Inputs sheet)
A6: Discount rate (WACC) | B6: =Inputs!$E$72 -> 0.16
A7: Terminal growth rate | B7: =Inputs!$E$73 -> 0.02
A8: Exit multiple (EV ÷ final-year EBITDA) | B8: =Inputs!$E$74 -> 5.5
A9: Tax rate (for the interest tax shield) | B9: =Inputs!$E$66 -> 0.21
A10: Sensitivity step: WACC | B10: =Inputs!$E$75 -> 0.01
A11: Sensitivity step: terminal growth | B11: =Inputs!$E$76 -> 0.005
A13: Free cash flow by year
A14: Year # | B14: 1 | C14: 2 | D14: 3
B15: Year 1 | C15: Year 2 | D15: Year 3
A16: EBITDA | B16: =SUMIF(Monthly!$C$5:$AL$5,B$14,Monthly!$C$41:$AL$41) -> 266071.69 | C16: =SUMIF(Monthly!$C$5:$AL$5,C$14,Monthly!$C$41:$AL$41) -> 362576.36 | D16: =SUMIF(Monthly!$C$5:$AL$5,D$14,Monthly!$C$41:$AL$41) -> 480449.96
A17: Unlevered free cash flow | B17: =SUMIF(Monthly!$C$5:$AL$5,B$14,Monthly!$C$89:$AL$89) -> 189183.16 | C17: =SUMIF(Monthly!$C$5:$AL$5,C$14,Monthly!$C$89:$AL$89) -> 249729.96 | D17: =SUMIF(Monthly!$C$5:$AL$5,D$14,Monthly!$C$89:$AL$89) -> 339699.4
A18: Discount factor | B18: =1/(1+Inputs!$E$72)^B$14 -> 0.86206897 | C18: =1/(1+Inputs!$E$72)^C$14 -> 0.7431629 | D18: =1/(1+Inputs!$E$72)^D$14 -> 0.64065767
A19: Present value of free cash flow | B19: =B17*B18 -> 163088.93 | C19: =C17*C18 -> 185590.04 | D19: =D17*D18 -> 217631.03
A21: Enterprise value
B22: Perpetual growth | C22: Exit multiple
A23: Present value of the plan's free cash flows | B23: =SUM($B$19:$D$19) -> 566310 | C23: =B23 -> 566310
A24: Final-year free cash flow | final-year EBITDA | B24: =$D$17 -> 339699.4 | C24: =$D$16 -> 480449.96
A25: Terminal value at the end of year 3 | B25: =IF($B$6>$B$7,B24*(1+$B$7)/($B$6-$B$7),0) -> 2474952.8 | C25: =C24*$B$8 -> 2642474.8
A26: Present value of the terminal value | B26: =B25/(1+$B$6)^$D$14 -> 1585597.5 | C26: =C25/(1+$B$6)^$D$14 -> 1692921.7
A27: Enterprise value | B27: =B23+B26 -> 2151907.5 | C27: =C23+C26 -> 2259231.7
A28: Terminal value share of enterprise value | B28: =IF(B27<>0,B26/B27,0) -> 0.73683348 | C28: =IF(C27<>0,C26/C27,0) -> 0.74933514
A29: Cross-check: implied exit multiple | implied perpetual growth | B29: =IF(C24>0,B25/C24,"n/a") -> 5.1513227 | C29: =IF(C25+B24<>0,(C25*$B$6-B24)/(C25+B24),"n/a") -> 0.027864424
A30: Enterprise value — average of the two methods | B30: =AVERAGE(B27,C27) -> 2205569.6
A32: Sensitivity: enterprise value (perpetual growth) by WACC and terminal growth
A33: WACC ↓ · terminal growth → | B33: =$B$7+(-2)*$B$11 -> 0.01 | C33: =$B$7+(-1)*$B$11 -> 0.015 | D33: =$B$7+(0)*$B$11 -> 0.02 | E33: =$B$7+(1)*$B$11 -> 0.025 | F33: =$B$7+(2)*$B$11 -> 0.03
A34: =$B$6+(-2)*$B$10 -> 0.14 | B34: =IF($A34>B$33,SUMPRODUCT($B$17:$D$17/(1+$A34)^$B$14:$D$14)+$D$17*(1+B$33)/($A34-B$33)/(1+$A34)^$D$14,"n/a") -> 2368783.5 | C34: =IF($A34>C$33,SUMPRODUCT($B$17:$D$17/(1+$A34)^$B$14:$D$14)+$D$17*(1+C$33)/($A34-C$33)/(1+$A34)^$D$14,"n/a") -> 2449210.5 | D34: =IF($A34>D$33,SUMPRODUCT($B$17:$D$17/(1+$A34)^$B$14:$D$14)+$D$17*(1+D$33)/($A34-D$33)/(1+$A34)^$D$14,"n/a") -> 2536339.7 | E34: =IF($A34>E$33,SUMPRODUCT($B$17:$D$17/(1+$A34)^$B$14:$D$14)+$D$17*(1+E$33)/($A34-E$33)/(1+$A34)^$D$14,"n/a") -> 2631045.4 | F34: =IF($A34>F$33,SUMPRODUCT($B$17:$D$17/(1+$A34)^$B$14:$D$14)+$D$17*(1+F$33)/($A34-F$33)/(1+$A34)^$D$14,"n/a") -> 2734360.7
A35: =$B$6+(-1)*$B$10 -> 0.15 | B35: =IF($A35>B$33,SUMPRODUCT($B$17:$D$17/(1+$A35)^$B$14:$D$14)+$D$17*(1+B$33)/($A35-B$33)/(1+$A35)^$D$14,"n/a") -> 2188064.2 | C35: =IF($A35>C$33,SUMPRODUCT($B$17:$D$17/(1+$A35)^$B$14:$D$14)+$D$17*(1+C$33)/($A35-C$33)/(1+$A35)^$D$14,"n/a") -> 2256017 | D35: =IF($A35>D$33,SUMPRODUCT($B$17:$D$17/(1+$A35)^$B$14:$D$14)+$D$17*(1+D$33)/($A35-D$33)/(1+$A35)^$D$14,"n/a") -> 2329196.9 | E35: =IF($A35>E$33,SUMPRODUCT($B$17:$D$17/(1+$A35)^$B$14:$D$14)+$D$17*(1+E$33)/($A35-E$33)/(1+$A35)^$D$14,"n/a") -> 2408231.2 | F35: =IF($A35>F$33,SUMPRODUCT($B$17:$D$17/(1+$A35)^$B$14:$D$14)+$D$17*(1+F$33)/($A35-F$33)/(1+$A35)^$D$14,"n/a") -> 2493851.7
A36: =$B$6+(0)*$B$10 -> 0.16 | B36: =IF($A36>B$33,SUMPRODUCT($B$17:$D$17/(1+$A36)^$B$14:$D$14)+$D$17*(1+B$33)/($A36-B$33)/(1+$A36)^$D$14,"n/a") -> 2031692.3 | C36: =IF($A36>C$33,SUMPRODUCT($B$17:$D$17/(1+$A36)^$B$14:$D$14)+$D$17*(1+C$33)/($A36-C$33)/(1+$A36)^$D$14,"n/a") -> 2089727.2 | D36: =IF($A36>D$33,SUMPRODUCT($B$17:$D$17/(1+$A36)^$B$14:$D$14)+$D$17*(1+D$33)/($A36-D$33)/(1+$A36)^$D$14,"n/a") -> 2151907.5 | E36: =IF($A36>E$33,SUMPRODUCT($B$17:$D$17/(1+$A36)^$B$14:$D$14)+$D$17*(1+E$33)/($A36-E$33)/(1+$A36)^$D$14,"n/a") -> 2218693.7 | F36: =IF($A36>F$33,SUMPRODUCT($B$17:$D$17/(1+$A36)^$B$14:$D$14)+$D$17*(1+F$33)/($A36-F$33)/(1+$A36)^$D$14,"n/a") -> 2290617.4
A37: =$B$6+(1)*$B$10 -> 0.17 | B37: =IF($A37>B$33,SUMPRODUCT($B$17:$D$17/(1+$A37)^$B$14:$D$14)+$D$17*(1+B$33)/($A37-B$33)/(1+$A37)^$D$14,"n/a") -> 1895095 | C37: =IF($A37>C$33,SUMPRODUCT($B$17:$D$17/(1+$A37)^$B$14:$D$14)+$D$17*(1+C$33)/($A37-C$33)/(1+$A37)^$D$14,"n/a") -> 1945126.2 | D37: =IF($A37>D$33,SUMPRODUCT($B$17:$D$17/(1+$A37)^$B$14:$D$14)+$D$17*(1+D$33)/($A37-D$33)/(1+$A37)^$D$14,"n/a") -> 1998492.9 | E37: =IF($A37>E$33,SUMPRODUCT($B$17:$D$17/(1+$A37)^$B$14:$D$14)+$D$17*(1+E$33)/($A37-E$33)/(1+$A37)^$D$14,"n/a") -> 2055540 | F37: =IF($A37>F$33,SUMPRODUCT($B$17:$D$17/(1+$A37)^$B$14:$D$14)+$D$17*(1+F$33)/($A37-F$33)/(1+$A37)^$D$14,"n/a") -> 2116662
A38: =$B$6+(2)*$B$10 -> 0.18 | B38: =IF($A38>B$33,SUMPRODUCT($B$17:$D$17/(1+$A38)^$B$14:$D$14)+$D$17*(1+B$33)/($A38-B$33)/(1+$A38)^$D$14,"n/a") -> 1774775.8 | C38: =IF($A38>C$33,SUMPRODUCT($B$17:$D$17/(1+$A38)^$B$14:$D$14)+$D$17*(1+C$33)/($A38-C$33)/(1+$A38)^$D$14,"n/a") -> 1818263.7 | D38: =IF($A38>D$33,SUMPRODUCT($B$17:$D$17/(1+$A38)^$B$14:$D$14)+$D$17*(1+D$33)/($A38-D$33)/(1+$A38)^$D$14,"n/a") -> 1864469.5 | E38: =IF($A38>E$33,SUMPRODUCT($B$17:$D$17/(1+$A38)^$B$14:$D$14)+$D$17*(1+E$33)/($A38-E$33)/(1+$A38)^$D$14,"n/a") -> 1913656.4 | F38: =IF($A38>F$33,SUMPRODUCT($B$17:$D$17/(1+$A38)^$B$14:$D$14)+$D$17*(1+F$33)/($A38-F$33)/(1+$A38)^$D$14,"n/a") -> 1966122.4
A40: Free cash flow = operating cash flow + interest × (1 − tax rate) − capital spending. Cells marked n/a: WACC not above growth.

Sheet Sources & Uses
A1: Sources and uses of funds | E1: =HYPERLINK("#'Cover'!A1","◂ Contents") -> ◂ Contents
A2: Live for the selected scenario. Where the money comes from and where it goes in the period set below.
A3: Scenario shown | B3: =CHOOSE(Dashboard!$B$4,"Low","Base","High") -> Base
A5: Funding structure ($'000) — raised at the start of the plan
B6: Amount | C6: Share
A7: Equity | B7: =Inputs!$E$54 -> 100000 | C7: =IF($B$9=0,0,B7/$B$9) -> 0.28571429
A8: Debt (loan) | B8: =Inputs!$E$55 -> 250000 | C8: =IF($B$9=0,0,B8/$B$9) -> 0.71428571
A9: Total funding | B9: =B7+B8 -> 350000 | C9: =IF(B9=0,0,1) -> 1
A10: Gearing (debt ÷ equity) | B10: =IF(B7<=0,IF(B8>0,"n/a",0),B8/B7) -> 2.5 | D10: n/a: debt without positive equity
A11: Funding required by the plan (Break-even sheet) | B11: ='Break-even'!B12 -> 108761.88
A12: Funding surplus / (shortfall) | B12: ='Break-even'!B17 -> 241238.12
A14: ="Sources and uses of cash in the first "&$B$16&IF($B$16=1," month"," months")&" ($'000)" -> Sources and uses of cash in the first 12 months ($'000)
A15: Period covered (months from the start) | B15: 12 | D15: 1 to 36 (capped)
A16: Months used | B16: =MIN(36,MAX(1,ROUND(B15,0))) -> 12
A17: Sources | B17: Amount | C17: Share
A18: Equity raised | B18: =SUMPRODUCT(--(Monthly!$C$4:$AL$4<=$B$16),Monthly!$C$76:$AL$76) -> 100000 | C18: =IF($B$21=0,0,B18/$B$21) -> 0.18358366
A19: Loan drawdowns | B19: =SUMPRODUCT(--(Monthly!$C$4:$AL$4<=$B$16),Monthly!$C$61:$AL$61) -> 250000 | C19: =IF($B$21=0,0,B19/$B$21) -> 0.45895914
A20: Cash generated by operations | B20: =MAX(0,SUMPRODUCT(--(Monthly!$C$4:$AL$4<=$B$16),Monthly!$C$74:$AL$74)) -> 194710.8 | C20: =IF($B$21=0,0,B20/$B$21) -> 0.35745721
A21: Total sources | B21: =SUM(B18:B20) -> 544710.8 | C21: =IF(B21=0,0,1) -> 1
A23: Uses | B23: Amount | C23: Share
A24: Cash used by operations | B24: =MAX(0,-SUMPRODUCT(--(Monthly!$C$4:$AL$4<=$B$16),Monthly!$C$74:$AL$74)) -> 0 | C24: =IF($B$28=0,0,B24/$B$28) -> 0
A25: Capital spending | B25: =-SUMPRODUCT(--(Monthly!$C$4:$AL$4<=$B$16),Monthly!$C$75:$AL$75) -> 20000 | C25: =IF($B$28=0,0,B25/$B$28) -> 0.036716731
A26: Loan repayments | B26: =-SUMPRODUCT(--(Monthly!$C$4:$AL$4<=$B$16),Monthly!$C$62:$AL$62) -> 45833.333 | C26: =IF($B$28=0,0,B26/$B$28) -> 0.084142509
A27: Cash at the end of the period | B27: =INDEX(Monthly!$C$80:$AL$80,$B$16) -> 478877.47 | C27: =IF($B$28=0,0,B27/$B$28) -> 0.87914076
A28: Total uses | B28: =SUM(B24:B27) -> 544710.8 | C28: =IF(B28=0,0,1) -> 1
A29: Sources − uses (must be 0; opening cash is 0) | B29: =B21-B28 -> 0

Sheet KPIs
A1: KPIs & ratios | G1: =HYPERLINK("#'Cover'!A1","◂ Contents") -> ◂ Contents
A2: Home services financial model (growing) — industry metrics and financial ratios for the active scenario
A4: Financial ratios
B5: 1 | C5: 2 | D5: 3 | E5: Target
A6: Revenue growth | B6: =IF(N('P&L'!A5)<=0,"n/a",'P&L'!B5/'P&L'!A5-1) -> n/a | C6: =IF(N('P&L'!B5)<=0,"n/a",'P&L'!C5/'P&L'!B5-1) -> 0.17862549 | D6: =IF(N('P&L'!C5)<=0,"n/a",'P&L'!D5/'P&L'!C5-1) -> 0.17895235
A7: Gross margin | B7: =IF('P&L'!B5<=0,"n/a",'P&L'!B7/'P&L'!B5) -> 0.38585434 | C7: =IF('P&L'!C5<=0,"n/a",'P&L'!C7/'P&L'!C5) -> 0.39481791 | D7: =IF('P&L'!D5<=0,"n/a",'P&L'!D7/'P&L'!D5) -> 0.40356802
A8: EBITDA margin | B8: =IF('P&L'!B5<=0,"n/a",'P&L'!B17/'P&L'!B5) -> 0.15559475 | C8: =IF('P&L'!C5<=0,"n/a",'P&L'!C17/'P&L'!C5) -> 0.17989534 | D8: =IF('P&L'!D5<=0,"n/a",'P&L'!D17/'P&L'!D5) -> 0.2021959
A9: Net margin | B9: =IF('P&L'!B5<=0,"n/a",'P&L'!B24/'P&L'!B5) -> 0.11260871 | C9: =IF('P&L'!C5<=0,"n/a",'P&L'!C24/'P&L'!C5) -> 0.13196803 | D9: =IF('P&L'!D5<=0,"n/a",'P&L'!D24/'P&L'!D5) -> 0.14964082
A10: Payroll, % of revenue | B10: =IF('P&L'!B5<=0,"n/a",-SUMIF(Headcount!$C$5:$AL$5,B$5,Headcount!$C$15:$AL$15)/'P&L'!B5) -> 0.35239148 | C10: =IF('P&L'!C5<=0,"n/a",-SUMIF(Headcount!$C$5:$AL$5,C$5,Headcount!$C$15:$AL$15)/'P&L'!C5) -> 0.34385137 | D10: =IF('P&L'!D5<=0,"n/a",-SUMIF(Headcount!$C$5:$AL$5,D$5,Headcount!$C$15:$AL$15)/'P&L'!D5) -> 0.33544052
A11: Marketing, % of revenue | B11: =IF('P&L'!B5<=0,"n/a",-'P&L'!B10/'P&L'!B5) -> 0.063156787 | C11: =IF('P&L'!C5<=0,"n/a",-'P&L'!C10/'P&L'!C5) -> 0.061622886 | D11: =IF('P&L'!D5<=0,"n/a",-'P&L'!D10/'P&L'!D5) -> 0.060109571
A12: Operating expenses, % of revenue | B12: =IF('P&L'!B5<=0,"n/a",-'P&L'!B16/'P&L'!B5) -> 0.23025959 | C12: =IF('P&L'!C5<=0,"n/a",-'P&L'!C16/'P&L'!C5) -> 0.21492256 | D12: =IF('P&L'!D5<=0,"n/a",-'P&L'!D16/'P&L'!D5) -> 0.20137211
A13: Current ratio (current assets ÷ current liabilities) | B13: =IF(('Balance Sheet'!B12-'Balance Sheet'!B11)<=0,"n/a",('Balance Sheet'!B5+'Balance Sheet'!B6+'Balance Sheet'!B7)/('Balance Sheet'!B12-'Balance Sheet'!B11)) -> 9.4585262 | C13: =IF(('Balance Sheet'!C12-'Balance Sheet'!C11)<=0,"n/a",('Balance Sheet'!C5+'Balance Sheet'!C6+'Balance Sheet'!C7)/('Balance Sheet'!C12-'Balance Sheet'!C11)) -> 11.130782 | D13: =IF(('Balance Sheet'!D12-'Balance Sheet'!D11)<=0,"n/a",('Balance Sheet'!D5+'Balance Sheet'!D6+'Balance Sheet'!D7)/('Balance Sheet'!D12-'Balance Sheet'!D11)) -> 13.369884
A14: Debt ÷ equity (loan ÷ total equity) | B14: =IF('Balance Sheet'!B15<=0,"n/a",'Balance Sheet'!B11/'Balance Sheet'!B15) -> 0.69785235 | C14: =IF('Balance Sheet'!C15<=0,"n/a",'Balance Sheet'!C11/'Balance Sheet'!C15) -> 0.27601533 | D14: =IF('Balance Sheet'!D15<=0,"n/a",'Balance Sheet'!D11/'Balance Sheet'!D15) -> 0.11395363
A15: Return on assets (net income ÷ year-end assets) | B15: =IF('Balance Sheet'!B9<=0,"n/a",'P&L'!B24/'Balance Sheet'!B9) -> 0.34786219 | C15: =IF('Balance Sheet'!C9<=0,"n/a",'P&L'!C24/'Balance Sheet'!C9) -> 0.34148453 | D15: =IF('Balance Sheet'!D9<=0,"n/a",'P&L'!D24/'Balance Sheet'!D9) -> 0.32460871
A16: Return on equity (net income ÷ year-end equity) | B16: =IF('Balance Sheet'!B15<=0,"n/a",'P&L'!B24/'Balance Sheet'!B15) -> 0.65819477 | C16: =IF('Balance Sheet'!C15<=0,"n/a",'P&L'!C24/'Balance Sheet'!C15) -> 0.47620179 | D16: =IF('Balance Sheet'!D15<=0,"n/a",'P&L'!D24/'Balance Sheet'!D15) -> 0.38897823
A18: DuPont analysis — return on equity = net margin × asset turnover × equity multiplier
B19: 1 | C19: 2 | D19: 3
A20: Net margin | B20: =IF('P&L'!B5<=0,"n/a",'P&L'!B24/'P&L'!B5) -> 0.11260871 | C20: =IF('P&L'!C5<=0,"n/a",'P&L'!C24/'P&L'!C5) -> 0.13196803 | D20: =IF('P&L'!D5<=0,"n/a",'P&L'!D24/'P&L'!D5) -> 0.14964082
A21: × Asset turnover (revenue ÷ assets) | B21: =IF('Balance Sheet'!B9<=0,"n/a",'P&L'!B5/'Balance Sheet'!B9) -> 3.0891233 | C21: =IF('Balance Sheet'!C9<=0,"n/a",'P&L'!C5/'Balance Sheet'!C9) -> 2.5876307 | D21: =IF('Balance Sheet'!D9<=0,"n/a",'P&L'!D5/'Balance Sheet'!D9) -> 2.1692524
A22: × Equity multiplier (assets ÷ equity) | B22: =IF('Balance Sheet'!B15<=0,"n/a",'Balance Sheet'!B9/'Balance Sheet'!B15) -> 1.8921136 | C22: =IF('Balance Sheet'!C15<=0,"n/a",'Balance Sheet'!C9/'Balance Sheet'!C15) -> 1.3945047 | D22: =IF('Balance Sheet'!D15<=0,"n/a",'Balance Sheet'!D9/'Balance Sheet'!D15) -> 1.1982988
A23: Return on equity (product of the three) | B23: =IF(AND(ISNUMBER(B20),ISNUMBER(B21),ISNUMBER(B22)),B20*B21*B22,"n/a") -> 0.65819477 | C23: =IF(AND(ISNUMBER(C20),ISNUMBER(C21),ISNUMBER(C22)),C20*C21*C22,"n/a") -> 0.47620179 | D23: =IF(AND(ISNUMBER(D20),ISNUMBER(D21),ISNUMBER(D22)),D20*D21*D22,"n/a") -> 0.38897823
A24: Check: product − return on equity (must be 0) | B24: =IF(AND(ISNUMBER(B23),ISNUMBER(B16)),B23-B16,IF(ISNUMBER(B23),1,IF(AND(ISNUMBER(B16),ISNUMBER(B20),ISNUMBER(B21)),1,0))) -> 0 | C24: =IF(AND(ISNUMBER(C23),ISNUMBER(C16)),C23-C16,IF(ISNUMBER(C23),1,IF(AND(ISNUMBER(C16),ISNUMBER(C20),ISNUMBER(C21)),1,0))) -> 0 | D24: =IF(AND(ISNUMBER(D23),ISNUMBER(D16)),D23-D16,IF(ISNUMBER(D23),1,IF(AND(ISNUMBER(D16),ISNUMBER(D20),ISNUMBER(D21)),1,0))) -> 0
A26: Home services metrics ($'000; per-unit rows in $)
A27: Year # | B27: 1 | C27: 2 | D27: 3
B28: Year 1 | C28: Year 2 | D28: Year 3 | E28: Target
A29: Field technicians (FTE, year end) | B29: =INDEX(Monthly!$C$8:$AL$8,B$27*12) -> 7 | C29: =INDEX(Monthly!$C$8:$AL$8,C$27*12) -> 7.84 | D29: =INDEX(Monthly!$C$8:$AL$8,D$27*12) -> 8.7808
A30: Job capacity | B30: =SUMIF(Monthly!$C$5:$AL$5,B$27,Monthly!$C$9:$AL$9) -> 4410 | C30: =SUMIF(Monthly!$C$5:$AL$5,C$27,Monthly!$C$9:$AL$9) -> 4939.2 | D30: =SUMIF(Monthly!$C$5:$AL$5,D$27,Monthly!$C$9:$AL$9) -> 5531.904
A31: Jobs demanded | B31: =SUMIF(Monthly!$C$5:$AL$5,B$27,Monthly!$C$14:$AL$14) -> 3732 | C31: =SUMIF(Monthly!$C$5:$AL$5,C$27,Monthly!$C$14:$AL$14) -> 4291.8 | D31: =SUMIF(Monthly!$C$5:$AL$5,D$27,Monthly!$C$14:$AL$14) -> 4935.57
A32: Jobs completed | B32: =SUMIF(Monthly!$C$5:$AL$5,B$27,Monthly!$C$15:$AL$15) -> 3668.25 | C32: =SUMIF(Monthly!$C$5:$AL$5,C$27,Monthly!$C$15:$AL$15) -> 4185.4125 | D32: =SUMIF(Monthly!$C$5:$AL$5,D$27,Monthly!$C$15:$AL$15) -> 4776.1804
A33: Technician utilisation (jobs ÷ capacity) | B33: =IF(B30=0,0,B32/B30) -> 0.83180272 | C33: =IF(C30=0,0,C32/C30) -> 0.84738672 | D33: =IF(D30=0,0,D32/D30) -> 0.86338815
A34: Jobs turned away (demand above capacity) | B34: =B31-B32 -> 63.75 | C34: =C31-C32 -> 106.3875 | D34: =D31-D32 -> 159.38962
A35: Jobs booked from marketing leads | B35: =SUMIF(Monthly!$C$5:$AL$5,B$27,Monthly!$C$12:$AL$12) -> 972 | C35: =SUMIF(Monthly!$C$5:$AL$5,C$27,Monthly!$C$12:$AL$12) -> 1117.8 | D35: =SUMIF(Monthly!$C$5:$AL$5,D$27,Monthly!$C$12:$AL$12) -> 1285.47
A36: Marketing spend | B36: =-SUMIF(Monthly!$C$5:$AL$5,B$27,Monthly!$C$34:$AL$34) -> 108000 | C36: =-SUMIF(Monthly!$C$5:$AL$5,C$27,Monthly!$C$34:$AL$34) -> 124200 | D36: =-SUMIF(Monthly!$C$5:$AL$5,D$27,Monthly!$C$34:$AL$34) -> 142830
A37: Marketing cost per booked job ($) | B37: =IF(B35=0,0,B36/B35) -> 111.11111 | C37: =IF(C35=0,0,C36/C35) -> 111.11111 | D37: =IF(D35=0,0,D36/D35) -> 111.11111
A38: Revenue | B38: =SUMIF(Monthly!$C$5:$AL$5,B$27,Monthly!$C$22:$AL$22) -> 1710030 | C38: =SUMIF(Monthly!$C$5:$AL$5,C$27,Monthly!$C$22:$AL$22) -> 2015484.9 | D38: =SUMIF(Monthly!$C$5:$AL$5,D$27,Monthly!$C$22:$AL$22) -> 2376160.7
A39: Job revenue | B39: =SUMIF(Monthly!$C$5:$AL$5,B$27,Monthly!$C$19:$AL$19) -> 1614030 | C39: =SUMIF(Monthly!$C$5:$AL$5,C$27,Monthly!$C$19:$AL$19) -> 1896828.9 | D39: =SUMIF(Monthly!$C$5:$AL$5,D$27,Monthly!$C$19:$AL$19) -> 2229501.9
A40: Average revenue per job ($) | B40: =IF(B32=0,0,B39/B32) -> 440 | C40: =IF(C32=0,0,C39/C32) -> 453.2 | D40: =IF(D32=0,0,D39/D32) -> 466.796
A41: Revenue per technician (year-end FTE) | B41: =IF(B29=0,0,B38/B29) -> 244290 | C41: =IF(C29=0,0,C38/C29) -> 257077.16 | D41: =IF(D29=0,0,D38/D29) -> 270608.68
A42: Maintenance plan members (year end) | B42: =INDEX(Monthly!$C$20:$AL$20,B$27*12) -> 400 | C42: =INDEX(Monthly!$C$20:$AL$20,C$27*12) -> 480 | D42: =INDEX(Monthly!$C$20:$AL$20,D$27*12) -> 576
A43: Maintenance plan revenue | B43: =SUMIF(Monthly!$C$5:$AL$5,B$27,Monthly!$C$21:$AL$21) -> 96000 | C43: =SUMIF(Monthly!$C$5:$AL$5,C$27,Monthly!$C$21:$AL$21) -> 118656 | D43: =SUMIF(Monthly!$C$5:$AL$5,D$27,Monthly!$C$21:$AL$21) -> 146658.82
A44: Plans share of revenue | B44: =IF(B38=0,0,B43/B38) -> 0.056139366 | C44: =IF(C38=0,0,C43/C38) -> 0.058872184 | D44: =IF(D38=0,0,D43/D38) -> 0.061720916
A45: Gross profit | B45: =SUMIF(Monthly!$C$5:$AL$5,B$27,Monthly!$C$30:$AL$30) -> 659822.5 | C45: =SUMIF(Monthly!$C$5:$AL$5,C$27,Monthly!$C$30:$AL$30) -> 795749.55 | D45: =SUMIF(Monthly!$C$5:$AL$5,D$27,Monthly!$C$30:$AL$30) -> 958942.46
A46: Gross margin | B46: =IF(B38=0,0,B45/B38) -> 0.38585434 | C46: =IF(C38=0,0,C45/C38) -> 0.39481791 | D46: =IF(D38=0,0,D45/D38) -> 0.40356802
A47: Gross profit per job (all gross profit ÷ jobs) ($) | B47: =IF(B32=0,0,B45/B32) -> 179.87392 | C47: =IF(C32=0,0,C45/C32) -> 190.12452 | D47: =IF(D32=0,0,D45/D32) -> 200.77602
A48: EBITDA | B48: =SUMIF(Monthly!$C$5:$AL$5,B$27,Monthly!$C$41:$AL$41) -> 266071.69 | C48: =SUMIF(Monthly!$C$5:$AL$5,C$27,Monthly!$C$41:$AL$41) -> 362576.36 | D48: =SUMIF(Monthly!$C$5:$AL$5,D$27,Monthly!$C$41:$AL$41) -> 480449.96
A49: EBITDA margin | B49: =IF(B38=0,0,B48/B38) -> 0.15559475 | C49: =IF(C38=0,0,C48/C38) -> 0.17989534 | D49: =IF(D38=0,0,D48/D38) -> 0.2021959

Sheet Inputs
A1: Inputs — Low / Base / High | I1: =HYPERLINK("#'Cover'!A1","◂ Contents") -> ◂ Contents
A2: Illustrative assumptions — replace them with your own numbers.
A5: Driver | B5: Low | C5: Base | D5: High | E5: Active | F5: Unit | G5: Source / comment
A6: Technician capacity
A7: Jobs per technician per working day | B7: 2.35 | C7: 2.5 | D7: 2.65 | E7: =CHOOSE(Dashboard!$B$4,B7,C7,D7) -> 2.5 | F7: jobs | G7: Low ≤ Base ≤ High
A8: Working days per month | B8: 21 | C8: 21 | D8: 21 | E8: =CHOOSE(Dashboard!$B$4,B8,C8,D8) -> 21 | F8: days
A10: Demand
A11: Marketing budget per month | B11: 9000 | C11: 9000 | D11: 9000 | E11: =CHOOSE(Dashboard!$B$4,B11,C11,D11) -> 9000 | F11: $
A12: Marketing budget growth per year | B12: 0.12 | C12: 0.15 | D12: 0.18 | E12: =CHOOSE(Dashboard!$B$4,B12,C12,D12) -> 0.15 | F12: % | G12: Low ≤ Base ≤ High
A13: Cost per lead | B13: 52 | C13: 50 | D13: 48 | E13: =CHOOSE(Dashboard!$B$4,B13,C13,D13) -> 50 | F13: $ | G13: Low ≥ Base ≥ High (lower is better)
A14: Leads booked as jobs | B14: 0.42 | C14: 0.45 | D14: 0.48 | E14: =CHOOSE(Dashboard!$B$4,B14,C14,D14) -> 0.45 | F14: % | G14: Low ≤ Base ≤ High
A15: Repeat & referral jobs per month (year 1) | B15: 190 | C15: 230 | D15: 270 | E15: =CHOOSE(Dashboard!$B$4,B15,C15,D15) -> 230 | F15: jobs | G15: Low ≤ Base ≤ High
A16: Repeat & referral jobs growth per year | B16: 0.12 | C16: 0.15 | D16: 0.18 | E16: =CHOOSE(Dashboard!$B$4,B16,C16,D16) -> 0.15 | F16: % | G16: Low ≤ Base ≤ High
A17: Busy-season uplift, June–August (monthly models) | B17: 0.25 | C17: 0.25 | D17: 0.25 | E17: =CHOOSE(Dashboard!$B$4,B17,C17,D17) -> 0.25 | F17: %
A19: Prices
A20: Average revenue per job (year 1) | B20: 415 | C20: 440 | D20: 465 | E20: =CHOOSE(Dashboard!$B$4,B20,C20,D20) -> 440 | F20: $ | G20: Low ≤ Base ≤ High
A21: Price increase per year | B21: 0.02 | C21: 0.03 | D21: 0.04 | E21: =CHOOSE(Dashboard!$B$4,B21,C21,D21) -> 0.03 | F21: % | G21: Low ≤ Base ≤ High
A23: Maintenance plans
A24: Maintenance plan members (year-1 average) | B24: 300 | C24: 400 | D24: 500 | E24: =CHOOSE(Dashboard!$B$4,B24,C24,D24) -> 400 | F24: # | G24: Low ≤ Base ≤ High
A25: Plan members growth per year | B25: 0.15 | C25: 0.2 | D25: 0.25 | E25: =CHOOSE(Dashboard!$B$4,B25,C25,D25) -> 0.2 | F25: % | G25: Low ≤ Base ≤ High
A26: Plan fee per member per month (year 1) | B26: 18 | C26: 20 | D26: 22 | E26: =CHOOSE(Dashboard!$B$4,B26,C26,D26) -> 20 | F26: $ | G26: Low ≤ Base ≤ High
A27: Cost of plan visits, % of plan fees | B27: 0.42 | C27: 0.4 | D27: 0.38 | E27: =CHOOSE(Dashboard!$B$4,B27,C27,D27) -> 0.4 | F27: % | G27: Low ≥ Base ≥ High (lower is better)
A29: Costs
A30: Materials & parts, % of job revenue | B30: 0.26 | C30: 0.25 | D30: 0.24 | E30: =CHOOSE(Dashboard!$B$4,B30,C30,D30) -> 0.25 | F30: % | G30: Low ≥ Base ≥ High (lower is better)
A31: Vehicle per technician per month (lease, fuel, upkeep) | B31: 1350 | C31: 1300 | D31: 1250 | E31: =CHOOSE(Dashboard!$B$4,B31,C31,D31) -> 1300 | F31: $ | G31: Low ≥ Base ≥ High (lower is better)
A32: Field software & phone per technician per month | B32: 120 | C32: 120 | D32: 120 | E32: =CHOOSE(Dashboard!$B$4,B32,C32,D32) -> 120 | F32: $
A33: Insurance & licences per month | B33: 3500 | C33: 3500 | D33: 3500 | E33: =CHOOSE(Dashboard!$B$4,B33,C33,D33) -> 3500 | F33: $
A34: Shop / office rent per month | B34: 4500 | C34: 4500 | D34: 4500 | E34: =CHOOSE(Dashboard!$B$4,B34,C34,D34) -> 4500 | F34: $
A35: Other G&A per month (accounting, legal, bank) | B35: 2500 | C35: 2500 | D35: 2500 | E35: =CHOOSE(Dashboard!$B$4,B35,C35,D35) -> 2500 | F35: $
A36: Card processing fees, % of revenue | B36: 0.029 | C36: 0.027 | D36: 0.025 | E36: =CHOOSE(Dashboard!$B$4,B36,C36,D36) -> 0.027 | F36: % | G36: Low ≥ Base ≥ High (lower is better)
A37: Start-up capex (shop, equipment) | B37: 20000 | C37: 20000 | D37: 20000 | E37: =CHOOSE(Dashboard!$B$4,B37,C37,D37) -> 20000 | F37: $
A38: Van & tools per technician added | B38: 47000 | C38: 45000 | D38: 43000 | E38: =CHOOSE(Dashboard!$B$4,B38,C38,D38) -> 45000 | F38: $ | G38: Low ≥ Base ≥ High (lower is better)
A39: Technicians already equipped at start (own vans & tools) | B39: 7 | C39: 7 | D39: 7 | E39: =CHOOSE(Dashboard!$B$4,B39,C39,D39) -> 7 | F39: FTE
A41: Headcount
A42: Field technicians: headcount (FTE) | B42: 7 | C42: 7 | D42: 7 | E42: =CHOOSE(Dashboard!$B$4,B42,C42,D42) -> 7 | F42: FTE | G42: Low ≤ Base ≤ High
A43: Field technicians: salary per FTE per year | B43: 62000 | C43: 62000 | D43: 62000 | E43: =CHOOSE(Dashboard!$B$4,B43,C43,D43) -> 62000 | F43: $
A44: Field technicians: headcount growth per year | B44: 0.12 | C44: 0.12 | D44: 0.12 | E44: =CHOOSE(Dashboard!$B$4,B44,C44,D44) -> 0.12 | F44: % | G44: Low ≤ Base ≤ High
A45: Field technicians: first month on payroll | B45: 1 | C45: 1 | D45: 1 | E45: =CHOOSE(Dashboard!$B$4,B45,C45,D45) -> 1 | F45: month #
A46: Dispatch & office: headcount (FTE) | B46: 2 | C46: 2 | D46: 2 | E46: =CHOOSE(Dashboard!$B$4,B46,C46,D46) -> 2 | F46: FTE | G46: Low ≤ Base ≤ High
A47: Dispatch & office: salary per FTE per year | B47: 45000 | C47: 45000 | D47: 45000 | E47: =CHOOSE(Dashboard!$B$4,B47,C47,D47) -> 45000 | F47: $
A48: Dispatch & office: headcount growth per year | B48: 0.1 | C48: 0.1 | D48: 0.1 | E48: =CHOOSE(Dashboard!$B$4,B48,C48,D48) -> 0.1 | F48: % | G48: Low ≤ Base ≤ High
A49: Dispatch & office: first month on payroll | B49: 1 | C49: 1 | D49: 1 | E49: =CHOOSE(Dashboard!$B$4,B49,C49,D49) -> 1 | F49: month #
A50: Payroll taxes & benefits, % of salary | B50: 0.15 | C50: 0.15 | D50: 0.15 | E50: =CHOOSE(Dashboard!$B$4,B50,C50,D50) -> 0.15 | F50: %
A51: Wage growth per year | B51: 0.03 | C51: 0.03 | D51: 0.03 | E51: =CHOOSE(Dashboard!$B$4,B51,C51,D51) -> 0.03 | F51: %
A53: Funding
A54: Equity raised at start | B54: 100000 | C54: 100000 | D54: 100000 | E54: =CHOOSE(Dashboard!$B$4,B54,C54,D54) -> 100000 | F54: $
A55: Loan drawn at start | B55: 250000 | C55: 250000 | D55: 250000 | E55: =CHOOSE(Dashboard!$B$4,B55,C55,D55) -> 250000 | F55: $
A56: Loan interest rate per year | B56: 0.08 | C56: 0.08 | D56: 0.08 | E56: =CHOOSE(Dashboard!$B$4,B56,C56,D56) -> 0.08 | F56: %
A57: Loan repayment term | B57: 5 | C57: 5 | D57: 5 | E57: =CHOOSE(Dashboard!$B$4,B57,C57,D57) -> 5 | F57: years
A59: Working capital
A60: Customer payment terms (receivable days) | B60: 10 | C60: 10 | D60: 10 | E60: =CHOOSE(Dashboard!$B$4,B60,C60,D60) -> 10 | F60: days
A61: Inventory held (days of COGS) | B61: 5 | C61: 5 | D61: 5 | E61: =CHOOSE(Dashboard!$B$4,B61,C61,D61) -> 5 | F61: days
A62: Supplier payment terms (payable days) | B62: 20 | C62: 20 | D62: 20 | E62: =CHOOSE(Dashboard!$B$4,B62,C62,D62) -> 20 | F62: days
A64: Tax & depreciation
A65: Depreciation period for capex | B65: 5 | C65: 5 | D65: 5 | E65: =CHOOSE(Dashboard!$B$4,B65,C65,D65) -> 5 | F65: years
A66: Income tax rate | B66: 0.21 | C66: 0.21 | D66: 0.21 | E66: =CHOOSE(Dashboard!$B$4,B66,C66,D66) -> 0.21 | F66: %
A68: Break-even & funding
A69: Minimum cash buffer to keep | B69: 98000 | C69: 98000 | D69: 98000 | E69: =CHOOSE(Dashboard!$B$4,B69,C69,D69) -> 98000 | F69: $ | G69: About 3 months of costs
A71: Valuation
A72: Discount rate (WACC) | B72: 0.2 | C72: 0.16 | D72: 0.13 | E72: =CHOOSE(Dashboard!$B$4,B72,C72,D72) -> 0.16 | F72: % | G72: Low ≥ Base ≥ High (lower is better)
A73: Terminal growth rate (perpetuity) | B73: 0.01 | C73: 0.02 | D73: 0.03 | E73: =CHOOSE(Dashboard!$B$4,B73,C73,D73) -> 0.02 | F73: % | G73: Low ≤ Base ≤ High
A74: Exit multiple (EV ÷ final-year EBITDA) | B74: 4 | C74: 5.5 | D74: 7 | E74: =CHOOSE(Dashboard!$B$4,B74,C74,D74) -> 5.5 | F74: x | G74: Low ≤ Base ≤ High
A75: Sensitivity table: WACC step | B75: 0.01 | C75: 0.01 | D75: 0.01 | E75: =CHOOSE(Dashboard!$B$4,B75,C75,D75) -> 0.01 | F75: %
A76: Sensitivity table: growth step | B76: 0.005 | C76: 0.005 | D76: 0.005 | E76: =CHOOSE(Dashboard!$B$4,B76,C76,D76) -> 0.005 | F76: %
A78: Legend: yellow cell with blue figure = input you can change · black = formula · green = link to another sheet · grey = active value (column E follows the scenario on the Dashboard).

Sheet P&L
A1: Annual profit & loss | F1: =HYPERLINK("#'Cover'!A1","◂ Contents") -> ◂ Contents
A2: Rolled up from the period detail (SUMIF on the year row; balances at year end).
A3: Year # | B3: 1 | C3: 2 | D3: 3
B4: Year 1 | C4: Year 2 | D4: Year 3
A5: Revenue | B5: =SUMIF(Monthly!$C$5:$AL$5,B$3,Monthly!$C$22:$AL$22) -> 1710030 | C5: =SUMIF(Monthly!$C$5:$AL$5,C$3,Monthly!$C$22:$AL$22) -> 2015484.9 | D5: =SUMIF(Monthly!$C$5:$AL$5,D$3,Monthly!$C$22:$AL$22) -> 2376160.7
A6: Cost of delivery | B6: =SUMIF(Monthly!$C$5:$AL$5,B$3,Monthly!$C$29:$AL$29) -> -1050207.5 | C6: =SUMIF(Monthly!$C$5:$AL$5,C$3,Monthly!$C$29:$AL$29) -> -1219735.4 | D6: =SUMIF(Monthly!$C$5:$AL$5,D$3,Monthly!$C$29:$AL$29) -> -1417218.2
A7: Gross profit | B7: =SUMIF(Monthly!$C$5:$AL$5,B$3,Monthly!$C$30:$AL$30) -> 659822.5 | C7: =SUMIF(Monthly!$C$5:$AL$5,C$3,Monthly!$C$30:$AL$30) -> 795749.55 | D7: =SUMIF(Monthly!$C$5:$AL$5,D$3,Monthly!$C$30:$AL$30) -> 958942.46
A8: Gross margin | B8: =IF(B5=0,0,B7/B5) -> 0.38585434 | C8: =IF(C5=0,0,C7/C5) -> 0.39481791 | D8: =IF(D5=0,0,D7/D5) -> 0.40356802
A9: Dispatch, office & other payroll | B9: =SUMIF(Monthly!$C$5:$AL$5,B$3,Monthly!$C$33:$AL$33) -> -103500 | C9: =SUMIF(Monthly!$C$5:$AL$5,C$3,Monthly!$C$33:$AL$33) -> -117265.5 | D9: =SUMIF(Monthly!$C$5:$AL$5,D$3,Monthly!$C$33:$AL$33) -> -132861.81
A10: Marketing | B10: =SUMIF(Monthly!$C$5:$AL$5,B$3,Monthly!$C$34:$AL$34) -> -108000 | C10: =SUMIF(Monthly!$C$5:$AL$5,C$3,Monthly!$C$34:$AL$34) -> -124200 | D10: =SUMIF(Monthly!$C$5:$AL$5,D$3,Monthly!$C$34:$AL$34) -> -142830
A11: Field software & phones | B11: =SUMIF(Monthly!$C$5:$AL$5,B$3,Monthly!$C$35:$AL$35) -> -10080 | C11: =SUMIF(Monthly!$C$5:$AL$5,C$3,Monthly!$C$35:$AL$35) -> -11289.6 | D11: =SUMIF(Monthly!$C$5:$AL$5,D$3,Monthly!$C$35:$AL$35) -> -12644.352
A12: Insurance & licences | B12: =SUMIF(Monthly!$C$5:$AL$5,B$3,Monthly!$C$36:$AL$36) -> -42000 | C12: =SUMIF(Monthly!$C$5:$AL$5,C$3,Monthly!$C$36:$AL$36) -> -42000 | D12: =SUMIF(Monthly!$C$5:$AL$5,D$3,Monthly!$C$36:$AL$36) -> -42000
A13: Shop / office rent | B13: =SUMIF(Monthly!$C$5:$AL$5,B$3,Monthly!$C$37:$AL$37) -> -54000 | C13: =SUMIF(Monthly!$C$5:$AL$5,C$3,Monthly!$C$37:$AL$37) -> -54000 | D13: =SUMIF(Monthly!$C$5:$AL$5,D$3,Monthly!$C$37:$AL$37) -> -54000
A14: Other G&A | B14: =SUMIF(Monthly!$C$5:$AL$5,B$3,Monthly!$C$38:$AL$38) -> -30000 | C14: =SUMIF(Monthly!$C$5:$AL$5,C$3,Monthly!$C$38:$AL$38) -> -30000 | D14: =SUMIF(Monthly!$C$5:$AL$5,D$3,Monthly!$C$38:$AL$38) -> -30000
A15: Card processing fees | B15: =SUMIF(Monthly!$C$5:$AL$5,B$3,Monthly!$C$39:$AL$39) -> -46170.81 | C15: =SUMIF(Monthly!$C$5:$AL$5,C$3,Monthly!$C$39:$AL$39) -> -54418.094 | D15: =SUMIF(Monthly!$C$5:$AL$5,D$3,Monthly!$C$39:$AL$39) -> -64156.339
A16: Total operating expenses | B16: =SUMIF(Monthly!$C$5:$AL$5,B$3,Monthly!$C$40:$AL$40) -> -393750.81 | C16: =SUMIF(Monthly!$C$5:$AL$5,C$3,Monthly!$C$40:$AL$40) -> -433173.19 | D16: =SUMIF(Monthly!$C$5:$AL$5,D$3,Monthly!$C$40:$AL$40) -> -478492.5
A17: EBITDA | B17: =SUMIF(Monthly!$C$5:$AL$5,B$3,Monthly!$C$41:$AL$41) -> 266071.69 | C17: =SUMIF(Monthly!$C$5:$AL$5,C$3,Monthly!$C$41:$AL$41) -> 362576.36 | D17: =SUMIF(Monthly!$C$5:$AL$5,D$3,Monthly!$C$41:$AL$41) -> 480449.96
A18: EBITDA margin | B18: =IF(B5=0,0,B17/B5) -> 0.15559475 | C18: =IF(C5=0,0,C17/C5) -> 0.17989534 | D18: =IF(D5=0,0,D17/D5) -> 0.2021959
A19: Depreciation | B19: =SUMIF(Monthly!$C$5:$AL$5,B$3,Monthly!$C$55:$AL$55) -> -4000 | C19: =SUMIF(Monthly!$C$5:$AL$5,C$3,Monthly!$C$55:$AL$55) -> -11560 | D19: =SUMIF(Monthly!$C$5:$AL$5,D$3,Monthly!$C$55:$AL$55) -> -20027.2
A20: EBIT | B20: =SUMIF(Monthly!$C$5:$AL$5,B$3,Monthly!$C$44:$AL$44) -> 262071.69 | C20: =SUMIF(Monthly!$C$5:$AL$5,C$3,Monthly!$C$44:$AL$44) -> 351016.36 | D20: =SUMIF(Monthly!$C$5:$AL$5,D$3,Monthly!$C$44:$AL$44) -> 460422.76
A21: Interest | B21: =SUMIF(Monthly!$C$5:$AL$5,B$3,Monthly!$C$45:$AL$45) -> -18319.444 | C21: =SUMIF(Monthly!$C$5:$AL$5,C$3,Monthly!$C$45:$AL$45) -> -14333.333 | D21: =SUMIF(Monthly!$C$5:$AL$5,D$3,Monthly!$C$45:$AL$45) -> -10333.333
A22: Pre-tax income | B22: =SUMIF(Monthly!$C$5:$AL$5,B$3,Monthly!$C$46:$AL$46) -> 243752.25 | C22: =SUMIF(Monthly!$C$5:$AL$5,C$3,Monthly!$C$46:$AL$46) -> 336683.02 | D22: =SUMIF(Monthly!$C$5:$AL$5,D$3,Monthly!$C$46:$AL$46) -> 450089.43
A23: Income tax | B23: =SUMIF(Monthly!$C$5:$AL$5,B$3,Monthly!$C$49:$AL$49) -> -51187.972 | C23: =SUMIF(Monthly!$C$5:$AL$5,C$3,Monthly!$C$49:$AL$49) -> -70703.435 | D23: =SUMIF(Monthly!$C$5:$AL$5,D$3,Monthly!$C$49:$AL$49) -> -94518.78
A24: Net income | B24: =SUMIF(Monthly!$C$5:$AL$5,B$3,Monthly!$C$50:$AL$50) -> 192564.27 | C24: =SUMIF(Monthly!$C$5:$AL$5,C$3,Monthly!$C$50:$AL$50) -> 265979.59 | D24: =SUMIF(Monthly!$C$5:$AL$5,D$3,Monthly!$C$50:$AL$50) -> 355570.65
A25: Net margin | B25: =IF(B5=0,0,B24/B5) -> 0.11260871 | C25: =IF(C5=0,0,C24/C5) -> 0.13196803 | D25: =IF(D5=0,0,D24/D5) -> 0.14964082

Sheet Cash Flow
A1: Annual cash flow statement | F1: =HYPERLINK("#'Cover'!A1","◂ Contents") -> ◂ Contents
A2: Rolled up from the period detail (SUMIF on the year row; balances at year end).
A3: Year # | B3: 1 | C3: 2 | D3: 3
B4: Year 1 | C4: Year 2 | D4: Year 3
A5: Net income | B5: =SUMIF(Monthly!$C$5:$AL$5,B$3,Monthly!$C$50:$AL$50) -> 192564.27 | C5: =SUMIF(Monthly!$C$5:$AL$5,C$3,Monthly!$C$50:$AL$50) -> 265979.59 | D5: =SUMIF(Monthly!$C$5:$AL$5,D$3,Monthly!$C$50:$AL$50) -> 355570.65
A6: Add back depreciation | B6: =-SUMIF(Monthly!$C$5:$AL$5,B$3,Monthly!$C$55:$AL$55) -> 4000 | C6: =-SUMIF(Monthly!$C$5:$AL$5,C$3,Monthly!$C$55:$AL$55) -> 11560 | D6: =-SUMIF(Monthly!$C$5:$AL$5,D$3,Monthly!$C$55:$AL$55) -> 20027.2
A7: (Increase) / decrease in receivables | B7: =SUMIF(Monthly!$C$5:$AL$5,B$3,Monthly!$C$69:$AL$69) -> -44478.889 | C7: =SUMIF(Monthly!$C$5:$AL$5,C$3,Monthly!$C$69:$AL$69) -> -8343.6883 | D7: =SUMIF(Monthly!$C$5:$AL$5,D$3,Monthly!$C$69:$AL$69) -> -9915.5095
A8: (Increase) / decrease in inventory | B8: =SUMIF(Monthly!$C$5:$AL$5,B$3,Monthly!$C$70:$AL$70) -> -14208.472 | C8: =SUMIF(Monthly!$C$5:$AL$5,C$3,Monthly!$C$70:$AL$70) -> -2336.9077 | D8: =SUMIF(Monthly!$C$5:$AL$5,D$3,Monthly!$C$70:$AL$70) -> -2729.9096
A9: Increase / (decrease) in payables | B9: =SUMIF(Monthly!$C$5:$AL$5,B$3,Monthly!$C$71:$AL$71) -> 56833.889 | C9: =SUMIF(Monthly!$C$5:$AL$5,C$3,Monthly!$C$71:$AL$71) -> 9347.6308 | D9: =SUMIF(Monthly!$C$5:$AL$5,D$3,Monthly!$C$71:$AL$71) -> 10919.639
A10: Operating cash flow | B10: =SUMIF(Monthly!$C$5:$AL$5,B$3,Monthly!$C$74:$AL$74) -> 194710.8 | C10: =SUMIF(Monthly!$C$5:$AL$5,C$3,Monthly!$C$74:$AL$74) -> 276206.62 | D10: =SUMIF(Monthly!$C$5:$AL$5,D$3,Monthly!$C$74:$AL$74) -> 373872.07
A11: Capital spending | B11: =SUMIF(Monthly!$C$5:$AL$5,B$3,Monthly!$C$75:$AL$75) -> -20000 | C11: =SUMIF(Monthly!$C$5:$AL$5,C$3,Monthly!$C$75:$AL$75) -> -37800 | D11: =SUMIF(Monthly!$C$5:$AL$5,D$3,Monthly!$C$75:$AL$75) -> -42336
A12: Equity raised | B12: =SUMIF(Monthly!$C$5:$AL$5,B$3,Monthly!$C$76:$AL$76) -> 100000 | C12: =SUMIF(Monthly!$C$5:$AL$5,C$3,Monthly!$C$76:$AL$76) -> 0 | D12: =SUMIF(Monthly!$C$5:$AL$5,D$3,Monthly!$C$76:$AL$76) -> 0
A13: Loan drawdown | B13: =SUMIF(Monthly!$C$5:$AL$5,B$3,Monthly!$C$61:$AL$61) -> 250000 | C13: =SUMIF(Monthly!$C$5:$AL$5,C$3,Monthly!$C$61:$AL$61) -> 0 | D13: =SUMIF(Monthly!$C$5:$AL$5,D$3,Monthly!$C$61:$AL$61) -> 0
A14: Loan repayment | B14: =SUMIF(Monthly!$C$5:$AL$5,B$3,Monthly!$C$62:$AL$62) -> -45833.333 | C14: =SUMIF(Monthly!$C$5:$AL$5,C$3,Monthly!$C$62:$AL$62) -> -50000 | D14: =SUMIF(Monthly!$C$5:$AL$5,D$3,Monthly!$C$62:$AL$62) -> -50000
A15: Financing cash flow | B15: =SUMIF(Monthly!$C$5:$AL$5,B$3,Monthly!$C$77:$AL$77) -> 304166.67 | C15: =SUMIF(Monthly!$C$5:$AL$5,C$3,Monthly!$C$77:$AL$77) -> -50000 | D15: =SUMIF(Monthly!$C$5:$AL$5,D$3,Monthly!$C$77:$AL$77) -> -50000
A16: Net change in cash | B16: =SUMIF(Monthly!$C$5:$AL$5,B$3,Monthly!$C$78:$AL$78) -> 478877.47 | C16: =SUMIF(Monthly!$C$5:$AL$5,C$3,Monthly!$C$78:$AL$78) -> 188406.62 | D16: =SUMIF(Monthly!$C$5:$AL$5,D$3,Monthly!$C$78:$AL$78) -> 281536.07
A17: Opening cash | B17: =INDEX(Monthly!$C$79:$AL$79,(B$3-1)*12+1) -> 0 | C17: =INDEX(Monthly!$C$79:$AL$79,(C$3-1)*12+1) -> 478877.47 | D17: =INDEX(Monthly!$C$79:$AL$79,(D$3-1)*12+1) -> 667284.09
A18: Closing cash | B18: =INDEX(Monthly!$C$80:$AL$80,B$3*12) -> 478877.47 | C18: =INDEX(Monthly!$C$80:$AL$80,C$3*12) -> 667284.09 | D18: =INDEX(Monthly!$C$80:$AL$80,D$3*12) -> 948820.16

Sheet Balance Sheet
A1: Balance sheet at year end | F1: =HYPERLINK("#'Cover'!A1","◂ Contents") -> ◂ Contents
A2: Rolled up from the period detail (SUMIF on the year row; balances at year end).
A3: Year # | B3: 1 | C3: 2 | D3: 3
B4: Year 1 | C4: Year 2 | D4: Year 3
A5: Cash | B5: =INDEX(Monthly!$C$80:$AL$80,B$3*12) -> 478877.47 | C5: =INDEX(Monthly!$C$80:$AL$80,C$3*12) -> 667284.09 | D5: =INDEX(Monthly!$C$80:$AL$80,D$3*12) -> 948820.16
A6: Accounts receivable | B6: =INDEX(Monthly!$C$66:$AL$66,B$3*12) -> 44478.889 | C6: =INDEX(Monthly!$C$66:$AL$66,C$3*12) -> 52822.577 | D6: =INDEX(Monthly!$C$66:$AL$66,D$3*12) -> 62738.087
A7: Inventory | B7: =INDEX(Monthly!$C$67:$AL$67,B$3*12) -> 14208.472 | C7: =INDEX(Monthly!$C$67:$AL$67,C$3*12) -> 16545.38 | D7: =INDEX(Monthly!$C$67:$AL$67,D$3*12) -> 19275.29
A8: Net fixed assets | B8: =INDEX(Monthly!$C$57:$AL$57,B$3*12) -> 16000 | C8: =INDEX(Monthly!$C$57:$AL$57,C$3*12) -> 42240 | D8: =INDEX(Monthly!$C$57:$AL$57,D$3*12) -> 64548.8
A9: Total assets | B9: =INDEX(Monthly!$C$94:$AL$94,B$3*12) -> 553564.83 | C9: =INDEX(Monthly!$C$94:$AL$94,C$3*12) -> 778892.05 | D9: =INDEX(Monthly!$C$94:$AL$94,D$3*12) -> 1095382.3
A10: Accounts payable | B10: =INDEX(Monthly!$C$68:$AL$68,B$3*12) -> 56833.889 | C10: =INDEX(Monthly!$C$68:$AL$68,C$3*12) -> 66181.52 | D10: =INDEX(Monthly!$C$68:$AL$68,D$3*12) -> 77101.158
A11: Loan | B11: =INDEX(Monthly!$C$63:$AL$63,B$3*12) -> 204166.67 | C11: =INDEX(Monthly!$C$63:$AL$63,C$3*12) -> 154166.67 | D11: =INDEX(Monthly!$C$63:$AL$63,D$3*12) -> 104166.67
A12: Total liabilities | B12: =INDEX(Monthly!$C$95:$AL$95,B$3*12) -> 261000.56 | C12: =INDEX(Monthly!$C$95:$AL$95,C$3*12) -> 220348.19 | D12: =INDEX(Monthly!$C$95:$AL$95,D$3*12) -> 181267.82
A13: Paid-in capital | B13: =INDEX(Monthly!$C$92:$AL$92,B$3*12) -> 100000 | C13: =INDEX(Monthly!$C$92:$AL$92,C$3*12) -> 100000 | D13: =INDEX(Monthly!$C$92:$AL$92,D$3*12) -> 100000
A14: Retained earnings | B14: =INDEX(Monthly!$C$93:$AL$93,B$3*12) -> 192564.27 | C14: =INDEX(Monthly!$C$93:$AL$93,C$3*12) -> 458543.86 | D14: =INDEX(Monthly!$C$93:$AL$93,D$3*12) -> 814114.51
A15: Total equity | B15: =INDEX(Monthly!$C$96:$AL$96,B$3*12) -> 292564.27 | C15: =INDEX(Monthly!$C$96:$AL$96,C$3*12) -> 558543.86 | D15: =INDEX(Monthly!$C$96:$AL$96,D$3*12) -> 914114.51
A16: Total liabilities & equity | B16: =INDEX(Monthly!$C$97:$AL$97,B$3*12) -> 553564.83 | C16: =INDEX(Monthly!$C$97:$AL$97,C$3*12) -> 778892.05 | D16: =INDEX(Monthly!$C$97:$AL$97,D$3*12) -> 1095382.3
A17: Check: assets − liabilities − equity (must be 0) | B17: =INDEX(Monthly!$C$98:$AL$98,B$3*12) -> 0 | C17: =INDEX(Monthly!$C$98:$AL$98,C$3*12) -> 0 | D17: =INDEX(Monthly!$C$98:$AL$98,D$3*12) -> 0

Sheet Monthly
A1: Monthly projection | D1: =HYPERLINK("#'Cover'!A1","◂ Contents") -> ◂ Contents
A2: $ unless stated; costs shown as negatives. Every period uses the same formula.
A3: Month | C3: M1 | D3: M2 | E3: M3 | F3: M4 | G3: M5 | H3: M6 | I3: M7 | J3: M8 | K3: M9 | L3: M10 | M3: M11 | N3: M12 | O3: M13 | P3: M14 | Q3: M15 | R3: M16 | S3: M17 | T3: M18 | U3: M19 | V3: M20 | W3: M21 | X3: M22 | Y3: M23 | Z3: M24 | AA3: M25 | AB3: M26 | AC3: M27 | AD3: M28 | AE3: M29 | AF3: M30 | AG3: M31 | AH3: M32 | AI3: M33 | AJ3: M34 | AK3: M35 | AL3: M36
A4: Period # | C4: 1 | D4: 2 | E4: 3 | F4: 4 | G4: 5 | H4: 6 | I4: 7 | J4: 8 | K4: 9 | L4: 10 | M4: 11 | N4: 12 | O4: 13 | P4: 14 | Q4: 15 | R4: 16 | S4: 17 | T4: 18 | U4: 19 | V4: 20 | W4: 21 | X4: 22 | Y4: 23 | Z4: 24 | AA4: 25 | AB4: 26 | AC4: 27 | AD4: 28 | AE4: 29 | AF4: 30 | AG4: 31 | AH4: 32 | AI4: 33 | AJ4: 34 | AK4: 35 | AL4: 36
A5: Year # | C5: =ROUNDUP(C4*1/12,0) -> 1 | D5: =ROUNDUP(D4*1/12,0) -> 1 | E5: =ROUNDUP(E4*1/12,0) -> 1 | F5: =ROUNDUP(F4*1/12,0) -> 1 | G5: =ROUNDUP(G4*1/12,0) -> 1 | H5: =ROUNDUP(H4*1/12,0) -> 1 | I5: =ROUNDUP(I4*1/12,0) -> 1 | J5: =ROUNDUP(J4*1/12,0) -> 1 | ... AL5: =ROUNDUP(AL4*1/12,0) -> 3
A7: Jobs
A8: Field technicians (FTE) | C8: =Headcount!C8 -> 7 | D8: =Headcount!D8 -> 7 | E8: =Headcount!E8 -> 7 | F8: =Headcount!F8 -> 7 | G8: =Headcount!G8 -> 7 | H8: =Headcount!H8 -> 7 | I8: =Headcount!I8 -> 7 | J8: =Headcount!J8 -> 7 | ... AL8: =Headcount!AL8 -> 8.7808
A9: Job capacity (technicians × jobs per day × working days) | C9: =C8*Inputs!$E$7*Inputs!$E$8*1 -> 367.5 | D9: =D8*Inputs!$E$7*Inputs!$E$8*1 -> 367.5 | E9: =E8*Inputs!$E$7*Inputs!$E$8*1 -> 367.5 | F9: =F8*Inputs!$E$7*Inputs!$E$8*1 -> 367.5 | G9: =G8*Inputs!$E$7*Inputs!$E$8*1 -> 367.5 | H9: =H8*Inputs!$E$7*Inputs!$E$8*1 -> 367.5 | I9: =I8*Inputs!$E$7*Inputs!$E$8*1 -> 367.5 | J9: =J8*Inputs!$E$7*Inputs!$E$8*1 -> 367.5 | ... AL9: =AL8*Inputs!$E$7*Inputs!$E$8*1 -> 460.992
A10: Season factor (June–August busy season) | C10: =IF(AND(MOD(C$4-1,12)>=5,MOD(C$4-1,12)<=7),1+Inputs!$E$17,1-Inputs!$E$17/3) -> 0.91666667 | D10: =IF(AND(MOD(D$4-1,12)>=5,MOD(D$4-1,12)<=7),1+Inputs!$E$17,1-Inputs!$E$17/3) -> 0.91666667 | E10: =IF(AND(MOD(E$4-1,12)>=5,MOD(E$4-1,12)<=7),1+Inputs!$E$17,1-Inputs!$E$17/3) -> 0.91666667 | F10: =IF(AND(MOD(F$4-1,12)>=5,MOD(F$4-1,12)<=7),1+Inputs!$E$17,1-Inputs!$E$17/3) -> 0.91666667 | G10: =IF(AND(MOD(G$4-1,12)>=5,MOD(G$4-1,12)<=7),1+Inputs!$E$17,1-Inputs!$E$17/3) -> 0.91666667 | H10: =IF(AND(MOD(H$4-1,12)>=5,MOD(H$4-1,12)<=7),1+Inputs!$E$17,1-Inputs!$E$17/3) -> 1.25 | I10: =IF(AND(MOD(I$4-1,12)>=5,MOD(I$4-1,12)<=7),1+Inputs!$E$17,1-Inputs!$E$17/3) -> 1.25 | J10: =IF(AND(MOD(J$4-1,12)>=5,MOD(J$4-1,12)<=7),1+Inputs!$E$17,1-Inputs!$E$17/3) -> 1.25 | ... AL10: =IF(AND(MOD(AL$4-1,12)>=5,MOD(AL$4-1,12)<=7),1+Inputs!$E$17,1-Inputs!$E$17/3) -> 0.91666667
A11: Leads from marketing | C11: =-C34/MAX(1,Inputs!$E$13) -> 180 | D11: =-D34/MAX(1,Inputs!$E$13) -> 180 | E11: =-E34/MAX(1,Inputs!$E$13) -> 180 | F11: =-F34/MAX(1,Inputs!$E$13) -> 180 | G11: =-G34/MAX(1,Inputs!$E$13) -> 180 | H11: =-H34/MAX(1,Inputs!$E$13) -> 180 | I11: =-I34/MAX(1,Inputs!$E$13) -> 180 | J11: =-J34/MAX(1,Inputs!$E$13) -> 180 | ... AL11: =-AL34/MAX(1,Inputs!$E$13) -> 238.05
A12: Jobs booked from leads | C12: =C11*Inputs!$E$14*C10 -> 74.25 | D12: =D11*Inputs!$E$14*D10 -> 74.25 | E12: =E11*Inputs!$E$14*E10 -> 74.25 | F12: =F11*Inputs!$E$14*F10 -> 74.25 | G12: =G11*Inputs!$E$14*G10 -> 74.25 | H12: =H11*Inputs!$E$14*H10 -> 101.25 | I12: =I11*Inputs!$E$14*I10 -> 101.25 | J12: =J11*Inputs!$E$14*J10 -> 101.25 | ... AL12: =AL11*Inputs!$E$14*AL10 -> 98.195625
A13: Repeat & referral jobs | C13: =Inputs!$E$15*(1+Inputs!$E$16)^(C$5-1)*1*C10 -> 210.83333 | D13: =Inputs!$E$15*(1+Inputs!$E$16)^(D$5-1)*1*D10 -> 210.83333 | E13: =Inputs!$E$15*(1+Inputs!$E$16)^(E$5-1)*1*E10 -> 210.83333 | F13: =Inputs!$E$15*(1+Inputs!$E$16)^(F$5-1)*1*F10 -> 210.83333 | G13: =Inputs!$E$15*(1+Inputs!$E$16)^(G$5-1)*1*G10 -> 210.83333 | H13: =Inputs!$E$15*(1+Inputs!$E$16)^(H$5-1)*1*H10 -> 287.5 | I13: =Inputs!$E$15*(1+Inputs!$E$16)^(I$5-1)*1*I10 -> 287.5 | J13: =Inputs!$E$15*(1+Inputs!$E$16)^(J$5-1)*1*J10 -> 287.5 | ... AL13: =Inputs!$E$15*(1+Inputs!$E$16)^(AL$5-1)*1*AL10 -> 278.82708
A14: Jobs demanded | C14: =C12+C13 -> 285.08333 | D14: =D12+D13 -> 285.08333 | E14: =E12+E13 -> 285.08333 | F14: =F12+F13 -> 285.08333 | G14: =G12+G13 -> 285.08333 | H14: =H12+H13 -> 388.75 | I14: =I12+I13 -> 388.75 | J14: =J12+J13 -> 388.75 | ... AL14: =AL12+AL13 -> 377.02271
A15: Jobs completed (demand capped by capacity) | C15: =MIN(C9,C14) -> 285.08333 | D15: =MIN(D9,D14) -> 285.08333 | E15: =MIN(E9,E14) -> 285.08333 | F15: =MIN(F9,F14) -> 285.08333 | G15: =MIN(G9,G14) -> 285.08333 | H15: =MIN(H9,H14) -> 367.5 | I15: =MIN(I9,I14) -> 367.5 | J15: =MIN(J9,J14) -> 367.5 | ... AL15: =MIN(AL9,AL14) -> 377.02271
A17: Revenue
A18: Average revenue per job | C18: =Inputs!$E$20*(1+Inputs!$E$21)^(C$5-1) -> 440 | D18: =Inputs!$E$20*(1+Inputs!$E$21)^(D$5-1) -> 440 | E18: =Inputs!$E$20*(1+Inputs!$E$21)^(E$5-1) -> 440 | F18: =Inputs!$E$20*(1+Inputs!$E$21)^(F$5-1) -> 440 | G18: =Inputs!$E$20*(1+Inputs!$E$21)^(G$5-1) -> 440 | H18: =Inputs!$E$20*(1+Inputs!$E$21)^(H$5-1) -> 440 | I18: =Inputs!$E$20*(1+Inputs!$E$21)^(I$5-1) -> 440 | J18: =Inputs!$E$20*(1+Inputs!$E$21)^(J$5-1) -> 440 | ... AL18: =Inputs!$E$20*(1+Inputs!$E$21)^(AL$5-1) -> 466.796
A19: Job revenue | C19: =C15*C18 -> 125436.67 | D19: =D15*D18 -> 125436.67 | E19: =E15*E18 -> 125436.67 | F19: =F15*F18 -> 125436.67 | G19: =G15*G18 -> 125436.67 | H19: =H15*H18 -> 161700 | I19: =I15*I18 -> 161700 | J19: =J15*J18 -> 161700 | ... AL19: =AL15*AL18 -> 175992.69
A20: Maintenance plan members (average) | C20: =Inputs!$E$24*(1+Inputs!$E$25)^(C$5-1) -> 400 | D20: =Inputs!$E$24*(1+Inputs!$E$25)^(D$5-1) -> 400 | E20: =Inputs!$E$24*(1+Inputs!$E$25)^(E$5-1) -> 400 | F20: =Inputs!$E$24*(1+Inputs!$E$25)^(F$5-1) -> 400 | G20: =Inputs!$E$24*(1+Inputs!$E$25)^(G$5-1) -> 400 | H20: =Inputs!$E$24*(1+Inputs!$E$25)^(H$5-1) -> 400 | I20: =Inputs!$E$24*(1+Inputs!$E$25)^(I$5-1) -> 400 | J20: =Inputs!$E$24*(1+Inputs!$E$25)^(J$5-1) -> 400 | ... AL20: =Inputs!$E$24*(1+Inputs!$E$25)^(AL$5-1) -> 576
A21: Maintenance plan revenue | C21: =C20*Inputs!$E$26*(1+Inputs!$E$21)^(C$5-1)*1 -> 8000 | D21: =D20*Inputs!$E$26*(1+Inputs!$E$21)^(D$5-1)*1 -> 8000 | E21: =E20*Inputs!$E$26*(1+Inputs!$E$21)^(E$5-1)*1 -> 8000 | F21: =F20*Inputs!$E$26*(1+Inputs!$E$21)^(F$5-1)*1 -> 8000 | G21: =G20*Inputs!$E$26*(1+Inputs!$E$21)^(G$5-1)*1 -> 8000 | H21: =H20*Inputs!$E$26*(1+Inputs!$E$21)^(H$5-1)*1 -> 8000 | I21: =I20*Inputs!$E$26*(1+Inputs!$E$21)^(I$5-1)*1 -> 8000 | J21: =J20*Inputs!$E$26*(1+Inputs!$E$21)^(J$5-1)*1 -> 8000 | ... AL21: =AL20*Inputs!$E$26*(1+Inputs!$E$21)^(AL$5-1)*1 -> 12221.568
A22: Revenue | C22: =C19+C21 -> 133436.67 | D22: =D19+D21 -> 133436.67 | E22: =E19+E21 -> 133436.67 | F22: =F19+F21 -> 133436.67 | G22: =G19+G21 -> 133436.67 | H22: =H19+H21 -> 169700 | I22: =I19+I21 -> 169700 | J22: =J19+J21 -> 169700 | ... AL22: =AL19+AL21 -> 188214.26
A24: Cost of delivery
A25: Technician payroll | C25: =Headcount!C13 -> -41591.667 | D25: =Headcount!D13 -> -41591.667 | E25: =Headcount!E13 -> -41591.667 | F25: =Headcount!F13 -> -41591.667 | G25: =Headcount!G13 -> -41591.667 | H25: =Headcount!H13 -> -41591.667 | I25: =Headcount!I13 -> -41591.667 | J25: =Headcount!J13 -> -41591.667 | ... AL25: =Headcount!AL13 -> -55349.897
A26: Materials & parts | C26: =-C19*Inputs!$E$30 -> -31359.167 | D26: =-D19*Inputs!$E$30 -> -31359.167 | E26: =-E19*Inputs!$E$30 -> -31359.167 | F26: =-F19*Inputs!$E$30 -> -31359.167 | G26: =-G19*Inputs!$E$30 -> -31359.167 | H26: =-H19*Inputs!$E$30 -> -40425 | I26: =-I19*Inputs!$E$30 -> -40425 | J26: =-J19*Inputs!$E$30 -> -40425 | ... AL26: =-AL19*Inputs!$E$30 -> -43998.173
A27: Vehicles | C27: =-C8*Inputs!$E$31*1 -> -9100 | D27: =-D8*Inputs!$E$31*1 -> -9100 | E27: =-E8*Inputs!$E$31*1 -> -9100 | F27: =-F8*Inputs!$E$31*1 -> -9100 | G27: =-G8*Inputs!$E$31*1 -> -9100 | H27: =-H8*Inputs!$E$31*1 -> -9100 | I27: =-I8*Inputs!$E$31*1 -> -9100 | J27: =-J8*Inputs!$E$31*1 -> -9100 | ... AL27: =-AL8*Inputs!$E$31*1 -> -11415.04
A28: Plan visits | C28: =-C21*Inputs!$E$27 -> -3200 | D28: =-D21*Inputs!$E$27 -> -3200 | E28: =-E21*Inputs!$E$27 -> -3200 | F28: =-F21*Inputs!$E$27 -> -3200 | G28: =-G21*Inputs!$E$27 -> -3200 | H28: =-H21*Inputs!$E$27 -> -3200 | I28: =-I21*Inputs!$E$27 -> -3200 | J28: =-J21*Inputs!$E$27 -> -3200 | ... AL28: =-AL21*Inputs!$E$27 -> -4888.6272
A29: Cost of delivery | C29: =C25+C26+C27+C28 -> -85250.833 | D29: =D25+D26+D27+D28 -> -85250.833 | E29: =E25+E26+E27+E28 -> -85250.833 | F29: =F25+F26+F27+F28 -> -85250.833 | G29: =G25+G26+G27+G28 -> -85250.833 | H29: =H25+H26+H27+H28 -> -94316.667 | I29: =I25+I26+I27+I28 -> -94316.667 | J29: =J25+J26+J27+J28 -> -94316.667 | ... AL29: =AL25+AL26+AL27+AL28 -> -115651.74
A30: Gross profit | C30: =C22+C29 -> 48185.833 | D30: =D22+D29 -> 48185.833 | E30: =E22+E29 -> 48185.833 | F30: =F22+F29 -> 48185.833 | G30: =G22+G29 -> 48185.833 | H30: =H22+H29 -> 75383.333 | I30: =I22+I29 -> 75383.333 | J30: =J22+J29 -> 75383.333 | ... AL30: =AL22+AL29 -> 72562.523
A32: Operating expenses
A33: Dispatch, office & other payroll | C33: =Headcount!C15-Headcount!C13 -> -8625 | D33: =Headcount!D15-Headcount!D13 -> -8625 | E33: =Headcount!E15-Headcount!E13 -> -8625 | F33: =Headcount!F15-Headcount!F13 -> -8625 | G33: =Headcount!G15-Headcount!G13 -> -8625 | H33: =Headcount!H15-Headcount!H13 -> -8625 | I33: =Headcount!I15-Headcount!I13 -> -8625 | J33: =Headcount!J15-Headcount!J13 -> -8625 | ... AL33: =Headcount!AL15-Headcount!AL13 -> -11071.818
A34: Marketing | C34: =-Inputs!$E$11*(1+Inputs!$E$12)^(C$5-1)*1 -> -9000 | D34: =-Inputs!$E$11*(1+Inputs!$E$12)^(D$5-1)*1 -> -9000 | E34: =-Inputs!$E$11*(1+Inputs!$E$12)^(E$5-1)*1 -> -9000 | F34: =-Inputs!$E$11*(1+Inputs!$E$12)^(F$5-1)*1 -> -9000 | G34: =-Inputs!$E$11*(1+Inputs!$E$12)^(G$5-1)*1 -> -9000 | H34: =-Inputs!$E$11*(1+Inputs!$E$12)^(H$5-1)*1 -> -9000 | I34: =-Inputs!$E$11*(1+Inputs!$E$12)^(I$5-1)*1 -> -9000 | J34: =-Inputs!$E$11*(1+Inputs!$E$12)^(J$5-1)*1 -> -9000 | ... AL34: =-Inputs!$E$11*(1+Inputs!$E$12)^(AL$5-1)*1 -> -11902.5
A35: Field software & phones | C35: =-C8*Inputs!$E$32*1 -> -840 | D35: =-D8*Inputs!$E$32*1 -> -840 | E35: =-E8*Inputs!$E$32*1 -> -840 | F35: =-F8*Inputs!$E$32*1 -> -840 | G35: =-G8*Inputs!$E$32*1 -> -840 | H35: =-H8*Inputs!$E$32*1 -> -840 | I35: =-I8*Inputs!$E$32*1 -> -840 | J35: =-J8*Inputs!$E$32*1 -> -840 | ... AL35: =-AL8*Inputs!$E$32*1 -> -1053.696
A36: Insurance & licences | C36: =-Inputs!$E$33*1 -> -3500 | D36: =-Inputs!$E$33*1 -> -3500 | E36: =-Inputs!$E$33*1 -> -3500 | F36: =-Inputs!$E$33*1 -> -3500 | G36: =-Inputs!$E$33*1 -> -3500 | H36: =-Inputs!$E$33*1 -> -3500 | I36: =-Inputs!$E$33*1 -> -3500 | J36: =-Inputs!$E$33*1 -> -3500 | ... AL36: =-Inputs!$E$33*1 -> -3500
A37: Shop / office rent | C37: =-Inputs!$E$34*1 -> -4500 | D37: =-Inputs!$E$34*1 -> -4500 | E37: =-Inputs!$E$34*1 -> -4500 | F37: =-Inputs!$E$34*1 -> -4500 | G37: =-Inputs!$E$34*1 -> -4500 | H37: =-Inputs!$E$34*1 -> -4500 | I37: =-Inputs!$E$34*1 -> -4500 | J37: =-Inputs!$E$34*1 -> -4500 | ... AL37: =-Inputs!$E$34*1 -> -4500
A38: Other G&A | C38: =-Inputs!$E$35*1 -> -2500 | D38: =-Inputs!$E$35*1 -> -2500 | E38: =-Inputs!$E$35*1 -> -2500 | F38: =-Inputs!$E$35*1 -> -2500 | G38: =-Inputs!$E$35*1 -> -2500 | H38: =-Inputs!$E$35*1 -> -2500 | I38: =-Inputs!$E$35*1 -> -2500 | J38: =-Inputs!$E$35*1 -> -2500 | ... AL38: =-Inputs!$E$35*1 -> -2500
A39: Card processing fees | C39: =-C22*Inputs!$E$36 -> -3602.79 | D39: =-D22*Inputs!$E$36 -> -3602.79 | E39: =-E22*Inputs!$E$36 -> -3602.79 | F39: =-F22*Inputs!$E$36 -> -3602.79 | G39: =-G22*Inputs!$E$36 -> -3602.79 | H39: =-H22*Inputs!$E$36 -> -4581.9 | I39: =-I22*Inputs!$E$36 -> -4581.9 | J39: =-J22*Inputs!$E$36 -> -4581.9 | ... AL39: =-AL22*Inputs!$E$36 -> -5081.785
A40: Total operating expenses | C40: =C33+C34+C35+C36+C37+C38+C39 -> -32567.79 | D40: =D33+D34+D35+D36+D37+D38+D39 -> -32567.79 | E40: =E33+E34+E35+E36+E37+E38+E39 -> -32567.79 | F40: =F33+F34+F35+F36+F37+F38+F39 -> -32567.79 | G40: =G33+G34+G35+G36+G37+G38+G39 -> -32567.79 | H40: =H33+H34+H35+H36+H37+H38+H39 -> -33546.9 | I40: =I33+I34+I35+I36+I37+I38+I39 -> -33546.9 | J40: =J33+J34+J35+J36+J37+J38+J39 -> -33546.9 | ... AL40: =AL33+AL34+AL35+AL36+AL37+AL38+AL39 -> -39609.799
A41: EBITDA | C41: =C30+C40 -> 15618.043 | D41: =D30+D40 -> 15618.043 | E41: =E30+E40 -> 15618.043 | F41: =F30+F40 -> 15618.043 | G41: =G30+G40 -> 15618.043 | H41: =H30+H40 -> 41836.433 | I41: =I30+I40 -> 41836.433 | J41: =J30+J40 -> 41836.433 | ... AL41: =AL30+AL40 -> 32952.724
A43: Profit after depreciation, interest, tax
A44: EBIT | C44: =C41+C55 -> 15284.71 | D44: =D41+D55 -> 15284.71 | E44: =E41+E55 -> 15284.71 | F44: =F41+F55 -> 15284.71 | G44: =G41+G55 -> 15284.71 | H44: =H41+H55 -> 41503.1 | I44: =I41+I55 -> 41503.1 | J44: =J41+J55 -> 41503.1 | ... AL44: =AL41+AL55 -> 31283.791
A45: Interest on loan (average balance after drawdown) | C45: =-(C60+C61+C63)/2*Inputs!$E$56/12 -> -1666.6667 | D45: =-(D60+D61+D63)/2*Inputs!$E$56/12 -> -1652.7778 | E45: =-(E60+E61+E63)/2*Inputs!$E$56/12 -> -1625 | F45: =-(F60+F61+F63)/2*Inputs!$E$56/12 -> -1597.2222 | G45: =-(G60+G61+G63)/2*Inputs!$E$56/12 -> -1569.4444 | H45: =-(H60+H61+H63)/2*Inputs!$E$56/12 -> -1541.6667 | I45: =-(I60+I61+I63)/2*Inputs!$E$56/12 -> -1513.8889 | J45: =-(J60+J61+J63)/2*Inputs!$E$56/12 -> -1486.1111 | ... AL45: =-(AL60+AL61+AL63)/2*Inputs!$E$56/12 -> -708.33333
A46: Pre-tax income | C46: =C44+C45 -> 13618.043 | D46: =D44+D45 -> 13631.932 | E46: =E44+E45 -> 13659.71 | F46: =F44+F45 -> 13687.488 | G46: =G44+G45 -> 13715.266 | H46: =H44+H45 -> 39961.433 | I46: =I44+I45 -> 39989.211 | J46: =J44+J45 -> 40016.989 | ... AL46: =AL44+AL45 -> 30575.457
A47: Helper: cumulative pre-tax income | C47: =C46 -> 13618.043 | D47: =C47+D46 -> 27249.976 | E47: =D47+E46 -> 40909.686 | F47: =E47+F46 -> 54597.173 | G47: =F47+G46 -> 68312.439 | H47: =G47+H46 -> 108273.87 | I47: =H47+I46 -> 148263.08 | J47: =I47+J46 -> 188280.07 | K47: =J47+K46 -> 202106.45 | ... AL47: =AK47+AL46 -> 1030524.7
A48: Helper: cumulative taxable income (losses carried forward) | C48: =MAX(0,C47) -> 13618.043 | D48: =MAX(C48,D47) -> 27249.976 | E48: =MAX(D48,E47) -> 40909.686 | F48: =MAX(E48,F47) -> 54597.173 | G48: =MAX(F48,G47) -> 68312.439 | H48: =MAX(G48,H47) -> 108273.87 | I48: =MAX(H48,I47) -> 148263.08 | J48: =MAX(I48,J47) -> 188280.07 | K48: =MAX(J48,K47) -> 202106.45 | ... AL48: =MAX(AK48,AL47) -> 1030524.7
A49: Income tax | C49: =-C48*Inputs!$E$66 -> -2859.7891 | D49: =-(D48-C48)*Inputs!$E$66 -> -2862.7058 | E49: =-(E48-D48)*Inputs!$E$66 -> -2868.5391 | F49: =-(F48-E48)*Inputs!$E$66 -> -2874.3724 | G49: =-(G48-F48)*Inputs!$E$66 -> -2880.2058 | H49: =-(H48-G48)*Inputs!$E$66 -> -8391.901 | I49: =-(I48-H48)*Inputs!$E$66 -> -8397.7343 | J49: =-(J48-I48)*Inputs!$E$66 -> -8403.5677 | K49: =-(K48-J48)*Inputs!$E$66 -> -2903.5391 | ... AL49: =-(AL48-AK48)*Inputs!$E$66 -> -6420.8461
A50: Net income | C50: =C46+C49 -> 10758.254 | D50: =D46+D49 -> 10769.226 | E50: =E46+E49 -> 10791.171 | F50: =F46+F49 -> 10813.115 | G50: =G46+G49 -> 10835.06 | H50: =H46+H49 -> 31569.532 | I50: =I46+I49 -> 31591.477 | J50: =J46+J49 -> 31613.421 | ... AL50: =AL46+AL49 -> 24154.611
A52: Fixed assets & capital spending
A53: Capital spending (start-up + van & tools per technician added) | C53: =Inputs!$E$37+MAX(0,C8-Inputs!$E$39)*Inputs!$E$38 -> 20000 | D53: =MAX(0,D8-C8)*Inputs!$E$38 -> 0 | E53: =MAX(0,E8-D8)*Inputs!$E$38 -> 0 | F53: =MAX(0,F8-E8)*Inputs!$E$38 -> 0 | G53: =MAX(0,G8-F8)*Inputs!$E$38 -> 0 | H53: =MAX(0,H8-G8)*Inputs!$E$38 -> 0 | I53: =MAX(0,I8-H8)*Inputs!$E$38 -> 0 | J53: =MAX(0,J8-I8)*Inputs!$E$38 -> 0 | K53: =MAX(0,K8-J8)*Inputs!$E$38 -> 0 | ... AL53: =MAX(0,AL8-AK8)*Inputs!$E$38 -> 0
A54: Fixed assets at cost | C54: =C53 -> 20000 | D54: =C54+D53 -> 20000 | E54: =D54+E53 -> 20000 | F54: =E54+F53 -> 20000 | G54: =F54+G53 -> 20000 | H54: =G54+H53 -> 20000 | I54: =H54+I53 -> 20000 | J54: =I54+J53 -> 20000 | K54: =J54+K53 -> 20000 | ... AL54: =AK54+AL53 -> 100136
A55: Depreciation | C55: =-MIN(C54/MAX(1,Inputs!$E$65*12),C53) -> -333.33333 | D55: =-MIN(D54/MAX(1,Inputs!$E$65*12),C57+D53) -> -333.33333 | E55: =-MIN(E54/MAX(1,Inputs!$E$65*12),D57+E53) -> -333.33333 | F55: =-MIN(F54/MAX(1,Inputs!$E$65*12),E57+F53) -> -333.33333 | G55: =-MIN(G54/MAX(1,Inputs!$E$65*12),F57+G53) -> -333.33333 | H55: =-MIN(H54/MAX(1,Inputs!$E$65*12),G57+H53) -> -333.33333 | I55: =-MIN(I54/MAX(1,Inputs!$E$65*12),H57+I53) -> -333.33333 | J55: =-MIN(J54/MAX(1,Inputs!$E$65*12),I57+J53) -> -333.33333 | K55: =-MIN(K54/MAX(1,Inputs!$E$65*12),J57+K53) -> -333.33333 | ... AL55: =-MIN(AL54/MAX(1,Inputs!$E$65*12),AK57+AL53) -> -1668.9333
A56: Accumulated depreciation | C56: =C55 -> -333.33333 | D56: =C56+D55 -> -666.66667 | E56: =D56+E55 -> -1000 | F56: =E56+F55 -> -1333.3333 | G56: =F56+G55 -> -1666.6667 | H56: =G56+H55 -> -2000 | I56: =H56+I55 -> -2333.3333 | J56: =I56+J55 -> -2666.6667 | K56: =J56+K55 -> -3000 | ... AL56: =AK56+AL55 -> -35587.2
A57: Net fixed assets | C57: =C54+C56 -> 19666.667 | D57: =D54+D56 -> 19333.333 | E57: =E54+E56 -> 19000 | F57: =F54+F56 -> 18666.667 | G57: =G54+G56 -> 18333.333 | H57: =H54+H56 -> 18000 | I57: =I54+I56 -> 17666.667 | J57: =J54+J56 -> 17333.333 | ... AL57: =AL54+AL56 -> 64548.8
A59: Debt
A60: Loan — opening balance | C60: =0 -> 0 | D60: =C63 -> 250000 | E60: =D63 -> 245833.33 | F60: =E63 -> 241666.67 | G60: =F63 -> 237500 | H60: =G63 -> 233333.33 | I60: =H63 -> 229166.67 | J60: =I63 -> 225000 | K60: =J63 -> 220833.33 | ... AL60: =AK63 -> 108333.33
A61: Loan drawdown | C61: =IF(C$4=1,Inputs!$E$55,0) -> 250000 | D61: =IF(D$4=1,Inputs!$E$55,0) -> 0 | E61: =IF(E$4=1,Inputs!$E$55,0) -> 0 | F61: =IF(F$4=1,Inputs!$E$55,0) -> 0 | G61: =IF(G$4=1,Inputs!$E$55,0) -> 0 | H61: =IF(H$4=1,Inputs!$E$55,0) -> 0 | I61: =IF(I$4=1,Inputs!$E$55,0) -> 0 | J61: =IF(J$4=1,Inputs!$E$55,0) -> 0 | ... AL61: =IF(AL$4=1,Inputs!$E$55,0) -> 0
A62: Loan repayment | C62: =-MIN(C60,Inputs!$E$55/MAX(1,Inputs!$E$57*12)) -> 0 | D62: =-MIN(D60,Inputs!$E$55/MAX(1,Inputs!$E$57*12)) -> -4166.6667 | E62: =-MIN(E60,Inputs!$E$55/MAX(1,Inputs!$E$57*12)) -> -4166.6667 | F62: =-MIN(F60,Inputs!$E$55/MAX(1,Inputs!$E$57*12)) -> -4166.6667 | G62: =-MIN(G60,Inputs!$E$55/MAX(1,Inputs!$E$57*12)) -> -4166.6667 | H62: =-MIN(H60,Inputs!$E$55/MAX(1,Inputs!$E$57*12)) -> -4166.6667 | I62: =-MIN(I60,Inputs!$E$55/MAX(1,Inputs!$E$57*12)) -> -4166.6667 | J62: =-MIN(J60,Inputs!$E$55/MAX(1,Inputs!$E$57*12)) -> -4166.6667 | ... AL62: =-MIN(AL60,Inputs!$E$55/MAX(1,Inputs!$E$57*12)) -> -4166.6667
A63: Loan — closing balance | C63: =C60+C61+C62 -> 250000 | D63: =D60+D61+D62 -> 245833.33 | E63: =E60+E61+E62 -> 241666.67 | F63: =F60+F61+F62 -> 237500 | G63: =G60+G61+G62 -> 233333.33 | H63: =H60+H61+H62 -> 229166.67 | I63: =I60+I61+I62 -> 225000 | J63: =J60+J61+J62 -> 220833.33 | ... AL63: =AL60+AL61+AL62 -> 104166.67
A65: Working capital
A66: Accounts receivable | C66: =C22*Inputs!$E$60/30 -> 44478.889 | D66: =D22*Inputs!$E$60/30 -> 44478.889 | E66: =E22*Inputs!$E$60/30 -> 44478.889 | F66: =F22*Inputs!$E$60/30 -> 44478.889 | G66: =G22*Inputs!$E$60/30 -> 44478.889 | H66: =H22*Inputs!$E$60/30 -> 56566.667 | I66: =I22*Inputs!$E$60/30 -> 56566.667 | J66: =J22*Inputs!$E$60/30 -> 56566.667 | ... AL66: =AL22*Inputs!$E$60/30 -> 62738.087
A67: Inventory | C67: =-C29*Inputs!$E$61/30 -> 14208.472 | D67: =-D29*Inputs!$E$61/30 -> 14208.472 | E67: =-E29*Inputs!$E$61/30 -> 14208.472 | F67: =-F29*Inputs!$E$61/30 -> 14208.472 | G67: =-G29*Inputs!$E$61/30 -> 14208.472 | H67: =-H29*Inputs!$E$61/30 -> 15719.444 | I67: =-I29*Inputs!$E$61/30 -> 15719.444 | J67: =-J29*Inputs!$E$61/30 -> 15719.444 | ... AL67: =-AL29*Inputs!$E$61/30 -> 19275.29
A68: Accounts payable | C68: =-C29*Inputs!$E$62/30 -> 56833.889 | D68: =-D29*Inputs!$E$62/30 -> 56833.889 | E68: =-E29*Inputs!$E$62/30 -> 56833.889 | F68: =-F29*Inputs!$E$62/30 -> 56833.889 | G68: =-G29*Inputs!$E$62/30 -> 56833.889 | H68: =-H29*Inputs!$E$62/30 -> 62877.778 | I68: =-I29*Inputs!$E$62/30 -> 62877.778 | J68: =-J29*Inputs!$E$62/30 -> 62877.778 | ... AL68: =-AL29*Inputs!$E$62/30 -> 77101.158
A69: (Increase) / decrease in receivables | C69: =-C66 -> -44478.889 | D69: =C66-D66 -> 0 | E69: =D66-E66 -> 0 | F69: =E66-F66 -> 0 | G69: =F66-G66 -> 0 | H69: =G66-H66 -> -12087.778 | I69: =H66-I66 -> 0 | J69: =I66-J66 -> 0 | K69: =J66-K66 -> 12087.778 | ... AL69: =AK66-AL66 -> 0
A70: (Increase) / decrease in inventory | C70: =-C67 -> -14208.472 | D70: =C67-D67 -> 0 | E70: =D67-E67 -> 0 | F70: =E67-F67 -> 0 | G70: =F67-G67 -> 0 | H70: =G67-H67 -> -1510.9722 | I70: =H67-I67 -> 0 | J70: =I67-J67 -> 0 | K70: =J67-K67 -> 1510.9722 | ... AL70: =AK67-AL67 -> 0
A71: Increase / (decrease) in payables | C71: =C68 -> 56833.889 | D71: =D68-C68 -> 0 | E71: =E68-D68 -> 0 | F71: =F68-E68 -> 0 | G71: =G68-F68 -> 0 | H71: =H68-G68 -> 6043.8889 | I71: =I68-H68 -> 0 | J71: =J68-I68 -> 0 | K71: =K68-J68 -> -6043.8889 | ... AL71: =AL68-AK68 -> 0
A73: Cash flow
A74: Operating cash flow | C74: =C50-C55+C69+C70+C71 -> 9238.1153 | D74: =D50-D55+D69+D70+D71 -> 11102.56 | E74: =E50-E55+E69+E70+E71 -> 11124.504 | F74: =F50-F55+F69+F70+F71 -> 11146.449 | G74: =G50-G55+G69+G70+G71 -> 11168.393 | H74: =H50-H55+H69+H70+H71 -> 24348.005 | I74: =I50-I55+I69+I70+I71 -> 31924.81 | J74: =J50-J55+J69+J70+J71 -> 31946.755 | ... AL74: =AL50-AL55+AL69+AL70+AL71 -> 25823.545
A75: Investing cash flow (capex) | C75: =-C53 -> -20000 | D75: =-D53 -> 0 | E75: =-E53 -> 0 | F75: =-F53 -> 0 | G75: =-G53 -> 0 | H75: =-H53 -> 0 | I75: =-I53 -> 0 | J75: =-J53 -> 0 | ... AL75: =-AL53 -> 0
A76: Equity raised | C76: =IF(C$4=1,Inputs!$E$54,0) -> 100000 | D76: =IF(D$4=1,Inputs!$E$54,0) -> 0 | E76: =IF(E$4=1,Inputs!$E$54,0) -> 0 | F76: =IF(F$4=1,Inputs!$E$54,0) -> 0 | G76: =IF(G$4=1,Inputs!$E$54,0) -> 0 | H76: =IF(H$4=1,Inputs!$E$54,0) -> 0 | I76: =IF(I$4=1,Inputs!$E$54,0) -> 0 | J76: =IF(J$4=1,Inputs!$E$54,0) -> 0 | ... AL76: =IF(AL$4=1,Inputs!$E$54,0) -> 0
A77: Financing cash flow | C77: =C76+C61+C62 -> 350000 | D77: =D76+D61+D62 -> -4166.6667 | E77: =E76+E61+E62 -> -4166.6667 | F77: =F76+F61+F62 -> -4166.6667 | G77: =G76+G61+G62 -> -4166.6667 | H77: =H76+H61+H62 -> -4166.6667 | I77: =I76+I61+I62 -> -4166.6667 | J77: =J76+J61+J62 -> -4166.6667 | ... AL77: =AL76+AL61+AL62 -> -4166.6667
A78: Net cash flow | C78: =C74+C75+C77 -> 339238.12 | D78: =D74+D75+D77 -> 6935.8931 | E78: =E74+E75+E77 -> 6957.8376 | F78: =F74+F75+F77 -> 6979.782 | G78: =G74+G75+G77 -> 7001.7265 | H78: =H74+H75+H77 -> 20181.338 | I78: =I74+I75+I77 -> 27758.143 | J78: =J74+J75+J77 -> 27780.088 | ... AL78: =AL74+AL75+AL77 -> 21656.878
A79: Opening cash | C79: =0 -> 0 | D79: =C80 -> 339238.12 | E79: =D80 -> 346174.01 | F79: =E80 -> 353131.85 | G79: =F80 -> 360111.63 | H79: =G80 -> 367113.35 | I79: =H80 -> 387294.69 | J79: =I80 -> 415052.84 | K79: =J80 -> 442832.92 | ... AL79: =AK80 -> 927163.28
A80: Closing cash | C80: =C79+C78 -> 339238.12 | D80: =D79+D78 -> 346174.01 | E80: =E79+E78 -> 353131.85 | F80: =F79+F78 -> 360111.63 | G80: =G79+G78 -> 367113.35 | H80: =H79+H78 -> 387294.69 | I80: =I79+I78 -> 415052.84 | J80: =J79+J78 -> 442832.92 | ... AL80: =AL79+AL78 -> 948820.16
A81: Helper: EBITDA positive (1/0) | C81: =IF(C41>0,1,0) -> 1 | D81: =IF(D41>0,1,0) -> 1 | E81: =IF(E41>0,1,0) -> 1 | F81: =IF(F41>0,1,0) -> 1 | G81: =IF(G41>0,1,0) -> 1 | H81: =IF(H41>0,1,0) -> 1 | I81: =IF(I41>0,1,0) -> 1 | J81: =IF(J41>0,1,0) -> 1 | ... AL81: =IF(AL41>0,1,0) -> 1
A83: Goal modules
A84: Helper: net income positive (1/0) | C84: =IF(C50>0,1,0) -> 1 | D84: =IF(D50>0,1,0) -> 1 | E84: =IF(E50>0,1,0) -> 1 | F84: =IF(F50>0,1,0) -> 1 | G84: =IF(G50>0,1,0) -> 1 | H84: =IF(H50>0,1,0) -> 1 | I84: =IF(I50>0,1,0) -> 1 | J84: =IF(J50>0,1,0) -> 1 | ... AL84: =IF(AL50>0,1,0) -> 1
A85: Cash flow before financing (operating + investing) | C85: =C74+C75 -> -10761.885 | D85: =D74+D75 -> 11102.56 | E85: =E74+E75 -> 11124.504 | F85: =F74+F75 -> 11146.449 | G85: =G74+G75 -> 11168.393 | H85: =H74+H75 -> 24348.005 | I85: =I74+I75 -> 31924.81 | J85: =J74+J75 -> 31946.755 | ... AL85: =AL74+AL75 -> 25823.545
A86: Cumulative cash flow before financing | C86: =C85 -> -10761.885 | D86: =C86+D85 -> 340.67513 | E86: =D86+E85 -> 11465.179 | F86: =E86+F85 -> 22611.628 | G86: =F86+G85 -> 33780.021 | H86: =G86+H85 -> 58128.026 | I86: =H86+I85 -> 90052.836 | J86: =I86+J85 -> 121999.59 | K86: =J86+K85 -> 140810.62 | ... AL86: =AK86+AL85 -> 744653.49
A87: Helper: lowest cumulative cash flow so far | C87: =C86 -> -10761.885 | D87: =MIN(C87,D86) -> -10761.885 | E87: =MIN(D87,E86) -> -10761.885 | F87: =MIN(E87,F86) -> -10761.885 | G87: =MIN(F87,G86) -> -10761.885 | H87: =MIN(G87,H86) -> -10761.885 | I87: =MIN(H87,I86) -> -10761.885 | J87: =MIN(I87,J86) -> -10761.885 | K87: =MIN(J87,K86) -> -10761.885 | ... AL87: =MIN(AK87,AL86) -> -10761.885
A88: Helper: investment paid back (1/0) | C88: =IF(AND(C86>=0,C87<0),1,0) -> 0 | D88: =IF(AND(D86>=0,D87<0),1,0) -> 1 | E88: =IF(AND(E86>=0,E87<0),1,0) -> 1 | F88: =IF(AND(F86>=0,F87<0),1,0) -> 1 | G88: =IF(AND(G86>=0,G87<0),1,0) -> 1 | H88: =IF(AND(H86>=0,H87<0),1,0) -> 1 | I88: =IF(AND(I86>=0,I87<0),1,0) -> 1 | J88: =IF(AND(J86>=0,J87<0),1,0) -> 1 | ... AL88: =IF(AND(AL86>=0,AL87<0),1,0) -> 1
A89: Unlevered free cash flow (operating + after-tax interest − capex) | C89: =C74-C45*(1-Inputs!$E$66)+C75 -> -9445.218 | D89: =D74-D45*(1-Inputs!$E$66)+D75 -> 12408.254 | E89: =E74-E45*(1-Inputs!$E$66)+E75 -> 12408.254 | F89: =F74-F45*(1-Inputs!$E$66)+F75 -> 12408.254 | G89: =G74-G45*(1-Inputs!$E$66)+G75 -> 12408.254 | H89: =H74-H45*(1-Inputs!$E$66)+H75 -> 25565.921 | I89: =I74-I45*(1-Inputs!$E$66)+I75 -> 33120.782 | J89: =J74-J45*(1-Inputs!$E$66)+J75 -> 33120.782 | ... AL89: =AL74-AL45*(1-Inputs!$E$66)+AL75 -> 26383.128
A91: Balance sheet
A92: Paid-in capital | C92: =C76 -> 100000 | D92: =C92+D76 -> 100000 | E92: =D92+E76 -> 100000 | F92: =E92+F76 -> 100000 | G92: =F92+G76 -> 100000 | H92: =G92+H76 -> 100000 | I92: =H92+I76 -> 100000 | J92: =I92+J76 -> 100000 | K92: =J92+K76 -> 100000 | ... AL92: =AK92+AL76 -> 100000
A93: Retained earnings | C93: =C50 -> 10758.254 | D93: =C93+D50 -> 21527.481 | E93: =D93+E50 -> 32318.652 | F93: =E93+F50 -> 43131.767 | G93: =F93+G50 -> 53966.827 | H93: =G93+H50 -> 85536.359 | I93: =H93+I50 -> 117127.84 | J93: =I93+J50 -> 148741.26 | K93: =J93+K50 -> 159664.09 | ... AL93: =AK93+AL50 -> 814114.51
A94: Total assets | C94: =C80+C66+C67+C57 -> 417592.14 | D94: =D80+D66+D67+D57 -> 424194.7 | E94: =E80+E66+E67+E57 -> 430819.21 | F94: =F80+F66+F67+F57 -> 437465.66 | G94: =G80+G66+G67+G57 -> 444134.05 | H94: =H80+H66+H67+H57 -> 477580.8 | I94: =I80+I66+I67+I57 -> 505005.61 | J94: =J80+J66+J67+J57 -> 532452.37 | ... AL94: =AL80+AL66+AL67+AL57 -> 1095382.3
A95: Total liabilities | C95: =C68+C63 -> 306833.89 | D95: =D68+D63 -> 302667.22 | E95: =E68+E63 -> 298500.56 | F95: =F68+F63 -> 294333.89 | G95: =G68+G63 -> 290167.22 | H95: =H68+H63 -> 292044.44 | I95: =I68+I63 -> 287877.78 | J95: =J68+J63 -> 283711.11 | ... AL95: =AL68+AL63 -> 181267.82
A96: Total equity | C96: =C92+C93 -> 110758.25 | D96: =D92+D93 -> 121527.48 | E96: =E92+E93 -> 132318.65 | F96: =F92+F93 -> 143131.77 | G96: =G92+G93 -> 153966.83 | H96: =H92+H93 -> 185536.36 | I96: =I92+I93 -> 217127.84 | J96: =J92+J93 -> 248741.26 | ... AL96: =AL92+AL93 -> 914114.51
A97: Total liabilities & equity | C97: =C95+C96 -> 417592.14 | D97: =D95+D96 -> 424194.7 | E97: =E95+E96 -> 430819.21 | F97: =F95+F96 -> 437465.66 | G97: =G95+G96 -> 444134.05 | H97: =H95+H96 -> 477580.8 | I97: =I95+I96 -> 505005.61 | J97: =J95+J96 -> 532452.37 | ... AL97: =AL95+AL96 -> 1095382.3
A98: Check: assets − liabilities − equity | C98: =C94-C97 -> 0 | D98: =D94-D97 -> 0 | E98: =E94-E97 -> 0 | F98: =F94-F97 -> 0 | G98: =G94-G97 -> 0 | H98: =H94-H97 -> 0 | I98: =I94-I97 -> 0 | J98: =J94-J97 -> 0 | ... AL98: =AL94-AL97 -> 0

Sheet Headcount
A1: Headcount & payroll | D1: =HYPERLINK("#'Cover'!A1","◂ Contents") -> ◂ Contents
A2: $ unless stated; costs shown as negatives. Every period uses the same formula.
A3: Month | C3: M1 | D3: M2 | E3: M3 | F3: M4 | G3: M5 | H3: M6 | I3: M7 | J3: M8 | K3: M9 | L3: M10 | M3: M11 | N3: M12 | O3: M13 | P3: M14 | Q3: M15 | R3: M16 | S3: M17 | T3: M18 | U3: M19 | V3: M20 | W3: M21 | X3: M22 | Y3: M23 | Z3: M24 | AA3: M25 | AB3: M26 | AC3: M27 | AD3: M28 | AE3: M29 | AF3: M30 | AG3: M31 | AH3: M32 | AI3: M33 | AJ3: M34 | AK3: M35 | AL3: M36
A4: Period # | C4: 1 | D4: 2 | E4: 3 | F4: 4 | G4: 5 | H4: 6 | I4: 7 | J4: 8 | K4: 9 | L4: 10 | M4: 11 | N4: 12 | O4: 13 | P4: 14 | Q4: 15 | R4: 16 | S4: 17 | T4: 18 | U4: 19 | V4: 20 | W4: 21 | X4: 22 | Y4: 23 | Z4: 24 | AA4: 25 | AB4: 26 | AC4: 27 | AD4: 28 | AE4: 29 | AF4: 30 | AG4: 31 | AH4: 32 | AI4: 33 | AJ4: 34 | AK4: 35 | AL4: 36
A5: Year # | C5: =ROUNDUP(C4*1/12,0) -> 1 | D5: =ROUNDUP(D4*1/12,0) -> 1 | E5: =ROUNDUP(E4*1/12,0) -> 1 | F5: =ROUNDUP(F4*1/12,0) -> 1 | G5: =ROUNDUP(G4*1/12,0) -> 1 | H5: =ROUNDUP(H4*1/12,0) -> 1 | I5: =ROUNDUP(I4*1/12,0) -> 1 | J5: =ROUNDUP(J4*1/12,0) -> 1 | ... AL5: =ROUNDUP(AL4*1/12,0) -> 3
A7: Headcount (FTE)
A8: Field technicians — FTE | C8: =Inputs!$E$42*(1+Inputs!$E$44)^(C$5-1)*MAX(0,MIN(1,C$4*1-Inputs!$E$45+1))/1 -> 7 | D8: =Inputs!$E$42*(1+Inputs!$E$44)^(D$5-1)*MAX(0,MIN(1,D$4*1-Inputs!$E$45+1))/1 -> 7 | E8: =Inputs!$E$42*(1+Inputs!$E$44)^(E$5-1)*MAX(0,MIN(1,E$4*1-Inputs!$E$45+1))/1 -> 7 | F8: =Inputs!$E$42*(1+Inputs!$E$44)^(F$5-1)*MAX(0,MIN(1,F$4*1-Inputs!$E$45+1))/1 -> 7 | G8: =Inputs!$E$42*(1+Inputs!$E$44)^(G$5-1)*MAX(0,MIN(1,G$4*1-Inputs!$E$45+1))/1 -> 7 | H8: =Inputs!$E$42*(1+Inputs!$E$44)^(H$5-1)*MAX(0,MIN(1,H$4*1-Inputs!$E$45+1))/1 -> 7 | I8: =Inputs!$E$42*(1+Inputs!$E$44)^(I$5-1)*MAX(0,MIN(1,I$4*1-Inputs!$E$45+1))/1 -> 7 | J8: =Inputs!$E$42*(1+Inputs!$E$44)^(J$5-1)*MAX(0,MIN(1,J$4*1-Inputs!$E$45+1))/1 -> 7 | ... AL8: =Inputs!$E$42*(1+Inputs!$E$44)^(AL$5-1)*MAX(0,MIN(1,AL$4*1-Inputs!$E$45+1))/1 -> 8.7808
A9: Dispatch & office — FTE | C9: =Inputs!$E$46*(1+Inputs!$E$48)^(C$5-1)*MAX(0,MIN(1,C$4*1-Inputs!$E$49+1))/1 -> 2 | D9: =Inputs!$E$46*(1+Inputs!$E$48)^(D$5-1)*MAX(0,MIN(1,D$4*1-Inputs!$E$49+1))/1 -> 2 | E9: =Inputs!$E$46*(1+Inputs!$E$48)^(E$5-1)*MAX(0,MIN(1,E$4*1-Inputs!$E$49+1))/1 -> 2 | F9: =Inputs!$E$46*(1+Inputs!$E$48)^(F$5-1)*MAX(0,MIN(1,F$4*1-Inputs!$E$49+1))/1 -> 2 | G9: =Inputs!$E$46*(1+Inputs!$E$48)^(G$5-1)*MAX(0,MIN(1,G$4*1-Inputs!$E$49+1))/1 -> 2 | H9: =Inputs!$E$46*(1+Inputs!$E$48)^(H$5-1)*MAX(0,MIN(1,H$4*1-Inputs!$E$49+1))/1 -> 2 | I9: =Inputs!$E$46*(1+Inputs!$E$48)^(I$5-1)*MAX(0,MIN(1,I$4*1-Inputs!$E$49+1))/1 -> 2 | J9: =Inputs!$E$46*(1+Inputs!$E$48)^(J$5-1)*MAX(0,MIN(1,J$4*1-Inputs!$E$49+1))/1 -> 2 | ... AL9: =Inputs!$E$46*(1+Inputs!$E$48)^(AL$5-1)*MAX(0,MIN(1,AL$4*1-Inputs!$E$49+1))/1 -> 2.42
A10: Total FTE | C10: =C8+C9 -> 9 | D10: =D8+D9 -> 9 | E10: =E8+E9 -> 9 | F10: =F8+F9 -> 9 | G10: =G8+G9 -> 9 | H10: =H8+H9 -> 9 | I10: =I8+I9 -> 9 | J10: =J8+J9 -> 9 | ... AL10: =AL8+AL9 -> 11.2008
A12: Payroll cost (salary + taxes & benefits)
A13: Field technicians — payroll cost | C13: =-C8*Inputs!$E$43/12*1*(1+Inputs!$E$50)*(1+Inputs!$E$51)^(C$5-1) -> -41591.667 | D13: =-D8*Inputs!$E$43/12*1*(1+Inputs!$E$50)*(1+Inputs!$E$51)^(D$5-1) -> -41591.667 | E13: =-E8*Inputs!$E$43/12*1*(1+Inputs!$E$50)*(1+Inputs!$E$51)^(E$5-1) -> -41591.667 | F13: =-F8*Inputs!$E$43/12*1*(1+Inputs!$E$50)*(1+Inputs!$E$51)^(F$5-1) -> -41591.667 | G13: =-G8*Inputs!$E$43/12*1*(1+Inputs!$E$50)*(1+Inputs!$E$51)^(G$5-1) -> -41591.667 | H13: =-H8*Inputs!$E$43/12*1*(1+Inputs!$E$50)*(1+Inputs!$E$51)^(H$5-1) -> -41591.667 | I13: =-I8*Inputs!$E$43/12*1*(1+Inputs!$E$50)*(1+Inputs!$E$51)^(I$5-1) -> -41591.667 | J13: =-J8*Inputs!$E$43/12*1*(1+Inputs!$E$50)*(1+Inputs!$E$51)^(J$5-1) -> -41591.667 | ... AL13: =-AL8*Inputs!$E$43/12*1*(1+Inputs!$E$50)*(1+Inputs!$E$51)^(AL$5-1) -> -55349.897
A14: Dispatch & office — payroll cost | C14: =-C9*Inputs!$E$47/12*1*(1+Inputs!$E$50)*(1+Inputs!$E$51)^(C$5-1) -> -8625 | D14: =-D9*Inputs!$E$47/12*1*(1+Inputs!$E$50)*(1+Inputs!$E$51)^(D$5-1) -> -8625 | E14: =-E9*Inputs!$E$47/12*1*(1+Inputs!$E$50)*(1+Inputs!$E$51)^(E$5-1) -> -8625 | F14: =-F9*Inputs!$E$47/12*1*(1+Inputs!$E$50)*(1+Inputs!$E$51)^(F$5-1) -> -8625 | G14: =-G9*Inputs!$E$47/12*1*(1+Inputs!$E$50)*(1+Inputs!$E$51)^(G$5-1) -> -8625 | H14: =-H9*Inputs!$E$47/12*1*(1+Inputs!$E$50)*(1+Inputs!$E$51)^(H$5-1) -> -8625 | I14: =-I9*Inputs!$E$47/12*1*(1+Inputs!$E$50)*(1+Inputs!$E$51)^(I$5-1) -> -8625 | J14: =-J9*Inputs!$E$47/12*1*(1+Inputs!$E$50)*(1+Inputs!$E$51)^(J$5-1) -> -8625 | ... AL14: =-AL9*Inputs!$E$47/12*1*(1+Inputs!$E$50)*(1+Inputs!$E$51)^(AL$5-1) -> -11071.818
A15: Total payroll | C15: =C13+C14 -> -50216.667 | D15: =D13+D14 -> -50216.667 | E15: =E13+E14 -> -50216.667 | F15: =F13+F14 -> -50216.667 | G15: =G13+G14 -> -50216.667 | H15: =H13+H14 -> -50216.667 | I15: =I13+I14 -> -50216.667 | J15: =J13+J14 -> -50216.667 | ... AL15: =AL13+AL14 -> -66421.715

Sheet Scenario calc
A1: Scenario calculation — Low, Base and High side by side | D1: =HYPERLINK("#'Cover'!A1","◂ Contents") -> ◂ Contents
A2: The model's period calculation, copied three times; each copy reads its own Inputs column. Feeds the Scenarios sheet only.
A4: Low scenario — reads Inputs column B
A5: Month | C5: M1 | D5: M2 | E5: M3 | F5: M4 | G5: M5 | H5: M6 | I5: M7 | J5: M8 | K5: M9 | L5: M10 | M5: M11 | N5: M12 | O5: M13 | P5: M14 | Q5: M15 | R5: M16 | S5: M17 | T5: M18 | U5: M19 | V5: M20 | W5: M21 | X5: M22 | Y5: M23 | Z5: M24 | AA5: M25 | AB5: M26 | AC5: M27 | AD5: M28 | AE5: M29 | AF5: M30 | AG5: M31 | AH5: M32 | AI5: M33 | AJ5: M34 | AK5: M35 | AL5: M36
A6: Period # | C6: 1 | D6: 2 | E6: 3 | F6: 4 | G6: 5 | H6: 6 | I6: 7 | J6: 8 | K6: 9 | L6: 10 | M6: 11 | N6: 12 | O6: 13 | P6: 14 | Q6: 15 | R6: 16 | S6: 17 | T6: 18 | U6: 19 | V6: 20 | W6: 21 | X6: 22 | Y6: 23 | Z6: 24 | AA6: 25 | AB6: 26 | AC6: 27 | AD6: 28 | AE6: 29 | AF6: 30 | AG6: 31 | AH6: 32 | AI6: 33 | AJ6: 34 | AK6: 35 | AL6: 36
A7: Year # | C7: =ROUNDUP(C6*1/12,0) -> 1 | D7: =ROUNDUP(D6*1/12,0) -> 1 | E7: =ROUNDUP(E6*1/12,0) -> 1 | F7: =ROUNDUP(F6*1/12,0) -> 1 | G7: =ROUNDUP(G6*1/12,0) -> 1 | H7: =ROUNDUP(H6*1/12,0) -> 1 | I7: =ROUNDUP(I6*1/12,0) -> 1 | J7: =ROUNDUP(J6*1/12,0) -> 1 | ... AL7: =ROUNDUP(AL6*1/12,0) -> 3
A9: Jobs
A10: Field technicians (FTE) | C10: =C103 -> 7 | D10: =D103 -> 7 | E10: =E103 -> 7 | F10: =F103 -> 7 | G10: =G103 -> 7 | H10: =H103 -> 7 | I10: =I103 -> 7 | J10: =J103 -> 7 | ... AL10: =AL103 -> 8.7808
A11: Job capacity (technicians × jobs per day × working days) | C11: =C10*Inputs!$B$7*Inputs!$B$8*1 -> 345.45 | D11: =D10*Inputs!$B$7*Inputs!$B$8*1 -> 345.45 | E11: =E10*Inputs!$B$7*Inputs!$B$8*1 -> 345.45 | F11: =F10*Inputs!$B$7*Inputs!$B$8*1 -> 345.45 | G11: =G10*Inputs!$B$7*Inputs!$B$8*1 -> 345.45 | H11: =H10*Inputs!$B$7*Inputs!$B$8*1 -> 345.45 | I11: =I10*Inputs!$B$7*Inputs!$B$8*1 -> 345.45 | J11: =J10*Inputs!$B$7*Inputs!$B$8*1 -> 345.45 | ... AL11: =AL10*Inputs!$B$7*Inputs!$B$8*1 -> 433.33248
A12: Season factor (June–August busy season) | C12: =IF(AND(MOD(C$6-1,12)>=5,MOD(C$6-1,12)<=7),1+Inputs!$B$17,1-Inputs!$B$17/3) -> 0.91666667 | D12: =IF(AND(MOD(D$6-1,12)>=5,MOD(D$6-1,12)<=7),1+Inputs!$B$17,1-Inputs!$B$17/3) -> 0.91666667 | E12: =IF(AND(MOD(E$6-1,12)>=5,MOD(E$6-1,12)<=7),1+Inputs!$B$17,1-Inputs!$B$17/3) -> 0.91666667 | F12: =IF(AND(MOD(F$6-1,12)>=5,MOD(F$6-1,12)<=7),1+Inputs!$B$17,1-Inputs!$B$17/3) -> 0.91666667 | G12: =IF(AND(MOD(G$6-1,12)>=5,MOD(G$6-1,12)<=7),1+Inputs!$B$17,1-Inputs!$B$17/3) -> 0.91666667 | H12: =IF(AND(MOD(H$6-1,12)>=5,MOD(H$6-1,12)<=7),1+Inputs!$B$17,1-Inputs!$B$17/3) -> 1.25 | I12: =IF(AND(MOD(I$6-1,12)>=5,MOD(I$6-1,12)<=7),1+Inputs!$B$17,1-Inputs!$B$17/3) -> 1.25 | J12: =IF(AND(MOD(J$6-1,12)>=5,MOD(J$6-1,12)<=7),1+Inputs!$B$17,1-Inputs!$B$17/3) -> 1.25 | ... AL12: =IF(AND(MOD(AL$6-1,12)>=5,MOD(AL$6-1,12)<=7),1+Inputs!$B$17,1-Inputs!$B$17/3) -> 0.91666667
A13: Leads from marketing | C13: =-C36/MAX(1,Inputs!$B$13) -> 173.07692 | D13: =-D36/MAX(1,Inputs!$B$13) -> 173.07692 | E13: =-E36/MAX(1,Inputs!$B$13) -> 173.07692 | F13: =-F36/MAX(1,Inputs!$B$13) -> 173.07692 | G13: =-G36/MAX(1,Inputs!$B$13) -> 173.07692 | H13: =-H36/MAX(1,Inputs!$B$13) -> 173.07692 | I13: =-I36/MAX(1,Inputs!$B$13) -> 173.07692 | J13: =-J36/MAX(1,Inputs!$B$13) -> 173.07692 | ... AL13: =-AL36/MAX(1,Inputs!$B$13) -> 217.10769
A14: Jobs booked from leads | C14: =C13*Inputs!$B$14*C12 -> 66.634615 | D14: =D13*Inputs!$B$14*D12 -> 66.634615 | E14: =E13*Inputs!$B$14*E12 -> 66.634615 | F14: =F13*Inputs!$B$14*F12 -> 66.634615 | G14: =G13*Inputs!$B$14*G12 -> 66.634615 | H14: =H13*Inputs!$B$14*H12 -> 90.865385 | I14: =I13*Inputs!$B$14*I12 -> 90.865385 | J14: =J13*Inputs!$B$14*J12 -> 90.865385 | ... AL14: =AL13*Inputs!$B$14*AL12 -> 83.586462
A15: Repeat & referral jobs | C15: =Inputs!$B$15*(1+Inputs!$B$16)^(C$7-1)*1*C12 -> 174.16667 | D15: =Inputs!$B$15*(1+Inputs!$B$16)^(D$7-1)*1*D12 -> 174.16667 | E15: =Inputs!$B$15*(1+Inputs!$B$16)^(E$7-1)*1*E12 -> 174.16667 | F15: =Inputs!$B$15*(1+Inputs!$B$16)^(F$7-1)*1*F12 -> 174.16667 | G15: =Inputs!$B$15*(1+Inputs!$B$16)^(G$7-1)*1*G12 -> 174.16667 | H15: =Inputs!$B$15*(1+Inputs!$B$16)^(H$7-1)*1*H12 -> 237.5 | I15: =Inputs!$B$15*(1+Inputs!$B$16)^(I$7-1)*1*I12 -> 237.5 | J15: =Inputs!$B$15*(1+Inputs!$B$16)^(J$7-1)*1*J12 -> 237.5 | ... AL15: =Inputs!$B$15*(1+Inputs!$B$16)^(AL$7-1)*1*AL12 -> 218.47467
A16: Jobs demanded | C16: =C14+C15 -> 240.80128 | D16: =D14+D15 -> 240.80128 | E16: =E14+E15 -> 240.80128 | F16: =F14+F15 -> 240.80128 | G16: =G14+G15 -> 240.80128 | H16: =H14+H15 -> 328.36538 | I16: =I14+I15 -> 328.36538 | J16: =J14+J15 -> 328.36538 | ... AL16: =AL14+AL15 -> 302.06113
A17: Jobs completed (demand capped by capacity) | C17: =MIN(C11,C16) -> 240.80128 | D17: =MIN(D11,D16) -> 240.80128 | E17: =MIN(E11,E16) -> 240.80128 | F17: =MIN(F11,F16) -> 240.80128 | G17: =MIN(G11,G16) -> 240.80128 | H17: =MIN(H11,H16) -> 328.36538 | I17: =MIN(I11,I16) -> 328.36538 | J17: =MIN(J11,J16) -> 328.36538 | ... AL17: =MIN(AL11,AL16) -> 302.06113
A19: Revenue
A20: Average revenue per job | C20: =Inputs!$B$20*(1+Inputs!$B$21)^(C$7-1) -> 415 | D20: =Inputs!$B$20*(1+Inputs!$B$21)^(D$7-1) -> 415 | E20: =Inputs!$B$20*(1+Inputs!$B$21)^(E$7-1) -> 415 | F20: =Inputs!$B$20*(1+Inputs!$B$21)^(F$7-1) -> 415 | G20: =Inputs!$B$20*(1+Inputs!$B$21)^(G$7-1) -> 415 | H20: =Inputs!$B$20*(1+Inputs!$B$21)^(H$7-1) -> 415 | I20: =Inputs!$B$20*(1+Inputs!$B$21)^(I$7-1) -> 415 | J20: =Inputs!$B$20*(1+Inputs!$B$21)^(J$7-1) -> 415 | ... AL20: =Inputs!$B$20*(1+Inputs!$B$21)^(AL$7-1) -> 431.766
A21: Job revenue | C21: =C17*C20 -> 99932.532 | D21: =D17*D20 -> 99932.532 | E21: =E17*E20 -> 99932.532 | F21: =F17*F20 -> 99932.532 | G21: =G17*G20 -> 99932.532 | H21: =H17*H20 -> 136271.63 | I21: =I17*I20 -> 136271.63 | J21: =J17*J20 -> 136271.63 | ... AL21: =AL17*AL20 -> 130419.73
A22: Maintenance plan members (average) | C22: =Inputs!$B$24*(1+Inputs!$B$25)^(C$7-1) -> 300 | D22: =Inputs!$B$24*(1+Inputs!$B$25)^(D$7-1) -> 300 | E22: =Inputs!$B$24*(1+Inputs!$B$25)^(E$7-1) -> 300 | F22: =Inputs!$B$24*(1+Inputs!$B$25)^(F$7-1) -> 300 | G22: =Inputs!$B$24*(1+Inputs!$B$25)^(G$7-1) -> 300 | H22: =Inputs!$B$24*(1+Inputs!$B$25)^(H$7-1) -> 300 | I22: =Inputs!$B$24*(1+Inputs!$B$25)^(I$7-1) -> 300 | J22: =Inputs!$B$24*(1+Inputs!$B$25)^(J$7-1) -> 300 | ... AL22: =Inputs!$B$24*(1+Inputs!$B$25)^(AL$7-1) -> 396.75
A23: Maintenance plan revenue | C23: =C22*Inputs!$B$26*(1+Inputs!$B$21)^(C$7-1)*1 -> 5400 | D23: =D22*Inputs!$B$26*(1+Inputs!$B$21)^(D$7-1)*1 -> 5400 | E23: =E22*Inputs!$B$26*(1+Inputs!$B$21)^(E$7-1)*1 -> 5400 | F23: =F22*Inputs!$B$26*(1+Inputs!$B$21)^(F$7-1)*1 -> 5400 | G23: =G22*Inputs!$B$26*(1+Inputs!$B$21)^(G$7-1)*1 -> 5400 | H23: =H22*Inputs!$B$26*(1+Inputs!$B$21)^(H$7-1)*1 -> 5400 | I23: =I22*Inputs!$B$26*(1+Inputs!$B$21)^(I$7-1)*1 -> 5400 | J23: =J22*Inputs!$B$26*(1+Inputs!$B$21)^(J$7-1)*1 -> 5400 | ... AL23: =AL22*Inputs!$B$26*(1+Inputs!$B$21)^(AL$7-1)*1 -> 7430.0166
A24: Revenue | C24: =C21+C23 -> 105332.53 | D24: =D21+D23 -> 105332.53 | E24: =E21+E23 -> 105332.53 | F24: =F21+F23 -> 105332.53 | G24: =G21+G23 -> 105332.53 | H24: =H21+H23 -> 141671.63 | I24: =I21+I23 -> 141671.63 | J24: =J21+J23 -> 141671.63 | ... AL24: =AL21+AL23 -> 137849.74
A26: Cost of delivery
A27: Technician payroll | C27: =C108 -> -41591.667 | D27: =D108 -> -41591.667 | E27: =E108 -> -41591.667 | F27: =F108 -> -41591.667 | G27: =G108 -> -41591.667 | H27: =H108 -> -41591.667 | I27: =I108 -> -41591.667 | J27: =J108 -> -41591.667 | ... AL27: =AL108 -> -55349.897
A28: Materials & parts | C28: =-C21*Inputs!$B$30 -> -25982.458 | D28: =-D21*Inputs!$B$30 -> -25982.458 | E28: =-E21*Inputs!$B$30 -> -25982.458 | F28: =-F21*Inputs!$B$30 -> -25982.458 | G28: =-G21*Inputs!$B$30 -> -25982.458 | H28: =-H21*Inputs!$B$30 -> -35430.625 | I28: =-I21*Inputs!$B$30 -> -35430.625 | J28: =-J21*Inputs!$B$30 -> -35430.625 | ... AL28: =-AL21*Inputs!$B$30 -> -33909.129
A29: Vehicles | C29: =-C10*Inputs!$B$31*1 -> -9450 | D29: =-D10*Inputs!$B$31*1 -> -9450 | E29: =-E10*Inputs!$B$31*1 -> -9450 | F29: =-F10*Inputs!$B$31*1 -> -9450 | G29: =-G10*Inputs!$B$31*1 -> -9450 | H29: =-H10*Inputs!$B$31*1 -> -9450 | I29: =-I10*Inputs!$B$31*1 -> -9450 | J29: =-J10*Inputs!$B$31*1 -> -9450 | ... AL29: =-AL10*Inputs!$B$31*1 -> -11854.08
A30: Plan visits | C30: =-C23*Inputs!$B$27 -> -2268 | D30: =-D23*Inputs!$B$27 -> -2268 | E30: =-E23*Inputs!$B$27 -> -2268 | F30: =-F23*Inputs!$B$27 -> -2268 | G30: =-G23*Inputs!$B$27 -> -2268 | H30: =-H23*Inputs!$B$27 -> -2268 | I30: =-I23*Inputs!$B$27 -> -2268 | J30: =-J23*Inputs!$B$27 -> -2268 | ... AL30: =-AL23*Inputs!$B$27 -> -3120.607
A31: Cost of delivery | C31: =C27+C28+C29+C30 -> -79292.125 | D31: =D27+D28+D29+D30 -> -79292.125 | E31: =E27+E28+E29+E30 -> -79292.125 | F31: =F27+F28+F29+F30 -> -79292.125 | G31: =G27+G28+G29+G30 -> -79292.125 | H31: =H27+H28+H29+H30 -> -88740.292 | I31: =I27+I28+I29+I30 -> -88740.292 | J31: =J27+J28+J29+J30 -> -88740.292 | ... AL31: =AL27+AL28+AL29+AL30 -> -104233.71
A32: Gross profit | C32: =C24+C31 -> 26040.407 | D32: =D24+D31 -> 26040.407 | E32: =E24+E31 -> 26040.407 | F32: =F24+F31 -> 26040.407 | G32: =G24+G31 -> 26040.407 | H32: =H24+H31 -> 52931.343 | I32: =I24+I31 -> 52931.343 | J32: =J24+J31 -> 52931.343 | ... AL32: =AL24+AL31 -> 33616.029
A34: Operating expenses
A35: Dispatch, office & other payroll | C35: =C110-C108 -> -8625 | D35: =D110-D108 -> -8625 | E35: =E110-E108 -> -8625 | F35: =F110-F108 -> -8625 | G35: =G110-G108 -> -8625 | H35: =H110-H108 -> -8625 | I35: =I110-I108 -> -8625 | J35: =J110-J108 -> -8625 | ... AL35: =AL110-AL108 -> -11071.818
A36: Marketing | C36: =-Inputs!$B$11*(1+Inputs!$B$12)^(C$7-1)*1 -> -9000 | D36: =-Inputs!$B$11*(1+Inputs!$B$12)^(D$7-1)*1 -> -9000 | E36: =-Inputs!$B$11*(1+Inputs!$B$12)^(E$7-1)*1 -> -9000 | F36: =-Inputs!$B$11*(1+Inputs!$B$12)^(F$7-1)*1 -> -9000 | G36: =-Inputs!$B$11*(1+Inputs!$B$12)^(G$7-1)*1 -> -9000 | H36: =-Inputs!$B$11*(1+Inputs!$B$12)^(H$7-1)*1 -> -9000 | I36: =-Inputs!$B$11*(1+Inputs!$B$12)^(I$7-1)*1 -> -9000 | J36: =-Inputs!$B$11*(1+Inputs!$B$12)^(J$7-1)*1 -> -9000 | ... AL36: =-Inputs!$B$11*(1+Inputs!$B$12)^(AL$7-1)*1 -> -11289.6
A37: Field software & phones | C37: =-C10*Inputs!$B$32*1 -> -840 | D37: =-D10*Inputs!$B$32*1 -> -840 | E37: =-E10*Inputs!$B$32*1 -> -840 | F37: =-F10*Inputs!$B$32*1 -> -840 | G37: =-G10*Inputs!$B$32*1 -> -840 | H37: =-H10*Inputs!$B$32*1 -> -840 | I37: =-I10*Inputs!$B$32*1 -> -840 | J37: =-J10*Inputs!$B$32*1 -> -840 | ... AL37: =-AL10*Inputs!$B$32*1 -> -1053.696
A38: Insurance & licences | C38: =-Inputs!$B$33*1 -> -3500 | D38: =-Inputs!$B$33*1 -> -3500 | E38: =-Inputs!$B$33*1 -> -3500 | F38: =-Inputs!$B$33*1 -> -3500 | G38: =-Inputs!$B$33*1 -> -3500 | H38: =-Inputs!$B$33*1 -> -3500 | I38: =-Inputs!$B$33*1 -> -3500 | J38: =-Inputs!$B$33*1 -> -3500 | ... AL38: =-Inputs!$B$33*1 -> -3500
A39: Shop / office rent | C39: =-Inputs!$B$34*1 -> -4500 | D39: =-Inputs!$B$34*1 -> -4500 | E39: =-Inputs!$B$34*1 -> -4500 | F39: =-Inputs!$B$34*1 -> -4500 | G39: =-Inputs!$B$34*1 -> -4500 | H39: =-Inputs!$B$34*1 -> -4500 | I39: =-Inputs!$B$34*1 -> -4500 | J39: =-Inputs!$B$34*1 -> -4500 | ... AL39: =-Inputs!$B$34*1 -> -4500
A40: Other G&A | C40: =-Inputs!$B$35*1 -> -2500 | D40: =-Inputs!$B$35*1 -> -2500 | E40: =-Inputs!$B$35*1 -> -2500 | F40: =-Inputs!$B$35*1 -> -2500 | G40: =-Inputs!$B$35*1 -> -2500 | H40: =-Inputs!$B$35*1 -> -2500 | I40: =-Inputs!$B$35*1 -> -2500 | J40: =-Inputs!$B$35*1 -> -2500 | ... AL40: =-Inputs!$B$35*1 -> -2500
A41: Card processing fees | C41: =-C24*Inputs!$B$36 -> -3054.6434 | D41: =-D24*Inputs!$B$36 -> -3054.6434 | E41: =-E24*Inputs!$B$36 -> -3054.6434 | F41: =-F24*Inputs!$B$36 -> -3054.6434 | G41: =-G24*Inputs!$B$36 -> -3054.6434 | H41: =-H24*Inputs!$B$36 -> -4108.4774 | I41: =-I24*Inputs!$B$36 -> -4108.4774 | J41: =-J24*Inputs!$B$36 -> -4108.4774 | ... AL41: =-AL24*Inputs!$B$36 -> -3997.6425
A42: Total operating expenses | C42: =C35+C36+C37+C38+C39+C40+C41 -> -32019.643 | D42: =D35+D36+D37+D38+D39+D40+D41 -> -32019.643 | E42: =E35+E36+E37+E38+E39+E40+E41 -> -32019.643 | F42: =F35+F36+F37+F38+F39+F40+F41 -> -32019.643 | G42: =G35+G36+G37+G38+G39+G40+G41 -> -32019.643 | H42: =H35+H36+H37+H38+H39+H40+H41 -> -33073.477 | I42: =I35+I36+I37+I38+I39+I40+I41 -> -33073.477 | J42: =J35+J36+J37+J38+J39+J40+J41 -> -33073.477 | ... AL42: =AL35+AL36+AL37+AL38+AL39+AL40+AL41 -> -37912.756
A43: EBITDA | C43: =C32+C42 -> -5979.2364 | D43: =D32+D42 -> -5979.2364 | E43: =E32+E42 -> -5979.2364 | F43: =F32+F42 -> -5979.2364 | G43: =G32+G42 -> -5979.2364 | H43: =H32+H42 -> 19857.866 | I43: =I32+I42 -> 19857.866 | J43: =J32+J42 -> 19857.866 | ... AL43: =AL32+AL42 -> -4296.7271
A45: Profit after depreciation, interest, tax
A46: EBIT | C46: =C43+C57 -> -6312.5697 | D46: =D43+D57 -> -6312.5697 | E46: =E43+E57 -> -6312.5697 | F46: =F43+F57 -> -6312.5697 | G46: =G43+G57 -> -6312.5697 | H46: =H43+H57 -> 19524.532 | I46: =I43+I57 -> 19524.532 | J46: =J43+J57 -> 19524.532 | ... AL46: =AL43+AL57 -> -6025.0205
A47: Interest on loan (average balance after drawdown) | C47: =-(C62+C63+C65)/2*Inputs!$B$56/12 -> -1666.6667 | D47: =-(D62+D63+D65)/2*Inputs!$B$56/12 -> -1652.7778 | E47: =-(E62+E63+E65)/2*Inputs!$B$56/12 -> -1625 | F47: =-(F62+F63+F65)/2*Inputs!$B$56/12 -> -1597.2222 | G47: =-(G62+G63+G65)/2*Inputs!$B$56/12 -> -1569.4444 | H47: =-(H62+H63+H65)/2*Inputs!$B$56/12 -> -1541.6667 | I47: =-(I62+I63+I65)/2*Inputs!$B$56/12 -> -1513.8889 | J47: =-(J62+J63+J65)/2*Inputs!$B$56/12 -> -1486.1111 | ... AL47: =-(AL62+AL63+AL65)/2*Inputs!$B$56/12 -> -708.33333
A48: Pre-tax income | C48: =C46+C47 -> -7979.2364 | D48: =D46+D47 -> -7965.3475 | E48: =E46+E47 -> -7937.5697 | F48: =F46+F47 -> -7909.7919 | G48: =G46+G47 -> -7882.0142 | H48: =H46+H47 -> 17982.866 | I48: =I46+I47 -> 18010.643 | J48: =J46+J47 -> 18038.421 | ... AL48: =AL46+AL47 -> -6733.3538
A49: Helper: cumulative pre-tax income | C49: =C48 -> -7979.2364 | D49: =C49+D48 -> -15944.584 | E49: =D49+E48 -> -23882.154 | F49: =E49+F48 -> -31791.946 | G49: =F49+G48 -> -39673.96 | H49: =G49+H48 -> -21691.094 | I49: =H49+I48 -> -3680.4508 | J49: =I49+J48 -> 14357.97 | K49: =J49+K48 -> 6587.0673 | ... AL49: =AK49+AL48 -> 1920.2527
A50: Helper: cumulative taxable income (losses carried forward) | C50: =MAX(0,C49) -> 0 | D50: =MAX(C50,D49) -> 0 | E50: =MAX(D50,E49) -> 0 | F50: =MAX(E50,F49) -> 0 | G50: =MAX(F50,G49) -> 0 | H50: =MAX(G50,H49) -> 0 | I50: =MAX(H50,I49) -> 0 | J50: =MAX(I50,J49) -> 14357.97 | K50: =MAX(J50,K49) -> 14357.97 | ... AL50: =MAX(AK50,AL49) -> 29020.335
A51: Income tax | C51: =-C50*Inputs!$B$66 -> 0 | D51: =-(D50-C50)*Inputs!$B$66 -> 0 | E51: =-(E50-D50)*Inputs!$B$66 -> 0 | F51: =-(F50-E50)*Inputs!$B$66 -> 0 | G51: =-(G50-F50)*Inputs!$B$66 -> 0 | H51: =-(H50-G50)*Inputs!$B$66 -> 0 | I51: =-(I50-H50)*Inputs!$B$66 -> 0 | J51: =-(J50-I50)*Inputs!$B$66 -> -3015.1738 | K51: =-(K50-J50)*Inputs!$B$66 -> 0 | ... AL51: =-(AL50-AK50)*Inputs!$B$66 -> 0
A52: Net income | C52: =C48+C51 -> -7979.2364 | D52: =D48+D51 -> -7965.3475 | E52: =E48+E51 -> -7937.5697 | F52: =F48+F51 -> -7909.7919 | G52: =G48+G51 -> -7882.0142 | H52: =H48+H51 -> 17982.866 | I52: =I48+I51 -> 18010.643 | J52: =J48+J51 -> 15023.247 | ... AL52: =AL48+AL51 -> -6733.3538
A54: Fixed assets & capital spending
A55: Capital spending (start-up + van & tools per technician added) | C55: =Inputs!$B$37+MAX(0,C10-Inputs!$B$39)*Inputs!$B$38 -> 20000 | D55: =MAX(0,D10-C10)*Inputs!$B$38 -> 0 | E55: =MAX(0,E10-D10)*Inputs!$B$38 -> 0 | F55: =MAX(0,F10-E10)*Inputs!$B$38 -> 0 | G55: =MAX(0,G10-F10)*Inputs!$B$38 -> 0 | H55: =MAX(0,H10-G10)*Inputs!$B$38 -> 0 | I55: =MAX(0,I10-H10)*Inputs!$B$38 -> 0 | J55: =MAX(0,J10-I10)*Inputs!$B$38 -> 0 | K55: =MAX(0,K10-J10)*Inputs!$B$38 -> 0 | ... AL55: =MAX(0,AL10-AK10)*Inputs!$B$38 -> 0
A56: Fixed assets at cost | C56: =C55 -> 20000 | D56: =C56+D55 -> 20000 | E56: =D56+E55 -> 20000 | F56: =E56+F55 -> 20000 | G56: =F56+G55 -> 20000 | H56: =G56+H55 -> 20000 | I56: =H56+I55 -> 20000 | J56: =I56+J55 -> 20000 | K56: =J56+K55 -> 20000 | ... AL56: =AK56+AL55 -> 103697.6
A57: Depreciation | C57: =-MIN(C56/MAX(1,Inputs!$B$65*12),C55) -> -333.33333 | D57: =-MIN(D56/MAX(1,Inputs!$B$65*12),C59+D55) -> -333.33333 | E57: =-MIN(E56/MAX(1,Inputs!$B$65*12),D59+E55) -> -333.33333 | F57: =-MIN(F56/MAX(1,Inputs!$B$65*12),E59+F55) -> -333.33333 | G57: =-MIN(G56/MAX(1,Inputs!$B$65*12),F59+G55) -> -333.33333 | H57: =-MIN(H56/MAX(1,Inputs!$B$65*12),G59+H55) -> -333.33333 | I57: =-MIN(I56/MAX(1,Inputs!$B$65*12),H59+I55) -> -333.33333 | J57: =-MIN(J56/MAX(1,Inputs!$B$65*12),I59+J55) -> -333.33333 | K57: =-MIN(K56/MAX(1,Inputs!$B$65*12),J59+K55) -> -333.33333 | ... AL57: =-MIN(AL56/MAX(1,Inputs!$B$65*12),AK59+AL55) -> -1728.2933
A58: Accumulated depreciation | C58: =C57 -> -333.33333 | D58: =C58+D57 -> -666.66667 | E58: =D58+E57 -> -1000 | F58: =E58+F57 -> -1333.3333 | G58: =F58+G57 -> -1666.6667 | H58: =G58+H57 -> -2000 | I58: =H58+I57 -> -2333.3333 | J58: =I58+J57 -> -2666.6667 | K58: =J58+K57 -> -3000 | ... AL58: =AK58+AL57 -> -36635.52
A59: Net fixed assets | C59: =C56+C58 -> 19666.667 | D59: =D56+D58 -> 19333.333 | E59: =E56+E58 -> 19000 | F59: =F56+F58 -> 18666.667 | G59: =G56+G58 -> 18333.333 | H59: =H56+H58 -> 18000 | I59: =I56+I58 -> 17666.667 | J59: =J56+J58 -> 17333.333 | ... AL59: =AL56+AL58 -> 67062.08
A61: Debt
A62: Loan — opening balance | C62: =0 -> 0 | D62: =C65 -> 250000 | E62: =D65 -> 245833.33 | F62: =E65 -> 241666.67 | G62: =F65 -> 237500 | H62: =G65 -> 233333.33 | I62: =H65 -> 229166.67 | J62: =I65 -> 225000 | K62: =J65 -> 220833.33 | ... AL62: =AK65 -> 108333.33
A63: Loan drawdown | C63: =IF(C$6=1,Inputs!$B$55,0) -> 250000 | D63: =IF(D$6=1,Inputs!$B$55,0) -> 0 | E63: =IF(E$6=1,Inputs!$B$55,0) -> 0 | F63: =IF(F$6=1,Inputs!$B$55,0) -> 0 | G63: =IF(G$6=1,Inputs!$B$55,0) -> 0 | H63: =IF(H$6=1,Inputs!$B$55,0) -> 0 | I63: =IF(I$6=1,Inputs!$B$55,0) -> 0 | J63: =IF(J$6=1,Inputs!$B$55,0) -> 0 | ... AL63: =IF(AL$6=1,Inputs!$B$55,0) -> 0
A64: Loan repayment | C64: =-MIN(C62,Inputs!$B$55/MAX(1,Inputs!$B$57*12)) -> 0 | D64: =-MIN(D62,Inputs!$B$55/MAX(1,Inputs!$B$57*12)) -> -4166.6667 | E64: =-MIN(E62,Inputs!$B$55/MAX(1,Inputs!$B$57*12)) -> -4166.6667 | F64: =-MIN(F62,Inputs!$B$55/MAX(1,Inputs!$B$57*12)) -> -4166.6667 | G64: =-MIN(G62,Inputs!$B$55/MAX(1,Inputs!$B$57*12)) -> -4166.6667 | H64: =-MIN(H62,Inputs!$B$55/MAX(1,Inputs!$B$57*12)) -> -4166.6667 | I64: =-MIN(I62,Inputs!$B$55/MAX(1,Inputs!$B$57*12)) -> -4166.6667 | J64: =-MIN(J62,Inputs!$B$55/MAX(1,Inputs!$B$57*12)) -> -4166.6667 | ... AL64: =-MIN(AL62,Inputs!$B$55/MAX(1,Inputs!$B$57*12)) -> -4166.6667
A65: Loan — closing balance | C65: =C62+C63+C64 -> 250000 | D65: =D62+D63+D64 -> 245833.33 | E65: =E62+E63+E64 -> 241666.67 | F65: =F62+F63+F64 -> 237500 | G65: =G62+G63+G64 -> 233333.33 | H65: =H62+H63+H64 -> 229166.67 | I65: =I62+I63+I64 -> 225000 | J65: =J62+J63+J64 -> 220833.33 | ... AL65: =AL62+AL63+AL64 -> 104166.67
A67: Working capital
A68: Accounts receivable | C68: =C24*Inputs!$B$60/30 -> 35110.844 | D68: =D24*Inputs!$B$60/30 -> 35110.844 | E68: =E24*Inputs!$B$60/30 -> 35110.844 | F68: =F24*Inputs!$B$60/30 -> 35110.844 | G68: =G24*Inputs!$B$60/30 -> 35110.844 | H68: =H24*Inputs!$B$60/30 -> 47223.878 | I68: =I24*Inputs!$B$60/30 -> 47223.878 | J68: =J24*Inputs!$B$60/30 -> 47223.878 | ... AL68: =AL24*Inputs!$B$60/30 -> 45949.914
A69: Inventory | C69: =-C31*Inputs!$B$61/30 -> 13215.354 | D69: =-D31*Inputs!$B$61/30 -> 13215.354 | E69: =-E31*Inputs!$B$61/30 -> 13215.354 | F69: =-F31*Inputs!$B$61/30 -> 13215.354 | G69: =-G31*Inputs!$B$61/30 -> 13215.354 | H69: =-H31*Inputs!$B$61/30 -> 14790.049 | I69: =-I31*Inputs!$B$61/30 -> 14790.049 | J69: =-J31*Inputs!$B$61/30 -> 14790.049 | ... AL69: =-AL31*Inputs!$B$61/30 -> 17372.285
A70: Accounts payable | C70: =-C31*Inputs!$B$62/30 -> 52861.417 | D70: =-D31*Inputs!$B$62/30 -> 52861.417 | E70: =-E31*Inputs!$B$62/30 -> 52861.417 | F70: =-F31*Inputs!$B$62/30 -> 52861.417 | G70: =-G31*Inputs!$B$62/30 -> 52861.417 | H70: =-H31*Inputs!$B$62/30 -> 59160.194 | I70: =-I31*Inputs!$B$62/30 -> 59160.194 | J70: =-J31*Inputs!$B$62/30 -> 59160.194 | ... AL70: =-AL31*Inputs!$B$62/30 -> 69489.142
A71: (Increase) / decrease in receivables | C71: =-C68 -> -35110.844 | D71: =C68-D68 -> 0 | E71: =D68-E68 -> 0 | F71: =E68-F68 -> 0 | G71: =F68-G68 -> 0 | H71: =G68-H68 -> -12113.034 | I71: =H68-I68 -> 0 | J71: =I68-J68 -> 0 | K71: =J68-K68 -> 12113.034 | ... AL71: =AK68-AL68 -> 0
A72: (Increase) / decrease in inventory | C72: =-C69 -> -13215.354 | D72: =C69-D69 -> 0 | E72: =D69-E69 -> 0 | F72: =E69-F69 -> 0 | G72: =F69-G69 -> 0 | H72: =G69-H69 -> -1574.6944 | I72: =H69-I69 -> 0 | J72: =I69-J69 -> 0 | K72: =J69-K69 -> 1574.6944 | ... AL72: =AK69-AL69 -> 0
A73: Increase / (decrease) in payables | C73: =C70 -> 52861.417 | D73: =D70-C70 -> 0 | E73: =E70-D70 -> 0 | F73: =F70-E70 -> 0 | G73: =G70-F70 -> 0 | H73: =H70-G70 -> 6298.7778 | I73: =I70-H70 -> 0 | J73: =J70-I70 -> 0 | K73: =K70-J70 -> -6298.7778 | ... AL73: =AL70-AK70 -> 0
A75: Cash flow
A76: Operating cash flow | C76: =C52-C57+C71+C72+C73 -> -3110.6846 | D76: =D52-D57+D71+D72+D73 -> -7632.0142 | E76: =E52-E57+E71+E72+E73 -> -7604.2364 | F76: =F52-F57+F71+F72+F73 -> -7576.4586 | G76: =G52-G57+G71+G72+G73 -> -7548.6808 | H76: =H52-H57+H71+H72+H73 -> 10927.248 | I76: =I52-I57+I71+I72+I73 -> 18343.977 | J76: =J52-J57+J71+J72+J73 -> 15356.581 | ... AL76: =AL52-AL57+AL71+AL72+AL73 -> -5005.0605
A77: Investing cash flow (capex) | C77: =-C55 -> -20000 | D77: =-D55 -> 0 | E77: =-E55 -> 0 | F77: =-F55 -> 0 | G77: =-G55 -> 0 | H77: =-H55 -> 0 | I77: =-I55 -> 0 | J77: =-J55 -> 0 | ... AL77: =-AL55 -> 0
A78: Equity raised | C78: =IF(C$6=1,Inputs!$B$54,0) -> 100000 | D78: =IF(D$6=1,Inputs!$B$54,0) -> 0 | E78: =IF(E$6=1,Inputs!$B$54,0) -> 0 | F78: =IF(F$6=1,Inputs!$B$54,0) -> 0 | G78: =IF(G$6=1,Inputs!$B$54,0) -> 0 | H78: =IF(H$6=1,Inputs!$B$54,0) -> 0 | I78: =IF(I$6=1,Inputs!$B$54,0) -> 0 | J78: =IF(J$6=1,Inputs!$B$54,0) -> 0 | ... AL78: =IF(AL$6=1,Inputs!$B$54,0) -> 0
A79: Financing cash flow | C79: =C78+C63+C64 -> 350000 | D79: =D78+D63+D64 -> -4166.6667 | E79: =E78+E63+E64 -> -4166.6667 | F79: =F78+F63+F64 -> -4166.6667 | G79: =G78+G63+G64 -> -4166.6667 | H79: =H78+H63+H64 -> -4166.6667 | I79: =I78+I63+I64 -> -4166.6667 | J79: =J78+J63+J64 -> -4166.6667 | ... AL79: =AL78+AL63+AL64 -> -4166.6667
A80: Net cash flow | C80: =C76+C77+C79 -> 326889.32 | D80: =D76+D77+D79 -> -11798.681 | E80: =E76+E77+E79 -> -11770.903 | F80: =F76+F77+F79 -> -11743.125 | G80: =G76+G77+G79 -> -11715.347 | H80: =H76+H77+H79 -> 6760.5814 | I80: =I76+I77+I79 -> 14177.31 | J80: =J76+J77+J79 -> 11189.914 | ... AL80: =AL76+AL77+AL79 -> -9171.7271
A81: Opening cash | C81: =0 -> 0 | D81: =C82 -> 326889.32 | E81: =D82 -> 315090.63 | F81: =E82 -> 303319.73 | G81: =F82 -> 291576.61 | H81: =G82 -> 279861.26 | I81: =H82 -> 286621.84 | J81: =I82 -> 300799.15 | K81: =J82 -> 311989.06 | ... AL81: =AK82 -> 148269.24
A82: Closing cash | C82: =C81+C80 -> 326889.32 | D82: =D81+D80 -> 315090.63 | E82: =E81+E80 -> 303319.73 | F82: =F81+F80 -> 291576.61 | G82: =G81+G80 -> 279861.26 | H82: =H81+H80 -> 286621.84 | I82: =I81+I80 -> 300799.15 | J82: =J81+J80 -> 311989.06 | ... AL82: =AL81+AL80 -> 139097.51
A83: Helper: EBITDA positive (1/0) | C83: =IF(C43>0,1,0) -> 0 | D83: =IF(D43>0,1,0) -> 0 | E83: =IF(E43>0,1,0) -> 0 | F83: =IF(F43>0,1,0) -> 0 | G83: =IF(G43>0,1,0) -> 0 | H83: =IF(H43>0,1,0) -> 1 | I83: =IF(I43>0,1,0) -> 1 | J83: =IF(J43>0,1,0) -> 1 | ... AL83: =IF(AL43>0,1,0) -> 0
A85: Goal modules
A86: Helper: net income positive (1/0) | C86: =IF(C52>0,1,0) -> 0 | D86: =IF(D52>0,1,0) -> 0 | E86: =IF(E52>0,1,0) -> 0 | F86: =IF(F52>0,1,0) -> 0 | G86: =IF(G52>0,1,0) -> 0 | H86: =IF(H52>0,1,0) -> 1 | I86: =IF(I52>0,1,0) -> 1 | J86: =IF(J52>0,1,0) -> 1 | ... AL86: =IF(AL52>0,1,0) -> 0
A87: Cash flow before financing (operating + investing) | C87: =C76+C77 -> -23110.685 | D87: =D76+D77 -> -7632.0142 | E87: =E76+E77 -> -7604.2364 | F87: =F76+F77 -> -7576.4586 | G87: =G76+G77 -> -7548.6808 | H87: =H76+H77 -> 10927.248 | I87: =I76+I77 -> 18343.977 | J87: =J76+J77 -> 15356.581 | ... AL87: =AL76+AL77 -> -5005.0605
A88: Cumulative cash flow before financing | C88: =C87 -> -23110.685 | D88: =C88+D87 -> -30742.699 | E88: =D88+E87 -> -38346.935 | F88: =E88+F87 -> -45923.394 | G88: =F88+G87 -> -53472.075 | H88: =G88+H87 -> -42544.826 | I88: =H88+I87 -> -24200.85 | J88: =I88+J87 -> -8844.2692 | K88: =J88+K87 -> -8892.888 | ... AL88: =AK88+AL87 -> -65069.155
A89: Helper: lowest cumulative cash flow so far | C89: =C88 -> -23110.685 | D89: =MIN(C89,D88) -> -30742.699 | E89: =MIN(D89,E88) -> -38346.935 | F89: =MIN(E89,F88) -> -45923.394 | G89: =MIN(F89,G88) -> -53472.075 | H89: =MIN(G89,H88) -> -53472.075 | I89: =MIN(H89,I88) -> -53472.075 | J89: =MIN(I89,J88) -> -53472.075 | K89: =MIN(J89,K88) -> -53472.075 | ... AL89: =MIN(AK89,AL88) -> -127529.58
A90: Helper: investment paid back (1/0) | C90: =IF(AND(C88>=0,C89<0),1,0) -> 0 | D90: =IF(AND(D88>=0,D89<0),1,0) -> 0 | E90: =IF(AND(E88>=0,E89<0),1,0) -> 0 | F90: =IF(AND(F88>=0,F89<0),1,0) -> 0 | G90: =IF(AND(G88>=0,G89<0),1,0) -> 0 | H90: =IF(AND(H88>=0,H89<0),1,0) -> 0 | I90: =IF(AND(I88>=0,I89<0),1,0) -> 0 | J90: =IF(AND(J88>=0,J89<0),1,0) -> 0 | ... AL90: =IF(AND(AL88>=0,AL89<0),1,0) -> 0
A91: Unlevered free cash flow (operating + after-tax interest − capex) | C91: =C76-C47*(1-Inputs!$B$66)+C77 -> -21794.018 | D91: =D76-D47*(1-Inputs!$B$66)+D77 -> -6326.3197 | E91: =E76-E47*(1-Inputs!$B$66)+E77 -> -6320.4864 | F91: =F76-F47*(1-Inputs!$B$66)+F77 -> -6314.653 | G91: =G76-G47*(1-Inputs!$B$66)+G77 -> -6308.8197 | H91: =H76-H47*(1-Inputs!$B$66)+H77 -> 12145.165 | I91: =I76-I47*(1-Inputs!$B$66)+I77 -> 19539.949 | J91: =J76-J47*(1-Inputs!$B$66)+J77 -> 16530.608 | ... AL91: =AL76-AL47*(1-Inputs!$B$66)+AL77 -> -4445.4771
A93: Balance sheet
A94: Paid-in capital | C94: =C78 -> 100000 | D94: =C94+D78 -> 100000 | E94: =D94+E78 -> 100000 | F94: =E94+F78 -> 100000 | G94: =F94+G78 -> 100000 | H94: =G94+H78 -> 100000 | I94: =H94+I78 -> 100000 | J94: =I94+J78 -> 100000 | K94: =J94+K78 -> 100000 | ... AL94: =AK94+AL78 -> 100000
A95: Retained earnings | C95: =C52 -> -7979.2364 | D95: =C95+D52 -> -15944.584 | E95: =D95+E52 -> -23882.154 | F95: =E95+F52 -> -31791.946 | G95: =F95+G52 -> -39673.96 | H95: =G95+H52 -> -21691.094 | I95: =H95+I52 -> -3680.4508 | J95: =I95+J52 -> 11342.797 | K95: =J95+K52 -> 3571.8935 | ... AL95: =AK95+AL52 -> -4174.0176
A96: Total assets | C96: =C82+C68+C69+C59 -> 394882.18 | D96: =D82+D68+D69+D59 -> 382750.17 | E96: =E82+E68+E69+E59 -> 370645.93 | F96: =F82+F68+F69+F59 -> 358569.47 | G96: =G82+G68+G69+G59 -> 346520.79 | H96: =H82+H68+H69+H59 -> 366635.77 | I96: =I82+I68+I69+I59 -> 380479.74 | J96: =J82+J68+J69+J59 -> 391336.32 | ... AL96: =AL82+AL68+AL69+AL59 -> 269481.79
A97: Total liabilities | C97: =C70+C65 -> 302861.42 | D97: =D70+D65 -> 298694.75 | E97: =E70+E65 -> 294528.08 | F97: =F70+F65 -> 290361.42 | G97: =G70+G65 -> 286194.75 | H97: =H70+H65 -> 288326.86 | I97: =I70+I65 -> 284160.19 | J97: =J70+J65 -> 279993.53 | ... AL97: =AL70+AL65 -> 173655.81
A98: Total equity | C98: =C94+C95 -> 92020.764 | D98: =D94+D95 -> 84055.416 | E98: =E94+E95 -> 76117.846 | F98: =F94+F95 -> 68208.054 | G98: =G94+G95 -> 60326.04 | H98: =H94+H95 -> 78308.906 | I98: =I94+I95 -> 96319.549 | J98: =J94+J95 -> 111342.8 | ... AL98: =AL94+AL95 -> 95825.982
A99: Total liabilities & equity | C99: =C97+C98 -> 394882.18 | D99: =D97+D98 -> 382750.17 | E99: =E97+E98 -> 370645.93 | F99: =F97+F98 -> 358569.47 | G99: =G97+G98 -> 346520.79 | H99: =H97+H98 -> 366635.77 | I99: =I97+I98 -> 380479.74 | J99: =J97+J98 -> 391336.32 | ... AL99: =AL97+AL98 -> 269481.79
A100: Check: assets − liabilities − equity | C100: =C96-C99 -> 0 | D100: =D96-D99 -> 0 | E100: =E96-E99 -> 0 | F100: =F96-F99 -> 0 | G100: =G96-G99 -> 0 | H100: =H96-H99 -> 0 | I100: =I96-I99 -> 0 | J100: =J96-J99 -> 0 | ... AL100: =AL96-AL99 -> 0
A102: Headcount (FTE)
A103: Field technicians — FTE | C103: =Inputs!$B$42*(1+Inputs!$B$44)^(C$7-1)*MAX(0,MIN(1,C$6*1-Inputs!$B$45+1))/1 -> 7 | D103: =Inputs!$B$42*(1+Inputs!$B$44)^(D$7-1)*MAX(0,MIN(1,D$6*1-Inputs!$B$45+1))/1 -> 7 | E103: =Inputs!$B$42*(1+Inputs!$B$44)^(E$7-1)*MAX(0,MIN(1,E$6*1-Inputs!$B$45+1))/1 -> 7 | F103: =Inputs!$B$42*(1+Inputs!$B$44)^(F$7-1)*MAX(0,MIN(1,F$6*1-Inputs!$B$45+1))/1 -> 7 | G103: =Inputs!$B$42*(1+Inputs!$B$44)^(G$7-1)*MAX(0,MIN(1,G$6*1-Inputs!$B$45+1))/1 -> 7 | H103: =Inputs!$B$42*(1+Inputs!$B$44)^(H$7-1)*MAX(0,MIN(1,H$6*1-Inputs!$B$45+1))/1 -> 7 | I103: =Inputs!$B$42*(1+Inputs!$B$44)^(I$7-1)*MAX(0,MIN(1,I$6*1-Inputs!$B$45+1))/1 -> 7 | J103: =Inputs!$B$42*(1+Inputs!$B$44)^(J$7-1)*MAX(0,MIN(1,J$6*1-Inputs!$B$45+1))/1 -> 7 | ... AL103: =Inputs!$B$42*(1+Inputs!$B$44)^(AL$7-1)*MAX(0,MIN(1,AL$6*1-Inputs!$B$45+1))/1 -> 8.7808
A104: Dispatch & office — FTE | C104: =Inputs!$B$46*(1+Inputs!$B$48)^(C$7-1)*MAX(0,MIN(1,C$6*1-Inputs!$B$49+1))/1 -> 2 | D104: =Inputs!$B$46*(1+Inputs!$B$48)^(D$7-1)*MAX(0,MIN(1,D$6*1-Inputs!$B$49+1))/1 -> 2 | E104: =Inputs!$B$46*(1+Inputs!$B$48)^(E$7-1)*MAX(0,MIN(1,E$6*1-Inputs!$B$49+1))/1 -> 2 | F104: =Inputs!$B$46*(1+Inputs!$B$48)^(F$7-1)*MAX(0,MIN(1,F$6*1-Inputs!$B$49+1))/1 -> 2 | G104: =Inputs!$B$46*(1+Inputs!$B$48)^(G$7-1)*MAX(0,MIN(1,G$6*1-Inputs!$B$49+1))/1 -> 2 | H104: =Inputs!$B$46*(1+Inputs!$B$48)^(H$7-1)*MAX(0,MIN(1,H$6*1-Inputs!$B$49+1))/1 -> 2 | I104: =Inputs!$B$46*(1+Inputs!$B$48)^(I$7-1)*MAX(0,MIN(1,I$6*1-Inputs!$B$49+1))/1 -> 2 | J104: =Inputs!$B$46*(1+Inputs!$B$48)^(J$7-1)*MAX(0,MIN(1,J$6*1-Inputs!$B$49+1))/1 -> 2 | ... AL104: =Inputs!$B$46*(1+Inputs!$B$48)^(AL$7-1)*MAX(0,MIN(1,AL$6*1-Inputs!$B$49+1))/1 -> 2.42
A105: Total FTE | C105: =C103+C104 -> 9 | D105: =D103+D104 -> 9 | E105: =E103+E104 -> 9 | F105: =F103+F104 -> 9 | G105: =G103+G104 -> 9 | H105: =H103+H104 -> 9 | I105: =I103+I104 -> 9 | J105: =J103+J104 -> 9 | ... AL105: =AL103+AL104 -> 11.2008
A107: Payroll cost (salary + taxes & benefits)
A108: Field technicians — payroll cost | C108: =-C103*Inputs!$B$43/12*1*(1+Inputs!$B$50)*(1+Inputs!$B$51)^(C$7-1) -> -41591.667 | D108: =-D103*Inputs!$B$43/12*1*(1+Inputs!$B$50)*(1+Inputs!$B$51)^(D$7-1) -> -41591.667 | E108: =-E103*Inputs!$B$43/12*1*(1+Inputs!$B$50)*(1+Inputs!$B$51)^(E$7-1) -> -41591.667 | F108: =-F103*Inputs!$B$43/12*1*(1+Inputs!$B$50)*(1+Inputs!$B$51)^(F$7-1) -> -41591.667 | G108: =-G103*Inputs!$B$43/12*1*(1+Inputs!$B$50)*(1+Inputs!$B$51)^(G$7-1) -> -41591.667 | H108: =-H103*Inputs!$B$43/12*1*(1+Inputs!$B$50)*(1+Inputs!$B$51)^(H$7-1) -> -41591.667 | I108: =-I103*Inputs!$B$43/12*1*(1+Inputs!$B$50)*(1+Inputs!$B$51)^(I$7-1) -> -41591.667 | J108: =-J103*Inputs!$B$43/12*1*(1+Inputs!$B$50)*(1+Inputs!$B$51)^(J$7-1) -> -41591.667 | ... AL108: =-AL103*Inputs!$B$43/12*1*(1+Inputs!$B$50)*(1+Inputs!$B$51)^(AL$7-1) -> -55349.897
A109: Dispatch & office — payroll cost | C109: =-C104*Inputs!$B$47/12*1*(1+Inputs!$B$50)*(1+Inputs!$B$51)^(C$7-1) -> -8625 | D109: =-D104*Inputs!$B$47/12*1*(1+Inputs!$B$50)*(1+Inputs!$B$51)^(D$7-1) -> -8625 | E109: =-E104*Inputs!$B$47/12*1*(1+Inputs!$B$50)*(1+Inputs!$B$51)^(E$7-1) -> -8625 | F109: =-F104*Inputs!$B$47/12*1*(1+Inputs!$B$50)*(1+Inputs!$B$51)^(F$7-1) -> -8625 | G109: =-G104*Inputs!$B$47/12*1*(1+Inputs!$B$50)*(1+Inputs!$B$51)^(G$7-1) -> -8625 | H109: =-H104*Inputs!$B$47/12*1*(1+Inputs!$B$50)*(1+Inputs!$B$51)^(H$7-1) -> -8625 | I109: =-I104*Inputs!$B$47/12*1*(1+Inputs!$B$50)*(1+Inputs!$B$51)^(I$7-1) -> -8625 | J109: =-J104*Inputs!$B$47/12*1*(1+Inputs!$B$50)*(1+Inputs!$B$51)^(J$7-1) -> -8625 | ... AL109: =-AL104*Inputs!$B$47/12*1*(1+Inputs!$B$50)*(1+Inputs!$B$51)^(AL$7-1) -> -11071.818
A110: Total payroll | C110: =C108+C109 -> -50216.667 | D110: =D108+D109 -> -50216.667 | E110: =E108+E109 -> -50216.667 | F110: =F108+F109 -> -50216.667 | G110: =G108+G109 -> -50216.667 | H110: =H108+H109 -> -50216.667 | I110: =I108+I109 -> -50216.667 | J110: =J108+J109 -> -50216.667 | ... AL110: =AL108+AL109 -> -66421.715
A113: Base scenario — reads Inputs column C
A114: Month | C114: M1 | D114: M2 | E114: M3 | F114: M4 | G114: M5 | H114: M6 | I114: M7 | J114: M8 | K114: M9 | L114: M10 | M114: M11 | N114: M12 | O114: M13 | P114: M14 | Q114: M15 | R114: M16 | S114: M17 | T114: M18 | U114: M19 | V114: M20 | W114: M21 | X114: M22 | Y114: M23 | Z114: M24 | AA114: M25 | AB114: M26 | AC114: M27 | AD114: M28 | AE114: M29 | AF114: M30 | AG114: M31 | AH114: M32 | AI114: M33 | AJ114: M34 | AK114: M35 | AL114: M36
A115: Period # | C115: 1 | D115: 2 | E115: 3 | F115: 4 | G115: 5 | H115: 6 | I115: 7 | J115: 8 | K115: 9 | L115: 10 | M115: 11 | N115: 12 | O115: 13 | P115: 14 | Q115: 15 | R115: 16 | S115: 17 | T115: 18 | U115: 19 | V115: 20 | W115: 21 | X115: 22 | Y115: 23 | Z115: 24 | AA115: 25 | AB115: 26 | AC115: 27 | AD115: 28 | AE115: 29 | AF115: 30 | AG115: 31 | AH115: 32 | AI115: 33 | AJ115: 34 | AK115: 35 | AL115: 36
A116: Year # | C116: =ROUNDUP(C115*1/12,0) -> 1 | D116: =ROUNDUP(D115*1/12,0) -> 1 | E116: =ROUNDUP(E115*1/12,0) -> 1 | F116: =ROUNDUP(F115*1/12,0) -> 1 | G116: =ROUNDUP(G115*1/12,0) -> 1 | H116: =ROUNDUP(H115*1/12,0) -> 1 | I116: =ROUNDUP(I115*1/12,0) -> 1 | J116: =ROUNDUP(J115*1/12,0) -> 1 | ... AL116: =ROUNDUP(AL115*1/12,0) -> 3
...

Sheet Checks
A1: Model checks | E1: =HYPERLINK("#'Cover'!A1","◂ Contents") -> ◂ Contents
A2: Live formulas: they re-run every time an input changes.
A3: Check | B3: Result | C3: What it tests
A4: Annual revenue ties to period detail | B4: =IF(ABS(SUM('P&L'!$B$5:$D$5)-SUM(Monthly!$C$22:$AL$22))<0.5,"PASS","FAIL") -> PASS | C4: Sum of annual revenue equals the sum of every period
A5: Annual net income ties to period detail | B5: =IF(ABS(SUM('P&L'!$B$24:$D$24)-SUM(Monthly!$C$50:$AL$50))<0.5,"PASS","FAIL") -> PASS | C5: Sum of annual net income equals the sum of every period
A6: EBITDA reconciliation | B6: =IF(ABS(SUM(Monthly!$C$41:$AL$41)-SUM(Monthly!$C$30:$AL$30)-SUM(Monthly!$C$40:$AL$40))<0.5,"PASS","FAIL") -> PASS | C6: EBITDA = gross profit + operating expenses (costs are negative)
A7: Cash roll-forward | B7: =IF(ABS(INDEX(Monthly!$C$80:$AL$80,36)-SUM(Monthly!$C$78:$AL$78))<0.5,"PASS","FAIL") -> PASS | C7: Closing cash = all net cash flows since the start (opening cash is zero)
A8: Scenario selector valid | B8: =IF(AND(ISNUMBER(Dashboard!B4),Dashboard!B4>=1,Dashboard!B4<=3,INT(Dashboard!B4)=Dashboard!B4),"PASS","FAIL") -> PASS | C8: Dashboard!B4 is 1, 2 or 3
A9: Scenario ordering of drivers | B9: =IF(AND(Inputs!$B$7<=Inputs!$C$7,Inputs!$C$7<=Inputs!$D$7,Inputs!$B$12<=Inputs!$C$12,Inputs!$C$12<=Inputs!$D$12,Inputs!$B$13>=Inputs!$C$13,Inputs!$C$13>=Inputs!$D$13,Inputs!$B$14<=Inputs!$C$14,Inputs!$C$14<=Inputs!$D$14,Inputs!$B$15<=Inputs!$C$15,Inputs!$C$15<=Inputs!$D$15,Inputs!$B$16<=Inputs!$C$16,Inputs!$C$16<=Inputs!$D$16,Inputs!$B$20<=Inputs!$C$20,Inputs!$C$20<=Inputs!$D$20,Inputs!$B$21<=Inputs!$C$21,Inputs!$C$21<=Inputs!$D$21,Inputs!$B$24<=Inputs!$C$24,Inputs!$C$24<=Inputs!$D$24,Inputs!$B$25<=Inputs!$C$25,Inputs!$C$25<=Inputs!$D$25,Inputs!$B$26<=Inputs!$C$26,Inputs!$C$26<=Inputs!$D$26,Inputs!$B$27>=Inputs!$C$27,Inputs!$C$27>=Inputs!$D$27,Inputs!$B$30>=Inputs!$C$30,Inputs!$C$30>=Inputs!$D$30,Inputs!$B$31>=Inputs!$C$31,Inputs!$C$31>=Inputs!$D$31,Inputs!$B$36>=Inputs!$C$36,Inputs!$C$36>=Inputs!$D$36,Inputs!$B$38>=Inputs!$C$38,Inputs!$C$38>=Inputs!$D$38,Inputs!$B$42<=Inputs!$C$42,Inputs!$C$42<=Inputs!$D$42,Inputs!$B$44<=Inputs!$C$44,Inputs!$C$44<=Inputs!$D$44,Inputs!$B$46<=Inputs!$C$46,Inputs!$C$46<=Inputs!$D$46,Inputs!$B$48<=Inputs!$C$48,Inputs!$C$48<=Inputs!$D$48,Inputs!$B$72>=Inputs!$C$72,Inputs!$C$72>=Inputs!$D$72,Inputs!$B$73<=Inputs!$C$73,Inputs!$C$73<=Inputs!$D$73,Inputs!$B$74<=Inputs!$C$74,Inputs!$C$74<=Inputs!$D$74),"PASS","FAIL") -> PASS | C9: Low / Base / High ordered the right way for every growth and cost driver
A10: Gross margin within 0–100% | B10: =IF(AND(MIN('P&L'!$B$8:$D$8)>=0,MAX('P&L'!$B$8:$D$8)<=1),"PASS","FAIL") -> PASS | C10: Gross margin never negative or above 100%
A11: Loan balance never negative | B11: =IF(MIN(Monthly!$C$63:$AL$63)>=-0.5,"PASS","FAIL") -> PASS | C11: Repayments never exceed the loan
A12: Funding table ties to the cash flow | B12: =IF(ABS('Break-even'!B18-('Break-even'!B16-'Break-even'!B10))<0.5,"PASS","FAIL") -> PASS | C12: Lowest cash balance = sources of funds − uses of funds up to that point
A13: Valuation: discounting ties to NPV() | B13: =IF(ABS(Valuation!B23-NPV(Valuation!B6,Valuation!$B$17:$D$17))<0.5,"PASS","FAIL") -> PASS | C13: Sum of discounted free cash flows equals Excel's NPV of the same flows
A14: Valuation: WACC above terminal growth | B14: =IF(Valuation!B6>Valuation!B7,"PASS","FAIL") -> PASS | C14: The perpetual-growth formula needs WACC > g
A15: Valuation: sensitivity centre = enterprise value | B15: =IF(ABS(Valuation!D36-Valuation!B27)<0.5,"PASS","FAIL") -> PASS | C15: The middle of the WACC × growth table reproduces the headline value
A16: Valuation: final-year cash flow positive | B16: =IF(Valuation!$D$17>0,"PASS","WARN") -> PASS | C16: Business warning: a negative final-year cash flow gives a negative terminal value (often a 1-year plan still carrying start-up spending)
A17: Sources & uses balance | B17: =IF(ABS('Sources & Uses'!B21-'Sources & Uses'!B28)<0.5,"PASS","FAIL") -> PASS | C17: Sources of funds = uses of funds (incl. cash at the end) for the Sources & Uses period
A18: No error values | B18: =IF(SUMPRODUCT(--ISERROR(Monthly!$C$4:$AL$98))+SUMPRODUCT(--ISERROR(Headcount!$C$4:$AL$15))+SUMPRODUCT(--ISERROR('P&L'!$B$3:$D$25))+SUMPRODUCT(--ISERROR('Cash Flow'!$B$3:$D$18))+SUMPRODUCT(--ISERROR('Balance Sheet'!$B$3:$D$17))+SUMPRODUCT(--ISERROR(KPIs!$B$27:$D$49))+SUMPRODUCT(--ISERROR('Break-even'!$B$26:$D$33))+SUMPRODUCT(--ISERROR(Valuation!$B$14:$D$19))+SUMPRODUCT(--ISERROR('Break-even'!$B$3:$D$35))+SUMPRODUCT(--ISERROR(Valuation!$A$3:$F$40))+SUMPRODUCT(--ISERROR('Sources & Uses'!$B$3:$C$30))+SUMPRODUCT(--ISERROR(Dashboard!$A$6:$W$43))+SUMPRODUCT(--ISERROR(Summary!$A$5:$S$52))+SUMPRODUCT(--ISERROR(KPIs!$A$4:$E$49))+SUMPRODUCT(--ISERROR('Scenario calc'!$C$6:$AL$110))+SUMPRODUCT(--ISERROR('Scenario calc'!$C$115:$AL$219))+SUMPRODUCT(--ISERROR('Scenario calc'!$C$224:$AL$328))+SUMPRODUCT(--ISERROR(Scenarios!$B$5:$E$50))=0,"PASS","FAIL") -> PASS | C18: No error values (divide-by-zero, broken references) on any calculation sheet
A19: Summary ties to statements | B19: =IF(IFERROR(AND(SUMPRODUCT(--(ABS(Summary!$B$7:$D$7-'P&L'!$B$5:$D$5)>0.5))=0,SUMPRODUCT(--(ABS(Summary!$B$19:$D$19-'P&L'!$B$24:$D$24)>0.5))=0,SUMPRODUCT(--(ABS(Summary!$B$31:$D$31-'Cash Flow'!$B$18:$D$18)>0.5))=0,SUMPRODUCT(--(ABS(Summary!$B$41:$D$41-'Balance Sheet'!$B$5:$D$5)>0.5))=0,ABS(SUM(Summary!$H$7:$S$7)-INDEX(Summary!$B$7:$D$7,Summary!$R$2))<0.5,ABS(SUM(Summary!$H$19:$S$19)-INDEX(Summary!$B$19:$D$19,Summary!$R$2))<0.5,ABS(Summary!$S$31-INDEX(Summary!$B$31:$D$31,Summary!$R$2))<0.5),FALSE()),"PASS","FAIL") -> PASS | C19: Summary revenue, net income and closing cash equal the statements every year; the detailed year adds up to its annual figure
A20: DuPont ties to return on equity | B20: =IF(SUMPRODUCT(--(ABS(KPIs!$B$24:$D$24)>0.000000001))>0,"FAIL",IF(SUMPRODUCT(ISNUMBER(KPIs!$B$23:$D$23)*ISNUMBER(KPIs!$B$16:$D$16))=0,"n/a","PASS")) -> PASS | C20: Net margin × asset turnover × equity multiplier equals return on equity every year; n/a = no year where both are defined (a one-sided n/a is a FAIL)
A21: Scenarios: Active = selected scenario | B21: =IF(IFERROR(AND(ABS(Scenarios!E17-INDEX(Scenarios!B17:D17,1,Dashboard!$B$4))<0.5,ABS(Scenarios!E18-INDEX(Scenarios!B18:D18,1,Dashboard!$B$4))<0.5,ABS(Scenarios!E19-INDEX(Scenarios!B19:D19,1,Dashboard!$B$4))<0.5,ABS(Scenarios!E20-INDEX(Scenarios!B20:D20,1,Dashboard!$B$4))<0.000001,ABS(Scenarios!E21-INDEX(Scenarios!B21:D21,1,Dashboard!$B$4))<0.5,ABS(Scenarios!E22-INDEX(Scenarios!B22:D22,1,Dashboard!$B$4))<0.5,ABS(Scenarios!E23-INDEX(Scenarios!B23:D23,1,Dashboard!$B$4))<0.5,ABS(Scenarios!E24-INDEX(Scenarios!B24:D24,1,Dashboard!$B$4))<0.5,ABS(Scenarios!E25-INDEX(Scenarios!B25:D25,1,Dashboard!$B$4))<0.5,ABS(Scenarios!E26-INDEX(Scenarios!B26:D26,1,Dashboard!$B$4))<0.5),FALSE()),"PASS","FAIL") -> PASS | C21: On the Scenarios sheet the live model (Active) equals the Low / Base / High column chosen on the Dashboard for every output
A22: Balance sheet balances every period | B22: =IF(SUMPRODUCT(--(ABS(Monthly!$C$98:$AL$98)>0.5))=0,"PASS","FAIL") -> PASS | C22: Assets = liabilities + equity in every period
A23: Funding sufficient (cash ≥ 0) | B23: =IF(MIN(Monthly!$C$80:$AL$80)>=0,"PASS","WARN") -> PASS | C23: Business warning, not an error: cash dips below zero in this scenario
A25: Overall verdict | B25: =IF(COUNTIF(B4:B23,"FAIL")>0,"FAIL",IF(COUNTIF(B4:B23,"WARN")>0,"PASS WITH WARNINGS","PASS")) -> PASS
