Workbook

Sheet Cover
B2: Pet grooming & boarding financial model (planning)
B3: 5-year financial model · monthly detail · Low / Base / High scenarios · US dollars · Full plan
B5: Purpose | D5: Revenue and profit plan
B6: Active scenario | D6: =Dashboard!C4&" (change it on the Dashboard, cell B4)" -> Base (change it on the Dashboard, cell B4)
B7: Model checks | D7: =Checks!B25 -> PASS
B8: Prepared | D8: 22 October 2026
B10: Contents
C11: PRESENTATION
B12: 1 | C12: =HYPERLINK("#Dashboard!A1","Dashboard") -> Dashboard | D12: Scenario switch, key numbers, core financials
B13: 2 | C13: =HYPERLINK("#Summary!A1","Summary") -> Summary | D13: Income statement, cash flow and balance sheet — every year and any year by month
B14: 3 | C14: =HYPERLINK("#Scenarios!A1","Scenarios") -> Scenarios | D14: Low / Base / High side by side: drivers, outputs, charts
B15: 4 | C15: =HYPERLINK("#'Break-even'!A1","Break-even") -> Break-even | D15: Startup costs, funding need, break-even timing and revenue
B16: 5 | C16: =HYPERLINK("#Valuation!A1","Valuation") -> Valuation | D16: Free cash flow, DCF (perpetual growth and exit multiple), WACC × growth sensitivity
B17: 6 | C17: =HYPERLINK("#'Sources & Uses'!A1","Sources & Uses") -> Sources & Uses | D17: Funding structure, sources and uses of cash for the first months
B18: 7 | C18: =HYPERLINK("#KPIs!A1","KPIs") -> KPIs | D18: Financial ratios, DuPont analysis, industry metrics
C19: INPUTS
B20: 8 | C20: =HYPERLINK("#Inputs!A1","Inputs") -> Inputs | D20: Every assumption, Low / Base / High, with units and comments
C21: STATEMENTS
B22: 9 | C22: =HYPERLINK("#'P&L'!A1","P&L") -> P&L | D22: Annual profit & loss
B23: 10 | C23: =HYPERLINK("#'Cash Flow'!A1","Cash Flow") -> Cash Flow | D23: Annual cash flow statement
B24: 11 | C24: =HYPERLINK("#'Balance Sheet'!A1","Balance Sheet") -> Balance Sheet | D24: Balance sheet at year end
C25: CALCULATIONS
B26: 12 | C26: =HYPERLINK("#Monthly!A1","Monthly") -> Monthly | D26: Month-by-month engine of the model
B27: 13 | C27: =HYPERLINK("#Headcount!A1","Headcount") -> Headcount | D27: Team and payroll
B28: 14 | C28: =HYPERLINK("#'Scenario calc'!A1","Scenario calc") -> Scenario calc | D28: Low, Base and High calculated side by side for the Scenarios sheet
C29: CONTROL
B30: 15 | C30: =HYPERLINK("#Checks!A1","Checks") -> Checks | D30: Live integrity checks and the overall verdict
B32: How to read this file
C33: 1000 | D33: Input you can change — yellow cell with a blue figure (Inputs sheet and the view switches)
C34: 1000 | D34: Formula — calculated, do not overwrite
C35: 1000 | D35: Link to another sheet
C36: 1000 | D36: Active value the model uses (follows the scenario)

Sheet Dashboard
A1: Dashboard | W1: =HYPERLINK("#'Cover'!A1","◂ Contents") -> ◂ Contents
A2: Pet grooming & boarding financial model (planning)
A4: Active scenario | B4: 2 | C4: =CHOOSE(B4,"Low","Base","High") -> Base | D4: 1 = Low · 2 = Base · 3 = High — every sheet follows this cell | S4: Model checks | T4: =Checks!B25 -> PASS
A6: REVENUE · YEAR 5 | C6: EBITDA MARGIN · YEAR 5 | H6: NET INCOME · YEAR 5 | L6: LOWEST CASH BALANCE | P6: FUNDING REQUIRED | T6: ENTERPRISE VALUE (DCF)
A7: =F12 -> 997614.88 | C7: =F17 -> 0.2009116 | H7: =F18 -> 134898.35 | L7: =F39 -> 147500.34 | P7: =F37 -> 391499.66 | T7: =F44 -> 273323.31
A8: =IF(AND(B12>0,F12>=0),(F12/B12)^(1/4)-1,"CAGR n/a") -> 0.14793647 | C8: =F16 -> 200432.4 | H8: =F19 -> 0.13522087 | L8: ='Break-even'!B6 -> 10 | P8: =IF(F38>=0,"Covered by funding raised",-F38) -> Covered by funding raised | T8: Average of 2 methods
A10: Core financials ($'000) — active scenario
B11: 1 | C11: 2 | D11: 3 | E11: 4 | F11: 5
A12: Revenue | B12: =SUMIF(Monthly!$C$5:$BJ$5,B$11,Monthly!$C$31:$BJ$31) -> 574501.95 | C12: =SUMIF(Monthly!$C$5:$BJ$5,C$11,Monthly!$C$31:$BJ$31) -> 835486.76 | D12: =SUMIF(Monthly!$C$5:$BJ$5,D$11,Monthly!$C$31:$BJ$31) -> 886367.9 | E12: =SUMIF(Monthly!$C$5:$BJ$5,E$11,Monthly!$C$31:$BJ$31) -> 940347.71 | F12: =SUMIF(Monthly!$C$5:$BJ$5,F$11,Monthly!$C$31:$BJ$31) -> 997614.88
A13: Gross profit | B13: =SUMIF(Monthly!$C$5:$BJ$5,B$11,Monthly!$C$40:$BJ$40) -> 369936.66 | C13: =SUMIF(Monthly!$C$5:$BJ$5,C$11,Monthly!$C$40:$BJ$40) -> 556642.48 | D13: =SUMIF(Monthly!$C$5:$BJ$5,D$11,Monthly!$C$40:$BJ$40) -> 592006.05 | E13: =SUMIF(Monthly!$C$5:$BJ$5,E$11,Monthly!$C$40:$BJ$40) -> 629567.18 | F13: =SUMIF(Monthly!$C$5:$BJ$5,F$11,Monthly!$C$40:$BJ$40) -> 669461.03
A14: Gross margin | B14: =IF(B12=0,0,B13/B12) -> 0.64392586 | C14: =IF(C12=0,0,C13/C12) -> 0.66624932 | D14: =IF(D12=0,0,D13/D12) -> 0.66790105 | E14: =IF(E12=0,0,E13/E12) -> 0.66950467 | F14: =IF(F12=0,0,F13/F12) -> 0.67106159
A15: Operating expenses | B15: =SUMIF(Monthly!$C$5:$BJ$5,B$11,Monthly!$C$49:$BJ$49) -> -434085.06 | C15: =SUMIF(Monthly!$C$5:$BJ$5,C$11,Monthly!$C$49:$BJ$49) -> -444760.1 | D15: =SUMIF(Monthly!$C$5:$BJ$5,D$11,Monthly!$C$49:$BJ$49) -> -451149.4 | E15: =SUMIF(Monthly!$C$5:$BJ$5,E$11,Monthly!$C$49:$BJ$49) -> -459323.15 | F15: =SUMIF(Monthly!$C$5:$BJ$5,F$11,Monthly!$C$49:$BJ$49) -> -469028.62
A16: EBITDA | B16: =SUMIF(Monthly!$C$5:$BJ$5,B$11,Monthly!$C$50:$BJ$50) -> -64148.399 | C16: =SUMIF(Monthly!$C$5:$BJ$5,C$11,Monthly!$C$50:$BJ$50) -> 111882.38 | D16: =SUMIF(Monthly!$C$5:$BJ$5,D$11,Monthly!$C$50:$BJ$50) -> 140856.65 | E16: =SUMIF(Monthly!$C$5:$BJ$5,E$11,Monthly!$C$50:$BJ$50) -> 170244.04 | F16: =SUMIF(Monthly!$C$5:$BJ$5,F$11,Monthly!$C$50:$BJ$50) -> 200432.4
A17: EBITDA margin | B17: =IF(B12=0,0,B16/B12) -> -0.11165915 | C17: =IF(C12=0,0,C16/C12) -> 0.13391281 | D17: =IF(D12=0,0,D16/D12) -> 0.15891443 | E17: =IF(E12=0,0,E16/E12) -> 0.18104371 | F17: =IF(F12=0,0,F16/F12) -> 0.2009116
A18: Net income | B18: =SUMIF(Monthly!$C$5:$BJ$5,B$11,Monthly!$C$59:$BJ$59) -> -96017.149 | C18: =SUMIF(Monthly!$C$5:$BJ$5,C$11,Monthly!$C$59:$BJ$59) -> 80557.379 | D18: =SUMIF(Monthly!$C$5:$BJ$5,D$11,Monthly!$C$59:$BJ$59) -> 90211.054 | E18: =SUMIF(Monthly!$C$5:$BJ$5,E$11,Monthly!$C$59:$BJ$59) -> 110615.04 | F18: =SUMIF(Monthly!$C$5:$BJ$5,F$11,Monthly!$C$59:$BJ$59) -> 134898.35
A19: Net margin | B19: =IF(B12=0,0,B18/B12) -> -0.16713111 | C19: =IF(C12=0,0,C18/C12) -> 0.096419695 | D19: =IF(D12=0,0,D18/D12) -> 0.10177608 | E19: =IF(E12=0,0,E18/E12) -> 0.11763206 | F19: =IF(F12=0,0,F18/F12) -> 0.13522087
A20: Operating cash flow | B20: =SUMIF(Monthly!$C$5:$BJ$5,B$11,Monthly!$C$89:$BJ$89) -> -62809.527 | C20: =SUMIF(Monthly!$C$5:$BJ$5,C$11,Monthly!$C$89:$BJ$89) -> 105940.94 | D20: =SUMIF(Monthly!$C$5:$BJ$5,D$11,Monthly!$C$89:$BJ$89) -> 116873.34 | E20: =SUMIF(Monthly!$C$5:$BJ$5,E$11,Monthly!$C$89:$BJ$89) -> 138557.72 | F20: =SUMIF(Monthly!$C$5:$BJ$5,F$11,Monthly!$C$89:$BJ$89) -> 164123.22
A21: Investing cash flow | B21: =SUMIF(Monthly!$C$5:$BJ$5,B$11,Monthly!$C$90:$BJ$90) -> -189000 | C21: =SUMIF(Monthly!$C$5:$BJ$5,C$11,Monthly!$C$90:$BJ$90) -> -10000 | D21: =SUMIF(Monthly!$C$5:$BJ$5,D$11,Monthly!$C$90:$BJ$90) -> -10000 | E21: =SUMIF(Monthly!$C$5:$BJ$5,E$11,Monthly!$C$90:$BJ$90) -> -10000 | F21: =SUMIF(Monthly!$C$5:$BJ$5,F$11,Monthly!$C$90:$BJ$90) -> -10000
A22: Financing cash flow | B22: =SUMIF(Monthly!$C$5:$BJ$5,B$11,Monthly!$C$92:$BJ$92) -> 411666.67 | C22: =SUMIF(Monthly!$C$5:$BJ$5,C$11,Monthly!$C$92:$BJ$92) -> -20000 | D22: =SUMIF(Monthly!$C$5:$BJ$5,D$11,Monthly!$C$92:$BJ$92) -> -20000 | E22: =SUMIF(Monthly!$C$5:$BJ$5,E$11,Monthly!$C$92:$BJ$92) -> -20000 | F22: =SUMIF(Monthly!$C$5:$BJ$5,F$11,Monthly!$C$92:$BJ$92) -> -20000
A23: Net change in cash | B23: =SUMIF(Monthly!$C$5:$BJ$5,B$11,Monthly!$C$93:$BJ$93) -> 159857.14 | C23: =SUMIF(Monthly!$C$5:$BJ$5,C$11,Monthly!$C$93:$BJ$93) -> 75940.942 | D23: =SUMIF(Monthly!$C$5:$BJ$5,D$11,Monthly!$C$93:$BJ$93) -> 86873.338 | E23: =SUMIF(Monthly!$C$5:$BJ$5,E$11,Monthly!$C$93:$BJ$93) -> 108557.72 | F23: =SUMIF(Monthly!$C$5:$BJ$5,F$11,Monthly!$C$93:$BJ$93) -> 134123.22
A24: Year-end cash | B24: =INDEX(Monthly!$C$95:$BJ$95,B$11*12) -> 159857.14 | C24: =INDEX(Monthly!$C$95:$BJ$95,C$11*12) -> 235798.08 | D24: =INDEX(Monthly!$C$95:$BJ$95,D$11*12) -> 322671.42 | E24: =INDEX(Monthly!$C$95:$BJ$95,E$11*12) -> 431229.14 | F24: =INDEX(Monthly!$C$95:$BJ$95,F$11*12) -> 565352.36
A26: Pet care metrics
B27: 1 | C27: 2 | D27: 3 | E27: 4 | F27: 5
A28: Grooms completed | B28: =KPIs!B30 -> 3619.2 | C28: =KPIs!C30 -> 5141.76 | D28: =KPIs!D30 -> 5296.0128 | E28: =KPIs!E30 -> 5454.8932 | F28: =KPIs!F30 -> 5618.54
A29: Grooming capacity used | B29: =KPIs!B32 -> 0.52727273 | C29: =KPIs!C32 -> 0.74909091 | D29: =KPIs!D32 -> 0.77156364 | E29: =KPIs!E32 -> 0.79471055 | F29: =KPIs!F32 -> 0.81855186
A30: Boarding occupancy | B30: =KPIs!B36 -> 0.45539 | C30: =KPIs!C36 -> 0.6386 | D30: =KPIs!D36 -> 0.657758 | E30: =KPIs!E36 -> 0.67749074 | F30: =KPIs!F36 -> 0.69781546
A31: Boarding revenue per available run-night | B31: =KPIs!B43 -> 25.04645 | C31: =KPIs!C43 -> 36.17669 | D31: =KPIs!D43 -> 38.37985 | E31: =KPIs!E43 -> 40.717183 | F31: =KPIs!F43 -> 43.19686
A32: Team (FTE, year end) | B32: =INDEX(Headcount!$C$11:$BJ$11,B$27*12) -> 8 | C32: =INDEX(Headcount!$C$11:$BJ$11,C$27*12) -> 8 | D32: =INDEX(Headcount!$C$11:$BJ$11,D$27*12) -> 8 | E32: =INDEX(Headcount!$C$11:$BJ$11,E$27*12) -> 8 | F32: =INDEX(Headcount!$C$11:$BJ$11,F$27*12) -> 8
A34: Funding & valuation ($'000) — active scenario
A35: Equity raised | F35: =Inputs!$E$71 -> 330000
A36: Loan drawn | F36: =Inputs!$E$72 -> 100000
A37: Funding required (incl. cash buffer) | F37: ='Break-even'!B12 -> 391499.66
A38: Funding surplus / (shortfall) | F38: ='Break-even'!B17 -> 38500.342
A39: ="Lowest cash balance (month "&'Break-even'!B6&")" -> Lowest cash balance (month 10) | F39: ='Break-even'!B18 -> 147500.34
A40: First month with positive EBITDA | F40: ='Break-even'!B21 -> 7
A41: Cash invested paid back | F41: ='Break-even'!B23 -> 42
A42: Enterprise value — perpetual growth | F42: =Valuation!B27 -> 254555.77
A43: Enterprise value — exit multiple | F43: =Valuation!C27 -> 292090.86
A44: Enterprise value — average | F44: =Valuation!B30 -> 273323.31

Sheet Summary
A1: Financial statements summary | U1: =HYPERLINK("#'Cover'!A1","◂ Contents") -> ◂ Contents
A2: Pet grooming & boarding financial model (planning) | P2: Select detailed year: | R2: 1
A5: Income statement ($'000) — by year | H5: ="Income statement ($'000) — Year "&$R$2&", by month" -> Income statement ($'000) — Year 1, by month
B6: 1 | C6: 2 | D6: 3 | E6: 4 | F6: 5 | H6: =INDEX(Monthly!$C$4:$BJ$4,($R$2-1)*12+1) -> 1 | I6: =INDEX(Monthly!$C$4:$BJ$4,($R$2-1)*12+2) -> 2 | J6: =INDEX(Monthly!$C$4:$BJ$4,($R$2-1)*12+3) -> 3 | K6: =INDEX(Monthly!$C$4:$BJ$4,($R$2-1)*12+4) -> 4 | L6: =INDEX(Monthly!$C$4:$BJ$4,($R$2-1)*12+5) -> 5 | M6: =INDEX(Monthly!$C$4:$BJ$4,($R$2-1)*12+6) -> 6 | N6: =INDEX(Monthly!$C$4:$BJ$4,($R$2-1)*12+7) -> 7 | O6: =INDEX(Monthly!$C$4:$BJ$4,($R$2-1)*12+8) -> 8 | P6: =INDEX(Monthly!$C$4:$BJ$4,($R$2-1)*12+9) -> 9 | Q6: =INDEX(Monthly!$C$4:$BJ$4,($R$2-1)*12+10) -> 10 | R6: =INDEX(Monthly!$C$4:$BJ$4,($R$2-1)*12+11) -> 11 | S6: =INDEX(Monthly!$C$4:$BJ$4,($R$2-1)*12+12) -> 12
A7: Revenue | B7: ='P&L'!B5 -> 574501.95 | C7: ='P&L'!C5 -> 835486.76 | D7: ='P&L'!D5 -> 886367.9 | E7: ='P&L'!E5 -> 940347.71 | F7: ='P&L'!F5 -> 997614.88 | H7: =INDEX(Monthly!$C$31:$BJ$31,($R$2-1)*12+1) -> 25006.912 | I7: =INDEX(Monthly!$C$31:$BJ$31,($R$2-1)*12+2) -> 28757.949 | J7: =INDEX(Monthly!$C$31:$BJ$31,($R$2-1)*12+3) -> 32508.986 | K7: =INDEX(Monthly!$C$31:$BJ$31,($R$2-1)*12+4) -> 36260.022 | L7: =INDEX(Monthly!$C$31:$BJ$31,($R$2-1)*12+5) -> 40011.059 | M7: =INDEX(Monthly!$C$31:$BJ$31,($R$2-1)*12+6) -> 50292.928 | N7: =INDEX(Monthly!$C$31:$BJ$31,($R$2-1)*12+7) -> 54603.75 | O7: =INDEX(Monthly!$C$31:$BJ$31,($R$2-1)*12+8) -> 58914.573 | P7: =INDEX(Monthly!$C$31:$BJ$31,($R$2-1)*12+9) -> 55015.206 | Q7: =INDEX(Monthly!$C$31:$BJ$31,($R$2-1)*12+10) -> 58766.243 | R7: =INDEX(Monthly!$C$31:$BJ$31,($R$2-1)*12+11) -> 62517.28 | S7: =INDEX(Monthly!$C$31:$BJ$31,($R$2-1)*12+12) -> 71847.04
A8: Cost of sales | B8: ='P&L'!B6 -> -204565.29 | C8: ='P&L'!C6 -> -278844.28 | D8: ='P&L'!D6 -> -294361.85 | E8: ='P&L'!E6 -> -310780.52 | F8: ='P&L'!F6 -> -328153.86 | H8: =INDEX(Monthly!$C$39:$BJ$39,($R$2-1)*12+1) -> -10970.204 | I8: =INDEX(Monthly!$C$39:$BJ$39,($R$2-1)*12+2) -> -12040.734 | J8: =INDEX(Monthly!$C$39:$BJ$39,($R$2-1)*12+3) -> -13111.265 | K8: =INDEX(Monthly!$C$39:$BJ$39,($R$2-1)*12+4) -> -14181.795 | L8: =INDEX(Monthly!$C$39:$BJ$39,($R$2-1)*12+5) -> -15252.326 | M8: =INDEX(Monthly!$C$39:$BJ$39,($R$2-1)*12+6) -> -17035.311 | N8: =INDEX(Monthly!$C$39:$BJ$39,($R$2-1)*12+7) -> -18166.909 | O8: =INDEX(Monthly!$C$39:$BJ$39,($R$2-1)*12+8) -> -19298.507 | P8: =INDEX(Monthly!$C$39:$BJ$39,($R$2-1)*12+9) -> -19534.448 | Q8: =INDEX(Monthly!$C$39:$BJ$39,($R$2-1)*12+10) -> -20604.979 | R8: =INDEX(Monthly!$C$39:$BJ$39,($R$2-1)*12+11) -> -21675.509 | S8: =INDEX(Monthly!$C$39:$BJ$39,($R$2-1)*12+12) -> -22693.301
A9: Gross profit | B9: ='P&L'!B7 -> 369936.66 | C9: ='P&L'!C7 -> 556642.48 | D9: ='P&L'!D7 -> 592006.05 | E9: ='P&L'!E7 -> 629567.18 | F9: ='P&L'!F7 -> 669461.03 | H9: =INDEX(Monthly!$C$40:$BJ$40,($R$2-1)*12+1) -> 14036.708 | I9: =INDEX(Monthly!$C$40:$BJ$40,($R$2-1)*12+2) -> 16717.215 | J9: =INDEX(Monthly!$C$40:$BJ$40,($R$2-1)*12+3) -> 19397.721 | K9: =INDEX(Monthly!$C$40:$BJ$40,($R$2-1)*12+4) -> 22078.227 | L9: =INDEX(Monthly!$C$40:$BJ$40,($R$2-1)*12+5) -> 24758.733 | M9: =INDEX(Monthly!$C$40:$BJ$40,($R$2-1)*12+6) -> 33257.617 | N9: =INDEX(Monthly!$C$40:$BJ$40,($R$2-1)*12+7) -> 36436.841 | O9: =INDEX(Monthly!$C$40:$BJ$40,($R$2-1)*12+8) -> 39616.066 | P9: =INDEX(Monthly!$C$40:$BJ$40,($R$2-1)*12+9) -> 35480.758 | Q9: =INDEX(Monthly!$C$40:$BJ$40,($R$2-1)*12+10) -> 38161.264 | R9: =INDEX(Monthly!$C$40:$BJ$40,($R$2-1)*12+11) -> 40841.771 | S9: =INDEX(Monthly!$C$40:$BJ$40,($R$2-1)*12+12) -> 49153.739
A10: Gross margin | B10: ='P&L'!B8 -> 0.64392586 | C10: ='P&L'!C8 -> 0.66624932 | D10: ='P&L'!D8 -> 0.66790105 | E10: ='P&L'!E8 -> 0.66950467 | F10: ='P&L'!F8 -> 0.67106159 | H10: =IF(H7=0,0,H9/H7) -> 0.56131314 | I10: =IF(I7=0,0,I9/I7) -> 0.58130761 | J10: =IF(J7=0,0,J9/J7) -> 0.59668797 | K10: =IF(K7=0,0,K9/K7) -> 0.60888619 | L10: =IF(L7=0,0,L9/L7) -> 0.61879725 | M10: =IF(M7=0,0,M9/M7) -> 0.6612782 | N10: =IF(N7=0,0,N9/N7) -> 0.66729558 | O10: =IF(O7=0,0,O9/O7) -> 0.67243237 | ... S10: =IF(S7=0,0,S9/S7) -> 0.68414424
A11: Total operating expenses | B11: ='P&L'!B15 -> -434085.06 | C11: ='P&L'!C15 -> -444760.1 | D11: ='P&L'!D15 -> -451149.4 | E11: ='P&L'!E15 -> -459323.15 | F11: ='P&L'!F15 -> -469028.62 | H11: =INDEX(Monthly!$C$49:$BJ$49,($R$2-1)*12+1) -> -35487.707 | I11: =INDEX(Monthly!$C$49:$BJ$49,($R$2-1)*12+2) -> -35600.238 | J11: =INDEX(Monthly!$C$49:$BJ$49,($R$2-1)*12+3) -> -35712.77 | K11: =INDEX(Monthly!$C$49:$BJ$49,($R$2-1)*12+4) -> -35825.301 | L11: =INDEX(Monthly!$C$49:$BJ$49,($R$2-1)*12+5) -> -35937.832 | M11: =INDEX(Monthly!$C$49:$BJ$49,($R$2-1)*12+6) -> -36246.288 | N11: =INDEX(Monthly!$C$49:$BJ$49,($R$2-1)*12+7) -> -36375.613 | O11: =INDEX(Monthly!$C$49:$BJ$49,($R$2-1)*12+8) -> -36504.937 | P11: =INDEX(Monthly!$C$49:$BJ$49,($R$2-1)*12+9) -> -36387.956 | Q11: =INDEX(Monthly!$C$49:$BJ$49,($R$2-1)*12+10) -> -36500.487 | R11: =INDEX(Monthly!$C$49:$BJ$49,($R$2-1)*12+11) -> -36613.018 | S11: =INDEX(Monthly!$C$49:$BJ$49,($R$2-1)*12+12) -> -36892.911
A12: EBITDA | B12: ='P&L'!B16 -> -64148.399 | C12: ='P&L'!C16 -> 111882.38 | D12: ='P&L'!D16 -> 140856.65 | E12: ='P&L'!E16 -> 170244.04 | F12: ='P&L'!F16 -> 200432.4 | H12: =INDEX(Monthly!$C$50:$BJ$50,($R$2-1)*12+1) -> -21450.999 | I12: =INDEX(Monthly!$C$50:$BJ$50,($R$2-1)*12+2) -> -18883.024 | J12: =INDEX(Monthly!$C$50:$BJ$50,($R$2-1)*12+3) -> -16315.049 | K12: =INDEX(Monthly!$C$50:$BJ$50,($R$2-1)*12+4) -> -13747.074 | L12: =INDEX(Monthly!$C$50:$BJ$50,($R$2-1)*12+5) -> -11179.099 | M12: =INDEX(Monthly!$C$50:$BJ$50,($R$2-1)*12+6) -> -2988.6708 | N12: =INDEX(Monthly!$C$50:$BJ$50,($R$2-1)*12+7) -> 61.228875 | O12: =INDEX(Monthly!$C$50:$BJ$50,($R$2-1)*12+8) -> 3111.1285 | P12: =INDEX(Monthly!$C$50:$BJ$50,($R$2-1)*12+9) -> -907.19801 | Q12: =INDEX(Monthly!$C$50:$BJ$50,($R$2-1)*12+10) -> 1660.7771 | R12: =INDEX(Monthly!$C$50:$BJ$50,($R$2-1)*12+11) -> 4228.7523 | S12: =INDEX(Monthly!$C$50:$BJ$50,($R$2-1)*12+12) -> 12260.827
A13: EBITDA margin | B13: ='P&L'!B17 -> -0.11165915 | C13: ='P&L'!C17 -> 0.13391281 | D13: ='P&L'!D17 -> 0.15891443 | E13: ='P&L'!E17 -> 0.18104371 | F13: ='P&L'!F17 -> 0.2009116 | H13: =IF(H7=0,0,H12/H7) -> -0.8578028 | I13: =IF(I7=0,0,I12/I7) -> -0.65661929 | J13: =IF(J7=0,0,J12/J7) -> -0.50186275 | K13: =IF(K7=0,0,K12/K7) -> -0.3791248 | L13: =IF(L7=0,0,L12/L7) -> -0.27940022 | M13: =IF(M7=0,0,M12/M7) -> -0.059425269 | N13: =IF(N7=0,0,N12/N7) -> 0.0011213309 | O13: =IF(O7=0,0,O12/O7) -> 0.052807453 | ... S13: =IF(S7=0,0,S12/S7) -> 0.17065181
A14: Depreciation | B14: ='P&L'!B18 -> -23625 | C14: ='P&L'!C18 -> -24875 | D14: ='P&L'!D18 -> -26125 | E14: ='P&L'!E18 -> -27375 | F14: ='P&L'!F18 -> -28625 | H14: =INDEX(Monthly!$C$70:$BJ$70,($R$2-1)*12+1) -> -1968.75 | I14: =INDEX(Monthly!$C$70:$BJ$70,($R$2-1)*12+2) -> -1968.75 | J14: =INDEX(Monthly!$C$70:$BJ$70,($R$2-1)*12+3) -> -1968.75 | K14: =INDEX(Monthly!$C$70:$BJ$70,($R$2-1)*12+4) -> -1968.75 | L14: =INDEX(Monthly!$C$70:$BJ$70,($R$2-1)*12+5) -> -1968.75 | M14: =INDEX(Monthly!$C$70:$BJ$70,($R$2-1)*12+6) -> -1968.75 | N14: =INDEX(Monthly!$C$70:$BJ$70,($R$2-1)*12+7) -> -1968.75 | O14: =INDEX(Monthly!$C$70:$BJ$70,($R$2-1)*12+8) -> -1968.75 | P14: =INDEX(Monthly!$C$70:$BJ$70,($R$2-1)*12+9) -> -1968.75 | Q14: =INDEX(Monthly!$C$70:$BJ$70,($R$2-1)*12+10) -> -1968.75 | R14: =INDEX(Monthly!$C$70:$BJ$70,($R$2-1)*12+11) -> -1968.75 | S14: =INDEX(Monthly!$C$70:$BJ$70,($R$2-1)*12+12) -> -1968.75
A15: EBIT | B15: ='P&L'!B19 -> -87773.399 | C15: ='P&L'!C19 -> 87007.379 | D15: ='P&L'!D19 -> 114731.65 | E15: ='P&L'!E19 -> 142869.04 | F15: ='P&L'!F19 -> 171807.4 | H15: =INDEX(Monthly!$C$53:$BJ$53,($R$2-1)*12+1) -> -23419.749 | I15: =INDEX(Monthly!$C$53:$BJ$53,($R$2-1)*12+2) -> -20851.774 | J15: =INDEX(Monthly!$C$53:$BJ$53,($R$2-1)*12+3) -> -18283.799 | K15: =INDEX(Monthly!$C$53:$BJ$53,($R$2-1)*12+4) -> -15715.824 | L15: =INDEX(Monthly!$C$53:$BJ$53,($R$2-1)*12+5) -> -13147.849 | M15: =INDEX(Monthly!$C$53:$BJ$53,($R$2-1)*12+6) -> -4957.4208 | N15: =INDEX(Monthly!$C$53:$BJ$53,($R$2-1)*12+7) -> -1907.5211 | O15: =INDEX(Monthly!$C$53:$BJ$53,($R$2-1)*12+8) -> 1142.3785 | P15: =INDEX(Monthly!$C$53:$BJ$53,($R$2-1)*12+9) -> -2875.948 | Q15: =INDEX(Monthly!$C$53:$BJ$53,($R$2-1)*12+10) -> -307.97287 | R15: =INDEX(Monthly!$C$53:$BJ$53,($R$2-1)*12+11) -> 2260.0023 | S15: =INDEX(Monthly!$C$53:$BJ$53,($R$2-1)*12+12) -> 10292.077
A16: Interest | B16: ='P&L'!B20 -> -8243.75 | C16: ='P&L'!C20 -> -6450 | D16: ='P&L'!D20 -> -4650 | E16: ='P&L'!E20 -> -2850 | F16: ='P&L'!F20 -> -1050 | H16: =INDEX(Monthly!$C$54:$BJ$54,($R$2-1)*12+1) -> -750 | I16: =INDEX(Monthly!$C$54:$BJ$54,($R$2-1)*12+2) -> -743.75 | J16: =INDEX(Monthly!$C$54:$BJ$54,($R$2-1)*12+3) -> -731.25 | K16: =INDEX(Monthly!$C$54:$BJ$54,($R$2-1)*12+4) -> -718.75 | L16: =INDEX(Monthly!$C$54:$BJ$54,($R$2-1)*12+5) -> -706.25 | M16: =INDEX(Monthly!$C$54:$BJ$54,($R$2-1)*12+6) -> -693.75 | N16: =INDEX(Monthly!$C$54:$BJ$54,($R$2-1)*12+7) -> -681.25 | O16: =INDEX(Monthly!$C$54:$BJ$54,($R$2-1)*12+8) -> -668.75 | P16: =INDEX(Monthly!$C$54:$BJ$54,($R$2-1)*12+9) -> -656.25 | Q16: =INDEX(Monthly!$C$54:$BJ$54,($R$2-1)*12+10) -> -643.75 | R16: =INDEX(Monthly!$C$54:$BJ$54,($R$2-1)*12+11) -> -631.25 | S16: =INDEX(Monthly!$C$54:$BJ$54,($R$2-1)*12+12) -> -618.75
A17: Pre-tax income | B17: ='P&L'!B21 -> -96017.149 | C17: ='P&L'!C21 -> 80557.379 | D17: ='P&L'!D21 -> 110081.65 | E17: ='P&L'!E21 -> 140019.04 | F17: ='P&L'!F21 -> 170757.4 | H17: =INDEX(Monthly!$C$55:$BJ$55,($R$2-1)*12+1) -> -24169.749 | I17: =INDEX(Monthly!$C$55:$BJ$55,($R$2-1)*12+2) -> -21595.524 | J17: =INDEX(Monthly!$C$55:$BJ$55,($R$2-1)*12+3) -> -19015.049 | K17: =INDEX(Monthly!$C$55:$BJ$55,($R$2-1)*12+4) -> -16434.574 | L17: =INDEX(Monthly!$C$55:$BJ$55,($R$2-1)*12+5) -> -13854.099 | M17: =INDEX(Monthly!$C$55:$BJ$55,($R$2-1)*12+6) -> -5651.1708 | N17: =INDEX(Monthly!$C$55:$BJ$55,($R$2-1)*12+7) -> -2588.7711 | O17: =INDEX(Monthly!$C$55:$BJ$55,($R$2-1)*12+8) -> 473.62852 | P17: =INDEX(Monthly!$C$55:$BJ$55,($R$2-1)*12+9) -> -3532.198 | Q17: =INDEX(Monthly!$C$55:$BJ$55,($R$2-1)*12+10) -> -951.72287 | R17: =INDEX(Monthly!$C$55:$BJ$55,($R$2-1)*12+11) -> 1628.7523 | S17: =INDEX(Monthly!$C$55:$BJ$55,($R$2-1)*12+12) -> 9673.3275
A18: Income tax | B18: ='P&L'!B22 -> 0 | C18: ='P&L'!C22 -> 0 | D18: ='P&L'!D22 -> -19870.594 | E18: ='P&L'!E22 -> -29403.997 | F18: ='P&L'!F22 -> -35859.054 | H18: =INDEX(Monthly!$C$58:$BJ$58,($R$2-1)*12+1) -> 0 | I18: =INDEX(Monthly!$C$58:$BJ$58,($R$2-1)*12+2) -> 0 | J18: =INDEX(Monthly!$C$58:$BJ$58,($R$2-1)*12+3) -> 0 | K18: =INDEX(Monthly!$C$58:$BJ$58,($R$2-1)*12+4) -> 0 | L18: =INDEX(Monthly!$C$58:$BJ$58,($R$2-1)*12+5) -> 0 | M18: =INDEX(Monthly!$C$58:$BJ$58,($R$2-1)*12+6) -> 0 | N18: =INDEX(Monthly!$C$58:$BJ$58,($R$2-1)*12+7) -> 0 | O18: =INDEX(Monthly!$C$58:$BJ$58,($R$2-1)*12+8) -> 0 | P18: =INDEX(Monthly!$C$58:$BJ$58,($R$2-1)*12+9) -> 0 | Q18: =INDEX(Monthly!$C$58:$BJ$58,($R$2-1)*12+10) -> 0 | R18: =INDEX(Monthly!$C$58:$BJ$58,($R$2-1)*12+11) -> 0 | S18: =INDEX(Monthly!$C$58:$BJ$58,($R$2-1)*12+12) -> 0
A19: Net income | B19: ='P&L'!B23 -> -96017.149 | C19: ='P&L'!C23 -> 80557.379 | D19: ='P&L'!D23 -> 90211.054 | E19: ='P&L'!E23 -> 110615.04 | F19: ='P&L'!F23 -> 134898.35 | H19: =INDEX(Monthly!$C$59:$BJ$59,($R$2-1)*12+1) -> -24169.749 | I19: =INDEX(Monthly!$C$59:$BJ$59,($R$2-1)*12+2) -> -21595.524 | J19: =INDEX(Monthly!$C$59:$BJ$59,($R$2-1)*12+3) -> -19015.049 | K19: =INDEX(Monthly!$C$59:$BJ$59,($R$2-1)*12+4) -> -16434.574 | L19: =INDEX(Monthly!$C$59:$BJ$59,($R$2-1)*12+5) -> -13854.099 | M19: =INDEX(Monthly!$C$59:$BJ$59,($R$2-1)*12+6) -> -5651.1708 | N19: =INDEX(Monthly!$C$59:$BJ$59,($R$2-1)*12+7) -> -2588.7711 | O19: =INDEX(Monthly!$C$59:$BJ$59,($R$2-1)*12+8) -> 473.62852 | P19: =INDEX(Monthly!$C$59:$BJ$59,($R$2-1)*12+9) -> -3532.198 | Q19: =INDEX(Monthly!$C$59:$BJ$59,($R$2-1)*12+10) -> -951.72287 | R19: =INDEX(Monthly!$C$59:$BJ$59,($R$2-1)*12+11) -> 1628.7523 | S19: =INDEX(Monthly!$C$59:$BJ$59,($R$2-1)*12+12) -> 9673.3275
A20: Net margin | B20: ='P&L'!B24 -> -0.16713111 | C20: ='P&L'!C24 -> 0.096419695 | D20: ='P&L'!D24 -> 0.10177608 | E20: ='P&L'!E24 -> 0.11763206 | F20: ='P&L'!F24 -> 0.13522087 | H20: =IF(H7=0,0,H19/H7) -> -0.96652274 | I20: =IF(I7=0,0,I19/I7) -> -0.75094104 | J20: =IF(J7=0,0,J19/J7) -> -0.58491671 | K20: =IF(K7=0,0,K19/K7) -> -0.45324224 | L20: =IF(L7=0,0,L19/L7) -> -0.34625673 | M20: =IF(M7=0,0,M19/M7) -> -0.11236512 | N20: =IF(N7=0,0,N19/N7) -> -0.047410134 | O20: =IF(O7=0,0,O19/O7) -> 0.0080392422 | ... S20: =IF(S7=0,0,S19/S7) -> 0.1346378
A22: Cash flow ($'000) — by year | H22: ="Cash flow ($'000) — Year "&$R$2&", by month" -> Cash flow ($'000) — Year 1, by month
B23: 1 | C23: 2 | D23: 3 | E23: 4 | F23: 5 | H23: =INDEX(Monthly!$C$4:$BJ$4,($R$2-1)*12+1) -> 1 | I23: =INDEX(Monthly!$C$4:$BJ$4,($R$2-1)*12+2) -> 2 | J23: =INDEX(Monthly!$C$4:$BJ$4,($R$2-1)*12+3) -> 3 | K23: =INDEX(Monthly!$C$4:$BJ$4,($R$2-1)*12+4) -> 4 | L23: =INDEX(Monthly!$C$4:$BJ$4,($R$2-1)*12+5) -> 5 | M23: =INDEX(Monthly!$C$4:$BJ$4,($R$2-1)*12+6) -> 6 | N23: =INDEX(Monthly!$C$4:$BJ$4,($R$2-1)*12+7) -> 7 | O23: =INDEX(Monthly!$C$4:$BJ$4,($R$2-1)*12+8) -> 8 | P23: =INDEX(Monthly!$C$4:$BJ$4,($R$2-1)*12+9) -> 9 | Q23: =INDEX(Monthly!$C$4:$BJ$4,($R$2-1)*12+10) -> 10 | R23: =INDEX(Monthly!$C$4:$BJ$4,($R$2-1)*12+11) -> 11 | S23: =INDEX(Monthly!$C$4:$BJ$4,($R$2-1)*12+12) -> 12
A24: Operating cash flow | B24: ='Cash Flow'!B10 -> -62809.527 | C24: ='Cash Flow'!C10 -> 105940.94 | D24: ='Cash Flow'!D10 -> 116873.34 | E24: ='Cash Flow'!E10 -> 138557.72 | F24: ='Cash Flow'!F10 -> 164123.22 | H24: =INDEX(Monthly!$C$89:$BJ$89,($R$2-1)*12+1) -> -16920.331 | I24: =INDEX(Monthly!$C$89:$BJ$89,($R$2-1)*12+2) -> -19198.84 | J24: =INDEX(Monthly!$C$89:$BJ$89,($R$2-1)*12+3) -> -16618.365 | K24: =INDEX(Monthly!$C$89:$BJ$89,($R$2-1)*12+4) -> -14037.89 | L24: =INDEX(Monthly!$C$89:$BJ$89,($R$2-1)*12+5) -> -11457.415 | M24: =INDEX(Monthly!$C$89:$BJ$89,($R$2-1)*12+6) -> -3238.6549 | N24: =INDEX(Monthly!$C$89:$BJ$89,($R$2-1)*12+7) -> -190.7305 | O24: =INDEX(Monthly!$C$89:$BJ$89,($R$2-1)*12+8) -> 2871.6691 | P24: =INDEX(Monthly!$C$89:$BJ$89,($R$2-1)*12+9) -> -1154.0609 | Q24: =INDEX(Monthly!$C$89:$BJ$89,($R$2-1)*12+10) -> 1444.9607 | R24: =INDEX(Monthly!$C$89:$BJ$89,($R$2-1)*12+11) -> 4025.4358 | S24: =INDEX(Monthly!$C$89:$BJ$89,($R$2-1)*12+12) -> 11664.695
A25: Capital spending | B25: ='Cash Flow'!B11 -> -189000 | C25: ='Cash Flow'!C11 -> -10000 | D25: ='Cash Flow'!D11 -> -10000 | E25: ='Cash Flow'!E11 -> -10000 | F25: ='Cash Flow'!F11 -> -10000 | H25: =INDEX(Monthly!$C$90:$BJ$90,($R$2-1)*12+1) -> -189000 | I25: =INDEX(Monthly!$C$90:$BJ$90,($R$2-1)*12+2) -> 0 | J25: =INDEX(Monthly!$C$90:$BJ$90,($R$2-1)*12+3) -> 0 | K25: =INDEX(Monthly!$C$90:$BJ$90,($R$2-1)*12+4) -> 0 | L25: =INDEX(Monthly!$C$90:$BJ$90,($R$2-1)*12+5) -> 0 | M25: =INDEX(Monthly!$C$90:$BJ$90,($R$2-1)*12+6) -> 0 | N25: =INDEX(Monthly!$C$90:$BJ$90,($R$2-1)*12+7) -> 0 | O25: =INDEX(Monthly!$C$90:$BJ$90,($R$2-1)*12+8) -> 0 | P25: =INDEX(Monthly!$C$90:$BJ$90,($R$2-1)*12+9) -> 0 | Q25: =INDEX(Monthly!$C$90:$BJ$90,($R$2-1)*12+10) -> 0 | R25: =INDEX(Monthly!$C$90:$BJ$90,($R$2-1)*12+11) -> 0 | S25: =INDEX(Monthly!$C$90:$BJ$90,($R$2-1)*12+12) -> 0
A26: Equity raised | B26: ='Cash Flow'!B12 -> 330000 | C26: ='Cash Flow'!C12 -> 0 | D26: ='Cash Flow'!D12 -> 0 | E26: ='Cash Flow'!E12 -> 0 | F26: ='Cash Flow'!F12 -> 0 | H26: =INDEX(Monthly!$C$91:$BJ$91,($R$2-1)*12+1) -> 330000 | I26: =INDEX(Monthly!$C$91:$BJ$91,($R$2-1)*12+2) -> 0 | J26: =INDEX(Monthly!$C$91:$BJ$91,($R$2-1)*12+3) -> 0 | K26: =INDEX(Monthly!$C$91:$BJ$91,($R$2-1)*12+4) -> 0 | L26: =INDEX(Monthly!$C$91:$BJ$91,($R$2-1)*12+5) -> 0 | M26: =INDEX(Monthly!$C$91:$BJ$91,($R$2-1)*12+6) -> 0 | N26: =INDEX(Monthly!$C$91:$BJ$91,($R$2-1)*12+7) -> 0 | O26: =INDEX(Monthly!$C$91:$BJ$91,($R$2-1)*12+8) -> 0 | P26: =INDEX(Monthly!$C$91:$BJ$91,($R$2-1)*12+9) -> 0 | Q26: =INDEX(Monthly!$C$91:$BJ$91,($R$2-1)*12+10) -> 0 | R26: =INDEX(Monthly!$C$91:$BJ$91,($R$2-1)*12+11) -> 0 | S26: =INDEX(Monthly!$C$91:$BJ$91,($R$2-1)*12+12) -> 0
A27: Loan drawdown | B27: ='Cash Flow'!B13 -> 100000 | C27: ='Cash Flow'!C13 -> 0 | D27: ='Cash Flow'!D13 -> 0 | E27: ='Cash Flow'!E13 -> 0 | F27: ='Cash Flow'!F13 -> 0 | H27: =INDEX(Monthly!$C$76:$BJ$76,($R$2-1)*12+1) -> 100000 | I27: =INDEX(Monthly!$C$76:$BJ$76,($R$2-1)*12+2) -> 0 | J27: =INDEX(Monthly!$C$76:$BJ$76,($R$2-1)*12+3) -> 0 | K27: =INDEX(Monthly!$C$76:$BJ$76,($R$2-1)*12+4) -> 0 | L27: =INDEX(Monthly!$C$76:$BJ$76,($R$2-1)*12+5) -> 0 | M27: =INDEX(Monthly!$C$76:$BJ$76,($R$2-1)*12+6) -> 0 | N27: =INDEX(Monthly!$C$76:$BJ$76,($R$2-1)*12+7) -> 0 | O27: =INDEX(Monthly!$C$76:$BJ$76,($R$2-1)*12+8) -> 0 | P27: =INDEX(Monthly!$C$76:$BJ$76,($R$2-1)*12+9) -> 0 | Q27: =INDEX(Monthly!$C$76:$BJ$76,($R$2-1)*12+10) -> 0 | R27: =INDEX(Monthly!$C$76:$BJ$76,($R$2-1)*12+11) -> 0 | S27: =INDEX(Monthly!$C$76:$BJ$76,($R$2-1)*12+12) -> 0
A28: Loan repayment | B28: ='Cash Flow'!B14 -> -18333.333 | C28: ='Cash Flow'!C14 -> -20000 | D28: ='Cash Flow'!D14 -> -20000 | E28: ='Cash Flow'!E14 -> -20000 | F28: ='Cash Flow'!F14 -> -20000 | H28: =INDEX(Monthly!$C$77:$BJ$77,($R$2-1)*12+1) -> 0 | I28: =INDEX(Monthly!$C$77:$BJ$77,($R$2-1)*12+2) -> -1666.6667 | J28: =INDEX(Monthly!$C$77:$BJ$77,($R$2-1)*12+3) -> -1666.6667 | K28: =INDEX(Monthly!$C$77:$BJ$77,($R$2-1)*12+4) -> -1666.6667 | L28: =INDEX(Monthly!$C$77:$BJ$77,($R$2-1)*12+5) -> -1666.6667 | M28: =INDEX(Monthly!$C$77:$BJ$77,($R$2-1)*12+6) -> -1666.6667 | N28: =INDEX(Monthly!$C$77:$BJ$77,($R$2-1)*12+7) -> -1666.6667 | O28: =INDEX(Monthly!$C$77:$BJ$77,($R$2-1)*12+8) -> -1666.6667 | P28: =INDEX(Monthly!$C$77:$BJ$77,($R$2-1)*12+9) -> -1666.6667 | Q28: =INDEX(Monthly!$C$77:$BJ$77,($R$2-1)*12+10) -> -1666.6667 | R28: =INDEX(Monthly!$C$77:$BJ$77,($R$2-1)*12+11) -> -1666.6667 | S28: =INDEX(Monthly!$C$77:$BJ$77,($R$2-1)*12+12) -> -1666.6667
A29: Financing cash flow | B29: ='Cash Flow'!B15 -> 411666.67 | C29: ='Cash Flow'!C15 -> -20000 | D29: ='Cash Flow'!D15 -> -20000 | E29: ='Cash Flow'!E15 -> -20000 | F29: ='Cash Flow'!F15 -> -20000 | H29: =INDEX(Monthly!$C$92:$BJ$92,($R$2-1)*12+1) -> 430000 | I29: =INDEX(Monthly!$C$92:$BJ$92,($R$2-1)*12+2) -> -1666.6667 | J29: =INDEX(Monthly!$C$92:$BJ$92,($R$2-1)*12+3) -> -1666.6667 | K29: =INDEX(Monthly!$C$92:$BJ$92,($R$2-1)*12+4) -> -1666.6667 | L29: =INDEX(Monthly!$C$92:$BJ$92,($R$2-1)*12+5) -> -1666.6667 | M29: =INDEX(Monthly!$C$92:$BJ$92,($R$2-1)*12+6) -> -1666.6667 | N29: =INDEX(Monthly!$C$92:$BJ$92,($R$2-1)*12+7) -> -1666.6667 | O29: =INDEX(Monthly!$C$92:$BJ$92,($R$2-1)*12+8) -> -1666.6667 | P29: =INDEX(Monthly!$C$92:$BJ$92,($R$2-1)*12+9) -> -1666.6667 | Q29: =INDEX(Monthly!$C$92:$BJ$92,($R$2-1)*12+10) -> -1666.6667 | R29: =INDEX(Monthly!$C$92:$BJ$92,($R$2-1)*12+11) -> -1666.6667 | S29: =INDEX(Monthly!$C$92:$BJ$92,($R$2-1)*12+12) -> -1666.6667
A30: Net change in cash | B30: ='Cash Flow'!B16 -> 159857.14 | C30: ='Cash Flow'!C16 -> 75940.942 | D30: ='Cash Flow'!D16 -> 86873.338 | E30: ='Cash Flow'!E16 -> 108557.72 | F30: ='Cash Flow'!F16 -> 134123.22 | H30: =INDEX(Monthly!$C$93:$BJ$93,($R$2-1)*12+1) -> 224079.67 | I30: =INDEX(Monthly!$C$93:$BJ$93,($R$2-1)*12+2) -> -20865.507 | J30: =INDEX(Monthly!$C$93:$BJ$93,($R$2-1)*12+3) -> -18285.032 | K30: =INDEX(Monthly!$C$93:$BJ$93,($R$2-1)*12+4) -> -15704.557 | L30: =INDEX(Monthly!$C$93:$BJ$93,($R$2-1)*12+5) -> -13124.082 | M30: =INDEX(Monthly!$C$93:$BJ$93,($R$2-1)*12+6) -> -4905.3216 | N30: =INDEX(Monthly!$C$93:$BJ$93,($R$2-1)*12+7) -> -1857.3972 | O30: =INDEX(Monthly!$C$93:$BJ$93,($R$2-1)*12+8) -> 1205.0025 | P30: =INDEX(Monthly!$C$93:$BJ$93,($R$2-1)*12+9) -> -2820.7275 | Q30: =INDEX(Monthly!$C$93:$BJ$93,($R$2-1)*12+10) -> -221.70597 | R30: =INDEX(Monthly!$C$93:$BJ$93,($R$2-1)*12+11) -> 2358.7692 | S30: =INDEX(Monthly!$C$93:$BJ$93,($R$2-1)*12+12) -> 9998.0284
A31: Closing cash | B31: ='Cash Flow'!B18 -> 159857.14 | C31: ='Cash Flow'!C18 -> 235798.08 | D31: ='Cash Flow'!D18 -> 322671.42 | E31: ='Cash Flow'!E18 -> 431229.14 | F31: ='Cash Flow'!F18 -> 565352.36 | H31: =INDEX(Monthly!$C$95:$BJ$95,($R$2-1)*12+1) -> 224079.67 | I31: =INDEX(Monthly!$C$95:$BJ$95,($R$2-1)*12+2) -> 203214.16 | J31: =INDEX(Monthly!$C$95:$BJ$95,($R$2-1)*12+3) -> 184929.13 | K31: =INDEX(Monthly!$C$95:$BJ$95,($R$2-1)*12+4) -> 169224.57 | L31: =INDEX(Monthly!$C$95:$BJ$95,($R$2-1)*12+5) -> 156100.49 | M31: =INDEX(Monthly!$C$95:$BJ$95,($R$2-1)*12+6) -> 151195.17 | N31: =INDEX(Monthly!$C$95:$BJ$95,($R$2-1)*12+7) -> 149337.77 | O31: =INDEX(Monthly!$C$95:$BJ$95,($R$2-1)*12+8) -> 150542.78 | P31: =INDEX(Monthly!$C$95:$BJ$95,($R$2-1)*12+9) -> 147722.05 | Q31: =INDEX(Monthly!$C$95:$BJ$95,($R$2-1)*12+10) -> 147500.34 | R31: =INDEX(Monthly!$C$95:$BJ$95,($R$2-1)*12+11) -> 149859.11 | S31: =INDEX(Monthly!$C$95:$BJ$95,($R$2-1)*12+12) -> 159857.14
A39: Balance sheet at year end ($'000) | H39: ="Balance sheet at month end ($'000) — Year "&$R$2 -> Balance sheet at month end ($'000) — Year 1
B40: 1 | C40: 2 | D40: 3 | E40: 4 | F40: 5 | H40: =INDEX(Monthly!$C$4:$BJ$4,($R$2-1)*12+1) -> 1 | I40: =INDEX(Monthly!$C$4:$BJ$4,($R$2-1)*12+2) -> 2 | J40: =INDEX(Monthly!$C$4:$BJ$4,($R$2-1)*12+3) -> 3 | K40: =INDEX(Monthly!$C$4:$BJ$4,($R$2-1)*12+4) -> 4 | L40: =INDEX(Monthly!$C$4:$BJ$4,($R$2-1)*12+5) -> 5 | M40: =INDEX(Monthly!$C$4:$BJ$4,($R$2-1)*12+6) -> 6 | N40: =INDEX(Monthly!$C$4:$BJ$4,($R$2-1)*12+7) -> 7 | O40: =INDEX(Monthly!$C$4:$BJ$4,($R$2-1)*12+8) -> 8 | P40: =INDEX(Monthly!$C$4:$BJ$4,($R$2-1)*12+9) -> 9 | Q40: =INDEX(Monthly!$C$4:$BJ$4,($R$2-1)*12+10) -> 10 | R40: =INDEX(Monthly!$C$4:$BJ$4,($R$2-1)*12+11) -> 11 | S40: =INDEX(Monthly!$C$4:$BJ$4,($R$2-1)*12+12) -> 12
A41: Cash | B41: ='Balance Sheet'!B5 -> 159857.14 | C41: ='Balance Sheet'!C5 -> 235798.08 | D41: ='Balance Sheet'!D5 -> 322671.42 | E41: ='Balance Sheet'!E5 -> 431229.14 | F41: ='Balance Sheet'!F5 -> 565352.36 | H41: =INDEX(Monthly!$C$95:$BJ$95,($R$2-1)*12+1) -> 224079.67 | I41: =INDEX(Monthly!$C$95:$BJ$95,($R$2-1)*12+2) -> 203214.16 | J41: =INDEX(Monthly!$C$95:$BJ$95,($R$2-1)*12+3) -> 184929.13 | K41: =INDEX(Monthly!$C$95:$BJ$95,($R$2-1)*12+4) -> 169224.57 | L41: =INDEX(Monthly!$C$95:$BJ$95,($R$2-1)*12+5) -> 156100.49 | M41: =INDEX(Monthly!$C$95:$BJ$95,($R$2-1)*12+6) -> 151195.17 | N41: =INDEX(Monthly!$C$95:$BJ$95,($R$2-1)*12+7) -> 149337.77 | O41: =INDEX(Monthly!$C$95:$BJ$95,($R$2-1)*12+8) -> 150542.78 | P41: =INDEX(Monthly!$C$95:$BJ$95,($R$2-1)*12+9) -> 147722.05 | Q41: =INDEX(Monthly!$C$95:$BJ$95,($R$2-1)*12+10) -> 147500.34 | R41: =INDEX(Monthly!$C$95:$BJ$95,($R$2-1)*12+11) -> 149859.11 | S41: =INDEX(Monthly!$C$95:$BJ$95,($R$2-1)*12+12) -> 159857.14
A42: Accounts receivable | B42: ='Balance Sheet'!B6 -> 4789.8027 | C42: ='Balance Sheet'!C6 -> 5081.5016 | D42: ='Balance Sheet'!D6 -> 5390.9651 | E42: ='Balance Sheet'!E6 -> 5719.2749 | F42: ='Balance Sheet'!F6 -> 6067.5787 | H42: =INDEX(Monthly!$C$81:$BJ$81,($R$2-1)*12+1) -> 1667.1275 | I42: =INDEX(Monthly!$C$81:$BJ$81,($R$2-1)*12+2) -> 1917.1966 | J42: =INDEX(Monthly!$C$81:$BJ$81,($R$2-1)*12+3) -> 2167.2657 | K42: =INDEX(Monthly!$C$81:$BJ$81,($R$2-1)*12+4) -> 2417.3348 | L42: =INDEX(Monthly!$C$81:$BJ$81,($R$2-1)*12+5) -> 2667.4039 | M42: =INDEX(Monthly!$C$81:$BJ$81,($R$2-1)*12+6) -> 3352.8619 | N42: =INDEX(Monthly!$C$81:$BJ$81,($R$2-1)*12+7) -> 3640.25 | O42: =INDEX(Monthly!$C$81:$BJ$81,($R$2-1)*12+8) -> 3927.6382 | P42: =INDEX(Monthly!$C$81:$BJ$81,($R$2-1)*12+9) -> 3667.6804 | Q42: =INDEX(Monthly!$C$81:$BJ$81,($R$2-1)*12+10) -> 3917.7495 | R42: =INDEX(Monthly!$C$81:$BJ$81,($R$2-1)*12+11) -> 4167.8187 | S42: =INDEX(Monthly!$C$81:$BJ$81,($R$2-1)*12+12) -> 4789.8027
A43: Inventory | B43: ='Balance Sheet'!B7 -> 4538.6603 | C43: ='Balance Sheet'!C7 -> 4791.3747 | D43: ='Balance Sheet'!D7 -> 5058.7687 | E43: ='Balance Sheet'!E7 -> 5341.715 | F43: ='Balance Sheet'!F7 -> 5641.1387 | H43: =INDEX(Monthly!$C$82:$BJ$82,($R$2-1)*12+1) -> 2194.0407 | I43: =INDEX(Monthly!$C$82:$BJ$82,($R$2-1)*12+2) -> 2408.1469 | J43: =INDEX(Monthly!$C$82:$BJ$82,($R$2-1)*12+3) -> 2622.253 | K43: =INDEX(Monthly!$C$82:$BJ$82,($R$2-1)*12+4) -> 2836.3591 | L43: =INDEX(Monthly!$C$82:$BJ$82,($R$2-1)*12+5) -> 3050.4652 | M43: =INDEX(Monthly!$C$82:$BJ$82,($R$2-1)*12+6) -> 3407.0622 | N43: =INDEX(Monthly!$C$82:$BJ$82,($R$2-1)*12+7) -> 3633.3818 | O43: =INDEX(Monthly!$C$82:$BJ$82,($R$2-1)*12+8) -> 3859.7014 | P43: =INDEX(Monthly!$C$82:$BJ$82,($R$2-1)*12+9) -> 3906.8896 | Q43: =INDEX(Monthly!$C$82:$BJ$82,($R$2-1)*12+10) -> 4120.9958 | R43: =INDEX(Monthly!$C$82:$BJ$82,($R$2-1)*12+11) -> 4335.1019 | S43: =INDEX(Monthly!$C$82:$BJ$82,($R$2-1)*12+12) -> 4538.6603
A44: Net fixed assets | B44: ='Balance Sheet'!B8 -> 165375 | C44: ='Balance Sheet'!C8 -> 150500 | D44: ='Balance Sheet'!D8 -> 134375 | E44: ='Balance Sheet'!E8 -> 117000 | F44: ='Balance Sheet'!F8 -> 98375 | H44: =INDEX(Monthly!$C$72:$BJ$72,($R$2-1)*12+1) -> 187031.25 | I44: =INDEX(Monthly!$C$72:$BJ$72,($R$2-1)*12+2) -> 185062.5 | J44: =INDEX(Monthly!$C$72:$BJ$72,($R$2-1)*12+3) -> 183093.75 | K44: =INDEX(Monthly!$C$72:$BJ$72,($R$2-1)*12+4) -> 181125 | L44: =INDEX(Monthly!$C$72:$BJ$72,($R$2-1)*12+5) -> 179156.25 | M44: =INDEX(Monthly!$C$72:$BJ$72,($R$2-1)*12+6) -> 177187.5 | N44: =INDEX(Monthly!$C$72:$BJ$72,($R$2-1)*12+7) -> 175218.75 | O44: =INDEX(Monthly!$C$72:$BJ$72,($R$2-1)*12+8) -> 173250 | P44: =INDEX(Monthly!$C$72:$BJ$72,($R$2-1)*12+9) -> 171281.25 | Q44: =INDEX(Monthly!$C$72:$BJ$72,($R$2-1)*12+10) -> 169312.5 | R44: =INDEX(Monthly!$C$72:$BJ$72,($R$2-1)*12+11) -> 167343.75 | S44: =INDEX(Monthly!$C$72:$BJ$72,($R$2-1)*12+12) -> 165375
A45: Total assets | B45: ='Balance Sheet'!B9 -> 334560.6 | C45: ='Balance Sheet'!C9 -> 396170.96 | D45: ='Balance Sheet'!D9 -> 467496.15 | E45: ='Balance Sheet'!E9 -> 559290.13 | F45: ='Balance Sheet'!F9 -> 675436.08 | H45: =INDEX(Monthly!$C$109:$BJ$109,($R$2-1)*12+1) -> 414972.09 | I45: =INDEX(Monthly!$C$109:$BJ$109,($R$2-1)*12+2) -> 392602.01 | J45: =INDEX(Monthly!$C$109:$BJ$109,($R$2-1)*12+3) -> 372812.4 | K45: =INDEX(Monthly!$C$109:$BJ$109,($R$2-1)*12+4) -> 355603.27 | L45: =INDEX(Monthly!$C$109:$BJ$109,($R$2-1)*12+5) -> 340974.61 | M45: =INDEX(Monthly!$C$109:$BJ$109,($R$2-1)*12+6) -> 335142.59 | N45: =INDEX(Monthly!$C$109:$BJ$109,($R$2-1)*12+7) -> 331830.15 | O45: =INDEX(Monthly!$C$109:$BJ$109,($R$2-1)*12+8) -> 331580.12 | P45: =INDEX(Monthly!$C$109:$BJ$109,($R$2-1)*12+9) -> 326577.87 | Q45: =INDEX(Monthly!$C$109:$BJ$109,($R$2-1)*12+10) -> 324851.59 | R45: =INDEX(Monthly!$C$109:$BJ$109,($R$2-1)*12+11) -> 325705.78 | S45: =INDEX(Monthly!$C$109:$BJ$109,($R$2-1)*12+12) -> 334560.6
A46: Accounts payable | B46: ='Balance Sheet'!B10 -> 18911.084 | C46: ='Balance Sheet'!C10 -> 19964.061 | D46: ='Balance Sheet'!D10 -> 21078.203 | E46: ='Balance Sheet'!E10 -> 22257.146 | F46: ='Balance Sheet'!F10 -> 23504.745 | H46: =INDEX(Monthly!$C$83:$BJ$83,($R$2-1)*12+1) -> 9141.8364 | I46: =INDEX(Monthly!$C$83:$BJ$83,($R$2-1)*12+2) -> 10033.945 | J46: =INDEX(Monthly!$C$83:$BJ$83,($R$2-1)*12+3) -> 10926.054 | K46: =INDEX(Monthly!$C$83:$BJ$83,($R$2-1)*12+4) -> 11818.163 | L46: =INDEX(Monthly!$C$83:$BJ$83,($R$2-1)*12+5) -> 12710.272 | M46: =INDEX(Monthly!$C$83:$BJ$83,($R$2-1)*12+6) -> 14196.092 | N46: =INDEX(Monthly!$C$83:$BJ$83,($R$2-1)*12+7) -> 15139.091 | O46: =INDEX(Monthly!$C$83:$BJ$83,($R$2-1)*12+8) -> 16082.089 | P46: =INDEX(Monthly!$C$83:$BJ$83,($R$2-1)*12+9) -> 16278.707 | Q46: =INDEX(Monthly!$C$83:$BJ$83,($R$2-1)*12+10) -> 17170.816 | R46: =INDEX(Monthly!$C$83:$BJ$83,($R$2-1)*12+11) -> 18062.924 | S46: =INDEX(Monthly!$C$83:$BJ$83,($R$2-1)*12+12) -> 18911.084
A47: Loan | B47: ='Balance Sheet'!B11 -> 81666.667 | C47: ='Balance Sheet'!C11 -> 61666.667 | D47: ='Balance Sheet'!D11 -> 41666.667 | E47: ='Balance Sheet'!E11 -> 21666.667 | F47: ='Balance Sheet'!F11 -> 1666.6667 | H47: =INDEX(Monthly!$C$78:$BJ$78,($R$2-1)*12+1) -> 100000 | I47: =INDEX(Monthly!$C$78:$BJ$78,($R$2-1)*12+2) -> 98333.333 | J47: =INDEX(Monthly!$C$78:$BJ$78,($R$2-1)*12+3) -> 96666.667 | K47: =INDEX(Monthly!$C$78:$BJ$78,($R$2-1)*12+4) -> 95000 | L47: =INDEX(Monthly!$C$78:$BJ$78,($R$2-1)*12+5) -> 93333.333 | M47: =INDEX(Monthly!$C$78:$BJ$78,($R$2-1)*12+6) -> 91666.667 | N47: =INDEX(Monthly!$C$78:$BJ$78,($R$2-1)*12+7) -> 90000 | O47: =INDEX(Monthly!$C$78:$BJ$78,($R$2-1)*12+8) -> 88333.333 | P47: =INDEX(Monthly!$C$78:$BJ$78,($R$2-1)*12+9) -> 86666.667 | Q47: =INDEX(Monthly!$C$78:$BJ$78,($R$2-1)*12+10) -> 85000 | R47: =INDEX(Monthly!$C$78:$BJ$78,($R$2-1)*12+11) -> 83333.333 | S47: =INDEX(Monthly!$C$78:$BJ$78,($R$2-1)*12+12) -> 81666.667
A48: Total liabilities | B48: ='Balance Sheet'!B12 -> 100577.75 | C48: ='Balance Sheet'!C12 -> 81630.728 | D48: ='Balance Sheet'!D12 -> 62744.87 | E48: ='Balance Sheet'!E12 -> 43923.812 | F48: ='Balance Sheet'!F12 -> 25171.411 | H48: =INDEX(Monthly!$C$110:$BJ$110,($R$2-1)*12+1) -> 109141.84 | I48: =INDEX(Monthly!$C$110:$BJ$110,($R$2-1)*12+2) -> 108367.28 | J48: =INDEX(Monthly!$C$110:$BJ$110,($R$2-1)*12+3) -> 107592.72 | K48: =INDEX(Monthly!$C$110:$BJ$110,($R$2-1)*12+4) -> 106818.16 | L48: =INDEX(Monthly!$C$110:$BJ$110,($R$2-1)*12+5) -> 106043.6 | M48: =INDEX(Monthly!$C$110:$BJ$110,($R$2-1)*12+6) -> 105862.76 | N48: =INDEX(Monthly!$C$110:$BJ$110,($R$2-1)*12+7) -> 105139.09 | O48: =INDEX(Monthly!$C$110:$BJ$110,($R$2-1)*12+8) -> 104415.42 | P48: =INDEX(Monthly!$C$110:$BJ$110,($R$2-1)*12+9) -> 102945.37 | Q48: =INDEX(Monthly!$C$110:$BJ$110,($R$2-1)*12+10) -> 102170.82 | R48: =INDEX(Monthly!$C$110:$BJ$110,($R$2-1)*12+11) -> 101396.26 | S48: =INDEX(Monthly!$C$110:$BJ$110,($R$2-1)*12+12) -> 100577.75
A49: Paid-in capital | B49: ='Balance Sheet'!B13 -> 330000 | C49: ='Balance Sheet'!C13 -> 330000 | D49: ='Balance Sheet'!D13 -> 330000 | E49: ='Balance Sheet'!E13 -> 330000 | F49: ='Balance Sheet'!F13 -> 330000 | H49: =INDEX(Monthly!$C$107:$BJ$107,($R$2-1)*12+1) -> 330000 | I49: =INDEX(Monthly!$C$107:$BJ$107,($R$2-1)*12+2) -> 330000 | J49: =INDEX(Monthly!$C$107:$BJ$107,($R$2-1)*12+3) -> 330000 | K49: =INDEX(Monthly!$C$107:$BJ$107,($R$2-1)*12+4) -> 330000 | L49: =INDEX(Monthly!$C$107:$BJ$107,($R$2-1)*12+5) -> 330000 | M49: =INDEX(Monthly!$C$107:$BJ$107,($R$2-1)*12+6) -> 330000 | N49: =INDEX(Monthly!$C$107:$BJ$107,($R$2-1)*12+7) -> 330000 | O49: =INDEX(Monthly!$C$107:$BJ$107,($R$2-1)*12+8) -> 330000 | P49: =INDEX(Monthly!$C$107:$BJ$107,($R$2-1)*12+9) -> 330000 | Q49: =INDEX(Monthly!$C$107:$BJ$107,($R$2-1)*12+10) -> 330000 | R49: =INDEX(Monthly!$C$107:$BJ$107,($R$2-1)*12+11) -> 330000 | S49: =INDEX(Monthly!$C$107:$BJ$107,($R$2-1)*12+12) -> 330000
A50: Retained earnings | B50: ='Balance Sheet'!B14 -> -96017.149 | C50: ='Balance Sheet'!C14 -> -15459.77 | D50: ='Balance Sheet'!D14 -> 74751.284 | E50: ='Balance Sheet'!E14 -> 185366.32 | F50: ='Balance Sheet'!F14 -> 320264.67 | H50: =INDEX(Monthly!$C$108:$BJ$108,($R$2-1)*12+1) -> -24169.749 | I50: =INDEX(Monthly!$C$108:$BJ$108,($R$2-1)*12+2) -> -45765.273 | J50: =INDEX(Monthly!$C$108:$BJ$108,($R$2-1)*12+3) -> -64780.322 | K50: =INDEX(Monthly!$C$108:$BJ$108,($R$2-1)*12+4) -> -81214.896 | L50: =INDEX(Monthly!$C$108:$BJ$108,($R$2-1)*12+5) -> -95068.994 | M50: =INDEX(Monthly!$C$108:$BJ$108,($R$2-1)*12+6) -> -100720.16 | N50: =INDEX(Monthly!$C$108:$BJ$108,($R$2-1)*12+7) -> -103308.94 | O50: =INDEX(Monthly!$C$108:$BJ$108,($R$2-1)*12+8) -> -102835.31 | P50: =INDEX(Monthly!$C$108:$BJ$108,($R$2-1)*12+9) -> -106367.51 | Q50: =INDEX(Monthly!$C$108:$BJ$108,($R$2-1)*12+10) -> -107319.23 | R50: =INDEX(Monthly!$C$108:$BJ$108,($R$2-1)*12+11) -> -105690.48 | S50: =INDEX(Monthly!$C$108:$BJ$108,($R$2-1)*12+12) -> -96017.149
A51: Total equity | B51: ='Balance Sheet'!B15 -> 233982.85 | C51: ='Balance Sheet'!C15 -> 314540.23 | D51: ='Balance Sheet'!D15 -> 404751.28 | E51: ='Balance Sheet'!E15 -> 515366.32 | F51: ='Balance Sheet'!F15 -> 650264.67 | H51: =INDEX(Monthly!$C$111:$BJ$111,($R$2-1)*12+1) -> 305830.25 | I51: =INDEX(Monthly!$C$111:$BJ$111,($R$2-1)*12+2) -> 284234.73 | J51: =INDEX(Monthly!$C$111:$BJ$111,($R$2-1)*12+3) -> 265219.68 | K51: =INDEX(Monthly!$C$111:$BJ$111,($R$2-1)*12+4) -> 248785.1 | L51: =INDEX(Monthly!$C$111:$BJ$111,($R$2-1)*12+5) -> 234931.01 | M51: =INDEX(Monthly!$C$111:$BJ$111,($R$2-1)*12+6) -> 229279.84 | N51: =INDEX(Monthly!$C$111:$BJ$111,($R$2-1)*12+7) -> 226691.06 | O51: =INDEX(Monthly!$C$111:$BJ$111,($R$2-1)*12+8) -> 227164.69 | P51: =INDEX(Monthly!$C$111:$BJ$111,($R$2-1)*12+9) -> 223632.49 | Q51: =INDEX(Monthly!$C$111:$BJ$111,($R$2-1)*12+10) -> 222680.77 | R51: =INDEX(Monthly!$C$111:$BJ$111,($R$2-1)*12+11) -> 224309.52 | S51: =INDEX(Monthly!$C$111:$BJ$111,($R$2-1)*12+12) -> 233982.85
A52: Total liabilities & equity | B52: ='Balance Sheet'!B16 -> 334560.6 | C52: ='Balance Sheet'!C16 -> 396170.96 | D52: ='Balance Sheet'!D16 -> 467496.15 | E52: ='Balance Sheet'!E16 -> 559290.13 | F52: ='Balance Sheet'!F16 -> 675436.08 | H52: =INDEX(Monthly!$C$112:$BJ$112,($R$2-1)*12+1) -> 414972.09 | I52: =INDEX(Monthly!$C$112:$BJ$112,($R$2-1)*12+2) -> 392602.01 | J52: =INDEX(Monthly!$C$112:$BJ$112,($R$2-1)*12+3) -> 372812.4 | K52: =INDEX(Monthly!$C$112:$BJ$112,($R$2-1)*12+4) -> 355603.27 | L52: =INDEX(Monthly!$C$112:$BJ$112,($R$2-1)*12+5) -> 340974.61 | M52: =INDEX(Monthly!$C$112:$BJ$112,($R$2-1)*12+6) -> 335142.59 | N52: =INDEX(Monthly!$C$112:$BJ$112,($R$2-1)*12+7) -> 331830.15 | O52: =INDEX(Monthly!$C$112:$BJ$112,($R$2-1)*12+8) -> 331580.12 | P52: =INDEX(Monthly!$C$112:$BJ$112,($R$2-1)*12+9) -> 326577.87 | Q52: =INDEX(Monthly!$C$112:$BJ$112,($R$2-1)*12+10) -> 324851.59 | R52: =INDEX(Monthly!$C$112:$BJ$112,($R$2-1)*12+11) -> 325705.78 | S52: =INDEX(Monthly!$C$112:$BJ$112,($R$2-1)*12+12) -> 334560.6

Sheet Scenarios
A1: Scenarios — Low / Base / High | H1: =HYPERLINK("#'Cover'!A1","◂ Contents") -> ◂ Contents
A2: All three scenarios calculated side by side, live: change any input and every column updates. Active = the scenario chosen on the Dashboard.
A5: Key drivers
A6: Driver | B6: Low | C6: Base | D6: High | E6: Active
A7: Grooming appointments per operating day at maturity (year 1) (grooms) | B7: =Inputs!$B$7 -> 13 | C7: =Inputs!$C$7 -> 16 | D7: =Inputs!$D$7 -> 19 | E7: =Inputs!$E$7 -> 16
A8: Average price per groom (year 1) ($) | B8: =Inputs!$B$19 -> 68 | C8: =Inputs!$C$19 -> 75 | D8: =Inputs!$D$19 -> 82 | E8: =Inputs!$E$19 -> 75
A9: Kennel runs / suites (runs) | B9: =Inputs!$B$25 -> 30 | C9: =Inputs!$C$25 -> 30 | D9: =Inputs!$D$25 -> 30 | E9: =Inputs!$E$25 -> 30
A10: Average boarding occupancy at maturity, % of run-nights (year 1) (%) | B10: =Inputs!$B$26 -> 0.5 | C10: =Inputs!$C$26 -> 0.62 | D10: =Inputs!$D$26 -> 0.72 | E10: =Inputs!$E$26 -> 0.62
A11: Average nightly rate per run (year 1) ($) | B11: =Inputs!$B$30 -> 50 | C11: =Inputs!$C$30 -> 55 | D11: =Inputs!$D$30 -> 60 | E11: =Inputs!$E$30 -> 55
A12: Shop rent or land cost per month ($) | B12: =Inputs!$B$38 -> 9000 | C12: =Inputs!$C$38 -> 9000 | D12: =Inputs!$D$38 -> 9000 | E12: =Inputs!$E$38 -> 9000
A13: Equity raised at start ($) | B13: =Inputs!$B$71 -> 330000 | C13: =Inputs!$C$71 -> 330000 | D13: =Inputs!$D$71 -> 330000 | E13: =Inputs!$E$71 -> 330000
A15: Results by scenario ($'000)
A16: Output | B16: Low | C16: Base | D16: High | E16: Active
A17: Revenue — final year | B17: =F30 -> 597040.31 | C17: =F31 -> 997614.88 | D17: =F32 -> 1453698.6 | E17: ='P&L'!F5 -> 997614.88
A18: Revenue — whole plan | B18: =SUM(B30:F30) -> 2677640.9 | C18: =SUM(B31:F31) -> 4234319.2 | D18: =SUM(B32:F32) -> 5966543.8 | E18: =SUM('P&L'!$B$5:$F$5) -> 4234319.2
A19: EBITDA — final year | B19: =F36 -> -110629.38 | C19: =F37 -> 200432.4 | D19: =F38 -> 538537.46 | E19: ='P&L'!F16 -> 200432.4
A20: EBITDA margin — final year | B20: =IF(B17=0,0,B19/B17) -> -0.18529634 | C20: =IF(C17=0,0,C19/C17) -> 0.2009116 | D20: =IF(D17=0,0,D19/D17) -> 0.3704602 | E20: =IF(E17=0,0,E19/E17) -> 0.2009116
A21: Net income — final year | B21: =F42 -> -140304.38 | C21: =F43 -> 134898.35 | D21: =F44 -> 402001.35 | E21: ='P&L'!F23 -> 134898.35
A22: Net income — whole plan | B22: =SUM(B42:F42) -> -786729.95 | C22: =SUM(B43:F43) -> 320264.67 | D22: =SUM(B44:F44) -> 1354153.3 | E22: =SUM('P&L'!$B$23:$F$23) -> 320264.67
A23: Cash at the end of the plan | B23: =F48 -> -543720.4 | C23: =F49 -> 565352.36 | D23: =F50 -> 1601777 | E23: ='Balance Sheet'!F5 -> 565352.36
A24: Lowest cash balance | B24: =MIN('Scenario calc'!$C$97:$BJ$97) -> -543720.4 | C24: =MIN('Scenario calc'!$C$223:$BJ$223) -> 147500.34 | D24: =MIN('Scenario calc'!$C$349:$BJ$349) -> 220781.46 | E24: ='Break-even'!B18 -> 147500.34
A25: Lowest cash point (month #) | B25: =MATCH(MIN('Scenario calc'!$C$97:$BJ$97),'Scenario calc'!$C$97:$BJ$97,0) -> 60 | C25: =MATCH(MIN('Scenario calc'!$C$223:$BJ$223),'Scenario calc'!$C$223:$BJ$223,0) -> 10 | D25: =MATCH(MIN('Scenario calc'!$C$349:$BJ$349),'Scenario calc'!$C$349:$BJ$349,0) -> 4 | E25: ='Break-even'!B6 -> 10
A26: Funding required (incl. cash buffer) | B26: =SUMPRODUCT(--('Scenario calc'!$C$6:$BJ$6<=B25),'Scenario calc'!$C$69:$BJ$69)-SUMPRODUCT(--('Scenario calc'!$C$6:$BJ$6<=B25),'Scenario calc'!$C$91:$BJ$91)-SUMPRODUCT(--('Scenario calc'!$C$6:$BJ$6<=B25),'Scenario calc'!$C$79:$BJ$79)+Inputs!$B$86 -> 1082720.4 | C26: =SUMPRODUCT(--('Scenario calc'!$C$132:$BJ$132<=C25),'Scenario calc'!$C$195:$BJ$195)-SUMPRODUCT(--('Scenario calc'!$C$132:$BJ$132<=C25),'Scenario calc'!$C$217:$BJ$217)-SUMPRODUCT(--('Scenario calc'!$C$132:$BJ$132<=C25),'Scenario calc'!$C$205:$BJ$205)+Inputs!$C$86 -> 391499.66 | D26: =SUMPRODUCT(--('Scenario calc'!$C$258:$BJ$258<=D25),'Scenario calc'!$C$321:$BJ$321)-SUMPRODUCT(--('Scenario calc'!$C$258:$BJ$258<=D25),'Scenario calc'!$C$343:$BJ$343)-SUMPRODUCT(--('Scenario calc'!$C$258:$BJ$258<=D25),'Scenario calc'!$C$331:$BJ$331)+Inputs!$D$86 -> 318218.54 | E26: ='Break-even'!B12 -> 391499.66
A28: Revenue by year ($'000)
A29: Scenario | B29: 1 | C29: 2 | D29: 3 | E29: 4 | F29: 5
A30: Low | B30: =SUMIF('Scenario calc'!$C$7:$BJ$7,B$29,'Scenario calc'!$C$33:$BJ$33) -> 331698.3 | C30: =SUMIF('Scenario calc'!$C$7:$BJ$7,C$29,'Scenario calc'!$C$33:$BJ$33) -> 572496.99 | D30: =SUMIF('Scenario calc'!$C$7:$BJ$7,D$29,'Scenario calc'!$C$33:$BJ$33) -> 585276.25 | E30: =SUMIF('Scenario calc'!$C$7:$BJ$7,E$29,'Scenario calc'!$C$33:$BJ$33) -> 591129.02 | F30: =SUMIF('Scenario calc'!$C$7:$BJ$7,F$29,'Scenario calc'!$C$33:$BJ$33) -> 597040.31
A31: Base | B31: =SUMIF('Scenario calc'!$C$133:$BJ$133,B$29,'Scenario calc'!$C$159:$BJ$159) -> 574501.95 | C31: =SUMIF('Scenario calc'!$C$133:$BJ$133,C$29,'Scenario calc'!$C$159:$BJ$159) -> 835486.76 | D31: =SUMIF('Scenario calc'!$C$133:$BJ$133,D$29,'Scenario calc'!$C$159:$BJ$159) -> 886367.9 | E31: =SUMIF('Scenario calc'!$C$133:$BJ$133,E$29,'Scenario calc'!$C$159:$BJ$159) -> 940347.71 | F31: =SUMIF('Scenario calc'!$C$133:$BJ$133,F$29,'Scenario calc'!$C$159:$BJ$159) -> 997614.88
A32: High | B32: =SUMIF('Scenario calc'!$C$259:$BJ$259,B$29,'Scenario calc'!$C$285:$BJ$285) -> 832792.8 | C32: =SUMIF('Scenario calc'!$C$259:$BJ$259,C$29,'Scenario calc'!$C$285:$BJ$285) -> 1117499.1 | D32: =SUMIF('Scenario calc'!$C$259:$BJ$259,D$29,'Scenario calc'!$C$285:$BJ$285) -> 1226561.8 | E32: =SUMIF('Scenario calc'!$C$259:$BJ$259,E$29,'Scenario calc'!$C$285:$BJ$285) -> 1335991.5 | F32: =SUMIF('Scenario calc'!$C$259:$BJ$259,F$29,'Scenario calc'!$C$285:$BJ$285) -> 1453698.6
A34: EBITDA by year ($'000)
A35: Scenario | B35: 1 | C35: 2 | D35: 3 | E35: 4 | F35: 5
A36: Low | B36: =SUMIF('Scenario calc'!$C$7:$BJ$7,B$35,'Scenario calc'!$C$52:$BJ$52) -> -243337.02 | C36: =SUMIF('Scenario calc'!$C$7:$BJ$7,C$35,'Scenario calc'!$C$52:$BJ$52) -> -89345.268 | D36: =SUMIF('Scenario calc'!$C$7:$BJ$7,D$35,'Scenario calc'!$C$52:$BJ$52) -> -90341.043 | E36: =SUMIF('Scenario calc'!$C$7:$BJ$7,E$35,'Scenario calc'!$C$52:$BJ$52) -> -99208.487 | F36: =SUMIF('Scenario calc'!$C$7:$BJ$7,F$35,'Scenario calc'!$C$52:$BJ$52) -> -110629.38
A37: Base | B37: =SUMIF('Scenario calc'!$C$133:$BJ$133,B$35,'Scenario calc'!$C$178:$BJ$178) -> -64148.399 | C37: =SUMIF('Scenario calc'!$C$133:$BJ$133,C$35,'Scenario calc'!$C$178:$BJ$178) -> 111882.38 | D37: =SUMIF('Scenario calc'!$C$133:$BJ$133,D$35,'Scenario calc'!$C$178:$BJ$178) -> 140856.65 | E37: =SUMIF('Scenario calc'!$C$133:$BJ$133,E$35,'Scenario calc'!$C$178:$BJ$178) -> 170244.04 | F37: =SUMIF('Scenario calc'!$C$133:$BJ$133,F$35,'Scenario calc'!$C$178:$BJ$178) -> 200432.4
A38: High | B38: =SUMIF('Scenario calc'!$C$259:$BJ$259,B$35,'Scenario calc'!$C$304:$BJ$304) -> 134331.52 | C38: =SUMIF('Scenario calc'!$C$259:$BJ$259,C$35,'Scenario calc'!$C$304:$BJ$304) -> 329513.8 | D38: =SUMIF('Scenario calc'!$C$259:$BJ$259,D$35,'Scenario calc'!$C$304:$BJ$304) -> 399100.86 | E38: =SUMIF('Scenario calc'!$C$259:$BJ$259,E$35,'Scenario calc'!$C$304:$BJ$304) -> 466503.17 | F38: =SUMIF('Scenario calc'!$C$259:$BJ$259,F$35,'Scenario calc'!$C$304:$BJ$304) -> 538537.46
A40: Net income by year ($'000)
A41: Scenario | B41: 1 | C41: 2 | D41: 3 | E41: 4 | F41: 5
A42: Low | B42: =SUMIF('Scenario calc'!$C$7:$BJ$7,B$41,'Scenario calc'!$C$61:$BJ$61) -> -275205.77 | C42: =SUMIF('Scenario calc'!$C$7:$BJ$7,C$41,'Scenario calc'!$C$61:$BJ$61) -> -120670.27 | D42: =SUMIF('Scenario calc'!$C$7:$BJ$7,D$41,'Scenario calc'!$C$61:$BJ$61) -> -121116.04 | E42: =SUMIF('Scenario calc'!$C$7:$BJ$7,E$41,'Scenario calc'!$C$61:$BJ$61) -> -129433.49 | F42: =SUMIF('Scenario calc'!$C$7:$BJ$7,F$41,'Scenario calc'!$C$61:$BJ$61) -> -140304.38
A43: Base | B43: =SUMIF('Scenario calc'!$C$133:$BJ$133,B$41,'Scenario calc'!$C$187:$BJ$187) -> -96017.149 | C43: =SUMIF('Scenario calc'!$C$133:$BJ$133,C$41,'Scenario calc'!$C$187:$BJ$187) -> 80557.379 | D43: =SUMIF('Scenario calc'!$C$133:$BJ$133,D$41,'Scenario calc'!$C$187:$BJ$187) -> 90211.054 | E43: =SUMIF('Scenario calc'!$C$133:$BJ$133,E$41,'Scenario calc'!$C$187:$BJ$187) -> 110615.04 | F43: =SUMIF('Scenario calc'!$C$133:$BJ$133,F$41,'Scenario calc'!$C$187:$BJ$187) -> 134898.35
A44: High | B44: =SUMIF('Scenario calc'!$C$259:$BJ$259,B$41,'Scenario calc'!$C$313:$BJ$313) -> 80945.59 | C44: =SUMIF('Scenario calc'!$C$259:$BJ$259,C$41,'Scenario calc'!$C$313:$BJ$313) -> 235569.15 | D44: =SUMIF('Scenario calc'!$C$259:$BJ$259,D$41,'Scenario calc'!$C$313:$BJ$313) -> 290977.43 | E44: =SUMIF('Scenario calc'!$C$259:$BJ$259,E$41,'Scenario calc'!$C$313:$BJ$313) -> 344659.76 | F44: =SUMIF('Scenario calc'!$C$259:$BJ$259,F$41,'Scenario calc'!$C$313:$BJ$313) -> 402001.35
A46: Cash at year end by year ($'000)
A47: Scenario | B47: 1 | C47: 2 | D47: 3 | E47: 4 | F47: 5
A48: Low | B48: =INDEX('Scenario calc'!$C$97:$BJ$97,B$47*12) -> -21226.827 | C48: =INDEX('Scenario calc'!$C$97:$BJ$97,C$47*12) -> -145833.11 | D48: =INDEX('Scenario calc'!$C$97:$BJ$97,D$47*12) -> -270553.71 | E48: =INDEX('Scenario calc'!$C$97:$BJ$97,E$47*12) -> -402331.79 | F48: =INDEX('Scenario calc'!$C$97:$BJ$97,F$47*12) -> -543720.4
A49: Base | B49: =INDEX('Scenario calc'!$C$223:$BJ$223,B$47*12) -> 159857.14 | C49: =INDEX('Scenario calc'!$C$223:$BJ$223,C$47*12) -> 235798.08 | D49: =INDEX('Scenario calc'!$C$223:$BJ$223,D$47*12) -> 322671.42 | E49: =INDEX('Scenario calc'!$C$223:$BJ$223,E$47*12) -> 431229.14 | F49: =INDEX('Scenario calc'!$C$223:$BJ$223,F$47*12) -> 565352.36
A50: High | B50: =INDEX('Scenario calc'!$C$349:$BJ$349,B$47*12) -> 337680.78 | C50: =INDEX('Scenario calc'!$C$349:$BJ$349,C$47*12) -> 568958.06 | D50: =INDEX('Scenario calc'!$C$349:$BJ$349,D$47*12) -> 856969.37 | E50: =INDEX('Scenario calc'!$C$349:$BJ$349,E$47*12) -> 1200024.6 | F50: =INDEX('Scenario calc'!$C$349:$BJ$349,F$47*12) -> 1601777

Sheet Break-even
A1: Startup costs, funding need and break-even | H1: =HYPERLINK("#'Cover'!A1","◂ Contents") -> ◂ Contents
A2: Live for the selected scenario. Periods are counted in months from the start of the plan.
A3: Scenario shown | B3: =CHOOSE(Dashboard!$B$4,"Low","Base","High") -> Base
A5: Startup costs & funding need (up to the lowest cash point)
A6: Lowest cash point (month #) | B6: =MATCH(MIN(Monthly!$C$95:$BJ$95),Monthly!$C$95:$BJ$95,0) -> 10
A7: Capital spending up to the lowest cash point | B7: =SUMPRODUCT(--(Monthly!$C$4:$BJ$4<=$B$6),Monthly!$C$67:$BJ$67) -> 189000
A8: Operating cash burn up to the lowest cash point | B8: =-SUMPRODUCT(--(Monthly!$C$4:$BJ$4<=$B$6),Monthly!$C$89:$BJ$89) -> 78499.658 | D8: Losses and working capital before the business funds itself
A9: Loan repayments up to the lowest cash point | B9: =-SUMPRODUCT(--(Monthly!$C$4:$BJ$4<=$B$6),Monthly!$C$77:$BJ$77) -> 15000
A10: Total uses of funds | B10: =B7+B8+B9 -> 282499.66
A11: Minimum cash buffer to keep | B11: =Inputs!$E$86 -> 109000 | D11: Input on the Inputs sheet
A12: Funding required (uses + buffer) | B12: =B10+B11 -> 391499.66
A14: Equity raised | B14: =Inputs!$E$71 -> 330000
A15: Loan drawn | B15: =Inputs!$E$72 -> 100000
A16: Total sources of funds | B16: =B14+B15 -> 430000
A17: Funding surplus / (shortfall) | B17: =B16-B12 -> 38500.342 | D17: Negative = raise at least this much more
A18: Lowest cash balance in the plan | B18: =MIN(Monthly!$C$95:$BJ$95) -> 147500.34 | D18: Equals sources minus uses
A20: Break-even timing
A21: First month with positive EBITDA (month #) | B21: =IFERROR(MATCH(1,Monthly!$C$96:$BJ$96,0),"Not within horizon") -> 7
A22: First month with positive net income (month #) | B22: =IFERROR(MATCH(1,Monthly!$C$99:$BJ$99,0),"Not within horizon") -> 8
A23: Cash invested paid back (month #) | B23: =IF(MIN(Monthly!$C$101:$BJ$101)>=0,"No investment to pay back",IFERROR(MATCH(1,Monthly!$C$103:$BJ$103,0),"Not within horizon")) -> 42 | D23: Cumulative operating + investing cash flow back to zero
A25: Annual break-even revenue
A26: Year # | B26: 1 | C26: 2 | D26: 3 | E26: 4 | F26: 5
B27: Year 1 | C27: Year 2 | D27: Year 3 | E27: Year 4 | F27: Year 5
A28: Revenue | B28: =SUMIF(Monthly!$C$5:$BJ$5,B$26,Monthly!$C$31:$BJ$31) -> 574501.95 | C28: =SUMIF(Monthly!$C$5:$BJ$5,C$26,Monthly!$C$31:$BJ$31) -> 835486.76 | D28: =SUMIF(Monthly!$C$5:$BJ$5,D$26,Monthly!$C$31:$BJ$31) -> 886367.9 | E28: =SUMIF(Monthly!$C$5:$BJ$5,E$26,Monthly!$C$31:$BJ$31) -> 940347.71 | F28: =SUMIF(Monthly!$C$5:$BJ$5,F$26,Monthly!$C$31:$BJ$31) -> 997614.88
A29: Gross profit | B29: =SUMIF(Monthly!$C$5:$BJ$5,B$26,Monthly!$C$40:$BJ$40) -> 369936.66 | C29: =SUMIF(Monthly!$C$5:$BJ$5,C$26,Monthly!$C$40:$BJ$40) -> 556642.48 | D29: =SUMIF(Monthly!$C$5:$BJ$5,D$26,Monthly!$C$40:$BJ$40) -> 592006.05 | E29: =SUMIF(Monthly!$C$5:$BJ$5,E$26,Monthly!$C$40:$BJ$40) -> 629567.18 | F29: =SUMIF(Monthly!$C$5:$BJ$5,F$26,Monthly!$C$40:$BJ$40) -> 669461.03
A30: Gross margin (contribution) | B30: =IF(B28=0,0,B29/B28) -> 0.64392586 | C30: =IF(C28=0,0,C29/C28) -> 0.66624932 | D30: =IF(D28=0,0,D29/D28) -> 0.66790105 | E30: =IF(E28=0,0,E29/E28) -> 0.66950467 | F30: =IF(F28=0,0,F29/F28) -> 0.67106159
A31: Operating expenses (treated as fixed) | B31: =-SUMIF(Monthly!$C$5:$BJ$5,B$26,Monthly!$C$49:$BJ$49) -> 434085.06 | C31: =-SUMIF(Monthly!$C$5:$BJ$5,C$26,Monthly!$C$49:$BJ$49) -> 444760.1 | D31: =-SUMIF(Monthly!$C$5:$BJ$5,D$26,Monthly!$C$49:$BJ$49) -> 451149.4 | E31: =-SUMIF(Monthly!$C$5:$BJ$5,E$26,Monthly!$C$49:$BJ$49) -> 459323.15 | F31: =-SUMIF(Monthly!$C$5:$BJ$5,F$26,Monthly!$C$49:$BJ$49) -> 469028.62
A32: Break-even revenue (EBITDA = 0) | B32: =IF(B30>0,B31/B30,"n/a") -> 674122.73 | C32: =IF(C30>0,C31/C30,"n/a") -> 667558.06 | D32: =IF(D30>0,D31/D30,"n/a") -> 675473.42 | E32: =IF(E30>0,E31/E30,"n/a") -> 686064.14 | F32: =IF(F30>0,F31/F30,"n/a") -> 698935.29
A33: Margin of safety (revenue above break-even) | B33: =IF(AND(ISNUMBER(B32),B28>0),(B28-B32)/B28,"n/a") -> -0.17340374 | C33: =IF(AND(ISNUMBER(C32),C28>0),(C28-C32)/C28,"n/a") -> 0.20099504 | D33: =IF(AND(ISNUMBER(D32),D28>0),(D28-D32)/D28,"n/a") -> 0.2379311 | E33: =IF(AND(ISNUMBER(E32),E28>0),(E28-E32)/E28,"n/a") -> 0.27041441 | F33: =IF(AND(ISNUMBER(F32),F28>0),(F28-F32)/F28,"n/a") -> 0.29939368
A35: Simplification: cost of sales is treated as variable and operating expenses as fixed, so break-even revenue = operating expenses ÷ gross margin.

Sheet Valuation
A1: Discounted cash flow valuation | H1: =HYPERLINK("#'Cover'!A1","◂ Contents") -> ◂ Contents
A2: Enterprise value at the start of the plan, before the funding raised in period 1. Year-end discounting.
A3: Scenario shown | B3: =CHOOSE(Dashboard!$B$4,"Low","Base","High") -> Base
A5: Assumptions (active scenario, from the Inputs sheet)
A6: Discount rate (WACC) | B6: =Inputs!$E$89 -> 0.25
A7: Terminal growth rate | B7: =Inputs!$E$90 -> 0.02
A8: Exit multiple (EV ÷ final-year EBITDA) | B8: =Inputs!$E$91 -> 4
A9: Tax rate (for the interest tax shield) | B9: =Inputs!$E$83 -> 0.21
A10: Sensitivity step: WACC | B10: =Inputs!$E$92 -> 0.01
A11: Sensitivity step: terminal growth | B11: =Inputs!$E$93 -> 0.005
A13: Free cash flow by year
A14: Year # | B14: 1 | C14: 2 | D14: 3 | E14: 4 | F14: 5
B15: Year 1 | C15: Year 2 | D15: Year 3 | E15: Year 4 | F15: Year 5
A16: EBITDA | B16: =SUMIF(Monthly!$C$5:$BJ$5,B$14,Monthly!$C$50:$BJ$50) -> -64148.399 | C16: =SUMIF(Monthly!$C$5:$BJ$5,C$14,Monthly!$C$50:$BJ$50) -> 111882.38 | D16: =SUMIF(Monthly!$C$5:$BJ$5,D$14,Monthly!$C$50:$BJ$50) -> 140856.65 | E16: =SUMIF(Monthly!$C$5:$BJ$5,E$14,Monthly!$C$50:$BJ$50) -> 170244.04 | F16: =SUMIF(Monthly!$C$5:$BJ$5,F$14,Monthly!$C$50:$BJ$50) -> 200432.4
A17: Unlevered free cash flow | B17: =SUMIF(Monthly!$C$5:$BJ$5,B$14,Monthly!$C$104:$BJ$104) -> -245296.96 | C17: =SUMIF(Monthly!$C$5:$BJ$5,C$14,Monthly!$C$104:$BJ$104) -> 101036.44 | D17: =SUMIF(Monthly!$C$5:$BJ$5,D$14,Monthly!$C$104:$BJ$104) -> 110546.84 | E17: =SUMIF(Monthly!$C$5:$BJ$5,E$14,Monthly!$C$104:$BJ$104) -> 130809.22 | F17: =SUMIF(Monthly!$C$5:$BJ$5,F$14,Monthly!$C$104:$BJ$104) -> 154952.72
A18: Discount factor | B18: =1/(1+Inputs!$E$89)^B$14 -> 0.8 | C18: =1/(1+Inputs!$E$89)^C$14 -> 0.64 | D18: =1/(1+Inputs!$E$89)^D$14 -> 0.512 | E18: =1/(1+Inputs!$E$89)^E$14 -> 0.4096 | F18: =1/(1+Inputs!$E$89)^F$14 -> 0.32768
A19: Present value of free cash flow | B19: =B17*B18 -> -196237.57 | C19: =C17*C18 -> 64663.323 | D19: =D17*D18 -> 56599.981 | E19: =E17*E18 -> 53579.458 | F19: =F17*F18 -> 50774.907
A21: Enterprise value
B22: Perpetual growth | C22: Exit multiple
A23: Present value of the plan's free cash flows | B23: =SUM($B$19:$F$19) -> 29380.098 | C23: =B23 -> 29380.098
A24: Final-year free cash flow | final-year EBITDA | B24: =$F$17 -> 154952.72 | C24: =$F$16 -> 200432.4
A25: Terminal value at the end of year 5 | B25: =IF($B$6>$B$7,B24*(1+$B$7)/($B$6-$B$7),0) -> 687181.62 | C25: =C24*$B$8 -> 801729.61
A26: Present value of the terminal value | B26: =B25/(1+$B$6)^$F$14 -> 225175.67 | C26: =C25/(1+$B$6)^$F$14 -> 262710.76
A27: Enterprise value | B27: =B23+B26 -> 254555.77 | C27: =C23+C26 -> 292090.86
A28: Terminal value share of enterprise value | B28: =IF(B27<>0,B26/B27,0) -> 0.88458287 | C28: =IF(C27<>0,C26/C27,0) -> 0.89941452
A29: Cross-check: implied exit multiple | implied perpetual growth | B29: =IF(C24>0,B25/C24,"n/a") -> 3.4284957 | C29: =IF(C25+B24<>0,(C25*$B$6-B24)/(C25+B24),"n/a") -> 0.04753896
A30: Enterprise value — average of the two methods | B30: =AVERAGE(B27,C27) -> 273323.31
A32: Sensitivity: enterprise value (perpetual growth) by WACC and terminal growth
A33: WACC ↓ · terminal growth → | B33: =$B$7+(-2)*$B$11 -> 0.01 | C33: =$B$7+(-1)*$B$11 -> 0.015 | D33: =$B$7+(0)*$B$11 -> 0.02 | E33: =$B$7+(1)*$B$11 -> 0.025 | F33: =$B$7+(2)*$B$11 -> 0.03
A34: =$B$6+(-2)*$B$10 -> 0.23 | B34: =IF($A34>B$33,SUMPRODUCT($B$17:$F$17/(1+$A34)^$B$14:$F$14)+$F$17*(1+B$33)/($A34-B$33)/(1+$A34)^$F$14,"n/a") -> 291631.43 | C34: =IF($A34>C$33,SUMPRODUCT($B$17:$F$17/(1+$A34)^$B$14:$F$14)+$F$17*(1+C$33)/($A34-C$33)/(1+$A34)^$F$14,"n/a") -> 298787.71 | D34: =IF($A34>D$33,SUMPRODUCT($B$17:$F$17/(1+$A34)^$B$14:$F$14)+$F$17*(1+D$33)/($A34-D$33)/(1+$A34)^$F$14,"n/a") -> 306284.77 | E34: =IF($A34>E$33,SUMPRODUCT($B$17:$F$17/(1+$A34)^$B$14:$F$14)+$F$17*(1+E$33)/($A34-E$33)/(1+$A34)^$F$14,"n/a") -> 314147.54 | F34: =IF($A34>F$33,SUMPRODUCT($B$17:$F$17/(1+$A34)^$B$14:$F$14)+$F$17*(1+F$33)/($A34-F$33)/(1+$A34)^$F$14,"n/a") -> 322403.45
A35: =$B$6+(-1)*$B$10 -> 0.24 | B35: =IF($A35>B$33,SUMPRODUCT($B$17:$F$17/(1+$A35)^$B$14:$F$14)+$F$17*(1+B$33)/($A35-B$33)/(1+$A35)^$F$14,"n/a") -> 266160.08 | C35: =IF($A35>C$33,SUMPRODUCT($B$17:$F$17/(1+$A35)^$B$14:$F$14)+$F$17*(1+C$33)/($A35-C$33)/(1+$A35)^$F$14,"n/a") -> 272492.54 | D35: =IF($A35>D$33,SUMPRODUCT($B$17:$F$17/(1+$A35)^$B$14:$F$14)+$F$17*(1+D$33)/($A35-D$33)/(1+$A35)^$F$14,"n/a") -> 279112.83 | E35: =IF($A35>E$33,SUMPRODUCT($B$17:$F$17/(1+$A35)^$B$14:$F$14)+$F$17*(1+E$33)/($A35-E$33)/(1+$A35)^$F$14,"n/a") -> 286041.05 | F35: =IF($A35>F$33,SUMPRODUCT($B$17:$F$17/(1+$A35)^$B$14:$F$14)+$F$17*(1+F$33)/($A35-F$33)/(1+$A35)^$F$14,"n/a") -> 293299.18
A36: =$B$6+(0)*$B$10 -> 0.25 | B36: =IF($A36>B$33,SUMPRODUCT($B$17:$F$17/(1+$A36)^$B$14:$F$14)+$F$17*(1+B$33)/($A36-B$33)/(1+$A36)^$F$14,"n/a") -> 243057.83 | C36: =IF($A36>C$33,SUMPRODUCT($B$17:$F$17/(1+$A36)^$B$14:$F$14)+$F$17*(1+C$33)/($A36-C$33)/(1+$A36)^$F$14,"n/a") -> 248684.48 | D36: =IF($A36>D$33,SUMPRODUCT($B$17:$F$17/(1+$A36)^$B$14:$F$14)+$F$17*(1+D$33)/($A36-D$33)/(1+$A36)^$F$14,"n/a") -> 254555.77 | E36: =IF($A36>E$33,SUMPRODUCT($B$17:$F$17/(1+$A36)^$B$14:$F$14)+$F$17*(1+E$33)/($A36-E$33)/(1+$A36)^$F$14,"n/a") -> 260688.01 | F36: =IF($A36>F$33,SUMPRODUCT($B$17:$F$17/(1+$A36)^$B$14:$F$14)+$F$17*(1+F$33)/($A36-F$33)/(1+$A36)^$F$14,"n/a") -> 267098.98
A37: =$B$6+(1)*$B$10 -> 0.26 | B37: =IF($A37>B$33,SUMPRODUCT($B$17:$F$17/(1+$A37)^$B$14:$F$14)+$F$17*(1+B$33)/($A37-B$33)/(1+$A37)^$F$14,"n/a") -> 222033.02 | C37: =IF($A37>C$33,SUMPRODUCT($B$17:$F$17/(1+$A37)^$B$14:$F$14)+$F$17*(1+C$33)/($A37-C$33)/(1+$A37)^$F$14,"n/a") -> 227051.6 | D37: =IF($A37>D$33,SUMPRODUCT($B$17:$F$17/(1+$A37)^$B$14:$F$14)+$F$17*(1+D$33)/($A37-D$33)/(1+$A37)^$F$14,"n/a") -> 232279.29 | E37: =IF($A37>E$33,SUMPRODUCT($B$17:$F$17/(1+$A37)^$B$14:$F$14)+$F$17*(1+E$33)/($A37-E$33)/(1+$A37)^$F$14,"n/a") -> 237729.44 | F37: =IF($A37>F$33,SUMPRODUCT($B$17:$F$17/(1+$A37)^$B$14:$F$14)+$F$17*(1+F$33)/($A37-F$33)/(1+$A37)^$F$14,"n/a") -> 243416.54
A38: =$B$6+(2)*$B$10 -> 0.27 | B38: =IF($A38>B$33,SUMPRODUCT($B$17:$F$17/(1+$A38)^$B$14:$F$14)+$F$17*(1+B$33)/($A38-B$33)/(1+$A38)^$F$14,"n/a") -> 202839.18 | C38: =IF($A38>C$33,SUMPRODUCT($B$17:$F$17/(1+$A38)^$B$14:$F$14)+$F$17*(1+C$33)/($A38-C$33)/(1+$A38)^$F$14,"n/a") -> 207331.19 | D38: =IF($A38>D$33,SUMPRODUCT($B$17:$F$17/(1+$A38)^$B$14:$F$14)+$F$17*(1+D$33)/($A38-D$33)/(1+$A38)^$F$14,"n/a") -> 212002.88 | E38: =IF($A38>E$33,SUMPRODUCT($B$17:$F$17/(1+$A38)^$B$14:$F$14)+$F$17*(1+E$33)/($A38-E$33)/(1+$A38)^$F$14,"n/a") -> 216865.25 | F38: =IF($A38>F$33,SUMPRODUCT($B$17:$F$17/(1+$A38)^$B$14:$F$14)+$F$17*(1+F$33)/($A38-F$33)/(1+$A38)^$F$14,"n/a") -> 221930.22
A40: Free cash flow = operating cash flow + interest × (1 − tax rate) − capital spending. Cells marked n/a: WACC not above growth.

Sheet Sources & Uses
A1: Sources and uses of funds | E1: =HYPERLINK("#'Cover'!A1","◂ Contents") -> ◂ Contents
A2: Live for the selected scenario. Where the money comes from and where it goes in the period set below.
A3: Scenario shown | B3: =CHOOSE(Dashboard!$B$4,"Low","Base","High") -> Base
A5: Funding structure ($'000) — raised at the start of the plan
B6: Amount | C6: Share
A7: Equity | B7: =Inputs!$E$71 -> 330000 | C7: =IF($B$9=0,0,B7/$B$9) -> 0.76744186
A8: Debt (loan) | B8: =Inputs!$E$72 -> 100000 | C8: =IF($B$9=0,0,B8/$B$9) -> 0.23255814
A9: Total funding | B9: =B7+B8 -> 430000 | C9: =IF(B9=0,0,1) -> 1
A10: Gearing (debt ÷ equity) | B10: =IF(B7<=0,IF(B8>0,"n/a",0),B8/B7) -> 0.3030303 | D10: n/a: debt without positive equity
A11: Funding required by the plan (Break-even sheet) | B11: ='Break-even'!B12 -> 391499.66
A12: Funding surplus / (shortfall) | B12: ='Break-even'!B17 -> 38500.342
A14: ="Sources and uses of cash in the first "&$B$16&IF($B$16=1," month"," months")&" ($'000)" -> Sources and uses of cash in the first 12 months ($'000)
A15: Period covered (months from the start) | B15: 12 | D15: 1 to 60 (capped)
A16: Months used | B16: =MIN(60,MAX(1,ROUND(B15,0))) -> 12
A17: Sources | B17: Amount | C17: Share
A18: Equity raised | B18: =SUMPRODUCT(--(Monthly!$C$4:$BJ$4<=$B$16),Monthly!$C$91:$BJ$91) -> 330000 | C18: =IF($B$21=0,0,B18/$B$21) -> 0.76744186
A19: Loan drawdowns | B19: =SUMPRODUCT(--(Monthly!$C$4:$BJ$4<=$B$16),Monthly!$C$76:$BJ$76) -> 100000 | C19: =IF($B$21=0,0,B19/$B$21) -> 0.23255814
A20: Cash generated by operations | B20: =MAX(0,SUMPRODUCT(--(Monthly!$C$4:$BJ$4<=$B$16),Monthly!$C$89:$BJ$89)) -> 0 | C20: =IF($B$21=0,0,B20/$B$21) -> 0
A21: Total sources | B21: =SUM(B18:B20) -> 430000 | C21: =IF(B21=0,0,1) -> 1
A23: Uses | B23: Amount | C23: Share
A24: Cash used by operations | B24: =MAX(0,-SUMPRODUCT(--(Monthly!$C$4:$BJ$4<=$B$16),Monthly!$C$89:$BJ$89)) -> 62809.527 | C24: =IF($B$28=0,0,B24/$B$28) -> 0.14606867
A25: Capital spending | B25: =-SUMPRODUCT(--(Monthly!$C$4:$BJ$4<=$B$16),Monthly!$C$90:$BJ$90) -> 189000 | C25: =IF($B$28=0,0,B25/$B$28) -> 0.43953488
A26: Loan repayments | B26: =-SUMPRODUCT(--(Monthly!$C$4:$BJ$4<=$B$16),Monthly!$C$77:$BJ$77) -> 18333.333 | C26: =IF($B$28=0,0,B26/$B$28) -> 0.042635659
A27: Cash at the end of the period | B27: =INDEX(Monthly!$C$95:$BJ$95,$B$16) -> 159857.14 | C27: =IF($B$28=0,0,B27/$B$28) -> 0.37176079
A28: Total uses | B28: =SUM(B24:B27) -> 430000 | C28: =IF(B28=0,0,1) -> 1
A29: Sources − uses (must be 0; opening cash is 0) | B29: =B21-B28 -> 0

Sheet KPIs
A1: KPIs & ratios | I1: =HYPERLINK("#'Cover'!A1","◂ Contents") -> ◂ Contents
A2: Pet grooming & boarding financial model (planning) — industry metrics and financial ratios for the active scenario
A4: Financial ratios
B5: 1 | C5: 2 | D5: 3 | E5: 4 | F5: 5 | G5: Target
A6: Revenue growth | B6: =IF(N('P&L'!A5)<=0,"n/a",'P&L'!B5/'P&L'!A5-1) -> n/a | C6: =IF(N('P&L'!B5)<=0,"n/a",'P&L'!C5/'P&L'!B5-1) -> 0.45428011 | D6: =IF(N('P&L'!C5)<=0,"n/a",'P&L'!D5/'P&L'!C5-1) -> 0.0609 | E6: =IF(N('P&L'!D5)<=0,"n/a",'P&L'!E5/'P&L'!D5-1) -> 0.0609 | F6: =IF(N('P&L'!E5)<=0,"n/a",'P&L'!F5/'P&L'!E5-1) -> 0.0609
A7: Gross margin | B7: =IF('P&L'!B5<=0,"n/a",'P&L'!B7/'P&L'!B5) -> 0.64392586 | C7: =IF('P&L'!C5<=0,"n/a",'P&L'!C7/'P&L'!C5) -> 0.66624932 | D7: =IF('P&L'!D5<=0,"n/a",'P&L'!D7/'P&L'!D5) -> 0.66790105 | E7: =IF('P&L'!E5<=0,"n/a",'P&L'!E7/'P&L'!E5) -> 0.66950467 | F7: =IF('P&L'!F5<=0,"n/a",'P&L'!F7/'P&L'!F5) -> 0.67106159
A8: EBITDA margin | B8: =IF('P&L'!B5<=0,"n/a",'P&L'!B16/'P&L'!B5) -> -0.11165915 | C8: =IF('P&L'!C5<=0,"n/a",'P&L'!C16/'P&L'!C5) -> 0.13391281 | D8: =IF('P&L'!D5<=0,"n/a",'P&L'!D16/'P&L'!D5) -> 0.15891443 | E8: =IF('P&L'!E5<=0,"n/a",'P&L'!E16/'P&L'!E5) -> 0.18104371 | F8: =IF('P&L'!F5<=0,"n/a",'P&L'!F16/'P&L'!F5) -> 0.2009116
A9: Net margin | B9: =IF('P&L'!B5<=0,"n/a",'P&L'!B23/'P&L'!B5) -> -0.16713111 | C9: =IF('P&L'!C5<=0,"n/a",'P&L'!C23/'P&L'!C5) -> 0.096419695 | D9: =IF('P&L'!D5<=0,"n/a",'P&L'!D23/'P&L'!D5) -> 0.10177608 | E9: =IF('P&L'!E5<=0,"n/a",'P&L'!E23/'P&L'!E5) -> 0.11763206 | F9: =IF('P&L'!F5<=0,"n/a",'P&L'!F23/'P&L'!F5) -> 0.13522087
A10: Payroll, % of revenue | B10: =IF('P&L'!B5<=0,"n/a",-SUMIF(Headcount!$C$5:$BJ$5,B$5,Headcount!$C$17:$BJ$17)/'P&L'!B5) -> 0.39834504 | C10: =IF('P&L'!C5<=0,"n/a",-SUMIF(Headcount!$C$5:$BJ$5,C$5,Headcount!$C$17:$BJ$17)/'P&L'!C5) -> 0.28212955 | D10: =IF('P&L'!D5<=0,"n/a",-SUMIF(Headcount!$C$5:$BJ$5,D$5,Headcount!$C$17:$BJ$17)/'P&L'!D5) -> 0.27391218 | E10: =IF('P&L'!E5<=0,"n/a",-SUMIF(Headcount!$C$5:$BJ$5,E$5,Headcount!$C$17:$BJ$17)/'P&L'!E5) -> 0.26593416 | F10: =IF('P&L'!F5<=0,"n/a",-SUMIF(Headcount!$C$5:$BJ$5,F$5,Headcount!$C$17:$BJ$17)/'P&L'!F5) -> 0.2581885
A11: Marketing, % of revenue | B11: =IF('P&L'!B5<=0,"n/a",-'P&L'!B13/'P&L'!B5) -> 0.073106802 | C11: =IF('P&L'!C5<=0,"n/a",-'P&L'!C13/'P&L'!C5) -> 0.040216077 | D11: =IF('P&L'!D5<=0,"n/a",-'P&L'!D13/'P&L'!D5) -> 0.030326008 | E11: =IF('P&L'!E5<=0,"n/a",-'P&L'!E13/'P&L'!E5) -> 0.022868137 | F11: =IF('P&L'!F5<=0,"n/a",-'P&L'!F13/'P&L'!F5) -> 0.01724433
A12: Operating expenses, % of revenue | B12: =IF('P&L'!B5<=0,"n/a",-'P&L'!B15/'P&L'!B5) -> 0.75558501 | C12: =IF('P&L'!C5<=0,"n/a",-'P&L'!C15/'P&L'!C5) -> 0.53233651 | D12: =IF('P&L'!D5<=0,"n/a",-'P&L'!D15/'P&L'!D5) -> 0.50898662 | E12: =IF('P&L'!E5<=0,"n/a",-'P&L'!E15/'P&L'!E5) -> 0.48846096 | F12: =IF('P&L'!F5<=0,"n/a",-'P&L'!F15/'P&L'!F5) -> 0.47014999
A13: Current ratio (current assets ÷ current liabilities) | B13: =IF(('Balance Sheet'!B12-'Balance Sheet'!B11)<=0,"n/a",('Balance Sheet'!B5+'Balance Sheet'!B6+'Balance Sheet'!B7)/('Balance Sheet'!B12-'Balance Sheet'!B11)) -> 8.9463723 | C13: =IF(('Balance Sheet'!C12-'Balance Sheet'!C11)<=0,"n/a",('Balance Sheet'!C5+'Balance Sheet'!C6+'Balance Sheet'!C7)/('Balance Sheet'!C12-'Balance Sheet'!C11)) -> 12.30566 | D13: =IF(('Balance Sheet'!D12-'Balance Sheet'!D11)<=0,"n/a",('Balance Sheet'!D5+'Balance Sheet'!D6+'Balance Sheet'!D7)/('Balance Sheet'!D12-'Balance Sheet'!D11)) -> 15.804059 | E13: =IF(('Balance Sheet'!E12-'Balance Sheet'!E11)<=0,"n/a",('Balance Sheet'!E5+'Balance Sheet'!E6+'Balance Sheet'!E7)/('Balance Sheet'!E12-'Balance Sheet'!E11)) -> 19.871826 | F13: =IF(('Balance Sheet'!F12-'Balance Sheet'!F11)<=0,"n/a",('Balance Sheet'!F5+'Balance Sheet'!F6+'Balance Sheet'!F7)/('Balance Sheet'!F12-'Balance Sheet'!F11)) -> 24.550834
A14: Debt ÷ equity (loan ÷ total equity) | B14: =IF('Balance Sheet'!B15<=0,"n/a",'Balance Sheet'!B11/'Balance Sheet'!B15) -> 0.34902843 | C14: =IF('Balance Sheet'!C15<=0,"n/a",'Balance Sheet'!C11/'Balance Sheet'!C15) -> 0.19605335 | D14: =IF('Balance Sheet'!D15<=0,"n/a",'Balance Sheet'!D11/'Balance Sheet'!D15) -> 0.10294388 | E14: =IF('Balance Sheet'!E15<=0,"n/a",'Balance Sheet'!E11/'Balance Sheet'!E15) -> 0.042041293 | F14: =IF('Balance Sheet'!F15<=0,"n/a",'Balance Sheet'!F11/'Balance Sheet'!F15) -> 0.0025630589
A15: Return on assets (net income ÷ year-end assets) | B15: =IF('Balance Sheet'!B9<=0,"n/a",'P&L'!B23/'Balance Sheet'!B9) -> -0.28699479 | C15: =IF('Balance Sheet'!C9<=0,"n/a",'P&L'!C23/'Balance Sheet'!C9) -> 0.20333994 | D15: =IF('Balance Sheet'!D9<=0,"n/a",'P&L'!D23/'Balance Sheet'!D9) -> 0.19296641 | E15: =IF('Balance Sheet'!E9<=0,"n/a",'P&L'!E23/'Balance Sheet'!E9) -> 0.19777756 | F15: =IF('Balance Sheet'!F9<=0,"n/a",'P&L'!F23/'Balance Sheet'!F9) -> 0.19972038
A16: Return on equity (net income ÷ year-end equity) | B16: =IF('Balance Sheet'!B15<=0,"n/a",'P&L'!B23/'Balance Sheet'!B15) -> -0.41035977 | C16: =IF('Balance Sheet'!C15<=0,"n/a",'P&L'!C23/'Balance Sheet'!C15) -> 0.25611153 | D16: =IF('Balance Sheet'!D15<=0,"n/a",'P&L'!D23/'Balance Sheet'!D15) -> 0.22288022 | E16: =IF('Balance Sheet'!E15<=0,"n/a",'P&L'!E23/'Balance Sheet'!E15) -> 0.21463381 | F16: =IF('Balance Sheet'!F15<=0,"n/a",'P&L'!F23/'Balance Sheet'!F15) -> 0.20745145
A18: DuPont analysis — return on equity = net margin × asset turnover × equity multiplier
B19: 1 | C19: 2 | D19: 3 | E19: 4 | F19: 5
A20: Net margin | B20: =IF('P&L'!B5<=0,"n/a",'P&L'!B23/'P&L'!B5) -> -0.16713111 | C20: =IF('P&L'!C5<=0,"n/a",'P&L'!C23/'P&L'!C5) -> 0.096419695 | D20: =IF('P&L'!D5<=0,"n/a",'P&L'!D23/'P&L'!D5) -> 0.10177608 | E20: =IF('P&L'!E5<=0,"n/a",'P&L'!E23/'P&L'!E5) -> 0.11763206 | F20: =IF('P&L'!F5<=0,"n/a",'P&L'!F23/'P&L'!F5) -> 0.13522087
A21: × Asset turnover (revenue ÷ assets) | B21: =IF('Balance Sheet'!B9<=0,"n/a",'P&L'!B5/'Balance Sheet'!B9) -> 1.7171835 | C21: =IF('Balance Sheet'!C9<=0,"n/a",'P&L'!C5/'Balance Sheet'!C9) -> 2.1089046 | D21: =IF('Balance Sheet'!D9<=0,"n/a",'P&L'!D5/'Balance Sheet'!D9) -> 1.8959897 | E21: =IF('Balance Sheet'!E9<=0,"n/a",'P&L'!E5/'Balance Sheet'!E9) -> 1.6813236 | F21: =IF('Balance Sheet'!F9<=0,"n/a",'P&L'!F5/'Balance Sheet'!F9) -> 1.4769938
A22: × Equity multiplier (assets ÷ equity) | B22: =IF('Balance Sheet'!B15<=0,"n/a",'Balance Sheet'!B9/'Balance Sheet'!B15) -> 1.429851 | C22: =IF('Balance Sheet'!C15<=0,"n/a",'Balance Sheet'!C9/'Balance Sheet'!C15) -> 1.259524 | D22: =IF('Balance Sheet'!D15<=0,"n/a",'Balance Sheet'!D9/'Balance Sheet'!D15) -> 1.1550208 | E22: =IF('Balance Sheet'!E15<=0,"n/a",'Balance Sheet'!E9/'Balance Sheet'!E15) -> 1.0852283 | F22: =IF('Balance Sheet'!F15<=0,"n/a",'Balance Sheet'!F9/'Balance Sheet'!F15) -> 1.0387095
A23: Return on equity (product of the three) | B23: =IF(AND(ISNUMBER(B20),ISNUMBER(B21),ISNUMBER(B22)),B20*B21*B22,"n/a") -> -0.41035977 | C23: =IF(AND(ISNUMBER(C20),ISNUMBER(C21),ISNUMBER(C22)),C20*C21*C22,"n/a") -> 0.25611153 | D23: =IF(AND(ISNUMBER(D20),ISNUMBER(D21),ISNUMBER(D22)),D20*D21*D22,"n/a") -> 0.22288022 | E23: =IF(AND(ISNUMBER(E20),ISNUMBER(E21),ISNUMBER(E22)),E20*E21*E22,"n/a") -> 0.21463381 | F23: =IF(AND(ISNUMBER(F20),ISNUMBER(F21),ISNUMBER(F22)),F20*F21*F22,"n/a") -> 0.20745145
A24: Check: product − return on equity (must be 0) | B24: =IF(AND(ISNUMBER(B23),ISNUMBER(B16)),B23-B16,IF(ISNUMBER(B23),1,IF(AND(ISNUMBER(B16),ISNUMBER(B20),ISNUMBER(B21)),1,0))) -> 0 | C24: =IF(AND(ISNUMBER(C23),ISNUMBER(C16)),C23-C16,IF(ISNUMBER(C23),1,IF(AND(ISNUMBER(C16),ISNUMBER(C20),ISNUMBER(C21)),1,0))) -> 0 | D24: =IF(AND(ISNUMBER(D23),ISNUMBER(D16)),D23-D16,IF(ISNUMBER(D23),1,IF(AND(ISNUMBER(D16),ISNUMBER(D20),ISNUMBER(D21)),1,0))) -> 0 | E24: =IF(AND(ISNUMBER(E23),ISNUMBER(E16)),E23-E16,IF(ISNUMBER(E23),1,IF(AND(ISNUMBER(E16),ISNUMBER(E20),ISNUMBER(E21)),1,0))) -> 0 | F24: =IF(AND(ISNUMBER(F23),ISNUMBER(F16)),F23-F16,IF(ISNUMBER(F23),1,IF(AND(ISNUMBER(F16),ISNUMBER(F20),ISNUMBER(F21)),1,0))) -> 0
A26: Pet care metrics ($'000; per-unit rows in $)
A27: Year # | B27: 1 | C27: 2 | D27: 3 | E27: 4 | F27: 5
B28: Year 1 | C28: Year 2 | D28: Year 3 | E28: Year 4 | F28: Year 5 | G28: Target
A29: Groomers (FTE) | B29: =INDEX(Monthly!$C$13:$BJ$13,B$27*12) -> 4 | C29: =INDEX(Monthly!$C$13:$BJ$13,C$27*12) -> 4 | D29: =INDEX(Monthly!$C$13:$BJ$13,D$27*12) -> 4 | E29: =INDEX(Monthly!$C$13:$BJ$13,E$27*12) -> 4 | F29: =INDEX(Monthly!$C$13:$BJ$13,F$27*12) -> 4
A30: Grooms completed | B30: =SUMIF(Monthly!$C$5:$BJ$5,B$27,Monthly!$C$17:$BJ$17) -> 3619.2 | C30: =SUMIF(Monthly!$C$5:$BJ$5,C$27,Monthly!$C$17:$BJ$17) -> 5141.76 | D30: =SUMIF(Monthly!$C$5:$BJ$5,D$27,Monthly!$C$17:$BJ$17) -> 5296.0128 | E30: =SUMIF(Monthly!$C$5:$BJ$5,E$27,Monthly!$C$17:$BJ$17) -> 5454.8932 | F30: =SUMIF(Monthly!$C$5:$BJ$5,F$27,Monthly!$C$17:$BJ$17) -> 5618.54
A31: Grooming capacity (lower of stations and groomers) | B31: =SUMIF(Monthly!$C$5:$BJ$5,B$27,Monthly!$C$16:$BJ$16) -> 6864 | C31: =SUMIF(Monthly!$C$5:$BJ$5,C$27,Monthly!$C$16:$BJ$16) -> 6864 | D31: =SUMIF(Monthly!$C$5:$BJ$5,D$27,Monthly!$C$16:$BJ$16) -> 6864 | E31: =SUMIF(Monthly!$C$5:$BJ$5,E$27,Monthly!$C$16:$BJ$16) -> 6864 | F31: =SUMIF(Monthly!$C$5:$BJ$5,F$27,Monthly!$C$16:$BJ$16) -> 6864
A32: Grooming capacity used | B32: =IF(B31=0,0,B30/B31) -> 0.52727273 | C32: =IF(C31=0,0,C30/C31) -> 0.74909091 | D32: =IF(D31=0,0,D30/D31) -> 0.77156364 | E32: =IF(E31=0,0,E30/E31) -> 0.79471055 | F32: =IF(F31=0,0,F30/F31) -> 0.81855186
A33: Grooms lost to the capacity limit | B33: =SUMIF(Monthly!$C$5:$BJ$5,B$27,Monthly!$C$18:$BJ$18) -> 0 | C33: =SUMIF(Monthly!$C$5:$BJ$5,C$27,Monthly!$C$18:$BJ$18) -> 0 | D33: =SUMIF(Monthly!$C$5:$BJ$5,D$27,Monthly!$C$18:$BJ$18) -> 0 | E33: =SUMIF(Monthly!$C$5:$BJ$5,E$27,Monthly!$C$18:$BJ$18) -> 0 | F33: =SUMIF(Monthly!$C$5:$BJ$5,F$27,Monthly!$C$18:$BJ$18) -> 0
A34: Boarded run-nights | B34: =SUMIF(Monthly!$C$5:$BJ$5,B$27,Monthly!$C$24:$BJ$24) -> 4983.7882 | C34: =SUMIF(Monthly!$C$5:$BJ$5,C$27,Monthly!$C$24:$BJ$24) -> 6988.8384 | D34: =SUMIF(Monthly!$C$5:$BJ$5,D$27,Monthly!$C$24:$BJ$24) -> 7198.5036 | E34: =SUMIF(Monthly!$C$5:$BJ$5,E$27,Monthly!$C$24:$BJ$24) -> 7414.4587 | F34: =SUMIF(Monthly!$C$5:$BJ$5,F$27,Monthly!$C$24:$BJ$24) -> 7636.8924
A35: Available run-nights | B35: =SUMIF(Monthly!$C$5:$BJ$5,B$27,Monthly!$C$22:$BJ$22) -> 10944 | C35: =SUMIF(Monthly!$C$5:$BJ$5,C$27,Monthly!$C$22:$BJ$22) -> 10944 | D35: =SUMIF(Monthly!$C$5:$BJ$5,D$27,Monthly!$C$22:$BJ$22) -> 10944 | E35: =SUMIF(Monthly!$C$5:$BJ$5,E$27,Monthly!$C$22:$BJ$22) -> 10944 | F35: =SUMIF(Monthly!$C$5:$BJ$5,F$27,Monthly!$C$22:$BJ$22) -> 10944
A36: Boarding occupancy | B36: =IF(B35=0,0,B34/B35) -> 0.45539 | C36: =IF(C35=0,0,C34/C35) -> 0.6386 | D36: =IF(D35=0,0,D34/D35) -> 0.657758 | E36: =IF(E35=0,0,E34/E35) -> 0.67749074 | F36: =IF(F35=0,0,F34/F35) -> 0.69781546
A37: Revenue | B37: =SUMIF(Monthly!$C$5:$BJ$5,B$27,Monthly!$C$31:$BJ$31) -> 574501.95 | C37: =SUMIF(Monthly!$C$5:$BJ$5,C$27,Monthly!$C$31:$BJ$31) -> 835486.76 | D37: =SUMIF(Monthly!$C$5:$BJ$5,D$27,Monthly!$C$31:$BJ$31) -> 886367.9 | E37: =SUMIF(Monthly!$C$5:$BJ$5,E$27,Monthly!$C$31:$BJ$31) -> 940347.71 | F37: =SUMIF(Monthly!$C$5:$BJ$5,F$27,Monthly!$C$31:$BJ$31) -> 997614.88
A38: Grooming revenue | B38: =SUMIF(Monthly!$C$5:$BJ$5,B$27,Monthly!$C$28:$BJ$28) -> 271440 | C38: =SUMIF(Monthly!$C$5:$BJ$5,C$27,Monthly!$C$28:$BJ$28) -> 397200.96 | D38: =SUMIF(Monthly!$C$5:$BJ$5,D$27,Monthly!$C$28:$BJ$28) -> 421390.5 | E38: =SUMIF(Monthly!$C$5:$BJ$5,E$27,Monthly!$C$28:$BJ$28) -> 447053.18 | F38: =SUMIF(Monthly!$C$5:$BJ$5,F$27,Monthly!$C$28:$BJ$28) -> 474278.72
A39: Boarding revenue | B39: =SUMIF(Monthly!$C$5:$BJ$5,B$27,Monthly!$C$29:$BJ$29) -> 274108.35 | C39: =SUMIF(Monthly!$C$5:$BJ$5,C$27,Monthly!$C$29:$BJ$29) -> 395917.7 | D39: =SUMIF(Monthly!$C$5:$BJ$5,D$27,Monthly!$C$29:$BJ$29) -> 420029.08 | E39: =SUMIF(Monthly!$C$5:$BJ$5,E$27,Monthly!$C$29:$BJ$29) -> 445608.85 | F39: =SUMIF(Monthly!$C$5:$BJ$5,F$27,Monthly!$C$29:$BJ$29) -> 472746.43
A40: Retail revenue | B40: =SUMIF(Monthly!$C$5:$BJ$5,B$27,Monthly!$C$30:$BJ$30) -> 28953.6 | C40: =SUMIF(Monthly!$C$5:$BJ$5,C$27,Monthly!$C$30:$BJ$30) -> 42368.102 | D40: =SUMIF(Monthly!$C$5:$BJ$5,D$27,Monthly!$C$30:$BJ$30) -> 44948.32 | E40: =SUMIF(Monthly!$C$5:$BJ$5,E$27,Monthly!$C$30:$BJ$30) -> 47685.673 | F40: =SUMIF(Monthly!$C$5:$BJ$5,F$27,Monthly!$C$30:$BJ$30) -> 50589.73
A41: Boarding share of revenue | B41: =IF(B37=0,0,B39/B37) -> 0.47712344 | C41: =IF(C37=0,0,C39/C37) -> 0.47387669 | D41: =IF(D37=0,0,D39/D37) -> 0.47387669 | E41: =IF(E37=0,0,E39/E37) -> 0.47387669 | F41: =IF(F37=0,0,F39/F37) -> 0.47387669
A42: Revenue per groom (grooming + retail) ($) | B42: =IF(B30=0,0,(B38+B40)/B30) -> 83 | C42: =IF(C30=0,0,(C38+C40)/C30) -> 85.49 | D42: =IF(D30=0,0,(D38+D40)/D30) -> 88.0547 | E42: =IF(E30=0,0,(E38+E40)/E30) -> 90.696341 | F42: =IF(F30=0,0,(F38+F40)/F30) -> 93.417231
A43: Boarding revenue per available run-night ($) | B43: =IF(B35=0,0,B39/B35) -> 25.04645 | C43: =IF(C35=0,0,C39/C35) -> 36.17669 | D43: =IF(D35=0,0,D39/D35) -> 38.37985 | E43: =IF(E35=0,0,E39/E35) -> 40.717183 | F43: =IF(F35=0,0,F39/F35) -> 43.19686
A44: Revenue per groomer (year-end FTE) | B44: =IF(B29=0,0,B37/B29) -> 143625.49 | C44: =IF(C29=0,0,C37/C29) -> 208871.69 | D44: =IF(D29=0,0,D37/D29) -> 221591.98 | E44: =IF(E29=0,0,E37/E29) -> 235086.93 | F44: =IF(F29=0,0,F37/F29) -> 249403.72
A45: Gross profit | B45: =SUMIF(Monthly!$C$5:$BJ$5,B$27,Monthly!$C$40:$BJ$40) -> 369936.66 | C45: =SUMIF(Monthly!$C$5:$BJ$5,C$27,Monthly!$C$40:$BJ$40) -> 556642.48 | D45: =SUMIF(Monthly!$C$5:$BJ$5,D$27,Monthly!$C$40:$BJ$40) -> 592006.05 | E45: =SUMIF(Monthly!$C$5:$BJ$5,E$27,Monthly!$C$40:$BJ$40) -> 629567.18 | F45: =SUMIF(Monthly!$C$5:$BJ$5,F$27,Monthly!$C$40:$BJ$40) -> 669461.03
A46: Gross margin | B46: =IF(B37=0,0,B45/B37) -> 0.64392586 | C46: =IF(C37=0,0,C45/C37) -> 0.66624932 | D46: =IF(D37=0,0,D45/D37) -> 0.66790105 | E46: =IF(E37=0,0,E45/E37) -> 0.66950467 | F46: =IF(F37=0,0,F45/F37) -> 0.67106159
A47: EBITDA | B47: =SUMIF(Monthly!$C$5:$BJ$5,B$27,Monthly!$C$50:$BJ$50) -> -64148.399 | C47: =SUMIF(Monthly!$C$5:$BJ$5,C$27,Monthly!$C$50:$BJ$50) -> 111882.38 | D47: =SUMIF(Monthly!$C$5:$BJ$5,D$27,Monthly!$C$50:$BJ$50) -> 140856.65 | E47: =SUMIF(Monthly!$C$5:$BJ$5,E$27,Monthly!$C$50:$BJ$50) -> 170244.04 | F47: =SUMIF(Monthly!$C$5:$BJ$5,F$27,Monthly!$C$50:$BJ$50) -> 200432.4
A48: EBITDA margin | B48: =IF(B37=0,0,B47/B37) -> -0.11165915 | C48: =IF(C37=0,0,C47/C37) -> 0.13391281 | D48: =IF(D37=0,0,D47/D37) -> 0.15891443 | E48: =IF(E37=0,0,E47/E37) -> 0.18104371 | F48: =IF(F37=0,0,F47/F37) -> 0.2009116

Sheet Inputs
A1: Inputs — Low / Base / High | I1: =HYPERLINK("#'Cover'!A1","◂ Contents") -> ◂ Contents
A2: Illustrative assumptions - replace them with your own numbers.
A5: Driver | B5: Low | C5: Base | D5: High | E5: Active | F5: Unit | G5: Source / comment
A6: Grooming demand
A7: Grooming appointments per operating day at maturity (year 1) | B7: 13 | C7: 16 | D7: 19 | E7: =CHOOSE(Dashboard!$B$4,B7,C7,D7) -> 16 | F7: grooms | G7: Low ≤ Base ≤ High
A8: Grooming volume growth per year | B8: 0 | C8: 0.03 | D8: 0.06 | E8: =CHOOSE(Dashboard!$B$4,B8,C8,D8) -> 0.03 | F8: % | G8: Low ≤ Base ≤ High
A9: Operating days per month | B9: 26 | C9: 26 | D9: 26 | E9: =CHOOSE(Dashboard!$B$4,B9,C9,D9) -> 26 | F9: days
A10: Months to reach mature volume (0 = already mature) | B10: 14 | C10: 10 | D10: 8 | E10: =CHOOSE(Dashboard!$B$4,B10,C10,D10) -> 10 | F10: months | G10: Low ≥ Base ≥ High (lower is better)
A11: Volume in month 1, % of mature (grooming and boarding) | B11: 0.3 | C11: 0.4 | D11: 0.5 | E11: =CHOOSE(Dashboard!$B$4,B11,C11,D11) -> 0.4 | F11: % | G11: Low ≤ Base ≤ High
A13: Grooming capacity
A14: Grooming tables / tub stations | B14: 4 | C14: 4 | D14: 4 | E14: =CHOOSE(Dashboard!$B$4,B14,C14,D14) -> 4 | F14: stations
A15: Grooms one station can turn per operating day | B15: 6 | C15: 6 | D15: 6 | E15: =CHOOSE(Dashboard!$B$4,B15,C15,D15) -> 6 | F15: grooms | G15: Low ≤ Base ≤ High
A16: Grooms one groomer can finish per operating day | B16: 5 | C16: 5.5 | D16: 6 | E16: =CHOOSE(Dashboard!$B$4,B16,C16,D16) -> 5.5 | F16: grooms | G16: Low ≤ Base ≤ High
A18: Grooming prices & retail
A19: Average price per groom (year 1) | B19: 68 | C19: 75 | D19: 82 | E19: =CHOOSE(Dashboard!$B$4,B19,C19,D19) -> 75 | F19: $ | G19: Low ≤ Base ≤ High
A20: Price increase per year (grooming, boarding, retail) | B20: 0.01 | C20: 0.03 | D20: 0.04 | E20: =CHOOSE(Dashboard!$B$4,B20,C20,D20) -> 0.03 | F20: % | G20: Low ≤ Base ≤ High
A21: Retail sales per groom (shampoo, treats, accessories; year 1) | B21: 6 | C21: 8 | D21: 10 | E21: =CHOOSE(Dashboard!$B$4,B21,C21,D21) -> 8 | F21: $ | G21: Low ≤ Base ≤ High
A22: Retail gross margin, % of retail sales | B22: 0.36 | C22: 0.4 | D22: 0.44 | E22: =CHOOSE(Dashboard!$B$4,B22,C22,D22) -> 0.4 | F22: % | G22: Low ≤ Base ≤ High
A24: Boarding
A25: Kennel runs / suites | B25: 30 | C25: 30 | D25: 30 | E25: =CHOOSE(Dashboard!$B$4,B25,C25,D25) -> 30 | F25: runs
A26: Average boarding occupancy at maturity, % of run-nights (year 1) | B26: 0.5 | C26: 0.62 | D26: 0.72 | E26: =CHOOSE(Dashboard!$B$4,B26,C26,D26) -> 0.62 | F26: % | G26: Low ≤ Base ≤ High
A27: Occupancy growth per year (capped at 100%) | B27: 0 | C27: 0.03 | D27: 0.05 | E27: =CHOOSE(Dashboard!$B$4,B27,C27,D27) -> 0.03 | F27: % | G27: Low ≤ Base ≤ High
A28: Peak-season uplift, June-August and December (monthly models) | B28: 0.15 | C28: 0.2 | D28: 0.25 | E28: =CHOOSE(Dashboard!$B$4,B28,C28,D28) -> 0.2 | F28: %
A29: Calendar nights per month | B29: 30.4 | C29: 30.4 | D29: 30.4 | E29: =CHOOSE(Dashboard!$B$4,B29,C29,D29) -> 30.4 | F29: nights
A30: Average nightly rate per run (year 1) | B30: 50 | C30: 55 | D30: 60 | E30: =CHOOSE(Dashboard!$B$4,B30,C30,D30) -> 55 | F30: $ | G30: Low ≤ Base ≤ High
A32: Cost of sales
A33: Groomer commission, % of grooming revenue | B33: 0.37 | C33: 0.35 | D33: 0.33 | E33: =CHOOSE(Dashboard!$B$4,B33,C33,D33) -> 0.35 | F33: % | G33: Low ≥ Base ≥ High (lower is better)
A34: Shampoo, blades & supplies per groom (year 1) | B34: 5 | C34: 4.5 | D34: 4 | E34: =CHOOSE(Dashboard!$B$4,B34,C34,D34) -> 4.5 | F34: $ | G34: Low ≥ Base ≥ High (lower is better)
A35: Food, cleaning & laundry per boarded night (year 1) | B35: 7 | C35: 6 | D35: 5.5 | E35: =CHOOSE(Dashboard!$B$4,B35,C35,D35) -> 6 | F35: $ | G35: Low ≥ Base ≥ High (lower is better)
A37: Shop costs
A38: Shop rent or land cost per month | B38: 9000 | C38: 9000 | D38: 9000 | E38: =CHOOSE(Dashboard!$B$4,B38,C38,D38) -> 9000 | F38: $
A39: Rent increase per year | B39: 0.03 | C39: 0.03 | D39: 0.03 | E39: =CHOOSE(Dashboard!$B$4,B39,C39,D39) -> 0.03 | F39: %
A40: Insurance (care, custody, liability) per month | B40: 2500 | C40: 2500 | D40: 2500 | E40: =CHOOSE(Dashboard!$B$4,B40,C40,D40) -> 2500 | F40: $
A41: Utilities, software, vet-on-call & other G&A per month | B41: 4500 | C41: 4500 | D41: 4500 | E41: =CHOOSE(Dashboard!$B$4,B41,C41,D41) -> 4500 | F41: $
A42: Marketing budget per month (year 1) | B42: 3500 | C42: 3500 | D42: 3500 | E42: =CHOOSE(Dashboard!$B$4,B42,C42,D42) -> 3500 | F42: $
A43: Marketing budget growth per year | B43: -0.3 | C43: -0.2 | D43: -0.1 | E43: =CHOOSE(Dashboard!$B$4,B43,C43,D43) -> -0.2 | F43: % | G43: Low ≤ Base ≤ High
A44: Card processing fees, % of revenue | B44: 0.032 | C44: 0.03 | D44: 0.028 | E44: =CHOOSE(Dashboard!$B$4,B44,C44,D44) -> 0.03 | F44: % | G44: Low ≥ Base ≥ High (lower is better)
A45: Cost increase per year (insurance, utilities, supplies, food) | B45: 0.04 | C45: 0.03 | D45: 0.025 | E45: =CHOOSE(Dashboard!$B$4,B45,C45,D45) -> 0.03 | F45: % | G45: Low ≥ Base ≥ High (lower is better)
A47: Capital spending
A48: Grooming table, tub & dryer per station (month 1) | B48: 6000 | C48: 6000 | D48: 6000 | E48: =CHOOSE(Dashboard!$B$4,B48,C48,D48) -> 6000 | F48: $
A49: Kennel run build-out per run (month 1) | B49: 2500 | C49: 2500 | D49: 2500 | E49: =CHOOSE(Dashboard!$B$4,B49,C49,D49) -> 2500 | F49: $
A50: Leasehold improvements, flooring, HVAC & signage (month 1) | B50: 90000 | C50: 90000 | D50: 90000 | E50: =CHOOSE(Dashboard!$B$4,B50,C50,D50) -> 90000 | F50: $
A51: Land or building purchase (month 1; never depreciated, 0 = leased shop) | B51: 0 | C51: 0 | D51: 0 | E51: =CHOOSE(Dashboard!$B$4,B51,C51,D51) -> 0 | F51: $
A52: Equipment & kennel refresh per year (from year 2) | B52: 10000 | C52: 10000 | D52: 10000 | E52: =CHOOSE(Dashboard!$B$4,B52,C52,D52) -> 10000 | F52: $
A54: Headcount
A55: Groomers (guaranteed base pay): headcount (FTE) | B55: 4 | C55: 4 | D55: 4 | E55: =CHOOSE(Dashboard!$B$4,B55,C55,D55) -> 4 | F55: FTE | G55: Low ≤ Base ≤ High
A56: Groomers (guaranteed base pay): salary per FTE per year | B56: 10000 | C56: 10000 | D56: 10000 | E56: =CHOOSE(Dashboard!$B$4,B56,C56,D56) -> 10000 | F56: $
A57: Groomers (guaranteed base pay): headcount growth per year | B57: 0 | C57: 0 | D57: 0 | E57: =CHOOSE(Dashboard!$B$4,B57,C57,D57) -> 0 | F57: % | G57: Low ≤ Base ≤ High
A58: Groomers (guaranteed base pay): first month on payroll | B58: 1 | C58: 1 | D58: 1 | E58: =CHOOSE(Dashboard!$B$4,B58,C58,D58) -> 1 | F58: month #
A59: Kennel attendants & daycare: headcount (FTE) | B59: 3 | C59: 3 | D59: 3 | E59: =CHOOSE(Dashboard!$B$4,B59,C59,D59) -> 3 | F59: FTE | G59: Low ≤ Base ≤ High
A60: Kennel attendants & daycare: salary per FTE per year | B60: 33000 | C60: 33000 | D60: 33000 | E60: =CHOOSE(Dashboard!$B$4,B60,C60,D60) -> 33000 | F60: $
A61: Kennel attendants & daycare: headcount growth per year | B61: 0 | C61: 0 | D61: 0 | E61: =CHOOSE(Dashboard!$B$4,B61,C61,D61) -> 0 | F61: % | G61: Low ≤ Base ≤ High
A62: Kennel attendants & daycare: first month on payroll | B62: 1 | C62: 1 | D62: 1 | E62: =CHOOSE(Dashboard!$B$4,B62,C62,D62) -> 1 | F62: month #
A63: Manager & front desk: headcount (FTE) | B63: 1 | C63: 1 | D63: 1 | E63: =CHOOSE(Dashboard!$B$4,B63,C63,D63) -> 1 | F63: FTE | G63: Low ≤ Base ≤ High
A64: Manager & front desk: salary per FTE per year | B64: 60000 | C64: 60000 | D64: 60000 | E64: =CHOOSE(Dashboard!$B$4,B64,C64,D64) -> 60000 | F64: $
A65: Manager & front desk: headcount growth per year | B65: 0 | C65: 0 | D65: 0 | E65: =CHOOSE(Dashboard!$B$4,B65,C65,D65) -> 0 | F65: % | G65: Low ≤ Base ≤ High
A66: Manager & front desk: first month on payroll | B66: 1 | C66: 1 | D66: 1 | E66: =CHOOSE(Dashboard!$B$4,B66,C66,D66) -> 1 | F66: month #
A67: Payroll taxes & benefits, % of salary | B67: 0.15 | C67: 0.15 | D67: 0.15 | E67: =CHOOSE(Dashboard!$B$4,B67,C67,D67) -> 0.15 | F67: %
A68: Wage growth per year | B68: 0.04 | C68: 0.03 | D68: 0.03 | E68: =CHOOSE(Dashboard!$B$4,B68,C68,D68) -> 0.03 | F68: %
A70: Funding
A71: Equity raised at start | B71: 330000 | C71: 330000 | D71: 330000 | E71: =CHOOSE(Dashboard!$B$4,B71,C71,D71) -> 330000 | F71: $
A72: Loan drawn at start | B72: 100000 | C72: 100000 | D72: 100000 | E72: =CHOOSE(Dashboard!$B$4,B72,C72,D72) -> 100000 | F72: $
A73: Loan interest rate per year | B73: 0.09 | C73: 0.09 | D73: 0.09 | E73: =CHOOSE(Dashboard!$B$4,B73,C73,D73) -> 0.09 | F73: %
A74: Loan repayment term | B74: 5 | C74: 5 | D74: 5 | E74: =CHOOSE(Dashboard!$B$4,B74,C74,D74) -> 5 | F74: years
A76: Working capital
A77: Customer payment terms (receivable days) | B77: 2 | C77: 2 | D77: 2 | E77: =CHOOSE(Dashboard!$B$4,B77,C77,D77) -> 2 | F77: days
A78: Inventory held (days of COGS) | B78: 6 | C78: 6 | D78: 6 | E78: =CHOOSE(Dashboard!$B$4,B78,C78,D78) -> 6 | F78: days
A79: Supplier payment terms (payable days) | B79: 25 | C79: 25 | D79: 25 | E79: =CHOOSE(Dashboard!$B$4,B79,C79,D79) -> 25 | F79: days
A81: Tax & depreciation
A82: Depreciation period for capex | B82: 8 | C82: 8 | D82: 8 | E82: =CHOOSE(Dashboard!$B$4,B82,C82,D82) -> 8 | F82: years
A83: Income tax rate | B83: 0.21 | C83: 0.21 | D83: 0.21 | E83: =CHOOSE(Dashboard!$B$4,B83,C83,D83) -> 0.21 | F83: %
A85: Break-even & funding
A86: Minimum cash buffer to keep | B86: 109000 | C86: 109000 | D86: 109000 | E86: =CHOOSE(Dashboard!$B$4,B86,C86,D86) -> 109000 | F86: $ | G86: About 3 months of costs
A88: Valuation
A89: Discount rate (WACC) | B89: 0.3 | C89: 0.25 | D89: 0.2 | E89: =CHOOSE(Dashboard!$B$4,B89,C89,D89) -> 0.25 | F89: % | G89: Low ≥ Base ≥ High (lower is better)
A90: Terminal growth rate (perpetuity) | B90: 0.01 | C90: 0.02 | D90: 0.03 | E90: =CHOOSE(Dashboard!$B$4,B90,C90,D90) -> 0.02 | F90: % | G90: Low ≤ Base ≤ High
A91: Exit multiple (EV ÷ final-year EBITDA) | B91: 3 | C91: 4 | D91: 5 | E91: =CHOOSE(Dashboard!$B$4,B91,C91,D91) -> 4 | F91: x | G91: Low ≤ Base ≤ High
A92: Sensitivity table: WACC step | B92: 0.01 | C92: 0.01 | D92: 0.01 | E92: =CHOOSE(Dashboard!$B$4,B92,C92,D92) -> 0.01 | F92: %
A93: Sensitivity table: growth step | B93: 0.005 | C93: 0.005 | D93: 0.005 | E93: =CHOOSE(Dashboard!$B$4,B93,C93,D93) -> 0.005 | F93: %
A95: Legend: yellow cell with blue figure = input you can change · black = formula · green = link to another sheet · grey = active value (column E follows the scenario on the Dashboard).

Sheet P&L
A1: Annual profit & loss | H1: =HYPERLINK("#'Cover'!A1","◂ Contents") -> ◂ Contents
A2: Rolled up from the period detail (SUMIF on the year row; balances at year end).
A3: Year # | B3: 1 | C3: 2 | D3: 3 | E3: 4 | F3: 5
B4: Year 1 | C4: Year 2 | D4: Year 3 | E4: Year 4 | F4: Year 5
A5: Revenue | B5: =SUMIF(Monthly!$C$5:$BJ$5,B$3,Monthly!$C$31:$BJ$31) -> 574501.95 | C5: =SUMIF(Monthly!$C$5:$BJ$5,C$3,Monthly!$C$31:$BJ$31) -> 835486.76 | D5: =SUMIF(Monthly!$C$5:$BJ$5,D$3,Monthly!$C$31:$BJ$31) -> 886367.9 | E5: =SUMIF(Monthly!$C$5:$BJ$5,E$3,Monthly!$C$31:$BJ$31) -> 940347.71 | F5: =SUMIF(Monthly!$C$5:$BJ$5,F$3,Monthly!$C$31:$BJ$31) -> 997614.88
A6: Cost of sales | B6: =SUMIF(Monthly!$C$5:$BJ$5,B$3,Monthly!$C$39:$BJ$39) -> -204565.29 | C6: =SUMIF(Monthly!$C$5:$BJ$5,C$3,Monthly!$C$39:$BJ$39) -> -278844.28 | D6: =SUMIF(Monthly!$C$5:$BJ$5,D$3,Monthly!$C$39:$BJ$39) -> -294361.85 | E6: =SUMIF(Monthly!$C$5:$BJ$5,E$3,Monthly!$C$39:$BJ$39) -> -310780.52 | F6: =SUMIF(Monthly!$C$5:$BJ$5,F$3,Monthly!$C$39:$BJ$39) -> -328153.86
A7: Gross profit | B7: =SUMIF(Monthly!$C$5:$BJ$5,B$3,Monthly!$C$40:$BJ$40) -> 369936.66 | C7: =SUMIF(Monthly!$C$5:$BJ$5,C$3,Monthly!$C$40:$BJ$40) -> 556642.48 | D7: =SUMIF(Monthly!$C$5:$BJ$5,D$3,Monthly!$C$40:$BJ$40) -> 592006.05 | E7: =SUMIF(Monthly!$C$5:$BJ$5,E$3,Monthly!$C$40:$BJ$40) -> 629567.18 | F7: =SUMIF(Monthly!$C$5:$BJ$5,F$3,Monthly!$C$40:$BJ$40) -> 669461.03
A8: Gross margin | B8: =IF(B5=0,0,B7/B5) -> 0.64392586 | C8: =IF(C5=0,0,C7/C5) -> 0.66624932 | D8: =IF(D5=0,0,D7/D5) -> 0.66790105 | E8: =IF(E5=0,0,E7/E5) -> 0.66950467 | F8: =IF(F5=0,0,F7/F5) -> 0.67106159
A9: Attendants, manager & other payroll | B9: =SUMIF(Monthly!$C$5:$BJ$5,B$3,Monthly!$C$43:$BJ$43) -> -182850 | C9: =SUMIF(Monthly!$C$5:$BJ$5,C$3,Monthly!$C$43:$BJ$43) -> -188335.5 | D9: =SUMIF(Monthly!$C$5:$BJ$5,D$3,Monthly!$C$43:$BJ$43) -> -193985.57 | E9: =SUMIF(Monthly!$C$5:$BJ$5,E$3,Monthly!$C$43:$BJ$43) -> -199805.13 | F9: =SUMIF(Monthly!$C$5:$BJ$5,F$3,Monthly!$C$43:$BJ$43) -> -205799.29
A10: Shop rent or land cost | B10: =SUMIF(Monthly!$C$5:$BJ$5,B$3,Monthly!$C$44:$BJ$44) -> -108000 | C10: =SUMIF(Monthly!$C$5:$BJ$5,C$3,Monthly!$C$44:$BJ$44) -> -111240 | D10: =SUMIF(Monthly!$C$5:$BJ$5,D$3,Monthly!$C$44:$BJ$44) -> -114577.2 | E10: =SUMIF(Monthly!$C$5:$BJ$5,E$3,Monthly!$C$44:$BJ$44) -> -118014.52 | F10: =SUMIF(Monthly!$C$5:$BJ$5,F$3,Monthly!$C$44:$BJ$44) -> -121554.95
A11: Insurance | B11: =SUMIF(Monthly!$C$5:$BJ$5,B$3,Monthly!$C$45:$BJ$45) -> -30000 | C11: =SUMIF(Monthly!$C$5:$BJ$5,C$3,Monthly!$C$45:$BJ$45) -> -30900 | D11: =SUMIF(Monthly!$C$5:$BJ$5,D$3,Monthly!$C$45:$BJ$45) -> -31827 | E11: =SUMIF(Monthly!$C$5:$BJ$5,E$3,Monthly!$C$45:$BJ$45) -> -32781.81 | F11: =SUMIF(Monthly!$C$5:$BJ$5,F$3,Monthly!$C$45:$BJ$45) -> -33765.264
A12: Utilities, software & other G&A | B12: =SUMIF(Monthly!$C$5:$BJ$5,B$3,Monthly!$C$46:$BJ$46) -> -54000 | C12: =SUMIF(Monthly!$C$5:$BJ$5,C$3,Monthly!$C$46:$BJ$46) -> -55620 | D12: =SUMIF(Monthly!$C$5:$BJ$5,D$3,Monthly!$C$46:$BJ$46) -> -57288.6 | E12: =SUMIF(Monthly!$C$5:$BJ$5,E$3,Monthly!$C$46:$BJ$46) -> -59007.258 | F12: =SUMIF(Monthly!$C$5:$BJ$5,F$3,Monthly!$C$46:$BJ$46) -> -60777.476
A13: Marketing | B13: =SUMIF(Monthly!$C$5:$BJ$5,B$3,Monthly!$C$47:$BJ$47) -> -42000 | C13: =SUMIF(Monthly!$C$5:$BJ$5,C$3,Monthly!$C$47:$BJ$47) -> -33600 | D13: =SUMIF(Monthly!$C$5:$BJ$5,D$3,Monthly!$C$47:$BJ$47) -> -26880 | E13: =SUMIF(Monthly!$C$5:$BJ$5,E$3,Monthly!$C$47:$BJ$47) -> -21504 | F13: =SUMIF(Monthly!$C$5:$BJ$5,F$3,Monthly!$C$47:$BJ$47) -> -17203.2
A14: Card processing fees | B14: =SUMIF(Monthly!$C$5:$BJ$5,B$3,Monthly!$C$48:$BJ$48) -> -17235.058 | C14: =SUMIF(Monthly!$C$5:$BJ$5,C$3,Monthly!$C$48:$BJ$48) -> -25064.603 | D14: =SUMIF(Monthly!$C$5:$BJ$5,D$3,Monthly!$C$48:$BJ$48) -> -26591.037 | E14: =SUMIF(Monthly!$C$5:$BJ$5,E$3,Monthly!$C$48:$BJ$48) -> -28210.431 | F14: =SUMIF(Monthly!$C$5:$BJ$5,F$3,Monthly!$C$48:$BJ$48) -> -29928.446
A15: Total operating expenses | B15: =SUMIF(Monthly!$C$5:$BJ$5,B$3,Monthly!$C$49:$BJ$49) -> -434085.06 | C15: =SUMIF(Monthly!$C$5:$BJ$5,C$3,Monthly!$C$49:$BJ$49) -> -444760.1 | D15: =SUMIF(Monthly!$C$5:$BJ$5,D$3,Monthly!$C$49:$BJ$49) -> -451149.4 | E15: =SUMIF(Monthly!$C$5:$BJ$5,E$3,Monthly!$C$49:$BJ$49) -> -459323.15 | F15: =SUMIF(Monthly!$C$5:$BJ$5,F$3,Monthly!$C$49:$BJ$49) -> -469028.62
A16: EBITDA | B16: =SUMIF(Monthly!$C$5:$BJ$5,B$3,Monthly!$C$50:$BJ$50) -> -64148.399 | C16: =SUMIF(Monthly!$C$5:$BJ$5,C$3,Monthly!$C$50:$BJ$50) -> 111882.38 | D16: =SUMIF(Monthly!$C$5:$BJ$5,D$3,Monthly!$C$50:$BJ$50) -> 140856.65 | E16: =SUMIF(Monthly!$C$5:$BJ$5,E$3,Monthly!$C$50:$BJ$50) -> 170244.04 | F16: =SUMIF(Monthly!$C$5:$BJ$5,F$3,Monthly!$C$50:$BJ$50) -> 200432.4
A17: EBITDA margin | B17: =IF(B5=0,0,B16/B5) -> -0.11165915 | C17: =IF(C5=0,0,C16/C5) -> 0.13391281 | D17: =IF(D5=0,0,D16/D5) -> 0.15891443 | E17: =IF(E5=0,0,E16/E5) -> 0.18104371 | F17: =IF(F5=0,0,F16/F5) -> 0.2009116
A18: Depreciation | B18: =SUMIF(Monthly!$C$5:$BJ$5,B$3,Monthly!$C$70:$BJ$70) -> -23625 | C18: =SUMIF(Monthly!$C$5:$BJ$5,C$3,Monthly!$C$70:$BJ$70) -> -24875 | D18: =SUMIF(Monthly!$C$5:$BJ$5,D$3,Monthly!$C$70:$BJ$70) -> -26125 | E18: =SUMIF(Monthly!$C$5:$BJ$5,E$3,Monthly!$C$70:$BJ$70) -> -27375 | F18: =SUMIF(Monthly!$C$5:$BJ$5,F$3,Monthly!$C$70:$BJ$70) -> -28625
A19: EBIT | B19: =SUMIF(Monthly!$C$5:$BJ$5,B$3,Monthly!$C$53:$BJ$53) -> -87773.399 | C19: =SUMIF(Monthly!$C$5:$BJ$5,C$3,Monthly!$C$53:$BJ$53) -> 87007.379 | D19: =SUMIF(Monthly!$C$5:$BJ$5,D$3,Monthly!$C$53:$BJ$53) -> 114731.65 | E19: =SUMIF(Monthly!$C$5:$BJ$5,E$3,Monthly!$C$53:$BJ$53) -> 142869.04 | F19: =SUMIF(Monthly!$C$5:$BJ$5,F$3,Monthly!$C$53:$BJ$53) -> 171807.4
A20: Interest | B20: =SUMIF(Monthly!$C$5:$BJ$5,B$3,Monthly!$C$54:$BJ$54) -> -8243.75 | C20: =SUMIF(Monthly!$C$5:$BJ$5,C$3,Monthly!$C$54:$BJ$54) -> -6450 | D20: =SUMIF(Monthly!$C$5:$BJ$5,D$3,Monthly!$C$54:$BJ$54) -> -4650 | E20: =SUMIF(Monthly!$C$5:$BJ$5,E$3,Monthly!$C$54:$BJ$54) -> -2850 | F20: =SUMIF(Monthly!$C$5:$BJ$5,F$3,Monthly!$C$54:$BJ$54) -> -1050
A21: Pre-tax income | B21: =SUMIF(Monthly!$C$5:$BJ$5,B$3,Monthly!$C$55:$BJ$55) -> -96017.149 | C21: =SUMIF(Monthly!$C$5:$BJ$5,C$3,Monthly!$C$55:$BJ$55) -> 80557.379 | D21: =SUMIF(Monthly!$C$5:$BJ$5,D$3,Monthly!$C$55:$BJ$55) -> 110081.65 | E21: =SUMIF(Monthly!$C$5:$BJ$5,E$3,Monthly!$C$55:$BJ$55) -> 140019.04 | F21: =SUMIF(Monthly!$C$5:$BJ$5,F$3,Monthly!$C$55:$BJ$55) -> 170757.4
A22: Income tax | B22: =SUMIF(Monthly!$C$5:$BJ$5,B$3,Monthly!$C$58:$BJ$58) -> 0 | C22: =SUMIF(Monthly!$C$5:$BJ$5,C$3,Monthly!$C$58:$BJ$58) -> 0 | D22: =SUMIF(Monthly!$C$5:$BJ$5,D$3,Monthly!$C$58:$BJ$58) -> -19870.594 | E22: =SUMIF(Monthly!$C$5:$BJ$5,E$3,Monthly!$C$58:$BJ$58) -> -29403.997 | F22: =SUMIF(Monthly!$C$5:$BJ$5,F$3,Monthly!$C$58:$BJ$58) -> -35859.054
A23: Net income | B23: =SUMIF(Monthly!$C$5:$BJ$5,B$3,Monthly!$C$59:$BJ$59) -> -96017.149 | C23: =SUMIF(Monthly!$C$5:$BJ$5,C$3,Monthly!$C$59:$BJ$59) -> 80557.379 | D23: =SUMIF(Monthly!$C$5:$BJ$5,D$3,Monthly!$C$59:$BJ$59) -> 90211.054 | E23: =SUMIF(Monthly!$C$5:$BJ$5,E$3,Monthly!$C$59:$BJ$59) -> 110615.04 | F23: =SUMIF(Monthly!$C$5:$BJ$5,F$3,Monthly!$C$59:$BJ$59) -> 134898.35
A24: Net margin | B24: =IF(B5=0,0,B23/B5) -> -0.16713111 | C24: =IF(C5=0,0,C23/C5) -> 0.096419695 | D24: =IF(D5=0,0,D23/D5) -> 0.10177608 | E24: =IF(E5=0,0,E23/E5) -> 0.11763206 | F24: =IF(F5=0,0,F23/F5) -> 0.13522087

Sheet Cash Flow
A1: Annual cash flow statement | H1: =HYPERLINK("#'Cover'!A1","◂ Contents") -> ◂ Contents
A2: Rolled up from the period detail (SUMIF on the year row; balances at year end).
A3: Year # | B3: 1 | C3: 2 | D3: 3 | E3: 4 | F3: 5
B4: Year 1 | C4: Year 2 | D4: Year 3 | E4: Year 4 | F4: Year 5
A5: Net income | B5: =SUMIF(Monthly!$C$5:$BJ$5,B$3,Monthly!$C$59:$BJ$59) -> -96017.149 | C5: =SUMIF(Monthly!$C$5:$BJ$5,C$3,Monthly!$C$59:$BJ$59) -> 80557.379 | D5: =SUMIF(Monthly!$C$5:$BJ$5,D$3,Monthly!$C$59:$BJ$59) -> 90211.054 | E5: =SUMIF(Monthly!$C$5:$BJ$5,E$3,Monthly!$C$59:$BJ$59) -> 110615.04 | F5: =SUMIF(Monthly!$C$5:$BJ$5,F$3,Monthly!$C$59:$BJ$59) -> 134898.35
A6: Add back depreciation | B6: =-SUMIF(Monthly!$C$5:$BJ$5,B$3,Monthly!$C$70:$BJ$70) -> 23625 | C6: =-SUMIF(Monthly!$C$5:$BJ$5,C$3,Monthly!$C$70:$BJ$70) -> 24875 | D6: =-SUMIF(Monthly!$C$5:$BJ$5,D$3,Monthly!$C$70:$BJ$70) -> 26125 | E6: =-SUMIF(Monthly!$C$5:$BJ$5,E$3,Monthly!$C$70:$BJ$70) -> 27375 | F6: =-SUMIF(Monthly!$C$5:$BJ$5,F$3,Monthly!$C$70:$BJ$70) -> 28625
A7: (Increase) / decrease in receivables | B7: =SUMIF(Monthly!$C$5:$BJ$5,B$3,Monthly!$C$84:$BJ$84) -> -4789.8027 | C7: =SUMIF(Monthly!$C$5:$BJ$5,C$3,Monthly!$C$84:$BJ$84) -> -291.69898 | D7: =SUMIF(Monthly!$C$5:$BJ$5,D$3,Monthly!$C$84:$BJ$84) -> -309.46345 | E7: =SUMIF(Monthly!$C$5:$BJ$5,E$3,Monthly!$C$84:$BJ$84) -> -328.30977 | F7: =SUMIF(Monthly!$C$5:$BJ$5,F$3,Monthly!$C$84:$BJ$84) -> -348.30384
A8: (Increase) / decrease in inventory | B8: =SUMIF(Monthly!$C$5:$BJ$5,B$3,Monthly!$C$85:$BJ$85) -> -4538.6603 | C8: =SUMIF(Monthly!$C$5:$BJ$5,C$3,Monthly!$C$85:$BJ$85) -> -252.71441 | D8: =SUMIF(Monthly!$C$5:$BJ$5,D$3,Monthly!$C$85:$BJ$85) -> -267.39402 | E8: =SUMIF(Monthly!$C$5:$BJ$5,E$3,Monthly!$C$85:$BJ$85) -> -282.94629 | F8: =SUMIF(Monthly!$C$5:$BJ$5,F$3,Monthly!$C$85:$BJ$85) -> -299.42374
A9: Increase / (decrease) in payables | B9: =SUMIF(Monthly!$C$5:$BJ$5,B$3,Monthly!$C$86:$BJ$86) -> 18911.084 | C9: =SUMIF(Monthly!$C$5:$BJ$5,C$3,Monthly!$C$86:$BJ$86) -> 1052.9767 | D9: =SUMIF(Monthly!$C$5:$BJ$5,D$3,Monthly!$C$86:$BJ$86) -> 1114.1417 | E9: =SUMIF(Monthly!$C$5:$BJ$5,E$3,Monthly!$C$86:$BJ$86) -> 1178.9429 | F9: =SUMIF(Monthly!$C$5:$BJ$5,F$3,Monthly!$C$86:$BJ$86) -> 1247.5989
A10: Operating cash flow | B10: =SUMIF(Monthly!$C$5:$BJ$5,B$3,Monthly!$C$89:$BJ$89) -> -62809.527 | C10: =SUMIF(Monthly!$C$5:$BJ$5,C$3,Monthly!$C$89:$BJ$89) -> 105940.94 | D10: =SUMIF(Monthly!$C$5:$BJ$5,D$3,Monthly!$C$89:$BJ$89) -> 116873.34 | E10: =SUMIF(Monthly!$C$5:$BJ$5,E$3,Monthly!$C$89:$BJ$89) -> 138557.72 | F10: =SUMIF(Monthly!$C$5:$BJ$5,F$3,Monthly!$C$89:$BJ$89) -> 164123.22
A11: Capital spending | B11: =SUMIF(Monthly!$C$5:$BJ$5,B$3,Monthly!$C$90:$BJ$90) -> -189000 | C11: =SUMIF(Monthly!$C$5:$BJ$5,C$3,Monthly!$C$90:$BJ$90) -> -10000 | D11: =SUMIF(Monthly!$C$5:$BJ$5,D$3,Monthly!$C$90:$BJ$90) -> -10000 | E11: =SUMIF(Monthly!$C$5:$BJ$5,E$3,Monthly!$C$90:$BJ$90) -> -10000 | F11: =SUMIF(Monthly!$C$5:$BJ$5,F$3,Monthly!$C$90:$BJ$90) -> -10000
A12: Equity raised | B12: =SUMIF(Monthly!$C$5:$BJ$5,B$3,Monthly!$C$91:$BJ$91) -> 330000 | C12: =SUMIF(Monthly!$C$5:$BJ$5,C$3,Monthly!$C$91:$BJ$91) -> 0 | D12: =SUMIF(Monthly!$C$5:$BJ$5,D$3,Monthly!$C$91:$BJ$91) -> 0 | E12: =SUMIF(Monthly!$C$5:$BJ$5,E$3,Monthly!$C$91:$BJ$91) -> 0 | F12: =SUMIF(Monthly!$C$5:$BJ$5,F$3,Monthly!$C$91:$BJ$91) -> 0
A13: Loan drawdown | B13: =SUMIF(Monthly!$C$5:$BJ$5,B$3,Monthly!$C$76:$BJ$76) -> 100000 | C13: =SUMIF(Monthly!$C$5:$BJ$5,C$3,Monthly!$C$76:$BJ$76) -> 0 | D13: =SUMIF(Monthly!$C$5:$BJ$5,D$3,Monthly!$C$76:$BJ$76) -> 0 | E13: =SUMIF(Monthly!$C$5:$BJ$5,E$3,Monthly!$C$76:$BJ$76) -> 0 | F13: =SUMIF(Monthly!$C$5:$BJ$5,F$3,Monthly!$C$76:$BJ$76) -> 0
A14: Loan repayment | B14: =SUMIF(Monthly!$C$5:$BJ$5,B$3,Monthly!$C$77:$BJ$77) -> -18333.333 | C14: =SUMIF(Monthly!$C$5:$BJ$5,C$3,Monthly!$C$77:$BJ$77) -> -20000 | D14: =SUMIF(Monthly!$C$5:$BJ$5,D$3,Monthly!$C$77:$BJ$77) -> -20000 | E14: =SUMIF(Monthly!$C$5:$BJ$5,E$3,Monthly!$C$77:$BJ$77) -> -20000 | F14: =SUMIF(Monthly!$C$5:$BJ$5,F$3,Monthly!$C$77:$BJ$77) -> -20000
A15: Financing cash flow | B15: =SUMIF(Monthly!$C$5:$BJ$5,B$3,Monthly!$C$92:$BJ$92) -> 411666.67 | C15: =SUMIF(Monthly!$C$5:$BJ$5,C$3,Monthly!$C$92:$BJ$92) -> -20000 | D15: =SUMIF(Monthly!$C$5:$BJ$5,D$3,Monthly!$C$92:$BJ$92) -> -20000 | E15: =SUMIF(Monthly!$C$5:$BJ$5,E$3,Monthly!$C$92:$BJ$92) -> -20000 | F15: =SUMIF(Monthly!$C$5:$BJ$5,F$3,Monthly!$C$92:$BJ$92) -> -20000
A16: Net change in cash | B16: =SUMIF(Monthly!$C$5:$BJ$5,B$3,Monthly!$C$93:$BJ$93) -> 159857.14 | C16: =SUMIF(Monthly!$C$5:$BJ$5,C$3,Monthly!$C$93:$BJ$93) -> 75940.942 | D16: =SUMIF(Monthly!$C$5:$BJ$5,D$3,Monthly!$C$93:$BJ$93) -> 86873.338 | E16: =SUMIF(Monthly!$C$5:$BJ$5,E$3,Monthly!$C$93:$BJ$93) -> 108557.72 | F16: =SUMIF(Monthly!$C$5:$BJ$5,F$3,Monthly!$C$93:$BJ$93) -> 134123.22
A17: Opening cash | B17: =INDEX(Monthly!$C$94:$BJ$94,(B$3-1)*12+1) -> 0 | C17: =INDEX(Monthly!$C$94:$BJ$94,(C$3-1)*12+1) -> 159857.14 | D17: =INDEX(Monthly!$C$94:$BJ$94,(D$3-1)*12+1) -> 235798.08 | E17: =INDEX(Monthly!$C$94:$BJ$94,(E$3-1)*12+1) -> 322671.42 | F17: =INDEX(Monthly!$C$94:$BJ$94,(F$3-1)*12+1) -> 431229.14
A18: Closing cash | B18: =INDEX(Monthly!$C$95:$BJ$95,B$3*12) -> 159857.14 | C18: =INDEX(Monthly!$C$95:$BJ$95,C$3*12) -> 235798.08 | D18: =INDEX(Monthly!$C$95:$BJ$95,D$3*12) -> 322671.42 | E18: =INDEX(Monthly!$C$95:$BJ$95,E$3*12) -> 431229.14 | F18: =INDEX(Monthly!$C$95:$BJ$95,F$3*12) -> 565352.36

Sheet Balance Sheet
A1: Balance sheet at year end | H1: =HYPERLINK("#'Cover'!A1","◂ Contents") -> ◂ Contents
A2: Rolled up from the period detail (SUMIF on the year row; balances at year end).
A3: Year # | B3: 1 | C3: 2 | D3: 3 | E3: 4 | F3: 5
B4: Year 1 | C4: Year 2 | D4: Year 3 | E4: Year 4 | F4: Year 5
A5: Cash | B5: =INDEX(Monthly!$C$95:$BJ$95,B$3*12) -> 159857.14 | C5: =INDEX(Monthly!$C$95:$BJ$95,C$3*12) -> 235798.08 | D5: =INDEX(Monthly!$C$95:$BJ$95,D$3*12) -> 322671.42 | E5: =INDEX(Monthly!$C$95:$BJ$95,E$3*12) -> 431229.14 | F5: =INDEX(Monthly!$C$95:$BJ$95,F$3*12) -> 565352.36
A6: Accounts receivable | B6: =INDEX(Monthly!$C$81:$BJ$81,B$3*12) -> 4789.8027 | C6: =INDEX(Monthly!$C$81:$BJ$81,C$3*12) -> 5081.5016 | D6: =INDEX(Monthly!$C$81:$BJ$81,D$3*12) -> 5390.9651 | E6: =INDEX(Monthly!$C$81:$BJ$81,E$3*12) -> 5719.2749 | F6: =INDEX(Monthly!$C$81:$BJ$81,F$3*12) -> 6067.5787
A7: Inventory | B7: =INDEX(Monthly!$C$82:$BJ$82,B$3*12) -> 4538.6603 | C7: =INDEX(Monthly!$C$82:$BJ$82,C$3*12) -> 4791.3747 | D7: =INDEX(Monthly!$C$82:$BJ$82,D$3*12) -> 5058.7687 | E7: =INDEX(Monthly!$C$82:$BJ$82,E$3*12) -> 5341.715 | F7: =INDEX(Monthly!$C$82:$BJ$82,F$3*12) -> 5641.1387
A8: Net fixed assets | B8: =INDEX(Monthly!$C$72:$BJ$72,B$3*12) -> 165375 | C8: =INDEX(Monthly!$C$72:$BJ$72,C$3*12) -> 150500 | D8: =INDEX(Monthly!$C$72:$BJ$72,D$3*12) -> 134375 | E8: =INDEX(Monthly!$C$72:$BJ$72,E$3*12) -> 117000 | F8: =INDEX(Monthly!$C$72:$BJ$72,F$3*12) -> 98375
A9: Total assets | B9: =INDEX(Monthly!$C$109:$BJ$109,B$3*12) -> 334560.6 | C9: =INDEX(Monthly!$C$109:$BJ$109,C$3*12) -> 396170.96 | D9: =INDEX(Monthly!$C$109:$BJ$109,D$3*12) -> 467496.15 | E9: =INDEX(Monthly!$C$109:$BJ$109,E$3*12) -> 559290.13 | F9: =INDEX(Monthly!$C$109:$BJ$109,F$3*12) -> 675436.08
A10: Accounts payable | B10: =INDEX(Monthly!$C$83:$BJ$83,B$3*12) -> 18911.084 | C10: =INDEX(Monthly!$C$83:$BJ$83,C$3*12) -> 19964.061 | D10: =INDEX(Monthly!$C$83:$BJ$83,D$3*12) -> 21078.203 | E10: =INDEX(Monthly!$C$83:$BJ$83,E$3*12) -> 22257.146 | F10: =INDEX(Monthly!$C$83:$BJ$83,F$3*12) -> 23504.745
A11: Loan | B11: =INDEX(Monthly!$C$78:$BJ$78,B$3*12) -> 81666.667 | C11: =INDEX(Monthly!$C$78:$BJ$78,C$3*12) -> 61666.667 | D11: =INDEX(Monthly!$C$78:$BJ$78,D$3*12) -> 41666.667 | E11: =INDEX(Monthly!$C$78:$BJ$78,E$3*12) -> 21666.667 | F11: =INDEX(Monthly!$C$78:$BJ$78,F$3*12) -> 1666.6667
A12: Total liabilities | B12: =INDEX(Monthly!$C$110:$BJ$110,B$3*12) -> 100577.75 | C12: =INDEX(Monthly!$C$110:$BJ$110,C$3*12) -> 81630.728 | D12: =INDEX(Monthly!$C$110:$BJ$110,D$3*12) -> 62744.87 | E12: =INDEX(Monthly!$C$110:$BJ$110,E$3*12) -> 43923.812 | F12: =INDEX(Monthly!$C$110:$BJ$110,F$3*12) -> 25171.411
A13: Paid-in capital | B13: =INDEX(Monthly!$C$107:$BJ$107,B$3*12) -> 330000 | C13: =INDEX(Monthly!$C$107:$BJ$107,C$3*12) -> 330000 | D13: =INDEX(Monthly!$C$107:$BJ$107,D$3*12) -> 330000 | E13: =INDEX(Monthly!$C$107:$BJ$107,E$3*12) -> 330000 | F13: =INDEX(Monthly!$C$107:$BJ$107,F$3*12) -> 330000
A14: Retained earnings | B14: =INDEX(Monthly!$C$108:$BJ$108,B$3*12) -> -96017.149 | C14: =INDEX(Monthly!$C$108:$BJ$108,C$3*12) -> -15459.77 | D14: =INDEX(Monthly!$C$108:$BJ$108,D$3*12) -> 74751.284 | E14: =INDEX(Monthly!$C$108:$BJ$108,E$3*12) -> 185366.32 | F14: =INDEX(Monthly!$C$108:$BJ$108,F$3*12) -> 320264.67
A15: Total equity | B15: =INDEX(Monthly!$C$111:$BJ$111,B$3*12) -> 233982.85 | C15: =INDEX(Monthly!$C$111:$BJ$111,C$3*12) -> 314540.23 | D15: =INDEX(Monthly!$C$111:$BJ$111,D$3*12) -> 404751.28 | E15: =INDEX(Monthly!$C$111:$BJ$111,E$3*12) -> 515366.32 | F15: =INDEX(Monthly!$C$111:$BJ$111,F$3*12) -> 650264.67
A16: Total liabilities & equity | B16: =INDEX(Monthly!$C$112:$BJ$112,B$3*12) -> 334560.6 | C16: =INDEX(Monthly!$C$112:$BJ$112,C$3*12) -> 396170.96 | D16: =INDEX(Monthly!$C$112:$BJ$112,D$3*12) -> 467496.15 | E16: =INDEX(Monthly!$C$112:$BJ$112,E$3*12) -> 559290.13 | F16: =INDEX(Monthly!$C$112:$BJ$112,F$3*12) -> 675436.08
A17: Check: assets − liabilities − equity (must be 0) | B17: =INDEX(Monthly!$C$113:$BJ$113,B$3*12) -> 0 | C17: =INDEX(Monthly!$C$113:$BJ$113,C$3*12) -> 0 | D17: =INDEX(Monthly!$C$113:$BJ$113,D$3*12) -> 0 | E17: =INDEX(Monthly!$C$113:$BJ$113,E$3*12) -> 0 | F17: =INDEX(Monthly!$C$113:$BJ$113,F$3*12) -> 0

Sheet Monthly
A1: Monthly projection | D1: =HYPERLINK("#'Cover'!A1","◂ Contents") -> ◂ Contents
A2: $ unless stated; costs shown as negatives. Every period uses the same formula.
A3: Month | C3: M1 | D3: M2 | E3: M3 | F3: M4 | G3: M5 | H3: M6 | I3: M7 | J3: M8 | K3: M9 | L3: M10 | M3: M11 | N3: M12 | O3: M13 | P3: M14 | Q3: M15 | R3: M16 | S3: M17 | T3: M18 | U3: M19 | V3: M20 | W3: M21 | X3: M22 | Y3: M23 | Z3: M24 | AA3: M25 | AB3: M26 | AC3: M27 | AD3: M28 | AE3: M29 | AF3: M30 | AG3: M31 | AH3: M32 | AI3: M33 | AJ3: M34 | AK3: M35 | AL3: M36 | AM3: M37 | AN3: M38 | AO3: M39 | AP3: M40 | AQ3: M41 | AR3: M42 | AS3: M43 | AT3: M44 | AU3: M45 | AV3: M46 | AW3: M47 | AX3: M48 | AY3: M49 | AZ3: M50 | BA3: M51 | BB3: M52 | BC3: M53 | BD3: M54 | BE3: M55 | BF3: M56 | BG3: M57 | BH3: M58 | BI3: M59 | BJ3: M60
A4: Period # | C4: 1 | D4: 2 | E4: 3 | F4: 4 | G4: 5 | H4: 6 | I4: 7 | J4: 8 | K4: 9 | L4: 10 | M4: 11 | N4: 12 | O4: 13 | P4: 14 | Q4: 15 | R4: 16 | S4: 17 | T4: 18 | U4: 19 | V4: 20 | W4: 21 | X4: 22 | Y4: 23 | Z4: 24 | AA4: 25 | AB4: 26 | AC4: 27 | AD4: 28 | AE4: 29 | AF4: 30 | AG4: 31 | AH4: 32 | AI4: 33 | AJ4: 34 | AK4: 35 | AL4: 36 | AM4: 37 | AN4: 38 | AO4: 39 | AP4: 40 | AQ4: 41 | AR4: 42 | AS4: 43 | AT4: 44 | AU4: 45 | AV4: 46 | AW4: 47 | AX4: 48 | AY4: 49 | AZ4: 50 | BA4: 51 | BB4: 52 | BC4: 53 | BD4: 54 | BE4: 55 | BF4: 56 | BG4: 57 | BH4: 58 | BI4: 59 | BJ4: 60
A5: Year # | C5: =ROUNDUP(C4*1/12,0) -> 1 | D5: =ROUNDUP(D4*1/12,0) -> 1 | E5: =ROUNDUP(E4*1/12,0) -> 1 | F5: =ROUNDUP(F4*1/12,0) -> 1 | G5: =ROUNDUP(G4*1/12,0) -> 1 | H5: =ROUNDUP(H4*1/12,0) -> 1 | I5: =ROUNDUP(I4*1/12,0) -> 1 | J5: =ROUNDUP(J4*1/12,0) -> 1 | ... BJ5: =ROUNDUP(BJ4*1/12,0) -> 5
A7: Grooming demand
A8: Helper: months of the period still on the ramp-up | C8: =MAX(0,MIN(1,Inputs!$E$10-(C$4-1)*1)) -> 1 | D8: =MAX(0,MIN(1,Inputs!$E$10-(D$4-1)*1)) -> 1 | E8: =MAX(0,MIN(1,Inputs!$E$10-(E$4-1)*1)) -> 1 | F8: =MAX(0,MIN(1,Inputs!$E$10-(F$4-1)*1)) -> 1 | G8: =MAX(0,MIN(1,Inputs!$E$10-(G$4-1)*1)) -> 1 | H8: =MAX(0,MIN(1,Inputs!$E$10-(H$4-1)*1)) -> 1 | I8: =MAX(0,MIN(1,Inputs!$E$10-(I$4-1)*1)) -> 1 | J8: =MAX(0,MIN(1,Inputs!$E$10-(J$4-1)*1)) -> 1 | ... BJ8: =MAX(0,MIN(1,Inputs!$E$10-(BJ$4-1)*1)) -> 0
A9: Ramp-up factor (share of mature volume) | C9: =IF(Inputs!$E$10<=0,1,(C8*Inputs!$E$11+(1-Inputs!$E$11)/MAX(1,Inputs!$E$10)*(C8*(C$4-1)*1+C8*(C8-1)/2)+1-C8)/1) -> 0.4 | D9: =IF(Inputs!$E$10<=0,1,(D8*Inputs!$E$11+(1-Inputs!$E$11)/MAX(1,Inputs!$E$10)*(D8*(D$4-1)*1+D8*(D8-1)/2)+1-D8)/1) -> 0.46 | E9: =IF(Inputs!$E$10<=0,1,(E8*Inputs!$E$11+(1-Inputs!$E$11)/MAX(1,Inputs!$E$10)*(E8*(E$4-1)*1+E8*(E8-1)/2)+1-E8)/1) -> 0.52 | F9: =IF(Inputs!$E$10<=0,1,(F8*Inputs!$E$11+(1-Inputs!$E$11)/MAX(1,Inputs!$E$10)*(F8*(F$4-1)*1+F8*(F8-1)/2)+1-F8)/1) -> 0.58 | G9: =IF(Inputs!$E$10<=0,1,(G8*Inputs!$E$11+(1-Inputs!$E$11)/MAX(1,Inputs!$E$10)*(G8*(G$4-1)*1+G8*(G8-1)/2)+1-G8)/1) -> 0.64 | H9: =IF(Inputs!$E$10<=0,1,(H8*Inputs!$E$11+(1-Inputs!$E$11)/MAX(1,Inputs!$E$10)*(H8*(H$4-1)*1+H8*(H8-1)/2)+1-H8)/1) -> 0.7 | I9: =IF(Inputs!$E$10<=0,1,(I8*Inputs!$E$11+(1-Inputs!$E$11)/MAX(1,Inputs!$E$10)*(I8*(I$4-1)*1+I8*(I8-1)/2)+1-I8)/1) -> 0.76 | J9: =IF(Inputs!$E$10<=0,1,(J8*Inputs!$E$11+(1-Inputs!$E$11)/MAX(1,Inputs!$E$10)*(J8*(J$4-1)*1+J8*(J8-1)/2)+1-J8)/1) -> 0.82 | ... BJ9: =IF(Inputs!$E$10<=0,1,(BJ8*Inputs!$E$11+(1-Inputs!$E$11)/MAX(1,Inputs!$E$10)*(BJ8*(BJ$4-1)*1+BJ8*(BJ8-1)/2)+1-BJ8)/1) -> 1
A10: Grooms demanded | C10: =Inputs!$E$7*(1+Inputs!$E$8)^(C$5-1)*Inputs!$E$9*1*C9 -> 166.4 | D10: =Inputs!$E$7*(1+Inputs!$E$8)^(D$5-1)*Inputs!$E$9*1*D9 -> 191.36 | E10: =Inputs!$E$7*(1+Inputs!$E$8)^(E$5-1)*Inputs!$E$9*1*E9 -> 216.32 | F10: =Inputs!$E$7*(1+Inputs!$E$8)^(F$5-1)*Inputs!$E$9*1*F9 -> 241.28 | G10: =Inputs!$E$7*(1+Inputs!$E$8)^(G$5-1)*Inputs!$E$9*1*G9 -> 266.24 | H10: =Inputs!$E$7*(1+Inputs!$E$8)^(H$5-1)*Inputs!$E$9*1*H9 -> 291.2 | I10: =Inputs!$E$7*(1+Inputs!$E$8)^(I$5-1)*Inputs!$E$9*1*I9 -> 316.16 | J10: =Inputs!$E$7*(1+Inputs!$E$8)^(J$5-1)*Inputs!$E$9*1*J9 -> 341.12 | ... BJ10: =Inputs!$E$7*(1+Inputs!$E$8)^(BJ$5-1)*Inputs!$E$9*1*BJ9 -> 468.21166
A12: Grooming capacity
A13: Groomers (FTE) | C13: =Headcount!C8 -> 4 | D13: =Headcount!D8 -> 4 | E13: =Headcount!E8 -> 4 | F13: =Headcount!F8 -> 4 | G13: =Headcount!G8 -> 4 | H13: =Headcount!H8 -> 4 | I13: =Headcount!I8 -> 4 | J13: =Headcount!J8 -> 4 | ... BJ13: =Headcount!BJ8 -> 4
A14: Station capacity (stations × grooms per station-day × operating days) | C14: =Inputs!$E$14*Inputs!$E$15*Inputs!$E$9*1 -> 624 | D14: =Inputs!$E$14*Inputs!$E$15*Inputs!$E$9*1 -> 624 | E14: =Inputs!$E$14*Inputs!$E$15*Inputs!$E$9*1 -> 624 | F14: =Inputs!$E$14*Inputs!$E$15*Inputs!$E$9*1 -> 624 | G14: =Inputs!$E$14*Inputs!$E$15*Inputs!$E$9*1 -> 624 | H14: =Inputs!$E$14*Inputs!$E$15*Inputs!$E$9*1 -> 624 | I14: =Inputs!$E$14*Inputs!$E$15*Inputs!$E$9*1 -> 624 | J14: =Inputs!$E$14*Inputs!$E$15*Inputs!$E$9*1 -> 624 | ... BJ14: =Inputs!$E$14*Inputs!$E$15*Inputs!$E$9*1 -> 624
A15: Groomer capacity (FTE × grooms per groomer-day × operating days) | C15: =C13*Inputs!$E$16*Inputs!$E$9*1 -> 572 | D15: =D13*Inputs!$E$16*Inputs!$E$9*1 -> 572 | E15: =E13*Inputs!$E$16*Inputs!$E$9*1 -> 572 | F15: =F13*Inputs!$E$16*Inputs!$E$9*1 -> 572 | G15: =G13*Inputs!$E$16*Inputs!$E$9*1 -> 572 | H15: =H13*Inputs!$E$16*Inputs!$E$9*1 -> 572 | I15: =I13*Inputs!$E$16*Inputs!$E$9*1 -> 572 | J15: =J13*Inputs!$E$16*Inputs!$E$9*1 -> 572 | ... BJ15: =BJ13*Inputs!$E$16*Inputs!$E$9*1 -> 572
A16: Grooming capacity (lower of stations and groomers) | C16: =MIN(C14,C15) -> 572 | D16: =MIN(D14,D15) -> 572 | E16: =MIN(E14,E15) -> 572 | F16: =MIN(F14,F15) -> 572 | G16: =MIN(G14,G15) -> 572 | H16: =MIN(H14,H15) -> 572 | I16: =MIN(I14,I15) -> 572 | J16: =MIN(J14,J15) -> 572 | ... BJ16: =MIN(BJ14,BJ15) -> 572
A17: Grooms completed (demand capped by capacity) | C17: =MIN(C10,C16) -> 166.4 | D17: =MIN(D10,D16) -> 191.36 | E17: =MIN(E10,E16) -> 216.32 | F17: =MIN(F10,F16) -> 241.28 | G17: =MIN(G10,G16) -> 266.24 | H17: =MIN(H10,H16) -> 291.2 | I17: =MIN(I10,I16) -> 316.16 | J17: =MIN(J10,J16) -> 341.12 | ... BJ17: =MIN(BJ10,BJ16) -> 468.21166
A18: Grooms lost to the capacity limit | C18: =C10-C17 -> 0 | D18: =D10-D17 -> 0 | E18: =E10-E17 -> 0 | F18: =F10-F17 -> 0 | G18: =G10-G17 -> 0 | H18: =H10-H17 -> 0 | I18: =I10-I17 -> 0 | J18: =J10-J17 -> 0 | ... BJ18: =BJ10-BJ17 -> 0
A20: Boarding
A21: Boarding season factor (June-August, December) | C21: =IF(OR(AND(MOD(C$4-1,12)>=5,MOD(C$4-1,12)<=7),MOD(C$4-1,12)=11),1+Inputs!$E$28,1-Inputs!$E$28/2) -> 0.9 | D21: =IF(OR(AND(MOD(D$4-1,12)>=5,MOD(D$4-1,12)<=7),MOD(D$4-1,12)=11),1+Inputs!$E$28,1-Inputs!$E$28/2) -> 0.9 | E21: =IF(OR(AND(MOD(E$4-1,12)>=5,MOD(E$4-1,12)<=7),MOD(E$4-1,12)=11),1+Inputs!$E$28,1-Inputs!$E$28/2) -> 0.9 | F21: =IF(OR(AND(MOD(F$4-1,12)>=5,MOD(F$4-1,12)<=7),MOD(F$4-1,12)=11),1+Inputs!$E$28,1-Inputs!$E$28/2) -> 0.9 | G21: =IF(OR(AND(MOD(G$4-1,12)>=5,MOD(G$4-1,12)<=7),MOD(G$4-1,12)=11),1+Inputs!$E$28,1-Inputs!$E$28/2) -> 0.9 | H21: =IF(OR(AND(MOD(H$4-1,12)>=5,MOD(H$4-1,12)<=7),MOD(H$4-1,12)=11),1+Inputs!$E$28,1-Inputs!$E$28/2) -> 1.2 | I21: =IF(OR(AND(MOD(I$4-1,12)>=5,MOD(I$4-1,12)<=7),MOD(I$4-1,12)=11),1+Inputs!$E$28,1-Inputs!$E$28/2) -> 1.2 | J21: =IF(OR(AND(MOD(J$4-1,12)>=5,MOD(J$4-1,12)<=7),MOD(J$4-1,12)=11),1+Inputs!$E$28,1-Inputs!$E$28/2) -> 1.2 | ... BJ21: =IF(OR(AND(MOD(BJ$4-1,12)>=5,MOD(BJ$4-1,12)<=7),MOD(BJ$4-1,12)=11),1+Inputs!$E$28,1-Inputs!$E$28/2) -> 1.2
A22: Available run-nights (runs × calendar nights) | C22: =Inputs!$E$25*Inputs!$E$29*1 -> 912 | D22: =Inputs!$E$25*Inputs!$E$29*1 -> 912 | E22: =Inputs!$E$25*Inputs!$E$29*1 -> 912 | F22: =Inputs!$E$25*Inputs!$E$29*1 -> 912 | G22: =Inputs!$E$25*Inputs!$E$29*1 -> 912 | H22: =Inputs!$E$25*Inputs!$E$29*1 -> 912 | I22: =Inputs!$E$25*Inputs!$E$29*1 -> 912 | J22: =Inputs!$E$25*Inputs!$E$29*1 -> 912 | ... BJ22: =Inputs!$E$25*Inputs!$E$29*1 -> 912
A23: Occupancy (maturity × growth × ramp × season, capped at 100%) | C23: =MIN(1,Inputs!$E$26*(1+Inputs!$E$27)^(C$5-1)*C9*C21) -> 0.2232 | D23: =MIN(1,Inputs!$E$26*(1+Inputs!$E$27)^(D$5-1)*D9*D21) -> 0.25668 | E23: =MIN(1,Inputs!$E$26*(1+Inputs!$E$27)^(E$5-1)*E9*E21) -> 0.29016 | F23: =MIN(1,Inputs!$E$26*(1+Inputs!$E$27)^(F$5-1)*F9*F21) -> 0.32364 | G23: =MIN(1,Inputs!$E$26*(1+Inputs!$E$27)^(G$5-1)*G9*G21) -> 0.35712 | H23: =MIN(1,Inputs!$E$26*(1+Inputs!$E$27)^(H$5-1)*H9*H21) -> 0.5208 | I23: =MIN(1,Inputs!$E$26*(1+Inputs!$E$27)^(I$5-1)*I9*I21) -> 0.56544 | J23: =MIN(1,Inputs!$E$26*(1+Inputs!$E$27)^(J$5-1)*J9*J21) -> 0.61008 | ... BJ23: =MIN(1,Inputs!$E$26*(1+Inputs!$E$27)^(BJ$5-1)*BJ9*BJ21) -> 0.83737855
A24: Boarded run-nights | C24: =C22*C23 -> 203.5584 | D24: =D22*D23 -> 234.09216 | E24: =E22*E23 -> 264.62592 | F24: =F22*F23 -> 295.15968 | G24: =G22*G23 -> 325.69344 | H24: =H22*H23 -> 474.9696 | I24: =I22*I23 -> 515.68128 | J24: =J22*J23 -> 556.39296 | ... BJ24: =BJ22*BJ23 -> 763.68924
A26: Revenue
A27: Average price per groom | C27: =Inputs!$E$19*(1+Inputs!$E$20)^(C$5-1) -> 75 | D27: =Inputs!$E$19*(1+Inputs!$E$20)^(D$5-1) -> 75 | E27: =Inputs!$E$19*(1+Inputs!$E$20)^(E$5-1) -> 75 | F27: =Inputs!$E$19*(1+Inputs!$E$20)^(F$5-1) -> 75 | G27: =Inputs!$E$19*(1+Inputs!$E$20)^(G$5-1) -> 75 | H27: =Inputs!$E$19*(1+Inputs!$E$20)^(H$5-1) -> 75 | I27: =Inputs!$E$19*(1+Inputs!$E$20)^(I$5-1) -> 75 | J27: =Inputs!$E$19*(1+Inputs!$E$20)^(J$5-1) -> 75 | ... BJ27: =Inputs!$E$19*(1+Inputs!$E$20)^(BJ$5-1) -> 84.413161
A28: Grooming revenue | C28: =C17*C27 -> 12480 | D28: =D17*D27 -> 14352 | E28: =E17*E27 -> 16224 | F28: =F17*F27 -> 18096 | G28: =G17*G27 -> 19968 | H28: =H17*H27 -> 21840 | I28: =I17*I27 -> 23712 | J28: =J17*J27 -> 25584 | ... BJ28: =BJ17*BJ27 -> 39523.227
A29: Boarding revenue | C29: =C24*Inputs!$E$30*(1+Inputs!$E$20)^(C$5-1) -> 11195.712 | D29: =D24*Inputs!$E$30*(1+Inputs!$E$20)^(D$5-1) -> 12875.069 | E29: =E24*Inputs!$E$30*(1+Inputs!$E$20)^(E$5-1) -> 14554.426 | F29: =F24*Inputs!$E$30*(1+Inputs!$E$20)^(F$5-1) -> 16233.782 | G29: =G24*Inputs!$E$30*(1+Inputs!$E$20)^(G$5-1) -> 17913.139 | H29: =H24*Inputs!$E$30*(1+Inputs!$E$20)^(H$5-1) -> 26123.328 | I29: =I24*Inputs!$E$30*(1+Inputs!$E$20)^(I$5-1) -> 28362.47 | J29: =J24*Inputs!$E$30*(1+Inputs!$E$20)^(J$5-1) -> 30601.613 | ... BJ29: =BJ24*Inputs!$E$30*(1+Inputs!$E$20)^(BJ$5-1) -> 47274.643
A30: Retail revenue | C30: =C17*Inputs!$E$21*(1+Inputs!$E$20)^(C$5-1) -> 1331.2 | D30: =D17*Inputs!$E$21*(1+Inputs!$E$20)^(D$5-1) -> 1530.88 | E30: =E17*Inputs!$E$21*(1+Inputs!$E$20)^(E$5-1) -> 1730.56 | F30: =F17*Inputs!$E$21*(1+Inputs!$E$20)^(F$5-1) -> 1930.24 | G30: =G17*Inputs!$E$21*(1+Inputs!$E$20)^(G$5-1) -> 2129.92 | H30: =H17*Inputs!$E$21*(1+Inputs!$E$20)^(H$5-1) -> 2329.6 | I30: =I17*Inputs!$E$21*(1+Inputs!$E$20)^(I$5-1) -> 2529.28 | J30: =J17*Inputs!$E$21*(1+Inputs!$E$20)^(J$5-1) -> 2728.96 | ... BJ30: =BJ17*Inputs!$E$21*(1+Inputs!$E$20)^(BJ$5-1) -> 4215.8108
A31: Revenue | C31: =C28+C29+C30 -> 25006.912 | D31: =D28+D29+D30 -> 28757.949 | E31: =E28+E29+E30 -> 32508.986 | F31: =F28+F29+F30 -> 36260.022 | G31: =G28+G29+G30 -> 40011.059 | H31: =H28+H29+H30 -> 50292.928 | I31: =I28+I29+I30 -> 54603.75 | J31: =J28+J29+J30 -> 58914.573 | ... BJ31: =BJ28+BJ29+BJ30 -> 91013.681
A33: Cost of sales
A34: Groomer base pay | C34: =Headcount!C14 -> -3833.3333 | D34: =Headcount!D14 -> -3833.3333 | E34: =Headcount!E14 -> -3833.3333 | F34: =Headcount!F14 -> -3833.3333 | G34: =Headcount!G14 -> -3833.3333 | H34: =Headcount!H14 -> -3833.3333 | I34: =Headcount!I14 -> -3833.3333 | J34: =Headcount!J14 -> -3833.3333 | ... BJ34: =Headcount!BJ14 -> -4314.4504
A35: Groomer commission | C35: =-C28*Inputs!$E$33 -> -4368 | D35: =-D28*Inputs!$E$33 -> -5023.2 | E35: =-E28*Inputs!$E$33 -> -5678.4 | F35: =-F28*Inputs!$E$33 -> -6333.6 | G35: =-G28*Inputs!$E$33 -> -6988.8 | H35: =-H28*Inputs!$E$33 -> -7644 | I35: =-I28*Inputs!$E$33 -> -8299.2 | J35: =-J28*Inputs!$E$33 -> -8954.4 | ... BJ35: =-BJ28*Inputs!$E$33 -> -13833.129
A36: Grooming supplies | C36: =-C17*Inputs!$E$34*(1+Inputs!$E$45)^(C$5-1) -> -748.8 | D36: =-D17*Inputs!$E$34*(1+Inputs!$E$45)^(D$5-1) -> -861.12 | E36: =-E17*Inputs!$E$34*(1+Inputs!$E$45)^(E$5-1) -> -973.44 | F36: =-F17*Inputs!$E$34*(1+Inputs!$E$45)^(F$5-1) -> -1085.76 | G36: =-G17*Inputs!$E$34*(1+Inputs!$E$45)^(G$5-1) -> -1198.08 | H36: =-H17*Inputs!$E$34*(1+Inputs!$E$45)^(H$5-1) -> -1310.4 | I36: =-I17*Inputs!$E$34*(1+Inputs!$E$45)^(I$5-1) -> -1422.72 | J36: =-J17*Inputs!$E$34*(1+Inputs!$E$45)^(J$5-1) -> -1535.04 | ... BJ36: =-BJ17*Inputs!$E$34*(1+Inputs!$E$45)^(BJ$5-1) -> -2371.3936
A37: Boarding food, cleaning & laundry | C37: =-C24*Inputs!$E$35*(1+Inputs!$E$45)^(C$5-1) -> -1221.3504 | D37: =-D24*Inputs!$E$35*(1+Inputs!$E$45)^(D$5-1) -> -1404.553 | E37: =-E24*Inputs!$E$35*(1+Inputs!$E$45)^(E$5-1) -> -1587.7555 | F37: =-F24*Inputs!$E$35*(1+Inputs!$E$45)^(F$5-1) -> -1770.9581 | G37: =-G24*Inputs!$E$35*(1+Inputs!$E$45)^(G$5-1) -> -1954.1606 | H37: =-H24*Inputs!$E$35*(1+Inputs!$E$45)^(H$5-1) -> -2849.8176 | I37: =-I24*Inputs!$E$35*(1+Inputs!$E$45)^(I$5-1) -> -3094.0877 | J37: =-J24*Inputs!$E$35*(1+Inputs!$E$45)^(J$5-1) -> -3338.3578 | ... BJ37: =-BJ24*Inputs!$E$35*(1+Inputs!$E$45)^(BJ$5-1) -> -5157.2338
A38: Retail cost of goods | C38: =-C30*(1-Inputs!$E$22) -> -798.72 | D38: =-D30*(1-Inputs!$E$22) -> -918.528 | E38: =-E30*(1-Inputs!$E$22) -> -1038.336 | F38: =-F30*(1-Inputs!$E$22) -> -1158.144 | G38: =-G30*(1-Inputs!$E$22) -> -1277.952 | H38: =-H30*(1-Inputs!$E$22) -> -1397.76 | I38: =-I30*(1-Inputs!$E$22) -> -1517.568 | J38: =-J30*(1-Inputs!$E$22) -> -1637.376 | ... BJ38: =-BJ30*(1-Inputs!$E$22) -> -2529.4865
A39: Cost of sales | C39: =C34+C35+C36+C37+C38 -> -10970.204 | D39: =D34+D35+D36+D37+D38 -> -12040.734 | E39: =E34+E35+E36+E37+E38 -> -13111.265 | F39: =F34+F35+F36+F37+F38 -> -14181.795 | G39: =G34+G35+G36+G37+G38 -> -15252.326 | H39: =H34+H35+H36+H37+H38 -> -17035.311 | I39: =I34+I35+I36+I37+I38 -> -18166.909 | J39: =J34+J35+J36+J37+J38 -> -19298.507 | ... BJ39: =BJ34+BJ35+BJ36+BJ37+BJ38 -> -28205.694
A40: Gross profit | C40: =C31+C39 -> 14036.708 | D40: =D31+D39 -> 16717.215 | E40: =E31+E39 -> 19397.721 | F40: =F31+F39 -> 22078.227 | G40: =G31+G39 -> 24758.733 | H40: =H31+H39 -> 33257.617 | I40: =I31+I39 -> 36436.841 | J40: =J31+J39 -> 39616.066 | ... BJ40: =BJ31+BJ39 -> 62807.987
A42: Operating expenses
A43: Attendants, manager & other payroll | C43: =Headcount!C17-Headcount!C14 -> -15237.5 | D43: =Headcount!D17-Headcount!D14 -> -15237.5 | E43: =Headcount!E17-Headcount!E14 -> -15237.5 | F43: =Headcount!F17-Headcount!F14 -> -15237.5 | G43: =Headcount!G17-Headcount!G14 -> -15237.5 | H43: =Headcount!H17-Headcount!H14 -> -15237.5 | I43: =Headcount!I17-Headcount!I14 -> -15237.5 | J43: =Headcount!J17-Headcount!J14 -> -15237.5 | ... BJ43: =Headcount!BJ17-Headcount!BJ14 -> -17149.94
A44: Shop rent or land cost | C44: =-Inputs!$E$38*(1+Inputs!$E$39)^(C$5-1)*1 -> -9000 | D44: =-Inputs!$E$38*(1+Inputs!$E$39)^(D$5-1)*1 -> -9000 | E44: =-Inputs!$E$38*(1+Inputs!$E$39)^(E$5-1)*1 -> -9000 | F44: =-Inputs!$E$38*(1+Inputs!$E$39)^(F$5-1)*1 -> -9000 | G44: =-Inputs!$E$38*(1+Inputs!$E$39)^(G$5-1)*1 -> -9000 | H44: =-Inputs!$E$38*(1+Inputs!$E$39)^(H$5-1)*1 -> -9000 | I44: =-Inputs!$E$38*(1+Inputs!$E$39)^(I$5-1)*1 -> -9000 | J44: =-Inputs!$E$38*(1+Inputs!$E$39)^(J$5-1)*1 -> -9000 | ... BJ44: =-Inputs!$E$38*(1+Inputs!$E$39)^(BJ$5-1)*1 -> -10129.579
A45: Insurance | C45: =-Inputs!$E$40*(1+Inputs!$E$45)^(C$5-1)*1 -> -2500 | D45: =-Inputs!$E$40*(1+Inputs!$E$45)^(D$5-1)*1 -> -2500 | E45: =-Inputs!$E$40*(1+Inputs!$E$45)^(E$5-1)*1 -> -2500 | F45: =-Inputs!$E$40*(1+Inputs!$E$45)^(F$5-1)*1 -> -2500 | G45: =-Inputs!$E$40*(1+Inputs!$E$45)^(G$5-1)*1 -> -2500 | H45: =-Inputs!$E$40*(1+Inputs!$E$45)^(H$5-1)*1 -> -2500 | I45: =-Inputs!$E$40*(1+Inputs!$E$45)^(I$5-1)*1 -> -2500 | J45: =-Inputs!$E$40*(1+Inputs!$E$45)^(J$5-1)*1 -> -2500 | ... BJ45: =-Inputs!$E$40*(1+Inputs!$E$45)^(BJ$5-1)*1 -> -2813.772
A46: Utilities, software & other G&A | C46: =-Inputs!$E$41*(1+Inputs!$E$45)^(C$5-1)*1 -> -4500 | D46: =-Inputs!$E$41*(1+Inputs!$E$45)^(D$5-1)*1 -> -4500 | E46: =-Inputs!$E$41*(1+Inputs!$E$45)^(E$5-1)*1 -> -4500 | F46: =-Inputs!$E$41*(1+Inputs!$E$45)^(F$5-1)*1 -> -4500 | G46: =-Inputs!$E$41*(1+Inputs!$E$45)^(G$5-1)*1 -> -4500 | H46: =-Inputs!$E$41*(1+Inputs!$E$45)^(H$5-1)*1 -> -4500 | I46: =-Inputs!$E$41*(1+Inputs!$E$45)^(I$5-1)*1 -> -4500 | J46: =-Inputs!$E$41*(1+Inputs!$E$45)^(J$5-1)*1 -> -4500 | ... BJ46: =-Inputs!$E$41*(1+Inputs!$E$45)^(BJ$5-1)*1 -> -5064.7896
A47: Marketing | C47: =-Inputs!$E$42*(1+Inputs!$E$43)^(C$5-1)*1 -> -3500 | D47: =-Inputs!$E$42*(1+Inputs!$E$43)^(D$5-1)*1 -> -3500 | E47: =-Inputs!$E$42*(1+Inputs!$E$43)^(E$5-1)*1 -> -3500 | F47: =-Inputs!$E$42*(1+Inputs!$E$43)^(F$5-1)*1 -> -3500 | G47: =-Inputs!$E$42*(1+Inputs!$E$43)^(G$5-1)*1 -> -3500 | H47: =-Inputs!$E$42*(1+Inputs!$E$43)^(H$5-1)*1 -> -3500 | I47: =-Inputs!$E$42*(1+Inputs!$E$43)^(I$5-1)*1 -> -3500 | J47: =-Inputs!$E$42*(1+Inputs!$E$43)^(J$5-1)*1 -> -3500 | ... BJ47: =-Inputs!$E$42*(1+Inputs!$E$43)^(BJ$5-1)*1 -> -1433.6
A48: Card processing fees | C48: =-C31*Inputs!$E$44 -> -750.20736 | D48: =-D31*Inputs!$E$44 -> -862.73846 | E48: =-E31*Inputs!$E$44 -> -975.26957 | F48: =-F31*Inputs!$E$44 -> -1087.8007 | G48: =-G31*Inputs!$E$44 -> -1200.3318 | H48: =-H31*Inputs!$E$44 -> -1508.7878 | I48: =-I31*Inputs!$E$44 -> -1638.1125 | J48: =-J31*Inputs!$E$44 -> -1767.4372 | ... BJ48: =-BJ31*Inputs!$E$44 -> -2730.4104
A49: Total operating expenses | C49: =C43+C44+C45+C46+C47+C48 -> -35487.707 | D49: =D43+D44+D45+D46+D47+D48 -> -35600.238 | E49: =E43+E44+E45+E46+E47+E48 -> -35712.77 | F49: =F43+F44+F45+F46+F47+F48 -> -35825.301 | G49: =G43+G44+G45+G46+G47+G48 -> -35937.832 | H49: =H43+H44+H45+H46+H47+H48 -> -36246.288 | I49: =I43+I44+I45+I46+I47+I48 -> -36375.613 | J49: =J43+J44+J45+J46+J47+J48 -> -36504.937 | ... BJ49: =BJ43+BJ44+BJ45+BJ46+BJ47+BJ48 -> -39322.092
A50: EBITDA | C50: =C40+C49 -> -21450.999 | D50: =D40+D49 -> -18883.024 | E50: =E40+E49 -> -16315.049 | F50: =F40+F49 -> -13747.074 | G50: =G40+G49 -> -11179.099 | H50: =H40+H49 -> -2988.6708 | I50: =I40+I49 -> 61.228875 | J50: =J40+J49 -> 3111.1285 | ... BJ50: =BJ40+BJ49 -> 23485.895
A52: Profit after depreciation, interest, tax
A53: EBIT | C53: =C50+C70 -> -23419.749 | D53: =D50+D70 -> -20851.774 | E53: =E50+E70 -> -18283.799 | F53: =F50+F70 -> -15715.824 | G53: =G50+G70 -> -13147.849 | H53: =H50+H70 -> -4957.4208 | I53: =I50+I70 -> -1907.5211 | J53: =J50+J70 -> 1142.3785 | ... BJ53: =BJ50+BJ70 -> 21100.479
A54: Interest on loan (average balance after drawdown) | C54: =-(C75+C76+C78)/2*Inputs!$E$73/12 -> -750 | D54: =-(D75+D76+D78)/2*Inputs!$E$73/12 -> -743.75 | E54: =-(E75+E76+E78)/2*Inputs!$E$73/12 -> -731.25 | F54: =-(F75+F76+F78)/2*Inputs!$E$73/12 -> -718.75 | G54: =-(G75+G76+G78)/2*Inputs!$E$73/12 -> -706.25 | H54: =-(H75+H76+H78)/2*Inputs!$E$73/12 -> -693.75 | I54: =-(I75+I76+I78)/2*Inputs!$E$73/12 -> -681.25 | J54: =-(J75+J76+J78)/2*Inputs!$E$73/12 -> -668.75 | ... BJ54: =-(BJ75+BJ76+BJ78)/2*Inputs!$E$73/12 -> -18.75
A55: Pre-tax income | C55: =C53+C54 -> -24169.749 | D55: =D53+D54 -> -21595.524 | E55: =E53+E54 -> -19015.049 | F55: =F53+F54 -> -16434.574 | G55: =G53+G54 -> -13854.099 | H55: =H53+H54 -> -5651.1708 | I55: =I53+I54 -> -2588.7711 | J55: =J53+J54 -> 473.62852 | ... BJ55: =BJ53+BJ54 -> 21081.729
A56: Helper: cumulative pre-tax income | C56: =C55 -> -24169.749 | D56: =C56+D55 -> -45765.273 | E56: =D56+E55 -> -64780.322 | F56: =E56+F55 -> -81214.896 | G56: =F56+G55 -> -95068.994 | H56: =G56+H55 -> -100720.16 | I56: =H56+I55 -> -103308.94 | J56: =I56+J55 -> -102835.31 | K56: =J56+K55 -> -106367.51 | ... BJ56: =BI56+BJ55 -> 405398.32
A57: Helper: cumulative taxable income (losses carried forward) | C57: =MAX(0,C56) -> 0 | D57: =MAX(C57,D56) -> 0 | E57: =MAX(D57,E56) -> 0 | F57: =MAX(E57,F56) -> 0 | G57: =MAX(F57,G56) -> 0 | H57: =MAX(G57,H56) -> 0 | I57: =MAX(H57,I56) -> 0 | J57: =MAX(I57,J56) -> 0 | K57: =MAX(J57,K56) -> 0 | ... BJ57: =MAX(BI57,BJ56) -> 405398.32
A58: Income tax | C58: =-C57*Inputs!$E$83 -> 0 | D58: =-(D57-C57)*Inputs!$E$83 -> 0 | E58: =-(E57-D57)*Inputs!$E$83 -> 0 | F58: =-(F57-E57)*Inputs!$E$83 -> 0 | G58: =-(G57-F57)*Inputs!$E$83 -> 0 | H58: =-(H57-G57)*Inputs!$E$83 -> 0 | I58: =-(I57-H57)*Inputs!$E$83 -> 0 | J58: =-(J57-I57)*Inputs!$E$83 -> 0 | K58: =-(K57-J57)*Inputs!$E$83 -> 0 | ... BJ58: =-(BJ57-BI57)*Inputs!$E$83 -> -4427.163
A59: Net income | C59: =C55+C58 -> -24169.749 | D59: =D55+D58 -> -21595.524 | E59: =E55+E58 -> -19015.049 | F59: =F55+F58 -> -16434.574 | G59: =G55+G58 -> -13854.099 | H59: =H55+H58 -> -5651.1708 | I59: =I55+I58 -> -2588.7711 | J59: =J55+J58 -> 473.62852 | ... BJ59: =BJ55+BJ58 -> 16654.566
A61: Fixed assets & capital spending
A62: Grooming tables, tubs & dryers | C62: =IF(C$4=1,Inputs!$E$14*Inputs!$E$48,0) -> 24000 | D62: =IF(D$4=1,Inputs!$E$14*Inputs!$E$48,0) -> 0 | E62: =IF(E$4=1,Inputs!$E$14*Inputs!$E$48,0) -> 0 | F62: =IF(F$4=1,Inputs!$E$14*Inputs!$E$48,0) -> 0 | G62: =IF(G$4=1,Inputs!$E$14*Inputs!$E$48,0) -> 0 | H62: =IF(H$4=1,Inputs!$E$14*Inputs!$E$48,0) -> 0 | I62: =IF(I$4=1,Inputs!$E$14*Inputs!$E$48,0) -> 0 | J62: =IF(J$4=1,Inputs!$E$14*Inputs!$E$48,0) -> 0 | ... BJ62: =IF(BJ$4=1,Inputs!$E$14*Inputs!$E$48,0) -> 0
A63: Kennel run build-out | C63: =IF(C$4=1,Inputs!$E$25*Inputs!$E$49,0) -> 75000 | D63: =IF(D$4=1,Inputs!$E$25*Inputs!$E$49,0) -> 0 | E63: =IF(E$4=1,Inputs!$E$25*Inputs!$E$49,0) -> 0 | F63: =IF(F$4=1,Inputs!$E$25*Inputs!$E$49,0) -> 0 | G63: =IF(G$4=1,Inputs!$E$25*Inputs!$E$49,0) -> 0 | H63: =IF(H$4=1,Inputs!$E$25*Inputs!$E$49,0) -> 0 | I63: =IF(I$4=1,Inputs!$E$25*Inputs!$E$49,0) -> 0 | J63: =IF(J$4=1,Inputs!$E$25*Inputs!$E$49,0) -> 0 | ... BJ63: =IF(BJ$4=1,Inputs!$E$25*Inputs!$E$49,0) -> 0
A64: Leasehold improvements & signage | C64: =IF(C$4=1,Inputs!$E$50,0) -> 90000 | D64: =IF(D$4=1,Inputs!$E$50,0) -> 0 | E64: =IF(E$4=1,Inputs!$E$50,0) -> 0 | F64: =IF(F$4=1,Inputs!$E$50,0) -> 0 | G64: =IF(G$4=1,Inputs!$E$50,0) -> 0 | H64: =IF(H$4=1,Inputs!$E$50,0) -> 0 | I64: =IF(I$4=1,Inputs!$E$50,0) -> 0 | J64: =IF(J$4=1,Inputs!$E$50,0) -> 0 | ... BJ64: =IF(BJ$4=1,Inputs!$E$50,0) -> 0
A65: Land or building (not depreciated) | C65: =IF(C$4=1,Inputs!$E$51,0) -> 0 | D65: =IF(D$4=1,Inputs!$E$51,0) -> 0 | E65: =IF(E$4=1,Inputs!$E$51,0) -> 0 | F65: =IF(F$4=1,Inputs!$E$51,0) -> 0 | G65: =IF(G$4=1,Inputs!$E$51,0) -> 0 | H65: =IF(H$4=1,Inputs!$E$51,0) -> 0 | I65: =IF(I$4=1,Inputs!$E$51,0) -> 0 | J65: =IF(J$4=1,Inputs!$E$51,0) -> 0 | ... BJ65: =IF(BJ$4=1,Inputs!$E$51,0) -> 0
A66: Equipment & kennel refresh (first period of each year from year 2) | C66: =IF(AND(C$5>1,MOD(C$4-1,12)=0),Inputs!$E$52,0) -> 0 | D66: =IF(AND(D$5>1,MOD(D$4-1,12)=0),Inputs!$E$52,0) -> 0 | E66: =IF(AND(E$5>1,MOD(E$4-1,12)=0),Inputs!$E$52,0) -> 0 | F66: =IF(AND(F$5>1,MOD(F$4-1,12)=0),Inputs!$E$52,0) -> 0 | G66: =IF(AND(G$5>1,MOD(G$4-1,12)=0),Inputs!$E$52,0) -> 0 | H66: =IF(AND(H$5>1,MOD(H$4-1,12)=0),Inputs!$E$52,0) -> 0 | I66: =IF(AND(I$5>1,MOD(I$4-1,12)=0),Inputs!$E$52,0) -> 0 | J66: =IF(AND(J$5>1,MOD(J$4-1,12)=0),Inputs!$E$52,0) -> 0 | ... BJ66: =IF(AND(BJ$5>1,MOD(BJ$4-1,12)=0),Inputs!$E$52,0) -> 0
A67: Capital spending | C67: =C62+C63+C64+C65+C66 -> 189000 | D67: =D62+D63+D64+D65+D66 -> 0 | E67: =E62+E63+E64+E65+E66 -> 0 | F67: =F62+F63+F64+F65+F66 -> 0 | G67: =G62+G63+G64+G65+G66 -> 0 | H67: =H62+H63+H64+H65+H66 -> 0 | I67: =I62+I63+I64+I65+I66 -> 0 | J67: =J62+J63+J64+J65+J66 -> 0 | ... BJ67: =BJ62+BJ63+BJ64+BJ65+BJ66 -> 0
A68: Fixed assets at cost | C68: =C67 -> 189000 | D68: =C68+D67 -> 189000 | E68: =D68+E67 -> 189000 | F68: =E68+F67 -> 189000 | G68: =F68+G67 -> 189000 | H68: =G68+H67 -> 189000 | I68: =H68+I67 -> 189000 | J68: =I68+J67 -> 189000 | K68: =J68+K67 -> 189000 | ... BJ68: =BI68+BJ67 -> 229000
A69: Land at cost (not depreciated) | C69: =C65 -> 0 | D69: =C69+D65 -> 0 | E69: =D69+E65 -> 0 | F69: =E69+F65 -> 0 | G69: =F69+G65 -> 0 | H69: =G69+H65 -> 0 | I69: =H69+I65 -> 0 | J69: =I69+J65 -> 0 | K69: =J69+K65 -> 0 | ... BJ69: =BI69+BJ65 -> 0
A70: Depreciation | C70: =-MIN((C68-C69)/MAX(1,Inputs!$E$82*12),C67-C69) -> -1968.75 | D70: =-MIN((D68-D69)/MAX(1,Inputs!$E$82*12),C72+D67-D69) -> -1968.75 | E70: =-MIN((E68-E69)/MAX(1,Inputs!$E$82*12),D72+E67-E69) -> -1968.75 | F70: =-MIN((F68-F69)/MAX(1,Inputs!$E$82*12),E72+F67-F69) -> -1968.75 | G70: =-MIN((G68-G69)/MAX(1,Inputs!$E$82*12),F72+G67-G69) -> -1968.75 | H70: =-MIN((H68-H69)/MAX(1,Inputs!$E$82*12),G72+H67-H69) -> -1968.75 | I70: =-MIN((I68-I69)/MAX(1,Inputs!$E$82*12),H72+I67-I69) -> -1968.75 | J70: =-MIN((J68-J69)/MAX(1,Inputs!$E$82*12),I72+J67-J69) -> -1968.75 | K70: =-MIN((K68-K69)/MAX(1,Inputs!$E$82*12),J72+K67-K69) -> -1968.75 | ... BJ70: =-MIN((BJ68-BJ69)/MAX(1,Inputs!$E$82*12),BI72+BJ67-BJ69) -> -2385.4167
A71: Accumulated depreciation | C71: =C70 -> -1968.75 | D71: =C71+D70 -> -3937.5 | E71: =D71+E70 -> -5906.25 | F71: =E71+F70 -> -7875 | G71: =F71+G70 -> -9843.75 | H71: =G71+H70 -> -11812.5 | I71: =H71+I70 -> -13781.25 | J71: =I71+J70 -> -15750 | K71: =J71+K70 -> -17718.75 | ... BJ71: =BI71+BJ70 -> -130625
A72: Net fixed assets | C72: =C68+C71 -> 187031.25 | D72: =D68+D71 -> 185062.5 | E72: =E68+E71 -> 183093.75 | F72: =F68+F71 -> 181125 | G72: =G68+G71 -> 179156.25 | H72: =H68+H71 -> 177187.5 | I72: =I68+I71 -> 175218.75 | J72: =J68+J71 -> 173250 | ... BJ72: =BJ68+BJ71 -> 98375
A74: Debt
A75: Loan — opening balance | C75: =0 -> 0 | D75: =C78 -> 100000 | E75: =D78 -> 98333.333 | F75: =E78 -> 96666.667 | G75: =F78 -> 95000 | H75: =G78 -> 93333.333 | I75: =H78 -> 91666.667 | J75: =I78 -> 90000 | K75: =J78 -> 88333.333 | ... BJ75: =BI78 -> 3333.3333
A76: Loan drawdown | C76: =IF(C$4=1,Inputs!$E$72,0) -> 100000 | D76: =IF(D$4=1,Inputs!$E$72,0) -> 0 | E76: =IF(E$4=1,Inputs!$E$72,0) -> 0 | F76: =IF(F$4=1,Inputs!$E$72,0) -> 0 | G76: =IF(G$4=1,Inputs!$E$72,0) -> 0 | H76: =IF(H$4=1,Inputs!$E$72,0) -> 0 | I76: =IF(I$4=1,Inputs!$E$72,0) -> 0 | J76: =IF(J$4=1,Inputs!$E$72,0) -> 0 | ... BJ76: =IF(BJ$4=1,Inputs!$E$72,0) -> 0
A77: Loan repayment | C77: =-MIN(C75,Inputs!$E$72/MAX(1,Inputs!$E$74*12)) -> 0 | D77: =-MIN(D75,Inputs!$E$72/MAX(1,Inputs!$E$74*12)) -> -1666.6667 | E77: =-MIN(E75,Inputs!$E$72/MAX(1,Inputs!$E$74*12)) -> -1666.6667 | F77: =-MIN(F75,Inputs!$E$72/MAX(1,Inputs!$E$74*12)) -> -1666.6667 | G77: =-MIN(G75,Inputs!$E$72/MAX(1,Inputs!$E$74*12)) -> -1666.6667 | H77: =-MIN(H75,Inputs!$E$72/MAX(1,Inputs!$E$74*12)) -> -1666.6667 | I77: =-MIN(I75,Inputs!$E$72/MAX(1,Inputs!$E$74*12)) -> -1666.6667 | J77: =-MIN(J75,Inputs!$E$72/MAX(1,Inputs!$E$74*12)) -> -1666.6667 | ... BJ77: =-MIN(BJ75,Inputs!$E$72/MAX(1,Inputs!$E$74*12)) -> -1666.6667
A78: Loan — closing balance | C78: =C75+C76+C77 -> 100000 | D78: =D75+D76+D77 -> 98333.333 | E78: =E75+E76+E77 -> 96666.667 | F78: =F75+F76+F77 -> 95000 | G78: =G75+G76+G77 -> 93333.333 | H78: =H75+H76+H77 -> 91666.667 | I78: =I75+I76+I77 -> 90000 | J78: =J75+J76+J77 -> 88333.333 | ... BJ78: =BJ75+BJ76+BJ77 -> 1666.6667
A80: Working capital
A81: Accounts receivable | C81: =C31*Inputs!$E$77/30 -> 1667.1275 | D81: =D31*Inputs!$E$77/30 -> 1917.1966 | E81: =E31*Inputs!$E$77/30 -> 2167.2657 | F81: =F31*Inputs!$E$77/30 -> 2417.3348 | G81: =G31*Inputs!$E$77/30 -> 2667.4039 | H81: =H31*Inputs!$E$77/30 -> 3352.8619 | I81: =I31*Inputs!$E$77/30 -> 3640.25 | J81: =J31*Inputs!$E$77/30 -> 3927.6382 | ... BJ81: =BJ31*Inputs!$E$77/30 -> 6067.5787
A82: Inventory | C82: =-C39*Inputs!$E$78/30 -> 2194.0407 | D82: =-D39*Inputs!$E$78/30 -> 2408.1469 | E82: =-E39*Inputs!$E$78/30 -> 2622.253 | F82: =-F39*Inputs!$E$78/30 -> 2836.3591 | G82: =-G39*Inputs!$E$78/30 -> 3050.4652 | H82: =-H39*Inputs!$E$78/30 -> 3407.0622 | I82: =-I39*Inputs!$E$78/30 -> 3633.3818 | J82: =-J39*Inputs!$E$78/30 -> 3859.7014 | ... BJ82: =-BJ39*Inputs!$E$78/30 -> 5641.1387
A83: Accounts payable | C83: =-C39*Inputs!$E$79/30 -> 9141.8364 | D83: =-D39*Inputs!$E$79/30 -> 10033.945 | E83: =-E39*Inputs!$E$79/30 -> 10926.054 | F83: =-F39*Inputs!$E$79/30 -> 11818.163 | G83: =-G39*Inputs!$E$79/30 -> 12710.272 | H83: =-H39*Inputs!$E$79/30 -> 14196.092 | I83: =-I39*Inputs!$E$79/30 -> 15139.091 | J83: =-J39*Inputs!$E$79/30 -> 16082.089 | ... BJ83: =-BJ39*Inputs!$E$79/30 -> 23504.745
A84: (Increase) / decrease in receivables | C84: =-C81 -> -1667.1275 | D84: =C81-D81 -> -250.06912 | E84: =D81-E81 -> -250.06912 | F84: =E81-F81 -> -250.06912 | G84: =F81-G81 -> -250.06912 | H84: =G81-H81 -> -685.45792 | I84: =H81-I81 -> -287.38816 | J84: =I81-J81 -> -287.38816 | K84: =J81-K81 -> 259.95776 | ... BJ84: =BI81-BJ81 -> -787.91072
A85: (Increase) / decrease in inventory | C85: =-C82 -> -2194.0407 | D85: =C82-D82 -> -214.10611 | E85: =D82-E82 -> -214.10611 | F85: =E82-F82 -> -214.10611 | G85: =F82-G82 -> -214.10611 | H85: =G82-H82 -> -356.59699 | I85: =H82-I82 -> -226.31962 | J85: =I82-J82 -> -226.31962 | K85: =J82-K82 -> -47.188224 | ... BJ85: =BI82-BJ82 -> -257.86169
A86: Increase / (decrease) in payables | C86: =C83 -> 9141.8364 | D86: =D83-C83 -> 892.1088 | E86: =E83-D83 -> 892.1088 | F86: =F83-E83 -> 892.1088 | G86: =G83-F83 -> 892.1088 | H86: =H83-G83 -> 1485.8208 | I86: =I83-H83 -> 942.9984 | J86: =J83-I83 -> 942.9984 | K86: =K83-J83 -> 196.6176 | ... BJ86: =BJ83-BI83 -> 1074.4237
A88: Cash flow
A89: Operating cash flow | C89: =C59-C70+C84+C85+C86 -> -16920.331 | D89: =D59-D70+D84+D85+D86 -> -19198.84 | E89: =E59-E70+E84+E85+E86 -> -16618.365 | F89: =F59-F70+F84+F85+F86 -> -14037.89 | G89: =G59-G70+G84+G85+G86 -> -11457.415 | H89: =H59-H70+H84+H85+H86 -> -3238.6549 | I89: =I59-I70+I84+I85+I86 -> -190.7305 | J89: =J59-J70+J84+J85+J86 -> 2871.6691 | ... BJ89: =BJ59-BJ70+BJ84+BJ85+BJ86 -> 19068.634
A90: Investing cash flow (capex) | C90: =-C67 -> -189000 | D90: =-D67 -> 0 | E90: =-E67 -> 0 | F90: =-F67 -> 0 | G90: =-G67 -> 0 | H90: =-H67 -> 0 | I90: =-I67 -> 0 | J90: =-J67 -> 0 | ... BJ90: =-BJ67 -> 0
A91: Equity raised | C91: =IF(C$4=1,Inputs!$E$71,0) -> 330000 | D91: =IF(D$4=1,Inputs!$E$71,0) -> 0 | E91: =IF(E$4=1,Inputs!$E$71,0) -> 0 | F91: =IF(F$4=1,Inputs!$E$71,0) -> 0 | G91: =IF(G$4=1,Inputs!$E$71,0) -> 0 | H91: =IF(H$4=1,Inputs!$E$71,0) -> 0 | I91: =IF(I$4=1,Inputs!$E$71,0) -> 0 | J91: =IF(J$4=1,Inputs!$E$71,0) -> 0 | ... BJ91: =IF(BJ$4=1,Inputs!$E$71,0) -> 0
A92: Financing cash flow | C92: =C91+C76+C77 -> 430000 | D92: =D91+D76+D77 -> -1666.6667 | E92: =E91+E76+E77 -> -1666.6667 | F92: =F91+F76+F77 -> -1666.6667 | G92: =G91+G76+G77 -> -1666.6667 | H92: =H91+H76+H77 -> -1666.6667 | I92: =I91+I76+I77 -> -1666.6667 | J92: =J91+J76+J77 -> -1666.6667 | ... BJ92: =BJ91+BJ76+BJ77 -> -1666.6667
A93: Net cash flow | C93: =C89+C90+C92 -> 224079.67 | D93: =D89+D90+D92 -> -20865.507 | E93: =E89+E90+E92 -> -18285.032 | F93: =F89+F90+F92 -> -15704.557 | G93: =G89+G90+G92 -> -13124.082 | H93: =H89+H90+H92 -> -4905.3216 | I93: =I89+I90+I92 -> -1857.3972 | J93: =J89+J90+J92 -> 1205.0025 | ... BJ93: =BJ89+BJ90+BJ92 -> 17401.967
A94: Opening cash | C94: =0 -> 0 | D94: =C95 -> 224079.67 | E94: =D95 -> 203214.16 | F94: =E95 -> 184929.13 | G94: =F95 -> 169224.57 | H94: =G95 -> 156100.49 | I94: =H95 -> 151195.17 | J94: =I95 -> 149337.77 | K94: =J95 -> 150542.78 | ... BJ94: =BI95 -> 547950.4
A95: Closing cash | C95: =C94+C93 -> 224079.67 | D95: =D94+D93 -> 203214.16 | E95: =E94+E93 -> 184929.13 | F95: =F94+F93 -> 169224.57 | G95: =G94+G93 -> 156100.49 | H95: =H94+H93 -> 151195.17 | I95: =I94+I93 -> 149337.77 | J95: =J94+J93 -> 150542.78 | ... BJ95: =BJ94+BJ93 -> 565352.36
A96: Helper: EBITDA positive (1/0) | C96: =IF(C50>0,1,0) -> 0 | D96: =IF(D50>0,1,0) -> 0 | E96: =IF(E50>0,1,0) -> 0 | F96: =IF(F50>0,1,0) -> 0 | G96: =IF(G50>0,1,0) -> 0 | H96: =IF(H50>0,1,0) -> 0 | I96: =IF(I50>0,1,0) -> 1 | J96: =IF(J50>0,1,0) -> 1 | ... BJ96: =IF(BJ50>0,1,0) -> 1
A98: Goal modules
A99: Helper: net income positive (1/0) | C99: =IF(C59>0,1,0) -> 0 | D99: =IF(D59>0,1,0) -> 0 | E99: =IF(E59>0,1,0) -> 0 | F99: =IF(F59>0,1,0) -> 0 | G99: =IF(G59>0,1,0) -> 0 | H99: =IF(H59>0,1,0) -> 0 | I99: =IF(I59>0,1,0) -> 0 | J99: =IF(J59>0,1,0) -> 1 | ... BJ99: =IF(BJ59>0,1,0) -> 1
A100: Cash flow before financing (operating + investing) | C100: =C89+C90 -> -205920.33 | D100: =D89+D90 -> -19198.84 | E100: =E89+E90 -> -16618.365 | F100: =F89+F90 -> -14037.89 | G100: =G89+G90 -> -11457.415 | H100: =H89+H90 -> -3238.6549 | I100: =I89+I90 -> -190.7305 | J100: =J89+J90 -> 2871.6691 | ... BJ100: =BJ89+BJ90 -> 19068.634
A101: Cumulative cash flow before financing | C101: =C100 -> -205920.33 | D101: =C101+D100 -> -225119.17 | E101: =D101+E100 -> -241737.54 | F101: =E101+F100 -> -255775.43 | G101: =F101+G100 -> -267232.84 | H101: =G101+H100 -> -270471.5 | I101: =H101+I100 -> -270662.23 | J101: =I101+J100 -> -267790.56 | K101: =J101+K100 -> -268944.62 | ... BJ101: =BI101+BJ100 -> 233685.7
A102: Helper: lowest cumulative cash flow so far | C102: =C101 -> -205920.33 | D102: =MIN(C102,D101) -> -225119.17 | E102: =MIN(D102,E101) -> -241737.54 | F102: =MIN(E102,F101) -> -255775.43 | G102: =MIN(F102,G101) -> -267232.84 | H102: =MIN(G102,H101) -> -270471.5 | I102: =MIN(H102,I101) -> -270662.23 | J102: =MIN(I102,J101) -> -270662.23 | K102: =MIN(J102,K101) -> -270662.23 | ... BJ102: =MIN(BI102,BJ101) -> -270662.23
A103: Helper: investment paid back (1/0) | C103: =IF(AND(C101>=0,C102<0),1,0) -> 0 | D103: =IF(AND(D101>=0,D102<0),1,0) -> 0 | E103: =IF(AND(E101>=0,E102<0),1,0) -> 0 | F103: =IF(AND(F101>=0,F102<0),1,0) -> 0 | G103: =IF(AND(G101>=0,G102<0),1,0) -> 0 | H103: =IF(AND(H101>=0,H102<0),1,0) -> 0 | I103: =IF(AND(I101>=0,I102<0),1,0) -> 0 | J103: =IF(AND(J101>=0,J102<0),1,0) -> 0 | ... BJ103: =IF(AND(BJ101>=0,BJ102<0),1,0) -> 1
A104: Unlevered free cash flow (operating + after-tax interest − capex) | C104: =C89-C54*(1-Inputs!$E$83)+C90 -> -205327.83 | D104: =D89-D54*(1-Inputs!$E$83)+D90 -> -18611.278 | E104: =E89-E54*(1-Inputs!$E$83)+E90 -> -16040.678 | F104: =F89-F54*(1-Inputs!$E$83)+F90 -> -13470.078 | G104: =G89-G54*(1-Inputs!$E$83)+G90 -> -10899.477 | H104: =H89-H54*(1-Inputs!$E$83)+H90 -> -2690.5924 | I104: =I89-I54*(1-Inputs!$E$83)+I90 -> 347.457 | J104: =J89-J54*(1-Inputs!$E$83)+J90 -> 3399.9816 | ... BJ104: =BJ89-BJ54*(1-Inputs!$E$83)+BJ90 -> 19083.446
A106: Balance sheet
A107: Paid-in capital | C107: =C91 -> 330000 | D107: =C107+D91 -> 330000 | E107: =D107+E91 -> 330000 | F107: =E107+F91 -> 330000 | G107: =F107+G91 -> 330000 | H107: =G107+H91 -> 330000 | I107: =H107+I91 -> 330000 | J107: =I107+J91 -> 330000 | K107: =J107+K91 -> 330000 | ... BJ107: =BI107+BJ91 -> 330000
A108: Retained earnings | C108: =C59 -> -24169.749 | D108: =C108+D59 -> -45765.273 | E108: =D108+E59 -> -64780.322 | F108: =E108+F59 -> -81214.896 | G108: =F108+G59 -> -95068.994 | H108: =G108+H59 -> -100720.16 | I108: =H108+I59 -> -103308.94 | J108: =I108+J59 -> -102835.31 | K108: =J108+K59 -> -106367.51 | ... BJ108: =BI108+BJ59 -> 320264.67
A109: Total assets | C109: =C95+C81+C82+C72 -> 414972.09 | D109: =D95+D81+D82+D72 -> 392602.01 | E109: =E95+E81+E82+E72 -> 372812.4 | F109: =F95+F81+F82+F72 -> 355603.27 | G109: =G95+G81+G82+G72 -> 340974.61 | H109: =H95+H81+H82+H72 -> 335142.59 | I109: =I95+I81+I82+I72 -> 331830.15 | J109: =J95+J81+J82+J72 -> 331580.12 | ... BJ109: =BJ95+BJ81+BJ82+BJ72 -> 675436.08
A110: Total liabilities | C110: =C83+C78 -> 109141.84 | D110: =D83+D78 -> 108367.28 | E110: =E83+E78 -> 107592.72 | F110: =F83+F78 -> 106818.16 | G110: =G83+G78 -> 106043.6 | H110: =H83+H78 -> 105862.76 | I110: =I83+I78 -> 105139.09 | J110: =J83+J78 -> 104415.42 | ... BJ110: =BJ83+BJ78 -> 25171.411
A111: Total equity | C111: =C107+C108 -> 305830.25 | D111: =D107+D108 -> 284234.73 | E111: =E107+E108 -> 265219.68 | F111: =F107+F108 -> 248785.1 | G111: =G107+G108 -> 234931.01 | H111: =H107+H108 -> 229279.84 | I111: =I107+I108 -> 226691.06 | J111: =J107+J108 -> 227164.69 | ... BJ111: =BJ107+BJ108 -> 650264.67
A112: Total liabilities & equity | C112: =C110+C111 -> 414972.09 | D112: =D110+D111 -> 392602.01 | E112: =E110+E111 -> 372812.4 | F112: =F110+F111 -> 355603.27 | G112: =G110+G111 -> 340974.61 | H112: =H110+H111 -> 335142.59 | I112: =I110+I111 -> 331830.15 | J112: =J110+J111 -> 331580.12 | ... BJ112: =BJ110+BJ111 -> 675436.08
A113: Check: assets − liabilities − equity | C113: =C109-C112 -> 0 | D113: =D109-D112 -> 0 | E113: =E109-E112 -> 0 | F113: =F109-F112 -> 0 | G113: =G109-G112 -> 0 | H113: =H109-H112 -> 0 | I113: =I109-I112 -> 0 | J113: =J109-J112 -> 0 | ... BJ113: =BJ109-BJ112 -> 0

Sheet Headcount
A1: Headcount & payroll | D1: =HYPERLINK("#'Cover'!A1","◂ Contents") -> ◂ Contents
A2: $ unless stated; costs shown as negatives. Every period uses the same formula.
A3: Month | C3: M1 | D3: M2 | E3: M3 | F3: M4 | G3: M5 | H3: M6 | I3: M7 | J3: M8 | K3: M9 | L3: M10 | M3: M11 | N3: M12 | O3: M13 | P3: M14 | Q3: M15 | R3: M16 | S3: M17 | T3: M18 | U3: M19 | V3: M20 | W3: M21 | X3: M22 | Y3: M23 | Z3: M24 | AA3: M25 | AB3: M26 | AC3: M27 | AD3: M28 | AE3: M29 | AF3: M30 | AG3: M31 | AH3: M32 | AI3: M33 | AJ3: M34 | AK3: M35 | AL3: M36 | AM3: M37 | AN3: M38 | AO3: M39 | AP3: M40 | AQ3: M41 | AR3: M42 | AS3: M43 | AT3: M44 | AU3: M45 | AV3: M46 | AW3: M47 | AX3: M48 | AY3: M49 | AZ3: M50 | BA3: M51 | BB3: M52 | BC3: M53 | BD3: M54 | BE3: M55 | BF3: M56 | BG3: M57 | BH3: M58 | BI3: M59 | BJ3: M60
A4: Period # | C4: 1 | D4: 2 | E4: 3 | F4: 4 | G4: 5 | H4: 6 | I4: 7 | J4: 8 | K4: 9 | L4: 10 | M4: 11 | N4: 12 | O4: 13 | P4: 14 | Q4: 15 | R4: 16 | S4: 17 | T4: 18 | U4: 19 | V4: 20 | W4: 21 | X4: 22 | Y4: 23 | Z4: 24 | AA4: 25 | AB4: 26 | AC4: 27 | AD4: 28 | AE4: 29 | AF4: 30 | AG4: 31 | AH4: 32 | AI4: 33 | AJ4: 34 | AK4: 35 | AL4: 36 | AM4: 37 | AN4: 38 | AO4: 39 | AP4: 40 | AQ4: 41 | AR4: 42 | AS4: 43 | AT4: 44 | AU4: 45 | AV4: 46 | AW4: 47 | AX4: 48 | AY4: 49 | AZ4: 50 | BA4: 51 | BB4: 52 | BC4: 53 | BD4: 54 | BE4: 55 | BF4: 56 | BG4: 57 | BH4: 58 | BI4: 59 | BJ4: 60
A5: Year # | C5: =ROUNDUP(C4*1/12,0) -> 1 | D5: =ROUNDUP(D4*1/12,0) -> 1 | E5: =ROUNDUP(E4*1/12,0) -> 1 | F5: =ROUNDUP(F4*1/12,0) -> 1 | G5: =ROUNDUP(G4*1/12,0) -> 1 | H5: =ROUNDUP(H4*1/12,0) -> 1 | I5: =ROUNDUP(I4*1/12,0) -> 1 | J5: =ROUNDUP(J4*1/12,0) -> 1 | ... BJ5: =ROUNDUP(BJ4*1/12,0) -> 5
A7: Headcount (FTE)
A8: Groomers (guaranteed base pay) — FTE | C8: =Inputs!$E$55*(1+Inputs!$E$57)^(C$5-1)*MAX(0,MIN(1,C$4*1-Inputs!$E$58+1))/1 -> 4 | D8: =Inputs!$E$55*(1+Inputs!$E$57)^(D$5-1)*MAX(0,MIN(1,D$4*1-Inputs!$E$58+1))/1 -> 4 | E8: =Inputs!$E$55*(1+Inputs!$E$57)^(E$5-1)*MAX(0,MIN(1,E$4*1-Inputs!$E$58+1))/1 -> 4 | F8: =Inputs!$E$55*(1+Inputs!$E$57)^(F$5-1)*MAX(0,MIN(1,F$4*1-Inputs!$E$58+1))/1 -> 4 | G8: =Inputs!$E$55*(1+Inputs!$E$57)^(G$5-1)*MAX(0,MIN(1,G$4*1-Inputs!$E$58+1))/1 -> 4 | H8: =Inputs!$E$55*(1+Inputs!$E$57)^(H$5-1)*MAX(0,MIN(1,H$4*1-Inputs!$E$58+1))/1 -> 4 | I8: =Inputs!$E$55*(1+Inputs!$E$57)^(I$5-1)*MAX(0,MIN(1,I$4*1-Inputs!$E$58+1))/1 -> 4 | J8: =Inputs!$E$55*(1+Inputs!$E$57)^(J$5-1)*MAX(0,MIN(1,J$4*1-Inputs!$E$58+1))/1 -> 4 | ... BJ8: =Inputs!$E$55*(1+Inputs!$E$57)^(BJ$5-1)*MAX(0,MIN(1,BJ$4*1-Inputs!$E$58+1))/1 -> 4
A9: Kennel attendants & daycare — FTE | C9: =Inputs!$E$59*(1+Inputs!$E$61)^(C$5-1)*MAX(0,MIN(1,C$4*1-Inputs!$E$62+1))/1 -> 3 | D9: =Inputs!$E$59*(1+Inputs!$E$61)^(D$5-1)*MAX(0,MIN(1,D$4*1-Inputs!$E$62+1))/1 -> 3 | E9: =Inputs!$E$59*(1+Inputs!$E$61)^(E$5-1)*MAX(0,MIN(1,E$4*1-Inputs!$E$62+1))/1 -> 3 | F9: =Inputs!$E$59*(1+Inputs!$E$61)^(F$5-1)*MAX(0,MIN(1,F$4*1-Inputs!$E$62+1))/1 -> 3 | G9: =Inputs!$E$59*(1+Inputs!$E$61)^(G$5-1)*MAX(0,MIN(1,G$4*1-Inputs!$E$62+1))/1 -> 3 | H9: =Inputs!$E$59*(1+Inputs!$E$61)^(H$5-1)*MAX(0,MIN(1,H$4*1-Inputs!$E$62+1))/1 -> 3 | I9: =Inputs!$E$59*(1+Inputs!$E$61)^(I$5-1)*MAX(0,MIN(1,I$4*1-Inputs!$E$62+1))/1 -> 3 | J9: =Inputs!$E$59*(1+Inputs!$E$61)^(J$5-1)*MAX(0,MIN(1,J$4*1-Inputs!$E$62+1))/1 -> 3 | ... BJ9: =Inputs!$E$59*(1+Inputs!$E$61)^(BJ$5-1)*MAX(0,MIN(1,BJ$4*1-Inputs!$E$62+1))/1 -> 3
A10: Manager & front desk — FTE | C10: =Inputs!$E$63*(1+Inputs!$E$65)^(C$5-1)*MAX(0,MIN(1,C$4*1-Inputs!$E$66+1))/1 -> 1 | D10: =Inputs!$E$63*(1+Inputs!$E$65)^(D$5-1)*MAX(0,MIN(1,D$4*1-Inputs!$E$66+1))/1 -> 1 | E10: =Inputs!$E$63*(1+Inputs!$E$65)^(E$5-1)*MAX(0,MIN(1,E$4*1-Inputs!$E$66+1))/1 -> 1 | F10: =Inputs!$E$63*(1+Inputs!$E$65)^(F$5-1)*MAX(0,MIN(1,F$4*1-Inputs!$E$66+1))/1 -> 1 | G10: =Inputs!$E$63*(1+Inputs!$E$65)^(G$5-1)*MAX(0,MIN(1,G$4*1-Inputs!$E$66+1))/1 -> 1 | H10: =Inputs!$E$63*(1+Inputs!$E$65)^(H$5-1)*MAX(0,MIN(1,H$4*1-Inputs!$E$66+1))/1 -> 1 | I10: =Inputs!$E$63*(1+Inputs!$E$65)^(I$5-1)*MAX(0,MIN(1,I$4*1-Inputs!$E$66+1))/1 -> 1 | J10: =Inputs!$E$63*(1+Inputs!$E$65)^(J$5-1)*MAX(0,MIN(1,J$4*1-Inputs!$E$66+1))/1 -> 1 | ... BJ10: =Inputs!$E$63*(1+Inputs!$E$65)^(BJ$5-1)*MAX(0,MIN(1,BJ$4*1-Inputs!$E$66+1))/1 -> 1
A11: Total FTE | C11: =C8+C9+C10 -> 8 | D11: =D8+D9+D10 -> 8 | E11: =E8+E9+E10 -> 8 | F11: =F8+F9+F10 -> 8 | G11: =G8+G9+G10 -> 8 | H11: =H8+H9+H10 -> 8 | I11: =I8+I9+I10 -> 8 | J11: =J8+J9+J10 -> 8 | ... BJ11: =BJ8+BJ9+BJ10 -> 8
A13: Payroll cost (salary + taxes & benefits)
A14: Groomers (guaranteed base pay) — payroll cost | C14: =-C8*Inputs!$E$56/12*1*(1+Inputs!$E$67)*(1+Inputs!$E$68)^(C$5-1) -> -3833.3333 | D14: =-D8*Inputs!$E$56/12*1*(1+Inputs!$E$67)*(1+Inputs!$E$68)^(D$5-1) -> -3833.3333 | E14: =-E8*Inputs!$E$56/12*1*(1+Inputs!$E$67)*(1+Inputs!$E$68)^(E$5-1) -> -3833.3333 | F14: =-F8*Inputs!$E$56/12*1*(1+Inputs!$E$67)*(1+Inputs!$E$68)^(F$5-1) -> -3833.3333 | G14: =-G8*Inputs!$E$56/12*1*(1+Inputs!$E$67)*(1+Inputs!$E$68)^(G$5-1) -> -3833.3333 | H14: =-H8*Inputs!$E$56/12*1*(1+Inputs!$E$67)*(1+Inputs!$E$68)^(H$5-1) -> -3833.3333 | I14: =-I8*Inputs!$E$56/12*1*(1+Inputs!$E$67)*(1+Inputs!$E$68)^(I$5-1) -> -3833.3333 | J14: =-J8*Inputs!$E$56/12*1*(1+Inputs!$E$67)*(1+Inputs!$E$68)^(J$5-1) -> -3833.3333 | ... BJ14: =-BJ8*Inputs!$E$56/12*1*(1+Inputs!$E$67)*(1+Inputs!$E$68)^(BJ$5-1) -> -4314.4504
A15: Kennel attendants & daycare — payroll cost | C15: =-C9*Inputs!$E$60/12*1*(1+Inputs!$E$67)*(1+Inputs!$E$68)^(C$5-1) -> -9487.5 | D15: =-D9*Inputs!$E$60/12*1*(1+Inputs!$E$67)*(1+Inputs!$E$68)^(D$5-1) -> -9487.5 | E15: =-E9*Inputs!$E$60/12*1*(1+Inputs!$E$67)*(1+Inputs!$E$68)^(E$5-1) -> -9487.5 | F15: =-F9*Inputs!$E$60/12*1*(1+Inputs!$E$67)*(1+Inputs!$E$68)^(F$5-1) -> -9487.5 | G15: =-G9*Inputs!$E$60/12*1*(1+Inputs!$E$67)*(1+Inputs!$E$68)^(G$5-1) -> -9487.5 | H15: =-H9*Inputs!$E$60/12*1*(1+Inputs!$E$67)*(1+Inputs!$E$68)^(H$5-1) -> -9487.5 | I15: =-I9*Inputs!$E$60/12*1*(1+Inputs!$E$67)*(1+Inputs!$E$68)^(I$5-1) -> -9487.5 | J15: =-J9*Inputs!$E$60/12*1*(1+Inputs!$E$67)*(1+Inputs!$E$68)^(J$5-1) -> -9487.5 | ... BJ15: =-BJ9*Inputs!$E$60/12*1*(1+Inputs!$E$67)*(1+Inputs!$E$68)^(BJ$5-1) -> -10678.265
A16: Manager & front desk — payroll cost | C16: =-C10*Inputs!$E$64/12*1*(1+Inputs!$E$67)*(1+Inputs!$E$68)^(C$5-1) -> -5750 | D16: =-D10*Inputs!$E$64/12*1*(1+Inputs!$E$67)*(1+Inputs!$E$68)^(D$5-1) -> -5750 | E16: =-E10*Inputs!$E$64/12*1*(1+Inputs!$E$67)*(1+Inputs!$E$68)^(E$5-1) -> -5750 | F16: =-F10*Inputs!$E$64/12*1*(1+Inputs!$E$67)*(1+Inputs!$E$68)^(F$5-1) -> -5750 | G16: =-G10*Inputs!$E$64/12*1*(1+Inputs!$E$67)*(1+Inputs!$E$68)^(G$5-1) -> -5750 | H16: =-H10*Inputs!$E$64/12*1*(1+Inputs!$E$67)*(1+Inputs!$E$68)^(H$5-1) -> -5750 | I16: =-I10*Inputs!$E$64/12*1*(1+Inputs!$E$67)*(1+Inputs!$E$68)^(I$5-1) -> -5750 | J16: =-J10*Inputs!$E$64/12*1*(1+Inputs!$E$67)*(1+Inputs!$E$68)^(J$5-1) -> -5750 | ... BJ16: =-BJ10*Inputs!$E$64/12*1*(1+Inputs!$E$67)*(1+Inputs!$E$68)^(BJ$5-1) -> -6471.6757
A17: Total payroll | C17: =C14+C15+C16 -> -19070.833 | D17: =D14+D15+D16 -> -19070.833 | E17: =E14+E15+E16 -> -19070.833 | F17: =F14+F15+F16 -> -19070.833 | G17: =G14+G15+G16 -> -19070.833 | H17: =H14+H15+H16 -> -19070.833 | I17: =I14+I15+I16 -> -19070.833 | J17: =J14+J15+J16 -> -19070.833 | ... BJ17: =BJ14+BJ15+BJ16 -> -21464.391

Sheet Scenario calc
A1: Scenario calculation — Low, Base and High side by side | D1: =HYPERLINK("#'Cover'!A1","◂ Contents") -> ◂ Contents
A2: The model's period calculation, copied three times; each copy reads its own Inputs column. Feeds the Scenarios sheet only.
A4: Low scenario — reads Inputs column B
A5: Month | C5: M1 | D5: M2 | E5: M3 | F5: M4 | G5: M5 | H5: M6 | I5: M7 | J5: M8 | K5: M9 | L5: M10 | M5: M11 | N5: M12 | O5: M13 | P5: M14 | Q5: M15 | R5: M16 | S5: M17 | T5: M18 | U5: M19 | V5: M20 | W5: M21 | X5: M22 | Y5: M23 | Z5: M24 | AA5: M25 | AB5: M26 | AC5: M27 | AD5: M28 | AE5: M29 | AF5: M30 | AG5: M31 | AH5: M32 | AI5: M33 | AJ5: M34 | AK5: M35 | AL5: M36 | AM5: M37 | AN5: M38 | AO5: M39 | AP5: M40 | AQ5: M41 | AR5: M42 | AS5: M43 | AT5: M44 | AU5: M45 | AV5: M46 | AW5: M47 | AX5: M48 | AY5: M49 | AZ5: M50 | BA5: M51 | BB5: M52 | BC5: M53 | BD5: M54 | BE5: M55 | BF5: M56 | BG5: M57 | BH5: M58 | BI5: M59 | BJ5: M60
A6: Period # | C6: 1 | D6: 2 | E6: 3 | F6: 4 | G6: 5 | H6: 6 | I6: 7 | J6: 8 | K6: 9 | L6: 10 | M6: 11 | N6: 12 | O6: 13 | P6: 14 | Q6: 15 | R6: 16 | S6: 17 | T6: 18 | U6: 19 | V6: 20 | W6: 21 | X6: 22 | Y6: 23 | Z6: 24 | AA6: 25 | AB6: 26 | AC6: 27 | AD6: 28 | AE6: 29 | AF6: 30 | AG6: 31 | AH6: 32 | AI6: 33 | AJ6: 34 | AK6: 35 | AL6: 36 | AM6: 37 | AN6: 38 | AO6: 39 | AP6: 40 | AQ6: 41 | AR6: 42 | AS6: 43 | AT6: 44 | AU6: 45 | AV6: 46 | AW6: 47 | AX6: 48 | AY6: 49 | AZ6: 50 | BA6: 51 | BB6: 52 | BC6: 53 | BD6: 54 | BE6: 55 | BF6: 56 | BG6: 57 | BH6: 58 | BI6: 59 | BJ6: 60
A7: Year # | C7: =ROUNDUP(C6*1/12,0) -> 1 | D7: =ROUNDUP(D6*1/12,0) -> 1 | E7: =ROUNDUP(E6*1/12,0) -> 1 | F7: =ROUNDUP(F6*1/12,0) -> 1 | G7: =ROUNDUP(G6*1/12,0) -> 1 | H7: =ROUNDUP(H6*1/12,0) -> 1 | I7: =ROUNDUP(I6*1/12,0) -> 1 | J7: =ROUNDUP(J6*1/12,0) -> 1 | ... BJ7: =ROUNDUP(BJ6*1/12,0) -> 5
A9: Grooming demand
A10: Helper: months of the period still on the ramp-up | C10: =MAX(0,MIN(1,Inputs!$B$10-(C$6-1)*1)) -> 1 | D10: =MAX(0,MIN(1,Inputs!$B$10-(D$6-1)*1)) -> 1 | E10: =MAX(0,MIN(1,Inputs!$B$10-(E$6-1)*1)) -> 1 | F10: =MAX(0,MIN(1,Inputs!$B$10-(F$6-1)*1)) -> 1 | G10: =MAX(0,MIN(1,Inputs!$B$10-(G$6-1)*1)) -> 1 | H10: =MAX(0,MIN(1,Inputs!$B$10-(H$6-1)*1)) -> 1 | I10: =MAX(0,MIN(1,Inputs!$B$10-(I$6-1)*1)) -> 1 | J10: =MAX(0,MIN(1,Inputs!$B$10-(J$6-1)*1)) -> 1 | ... BJ10: =MAX(0,MIN(1,Inputs!$B$10-(BJ$6-1)*1)) -> 0
A11: Ramp-up factor (share of mature volume) | C11: =IF(Inputs!$B$10<=0,1,(C10*Inputs!$B$11+(1-Inputs!$B$11)/MAX(1,Inputs!$B$10)*(C10*(C$6-1)*1+C10*(C10-1)/2)+1-C10)/1) -> 0.3 | D11: =IF(Inputs!$B$10<=0,1,(D10*Inputs!$B$11+(1-Inputs!$B$11)/MAX(1,Inputs!$B$10)*(D10*(D$6-1)*1+D10*(D10-1)/2)+1-D10)/1) -> 0.35 | E11: =IF(Inputs!$B$10<=0,1,(E10*Inputs!$B$11+(1-Inputs!$B$11)/MAX(1,Inputs!$B$10)*(E10*(E$6-1)*1+E10*(E10-1)/2)+1-E10)/1) -> 0.4 | F11: =IF(Inputs!$B$10<=0,1,(F10*Inputs!$B$11+(1-Inputs!$B$11)/MAX(1,Inputs!$B$10)*(F10*(F$6-1)*1+F10*(F10-1)/2)+1-F10)/1) -> 0.45 | G11: =IF(Inputs!$B$10<=0,1,(G10*Inputs!$B$11+(1-Inputs!$B$11)/MAX(1,Inputs!$B$10)*(G10*(G$6-1)*1+G10*(G10-1)/2)+1-G10)/1) -> 0.5 | H11: =IF(Inputs!$B$10<=0,1,(H10*Inputs!$B$11+(1-Inputs!$B$11)/MAX(1,Inputs!$B$10)*(H10*(H$6-1)*1+H10*(H10-1)/2)+1-H10)/1) -> 0.55 | I11: =IF(Inputs!$B$10<=0,1,(I10*Inputs!$B$11+(1-Inputs!$B$11)/MAX(1,Inputs!$B$10)*(I10*(I$6-1)*1+I10*(I10-1)/2)+1-I10)/1) -> 0.6 | J11: =IF(Inputs!$B$10<=0,1,(J10*Inputs!$B$11+(1-Inputs!$B$11)/MAX(1,Inputs!$B$10)*(J10*(J$6-1)*1+J10*(J10-1)/2)+1-J10)/1) -> 0.65 | ... BJ11: =IF(Inputs!$B$10<=0,1,(BJ10*Inputs!$B$11+(1-Inputs!$B$11)/MAX(1,Inputs!$B$10)*(BJ10*(BJ$6-1)*1+BJ10*(BJ10-1)/2)+1-BJ10)/1) -> 1
A12: Grooms demanded | C12: =Inputs!$B$7*(1+Inputs!$B$8)^(C$7-1)*Inputs!$B$9*1*C11 -> 101.4 | D12: =Inputs!$B$7*(1+Inputs!$B$8)^(D$7-1)*Inputs!$B$9*1*D11 -> 118.3 | E12: =Inputs!$B$7*(1+Inputs!$B$8)^(E$7-1)*Inputs!$B$9*1*E11 -> 135.2 | F12: =Inputs!$B$7*(1+Inputs!$B$8)^(F$7-1)*Inputs!$B$9*1*F11 -> 152.1 | G12: =Inputs!$B$7*(1+Inputs!$B$8)^(G$7-1)*Inputs!$B$9*1*G11 -> 169 | H12: =Inputs!$B$7*(1+Inputs!$B$8)^(H$7-1)*Inputs!$B$9*1*H11 -> 185.9 | I12: =Inputs!$B$7*(1+Inputs!$B$8)^(I$7-1)*Inputs!$B$9*1*I11 -> 202.8 | J12: =Inputs!$B$7*(1+Inputs!$B$8)^(J$7-1)*Inputs!$B$9*1*J11 -> 219.7 | ... BJ12: =Inputs!$B$7*(1+Inputs!$B$8)^(BJ$7-1)*Inputs!$B$9*1*BJ11 -> 338
A14: Grooming capacity
A15: Groomers (FTE) | C15: =C118 -> 4 | D15: =D118 -> 4 | E15: =E118 -> 4 | F15: =F118 -> 4 | G15: =G118 -> 4 | H15: =H118 -> 4 | I15: =I118 -> 4 | J15: =J118 -> 4 | ... BJ15: =BJ118 -> 4
A16: Station capacity (stations × grooms per station-day × operating days) | C16: =Inputs!$B$14*Inputs!$B$15*Inputs!$B$9*1 -> 624 | D16: =Inputs!$B$14*Inputs!$B$15*Inputs!$B$9*1 -> 624 | E16: =Inputs!$B$14*Inputs!$B$15*Inputs!$B$9*1 -> 624 | F16: =Inputs!$B$14*Inputs!$B$15*Inputs!$B$9*1 -> 624 | G16: =Inputs!$B$14*Inputs!$B$15*Inputs!$B$9*1 -> 624 | H16: =Inputs!$B$14*Inputs!$B$15*Inputs!$B$9*1 -> 624 | I16: =Inputs!$B$14*Inputs!$B$15*Inputs!$B$9*1 -> 624 | J16: =Inputs!$B$14*Inputs!$B$15*Inputs!$B$9*1 -> 624 | ... BJ16: =Inputs!$B$14*Inputs!$B$15*Inputs!$B$9*1 -> 624
A17: Groomer capacity (FTE × grooms per groomer-day × operating days) | C17: =C15*Inputs!$B$16*Inputs!$B$9*1 -> 520 | D17: =D15*Inputs!$B$16*Inputs!$B$9*1 -> 520 | E17: =E15*Inputs!$B$16*Inputs!$B$9*1 -> 520 | F17: =F15*Inputs!$B$16*Inputs!$B$9*1 -> 520 | G17: =G15*Inputs!$B$16*Inputs!$B$9*1 -> 520 | H17: =H15*Inputs!$B$16*Inputs!$B$9*1 -> 520 | I17: =I15*Inputs!$B$16*Inputs!$B$9*1 -> 520 | J17: =J15*Inputs!$B$16*Inputs!$B$9*1 -> 520 | ... BJ17: =BJ15*Inputs!$B$16*Inputs!$B$9*1 -> 520
A18: Grooming capacity (lower of stations and groomers) | C18: =MIN(C16,C17) -> 520 | D18: =MIN(D16,D17) -> 520 | E18: =MIN(E16,E17) -> 520 | F18: =MIN(F16,F17) -> 520 | G18: =MIN(G16,G17) -> 520 | H18: =MIN(H16,H17) -> 520 | I18: =MIN(I16,I17) -> 520 | J18: =MIN(J16,J17) -> 520 | ... BJ18: =MIN(BJ16,BJ17) -> 520
A19: Grooms completed (demand capped by capacity) | C19: =MIN(C12,C18) -> 101.4 | D19: =MIN(D12,D18) -> 118.3 | E19: =MIN(E12,E18) -> 135.2 | F19: =MIN(F12,F18) -> 152.1 | G19: =MIN(G12,G18) -> 169 | H19: =MIN(H12,H18) -> 185.9 | I19: =MIN(I12,I18) -> 202.8 | J19: =MIN(J12,J18) -> 219.7 | ... BJ19: =MIN(BJ12,BJ18) -> 338
A20: Grooms lost to the capacity limit | C20: =C12-C19 -> 0 | D20: =D12-D19 -> 0 | E20: =E12-E19 -> 0 | F20: =F12-F19 -> 0 | G20: =G12-G19 -> 0 | H20: =H12-H19 -> 0 | I20: =I12-I19 -> 0 | J20: =J12-J19 -> 0 | ... BJ20: =BJ12-BJ19 -> 0
A22: Boarding
A23: Boarding season factor (June-August, December) | C23: =IF(OR(AND(MOD(C$6-1,12)>=5,MOD(C$6-1,12)<=7),MOD(C$6-1,12)=11),1+Inputs!$B$28,1-Inputs!$B$28/2) -> 0.925 | D23: =IF(OR(AND(MOD(D$6-1,12)>=5,MOD(D$6-1,12)<=7),MOD(D$6-1,12)=11),1+Inputs!$B$28,1-Inputs!$B$28/2) -> 0.925 | E23: =IF(OR(AND(MOD(E$6-1,12)>=5,MOD(E$6-1,12)<=7),MOD(E$6-1,12)=11),1+Inputs!$B$28,1-Inputs!$B$28/2) -> 0.925 | F23: =IF(OR(AND(MOD(F$6-1,12)>=5,MOD(F$6-1,12)<=7),MOD(F$6-1,12)=11),1+Inputs!$B$28,1-Inputs!$B$28/2) -> 0.925 | G23: =IF(OR(AND(MOD(G$6-1,12)>=5,MOD(G$6-1,12)<=7),MOD(G$6-1,12)=11),1+Inputs!$B$28,1-Inputs!$B$28/2) -> 0.925 | H23: =IF(OR(AND(MOD(H$6-1,12)>=5,MOD(H$6-1,12)<=7),MOD(H$6-1,12)=11),1+Inputs!$B$28,1-Inputs!$B$28/2) -> 1.15 | I23: =IF(OR(AND(MOD(I$6-1,12)>=5,MOD(I$6-1,12)<=7),MOD(I$6-1,12)=11),1+Inputs!$B$28,1-Inputs!$B$28/2) -> 1.15 | J23: =IF(OR(AND(MOD(J$6-1,12)>=5,MOD(J$6-1,12)<=7),MOD(J$6-1,12)=11),1+Inputs!$B$28,1-Inputs!$B$28/2) -> 1.15 | ... BJ23: =IF(OR(AND(MOD(BJ$6-1,12)>=5,MOD(BJ$6-1,12)<=7),MOD(BJ$6-1,12)=11),1+Inputs!$B$28,1-Inputs!$B$28/2) -> 1.15
A24: Available run-nights (runs × calendar nights) | C24: =Inputs!$B$25*Inputs!$B$29*1 -> 912 | D24: =Inputs!$B$25*Inputs!$B$29*1 -> 912 | E24: =Inputs!$B$25*Inputs!$B$29*1 -> 912 | F24: =Inputs!$B$25*Inputs!$B$29*1 -> 912 | G24: =Inputs!$B$25*Inputs!$B$29*1 -> 912 | H24: =Inputs!$B$25*Inputs!$B$29*1 -> 912 | I24: =Inputs!$B$25*Inputs!$B$29*1 -> 912 | J24: =Inputs!$B$25*Inputs!$B$29*1 -> 912 | ... BJ24: =Inputs!$B$25*Inputs!$B$29*1 -> 912
A25: Occupancy (maturity × growth × ramp × season, capped at 100%) | C25: =MIN(1,Inputs!$B$26*(1+Inputs!$B$27)^(C$7-1)*C11*C23) -> 0.13875 | D25: =MIN(1,Inputs!$B$26*(1+Inputs!$B$27)^(D$7-1)*D11*D23) -> 0.161875 | E25: =MIN(1,Inputs!$B$26*(1+Inputs!$B$27)^(E$7-1)*E11*E23) -> 0.185 | F25: =MIN(1,Inputs!$B$26*(1+Inputs!$B$27)^(F$7-1)*F11*F23) -> 0.208125 | G25: =MIN(1,Inputs!$B$26*(1+Inputs!$B$27)^(G$7-1)*G11*G23) -> 0.23125 | H25: =MIN(1,Inputs!$B$26*(1+Inputs!$B$27)^(H$7-1)*H11*H23) -> 0.31625 | I25: =MIN(1,Inputs!$B$26*(1+Inputs!$B$27)^(I$7-1)*I11*I23) -> 0.345 | J25: =MIN(1,Inputs!$B$26*(1+Inputs!$B$27)^(J$7-1)*J11*J23) -> 0.37375 | ... BJ25: =MIN(1,Inputs!$B$26*(1+Inputs!$B$27)^(BJ$7-1)*BJ11*BJ23) -> 0.575
A26: Boarded run-nights | C26: =C24*C25 -> 126.54 | D26: =D24*D25 -> 147.63 | E26: =E24*E25 -> 168.72 | F26: =F24*F25 -> 189.81 | G26: =G24*G25 -> 210.9 | H26: =H24*H25 -> 288.42 | I26: =I24*I25 -> 314.64 | J26: =J24*J25 -> 340.86 | ... BJ26: =BJ24*BJ25 -> 524.4
A28: Revenue
A29: Average price per groom | C29: =Inputs!$B$19*(1+Inputs!$B$20)^(C$7-1) -> 68 | D29: =Inputs!$B$19*(1+Inputs!$B$20)^(D$7-1) -> 68 | E29: =Inputs!$B$19*(1+Inputs!$B$20)^(E$7-1) -> 68 | F29: =Inputs!$B$19*(1+Inputs!$B$20)^(F$7-1) -> 68 | G29: =Inputs!$B$19*(1+Inputs!$B$20)^(G$7-1) -> 68 | H29: =Inputs!$B$19*(1+Inputs!$B$20)^(H$7-1) -> 68 | I29: =Inputs!$B$19*(1+Inputs!$B$20)^(I$7-1) -> 68 | J29: =Inputs!$B$19*(1+Inputs!$B$20)^(J$7-1) -> 68 | ... BJ29: =Inputs!$B$19*(1+Inputs!$B$20)^(BJ$7-1) -> 70.761073
A30: Grooming revenue | C30: =C19*C29 -> 6895.2 | D30: =D19*D29 -> 8044.4 | E30: =E19*E29 -> 9193.6 | F30: =F19*F29 -> 10342.8 | G30: =G19*G29 -> 11492 | H30: =H19*H29 -> 12641.2 | I30: =I19*I29 -> 13790.4 | J30: =J19*J29 -> 14939.6 | ... BJ30: =BJ19*BJ29 -> 23917.243
A31: Boarding revenue | C31: =C26*Inputs!$B$30*(1+Inputs!$B$20)^(C$7-1) -> 6327 | D31: =D26*Inputs!$B$30*(1+Inputs!$B$20)^(D$7-1) -> 7381.5 | E31: =E26*Inputs!$B$30*(1+Inputs!$B$20)^(E$7-1) -> 8436 | F31: =F26*Inputs!$B$30*(1+Inputs!$B$20)^(F$7-1) -> 9490.5 | G31: =G26*Inputs!$B$30*(1+Inputs!$B$20)^(G$7-1) -> 10545 | H31: =H26*Inputs!$B$30*(1+Inputs!$B$20)^(H$7-1) -> 14421 | I31: =I26*Inputs!$B$30*(1+Inputs!$B$20)^(I$7-1) -> 15732 | J31: =J26*Inputs!$B$30*(1+Inputs!$B$20)^(J$7-1) -> 17043 | ... BJ31: =BJ26*Inputs!$B$30*(1+Inputs!$B$20)^(BJ$7-1) -> 27284.637
A32: Retail revenue | C32: =C19*Inputs!$B$21*(1+Inputs!$B$20)^(C$7-1) -> 608.4 | D32: =D19*Inputs!$B$21*(1+Inputs!$B$20)^(D$7-1) -> 709.8 | E32: =E19*Inputs!$B$21*(1+Inputs!$B$20)^(E$7-1) -> 811.2 | F32: =F19*Inputs!$B$21*(1+Inputs!$B$20)^(F$7-1) -> 912.6 | G32: =G19*Inputs!$B$21*(1+Inputs!$B$20)^(G$7-1) -> 1014 | H32: =H19*Inputs!$B$21*(1+Inputs!$B$20)^(H$7-1) -> 1115.4 | I32: =I19*Inputs!$B$21*(1+Inputs!$B$20)^(I$7-1) -> 1216.8 | J32: =J19*Inputs!$B$21*(1+Inputs!$B$20)^(J$7-1) -> 1318.2 | ... BJ32: =BJ19*Inputs!$B$21*(1+Inputs!$B$20)^(BJ$7-1) -> 2110.3449
A33: Revenue | C33: =C30+C31+C32 -> 13830.6 | D33: =D30+D31+D32 -> 16135.7 | E33: =E30+E31+E32 -> 18440.8 | F33: =F30+F31+F32 -> 20745.9 | G33: =G30+G31+G32 -> 23051 | H33: =H30+H31+H32 -> 28177.6 | I33: =I30+I31+I32 -> 30739.2 | J33: =J30+J31+J32 -> 33300.8 | ... BJ33: =BJ30+BJ31+BJ32 -> 53312.225
A35: Cost of sales
A36: Groomer base pay | C36: =C124 -> -3833.3333 | D36: =D124 -> -3833.3333 | E36: =E124 -> -3833.3333 | F36: =F124 -> -3833.3333 | G36: =G124 -> -3833.3333 | H36: =H124 -> -3833.3333 | I36: =I124 -> -3833.3333 | J36: =J124 -> -3833.3333 | ... BJ36: =BJ124 -> -4484.4578
A37: Groomer commission | C37: =-C30*Inputs!$B$33 -> -2551.224 | D37: =-D30*Inputs!$B$33 -> -2976.428 | E37: =-E30*Inputs!$B$33 -> -3401.632 | F37: =-F30*Inputs!$B$33 -> -3826.836 | G37: =-G30*Inputs!$B$33 -> -4252.04 | H37: =-H30*Inputs!$B$33 -> -4677.244 | I37: =-I30*Inputs!$B$33 -> -5102.448 | J37: =-J30*Inputs!$B$33 -> -5527.652 | ... BJ37: =-BJ30*Inputs!$B$33 -> -8849.3797
A38: Grooming supplies | C38: =-C19*Inputs!$B$34*(1+Inputs!$B$45)^(C$7-1) -> -507 | D38: =-D19*Inputs!$B$34*(1+Inputs!$B$45)^(D$7-1) -> -591.5 | E38: =-E19*Inputs!$B$34*(1+Inputs!$B$45)^(E$7-1) -> -676 | F38: =-F19*Inputs!$B$34*(1+Inputs!$B$45)^(F$7-1) -> -760.5 | G38: =-G19*Inputs!$B$34*(1+Inputs!$B$45)^(G$7-1) -> -845 | H38: =-H19*Inputs!$B$34*(1+Inputs!$B$45)^(H$7-1) -> -929.5 | I38: =-I19*Inputs!$B$34*(1+Inputs!$B$45)^(I$7-1) -> -1014 | J38: =-J19*Inputs!$B$34*(1+Inputs!$B$45)^(J$7-1) -> -1098.5 | ... BJ38: =-BJ19*Inputs!$B$34*(1+Inputs!$B$45)^(BJ$7-1) -> -1977.061
A39: Boarding food, cleaning & laundry | C39: =-C26*Inputs!$B$35*(1+Inputs!$B$45)^(C$7-1) -> -885.78 | D39: =-D26*Inputs!$B$35*(1+Inputs!$B$45)^(D$7-1) -> -1033.41 | E39: =-E26*Inputs!$B$35*(1+Inputs!$B$45)^(E$7-1) -> -1181.04 | F39: =-F26*Inputs!$B$35*(1+Inputs!$B$45)^(F$7-1) -> -1328.67 | G39: =-G26*Inputs!$B$35*(1+Inputs!$B$45)^(G$7-1) -> -1476.3 | H39: =-H26*Inputs!$B$35*(1+Inputs!$B$45)^(H$7-1) -> -2018.94 | I39: =-I26*Inputs!$B$35*(1+Inputs!$B$45)^(I$7-1) -> -2202.48 | J39: =-J26*Inputs!$B$35*(1+Inputs!$B$45)^(J$7-1) -> -2386.02 | ... BJ39: =-BJ26*Inputs!$B$35*(1+Inputs!$B$45)^(BJ$7-1) -> -4294.3168
A40: Retail cost of goods | C40: =-C32*(1-Inputs!$B$22) -> -389.376 | D40: =-D32*(1-Inputs!$B$22) -> -454.272 | E40: =-E32*(1-Inputs!$B$22) -> -519.168 | F40: =-F32*(1-Inputs!$B$22) -> -584.064 | G40: =-G32*(1-Inputs!$B$22) -> -648.96 | H40: =-H32*(1-Inputs!$B$22) -> -713.856 | I40: =-I32*(1-Inputs!$B$22) -> -778.752 | J40: =-J32*(1-Inputs!$B$22) -> -843.648 | ... BJ40: =-BJ32*(1-Inputs!$B$22) -> -1350.6208
A41: Cost of sales | C41: =C36+C37+C38+C39+C40 -> -8166.7133 | D41: =D36+D37+D38+D39+D40 -> -8888.9433 | E41: =E36+E37+E38+E39+E40 -> -9611.1733 | F41: =F36+F37+F38+F39+F40 -> -10333.403 | G41: =G36+G37+G38+G39+G40 -> -11055.633 | H41: =H36+H37+H38+H39+H40 -> -12172.873 | I41: =I36+I37+I38+I39+I40 -> -12931.013 | J41: =J36+J37+J38+J39+J40 -> -13689.153 | ... BJ41: =BJ36+BJ37+BJ38+BJ39+BJ40 -> -20955.836
A42: Gross profit | C42: =C33+C41 -> 5663.8867 | D42: =D33+D41 -> 7246.7567 | E42: =E33+E41 -> 8829.6267 | F42: =F33+F41 -> 10412.497 | G42: =G33+G41 -> 11995.367 | H42: =H33+H41 -> 16004.727 | I42: =I33+I41 -> 17808.187 | J42: =J33+J41 -> 19611.647 | ... BJ42: =BJ33+BJ41 -> 32356.389
A44: Operating expenses
A45: Attendants, manager & other payroll | C45: =C127-C124 -> -15237.5 | D45: =D127-D124 -> -15237.5 | E45: =E127-E124 -> -15237.5 | F45: =F127-F124 -> -15237.5 | G45: =G127-G124 -> -15237.5 | H45: =H127-H124 -> -15237.5 | I45: =I127-I124 -> -15237.5 | J45: =J127-J124 -> -15237.5 | ... BJ45: =BJ127-BJ124 -> -17825.72
A46: Shop rent or land cost | C46: =-Inputs!$B$38*(1+Inputs!$B$39)^(C$7-1)*1 -> -9000 | D46: =-Inputs!$B$38*(1+Inputs!$B$39)^(D$7-1)*1 -> -9000 | E46: =-Inputs!$B$38*(1+Inputs!$B$39)^(E$7-1)*1 -> -9000 | F46: =-Inputs!$B$38*(1+Inputs!$B$39)^(F$7-1)*1 -> -9000 | G46: =-Inputs!$B$38*(1+Inputs!$B$39)^(G$7-1)*1 -> -9000 | H46: =-Inputs!$B$38*(1+Inputs!$B$39)^(H$7-1)*1 -> -9000 | I46: =-Inputs!$B$38*(1+Inputs!$B$39)^(I$7-1)*1 -> -9000 | J46: =-Inputs!$B$38*(1+Inputs!$B$39)^(J$7-1)*1 -> -9000 | ... BJ46: =-Inputs!$B$38*(1+Inputs!$B$39)^(BJ$7-1)*1 -> -10129.579
A47: Insurance | C47: =-Inputs!$B$40*(1+Inputs!$B$45)^(C$7-1)*1 -> -2500 | D47: =-Inputs!$B$40*(1+Inputs!$B$45)^(D$7-1)*1 -> -2500 | E47: =-Inputs!$B$40*(1+Inputs!$B$45)^(E$7-1)*1 -> -2500 | F47: =-Inputs!$B$40*(1+Inputs!$B$45)^(F$7-1)*1 -> -2500 | G47: =-Inputs!$B$40*(1+Inputs!$B$45)^(G$7-1)*1 -> -2500 | H47: =-Inputs!$B$40*(1+Inputs!$B$45)^(H$7-1)*1 -> -2500 | I47: =-Inputs!$B$40*(1+Inputs!$B$45)^(I$7-1)*1 -> -2500 | J47: =-Inputs!$B$40*(1+Inputs!$B$45)^(J$7-1)*1 -> -2500 | ... BJ47: =-Inputs!$B$40*(1+Inputs!$B$45)^(BJ$7-1)*1 -> -2924.6464
A48: Utilities, software & other G&A | C48: =-Inputs!$B$41*(1+Inputs!$B$45)^(C$7-1)*1 -> -4500 | D48: =-Inputs!$B$41*(1+Inputs!$B$45)^(D$7-1)*1 -> -4500 | E48: =-Inputs!$B$41*(1+Inputs!$B$45)^(E$7-1)*1 -> -4500 | F48: =-Inputs!$B$41*(1+Inputs!$B$45)^(F$7-1)*1 -> -4500 | G48: =-Inputs!$B$41*(1+Inputs!$B$45)^(G$7-1)*1 -> -4500 | H48: =-Inputs!$B$41*(1+Inputs!$B$45)^(H$7-1)*1 -> -4500 | I48: =-Inputs!$B$41*(1+Inputs!$B$45)^(I$7-1)*1 -> -4500 | J48: =-Inputs!$B$41*(1+Inputs!$B$45)^(J$7-1)*1 -> -4500 | ... BJ48: =-Inputs!$B$41*(1+Inputs!$B$45)^(BJ$7-1)*1 -> -5264.3635
A49: Marketing | C49: =-Inputs!$B$42*(1+Inputs!$B$43)^(C$7-1)*1 -> -3500 | D49: =-Inputs!$B$42*(1+Inputs!$B$43)^(D$7-1)*1 -> -3500 | E49: =-Inputs!$B$42*(1+Inputs!$B$43)^(E$7-1)*1 -> -3500 | F49: =-Inputs!$B$42*(1+Inputs!$B$43)^(F$7-1)*1 -> -3500 | G49: =-Inputs!$B$42*(1+Inputs!$B$43)^(G$7-1)*1 -> -3500 | H49: =-Inputs!$B$42*(1+Inputs!$B$43)^(H$7-1)*1 -> -3500 | I49: =-Inputs!$B$42*(1+Inputs!$B$43)^(I$7-1)*1 -> -3500 | J49: =-Inputs!$B$42*(1+Inputs!$B$43)^(J$7-1)*1 -> -3500 | ... BJ49: =-Inputs!$B$42*(1+Inputs!$B$43)^(BJ$7-1)*1 -> -840.35
A50: Card processing fees | C50: =-C33*Inputs!$B$44 -> -442.5792 | D50: =-D33*Inputs!$B$44 -> -516.3424 | E50: =-E33*Inputs!$B$44 -> -590.1056 | F50: =-F33*Inputs!$B$44 -> -663.8688 | G50: =-G33*Inputs!$B$44 -> -737.632 | H50: =-H33*Inputs!$B$44 -> -901.6832 | I50: =-I33*Inputs!$B$44 -> -983.6544 | J50: =-J33*Inputs!$B$44 -> -1065.6256 | ... BJ50: =-BJ33*Inputs!$B$44 -> -1705.9912
A51: Total operating expenses | C51: =C45+C46+C47+C48+C49+C50 -> -35180.079 | D51: =D45+D46+D47+D48+D49+D50 -> -35253.842 | E51: =E45+E46+E47+E48+E49+E50 -> -35327.606 | F51: =F45+F46+F47+F48+F49+F50 -> -35401.369 | G51: =G45+G46+G47+G48+G49+G50 -> -35475.132 | H51: =H45+H46+H47+H48+H49+H50 -> -35639.183 | I51: =I45+I46+I47+I48+I49+I50 -> -35721.154 | J51: =J45+J46+J47+J48+J49+J50 -> -35803.126 | ... BJ51: =BJ45+BJ46+BJ47+BJ48+BJ49+BJ50 -> -38690.65
A52: EBITDA | C52: =C42+C51 -> -29516.193 | D52: =D42+D51 -> -28007.086 | E52: =E42+E51 -> -26497.979 | F52: =F42+F51 -> -24988.872 | G52: =G42+G51 -> -23479.765 | H52: =H42+H51 -> -19634.457 | I52: =I42+I51 -> -17912.968 | J52: =J42+J51 -> -16191.479 | ... BJ52: =BJ42+BJ51 -> -6334.2617
A54: Profit after depreciation, interest, tax
A55: EBIT | C55: =C52+C72 -> -31484.943 | D55: =D52+D72 -> -29975.836 | E55: =E52+E72 -> -28466.729 | F55: =F52+F72 -> -26957.622 | G55: =G52+G72 -> -25448.515 | H55: =H52+H72 -> -21603.207 | I55: =I52+I72 -> -19881.718 | J55: =J52+J72 -> -18160.229 | ... BJ55: =BJ52+BJ72 -> -8719.6783
A56: Interest on loan (average balance after drawdown) | C56: =-(C77+C78+C80)/2*Inputs!$B$73/12 -> -750 | D56: =-(D77+D78+D80)/2*Inputs!$B$73/12 -> -743.75 | E56: =-(E77+E78+E80)/2*Inputs!$B$73/12 -> -731.25 | F56: =-(F77+F78+F80)/2*Inputs!$B$73/12 -> -718.75 | G56: =-(G77+G78+G80)/2*Inputs!$B$73/12 -> -706.25 | H56: =-(H77+H78+H80)/2*Inputs!$B$73/12 -> -693.75 | I56: =-(I77+I78+I80)/2*Inputs!$B$73/12 -> -681.25 | J56: =-(J77+J78+J80)/2*Inputs!$B$73/12 -> -668.75 | ... BJ56: =-(BJ77+BJ78+BJ80)/2*Inputs!$B$73/12 -> -18.75
A57: Pre-tax income | C57: =C55+C56 -> -32234.943 | D57: =D55+D56 -> -30719.586 | E57: =E55+E56 -> -29197.979 | F57: =F55+F56 -> -27676.372 | G57: =G55+G56 -> -26154.765 | H57: =H55+H56 -> -22296.957 | I57: =I55+I56 -> -20562.968 | J57: =J55+J56 -> -18828.979 | ... BJ57: =BJ55+BJ56 -> -8738.4283
A58: Helper: cumulative pre-tax income | C58: =C57 -> -32234.943 | D58: =C58+D57 -> -62954.528 | E58: =D58+E57 -> -92152.507 | F58: =E58+F57 -> -119828.88 | G58: =F58+G57 -> -145983.64 | H58: =G58+H57 -> -168280.6 | I58: =H58+I57 -> -188843.57 | J58: =I58+J57 -> -207672.55 | K58: =J58+K57 -> -227740.89 | ... BJ58: =BI58+BJ57 -> -786729.95
A59: Helper: cumulative taxable income (losses carried forward) | C59: =MAX(0,C58) -> 0 | D59: =MAX(C59,D58) -> 0 | E59: =MAX(D59,E58) -> 0 | F59: =MAX(E59,F58) -> 0 | G59: =MAX(F59,G58) -> 0 | H59: =MAX(G59,H58) -> 0 | I59: =MAX(H59,I58) -> 0 | J59: =MAX(I59,J58) -> 0 | K59: =MAX(J59,K58) -> 0 | ... BJ59: =MAX(BI59,BJ58) -> 0
A60: Income tax | C60: =-C59*Inputs!$B$83 -> 0 | D60: =-(D59-C59)*Inputs!$B$83 -> 0 | E60: =-(E59-D59)*Inputs!$B$83 -> 0 | F60: =-(F59-E59)*Inputs!$B$83 -> 0 | G60: =-(G59-F59)*Inputs!$B$83 -> 0 | H60: =-(H59-G59)*Inputs!$B$83 -> 0 | I60: =-(I59-H59)*Inputs!$B$83 -> 0 | J60: =-(J59-I59)*Inputs!$B$83 -> 0 | K60: =-(K59-J59)*Inputs!$B$83 -> 0 | ... BJ60: =-(BJ59-BI59)*Inputs!$B$83 -> 0
A61: Net income | C61: =C57+C60 -> -32234.943 | D61: =D57+D60 -> -30719.586 | E61: =E57+E60 -> -29197.979 | F61: =F57+F60 -> -27676.372 | G61: =G57+G60 -> -26154.765 | H61: =H57+H60 -> -22296.957 | I61: =I57+I60 -> -20562.968 | J61: =J57+J60 -> -18828.979 | ... BJ61: =BJ57+BJ60 -> -8738.4283
A63: Fixed assets & capital spending
A64: Grooming tables, tubs & dryers | C64: =IF(C$6=1,Inputs!$B$14*Inputs!$B$48,0) -> 24000 | D64: =IF(D$6=1,Inputs!$B$14*Inputs!$B$48,0) -> 0 | E64: =IF(E$6=1,Inputs!$B$14*Inputs!$B$48,0) -> 0 | F64: =IF(F$6=1,Inputs!$B$14*Inputs!$B$48,0) -> 0 | G64: =IF(G$6=1,Inputs!$B$14*Inputs!$B$48,0) -> 0 | H64: =IF(H$6=1,Inputs!$B$14*Inputs!$B$48,0) -> 0 | I64: =IF(I$6=1,Inputs!$B$14*Inputs!$B$48,0) -> 0 | J64: =IF(J$6=1,Inputs!$B$14*Inputs!$B$48,0) -> 0 | ... BJ64: =IF(BJ$6=1,Inputs!$B$14*Inputs!$B$48,0) -> 0
A65: Kennel run build-out | C65: =IF(C$6=1,Inputs!$B$25*Inputs!$B$49,0) -> 75000 | D65: =IF(D$6=1,Inputs!$B$25*Inputs!$B$49,0) -> 0 | E65: =IF(E$6=1,Inputs!$B$25*Inputs!$B$49,0) -> 0 | F65: =IF(F$6=1,Inputs!$B$25*Inputs!$B$49,0) -> 0 | G65: =IF(G$6=1,Inputs!$B$25*Inputs!$B$49,0) -> 0 | H65: =IF(H$6=1,Inputs!$B$25*Inputs!$B$49,0) -> 0 | I65: =IF(I$6=1,Inputs!$B$25*Inputs!$B$49,0) -> 0 | J65: =IF(J$6=1,Inputs!$B$25*Inputs!$B$49,0) -> 0 | ... BJ65: =IF(BJ$6=1,Inputs!$B$25*Inputs!$B$49,0) -> 0
A66: Leasehold improvements & signage | C66: =IF(C$6=1,Inputs!$B$50,0) -> 90000 | D66: =IF(D$6=1,Inputs!$B$50,0) -> 0 | E66: =IF(E$6=1,Inputs!$B$50,0) -> 0 | F66: =IF(F$6=1,Inputs!$B$50,0) -> 0 | G66: =IF(G$6=1,Inputs!$B$50,0) -> 0 | H66: =IF(H$6=1,Inputs!$B$50,0) -> 0 | I66: =IF(I$6=1,Inputs!$B$50,0) -> 0 | J66: =IF(J$6=1,Inputs!$B$50,0) -> 0 | ... BJ66: =IF(BJ$6=1,Inputs!$B$50,0) -> 0
A67: Land or building (not depreciated) | C67: =IF(C$6=1,Inputs!$B$51,0) -> 0 | D67: =IF(D$6=1,Inputs!$B$51,0) -> 0 | E67: =IF(E$6=1,Inputs!$B$51,0) -> 0 | F67: =IF(F$6=1,Inputs!$B$51,0) -> 0 | G67: =IF(G$6=1,Inputs!$B$51,0) -> 0 | H67: =IF(H$6=1,Inputs!$B$51,0) -> 0 | I67: =IF(I$6=1,Inputs!$B$51,0) -> 0 | J67: =IF(J$6=1,Inputs!$B$51,0) -> 0 | ... BJ67: =IF(BJ$6=1,Inputs!$B$51,0) -> 0
A68: Equipment & kennel refresh (first period of each year from year 2) | C68: =IF(AND(C$7>1,MOD(C$6-1,12)=0),Inputs!$B$52,0) -> 0 | D68: =IF(AND(D$7>1,MOD(D$6-1,12)=0),Inputs!$B$52,0) -> 0 | E68: =IF(AND(E$7>1,MOD(E$6-1,12)=0),Inputs!$B$52,0) -> 0 | F68: =IF(AND(F$7>1,MOD(F$6-1,12)=0),Inputs!$B$52,0) -> 0 | G68: =IF(AND(G$7>1,MOD(G$6-1,12)=0),Inputs!$B$52,0) -> 0 | H68: =IF(AND(H$7>1,MOD(H$6-1,12)=0),Inputs!$B$52,0) -> 0 | I68: =IF(AND(I$7>1,MOD(I$6-1,12)=0),Inputs!$B$52,0) -> 0 | J68: =IF(AND(J$7>1,MOD(J$6-1,12)=0),Inputs!$B$52,0) -> 0 | ... BJ68: =IF(AND(BJ$7>1,MOD(BJ$6-1,12)=0),Inputs!$B$52,0) -> 0
A69: Capital spending | C69: =C64+C65+C66+C67+C68 -> 189000 | D69: =D64+D65+D66+D67+D68 -> 0 | E69: =E64+E65+E66+E67+E68 -> 0 | F69: =F64+F65+F66+F67+F68 -> 0 | G69: =G64+G65+G66+G67+G68 -> 0 | H69: =H64+H65+H66+H67+H68 -> 0 | I69: =I64+I65+I66+I67+I68 -> 0 | J69: =J64+J65+J66+J67+J68 -> 0 | ... BJ69: =BJ64+BJ65+BJ66+BJ67+BJ68 -> 0
A70: Fixed assets at cost | C70: =C69 -> 189000 | D70: =C70+D69 -> 189000 | E70: =D70+E69 -> 189000 | F70: =E70+F69 -> 189000 | G70: =F70+G69 -> 189000 | H70: =G70+H69 -> 189000 | I70: =H70+I69 -> 189000 | J70: =I70+J69 -> 189000 | K70: =J70+K69 -> 189000 | ... BJ70: =BI70+BJ69 -> 229000
A71: Land at cost (not depreciated) | C71: =C67 -> 0 | D71: =C71+D67 -> 0 | E71: =D71+E67 -> 0 | F71: =E71+F67 -> 0 | G71: =F71+G67 -> 0 | H71: =G71+H67 -> 0 | I71: =H71+I67 -> 0 | J71: =I71+J67 -> 0 | K71: =J71+K67 -> 0 | ... BJ71: =BI71+BJ67 -> 0
A72: Depreciation | C72: =-MIN((C70-C71)/MAX(1,Inputs!$B$82*12),C69-C71) -> -1968.75 | D72: =-MIN((D70-D71)/MAX(1,Inputs!$B$82*12),C74+D69-D71) -> -1968.75 | E72: =-MIN((E70-E71)/MAX(1,Inputs!$B$82*12),D74+E69-E71) -> -1968.75 | F72: =-MIN((F70-F71)/MAX(1,Inputs!$B$82*12),E74+F69-F71) -> -1968.75 | G72: =-MIN((G70-G71)/MAX(1,Inputs!$B$82*12),F74+G69-G71) -> -1968.75 | H72: =-MIN((H70-H71)/MAX(1,Inputs!$B$82*12),G74+H69-H71) -> -1968.75 | I72: =-MIN((I70-I71)/MAX(1,Inputs!$B$82*12),H74+I69-I71) -> -1968.75 | J72: =-MIN((J70-J71)/MAX(1,Inputs!$B$82*12),I74+J69-J71) -> -1968.75 | K72: =-MIN((K70-K71)/MAX(1,Inputs!$B$82*12),J74+K69-K71) -> -1968.75 | ... BJ72: =-MIN((BJ70-BJ71)/MAX(1,Inputs!$B$82*12),BI74+BJ69-BJ71) -> -2385.4167
A73: Accumulated depreciation | C73: =C72 -> -1968.75 | D73: =C73+D72 -> -3937.5 | E73: =D73+E72 -> -5906.25 | F73: =E73+F72 -> -7875 | G73: =F73+G72 -> -9843.75 | H73: =G73+H72 -> -11812.5 | I73: =H73+I72 -> -13781.25 | J73: =I73+J72 -> -15750 | K73: =J73+K72 -> -17718.75 | ... BJ73: =BI73+BJ72 -> -130625
A74: Net fixed assets | C74: =C70+C73 -> 187031.25 | D74: =D70+D73 -> 185062.5 | E74: =E70+E73 -> 183093.75 | F74: =F70+F73 -> 181125 | G74: =G70+G73 -> 179156.25 | H74: =H70+H73 -> 177187.5 | I74: =I70+I73 -> 175218.75 | J74: =J70+J73 -> 173250 | ... BJ74: =BJ70+BJ73 -> 98375
A76: Debt
A77: Loan — opening balance | C77: =0 -> 0 | D77: =C80 -> 100000 | E77: =D80 -> 98333.333 | F77: =E80 -> 96666.667 | G77: =F80 -> 95000 | H77: =G80 -> 93333.333 | I77: =H80 -> 91666.667 | J77: =I80 -> 90000 | K77: =J80 -> 88333.333 | ... BJ77: =BI80 -> 3333.3333
A78: Loan drawdown | C78: =IF(C$6=1,Inputs!$B$72,0) -> 100000 | D78: =IF(D$6=1,Inputs!$B$72,0) -> 0 | E78: =IF(E$6=1,Inputs!$B$72,0) -> 0 | F78: =IF(F$6=1,Inputs!$B$72,0) -> 0 | G78: =IF(G$6=1,Inputs!$B$72,0) -> 0 | H78: =IF(H$6=1,Inputs!$B$72,0) -> 0 | I78: =IF(I$6=1,Inputs!$B$72,0) -> 0 | J78: =IF(J$6=1,Inputs!$B$72,0) -> 0 | ... BJ78: =IF(BJ$6=1,Inputs!$B$72,0) -> 0
A79: Loan repayment | C79: =-MIN(C77,Inputs!$B$72/MAX(1,Inputs!$B$74*12)) -> 0 | D79: =-MIN(D77,Inputs!$B$72/MAX(1,Inputs!$B$74*12)) -> -1666.6667 | E79: =-MIN(E77,Inputs!$B$72/MAX(1,Inputs!$B$74*12)) -> -1666.6667 | F79: =-MIN(F77,Inputs!$B$72/MAX(1,Inputs!$B$74*12)) -> -1666.6667 | G79: =-MIN(G77,Inputs!$B$72/MAX(1,Inputs!$B$74*12)) -> -1666.6667 | H79: =-MIN(H77,Inputs!$B$72/MAX(1,Inputs!$B$74*12)) -> -1666.6667 | I79: =-MIN(I77,Inputs!$B$72/MAX(1,Inputs!$B$74*12)) -> -1666.6667 | J79: =-MIN(J77,Inputs!$B$72/MAX(1,Inputs!$B$74*12)) -> -1666.6667 | ... BJ79: =-MIN(BJ77,Inputs!$B$72/MAX(1,Inputs!$B$74*12)) -> -1666.6667
A80: Loan — closing balance | C80: =C77+C78+C79 -> 100000 | D80: =D77+D78+D79 -> 98333.333 | E80: =E77+E78+E79 -> 96666.667 | F80: =F77+F78+F79 -> 95000 | G80: =G77+G78+G79 -> 93333.333 | H80: =H77+H78+H79 -> 91666.667 | I80: =I77+I78+I79 -> 90000 | J80: =J77+J78+J79 -> 88333.333 | ... BJ80: =BJ77+BJ78+BJ79 -> 1666.6667
A82: Working capital
A83: Accounts receivable | C83: =C33*Inputs!$B$77/30 -> 922.04 | D83: =D33*Inputs!$B$77/30 -> 1075.7133 | E83: =E33*Inputs!$B$77/30 -> 1229.3867 | F83: =F33*Inputs!$B$77/30 -> 1383.06 | G83: =G33*Inputs!$B$77/30 -> 1536.7333 | H83: =H33*Inputs!$B$77/30 -> 1878.5067 | I83: =I33*Inputs!$B$77/30 -> 2049.28 | J83: =J33*Inputs!$B$77/30 -> 2220.0533 | ... BJ83: =BJ33*Inputs!$B$77/30 -> 3554.1483
A84: Inventory | C84: =-C41*Inputs!$B$78/30 -> 1633.3427 | D84: =-D41*Inputs!$B$78/30 -> 1777.7887 | E84: =-E41*Inputs!$B$78/30 -> 1922.2347 | F84: =-F41*Inputs!$B$78/30 -> 2066.6807 | G84: =-G41*Inputs!$B$78/30 -> 2211.1267 | H84: =-H41*Inputs!$B$78/30 -> 2434.5747 | I84: =-I41*Inputs!$B$78/30 -> 2586.2027 | J84: =-J41*Inputs!$B$78/30 -> 2737.8307 | ... BJ84: =-BJ41*Inputs!$B$78/30 -> 4191.1672
A85: Accounts payable | C85: =-C41*Inputs!$B$79/30 -> 6805.5944 | D85: =-D41*Inputs!$B$79/30 -> 7407.4528 | E85: =-E41*Inputs!$B$79/30 -> 8009.3111 | F85: =-F41*Inputs!$B$79/30 -> 8611.1694 | G85: =-G41*Inputs!$B$79/30 -> 9213.0278 | H85: =-H41*Inputs!$B$79/30 -> 10144.061 | I85: =-I41*Inputs!$B$79/30 -> 10775.844 | J85: =-J41*Inputs!$B$79/30 -> 11407.628 | ... BJ85: =-BJ41*Inputs!$B$79/30 -> 17463.197
A86: (Increase) / decrease in receivables | C86: =-C83 -> -922.04 | D86: =C83-D83 -> -153.67333 | E86: =D83-E83 -> -153.67333 | F86: =E83-F83 -> -153.67333 | G86: =F83-G83 -> -153.67333 | H86: =G83-H83 -> -341.77333 | I86: =H83-I83 -> -170.77333 | J86: =I83-J83 -> -170.77333 | K86: =J83-K83 -> 68.626667 | ... BJ86: =BI83-BJ83 -> -355.88657
A87: (Increase) / decrease in inventory | C87: =-C84 -> -1633.3427 | D87: =C84-D84 -> -144.446 | E87: =D84-E84 -> -144.446 | F87: =E84-F84 -> -144.446 | G87: =F84-G84 -> -144.446 | H87: =G84-H84 -> -223.448 | I87: =H84-I84 -> -151.628 | J87: =I84-J84 -> -151.628 | K87: =J84-K84 -> -51.08 | ... BJ87: =BI84-BJ84 -> -168.03848
A88: Increase / (decrease) in payables | C88: =C85 -> 6805.5944 | D88: =D85-C85 -> 601.85833 | E88: =E85-D85 -> 601.85833 | F88: =F85-E85 -> 601.85833 | G88: =G85-F85 -> 601.85833 | H88: =H85-G85 -> 931.03333 | I88: =I85-H85 -> 631.78333 | J88: =J85-I85 -> 631.78333 | K88: =K85-J85 -> 212.83333 | ... BJ88: =BJ85-BI85 -> 700.16035
A90: Cash flow
A91: Operating cash flow | C91: =C61-C72+C86+C87+C88 -> -26015.981 | D91: =D61-D72+D86+D87+D88 -> -28447.097 | E91: =E61-E72+E86+E87+E88 -> -26925.49 | F91: =F61-F72+F86+F87+F88 -> -25403.883 | G91: =G61-G72+G86+G87+G88 -> -23882.276 | H91: =H61-H72+H86+H87+H88 -> -19962.395 | I91: =I61-I72+I86+I87+I88 -> -18284.836 | J91: =J61-J72+J86+J87+J88 -> -16550.847 | ... BJ91: =BJ61-BJ72+BJ86+BJ87+BJ88 -> -6176.7764
A92: Investing cash flow (capex) | C92: =-C69 -> -189000 | D92: =-D69 -> 0 | E92: =-E69 -> 0 | F92: =-F69 -> 0 | G92: =-G69 -> 0 | H92: =-H69 -> 0 | I92: =-I69 -> 0 | J92: =-J69 -> 0 | ... BJ92: =-BJ69 -> 0
A93: Equity raised | C93: =IF(C$6=1,Inputs!$B$71,0) -> 330000 | D93: =IF(D$6=1,Inputs!$B$71,0) -> 0 | E93: =IF(E$6=1,Inputs!$B$71,0) -> 0 | F93: =IF(F$6=1,Inputs!$B$71,0) -> 0 | G93: =IF(G$6=1,Inputs!$B$71,0) -> 0 | H93: =IF(H$6=1,Inputs!$B$71,0) -> 0 | I93: =IF(I$6=1,Inputs!$B$71,0) -> 0 | J93: =IF(J$6=1,Inputs!$B$71,0) -> 0 | ... BJ93: =IF(BJ$6=1,Inputs!$B$71,0) -> 0
A94: Financing cash flow | C94: =C93+C78+C79 -> 430000 | D94: =D93+D78+D79 -> -1666.6667 | E94: =E93+E78+E79 -> -1666.6667 | F94: =F93+F78+F79 -> -1666.6667 | G94: =G93+G78+G79 -> -1666.6667 | H94: =H93+H78+H79 -> -1666.6667 | I94: =I93+I78+I79 -> -1666.6667 | J94: =J93+J78+J79 -> -1666.6667 | ... BJ94: =BJ93+BJ78+BJ79 -> -1666.6667
A95: Net cash flow | C95: =C91+C92+C94 -> 214984.02 | D95: =D91+D92+D94 -> -30113.763 | E95: =E91+E92+E94 -> -28592.157 | F95: =F91+F92+F94 -> -27070.55 | G95: =G91+G92+G94 -> -25548.943 | H95: =H91+H92+H94 -> -21629.061 | I95: =I91+I92+I94 -> -19951.502 | J95: =J91+J92+J94 -> -18217.514 | ... BJ95: =BJ91+BJ92+BJ94 -> -7843.443
A96: Opening cash | C96: =0 -> 0 | D96: =C97 -> 214984.02 | E96: =D97 -> 184870.26 | F96: =E97 -> 156278.1 | G96: =F97 -> 129207.55 | H96: =G97 -> 103658.61 | I96: =H97 -> 82029.545 | J96: =I97 -> 62078.043 | K96: =J97 -> 43860.529 | ... BJ96: =BI97 -> -535876.96
A97: Closing cash | C97: =C96+C95 -> 214984.02 | D97: =D96+D95 -> 184870.26 | E97: =E96+E95 -> 156278.1 | F97: =F96+F95 -> 129207.55 | G97: =G96+G95 -> 103658.61 | H97: =H96+H95 -> 82029.545 | I97: =I96+I95 -> 62078.043 | J97: =J96+J95 -> 43860.529 | ... BJ97: =BJ96+BJ95 -> -543720.4
A98: Helper: EBITDA positive (1/0) | C98: =IF(C52>0,1,0) -> 0 | D98: =IF(D52>0,1,0) -> 0 | E98: =IF(E52>0,1,0) -> 0 | F98: =IF(F52>0,1,0) -> 0 | G98: =IF(G52>0,1,0) -> 0 | H98: =IF(H52>0,1,0) -> 0 | I98: =IF(I52>0,1,0) -> 0 | J98: =IF(J52>0,1,0) -> 0 | ... BJ98: =IF(BJ52>0,1,0) -> 0
A100: Goal modules
A101: Helper: net income positive (1/0) | C101: =IF(C61>0,1,0) -> 0 | D101: =IF(D61>0,1,0) -> 0 | E101: =IF(E61>0,1,0) -> 0 | F101: =IF(F61>0,1,0) -> 0 | G101: =IF(G61>0,1,0) -> 0 | H101: =IF(H61>0,1,0) -> 0 | I101: =IF(I61>0,1,0) -> 0 | J101: =IF(J61>0,1,0) -> 0 | ... BJ101: =IF(BJ61>0,1,0) -> 0
A102: Cash flow before financing (operating + investing) | C102: =C91+C92 -> -215015.98 | D102: =D91+D92 -> -28447.097 | E102: =E91+E92 -> -26925.49 | F102: =F91+F92 -> -25403.883 | G102: =G91+G92 -> -23882.276 | H102: =H91+H92 -> -19962.395 | I102: =I91+I92 -> -18284.836 | J102: =J91+J92 -> -16550.847 | ... BJ102: =BJ91+BJ92 -> -6176.7764
A103: Cumulative cash flow before financing | C103: =C102 -> -215015.98 | D103: =C103+D102 -> -243463.08 | E103: =D103+E102 -> -270388.57 | F103: =E103+F102 -> -295792.45 | G103: =F103+G102 -> -319674.73 | H103: =G103+H102 -> -339637.12 | I103: =H103+I102 -> -357921.96 | J103: =I103+J102 -> -374472.8 | K103: =J103+K102 -> -392342.01 | ... BJ103: =BI103+BJ102 -> -875387.07
A104: Helper: lowest cumulative cash flow so far | C104: =C103 -> -215015.98 | D104: =MIN(C104,D103) -> -243463.08 | E104: =MIN(D104,E103) -> -270388.57 | F104: =MIN(E104,F103) -> -295792.45 | G104: =MIN(F104,G103) -> -319674.73 | H104: =MIN(G104,H103) -> -339637.12 | I104: =MIN(H104,I103) -> -357921.96 | J104: =MIN(I104,J103) -> -374472.8 | K104: =MIN(J104,K103) -> -392342.01 | ... BJ104: =MIN(BI104,BJ103) -> -875387.07
A105: Helper: investment paid back (1/0) | C105: =IF(AND(C103>=0,C104<0),1,0) -> 0 | D105: =IF(AND(D103>=0,D104<0),1,0) -> 0 | E105: =IF(AND(E103>=0,E104<0),1,0) -> 0 | F105: =IF(AND(F103>=0,F104<0),1,0) -> 0 | G105: =IF(AND(G103>=0,G104<0),1,0) -> 0 | H105: =IF(AND(H103>=0,H104<0),1,0) -> 0 | I105: =IF(AND(I103>=0,I104<0),1,0) -> 0 | J105: =IF(AND(J103>=0,J104<0),1,0) -> 0 | ... BJ105: =IF(AND(BJ103>=0,BJ104<0),1,0) -> 0
A106: Unlevered free cash flow (operating + after-tax interest − capex) | C106: =C91-C56*(1-Inputs!$B$83)+C92 -> -214423.48 | D106: =D91-D56*(1-Inputs!$B$83)+D92 -> -27859.534 | E106: =E91-E56*(1-Inputs!$B$83)+E92 -> -26347.802 | F106: =F91-F56*(1-Inputs!$B$83)+F92 -> -24836.071 | G106: =G91-G56*(1-Inputs!$B$83)+G92 -> -23324.339 | H106: =H91-H56*(1-Inputs!$B$83)+H92 -> -19414.332 | I106: =I91-I56*(1-Inputs!$B$83)+I92 -> -17746.648 | J106: =J91-J56*(1-Inputs!$B$83)+J92 -> -16022.534 | ... BJ106: =BJ91-BJ56*(1-Inputs!$B$83)+BJ92 -> -6161.9639
A108: Balance sheet
A109: Paid-in capital | C109: =C93 -> 330000 | D109: =C109+D93 -> 330000 | E109: =D109+E93 -> 330000 | F109: =E109+F93 -> 330000 | G109: =F109+G93 -> 330000 | H109: =G109+H93 -> 330000 | I109: =H109+I93 -> 330000 | J109: =I109+J93 -> 330000 | K109: =J109+K93 -> 330000 | ... BJ109: =BI109+BJ93 -> 330000
A110: Retained earnings | C110: =C61 -> -32234.943 | D110: =C110+D61 -> -62954.528 | E110: =D110+E61 -> -92152.507 | F110: =E110+F61 -> -119828.88 | G110: =F110+G61 -> -145983.64 | H110: =G110+H61 -> -168280.6 | I110: =H110+I61 -> -188843.57 | J110: =I110+J61 -> -207672.55 | K110: =J110+K61 -> -227740.89 | ... BJ110: =BI110+BJ61 -> -786729.95
A111: Total assets | C111: =C97+C83+C84+C74 -> 404570.65 | D111: =D97+D83+D84+D74 -> 372786.26 | E111: =E97+E83+E84+E74 -> 342523.47 | F111: =F97+F83+F84+F74 -> 313782.29 | G111: =G97+G83+G84+G74 -> 286562.72 | H111: =H97+H83+H84+H74 -> 263530.13 | I111: =I97+I83+I84+I74 -> 241932.28 | J111: =J97+J83+J84+J74 -> 222068.41 | ... BJ111: =BJ97+BJ83+BJ84+BJ74 -> -437600.08
A112: Total liabilities | C112: =C85+C80 -> 106805.59 | D112: =D85+D80 -> 105740.79 | E112: =E85+E80 -> 104675.98 | F112: =F85+F80 -> 103611.17 | G112: =G85+G80 -> 102546.36 | H112: =H85+H80 -> 101810.73 | I112: =I85+I80 -> 100775.84 | J112: =J85+J80 -> 99740.961 | ... BJ112: =BJ85+BJ80 -> 19129.863
A113: Total equity | C113: =C109+C110 -> 297765.06 | D113: =D109+D110 -> 267045.47 | E113: =E109+E110 -> 237847.49 | F113: =F109+F110 -> 210171.12 | G113: =G109+G110 -> 184016.36 | H113: =H109+H110 -> 161719.4 | I113: =I109+I110 -> 141156.43 | J113: =J109+J110 -> 122327.45 | ... BJ113: =BJ109+BJ110 -> -456729.95
A114: Total liabilities & equity | C114: =C112+C113 -> 404570.65 | D114: =D112+D113 -> 372786.26 | E114: =E112+E113 -> 342523.47 | F114: =F112+F113 -> 313782.29 | G114: =G112+G113 -> 286562.72 | H114: =H112+H113 -> 263530.13 | I114: =I112+I113 -> 241932.28 | J114: =J112+J113 -> 222068.41 | ... BJ114: =BJ112+BJ113 -> -437600.08
...

Sheet Checks
A1: Model checks | E1: =HYPERLINK("#'Cover'!A1","◂ Contents") -> ◂ Contents
A2: Live formulas: they re-run every time an input changes.
A3: Check | B3: Result | C3: What it tests
A4: Annual revenue ties to period detail | B4: =IF(ABS(SUM('P&L'!$B$5:$F$5)-SUM(Monthly!$C$31:$BJ$31))<0.5,"PASS","FAIL") -> PASS | C4: Sum of annual revenue equals the sum of every period
A5: Annual net income ties to period detail | B5: =IF(ABS(SUM('P&L'!$B$23:$F$23)-SUM(Monthly!$C$59:$BJ$59))<0.5,"PASS","FAIL") -> PASS | C5: Sum of annual net income equals the sum of every period
A6: EBITDA reconciliation | B6: =IF(ABS(SUM(Monthly!$C$50:$BJ$50)-SUM(Monthly!$C$40:$BJ$40)-SUM(Monthly!$C$49:$BJ$49))<0.5,"PASS","FAIL") -> PASS | C6: EBITDA = gross profit + operating expenses (costs are negative)
A7: Cash roll-forward | B7: =IF(ABS(INDEX(Monthly!$C$95:$BJ$95,60)-SUM(Monthly!$C$93:$BJ$93))<0.5,"PASS","FAIL") -> PASS | C7: Closing cash = all net cash flows since the start (opening cash is zero)
A8: Scenario selector valid | B8: =IF(AND(ISNUMBER(Dashboard!B4),Dashboard!B4>=1,Dashboard!B4<=3,INT(Dashboard!B4)=Dashboard!B4),"PASS","FAIL") -> PASS | C8: Dashboard!B4 is 1, 2 or 3
A9: Scenario ordering of drivers | B9: =IF(AND(Inputs!$B$7<=Inputs!$C$7,Inputs!$C$7<=Inputs!$D$7,Inputs!$B$8<=Inputs!$C$8,Inputs!$C$8<=Inputs!$D$8,Inputs!$B$10>=Inputs!$C$10,Inputs!$C$10>=Inputs!$D$10,Inputs!$B$11<=Inputs!$C$11,Inputs!$C$11<=Inputs!$D$11,Inputs!$B$15<=Inputs!$C$15,Inputs!$C$15<=Inputs!$D$15,Inputs!$B$16<=Inputs!$C$16,Inputs!$C$16<=Inputs!$D$16,Inputs!$B$19<=Inputs!$C$19,Inputs!$C$19<=Inputs!$D$19,Inputs!$B$20<=Inputs!$C$20,Inputs!$C$20<=Inputs!$D$20,Inputs!$B$21<=Inputs!$C$21,Inputs!$C$21<=Inputs!$D$21,Inputs!$B$22<=Inputs!$C$22,Inputs!$C$22<=Inputs!$D$22,Inputs!$B$26<=Inputs!$C$26,Inputs!$C$26<=Inputs!$D$26,Inputs!$B$27<=Inputs!$C$27,Inputs!$C$27<=Inputs!$D$27,Inputs!$B$30<=Inputs!$C$30,Inputs!$C$30<=Inputs!$D$30,Inputs!$B$33>=Inputs!$C$33,Inputs!$C$33>=Inputs!$D$33,Inputs!$B$34>=Inputs!$C$34,Inputs!$C$34>=Inputs!$D$34,Inputs!$B$35>=Inputs!$C$35,Inputs!$C$35>=Inputs!$D$35,Inputs!$B$43<=Inputs!$C$43,Inputs!$C$43<=Inputs!$D$43,Inputs!$B$44>=Inputs!$C$44,Inputs!$C$44>=Inputs!$D$44,Inputs!$B$45>=Inputs!$C$45,Inputs!$C$45>=Inputs!$D$45,Inputs!$B$55<=Inputs!$C$55,Inputs!$C$55<=Inputs!$D$55,Inputs!$B$57<=Inputs!$C$57,Inputs!$C$57<=Inputs!$D$57,Inputs!$B$59<=Inputs!$C$59,Inputs!$C$59<=Inputs!$D$59,Inputs!$B$61<=Inputs!$C$61,Inputs!$C$61<=Inputs!$D$61,Inputs!$B$63<=Inputs!$C$63,Inputs!$C$63<=Inputs!$D$63,Inputs!$B$65<=Inputs!$C$65,Inputs!$C$65<=Inputs!$D$65,Inputs!$B$89>=Inputs!$C$89,Inputs!$C$89>=Inputs!$D$89,Inputs!$B$90<=Inputs!$C$90,Inputs!$C$90<=Inputs!$D$90,Inputs!$B$91<=Inputs!$C$91,Inputs!$C$91<=Inputs!$D$91),"PASS","FAIL") -> PASS | C9: Low / Base / High ordered the right way for every growth and cost driver
A10: Gross margin within 0–100% | B10: =IF(AND(MIN('P&L'!$B$8:$F$8)>=0,MAX('P&L'!$B$8:$F$8)<=1),"PASS","FAIL") -> PASS | C10: Gross margin never negative or above 100%
A11: Loan balance never negative | B11: =IF(MIN(Monthly!$C$78:$BJ$78)>=-0.5,"PASS","FAIL") -> PASS | C11: Repayments never exceed the loan
A12: Funding table ties to the cash flow | B12: =IF(ABS('Break-even'!B18-('Break-even'!B16-'Break-even'!B10))<0.5,"PASS","FAIL") -> PASS | C12: Lowest cash balance = sources of funds − uses of funds up to that point
A13: Valuation: discounting ties to NPV() | B13: =IF(ABS(Valuation!B23-NPV(Valuation!B6,Valuation!$B$17:$F$17))<0.5,"PASS","FAIL") -> PASS | C13: Sum of discounted free cash flows equals Excel's NPV of the same flows
A14: Valuation: WACC above terminal growth | B14: =IF(Valuation!B6>Valuation!B7,"PASS","FAIL") -> PASS | C14: The perpetual-growth formula needs WACC > g
A15: Valuation: sensitivity centre = enterprise value | B15: =IF(ABS(Valuation!D36-Valuation!B27)<0.5,"PASS","FAIL") -> PASS | C15: The middle of the WACC × growth table reproduces the headline value
A16: Valuation: final-year cash flow positive | B16: =IF(Valuation!$F$17>0,"PASS","WARN") -> PASS | C16: Business warning: a negative final-year cash flow gives a negative terminal value (often a 1-year plan still carrying start-up spending)
A17: Sources & uses balance | B17: =IF(ABS('Sources & Uses'!B21-'Sources & Uses'!B28)<0.5,"PASS","FAIL") -> PASS | C17: Sources of funds = uses of funds (incl. cash at the end) for the Sources & Uses period
A18: No error values | B18: =IF(SUMPRODUCT(--ISERROR(Monthly!$C$4:$BJ$113))+SUMPRODUCT(--ISERROR(Headcount!$C$4:$BJ$17))+SUMPRODUCT(--ISERROR('P&L'!$B$3:$F$24))+SUMPRODUCT(--ISERROR('Cash Flow'!$B$3:$F$18))+SUMPRODUCT(--ISERROR('Balance Sheet'!$B$3:$F$17))+SUMPRODUCT(--ISERROR(KPIs!$B$27:$F$48))+SUMPRODUCT(--ISERROR('Break-even'!$B$26:$F$33))+SUMPRODUCT(--ISERROR(Valuation!$B$14:$F$19))+SUMPRODUCT(--ISERROR('Break-even'!$B$3:$F$35))+SUMPRODUCT(--ISERROR(Valuation!$A$3:$F$40))+SUMPRODUCT(--ISERROR('Sources & Uses'!$B$3:$C$30))+SUMPRODUCT(--ISERROR(Dashboard!$A$6:$W$44))+SUMPRODUCT(--ISERROR(Summary!$A$5:$S$52))+SUMPRODUCT(--ISERROR(KPIs!$A$4:$G$48))+SUMPRODUCT(--ISERROR('Scenario calc'!$C$6:$BJ$127))+SUMPRODUCT(--ISERROR('Scenario calc'!$C$132:$BJ$253))+SUMPRODUCT(--ISERROR('Scenario calc'!$C$258:$BJ$379))+SUMPRODUCT(--ISERROR(Scenarios!$B$5:$F$50))=0,"PASS","FAIL") -> PASS | C18: No error values (divide-by-zero, broken references) on any calculation sheet
A19: Summary ties to statements | B19: =IF(IFERROR(AND(SUMPRODUCT(--(ABS(Summary!$B$7:$F$7-'P&L'!$B$5:$F$5)>0.5))=0,SUMPRODUCT(--(ABS(Summary!$B$19:$F$19-'P&L'!$B$23:$F$23)>0.5))=0,SUMPRODUCT(--(ABS(Summary!$B$31:$F$31-'Cash Flow'!$B$18:$F$18)>0.5))=0,SUMPRODUCT(--(ABS(Summary!$B$41:$F$41-'Balance Sheet'!$B$5:$F$5)>0.5))=0,ABS(SUM(Summary!$H$7:$S$7)-INDEX(Summary!$B$7:$F$7,Summary!$R$2))<0.5,ABS(SUM(Summary!$H$19:$S$19)-INDEX(Summary!$B$19:$F$19,Summary!$R$2))<0.5,ABS(Summary!$S$31-INDEX(Summary!$B$31:$F$31,Summary!$R$2))<0.5),FALSE()),"PASS","FAIL") -> PASS | C19: Summary revenue, net income and closing cash equal the statements every year; the detailed year adds up to its annual figure
A20: DuPont ties to return on equity | B20: =IF(SUMPRODUCT(--(ABS(KPIs!$B$24:$F$24)>0.000000001))>0,"FAIL",IF(SUMPRODUCT(ISNUMBER(KPIs!$B$23:$F$23)*ISNUMBER(KPIs!$B$16:$F$16))=0,"n/a","PASS")) -> PASS | C20: Net margin × asset turnover × equity multiplier equals return on equity every year; n/a = no year where both are defined (a one-sided n/a is a FAIL)
A21: Scenarios: Active = selected scenario | B21: =IF(IFERROR(AND(ABS(Scenarios!E17-INDEX(Scenarios!B17:D17,1,Dashboard!$B$4))<0.5,ABS(Scenarios!E18-INDEX(Scenarios!B18:D18,1,Dashboard!$B$4))<0.5,ABS(Scenarios!E19-INDEX(Scenarios!B19:D19,1,Dashboard!$B$4))<0.5,ABS(Scenarios!E20-INDEX(Scenarios!B20:D20,1,Dashboard!$B$4))<0.000001,ABS(Scenarios!E21-INDEX(Scenarios!B21:D21,1,Dashboard!$B$4))<0.5,ABS(Scenarios!E22-INDEX(Scenarios!B22:D22,1,Dashboard!$B$4))<0.5,ABS(Scenarios!E23-INDEX(Scenarios!B23:D23,1,Dashboard!$B$4))<0.5,ABS(Scenarios!E24-INDEX(Scenarios!B24:D24,1,Dashboard!$B$4))<0.5,ABS(Scenarios!E25-INDEX(Scenarios!B25:D25,1,Dashboard!$B$4))<0.5,ABS(Scenarios!E26-INDEX(Scenarios!B26:D26,1,Dashboard!$B$4))<0.5),FALSE()),"PASS","FAIL") -> PASS | C21: On the Scenarios sheet the live model (Active) equals the Low / Base / High column chosen on the Dashboard for every output
A22: Balance sheet balances every period | B22: =IF(SUMPRODUCT(--(ABS(Monthly!$C$113:$BJ$113)>0.5))=0,"PASS","FAIL") -> PASS | C22: Assets = liabilities + equity in every period
A23: Funding sufficient (cash ≥ 0) | B23: =IF(MIN(Monthly!$C$95:$BJ$95)>=0,"PASS","WARN") -> PASS | C23: Business warning, not an error: cash dips below zero in this scenario
A25: Overall verdict | B25: =IF(COUNTIF(B4:B23,"FAIL")>0,"FAIL",IF(COUNTIF(B4:B23,"WARN")>0,"PASS WITH WARNINGS","PASS")) -> PASS
