Workbook

Sheet Cover
B2: Rental property financial model (early)
B3: 5-year financial model · monthly detail · Low / Base / High scenarios · US dollars · Full plan
B5: Purpose | D5: Revenue and profit plan
B6: Active scenario | D6: =Dashboard!C4&" (change it on the Dashboard, cell B4)" -> Base (change it on the Dashboard, cell B4)
B7: Model checks | D7: =Checks!B30 -> PASS
B8: Prepared | D8: 21 October 2026
B10: Contents
C11: PRESENTATION
B12: 1 | C12: =HYPERLINK("#Dashboard!A1","Dashboard") -> Dashboard | D12: Scenario switch, key numbers, core financials
B13: 2 | C13: =HYPERLINK("#Summary!A1","Summary") -> Summary | D13: Income statement, cash flow and balance sheet — every year and any year by month
B14: 3 | C14: =HYPERLINK("#'Break-even'!A1","Break-even") -> Break-even | D14: Startup costs, funding need, break-even timing and revenue
B15: 4 | C15: =HYPERLINK("#Valuation!A1","Valuation") -> Valuation | D15: Free cash flow, DCF (perpetual growth and exit multiple), WACC × growth sensitivity
B16: 5 | C16: =HYPERLINK("#'Sources & Uses'!A1","Sources & Uses") -> Sources & Uses | D16: Funding structure, sources and uses of cash for the first months
B17: 6 | C17: =HYPERLINK("#KPIs!A1","KPIs") -> KPIs | D17: Financial ratios, DuPont analysis, industry metrics
B18: 7 | C18: =HYPERLINK("#Returns!A1","Returns") -> Returns | D18: Property returns: unlevered and levered IRR, NPV, multiple
C19: INPUTS
B20: 8 | C20: =HYPERLINK("#Inputs!A1","Inputs") -> Inputs | D20: Every assumption, Low / Base / High, with units and comments
C21: STATEMENTS
B22: 9 | C22: =HYPERLINK("#'P&L'!A1","P&L") -> P&L | D22: Annual profit & loss
B23: 10 | C23: =HYPERLINK("#'Cash Flow'!A1","Cash Flow") -> Cash Flow | D23: Annual cash flow statement
B24: 11 | C24: =HYPERLINK("#'Balance Sheet'!A1","Balance Sheet") -> Balance Sheet | D24: Balance sheet at year end
C25: CALCULATIONS
B26: 12 | C26: =HYPERLINK("#Monthly!A1","Monthly") -> Monthly | D26: Month-by-month engine of the model
B27: 13 | C27: =HYPERLINK("#Headcount!A1","Headcount") -> Headcount | D27: Team and payroll
C28: CONTROL
B29: 14 | C29: =HYPERLINK("#Checks!A1","Checks") -> Checks | D29: Live integrity checks and the overall verdict
B31: How to read this file
C32: 1000 | D32: Input you can change — yellow cell with a blue figure (Inputs sheet and the view switches)
C33: 1000 | D33: Formula — calculated, do not overwrite
C34: 1000 | D34: Link to another sheet
C35: 1000 | D35: Active value the model uses (follows the scenario)

Sheet Dashboard
A1: Dashboard | W1: =HYPERLINK("#'Cover'!A1","◂ Contents") -> ◂ Contents
A2: Rental property financial model (early)
A4: Active scenario | B4: 2 | C4: =CHOOSE(B4,"Low","Base","High") -> Base | D4: 1 = Low · 2 = Base · 3 = High — every sheet follows this cell | S4: Model checks | T4: =Checks!B30 -> PASS
A6: REVENUE · YEAR 5 | C6: EBITDA MARGIN · YEAR 5 | H6: NET INCOME · YEAR 5 | L6: LOWEST CASH BALANCE | P6: FUNDING REQUIRED | T6: ENTERPRISE VALUE (DCF)
A7: =F12 -> 221331.31 | C7: =F17 -> 0.63737605 | H7: =F18 -> 9742.0455 | L7: =F38 -> 58003.017 | P7: =F36 -> 1913997 | T7: =F43 -> -986206.56
A8: =IF(AND(B12>0,F12>=0),(F12/B12)^(1/4)-1,"CAGR n/a") -> 0.03 | C8: =F16 -> 141071.27 | H8: =F19 -> 0.044015669 | L8: ='Break-even'!B6 -> 1 | P8: =IF(F37>=0,"Covered by funding raised",-F37) -> Covered by funding raised | T8: Average of 2 methods
A10: Core financials ($'000) — active scenario
B11: 1 | C11: 2 | D11: 3 | E11: 4 | F11: 5
A12: Revenue | B12: =SUMIF(Monthly!$C$5:$BJ$5,B$11,Monthly!$C$12:$BJ$12) -> 196650 | C12: =SUMIF(Monthly!$C$5:$BJ$5,C$11,Monthly!$C$12:$BJ$12) -> 202549.5 | D12: =SUMIF(Monthly!$C$5:$BJ$5,D$11,Monthly!$C$12:$BJ$12) -> 208625.98 | E12: =SUMIF(Monthly!$C$5:$BJ$5,E$11,Monthly!$C$12:$BJ$12) -> 214884.76 | F12: =SUMIF(Monthly!$C$5:$BJ$5,F$11,Monthly!$C$12:$BJ$12) -> 221331.31
A13: Gross profit | B13: =SUMIF(Monthly!$C$5:$BJ$5,B$11,Monthly!$C$18:$BJ$18) -> 174222 | C13: =SUMIF(Monthly!$C$5:$BJ$5,C$11,Monthly!$C$18:$BJ$18) -> 179448.66 | D13: =SUMIF(Monthly!$C$5:$BJ$5,D$11,Monthly!$C$18:$BJ$18) -> 184832.12 | E13: =SUMIF(Monthly!$C$5:$BJ$5,E$11,Monthly!$C$18:$BJ$18) -> 190377.08 | F13: =SUMIF(Monthly!$C$5:$BJ$5,F$11,Monthly!$C$18:$BJ$18) -> 196088.4
A14: Gross margin | B14: =IF(B12=0,0,B13/B12) -> 0.88594966 | C14: =IF(C12=0,0,C13/C12) -> 0.88594966 | D14: =IF(D12=0,0,D13/D12) -> 0.88594966 | E14: =IF(E12=0,0,E13/E12) -> 0.88594966 | F14: =IF(F12=0,0,F13/F12) -> 0.88594966
A15: Operating expenses | B15: =SUMIF(Monthly!$C$5:$BJ$5,B$11,Monthly!$C$25:$BJ$25) -> -48882 | C15: =SUMIF(Monthly!$C$5:$BJ$5,C$11,Monthly!$C$25:$BJ$25) -> -50348.46 | D15: =SUMIF(Monthly!$C$5:$BJ$5,D$11,Monthly!$C$25:$BJ$25) -> -51858.914 | E15: =SUMIF(Monthly!$C$5:$BJ$5,E$11,Monthly!$C$25:$BJ$25) -> -53414.681 | F15: =SUMIF(Monthly!$C$5:$BJ$5,F$11,Monthly!$C$25:$BJ$25) -> -55017.122
A16: EBITDA | B16: =SUMIF(Monthly!$C$5:$BJ$5,B$11,Monthly!$C$26:$BJ$26) -> 125340 | C16: =SUMIF(Monthly!$C$5:$BJ$5,C$11,Monthly!$C$26:$BJ$26) -> 129100.2 | D16: =SUMIF(Monthly!$C$5:$BJ$5,D$11,Monthly!$C$26:$BJ$26) -> 132973.21 | E16: =SUMIF(Monthly!$C$5:$BJ$5,E$11,Monthly!$C$26:$BJ$26) -> 136962.4 | F16: =SUMIF(Monthly!$C$5:$BJ$5,F$11,Monthly!$C$26:$BJ$26) -> 141071.27
A17: EBITDA margin | B17: =IF(B12=0,0,B16/B12) -> 0.63737605 | C17: =IF(C12=0,0,C16/C12) -> 0.63737605 | D17: =IF(D12=0,0,D16/D12) -> 0.63737605 | E17: =IF(E12=0,0,E16/E12) -> 0.63737605 | F17: =IF(F12=0,0,F16/F12) -> 0.63737605
A18: Net income | B18: =SUMIF(Monthly!$C$5:$BJ$5,B$11,Monthly!$C$35:$BJ$35) -> -9205.6762 | C18: =SUMIF(Monthly!$C$5:$BJ$5,C$11,Monthly!$C$35:$BJ$35) -> -4678.9386 | D18: =SUMIF(Monthly!$C$5:$BJ$5,D$11,Monthly!$C$35:$BJ$35) -> 16.812047 | E18: =SUMIF(Monthly!$C$5:$BJ$5,E$11,Monthly!$C$35:$BJ$35) -> 4888.8702 | F18: =SUMIF(Monthly!$C$5:$BJ$5,F$11,Monthly!$C$35:$BJ$35) -> 9742.0455
A19: Net margin | B19: =IF(B12=0,0,B18/B12) -> -0.04681249 | C19: =IF(C12=0,0,C18/C12) -> -0.023100223 | D19: =IF(D12=0,0,D18/D12) -> 8.0584628e-05 | E19: =IF(E12=0,0,E18/E12) -> 0.022751125 | F19: =IF(F12=0,0,F18/F12) -> 0.044015669
A20: Operating cash flow | B20: =SUMIF(Monthly!$C$5:$BJ$5,B$11,Monthly!$C$65:$BJ$65) -> 48669.41 | C20: =SUMIF(Monthly!$C$5:$BJ$5,C$11,Monthly!$C$65:$BJ$65) -> 52421.419 | D20: =SUMIF(Monthly!$C$5:$BJ$5,D$11,Monthly!$C$65:$BJ$65) -> 57253.699 | E20: =SUMIF(Monthly!$C$5:$BJ$5,E$11,Monthly!$C$65:$BJ$65) -> 62266.382 | F20: =SUMIF(Monthly!$C$5:$BJ$5,F$11,Monthly!$C$65:$BJ$65) -> 67264.401
A21: Investing cash flow | B21: =SUMIF(Monthly!$C$5:$BJ$5,B$11,Monthly!$C$66:$BJ$66) -> -1909000 | C21: =SUMIF(Monthly!$C$5:$BJ$5,C$11,Monthly!$C$66:$BJ$66) -> -3605 | D21: =SUMIF(Monthly!$C$5:$BJ$5,D$11,Monthly!$C$66:$BJ$66) -> -3713.15 | E21: =SUMIF(Monthly!$C$5:$BJ$5,E$11,Monthly!$C$66:$BJ$66) -> -3824.5445 | F21: =SUMIF(Monthly!$C$5:$BJ$5,F$11,Monthly!$C$66:$BJ$66) -> -3939.2808
A22: Financing cash flow | B22: =SUMIF(Monthly!$C$5:$BJ$5,B$11,Monthly!$C$68:$BJ$68) -> 1946587.3 | C22: =SUMIF(Monthly!$C$5:$BJ$5,C$11,Monthly!$C$68:$BJ$68) -> -14310.979 | D22: =SUMIF(Monthly!$C$5:$BJ$5,D$11,Monthly!$C$68:$BJ$68) -> -15269.412 | E22: =SUMIF(Monthly!$C$5:$BJ$5,E$11,Monthly!$C$68:$BJ$68) -> -16292.033 | F22: =SUMIF(Monthly!$C$5:$BJ$5,F$11,Monthly!$C$68:$BJ$68) -> -17383.141
A23: Net change in cash | B23: =SUMIF(Monthly!$C$5:$BJ$5,B$11,Monthly!$C$69:$BJ$69) -> 86256.705 | C23: =SUMIF(Monthly!$C$5:$BJ$5,C$11,Monthly!$C$69:$BJ$69) -> 34505.44 | D23: =SUMIF(Monthly!$C$5:$BJ$5,D$11,Monthly!$C$69:$BJ$69) -> 38271.137 | E23: =SUMIF(Monthly!$C$5:$BJ$5,E$11,Monthly!$C$69:$BJ$69) -> 42149.805 | F23: =SUMIF(Monthly!$C$5:$BJ$5,F$11,Monthly!$C$69:$BJ$69) -> 45941.98
A24: Year-end cash | B24: =INDEX(Monthly!$C$71:$BJ$71,B$11*12) -> 86256.705 | C24: =INDEX(Monthly!$C$71:$BJ$71,C$11*12) -> 120762.14 | D24: =INDEX(Monthly!$C$71:$BJ$71,D$11*12) -> 159033.28 | E24: =INDEX(Monthly!$C$71:$BJ$71,E$11*12) -> 201183.09 | F24: =INDEX(Monthly!$C$71:$BJ$71,F$11*12) -> 247125.07
A26: Property metrics
B27: 1 | C27: 2 | D27: 3 | E27: 4 | F27: 5
A28: Net operating income (NOI) | B28: =KPIs!B33 -> 125340 | C28: =KPIs!C33 -> 129100.2 | D28: =KPIs!D33 -> 132973.21 | E28: =KPIs!E33 -> 136962.4 | F28: =KPIs!F33 -> 141071.27
A29: Economic occupancy | B29: =KPIs!B31 -> 0.95 | C29: =KPIs!C31 -> 0.95 | D29: =KPIs!D31 -> 0.95 | E29: =KPIs!E31 -> 0.95 | F29: =KPIs!F31 -> 0.95
A30: Debt service (interest + principal) | B30: =KPIs!B38 -> 91017.795 | C30: =KPIs!C38 -> 91017.795 | D30: =KPIs!D38 -> 91017.795 | E30: =KPIs!E38 -> 91017.795 | F30: =KPIs!F38 -> 91017.795
A31: Debt service coverage | B31: =KPIs!B39 -> 1.3770933 | C31: =KPIs!C39 -> 1.4184061 | D31: =KPIs!D39 -> 1.4609583 | E31: =KPIs!E39 -> 1.5047871 | F31: =KPIs!F39 -> 1.5499307
A33: Funding & valuation ($'000) — active scenario
A34: Equity raised | F34: =Inputs!$E$34 -> 760000
A35: Loan drawn | F35: =Inputs!$E$35 -> 1200000
A36: Funding required (incl. cash buffer) | F36: ='Break-even'!B12 -> 1913997
A37: Funding surplus / (shortfall) | F37: ='Break-even'!B17 -> 46003.017
A38: ="Lowest cash balance (month "&'Break-even'!B6&")" -> Lowest cash balance (month 1) | F38: ='Break-even'!B18 -> 58003.017
A39: First month with positive EBITDA | F39: ='Break-even'!B21 -> 1
A40: Cash invested paid back | F40: ='Break-even'!B23 -> Not within horizon
A41: Enterprise value — perpetual growth | F41: =Valuation!B27 -> -975424.3
A42: Enterprise value — exit multiple | F42: =Valuation!C27 -> -996988.81
A43: Enterprise value — average | F43: =Valuation!B30 -> -986206.56

Sheet Summary
A1: Financial statements summary | U1: =HYPERLINK("#'Cover'!A1","◂ Contents") -> ◂ Contents
A2: Rental property financial model (early) | P2: Select detailed year: | R2: 1
A5: Income statement ($'000) — by year | H5: ="Income statement ($'000) — Year "&$R$2&", by month" -> Income statement ($'000) — Year 1, by month
B6: 1 | C6: 2 | D6: 3 | E6: 4 | F6: 5 | H6: =INDEX(Monthly!$C$4:$BJ$4,($R$2-1)*12+1) -> 1 | I6: =INDEX(Monthly!$C$4:$BJ$4,($R$2-1)*12+2) -> 2 | J6: =INDEX(Monthly!$C$4:$BJ$4,($R$2-1)*12+3) -> 3 | K6: =INDEX(Monthly!$C$4:$BJ$4,($R$2-1)*12+4) -> 4 | L6: =INDEX(Monthly!$C$4:$BJ$4,($R$2-1)*12+5) -> 5 | M6: =INDEX(Monthly!$C$4:$BJ$4,($R$2-1)*12+6) -> 6 | N6: =INDEX(Monthly!$C$4:$BJ$4,($R$2-1)*12+7) -> 7 | O6: =INDEX(Monthly!$C$4:$BJ$4,($R$2-1)*12+8) -> 8 | P6: =INDEX(Monthly!$C$4:$BJ$4,($R$2-1)*12+9) -> 9 | Q6: =INDEX(Monthly!$C$4:$BJ$4,($R$2-1)*12+10) -> 10 | R6: =INDEX(Monthly!$C$4:$BJ$4,($R$2-1)*12+11) -> 11 | S6: =INDEX(Monthly!$C$4:$BJ$4,($R$2-1)*12+12) -> 12
A7: Revenue | B7: ='P&L'!B5 -> 196650 | C7: ='P&L'!C5 -> 202549.5 | D7: ='P&L'!D5 -> 208625.98 | E7: ='P&L'!E5 -> 214884.76 | F7: ='P&L'!F5 -> 221331.31 | H7: =INDEX(Monthly!$C$12:$BJ$12,($R$2-1)*12+1) -> 16387.5 | I7: =INDEX(Monthly!$C$12:$BJ$12,($R$2-1)*12+2) -> 16387.5 | J7: =INDEX(Monthly!$C$12:$BJ$12,($R$2-1)*12+3) -> 16387.5 | K7: =INDEX(Monthly!$C$12:$BJ$12,($R$2-1)*12+4) -> 16387.5 | L7: =INDEX(Monthly!$C$12:$BJ$12,($R$2-1)*12+5) -> 16387.5 | M7: =INDEX(Monthly!$C$12:$BJ$12,($R$2-1)*12+6) -> 16387.5 | N7: =INDEX(Monthly!$C$12:$BJ$12,($R$2-1)*12+7) -> 16387.5 | O7: =INDEX(Monthly!$C$12:$BJ$12,($R$2-1)*12+8) -> 16387.5 | P7: =INDEX(Monthly!$C$12:$BJ$12,($R$2-1)*12+9) -> 16387.5 | Q7: =INDEX(Monthly!$C$12:$BJ$12,($R$2-1)*12+10) -> 16387.5 | R7: =INDEX(Monthly!$C$12:$BJ$12,($R$2-1)*12+11) -> 16387.5 | S7: =INDEX(Monthly!$C$12:$BJ$12,($R$2-1)*12+12) -> 16387.5
A8: Direct property costs | B8: ='P&L'!B6 -> -22428 | C8: ='P&L'!C6 -> -23100.84 | D8: ='P&L'!D6 -> -23793.865 | E8: ='P&L'!E6 -> -24507.681 | F8: ='P&L'!F6 -> -25242.912 | H8: =INDEX(Monthly!$C$17:$BJ$17,($R$2-1)*12+1) -> -1869 | I8: =INDEX(Monthly!$C$17:$BJ$17,($R$2-1)*12+2) -> -1869 | J8: =INDEX(Monthly!$C$17:$BJ$17,($R$2-1)*12+3) -> -1869 | K8: =INDEX(Monthly!$C$17:$BJ$17,($R$2-1)*12+4) -> -1869 | L8: =INDEX(Monthly!$C$17:$BJ$17,($R$2-1)*12+5) -> -1869 | M8: =INDEX(Monthly!$C$17:$BJ$17,($R$2-1)*12+6) -> -1869 | N8: =INDEX(Monthly!$C$17:$BJ$17,($R$2-1)*12+7) -> -1869 | O8: =INDEX(Monthly!$C$17:$BJ$17,($R$2-1)*12+8) -> -1869 | P8: =INDEX(Monthly!$C$17:$BJ$17,($R$2-1)*12+9) -> -1869 | Q8: =INDEX(Monthly!$C$17:$BJ$17,($R$2-1)*12+10) -> -1869 | R8: =INDEX(Monthly!$C$17:$BJ$17,($R$2-1)*12+11) -> -1869 | S8: =INDEX(Monthly!$C$17:$BJ$17,($R$2-1)*12+12) -> -1869
A9: Gross profit | B9: ='P&L'!B7 -> 174222 | C9: ='P&L'!C7 -> 179448.66 | D9: ='P&L'!D7 -> 184832.12 | E9: ='P&L'!E7 -> 190377.08 | F9: ='P&L'!F7 -> 196088.4 | H9: =INDEX(Monthly!$C$18:$BJ$18,($R$2-1)*12+1) -> 14518.5 | I9: =INDEX(Monthly!$C$18:$BJ$18,($R$2-1)*12+2) -> 14518.5 | J9: =INDEX(Monthly!$C$18:$BJ$18,($R$2-1)*12+3) -> 14518.5 | K9: =INDEX(Monthly!$C$18:$BJ$18,($R$2-1)*12+4) -> 14518.5 | L9: =INDEX(Monthly!$C$18:$BJ$18,($R$2-1)*12+5) -> 14518.5 | M9: =INDEX(Monthly!$C$18:$BJ$18,($R$2-1)*12+6) -> 14518.5 | N9: =INDEX(Monthly!$C$18:$BJ$18,($R$2-1)*12+7) -> 14518.5 | O9: =INDEX(Monthly!$C$18:$BJ$18,($R$2-1)*12+8) -> 14518.5 | P9: =INDEX(Monthly!$C$18:$BJ$18,($R$2-1)*12+9) -> 14518.5 | Q9: =INDEX(Monthly!$C$18:$BJ$18,($R$2-1)*12+10) -> 14518.5 | R9: =INDEX(Monthly!$C$18:$BJ$18,($R$2-1)*12+11) -> 14518.5 | S9: =INDEX(Monthly!$C$18:$BJ$18,($R$2-1)*12+12) -> 14518.5
A10: Gross margin | B10: ='P&L'!B8 -> 0.88594966 | C10: ='P&L'!C8 -> 0.88594966 | D10: ='P&L'!D8 -> 0.88594966 | E10: ='P&L'!E8 -> 0.88594966 | F10: ='P&L'!F8 -> 0.88594966 | H10: =IF(H7=0,0,H9/H7) -> 0.88594966 | I10: =IF(I7=0,0,I9/I7) -> 0.88594966 | J10: =IF(J7=0,0,J9/J7) -> 0.88594966 | K10: =IF(K7=0,0,K9/K7) -> 0.88594966 | L10: =IF(L7=0,0,L9/L7) -> 0.88594966 | M10: =IF(M7=0,0,M9/M7) -> 0.88594966 | N10: =IF(N7=0,0,N9/N7) -> 0.88594966 | O10: =IF(O7=0,0,O9/O7) -> 0.88594966 | ... S10: =IF(S7=0,0,S9/S7) -> 0.88594966
A11: Total operating expenses | B11: ='P&L'!B13 -> -48882 | C11: ='P&L'!C13 -> -50348.46 | D11: ='P&L'!D13 -> -51858.914 | E11: ='P&L'!E13 -> -53414.681 | F11: ='P&L'!F13 -> -55017.122 | H11: =INDEX(Monthly!$C$25:$BJ$25,($R$2-1)*12+1) -> -4073.5 | I11: =INDEX(Monthly!$C$25:$BJ$25,($R$2-1)*12+2) -> -4073.5 | J11: =INDEX(Monthly!$C$25:$BJ$25,($R$2-1)*12+3) -> -4073.5 | K11: =INDEX(Monthly!$C$25:$BJ$25,($R$2-1)*12+4) -> -4073.5 | L11: =INDEX(Monthly!$C$25:$BJ$25,($R$2-1)*12+5) -> -4073.5 | M11: =INDEX(Monthly!$C$25:$BJ$25,($R$2-1)*12+6) -> -4073.5 | N11: =INDEX(Monthly!$C$25:$BJ$25,($R$2-1)*12+7) -> -4073.5 | O11: =INDEX(Monthly!$C$25:$BJ$25,($R$2-1)*12+8) -> -4073.5 | P11: =INDEX(Monthly!$C$25:$BJ$25,($R$2-1)*12+9) -> -4073.5 | Q11: =INDEX(Monthly!$C$25:$BJ$25,($R$2-1)*12+10) -> -4073.5 | R11: =INDEX(Monthly!$C$25:$BJ$25,($R$2-1)*12+11) -> -4073.5 | S11: =INDEX(Monthly!$C$25:$BJ$25,($R$2-1)*12+12) -> -4073.5
A12: EBITDA | B12: ='P&L'!B14 -> 125340 | C12: ='P&L'!C14 -> 129100.2 | D12: ='P&L'!D14 -> 132973.21 | E12: ='P&L'!E14 -> 136962.4 | F12: ='P&L'!F14 -> 141071.27 | H12: =INDEX(Monthly!$C$26:$BJ$26,($R$2-1)*12+1) -> 10445 | I12: =INDEX(Monthly!$C$26:$BJ$26,($R$2-1)*12+2) -> 10445 | J12: =INDEX(Monthly!$C$26:$BJ$26,($R$2-1)*12+3) -> 10445 | K12: =INDEX(Monthly!$C$26:$BJ$26,($R$2-1)*12+4) -> 10445 | L12: =INDEX(Monthly!$C$26:$BJ$26,($R$2-1)*12+5) -> 10445 | M12: =INDEX(Monthly!$C$26:$BJ$26,($R$2-1)*12+6) -> 10445 | N12: =INDEX(Monthly!$C$26:$BJ$26,($R$2-1)*12+7) -> 10445 | O12: =INDEX(Monthly!$C$26:$BJ$26,($R$2-1)*12+8) -> 10445 | P12: =INDEX(Monthly!$C$26:$BJ$26,($R$2-1)*12+9) -> 10445 | Q12: =INDEX(Monthly!$C$26:$BJ$26,($R$2-1)*12+10) -> 10445 | R12: =INDEX(Monthly!$C$26:$BJ$26,($R$2-1)*12+11) -> 10445 | S12: =INDEX(Monthly!$C$26:$BJ$26,($R$2-1)*12+12) -> 10445
A13: EBITDA margin | B13: ='P&L'!B15 -> 0.63737605 | C13: ='P&L'!C15 -> 0.63737605 | D13: ='P&L'!D15 -> 0.63737605 | E13: ='P&L'!E15 -> 0.63737605 | F13: ='P&L'!F15 -> 0.63737605 | H13: =IF(H7=0,0,H12/H7) -> 0.63737605 | I13: =IF(I7=0,0,I12/I7) -> 0.63737605 | J13: =IF(J7=0,0,J12/J7) -> 0.63737605 | K13: =IF(K7=0,0,K12/K7) -> 0.63737605 | L13: =IF(L7=0,0,L12/L7) -> 0.63737605 | M13: =IF(M7=0,0,M12/M7) -> 0.63737605 | N13: =IF(N7=0,0,N12/N7) -> 0.63737605 | O13: =IF(O7=0,0,O12/O7) -> 0.63737605 | ... S13: =IF(S7=0,0,S12/S7) -> 0.63737605
A14: Depreciation | B14: ='P&L'!B16 -> -56940.586 | C14: ='P&L'!C16 -> -57072.323 | D14: ='P&L'!D16 -> -57208.011 | E14: ='P&L'!E16 -> -57347.77 | F14: ='P&L'!F16 -> -57491.721 | H14: =INDEX(Monthly!$C$44:$BJ$44,($R$2-1)*12+1) -> -4740.0977 | I14: =INDEX(Monthly!$C$44:$BJ$44,($R$2-1)*12+2) -> -4740.9979 | J14: =INDEX(Monthly!$C$44:$BJ$44,($R$2-1)*12+3) -> -4741.8981 | K14: =INDEX(Monthly!$C$44:$BJ$44,($R$2-1)*12+4) -> -4742.7984 | L14: =INDEX(Monthly!$C$44:$BJ$44,($R$2-1)*12+5) -> -4743.6986 | M14: =INDEX(Monthly!$C$44:$BJ$44,($R$2-1)*12+6) -> -4744.5988 | N14: =INDEX(Monthly!$C$44:$BJ$44,($R$2-1)*12+7) -> -4745.499 | O14: =INDEX(Monthly!$C$44:$BJ$44,($R$2-1)*12+8) -> -4746.3992 | P14: =INDEX(Monthly!$C$44:$BJ$44,($R$2-1)*12+9) -> -4747.2994 | Q14: =INDEX(Monthly!$C$44:$BJ$44,($R$2-1)*12+10) -> -4748.1996 | R14: =INDEX(Monthly!$C$44:$BJ$44,($R$2-1)*12+11) -> -4749.0998 | S14: =INDEX(Monthly!$C$44:$BJ$44,($R$2-1)*12+12) -> -4750
A15: EBIT | B15: ='P&L'!B17 -> 68399.414 | C15: ='P&L'!C17 -> 72027.877 | D15: ='P&L'!D17 -> 75765.195 | E15: ='P&L'!E17 -> 79614.633 | F15: ='P&L'!F17 -> 83579.553 | H15: =INDEX(Monthly!$C$29:$BJ$29,($R$2-1)*12+1) -> 5704.9023 | I15: =INDEX(Monthly!$C$29:$BJ$29,($R$2-1)*12+2) -> 5704.0021 | J15: =INDEX(Monthly!$C$29:$BJ$29,($R$2-1)*12+3) -> 5703.1019 | K15: =INDEX(Monthly!$C$29:$BJ$29,($R$2-1)*12+4) -> 5702.2016 | L15: =INDEX(Monthly!$C$29:$BJ$29,($R$2-1)*12+5) -> 5701.3014 | M15: =INDEX(Monthly!$C$29:$BJ$29,($R$2-1)*12+6) -> 5700.4012 | N15: =INDEX(Monthly!$C$29:$BJ$29,($R$2-1)*12+7) -> 5699.501 | O15: =INDEX(Monthly!$C$29:$BJ$29,($R$2-1)*12+8) -> 5698.6008 | P15: =INDEX(Monthly!$C$29:$BJ$29,($R$2-1)*12+9) -> 5697.7006 | Q15: =INDEX(Monthly!$C$29:$BJ$29,($R$2-1)*12+10) -> 5696.8004 | R15: =INDEX(Monthly!$C$29:$BJ$29,($R$2-1)*12+11) -> 5695.9002 | S15: =INDEX(Monthly!$C$29:$BJ$29,($R$2-1)*12+12) -> 5695
A16: Interest | B16: ='P&L'!B18 -> -77605.09 | C16: ='P&L'!C18 -> -76706.816 | D16: ='P&L'!D18 -> -75748.383 | E16: ='P&L'!E18 -> -74725.762 | F16: ='P&L'!F18 -> -73634.655 | H16: =INDEX(Monthly!$C$30:$BJ$30,($R$2-1)*12+1) -> -6500 | I16: =INDEX(Monthly!$C$30:$BJ$30,($R$2-1)*12+2) -> -6494.1239 | J16: =INDEX(Monthly!$C$30:$BJ$30,($R$2-1)*12+3) -> -6488.216 | K16: =INDEX(Monthly!$C$30:$BJ$30,($R$2-1)*12+4) -> -6482.2761 | L16: =INDEX(Monthly!$C$30:$BJ$30,($R$2-1)*12+5) -> -6476.304 | M16: =INDEX(Monthly!$C$30:$BJ$30,($R$2-1)*12+6) -> -6470.2995 | N16: =INDEX(Monthly!$C$30:$BJ$30,($R$2-1)*12+7) -> -6464.2626 | O16: =INDEX(Monthly!$C$30:$BJ$30,($R$2-1)*12+8) -> -6458.1929 | P16: =INDEX(Monthly!$C$30:$BJ$30,($R$2-1)*12+9) -> -6452.0904 | Q16: =INDEX(Monthly!$C$30:$BJ$30,($R$2-1)*12+10) -> -6445.9548 | R16: =INDEX(Monthly!$C$30:$BJ$30,($R$2-1)*12+11) -> -6439.7859 | S16: =INDEX(Monthly!$C$30:$BJ$30,($R$2-1)*12+12) -> -6433.5837
A17: Pre-tax income | B17: ='P&L'!B19 -> -9205.6762 | C17: ='P&L'!C19 -> -4678.9386 | D17: ='P&L'!D19 -> 16.812047 | E17: ='P&L'!E19 -> 4888.8702 | F17: ='P&L'!F19 -> 9944.8983 | H17: =INDEX(Monthly!$C$31:$BJ$31,($R$2-1)*12+1) -> -795.09774 | I17: =INDEX(Monthly!$C$31:$BJ$31,($R$2-1)*12+2) -> -790.12185 | J17: =INDEX(Monthly!$C$31:$BJ$31,($R$2-1)*12+3) -> -785.11414 | K17: =INDEX(Monthly!$C$31:$BJ$31,($R$2-1)*12+4) -> -780.07443 | L17: =INDEX(Monthly!$C$31:$BJ$31,($R$2-1)*12+5) -> -775.00254 | M17: =INDEX(Monthly!$C$31:$BJ$31,($R$2-1)*12+6) -> -769.89831 | N17: =INDEX(Monthly!$C$31:$BJ$31,($R$2-1)*12+7) -> -764.76155 | O17: =INDEX(Monthly!$C$31:$BJ$31,($R$2-1)*12+8) -> -759.59209 | P17: =INDEX(Monthly!$C$31:$BJ$31,($R$2-1)*12+9) -> -754.38975 | Q17: =INDEX(Monthly!$C$31:$BJ$31,($R$2-1)*12+10) -> -749.15436 | R17: =INDEX(Monthly!$C$31:$BJ$31,($R$2-1)*12+11) -> -743.88573 | S17: =INDEX(Monthly!$C$31:$BJ$31,($R$2-1)*12+12) -> -738.58369
A18: Income tax | B18: ='P&L'!B20 -> 0 | C18: ='P&L'!C20 -> 0 | D18: ='P&L'!D20 -> 0 | E18: ='P&L'!E20 -> 0 | F18: ='P&L'!F20 -> -202.85282 | H18: =INDEX(Monthly!$C$34:$BJ$34,($R$2-1)*12+1) -> 0 | I18: =INDEX(Monthly!$C$34:$BJ$34,($R$2-1)*12+2) -> 0 | J18: =INDEX(Monthly!$C$34:$BJ$34,($R$2-1)*12+3) -> 0 | K18: =INDEX(Monthly!$C$34:$BJ$34,($R$2-1)*12+4) -> 0 | L18: =INDEX(Monthly!$C$34:$BJ$34,($R$2-1)*12+5) -> 0 | M18: =INDEX(Monthly!$C$34:$BJ$34,($R$2-1)*12+6) -> 0 | N18: =INDEX(Monthly!$C$34:$BJ$34,($R$2-1)*12+7) -> 0 | O18: =INDEX(Monthly!$C$34:$BJ$34,($R$2-1)*12+8) -> 0 | P18: =INDEX(Monthly!$C$34:$BJ$34,($R$2-1)*12+9) -> 0 | Q18: =INDEX(Monthly!$C$34:$BJ$34,($R$2-1)*12+10) -> 0 | R18: =INDEX(Monthly!$C$34:$BJ$34,($R$2-1)*12+11) -> 0 | S18: =INDEX(Monthly!$C$34:$BJ$34,($R$2-1)*12+12) -> 0
A19: Net income | B19: ='P&L'!B21 -> -9205.6762 | C19: ='P&L'!C21 -> -4678.9386 | D19: ='P&L'!D21 -> 16.812047 | E19: ='P&L'!E21 -> 4888.8702 | F19: ='P&L'!F21 -> 9742.0455 | H19: =INDEX(Monthly!$C$35:$BJ$35,($R$2-1)*12+1) -> -795.09774 | I19: =INDEX(Monthly!$C$35:$BJ$35,($R$2-1)*12+2) -> -790.12185 | J19: =INDEX(Monthly!$C$35:$BJ$35,($R$2-1)*12+3) -> -785.11414 | K19: =INDEX(Monthly!$C$35:$BJ$35,($R$2-1)*12+4) -> -780.07443 | L19: =INDEX(Monthly!$C$35:$BJ$35,($R$2-1)*12+5) -> -775.00254 | M19: =INDEX(Monthly!$C$35:$BJ$35,($R$2-1)*12+6) -> -769.89831 | N19: =INDEX(Monthly!$C$35:$BJ$35,($R$2-1)*12+7) -> -764.76155 | O19: =INDEX(Monthly!$C$35:$BJ$35,($R$2-1)*12+8) -> -759.59209 | P19: =INDEX(Monthly!$C$35:$BJ$35,($R$2-1)*12+9) -> -754.38975 | Q19: =INDEX(Monthly!$C$35:$BJ$35,($R$2-1)*12+10) -> -749.15436 | R19: =INDEX(Monthly!$C$35:$BJ$35,($R$2-1)*12+11) -> -743.88573 | S19: =INDEX(Monthly!$C$35:$BJ$35,($R$2-1)*12+12) -> -738.58369
A20: Net margin | B20: ='P&L'!B22 -> -0.04681249 | C20: ='P&L'!C22 -> -0.023100223 | D20: ='P&L'!D22 -> 8.0584628e-05 | E20: ='P&L'!E22 -> 0.022751125 | F20: ='P&L'!F22 -> 0.044015669 | H20: =IF(H7=0,0,H19/H7) -> -0.04851855 | I20: =IF(I7=0,0,I19/I7) -> -0.048214911 | J20: =IF(J7=0,0,J19/J7) -> -0.04790933 | K20: =IF(K7=0,0,K19/K7) -> -0.047601796 | L20: =IF(L7=0,0,L19/L7) -> -0.047292299 | M20: =IF(M7=0,0,M19/M7) -> -0.046980827 | N20: =IF(N7=0,0,N19/N7) -> -0.046667371 | O20: =IF(O7=0,0,O19/O7) -> -0.04635192 | ... S20: =IF(S7=0,0,S19/S7) -> -0.045069943
A22: Cash flow ($'000) — by year | H22: ="Cash flow ($'000) — Year "&$R$2&", by month" -> Cash flow ($'000) — Year 1, by month
B23: 1 | C23: 2 | D23: 3 | E23: 4 | F23: 5 | H23: =INDEX(Monthly!$C$4:$BJ$4,($R$2-1)*12+1) -> 1 | I23: =INDEX(Monthly!$C$4:$BJ$4,($R$2-1)*12+2) -> 2 | J23: =INDEX(Monthly!$C$4:$BJ$4,($R$2-1)*12+3) -> 3 | K23: =INDEX(Monthly!$C$4:$BJ$4,($R$2-1)*12+4) -> 4 | L23: =INDEX(Monthly!$C$4:$BJ$4,($R$2-1)*12+5) -> 5 | M23: =INDEX(Monthly!$C$4:$BJ$4,($R$2-1)*12+6) -> 6 | N23: =INDEX(Monthly!$C$4:$BJ$4,($R$2-1)*12+7) -> 7 | O23: =INDEX(Monthly!$C$4:$BJ$4,($R$2-1)*12+8) -> 8 | P23: =INDEX(Monthly!$C$4:$BJ$4,($R$2-1)*12+9) -> 9 | Q23: =INDEX(Monthly!$C$4:$BJ$4,($R$2-1)*12+10) -> 10 | R23: =INDEX(Monthly!$C$4:$BJ$4,($R$2-1)*12+11) -> 11 | S23: =INDEX(Monthly!$C$4:$BJ$4,($R$2-1)*12+12) -> 12
A24: Operating cash flow | B24: ='Cash Flow'!B10 -> 48669.41 | C24: ='Cash Flow'!C10 -> 52421.419 | D24: ='Cash Flow'!D10 -> 57253.699 | E24: ='Cash Flow'!E10 -> 62266.382 | F24: ='Cash Flow'!F10 -> 67264.401 | H24: =INDEX(Monthly!$C$65:$BJ$65,($R$2-1)*12+1) -> 4879.5 | I24: =INDEX(Monthly!$C$65:$BJ$65,($R$2-1)*12+2) -> 3950.8761 | J24: =INDEX(Monthly!$C$65:$BJ$65,($R$2-1)*12+3) -> 3956.784 | K24: =INDEX(Monthly!$C$65:$BJ$65,($R$2-1)*12+4) -> 3962.7239 | L24: =INDEX(Monthly!$C$65:$BJ$65,($R$2-1)*12+5) -> 3968.696 | M24: =INDEX(Monthly!$C$65:$BJ$65,($R$2-1)*12+6) -> 3974.7005 | N24: =INDEX(Monthly!$C$65:$BJ$65,($R$2-1)*12+7) -> 3980.7374 | O24: =INDEX(Monthly!$C$65:$BJ$65,($R$2-1)*12+8) -> 3986.8071 | P24: =INDEX(Monthly!$C$65:$BJ$65,($R$2-1)*12+9) -> 3992.9096 | Q24: =INDEX(Monthly!$C$65:$BJ$65,($R$2-1)*12+10) -> 3999.0452 | R24: =INDEX(Monthly!$C$65:$BJ$65,($R$2-1)*12+11) -> 4005.2141 | S24: =INDEX(Monthly!$C$65:$BJ$65,($R$2-1)*12+12) -> 4011.4163
A25: Capital spending | B25: ='Cash Flow'!B11 -> -1909000 | C25: ='Cash Flow'!C11 -> -3605 | D25: ='Cash Flow'!D11 -> -3713.15 | E25: ='Cash Flow'!E11 -> -3824.5445 | F25: ='Cash Flow'!F11 -> -3939.2808 | H25: =INDEX(Monthly!$C$66:$BJ$66,($R$2-1)*12+1) -> -1905791.7 | I25: =INDEX(Monthly!$C$66:$BJ$66,($R$2-1)*12+2) -> -291.66667 | J25: =INDEX(Monthly!$C$66:$BJ$66,($R$2-1)*12+3) -> -291.66667 | K25: =INDEX(Monthly!$C$66:$BJ$66,($R$2-1)*12+4) -> -291.66667 | L25: =INDEX(Monthly!$C$66:$BJ$66,($R$2-1)*12+5) -> -291.66667 | M25: =INDEX(Monthly!$C$66:$BJ$66,($R$2-1)*12+6) -> -291.66667 | N25: =INDEX(Monthly!$C$66:$BJ$66,($R$2-1)*12+7) -> -291.66667 | O25: =INDEX(Monthly!$C$66:$BJ$66,($R$2-1)*12+8) -> -291.66667 | P25: =INDEX(Monthly!$C$66:$BJ$66,($R$2-1)*12+9) -> -291.66667 | Q25: =INDEX(Monthly!$C$66:$BJ$66,($R$2-1)*12+10) -> -291.66667 | R25: =INDEX(Monthly!$C$66:$BJ$66,($R$2-1)*12+11) -> -291.66667 | S25: =INDEX(Monthly!$C$66:$BJ$66,($R$2-1)*12+12) -> -291.66667
A26: Equity raised | B26: ='Cash Flow'!B12 -> 760000 | C26: ='Cash Flow'!C12 -> 0 | D26: ='Cash Flow'!D12 -> 0 | E26: ='Cash Flow'!E12 -> 0 | F26: ='Cash Flow'!F12 -> 0 | H26: =INDEX(Monthly!$C$67:$BJ$67,($R$2-1)*12+1) -> 760000 | I26: =INDEX(Monthly!$C$67:$BJ$67,($R$2-1)*12+2) -> 0 | J26: =INDEX(Monthly!$C$67:$BJ$67,($R$2-1)*12+3) -> 0 | K26: =INDEX(Monthly!$C$67:$BJ$67,($R$2-1)*12+4) -> 0 | L26: =INDEX(Monthly!$C$67:$BJ$67,($R$2-1)*12+5) -> 0 | M26: =INDEX(Monthly!$C$67:$BJ$67,($R$2-1)*12+6) -> 0 | N26: =INDEX(Monthly!$C$67:$BJ$67,($R$2-1)*12+7) -> 0 | O26: =INDEX(Monthly!$C$67:$BJ$67,($R$2-1)*12+8) -> 0 | P26: =INDEX(Monthly!$C$67:$BJ$67,($R$2-1)*12+9) -> 0 | Q26: =INDEX(Monthly!$C$67:$BJ$67,($R$2-1)*12+10) -> 0 | R26: =INDEX(Monthly!$C$67:$BJ$67,($R$2-1)*12+11) -> 0 | S26: =INDEX(Monthly!$C$67:$BJ$67,($R$2-1)*12+12) -> 0
A27: Loan drawdown | B27: ='Cash Flow'!B13 -> 1200000 | C27: ='Cash Flow'!C13 -> 0 | D27: ='Cash Flow'!D13 -> 0 | E27: ='Cash Flow'!E13 -> 0 | F27: ='Cash Flow'!F13 -> 0 | H27: =INDEX(Monthly!$C$50:$BJ$50,($R$2-1)*12+1) -> 1200000 | I27: =INDEX(Monthly!$C$50:$BJ$50,($R$2-1)*12+2) -> 0 | J27: =INDEX(Monthly!$C$50:$BJ$50,($R$2-1)*12+3) -> 0 | K27: =INDEX(Monthly!$C$50:$BJ$50,($R$2-1)*12+4) -> 0 | L27: =INDEX(Monthly!$C$50:$BJ$50,($R$2-1)*12+5) -> 0 | M27: =INDEX(Monthly!$C$50:$BJ$50,($R$2-1)*12+6) -> 0 | N27: =INDEX(Monthly!$C$50:$BJ$50,($R$2-1)*12+7) -> 0 | O27: =INDEX(Monthly!$C$50:$BJ$50,($R$2-1)*12+8) -> 0 | P27: =INDEX(Monthly!$C$50:$BJ$50,($R$2-1)*12+9) -> 0 | Q27: =INDEX(Monthly!$C$50:$BJ$50,($R$2-1)*12+10) -> 0 | R27: =INDEX(Monthly!$C$50:$BJ$50,($R$2-1)*12+11) -> 0 | S27: =INDEX(Monthly!$C$50:$BJ$50,($R$2-1)*12+12) -> 0
A28: Loan repayment | B28: ='Cash Flow'!B14 -> -13412.706 | C28: ='Cash Flow'!C14 -> -14310.979 | D28: ='Cash Flow'!D14 -> -15269.412 | E28: ='Cash Flow'!E14 -> -16292.033 | F28: ='Cash Flow'!F14 -> -17383.141 | H28: =INDEX(Monthly!$C$52:$BJ$52,($R$2-1)*12+1) -> -1084.8163 | I28: =INDEX(Monthly!$C$52:$BJ$52,($R$2-1)*12+2) -> -1090.6924 | J28: =INDEX(Monthly!$C$52:$BJ$52,($R$2-1)*12+3) -> -1096.6003 | K28: =INDEX(Monthly!$C$52:$BJ$52,($R$2-1)*12+4) -> -1102.5402 | L28: =INDEX(Monthly!$C$52:$BJ$52,($R$2-1)*12+5) -> -1108.5123 | M28: =INDEX(Monthly!$C$52:$BJ$52,($R$2-1)*12+6) -> -1114.5167 | N28: =INDEX(Monthly!$C$52:$BJ$52,($R$2-1)*12+7) -> -1120.5537 | O28: =INDEX(Monthly!$C$52:$BJ$52,($R$2-1)*12+8) -> -1126.6234 | P28: =INDEX(Monthly!$C$52:$BJ$52,($R$2-1)*12+9) -> -1132.7259 | Q28: =INDEX(Monthly!$C$52:$BJ$52,($R$2-1)*12+10) -> -1138.8615 | R28: =INDEX(Monthly!$C$52:$BJ$52,($R$2-1)*12+11) -> -1145.0303 | S28: =INDEX(Monthly!$C$52:$BJ$52,($R$2-1)*12+12) -> -1151.2326
A29: Financing cash flow | B29: ='Cash Flow'!B15 -> 1946587.3 | C29: ='Cash Flow'!C15 -> -14310.979 | D29: ='Cash Flow'!D15 -> -15269.412 | E29: ='Cash Flow'!E15 -> -16292.033 | F29: ='Cash Flow'!F15 -> -17383.141 | H29: =INDEX(Monthly!$C$68:$BJ$68,($R$2-1)*12+1) -> 1958915.2 | I29: =INDEX(Monthly!$C$68:$BJ$68,($R$2-1)*12+2) -> -1090.6924 | J29: =INDEX(Monthly!$C$68:$BJ$68,($R$2-1)*12+3) -> -1096.6003 | K29: =INDEX(Monthly!$C$68:$BJ$68,($R$2-1)*12+4) -> -1102.5402 | L29: =INDEX(Monthly!$C$68:$BJ$68,($R$2-1)*12+5) -> -1108.5123 | M29: =INDEX(Monthly!$C$68:$BJ$68,($R$2-1)*12+6) -> -1114.5167 | N29: =INDEX(Monthly!$C$68:$BJ$68,($R$2-1)*12+7) -> -1120.5537 | O29: =INDEX(Monthly!$C$68:$BJ$68,($R$2-1)*12+8) -> -1126.6234 | P29: =INDEX(Monthly!$C$68:$BJ$68,($R$2-1)*12+9) -> -1132.7259 | Q29: =INDEX(Monthly!$C$68:$BJ$68,($R$2-1)*12+10) -> -1138.8615 | R29: =INDEX(Monthly!$C$68:$BJ$68,($R$2-1)*12+11) -> -1145.0303 | S29: =INDEX(Monthly!$C$68:$BJ$68,($R$2-1)*12+12) -> -1151.2326
A30: Net change in cash | B30: ='Cash Flow'!B16 -> 86256.705 | C30: ='Cash Flow'!C16 -> 34505.44 | D30: ='Cash Flow'!D16 -> 38271.137 | E30: ='Cash Flow'!E16 -> 42149.805 | F30: ='Cash Flow'!F16 -> 45941.98 | H30: =INDEX(Monthly!$C$69:$BJ$69,($R$2-1)*12+1) -> 58003.017 | I30: =INDEX(Monthly!$C$69:$BJ$69,($R$2-1)*12+2) -> 2568.5171 | J30: =INDEX(Monthly!$C$69:$BJ$69,($R$2-1)*12+3) -> 2568.5171 | K30: =INDEX(Monthly!$C$69:$BJ$69,($R$2-1)*12+4) -> 2568.5171 | L30: =INDEX(Monthly!$C$69:$BJ$69,($R$2-1)*12+5) -> 2568.5171 | M30: =INDEX(Monthly!$C$69:$BJ$69,($R$2-1)*12+6) -> 2568.5171 | N30: =INDEX(Monthly!$C$69:$BJ$69,($R$2-1)*12+7) -> 2568.5171 | O30: =INDEX(Monthly!$C$69:$BJ$69,($R$2-1)*12+8) -> 2568.5171 | P30: =INDEX(Monthly!$C$69:$BJ$69,($R$2-1)*12+9) -> 2568.5171 | Q30: =INDEX(Monthly!$C$69:$BJ$69,($R$2-1)*12+10) -> 2568.5171 | R30: =INDEX(Monthly!$C$69:$BJ$69,($R$2-1)*12+11) -> 2568.5171 | S30: =INDEX(Monthly!$C$69:$BJ$69,($R$2-1)*12+12) -> 2568.5171
A31: Closing cash | B31: ='Cash Flow'!B18 -> 86256.705 | C31: ='Cash Flow'!C18 -> 120762.14 | D31: ='Cash Flow'!D18 -> 159033.28 | E31: ='Cash Flow'!E18 -> 201183.09 | F31: ='Cash Flow'!F18 -> 247125.07 | H31: =INDEX(Monthly!$C$71:$BJ$71,($R$2-1)*12+1) -> 58003.017 | I31: =INDEX(Monthly!$C$71:$BJ$71,($R$2-1)*12+2) -> 60571.534 | J31: =INDEX(Monthly!$C$71:$BJ$71,($R$2-1)*12+3) -> 63140.051 | K31: =INDEX(Monthly!$C$71:$BJ$71,($R$2-1)*12+4) -> 65708.568 | L31: =INDEX(Monthly!$C$71:$BJ$71,($R$2-1)*12+5) -> 68277.085 | M31: =INDEX(Monthly!$C$71:$BJ$71,($R$2-1)*12+6) -> 70845.602 | N31: =INDEX(Monthly!$C$71:$BJ$71,($R$2-1)*12+7) -> 73414.119 | O31: =INDEX(Monthly!$C$71:$BJ$71,($R$2-1)*12+8) -> 75982.636 | P31: =INDEX(Monthly!$C$71:$BJ$71,($R$2-1)*12+9) -> 78551.153 | Q31: =INDEX(Monthly!$C$71:$BJ$71,($R$2-1)*12+10) -> 81119.671 | R31: =INDEX(Monthly!$C$71:$BJ$71,($R$2-1)*12+11) -> 83688.188 | S31: =INDEX(Monthly!$C$71:$BJ$71,($R$2-1)*12+12) -> 86256.705
A39: Balance sheet at year end ($'000) | H39: ="Balance sheet at month end ($'000) — Year "&$R$2 -> Balance sheet at month end ($'000) — Year 1
B40: 1 | C40: 2 | D40: 3 | E40: 4 | F40: 5 | H40: =INDEX(Monthly!$C$4:$BJ$4,($R$2-1)*12+1) -> 1 | I40: =INDEX(Monthly!$C$4:$BJ$4,($R$2-1)*12+2) -> 2 | J40: =INDEX(Monthly!$C$4:$BJ$4,($R$2-1)*12+3) -> 3 | K40: =INDEX(Monthly!$C$4:$BJ$4,($R$2-1)*12+4) -> 4 | L40: =INDEX(Monthly!$C$4:$BJ$4,($R$2-1)*12+5) -> 5 | M40: =INDEX(Monthly!$C$4:$BJ$4,($R$2-1)*12+6) -> 6 | N40: =INDEX(Monthly!$C$4:$BJ$4,($R$2-1)*12+7) -> 7 | O40: =INDEX(Monthly!$C$4:$BJ$4,($R$2-1)*12+8) -> 8 | P40: =INDEX(Monthly!$C$4:$BJ$4,($R$2-1)*12+9) -> 9 | Q40: =INDEX(Monthly!$C$4:$BJ$4,($R$2-1)*12+10) -> 10 | R40: =INDEX(Monthly!$C$4:$BJ$4,($R$2-1)*12+11) -> 11 | S40: =INDEX(Monthly!$C$4:$BJ$4,($R$2-1)*12+12) -> 12
A41: Cash | B41: ='Balance Sheet'!B5 -> 86256.705 | C41: ='Balance Sheet'!C5 -> 120762.14 | D41: ='Balance Sheet'!D5 -> 159033.28 | E41: ='Balance Sheet'!E5 -> 201183.09 | F41: ='Balance Sheet'!F5 -> 247125.07 | H41: =INDEX(Monthly!$C$71:$BJ$71,($R$2-1)*12+1) -> 58003.017 | I41: =INDEX(Monthly!$C$71:$BJ$71,($R$2-1)*12+2) -> 60571.534 | J41: =INDEX(Monthly!$C$71:$BJ$71,($R$2-1)*12+3) -> 63140.051 | K41: =INDEX(Monthly!$C$71:$BJ$71,($R$2-1)*12+4) -> 65708.568 | L41: =INDEX(Monthly!$C$71:$BJ$71,($R$2-1)*12+5) -> 68277.085 | M41: =INDEX(Monthly!$C$71:$BJ$71,($R$2-1)*12+6) -> 70845.602 | N41: =INDEX(Monthly!$C$71:$BJ$71,($R$2-1)*12+7) -> 73414.119 | O41: =INDEX(Monthly!$C$71:$BJ$71,($R$2-1)*12+8) -> 75982.636 | P41: =INDEX(Monthly!$C$71:$BJ$71,($R$2-1)*12+9) -> 78551.153 | Q41: =INDEX(Monthly!$C$71:$BJ$71,($R$2-1)*12+10) -> 81119.671 | R41: =INDEX(Monthly!$C$71:$BJ$71,($R$2-1)*12+11) -> 83688.188 | S41: =INDEX(Monthly!$C$71:$BJ$71,($R$2-1)*12+12) -> 86256.705
A42: Accounts receivable | B42: ='Balance Sheet'!B6 -> 0 | C42: ='Balance Sheet'!C6 -> 0 | D42: ='Balance Sheet'!D6 -> 0 | E42: ='Balance Sheet'!E6 -> 0 | F42: ='Balance Sheet'!F6 -> 0 | H42: =INDEX(Monthly!$C$57:$BJ$57,($R$2-1)*12+1) -> 0 | I42: =INDEX(Monthly!$C$57:$BJ$57,($R$2-1)*12+2) -> 0 | J42: =INDEX(Monthly!$C$57:$BJ$57,($R$2-1)*12+3) -> 0 | K42: =INDEX(Monthly!$C$57:$BJ$57,($R$2-1)*12+4) -> 0 | L42: =INDEX(Monthly!$C$57:$BJ$57,($R$2-1)*12+5) -> 0 | M42: =INDEX(Monthly!$C$57:$BJ$57,($R$2-1)*12+6) -> 0 | N42: =INDEX(Monthly!$C$57:$BJ$57,($R$2-1)*12+7) -> 0 | O42: =INDEX(Monthly!$C$57:$BJ$57,($R$2-1)*12+8) -> 0 | P42: =INDEX(Monthly!$C$57:$BJ$57,($R$2-1)*12+9) -> 0 | Q42: =INDEX(Monthly!$C$57:$BJ$57,($R$2-1)*12+10) -> 0 | R42: =INDEX(Monthly!$C$57:$BJ$57,($R$2-1)*12+11) -> 0 | S42: =INDEX(Monthly!$C$57:$BJ$57,($R$2-1)*12+12) -> 0
A43: Inventory | B43: ='Balance Sheet'!B7 -> 0 | C43: ='Balance Sheet'!C7 -> 0 | D43: ='Balance Sheet'!D7 -> 0 | E43: ='Balance Sheet'!E7 -> 0 | F43: ='Balance Sheet'!F7 -> 0 | H43: =INDEX(Monthly!$C$58:$BJ$58,($R$2-1)*12+1) -> 0 | I43: =INDEX(Monthly!$C$58:$BJ$58,($R$2-1)*12+2) -> 0 | J43: =INDEX(Monthly!$C$58:$BJ$58,($R$2-1)*12+3) -> 0 | K43: =INDEX(Monthly!$C$58:$BJ$58,($R$2-1)*12+4) -> 0 | L43: =INDEX(Monthly!$C$58:$BJ$58,($R$2-1)*12+5) -> 0 | M43: =INDEX(Monthly!$C$58:$BJ$58,($R$2-1)*12+6) -> 0 | N43: =INDEX(Monthly!$C$58:$BJ$58,($R$2-1)*12+7) -> 0 | O43: =INDEX(Monthly!$C$58:$BJ$58,($R$2-1)*12+8) -> 0 | P43: =INDEX(Monthly!$C$58:$BJ$58,($R$2-1)*12+9) -> 0 | Q43: =INDEX(Monthly!$C$58:$BJ$58,($R$2-1)*12+10) -> 0 | R43: =INDEX(Monthly!$C$58:$BJ$58,($R$2-1)*12+11) -> 0 | S43: =INDEX(Monthly!$C$58:$BJ$58,($R$2-1)*12+12) -> 0
A44: Net fixed assets | B44: ='Balance Sheet'!B8 -> 1852059.4 | C44: ='Balance Sheet'!C8 -> 1798592.1 | D44: ='Balance Sheet'!D8 -> 1745097.2 | E44: ='Balance Sheet'!E8 -> 1691574 | F44: ='Balance Sheet'!F8 -> 1638021.6 | H44: =INDEX(Monthly!$C$46:$BJ$46,($R$2-1)*12+1) -> 1901051.6 | I44: =INDEX(Monthly!$C$46:$BJ$46,($R$2-1)*12+2) -> 1896602.2 | J44: =INDEX(Monthly!$C$46:$BJ$46,($R$2-1)*12+3) -> 1892152 | K44: =INDEX(Monthly!$C$46:$BJ$46,($R$2-1)*12+4) -> 1887700.9 | L44: =INDEX(Monthly!$C$46:$BJ$46,($R$2-1)*12+5) -> 1883248.8 | M44: =INDEX(Monthly!$C$46:$BJ$46,($R$2-1)*12+6) -> 1878795.9 | N44: =INDEX(Monthly!$C$46:$BJ$46,($R$2-1)*12+7) -> 1874342.1 | O44: =INDEX(Monthly!$C$46:$BJ$46,($R$2-1)*12+8) -> 1869887.3 | P44: =INDEX(Monthly!$C$46:$BJ$46,($R$2-1)*12+9) -> 1865431.7 | Q44: =INDEX(Monthly!$C$46:$BJ$46,($R$2-1)*12+10) -> 1860975.2 | R44: =INDEX(Monthly!$C$46:$BJ$46,($R$2-1)*12+11) -> 1856517.7 | S44: =INDEX(Monthly!$C$46:$BJ$46,($R$2-1)*12+12) -> 1852059.4
A45: Total assets | B45: ='Balance Sheet'!B9 -> 1938316.1 | C45: ='Balance Sheet'!C9 -> 1919354.2 | D45: ='Balance Sheet'!D9 -> 1904130.5 | E45: ='Balance Sheet'!E9 -> 1892757.1 | F45: ='Balance Sheet'!F9 -> 1885146.6 | H45: =INDEX(Monthly!$C$85:$BJ$85,($R$2-1)*12+1) -> 1959054.6 | I45: =INDEX(Monthly!$C$85:$BJ$85,($R$2-1)*12+2) -> 1957173.8 | J45: =INDEX(Monthly!$C$85:$BJ$85,($R$2-1)*12+3) -> 1955292.1 | K45: =INDEX(Monthly!$C$85:$BJ$85,($R$2-1)*12+4) -> 1953409.4 | L45: =INDEX(Monthly!$C$85:$BJ$85,($R$2-1)*12+5) -> 1951525.9 | M45: =INDEX(Monthly!$C$85:$BJ$85,($R$2-1)*12+6) -> 1949641.5 | N45: =INDEX(Monthly!$C$85:$BJ$85,($R$2-1)*12+7) -> 1947756.2 | O45: =INDEX(Monthly!$C$85:$BJ$85,($R$2-1)*12+8) -> 1945870 | P45: =INDEX(Monthly!$C$85:$BJ$85,($R$2-1)*12+9) -> 1943982.9 | Q45: =INDEX(Monthly!$C$85:$BJ$85,($R$2-1)*12+10) -> 1942094.9 | R45: =INDEX(Monthly!$C$85:$BJ$85,($R$2-1)*12+11) -> 1940205.9 | S45: =INDEX(Monthly!$C$85:$BJ$85,($R$2-1)*12+12) -> 1938316.1
A46: Accounts payable | B46: ='Balance Sheet'!B10 -> 934.5 | C46: ='Balance Sheet'!C10 -> 962.535 | D46: ='Balance Sheet'!D10 -> 991.41105 | E46: ='Balance Sheet'!E10 -> 1021.1534 | F46: ='Balance Sheet'!F10 -> 1051.788 | H46: =INDEX(Monthly!$C$59:$BJ$59,($R$2-1)*12+1) -> 934.5 | I46: =INDEX(Monthly!$C$59:$BJ$59,($R$2-1)*12+2) -> 934.5 | J46: =INDEX(Monthly!$C$59:$BJ$59,($R$2-1)*12+3) -> 934.5 | K46: =INDEX(Monthly!$C$59:$BJ$59,($R$2-1)*12+4) -> 934.5 | L46: =INDEX(Monthly!$C$59:$BJ$59,($R$2-1)*12+5) -> 934.5 | M46: =INDEX(Monthly!$C$59:$BJ$59,($R$2-1)*12+6) -> 934.5 | N46: =INDEX(Monthly!$C$59:$BJ$59,($R$2-1)*12+7) -> 934.5 | O46: =INDEX(Monthly!$C$59:$BJ$59,($R$2-1)*12+8) -> 934.5 | P46: =INDEX(Monthly!$C$59:$BJ$59,($R$2-1)*12+9) -> 934.5 | Q46: =INDEX(Monthly!$C$59:$BJ$59,($R$2-1)*12+10) -> 934.5 | R46: =INDEX(Monthly!$C$59:$BJ$59,($R$2-1)*12+11) -> 934.5 | S46: =INDEX(Monthly!$C$59:$BJ$59,($R$2-1)*12+12) -> 934.5
A47: Loan | B47: ='Balance Sheet'!B11 -> 1186587.3 | C47: ='Balance Sheet'!C11 -> 1172276.3 | D47: ='Balance Sheet'!D11 -> 1157006.9 | E47: ='Balance Sheet'!E11 -> 1140714.9 | F47: ='Balance Sheet'!F11 -> 1123331.7 | H47: =INDEX(Monthly!$C$54:$BJ$54,($R$2-1)*12+1) -> 1198915.2 | I47: =INDEX(Monthly!$C$54:$BJ$54,($R$2-1)*12+2) -> 1197824.5 | J47: =INDEX(Monthly!$C$54:$BJ$54,($R$2-1)*12+3) -> 1196727.9 | K47: =INDEX(Monthly!$C$54:$BJ$54,($R$2-1)*12+4) -> 1195625.4 | L47: =INDEX(Monthly!$C$54:$BJ$54,($R$2-1)*12+5) -> 1194516.8 | M47: =INDEX(Monthly!$C$54:$BJ$54,($R$2-1)*12+6) -> 1193402.3 | N47: =INDEX(Monthly!$C$54:$BJ$54,($R$2-1)*12+7) -> 1192281.8 | O47: =INDEX(Monthly!$C$54:$BJ$54,($R$2-1)*12+8) -> 1191155.1 | P47: =INDEX(Monthly!$C$54:$BJ$54,($R$2-1)*12+9) -> 1190022.4 | Q47: =INDEX(Monthly!$C$54:$BJ$54,($R$2-1)*12+10) -> 1188883.6 | R47: =INDEX(Monthly!$C$54:$BJ$54,($R$2-1)*12+11) -> 1187738.5 | S47: =INDEX(Monthly!$C$54:$BJ$54,($R$2-1)*12+12) -> 1186587.3
A48: Total liabilities | B48: ='Balance Sheet'!B12 -> 1187521.8 | C48: ='Balance Sheet'!C12 -> 1173238.9 | D48: ='Balance Sheet'!D12 -> 1157998.3 | E48: ='Balance Sheet'!E12 -> 1141736 | F48: ='Balance Sheet'!F12 -> 1124383.5 | H48: =INDEX(Monthly!$C$86:$BJ$86,($R$2-1)*12+1) -> 1199849.7 | I48: =INDEX(Monthly!$C$86:$BJ$86,($R$2-1)*12+2) -> 1198759 | J48: =INDEX(Monthly!$C$86:$BJ$86,($R$2-1)*12+3) -> 1197662.4 | K48: =INDEX(Monthly!$C$86:$BJ$86,($R$2-1)*12+4) -> 1196559.9 | L48: =INDEX(Monthly!$C$86:$BJ$86,($R$2-1)*12+5) -> 1195451.3 | M48: =INDEX(Monthly!$C$86:$BJ$86,($R$2-1)*12+6) -> 1194336.8 | N48: =INDEX(Monthly!$C$86:$BJ$86,($R$2-1)*12+7) -> 1193216.3 | O48: =INDEX(Monthly!$C$86:$BJ$86,($R$2-1)*12+8) -> 1192089.6 | P48: =INDEX(Monthly!$C$86:$BJ$86,($R$2-1)*12+9) -> 1190956.9 | Q48: =INDEX(Monthly!$C$86:$BJ$86,($R$2-1)*12+10) -> 1189818.1 | R48: =INDEX(Monthly!$C$86:$BJ$86,($R$2-1)*12+11) -> 1188673 | S48: =INDEX(Monthly!$C$86:$BJ$86,($R$2-1)*12+12) -> 1187521.8
A49: Paid-in capital | B49: ='Balance Sheet'!B13 -> 760000 | C49: ='Balance Sheet'!C13 -> 760000 | D49: ='Balance Sheet'!D13 -> 760000 | E49: ='Balance Sheet'!E13 -> 760000 | F49: ='Balance Sheet'!F13 -> 760000 | H49: =INDEX(Monthly!$C$83:$BJ$83,($R$2-1)*12+1) -> 760000 | I49: =INDEX(Monthly!$C$83:$BJ$83,($R$2-1)*12+2) -> 760000 | J49: =INDEX(Monthly!$C$83:$BJ$83,($R$2-1)*12+3) -> 760000 | K49: =INDEX(Monthly!$C$83:$BJ$83,($R$2-1)*12+4) -> 760000 | L49: =INDEX(Monthly!$C$83:$BJ$83,($R$2-1)*12+5) -> 760000 | M49: =INDEX(Monthly!$C$83:$BJ$83,($R$2-1)*12+6) -> 760000 | N49: =INDEX(Monthly!$C$83:$BJ$83,($R$2-1)*12+7) -> 760000 | O49: =INDEX(Monthly!$C$83:$BJ$83,($R$2-1)*12+8) -> 760000 | P49: =INDEX(Monthly!$C$83:$BJ$83,($R$2-1)*12+9) -> 760000 | Q49: =INDEX(Monthly!$C$83:$BJ$83,($R$2-1)*12+10) -> 760000 | R49: =INDEX(Monthly!$C$83:$BJ$83,($R$2-1)*12+11) -> 760000 | S49: =INDEX(Monthly!$C$83:$BJ$83,($R$2-1)*12+12) -> 760000
A50: Retained earnings | B50: ='Balance Sheet'!B14 -> -9205.6762 | C50: ='Balance Sheet'!C14 -> -13884.615 | D50: ='Balance Sheet'!D14 -> -13867.803 | E50: ='Balance Sheet'!E14 -> -8978.9325 | F50: ='Balance Sheet'!F14 -> 763.11298 | H50: =INDEX(Monthly!$C$84:$BJ$84,($R$2-1)*12+1) -> -795.09774 | I50: =INDEX(Monthly!$C$84:$BJ$84,($R$2-1)*12+2) -> -1585.2196 | J50: =INDEX(Monthly!$C$84:$BJ$84,($R$2-1)*12+3) -> -2370.3337 | K50: =INDEX(Monthly!$C$84:$BJ$84,($R$2-1)*12+4) -> -3150.4082 | L50: =INDEX(Monthly!$C$84:$BJ$84,($R$2-1)*12+5) -> -3925.4107 | M50: =INDEX(Monthly!$C$84:$BJ$84,($R$2-1)*12+6) -> -4695.309 | N50: =INDEX(Monthly!$C$84:$BJ$84,($R$2-1)*12+7) -> -5460.0706 | O50: =INDEX(Monthly!$C$84:$BJ$84,($R$2-1)*12+8) -> -6219.6627 | P50: =INDEX(Monthly!$C$84:$BJ$84,($R$2-1)*12+9) -> -6974.0524 | Q50: =INDEX(Monthly!$C$84:$BJ$84,($R$2-1)*12+10) -> -7723.2068 | R50: =INDEX(Monthly!$C$84:$BJ$84,($R$2-1)*12+11) -> -8467.0925 | S50: =INDEX(Monthly!$C$84:$BJ$84,($R$2-1)*12+12) -> -9205.6762
A51: Total equity | B51: ='Balance Sheet'!B15 -> 750794.32 | C51: ='Balance Sheet'!C15 -> 746115.39 | D51: ='Balance Sheet'!D15 -> 746132.2 | E51: ='Balance Sheet'!E15 -> 751021.07 | F51: ='Balance Sheet'!F15 -> 760763.11 | H51: =INDEX(Monthly!$C$87:$BJ$87,($R$2-1)*12+1) -> 759204.9 | I51: =INDEX(Monthly!$C$87:$BJ$87,($R$2-1)*12+2) -> 758414.78 | J51: =INDEX(Monthly!$C$87:$BJ$87,($R$2-1)*12+3) -> 757629.67 | K51: =INDEX(Monthly!$C$87:$BJ$87,($R$2-1)*12+4) -> 756849.59 | L51: =INDEX(Monthly!$C$87:$BJ$87,($R$2-1)*12+5) -> 756074.59 | M51: =INDEX(Monthly!$C$87:$BJ$87,($R$2-1)*12+6) -> 755304.69 | N51: =INDEX(Monthly!$C$87:$BJ$87,($R$2-1)*12+7) -> 754539.93 | O51: =INDEX(Monthly!$C$87:$BJ$87,($R$2-1)*12+8) -> 753780.34 | P51: =INDEX(Monthly!$C$87:$BJ$87,($R$2-1)*12+9) -> 753025.95 | Q51: =INDEX(Monthly!$C$87:$BJ$87,($R$2-1)*12+10) -> 752276.79 | R51: =INDEX(Monthly!$C$87:$BJ$87,($R$2-1)*12+11) -> 751532.91 | S51: =INDEX(Monthly!$C$87:$BJ$87,($R$2-1)*12+12) -> 750794.32
A52: Total liabilities & equity | B52: ='Balance Sheet'!B16 -> 1938316.1 | C52: ='Balance Sheet'!C16 -> 1919354.2 | D52: ='Balance Sheet'!D16 -> 1904130.5 | E52: ='Balance Sheet'!E16 -> 1892757.1 | F52: ='Balance Sheet'!F16 -> 1885146.6 | H52: =INDEX(Monthly!$C$88:$BJ$88,($R$2-1)*12+1) -> 1959054.6 | I52: =INDEX(Monthly!$C$88:$BJ$88,($R$2-1)*12+2) -> 1957173.8 | J52: =INDEX(Monthly!$C$88:$BJ$88,($R$2-1)*12+3) -> 1955292.1 | K52: =INDEX(Monthly!$C$88:$BJ$88,($R$2-1)*12+4) -> 1953409.4 | L52: =INDEX(Monthly!$C$88:$BJ$88,($R$2-1)*12+5) -> 1951525.9 | M52: =INDEX(Monthly!$C$88:$BJ$88,($R$2-1)*12+6) -> 1949641.5 | N52: =INDEX(Monthly!$C$88:$BJ$88,($R$2-1)*12+7) -> 1947756.2 | O52: =INDEX(Monthly!$C$88:$BJ$88,($R$2-1)*12+8) -> 1945870 | P52: =INDEX(Monthly!$C$88:$BJ$88,($R$2-1)*12+9) -> 1943982.9 | Q52: =INDEX(Monthly!$C$88:$BJ$88,($R$2-1)*12+10) -> 1942094.9 | R52: =INDEX(Monthly!$C$88:$BJ$88,($R$2-1)*12+11) -> 1940205.9 | S52: =INDEX(Monthly!$C$88:$BJ$88,($R$2-1)*12+12) -> 1938316.1

Sheet Break-even
A1: Startup costs, funding need and break-even | H1: =HYPERLINK("#'Cover'!A1","◂ Contents") -> ◂ Contents
A2: Live for the selected scenario. Periods are counted in months from the start of the plan.
A3: Scenario shown | B3: =CHOOSE(Dashboard!$B$4,"Low","Base","High") -> Base
A5: Startup costs & funding need (up to the lowest cash point)
A6: Lowest cash point (month #) | B6: =MATCH(MIN(Monthly!$C$71:$BJ$71),Monthly!$C$71:$BJ$71,0) -> 1
A7: Capital spending up to the lowest cash point | B7: =SUMPRODUCT(--(Monthly!$C$4:$BJ$4<=$B$6),Monthly!$C$41:$BJ$41) -> 1905791.7
A8: Operating cash burn up to the lowest cash point | B8: =-SUMPRODUCT(--(Monthly!$C$4:$BJ$4<=$B$6),Monthly!$C$65:$BJ$65) -> -4879.5 | D8: Losses and working capital before the business funds itself
A9: Loan repayments up to the lowest cash point | B9: =-SUMPRODUCT(--(Monthly!$C$4:$BJ$4<=$B$6),Monthly!$C$52:$BJ$52) -> 1084.8163
A10: Total uses of funds | B10: =B7+B8+B9 -> 1901997
A11: Minimum cash buffer to keep | B11: =Inputs!$E$49 -> 12000 | D11: Input on the Inputs sheet
A12: Funding required (uses + buffer) | B12: =B10+B11 -> 1913997
A14: Equity raised | B14: =Inputs!$E$34 -> 760000
A15: Loan drawn | B15: =Inputs!$E$35 -> 1200000
A16: Total sources of funds | B16: =B14+B15 -> 1960000
A17: Funding surplus / (shortfall) | B17: =B16-B12 -> 46003.017 | D17: Negative = raise at least this much more
A18: Lowest cash balance in the plan | B18: =MIN(Monthly!$C$71:$BJ$71) -> 58003.017 | D18: Equals sources minus uses
A20: Break-even timing
A21: First month with positive EBITDA (month #) | B21: =IFERROR(MATCH(1,Monthly!$C$72:$BJ$72,0),"Not within horizon") -> 1
A22: First month with positive net income (month #) | B22: =IFERROR(MATCH(1,Monthly!$C$75:$BJ$75,0),"Not within horizon") -> 31
A23: Cash invested paid back (month #) | B23: =IF(MIN(Monthly!$C$77:$BJ$77)>=0,"No investment to pay back",IFERROR(MATCH(1,Monthly!$C$79:$BJ$79,0),"Not within horizon")) -> Not within horizon | D23: Cumulative operating + investing cash flow back to zero
A25: Annual break-even revenue
A26: Year # | B26: 1 | C26: 2 | D26: 3 | E26: 4 | F26: 5
B27: Year 1 | C27: Year 2 | D27: Year 3 | E27: Year 4 | F27: Year 5
A28: Revenue | B28: =SUMIF(Monthly!$C$5:$BJ$5,B$26,Monthly!$C$12:$BJ$12) -> 196650 | C28: =SUMIF(Monthly!$C$5:$BJ$5,C$26,Monthly!$C$12:$BJ$12) -> 202549.5 | D28: =SUMIF(Monthly!$C$5:$BJ$5,D$26,Monthly!$C$12:$BJ$12) -> 208625.98 | E28: =SUMIF(Monthly!$C$5:$BJ$5,E$26,Monthly!$C$12:$BJ$12) -> 214884.76 | F28: =SUMIF(Monthly!$C$5:$BJ$5,F$26,Monthly!$C$12:$BJ$12) -> 221331.31
A29: Gross profit | B29: =SUMIF(Monthly!$C$5:$BJ$5,B$26,Monthly!$C$18:$BJ$18) -> 174222 | C29: =SUMIF(Monthly!$C$5:$BJ$5,C$26,Monthly!$C$18:$BJ$18) -> 179448.66 | D29: =SUMIF(Monthly!$C$5:$BJ$5,D$26,Monthly!$C$18:$BJ$18) -> 184832.12 | E29: =SUMIF(Monthly!$C$5:$BJ$5,E$26,Monthly!$C$18:$BJ$18) -> 190377.08 | F29: =SUMIF(Monthly!$C$5:$BJ$5,F$26,Monthly!$C$18:$BJ$18) -> 196088.4
A30: Gross margin (contribution) | B30: =IF(B28=0,0,B29/B28) -> 0.88594966 | C30: =IF(C28=0,0,C29/C28) -> 0.88594966 | D30: =IF(D28=0,0,D29/D28) -> 0.88594966 | E30: =IF(E28=0,0,E29/E28) -> 0.88594966 | F30: =IF(F28=0,0,F29/F28) -> 0.88594966
A31: Operating expenses (treated as fixed) | B31: =-SUMIF(Monthly!$C$5:$BJ$5,B$26,Monthly!$C$25:$BJ$25) -> 48882 | C31: =-SUMIF(Monthly!$C$5:$BJ$5,C$26,Monthly!$C$25:$BJ$25) -> 50348.46 | D31: =-SUMIF(Monthly!$C$5:$BJ$5,D$26,Monthly!$C$25:$BJ$25) -> 51858.914 | E31: =-SUMIF(Monthly!$C$5:$BJ$5,E$26,Monthly!$C$25:$BJ$25) -> 53414.681 | F31: =-SUMIF(Monthly!$C$5:$BJ$5,F$26,Monthly!$C$25:$BJ$25) -> 55017.122
A32: Break-even revenue (EBITDA = 0) | B32: =IF(B30>0,B31/B30,"n/a") -> 55174.693 | C32: =IF(C30>0,C31/C30,"n/a") -> 56829.933 | D32: =IF(D30>0,D31/D30,"n/a") -> 58534.831 | E32: =IF(E30>0,E31/E30,"n/a") -> 60290.876 | F32: =IF(F30>0,F31/F30,"n/a") -> 62099.603
A33: Margin of safety (revenue above break-even) | B33: =IF(AND(ISNUMBER(B32),B28>0),(B28-B32)/B28,"n/a") -> 0.71942694 | C33: =IF(AND(ISNUMBER(C32),C28>0),(C28-C32)/C28,"n/a") -> 0.71942694 | D33: =IF(AND(ISNUMBER(D32),D28>0),(D28-D32)/D28,"n/a") -> 0.71942694 | E33: =IF(AND(ISNUMBER(E32),E28>0),(E28-E32)/E28,"n/a") -> 0.71942694 | F33: =IF(AND(ISNUMBER(F32),F28>0),(F28-F32)/F28,"n/a") -> 0.71942694
A35: Simplification: cost of sales is treated as variable and operating expenses as fixed, so break-even revenue = operating expenses ÷ gross margin.

Sheet Valuation
A1: Discounted cash flow valuation | H1: =HYPERLINK("#'Cover'!A1","◂ Contents") -> ◂ Contents
A2: Enterprise value at the start of the plan, before the funding raised in period 1. Year-end discounting.
A3: Scenario shown | B3: =CHOOSE(Dashboard!$B$4,"Low","Base","High") -> Base
A5: Assumptions (active scenario, from the Inputs sheet)
A6: Discount rate (WACC) | B6: =Inputs!$E$52 -> 0.2
A7: Terminal growth rate | B7: =Inputs!$E$53 -> 0.02
A8: Exit multiple (EV ÷ final-year EBITDA) | B8: =Inputs!$E$54 -> 4.5
A9: Tax rate (for the interest tax shield) | B9: =Inputs!$E$46 -> 0.21
A10: Sensitivity step: WACC | B10: =Inputs!$E$55 -> 0.01
A11: Sensitivity step: terminal growth | B11: =Inputs!$E$56 -> 0.005
A13: Free cash flow by year
A14: Year # | B14: 1 | C14: 2 | D14: 3 | E14: 4 | F14: 5
B15: Year 1 | C15: Year 2 | D15: Year 3 | E15: Year 4 | F15: Year 5
A16: EBITDA | B16: =SUMIF(Monthly!$C$5:$BJ$5,B$14,Monthly!$C$26:$BJ$26) -> 125340 | C16: =SUMIF(Monthly!$C$5:$BJ$5,C$14,Monthly!$C$26:$BJ$26) -> 129100.2 | D16: =SUMIF(Monthly!$C$5:$BJ$5,D$14,Monthly!$C$26:$BJ$26) -> 132973.21 | E16: =SUMIF(Monthly!$C$5:$BJ$5,E$14,Monthly!$C$26:$BJ$26) -> 136962.4 | F16: =SUMIF(Monthly!$C$5:$BJ$5,F$14,Monthly!$C$26:$BJ$26) -> 141071.27
A17: Unlevered free cash flow | B17: =SUMIF(Monthly!$C$5:$BJ$5,B$14,Monthly!$C$80:$BJ$80) -> -1799022.6 | C17: =SUMIF(Monthly!$C$5:$BJ$5,C$14,Monthly!$C$80:$BJ$80) -> 109414.8 | D17: =SUMIF(Monthly!$C$5:$BJ$5,D$14,Monthly!$C$80:$BJ$80) -> 113381.77 | E17: =SUMIF(Monthly!$C$5:$BJ$5,E$14,Monthly!$C$80:$BJ$80) -> 117475.19 | F17: =SUMIF(Monthly!$C$5:$BJ$5,F$14,Monthly!$C$80:$BJ$80) -> 121496.5
A18: Discount factor | B18: =1/(1+Inputs!$E$52)^B$14 -> 0.83333333 | C18: =1/(1+Inputs!$E$52)^C$14 -> 0.69444444 | D18: =1/(1+Inputs!$E$52)^D$14 -> 0.5787037 | E18: =1/(1+Inputs!$E$52)^E$14 -> 0.48225309 | F18: =1/(1+Inputs!$E$52)^F$14 -> 0.40187757
A19: Present value of free cash flow | B19: =B17*B18 -> -1499185.5 | C19: =C17*C18 -> 75982.503 | D19: =D17*D18 -> 65614.451 | E19: =E17*E18 -> 56652.773 | F19: =F17*F18 -> 48826.717
A21: Enterprise value
B22: Perpetual growth | C22: Exit multiple
A23: Present value of the plan's free cash flows | B23: =SUM($B$19:$F$19) -> -1252109 | C23: =B23 -> -1252109
A24: Final-year free cash flow | final-year EBITDA | B24: =$F$17 -> 121496.5 | C24: =$F$16 -> 141071.27
A25: Terminal value at the end of year 5 | B25: =IF($B$6>$B$7,B24*(1+$B$7)/($B$6-$B$7),0) -> 688480.15 | C25: =C24*$B$8 -> 634820.73
A26: Present value of the terminal value | B26: =B25/(1+$B$6)^$F$14 -> 276684.73 | C26: =C25/(1+$B$6)^$F$14 -> 255120.22
A27: Enterprise value | B27: =B23+B26 -> -975424.3 | C27: =C23+C26 -> -996988.81
A28: Terminal value share of enterprise value | B28: =IF(B27<>0,B26/B27,0) -> -0.28365577 | C28: =IF(C27<>0,C26/C27,0) -> -0.25589075
A29: Cross-check: implied exit multiple | implied perpetual growth | B29: =IF(C24>0,B25/C24,"n/a") -> 4.880371 | C29: =IF(C25+B24<>0,(C25*$B$6-B24)/(C25+B24),"n/a") -> 0.0072293066
A30: Enterprise value — average of the two methods | B30: =AVERAGE(B27,C27) -> -986206.56
A32: Sensitivity: enterprise value (perpetual growth) by WACC and terminal growth
A33: WACC ↓ · terminal growth → | B33: =$B$7+(-2)*$B$11 -> 0.01 | C33: =$B$7+(-1)*$B$11 -> 0.015 | D33: =$B$7+(0)*$B$11 -> 0.02 | E33: =$B$7+(1)*$B$11 -> 0.025 | F33: =$B$7+(2)*$B$11 -> 0.03
A34: =$B$6+(-2)*$B$10 -> 0.18 | B34: =IF($A34>B$33,SUMPRODUCT($B$17:$F$17/(1+$A34)^$B$14:$F$14)+$F$17*(1+B$33)/($A34-B$33)/(1+$A34)^$F$14,"n/a") -> -947788.63 | C34: =IF($A34>C$33,SUMPRODUCT($B$17:$F$17/(1+$A34)^$B$14:$F$14)+$F$17*(1+C$33)/($A34-C$33)/(1+$A34)^$F$14,"n/a") -> -936618.12 | D34: =IF($A34>D$33,SUMPRODUCT($B$17:$F$17/(1+$A34)^$B$14:$F$14)+$F$17*(1+D$33)/($A34-D$33)/(1+$A34)^$F$14,"n/a") -> -924749.46 | E34: =IF($A34>E$33,SUMPRODUCT($B$17:$F$17/(1+$A34)^$B$14:$F$14)+$F$17*(1+E$33)/($A34-E$33)/(1+$A34)^$F$14,"n/a") -> -912115.08 | F34: =IF($A34>F$33,SUMPRODUCT($B$17:$F$17/(1+$A34)^$B$14:$F$14)+$F$17*(1+F$33)/($A34-F$33)/(1+$A34)^$F$14,"n/a") -> -898638.4
A35: =$B$6+(-1)*$B$10 -> 0.19 | B35: =IF($A35>B$33,SUMPRODUCT($B$17:$F$17/(1+$A35)^$B$14:$F$14)+$F$17*(1+B$33)/($A35-B$33)/(1+$A35)^$F$14,"n/a") -> -972063.34 | C35: =IF($A35>C$33,SUMPRODUCT($B$17:$F$17/(1+$A35)^$B$14:$F$14)+$F$17*(1+C$33)/($A35-C$33)/(1+$A35)^$F$14,"n/a") -> -962446.43 | D35: =IF($A35>D$33,SUMPRODUCT($B$17:$F$17/(1+$A35)^$B$14:$F$14)+$F$17*(1+D$33)/($A35-D$33)/(1+$A35)^$F$14,"n/a") -> -952263.83 | E35: =IF($A35>E$33,SUMPRODUCT($B$17:$F$17/(1+$A35)^$B$14:$F$14)+$F$17*(1+E$33)/($A35-E$33)/(1+$A35)^$F$14,"n/a") -> -941464.09 | F35: =IF($A35>F$33,SUMPRODUCT($B$17:$F$17/(1+$A35)^$B$14:$F$14)+$F$17*(1+F$33)/($A35-F$33)/(1+$A35)^$F$14,"n/a") -> -929989.38
A36: =$B$6+(0)*$B$10 -> 0.2 | B36: =IF($A36>B$33,SUMPRODUCT($B$17:$F$17/(1+$A36)^$B$14:$F$14)+$F$17*(1+B$33)/($A36-B$33)/(1+$A36)^$F$14,"n/a") -> -992556.48 | C36: =IF($A36>C$33,SUMPRODUCT($B$17:$F$17/(1+$A36)^$B$14:$F$14)+$F$17*(1+C$33)/($A36-C$33)/(1+$A36)^$F$14,"n/a") -> -984221.9 | D36: =IF($A36>D$33,SUMPRODUCT($B$17:$F$17/(1+$A36)^$B$14:$F$14)+$F$17*(1+D$33)/($A36-D$33)/(1+$A36)^$F$14,"n/a") -> -975424.3 | E36: =IF($A36>E$33,SUMPRODUCT($B$17:$F$17/(1+$A36)^$B$14:$F$14)+$F$17*(1+E$33)/($A36-E$33)/(1+$A36)^$F$14,"n/a") -> -966123.97 | F36: =IF($A36>F$33,SUMPRODUCT($B$17:$F$17/(1+$A36)^$B$14:$F$14)+$F$17*(1+F$33)/($A36-F$33)/(1+$A36)^$F$14,"n/a") -> -956276.57
A37: =$B$6+(1)*$B$10 -> 0.21 | B37: =IF($A37>B$33,SUMPRODUCT($B$17:$F$17/(1+$A37)^$B$14:$F$14)+$F$17*(1+B$33)/($A37-B$33)/(1+$A37)^$F$14,"n/a") -> -1009864.6 | C37: =IF($A37>C$33,SUMPRODUCT($B$17:$F$17/(1+$A37)^$B$14:$F$14)+$F$17*(1+C$33)/($A37-C$33)/(1+$A37)^$F$14,"n/a") -> -1002598 | D37: =IF($A37>D$33,SUMPRODUCT($B$17:$F$17/(1+$A37)^$B$14:$F$14)+$F$17*(1+D$33)/($A37-D$33)/(1+$A37)^$F$14,"n/a") -> -994949.04 | E37: =IF($A37>E$33,SUMPRODUCT($B$17:$F$17/(1+$A37)^$B$14:$F$14)+$F$17*(1+E$33)/($A37-E$33)/(1+$A37)^$F$14,"n/a") -> -986886.59 | F37: =IF($A37>F$33,SUMPRODUCT($B$17:$F$17/(1+$A37)^$B$14:$F$14)+$F$17*(1+F$33)/($A37-F$33)/(1+$A37)^$F$14,"n/a") -> -978376.23
A38: =$B$6+(2)*$B$10 -> 0.22 | B38: =IF($A38>B$33,SUMPRODUCT($B$17:$F$17/(1+$A38)^$B$14:$F$14)+$F$17*(1+B$33)/($A38-B$33)/(1+$A38)^$F$14,"n/a") -> -1024469.6 | C38: =IF($A38>C$33,SUMPRODUCT($B$17:$F$17/(1+$A38)^$B$14:$F$14)+$F$17*(1+C$33)/($A38-C$33)/(1+$A38)^$F$14,"n/a") -> -1018099.8 | D38: =IF($A38>D$33,SUMPRODUCT($B$17:$F$17/(1+$A38)^$B$14:$F$14)+$F$17*(1+D$33)/($A38-D$33)/(1+$A38)^$F$14,"n/a") -> -1011411.6 | E38: =IF($A38>E$33,SUMPRODUCT($B$17:$F$17/(1+$A38)^$B$14:$F$14)+$F$17*(1+E$33)/($A38-E$33)/(1+$A38)^$F$14,"n/a") -> -1004380.4 | F38: =IF($A38>F$33,SUMPRODUCT($B$17:$F$17/(1+$A38)^$B$14:$F$14)+$F$17*(1+F$33)/($A38-F$33)/(1+$A38)^$F$14,"n/a") -> -996979.14
A40: Free cash flow = operating cash flow + interest × (1 − tax rate) − capital spending. Cells marked n/a: WACC not above growth.

Sheet Sources & Uses
A1: Sources and uses of funds | E1: =HYPERLINK("#'Cover'!A1","◂ Contents") -> ◂ Contents
A2: Live for the selected scenario. Where the money comes from and where it goes in the period set below.
A3: Scenario shown | B3: =CHOOSE(Dashboard!$B$4,"Low","Base","High") -> Base
A5: Funding structure ($'000) — raised at the start of the plan
B6: Amount | C6: Share
A7: Equity | B7: =Inputs!$E$34 -> 760000 | C7: =IF($B$9=0,0,B7/$B$9) -> 0.3877551
A8: Debt (loan) | B8: =Inputs!$E$35 -> 1200000 | C8: =IF($B$9=0,0,B8/$B$9) -> 0.6122449
A9: Total funding | B9: =B7+B8 -> 1960000 | C9: =IF(B9=0,0,1) -> 1
A10: Gearing (debt ÷ equity) | B10: =IF(B7<=0,IF(B8>0,"n/a",0),B8/B7) -> 1.5789474 | D10: n/a: debt without positive equity
A11: Funding required by the plan (Break-even sheet) | B11: ='Break-even'!B12 -> 1913997
A12: Funding surplus / (shortfall) | B12: ='Break-even'!B17 -> 46003.017
A14: ="Sources and uses of cash in the first "&$B$16&IF($B$16=1," month"," months")&" ($'000)" -> Sources and uses of cash in the first 12 months ($'000)
A15: Period covered (months from the start) | B15: 12 | D15: 1 to 60 (capped)
A16: Months used | B16: =MIN(60,MAX(1,ROUND(B15,0))) -> 12
A17: Sources | B17: Amount | C17: Share
A18: Equity raised | B18: =SUMPRODUCT(--(Monthly!$C$4:$BJ$4<=$B$16),Monthly!$C$67:$BJ$67) -> 760000 | C18: =IF($B$21=0,0,B18/$B$21) -> 0.37835992
A19: Loan drawdowns | B19: =SUMPRODUCT(--(Monthly!$C$4:$BJ$4<=$B$16),Monthly!$C$50:$BJ$50) -> 1200000 | C19: =IF($B$21=0,0,B19/$B$21) -> 0.5974104
A20: Cash generated by operations | B20: =MAX(0,SUMPRODUCT(--(Monthly!$C$4:$BJ$4<=$B$16),Monthly!$C$65:$BJ$65)) -> 48669.41 | C20: =IF($B$21=0,0,B20/$B$21) -> 0.024229677
A21: Total sources | B21: =SUM(B18:B20) -> 2008669.4 | C21: =IF(B21=0,0,1) -> 1
A23: Uses | B23: Amount | C23: Share
A24: Cash used by operations | B24: =MAX(0,-SUMPRODUCT(--(Monthly!$C$4:$BJ$4<=$B$16),Monthly!$C$65:$BJ$65)) -> 0 | C24: =IF($B$28=0,0,B24/$B$28) -> 0
A25: Capital spending | B25: =-SUMPRODUCT(--(Monthly!$C$4:$BJ$4<=$B$16),Monthly!$C$66:$BJ$66) -> 1909000 | C25: =IF($B$28=0,0,B25/$B$28) -> 0.95038038
A26: Loan repayments | B26: =-SUMPRODUCT(--(Monthly!$C$4:$BJ$4<=$B$16),Monthly!$C$52:$BJ$52) -> 13412.706 | C26: =IF($B$28=0,0,B26/$B$28) -> 0.0066774082
A27: Cash at the end of the period | B27: =INDEX(Monthly!$C$71:$BJ$71,$B$16) -> 86256.705 | C27: =IF($B$28=0,0,B27/$B$28) -> 0.04294221
A28: Total uses | B28: =SUM(B24:B27) -> 2008669.4 | C28: =IF(B28=0,0,1) -> 1
A29: Sources − uses (must be 0; opening cash is 0) | B29: =B21-B28 -> 0

Sheet KPIs
A1: KPIs & ratios | I1: =HYPERLINK("#'Cover'!A1","◂ Contents") -> ◂ Contents
A2: Rental property financial model (early) — industry metrics and financial ratios for the active scenario
A4: Financial ratios
B5: 1 | C5: 2 | D5: 3 | E5: 4 | F5: 5 | G5: Target
A6: Revenue growth | B6: =IF(N('P&L'!A5)<=0,"n/a",'P&L'!B5/'P&L'!A5-1) -> n/a | C6: =IF(N('P&L'!B5)<=0,"n/a",'P&L'!C5/'P&L'!B5-1) -> 0.03 | D6: =IF(N('P&L'!C5)<=0,"n/a",'P&L'!D5/'P&L'!C5-1) -> 0.03 | E6: =IF(N('P&L'!D5)<=0,"n/a",'P&L'!E5/'P&L'!D5-1) -> 0.03 | F6: =IF(N('P&L'!E5)<=0,"n/a",'P&L'!F5/'P&L'!E5-1) -> 0.03
A7: Gross margin | B7: =IF('P&L'!B5<=0,"n/a",'P&L'!B7/'P&L'!B5) -> 0.88594966 | C7: =IF('P&L'!C5<=0,"n/a",'P&L'!C7/'P&L'!C5) -> 0.88594966 | D7: =IF('P&L'!D5<=0,"n/a",'P&L'!D7/'P&L'!D5) -> 0.88594966 | E7: =IF('P&L'!E5<=0,"n/a",'P&L'!E7/'P&L'!E5) -> 0.88594966 | F7: =IF('P&L'!F5<=0,"n/a",'P&L'!F7/'P&L'!F5) -> 0.88594966
A8: EBITDA margin | B8: =IF('P&L'!B5<=0,"n/a",'P&L'!B14/'P&L'!B5) -> 0.63737605 | C8: =IF('P&L'!C5<=0,"n/a",'P&L'!C14/'P&L'!C5) -> 0.63737605 | D8: =IF('P&L'!D5<=0,"n/a",'P&L'!D14/'P&L'!D5) -> 0.63737605 | E8: =IF('P&L'!E5<=0,"n/a",'P&L'!E14/'P&L'!E5) -> 0.63737605 | F8: =IF('P&L'!F5<=0,"n/a",'P&L'!F14/'P&L'!F5) -> 0.63737605
A9: Net margin | B9: =IF('P&L'!B5<=0,"n/a",'P&L'!B21/'P&L'!B5) -> -0.04681249 | C9: =IF('P&L'!C5<=0,"n/a",'P&L'!C21/'P&L'!C5) -> -0.023100223 | D9: =IF('P&L'!D5<=0,"n/a",'P&L'!D21/'P&L'!D5) -> 8.0584628e-05 | E9: =IF('P&L'!E5<=0,"n/a",'P&L'!E21/'P&L'!E5) -> 0.022751125 | F9: =IF('P&L'!F5<=0,"n/a",'P&L'!F21/'P&L'!F5) -> 0.044015669
A10: Payroll, % of revenue | B10: =IF('P&L'!B5<=0,"n/a",-SUMIF(Headcount!$C$5:$BJ$5,B$5,Headcount!$C$7:$BJ$7)/'P&L'!B5) -> 0 | C10: =IF('P&L'!C5<=0,"n/a",-SUMIF(Headcount!$C$5:$BJ$5,C$5,Headcount!$C$7:$BJ$7)/'P&L'!C5) -> 0 | D10: =IF('P&L'!D5<=0,"n/a",-SUMIF(Headcount!$C$5:$BJ$5,D$5,Headcount!$C$7:$BJ$7)/'P&L'!D5) -> 0 | E10: =IF('P&L'!E5<=0,"n/a",-SUMIF(Headcount!$C$5:$BJ$5,E$5,Headcount!$C$7:$BJ$7)/'P&L'!E5) -> 0 | F10: =IF('P&L'!F5<=0,"n/a",-SUMIF(Headcount!$C$5:$BJ$5,F$5,Headcount!$C$7:$BJ$7)/'P&L'!F5) -> 0
A11: Operating expenses, % of revenue | B11: =IF('P&L'!B5<=0,"n/a",-'P&L'!B13/'P&L'!B5) -> 0.24857361 | C11: =IF('P&L'!C5<=0,"n/a",-'P&L'!C13/'P&L'!C5) -> 0.24857361 | D11: =IF('P&L'!D5<=0,"n/a",-'P&L'!D13/'P&L'!D5) -> 0.24857361 | E11: =IF('P&L'!E5<=0,"n/a",-'P&L'!E13/'P&L'!E5) -> 0.24857361 | F11: =IF('P&L'!F5<=0,"n/a",-'P&L'!F13/'P&L'!F5) -> 0.24857361
A12: Current ratio (current assets ÷ current liabilities) | B12: =IF(('Balance Sheet'!B12-'Balance Sheet'!B11)<=0,"n/a",('Balance Sheet'!B5+'Balance Sheet'!B6+'Balance Sheet'!B7)/('Balance Sheet'!B12-'Balance Sheet'!B11)) -> 92.30252 | C12: =IF(('Balance Sheet'!C12-'Balance Sheet'!C11)<=0,"n/a",('Balance Sheet'!C5+'Balance Sheet'!C6+'Balance Sheet'!C7)/('Balance Sheet'!C12-'Balance Sheet'!C11)) -> 125.4626 | D12: =IF(('Balance Sheet'!D12-'Balance Sheet'!D11)<=0,"n/a",('Balance Sheet'!D5+'Balance Sheet'!D6+'Balance Sheet'!D7)/('Balance Sheet'!D12-'Balance Sheet'!D11)) -> 160.41104 | E12: =IF(('Balance Sheet'!E12-'Balance Sheet'!E11)<=0,"n/a",('Balance Sheet'!E5+'Balance Sheet'!E6+'Balance Sheet'!E7)/('Balance Sheet'!E12-'Balance Sheet'!E11)) -> 197.01554 | F12: =IF(('Balance Sheet'!F12-'Balance Sheet'!F11)<=0,"n/a",('Balance Sheet'!F5+'Balance Sheet'!F6+'Balance Sheet'!F7)/('Balance Sheet'!F12-'Balance Sheet'!F11)) -> 234.95711
A13: Debt ÷ equity (loan ÷ total equity) | B13: =IF('Balance Sheet'!B15<=0,"n/a",'Balance Sheet'!B11/'Balance Sheet'!B15) -> 1.5804425 | C13: =IF('Balance Sheet'!C15<=0,"n/a",'Balance Sheet'!C11/'Balance Sheet'!C15) -> 1.571173 | D13: =IF('Balance Sheet'!D15<=0,"n/a",'Balance Sheet'!D11/'Balance Sheet'!D15) -> 1.5506728 | E13: =IF('Balance Sheet'!E15<=0,"n/a",'Balance Sheet'!E11/'Balance Sheet'!E15) -> 1.5188853 | F13: =IF('Balance Sheet'!F15<=0,"n/a",'Balance Sheet'!F11/'Balance Sheet'!F15) -> 1.4765854
A14: Return on assets (net income ÷ year-end assets) | B14: =IF('Balance Sheet'!B9<=0,"n/a",'P&L'!B21/'Balance Sheet'!B9) -> -0.0047493162 | C14: =IF('Balance Sheet'!C9<=0,"n/a",'P&L'!C21/'Balance Sheet'!C9) -> -0.0024377671 | D14: =IF('Balance Sheet'!D9<=0,"n/a",'P&L'!D21/'Balance Sheet'!D9) -> 8.8292516e-06 | E14: =IF('Balance Sheet'!E9<=0,"n/a",'P&L'!E21/'Balance Sheet'!E9) -> 0.0025829359 | F14: =IF('Balance Sheet'!F9<=0,"n/a",'P&L'!F21/'Balance Sheet'!F9) -> 0.0051677919
A15: Return on equity (net income ÷ year-end equity) | B15: =IF('Balance Sheet'!B15<=0,"n/a",'P&L'!B21/'Balance Sheet'!B15) -> -0.012261249 | C15: =IF('Balance Sheet'!C15<=0,"n/a",'P&L'!C21/'Balance Sheet'!C15) -> -0.0062710656 | D15: =IF('Balance Sheet'!D15<=0,"n/a",'P&L'!D21/'Balance Sheet'!D15) -> 2.2532264e-05 | E15: =IF('Balance Sheet'!E15<=0,"n/a",'P&L'!E21/'Balance Sheet'!E15) -> 0.0065096312 | F15: =IF('Balance Sheet'!F15<=0,"n/a",'P&L'!F21/'Balance Sheet'!F15) -> 0.012805623
A17: DuPont analysis — return on equity = net margin × asset turnover × equity multiplier
B18: 1 | C18: 2 | D18: 3 | E18: 4 | F18: 5
A19: Net margin | B19: =IF('P&L'!B5<=0,"n/a",'P&L'!B21/'P&L'!B5) -> -0.04681249 | C19: =IF('P&L'!C5<=0,"n/a",'P&L'!C21/'P&L'!C5) -> -0.023100223 | D19: =IF('P&L'!D5<=0,"n/a",'P&L'!D21/'P&L'!D5) -> 8.0584628e-05 | E19: =IF('P&L'!E5<=0,"n/a",'P&L'!E21/'P&L'!E5) -> 0.022751125 | F19: =IF('P&L'!F5<=0,"n/a",'P&L'!F21/'P&L'!F5) -> 0.044015669
A20: × Asset turnover (revenue ÷ assets) | B20: =IF('Balance Sheet'!B9<=0,"n/a",'P&L'!B5/'Balance Sheet'!B9) -> 0.10145404 | C20: =IF('Balance Sheet'!C9<=0,"n/a",'P&L'!C5/'Balance Sheet'!C9) -> 0.10553002 | D20: =IF('Balance Sheet'!D9<=0,"n/a",'P&L'!D5/'Balance Sheet'!D9) -> 0.10956496 | E20: =IF('Balance Sheet'!E9<=0,"n/a",'P&L'!E5/'Balance Sheet'!E9) -> 0.11353003 | F20: =IF('Balance Sheet'!F9<=0,"n/a",'P&L'!F5/'Balance Sheet'!F9) -> 0.11740801
A21: × Equity multiplier (assets ÷ equity) | B21: =IF('Balance Sheet'!B15<=0,"n/a",'Balance Sheet'!B9/'Balance Sheet'!B15) -> 2.5816872 | C21: =IF('Balance Sheet'!C15<=0,"n/a",'Balance Sheet'!C9/'Balance Sheet'!C15) -> 2.572463 | D21: =IF('Balance Sheet'!D15<=0,"n/a",'Balance Sheet'!D9/'Balance Sheet'!D15) -> 2.5520015 | E21: =IF('Balance Sheet'!E15<=0,"n/a",'Balance Sheet'!E9/'Balance Sheet'!E15) -> 2.520245 | F21: =IF('Balance Sheet'!F15<=0,"n/a",'Balance Sheet'!F9/'Balance Sheet'!F15) -> 2.477968
A22: Return on equity (product of the three) | B22: =IF(AND(ISNUMBER(B19),ISNUMBER(B20),ISNUMBER(B21)),B19*B20*B21,"n/a") -> -0.012261249 | C22: =IF(AND(ISNUMBER(C19),ISNUMBER(C20),ISNUMBER(C21)),C19*C20*C21,"n/a") -> -0.0062710656 | D22: =IF(AND(ISNUMBER(D19),ISNUMBER(D20),ISNUMBER(D21)),D19*D20*D21,"n/a") -> 2.2532264e-05 | E22: =IF(AND(ISNUMBER(E19),ISNUMBER(E20),ISNUMBER(E21)),E19*E20*E21,"n/a") -> 0.0065096312 | F22: =IF(AND(ISNUMBER(F19),ISNUMBER(F20),ISNUMBER(F21)),F19*F20*F21,"n/a") -> 0.012805623
A23: Check: product − return on equity (must be 0) | B23: =IF(AND(ISNUMBER(B22),ISNUMBER(B15)),B22-B15,IF(ISNUMBER(B22),1,IF(AND(ISNUMBER(B15),ISNUMBER(B19),ISNUMBER(B20)),1,0))) -> 0 | C23: =IF(AND(ISNUMBER(C22),ISNUMBER(C15)),C22-C15,IF(ISNUMBER(C22),1,IF(AND(ISNUMBER(C15),ISNUMBER(C19),ISNUMBER(C20)),1,0))) -> 0 | D23: =IF(AND(ISNUMBER(D22),ISNUMBER(D15)),D22-D15,IF(ISNUMBER(D22),1,IF(AND(ISNUMBER(D15),ISNUMBER(D19),ISNUMBER(D20)),1,0))) -> 0 | E23: =IF(AND(ISNUMBER(E22),ISNUMBER(E15)),E22-E15,IF(ISNUMBER(E22),1,IF(AND(ISNUMBER(E15),ISNUMBER(E19),ISNUMBER(E20)),1,0))) -> 0 | F23: =IF(AND(ISNUMBER(F22),ISNUMBER(F15)),F22-F15,IF(ISNUMBER(F22),1,IF(AND(ISNUMBER(F15),ISNUMBER(F19),ISNUMBER(F20)),1,0))) -> 0
A25: Property metrics ($'000; per-unit rows in $)
A26: Year # | B26: 1 | C26: 2 | D26: 3 | E26: 4 | F26: 5
B27: Year 1 | C27: Year 2 | D27: Year 3 | E27: Year 4 | F27: Year 5 | G27: Target
A28: Average rent per unit per month ($) | B28: =INDEX(Monthly!$C$8:$BJ$8,B$26*12) -> 1700 | C28: =INDEX(Monthly!$C$8:$BJ$8,C$26*12) -> 1751 | D28: =INDEX(Monthly!$C$8:$BJ$8,D$26*12) -> 1803.53 | E28: =INDEX(Monthly!$C$8:$BJ$8,E$26*12) -> 1857.6359 | F28: =INDEX(Monthly!$C$8:$BJ$8,F$26*12) -> 1913.365
A29: Gross potential rent | B29: =SUMIF(Monthly!$C$5:$BJ$5,B$26,Monthly!$C$9:$BJ$9) -> 204000 | C29: =SUMIF(Monthly!$C$5:$BJ$5,C$26,Monthly!$C$9:$BJ$9) -> 210120 | D29: =SUMIF(Monthly!$C$5:$BJ$5,D$26,Monthly!$C$9:$BJ$9) -> 216423.6 | E29: =SUMIF(Monthly!$C$5:$BJ$5,E$26,Monthly!$C$9:$BJ$9) -> 222916.31 | F29: =SUMIF(Monthly!$C$5:$BJ$5,F$26,Monthly!$C$9:$BJ$9) -> 229603.8
A30: Vacancy & credit loss | B30: =SUMIF(Monthly!$C$5:$BJ$5,B$26,Monthly!$C$10:$BJ$10) -> -10200 | C30: =SUMIF(Monthly!$C$5:$BJ$5,C$26,Monthly!$C$10:$BJ$10) -> -10506 | D30: =SUMIF(Monthly!$C$5:$BJ$5,D$26,Monthly!$C$10:$BJ$10) -> -10821.18 | E30: =SUMIF(Monthly!$C$5:$BJ$5,E$26,Monthly!$C$10:$BJ$10) -> -11145.815 | F30: =SUMIF(Monthly!$C$5:$BJ$5,F$26,Monthly!$C$10:$BJ$10) -> -11480.19
A31: Economic occupancy (collected ÷ potential rent) | B31: =IF(B29=0,0,(B29+B30)/B29) -> 0.95 | C31: =IF(C29=0,0,(C29+C30)/C29) -> 0.95 | D31: =IF(D29=0,0,(D29+D30)/D29) -> 0.95 | E31: =IF(E29=0,0,(E29+E30)/E29) -> 0.95 | F31: =IF(F29=0,0,(F29+F30)/F29) -> 0.95
A32: Revenue (effective gross income) | B32: =SUMIF(Monthly!$C$5:$BJ$5,B$26,Monthly!$C$12:$BJ$12) -> 196650 | C32: =SUMIF(Monthly!$C$5:$BJ$5,C$26,Monthly!$C$12:$BJ$12) -> 202549.5 | D32: =SUMIF(Monthly!$C$5:$BJ$5,D$26,Monthly!$C$12:$BJ$12) -> 208625.98 | E32: =SUMIF(Monthly!$C$5:$BJ$5,E$26,Monthly!$C$12:$BJ$12) -> 214884.76 | F32: =SUMIF(Monthly!$C$5:$BJ$5,F$26,Monthly!$C$12:$BJ$12) -> 221331.31
A33: Net operating income (NOI = EBITDA) | B33: =SUMIF(Monthly!$C$5:$BJ$5,B$26,Monthly!$C$26:$BJ$26) -> 125340 | C33: =SUMIF(Monthly!$C$5:$BJ$5,C$26,Monthly!$C$26:$BJ$26) -> 129100.2 | D33: =SUMIF(Monthly!$C$5:$BJ$5,D$26,Monthly!$C$26:$BJ$26) -> 132973.21 | E33: =SUMIF(Monthly!$C$5:$BJ$5,E$26,Monthly!$C$26:$BJ$26) -> 136962.4 | F33: =SUMIF(Monthly!$C$5:$BJ$5,F$26,Monthly!$C$26:$BJ$26) -> 141071.27
A34: NOI margin | B34: =IF(B32=0,0,B33/B32) -> 0.63737605 | C34: =IF(C32=0,0,C33/C32) -> 0.63737605 | D34: =IF(D32=0,0,D33/D32) -> 0.63737605 | E34: =IF(E32=0,0,E33/E32) -> 0.63737605 | F34: =IF(F32=0,0,F33/F32) -> 0.63737605
A35: Operating expense ratio | B35: =IF(B32=0,0,1-B33/B32) -> 0.36262395 | C35: =IF(C32=0,0,1-C33/C32) -> 0.36262395 | D35: =IF(D32=0,0,1-D33/D32) -> 0.36262395 | E35: =IF(E32=0,0,1-E33/E32) -> 0.36262395 | F35: =IF(F32=0,0,1-F33/F32) -> 0.36262395
A36: NOI per unit ($) | B36: =IF(Inputs!$E$10=0,0,B33/Inputs!$E$10) -> 12534 | C36: =IF(Inputs!$E$10=0,0,C33/Inputs!$E$10) -> 12910.02 | D36: =IF(Inputs!$E$10=0,0,D33/Inputs!$E$10) -> 13297.321 | E36: =IF(Inputs!$E$10=0,0,E33/Inputs!$E$10) -> 13696.24 | F36: =IF(Inputs!$E$10=0,0,F33/Inputs!$E$10) -> 14107.127
A37: NOI ÷ purchase price | B37: =IF(Inputs!$E$7=0,0,B33/Inputs!$E$7) -> 0.067751351 | C37: =IF(Inputs!$E$7=0,0,C33/Inputs!$E$7) -> 0.069783892 | D37: =IF(Inputs!$E$7=0,0,D33/Inputs!$E$7) -> 0.071877409 | E37: =IF(Inputs!$E$7=0,0,E33/Inputs!$E$7) -> 0.074033731 | F37: =IF(Inputs!$E$7=0,0,F33/Inputs!$E$7) -> 0.076254743
A38: Debt service (interest + principal) | B38: =-SUMIF(Monthly!$C$5:$BJ$5,B$26,Monthly!$C$53:$BJ$53) -> 91017.795 | C38: =-SUMIF(Monthly!$C$5:$BJ$5,C$26,Monthly!$C$53:$BJ$53) -> 91017.795 | D38: =-SUMIF(Monthly!$C$5:$BJ$5,D$26,Monthly!$C$53:$BJ$53) -> 91017.795 | E38: =-SUMIF(Monthly!$C$5:$BJ$5,E$26,Monthly!$C$53:$BJ$53) -> 91017.795 | F38: =-SUMIF(Monthly!$C$5:$BJ$5,F$26,Monthly!$C$53:$BJ$53) -> 91017.795
A39: Debt service coverage (NOI ÷ debt service) | B39: =IF(B38>0.5,B33/B38,"n/a") -> 1.3770933 | C39: =IF(C38>0.5,C33/C38,"n/a") -> 1.4184061 | D39: =IF(D38>0.5,D33/D38,"n/a") -> 1.4609583 | E39: =IF(E38>0.5,E33/E38,"n/a") -> 1.5047871 | F39: =IF(F38>0.5,F33/F38,"n/a") -> 1.5499307
A40: Loan balance (year end) | B40: =INDEX(Monthly!$C$54:$BJ$54,B$26*12) -> 1186587.3 | C40: =INDEX(Monthly!$C$54:$BJ$54,C$26*12) -> 1172276.3 | D40: =INDEX(Monthly!$C$54:$BJ$54,D$26*12) -> 1157006.9 | E40: =INDEX(Monthly!$C$54:$BJ$54,E$26*12) -> 1140714.9 | F40: =INDEX(Monthly!$C$54:$BJ$54,F$26*12) -> 1123331.7
A41: Loan ÷ purchase price (year end) | B41: =IF(Inputs!$E$7=0,0,B40/Inputs!$E$7) -> 0.64139854 | C41: =IF(Inputs!$E$7=0,0,C40/Inputs!$E$7) -> 0.63366287 | D41: =IF(Inputs!$E$7=0,0,D40/Inputs!$E$7) -> 0.62540914 | E41: =IF(Inputs!$E$7=0,0,E40/Inputs!$E$7) -> 0.61660263 | F41: =IF(Inputs!$E$7=0,0,F40/Inputs!$E$7) -> 0.60720634

Sheet Returns
A1: Property returns — purchase, hold and sale | I1: =HYPERLINK("#'Cover'!A1","◂ Contents") -> ◂ Contents
A2: Live for the selected scenario. Year 0 = purchase; sale at the end of year 5. Cash flows before income tax.
A3: Scenario shown | B3: =CHOOSE(Dashboard!$B$4,"Low","Base","High") -> Base
A5: Purchase (active scenario, from the Inputs sheet)
A6: Purchase price | B6: =Inputs!$E$7 -> 1850000
A7: Closing costs | B7: =B6*Inputs!$E$9 -> 55500
A8: All-in purchase cost | B8: =B6+B7 -> 1905500
A9: Loan drawn at purchase | B9: =Inputs!$E$35 -> 1200000
A10: Equity invested in the property | B10: =B8-B9 -> 705500
A11: Loan-to-value at purchase | B11: =IF(B6>0,B9/B6,0) -> 0.64864865
A13: Cash flows by year
B14: Year 0 | C14: Year 1 | D14: Year 2 | E14: Year 3 | F14: Year 4 | G14: Year 5
A15: Year # | B15: =0 -> 0 | C15: =B15+1 -> 1 | D15: =C15+1 -> 2 | E15: =D15+1 -> 3 | F15: =E15+1 -> 4 | G15: =F15+1 -> 5
A16: Purchase incl. closing costs | B16: =-IF(B$15=0,$B$8,0) -> -1905500 | C16: =-IF(C$15=0,$B$8,0) -> 0 | D16: =-IF(D$15=0,$B$8,0) -> 0 | E16: =-IF(E$15=0,$B$8,0) -> 0 | F16: =-IF(F$15=0,$B$8,0) -> 0 | G16: =-IF(G$15=0,$B$8,0) -> 0
A17: Net operating income (NOI = EBITDA) | B17: =SUMIF(Monthly!$C$5:$BJ$5,B$15,Monthly!$C$26:$BJ$26) -> 0 | C17: =SUMIF(Monthly!$C$5:$BJ$5,C$15,Monthly!$C$26:$BJ$26) -> 125340 | D17: =SUMIF(Monthly!$C$5:$BJ$5,D$15,Monthly!$C$26:$BJ$26) -> 129100.2 | E17: =SUMIF(Monthly!$C$5:$BJ$5,E$15,Monthly!$C$26:$BJ$26) -> 132973.21 | F17: =SUMIF(Monthly!$C$5:$BJ$5,F$15,Monthly!$C$26:$BJ$26) -> 136962.4 | G17: =SUMIF(Monthly!$C$5:$BJ$5,G$15,Monthly!$C$26:$BJ$26) -> 141071.27
A18: Capital reserves (capex other than the purchase) | B18: =-(SUMIF(Monthly!$C$5:$BJ$5,B$15,Monthly!$C$41:$BJ$41)-SUMIF(Monthly!$C$5:$BJ$5,B$15,Monthly!$C$38:$BJ$38)) -> 0 | C18: =-(SUMIF(Monthly!$C$5:$BJ$5,C$15,Monthly!$C$41:$BJ$41)-SUMIF(Monthly!$C$5:$BJ$5,C$15,Monthly!$C$38:$BJ$38)) -> -3500 | D18: =-(SUMIF(Monthly!$C$5:$BJ$5,D$15,Monthly!$C$41:$BJ$41)-SUMIF(Monthly!$C$5:$BJ$5,D$15,Monthly!$C$38:$BJ$38)) -> -3605 | E18: =-(SUMIF(Monthly!$C$5:$BJ$5,E$15,Monthly!$C$41:$BJ$41)-SUMIF(Monthly!$C$5:$BJ$5,E$15,Monthly!$C$38:$BJ$38)) -> -3713.15 | F18: =-(SUMIF(Monthly!$C$5:$BJ$5,F$15,Monthly!$C$41:$BJ$41)-SUMIF(Monthly!$C$5:$BJ$5,F$15,Monthly!$C$38:$BJ$38)) -> -3824.5445 | G18: =-(SUMIF(Monthly!$C$5:$BJ$5,G$15,Monthly!$C$41:$BJ$41)-SUMIF(Monthly!$C$5:$BJ$5,G$15,Monthly!$C$38:$BJ$38)) -> -3939.2808
A19: Sale proceeds, net of selling costs | B19: =IF(B$15=$G$15,$B$36,0) -> 0 | C19: =IF(C$15=$G$15,$B$36,0) -> 0 | D19: =IF(D$15=$G$15,$B$36,0) -> 0 | E19: =IF(E$15=$G$15,$B$36,0) -> 0 | F19: =IF(F$15=$G$15,$B$36,0) -> 0 | G19: =IF(G$15=$G$15,$B$36,0) -> 2045011
A20: Unlevered cash flow (property, before tax) | B20: =B16+B17+B18+B19 -> -1905500 | C20: =C16+C17+C18+C19 -> 121840 | D20: =D16+D17+D18+D19 -> 125495.2 | E20: =E16+E17+E18+E19 -> 129260.06 | F20: =F16+F17+F18+F19 -> 133137.86 | G20: =G16+G17+G18+G19 -> 2182143
A21: Loan drawn | B21: =IF(B$15=0,$B$9,0) -> 1200000 | C21: =IF(C$15=0,$B$9,0) -> 0 | D21: =IF(D$15=0,$B$9,0) -> 0 | E21: =IF(E$15=0,$B$9,0) -> 0 | F21: =IF(F$15=0,$B$9,0) -> 0 | G21: =IF(G$15=0,$B$9,0) -> 0
A22: Interest | B22: =SUMIF(Monthly!$C$5:$BJ$5,B$15,Monthly!$C$30:$BJ$30) -> 0 | C22: =SUMIF(Monthly!$C$5:$BJ$5,C$15,Monthly!$C$30:$BJ$30) -> -77605.09 | D22: =SUMIF(Monthly!$C$5:$BJ$5,D$15,Monthly!$C$30:$BJ$30) -> -76706.816 | E22: =SUMIF(Monthly!$C$5:$BJ$5,E$15,Monthly!$C$30:$BJ$30) -> -75748.383 | F22: =SUMIF(Monthly!$C$5:$BJ$5,F$15,Monthly!$C$30:$BJ$30) -> -74725.762 | G22: =SUMIF(Monthly!$C$5:$BJ$5,G$15,Monthly!$C$30:$BJ$30) -> -73634.655
A23: Principal repaid | B23: =SUMIF(Monthly!$C$5:$BJ$5,B$15,Monthly!$C$52:$BJ$52) -> 0 | C23: =SUMIF(Monthly!$C$5:$BJ$5,C$15,Monthly!$C$52:$BJ$52) -> -13412.706 | D23: =SUMIF(Monthly!$C$5:$BJ$5,D$15,Monthly!$C$52:$BJ$52) -> -14310.979 | E23: =SUMIF(Monthly!$C$5:$BJ$5,E$15,Monthly!$C$52:$BJ$52) -> -15269.412 | F23: =SUMIF(Monthly!$C$5:$BJ$5,F$15,Monthly!$C$52:$BJ$52) -> -16292.033 | G23: =SUMIF(Monthly!$C$5:$BJ$5,G$15,Monthly!$C$52:$BJ$52) -> -17383.141
A24: Loan balance repaid at sale | B24: =-IF(B$15=$G$15,$B$37,0) -> 0 | C24: =-IF(C$15=$G$15,$B$37,0) -> 0 | D24: =-IF(D$15=$G$15,$B$37,0) -> 0 | E24: =-IF(E$15=$G$15,$B$37,0) -> 0 | F24: =-IF(F$15=$G$15,$B$37,0) -> 0 | G24: =-IF(G$15=$G$15,$B$37,0) -> -1123331.7
A25: Levered cash flow (equity, before tax) | B25: =B20+B21+B22+B23+B24 -> -705500 | C25: =C20+C21+C22+C23+C24 -> 30822.205 | D25: =D20+D21+D22+D23+D24 -> 34477.405 | E25: =E20+E21+E22+E23+E24 -> 38242.261 | F25: =F20+F21+F22+F23+F24 -> 42120.062 | G25: =G20+G21+G22+G23+G24 -> 967793.46
A26: Debt service coverage (NOI ÷ debt service) | B26: =IF(-(B22+B23)>0.5,B17/-(B22+B23),"n/a") -> n/a | C26: =IF(-(C22+C23)>0.5,C17/-(C22+C23),"n/a") -> 1.3770933 | D26: =IF(-(D22+D23)>0.5,D17/-(D22+D23),"n/a") -> 1.4184061 | E26: =IF(-(E22+E23)>0.5,E17/-(E22+E23),"n/a") -> 1.4609583 | F26: =IF(-(F22+F23)>0.5,F17/-(F22+F23),"n/a") -> 1.5047871 | G26: =IF(-(G22+G23)>0.5,G17/-(G22+G23),"n/a") -> 1.5499307
A27: Cash-on-cash return (levered cash flow before sale ÷ equity invested) | B27: =IF(AND(B$15>0,$B$10>0),(B17+B18+B22+B23)/$B$10,"n/a") -> n/a | C27: =IF(AND(C$15>0,$B$10>0),(C17+C18+C22+C23)/$B$10,"n/a") -> 0.043688454 | D27: =IF(AND(D$15>0,$B$10>0),(D17+D18+D22+D23)/$B$10,"n/a") -> 0.048869461 | E27: =IF(AND(E$15>0,$B$10>0),(E17+E18+E22+E23)/$B$10,"n/a") -> 0.054205897 | F27: =IF(AND(F$15>0,$B$10>0),(F17+F18+F22+F23)/$B$10,"n/a") -> 0.059702427 | G27: =IF(AND(G$15>0,$B$10>0),(G17+G18+G22+G23)/$B$10,"n/a") -> 0.065363853
A28: Helper: sign of the unlevered cash flow (a zero keeps the previous sign) | B28: =SIGN(B20) -> -1 | C28: =IF(C20=0,B28,SIGN(C20)) -> 1 | D28: =IF(D20=0,C28,SIGN(D20)) -> 1 | E28: =IF(E20=0,D28,SIGN(E20)) -> 1 | F28: =IF(F20=0,E28,SIGN(F20)) -> 1 | G28: =IF(G20=0,F28,SIGN(G20)) -> 1
A29: Helper: sign of the levered cash flow (a zero keeps the previous sign) | B29: =SIGN(B25) -> -1 | C29: =IF(C25=0,B29,SIGN(C25)) -> 1 | D29: =IF(D25=0,C29,SIGN(D25)) -> 1 | E29: =IF(E25=0,D29,SIGN(E25)) -> 1 | F29: =IF(F25=0,E29,SIGN(F25)) -> 1 | G29: =IF(G25=0,F29,SIGN(G25)) -> 1
A31: Sale at the end of year 5
A32: Year 6 NOI (year 5 NOI × (1 + rent growth)) | B32: =G17*(1+Inputs!$E$14) -> 145303.41
A33: Exit cap rate | B33: =Inputs!$E$29 -> 0.0675
A34: Sale price (next-year NOI ÷ exit cap rate) | B34: =IF(B33>0,B32/B33,0) -> 2152643.1
A35: Selling costs | B35: =-B34*Inputs!$E$30 -> -107632.16
A36: Net sale proceeds | B36: =B34+B35 -> 2045011
A37: Loan balance at the end of year 5 | B37: =INDEX(Monthly!$C$54:$BJ$54,60) -> 1123331.7
A38: Net proceeds to equity | B38: =B36-B37 -> 921679.26
A40: Returns
B41: Unlevered | C41: Levered
A42: Internal rate of return (IRR) | B42: =IF(B44=1,IFERROR(IRR($B$20:$G$20,B43),IFERROR(IRR($B$20:$G$20),"n/a")),"n/a") -> 0.080064874 | C42: =IF(C44=1,IFERROR(IRR($B$25:$G$25,C43),IFERROR(IRR($B$25:$G$25),"n/a")),"n/a") -> 0.10318135
A43: Helper: IRR starting estimate ((inflows ÷ outflows) ^ (1 ÷ years) − 1) | B43: =IF(AND(SUMIF($B$20:$G$20,">0")>0,-SUMIF($B$20:$G$20,"<0")>0),MAX(-0.99,(SUMIF($B$20:$G$20,">0")/(-SUMIF($B$20:$G$20,"<0")))^(1/$G$15)-1),0.1) -> 0.07154206 | C43: =IF(AND(SUMIF($B$25:$G$25,">0")>0,-SUMIF($B$25:$G$25,"<0")>0),MAX(-0.99,(SUMIF($B$25:$G$25,">0")/(-SUMIF($B$25:$G$25,"<0")))^(1/$G$15)-1),0.1) -> 0.095557461
A44: Helper: IRR defined (1 = one sign change and inflows ≥ 25% of outflows) | B44: =IF(AND(SUMPRODUCT(--($B$28:$F$28*$C$28:$G$28<0))=1,SUMIF($B$20:$G$20,">0")>=0.25*-SUMIF($B$20:$G$20,"<0")),1,0) -> 1 | C44: =IF(AND(SUMPRODUCT(--($B$29:$F$29*$C$29:$G$29<0))=1,SUMIF($B$25:$G$25,">0")>=0.25*-SUMIF($B$25:$G$25,"<0")),1,0) -> 1
A45: Discount rate for NPV | B45: =Inputs!$E$31 -> 0.1
A46: Net present value at the discount rate | B46: =$B$20+NPV($B$45,$C$20:$G$20) -> -148032.27 | C46: =$B$25+NPV($B$45,$C$25:$G$25) -> 9438.0496
A47: Total profit (sum of cash flows) | B47: =SUM($B$20:$G$20) -> 786376.1 | C47: =SUM($B$25:$G$25) -> 407955.39
A48: Multiple of money invested (inflows ÷ year-0 outflow) | B48: =IF($B$20<0,SUM($C$20:$G$20)/-$B$20,"n/a") -> 1.4126875 | C48: =IF($B$25<0,SUM($C$25:$G$25)/-$B$25,"n/a") -> 1.57825
A49: Going-in cap rate (year-1 NOI ÷ purchase price) | B49: =IF(B6>0,C17/B6,0) -> 0.067751351
A51: IRR and NPV use yearly flows with the purchase at year 0 and the sale at the end of the final year. n/a = no debt service or no equity invested; IRR n/a = the flows change sign more than once (IRR not unique) or return less than 25% of the money put in.

Sheet Inputs
A1: Inputs — Low / Base / High | I1: =HYPERLINK("#'Cover'!A1","◂ Contents") -> ◂ Contents
A2: Illustrative assumptions — replace them with your own numbers.
A5: Driver | B5: Low | C5: Base | D5: High | E5: Active | F5: Unit | G5: Source / comment
A6: Property
A7: Purchase price | B7: 1850000 | C7: 1850000 | D7: 1850000 | E7: =CHOOSE(Dashboard!$B$4,B7,C7,D7) -> 1850000 | F7: $
A8: Land share of the price (not depreciated) | B8: 0.2 | C8: 0.2 | D8: 0.2 | E8: =CHOOSE(Dashboard!$B$4,B8,C8,D8) -> 0.2 | F8: %
A9: Closing costs, % of price | B9: 0.03 | C9: 0.03 | D9: 0.03 | E9: =CHOOSE(Dashboard!$B$4,B9,C9,D9) -> 0.03 | F9: % | G9: Low ≥ Base ≥ High (lower is better)
A10: Rentable units | B10: 10 | C10: 10 | D10: 10 | E10: =CHOOSE(Dashboard!$B$4,B10,C10,D10) -> 10 | F10: #
A12: Rent roll
A13: Average rent per unit per month (year 1) | B13: 1600 | C13: 1700 | D13: 1800 | E13: =CHOOSE(Dashboard!$B$4,B13,C13,D13) -> 1700 | F13: $ | G13: Low ≤ Base ≤ High
A14: Rent growth per year | B14: 0.02 | C14: 0.03 | D14: 0.04 | E14: =CHOOSE(Dashboard!$B$4,B14,C14,D14) -> 0.03 | F14: % | G14: Low ≤ Base ≤ High
A15: Vacancy & credit loss, % of potential rent | B15: 0.08 | C15: 0.05 | D15: 0.04 | E15: =CHOOSE(Dashboard!$B$4,B15,C15,D15) -> 0.05 | F15: % | G15: Low ≥ Base ≥ High (lower is better)
A16: Other income per unit per month (parking, laundry, fees) | B16: 20 | C16: 25 | D16: 30 | E16: =CHOOSE(Dashboard!$B$4,B16,C16,D16) -> 25 | F16: $ | G16: Low ≤ Base ≤ High
A18: Operating costs
A19: Repairs & maintenance, % of collected rent | B19: 0.07 | C19: 0.06 | D19: 0.05 | E19: =CHOOSE(Dashboard!$B$4,B19,C19,D19) -> 0.06 | F19: % | G19: Low ≥ Base ≥ High (lower is better)
A20: Owner-paid utilities & common areas per month | B20: 900 | C20: 900 | D20: 900 | E20: =CHOOSE(Dashboard!$B$4,B20,C20,D20) -> 900 | F20: $
A21: Property tax per year, % of purchase price | B21: 0.011 | C21: 0.011 | D21: 0.011 | E21: =CHOOSE(Dashboard!$B$4,B21,C21,D21) -> 0.011 | F21: %
A22: Insurance per unit per year | B22: 800 | C22: 800 | D22: 800 | E22: =CHOOSE(Dashboard!$B$4,B22,C22,D22) -> 800 | F22: $
A23: Property management fee, % of revenue | B23: 0.08 | C23: 0.08 | D23: 0.08 | E23: =CHOOSE(Dashboard!$B$4,B23,C23,D23) -> 0.08 | F23: % | G23: Low ≥ Base ≥ High (lower is better)
A24: Legal, accounting & other G&A per month | B24: 400 | C24: 400 | D24: 400 | E24: =CHOOSE(Dashboard!$B$4,B24,C24,D24) -> 400 | F24: $
A25: Operating cost inflation per year | B25: 0.04 | C25: 0.03 | D25: 0.025 | E25: =CHOOSE(Dashboard!$B$4,B25,C25,D25) -> 0.03 | F25: % | G25: Low ≥ Base ≥ High (lower is better)
A26: Capital reserve per unit per year (roofs, appliances) | B26: 350 | C26: 350 | D26: 350 | E26: =CHOOSE(Dashboard!$B$4,B26,C26,D26) -> 350 | F26: $
A28: Sale & returns
A29: Exit cap rate (next-year NOI ÷ sale price) | B29: 0.0725 | C29: 0.0675 | D29: 0.0625 | E29: =CHOOSE(Dashboard!$B$4,B29,C29,D29) -> 0.0675 | F29: % | G29: Low ≥ Base ≥ High (lower is better)
A30: Selling costs, % of sale price | B30: 0.06 | C30: 0.05 | D30: 0.05 | E30: =CHOOSE(Dashboard!$B$4,B30,C30,D30) -> 0.05 | F30: % | G30: Low ≥ Base ≥ High (lower is better)
A31: Discount rate for NPV (your target return) | B31: 0.1 | C31: 0.1 | D31: 0.1 | E31: =CHOOSE(Dashboard!$B$4,B31,C31,D31) -> 0.1 | F31: %
A33: Funding
A34: Equity raised at start | B34: 760000 | C34: 760000 | D34: 760000 | E34: =CHOOSE(Dashboard!$B$4,B34,C34,D34) -> 760000 | F34: $
A35: Loan drawn at start | B35: 1200000 | C35: 1200000 | D35: 1200000 | E35: =CHOOSE(Dashboard!$B$4,B35,C35,D35) -> 1200000 | F35: $
A36: Loan interest rate per year | B36: 0.065 | C36: 0.065 | D36: 0.065 | E36: =CHOOSE(Dashboard!$B$4,B36,C36,D36) -> 0.065 | F36: %
A37: Loan repayment term | B37: 30 | C37: 30 | D37: 30 | E37: =CHOOSE(Dashboard!$B$4,B37,C37,D37) -> 30 | F37: years
A39: Working capital
A40: Customer payment terms (receivable days) | B40: 0 | C40: 0 | D40: 0 | E40: =CHOOSE(Dashboard!$B$4,B40,C40,D40) -> 0 | F40: days
A41: Inventory held (days of COGS) | B41: 0 | C41: 0 | D41: 0 | E41: =CHOOSE(Dashboard!$B$4,B41,C41,D41) -> 0 | F41: days
A42: Supplier payment terms (payable days) | B42: 15 | C42: 15 | D42: 15 | E42: =CHOOSE(Dashboard!$B$4,B42,C42,D42) -> 15 | F42: days
A44: Tax & depreciation
A45: Depreciation period for capex | B45: 27 | C45: 27 | D45: 27 | E45: =CHOOSE(Dashboard!$B$4,B45,C45,D45) -> 27 | F45: years
A46: Income tax rate | B46: 0.21 | C46: 0.21 | D46: 0.21 | E46: =CHOOSE(Dashboard!$B$4,B46,C46,D46) -> 0.21 | F46: %
A48: Break-even & funding
A49: Minimum cash buffer to keep | B49: 12000 | C49: 12000 | D49: 12000 | E49: =CHOOSE(Dashboard!$B$4,B49,C49,D49) -> 12000 | F49: $ | G49: About 3 months of costs
A51: Valuation
A52: Discount rate (WACC) | B52: 0.25 | C52: 0.2 | D52: 0.17 | E52: =CHOOSE(Dashboard!$B$4,B52,C52,D52) -> 0.2 | F52: % | G52: Low ≥ Base ≥ High (lower is better)
A53: Terminal growth rate (perpetuity) | B53: 0.01 | C53: 0.02 | D53: 0.03 | E53: =CHOOSE(Dashboard!$B$4,B53,C53,D53) -> 0.02 | F53: % | G53: Low ≤ Base ≤ High
A54: Exit multiple (EV ÷ final-year EBITDA) | B54: 3.5 | C54: 4.5 | D54: 6 | E54: =CHOOSE(Dashboard!$B$4,B54,C54,D54) -> 4.5 | F54: x | G54: Low ≤ Base ≤ High
A55: Sensitivity table: WACC step | B55: 0.01 | C55: 0.01 | D55: 0.01 | E55: =CHOOSE(Dashboard!$B$4,B55,C55,D55) -> 0.01 | F55: %
A56: Sensitivity table: growth step | B56: 0.005 | C56: 0.005 | D56: 0.005 | E56: =CHOOSE(Dashboard!$B$4,B56,C56,D56) -> 0.005 | F56: %
A58: Legend: yellow cell with blue figure = input you can change · black = formula · green = link to another sheet · grey = active value (column E follows the scenario on the Dashboard).

Sheet P&L
A1: Annual profit & loss | H1: =HYPERLINK("#'Cover'!A1","◂ Contents") -> ◂ Contents
A2: Rolled up from the period detail (SUMIF on the year row; balances at year end).
A3: Year # | B3: 1 | C3: 2 | D3: 3 | E3: 4 | F3: 5
B4: Year 1 | C4: Year 2 | D4: Year 3 | E4: Year 4 | F4: Year 5
A5: Revenue | B5: =SUMIF(Monthly!$C$5:$BJ$5,B$3,Monthly!$C$12:$BJ$12) -> 196650 | C5: =SUMIF(Monthly!$C$5:$BJ$5,C$3,Monthly!$C$12:$BJ$12) -> 202549.5 | D5: =SUMIF(Monthly!$C$5:$BJ$5,D$3,Monthly!$C$12:$BJ$12) -> 208625.98 | E5: =SUMIF(Monthly!$C$5:$BJ$5,E$3,Monthly!$C$12:$BJ$12) -> 214884.76 | F5: =SUMIF(Monthly!$C$5:$BJ$5,F$3,Monthly!$C$12:$BJ$12) -> 221331.31
A6: Direct property costs | B6: =SUMIF(Monthly!$C$5:$BJ$5,B$3,Monthly!$C$17:$BJ$17) -> -22428 | C6: =SUMIF(Monthly!$C$5:$BJ$5,C$3,Monthly!$C$17:$BJ$17) -> -23100.84 | D6: =SUMIF(Monthly!$C$5:$BJ$5,D$3,Monthly!$C$17:$BJ$17) -> -23793.865 | E6: =SUMIF(Monthly!$C$5:$BJ$5,E$3,Monthly!$C$17:$BJ$17) -> -24507.681 | F6: =SUMIF(Monthly!$C$5:$BJ$5,F$3,Monthly!$C$17:$BJ$17) -> -25242.912
A7: Gross profit | B7: =SUMIF(Monthly!$C$5:$BJ$5,B$3,Monthly!$C$18:$BJ$18) -> 174222 | C7: =SUMIF(Monthly!$C$5:$BJ$5,C$3,Monthly!$C$18:$BJ$18) -> 179448.66 | D7: =SUMIF(Monthly!$C$5:$BJ$5,D$3,Monthly!$C$18:$BJ$18) -> 184832.12 | E7: =SUMIF(Monthly!$C$5:$BJ$5,E$3,Monthly!$C$18:$BJ$18) -> 190377.08 | F7: =SUMIF(Monthly!$C$5:$BJ$5,F$3,Monthly!$C$18:$BJ$18) -> 196088.4
A8: Gross margin | B8: =IF(B5=0,0,B7/B5) -> 0.88594966 | C8: =IF(C5=0,0,C7/C5) -> 0.88594966 | D8: =IF(D5=0,0,D7/D5) -> 0.88594966 | E8: =IF(E5=0,0,E7/E5) -> 0.88594966 | F8: =IF(F5=0,0,F7/F5) -> 0.88594966
A9: Property tax | B9: =SUMIF(Monthly!$C$5:$BJ$5,B$3,Monthly!$C$21:$BJ$21) -> -20350 | C9: =SUMIF(Monthly!$C$5:$BJ$5,C$3,Monthly!$C$21:$BJ$21) -> -20960.5 | D9: =SUMIF(Monthly!$C$5:$BJ$5,D$3,Monthly!$C$21:$BJ$21) -> -21589.315 | E9: =SUMIF(Monthly!$C$5:$BJ$5,E$3,Monthly!$C$21:$BJ$21) -> -22236.994 | F9: =SUMIF(Monthly!$C$5:$BJ$5,F$3,Monthly!$C$21:$BJ$21) -> -22904.104
A10: Insurance | B10: =SUMIF(Monthly!$C$5:$BJ$5,B$3,Monthly!$C$22:$BJ$22) -> -8000 | C10: =SUMIF(Monthly!$C$5:$BJ$5,C$3,Monthly!$C$22:$BJ$22) -> -8240 | D10: =SUMIF(Monthly!$C$5:$BJ$5,D$3,Monthly!$C$22:$BJ$22) -> -8487.2 | E10: =SUMIF(Monthly!$C$5:$BJ$5,E$3,Monthly!$C$22:$BJ$22) -> -8741.816 | F10: =SUMIF(Monthly!$C$5:$BJ$5,F$3,Monthly!$C$22:$BJ$22) -> -9004.0705
A11: Property management | B11: =SUMIF(Monthly!$C$5:$BJ$5,B$3,Monthly!$C$23:$BJ$23) -> -15732 | C11: =SUMIF(Monthly!$C$5:$BJ$5,C$3,Monthly!$C$23:$BJ$23) -> -16203.96 | D11: =SUMIF(Monthly!$C$5:$BJ$5,D$3,Monthly!$C$23:$BJ$23) -> -16690.079 | E11: =SUMIF(Monthly!$C$5:$BJ$5,E$3,Monthly!$C$23:$BJ$23) -> -17190.781 | F11: =SUMIF(Monthly!$C$5:$BJ$5,F$3,Monthly!$C$23:$BJ$23) -> -17706.505
A12: Legal, accounting & other G&A | B12: =SUMIF(Monthly!$C$5:$BJ$5,B$3,Monthly!$C$24:$BJ$24) -> -4800 | C12: =SUMIF(Monthly!$C$5:$BJ$5,C$3,Monthly!$C$24:$BJ$24) -> -4944 | D12: =SUMIF(Monthly!$C$5:$BJ$5,D$3,Monthly!$C$24:$BJ$24) -> -5092.32 | E12: =SUMIF(Monthly!$C$5:$BJ$5,E$3,Monthly!$C$24:$BJ$24) -> -5245.0896 | F12: =SUMIF(Monthly!$C$5:$BJ$5,F$3,Monthly!$C$24:$BJ$24) -> -5402.4423
A13: Total operating expenses | B13: =SUMIF(Monthly!$C$5:$BJ$5,B$3,Monthly!$C$25:$BJ$25) -> -48882 | C13: =SUMIF(Monthly!$C$5:$BJ$5,C$3,Monthly!$C$25:$BJ$25) -> -50348.46 | D13: =SUMIF(Monthly!$C$5:$BJ$5,D$3,Monthly!$C$25:$BJ$25) -> -51858.914 | E13: =SUMIF(Monthly!$C$5:$BJ$5,E$3,Monthly!$C$25:$BJ$25) -> -53414.681 | F13: =SUMIF(Monthly!$C$5:$BJ$5,F$3,Monthly!$C$25:$BJ$25) -> -55017.122
A14: EBITDA | B14: =SUMIF(Monthly!$C$5:$BJ$5,B$3,Monthly!$C$26:$BJ$26) -> 125340 | C14: =SUMIF(Monthly!$C$5:$BJ$5,C$3,Monthly!$C$26:$BJ$26) -> 129100.2 | D14: =SUMIF(Monthly!$C$5:$BJ$5,D$3,Monthly!$C$26:$BJ$26) -> 132973.21 | E14: =SUMIF(Monthly!$C$5:$BJ$5,E$3,Monthly!$C$26:$BJ$26) -> 136962.4 | F14: =SUMIF(Monthly!$C$5:$BJ$5,F$3,Monthly!$C$26:$BJ$26) -> 141071.27
A15: EBITDA margin | B15: =IF(B5=0,0,B14/B5) -> 0.63737605 | C15: =IF(C5=0,0,C14/C5) -> 0.63737605 | D15: =IF(D5=0,0,D14/D5) -> 0.63737605 | E15: =IF(E5=0,0,E14/E5) -> 0.63737605 | F15: =IF(F5=0,0,F14/F5) -> 0.63737605
A16: Depreciation | B16: =SUMIF(Monthly!$C$5:$BJ$5,B$3,Monthly!$C$44:$BJ$44) -> -56940.586 | C16: =SUMIF(Monthly!$C$5:$BJ$5,C$3,Monthly!$C$44:$BJ$44) -> -57072.323 | D16: =SUMIF(Monthly!$C$5:$BJ$5,D$3,Monthly!$C$44:$BJ$44) -> -57208.011 | E16: =SUMIF(Monthly!$C$5:$BJ$5,E$3,Monthly!$C$44:$BJ$44) -> -57347.77 | F16: =SUMIF(Monthly!$C$5:$BJ$5,F$3,Monthly!$C$44:$BJ$44) -> -57491.721
A17: EBIT | B17: =SUMIF(Monthly!$C$5:$BJ$5,B$3,Monthly!$C$29:$BJ$29) -> 68399.414 | C17: =SUMIF(Monthly!$C$5:$BJ$5,C$3,Monthly!$C$29:$BJ$29) -> 72027.877 | D17: =SUMIF(Monthly!$C$5:$BJ$5,D$3,Monthly!$C$29:$BJ$29) -> 75765.195 | E17: =SUMIF(Monthly!$C$5:$BJ$5,E$3,Monthly!$C$29:$BJ$29) -> 79614.633 | F17: =SUMIF(Monthly!$C$5:$BJ$5,F$3,Monthly!$C$29:$BJ$29) -> 83579.553
A18: Interest | B18: =SUMIF(Monthly!$C$5:$BJ$5,B$3,Monthly!$C$30:$BJ$30) -> -77605.09 | C18: =SUMIF(Monthly!$C$5:$BJ$5,C$3,Monthly!$C$30:$BJ$30) -> -76706.816 | D18: =SUMIF(Monthly!$C$5:$BJ$5,D$3,Monthly!$C$30:$BJ$30) -> -75748.383 | E18: =SUMIF(Monthly!$C$5:$BJ$5,E$3,Monthly!$C$30:$BJ$30) -> -74725.762 | F18: =SUMIF(Monthly!$C$5:$BJ$5,F$3,Monthly!$C$30:$BJ$30) -> -73634.655
A19: Pre-tax income | B19: =SUMIF(Monthly!$C$5:$BJ$5,B$3,Monthly!$C$31:$BJ$31) -> -9205.6762 | C19: =SUMIF(Monthly!$C$5:$BJ$5,C$3,Monthly!$C$31:$BJ$31) -> -4678.9386 | D19: =SUMIF(Monthly!$C$5:$BJ$5,D$3,Monthly!$C$31:$BJ$31) -> 16.812047 | E19: =SUMIF(Monthly!$C$5:$BJ$5,E$3,Monthly!$C$31:$BJ$31) -> 4888.8702 | F19: =SUMIF(Monthly!$C$5:$BJ$5,F$3,Monthly!$C$31:$BJ$31) -> 9944.8983
A20: Income tax | B20: =SUMIF(Monthly!$C$5:$BJ$5,B$3,Monthly!$C$34:$BJ$34) -> 0 | C20: =SUMIF(Monthly!$C$5:$BJ$5,C$3,Monthly!$C$34:$BJ$34) -> 0 | D20: =SUMIF(Monthly!$C$5:$BJ$5,D$3,Monthly!$C$34:$BJ$34) -> 0 | E20: =SUMIF(Monthly!$C$5:$BJ$5,E$3,Monthly!$C$34:$BJ$34) -> 0 | F20: =SUMIF(Monthly!$C$5:$BJ$5,F$3,Monthly!$C$34:$BJ$34) -> -202.85282
A21: Net income | B21: =SUMIF(Monthly!$C$5:$BJ$5,B$3,Monthly!$C$35:$BJ$35) -> -9205.6762 | C21: =SUMIF(Monthly!$C$5:$BJ$5,C$3,Monthly!$C$35:$BJ$35) -> -4678.9386 | D21: =SUMIF(Monthly!$C$5:$BJ$5,D$3,Monthly!$C$35:$BJ$35) -> 16.812047 | E21: =SUMIF(Monthly!$C$5:$BJ$5,E$3,Monthly!$C$35:$BJ$35) -> 4888.8702 | F21: =SUMIF(Monthly!$C$5:$BJ$5,F$3,Monthly!$C$35:$BJ$35) -> 9742.0455
A22: Net margin | B22: =IF(B5=0,0,B21/B5) -> -0.04681249 | C22: =IF(C5=0,0,C21/C5) -> -0.023100223 | D22: =IF(D5=0,0,D21/D5) -> 8.0584628e-05 | E22: =IF(E5=0,0,E21/E5) -> 0.022751125 | F22: =IF(F5=0,0,F21/F5) -> 0.044015669

Sheet Cash Flow
A1: Annual cash flow statement | H1: =HYPERLINK("#'Cover'!A1","◂ Contents") -> ◂ Contents
A2: Rolled up from the period detail (SUMIF on the year row; balances at year end).
A3: Year # | B3: 1 | C3: 2 | D3: 3 | E3: 4 | F3: 5
B4: Year 1 | C4: Year 2 | D4: Year 3 | E4: Year 4 | F4: Year 5
A5: Net income | B5: =SUMIF(Monthly!$C$5:$BJ$5,B$3,Monthly!$C$35:$BJ$35) -> -9205.6762 | C5: =SUMIF(Monthly!$C$5:$BJ$5,C$3,Monthly!$C$35:$BJ$35) -> -4678.9386 | D5: =SUMIF(Monthly!$C$5:$BJ$5,D$3,Monthly!$C$35:$BJ$35) -> 16.812047 | E5: =SUMIF(Monthly!$C$5:$BJ$5,E$3,Monthly!$C$35:$BJ$35) -> 4888.8702 | F5: =SUMIF(Monthly!$C$5:$BJ$5,F$3,Monthly!$C$35:$BJ$35) -> 9742.0455
A6: Add back depreciation | B6: =-SUMIF(Monthly!$C$5:$BJ$5,B$3,Monthly!$C$44:$BJ$44) -> 56940.586 | C6: =-SUMIF(Monthly!$C$5:$BJ$5,C$3,Monthly!$C$44:$BJ$44) -> 57072.323 | D6: =-SUMIF(Monthly!$C$5:$BJ$5,D$3,Monthly!$C$44:$BJ$44) -> 57208.011 | E6: =-SUMIF(Monthly!$C$5:$BJ$5,E$3,Monthly!$C$44:$BJ$44) -> 57347.77 | F6: =-SUMIF(Monthly!$C$5:$BJ$5,F$3,Monthly!$C$44:$BJ$44) -> 57491.721
A7: (Increase) / decrease in receivables | B7: =SUMIF(Monthly!$C$5:$BJ$5,B$3,Monthly!$C$60:$BJ$60) -> 0 | C7: =SUMIF(Monthly!$C$5:$BJ$5,C$3,Monthly!$C$60:$BJ$60) -> 0 | D7: =SUMIF(Monthly!$C$5:$BJ$5,D$3,Monthly!$C$60:$BJ$60) -> 0 | E7: =SUMIF(Monthly!$C$5:$BJ$5,E$3,Monthly!$C$60:$BJ$60) -> 0 | F7: =SUMIF(Monthly!$C$5:$BJ$5,F$3,Monthly!$C$60:$BJ$60) -> 0
A8: (Increase) / decrease in inventory | B8: =SUMIF(Monthly!$C$5:$BJ$5,B$3,Monthly!$C$61:$BJ$61) -> 0 | C8: =SUMIF(Monthly!$C$5:$BJ$5,C$3,Monthly!$C$61:$BJ$61) -> 0 | D8: =SUMIF(Monthly!$C$5:$BJ$5,D$3,Monthly!$C$61:$BJ$61) -> 0 | E8: =SUMIF(Monthly!$C$5:$BJ$5,E$3,Monthly!$C$61:$BJ$61) -> 0 | F8: =SUMIF(Monthly!$C$5:$BJ$5,F$3,Monthly!$C$61:$BJ$61) -> 0
A9: Increase / (decrease) in payables | B9: =SUMIF(Monthly!$C$5:$BJ$5,B$3,Monthly!$C$62:$BJ$62) -> 934.5 | C9: =SUMIF(Monthly!$C$5:$BJ$5,C$3,Monthly!$C$62:$BJ$62) -> 28.035 | D9: =SUMIF(Monthly!$C$5:$BJ$5,D$3,Monthly!$C$62:$BJ$62) -> 28.87605 | E9: =SUMIF(Monthly!$C$5:$BJ$5,E$3,Monthly!$C$62:$BJ$62) -> 29.742332 | F9: =SUMIF(Monthly!$C$5:$BJ$5,F$3,Monthly!$C$62:$BJ$62) -> 30.634601
A10: Operating cash flow | B10: =SUMIF(Monthly!$C$5:$BJ$5,B$3,Monthly!$C$65:$BJ$65) -> 48669.41 | C10: =SUMIF(Monthly!$C$5:$BJ$5,C$3,Monthly!$C$65:$BJ$65) -> 52421.419 | D10: =SUMIF(Monthly!$C$5:$BJ$5,D$3,Monthly!$C$65:$BJ$65) -> 57253.699 | E10: =SUMIF(Monthly!$C$5:$BJ$5,E$3,Monthly!$C$65:$BJ$65) -> 62266.382 | F10: =SUMIF(Monthly!$C$5:$BJ$5,F$3,Monthly!$C$65:$BJ$65) -> 67264.401
A11: Capital spending | B11: =SUMIF(Monthly!$C$5:$BJ$5,B$3,Monthly!$C$66:$BJ$66) -> -1909000 | C11: =SUMIF(Monthly!$C$5:$BJ$5,C$3,Monthly!$C$66:$BJ$66) -> -3605 | D11: =SUMIF(Monthly!$C$5:$BJ$5,D$3,Monthly!$C$66:$BJ$66) -> -3713.15 | E11: =SUMIF(Monthly!$C$5:$BJ$5,E$3,Monthly!$C$66:$BJ$66) -> -3824.5445 | F11: =SUMIF(Monthly!$C$5:$BJ$5,F$3,Monthly!$C$66:$BJ$66) -> -3939.2808
A12: Equity raised | B12: =SUMIF(Monthly!$C$5:$BJ$5,B$3,Monthly!$C$67:$BJ$67) -> 760000 | C12: =SUMIF(Monthly!$C$5:$BJ$5,C$3,Monthly!$C$67:$BJ$67) -> 0 | D12: =SUMIF(Monthly!$C$5:$BJ$5,D$3,Monthly!$C$67:$BJ$67) -> 0 | E12: =SUMIF(Monthly!$C$5:$BJ$5,E$3,Monthly!$C$67:$BJ$67) -> 0 | F12: =SUMIF(Monthly!$C$5:$BJ$5,F$3,Monthly!$C$67:$BJ$67) -> 0
A13: Loan drawdown | B13: =SUMIF(Monthly!$C$5:$BJ$5,B$3,Monthly!$C$50:$BJ$50) -> 1200000 | C13: =SUMIF(Monthly!$C$5:$BJ$5,C$3,Monthly!$C$50:$BJ$50) -> 0 | D13: =SUMIF(Monthly!$C$5:$BJ$5,D$3,Monthly!$C$50:$BJ$50) -> 0 | E13: =SUMIF(Monthly!$C$5:$BJ$5,E$3,Monthly!$C$50:$BJ$50) -> 0 | F13: =SUMIF(Monthly!$C$5:$BJ$5,F$3,Monthly!$C$50:$BJ$50) -> 0
A14: Loan repayment | B14: =SUMIF(Monthly!$C$5:$BJ$5,B$3,Monthly!$C$52:$BJ$52) -> -13412.706 | C14: =SUMIF(Monthly!$C$5:$BJ$5,C$3,Monthly!$C$52:$BJ$52) -> -14310.979 | D14: =SUMIF(Monthly!$C$5:$BJ$5,D$3,Monthly!$C$52:$BJ$52) -> -15269.412 | E14: =SUMIF(Monthly!$C$5:$BJ$5,E$3,Monthly!$C$52:$BJ$52) -> -16292.033 | F14: =SUMIF(Monthly!$C$5:$BJ$5,F$3,Monthly!$C$52:$BJ$52) -> -17383.141
A15: Financing cash flow | B15: =SUMIF(Monthly!$C$5:$BJ$5,B$3,Monthly!$C$68:$BJ$68) -> 1946587.3 | C15: =SUMIF(Monthly!$C$5:$BJ$5,C$3,Monthly!$C$68:$BJ$68) -> -14310.979 | D15: =SUMIF(Monthly!$C$5:$BJ$5,D$3,Monthly!$C$68:$BJ$68) -> -15269.412 | E15: =SUMIF(Monthly!$C$5:$BJ$5,E$3,Monthly!$C$68:$BJ$68) -> -16292.033 | F15: =SUMIF(Monthly!$C$5:$BJ$5,F$3,Monthly!$C$68:$BJ$68) -> -17383.141
A16: Net change in cash | B16: =SUMIF(Monthly!$C$5:$BJ$5,B$3,Monthly!$C$69:$BJ$69) -> 86256.705 | C16: =SUMIF(Monthly!$C$5:$BJ$5,C$3,Monthly!$C$69:$BJ$69) -> 34505.44 | D16: =SUMIF(Monthly!$C$5:$BJ$5,D$3,Monthly!$C$69:$BJ$69) -> 38271.137 | E16: =SUMIF(Monthly!$C$5:$BJ$5,E$3,Monthly!$C$69:$BJ$69) -> 42149.805 | F16: =SUMIF(Monthly!$C$5:$BJ$5,F$3,Monthly!$C$69:$BJ$69) -> 45941.98
A17: Opening cash | B17: =INDEX(Monthly!$C$70:$BJ$70,(B$3-1)*12+1) -> 0 | C17: =INDEX(Monthly!$C$70:$BJ$70,(C$3-1)*12+1) -> 86256.705 | D17: =INDEX(Monthly!$C$70:$BJ$70,(D$3-1)*12+1) -> 120762.14 | E17: =INDEX(Monthly!$C$70:$BJ$70,(E$3-1)*12+1) -> 159033.28 | F17: =INDEX(Monthly!$C$70:$BJ$70,(F$3-1)*12+1) -> 201183.09
A18: Closing cash | B18: =INDEX(Monthly!$C$71:$BJ$71,B$3*12) -> 86256.705 | C18: =INDEX(Monthly!$C$71:$BJ$71,C$3*12) -> 120762.14 | D18: =INDEX(Monthly!$C$71:$BJ$71,D$3*12) -> 159033.28 | E18: =INDEX(Monthly!$C$71:$BJ$71,E$3*12) -> 201183.09 | F18: =INDEX(Monthly!$C$71:$BJ$71,F$3*12) -> 247125.07

Sheet Balance Sheet
A1: Balance sheet at year end | H1: =HYPERLINK("#'Cover'!A1","◂ Contents") -> ◂ Contents
A2: Rolled up from the period detail (SUMIF on the year row; balances at year end).
A3: Year # | B3: 1 | C3: 2 | D3: 3 | E3: 4 | F3: 5
B4: Year 1 | C4: Year 2 | D4: Year 3 | E4: Year 4 | F4: Year 5
A5: Cash | B5: =INDEX(Monthly!$C$71:$BJ$71,B$3*12) -> 86256.705 | C5: =INDEX(Monthly!$C$71:$BJ$71,C$3*12) -> 120762.14 | D5: =INDEX(Monthly!$C$71:$BJ$71,D$3*12) -> 159033.28 | E5: =INDEX(Monthly!$C$71:$BJ$71,E$3*12) -> 201183.09 | F5: =INDEX(Monthly!$C$71:$BJ$71,F$3*12) -> 247125.07
A6: Accounts receivable | B6: =INDEX(Monthly!$C$57:$BJ$57,B$3*12) -> 0 | C6: =INDEX(Monthly!$C$57:$BJ$57,C$3*12) -> 0 | D6: =INDEX(Monthly!$C$57:$BJ$57,D$3*12) -> 0 | E6: =INDEX(Monthly!$C$57:$BJ$57,E$3*12) -> 0 | F6: =INDEX(Monthly!$C$57:$BJ$57,F$3*12) -> 0
A7: Inventory | B7: =INDEX(Monthly!$C$58:$BJ$58,B$3*12) -> 0 | C7: =INDEX(Monthly!$C$58:$BJ$58,C$3*12) -> 0 | D7: =INDEX(Monthly!$C$58:$BJ$58,D$3*12) -> 0 | E7: =INDEX(Monthly!$C$58:$BJ$58,E$3*12) -> 0 | F7: =INDEX(Monthly!$C$58:$BJ$58,F$3*12) -> 0
A8: Net fixed assets | B8: =INDEX(Monthly!$C$46:$BJ$46,B$3*12) -> 1852059.4 | C8: =INDEX(Monthly!$C$46:$BJ$46,C$3*12) -> 1798592.1 | D8: =INDEX(Monthly!$C$46:$BJ$46,D$3*12) -> 1745097.2 | E8: =INDEX(Monthly!$C$46:$BJ$46,E$3*12) -> 1691574 | F8: =INDEX(Monthly!$C$46:$BJ$46,F$3*12) -> 1638021.6
A9: Total assets | B9: =INDEX(Monthly!$C$85:$BJ$85,B$3*12) -> 1938316.1 | C9: =INDEX(Monthly!$C$85:$BJ$85,C$3*12) -> 1919354.2 | D9: =INDEX(Monthly!$C$85:$BJ$85,D$3*12) -> 1904130.5 | E9: =INDEX(Monthly!$C$85:$BJ$85,E$3*12) -> 1892757.1 | F9: =INDEX(Monthly!$C$85:$BJ$85,F$3*12) -> 1885146.6
A10: Accounts payable | B10: =INDEX(Monthly!$C$59:$BJ$59,B$3*12) -> 934.5 | C10: =INDEX(Monthly!$C$59:$BJ$59,C$3*12) -> 962.535 | D10: =INDEX(Monthly!$C$59:$BJ$59,D$3*12) -> 991.41105 | E10: =INDEX(Monthly!$C$59:$BJ$59,E$3*12) -> 1021.1534 | F10: =INDEX(Monthly!$C$59:$BJ$59,F$3*12) -> 1051.788
A11: Loan | B11: =INDEX(Monthly!$C$54:$BJ$54,B$3*12) -> 1186587.3 | C11: =INDEX(Monthly!$C$54:$BJ$54,C$3*12) -> 1172276.3 | D11: =INDEX(Monthly!$C$54:$BJ$54,D$3*12) -> 1157006.9 | E11: =INDEX(Monthly!$C$54:$BJ$54,E$3*12) -> 1140714.9 | F11: =INDEX(Monthly!$C$54:$BJ$54,F$3*12) -> 1123331.7
A12: Total liabilities | B12: =INDEX(Monthly!$C$86:$BJ$86,B$3*12) -> 1187521.8 | C12: =INDEX(Monthly!$C$86:$BJ$86,C$3*12) -> 1173238.9 | D12: =INDEX(Monthly!$C$86:$BJ$86,D$3*12) -> 1157998.3 | E12: =INDEX(Monthly!$C$86:$BJ$86,E$3*12) -> 1141736 | F12: =INDEX(Monthly!$C$86:$BJ$86,F$3*12) -> 1124383.5
A13: Paid-in capital | B13: =INDEX(Monthly!$C$83:$BJ$83,B$3*12) -> 760000 | C13: =INDEX(Monthly!$C$83:$BJ$83,C$3*12) -> 760000 | D13: =INDEX(Monthly!$C$83:$BJ$83,D$3*12) -> 760000 | E13: =INDEX(Monthly!$C$83:$BJ$83,E$3*12) -> 760000 | F13: =INDEX(Monthly!$C$83:$BJ$83,F$3*12) -> 760000
A14: Retained earnings | B14: =INDEX(Monthly!$C$84:$BJ$84,B$3*12) -> -9205.6762 | C14: =INDEX(Monthly!$C$84:$BJ$84,C$3*12) -> -13884.615 | D14: =INDEX(Monthly!$C$84:$BJ$84,D$3*12) -> -13867.803 | E14: =INDEX(Monthly!$C$84:$BJ$84,E$3*12) -> -8978.9325 | F14: =INDEX(Monthly!$C$84:$BJ$84,F$3*12) -> 763.11298
A15: Total equity | B15: =INDEX(Monthly!$C$87:$BJ$87,B$3*12) -> 750794.32 | C15: =INDEX(Monthly!$C$87:$BJ$87,C$3*12) -> 746115.39 | D15: =INDEX(Monthly!$C$87:$BJ$87,D$3*12) -> 746132.2 | E15: =INDEX(Monthly!$C$87:$BJ$87,E$3*12) -> 751021.07 | F15: =INDEX(Monthly!$C$87:$BJ$87,F$3*12) -> 760763.11
A16: Total liabilities & equity | B16: =INDEX(Monthly!$C$88:$BJ$88,B$3*12) -> 1938316.1 | C16: =INDEX(Monthly!$C$88:$BJ$88,C$3*12) -> 1919354.2 | D16: =INDEX(Monthly!$C$88:$BJ$88,D$3*12) -> 1904130.5 | E16: =INDEX(Monthly!$C$88:$BJ$88,E$3*12) -> 1892757.1 | F16: =INDEX(Monthly!$C$88:$BJ$88,F$3*12) -> 1885146.6
A17: Check: assets − liabilities − equity (must be 0) | B17: =INDEX(Monthly!$C$89:$BJ$89,B$3*12) -> 0 | C17: =INDEX(Monthly!$C$89:$BJ$89,C$3*12) -> 0 | D17: =INDEX(Monthly!$C$89:$BJ$89,D$3*12) -> 0 | E17: =INDEX(Monthly!$C$89:$BJ$89,E$3*12) -> 0 | F17: =INDEX(Monthly!$C$89:$BJ$89,F$3*12) -> 0

Sheet Monthly
A1: Monthly projection | D1: =HYPERLINK("#'Cover'!A1","◂ Contents") -> ◂ Contents
A2: $ unless stated; costs shown as negatives. Every period uses the same formula.
A3: Month | C3: M1 | D3: M2 | E3: M3 | F3: M4 | G3: M5 | H3: M6 | I3: M7 | J3: M8 | K3: M9 | L3: M10 | M3: M11 | N3: M12 | O3: M13 | P3: M14 | Q3: M15 | R3: M16 | S3: M17 | T3: M18 | U3: M19 | V3: M20 | W3: M21 | X3: M22 | Y3: M23 | Z3: M24 | AA3: M25 | AB3: M26 | AC3: M27 | AD3: M28 | AE3: M29 | AF3: M30 | AG3: M31 | AH3: M32 | AI3: M33 | AJ3: M34 | AK3: M35 | AL3: M36 | AM3: M37 | AN3: M38 | AO3: M39 | AP3: M40 | AQ3: M41 | AR3: M42 | AS3: M43 | AT3: M44 | AU3: M45 | AV3: M46 | AW3: M47 | AX3: M48 | AY3: M49 | AZ3: M50 | BA3: M51 | BB3: M52 | BC3: M53 | BD3: M54 | BE3: M55 | BF3: M56 | BG3: M57 | BH3: M58 | BI3: M59 | BJ3: M60
A4: Period # | C4: 1 | D4: 2 | E4: 3 | F4: 4 | G4: 5 | H4: 6 | I4: 7 | J4: 8 | K4: 9 | L4: 10 | M4: 11 | N4: 12 | O4: 13 | P4: 14 | Q4: 15 | R4: 16 | S4: 17 | T4: 18 | U4: 19 | V4: 20 | W4: 21 | X4: 22 | Y4: 23 | Z4: 24 | AA4: 25 | AB4: 26 | AC4: 27 | AD4: 28 | AE4: 29 | AF4: 30 | AG4: 31 | AH4: 32 | AI4: 33 | AJ4: 34 | AK4: 35 | AL4: 36 | AM4: 37 | AN4: 38 | AO4: 39 | AP4: 40 | AQ4: 41 | AR4: 42 | AS4: 43 | AT4: 44 | AU4: 45 | AV4: 46 | AW4: 47 | AX4: 48 | AY4: 49 | AZ4: 50 | BA4: 51 | BB4: 52 | BC4: 53 | BD4: 54 | BE4: 55 | BF4: 56 | BG4: 57 | BH4: 58 | BI4: 59 | BJ4: 60
A5: Year # | C5: =ROUNDUP(C4*1/12,0) -> 1 | D5: =ROUNDUP(D4*1/12,0) -> 1 | E5: =ROUNDUP(E4*1/12,0) -> 1 | F5: =ROUNDUP(F4*1/12,0) -> 1 | G5: =ROUNDUP(G4*1/12,0) -> 1 | H5: =ROUNDUP(H4*1/12,0) -> 1 | I5: =ROUNDUP(I4*1/12,0) -> 1 | J5: =ROUNDUP(J4*1/12,0) -> 1 | ... BJ5: =ROUNDUP(BJ4*1/12,0) -> 5
A7: Rent roll
A8: Average rent per unit per month | C8: =Inputs!$E$13*(1+Inputs!$E$14)^(C$5-1) -> 1700 | D8: =Inputs!$E$13*(1+Inputs!$E$14)^(D$5-1) -> 1700 | E8: =Inputs!$E$13*(1+Inputs!$E$14)^(E$5-1) -> 1700 | F8: =Inputs!$E$13*(1+Inputs!$E$14)^(F$5-1) -> 1700 | G8: =Inputs!$E$13*(1+Inputs!$E$14)^(G$5-1) -> 1700 | H8: =Inputs!$E$13*(1+Inputs!$E$14)^(H$5-1) -> 1700 | I8: =Inputs!$E$13*(1+Inputs!$E$14)^(I$5-1) -> 1700 | J8: =Inputs!$E$13*(1+Inputs!$E$14)^(J$5-1) -> 1700 | ... BJ8: =Inputs!$E$13*(1+Inputs!$E$14)^(BJ$5-1) -> 1913.365
A9: Gross potential rent (all units let) | C9: =Inputs!$E$10*C8*1 -> 17000 | D9: =Inputs!$E$10*D8*1 -> 17000 | E9: =Inputs!$E$10*E8*1 -> 17000 | F9: =Inputs!$E$10*F8*1 -> 17000 | G9: =Inputs!$E$10*G8*1 -> 17000 | H9: =Inputs!$E$10*H8*1 -> 17000 | I9: =Inputs!$E$10*I8*1 -> 17000 | J9: =Inputs!$E$10*J8*1 -> 17000 | ... BJ9: =Inputs!$E$10*BJ8*1 -> 19133.65
A10: Vacancy & credit loss | C10: =-C9*Inputs!$E$15 -> -850 | D10: =-D9*Inputs!$E$15 -> -850 | E10: =-E9*Inputs!$E$15 -> -850 | F10: =-F9*Inputs!$E$15 -> -850 | G10: =-G9*Inputs!$E$15 -> -850 | H10: =-H9*Inputs!$E$15 -> -850 | I10: =-I9*Inputs!$E$15 -> -850 | J10: =-J9*Inputs!$E$15 -> -850 | ... BJ10: =-BJ9*Inputs!$E$15 -> -956.68249
A11: Other income (parking, laundry, fees) | C11: =Inputs!$E$10*Inputs!$E$16*(1+Inputs!$E$14)^(C$5-1)*(1-Inputs!$E$15)*1 -> 237.5 | D11: =Inputs!$E$10*Inputs!$E$16*(1+Inputs!$E$14)^(D$5-1)*(1-Inputs!$E$15)*1 -> 237.5 | E11: =Inputs!$E$10*Inputs!$E$16*(1+Inputs!$E$14)^(E$5-1)*(1-Inputs!$E$15)*1 -> 237.5 | F11: =Inputs!$E$10*Inputs!$E$16*(1+Inputs!$E$14)^(F$5-1)*(1-Inputs!$E$15)*1 -> 237.5 | G11: =Inputs!$E$10*Inputs!$E$16*(1+Inputs!$E$14)^(G$5-1)*(1-Inputs!$E$15)*1 -> 237.5 | H11: =Inputs!$E$10*Inputs!$E$16*(1+Inputs!$E$14)^(H$5-1)*(1-Inputs!$E$15)*1 -> 237.5 | I11: =Inputs!$E$10*Inputs!$E$16*(1+Inputs!$E$14)^(I$5-1)*(1-Inputs!$E$15)*1 -> 237.5 | J11: =Inputs!$E$10*Inputs!$E$16*(1+Inputs!$E$14)^(J$5-1)*(1-Inputs!$E$15)*1 -> 237.5 | ... BJ11: =Inputs!$E$10*Inputs!$E$16*(1+Inputs!$E$14)^(BJ$5-1)*(1-Inputs!$E$15)*1 -> 267.30834
A12: Revenue (effective gross income) | C12: =C9+C10+C11 -> 16387.5 | D12: =D9+D10+D11 -> 16387.5 | E12: =E9+E10+E11 -> 16387.5 | F12: =F9+F10+F11 -> 16387.5 | G12: =G9+G10+G11 -> 16387.5 | H12: =H9+H10+H11 -> 16387.5 | I12: =I9+I10+I11 -> 16387.5 | J12: =J9+J10+J11 -> 16387.5 | ... BJ12: =BJ9+BJ10+BJ11 -> 18444.276
A14: Direct property costs
A15: Repairs & maintenance | C15: =-(C9+C10)*Inputs!$E$19 -> -969 | D15: =-(D9+D10)*Inputs!$E$19 -> -969 | E15: =-(E9+E10)*Inputs!$E$19 -> -969 | F15: =-(F9+F10)*Inputs!$E$19 -> -969 | G15: =-(G9+G10)*Inputs!$E$19 -> -969 | H15: =-(H9+H10)*Inputs!$E$19 -> -969 | I15: =-(I9+I10)*Inputs!$E$19 -> -969 | J15: =-(J9+J10)*Inputs!$E$19 -> -969 | ... BJ15: =-(BJ9+BJ10)*Inputs!$E$19 -> -1090.618
A16: Owner-paid utilities & common areas | C16: =-Inputs!$E$20*(1+Inputs!$E$25)^(C$5-1)*1 -> -900 | D16: =-Inputs!$E$20*(1+Inputs!$E$25)^(D$5-1)*1 -> -900 | E16: =-Inputs!$E$20*(1+Inputs!$E$25)^(E$5-1)*1 -> -900 | F16: =-Inputs!$E$20*(1+Inputs!$E$25)^(F$5-1)*1 -> -900 | G16: =-Inputs!$E$20*(1+Inputs!$E$25)^(G$5-1)*1 -> -900 | H16: =-Inputs!$E$20*(1+Inputs!$E$25)^(H$5-1)*1 -> -900 | I16: =-Inputs!$E$20*(1+Inputs!$E$25)^(I$5-1)*1 -> -900 | J16: =-Inputs!$E$20*(1+Inputs!$E$25)^(J$5-1)*1 -> -900 | ... BJ16: =-Inputs!$E$20*(1+Inputs!$E$25)^(BJ$5-1)*1 -> -1012.9579
A17: Direct property costs | C17: =C15+C16 -> -1869 | D17: =D15+D16 -> -1869 | E17: =E15+E16 -> -1869 | F17: =F15+F16 -> -1869 | G17: =G15+G16 -> -1869 | H17: =H15+H16 -> -1869 | I17: =I15+I16 -> -1869 | J17: =J15+J16 -> -1869 | ... BJ17: =BJ15+BJ16 -> -2103.576
A18: Gross profit | C18: =C12+C17 -> 14518.5 | D18: =D12+D17 -> 14518.5 | E18: =E12+E17 -> 14518.5 | F18: =F12+F17 -> 14518.5 | G18: =G12+G17 -> 14518.5 | H18: =H12+H17 -> 14518.5 | I18: =I12+I17 -> 14518.5 | J18: =J12+J17 -> 14518.5 | ... BJ18: =BJ12+BJ17 -> 16340.7
A20: Operating expenses
A21: Property tax | C21: =-Inputs!$E$7*Inputs!$E$21/12*(1+Inputs!$E$25)^(C$5-1)*1 -> -1695.8333 | D21: =-Inputs!$E$7*Inputs!$E$21/12*(1+Inputs!$E$25)^(D$5-1)*1 -> -1695.8333 | E21: =-Inputs!$E$7*Inputs!$E$21/12*(1+Inputs!$E$25)^(E$5-1)*1 -> -1695.8333 | F21: =-Inputs!$E$7*Inputs!$E$21/12*(1+Inputs!$E$25)^(F$5-1)*1 -> -1695.8333 | G21: =-Inputs!$E$7*Inputs!$E$21/12*(1+Inputs!$E$25)^(G$5-1)*1 -> -1695.8333 | H21: =-Inputs!$E$7*Inputs!$E$21/12*(1+Inputs!$E$25)^(H$5-1)*1 -> -1695.8333 | I21: =-Inputs!$E$7*Inputs!$E$21/12*(1+Inputs!$E$25)^(I$5-1)*1 -> -1695.8333 | J21: =-Inputs!$E$7*Inputs!$E$21/12*(1+Inputs!$E$25)^(J$5-1)*1 -> -1695.8333 | ... BJ21: =-Inputs!$E$7*Inputs!$E$21/12*(1+Inputs!$E$25)^(BJ$5-1)*1 -> -1908.6754
A22: Insurance | C22: =-Inputs!$E$10*Inputs!$E$22/12*(1+Inputs!$E$25)^(C$5-1)*1 -> -666.66667 | D22: =-Inputs!$E$10*Inputs!$E$22/12*(1+Inputs!$E$25)^(D$5-1)*1 -> -666.66667 | E22: =-Inputs!$E$10*Inputs!$E$22/12*(1+Inputs!$E$25)^(E$5-1)*1 -> -666.66667 | F22: =-Inputs!$E$10*Inputs!$E$22/12*(1+Inputs!$E$25)^(F$5-1)*1 -> -666.66667 | G22: =-Inputs!$E$10*Inputs!$E$22/12*(1+Inputs!$E$25)^(G$5-1)*1 -> -666.66667 | H22: =-Inputs!$E$10*Inputs!$E$22/12*(1+Inputs!$E$25)^(H$5-1)*1 -> -666.66667 | I22: =-Inputs!$E$10*Inputs!$E$22/12*(1+Inputs!$E$25)^(I$5-1)*1 -> -666.66667 | J22: =-Inputs!$E$10*Inputs!$E$22/12*(1+Inputs!$E$25)^(J$5-1)*1 -> -666.66667 | ... BJ22: =-Inputs!$E$10*Inputs!$E$22/12*(1+Inputs!$E$25)^(BJ$5-1)*1 -> -750.33921
A23: Property management | C23: =-C12*Inputs!$E$23 -> -1311 | D23: =-D12*Inputs!$E$23 -> -1311 | E23: =-E12*Inputs!$E$23 -> -1311 | F23: =-F12*Inputs!$E$23 -> -1311 | G23: =-G12*Inputs!$E$23 -> -1311 | H23: =-H12*Inputs!$E$23 -> -1311 | I23: =-I12*Inputs!$E$23 -> -1311 | J23: =-J12*Inputs!$E$23 -> -1311 | ... BJ23: =-BJ12*Inputs!$E$23 -> -1475.542
A24: Legal, accounting & other G&A | C24: =-Inputs!$E$24*(1+Inputs!$E$25)^(C$5-1)*1 -> -400 | D24: =-Inputs!$E$24*(1+Inputs!$E$25)^(D$5-1)*1 -> -400 | E24: =-Inputs!$E$24*(1+Inputs!$E$25)^(E$5-1)*1 -> -400 | F24: =-Inputs!$E$24*(1+Inputs!$E$25)^(F$5-1)*1 -> -400 | G24: =-Inputs!$E$24*(1+Inputs!$E$25)^(G$5-1)*1 -> -400 | H24: =-Inputs!$E$24*(1+Inputs!$E$25)^(H$5-1)*1 -> -400 | I24: =-Inputs!$E$24*(1+Inputs!$E$25)^(I$5-1)*1 -> -400 | J24: =-Inputs!$E$24*(1+Inputs!$E$25)^(J$5-1)*1 -> -400 | ... BJ24: =-Inputs!$E$24*(1+Inputs!$E$25)^(BJ$5-1)*1 -> -450.20352
A25: Total operating expenses | C25: =C21+C22+C23+C24 -> -4073.5 | D25: =D21+D22+D23+D24 -> -4073.5 | E25: =E21+E22+E23+E24 -> -4073.5 | F25: =F21+F22+F23+F24 -> -4073.5 | G25: =G21+G22+G23+G24 -> -4073.5 | H25: =H21+H22+H23+H24 -> -4073.5 | I25: =I21+I22+I23+I24 -> -4073.5 | J25: =J21+J22+J23+J24 -> -4073.5 | ... BJ25: =BJ21+BJ22+BJ23+BJ24 -> -4584.7601
A26: EBITDA | C26: =C18+C25 -> 10445 | D26: =D18+D25 -> 10445 | E26: =E18+E25 -> 10445 | F26: =F18+F25 -> 10445 | G26: =G18+G25 -> 10445 | H26: =H18+H25 -> 10445 | I26: =I18+I25 -> 10445 | J26: =J18+J25 -> 10445 | ... BJ26: =BJ18+BJ25 -> 11755.94
A28: Profit after depreciation, interest, tax
A29: EBIT | C29: =C26+C44 -> 5704.9023 | D29: =D26+D44 -> 5704.0021 | E29: =E26+E44 -> 5703.1019 | F29: =F26+F44 -> 5702.2016 | G29: =G26+G44 -> 5701.3014 | H29: =H26+H44 -> 5700.4012 | I29: =I26+I44 -> 5699.501 | J29: =J26+J44 -> 5698.6008 | ... BJ29: =BJ26+BJ44 -> 6959.3902
A30: Interest on loan (balance after drawdown, start of period) | C30: =-(C49+C50)*Inputs!$E$36/12 -> -6500 | D30: =-(D49+D50)*Inputs!$E$36/12 -> -6494.1239 | E30: =-(E49+E50)*Inputs!$E$36/12 -> -6488.216 | F30: =-(F49+F50)*Inputs!$E$36/12 -> -6482.2761 | G30: =-(G49+G50)*Inputs!$E$36/12 -> -6476.304 | H30: =-(H49+H50)*Inputs!$E$36/12 -> -6470.2995 | I30: =-(I49+I50)*Inputs!$E$36/12 -> -6464.2626 | J30: =-(J49+J50)*Inputs!$E$36/12 -> -6458.1929 | ... BJ30: =-(BJ49+BJ50)*Inputs!$E$36/12 -> -6092.7953
A31: Pre-tax income | C31: =C29+C30 -> -795.09774 | D31: =D29+D30 -> -790.12185 | E31: =E29+E30 -> -785.11414 | F31: =F29+F30 -> -780.07443 | G31: =G29+G30 -> -775.00254 | H31: =H29+H30 -> -769.89831 | I31: =I29+I30 -> -764.76155 | J31: =J29+J30 -> -759.59209 | ... BJ31: =BJ29+BJ30 -> 866.5949
A32: Helper: cumulative pre-tax income | C32: =C31 -> -795.09774 | D32: =C32+D31 -> -1585.2196 | E32: =D32+E31 -> -2370.3337 | F32: =E32+F31 -> -3150.4082 | G32: =F32+G31 -> -3925.4107 | H32: =G32+H31 -> -4695.309 | I32: =H32+I31 -> -5460.0706 | J32: =I32+J31 -> -6219.6627 | K32: =J32+K31 -> -6974.0524 | ... BJ32: =BI32+BJ31 -> 965.9658
A33: Helper: cumulative taxable income (losses carried forward) | C33: =MAX(0,C32) -> 0 | D33: =MAX(C33,D32) -> 0 | E33: =MAX(D33,E32) -> 0 | F33: =MAX(E33,F32) -> 0 | G33: =MAX(F33,G32) -> 0 | H33: =MAX(G33,H32) -> 0 | I33: =MAX(H33,I32) -> 0 | J33: =MAX(I33,J32) -> 0 | K33: =MAX(J33,K32) -> 0 | ... BJ33: =MAX(BI33,BJ32) -> 965.9658
A34: Income tax | C34: =-C33*Inputs!$E$46 -> 0 | D34: =-(D33-C33)*Inputs!$E$46 -> 0 | E34: =-(E33-D33)*Inputs!$E$46 -> 0 | F34: =-(F33-E33)*Inputs!$E$46 -> 0 | G34: =-(G33-F33)*Inputs!$E$46 -> 0 | H34: =-(H33-G33)*Inputs!$E$46 -> 0 | I34: =-(I33-H33)*Inputs!$E$46 -> 0 | J34: =-(J33-I33)*Inputs!$E$46 -> 0 | K34: =-(K33-J33)*Inputs!$E$46 -> 0 | ... BJ34: =-(BJ33-BI33)*Inputs!$E$46 -> -181.98493
A35: Net income | C35: =C31+C34 -> -795.09774 | D35: =D31+D34 -> -790.12185 | E35: =E31+E34 -> -785.11414 | F35: =F31+F34 -> -780.07443 | G35: =G31+G34 -> -775.00254 | H35: =H31+H34 -> -769.89831 | I35: =I31+I34 -> -764.76155 | J35: =J31+J34 -> -759.59209 | ... BJ35: =BJ31+BJ34 -> 684.60997
A37: Fixed assets & capital spending
A38: Property purchase incl. closing costs | C38: =IF(C$4=1,Inputs!$E$7*(1+Inputs!$E$9),0) -> 1905500 | D38: =IF(D$4=1,Inputs!$E$7*(1+Inputs!$E$9),0) -> 0 | E38: =IF(E$4=1,Inputs!$E$7*(1+Inputs!$E$9),0) -> 0 | F38: =IF(F$4=1,Inputs!$E$7*(1+Inputs!$E$9),0) -> 0 | G38: =IF(G$4=1,Inputs!$E$7*(1+Inputs!$E$9),0) -> 0 | H38: =IF(H$4=1,Inputs!$E$7*(1+Inputs!$E$9),0) -> 0 | I38: =IF(I$4=1,Inputs!$E$7*(1+Inputs!$E$9),0) -> 0 | J38: =IF(J$4=1,Inputs!$E$7*(1+Inputs!$E$9),0) -> 0 | ... BJ38: =IF(BJ$4=1,Inputs!$E$7*(1+Inputs!$E$9),0) -> 0
A39: of which land (not depreciated) | C39: =IF(C$4=1,Inputs!$E$7*Inputs!$E$8,0) -> 370000 | D39: =IF(D$4=1,Inputs!$E$7*Inputs!$E$8,0) -> 0 | E39: =IF(E$4=1,Inputs!$E$7*Inputs!$E$8,0) -> 0 | F39: =IF(F$4=1,Inputs!$E$7*Inputs!$E$8,0) -> 0 | G39: =IF(G$4=1,Inputs!$E$7*Inputs!$E$8,0) -> 0 | H39: =IF(H$4=1,Inputs!$E$7*Inputs!$E$8,0) -> 0 | I39: =IF(I$4=1,Inputs!$E$7*Inputs!$E$8,0) -> 0 | J39: =IF(J$4=1,Inputs!$E$7*Inputs!$E$8,0) -> 0 | ... BJ39: =IF(BJ$4=1,Inputs!$E$7*Inputs!$E$8,0) -> 0
A40: Capital reserve spent | C40: =Inputs!$E$10*Inputs!$E$26/12*(1+Inputs!$E$25)^(C$5-1)*1 -> 291.66667 | D40: =Inputs!$E$10*Inputs!$E$26/12*(1+Inputs!$E$25)^(D$5-1)*1 -> 291.66667 | E40: =Inputs!$E$10*Inputs!$E$26/12*(1+Inputs!$E$25)^(E$5-1)*1 -> 291.66667 | F40: =Inputs!$E$10*Inputs!$E$26/12*(1+Inputs!$E$25)^(F$5-1)*1 -> 291.66667 | G40: =Inputs!$E$10*Inputs!$E$26/12*(1+Inputs!$E$25)^(G$5-1)*1 -> 291.66667 | H40: =Inputs!$E$10*Inputs!$E$26/12*(1+Inputs!$E$25)^(H$5-1)*1 -> 291.66667 | I40: =Inputs!$E$10*Inputs!$E$26/12*(1+Inputs!$E$25)^(I$5-1)*1 -> 291.66667 | J40: =Inputs!$E$10*Inputs!$E$26/12*(1+Inputs!$E$25)^(J$5-1)*1 -> 291.66667 | ... BJ40: =Inputs!$E$10*Inputs!$E$26/12*(1+Inputs!$E$25)^(BJ$5-1)*1 -> 328.2734
A41: Capital spending | C41: =C38+C40 -> 1905791.7 | D41: =D38+D40 -> 291.66667 | E41: =E38+E40 -> 291.66667 | F41: =F38+F40 -> 291.66667 | G41: =G38+G40 -> 291.66667 | H41: =H38+H40 -> 291.66667 | I41: =I38+I40 -> 291.66667 | J41: =J38+J40 -> 291.66667 | ... BJ41: =BJ38+BJ40 -> 328.2734
A42: Fixed assets at cost | C42: =C41 -> 1905791.7 | D42: =C42+D41 -> 1906083.3 | E42: =D42+E41 -> 1906375 | F42: =E42+F41 -> 1906666.7 | G42: =F42+G41 -> 1906958.3 | H42: =G42+H41 -> 1907250 | I42: =H42+I41 -> 1907541.7 | J42: =I42+J41 -> 1907833.3 | K42: =J42+K41 -> 1908125 | ... BJ42: =BI42+BJ41 -> 1924082
A43: Land at cost (not depreciated) | C43: =C39 -> 370000 | D43: =C43+D39 -> 370000 | E43: =D43+E39 -> 370000 | F43: =E43+F39 -> 370000 | G43: =F43+G39 -> 370000 | H43: =G43+H39 -> 370000 | I43: =H43+I39 -> 370000 | J43: =I43+J39 -> 370000 | K43: =J43+K39 -> 370000 | ... BJ43: =BI43+BJ39 -> 370000
A44: Depreciation | C44: =-MIN((C42-C43)/MAX(1,Inputs!$E$45*12),C41-C43) -> -4740.0977 | D44: =-MIN((D42-D43)/MAX(1,Inputs!$E$45*12),C46+D41-D43) -> -4740.9979 | E44: =-MIN((E42-E43)/MAX(1,Inputs!$E$45*12),D46+E41-E43) -> -4741.8981 | F44: =-MIN((F42-F43)/MAX(1,Inputs!$E$45*12),E46+F41-F43) -> -4742.7984 | G44: =-MIN((G42-G43)/MAX(1,Inputs!$E$45*12),F46+G41-G43) -> -4743.6986 | H44: =-MIN((H42-H43)/MAX(1,Inputs!$E$45*12),G46+H41-H43) -> -4744.5988 | I44: =-MIN((I42-I43)/MAX(1,Inputs!$E$45*12),H46+I41-I43) -> -4745.499 | J44: =-MIN((J42-J43)/MAX(1,Inputs!$E$45*12),I46+J41-J43) -> -4746.3992 | K44: =-MIN((K42-K43)/MAX(1,Inputs!$E$45*12),J46+K41-K43) -> -4747.2994 | ... BJ44: =-MIN((BJ42-BJ43)/MAX(1,Inputs!$E$45*12),BI46+BJ41-BJ43) -> -4796.5493
A45: Accumulated depreciation | C45: =C44 -> -4740.0977 | D45: =C45+D44 -> -9481.0957 | E45: =D45+E44 -> -14222.994 | F45: =E45+F44 -> -18965.792 | G45: =F45+G44 -> -23709.491 | H45: =G45+H44 -> -28454.09 | I45: =H45+I44 -> -33199.588 | J45: =I45+J44 -> -37945.988 | K45: =J45+K44 -> -42693.287 | ... BJ45: =BI45+BJ44 -> -286060.41
A46: Net fixed assets | C46: =C42+C45 -> 1901051.6 | D46: =D42+D45 -> 1896602.2 | E46: =E42+E45 -> 1892152 | F46: =F42+F45 -> 1887700.9 | G46: =G42+G45 -> 1883248.8 | H46: =H42+H45 -> 1878795.9 | I46: =I42+I45 -> 1874342.1 | J46: =J42+J45 -> 1869887.3 | ... BJ46: =BJ42+BJ45 -> 1638021.6
A48: Debt
A49: Loan — opening balance | C49: =0 -> 0 | D49: =C54 -> 1198915.2 | E49: =D54 -> 1197824.5 | F49: =E54 -> 1196727.9 | G49: =F54 -> 1195625.4 | H49: =G54 -> 1194516.8 | I49: =H54 -> 1193402.3 | J49: =I54 -> 1192281.8 | K49: =J54 -> 1191155.1 | ... BJ49: =BI54 -> 1124823.8
A50: Loan drawdown | C50: =IF(C$4=1,Inputs!$E$35,0) -> 1200000 | D50: =IF(D$4=1,Inputs!$E$35,0) -> 0 | E50: =IF(E$4=1,Inputs!$E$35,0) -> 0 | F50: =IF(F$4=1,Inputs!$E$35,0) -> 0 | G50: =IF(G$4=1,Inputs!$E$35,0) -> 0 | H50: =IF(H$4=1,Inputs!$E$35,0) -> 0 | I50: =IF(I$4=1,Inputs!$E$35,0) -> 0 | J50: =IF(J$4=1,Inputs!$E$35,0) -> 0 | ... BJ50: =IF(BJ$4=1,Inputs!$E$35,0) -> 0
A51: Scheduled loan payment (principal + interest, level) | C51: =-PMT(Inputs!$E$36/12,MAX(1,Inputs!$E$37*12),Inputs!$E$35) -> 7584.8163 | D51: =-PMT(Inputs!$E$36/12,MAX(1,Inputs!$E$37*12),Inputs!$E$35) -> 7584.8163 | E51: =-PMT(Inputs!$E$36/12,MAX(1,Inputs!$E$37*12),Inputs!$E$35) -> 7584.8163 | F51: =-PMT(Inputs!$E$36/12,MAX(1,Inputs!$E$37*12),Inputs!$E$35) -> 7584.8163 | G51: =-PMT(Inputs!$E$36/12,MAX(1,Inputs!$E$37*12),Inputs!$E$35) -> 7584.8163 | H51: =-PMT(Inputs!$E$36/12,MAX(1,Inputs!$E$37*12),Inputs!$E$35) -> 7584.8163 | I51: =-PMT(Inputs!$E$36/12,MAX(1,Inputs!$E$37*12),Inputs!$E$35) -> 7584.8163 | J51: =-PMT(Inputs!$E$36/12,MAX(1,Inputs!$E$37*12),Inputs!$E$35) -> 7584.8163 | ... BJ51: =-PMT(Inputs!$E$36/12,MAX(1,Inputs!$E$37*12),Inputs!$E$35) -> 7584.8163
A52: Loan repayment (principal) | C52: =-MIN(C49+C50,C51+C30) -> -1084.8163 | D52: =-MIN(D49+D50,D51+D30) -> -1090.6924 | E52: =-MIN(E49+E50,E51+E30) -> -1096.6003 | F52: =-MIN(F49+F50,F51+F30) -> -1102.5402 | G52: =-MIN(G49+G50,G51+G30) -> -1108.5123 | H52: =-MIN(H49+H50,H51+H30) -> -1114.5167 | I52: =-MIN(I49+I50,I51+I30) -> -1120.5537 | J52: =-MIN(J49+J50,J51+J30) -> -1126.6234 | ... BJ52: =-MIN(BJ49+BJ50,BJ51+BJ30) -> -1492.021
A53: Debt service (interest + principal) | C53: =C30+C52 -> -7584.8163 | D53: =D30+D52 -> -7584.8163 | E53: =E30+E52 -> -7584.8163 | F53: =F30+F52 -> -7584.8163 | G53: =G30+G52 -> -7584.8163 | H53: =H30+H52 -> -7584.8163 | I53: =I30+I52 -> -7584.8163 | J53: =J30+J52 -> -7584.8163 | ... BJ53: =BJ30+BJ52 -> -7584.8163
A54: Loan — closing balance | C54: =C49+C50+C52 -> 1198915.2 | D54: =D49+D50+D52 -> 1197824.5 | E54: =E49+E50+E52 -> 1196727.9 | F54: =F49+F50+F52 -> 1195625.4 | G54: =G49+G50+G52 -> 1194516.8 | H54: =H49+H50+H52 -> 1193402.3 | I54: =I49+I50+I52 -> 1192281.8 | J54: =J49+J50+J52 -> 1191155.1 | ... BJ54: =BJ49+BJ50+BJ52 -> 1123331.7
A56: Working capital
A57: Accounts receivable | C57: =C12*Inputs!$E$40/30 -> 0 | D57: =D12*Inputs!$E$40/30 -> 0 | E57: =E12*Inputs!$E$40/30 -> 0 | F57: =F12*Inputs!$E$40/30 -> 0 | G57: =G12*Inputs!$E$40/30 -> 0 | H57: =H12*Inputs!$E$40/30 -> 0 | I57: =I12*Inputs!$E$40/30 -> 0 | J57: =J12*Inputs!$E$40/30 -> 0 | ... BJ57: =BJ12*Inputs!$E$40/30 -> 0
A58: Inventory | C58: =-C17*Inputs!$E$41/30 -> 0 | D58: =-D17*Inputs!$E$41/30 -> 0 | E58: =-E17*Inputs!$E$41/30 -> 0 | F58: =-F17*Inputs!$E$41/30 -> 0 | G58: =-G17*Inputs!$E$41/30 -> 0 | H58: =-H17*Inputs!$E$41/30 -> 0 | I58: =-I17*Inputs!$E$41/30 -> 0 | J58: =-J17*Inputs!$E$41/30 -> 0 | ... BJ58: =-BJ17*Inputs!$E$41/30 -> 0
A59: Accounts payable | C59: =-C17*Inputs!$E$42/30 -> 934.5 | D59: =-D17*Inputs!$E$42/30 -> 934.5 | E59: =-E17*Inputs!$E$42/30 -> 934.5 | F59: =-F17*Inputs!$E$42/30 -> 934.5 | G59: =-G17*Inputs!$E$42/30 -> 934.5 | H59: =-H17*Inputs!$E$42/30 -> 934.5 | I59: =-I17*Inputs!$E$42/30 -> 934.5 | J59: =-J17*Inputs!$E$42/30 -> 934.5 | ... BJ59: =-BJ17*Inputs!$E$42/30 -> 1051.788
A60: (Increase) / decrease in receivables | C60: =-C57 -> 0 | D60: =C57-D57 -> 0 | E60: =D57-E57 -> 0 | F60: =E57-F57 -> 0 | G60: =F57-G57 -> 0 | H60: =G57-H57 -> 0 | I60: =H57-I57 -> 0 | J60: =I57-J57 -> 0 | K60: =J57-K57 -> 0 | ... BJ60: =BI57-BJ57 -> 0
A61: (Increase) / decrease in inventory | C61: =-C58 -> 0 | D61: =C58-D58 -> 0 | E61: =D58-E58 -> 0 | F61: =E58-F58 -> 0 | G61: =F58-G58 -> 0 | H61: =G58-H58 -> 0 | I61: =H58-I58 -> 0 | J61: =I58-J58 -> 0 | K61: =J58-K58 -> 0 | ... BJ61: =BI58-BJ58 -> 0
A62: Increase / (decrease) in payables | C62: =C59 -> 934.5 | D62: =D59-C59 -> 0 | E62: =E59-D59 -> 0 | F62: =F59-E59 -> 0 | G62: =G59-F59 -> 0 | H62: =H59-G59 -> 0 | I62: =I59-H59 -> 0 | J62: =J59-I59 -> 0 | K62: =K59-J59 -> 0 | ... BJ62: =BJ59-BI59 -> 0
A64: Cash flow
A65: Operating cash flow | C65: =C35-C44+C60+C61+C62 -> 4879.5 | D65: =D35-D44+D60+D61+D62 -> 3950.8761 | E65: =E35-E44+E60+E61+E62 -> 3956.784 | F65: =F35-F44+F60+F61+F62 -> 3962.7239 | G65: =G35-G44+G60+G61+G62 -> 3968.696 | H65: =H35-H44+H60+H61+H62 -> 3974.7005 | I65: =I35-I44+I60+I61+I62 -> 3980.7374 | J65: =J35-J44+J60+J61+J62 -> 3986.8071 | ... BJ65: =BJ35-BJ44+BJ60+BJ61+BJ62 -> 5481.1593
A66: Investing cash flow (capex) | C66: =-C41 -> -1905791.7 | D66: =-D41 -> -291.66667 | E66: =-E41 -> -291.66667 | F66: =-F41 -> -291.66667 | G66: =-G41 -> -291.66667 | H66: =-H41 -> -291.66667 | I66: =-I41 -> -291.66667 | J66: =-J41 -> -291.66667 | ... BJ66: =-BJ41 -> -328.2734
A67: Equity raised | C67: =IF(C$4=1,Inputs!$E$34,0) -> 760000 | D67: =IF(D$4=1,Inputs!$E$34,0) -> 0 | E67: =IF(E$4=1,Inputs!$E$34,0) -> 0 | F67: =IF(F$4=1,Inputs!$E$34,0) -> 0 | G67: =IF(G$4=1,Inputs!$E$34,0) -> 0 | H67: =IF(H$4=1,Inputs!$E$34,0) -> 0 | I67: =IF(I$4=1,Inputs!$E$34,0) -> 0 | J67: =IF(J$4=1,Inputs!$E$34,0) -> 0 | ... BJ67: =IF(BJ$4=1,Inputs!$E$34,0) -> 0
A68: Financing cash flow | C68: =C67+C50+C52 -> 1958915.2 | D68: =D67+D50+D52 -> -1090.6924 | E68: =E67+E50+E52 -> -1096.6003 | F68: =F67+F50+F52 -> -1102.5402 | G68: =G67+G50+G52 -> -1108.5123 | H68: =H67+H50+H52 -> -1114.5167 | I68: =I67+I50+I52 -> -1120.5537 | J68: =J67+J50+J52 -> -1126.6234 | ... BJ68: =BJ67+BJ50+BJ52 -> -1492.021
A69: Net cash flow | C69: =C65+C66+C68 -> 58003.017 | D69: =D65+D66+D68 -> 2568.5171 | E69: =E65+E66+E68 -> 2568.5171 | F69: =F65+F66+F68 -> 2568.5171 | G69: =G65+G66+G68 -> 2568.5171 | H69: =H65+H66+H68 -> 2568.5171 | I69: =I65+I66+I68 -> 2568.5171 | J69: =J65+J66+J68 -> 2568.5171 | ... BJ69: =BJ65+BJ66+BJ68 -> 3660.8649
A70: Opening cash | C70: =0 -> 0 | D70: =C71 -> 58003.017 | E70: =D71 -> 60571.534 | F70: =E71 -> 63140.051 | G70: =F71 -> 65708.568 | H70: =G71 -> 68277.085 | I70: =H71 -> 70845.602 | J70: =I71 -> 73414.119 | K70: =J71 -> 75982.636 | ... BJ70: =BI71 -> 243464.2
A71: Closing cash | C71: =C70+C69 -> 58003.017 | D71: =D70+D69 -> 60571.534 | E71: =E70+E69 -> 63140.051 | F71: =F70+F69 -> 65708.568 | G71: =G70+G69 -> 68277.085 | H71: =H70+H69 -> 70845.602 | I71: =I70+I69 -> 73414.119 | J71: =J70+J69 -> 75982.636 | ... BJ71: =BJ70+BJ69 -> 247125.07
A72: Helper: EBITDA positive (1/0) | C72: =IF(C26>0,1,0) -> 1 | D72: =IF(D26>0,1,0) -> 1 | E72: =IF(E26>0,1,0) -> 1 | F72: =IF(F26>0,1,0) -> 1 | G72: =IF(G26>0,1,0) -> 1 | H72: =IF(H26>0,1,0) -> 1 | I72: =IF(I26>0,1,0) -> 1 | J72: =IF(J26>0,1,0) -> 1 | ... BJ72: =IF(BJ26>0,1,0) -> 1
A74: Goal modules
A75: Helper: net income positive (1/0) | C75: =IF(C35>0,1,0) -> 0 | D75: =IF(D35>0,1,0) -> 0 | E75: =IF(E35>0,1,0) -> 0 | F75: =IF(F35>0,1,0) -> 0 | G75: =IF(G35>0,1,0) -> 0 | H75: =IF(H35>0,1,0) -> 0 | I75: =IF(I35>0,1,0) -> 0 | J75: =IF(J35>0,1,0) -> 0 | ... BJ75: =IF(BJ35>0,1,0) -> 1
A76: Cash flow before financing (operating + investing) | C76: =C65+C66 -> -1900912.2 | D76: =D65+D66 -> 3659.2094 | E76: =E65+E66 -> 3665.1173 | F76: =F65+F66 -> 3671.0573 | G76: =G65+G66 -> 3677.0293 | H76: =H65+H66 -> 3683.0338 | I76: =I65+I66 -> 3689.0708 | J76: =J65+J66 -> 3695.1404 | ... BJ76: =BJ65+BJ66 -> 5152.8859
A77: Cumulative cash flow before financing | C77: =C76 -> -1900912.2 | D77: =C77+D76 -> -1897253 | E77: =D77+E76 -> -1893587.8 | F77: =E77+F76 -> -1889916.8 | G77: =F77+G76 -> -1886239.8 | H77: =G77+H76 -> -1882556.7 | I77: =H77+I76 -> -1878867.6 | J77: =I77+J76 -> -1875172.5 | K77: =J77+K76 -> -1871471.3 | ... BJ77: =BI77+BJ76 -> -1636206.7
A78: Helper: lowest cumulative cash flow so far | C78: =C77 -> -1900912.2 | D78: =MIN(C78,D77) -> -1900912.2 | E78: =MIN(D78,E77) -> -1900912.2 | F78: =MIN(E78,F77) -> -1900912.2 | G78: =MIN(F78,G77) -> -1900912.2 | H78: =MIN(G78,H77) -> -1900912.2 | I78: =MIN(H78,I77) -> -1900912.2 | J78: =MIN(I78,J77) -> -1900912.2 | K78: =MIN(J78,K77) -> -1900912.2 | ... BJ78: =MIN(BI78,BJ77) -> -1900912.2
A79: Helper: investment paid back (1/0) | C79: =IF(AND(C77>=0,C78<0),1,0) -> 0 | D79: =IF(AND(D77>=0,D78<0),1,0) -> 0 | E79: =IF(AND(E77>=0,E78<0),1,0) -> 0 | F79: =IF(AND(F77>=0,F78<0),1,0) -> 0 | G79: =IF(AND(G77>=0,G78<0),1,0) -> 0 | H79: =IF(AND(H77>=0,H78<0),1,0) -> 0 | I79: =IF(AND(I77>=0,I78<0),1,0) -> 0 | J79: =IF(AND(J77>=0,J78<0),1,0) -> 0 | ... BJ79: =IF(AND(BJ77>=0,BJ78<0),1,0) -> 0
A80: Unlevered free cash flow (operating + after-tax interest − capex) | C80: =C65-C30*(1-Inputs!$E$46)+C66 -> -1895777.2 | D80: =D65-D30*(1-Inputs!$E$46)+D66 -> 8789.5673 | E80: =E65-E30*(1-Inputs!$E$46)+E66 -> 8790.808 | F80: =F65-F30*(1-Inputs!$E$46)+F66 -> 8792.0554 | G80: =G65-G30*(1-Inputs!$E$46)+G66 -> 8793.3095 | H80: =H65-H30*(1-Inputs!$E$46)+H66 -> 8794.5704 | I80: =I65-I30*(1-Inputs!$E$46)+I66 -> 8795.8382 | J80: =J65-J30*(1-Inputs!$E$46)+J66 -> 8797.1128 | ... BJ80: =BJ65-BJ30*(1-Inputs!$E$46)+BJ66 -> 9966.1942
A82: Balance sheet
A83: Paid-in capital | C83: =C67 -> 760000 | D83: =C83+D67 -> 760000 | E83: =D83+E67 -> 760000 | F83: =E83+F67 -> 760000 | G83: =F83+G67 -> 760000 | H83: =G83+H67 -> 760000 | I83: =H83+I67 -> 760000 | J83: =I83+J67 -> 760000 | K83: =J83+K67 -> 760000 | ... BJ83: =BI83+BJ67 -> 760000
A84: Retained earnings | C84: =C35 -> -795.09774 | D84: =C84+D35 -> -1585.2196 | E84: =D84+E35 -> -2370.3337 | F84: =E84+F35 -> -3150.4082 | G84: =F84+G35 -> -3925.4107 | H84: =G84+H35 -> -4695.309 | I84: =H84+I35 -> -5460.0706 | J84: =I84+J35 -> -6219.6627 | K84: =J84+K35 -> -6974.0524 | ... BJ84: =BI84+BJ35 -> 763.11298
A85: Total assets | C85: =C71+C57+C58+C46 -> 1959054.6 | D85: =D71+D57+D58+D46 -> 1957173.8 | E85: =E71+E57+E58+E46 -> 1955292.1 | F85: =F71+F57+F58+F46 -> 1953409.4 | G85: =G71+G57+G58+G46 -> 1951525.9 | H85: =H71+H57+H58+H46 -> 1949641.5 | I85: =I71+I57+I58+I46 -> 1947756.2 | J85: =J71+J57+J58+J46 -> 1945870 | ... BJ85: =BJ71+BJ57+BJ58+BJ46 -> 1885146.6
A86: Total liabilities | C86: =C59+C54 -> 1199849.7 | D86: =D59+D54 -> 1198759 | E86: =E59+E54 -> 1197662.4 | F86: =F59+F54 -> 1196559.9 | G86: =G59+G54 -> 1195451.3 | H86: =H59+H54 -> 1194336.8 | I86: =I59+I54 -> 1193216.3 | J86: =J59+J54 -> 1192089.6 | ... BJ86: =BJ59+BJ54 -> 1124383.5
A87: Total equity | C87: =C83+C84 -> 759204.9 | D87: =D83+D84 -> 758414.78 | E87: =E83+E84 -> 757629.67 | F87: =F83+F84 -> 756849.59 | G87: =G83+G84 -> 756074.59 | H87: =H83+H84 -> 755304.69 | I87: =I83+I84 -> 754539.93 | J87: =J83+J84 -> 753780.34 | ... BJ87: =BJ83+BJ84 -> 760763.11
A88: Total liabilities & equity | C88: =C86+C87 -> 1959054.6 | D88: =D86+D87 -> 1957173.8 | E88: =E86+E87 -> 1955292.1 | F88: =F86+F87 -> 1953409.4 | G88: =G86+G87 -> 1951525.9 | H88: =H86+H87 -> 1949641.5 | I88: =I86+I87 -> 1947756.2 | J88: =J86+J87 -> 1945870 | ... BJ88: =BJ86+BJ87 -> 1885146.6
A89: Check: assets − liabilities − equity | C89: =C85-C88 -> 0 | D89: =D85-D88 -> 0 | E89: =E85-E88 -> 0 | F89: =F85-F88 -> 0 | G89: =G85-G88 -> 0 | H89: =H85-H88 -> 0 | I89: =I85-I88 -> 0 | J89: =J85-J88 -> 0 | ... BJ89: =BJ85-BJ88 -> 0

Sheet Headcount
A1: Headcount & payroll | D1: =HYPERLINK("#'Cover'!A1","◂ Contents") -> ◂ Contents
A2: $ unless stated; costs shown as negatives. Every period uses the same formula.
A3: Month | C3: M1 | D3: M2 | E3: M3 | F3: M4 | G3: M5 | H3: M6 | I3: M7 | J3: M8 | K3: M9 | L3: M10 | M3: M11 | N3: M12 | O3: M13 | P3: M14 | Q3: M15 | R3: M16 | S3: M17 | T3: M18 | U3: M19 | V3: M20 | W3: M21 | X3: M22 | Y3: M23 | Z3: M24 | AA3: M25 | AB3: M26 | AC3: M27 | AD3: M28 | AE3: M29 | AF3: M30 | AG3: M31 | AH3: M32 | AI3: M33 | AJ3: M34 | AK3: M35 | AL3: M36 | AM3: M37 | AN3: M38 | AO3: M39 | AP3: M40 | AQ3: M41 | AR3: M42 | AS3: M43 | AT3: M44 | AU3: M45 | AV3: M46 | AW3: M47 | AX3: M48 | AY3: M49 | AZ3: M50 | BA3: M51 | BB3: M52 | BC3: M53 | BD3: M54 | BE3: M55 | BF3: M56 | BG3: M57 | BH3: M58 | BI3: M59 | BJ3: M60
A4: Period # | C4: 1 | D4: 2 | E4: 3 | F4: 4 | G4: 5 | H4: 6 | I4: 7 | J4: 8 | K4: 9 | L4: 10 | M4: 11 | N4: 12 | O4: 13 | P4: 14 | Q4: 15 | R4: 16 | S4: 17 | T4: 18 | U4: 19 | V4: 20 | W4: 21 | X4: 22 | Y4: 23 | Z4: 24 | AA4: 25 | AB4: 26 | AC4: 27 | AD4: 28 | AE4: 29 | AF4: 30 | AG4: 31 | AH4: 32 | AI4: 33 | AJ4: 34 | AK4: 35 | AL4: 36 | AM4: 37 | AN4: 38 | AO4: 39 | AP4: 40 | AQ4: 41 | AR4: 42 | AS4: 43 | AT4: 44 | AU4: 45 | AV4: 46 | AW4: 47 | AX4: 48 | AY4: 49 | AZ4: 50 | BA4: 51 | BB4: 52 | BC4: 53 | BD4: 54 | BE4: 55 | BF4: 56 | BG4: 57 | BH4: 58 | BI4: 59 | BJ4: 60
A5: Year # | C5: =ROUNDUP(C4*1/12,0) -> 1 | D5: =ROUNDUP(D4*1/12,0) -> 1 | E5: =ROUNDUP(E4*1/12,0) -> 1 | F5: =ROUNDUP(F4*1/12,0) -> 1 | G5: =ROUNDUP(G4*1/12,0) -> 1 | H5: =ROUNDUP(H4*1/12,0) -> 1 | I5: =ROUNDUP(I4*1/12,0) -> 1 | J5: =ROUNDUP(J4*1/12,0) -> 1 | ... BJ5: =ROUNDUP(BJ4*1/12,0) -> 5
A6: Total FTE | C6: =0 -> 0 | D6: =0 -> 0 | E6: =0 -> 0 | F6: =0 -> 0 | G6: =0 -> 0 | H6: =0 -> 0 | I6: =0 -> 0 | J6: =0 -> 0 | ... BJ6: =0 -> 0
A7: Total payroll | C7: =0 -> 0 | D7: =0 -> 0 | E7: =0 -> 0 | F7: =0 -> 0 | G7: =0 -> 0 | H7: =0 -> 0 | I7: =0 -> 0 | J7: =0 -> 0 | ... BJ7: =0 -> 0

Sheet Checks
A1: Model checks | E1: =HYPERLINK("#'Cover'!A1","◂ Contents") -> ◂ Contents
A2: Live formulas: they re-run every time an input changes.
A3: Check | B3: Result | C3: What it tests
A4: Annual revenue ties to period detail | B4: =IF(ABS(SUM('P&L'!$B$5:$F$5)-SUM(Monthly!$C$12:$BJ$12))<0.5,"PASS","FAIL") -> PASS | C4: Sum of annual revenue equals the sum of every period
A5: Annual net income ties to period detail | B5: =IF(ABS(SUM('P&L'!$B$21:$F$21)-SUM(Monthly!$C$35:$BJ$35))<0.5,"PASS","FAIL") -> PASS | C5: Sum of annual net income equals the sum of every period
A6: EBITDA reconciliation | B6: =IF(ABS(SUM(Monthly!$C$26:$BJ$26)-SUM(Monthly!$C$18:$BJ$18)-SUM(Monthly!$C$25:$BJ$25))<0.5,"PASS","FAIL") -> PASS | C6: EBITDA = gross profit + operating expenses (costs are negative)
A7: Cash roll-forward | B7: =IF(ABS(INDEX(Monthly!$C$71:$BJ$71,60)-SUM(Monthly!$C$69:$BJ$69))<0.5,"PASS","FAIL") -> PASS | C7: Closing cash = all net cash flows since the start (opening cash is zero)
A8: Scenario selector valid | B8: =IF(AND(ISNUMBER(Dashboard!B4),Dashboard!B4>=1,Dashboard!B4<=3,INT(Dashboard!B4)=Dashboard!B4),"PASS","FAIL") -> PASS | C8: Dashboard!B4 is 1, 2 or 3
A9: Scenario ordering of drivers | B9: =IF(AND(Inputs!$B$9>=Inputs!$C$9,Inputs!$C$9>=Inputs!$D$9,Inputs!$B$13<=Inputs!$C$13,Inputs!$C$13<=Inputs!$D$13,Inputs!$B$14<=Inputs!$C$14,Inputs!$C$14<=Inputs!$D$14,Inputs!$B$15>=Inputs!$C$15,Inputs!$C$15>=Inputs!$D$15,Inputs!$B$16<=Inputs!$C$16,Inputs!$C$16<=Inputs!$D$16,Inputs!$B$19>=Inputs!$C$19,Inputs!$C$19>=Inputs!$D$19,Inputs!$B$23>=Inputs!$C$23,Inputs!$C$23>=Inputs!$D$23,Inputs!$B$25>=Inputs!$C$25,Inputs!$C$25>=Inputs!$D$25,Inputs!$B$29>=Inputs!$C$29,Inputs!$C$29>=Inputs!$D$29,Inputs!$B$30>=Inputs!$C$30,Inputs!$C$30>=Inputs!$D$30,Inputs!$B$52>=Inputs!$C$52,Inputs!$C$52>=Inputs!$D$52,Inputs!$B$53<=Inputs!$C$53,Inputs!$C$53<=Inputs!$D$53,Inputs!$B$54<=Inputs!$C$54,Inputs!$C$54<=Inputs!$D$54),"PASS","FAIL") -> PASS | C9: Low / Base / High ordered the right way for every growth and cost driver
A10: Gross margin within 0–100% | B10: =IF(AND(MIN('P&L'!$B$8:$F$8)>=0,MAX('P&L'!$B$8:$F$8)<=1),"PASS","FAIL") -> PASS | C10: Gross margin never negative or above 100%
A11: Loan balance never negative | B11: =IF(MIN(Monthly!$C$54:$BJ$54)>=-0.5,"PASS","FAIL") -> PASS | C11: Repayments never exceed the loan
A12: Funding table ties to the cash flow | B12: =IF(ABS('Break-even'!B18-('Break-even'!B16-'Break-even'!B10))<0.5,"PASS","FAIL") -> PASS | C12: Lowest cash balance = sources of funds − uses of funds up to that point
A13: Valuation: discounting ties to NPV() | B13: =IF(ABS(Valuation!B23-NPV(Valuation!B6,Valuation!$B$17:$F$17))<0.5,"PASS","FAIL") -> PASS | C13: Sum of discounted free cash flows equals Excel's NPV of the same flows
A14: Valuation: WACC above terminal growth | B14: =IF(Valuation!B6>Valuation!B7,"PASS","FAIL") -> PASS | C14: The perpetual-growth formula needs WACC > g
A15: Valuation: sensitivity centre = enterprise value | B15: =IF(ABS(Valuation!D36-Valuation!B27)<0.5,"PASS","FAIL") -> PASS | C15: The middle of the WACC × growth table reproduces the headline value
A16: Valuation: final-year cash flow positive | B16: =IF(Valuation!$F$17>0,"PASS","WARN") -> PASS | C16: Business warning: a negative final-year cash flow gives a negative terminal value (often a 1-year plan still carrying start-up spending)
A17: Sources & uses balance | B17: =IF(ABS('Sources & Uses'!B21-'Sources & Uses'!B28)<0.5,"PASS","FAIL") -> PASS | C17: Sources of funds = uses of funds (incl. cash at the end) for the Sources & Uses period
A18: Returns: NOI ties to EBITDA | B18: =IF(ABS(SUM(Returns!$B$17:$G$17)-SUM(Monthly!$C$26:$BJ$26))<0.5,"PASS","FAIL") -> PASS | C18: NOI on the Returns sheet equals EBITDA summed over every period
A19: Returns: purchase ties to capital spending | B19: =IF(ABS(SUM(Returns!$B$16:$G$16)+SUM(Monthly!$C$38:$BJ$38))<0.5,"PASS","FAIL") -> PASS | C19: Purchase price + closing costs equals the purchase in the capex line
A20: Returns: loan fully repaid at sale | B20: =IF(ABS(SUM(Returns!$B$21:$G$21)+SUM(Returns!$B$23:$G$23)+SUM(Returns!$B$24:$G$24))<0.5,"PASS","FAIL") -> PASS | C20: Drawdown = principal repaid + balance repaid from the sale
A21: Returns: IRR discounts cash flows to zero | B21: =IF(IF(ISNUMBER(Returns!B42),ABS(SUMPRODUCT(Returns!$B$20:$G$20/(1+Returns!B42)^Returns!$B$15:$G$15))<1,TRUE()),"PASS","FAIL") -> PASS | C21: NPV of the unlevered cash flows at their IRR is zero
A22: Returns: levered IRR discounts cash flows to zero | B22: =IF(IF(ISNUMBER(Returns!C42),ABS(SUMPRODUCT(Returns!$B$25:$G$25/(1+Returns!C42)^Returns!$B$15:$G$15))<1,TRUE()),"PASS","FAIL") -> PASS | C22: NPV of the levered cash flows at their IRR is zero
A23: Debt service covered (DSCR ≥ 1.0x) | B23: =IF(SUMPRODUCT(--ISNUMBER(Returns!$C$26:$G$26),--(Returns!$C$26:$G$26<1))=0,"PASS","WARN") -> PASS | C23: Business warning: NOI does not cover the loan payments in at least one year
A24: No error values | B24: =IF(SUMPRODUCT(--ISERROR(Monthly!$C$4:$BJ$89))+SUMPRODUCT(--ISERROR(Headcount!$C$4:$BJ$7))+SUMPRODUCT(--ISERROR('P&L'!$B$3:$F$22))+SUMPRODUCT(--ISERROR('Cash Flow'!$B$3:$F$18))+SUMPRODUCT(--ISERROR('Balance Sheet'!$B$3:$F$17))+SUMPRODUCT(--ISERROR(KPIs!$B$26:$F$41))+SUMPRODUCT(--ISERROR('Break-even'!$B$26:$F$33))+SUMPRODUCT(--ISERROR(Valuation!$B$14:$F$19))+SUMPRODUCT(--ISERROR('Break-even'!$B$3:$F$35))+SUMPRODUCT(--ISERROR(Valuation!$A$3:$F$40))+SUMPRODUCT(--ISERROR('Sources & Uses'!$B$3:$C$30))+SUMPRODUCT(--ISERROR(Returns!$A$3:$G$51))+SUMPRODUCT(--ISERROR(Dashboard!$A$6:$W$43))+SUMPRODUCT(--ISERROR(Summary!$A$5:$S$52))+SUMPRODUCT(--ISERROR(KPIs!$A$4:$G$41))=0,"PASS","FAIL") -> PASS | C24: No error values (divide-by-zero, broken references) on any calculation sheet
A25: Summary ties to statements | B25: =IF(IFERROR(AND(SUMPRODUCT(--(ABS(Summary!$B$7:$F$7-'P&L'!$B$5:$F$5)>0.5))=0,SUMPRODUCT(--(ABS(Summary!$B$19:$F$19-'P&L'!$B$21:$F$21)>0.5))=0,SUMPRODUCT(--(ABS(Summary!$B$31:$F$31-'Cash Flow'!$B$18:$F$18)>0.5))=0,SUMPRODUCT(--(ABS(Summary!$B$41:$F$41-'Balance Sheet'!$B$5:$F$5)>0.5))=0,ABS(SUM(Summary!$H$7:$S$7)-INDEX(Summary!$B$7:$F$7,Summary!$R$2))<0.5,ABS(SUM(Summary!$H$19:$S$19)-INDEX(Summary!$B$19:$F$19,Summary!$R$2))<0.5,ABS(Summary!$S$31-INDEX(Summary!$B$31:$F$31,Summary!$R$2))<0.5),FALSE()),"PASS","FAIL") -> PASS | C25: Summary revenue, net income and closing cash equal the statements every year; the detailed year adds up to its annual figure
A26: DuPont ties to return on equity | B26: =IF(SUMPRODUCT(--(ABS(KPIs!$B$23:$F$23)>0.000000001))>0,"FAIL",IF(SUMPRODUCT(ISNUMBER(KPIs!$B$22:$F$22)*ISNUMBER(KPIs!$B$15:$F$15))=0,"n/a","PASS")) -> PASS | C26: Net margin × asset turnover × equity multiplier equals return on equity every year; n/a = no year where both are defined (a one-sided n/a is a FAIL)
A27: Balance sheet balances every period | B27: =IF(SUMPRODUCT(--(ABS(Monthly!$C$89:$BJ$89)>0.5))=0,"PASS","FAIL") -> PASS | C27: Assets = liabilities + equity in every period
A28: Funding sufficient (cash ≥ 0) | B28: =IF(MIN(Monthly!$C$71:$BJ$71)>=0,"PASS","WARN") -> PASS | C28: Business warning, not an error: cash dips below zero in this scenario
A30: Overall verdict | B30: =IF(COUNTIF(B4:B28,"FAIL")>0,"FAIL",IF(COUNTIF(B4:B28,"WARN")>0,"PASS WITH WARNINGS","PASS")) -> PASS
