Workbook

Sheet Cover
B2: Retail / e-commerce financial model (growing)
B3: 5-year financial model · monthly detail · Low / Base / High scenarios · US dollars · Full plan
B5: Purpose | D5: Revenue and profit plan
B6: Active scenario | D6: =Dashboard!C4&" (change it on the Dashboard, cell B4)" -> Base (change it on the Dashboard, cell B4)
B7: Model checks | D7: =Checks!B25 -> PASS
B8: Prepared | D8: 22 October 2026
B10: Contents
C11: PRESENTATION
B12: 1 | C12: =HYPERLINK("#Dashboard!A1","Dashboard") -> Dashboard | D12: Scenario switch, key numbers, core financials
B13: 2 | C13: =HYPERLINK("#Summary!A1","Summary") -> Summary | D13: Income statement, cash flow and balance sheet — every year and any year by month
B14: 3 | C14: =HYPERLINK("#Scenarios!A1","Scenarios") -> Scenarios | D14: Low / Base / High side by side: drivers, outputs, charts
B15: 4 | C15: =HYPERLINK("#'Break-even'!A1","Break-even") -> Break-even | D15: Startup costs, funding need, break-even timing and revenue
B16: 5 | C16: =HYPERLINK("#Valuation!A1","Valuation") -> Valuation | D16: Free cash flow, DCF (perpetual growth and exit multiple), WACC × growth sensitivity
B17: 6 | C17: =HYPERLINK("#'Sources & Uses'!A1","Sources & Uses") -> Sources & Uses | D17: Funding structure, sources and uses of cash for the first months
B18: 7 | C18: =HYPERLINK("#KPIs!A1","KPIs") -> KPIs | D18: Financial ratios, DuPont analysis, industry metrics
C19: INPUTS
B20: 8 | C20: =HYPERLINK("#Inputs!A1","Inputs") -> Inputs | D20: Every assumption, Low / Base / High, with units and comments
C21: STATEMENTS
B22: 9 | C22: =HYPERLINK("#'P&L'!A1","P&L") -> P&L | D22: Annual profit & loss
B23: 10 | C23: =HYPERLINK("#'Cash Flow'!A1","Cash Flow") -> Cash Flow | D23: Annual cash flow statement
B24: 11 | C24: =HYPERLINK("#'Balance Sheet'!A1","Balance Sheet") -> Balance Sheet | D24: Balance sheet at year end
C25: CALCULATIONS
B26: 12 | C26: =HYPERLINK("#Monthly!A1","Monthly") -> Monthly | D26: Month-by-month engine of the model
B27: 13 | C27: =HYPERLINK("#Headcount!A1","Headcount") -> Headcount | D27: Team and payroll
B28: 14 | C28: =HYPERLINK("#'Scenario calc'!A1","Scenario calc") -> Scenario calc | D28: Low, Base and High calculated side by side for the Scenarios sheet
C29: CONTROL
B30: 15 | C30: =HYPERLINK("#Checks!A1","Checks") -> Checks | D30: Live integrity checks and the overall verdict
B32: How to read this file
C33: 1000 | D33: Input you can change — yellow cell with a blue figure (Inputs sheet and the view switches)
C34: 1000 | D34: Formula — calculated, do not overwrite
C35: 1000 | D35: Link to another sheet
C36: 1000 | D36: Active value the model uses (follows the scenario)

Sheet Dashboard
A1: Dashboard | W1: =HYPERLINK("#'Cover'!A1","◂ Contents") -> ◂ Contents
A2: Retail / e-commerce financial model (growing)
A4: Active scenario | B4: 2 | C4: =CHOOSE(B4,"Low","Base","High") -> Base | D4: 1 = Low · 2 = Base · 3 = High — every sheet follows this cell | S4: Model checks | T4: =Checks!B25 -> PASS
A6: REVENUE · YEAR 5 | C6: EBITDA MARGIN · YEAR 5 | H6: NET INCOME · YEAR 5 | L6: LOWEST CASH BALANCE | P6: FUNDING REQUIRED | T6: ENTERPRISE VALUE (DCF)
A7: =F12 -> 14322508 | C7: =F17 -> 0.11067312 | H7: =F18 -> 1141341.2 | L7: =F39 -> 1260305.1 | P7: =F37 -> 1459694.9 | T7: =F44 -> 4528906.2
A8: =IF(AND(B12>0,F12>=0),(F12/B12)^(1/4)-1,"CAGR n/a") -> 0.26946145 | C8: =F16 -> 1585116.7 | H8: =F19 -> 0.07968864 | L8: ='Break-even'!B6 -> 13 | P8: =IF(F38>=0,"Covered by funding raised",-F38) -> Covered by funding raised | T8: Average of 2 methods
A10: Core financials ($'000) — active scenario
B11: 1 | C11: 2 | D11: 3 | E11: 4 | F11: 5
A12: Revenue | B12: =SUMIF(Monthly!$C$5:$BJ$5,B$11,Monthly!$C$25:$BJ$25) -> 5514942.9 | C12: =SUMIF(Monthly!$C$5:$BJ$5,C$11,Monthly!$C$25:$BJ$25) -> 7179087.9 | D12: =SUMIF(Monthly!$C$5:$BJ$5,D$11,Monthly!$C$25:$BJ$25) -> 9149574.9 | E12: =SUMIF(Monthly!$C$5:$BJ$5,E$11,Monthly!$C$25:$BJ$25) -> 11499932 | F12: =SUMIF(Monthly!$C$5:$BJ$5,F$11,Monthly!$C$25:$BJ$25) -> 14322508
A13: Gross profit | B13: =SUMIF(Monthly!$C$5:$BJ$5,B$11,Monthly!$C$27:$BJ$27) -> 3198666.9 | C13: =SUMIF(Monthly!$C$5:$BJ$5,C$11,Monthly!$C$27:$BJ$27) -> 4163871 | D13: =SUMIF(Monthly!$C$5:$BJ$5,D$11,Monthly!$C$27:$BJ$27) -> 5306753.4 | E13: =SUMIF(Monthly!$C$5:$BJ$5,E$11,Monthly!$C$27:$BJ$27) -> 6669960.6 | F13: =SUMIF(Monthly!$C$5:$BJ$5,F$11,Monthly!$C$27:$BJ$27) -> 8307054.9
A14: Gross margin | B14: =IF(B12=0,0,B13/B12) -> 0.58 | C14: =IF(C12=0,0,C13/C12) -> 0.58 | D14: =IF(D12=0,0,D13/D12) -> 0.58 | E14: =IF(E12=0,0,E13/E12) -> 0.58 | F14: =IF(F12=0,0,F13/F12) -> 0.58
A15: Operating expenses | B15: =SUMIF(Monthly!$C$5:$BJ$5,B$11,Monthly!$C$38:$BJ$38) -> -2881171.1 | C15: =SUMIF(Monthly!$C$5:$BJ$5,C$11,Monthly!$C$38:$BJ$38) -> -3582127.2 | D15: =SUMIF(Monthly!$C$5:$BJ$5,D$11,Monthly!$C$38:$BJ$38) -> -4429385.6 | E15: =SUMIF(Monthly!$C$5:$BJ$5,E$11,Monthly!$C$38:$BJ$38) -> -5460233 | F15: =SUMIF(Monthly!$C$5:$BJ$5,F$11,Monthly!$C$38:$BJ$38) -> -6721938.2
A16: EBITDA | B16: =SUMIF(Monthly!$C$5:$BJ$5,B$11,Monthly!$C$39:$BJ$39) -> 317495.71 | C16: =SUMIF(Monthly!$C$5:$BJ$5,C$11,Monthly!$C$39:$BJ$39) -> 581743.74 | D16: =SUMIF(Monthly!$C$5:$BJ$5,D$11,Monthly!$C$39:$BJ$39) -> 877367.82 | E16: =SUMIF(Monthly!$C$5:$BJ$5,E$11,Monthly!$C$39:$BJ$39) -> 1209727.6 | F16: =SUMIF(Monthly!$C$5:$BJ$5,F$11,Monthly!$C$39:$BJ$39) -> 1585116.7
A17: EBITDA margin | B17: =IF(B12=0,0,B16/B12) -> 0.057570082 | C17: =IF(C12=0,0,C16/C12) -> 0.0810331 | D17: =IF(D12=0,0,D16/D12) -> 0.095891649 | E17: =IF(E12=0,0,E16/E12) -> 0.10519433 | F17: =IF(F12=0,0,F16/F12) -> 0.11067312
A18: Net income | B18: =SUMIF(Monthly!$C$5:$BJ$5,B$11,Monthly!$C$48:$BJ$48) -> 182376.89 | C18: =SUMIF(Monthly!$C$5:$BJ$5,C$11,Monthly!$C$48:$BJ$48) -> 380502.32 | D18: =SUMIF(Monthly!$C$5:$BJ$5,D$11,Monthly!$C$48:$BJ$48) -> 603436.77 | E18: =SUMIF(Monthly!$C$5:$BJ$5,E$11,Monthly!$C$48:$BJ$48) -> 855392.43 | F18: =SUMIF(Monthly!$C$5:$BJ$5,F$11,Monthly!$C$48:$BJ$48) -> 1141341.2
A19: Net margin | B19: =IF(B12=0,0,B18/B12) -> 0.033069589 | C19: =IF(C12=0,0,C18/C12) -> 0.053001485 | D19: =IF(D12=0,0,D18/D12) -> 0.065952438 | E19: =IF(E12=0,0,E18/E12) -> 0.07438239 | F19: =IF(F12=0,0,F18/F12) -> 0.07968864
A20: Operating cash flow | B20: =SUMIF(Monthly!$C$5:$BJ$5,B$11,Monthly!$C$72:$BJ$72) -> -146060.15 | C20: =SUMIF(Monthly!$C$5:$BJ$5,C$11,Monthly!$C$72:$BJ$72) -> 334798.67 | D20: =SUMIF(Monthly!$C$5:$BJ$5,D$11,Monthly!$C$72:$BJ$72) -> 557937.43 | E20: =SUMIF(Monthly!$C$5:$BJ$5,E$11,Monthly!$C$72:$BJ$72) -> 804972.77 | F20: =SUMIF(Monthly!$C$5:$BJ$5,F$11,Monthly!$C$72:$BJ$72) -> 1079551.3
A21: Investing cash flow | B21: =SUMIF(Monthly!$C$5:$BJ$5,B$11,Monthly!$C$73:$BJ$73) -> -350000 | C21: =SUMIF(Monthly!$C$5:$BJ$5,C$11,Monthly!$C$73:$BJ$73) -> -150000 | D21: =SUMIF(Monthly!$C$5:$BJ$5,D$11,Monthly!$C$73:$BJ$73) -> -150000 | E21: =SUMIF(Monthly!$C$5:$BJ$5,E$11,Monthly!$C$73:$BJ$73) -> -150000 | F21: =SUMIF(Monthly!$C$5:$BJ$5,F$11,Monthly!$C$73:$BJ$73) -> -150000
A22: Financing cash flow | B22: =SUMIF(Monthly!$C$5:$BJ$5,B$11,Monthly!$C$75:$BJ$75) -> 1908333.3 | C22: =SUMIF(Monthly!$C$5:$BJ$5,C$11,Monthly!$C$75:$BJ$75) -> -100000 | D22: =SUMIF(Monthly!$C$5:$BJ$5,D$11,Monthly!$C$75:$BJ$75) -> -100000 | E22: =SUMIF(Monthly!$C$5:$BJ$5,E$11,Monthly!$C$75:$BJ$75) -> -100000 | F22: =SUMIF(Monthly!$C$5:$BJ$5,F$11,Monthly!$C$75:$BJ$75) -> -100000
A23: Net change in cash | B23: =SUMIF(Monthly!$C$5:$BJ$5,B$11,Monthly!$C$76:$BJ$76) -> 1412273.2 | C23: =SUMIF(Monthly!$C$5:$BJ$5,C$11,Monthly!$C$76:$BJ$76) -> 84798.669 | D23: =SUMIF(Monthly!$C$5:$BJ$5,D$11,Monthly!$C$76:$BJ$76) -> 307937.43 | E23: =SUMIF(Monthly!$C$5:$BJ$5,E$11,Monthly!$C$76:$BJ$76) -> 554972.77 | F23: =SUMIF(Monthly!$C$5:$BJ$5,F$11,Monthly!$C$76:$BJ$76) -> 829551.32
A24: Year-end cash | B24: =INDEX(Monthly!$C$78:$BJ$78,B$11*12) -> 1412273.2 | C24: =INDEX(Monthly!$C$78:$BJ$78,C$11*12) -> 1497071.8 | D24: =INDEX(Monthly!$C$78:$BJ$78,D$11*12) -> 1805009.3 | E24: =INDEX(Monthly!$C$78:$BJ$78,E$11*12) -> 2359982 | F24: =INDEX(Monthly!$C$78:$BJ$78,F$11*12) -> 3189533.4
A26: Retail metrics
B27: 1 | C27: 2 | D27: 3 | E27: 4 | F27: 5
A28: Online gross sales | B28: =KPIs!B33 -> 5002714.3 | C28: =KPIs!C33 -> 6255514.3 | D28: =KPIs!D33 -> 7825294.3 | E28: =KPIs!E33 -> 9793054.8 | F28: =KPIs!F33 -> 12260690
A29: Store gross sales | B29: =KPIs!B38 -> 1125000 | C29: =KPIs!C38 -> 1721250 | D29: =KPIs!D38 -> 2340900 | E29: =KPIs!E38 -> 2984647.5 | F29: =KPIs!F38 -> 3653208.5
A30: Online orders | B30: =KPIs!B30 -> 66702.857 | C30: =KPIs!C30 -> 81771.429 | D30: =KPIs!D30 -> 100285.71 | E30: =KPIs!E30 -> 123042.86 | F30: =KPIs!F30 -> 151026.43
A31: Stores open (year end) | B31: =KPIs!B37 -> 2 | C31: =KPIs!C37 -> 3 | D31: =KPIs!D37 -> 4 | E31: =KPIs!E37 -> 5 | F31: =KPIs!F37 -> 6
A32: Team (FTE, year end) | B32: =INDEX(Headcount!$C$12:$BJ$12,B$27*12) -> 21 | C32: =INDEX(Headcount!$C$12:$BJ$12,C$27*12) -> 25.85 | D32: =INDEX(Headcount!$C$12:$BJ$12,D$27*12) -> 31.8875 | E32: =INDEX(Headcount!$C$12:$BJ$12,E$27*12) -> 39.418625 | F32: =INDEX(Headcount!$C$12:$BJ$12,F$27*12) -> 48.831819
A34: Funding & valuation ($'000) — active scenario
A35: Equity raised | F35: =Inputs!$E$58 -> 1500000
A36: Loan drawn | F36: =Inputs!$E$59 -> 500000
A37: Funding required (incl. cash buffer) | F37: ='Break-even'!B12 -> 1459694.9
A38: Funding surplus / (shortfall) | F38: ='Break-even'!B17 -> 540305.08
A39: ="Lowest cash balance (month "&'Break-even'!B6&")" -> Lowest cash balance (month 13) | F39: ='Break-even'!B18 -> 1260305.1
A40: First month with positive EBITDA | F40: ='Break-even'!B21 -> 1
A41: Cash invested paid back | F41: ='Break-even'!B23 -> 36
A42: Enterprise value — perpetual growth | F42: =Valuation!B27 -> 4072114.7
A43: Enterprise value — exit multiple | F43: =Valuation!C27 -> 4985697.7
A44: Enterprise value — average | F44: =Valuation!B30 -> 4528906.2

Sheet Summary
A1: Financial statements summary | U1: =HYPERLINK("#'Cover'!A1","◂ Contents") -> ◂ Contents
A2: Retail / e-commerce financial model (growing) | P2: Select detailed year: | R2: 1
A5: Income statement ($'000) — by year | H5: ="Income statement ($'000) — Year "&$R$2&", by month" -> Income statement ($'000) — Year 1, by month
B6: 1 | C6: 2 | D6: 3 | E6: 4 | F6: 5 | H6: =INDEX(Monthly!$C$4:$BJ$4,($R$2-1)*12+1) -> 1 | I6: =INDEX(Monthly!$C$4:$BJ$4,($R$2-1)*12+2) -> 2 | J6: =INDEX(Monthly!$C$4:$BJ$4,($R$2-1)*12+3) -> 3 | K6: =INDEX(Monthly!$C$4:$BJ$4,($R$2-1)*12+4) -> 4 | L6: =INDEX(Monthly!$C$4:$BJ$4,($R$2-1)*12+5) -> 5 | M6: =INDEX(Monthly!$C$4:$BJ$4,($R$2-1)*12+6) -> 6 | N6: =INDEX(Monthly!$C$4:$BJ$4,($R$2-1)*12+7) -> 7 | O6: =INDEX(Monthly!$C$4:$BJ$4,($R$2-1)*12+8) -> 8 | P6: =INDEX(Monthly!$C$4:$BJ$4,($R$2-1)*12+9) -> 9 | Q6: =INDEX(Monthly!$C$4:$BJ$4,($R$2-1)*12+10) -> 10 | R6: =INDEX(Monthly!$C$4:$BJ$4,($R$2-1)*12+11) -> 11 | S6: =INDEX(Monthly!$C$4:$BJ$4,($R$2-1)*12+12) -> 12
A7: Revenue | B7: ='P&L'!B5 -> 5514942.9 | C7: ='P&L'!C5 -> 7179087.9 | D7: ='P&L'!D5 -> 9149574.9 | E7: ='P&L'!E5 -> 11499932 | F7: ='P&L'!F5 -> 14322508 | H7: =INDEX(Monthly!$C$25:$BJ$25,($R$2-1)*12+1) -> 442852.07 | I7: =INDEX(Monthly!$C$25:$BJ$25,($R$2-1)*12+2) -> 442852.07 | J7: =INDEX(Monthly!$C$25:$BJ$25,($R$2-1)*12+3) -> 442852.07 | K7: =INDEX(Monthly!$C$25:$BJ$25,($R$2-1)*12+4) -> 442852.07 | L7: =INDEX(Monthly!$C$25:$BJ$25,($R$2-1)*12+5) -> 442852.07 | M7: =INDEX(Monthly!$C$25:$BJ$25,($R$2-1)*12+6) -> 442852.07 | N7: =INDEX(Monthly!$C$25:$BJ$25,($R$2-1)*12+7) -> 442852.07 | O7: =INDEX(Monthly!$C$25:$BJ$25,($R$2-1)*12+8) -> 442852.07 | P7: =INDEX(Monthly!$C$25:$BJ$25,($R$2-1)*12+9) -> 442852.07 | Q7: =INDEX(Monthly!$C$25:$BJ$25,($R$2-1)*12+10) -> 442852.07 | R7: =INDEX(Monthly!$C$25:$BJ$25,($R$2-1)*12+11) -> 543211.07 | S7: =INDEX(Monthly!$C$25:$BJ$25,($R$2-1)*12+12) -> 543211.07
A8: Product cost | B8: ='P&L'!B6 -> -2316276 | C8: ='P&L'!C6 -> -3015216.9 | D8: ='P&L'!D6 -> -3842821.4 | E8: ='P&L'!E6 -> -4829971.5 | F8: ='P&L'!F6 -> -6015453.6 | H8: =INDEX(Monthly!$C$26:$BJ$26,($R$2-1)*12+1) -> -185997.87 | I8: =INDEX(Monthly!$C$26:$BJ$26,($R$2-1)*12+2) -> -185997.87 | J8: =INDEX(Monthly!$C$26:$BJ$26,($R$2-1)*12+3) -> -185997.87 | K8: =INDEX(Monthly!$C$26:$BJ$26,($R$2-1)*12+4) -> -185997.87 | L8: =INDEX(Monthly!$C$26:$BJ$26,($R$2-1)*12+5) -> -185997.87 | M8: =INDEX(Monthly!$C$26:$BJ$26,($R$2-1)*12+6) -> -185997.87 | N8: =INDEX(Monthly!$C$26:$BJ$26,($R$2-1)*12+7) -> -185997.87 | O8: =INDEX(Monthly!$C$26:$BJ$26,($R$2-1)*12+8) -> -185997.87 | P8: =INDEX(Monthly!$C$26:$BJ$26,($R$2-1)*12+9) -> -185997.87 | Q8: =INDEX(Monthly!$C$26:$BJ$26,($R$2-1)*12+10) -> -185997.87 | R8: =INDEX(Monthly!$C$26:$BJ$26,($R$2-1)*12+11) -> -228148.65 | S8: =INDEX(Monthly!$C$26:$BJ$26,($R$2-1)*12+12) -> -228148.65
A9: Gross profit | B9: ='P&L'!B7 -> 3198666.9 | C9: ='P&L'!C7 -> 4163871 | D9: ='P&L'!D7 -> 5306753.4 | E9: ='P&L'!E7 -> 6669960.6 | F9: ='P&L'!F7 -> 8307054.9 | H9: =INDEX(Monthly!$C$27:$BJ$27,($R$2-1)*12+1) -> 256854.2 | I9: =INDEX(Monthly!$C$27:$BJ$27,($R$2-1)*12+2) -> 256854.2 | J9: =INDEX(Monthly!$C$27:$BJ$27,($R$2-1)*12+3) -> 256854.2 | K9: =INDEX(Monthly!$C$27:$BJ$27,($R$2-1)*12+4) -> 256854.2 | L9: =INDEX(Monthly!$C$27:$BJ$27,($R$2-1)*12+5) -> 256854.2 | M9: =INDEX(Monthly!$C$27:$BJ$27,($R$2-1)*12+6) -> 256854.2 | N9: =INDEX(Monthly!$C$27:$BJ$27,($R$2-1)*12+7) -> 256854.2 | O9: =INDEX(Monthly!$C$27:$BJ$27,($R$2-1)*12+8) -> 256854.2 | P9: =INDEX(Monthly!$C$27:$BJ$27,($R$2-1)*12+9) -> 256854.2 | Q9: =INDEX(Monthly!$C$27:$BJ$27,($R$2-1)*12+10) -> 256854.2 | R9: =INDEX(Monthly!$C$27:$BJ$27,($R$2-1)*12+11) -> 315062.42 | S9: =INDEX(Monthly!$C$27:$BJ$27,($R$2-1)*12+12) -> 315062.42
A10: Gross margin | B10: ='P&L'!B8 -> 0.58 | C10: ='P&L'!C8 -> 0.58 | D10: ='P&L'!D8 -> 0.58 | E10: ='P&L'!E8 -> 0.58 | F10: ='P&L'!F8 -> 0.58 | H10: =IF(H7=0,0,H9/H7) -> 0.58 | I10: =IF(I7=0,0,I9/I7) -> 0.58 | J10: =IF(J7=0,0,J9/J7) -> 0.58 | K10: =IF(K7=0,0,K9/K7) -> 0.58 | L10: =IF(L7=0,0,L9/L7) -> 0.58 | M10: =IF(M7=0,0,M9/M7) -> 0.58 | N10: =IF(N7=0,0,N9/N7) -> 0.58 | O10: =IF(O7=0,0,O9/O7) -> 0.58 | ... S10: =IF(S7=0,0,S9/S7) -> 0.58
A11: Total operating expenses | B11: ='P&L'!B17 -> -2881171.1 | C11: ='P&L'!C17 -> -3582127.2 | D11: ='P&L'!D17 -> -4429385.6 | E11: ='P&L'!E17 -> -5460233 | F11: ='P&L'!F17 -> -6721938.2 | H11: =INDEX(Monthly!$C$38:$BJ$38,($R$2-1)*12+1) -> -238213.4 | I11: =INDEX(Monthly!$C$38:$BJ$38,($R$2-1)*12+2) -> -238213.4 | J11: =INDEX(Monthly!$C$38:$BJ$38,($R$2-1)*12+3) -> -238213.4 | K11: =INDEX(Monthly!$C$38:$BJ$38,($R$2-1)*12+4) -> -238213.4 | L11: =INDEX(Monthly!$C$38:$BJ$38,($R$2-1)*12+5) -> -238213.4 | M11: =INDEX(Monthly!$C$38:$BJ$38,($R$2-1)*12+6) -> -238213.4 | N11: =INDEX(Monthly!$C$38:$BJ$38,($R$2-1)*12+7) -> -238213.4 | O11: =INDEX(Monthly!$C$38:$BJ$38,($R$2-1)*12+8) -> -238213.4 | P11: =INDEX(Monthly!$C$38:$BJ$38,($R$2-1)*12+9) -> -238213.4 | Q11: =INDEX(Monthly!$C$38:$BJ$38,($R$2-1)*12+10) -> -238213.4 | R11: =INDEX(Monthly!$C$38:$BJ$38,($R$2-1)*12+11) -> -249518.57 | S11: =INDEX(Monthly!$C$38:$BJ$38,($R$2-1)*12+12) -> -249518.57
A12: EBITDA | B12: ='P&L'!B18 -> 317495.71 | C12: ='P&L'!C18 -> 581743.74 | D12: ='P&L'!D18 -> 877367.82 | E12: ='P&L'!E18 -> 1209727.6 | F12: ='P&L'!F18 -> 1585116.7 | H12: =INDEX(Monthly!$C$39:$BJ$39,($R$2-1)*12+1) -> 18640.801 | I12: =INDEX(Monthly!$C$39:$BJ$39,($R$2-1)*12+2) -> 18640.801 | J12: =INDEX(Monthly!$C$39:$BJ$39,($R$2-1)*12+3) -> 18640.801 | K12: =INDEX(Monthly!$C$39:$BJ$39,($R$2-1)*12+4) -> 18640.801 | L12: =INDEX(Monthly!$C$39:$BJ$39,($R$2-1)*12+5) -> 18640.801 | M12: =INDEX(Monthly!$C$39:$BJ$39,($R$2-1)*12+6) -> 18640.801 | N12: =INDEX(Monthly!$C$39:$BJ$39,($R$2-1)*12+7) -> 18640.801 | O12: =INDEX(Monthly!$C$39:$BJ$39,($R$2-1)*12+8) -> 18640.801 | P12: =INDEX(Monthly!$C$39:$BJ$39,($R$2-1)*12+9) -> 18640.801 | Q12: =INDEX(Monthly!$C$39:$BJ$39,($R$2-1)*12+10) -> 18640.801 | R12: =INDEX(Monthly!$C$39:$BJ$39,($R$2-1)*12+11) -> 65543.851 | S12: =INDEX(Monthly!$C$39:$BJ$39,($R$2-1)*12+12) -> 65543.851
A13: EBITDA margin | B13: ='P&L'!B19 -> 0.057570082 | C13: ='P&L'!C19 -> 0.0810331 | D13: ='P&L'!D19 -> 0.095891649 | E13: ='P&L'!E19 -> 0.10519433 | F13: ='P&L'!F19 -> 0.11067312 | H13: =IF(H7=0,0,H12/H7) -> 0.042092614 | I13: =IF(I7=0,0,I12/I7) -> 0.042092614 | J13: =IF(J7=0,0,J12/J7) -> 0.042092614 | K13: =IF(K7=0,0,K12/K7) -> 0.042092614 | L13: =IF(L7=0,0,L12/L7) -> 0.042092614 | M13: =IF(M7=0,0,M12/M7) -> 0.042092614 | N13: =IF(N7=0,0,N12/N7) -> 0.042092614 | O13: =IF(O7=0,0,O12/O7) -> 0.042092614 | ... S13: =IF(S7=0,0,S12/S7) -> 0.12066001
A14: Depreciation | B14: ='P&L'!B20 -> -50000 | C14: ='P&L'!C20 -> -71428.571 | D14: ='P&L'!D20 -> -92857.143 | E14: ='P&L'!E20 -> -114285.71 | F14: ='P&L'!F20 -> -135714.29 | H14: =INDEX(Monthly!$C$53:$BJ$53,($R$2-1)*12+1) -> -4166.6667 | I14: =INDEX(Monthly!$C$53:$BJ$53,($R$2-1)*12+2) -> -4166.6667 | J14: =INDEX(Monthly!$C$53:$BJ$53,($R$2-1)*12+3) -> -4166.6667 | K14: =INDEX(Monthly!$C$53:$BJ$53,($R$2-1)*12+4) -> -4166.6667 | L14: =INDEX(Monthly!$C$53:$BJ$53,($R$2-1)*12+5) -> -4166.6667 | M14: =INDEX(Monthly!$C$53:$BJ$53,($R$2-1)*12+6) -> -4166.6667 | N14: =INDEX(Monthly!$C$53:$BJ$53,($R$2-1)*12+7) -> -4166.6667 | O14: =INDEX(Monthly!$C$53:$BJ$53,($R$2-1)*12+8) -> -4166.6667 | P14: =INDEX(Monthly!$C$53:$BJ$53,($R$2-1)*12+9) -> -4166.6667 | Q14: =INDEX(Monthly!$C$53:$BJ$53,($R$2-1)*12+10) -> -4166.6667 | R14: =INDEX(Monthly!$C$53:$BJ$53,($R$2-1)*12+11) -> -4166.6667 | S14: =INDEX(Monthly!$C$53:$BJ$53,($R$2-1)*12+12) -> -4166.6667
A15: EBIT | B15: ='P&L'!B21 -> 267495.71 | C15: ='P&L'!C21 -> 510315.17 | D15: ='P&L'!D21 -> 784510.68 | E15: ='P&L'!E21 -> 1095441.9 | F15: ='P&L'!F21 -> 1449402.4 | H15: =INDEX(Monthly!$C$42:$BJ$42,($R$2-1)*12+1) -> 14474.135 | I15: =INDEX(Monthly!$C$42:$BJ$42,($R$2-1)*12+2) -> 14474.135 | J15: =INDEX(Monthly!$C$42:$BJ$42,($R$2-1)*12+3) -> 14474.135 | K15: =INDEX(Monthly!$C$42:$BJ$42,($R$2-1)*12+4) -> 14474.135 | L15: =INDEX(Monthly!$C$42:$BJ$42,($R$2-1)*12+5) -> 14474.135 | M15: =INDEX(Monthly!$C$42:$BJ$42,($R$2-1)*12+6) -> 14474.135 | N15: =INDEX(Monthly!$C$42:$BJ$42,($R$2-1)*12+7) -> 14474.135 | O15: =INDEX(Monthly!$C$42:$BJ$42,($R$2-1)*12+8) -> 14474.135 | P15: =INDEX(Monthly!$C$42:$BJ$42,($R$2-1)*12+9) -> 14474.135 | Q15: =INDEX(Monthly!$C$42:$BJ$42,($R$2-1)*12+10) -> 14474.135 | R15: =INDEX(Monthly!$C$42:$BJ$42,($R$2-1)*12+11) -> 61377.185 | S15: =INDEX(Monthly!$C$42:$BJ$42,($R$2-1)*12+12) -> 61377.185
A16: Interest | B16: ='P&L'!B22 -> -36638.889 | C16: ='P&L'!C22 -> -28666.667 | D16: ='P&L'!D22 -> -20666.667 | E16: ='P&L'!E22 -> -12666.667 | F16: ='P&L'!F22 -> -4666.6667 | H16: =INDEX(Monthly!$C$43:$BJ$43,($R$2-1)*12+1) -> -3333.3333 | I16: =INDEX(Monthly!$C$43:$BJ$43,($R$2-1)*12+2) -> -3305.5556 | J16: =INDEX(Monthly!$C$43:$BJ$43,($R$2-1)*12+3) -> -3250 | K16: =INDEX(Monthly!$C$43:$BJ$43,($R$2-1)*12+4) -> -3194.4444 | L16: =INDEX(Monthly!$C$43:$BJ$43,($R$2-1)*12+5) -> -3138.8889 | M16: =INDEX(Monthly!$C$43:$BJ$43,($R$2-1)*12+6) -> -3083.3333 | N16: =INDEX(Monthly!$C$43:$BJ$43,($R$2-1)*12+7) -> -3027.7778 | O16: =INDEX(Monthly!$C$43:$BJ$43,($R$2-1)*12+8) -> -2972.2222 | P16: =INDEX(Monthly!$C$43:$BJ$43,($R$2-1)*12+9) -> -2916.6667 | Q16: =INDEX(Monthly!$C$43:$BJ$43,($R$2-1)*12+10) -> -2861.1111 | R16: =INDEX(Monthly!$C$43:$BJ$43,($R$2-1)*12+11) -> -2805.5556 | S16: =INDEX(Monthly!$C$43:$BJ$43,($R$2-1)*12+12) -> -2750
A17: Pre-tax income | B17: ='P&L'!B23 -> 230856.83 | C17: ='P&L'!C23 -> 481648.5 | D17: ='P&L'!D23 -> 763844.01 | E17: ='P&L'!E23 -> 1082775.2 | F17: ='P&L'!F23 -> 1444735.7 | H17: =INDEX(Monthly!$C$44:$BJ$44,($R$2-1)*12+1) -> 11140.801 | I17: =INDEX(Monthly!$C$44:$BJ$44,($R$2-1)*12+2) -> 11168.579 | J17: =INDEX(Monthly!$C$44:$BJ$44,($R$2-1)*12+3) -> 11224.135 | K17: =INDEX(Monthly!$C$44:$BJ$44,($R$2-1)*12+4) -> 11279.69 | L17: =INDEX(Monthly!$C$44:$BJ$44,($R$2-1)*12+5) -> 11335.246 | M17: =INDEX(Monthly!$C$44:$BJ$44,($R$2-1)*12+6) -> 11390.801 | N17: =INDEX(Monthly!$C$44:$BJ$44,($R$2-1)*12+7) -> 11446.357 | O17: =INDEX(Monthly!$C$44:$BJ$44,($R$2-1)*12+8) -> 11501.912 | P17: =INDEX(Monthly!$C$44:$BJ$44,($R$2-1)*12+9) -> 11557.468 | Q17: =INDEX(Monthly!$C$44:$BJ$44,($R$2-1)*12+10) -> 11613.023 | R17: =INDEX(Monthly!$C$44:$BJ$44,($R$2-1)*12+11) -> 58571.629 | S17: =INDEX(Monthly!$C$44:$BJ$44,($R$2-1)*12+12) -> 58627.185
A18: Income tax | B18: ='P&L'!B24 -> -48479.933 | C18: ='P&L'!C24 -> -101146.19 | D18: ='P&L'!D24 -> -160407.24 | E18: ='P&L'!E24 -> -227382.8 | F18: ='P&L'!F24 -> -303394.5 | H18: =INDEX(Monthly!$C$47:$BJ$47,($R$2-1)*12+1) -> -2339.5682 | I18: =INDEX(Monthly!$C$47:$BJ$47,($R$2-1)*12+2) -> -2345.4016 | J18: =INDEX(Monthly!$C$47:$BJ$47,($R$2-1)*12+3) -> -2357.0682 | K18: =INDEX(Monthly!$C$47:$BJ$47,($R$2-1)*12+4) -> -2368.7349 | L18: =INDEX(Monthly!$C$47:$BJ$47,($R$2-1)*12+5) -> -2380.4016 | M18: =INDEX(Monthly!$C$47:$BJ$47,($R$2-1)*12+6) -> -2392.0682 | N18: =INDEX(Monthly!$C$47:$BJ$47,($R$2-1)*12+7) -> -2403.7349 | O18: =INDEX(Monthly!$C$47:$BJ$47,($R$2-1)*12+8) -> -2415.4016 | P18: =INDEX(Monthly!$C$47:$BJ$47,($R$2-1)*12+9) -> -2427.0682 | Q18: =INDEX(Monthly!$C$47:$BJ$47,($R$2-1)*12+10) -> -2438.7349 | R18: =INDEX(Monthly!$C$47:$BJ$47,($R$2-1)*12+11) -> -12300.042 | S18: =INDEX(Monthly!$C$47:$BJ$47,($R$2-1)*12+12) -> -12311.709
A19: Net income | B19: ='P&L'!B25 -> 182376.89 | C19: ='P&L'!C25 -> 380502.32 | D19: ='P&L'!D25 -> 603436.77 | E19: ='P&L'!E25 -> 855392.43 | F19: ='P&L'!F25 -> 1141341.2 | H19: =INDEX(Monthly!$C$48:$BJ$48,($R$2-1)*12+1) -> 8801.2329 | I19: =INDEX(Monthly!$C$48:$BJ$48,($R$2-1)*12+2) -> 8823.1774 | J19: =INDEX(Monthly!$C$48:$BJ$48,($R$2-1)*12+3) -> 8867.0663 | K19: =INDEX(Monthly!$C$48:$BJ$48,($R$2-1)*12+4) -> 8910.9552 | L19: =INDEX(Monthly!$C$48:$BJ$48,($R$2-1)*12+5) -> 8954.8441 | M19: =INDEX(Monthly!$C$48:$BJ$48,($R$2-1)*12+6) -> 8998.7329 | N19: =INDEX(Monthly!$C$48:$BJ$48,($R$2-1)*12+7) -> 9042.6218 | O19: =INDEX(Monthly!$C$48:$BJ$48,($R$2-1)*12+8) -> 9086.5107 | P19: =INDEX(Monthly!$C$48:$BJ$48,($R$2-1)*12+9) -> 9130.3996 | Q19: =INDEX(Monthly!$C$48:$BJ$48,($R$2-1)*12+10) -> 9174.2885 | R19: =INDEX(Monthly!$C$48:$BJ$48,($R$2-1)*12+11) -> 46271.587 | S19: =INDEX(Monthly!$C$48:$BJ$48,($R$2-1)*12+12) -> 46315.476
A20: Net margin | B20: ='P&L'!B26 -> 0.033069589 | C20: ='P&L'!C26 -> 0.053001485 | D20: ='P&L'!D26 -> 0.065952438 | E20: ='P&L'!E26 -> 0.07438239 | F20: ='P&L'!F26 -> 0.07968864 | H20: =IF(H7=0,0,H19/H7) -> 0.019873979 | I20: =IF(I7=0,0,I19/I7) -> 0.019923532 | J20: =IF(J7=0,0,J19/J7) -> 0.020022637 | K20: =IF(K7=0,0,K19/K7) -> 0.020121742 | L20: =IF(L7=0,0,L19/L7) -> 0.020220847 | M20: =IF(M7=0,0,M19/M7) -> 0.020319952 | N20: =IF(N7=0,0,N19/N7) -> 0.020419057 | O20: =IF(O7=0,0,O19/O7) -> 0.020518162 | ... S20: =IF(S7=0,0,S19/S7) -> 0.085262393
A22: Cash flow ($'000) — by year | H22: ="Cash flow ($'000) — Year "&$R$2&", by month" -> Cash flow ($'000) — Year 1, by month
B23: 1 | C23: 2 | D23: 3 | E23: 4 | F23: 5 | H23: =INDEX(Monthly!$C$4:$BJ$4,($R$2-1)*12+1) -> 1 | I23: =INDEX(Monthly!$C$4:$BJ$4,($R$2-1)*12+2) -> 2 | J23: =INDEX(Monthly!$C$4:$BJ$4,($R$2-1)*12+3) -> 3 | K23: =INDEX(Monthly!$C$4:$BJ$4,($R$2-1)*12+4) -> 4 | L23: =INDEX(Monthly!$C$4:$BJ$4,($R$2-1)*12+5) -> 5 | M23: =INDEX(Monthly!$C$4:$BJ$4,($R$2-1)*12+6) -> 6 | N23: =INDEX(Monthly!$C$4:$BJ$4,($R$2-1)*12+7) -> 7 | O23: =INDEX(Monthly!$C$4:$BJ$4,($R$2-1)*12+8) -> 8 | P23: =INDEX(Monthly!$C$4:$BJ$4,($R$2-1)*12+9) -> 9 | Q23: =INDEX(Monthly!$C$4:$BJ$4,($R$2-1)*12+10) -> 10 | R23: =INDEX(Monthly!$C$4:$BJ$4,($R$2-1)*12+11) -> 11 | S23: =INDEX(Monthly!$C$4:$BJ$4,($R$2-1)*12+12) -> 12
A24: Operating cash flow | B24: ='Cash Flow'!B10 -> -146060.15 | C24: ='Cash Flow'!C10 -> 334798.67 | D24: ='Cash Flow'!D10 -> 557937.43 | E24: ='Cash Flow'!E10 -> 804972.77 | F24: ='Cash Flow'!F10 -> 1079551.3 | H24: =INDEX(Monthly!$C$72:$BJ$72,($R$2-1)*12+1) -> -295552.38 | I24: =INDEX(Monthly!$C$72:$BJ$72,($R$2-1)*12+2) -> 12989.844 | J24: =INDEX(Monthly!$C$72:$BJ$72,($R$2-1)*12+3) -> 13033.733 | K24: =INDEX(Monthly!$C$72:$BJ$72,($R$2-1)*12+4) -> 13077.622 | L24: =INDEX(Monthly!$C$72:$BJ$72,($R$2-1)*12+5) -> 13121.511 | M24: =INDEX(Monthly!$C$72:$BJ$72,($R$2-1)*12+6) -> 13165.4 | N24: =INDEX(Monthly!$C$72:$BJ$72,($R$2-1)*12+7) -> 13209.288 | O24: =INDEX(Monthly!$C$72:$BJ$72,($R$2-1)*12+8) -> 13253.177 | P24: =INDEX(Monthly!$C$72:$BJ$72,($R$2-1)*12+9) -> 13297.066 | Q24: =INDEX(Monthly!$C$72:$BJ$72,($R$2-1)*12+10) -> 13340.955 | R24: =INDEX(Monthly!$C$72:$BJ$72,($R$2-1)*12+11) -> -19478.516 | S24: =INDEX(Monthly!$C$72:$BJ$72,($R$2-1)*12+12) -> 50482.142
A25: Capital spending | B25: ='Cash Flow'!B11 -> -350000 | C25: ='Cash Flow'!C11 -> -150000 | D25: ='Cash Flow'!D11 -> -150000 | E25: ='Cash Flow'!E11 -> -150000 | F25: ='Cash Flow'!F11 -> -150000 | H25: =INDEX(Monthly!$C$73:$BJ$73,($R$2-1)*12+1) -> -350000 | I25: =INDEX(Monthly!$C$73:$BJ$73,($R$2-1)*12+2) -> 0 | J25: =INDEX(Monthly!$C$73:$BJ$73,($R$2-1)*12+3) -> 0 | K25: =INDEX(Monthly!$C$73:$BJ$73,($R$2-1)*12+4) -> 0 | L25: =INDEX(Monthly!$C$73:$BJ$73,($R$2-1)*12+5) -> 0 | M25: =INDEX(Monthly!$C$73:$BJ$73,($R$2-1)*12+6) -> 0 | N25: =INDEX(Monthly!$C$73:$BJ$73,($R$2-1)*12+7) -> 0 | O25: =INDEX(Monthly!$C$73:$BJ$73,($R$2-1)*12+8) -> 0 | P25: =INDEX(Monthly!$C$73:$BJ$73,($R$2-1)*12+9) -> 0 | Q25: =INDEX(Monthly!$C$73:$BJ$73,($R$2-1)*12+10) -> 0 | R25: =INDEX(Monthly!$C$73:$BJ$73,($R$2-1)*12+11) -> 0 | S25: =INDEX(Monthly!$C$73:$BJ$73,($R$2-1)*12+12) -> 0
A26: Equity raised | B26: ='Cash Flow'!B12 -> 1500000 | C26: ='Cash Flow'!C12 -> 0 | D26: ='Cash Flow'!D12 -> 0 | E26: ='Cash Flow'!E12 -> 0 | F26: ='Cash Flow'!F12 -> 0 | H26: =INDEX(Monthly!$C$74:$BJ$74,($R$2-1)*12+1) -> 1500000 | I26: =INDEX(Monthly!$C$74:$BJ$74,($R$2-1)*12+2) -> 0 | J26: =INDEX(Monthly!$C$74:$BJ$74,($R$2-1)*12+3) -> 0 | K26: =INDEX(Monthly!$C$74:$BJ$74,($R$2-1)*12+4) -> 0 | L26: =INDEX(Monthly!$C$74:$BJ$74,($R$2-1)*12+5) -> 0 | M26: =INDEX(Monthly!$C$74:$BJ$74,($R$2-1)*12+6) -> 0 | N26: =INDEX(Monthly!$C$74:$BJ$74,($R$2-1)*12+7) -> 0 | O26: =INDEX(Monthly!$C$74:$BJ$74,($R$2-1)*12+8) -> 0 | P26: =INDEX(Monthly!$C$74:$BJ$74,($R$2-1)*12+9) -> 0 | Q26: =INDEX(Monthly!$C$74:$BJ$74,($R$2-1)*12+10) -> 0 | R26: =INDEX(Monthly!$C$74:$BJ$74,($R$2-1)*12+11) -> 0 | S26: =INDEX(Monthly!$C$74:$BJ$74,($R$2-1)*12+12) -> 0
A27: Loan drawdown | B27: ='Cash Flow'!B13 -> 500000 | C27: ='Cash Flow'!C13 -> 0 | D27: ='Cash Flow'!D13 -> 0 | E27: ='Cash Flow'!E13 -> 0 | F27: ='Cash Flow'!F13 -> 0 | H27: =INDEX(Monthly!$C$59:$BJ$59,($R$2-1)*12+1) -> 500000 | I27: =INDEX(Monthly!$C$59:$BJ$59,($R$2-1)*12+2) -> 0 | J27: =INDEX(Monthly!$C$59:$BJ$59,($R$2-1)*12+3) -> 0 | K27: =INDEX(Monthly!$C$59:$BJ$59,($R$2-1)*12+4) -> 0 | L27: =INDEX(Monthly!$C$59:$BJ$59,($R$2-1)*12+5) -> 0 | M27: =INDEX(Monthly!$C$59:$BJ$59,($R$2-1)*12+6) -> 0 | N27: =INDEX(Monthly!$C$59:$BJ$59,($R$2-1)*12+7) -> 0 | O27: =INDEX(Monthly!$C$59:$BJ$59,($R$2-1)*12+8) -> 0 | P27: =INDEX(Monthly!$C$59:$BJ$59,($R$2-1)*12+9) -> 0 | Q27: =INDEX(Monthly!$C$59:$BJ$59,($R$2-1)*12+10) -> 0 | R27: =INDEX(Monthly!$C$59:$BJ$59,($R$2-1)*12+11) -> 0 | S27: =INDEX(Monthly!$C$59:$BJ$59,($R$2-1)*12+12) -> 0
A28: Loan repayment | B28: ='Cash Flow'!B14 -> -91666.667 | C28: ='Cash Flow'!C14 -> -100000 | D28: ='Cash Flow'!D14 -> -100000 | E28: ='Cash Flow'!E14 -> -100000 | F28: ='Cash Flow'!F14 -> -100000 | H28: =INDEX(Monthly!$C$60:$BJ$60,($R$2-1)*12+1) -> 0 | I28: =INDEX(Monthly!$C$60:$BJ$60,($R$2-1)*12+2) -> -8333.3333 | J28: =INDEX(Monthly!$C$60:$BJ$60,($R$2-1)*12+3) -> -8333.3333 | K28: =INDEX(Monthly!$C$60:$BJ$60,($R$2-1)*12+4) -> -8333.3333 | L28: =INDEX(Monthly!$C$60:$BJ$60,($R$2-1)*12+5) -> -8333.3333 | M28: =INDEX(Monthly!$C$60:$BJ$60,($R$2-1)*12+6) -> -8333.3333 | N28: =INDEX(Monthly!$C$60:$BJ$60,($R$2-1)*12+7) -> -8333.3333 | O28: =INDEX(Monthly!$C$60:$BJ$60,($R$2-1)*12+8) -> -8333.3333 | P28: =INDEX(Monthly!$C$60:$BJ$60,($R$2-1)*12+9) -> -8333.3333 | Q28: =INDEX(Monthly!$C$60:$BJ$60,($R$2-1)*12+10) -> -8333.3333 | R28: =INDEX(Monthly!$C$60:$BJ$60,($R$2-1)*12+11) -> -8333.3333 | S28: =INDEX(Monthly!$C$60:$BJ$60,($R$2-1)*12+12) -> -8333.3333
A29: Financing cash flow | B29: ='Cash Flow'!B15 -> 1908333.3 | C29: ='Cash Flow'!C15 -> -100000 | D29: ='Cash Flow'!D15 -> -100000 | E29: ='Cash Flow'!E15 -> -100000 | F29: ='Cash Flow'!F15 -> -100000 | H29: =INDEX(Monthly!$C$75:$BJ$75,($R$2-1)*12+1) -> 2000000 | I29: =INDEX(Monthly!$C$75:$BJ$75,($R$2-1)*12+2) -> -8333.3333 | J29: =INDEX(Monthly!$C$75:$BJ$75,($R$2-1)*12+3) -> -8333.3333 | K29: =INDEX(Monthly!$C$75:$BJ$75,($R$2-1)*12+4) -> -8333.3333 | L29: =INDEX(Monthly!$C$75:$BJ$75,($R$2-1)*12+5) -> -8333.3333 | M29: =INDEX(Monthly!$C$75:$BJ$75,($R$2-1)*12+6) -> -8333.3333 | N29: =INDEX(Monthly!$C$75:$BJ$75,($R$2-1)*12+7) -> -8333.3333 | O29: =INDEX(Monthly!$C$75:$BJ$75,($R$2-1)*12+8) -> -8333.3333 | P29: =INDEX(Monthly!$C$75:$BJ$75,($R$2-1)*12+9) -> -8333.3333 | Q29: =INDEX(Monthly!$C$75:$BJ$75,($R$2-1)*12+10) -> -8333.3333 | R29: =INDEX(Monthly!$C$75:$BJ$75,($R$2-1)*12+11) -> -8333.3333 | S29: =INDEX(Monthly!$C$75:$BJ$75,($R$2-1)*12+12) -> -8333.3333
A30: Net change in cash | B30: ='Cash Flow'!B16 -> 1412273.2 | C30: ='Cash Flow'!C16 -> 84798.669 | D30: ='Cash Flow'!D16 -> 307937.43 | E30: ='Cash Flow'!E16 -> 554972.77 | F30: ='Cash Flow'!F16 -> 829551.32 | H30: =INDEX(Monthly!$C$76:$BJ$76,($R$2-1)*12+1) -> 1354447.6 | I30: =INDEX(Monthly!$C$76:$BJ$76,($R$2-1)*12+2) -> 4656.5107 | J30: =INDEX(Monthly!$C$76:$BJ$76,($R$2-1)*12+3) -> 4700.3996 | K30: =INDEX(Monthly!$C$76:$BJ$76,($R$2-1)*12+4) -> 4744.2885 | L30: =INDEX(Monthly!$C$76:$BJ$76,($R$2-1)*12+5) -> 4788.1774 | M30: =INDEX(Monthly!$C$76:$BJ$76,($R$2-1)*12+6) -> 4832.0663 | N30: =INDEX(Monthly!$C$76:$BJ$76,($R$2-1)*12+7) -> 4875.9552 | O30: =INDEX(Monthly!$C$76:$BJ$76,($R$2-1)*12+8) -> 4919.8441 | P30: =INDEX(Monthly!$C$76:$BJ$76,($R$2-1)*12+9) -> 4963.7329 | Q30: =INDEX(Monthly!$C$76:$BJ$76,($R$2-1)*12+10) -> 5007.6218 | R30: =INDEX(Monthly!$C$76:$BJ$76,($R$2-1)*12+11) -> -27811.85 | S30: =INDEX(Monthly!$C$76:$BJ$76,($R$2-1)*12+12) -> 42148.809
A31: Closing cash | B31: ='Cash Flow'!B18 -> 1412273.2 | C31: ='Cash Flow'!C18 -> 1497071.8 | D31: ='Cash Flow'!D18 -> 1805009.3 | E31: ='Cash Flow'!E18 -> 2359982 | F31: ='Cash Flow'!F18 -> 3189533.4 | H31: =INDEX(Monthly!$C$78:$BJ$78,($R$2-1)*12+1) -> 1354447.6 | I31: =INDEX(Monthly!$C$78:$BJ$78,($R$2-1)*12+2) -> 1359104.1 | J31: =INDEX(Monthly!$C$78:$BJ$78,($R$2-1)*12+3) -> 1363804.5 | K31: =INDEX(Monthly!$C$78:$BJ$78,($R$2-1)*12+4) -> 1368548.8 | L31: =INDEX(Monthly!$C$78:$BJ$78,($R$2-1)*12+5) -> 1373337 | M31: =INDEX(Monthly!$C$78:$BJ$78,($R$2-1)*12+6) -> 1378169.1 | N31: =INDEX(Monthly!$C$78:$BJ$78,($R$2-1)*12+7) -> 1383045 | O31: =INDEX(Monthly!$C$78:$BJ$78,($R$2-1)*12+8) -> 1387964.9 | P31: =INDEX(Monthly!$C$78:$BJ$78,($R$2-1)*12+9) -> 1392928.6 | Q31: =INDEX(Monthly!$C$78:$BJ$78,($R$2-1)*12+10) -> 1397936.2 | R31: =INDEX(Monthly!$C$78:$BJ$78,($R$2-1)*12+11) -> 1370124.4 | S31: =INDEX(Monthly!$C$78:$BJ$78,($R$2-1)*12+12) -> 1412273.2
A39: Balance sheet at year end ($'000) | H39: ="Balance sheet at month end ($'000) — Year "&$R$2 -> Balance sheet at month end ($'000) — Year 1
B40: 1 | C40: 2 | D40: 3 | E40: 4 | F40: 5 | H40: =INDEX(Monthly!$C$4:$BJ$4,($R$2-1)*12+1) -> 1 | I40: =INDEX(Monthly!$C$4:$BJ$4,($R$2-1)*12+2) -> 2 | J40: =INDEX(Monthly!$C$4:$BJ$4,($R$2-1)*12+3) -> 3 | K40: =INDEX(Monthly!$C$4:$BJ$4,($R$2-1)*12+4) -> 4 | L40: =INDEX(Monthly!$C$4:$BJ$4,($R$2-1)*12+5) -> 5 | M40: =INDEX(Monthly!$C$4:$BJ$4,($R$2-1)*12+6) -> 6 | N40: =INDEX(Monthly!$C$4:$BJ$4,($R$2-1)*12+7) -> 7 | O40: =INDEX(Monthly!$C$4:$BJ$4,($R$2-1)*12+8) -> 8 | P40: =INDEX(Monthly!$C$4:$BJ$4,($R$2-1)*12+9) -> 9 | Q40: =INDEX(Monthly!$C$4:$BJ$4,($R$2-1)*12+10) -> 10 | R40: =INDEX(Monthly!$C$4:$BJ$4,($R$2-1)*12+11) -> 11 | S40: =INDEX(Monthly!$C$4:$BJ$4,($R$2-1)*12+12) -> 12
A41: Cash | B41: ='Balance Sheet'!B5 -> 1412273.2 | C41: ='Balance Sheet'!C5 -> 1497071.8 | D41: ='Balance Sheet'!D5 -> 1805009.3 | E41: ='Balance Sheet'!E5 -> 2359982 | F41: ='Balance Sheet'!F5 -> 3189533.4 | H41: =INDEX(Monthly!$C$78:$BJ$78,($R$2-1)*12+1) -> 1354447.6 | I41: =INDEX(Monthly!$C$78:$BJ$78,($R$2-1)*12+2) -> 1359104.1 | J41: =INDEX(Monthly!$C$78:$BJ$78,($R$2-1)*12+3) -> 1363804.5 | K41: =INDEX(Monthly!$C$78:$BJ$78,($R$2-1)*12+4) -> 1368548.8 | L41: =INDEX(Monthly!$C$78:$BJ$78,($R$2-1)*12+5) -> 1373337 | M41: =INDEX(Monthly!$C$78:$BJ$78,($R$2-1)*12+6) -> 1378169.1 | N41: =INDEX(Monthly!$C$78:$BJ$78,($R$2-1)*12+7) -> 1383045 | O41: =INDEX(Monthly!$C$78:$BJ$78,($R$2-1)*12+8) -> 1387964.9 | P41: =INDEX(Monthly!$C$78:$BJ$78,($R$2-1)*12+9) -> 1392928.6 | Q41: =INDEX(Monthly!$C$78:$BJ$78,($R$2-1)*12+10) -> 1397936.2 | R41: =INDEX(Monthly!$C$78:$BJ$78,($R$2-1)*12+11) -> 1370124.4 | S41: =INDEX(Monthly!$C$78:$BJ$78,($R$2-1)*12+12) -> 1412273.2
A42: Accounts receivable | B42: ='Balance Sheet'!B6 -> 36214.071 | C42: ='Balance Sheet'!C6 -> 47422.896 | D42: ='Balance Sheet'!D6 -> 60662.751 | E42: ='Balance Sheet'!E6 -> 76424.031 | F42: ='Balance Sheet'!F6 -> 95323.953 | H42: =INDEX(Monthly!$C$64:$BJ$64,($R$2-1)*12+1) -> 29523.471 | I42: =INDEX(Monthly!$C$64:$BJ$64,($R$2-1)*12+2) -> 29523.471 | J42: =INDEX(Monthly!$C$64:$BJ$64,($R$2-1)*12+3) -> 29523.471 | K42: =INDEX(Monthly!$C$64:$BJ$64,($R$2-1)*12+4) -> 29523.471 | L42: =INDEX(Monthly!$C$64:$BJ$64,($R$2-1)*12+5) -> 29523.471 | M42: =INDEX(Monthly!$C$64:$BJ$64,($R$2-1)*12+6) -> 29523.471 | N42: =INDEX(Monthly!$C$64:$BJ$64,($R$2-1)*12+7) -> 29523.471 | O42: =INDEX(Monthly!$C$64:$BJ$64,($R$2-1)*12+8) -> 29523.471 | P42: =INDEX(Monthly!$C$64:$BJ$64,($R$2-1)*12+9) -> 29523.471 | Q42: =INDEX(Monthly!$C$64:$BJ$64,($R$2-1)*12+10) -> 29523.471 | R42: =INDEX(Monthly!$C$64:$BJ$64,($R$2-1)*12+11) -> 36214.071 | S42: =INDEX(Monthly!$C$64:$BJ$64,($R$2-1)*12+12) -> 36214.071
A43: Inventory | B43: ='Balance Sheet'!B7 -> 570371.62 | C43: ='Balance Sheet'!C7 -> 746910.62 | D43: ='Balance Sheet'!D7 -> 955438.33 | E43: ='Balance Sheet'!E7 -> 1203678.5 | F43: ='Balance Sheet'!F7 -> 1501352.3 | H43: =INDEX(Monthly!$C$65:$BJ$65,($R$2-1)*12+1) -> 464994.67 | I43: =INDEX(Monthly!$C$65:$BJ$65,($R$2-1)*12+2) -> 464994.67 | J43: =INDEX(Monthly!$C$65:$BJ$65,($R$2-1)*12+3) -> 464994.67 | K43: =INDEX(Monthly!$C$65:$BJ$65,($R$2-1)*12+4) -> 464994.67 | L43: =INDEX(Monthly!$C$65:$BJ$65,($R$2-1)*12+5) -> 464994.67 | M43: =INDEX(Monthly!$C$65:$BJ$65,($R$2-1)*12+6) -> 464994.67 | N43: =INDEX(Monthly!$C$65:$BJ$65,($R$2-1)*12+7) -> 464994.67 | O43: =INDEX(Monthly!$C$65:$BJ$65,($R$2-1)*12+8) -> 464994.67 | P43: =INDEX(Monthly!$C$65:$BJ$65,($R$2-1)*12+9) -> 464994.67 | Q43: =INDEX(Monthly!$C$65:$BJ$65,($R$2-1)*12+10) -> 464994.67 | R43: =INDEX(Monthly!$C$65:$BJ$65,($R$2-1)*12+11) -> 570371.62 | S43: =INDEX(Monthly!$C$65:$BJ$65,($R$2-1)*12+12) -> 570371.62
A44: Net fixed assets | B44: ='Balance Sheet'!B8 -> 300000 | C44: ='Balance Sheet'!C8 -> 378571.43 | D44: ='Balance Sheet'!D8 -> 435714.29 | E44: ='Balance Sheet'!E8 -> 471428.57 | F44: ='Balance Sheet'!F8 -> 485714.29 | H44: =INDEX(Monthly!$C$55:$BJ$55,($R$2-1)*12+1) -> 345833.33 | I44: =INDEX(Monthly!$C$55:$BJ$55,($R$2-1)*12+2) -> 341666.67 | J44: =INDEX(Monthly!$C$55:$BJ$55,($R$2-1)*12+3) -> 337500 | K44: =INDEX(Monthly!$C$55:$BJ$55,($R$2-1)*12+4) -> 333333.33 | L44: =INDEX(Monthly!$C$55:$BJ$55,($R$2-1)*12+5) -> 329166.67 | M44: =INDEX(Monthly!$C$55:$BJ$55,($R$2-1)*12+6) -> 325000 | N44: =INDEX(Monthly!$C$55:$BJ$55,($R$2-1)*12+7) -> 320833.33 | O44: =INDEX(Monthly!$C$55:$BJ$55,($R$2-1)*12+8) -> 316666.67 | P44: =INDEX(Monthly!$C$55:$BJ$55,($R$2-1)*12+9) -> 312500 | Q44: =INDEX(Monthly!$C$55:$BJ$55,($R$2-1)*12+10) -> 308333.33 | R44: =INDEX(Monthly!$C$55:$BJ$55,($R$2-1)*12+11) -> 304166.67 | S44: =INDEX(Monthly!$C$55:$BJ$55,($R$2-1)*12+12) -> 300000
A45: Total assets | B45: ='Balance Sheet'!B9 -> 2318858.9 | C45: ='Balance Sheet'!C9 -> 2669976.8 | D45: ='Balance Sheet'!D9 -> 3256824.6 | E45: ='Balance Sheet'!E9 -> 4111513.1 | F45: ='Balance Sheet'!F9 -> 5271923.9 | H45: =INDEX(Monthly!$C$92:$BJ$92,($R$2-1)*12+1) -> 2194799.1 | I45: =INDEX(Monthly!$C$92:$BJ$92,($R$2-1)*12+2) -> 2195288.9 | J45: =INDEX(Monthly!$C$92:$BJ$92,($R$2-1)*12+3) -> 2195822.7 | K45: =INDEX(Monthly!$C$92:$BJ$92,($R$2-1)*12+4) -> 2196400.3 | L45: =INDEX(Monthly!$C$92:$BJ$92,($R$2-1)*12+5) -> 2197021.8 | M45: =INDEX(Monthly!$C$92:$BJ$92,($R$2-1)*12+6) -> 2197687.2 | N45: =INDEX(Monthly!$C$92:$BJ$92,($R$2-1)*12+7) -> 2198396.5 | O45: =INDEX(Monthly!$C$92:$BJ$92,($R$2-1)*12+8) -> 2199149.7 | P45: =INDEX(Monthly!$C$92:$BJ$92,($R$2-1)*12+9) -> 2199946.7 | Q45: =INDEX(Monthly!$C$92:$BJ$92,($R$2-1)*12+10) -> 2200787.7 | R45: =INDEX(Monthly!$C$92:$BJ$92,($R$2-1)*12+11) -> 2280876.7 | S45: =INDEX(Monthly!$C$92:$BJ$92,($R$2-1)*12+12) -> 2318858.9
A46: Accounts payable | B46: ='Balance Sheet'!B10 -> 228148.65 | C46: ='Balance Sheet'!C10 -> 298764.25 | D46: ='Balance Sheet'!D10 -> 382175.33 | E46: ='Balance Sheet'!E10 -> 481471.4 | F46: ='Balance Sheet'!F10 -> 600540.91 | H46: =INDEX(Monthly!$C$66:$BJ$66,($R$2-1)*12+1) -> 185997.87 | I46: =INDEX(Monthly!$C$66:$BJ$66,($R$2-1)*12+2) -> 185997.87 | J46: =INDEX(Monthly!$C$66:$BJ$66,($R$2-1)*12+3) -> 185997.87 | K46: =INDEX(Monthly!$C$66:$BJ$66,($R$2-1)*12+4) -> 185997.87 | L46: =INDEX(Monthly!$C$66:$BJ$66,($R$2-1)*12+5) -> 185997.87 | M46: =INDEX(Monthly!$C$66:$BJ$66,($R$2-1)*12+6) -> 185997.87 | N46: =INDEX(Monthly!$C$66:$BJ$66,($R$2-1)*12+7) -> 185997.87 | O46: =INDEX(Monthly!$C$66:$BJ$66,($R$2-1)*12+8) -> 185997.87 | P46: =INDEX(Monthly!$C$66:$BJ$66,($R$2-1)*12+9) -> 185997.87 | Q46: =INDEX(Monthly!$C$66:$BJ$66,($R$2-1)*12+10) -> 185997.87 | R46: =INDEX(Monthly!$C$66:$BJ$66,($R$2-1)*12+11) -> 228148.65 | S46: =INDEX(Monthly!$C$66:$BJ$66,($R$2-1)*12+12) -> 228148.65
A47: Loan | B47: ='Balance Sheet'!B11 -> 408333.33 | C47: ='Balance Sheet'!C11 -> 308333.33 | D47: ='Balance Sheet'!D11 -> 208333.33 | E47: ='Balance Sheet'!E11 -> 108333.33 | F47: ='Balance Sheet'!F11 -> 8333.3333 | H47: =INDEX(Monthly!$C$61:$BJ$61,($R$2-1)*12+1) -> 500000 | I47: =INDEX(Monthly!$C$61:$BJ$61,($R$2-1)*12+2) -> 491666.67 | J47: =INDEX(Monthly!$C$61:$BJ$61,($R$2-1)*12+3) -> 483333.33 | K47: =INDEX(Monthly!$C$61:$BJ$61,($R$2-1)*12+4) -> 475000 | L47: =INDEX(Monthly!$C$61:$BJ$61,($R$2-1)*12+5) -> 466666.67 | M47: =INDEX(Monthly!$C$61:$BJ$61,($R$2-1)*12+6) -> 458333.33 | N47: =INDEX(Monthly!$C$61:$BJ$61,($R$2-1)*12+7) -> 450000 | O47: =INDEX(Monthly!$C$61:$BJ$61,($R$2-1)*12+8) -> 441666.67 | P47: =INDEX(Monthly!$C$61:$BJ$61,($R$2-1)*12+9) -> 433333.33 | Q47: =INDEX(Monthly!$C$61:$BJ$61,($R$2-1)*12+10) -> 425000 | R47: =INDEX(Monthly!$C$61:$BJ$61,($R$2-1)*12+11) -> 416666.67 | S47: =INDEX(Monthly!$C$61:$BJ$61,($R$2-1)*12+12) -> 408333.33
A48: Total liabilities | B48: ='Balance Sheet'!B12 -> 636481.98 | C48: ='Balance Sheet'!C12 -> 607097.58 | D48: ='Balance Sheet'!D12 -> 590508.67 | E48: ='Balance Sheet'!E12 -> 589804.73 | F48: ='Balance Sheet'!F12 -> 608874.24 | H48: =INDEX(Monthly!$C$93:$BJ$93,($R$2-1)*12+1) -> 685997.87 | I48: =INDEX(Monthly!$C$93:$BJ$93,($R$2-1)*12+2) -> 677664.54 | J48: =INDEX(Monthly!$C$93:$BJ$93,($R$2-1)*12+3) -> 669331.2 | K48: =INDEX(Monthly!$C$93:$BJ$93,($R$2-1)*12+4) -> 660997.87 | L48: =INDEX(Monthly!$C$93:$BJ$93,($R$2-1)*12+5) -> 652664.54 | M48: =INDEX(Monthly!$C$93:$BJ$93,($R$2-1)*12+6) -> 644331.2 | N48: =INDEX(Monthly!$C$93:$BJ$93,($R$2-1)*12+7) -> 635997.87 | O48: =INDEX(Monthly!$C$93:$BJ$93,($R$2-1)*12+8) -> 627664.54 | P48: =INDEX(Monthly!$C$93:$BJ$93,($R$2-1)*12+9) -> 619331.2 | Q48: =INDEX(Monthly!$C$93:$BJ$93,($R$2-1)*12+10) -> 610997.87 | R48: =INDEX(Monthly!$C$93:$BJ$93,($R$2-1)*12+11) -> 644815.32 | S48: =INDEX(Monthly!$C$93:$BJ$93,($R$2-1)*12+12) -> 636481.98
A49: Paid-in capital | B49: ='Balance Sheet'!B13 -> 1500000 | C49: ='Balance Sheet'!C13 -> 1500000 | D49: ='Balance Sheet'!D13 -> 1500000 | E49: ='Balance Sheet'!E13 -> 1500000 | F49: ='Balance Sheet'!F13 -> 1500000 | H49: =INDEX(Monthly!$C$90:$BJ$90,($R$2-1)*12+1) -> 1500000 | I49: =INDEX(Monthly!$C$90:$BJ$90,($R$2-1)*12+2) -> 1500000 | J49: =INDEX(Monthly!$C$90:$BJ$90,($R$2-1)*12+3) -> 1500000 | K49: =INDEX(Monthly!$C$90:$BJ$90,($R$2-1)*12+4) -> 1500000 | L49: =INDEX(Monthly!$C$90:$BJ$90,($R$2-1)*12+5) -> 1500000 | M49: =INDEX(Monthly!$C$90:$BJ$90,($R$2-1)*12+6) -> 1500000 | N49: =INDEX(Monthly!$C$90:$BJ$90,($R$2-1)*12+7) -> 1500000 | O49: =INDEX(Monthly!$C$90:$BJ$90,($R$2-1)*12+8) -> 1500000 | P49: =INDEX(Monthly!$C$90:$BJ$90,($R$2-1)*12+9) -> 1500000 | Q49: =INDEX(Monthly!$C$90:$BJ$90,($R$2-1)*12+10) -> 1500000 | R49: =INDEX(Monthly!$C$90:$BJ$90,($R$2-1)*12+11) -> 1500000 | S49: =INDEX(Monthly!$C$90:$BJ$90,($R$2-1)*12+12) -> 1500000
A50: Retained earnings | B50: ='Balance Sheet'!B14 -> 182376.89 | C50: ='Balance Sheet'!C14 -> 562879.21 | D50: ='Balance Sheet'!D14 -> 1166316 | E50: ='Balance Sheet'!E14 -> 2021708.4 | F50: ='Balance Sheet'!F14 -> 3163049.6 | H50: =INDEX(Monthly!$C$91:$BJ$91,($R$2-1)*12+1) -> 8801.2329 | I50: =INDEX(Monthly!$C$91:$BJ$91,($R$2-1)*12+2) -> 17624.41 | J50: =INDEX(Monthly!$C$91:$BJ$91,($R$2-1)*12+3) -> 26491.477 | K50: =INDEX(Monthly!$C$91:$BJ$91,($R$2-1)*12+4) -> 35402.432 | L50: =INDEX(Monthly!$C$91:$BJ$91,($R$2-1)*12+5) -> 44357.276 | M50: =INDEX(Monthly!$C$91:$BJ$91,($R$2-1)*12+6) -> 53356.009 | N50: =INDEX(Monthly!$C$91:$BJ$91,($R$2-1)*12+7) -> 62398.631 | O50: =INDEX(Monthly!$C$91:$BJ$91,($R$2-1)*12+8) -> 71485.141 | P50: =INDEX(Monthly!$C$91:$BJ$91,($R$2-1)*12+9) -> 80615.541 | Q50: =INDEX(Monthly!$C$91:$BJ$91,($R$2-1)*12+10) -> 89789.829 | R50: =INDEX(Monthly!$C$91:$BJ$91,($R$2-1)*12+11) -> 136061.42 | S50: =INDEX(Monthly!$C$91:$BJ$91,($R$2-1)*12+12) -> 182376.89
A51: Total equity | B51: ='Balance Sheet'!B15 -> 1682376.9 | C51: ='Balance Sheet'!C15 -> 2062879.2 | D51: ='Balance Sheet'!D15 -> 2666316 | E51: ='Balance Sheet'!E15 -> 3521708.4 | F51: ='Balance Sheet'!F15 -> 4663049.6 | H51: =INDEX(Monthly!$C$94:$BJ$94,($R$2-1)*12+1) -> 1508801.2 | I51: =INDEX(Monthly!$C$94:$BJ$94,($R$2-1)*12+2) -> 1517624.4 | J51: =INDEX(Monthly!$C$94:$BJ$94,($R$2-1)*12+3) -> 1526491.5 | K51: =INDEX(Monthly!$C$94:$BJ$94,($R$2-1)*12+4) -> 1535402.4 | L51: =INDEX(Monthly!$C$94:$BJ$94,($R$2-1)*12+5) -> 1544357.3 | M51: =INDEX(Monthly!$C$94:$BJ$94,($R$2-1)*12+6) -> 1553356 | N51: =INDEX(Monthly!$C$94:$BJ$94,($R$2-1)*12+7) -> 1562398.6 | O51: =INDEX(Monthly!$C$94:$BJ$94,($R$2-1)*12+8) -> 1571485.1 | P51: =INDEX(Monthly!$C$94:$BJ$94,($R$2-1)*12+9) -> 1580615.5 | Q51: =INDEX(Monthly!$C$94:$BJ$94,($R$2-1)*12+10) -> 1589789.8 | R51: =INDEX(Monthly!$C$94:$BJ$94,($R$2-1)*12+11) -> 1636061.4 | S51: =INDEX(Monthly!$C$94:$BJ$94,($R$2-1)*12+12) -> 1682376.9
A52: Total liabilities & equity | B52: ='Balance Sheet'!B16 -> 2318858.9 | C52: ='Balance Sheet'!C16 -> 2669976.8 | D52: ='Balance Sheet'!D16 -> 3256824.6 | E52: ='Balance Sheet'!E16 -> 4111513.1 | F52: ='Balance Sheet'!F16 -> 5271923.9 | H52: =INDEX(Monthly!$C$95:$BJ$95,($R$2-1)*12+1) -> 2194799.1 | I52: =INDEX(Monthly!$C$95:$BJ$95,($R$2-1)*12+2) -> 2195288.9 | J52: =INDEX(Monthly!$C$95:$BJ$95,($R$2-1)*12+3) -> 2195822.7 | K52: =INDEX(Monthly!$C$95:$BJ$95,($R$2-1)*12+4) -> 2196400.3 | L52: =INDEX(Monthly!$C$95:$BJ$95,($R$2-1)*12+5) -> 2197021.8 | M52: =INDEX(Monthly!$C$95:$BJ$95,($R$2-1)*12+6) -> 2197687.2 | N52: =INDEX(Monthly!$C$95:$BJ$95,($R$2-1)*12+7) -> 2198396.5 | O52: =INDEX(Monthly!$C$95:$BJ$95,($R$2-1)*12+8) -> 2199149.7 | P52: =INDEX(Monthly!$C$95:$BJ$95,($R$2-1)*12+9) -> 2199946.7 | Q52: =INDEX(Monthly!$C$95:$BJ$95,($R$2-1)*12+10) -> 2200787.7 | R52: =INDEX(Monthly!$C$95:$BJ$95,($R$2-1)*12+11) -> 2280876.7 | S52: =INDEX(Monthly!$C$95:$BJ$95,($R$2-1)*12+12) -> 2318858.9

Sheet Scenarios
A1: Scenarios — Low / Base / High | H1: =HYPERLINK("#'Cover'!A1","◂ Contents") -> ◂ Contents
A2: All three scenarios calculated side by side, live: change any input and every column updates. Active = the scenario chosen on the Dashboard.
A5: Key drivers
A6: Driver | B6: Low | C6: Base | D6: High | E6: Active
A7: Website visits per month (year 1, non-paid) (# / month) | B7: =Inputs!$B$7 -> 65000 | C7: =Inputs!$C$7 -> 80000 | D7: =Inputs!$D$7 -> 100000 | E7: =Inputs!$E$7 -> 80000
A8: Conversion rate (orders ÷ visits) (%) | B8: =Inputs!$B$9 -> 0.02 | C8: =Inputs!$C$9 -> 0.024 | D8: =Inputs!$D$9 -> 0.028 | E8: =Inputs!$E$9 -> 0.024
A9: Average order value (before returns) ($) | B9: =Inputs!$B$10 -> 65 | C9: =Inputs!$C$10 -> 75 | D9: =Inputs!$D$10 -> 85 | E9: =Inputs!$E$10 -> 75
A10: Paid ads budget per month (year 1) ($ / month) | B10: =Inputs!$B$13 -> 50000 | C10: =Inputs!$C$13 -> 50000 | D10: =Inputs!$D$13 -> 50000 | E10: =Inputs!$E$13 -> 50000
A11: Product cost, % of net sales (%) | B11: =Inputs!$B$30 -> 0.45 | C11: =Inputs!$C$30 -> 0.42 | D11: =Inputs!$D$30 -> 0.39 | E11: =Inputs!$E$30 -> 0.42
A12: Stores open at start (#) | B12: =Inputs!$B$18 -> 2 | C12: =Inputs!$C$18 -> 2 | D12: =Inputs!$D$18 -> 2 | E12: =Inputs!$E$18 -> 2
A13: Equity raised at start ($) | B13: =Inputs!$B$58 -> 1500000 | C13: =Inputs!$C$58 -> 1500000 | D13: =Inputs!$D$58 -> 1500000 | E13: =Inputs!$E$58 -> 1500000
A15: Results by scenario ($'000)
A16: Output | B16: Low | C16: Base | D16: High | E16: Active
A17: Revenue — final year | B17: =F30 -> 6972588.8 | C17: =F31 -> 14322508 | D17: =F32 -> 31530129 | E17: ='P&L'!F5 -> 14322508
A18: Revenue — whole plan | B18: =SUM(B30:F30) -> 25478839 | C18: =SUM(B31:F31) -> 47666046 | D18: =SUM(B32:F32) -> 92721302 | E18: =SUM('P&L'!$B$5:$F$5) -> 47666046
A19: EBITDA — final year | B19: =F36 -> -2181544.9 | C19: =F37 -> 1585116.7 | D19: =F38 -> 11124362 | E19: ='P&L'!F18 -> 1585116.7
A20: EBITDA margin — final year | B20: =IF(B17=0,0,B19/B17) -> -0.31287445 | C20: =IF(C17=0,0,C19/C17) -> 0.11067312 | D20: =IF(D17=0,0,D19/D17) -> 0.35281688 | E20: =IF(E17=0,0,E19/E17) -> 0.11067312
A21: Net income — final year | B21: =F42 -> -2321925.8 | C21: =F43 -> 1141341.2 | D21: =F44 -> 8677345 | E21: ='P&L'!F25 -> 1141341.2
A22: Net income — whole plan | B22: =SUM(B42:F42) -> -7543588.7 | C22: =SUM(B43:F43) -> 3163049.6 | D22: =SUM(B44:F44) -> 23191560 | E22: =SUM('P&L'!$B$25:$F$25) -> 3163049.6
A23: Cash at the end of the plan | B23: =F48 -> -7029882.6 | C23: =F49 -> 3189533.4 | D23: =F50 -> 22123099 | E23: ='Balance Sheet'!F5 -> 3189533.4
A24: Lowest cash balance | B24: =MIN('Scenario calc'!$C$80:$BJ$80) -> -7029882.6 | C24: =MIN('Scenario calc'!$C$191:$BJ$191) -> 1260305.1 | D24: =MIN('Scenario calc'!$C$302:$BJ$302) -> 1323640.8 | E24: ='Break-even'!B18 -> 1260305.1
A25: Lowest cash point (month #) | B25: =MATCH(MIN('Scenario calc'!$C$80:$BJ$80),'Scenario calc'!$C$80:$BJ$80,0) -> 60 | C25: =MATCH(MIN('Scenario calc'!$C$191:$BJ$191),'Scenario calc'!$C$191:$BJ$191,0) -> 13 | D25: =MATCH(MIN('Scenario calc'!$C$302:$BJ$302),'Scenario calc'!$C$302:$BJ$302,0) -> 1 | E25: ='Break-even'!B6 -> 13
A26: Funding required (incl. cash buffer) | B26: =SUMPRODUCT(--('Scenario calc'!$C$6:$BJ$6<=B25),'Scenario calc'!$C$53:$BJ$53)-SUMPRODUCT(--('Scenario calc'!$C$6:$BJ$6<=B25),'Scenario calc'!$C$74:$BJ$74)-SUMPRODUCT(--('Scenario calc'!$C$6:$BJ$6<=B25),'Scenario calc'!$C$62:$BJ$62)+Inputs!$B$73 -> 9749882.6 | C26: =SUMPRODUCT(--('Scenario calc'!$C$117:$BJ$117<=C25),'Scenario calc'!$C$164:$BJ$164)-SUMPRODUCT(--('Scenario calc'!$C$117:$BJ$117<=C25),'Scenario calc'!$C$185:$BJ$185)-SUMPRODUCT(--('Scenario calc'!$C$117:$BJ$117<=C25),'Scenario calc'!$C$173:$BJ$173)+Inputs!$C$73 -> 1459694.9 | D26: =SUMPRODUCT(--('Scenario calc'!$C$228:$BJ$228<=D25),'Scenario calc'!$C$275:$BJ$275)-SUMPRODUCT(--('Scenario calc'!$C$228:$BJ$228<=D25),'Scenario calc'!$C$296:$BJ$296)-SUMPRODUCT(--('Scenario calc'!$C$228:$BJ$228<=D25),'Scenario calc'!$C$284:$BJ$284)+Inputs!$D$73 -> 1396359.2 | E26: ='Break-even'!B12 -> 1459694.9
A28: Revenue by year ($'000)
A29: Scenario | B29: 1 | C29: 2 | D29: 3 | E29: 4 | F29: 5
A30: Low | B30: =SUMIF('Scenario calc'!$C$7:$BJ$7,B$29,'Scenario calc'!$C$27:$BJ$27) -> 3375914.7 | C30: =SUMIF('Scenario calc'!$C$7:$BJ$7,C$29,'Scenario calc'!$C$27:$BJ$27) -> 4163772.8 | D30: =SUMIF('Scenario calc'!$C$7:$BJ$7,D$29,'Scenario calc'!$C$27:$BJ$27) -> 5017510.1 | E30: =SUMIF('Scenario calc'!$C$7:$BJ$7,E$29,'Scenario calc'!$C$27:$BJ$27) -> 5949053.1 | F30: =SUMIF('Scenario calc'!$C$7:$BJ$7,F$29,'Scenario calc'!$C$27:$BJ$27) -> 6972588.8
A31: Base | B31: =SUMIF('Scenario calc'!$C$118:$BJ$118,B$29,'Scenario calc'!$C$138:$BJ$138) -> 5514942.9 | C31: =SUMIF('Scenario calc'!$C$118:$BJ$118,C$29,'Scenario calc'!$C$138:$BJ$138) -> 7179087.9 | D31: =SUMIF('Scenario calc'!$C$118:$BJ$118,D$29,'Scenario calc'!$C$138:$BJ$138) -> 9149574.9 | E31: =SUMIF('Scenario calc'!$C$118:$BJ$118,E$29,'Scenario calc'!$C$138:$BJ$138) -> 11499932 | F31: =SUMIF('Scenario calc'!$C$118:$BJ$118,F$29,'Scenario calc'!$C$138:$BJ$138) -> 14322508
A32: High | B32: =SUMIF('Scenario calc'!$C$229:$BJ$229,B$29,'Scenario calc'!$C$249:$BJ$249) -> 8858395.6 | C32: =SUMIF('Scenario calc'!$C$229:$BJ$229,C$29,'Scenario calc'!$C$249:$BJ$249) -> 12317220 | D32: =SUMIF('Scenario calc'!$C$229:$BJ$229,D$29,'Scenario calc'!$C$249:$BJ$249) -> 16913743 | E32: =SUMIF('Scenario calc'!$C$229:$BJ$229,E$29,'Scenario calc'!$C$249:$BJ$249) -> 23101814 | F32: =SUMIF('Scenario calc'!$C$229:$BJ$229,F$29,'Scenario calc'!$C$249:$BJ$249) -> 31530129
A34: EBITDA by year ($'000)
A35: Scenario | B35: 1 | C35: 2 | D35: 3 | E35: 4 | F35: 5
A36: Low | B36: =SUMIF('Scenario calc'!$C$7:$BJ$7,B$35,'Scenario calc'!$C$41:$BJ$41) -> -833184.37 | C36: =SUMIF('Scenario calc'!$C$7:$BJ$7,C$35,'Scenario calc'!$C$41:$BJ$41) -> -1015637.3 | D36: =SUMIF('Scenario calc'!$C$7:$BJ$7,D$35,'Scenario calc'!$C$41:$BJ$41) -> -1283745 | E36: =SUMIF('Scenario calc'!$C$7:$BJ$7,E$35,'Scenario calc'!$C$41:$BJ$41) -> -1661885.9 | F36: =SUMIF('Scenario calc'!$C$7:$BJ$7,F$35,'Scenario calc'!$C$41:$BJ$41) -> -2181544.9
A37: Base | B37: =SUMIF('Scenario calc'!$C$118:$BJ$118,B$35,'Scenario calc'!$C$152:$BJ$152) -> 317495.71 | C37: =SUMIF('Scenario calc'!$C$118:$BJ$118,C$35,'Scenario calc'!$C$152:$BJ$152) -> 581743.74 | D37: =SUMIF('Scenario calc'!$C$118:$BJ$118,D$35,'Scenario calc'!$C$152:$BJ$152) -> 877367.82 | E37: =SUMIF('Scenario calc'!$C$118:$BJ$118,E$35,'Scenario calc'!$C$152:$BJ$152) -> 1209727.6 | F37: =SUMIF('Scenario calc'!$C$118:$BJ$118,F$35,'Scenario calc'!$C$152:$BJ$152) -> 1585116.7
A38: High | B38: =SUMIF('Scenario calc'!$C$229:$BJ$229,B$35,'Scenario calc'!$C$263:$BJ$263) -> 2273994.9 | C38: =SUMIF('Scenario calc'!$C$229:$BJ$229,C$35,'Scenario calc'!$C$263:$BJ$263) -> 3538011.2 | D38: =SUMIF('Scenario calc'!$C$229:$BJ$229,D$35,'Scenario calc'!$C$263:$BJ$263) -> 5279916.7 | E38: =SUMIF('Scenario calc'!$C$229:$BJ$229,E$35,'Scenario calc'!$C$263:$BJ$263) -> 7707712.2 | F38: =SUMIF('Scenario calc'!$C$229:$BJ$229,F$35,'Scenario calc'!$C$263:$BJ$263) -> 11124362
A40: Net income by year ($'000)
A41: Scenario | B41: 1 | C41: 2 | D41: 3 | E41: 4 | F41: 5
A42: Low | B42: =SUMIF('Scenario calc'!$C$7:$BJ$7,B$41,'Scenario calc'!$C$50:$BJ$50) -> -919823.26 | C42: =SUMIF('Scenario calc'!$C$7:$BJ$7,C$41,'Scenario calc'!$C$50:$BJ$50) -> -1115732.5 | D42: =SUMIF('Scenario calc'!$C$7:$BJ$7,D$41,'Scenario calc'!$C$50:$BJ$50) -> -1397268.8 | E42: =SUMIF('Scenario calc'!$C$7:$BJ$7,E$41,'Scenario calc'!$C$50:$BJ$50) -> -1788838.3 | F42: =SUMIF('Scenario calc'!$C$7:$BJ$7,F$41,'Scenario calc'!$C$50:$BJ$50) -> -2321925.8
A43: Base | B43: =SUMIF('Scenario calc'!$C$118:$BJ$118,B$41,'Scenario calc'!$C$161:$BJ$161) -> 182376.89 | C43: =SUMIF('Scenario calc'!$C$118:$BJ$118,C$41,'Scenario calc'!$C$161:$BJ$161) -> 380502.32 | D43: =SUMIF('Scenario calc'!$C$118:$BJ$118,D$41,'Scenario calc'!$C$161:$BJ$161) -> 603436.77 | E43: =SUMIF('Scenario calc'!$C$118:$BJ$118,E$41,'Scenario calc'!$C$161:$BJ$161) -> 855392.43 | F43: =SUMIF('Scenario calc'!$C$118:$BJ$118,F$41,'Scenario calc'!$C$161:$BJ$161) -> 1141341.2
A44: High | B44: =SUMIF('Scenario calc'!$C$229:$BJ$229,B$41,'Scenario calc'!$C$272:$BJ$272) -> 1728011.3 | C44: =SUMIF('Scenario calc'!$C$229:$BJ$229,C$41,'Scenario calc'!$C$272:$BJ$272) -> 2715953.6 | D44: =SUMIF('Scenario calc'!$C$229:$BJ$229,D$41,'Scenario calc'!$C$272:$BJ$272) -> 4081450.4 | E44: =SUMIF('Scenario calc'!$C$229:$BJ$229,E$41,'Scenario calc'!$C$272:$BJ$272) -> 5988800.2 | F44: =SUMIF('Scenario calc'!$C$229:$BJ$229,F$41,'Scenario calc'!$C$272:$BJ$272) -> 8677345
A46: Cash at year end by year ($'000)
A47: Scenario | B47: 1 | C47: 2 | D47: 3 | E47: 4 | F47: 5
A48: Low | B48: =INDEX('Scenario calc'!$C$80:$BJ$80,B$47*12) -> 442011.65 | C48: =INDEX('Scenario calc'!$C$80:$BJ$80,C$47*12) -> -910645.13 | D48: =INDEX('Scenario calc'!$C$80:$BJ$80,D$47*12) -> -2527712.9 | E48: =INDEX('Scenario calc'!$C$80:$BJ$80,E$47*12) -> -4519985.3 | F48: =INDEX('Scenario calc'!$C$80:$BJ$80,F$47*12) -> -7029882.6
A49: Base | B49: =INDEX('Scenario calc'!$C$191:$BJ$191,B$47*12) -> 1412273.2 | C49: =INDEX('Scenario calc'!$C$191:$BJ$191,C$47*12) -> 1497071.8 | D49: =INDEX('Scenario calc'!$C$191:$BJ$191,D$47*12) -> 1805009.3 | E49: =INDEX('Scenario calc'!$C$191:$BJ$191,E$47*12) -> 2359982 | F49: =INDEX('Scenario calc'!$C$191:$BJ$191,F$47*12) -> 3189533.4
A50: High | B50: =INDEX('Scenario calc'!$C$302:$BJ$302,B$47*12) -> 2766559.6 | C50: =INDEX('Scenario calc'!$C$302:$BJ$302,C$47*12) -> 5073545.4 | D50: =INDEX('Scenario calc'!$C$302:$BJ$302,D$47*12) -> 8690557.5 | E50: =INDEX('Scenario calc'!$C$302:$BJ$302,E$47*12) -> 14128256 | F50: =INDEX('Scenario calc'!$C$302:$BJ$302,F$47*12) -> 22123099

Sheet Break-even
A1: Startup costs, funding need and break-even | H1: =HYPERLINK("#'Cover'!A1","◂ Contents") -> ◂ Contents
A2: Live for the selected scenario. Periods are counted in months from the start of the plan.
A3: Scenario shown | B3: =CHOOSE(Dashboard!$B$4,"Low","Base","High") -> Base
A5: Startup costs & funding need (up to the lowest cash point)
A6: Lowest cash point (month #) | B6: =MATCH(MIN(Monthly!$C$78:$BJ$78),Monthly!$C$78:$BJ$78,0) -> 13
A7: Capital spending up to the lowest cash point | B7: =SUMPRODUCT(--(Monthly!$C$4:$BJ$4<=$B$6),Monthly!$C$51:$BJ$51) -> 500000
A8: Operating cash burn up to the lowest cash point | B8: =-SUMPRODUCT(--(Monthly!$C$4:$BJ$4<=$B$6),Monthly!$C$72:$BJ$72) -> 139694.92 | D8: Losses and working capital before the business funds itself
A9: Loan repayments up to the lowest cash point | B9: =-SUMPRODUCT(--(Monthly!$C$4:$BJ$4<=$B$6),Monthly!$C$60:$BJ$60) -> 100000
A10: Total uses of funds | B10: =B7+B8+B9 -> 739694.92
A11: Minimum cash buffer to keep | B11: =Inputs!$E$73 -> 720000 | D11: Input on the Inputs sheet
A12: Funding required (uses + buffer) | B12: =B10+B11 -> 1459694.9
A14: Equity raised | B14: =Inputs!$E$58 -> 1500000
A15: Loan drawn | B15: =Inputs!$E$59 -> 500000
A16: Total sources of funds | B16: =B14+B15 -> 2000000
A17: Funding surplus / (shortfall) | B17: =B16-B12 -> 540305.08 | D17: Negative = raise at least this much more
A18: Lowest cash balance in the plan | B18: =MIN(Monthly!$C$78:$BJ$78) -> 1260305.1 | D18: Equals sources minus uses
A20: Break-even timing
A21: First month with positive EBITDA (month #) | B21: =IFERROR(MATCH(1,Monthly!$C$79:$BJ$79,0),"Not within horizon") -> 1
A22: First month with positive net income (month #) | B22: =IFERROR(MATCH(1,Monthly!$C$82:$BJ$82,0),"Not within horizon") -> 1
A23: Cash invested paid back (month #) | B23: =IF(MIN(Monthly!$C$84:$BJ$84)>=0,"No investment to pay back",IFERROR(MATCH(1,Monthly!$C$86:$BJ$86,0),"Not within horizon")) -> 36 | D23: Cumulative operating + investing cash flow back to zero
A25: Annual break-even revenue
A26: Year # | B26: 1 | C26: 2 | D26: 3 | E26: 4 | F26: 5
B27: Year 1 | C27: Year 2 | D27: Year 3 | E27: Year 4 | F27: Year 5
A28: Revenue | B28: =SUMIF(Monthly!$C$5:$BJ$5,B$26,Monthly!$C$25:$BJ$25) -> 5514942.9 | C28: =SUMIF(Monthly!$C$5:$BJ$5,C$26,Monthly!$C$25:$BJ$25) -> 7179087.9 | D28: =SUMIF(Monthly!$C$5:$BJ$5,D$26,Monthly!$C$25:$BJ$25) -> 9149574.9 | E28: =SUMIF(Monthly!$C$5:$BJ$5,E$26,Monthly!$C$25:$BJ$25) -> 11499932 | F28: =SUMIF(Monthly!$C$5:$BJ$5,F$26,Monthly!$C$25:$BJ$25) -> 14322508
A29: Gross profit | B29: =SUMIF(Monthly!$C$5:$BJ$5,B$26,Monthly!$C$27:$BJ$27) -> 3198666.9 | C29: =SUMIF(Monthly!$C$5:$BJ$5,C$26,Monthly!$C$27:$BJ$27) -> 4163871 | D29: =SUMIF(Monthly!$C$5:$BJ$5,D$26,Monthly!$C$27:$BJ$27) -> 5306753.4 | E29: =SUMIF(Monthly!$C$5:$BJ$5,E$26,Monthly!$C$27:$BJ$27) -> 6669960.6 | F29: =SUMIF(Monthly!$C$5:$BJ$5,F$26,Monthly!$C$27:$BJ$27) -> 8307054.9
A30: Gross margin (contribution) | B30: =IF(B28=0,0,B29/B28) -> 0.58 | C30: =IF(C28=0,0,C29/C28) -> 0.58 | D30: =IF(D28=0,0,D29/D28) -> 0.58 | E30: =IF(E28=0,0,E29/E28) -> 0.58 | F30: =IF(F28=0,0,F29/F28) -> 0.58
A31: Operating expenses (treated as fixed) | B31: =-SUMIF(Monthly!$C$5:$BJ$5,B$26,Monthly!$C$38:$BJ$38) -> 2881171.1 | C31: =-SUMIF(Monthly!$C$5:$BJ$5,C$26,Monthly!$C$38:$BJ$38) -> 3582127.2 | D31: =-SUMIF(Monthly!$C$5:$BJ$5,D$26,Monthly!$C$38:$BJ$38) -> 4429385.6 | E31: =-SUMIF(Monthly!$C$5:$BJ$5,E$26,Monthly!$C$38:$BJ$38) -> 5460233 | F31: =-SUMIF(Monthly!$C$5:$BJ$5,F$26,Monthly!$C$38:$BJ$38) -> 6721938.2
A32: Break-even revenue (EBITDA = 0) | B32: =IF(B30>0,B31/B30,"n/a") -> 4967536.5 | C32: =IF(C30>0,C31/C30,"n/a") -> 6176081.4 | D32: =IF(D30>0,D31/D30,"n/a") -> 7636871.7 | E32: =IF(E30>0,E31/E30,"n/a") -> 9414194.8 | F32: =IF(F30>0,F31/F30,"n/a") -> 11589549
A33: Margin of safety (revenue above break-even) | B33: =IF(AND(ISNUMBER(B32),B28>0),(B28-B32)/B28,"n/a") -> 0.099258763 | C33: =IF(AND(ISNUMBER(C32),C28>0),(C28-C32)/C28,"n/a") -> 0.13971224 | D33: =IF(AND(ISNUMBER(D32),D28>0),(D28-D32)/D28,"n/a") -> 0.16533043 | E33: =IF(AND(ISNUMBER(E32),E28>0),(E28-E32)/E28,"n/a") -> 0.18136953 | F33: =IF(AND(ISNUMBER(F32),F28>0),(F28-F32)/F28,"n/a") -> 0.19081572
A35: Simplification: cost of sales is treated as variable and operating expenses as fixed, so break-even revenue = operating expenses ÷ gross margin. In a year with zero or negative gross margin there is no break-even revenue (n/a); the chart line shows 0 there.

Sheet Valuation
A1: Discounted cash flow valuation | H1: =HYPERLINK("#'Cover'!A1","◂ Contents") -> ◂ Contents
A2: Enterprise value at the start of the plan, before the funding raised in period 1. Year-end discounting.
A3: Scenario shown | B3: =CHOOSE(Dashboard!$B$4,"Low","Base","High") -> Base
A5: Assumptions (active scenario, from the Inputs sheet)
A6: Discount rate (WACC) | B6: =Inputs!$E$76 -> 0.16
A7: Terminal growth rate | B7: =Inputs!$E$77 -> 0.02
A8: Exit multiple (EV ÷ final-year EBITDA) | B8: =Inputs!$E$78 -> 5.5
A9: Tax rate (for the interest tax shield) | B9: =Inputs!$E$70 -> 0.21
A10: Sensitivity step: WACC | B10: =Inputs!$E$79 -> 0.01
A11: Sensitivity step: terminal growth | B11: =Inputs!$E$80 -> 0.005
A13: Free cash flow by year
A14: Year # | B14: 1 | C14: 2 | D14: 3 | E14: 4 | F14: 5
B15: Year 1 | C15: Year 2 | D15: Year 3 | E15: Year 4 | F15: Year 5
A16: EBITDA | B16: =SUMIF(Monthly!$C$5:$BJ$5,B$14,Monthly!$C$39:$BJ$39) -> 317495.71 | C16: =SUMIF(Monthly!$C$5:$BJ$5,C$14,Monthly!$C$39:$BJ$39) -> 581743.74 | D16: =SUMIF(Monthly!$C$5:$BJ$5,D$14,Monthly!$C$39:$BJ$39) -> 877367.82 | E16: =SUMIF(Monthly!$C$5:$BJ$5,E$14,Monthly!$C$39:$BJ$39) -> 1209727.6 | F16: =SUMIF(Monthly!$C$5:$BJ$5,F$14,Monthly!$C$39:$BJ$39) -> 1585116.7
A17: Unlevered free cash flow | B17: =SUMIF(Monthly!$C$5:$BJ$5,B$14,Monthly!$C$87:$BJ$87) -> -467115.43 | C17: =SUMIF(Monthly!$C$5:$BJ$5,C$14,Monthly!$C$87:$BJ$87) -> 207445.34 | D17: =SUMIF(Monthly!$C$5:$BJ$5,D$14,Monthly!$C$87:$BJ$87) -> 424264.1 | E17: =SUMIF(Monthly!$C$5:$BJ$5,E$14,Monthly!$C$87:$BJ$87) -> 664979.44 | F17: =SUMIF(Monthly!$C$5:$BJ$5,F$14,Monthly!$C$87:$BJ$87) -> 933237.98
A18: Discount factor | B18: =1/(1+Inputs!$E$76)^B$14 -> 0.86206897 | C18: =1/(1+Inputs!$E$76)^C$14 -> 0.7431629 | D18: =1/(1+Inputs!$E$76)^D$14 -> 0.64065767 | E18: =1/(1+Inputs!$E$76)^E$14 -> 0.5522911 | F18: =1/(1+Inputs!$E$76)^F$14 -> 0.47611302
A19: Present value of free cash flow | B19: =B17*B18 -> -402685.72 | C19: =C17*C18 -> 154165.68 | D19: =D17*D18 -> 271808.05 | E19: =E17*E18 -> 367262.22 | F19: =F17*F18 -> 444326.75
A21: Enterprise value
B22: Perpetual growth | C22: Exit multiple
A23: Present value of the plan's free cash flows | B23: =SUM($B$19:$F$19) -> 834876.98 | C23: =B23 -> 834876.98
A24: Final-year free cash flow | final-year EBITDA | B24: =$F$17 -> 933237.98 | C24: =$F$16 -> 1585116.7
A25: Terminal value at the end of year 5 | B25: =IF($B$6>$B$7,B24*(1+$B$7)/($B$6-$B$7),0) -> 6799305.3 | C25: =C24*$B$8 -> 8718141.7
A26: Present value of the terminal value | B26: =B25/(1+$B$6)^$F$14 -> 3237237.8 | C26: =C25/(1+$B$6)^$F$14 -> 4150820.7
A27: Enterprise value | B27: =B23+B26 -> 4072114.7 | C27: =C23+C26 -> 4985697.7
A28: Terminal value share of enterprise value | B28: =IF(B27<>0,B26/B27,0) -> 0.79497705 | C28: =IF(C27<>0,C26/C27,0) -> 0.83254561
A29: Cross-check: implied exit multiple | implied perpetual growth | B29: =IF(C24>0,B25/C24,"n/a") -> 4.2894668 | C29: =IF(C25+B24<>0,(C25*$B$6-B24)/(C25+B24),"n/a") -> 0.047834061
A30: Enterprise value — average of the two methods | B30: =AVERAGE(B27,C27) -> 4528906.2
A32: Sensitivity: enterprise value (perpetual growth) by WACC and terminal growth
A33: WACC ↓ · terminal growth → | B33: =$B$7+(-2)*$B$11 -> 0.01 | C33: =$B$7+(-1)*$B$11 -> 0.015 | D33: =$B$7+(0)*$B$11 -> 0.02 | E33: =$B$7+(1)*$B$11 -> 0.025 | F33: =$B$7+(2)*$B$11 -> 0.03
A34: =$B$6+(-2)*$B$10 -> 0.14 | B34: =IF($A34>B$33,SUMPRODUCT($B$17:$F$17/(1+$A34)^$B$14:$F$14)+$F$17*(1+B$33)/($A34-B$33)/(1+$A34)^$F$14,"n/a") -> 4680358 | C34: =IF($A34>C$33,SUMPRODUCT($B$17:$F$17/(1+$A34)^$B$14:$F$14)+$F$17*(1+C$33)/($A34-C$33)/(1+$A34)^$F$14,"n/a") -> 4850373.9 | D34: =IF($A34>D$33,SUMPRODUCT($B$17:$F$17/(1+$A34)^$B$14:$F$14)+$F$17*(1+D$33)/($A34-D$33)/(1+$A34)^$F$14,"n/a") -> 5034557.8 | E34: =IF($A34>E$33,SUMPRODUCT($B$17:$F$17/(1+$A34)^$B$14:$F$14)+$F$17*(1+E$33)/($A34-E$33)/(1+$A34)^$F$14,"n/a") -> 5234757.8 | F34: =IF($A34>F$33,SUMPRODUCT($B$17:$F$17/(1+$A34)^$B$14:$F$14)+$F$17*(1+F$33)/($A34-F$33)/(1+$A34)^$F$14,"n/a") -> 5453157.7
A35: =$B$6+(-1)*$B$10 -> 0.15 | B35: =IF($A35>B$33,SUMPRODUCT($B$17:$F$17/(1+$A35)^$B$14:$F$14)+$F$17*(1+B$33)/($A35-B$33)/(1+$A35)^$F$14,"n/a") -> 4221134.7 | C35: =IF($A35>C$33,SUMPRODUCT($B$17:$F$17/(1+$A35)^$B$14:$F$14)+$F$17*(1+C$33)/($A35-C$33)/(1+$A35)^$F$14,"n/a") -> 4362293.9 | D35: =IF($A35>D$33,SUMPRODUCT($B$17:$F$17/(1+$A35)^$B$14:$F$14)+$F$17*(1+D$33)/($A35-D$33)/(1+$A35)^$F$14,"n/a") -> 4514311.6 | E35: =IF($A35>E$33,SUMPRODUCT($B$17:$F$17/(1+$A35)^$B$14:$F$14)+$F$17*(1+E$33)/($A35-E$33)/(1+$A35)^$F$14,"n/a") -> 4678490.6 | F35: =IF($A35>F$33,SUMPRODUCT($B$17:$F$17/(1+$A35)^$B$14:$F$14)+$F$17*(1+F$33)/($A35-F$33)/(1+$A35)^$F$14,"n/a") -> 4856351.2
A36: =$B$6+(0)*$B$10 -> 0.16 | B36: =IF($A36>B$33,SUMPRODUCT($B$17:$F$17/(1+$A36)^$B$14:$F$14)+$F$17*(1+B$33)/($A36-B$33)/(1+$A36)^$F$14,"n/a") -> 3826677.1 | C36: =IF($A36>C$33,SUMPRODUCT($B$17:$F$17/(1+$A36)^$B$14:$F$14)+$F$17*(1+C$33)/($A36-C$33)/(1+$A36)^$F$14,"n/a") -> 3945164.2 | D36: =IF($A36>D$33,SUMPRODUCT($B$17:$F$17/(1+$A36)^$B$14:$F$14)+$F$17*(1+D$33)/($A36-D$33)/(1+$A36)^$F$14,"n/a") -> 4072114.7 | E36: =IF($A36>E$33,SUMPRODUCT($B$17:$F$17/(1+$A36)^$B$14:$F$14)+$F$17*(1+E$33)/($A36-E$33)/(1+$A36)^$F$14,"n/a") -> 4208469 | F36: =IF($A36>F$33,SUMPRODUCT($B$17:$F$17/(1+$A36)^$B$14:$F$14)+$F$17*(1+F$33)/($A36-F$33)/(1+$A36)^$F$14,"n/a") -> 4355312
A37: =$B$6+(1)*$B$10 -> 0.17 | B37: =IF($A37>B$33,SUMPRODUCT($B$17:$F$17/(1+$A37)^$B$14:$F$14)+$F$17*(1+B$33)/($A37-B$33)/(1+$A37)^$F$14,"n/a") -> 3484702.6 | C37: =IF($A37>C$33,SUMPRODUCT($B$17:$F$17/(1+$A37)^$B$14:$F$14)+$F$17*(1+C$33)/($A37-C$33)/(1+$A37)^$F$14,"n/a") -> 3585110.3 | D37: =IF($A37>D$33,SUMPRODUCT($B$17:$F$17/(1+$A37)^$B$14:$F$14)+$F$17*(1+D$33)/($A37-D$33)/(1+$A37)^$F$14,"n/a") -> 3692212 | E37: =IF($A37>E$33,SUMPRODUCT($B$17:$F$17/(1+$A37)^$B$14:$F$14)+$F$17*(1+E$33)/($A37-E$33)/(1+$A37)^$F$14,"n/a") -> 3806699.9 | F37: =IF($A37>F$33,SUMPRODUCT($B$17:$F$17/(1+$A37)^$B$14:$F$14)+$F$17*(1+F$33)/($A37-F$33)/(1+$A37)^$F$14,"n/a") -> 3929365.5
A38: =$B$6+(2)*$B$10 -> 0.18 | B38: =IF($A38>B$33,SUMPRODUCT($B$17:$F$17/(1+$A38)^$B$14:$F$14)+$F$17*(1+B$33)/($A38-B$33)/(1+$A38)^$F$14,"n/a") -> 3185825.5 | C38: =IF($A38>C$33,SUMPRODUCT($B$17:$F$17/(1+$A38)^$B$14:$F$14)+$F$17*(1+C$33)/($A38-C$33)/(1+$A38)^$F$14,"n/a") -> 3271628.3 | D38: =IF($A38>D$33,SUMPRODUCT($B$17:$F$17/(1+$A38)^$B$14:$F$14)+$F$17*(1+D$33)/($A38-D$33)/(1+$A38)^$F$14,"n/a") -> 3362793.8 | E38: =IF($A38>E$33,SUMPRODUCT($B$17:$F$17/(1+$A38)^$B$14:$F$14)+$F$17*(1+E$33)/($A38-E$33)/(1+$A38)^$F$14,"n/a") -> 3459840.9 | F38: =IF($A38>F$33,SUMPRODUCT($B$17:$F$17/(1+$A38)^$B$14:$F$14)+$F$17*(1+F$33)/($A38-F$33)/(1+$A38)^$F$14,"n/a") -> 3563357.8
A40: Free cash flow = operating cash flow + interest × (1 − tax rate) − capital spending. Cells marked n/a: WACC not above growth.

Sheet Sources & Uses
A1: Sources and uses of funds | E1: =HYPERLINK("#'Cover'!A1","◂ Contents") -> ◂ Contents
A2: Live for the selected scenario. Where the money comes from and where it goes in the period set below.
A3: Scenario shown | B3: =CHOOSE(Dashboard!$B$4,"Low","Base","High") -> Base
A5: Funding structure ($'000) — raised at the start of the plan
B6: Amount | C6: Share
A7: Equity | B7: =Inputs!$E$58 -> 1500000 | C7: =IF($B$9=0,0,B7/$B$9) -> 0.75
A8: Debt (loan) | B8: =Inputs!$E$59 -> 500000 | C8: =IF($B$9=0,0,B8/$B$9) -> 0.25
A9: Total funding | B9: =B7+B8 -> 2000000 | C9: =IF(B9=0,0,1) -> 1
A10: Gearing (debt ÷ equity) | B10: =IF(B7<=0,IF(B8>0,"n/a",0),B8/B7) -> 0.33333333 | D10: n/a: debt without positive equity
A11: Funding required by the plan (Break-even sheet) | B11: ='Break-even'!B12 -> 1459694.9
A12: Funding surplus / (shortfall) | B12: ='Break-even'!B17 -> 540305.08
A14: ="Sources and uses of cash in the first "&$B$16&IF($B$16=1," month"," months")&" ($'000)" -> Sources and uses of cash in the first 12 months ($'000)
A15: Period covered (months from the start) | B15: 12 | D15: 1 to 60 (capped)
A16: Months used | B16: =MIN(60,MAX(1,ROUND(B15,0))) -> 12
A17: Sources | B17: Amount | C17: Share
A18: Equity raised | B18: =SUMPRODUCT(--(Monthly!$C$4:$BJ$4<=$B$16),Monthly!$C$74:$BJ$74) -> 1500000 | C18: =IF($B$21=0,0,B18/$B$21) -> 0.75
A19: Loan drawdowns | B19: =SUMPRODUCT(--(Monthly!$C$4:$BJ$4<=$B$16),Monthly!$C$59:$BJ$59) -> 500000 | C19: =IF($B$21=0,0,B19/$B$21) -> 0.25
A20: Cash generated by operations | B20: =MAX(0,SUMPRODUCT(--(Monthly!$C$4:$BJ$4<=$B$16),Monthly!$C$72:$BJ$72)) -> 0 | C20: =IF($B$21=0,0,B20/$B$21) -> 0
A21: Total sources | B21: =SUM(B18:B20) -> 2000000 | C21: =IF(B21=0,0,1) -> 1
A23: Uses | B23: Amount | C23: Share
A24: Cash used by operations | B24: =MAX(0,-SUMPRODUCT(--(Monthly!$C$4:$BJ$4<=$B$16),Monthly!$C$72:$BJ$72)) -> 146060.15 | C24: =IF($B$28=0,0,B24/$B$28) -> 0.073030077
A25: Capital spending | B25: =-SUMPRODUCT(--(Monthly!$C$4:$BJ$4<=$B$16),Monthly!$C$73:$BJ$73) -> 350000 | C25: =IF($B$28=0,0,B25/$B$28) -> 0.175
A26: Loan repayments | B26: =-SUMPRODUCT(--(Monthly!$C$4:$BJ$4<=$B$16),Monthly!$C$60:$BJ$60) -> 91666.667 | C26: =IF($B$28=0,0,B26/$B$28) -> 0.045833333
A27: Cash at the end of the period | B27: =INDEX(Monthly!$C$78:$BJ$78,$B$16) -> 1412273.2 | C27: =IF($B$28=0,0,B27/$B$28) -> 0.70613659
A28: Total uses | B28: =SUM(B24:B27) -> 2000000 | C28: =IF(B28=0,0,1) -> 1
A29: Sources − uses (must be 0; opening cash is 0) | B29: =B21-B28 -> 0

Sheet KPIs
A1: KPIs & ratios | I1: =HYPERLINK("#'Cover'!A1","◂ Contents") -> ◂ Contents
A2: Retail / e-commerce financial model (growing) — industry metrics and financial ratios for the active scenario
A4: Financial ratios
B5: 1 | C5: 2 | D5: 3 | E5: 4 | F5: 5 | G5: Target
A6: Revenue growth | B6: =IF(N('P&L'!A5)<=0,"n/a",'P&L'!B5/'P&L'!A5-1) -> n/a | C6: =IF(N('P&L'!B5)<=0,"n/a",'P&L'!C5/'P&L'!B5-1) -> 0.30175199 | D6: =IF(N('P&L'!C5)<=0,"n/a",'P&L'!D5/'P&L'!C5-1) -> 0.27447596 | E6: =IF(N('P&L'!D5)<=0,"n/a",'P&L'!E5/'P&L'!D5-1) -> 0.25688158 | F6: =IF(N('P&L'!E5)<=0,"n/a",'P&L'!F5/'P&L'!E5-1) -> 0.24544287
A7: Gross margin | B7: =IF('P&L'!B5<=0,"n/a",'P&L'!B7/'P&L'!B5) -> 0.58 | C7: =IF('P&L'!C5<=0,"n/a",'P&L'!C7/'P&L'!C5) -> 0.58 | D7: =IF('P&L'!D5<=0,"n/a",'P&L'!D7/'P&L'!D5) -> 0.58 | E7: =IF('P&L'!E5<=0,"n/a",'P&L'!E7/'P&L'!E5) -> 0.58 | F7: =IF('P&L'!F5<=0,"n/a",'P&L'!F7/'P&L'!F5) -> 0.58
A8: EBITDA margin | B8: =IF('P&L'!B5<=0,"n/a",'P&L'!B18/'P&L'!B5) -> 0.057570082 | C8: =IF('P&L'!C5<=0,"n/a",'P&L'!C18/'P&L'!C5) -> 0.0810331 | D8: =IF('P&L'!D5<=0,"n/a",'P&L'!D18/'P&L'!D5) -> 0.095891649 | E8: =IF('P&L'!E5<=0,"n/a",'P&L'!E18/'P&L'!E5) -> 0.10519433 | F8: =IF('P&L'!F5<=0,"n/a",'P&L'!F18/'P&L'!F5) -> 0.11067312
A9: Net margin | B9: =IF('P&L'!B5<=0,"n/a",'P&L'!B25/'P&L'!B5) -> 0.033069589 | C9: =IF('P&L'!C5<=0,"n/a",'P&L'!C25/'P&L'!C5) -> 0.053001485 | D9: =IF('P&L'!D5<=0,"n/a",'P&L'!D25/'P&L'!D5) -> 0.065952438 | E9: =IF('P&L'!E5<=0,"n/a",'P&L'!E25/'P&L'!E5) -> 0.07438239 | F9: =IF('P&L'!F5<=0,"n/a",'P&L'!F25/'P&L'!F5) -> 0.07968864
A10: Payroll, % of revenue | B10: =IF('P&L'!B5<=0,"n/a",-SUMIF(Headcount!$C$5:$BJ$5,B$5,Headcount!$C$19:$BJ$19)/'P&L'!B5) -> 0.22812566 | C10: =IF('P&L'!C5<=0,"n/a",-SUMIF(Headcount!$C$5:$BJ$5,C$5,Headcount!$C$19:$BJ$19)/'P&L'!C5) -> 0.21988631 | D10: =IF('P&L'!D5<=0,"n/a",-SUMIF(Headcount!$C$5:$BJ$5,D$5,Headcount!$C$19:$BJ$19)/'P&L'!D5) -> 0.21690763 | E10: =IF('P&L'!E5<=0,"n/a",-SUMIF(Headcount!$C$5:$BJ$5,E$5,Headcount!$C$19:$BJ$19)/'P&L'!E5) -> 0.2174006 | F10: =IF('P&L'!F5<=0,"n/a",-SUMIF(Headcount!$C$5:$BJ$5,F$5,Headcount!$C$19:$BJ$19)/'P&L'!F5) -> 0.22034489
A11: Marketing, % of revenue | B11: =IF('P&L'!B5<=0,"n/a",-'P&L'!B11/'P&L'!B5) -> 0.10879532 | C11: =IF('P&L'!C5<=0,"n/a",-'P&L'!C11/'P&L'!C5) -> 0.10029129 | D11: =IF('P&L'!D5<=0,"n/a",-'P&L'!D11/'P&L'!D5) -> 0.094430617 | E11: =IF('P&L'!E5<=0,"n/a",-'P&L'!E11/'P&L'!E5) -> 0.090157054 | F11: =IF('P&L'!F5<=0,"n/a",-'P&L'!F11/'P&L'!F5) -> 0.086867465
A12: Operating expenses, % of revenue | B12: =IF('P&L'!B5<=0,"n/a",-'P&L'!B17/'P&L'!B5) -> 0.52242992 | C12: =IF('P&L'!C5<=0,"n/a",-'P&L'!C17/'P&L'!C5) -> 0.4989669 | D12: =IF('P&L'!D5<=0,"n/a",-'P&L'!D17/'P&L'!D5) -> 0.48410835 | E12: =IF('P&L'!E5<=0,"n/a",-'P&L'!E17/'P&L'!E5) -> 0.47480567 | F12: =IF('P&L'!F5<=0,"n/a",-'P&L'!F17/'P&L'!F5) -> 0.46932688
A13: Current ratio (current assets ÷ current liabilities) | B13: =IF(('Balance Sheet'!B12-'Balance Sheet'!B11)<=0,"n/a",('Balance Sheet'!B5+'Balance Sheet'!B6+'Balance Sheet'!B7)/('Balance Sheet'!B12-'Balance Sheet'!B11)) -> 8.848875 | C13: =IF(('Balance Sheet'!C12-'Balance Sheet'!C11)<=0,"n/a",('Balance Sheet'!C5+'Balance Sheet'!C6+'Balance Sheet'!C7)/('Balance Sheet'!C12-'Balance Sheet'!C11)) -> 7.6696103 | D13: =IF(('Balance Sheet'!D12-'Balance Sheet'!D11)<=0,"n/a",('Balance Sheet'!D5+'Balance Sheet'!D6+'Balance Sheet'!D7)/('Balance Sheet'!D12-'Balance Sheet'!D11)) -> 7.3817175 | E13: =IF(('Balance Sheet'!E12-'Balance Sheet'!E11)<=0,"n/a",('Balance Sheet'!E5+'Balance Sheet'!E6+'Balance Sheet'!E7)/('Balance Sheet'!E12-'Balance Sheet'!E11)) -> 7.560334 | F13: =IF(('Balance Sheet'!F12-'Balance Sheet'!F11)<=0,"n/a",('Balance Sheet'!F5+'Balance Sheet'!F6+'Balance Sheet'!F7)/('Balance Sheet'!F12-'Balance Sheet'!F11)) -> 7.9698311
A14: Debt ÷ equity (loan ÷ total equity) | B14: =IF('Balance Sheet'!B15<=0,"n/a",'Balance Sheet'!B11/'Balance Sheet'!B15) -> 0.24271216 | C14: =IF('Balance Sheet'!C15<=0,"n/a",'Balance Sheet'!C11/'Balance Sheet'!C15) -> 0.14946747 | D14: =IF('Balance Sheet'!D15<=0,"n/a",'Balance Sheet'!D11/'Balance Sheet'!D15) -> 0.078135275 | E14: =IF('Balance Sheet'!E15<=0,"n/a",'Balance Sheet'!E11/'Balance Sheet'!E15) -> 0.030761585 | F14: =IF('Balance Sheet'!F15<=0,"n/a",'Balance Sheet'!F11/'Balance Sheet'!F15) -> 0.0017870994
A15: Return on assets (net income ÷ year-end assets) | B15: =IF('Balance Sheet'!B9<=0,"n/a",'P&L'!B25/'Balance Sheet'!B9) -> 0.078649414 | C15: =IF('Balance Sheet'!C9<=0,"n/a",'P&L'!C25/'Balance Sheet'!C9) -> 0.14251147 | D15: =IF('Balance Sheet'!D9<=0,"n/a",'P&L'!D25/'Balance Sheet'!D9) -> 0.18528378 | E15: =IF('Balance Sheet'!E9<=0,"n/a",'P&L'!E25/'Balance Sheet'!E9) -> 0.20804808 | F15: =IF('Balance Sheet'!F9<=0,"n/a",'P&L'!F25/'Balance Sheet'!F9) -> 0.21649425
A16: Return on equity (net income ÷ year-end equity) | B16: =IF('Balance Sheet'!B15<=0,"n/a",'P&L'!B25/'Balance Sheet'!B15) -> 0.1084043 | C16: =IF('Balance Sheet'!C15<=0,"n/a",'P&L'!C25/'Balance Sheet'!C15) -> 0.18445206 | D16: =IF('Balance Sheet'!D15<=0,"n/a",'P&L'!D25/'Balance Sheet'!D15) -> 0.22631855 | E16: =IF('Balance Sheet'!E15<=0,"n/a",'P&L'!E25/'Balance Sheet'!E15) -> 0.24289133 | F16: =IF('Balance Sheet'!F15<=0,"n/a",'P&L'!F25/'Balance Sheet'!F15) -> 0.24476283
A18: DuPont analysis — return on equity = net margin × asset turnover × equity multiplier
B19: 1 | C19: 2 | D19: 3 | E19: 4 | F19: 5
A20: Net margin | B20: =IF('P&L'!B5<=0,"n/a",'P&L'!B25/'P&L'!B5) -> 0.033069589 | C20: =IF('P&L'!C5<=0,"n/a",'P&L'!C25/'P&L'!C5) -> 0.053001485 | D20: =IF('P&L'!D5<=0,"n/a",'P&L'!D25/'P&L'!D5) -> 0.065952438 | E20: =IF('P&L'!E5<=0,"n/a",'P&L'!E25/'P&L'!E5) -> 0.07438239 | F20: =IF('P&L'!F5<=0,"n/a",'P&L'!F25/'P&L'!F5) -> 0.07968864
A21: × Asset turnover (revenue ÷ assets) | B21: =IF('Balance Sheet'!B9<=0,"n/a",'P&L'!B5/'Balance Sheet'!B9) -> 2.3783003 | C21: =IF('Balance Sheet'!C9<=0,"n/a",'P&L'!C5/'Balance Sheet'!C9) -> 2.6888203 | D21: =IF('Balance Sheet'!D9<=0,"n/a",'P&L'!D5/'Balance Sheet'!D9) -> 2.8093545 | E21: =IF('Balance Sheet'!E9<=0,"n/a",'P&L'!E5/'Balance Sheet'!E9) -> 2.7970073 | F21: =IF('Balance Sheet'!F9<=0,"n/a",'P&L'!F5/'Balance Sheet'!F9) -> 2.7167518
A22: × Equity multiplier (assets ÷ equity) | B22: =IF('Balance Sheet'!B15<=0,"n/a",'Balance Sheet'!B9/'Balance Sheet'!B15) -> 1.3783231 | C22: =IF('Balance Sheet'!C15<=0,"n/a",'Balance Sheet'!C9/'Balance Sheet'!C15) -> 1.2942962 | D22: =IF('Balance Sheet'!D15<=0,"n/a",'Balance Sheet'!D9/'Balance Sheet'!D15) -> 1.2214699 | E22: =IF('Balance Sheet'!E15<=0,"n/a",'Balance Sheet'!E9/'Balance Sheet'!E15) -> 1.1674769 | F22: =IF('Balance Sheet'!F15<=0,"n/a",'Balance Sheet'!F9/'Balance Sheet'!F15) -> 1.1305743
A23: Return on equity (product of the three) | B23: =IF(AND(ISNUMBER(B20),ISNUMBER(B21),ISNUMBER(B22)),B20*B21*B22,"n/a") -> 0.1084043 | C23: =IF(AND(ISNUMBER(C20),ISNUMBER(C21),ISNUMBER(C22)),C20*C21*C22,"n/a") -> 0.18445206 | D23: =IF(AND(ISNUMBER(D20),ISNUMBER(D21),ISNUMBER(D22)),D20*D21*D22,"n/a") -> 0.22631855 | E23: =IF(AND(ISNUMBER(E20),ISNUMBER(E21),ISNUMBER(E22)),E20*E21*E22,"n/a") -> 0.24289133 | F23: =IF(AND(ISNUMBER(F20),ISNUMBER(F21),ISNUMBER(F22)),F20*F21*F22,"n/a") -> 0.24476283
A24: Check: product − return on equity (must be 0) | B24: =IF(AND(ISNUMBER(B23),ISNUMBER(B16)),B23-B16,IF(ISNUMBER(B23),1,IF(AND(ISNUMBER(B16),ISNUMBER(B20),ISNUMBER(B21)),1,0))) -> 0 | C24: =IF(AND(ISNUMBER(C23),ISNUMBER(C16)),C23-C16,IF(ISNUMBER(C23),1,IF(AND(ISNUMBER(C16),ISNUMBER(C20),ISNUMBER(C21)),1,0))) -> 0 | D24: =IF(AND(ISNUMBER(D23),ISNUMBER(D16)),D23-D16,IF(ISNUMBER(D23),1,IF(AND(ISNUMBER(D16),ISNUMBER(D20),ISNUMBER(D21)),1,0))) -> 0 | E24: =IF(AND(ISNUMBER(E23),ISNUMBER(E16)),E23-E16,IF(ISNUMBER(E23),1,IF(AND(ISNUMBER(E16),ISNUMBER(E20),ISNUMBER(E21)),1,0))) -> 0 | F24: =IF(AND(ISNUMBER(F23),ISNUMBER(F16)),F23-F16,IF(ISNUMBER(F23),1,IF(AND(ISNUMBER(F16),ISNUMBER(F20),ISNUMBER(F21)),1,0))) -> 0
A26: Retail metrics ($'000; per-unit rows in $)
A27: Year # | B27: 1 | C27: 2 | D27: 3 | E27: 4 | F27: 5
B28: Year 1 | C28: Year 2 | D28: Year 3 | E28: Year 4 | F28: Year 5 | G28: Target
A29: Website visits (non-paid) | B29: =SUMIF(Monthly!$C$5:$BJ$5,B$27,Monthly!$C$9:$BJ$9) -> 960000 | C29: =SUMIF(Monthly!$C$5:$BJ$5,C$27,Monthly!$C$9:$BJ$9) -> 1200000 | D29: =SUMIF(Monthly!$C$5:$BJ$5,D$27,Monthly!$C$9:$BJ$9) -> 1500000 | E29: =SUMIF(Monthly!$C$5:$BJ$5,E$27,Monthly!$C$9:$BJ$9) -> 1875000 | F29: =SUMIF(Monthly!$C$5:$BJ$5,F$27,Monthly!$C$9:$BJ$9) -> 2343750
A30: Online orders | B30: =SUMIF(Monthly!$C$5:$BJ$5,B$27,Monthly!$C$14:$BJ$14) -> 66702.857 | C30: =SUMIF(Monthly!$C$5:$BJ$5,C$27,Monthly!$C$14:$BJ$14) -> 81771.429 | D30: =SUMIF(Monthly!$C$5:$BJ$5,D$27,Monthly!$C$14:$BJ$14) -> 100285.71 | E30: =SUMIF(Monthly!$C$5:$BJ$5,E$27,Monthly!$C$14:$BJ$14) -> 123042.86 | F30: =SUMIF(Monthly!$C$5:$BJ$5,F$27,Monthly!$C$14:$BJ$14) -> 151026.43
A31: Repeat orders | B31: =SUMIF(Monthly!$C$5:$BJ$5,B$27,Monthly!$C$13:$BJ$13) -> 22234.286 | C31: =SUMIF(Monthly!$C$5:$BJ$5,C$27,Monthly!$C$13:$BJ$13) -> 27257.143 | D31: =SUMIF(Monthly!$C$5:$BJ$5,D$27,Monthly!$C$13:$BJ$13) -> 33428.571 | E31: =SUMIF(Monthly!$C$5:$BJ$5,E$27,Monthly!$C$13:$BJ$13) -> 41014.286 | F31: =SUMIF(Monthly!$C$5:$BJ$5,F$27,Monthly!$C$13:$BJ$13) -> 50342.143
A32: Repeat orders, % of online orders | B32: =IF(B30=0,0,B31/B30) -> 0.33333333 | C32: =IF(C30=0,0,C31/C30) -> 0.33333333 | D32: =IF(D30=0,0,D31/D30) -> 0.33333333 | E32: =IF(E30=0,0,E31/E30) -> 0.33333333 | F32: =IF(F30=0,0,F31/F30) -> 0.33333333
A33: Online gross sales | B33: =SUMIF(Monthly!$C$5:$BJ$5,B$27,Monthly!$C$16:$BJ$16) -> 5002714.3 | C33: =SUMIF(Monthly!$C$5:$BJ$5,C$27,Monthly!$C$16:$BJ$16) -> 6255514.3 | D33: =SUMIF(Monthly!$C$5:$BJ$5,D$27,Monthly!$C$16:$BJ$16) -> 7825294.3 | E33: =SUMIF(Monthly!$C$5:$BJ$5,E$27,Monthly!$C$16:$BJ$16) -> 9793054.8 | F33: =SUMIF(Monthly!$C$5:$BJ$5,F$27,Monthly!$C$16:$BJ$16) -> 12260690
A34: Average order value ($) | B34: =IF(B30=0,0,B33/B30) -> 75 | C34: =IF(C30=0,0,C33/C30) -> 76.5 | D34: =IF(D30=0,0,D33/D30) -> 78.03 | E34: =IF(E30=0,0,E33/E30) -> 79.5906 | F34: =IF(F30=0,0,F33/F30) -> 81.182412
A35: Paid ads spend | B35: =-SUMIF(Monthly!$C$5:$BJ$5,B$27,Monthly!$C$32:$BJ$32) -> 600000 | C35: =-SUMIF(Monthly!$C$5:$BJ$5,C$27,Monthly!$C$32:$BJ$32) -> 720000 | D35: =-SUMIF(Monthly!$C$5:$BJ$5,D$27,Monthly!$C$32:$BJ$32) -> 864000 | E35: =-SUMIF(Monthly!$C$5:$BJ$5,E$27,Monthly!$C$32:$BJ$32) -> 1036800 | F35: =-SUMIF(Monthly!$C$5:$BJ$5,F$27,Monthly!$C$32:$BJ$32) -> 1244160
A36: Paid ads, % of online gross sales | B36: =IF(B33=0,0,B35/B33) -> 0.11993489 | C36: =IF(C33=0,0,C35/C33) -> 0.11509845 | D36: =IF(D33=0,0,D35/D33) -> 0.11041118 | E36: =IF(E33=0,0,E35/E33) -> 0.10587095 | F36: =IF(F33=0,0,F35/F33) -> 0.10147553
A37: Stores open (year end) | B37: =INDEX(Monthly!$C$19:$BJ$19,B$27*12) -> 2 | C37: =INDEX(Monthly!$C$19:$BJ$19,C$27*12) -> 3 | D37: =INDEX(Monthly!$C$19:$BJ$19,D$27*12) -> 4 | E37: =INDEX(Monthly!$C$19:$BJ$19,E$27*12) -> 5 | F37: =INDEX(Monthly!$C$19:$BJ$19,F$27*12) -> 6
A38: Store gross sales | B38: =SUMIF(Monthly!$C$5:$BJ$5,B$27,Monthly!$C$20:$BJ$20) -> 1125000 | C38: =SUMIF(Monthly!$C$5:$BJ$5,C$27,Monthly!$C$20:$BJ$20) -> 1721250 | D38: =SUMIF(Monthly!$C$5:$BJ$5,D$27,Monthly!$C$20:$BJ$20) -> 2340900 | E38: =SUMIF(Monthly!$C$5:$BJ$5,E$27,Monthly!$C$20:$BJ$20) -> 2984647.5 | F38: =SUMIF(Monthly!$C$5:$BJ$5,F$27,Monthly!$C$20:$BJ$20) -> 3653208.5
A39: Net sales | B39: =SUMIF(Monthly!$C$5:$BJ$5,B$27,Monthly!$C$25:$BJ$25) -> 5514942.9 | C39: =SUMIF(Monthly!$C$5:$BJ$5,C$27,Monthly!$C$25:$BJ$25) -> 7179087.9 | D39: =SUMIF(Monthly!$C$5:$BJ$5,D$27,Monthly!$C$25:$BJ$25) -> 9149574.9 | E39: =SUMIF(Monthly!$C$5:$BJ$5,E$27,Monthly!$C$25:$BJ$25) -> 11499932 | F39: =SUMIF(Monthly!$C$5:$BJ$5,F$27,Monthly!$C$25:$BJ$25) -> 14322508
A40: Gross profit (after product cost) | B40: =SUMIF(Monthly!$C$5:$BJ$5,B$27,Monthly!$C$27:$BJ$27) -> 3198666.9 | C40: =SUMIF(Monthly!$C$5:$BJ$5,C$27,Monthly!$C$27:$BJ$27) -> 4163871 | D40: =SUMIF(Monthly!$C$5:$BJ$5,D$27,Monthly!$C$27:$BJ$27) -> 5306753.4 | E40: =SUMIF(Monthly!$C$5:$BJ$5,E$27,Monthly!$C$27:$BJ$27) -> 6669960.6 | F40: =SUMIF(Monthly!$C$5:$BJ$5,F$27,Monthly!$C$27:$BJ$27) -> 8307054.9
A41: Gross margin | B41: =IF(B39=0,0,B40/B39) -> 0.58 | C41: =IF(C39=0,0,C40/C39) -> 0.58 | D41: =IF(D39=0,0,D40/D39) -> 0.58 | E41: =IF(E39=0,0,E40/E39) -> 0.58 | F41: =IF(F39=0,0,F40/F39) -> 0.58
A42: Product cost | B42: =-SUMIF(Monthly!$C$5:$BJ$5,B$27,Monthly!$C$26:$BJ$26) -> 2316276 | C42: =-SUMIF(Monthly!$C$5:$BJ$5,C$27,Monthly!$C$26:$BJ$26) -> 3015216.9 | D42: =-SUMIF(Monthly!$C$5:$BJ$5,D$27,Monthly!$C$26:$BJ$26) -> 3842821.4 | E42: =-SUMIF(Monthly!$C$5:$BJ$5,E$27,Monthly!$C$26:$BJ$26) -> 4829971.5 | F42: =-SUMIF(Monthly!$C$5:$BJ$5,F$27,Monthly!$C$26:$BJ$26) -> 6015453.6
A43: Inventory (year end) | B43: =INDEX(Monthly!$C$65:$BJ$65,B$27*12) -> 570371.62 | C43: =INDEX(Monthly!$C$65:$BJ$65,C$27*12) -> 746910.62 | D43: =INDEX(Monthly!$C$65:$BJ$65,D$27*12) -> 955438.33 | E43: =INDEX(Monthly!$C$65:$BJ$65,E$27*12) -> 1203678.5 | F43: =INDEX(Monthly!$C$65:$BJ$65,F$27*12) -> 1501352.3
A44: Inventory turns (product cost ÷ year-end inventory) | B44: =IF(B43=0,0,B42/B43) -> 4.0609944 | C44: =IF(C43=0,0,C42/C43) -> 4.036918 | D44: =IF(D43=0,0,D42/D43) -> 4.0220507 | E44: =IF(E43=0,0,E42/E43) -> 4.0126757 | F44: =IF(F43=0,0,F42/F43) -> 4.0066903

Sheet Inputs
A1: Inputs — Low / Base / High | I1: =HYPERLINK("#'Cover'!A1","◂ Contents") -> ◂ Contents
A2: Illustrative assumptions — replace them with your own numbers.
A5: Driver | B5: Low | C5: Base | D5: High | E5: Active | F5: Unit | G5: Source / comment
A6: Online channel
A7: Website visits per month (year 1, non-paid) | B7: 65000 | C7: 80000 | D7: 100000 | E7: =CHOOSE(Dashboard!$B$4,B7,C7,D7) -> 80000 | F7: # / month | G7: Low ≤ Base ≤ High
A8: Visit growth per year | B8: 0.1 | C8: 0.25 | D8: 0.4 | E8: =CHOOSE(Dashboard!$B$4,B8,C8,D8) -> 0.25 | F8: % | G8: Low ≤ Base ≤ High
A9: Conversion rate (orders ÷ visits) | B9: 0.02 | C9: 0.024 | D9: 0.028 | E9: =CHOOSE(Dashboard!$B$4,B9,C9,D9) -> 0.024 | F9: % | G9: Low ≤ Base ≤ High
A10: Average order value (before returns) | B10: 65 | C10: 75 | D10: 85 | E10: =CHOOSE(Dashboard!$B$4,B10,C10,D10) -> 75 | F10: $ | G10: Low ≤ Base ≤ High
A11: Average order value growth per year | B11: 0 | C11: 0.02 | D11: 0.04 | E11: =CHOOSE(Dashboard!$B$4,B11,C11,D11) -> 0.02 | F11: % | G11: Low ≤ Base ≤ High
A12: Repeat orders per new-customer order (returning customers) | B12: 0.4 | C12: 0.5 | D12: 0.6 | E12: =CHOOSE(Dashboard!$B$4,B12,C12,D12) -> 0.5 | F12: x | G12: Low ≤ Base ≤ High
A13: Paid ads budget per month (year 1) | B13: 50000 | C13: 50000 | D13: 50000 | E13: =CHOOSE(Dashboard!$B$4,B13,C13,D13) -> 50000 | F13: $ / month
A14: Paid ads budget growth per year | B14: 0.2 | C14: 0.2 | D14: 0.2 | E14: =CHOOSE(Dashboard!$B$4,B14,C14,D14) -> 0.2 | F14: %
A15: Paid cost per order (CAC) | B15: 36 | C15: 28 | D15: 22 | E15: =CHOOSE(Dashboard!$B$4,B15,C15,D15) -> 28 | F15: $ | G15: Low ≥ Base ≥ High (lower is better)
A17: Store channel
A18: Stores open at start | B18: 2 | C18: 2 | D18: 2 | E18: =CHOOSE(Dashboard!$B$4,B18,C18,D18) -> 2 | F18: # | G18: Low ≤ Base ≤ High
A19: New stores opened each year from year 2 | B19: 1 | C19: 1 | D19: 1 | E19: =CHOOSE(Dashboard!$B$4,B19,C19,D19) -> 1 | F19: # / year | G19: Low ≤ Base ≤ High
A20: Selling area per store | B20: 1500 | C20: 1500 | D20: 1500 | E20: =CHOOSE(Dashboard!$B$4,B20,C20,D20) -> 1500 | F20: sq ft
A21: Sales per sq ft per year (year 1) | B21: 300 | C21: 375 | D21: 450 | E21: =CHOOSE(Dashboard!$B$4,B21,C21,D21) -> 375 | F21: $ / sq ft | G21: Low ≤ Base ≤ High
A22: Like-for-like store sales growth per year | B22: 0 | C22: 0.02 | D22: 0.04 | E22: =CHOOSE(Dashboard!$B$4,B22,C22,D22) -> 0.02 | F22: % | G22: Low ≤ Base ≤ High
A23: Store rent per sq ft per year | B23: 40 | C23: 40 | D23: 40 | E23: =CHOOSE(Dashboard!$B$4,B23,C23,D23) -> 40 | F23: $ / sq ft
A24: Other running cost per store per month | B24: 2500 | C24: 2500 | D24: 2500 | E24: =CHOOSE(Dashboard!$B$4,B24,C24,D24) -> 2500 | F24: $
A25: Fit-out capex per new store | B25: 150000 | C25: 150000 | D25: 150000 | E25: =CHOOSE(Dashboard!$B$4,B25,C25,D25) -> 150000 | F25: $
A27: Costs
A28: Seasonality: Nov–Dec sales uplift (annual total unchanged) | B28: 0.3 | C28: 0.3 | D28: 0.3 | E28: =CHOOSE(Dashboard!$B$4,B28,C28,D28) -> 0.3 | F28: %
A29: Returns & refunds, % of gross sales | B29: 0.12 | C29: 0.1 | D29: 0.08 | E29: =CHOOSE(Dashboard!$B$4,B29,C29,D29) -> 0.1 | F29: % | G29: Low ≥ Base ≥ High (lower is better)
A30: Product cost, % of net sales | B30: 0.45 | C30: 0.42 | D30: 0.39 | E30: =CHOOSE(Dashboard!$B$4,B30,C30,D30) -> 0.42 | F30: % | G30: Low ≥ Base ≥ High (lower is better)
A31: Fulfilment & shipping per online order | B31: 9 | C31: 8 | D31: 7 | E31: =CHOOSE(Dashboard!$B$4,B31,C31,D31) -> 8 | F31: $ | G31: Low ≥ Base ≥ High (lower is better)
A32: Payment processing, % of net sales | B32: 0.03 | C32: 0.03 | D32: 0.03 | E32: =CHOOSE(Dashboard!$B$4,B32,C32,D32) -> 0.03 | F32: %
A33: E-commerce platform & software per month | B33: 4000 | C33: 4000 | D33: 4000 | E33: =CHOOSE(Dashboard!$B$4,B33,C33,D33) -> 4000 | F33: $
A34: Other G&A per month | B34: 8000 | C34: 8000 | D34: 8000 | E34: =CHOOSE(Dashboard!$B$4,B34,C34,D34) -> 8000 | F34: $
A35: Start-up capex (equipment, systems) | B35: 50000 | C35: 50000 | D35: 50000 | E35: =CHOOSE(Dashboard!$B$4,B35,C35,D35) -> 50000 | F35: $
A37: Headcount
A38: Operations & fulfilment: headcount (FTE) | B38: 6 | C38: 6 | D38: 6 | E38: =CHOOSE(Dashboard!$B$4,B38,C38,D38) -> 6 | F38: FTE | G38: Low ≤ Base ≤ High
A39: Operations & fulfilment: salary per FTE per year | B39: 50000 | C39: 50000 | D39: 50000 | E39: =CHOOSE(Dashboard!$B$4,B39,C39,D39) -> 50000 | F39: $
A40: Operations & fulfilment: headcount growth per year | B40: 0.2 | C40: 0.2 | D40: 0.2 | E40: =CHOOSE(Dashboard!$B$4,B40,C40,D40) -> 0.2 | F40: % | G40: Low ≤ Base ≤ High
A41: Operations & fulfilment: first month on payroll | B41: 1 | C41: 1 | D41: 1 | E41: =CHOOSE(Dashboard!$B$4,B41,C41,D41) -> 1 | F41: month #
A42: Marketing & e-commerce: headcount (FTE) | B42: 4 | C42: 4 | D42: 4 | E42: =CHOOSE(Dashboard!$B$4,B42,C42,D42) -> 4 | F42: FTE | G42: Low ≤ Base ≤ High
A43: Marketing & e-commerce: salary per FTE per year | B43: 70000 | C43: 70000 | D43: 70000 | E43: =CHOOSE(Dashboard!$B$4,B43,C43,D43) -> 70000 | F43: $
A44: Marketing & e-commerce: headcount growth per year | B44: 0.2 | C44: 0.2 | D44: 0.2 | E44: =CHOOSE(Dashboard!$B$4,B44,C44,D44) -> 0.2 | F44: % | G44: Low ≤ Base ≤ High
A45: Marketing & e-commerce: first month on payroll | B45: 1 | C45: 1 | D45: 1 | E45: =CHOOSE(Dashboard!$B$4,B45,C45,D45) -> 1 | F45: month #
A46: Store staff: headcount (FTE) | B46: 8 | C46: 8 | D46: 8 | E46: =CHOOSE(Dashboard!$B$4,B46,C46,D46) -> 8 | F46: FTE | G46: Low ≤ Base ≤ High
A47: Store staff: salary per FTE per year | B47: 38000 | C47: 38000 | D47: 38000 | E47: =CHOOSE(Dashboard!$B$4,B47,C47,D47) -> 38000 | F47: $
A48: Store staff: headcount growth per year | B48: 0.3 | C48: 0.3 | D48: 0.3 | E48: =CHOOSE(Dashboard!$B$4,B48,C48,D48) -> 0.3 | F48: % | G48: Low ≤ Base ≤ High
A49: Store staff: first month on payroll | B49: 1 | C49: 1 | D49: 1 | E49: =CHOOSE(Dashboard!$B$4,B49,C49,D49) -> 1 | F49: month #
A50: G&A (finance, admin): headcount (FTE) | B50: 3 | C50: 3 | D50: 3 | E50: =CHOOSE(Dashboard!$B$4,B50,C50,D50) -> 3 | F50: FTE | G50: Low ≤ Base ≤ High
A51: G&A (finance, admin): salary per FTE per year | B51: 70000 | C51: 70000 | D51: 70000 | E51: =CHOOSE(Dashboard!$B$4,B51,C51,D51) -> 70000 | F51: $
A52: G&A (finance, admin): headcount growth per year | B52: 0.15 | C52: 0.15 | D52: 0.15 | E52: =CHOOSE(Dashboard!$B$4,B52,C52,D52) -> 0.15 | F52: % | G52: Low ≤ Base ≤ High
A53: G&A (finance, admin): first month on payroll | B53: 1 | C53: 1 | D53: 1 | E53: =CHOOSE(Dashboard!$B$4,B53,C53,D53) -> 1 | F53: month #
A54: Payroll taxes & benefits, % of salary | B54: 0.15 | C54: 0.15 | D54: 0.15 | E54: =CHOOSE(Dashboard!$B$4,B54,C54,D54) -> 0.15 | F54: %
A55: Wage growth per year | B55: 0.03 | C55: 0.03 | D55: 0.03 | E55: =CHOOSE(Dashboard!$B$4,B55,C55,D55) -> 0.03 | F55: %
A57: Funding
A58: Equity raised at start | B58: 1500000 | C58: 1500000 | D58: 1500000 | E58: =CHOOSE(Dashboard!$B$4,B58,C58,D58) -> 1500000 | F58: $
A59: Loan drawn at start | B59: 500000 | C59: 500000 | D59: 500000 | E59: =CHOOSE(Dashboard!$B$4,B59,C59,D59) -> 500000 | F59: $
A60: Loan interest rate per year | B60: 0.08 | C60: 0.08 | D60: 0.08 | E60: =CHOOSE(Dashboard!$B$4,B60,C60,D60) -> 0.08 | F60: %
A61: Loan repayment term | B61: 5 | C61: 5 | D61: 5 | E61: =CHOOSE(Dashboard!$B$4,B61,C61,D61) -> 5 | F61: years
A63: Working capital
A64: Customer payment terms (receivable days) | B64: 2 | C64: 2 | D64: 2 | E64: =CHOOSE(Dashboard!$B$4,B64,C64,D64) -> 2 | F64: days
A65: Inventory held (days of COGS) | B65: 75 | C65: 75 | D65: 75 | E65: =CHOOSE(Dashboard!$B$4,B65,C65,D65) -> 75 | F65: days
A66: Supplier payment terms (payable days) | B66: 30 | C66: 30 | D66: 30 | E66: =CHOOSE(Dashboard!$B$4,B66,C66,D66) -> 30 | F66: days
A68: Tax & depreciation
A69: Depreciation period for capex | B69: 7 | C69: 7 | D69: 7 | E69: =CHOOSE(Dashboard!$B$4,B69,C69,D69) -> 7 | F69: years
A70: Income tax rate | B70: 0.21 | C70: 0.21 | D70: 0.21 | E70: =CHOOSE(Dashboard!$B$4,B70,C70,D70) -> 0.21 | F70: %
A72: Break-even & funding
A73: Minimum cash buffer to keep | B73: 720000 | C73: 720000 | D73: 720000 | E73: =CHOOSE(Dashboard!$B$4,B73,C73,D73) -> 720000 | F73: $ | G73: About 3 months of costs
A75: Valuation
A76: Discount rate (WACC) | B76: 0.2 | C76: 0.16 | D76: 0.13 | E76: =CHOOSE(Dashboard!$B$4,B76,C76,D76) -> 0.16 | F76: % | G76: Low ≥ Base ≥ High (lower is better)
A77: Terminal growth rate (perpetuity) | B77: 0.01 | C77: 0.02 | D77: 0.03 | E77: =CHOOSE(Dashboard!$B$4,B77,C77,D77) -> 0.02 | F77: % | G77: Low ≤ Base ≤ High
A78: Exit multiple (EV ÷ final-year EBITDA) | B78: 4 | C78: 5.5 | D78: 7 | E78: =CHOOSE(Dashboard!$B$4,B78,C78,D78) -> 5.5 | F78: x | G78: Low ≤ Base ≤ High
A79: Sensitivity table: WACC step | B79: 0.01 | C79: 0.01 | D79: 0.01 | E79: =CHOOSE(Dashboard!$B$4,B79,C79,D79) -> 0.01 | F79: %
A80: Sensitivity table: growth step | B80: 0.005 | C80: 0.005 | D80: 0.005 | E80: =CHOOSE(Dashboard!$B$4,B80,C80,D80) -> 0.005 | F80: %
A82: Legend: yellow cell with blue figure = input you can change · black = formula · green = link to another sheet · grey = active value (column E follows the scenario on the Dashboard).

Sheet P&L
A1: Annual profit & loss | H1: =HYPERLINK("#'Cover'!A1","◂ Contents") -> ◂ Contents
A2: Rolled up from the period detail (SUMIF on the year row; balances at year end).
A3: Year # | B3: 1 | C3: 2 | D3: 3 | E3: 4 | F3: 5
B4: Year 1 | C4: Year 2 | D4: Year 3 | E4: Year 4 | F4: Year 5
A5: Revenue | B5: =SUMIF(Monthly!$C$5:$BJ$5,B$3,Monthly!$C$25:$BJ$25) -> 5514942.9 | C5: =SUMIF(Monthly!$C$5:$BJ$5,C$3,Monthly!$C$25:$BJ$25) -> 7179087.9 | D5: =SUMIF(Monthly!$C$5:$BJ$5,D$3,Monthly!$C$25:$BJ$25) -> 9149574.9 | E5: =SUMIF(Monthly!$C$5:$BJ$5,E$3,Monthly!$C$25:$BJ$25) -> 11499932 | F5: =SUMIF(Monthly!$C$5:$BJ$5,F$3,Monthly!$C$25:$BJ$25) -> 14322508
A6: Product cost | B6: =SUMIF(Monthly!$C$5:$BJ$5,B$3,Monthly!$C$26:$BJ$26) -> -2316276 | C6: =SUMIF(Monthly!$C$5:$BJ$5,C$3,Monthly!$C$26:$BJ$26) -> -3015216.9 | D6: =SUMIF(Monthly!$C$5:$BJ$5,D$3,Monthly!$C$26:$BJ$26) -> -3842821.4 | E6: =SUMIF(Monthly!$C$5:$BJ$5,E$3,Monthly!$C$26:$BJ$26) -> -4829971.5 | F6: =SUMIF(Monthly!$C$5:$BJ$5,F$3,Monthly!$C$26:$BJ$26) -> -6015453.6
A7: Gross profit | B7: =SUMIF(Monthly!$C$5:$BJ$5,B$3,Monthly!$C$27:$BJ$27) -> 3198666.9 | C7: =SUMIF(Monthly!$C$5:$BJ$5,C$3,Monthly!$C$27:$BJ$27) -> 4163871 | D7: =SUMIF(Monthly!$C$5:$BJ$5,D$3,Monthly!$C$27:$BJ$27) -> 5306753.4 | E7: =SUMIF(Monthly!$C$5:$BJ$5,E$3,Monthly!$C$27:$BJ$27) -> 6669960.6 | F7: =SUMIF(Monthly!$C$5:$BJ$5,F$3,Monthly!$C$27:$BJ$27) -> 8307054.9
A8: Gross margin | B8: =IF(B5=0,0,B7/B5) -> 0.58 | C8: =IF(C5=0,0,C7/C5) -> 0.58 | D8: =IF(D5=0,0,D7/D5) -> 0.58 | E8: =IF(E5=0,0,E7/E5) -> 0.58 | F8: =IF(F5=0,0,F7/F5) -> 0.58
A9: Fulfilment & shipping | B9: =SUMIF(Monthly!$C$5:$BJ$5,B$3,Monthly!$C$30:$BJ$30) -> -533622.86 | C9: =SUMIF(Monthly!$C$5:$BJ$5,C$3,Monthly!$C$30:$BJ$30) -> -654171.43 | D9: =SUMIF(Monthly!$C$5:$BJ$5,D$3,Monthly!$C$30:$BJ$30) -> -802285.71 | E9: =SUMIF(Monthly!$C$5:$BJ$5,E$3,Monthly!$C$30:$BJ$30) -> -984342.86 | F9: =SUMIF(Monthly!$C$5:$BJ$5,F$3,Monthly!$C$30:$BJ$30) -> -1208211.4
A10: Payment processing | B10: =SUMIF(Monthly!$C$5:$BJ$5,B$3,Monthly!$C$31:$BJ$31) -> -165448.29 | C10: =SUMIF(Monthly!$C$5:$BJ$5,C$3,Monthly!$C$31:$BJ$31) -> -215372.64 | D10: =SUMIF(Monthly!$C$5:$BJ$5,D$3,Monthly!$C$31:$BJ$31) -> -274487.25 | E10: =SUMIF(Monthly!$C$5:$BJ$5,E$3,Monthly!$C$31:$BJ$31) -> -344997.96 | F10: =SUMIF(Monthly!$C$5:$BJ$5,F$3,Monthly!$C$31:$BJ$31) -> -429675.25
A11: Paid ads | B11: =SUMIF(Monthly!$C$5:$BJ$5,B$3,Monthly!$C$32:$BJ$32) -> -600000 | C11: =SUMIF(Monthly!$C$5:$BJ$5,C$3,Monthly!$C$32:$BJ$32) -> -720000 | D11: =SUMIF(Monthly!$C$5:$BJ$5,D$3,Monthly!$C$32:$BJ$32) -> -864000 | E11: =SUMIF(Monthly!$C$5:$BJ$5,E$3,Monthly!$C$32:$BJ$32) -> -1036800 | F11: =SUMIF(Monthly!$C$5:$BJ$5,F$3,Monthly!$C$32:$BJ$32) -> -1244160
A12: Payroll | B12: =SUMIF(Monthly!$C$5:$BJ$5,B$3,Monthly!$C$33:$BJ$33) -> -1258100 | C12: =SUMIF(Monthly!$C$5:$BJ$5,C$3,Monthly!$C$33:$BJ$33) -> -1578583.1 | D12: =SUMIF(Monthly!$C$5:$BJ$5,D$3,Monthly!$C$33:$BJ$33) -> -1984612.6 | E12: =SUMIF(Monthly!$C$5:$BJ$5,E$3,Monthly!$C$33:$BJ$33) -> -2500092.2 | F12: =SUMIF(Monthly!$C$5:$BJ$5,F$3,Monthly!$C$33:$BJ$33) -> -3155891.6
A13: Store rent | B13: =SUMIF(Monthly!$C$5:$BJ$5,B$3,Monthly!$C$34:$BJ$34) -> -120000 | C13: =SUMIF(Monthly!$C$5:$BJ$5,C$3,Monthly!$C$34:$BJ$34) -> -180000 | D13: =SUMIF(Monthly!$C$5:$BJ$5,D$3,Monthly!$C$34:$BJ$34) -> -240000 | E13: =SUMIF(Monthly!$C$5:$BJ$5,E$3,Monthly!$C$34:$BJ$34) -> -300000 | F13: =SUMIF(Monthly!$C$5:$BJ$5,F$3,Monthly!$C$34:$BJ$34) -> -360000
A14: Store running costs | B14: =SUMIF(Monthly!$C$5:$BJ$5,B$3,Monthly!$C$35:$BJ$35) -> -60000 | C14: =SUMIF(Monthly!$C$5:$BJ$5,C$3,Monthly!$C$35:$BJ$35) -> -90000 | D14: =SUMIF(Monthly!$C$5:$BJ$5,D$3,Monthly!$C$35:$BJ$35) -> -120000 | E14: =SUMIF(Monthly!$C$5:$BJ$5,E$3,Monthly!$C$35:$BJ$35) -> -150000 | F14: =SUMIF(Monthly!$C$5:$BJ$5,F$3,Monthly!$C$35:$BJ$35) -> -180000
A15: Platform & software | B15: =SUMIF(Monthly!$C$5:$BJ$5,B$3,Monthly!$C$36:$BJ$36) -> -48000 | C15: =SUMIF(Monthly!$C$5:$BJ$5,C$3,Monthly!$C$36:$BJ$36) -> -48000 | D15: =SUMIF(Monthly!$C$5:$BJ$5,D$3,Monthly!$C$36:$BJ$36) -> -48000 | E15: =SUMIF(Monthly!$C$5:$BJ$5,E$3,Monthly!$C$36:$BJ$36) -> -48000 | F15: =SUMIF(Monthly!$C$5:$BJ$5,F$3,Monthly!$C$36:$BJ$36) -> -48000
A16: Other G&A | B16: =SUMIF(Monthly!$C$5:$BJ$5,B$3,Monthly!$C$37:$BJ$37) -> -96000 | C16: =SUMIF(Monthly!$C$5:$BJ$5,C$3,Monthly!$C$37:$BJ$37) -> -96000 | D16: =SUMIF(Monthly!$C$5:$BJ$5,D$3,Monthly!$C$37:$BJ$37) -> -96000 | E16: =SUMIF(Monthly!$C$5:$BJ$5,E$3,Monthly!$C$37:$BJ$37) -> -96000 | F16: =SUMIF(Monthly!$C$5:$BJ$5,F$3,Monthly!$C$37:$BJ$37) -> -96000
A17: Total operating expenses | B17: =SUMIF(Monthly!$C$5:$BJ$5,B$3,Monthly!$C$38:$BJ$38) -> -2881171.1 | C17: =SUMIF(Monthly!$C$5:$BJ$5,C$3,Monthly!$C$38:$BJ$38) -> -3582127.2 | D17: =SUMIF(Monthly!$C$5:$BJ$5,D$3,Monthly!$C$38:$BJ$38) -> -4429385.6 | E17: =SUMIF(Monthly!$C$5:$BJ$5,E$3,Monthly!$C$38:$BJ$38) -> -5460233 | F17: =SUMIF(Monthly!$C$5:$BJ$5,F$3,Monthly!$C$38:$BJ$38) -> -6721938.2
A18: EBITDA | B18: =SUMIF(Monthly!$C$5:$BJ$5,B$3,Monthly!$C$39:$BJ$39) -> 317495.71 | C18: =SUMIF(Monthly!$C$5:$BJ$5,C$3,Monthly!$C$39:$BJ$39) -> 581743.74 | D18: =SUMIF(Monthly!$C$5:$BJ$5,D$3,Monthly!$C$39:$BJ$39) -> 877367.82 | E18: =SUMIF(Monthly!$C$5:$BJ$5,E$3,Monthly!$C$39:$BJ$39) -> 1209727.6 | F18: =SUMIF(Monthly!$C$5:$BJ$5,F$3,Monthly!$C$39:$BJ$39) -> 1585116.7
A19: EBITDA margin | B19: =IF(B5=0,0,B18/B5) -> 0.057570082 | C19: =IF(C5=0,0,C18/C5) -> 0.0810331 | D19: =IF(D5=0,0,D18/D5) -> 0.095891649 | E19: =IF(E5=0,0,E18/E5) -> 0.10519433 | F19: =IF(F5=0,0,F18/F5) -> 0.11067312
A20: Depreciation | B20: =SUMIF(Monthly!$C$5:$BJ$5,B$3,Monthly!$C$53:$BJ$53) -> -50000 | C20: =SUMIF(Monthly!$C$5:$BJ$5,C$3,Monthly!$C$53:$BJ$53) -> -71428.571 | D20: =SUMIF(Monthly!$C$5:$BJ$5,D$3,Monthly!$C$53:$BJ$53) -> -92857.143 | E20: =SUMIF(Monthly!$C$5:$BJ$5,E$3,Monthly!$C$53:$BJ$53) -> -114285.71 | F20: =SUMIF(Monthly!$C$5:$BJ$5,F$3,Monthly!$C$53:$BJ$53) -> -135714.29
A21: EBIT | B21: =SUMIF(Monthly!$C$5:$BJ$5,B$3,Monthly!$C$42:$BJ$42) -> 267495.71 | C21: =SUMIF(Monthly!$C$5:$BJ$5,C$3,Monthly!$C$42:$BJ$42) -> 510315.17 | D21: =SUMIF(Monthly!$C$5:$BJ$5,D$3,Monthly!$C$42:$BJ$42) -> 784510.68 | E21: =SUMIF(Monthly!$C$5:$BJ$5,E$3,Monthly!$C$42:$BJ$42) -> 1095441.9 | F21: =SUMIF(Monthly!$C$5:$BJ$5,F$3,Monthly!$C$42:$BJ$42) -> 1449402.4
A22: Interest | B22: =SUMIF(Monthly!$C$5:$BJ$5,B$3,Monthly!$C$43:$BJ$43) -> -36638.889 | C22: =SUMIF(Monthly!$C$5:$BJ$5,C$3,Monthly!$C$43:$BJ$43) -> -28666.667 | D22: =SUMIF(Monthly!$C$5:$BJ$5,D$3,Monthly!$C$43:$BJ$43) -> -20666.667 | E22: =SUMIF(Monthly!$C$5:$BJ$5,E$3,Monthly!$C$43:$BJ$43) -> -12666.667 | F22: =SUMIF(Monthly!$C$5:$BJ$5,F$3,Monthly!$C$43:$BJ$43) -> -4666.6667
A23: Pre-tax income | B23: =SUMIF(Monthly!$C$5:$BJ$5,B$3,Monthly!$C$44:$BJ$44) -> 230856.83 | C23: =SUMIF(Monthly!$C$5:$BJ$5,C$3,Monthly!$C$44:$BJ$44) -> 481648.5 | D23: =SUMIF(Monthly!$C$5:$BJ$5,D$3,Monthly!$C$44:$BJ$44) -> 763844.01 | E23: =SUMIF(Monthly!$C$5:$BJ$5,E$3,Monthly!$C$44:$BJ$44) -> 1082775.2 | F23: =SUMIF(Monthly!$C$5:$BJ$5,F$3,Monthly!$C$44:$BJ$44) -> 1444735.7
A24: Income tax | B24: =SUMIF(Monthly!$C$5:$BJ$5,B$3,Monthly!$C$47:$BJ$47) -> -48479.933 | C24: =SUMIF(Monthly!$C$5:$BJ$5,C$3,Monthly!$C$47:$BJ$47) -> -101146.19 | D24: =SUMIF(Monthly!$C$5:$BJ$5,D$3,Monthly!$C$47:$BJ$47) -> -160407.24 | E24: =SUMIF(Monthly!$C$5:$BJ$5,E$3,Monthly!$C$47:$BJ$47) -> -227382.8 | F24: =SUMIF(Monthly!$C$5:$BJ$5,F$3,Monthly!$C$47:$BJ$47) -> -303394.5
A25: Net income | B25: =SUMIF(Monthly!$C$5:$BJ$5,B$3,Monthly!$C$48:$BJ$48) -> 182376.89 | C25: =SUMIF(Monthly!$C$5:$BJ$5,C$3,Monthly!$C$48:$BJ$48) -> 380502.32 | D25: =SUMIF(Monthly!$C$5:$BJ$5,D$3,Monthly!$C$48:$BJ$48) -> 603436.77 | E25: =SUMIF(Monthly!$C$5:$BJ$5,E$3,Monthly!$C$48:$BJ$48) -> 855392.43 | F25: =SUMIF(Monthly!$C$5:$BJ$5,F$3,Monthly!$C$48:$BJ$48) -> 1141341.2
A26: Net margin | B26: =IF(B5=0,0,B25/B5) -> 0.033069589 | C26: =IF(C5=0,0,C25/C5) -> 0.053001485 | D26: =IF(D5=0,0,D25/D5) -> 0.065952438 | E26: =IF(E5=0,0,E25/E5) -> 0.07438239 | F26: =IF(F5=0,0,F25/F5) -> 0.07968864

Sheet Cash Flow
A1: Annual cash flow statement | H1: =HYPERLINK("#'Cover'!A1","◂ Contents") -> ◂ Contents
A2: Rolled up from the period detail (SUMIF on the year row; balances at year end).
A3: Year # | B3: 1 | C3: 2 | D3: 3 | E3: 4 | F3: 5
B4: Year 1 | C4: Year 2 | D4: Year 3 | E4: Year 4 | F4: Year 5
A5: Net income | B5: =SUMIF(Monthly!$C$5:$BJ$5,B$3,Monthly!$C$48:$BJ$48) -> 182376.89 | C5: =SUMIF(Monthly!$C$5:$BJ$5,C$3,Monthly!$C$48:$BJ$48) -> 380502.32 | D5: =SUMIF(Monthly!$C$5:$BJ$5,D$3,Monthly!$C$48:$BJ$48) -> 603436.77 | E5: =SUMIF(Monthly!$C$5:$BJ$5,E$3,Monthly!$C$48:$BJ$48) -> 855392.43 | F5: =SUMIF(Monthly!$C$5:$BJ$5,F$3,Monthly!$C$48:$BJ$48) -> 1141341.2
A6: Add back depreciation | B6: =-SUMIF(Monthly!$C$5:$BJ$5,B$3,Monthly!$C$53:$BJ$53) -> 50000 | C6: =-SUMIF(Monthly!$C$5:$BJ$5,C$3,Monthly!$C$53:$BJ$53) -> 71428.571 | D6: =-SUMIF(Monthly!$C$5:$BJ$5,D$3,Monthly!$C$53:$BJ$53) -> 92857.143 | E6: =-SUMIF(Monthly!$C$5:$BJ$5,E$3,Monthly!$C$53:$BJ$53) -> 114285.71 | F6: =-SUMIF(Monthly!$C$5:$BJ$5,F$3,Monthly!$C$53:$BJ$53) -> 135714.29
A7: (Increase) / decrease in receivables | B7: =SUMIF(Monthly!$C$5:$BJ$5,B$3,Monthly!$C$67:$BJ$67) -> -36214.071 | C7: =SUMIF(Monthly!$C$5:$BJ$5,C$3,Monthly!$C$67:$BJ$67) -> -11208.825 | D7: =SUMIF(Monthly!$C$5:$BJ$5,D$3,Monthly!$C$67:$BJ$67) -> -13239.855 | E7: =SUMIF(Monthly!$C$5:$BJ$5,E$3,Monthly!$C$67:$BJ$67) -> -15761.28 | F7: =SUMIF(Monthly!$C$5:$BJ$5,F$3,Monthly!$C$67:$BJ$67) -> -18899.922
A8: (Increase) / decrease in inventory | B8: =SUMIF(Monthly!$C$5:$BJ$5,B$3,Monthly!$C$68:$BJ$68) -> -570371.62 | C8: =SUMIF(Monthly!$C$5:$BJ$5,C$3,Monthly!$C$68:$BJ$68) -> -176538.99 | D8: =SUMIF(Monthly!$C$5:$BJ$5,D$3,Monthly!$C$68:$BJ$68) -> -208527.72 | E8: =SUMIF(Monthly!$C$5:$BJ$5,E$3,Monthly!$C$68:$BJ$68) -> -248240.16 | F8: =SUMIF(Monthly!$C$5:$BJ$5,F$3,Monthly!$C$68:$BJ$68) -> -297673.77
A9: Increase / (decrease) in payables | B9: =SUMIF(Monthly!$C$5:$BJ$5,B$3,Monthly!$C$69:$BJ$69) -> 228148.65 | C9: =SUMIF(Monthly!$C$5:$BJ$5,C$3,Monthly!$C$69:$BJ$69) -> 70615.598 | D9: =SUMIF(Monthly!$C$5:$BJ$5,D$3,Monthly!$C$69:$BJ$69) -> 83411.087 | E9: =SUMIF(Monthly!$C$5:$BJ$5,E$3,Monthly!$C$69:$BJ$69) -> 99296.062 | F9: =SUMIF(Monthly!$C$5:$BJ$5,F$3,Monthly!$C$69:$BJ$69) -> 119069.51
A10: Operating cash flow | B10: =SUMIF(Monthly!$C$5:$BJ$5,B$3,Monthly!$C$72:$BJ$72) -> -146060.15 | C10: =SUMIF(Monthly!$C$5:$BJ$5,C$3,Monthly!$C$72:$BJ$72) -> 334798.67 | D10: =SUMIF(Monthly!$C$5:$BJ$5,D$3,Monthly!$C$72:$BJ$72) -> 557937.43 | E10: =SUMIF(Monthly!$C$5:$BJ$5,E$3,Monthly!$C$72:$BJ$72) -> 804972.77 | F10: =SUMIF(Monthly!$C$5:$BJ$5,F$3,Monthly!$C$72:$BJ$72) -> 1079551.3
A11: Capital spending | B11: =SUMIF(Monthly!$C$5:$BJ$5,B$3,Monthly!$C$73:$BJ$73) -> -350000 | C11: =SUMIF(Monthly!$C$5:$BJ$5,C$3,Monthly!$C$73:$BJ$73) -> -150000 | D11: =SUMIF(Monthly!$C$5:$BJ$5,D$3,Monthly!$C$73:$BJ$73) -> -150000 | E11: =SUMIF(Monthly!$C$5:$BJ$5,E$3,Monthly!$C$73:$BJ$73) -> -150000 | F11: =SUMIF(Monthly!$C$5:$BJ$5,F$3,Monthly!$C$73:$BJ$73) -> -150000
A12: Equity raised | B12: =SUMIF(Monthly!$C$5:$BJ$5,B$3,Monthly!$C$74:$BJ$74) -> 1500000 | C12: =SUMIF(Monthly!$C$5:$BJ$5,C$3,Monthly!$C$74:$BJ$74) -> 0 | D12: =SUMIF(Monthly!$C$5:$BJ$5,D$3,Monthly!$C$74:$BJ$74) -> 0 | E12: =SUMIF(Monthly!$C$5:$BJ$5,E$3,Monthly!$C$74:$BJ$74) -> 0 | F12: =SUMIF(Monthly!$C$5:$BJ$5,F$3,Monthly!$C$74:$BJ$74) -> 0
A13: Loan drawdown | B13: =SUMIF(Monthly!$C$5:$BJ$5,B$3,Monthly!$C$59:$BJ$59) -> 500000 | C13: =SUMIF(Monthly!$C$5:$BJ$5,C$3,Monthly!$C$59:$BJ$59) -> 0 | D13: =SUMIF(Monthly!$C$5:$BJ$5,D$3,Monthly!$C$59:$BJ$59) -> 0 | E13: =SUMIF(Monthly!$C$5:$BJ$5,E$3,Monthly!$C$59:$BJ$59) -> 0 | F13: =SUMIF(Monthly!$C$5:$BJ$5,F$3,Monthly!$C$59:$BJ$59) -> 0
A14: Loan repayment | B14: =SUMIF(Monthly!$C$5:$BJ$5,B$3,Monthly!$C$60:$BJ$60) -> -91666.667 | C14: =SUMIF(Monthly!$C$5:$BJ$5,C$3,Monthly!$C$60:$BJ$60) -> -100000 | D14: =SUMIF(Monthly!$C$5:$BJ$5,D$3,Monthly!$C$60:$BJ$60) -> -100000 | E14: =SUMIF(Monthly!$C$5:$BJ$5,E$3,Monthly!$C$60:$BJ$60) -> -100000 | F14: =SUMIF(Monthly!$C$5:$BJ$5,F$3,Monthly!$C$60:$BJ$60) -> -100000
A15: Financing cash flow | B15: =SUMIF(Monthly!$C$5:$BJ$5,B$3,Monthly!$C$75:$BJ$75) -> 1908333.3 | C15: =SUMIF(Monthly!$C$5:$BJ$5,C$3,Monthly!$C$75:$BJ$75) -> -100000 | D15: =SUMIF(Monthly!$C$5:$BJ$5,D$3,Monthly!$C$75:$BJ$75) -> -100000 | E15: =SUMIF(Monthly!$C$5:$BJ$5,E$3,Monthly!$C$75:$BJ$75) -> -100000 | F15: =SUMIF(Monthly!$C$5:$BJ$5,F$3,Monthly!$C$75:$BJ$75) -> -100000
A16: Net change in cash | B16: =SUMIF(Monthly!$C$5:$BJ$5,B$3,Monthly!$C$76:$BJ$76) -> 1412273.2 | C16: =SUMIF(Monthly!$C$5:$BJ$5,C$3,Monthly!$C$76:$BJ$76) -> 84798.669 | D16: =SUMIF(Monthly!$C$5:$BJ$5,D$3,Monthly!$C$76:$BJ$76) -> 307937.43 | E16: =SUMIF(Monthly!$C$5:$BJ$5,E$3,Monthly!$C$76:$BJ$76) -> 554972.77 | F16: =SUMIF(Monthly!$C$5:$BJ$5,F$3,Monthly!$C$76:$BJ$76) -> 829551.32
A17: Opening cash | B17: =INDEX(Monthly!$C$77:$BJ$77,(B$3-1)*12+1) -> 0 | C17: =INDEX(Monthly!$C$77:$BJ$77,(C$3-1)*12+1) -> 1412273.2 | D17: =INDEX(Monthly!$C$77:$BJ$77,(D$3-1)*12+1) -> 1497071.8 | E17: =INDEX(Monthly!$C$77:$BJ$77,(E$3-1)*12+1) -> 1805009.3 | F17: =INDEX(Monthly!$C$77:$BJ$77,(F$3-1)*12+1) -> 2359982
A18: Closing cash | B18: =INDEX(Monthly!$C$78:$BJ$78,B$3*12) -> 1412273.2 | C18: =INDEX(Monthly!$C$78:$BJ$78,C$3*12) -> 1497071.8 | D18: =INDEX(Monthly!$C$78:$BJ$78,D$3*12) -> 1805009.3 | E18: =INDEX(Monthly!$C$78:$BJ$78,E$3*12) -> 2359982 | F18: =INDEX(Monthly!$C$78:$BJ$78,F$3*12) -> 3189533.4

Sheet Balance Sheet
A1: Balance sheet at year end | H1: =HYPERLINK("#'Cover'!A1","◂ Contents") -> ◂ Contents
A2: Rolled up from the period detail (SUMIF on the year row; balances at year end).
A3: Year # | B3: 1 | C3: 2 | D3: 3 | E3: 4 | F3: 5
B4: Year 1 | C4: Year 2 | D4: Year 3 | E4: Year 4 | F4: Year 5
A5: Cash | B5: =INDEX(Monthly!$C$78:$BJ$78,B$3*12) -> 1412273.2 | C5: =INDEX(Monthly!$C$78:$BJ$78,C$3*12) -> 1497071.8 | D5: =INDEX(Monthly!$C$78:$BJ$78,D$3*12) -> 1805009.3 | E5: =INDEX(Monthly!$C$78:$BJ$78,E$3*12) -> 2359982 | F5: =INDEX(Monthly!$C$78:$BJ$78,F$3*12) -> 3189533.4
A6: Accounts receivable | B6: =INDEX(Monthly!$C$64:$BJ$64,B$3*12) -> 36214.071 | C6: =INDEX(Monthly!$C$64:$BJ$64,C$3*12) -> 47422.896 | D6: =INDEX(Monthly!$C$64:$BJ$64,D$3*12) -> 60662.751 | E6: =INDEX(Monthly!$C$64:$BJ$64,E$3*12) -> 76424.031 | F6: =INDEX(Monthly!$C$64:$BJ$64,F$3*12) -> 95323.953
A7: Inventory | B7: =INDEX(Monthly!$C$65:$BJ$65,B$3*12) -> 570371.62 | C7: =INDEX(Monthly!$C$65:$BJ$65,C$3*12) -> 746910.62 | D7: =INDEX(Monthly!$C$65:$BJ$65,D$3*12) -> 955438.33 | E7: =INDEX(Monthly!$C$65:$BJ$65,E$3*12) -> 1203678.5 | F7: =INDEX(Monthly!$C$65:$BJ$65,F$3*12) -> 1501352.3
A8: Net fixed assets | B8: =INDEX(Monthly!$C$55:$BJ$55,B$3*12) -> 300000 | C8: =INDEX(Monthly!$C$55:$BJ$55,C$3*12) -> 378571.43 | D8: =INDEX(Monthly!$C$55:$BJ$55,D$3*12) -> 435714.29 | E8: =INDEX(Monthly!$C$55:$BJ$55,E$3*12) -> 471428.57 | F8: =INDEX(Monthly!$C$55:$BJ$55,F$3*12) -> 485714.29
A9: Total assets | B9: =INDEX(Monthly!$C$92:$BJ$92,B$3*12) -> 2318858.9 | C9: =INDEX(Monthly!$C$92:$BJ$92,C$3*12) -> 2669976.8 | D9: =INDEX(Monthly!$C$92:$BJ$92,D$3*12) -> 3256824.6 | E9: =INDEX(Monthly!$C$92:$BJ$92,E$3*12) -> 4111513.1 | F9: =INDEX(Monthly!$C$92:$BJ$92,F$3*12) -> 5271923.9
A10: Accounts payable | B10: =INDEX(Monthly!$C$66:$BJ$66,B$3*12) -> 228148.65 | C10: =INDEX(Monthly!$C$66:$BJ$66,C$3*12) -> 298764.25 | D10: =INDEX(Monthly!$C$66:$BJ$66,D$3*12) -> 382175.33 | E10: =INDEX(Monthly!$C$66:$BJ$66,E$3*12) -> 481471.4 | F10: =INDEX(Monthly!$C$66:$BJ$66,F$3*12) -> 600540.91
A11: Loan | B11: =INDEX(Monthly!$C$61:$BJ$61,B$3*12) -> 408333.33 | C11: =INDEX(Monthly!$C$61:$BJ$61,C$3*12) -> 308333.33 | D11: =INDEX(Monthly!$C$61:$BJ$61,D$3*12) -> 208333.33 | E11: =INDEX(Monthly!$C$61:$BJ$61,E$3*12) -> 108333.33 | F11: =INDEX(Monthly!$C$61:$BJ$61,F$3*12) -> 8333.3333
A12: Total liabilities | B12: =INDEX(Monthly!$C$93:$BJ$93,B$3*12) -> 636481.98 | C12: =INDEX(Monthly!$C$93:$BJ$93,C$3*12) -> 607097.58 | D12: =INDEX(Monthly!$C$93:$BJ$93,D$3*12) -> 590508.67 | E12: =INDEX(Monthly!$C$93:$BJ$93,E$3*12) -> 589804.73 | F12: =INDEX(Monthly!$C$93:$BJ$93,F$3*12) -> 608874.24
A13: Paid-in capital | B13: =INDEX(Monthly!$C$90:$BJ$90,B$3*12) -> 1500000 | C13: =INDEX(Monthly!$C$90:$BJ$90,C$3*12) -> 1500000 | D13: =INDEX(Monthly!$C$90:$BJ$90,D$3*12) -> 1500000 | E13: =INDEX(Monthly!$C$90:$BJ$90,E$3*12) -> 1500000 | F13: =INDEX(Monthly!$C$90:$BJ$90,F$3*12) -> 1500000
A14: Retained earnings | B14: =INDEX(Monthly!$C$91:$BJ$91,B$3*12) -> 182376.89 | C14: =INDEX(Monthly!$C$91:$BJ$91,C$3*12) -> 562879.21 | D14: =INDEX(Monthly!$C$91:$BJ$91,D$3*12) -> 1166316 | E14: =INDEX(Monthly!$C$91:$BJ$91,E$3*12) -> 2021708.4 | F14: =INDEX(Monthly!$C$91:$BJ$91,F$3*12) -> 3163049.6
A15: Total equity | B15: =INDEX(Monthly!$C$94:$BJ$94,B$3*12) -> 1682376.9 | C15: =INDEX(Monthly!$C$94:$BJ$94,C$3*12) -> 2062879.2 | D15: =INDEX(Monthly!$C$94:$BJ$94,D$3*12) -> 2666316 | E15: =INDEX(Monthly!$C$94:$BJ$94,E$3*12) -> 3521708.4 | F15: =INDEX(Monthly!$C$94:$BJ$94,F$3*12) -> 4663049.6
A16: Total liabilities & equity | B16: =INDEX(Monthly!$C$95:$BJ$95,B$3*12) -> 2318858.9 | C16: =INDEX(Monthly!$C$95:$BJ$95,C$3*12) -> 2669976.8 | D16: =INDEX(Monthly!$C$95:$BJ$95,D$3*12) -> 3256824.6 | E16: =INDEX(Monthly!$C$95:$BJ$95,E$3*12) -> 4111513.1 | F16: =INDEX(Monthly!$C$95:$BJ$95,F$3*12) -> 5271923.9
A17: Check: assets − liabilities − equity (must be 0) | B17: =INDEX(Monthly!$C$96:$BJ$96,B$3*12) -> 0 | C17: =INDEX(Monthly!$C$96:$BJ$96,C$3*12) -> 0 | D17: =INDEX(Monthly!$C$96:$BJ$96,D$3*12) -> 0 | E17: =INDEX(Monthly!$C$96:$BJ$96,E$3*12) -> 0 | F17: =INDEX(Monthly!$C$96:$BJ$96,F$3*12) -> 0

Sheet Monthly
A1: Monthly projection | D1: =HYPERLINK("#'Cover'!A1","◂ Contents") -> ◂ Contents
A2: $ unless stated; costs shown as negatives. Every period uses the same formula.
A3: Month | C3: M1 | D3: M2 | E3: M3 | F3: M4 | G3: M5 | H3: M6 | I3: M7 | J3: M8 | K3: M9 | L3: M10 | M3: M11 | N3: M12 | O3: M13 | P3: M14 | Q3: M15 | R3: M16 | S3: M17 | T3: M18 | U3: M19 | V3: M20 | W3: M21 | X3: M22 | Y3: M23 | Z3: M24 | AA3: M25 | AB3: M26 | AC3: M27 | AD3: M28 | AE3: M29 | AF3: M30 | AG3: M31 | AH3: M32 | AI3: M33 | AJ3: M34 | AK3: M35 | AL3: M36 | AM3: M37 | AN3: M38 | AO3: M39 | AP3: M40 | AQ3: M41 | AR3: M42 | AS3: M43 | AT3: M44 | AU3: M45 | AV3: M46 | AW3: M47 | AX3: M48 | AY3: M49 | AZ3: M50 | BA3: M51 | BB3: M52 | BC3: M53 | BD3: M54 | BE3: M55 | BF3: M56 | BG3: M57 | BH3: M58 | BI3: M59 | BJ3: M60
A4: Period # | C4: 1 | D4: 2 | E4: 3 | F4: 4 | G4: 5 | H4: 6 | I4: 7 | J4: 8 | K4: 9 | L4: 10 | M4: 11 | N4: 12 | O4: 13 | P4: 14 | Q4: 15 | R4: 16 | S4: 17 | T4: 18 | U4: 19 | V4: 20 | W4: 21 | X4: 22 | Y4: 23 | Z4: 24 | AA4: 25 | AB4: 26 | AC4: 27 | AD4: 28 | AE4: 29 | AF4: 30 | AG4: 31 | AH4: 32 | AI4: 33 | AJ4: 34 | AK4: 35 | AL4: 36 | AM4: 37 | AN4: 38 | AO4: 39 | AP4: 40 | AQ4: 41 | AR4: 42 | AS4: 43 | AT4: 44 | AU4: 45 | AV4: 46 | AW4: 47 | AX4: 48 | AY4: 49 | AZ4: 50 | BA4: 51 | BB4: 52 | BC4: 53 | BD4: 54 | BE4: 55 | BF4: 56 | BG4: 57 | BH4: 58 | BI4: 59 | BJ4: 60
A5: Year # | C5: =ROUNDUP(C4*1/12,0) -> 1 | D5: =ROUNDUP(D4*1/12,0) -> 1 | E5: =ROUNDUP(E4*1/12,0) -> 1 | F5: =ROUNDUP(F4*1/12,0) -> 1 | G5: =ROUNDUP(G4*1/12,0) -> 1 | H5: =ROUNDUP(H4*1/12,0) -> 1 | I5: =ROUNDUP(I4*1/12,0) -> 1 | J5: =ROUNDUP(J4*1/12,0) -> 1 | ... BJ5: =ROUNDUP(BJ4*1/12,0) -> 5
A7: Online channel
A8: Seasonality factor (averages 1.0 over a year) | C8: =IF(MOD(C$4-1,12)>=10,1+Inputs!$E$28,1-Inputs!$E$28/5) -> 0.94 | D8: =IF(MOD(D$4-1,12)>=10,1+Inputs!$E$28,1-Inputs!$E$28/5) -> 0.94 | E8: =IF(MOD(E$4-1,12)>=10,1+Inputs!$E$28,1-Inputs!$E$28/5) -> 0.94 | F8: =IF(MOD(F$4-1,12)>=10,1+Inputs!$E$28,1-Inputs!$E$28/5) -> 0.94 | G8: =IF(MOD(G$4-1,12)>=10,1+Inputs!$E$28,1-Inputs!$E$28/5) -> 0.94 | H8: =IF(MOD(H$4-1,12)>=10,1+Inputs!$E$28,1-Inputs!$E$28/5) -> 0.94 | I8: =IF(MOD(I$4-1,12)>=10,1+Inputs!$E$28,1-Inputs!$E$28/5) -> 0.94 | J8: =IF(MOD(J$4-1,12)>=10,1+Inputs!$E$28,1-Inputs!$E$28/5) -> 0.94 | ... BJ8: =IF(MOD(BJ$4-1,12)>=10,1+Inputs!$E$28,1-Inputs!$E$28/5) -> 1.3
A9: Website visits | C9: =Inputs!$E$7*(1+Inputs!$E$8)^(C$5-1)*1*C8 -> 75200 | D9: =Inputs!$E$7*(1+Inputs!$E$8)^(D$5-1)*1*D8 -> 75200 | E9: =Inputs!$E$7*(1+Inputs!$E$8)^(E$5-1)*1*E8 -> 75200 | F9: =Inputs!$E$7*(1+Inputs!$E$8)^(F$5-1)*1*F8 -> 75200 | G9: =Inputs!$E$7*(1+Inputs!$E$8)^(G$5-1)*1*G8 -> 75200 | H9: =Inputs!$E$7*(1+Inputs!$E$8)^(H$5-1)*1*H8 -> 75200 | I9: =Inputs!$E$7*(1+Inputs!$E$8)^(I$5-1)*1*I8 -> 75200 | J9: =Inputs!$E$7*(1+Inputs!$E$8)^(J$5-1)*1*J8 -> 75200 | ... BJ9: =Inputs!$E$7*(1+Inputs!$E$8)^(BJ$5-1)*1*BJ8 -> 253906.25
A10: Orders from visits | C10: =C9*Inputs!$E$9 -> 1804.8 | D10: =D9*Inputs!$E$9 -> 1804.8 | E10: =E9*Inputs!$E$9 -> 1804.8 | F10: =F9*Inputs!$E$9 -> 1804.8 | G10: =G9*Inputs!$E$9 -> 1804.8 | H10: =H9*Inputs!$E$9 -> 1804.8 | I10: =I9*Inputs!$E$9 -> 1804.8 | J10: =J9*Inputs!$E$9 -> 1804.8 | ... BJ10: =BJ9*Inputs!$E$9 -> 6093.75
A11: Orders from paid ads | C11: =-C32/MAX(1,Inputs!$E$15) -> 1785.7143 | D11: =-D32/MAX(1,Inputs!$E$15) -> 1785.7143 | E11: =-E32/MAX(1,Inputs!$E$15) -> 1785.7143 | F11: =-F32/MAX(1,Inputs!$E$15) -> 1785.7143 | G11: =-G32/MAX(1,Inputs!$E$15) -> 1785.7143 | H11: =-H32/MAX(1,Inputs!$E$15) -> 1785.7143 | I11: =-I32/MAX(1,Inputs!$E$15) -> 1785.7143 | J11: =-J32/MAX(1,Inputs!$E$15) -> 1785.7143 | ... BJ11: =-BJ32/MAX(1,Inputs!$E$15) -> 3702.8571
A12: Orders from new customers | C12: =C10+C11 -> 3590.5143 | D12: =D10+D11 -> 3590.5143 | E12: =E10+E11 -> 3590.5143 | F12: =F10+F11 -> 3590.5143 | G12: =G10+G11 -> 3590.5143 | H12: =H10+H11 -> 3590.5143 | I12: =I10+I11 -> 3590.5143 | J12: =J10+J11 -> 3590.5143 | ... BJ12: =BJ10+BJ11 -> 9796.6071
A13: Repeat orders from returning customers | C13: =C12*Inputs!$E$12 -> 1795.2571 | D13: =D12*Inputs!$E$12 -> 1795.2571 | E13: =E12*Inputs!$E$12 -> 1795.2571 | F13: =F12*Inputs!$E$12 -> 1795.2571 | G13: =G12*Inputs!$E$12 -> 1795.2571 | H13: =H12*Inputs!$E$12 -> 1795.2571 | I13: =I12*Inputs!$E$12 -> 1795.2571 | J13: =J12*Inputs!$E$12 -> 1795.2571 | ... BJ13: =BJ12*Inputs!$E$12 -> 4898.3036
A14: Online orders | C14: =C12+C13 -> 5385.7714 | D14: =D12+D13 -> 5385.7714 | E14: =E12+E13 -> 5385.7714 | F14: =F12+F13 -> 5385.7714 | G14: =G12+G13 -> 5385.7714 | H14: =H12+H13 -> 5385.7714 | I14: =I12+I13 -> 5385.7714 | J14: =J12+J13 -> 5385.7714 | ... BJ14: =BJ12+BJ13 -> 14694.911
A15: Average order value | C15: =Inputs!$E$10*(1+Inputs!$E$11)^(C$5-1) -> 75 | D15: =Inputs!$E$10*(1+Inputs!$E$11)^(D$5-1) -> 75 | E15: =Inputs!$E$10*(1+Inputs!$E$11)^(E$5-1) -> 75 | F15: =Inputs!$E$10*(1+Inputs!$E$11)^(F$5-1) -> 75 | G15: =Inputs!$E$10*(1+Inputs!$E$11)^(G$5-1) -> 75 | H15: =Inputs!$E$10*(1+Inputs!$E$11)^(H$5-1) -> 75 | I15: =Inputs!$E$10*(1+Inputs!$E$11)^(I$5-1) -> 75 | J15: =Inputs!$E$10*(1+Inputs!$E$11)^(J$5-1) -> 75 | ... BJ15: =Inputs!$E$10*(1+Inputs!$E$11)^(BJ$5-1) -> 81.182412
A16: Online gross sales | C16: =C14*C15 -> 403932.86 | D16: =D14*D15 -> 403932.86 | E16: =E14*E15 -> 403932.86 | F16: =F14*F15 -> 403932.86 | G16: =G14*G15 -> 403932.86 | H16: =H14*H15 -> 403932.86 | I16: =I14*I15 -> 403932.86 | J16: =J14*J15 -> 403932.86 | ... BJ16: =BJ14*BJ15 -> 1192968.3
A18: Store channel
A19: Stores open | C19: =Inputs!$E$18+Inputs!$E$19*(C$5-1) -> 2 | D19: =Inputs!$E$18+Inputs!$E$19*(D$5-1) -> 2 | E19: =Inputs!$E$18+Inputs!$E$19*(E$5-1) -> 2 | F19: =Inputs!$E$18+Inputs!$E$19*(F$5-1) -> 2 | G19: =Inputs!$E$18+Inputs!$E$19*(G$5-1) -> 2 | H19: =Inputs!$E$18+Inputs!$E$19*(H$5-1) -> 2 | I19: =Inputs!$E$18+Inputs!$E$19*(I$5-1) -> 2 | J19: =Inputs!$E$18+Inputs!$E$19*(J$5-1) -> 2 | ... BJ19: =Inputs!$E$18+Inputs!$E$19*(BJ$5-1) -> 6
A20: Store gross sales | C20: =C19*Inputs!$E$20*Inputs!$E$21*(1+Inputs!$E$22)^(C$5-1)/12*1*C8 -> 88125 | D20: =D19*Inputs!$E$20*Inputs!$E$21*(1+Inputs!$E$22)^(D$5-1)/12*1*D8 -> 88125 | E20: =E19*Inputs!$E$20*Inputs!$E$21*(1+Inputs!$E$22)^(E$5-1)/12*1*E8 -> 88125 | F20: =F19*Inputs!$E$20*Inputs!$E$21*(1+Inputs!$E$22)^(F$5-1)/12*1*F8 -> 88125 | G20: =G19*Inputs!$E$20*Inputs!$E$21*(1+Inputs!$E$22)^(G$5-1)/12*1*G8 -> 88125 | H20: =H19*Inputs!$E$20*Inputs!$E$21*(1+Inputs!$E$22)^(H$5-1)/12*1*H8 -> 88125 | I20: =I19*Inputs!$E$20*Inputs!$E$21*(1+Inputs!$E$22)^(I$5-1)/12*1*I8 -> 88125 | J20: =J19*Inputs!$E$20*Inputs!$E$21*(1+Inputs!$E$22)^(J$5-1)/12*1*J8 -> 88125 | ... BJ20: =BJ19*Inputs!$E$20*Inputs!$E$21*(1+Inputs!$E$22)^(BJ$5-1)/12*1*BJ8 -> 395764.26
A22: Net sales & product cost
A23: Gross sales | C23: =C16+C20 -> 492057.86 | D23: =D16+D20 -> 492057.86 | E23: =E16+E20 -> 492057.86 | F23: =F16+F20 -> 492057.86 | G23: =G16+G20 -> 492057.86 | H23: =H16+H20 -> 492057.86 | I23: =I16+I20 -> 492057.86 | J23: =J16+J20 -> 492057.86 | ... BJ23: =BJ16+BJ20 -> 1588732.6
A24: Returns & refunds | C24: =-C23*Inputs!$E$29 -> -49205.786 | D24: =-D23*Inputs!$E$29 -> -49205.786 | E24: =-E23*Inputs!$E$29 -> -49205.786 | F24: =-F23*Inputs!$E$29 -> -49205.786 | G24: =-G23*Inputs!$E$29 -> -49205.786 | H24: =-H23*Inputs!$E$29 -> -49205.786 | I24: =-I23*Inputs!$E$29 -> -49205.786 | J24: =-J23*Inputs!$E$29 -> -49205.786 | ... BJ24: =-BJ23*Inputs!$E$29 -> -158873.26
A25: Net sales | C25: =C23+C24 -> 442852.07 | D25: =D23+D24 -> 442852.07 | E25: =E23+E24 -> 442852.07 | F25: =F23+F24 -> 442852.07 | G25: =G23+G24 -> 442852.07 | H25: =H23+H24 -> 442852.07 | I25: =I23+I24 -> 442852.07 | J25: =J23+J24 -> 442852.07 | ... BJ25: =BJ23+BJ24 -> 1429859.3
A26: Product cost | C26: =-C25*Inputs!$E$30 -> -185997.87 | D26: =-D25*Inputs!$E$30 -> -185997.87 | E26: =-E25*Inputs!$E$30 -> -185997.87 | F26: =-F25*Inputs!$E$30 -> -185997.87 | G26: =-G25*Inputs!$E$30 -> -185997.87 | H26: =-H25*Inputs!$E$30 -> -185997.87 | I26: =-I25*Inputs!$E$30 -> -185997.87 | J26: =-J25*Inputs!$E$30 -> -185997.87 | ... BJ26: =-BJ25*Inputs!$E$30 -> -600540.91
A27: Gross profit | C27: =C25+C26 -> 256854.2 | D27: =D25+D26 -> 256854.2 | E27: =E25+E26 -> 256854.2 | F27: =F25+F26 -> 256854.2 | G27: =G25+G26 -> 256854.2 | H27: =H25+H26 -> 256854.2 | I27: =I25+I26 -> 256854.2 | J27: =J25+J26 -> 256854.2 | ... BJ27: =BJ25+BJ26 -> 829318.39
A29: Operating expenses
A30: Fulfilment & shipping | C30: =-C14*Inputs!$E$31 -> -43086.171 | D30: =-D14*Inputs!$E$31 -> -43086.171 | E30: =-E14*Inputs!$E$31 -> -43086.171 | F30: =-F14*Inputs!$E$31 -> -43086.171 | G30: =-G14*Inputs!$E$31 -> -43086.171 | H30: =-H14*Inputs!$E$31 -> -43086.171 | I30: =-I14*Inputs!$E$31 -> -43086.171 | J30: =-J14*Inputs!$E$31 -> -43086.171 | ... BJ30: =-BJ14*Inputs!$E$31 -> -117559.29
A31: Payment processing | C31: =-C25*Inputs!$E$32 -> -13285.562 | D31: =-D25*Inputs!$E$32 -> -13285.562 | E31: =-E25*Inputs!$E$32 -> -13285.562 | F31: =-F25*Inputs!$E$32 -> -13285.562 | G31: =-G25*Inputs!$E$32 -> -13285.562 | H31: =-H25*Inputs!$E$32 -> -13285.562 | I31: =-I25*Inputs!$E$32 -> -13285.562 | J31: =-J25*Inputs!$E$32 -> -13285.562 | ... BJ31: =-BJ25*Inputs!$E$32 -> -42895.779
A32: Paid ads | C32: =-Inputs!$E$13*(1+Inputs!$E$14)^(C$5-1)*1 -> -50000 | D32: =-Inputs!$E$13*(1+Inputs!$E$14)^(D$5-1)*1 -> -50000 | E32: =-Inputs!$E$13*(1+Inputs!$E$14)^(E$5-1)*1 -> -50000 | F32: =-Inputs!$E$13*(1+Inputs!$E$14)^(F$5-1)*1 -> -50000 | G32: =-Inputs!$E$13*(1+Inputs!$E$14)^(G$5-1)*1 -> -50000 | H32: =-Inputs!$E$13*(1+Inputs!$E$14)^(H$5-1)*1 -> -50000 | I32: =-Inputs!$E$13*(1+Inputs!$E$14)^(I$5-1)*1 -> -50000 | J32: =-Inputs!$E$13*(1+Inputs!$E$14)^(J$5-1)*1 -> -50000 | ... BJ32: =-Inputs!$E$13*(1+Inputs!$E$14)^(BJ$5-1)*1 -> -103680
A33: Payroll | C33: =Headcount!C19 -> -104841.67 | D33: =Headcount!D19 -> -104841.67 | E33: =Headcount!E19 -> -104841.67 | F33: =Headcount!F19 -> -104841.67 | G33: =Headcount!G19 -> -104841.67 | H33: =Headcount!H19 -> -104841.67 | I33: =Headcount!I19 -> -104841.67 | J33: =Headcount!J19 -> -104841.67 | ... BJ33: =Headcount!BJ19 -> -262990.96
A34: Store rent | C34: =-C19*Inputs!$E$20*Inputs!$E$23/12*1 -> -10000 | D34: =-D19*Inputs!$E$20*Inputs!$E$23/12*1 -> -10000 | E34: =-E19*Inputs!$E$20*Inputs!$E$23/12*1 -> -10000 | F34: =-F19*Inputs!$E$20*Inputs!$E$23/12*1 -> -10000 | G34: =-G19*Inputs!$E$20*Inputs!$E$23/12*1 -> -10000 | H34: =-H19*Inputs!$E$20*Inputs!$E$23/12*1 -> -10000 | I34: =-I19*Inputs!$E$20*Inputs!$E$23/12*1 -> -10000 | J34: =-J19*Inputs!$E$20*Inputs!$E$23/12*1 -> -10000 | ... BJ34: =-BJ19*Inputs!$E$20*Inputs!$E$23/12*1 -> -30000
A35: Store running costs | C35: =-C19*Inputs!$E$24*1 -> -5000 | D35: =-D19*Inputs!$E$24*1 -> -5000 | E35: =-E19*Inputs!$E$24*1 -> -5000 | F35: =-F19*Inputs!$E$24*1 -> -5000 | G35: =-G19*Inputs!$E$24*1 -> -5000 | H35: =-H19*Inputs!$E$24*1 -> -5000 | I35: =-I19*Inputs!$E$24*1 -> -5000 | J35: =-J19*Inputs!$E$24*1 -> -5000 | ... BJ35: =-BJ19*Inputs!$E$24*1 -> -15000
A36: Platform & software | C36: =-Inputs!$E$33*1 -> -4000 | D36: =-Inputs!$E$33*1 -> -4000 | E36: =-Inputs!$E$33*1 -> -4000 | F36: =-Inputs!$E$33*1 -> -4000 | G36: =-Inputs!$E$33*1 -> -4000 | H36: =-Inputs!$E$33*1 -> -4000 | I36: =-Inputs!$E$33*1 -> -4000 | J36: =-Inputs!$E$33*1 -> -4000 | ... BJ36: =-Inputs!$E$33*1 -> -4000
A37: Other G&A | C37: =-Inputs!$E$34*1 -> -8000 | D37: =-Inputs!$E$34*1 -> -8000 | E37: =-Inputs!$E$34*1 -> -8000 | F37: =-Inputs!$E$34*1 -> -8000 | G37: =-Inputs!$E$34*1 -> -8000 | H37: =-Inputs!$E$34*1 -> -8000 | I37: =-Inputs!$E$34*1 -> -8000 | J37: =-Inputs!$E$34*1 -> -8000 | ... BJ37: =-Inputs!$E$34*1 -> -8000
A38: Total operating expenses | C38: =C30+C31+C32+C33+C34+C35+C36+C37 -> -238213.4 | D38: =D30+D31+D32+D33+D34+D35+D36+D37 -> -238213.4 | E38: =E30+E31+E32+E33+E34+E35+E36+E37 -> -238213.4 | F38: =F30+F31+F32+F33+F34+F35+F36+F37 -> -238213.4 | G38: =G30+G31+G32+G33+G34+G35+G36+G37 -> -238213.4 | H38: =H30+H31+H32+H33+H34+H35+H36+H37 -> -238213.4 | I38: =I30+I31+I32+I33+I34+I35+I36+I37 -> -238213.4 | J38: =J30+J31+J32+J33+J34+J35+J36+J37 -> -238213.4 | ... BJ38: =BJ30+BJ31+BJ32+BJ33+BJ34+BJ35+BJ36+BJ37 -> -584126.03
A39: EBITDA | C39: =C27+C38 -> 18640.801 | D39: =D27+D38 -> 18640.801 | E39: =E27+E38 -> 18640.801 | F39: =F27+F38 -> 18640.801 | G39: =G27+G38 -> 18640.801 | H39: =H27+H38 -> 18640.801 | I39: =I27+I38 -> 18640.801 | J39: =J27+J38 -> 18640.801 | ... BJ39: =BJ27+BJ38 -> 245192.37
A41: Profit after depreciation, interest, tax
A42: EBIT | C42: =C39+C53 -> 14474.135 | D42: =D39+D53 -> 14474.135 | E42: =E39+E53 -> 14474.135 | F42: =F39+F53 -> 14474.135 | G42: =G39+G53 -> 14474.135 | H42: =H39+H53 -> 14474.135 | I42: =I39+I53 -> 14474.135 | J42: =J39+J53 -> 14474.135 | ... BJ42: =BJ39+BJ53 -> 233882.84
A43: Interest on loan (average balance after drawdown) | C43: =-(C58+C59+C61)/2*Inputs!$E$60/12 -> -3333.3333 | D43: =-(D58+D59+D61)/2*Inputs!$E$60/12 -> -3305.5556 | E43: =-(E58+E59+E61)/2*Inputs!$E$60/12 -> -3250 | F43: =-(F58+F59+F61)/2*Inputs!$E$60/12 -> -3194.4444 | G43: =-(G58+G59+G61)/2*Inputs!$E$60/12 -> -3138.8889 | H43: =-(H58+H59+H61)/2*Inputs!$E$60/12 -> -3083.3333 | I43: =-(I58+I59+I61)/2*Inputs!$E$60/12 -> -3027.7778 | J43: =-(J58+J59+J61)/2*Inputs!$E$60/12 -> -2972.2222 | ... BJ43: =-(BJ58+BJ59+BJ61)/2*Inputs!$E$60/12 -> -83.333333
A44: Pre-tax income | C44: =C42+C43 -> 11140.801 | D44: =D42+D43 -> 11168.579 | E44: =E42+E43 -> 11224.135 | F44: =F42+F43 -> 11279.69 | G44: =G42+G43 -> 11335.246 | H44: =H42+H43 -> 11390.801 | I44: =I42+I43 -> 11446.357 | J44: =J42+J43 -> 11501.912 | ... BJ44: =BJ42+BJ43 -> 233799.51
A45: Helper: cumulative pre-tax income | C45: =C44 -> 11140.801 | D45: =C45+D44 -> 22309.38 | E45: =D45+E44 -> 33533.515 | F45: =E45+F44 -> 44813.205 | G45: =F45+G44 -> 56148.45 | H45: =G45+H44 -> 67539.252 | I45: =H45+I44 -> 78985.608 | J45: =I45+J44 -> 90487.521 | K45: =J45+K44 -> 102044.99 | ... BJ45: =BI45+BJ44 -> 4003860.3
A46: Helper: cumulative taxable income (losses carried forward) | C46: =MAX(0,C45) -> 11140.801 | D46: =MAX(C46,D45) -> 22309.38 | E46: =MAX(D46,E45) -> 33533.515 | F46: =MAX(E46,F45) -> 44813.205 | G46: =MAX(F46,G45) -> 56148.45 | H46: =MAX(G46,H45) -> 67539.252 | I46: =MAX(H46,I45) -> 78985.608 | J46: =MAX(I46,J45) -> 90487.521 | K46: =MAX(J46,K45) -> 102044.99 | ... BJ46: =MAX(BI46,BJ45) -> 4003860.3
A47: Income tax | C47: =-C46*Inputs!$E$70 -> -2339.5682 | D47: =-(D46-C46)*Inputs!$E$70 -> -2345.4016 | E47: =-(E46-D46)*Inputs!$E$70 -> -2357.0682 | F47: =-(F46-E46)*Inputs!$E$70 -> -2368.7349 | G47: =-(G46-F46)*Inputs!$E$70 -> -2380.4016 | H47: =-(H46-G46)*Inputs!$E$70 -> -2392.0682 | I47: =-(I46-H46)*Inputs!$E$70 -> -2403.7349 | J47: =-(J46-I46)*Inputs!$E$70 -> -2415.4016 | K47: =-(K46-J46)*Inputs!$E$70 -> -2427.0682 | ... BJ47: =-(BJ46-BI46)*Inputs!$E$70 -> -49097.897
A48: Net income | C48: =C44+C47 -> 8801.2329 | D48: =D44+D47 -> 8823.1774 | E48: =E44+E47 -> 8867.0663 | F48: =F44+F47 -> 8910.9552 | G48: =G44+G47 -> 8954.8441 | H48: =H44+H47 -> 8998.7329 | I48: =I44+I47 -> 9042.6218 | J48: =J44+J47 -> 9086.5107 | ... BJ48: =BJ44+BJ47 -> 184701.61
A50: Fixed assets & capital spending
A51: Capital spending (start-up + store fit-outs) | C51: =IF(C$4=1,Inputs!$E$35+Inputs!$E$18*Inputs!$E$25,0)+IF(AND(C$4>1,MOD(C$4-1,12)=0),Inputs!$E$19*Inputs!$E$25,0) -> 350000 | D51: =IF(D$4=1,Inputs!$E$35+Inputs!$E$18*Inputs!$E$25,0)+IF(AND(D$4>1,MOD(D$4-1,12)=0),Inputs!$E$19*Inputs!$E$25,0) -> 0 | E51: =IF(E$4=1,Inputs!$E$35+Inputs!$E$18*Inputs!$E$25,0)+IF(AND(E$4>1,MOD(E$4-1,12)=0),Inputs!$E$19*Inputs!$E$25,0) -> 0 | F51: =IF(F$4=1,Inputs!$E$35+Inputs!$E$18*Inputs!$E$25,0)+IF(AND(F$4>1,MOD(F$4-1,12)=0),Inputs!$E$19*Inputs!$E$25,0) -> 0 | G51: =IF(G$4=1,Inputs!$E$35+Inputs!$E$18*Inputs!$E$25,0)+IF(AND(G$4>1,MOD(G$4-1,12)=0),Inputs!$E$19*Inputs!$E$25,0) -> 0 | H51: =IF(H$4=1,Inputs!$E$35+Inputs!$E$18*Inputs!$E$25,0)+IF(AND(H$4>1,MOD(H$4-1,12)=0),Inputs!$E$19*Inputs!$E$25,0) -> 0 | I51: =IF(I$4=1,Inputs!$E$35+Inputs!$E$18*Inputs!$E$25,0)+IF(AND(I$4>1,MOD(I$4-1,12)=0),Inputs!$E$19*Inputs!$E$25,0) -> 0 | J51: =IF(J$4=1,Inputs!$E$35+Inputs!$E$18*Inputs!$E$25,0)+IF(AND(J$4>1,MOD(J$4-1,12)=0),Inputs!$E$19*Inputs!$E$25,0) -> 0 | ... BJ51: =IF(BJ$4=1,Inputs!$E$35+Inputs!$E$18*Inputs!$E$25,0)+IF(AND(BJ$4>1,MOD(BJ$4-1,12)=0),Inputs!$E$19*Inputs!$E$25,0) -> 0
A52: Fixed assets at cost | C52: =C51 -> 350000 | D52: =C52+D51 -> 350000 | E52: =D52+E51 -> 350000 | F52: =E52+F51 -> 350000 | G52: =F52+G51 -> 350000 | H52: =G52+H51 -> 350000 | I52: =H52+I51 -> 350000 | J52: =I52+J51 -> 350000 | K52: =J52+K51 -> 350000 | ... BJ52: =BI52+BJ51 -> 950000
A53: Depreciation | C53: =-MIN(C52/MAX(1,Inputs!$E$69*12),C51) -> -4166.6667 | D53: =-MIN(D52/MAX(1,Inputs!$E$69*12),C55+D51) -> -4166.6667 | E53: =-MIN(E52/MAX(1,Inputs!$E$69*12),D55+E51) -> -4166.6667 | F53: =-MIN(F52/MAX(1,Inputs!$E$69*12),E55+F51) -> -4166.6667 | G53: =-MIN(G52/MAX(1,Inputs!$E$69*12),F55+G51) -> -4166.6667 | H53: =-MIN(H52/MAX(1,Inputs!$E$69*12),G55+H51) -> -4166.6667 | I53: =-MIN(I52/MAX(1,Inputs!$E$69*12),H55+I51) -> -4166.6667 | J53: =-MIN(J52/MAX(1,Inputs!$E$69*12),I55+J51) -> -4166.6667 | K53: =-MIN(K52/MAX(1,Inputs!$E$69*12),J55+K51) -> -4166.6667 | ... BJ53: =-MIN(BJ52/MAX(1,Inputs!$E$69*12),BI55+BJ51) -> -11309.524
A54: Accumulated depreciation | C54: =C53 -> -4166.6667 | D54: =C54+D53 -> -8333.3333 | E54: =D54+E53 -> -12500 | F54: =E54+F53 -> -16666.667 | G54: =F54+G53 -> -20833.333 | H54: =G54+H53 -> -25000 | I54: =H54+I53 -> -29166.667 | J54: =I54+J53 -> -33333.333 | K54: =J54+K53 -> -37500 | ... BJ54: =BI54+BJ53 -> -464285.71
A55: Net fixed assets | C55: =C52+C54 -> 345833.33 | D55: =D52+D54 -> 341666.67 | E55: =E52+E54 -> 337500 | F55: =F52+F54 -> 333333.33 | G55: =G52+G54 -> 329166.67 | H55: =H52+H54 -> 325000 | I55: =I52+I54 -> 320833.33 | J55: =J52+J54 -> 316666.67 | ... BJ55: =BJ52+BJ54 -> 485714.29
A57: Debt
A58: Loan — opening balance | C58: =0 -> 0 | D58: =C61 -> 500000 | E58: =D61 -> 491666.67 | F58: =E61 -> 483333.33 | G58: =F61 -> 475000 | H58: =G61 -> 466666.67 | I58: =H61 -> 458333.33 | J58: =I61 -> 450000 | K58: =J61 -> 441666.67 | ... BJ58: =BI61 -> 16666.667
A59: Loan drawdown | C59: =IF(C$4=1,Inputs!$E$59,0) -> 500000 | D59: =IF(D$4=1,Inputs!$E$59,0) -> 0 | E59: =IF(E$4=1,Inputs!$E$59,0) -> 0 | F59: =IF(F$4=1,Inputs!$E$59,0) -> 0 | G59: =IF(G$4=1,Inputs!$E$59,0) -> 0 | H59: =IF(H$4=1,Inputs!$E$59,0) -> 0 | I59: =IF(I$4=1,Inputs!$E$59,0) -> 0 | J59: =IF(J$4=1,Inputs!$E$59,0) -> 0 | ... BJ59: =IF(BJ$4=1,Inputs!$E$59,0) -> 0
A60: Loan repayment | C60: =-MIN(C58,Inputs!$E$59/MAX(1,Inputs!$E$61*12)) -> 0 | D60: =-MIN(D58,Inputs!$E$59/MAX(1,Inputs!$E$61*12)) -> -8333.3333 | E60: =-MIN(E58,Inputs!$E$59/MAX(1,Inputs!$E$61*12)) -> -8333.3333 | F60: =-MIN(F58,Inputs!$E$59/MAX(1,Inputs!$E$61*12)) -> -8333.3333 | G60: =-MIN(G58,Inputs!$E$59/MAX(1,Inputs!$E$61*12)) -> -8333.3333 | H60: =-MIN(H58,Inputs!$E$59/MAX(1,Inputs!$E$61*12)) -> -8333.3333 | I60: =-MIN(I58,Inputs!$E$59/MAX(1,Inputs!$E$61*12)) -> -8333.3333 | J60: =-MIN(J58,Inputs!$E$59/MAX(1,Inputs!$E$61*12)) -> -8333.3333 | ... BJ60: =-MIN(BJ58,Inputs!$E$59/MAX(1,Inputs!$E$61*12)) -> -8333.3333
A61: Loan — closing balance | C61: =C58+C59+C60 -> 500000 | D61: =D58+D59+D60 -> 491666.67 | E61: =E58+E59+E60 -> 483333.33 | F61: =F58+F59+F60 -> 475000 | G61: =G58+G59+G60 -> 466666.67 | H61: =H58+H59+H60 -> 458333.33 | I61: =I58+I59+I60 -> 450000 | J61: =J58+J59+J60 -> 441666.67 | ... BJ61: =BJ58+BJ59+BJ60 -> 8333.3333
A63: Working capital
A64: Accounts receivable | C64: =C25*Inputs!$E$64/30 -> 29523.471 | D64: =D25*Inputs!$E$64/30 -> 29523.471 | E64: =E25*Inputs!$E$64/30 -> 29523.471 | F64: =F25*Inputs!$E$64/30 -> 29523.471 | G64: =G25*Inputs!$E$64/30 -> 29523.471 | H64: =H25*Inputs!$E$64/30 -> 29523.471 | I64: =I25*Inputs!$E$64/30 -> 29523.471 | J64: =J25*Inputs!$E$64/30 -> 29523.471 | ... BJ64: =BJ25*Inputs!$E$64/30 -> 95323.953
A65: Inventory | C65: =-C26*Inputs!$E$65/30 -> 464994.67 | D65: =-D26*Inputs!$E$65/30 -> 464994.67 | E65: =-E26*Inputs!$E$65/30 -> 464994.67 | F65: =-F26*Inputs!$E$65/30 -> 464994.67 | G65: =-G26*Inputs!$E$65/30 -> 464994.67 | H65: =-H26*Inputs!$E$65/30 -> 464994.67 | I65: =-I26*Inputs!$E$65/30 -> 464994.67 | J65: =-J26*Inputs!$E$65/30 -> 464994.67 | ... BJ65: =-BJ26*Inputs!$E$65/30 -> 1501352.3
A66: Accounts payable | C66: =-C26*Inputs!$E$66/30 -> 185997.87 | D66: =-D26*Inputs!$E$66/30 -> 185997.87 | E66: =-E26*Inputs!$E$66/30 -> 185997.87 | F66: =-F26*Inputs!$E$66/30 -> 185997.87 | G66: =-G26*Inputs!$E$66/30 -> 185997.87 | H66: =-H26*Inputs!$E$66/30 -> 185997.87 | I66: =-I26*Inputs!$E$66/30 -> 185997.87 | J66: =-J26*Inputs!$E$66/30 -> 185997.87 | ... BJ66: =-BJ26*Inputs!$E$66/30 -> 600540.91
A67: (Increase) / decrease in receivables | C67: =-C64 -> -29523.471 | D67: =C64-D64 -> 0 | E67: =D64-E64 -> 0 | F67: =E64-F64 -> 0 | G67: =F64-G64 -> 0 | H67: =G64-H64 -> 0 | I67: =H64-I64 -> 0 | J67: =I64-J64 -> 0 | K67: =J64-K64 -> 0 | ... BJ67: =BI64-BJ64 -> 0
A68: (Increase) / decrease in inventory | C68: =-C65 -> -464994.67 | D68: =C65-D65 -> 0 | E68: =D65-E65 -> 0 | F68: =E65-F65 -> 0 | G68: =F65-G65 -> 0 | H68: =G65-H65 -> 0 | I68: =H65-I65 -> 0 | J68: =I65-J65 -> 0 | K68: =J65-K65 -> 0 | ... BJ68: =BI65-BJ65 -> 0
A69: Increase / (decrease) in payables | C69: =C66 -> 185997.87 | D69: =D66-C66 -> 0 | E69: =E66-D66 -> 0 | F69: =F66-E66 -> 0 | G69: =G66-F66 -> 0 | H69: =H66-G66 -> 0 | I69: =I66-H66 -> 0 | J69: =J66-I66 -> 0 | K69: =K66-J66 -> 0 | ... BJ69: =BJ66-BI66 -> 0
A71: Cash flow
A72: Operating cash flow | C72: =C48-C53+C67+C68+C69 -> -295552.38 | D72: =D48-D53+D67+D68+D69 -> 12989.844 | E72: =E48-E53+E67+E68+E69 -> 13033.733 | F72: =F48-F53+F67+F68+F69 -> 13077.622 | G72: =G48-G53+G67+G68+G69 -> 13121.511 | H72: =H48-H53+H67+H68+H69 -> 13165.4 | I72: =I48-I53+I67+I68+I69 -> 13209.288 | J72: =J48-J53+J67+J68+J69 -> 13253.177 | ... BJ72: =BJ48-BJ53+BJ67+BJ68+BJ69 -> 196011.14
A73: Investing cash flow (capex) | C73: =-C51 -> -350000 | D73: =-D51 -> 0 | E73: =-E51 -> 0 | F73: =-F51 -> 0 | G73: =-G51 -> 0 | H73: =-H51 -> 0 | I73: =-I51 -> 0 | J73: =-J51 -> 0 | ... BJ73: =-BJ51 -> 0
A74: Equity raised | C74: =IF(C$4=1,Inputs!$E$58,0) -> 1500000 | D74: =IF(D$4=1,Inputs!$E$58,0) -> 0 | E74: =IF(E$4=1,Inputs!$E$58,0) -> 0 | F74: =IF(F$4=1,Inputs!$E$58,0) -> 0 | G74: =IF(G$4=1,Inputs!$E$58,0) -> 0 | H74: =IF(H$4=1,Inputs!$E$58,0) -> 0 | I74: =IF(I$4=1,Inputs!$E$58,0) -> 0 | J74: =IF(J$4=1,Inputs!$E$58,0) -> 0 | ... BJ74: =IF(BJ$4=1,Inputs!$E$58,0) -> 0
A75: Financing cash flow | C75: =C74+C59+C60 -> 2000000 | D75: =D74+D59+D60 -> -8333.3333 | E75: =E74+E59+E60 -> -8333.3333 | F75: =F74+F59+F60 -> -8333.3333 | G75: =G74+G59+G60 -> -8333.3333 | H75: =H74+H59+H60 -> -8333.3333 | I75: =I74+I59+I60 -> -8333.3333 | J75: =J74+J59+J60 -> -8333.3333 | ... BJ75: =BJ74+BJ59+BJ60 -> -8333.3333
A76: Net cash flow | C76: =C72+C73+C75 -> 1354447.6 | D76: =D72+D73+D75 -> 4656.5107 | E76: =E72+E73+E75 -> 4700.3996 | F76: =F72+F73+F75 -> 4744.2885 | G76: =G72+G73+G75 -> 4788.1774 | H76: =H72+H73+H75 -> 4832.0663 | I76: =I72+I73+I75 -> 4875.9552 | J76: =J72+J73+J75 -> 4919.8441 | ... BJ76: =BJ72+BJ73+BJ75 -> 187677.8
A77: Opening cash | C77: =0 -> 0 | D77: =C78 -> 1354447.6 | E77: =D78 -> 1359104.1 | F77: =E78 -> 1363804.5 | G77: =F78 -> 1368548.8 | H77: =G78 -> 1373337 | I77: =H78 -> 1378169.1 | J77: =I78 -> 1383045 | K77: =J78 -> 1387964.9 | ... BJ77: =BI78 -> 3001855.6
A78: Closing cash | C78: =C77+C76 -> 1354447.6 | D78: =D77+D76 -> 1359104.1 | E78: =E77+E76 -> 1363804.5 | F78: =F77+F76 -> 1368548.8 | G78: =G77+G76 -> 1373337 | H78: =H77+H76 -> 1378169.1 | I78: =I77+I76 -> 1383045 | J78: =J77+J76 -> 1387964.9 | ... BJ78: =BJ77+BJ76 -> 3189533.4
A79: Helper: EBITDA positive (1/0) | C79: =IF(C39>0,1,0) -> 1 | D79: =IF(D39>0,1,0) -> 1 | E79: =IF(E39>0,1,0) -> 1 | F79: =IF(F39>0,1,0) -> 1 | G79: =IF(G39>0,1,0) -> 1 | H79: =IF(H39>0,1,0) -> 1 | I79: =IF(I39>0,1,0) -> 1 | J79: =IF(J39>0,1,0) -> 1 | ... BJ79: =IF(BJ39>0,1,0) -> 1
A81: Goal modules
A82: Helper: net income positive (1/0) | C82: =IF(C48>0,1,0) -> 1 | D82: =IF(D48>0,1,0) -> 1 | E82: =IF(E48>0,1,0) -> 1 | F82: =IF(F48>0,1,0) -> 1 | G82: =IF(G48>0,1,0) -> 1 | H82: =IF(H48>0,1,0) -> 1 | I82: =IF(I48>0,1,0) -> 1 | J82: =IF(J48>0,1,0) -> 1 | ... BJ82: =IF(BJ48>0,1,0) -> 1
A83: Cash flow before financing (operating + investing) | C83: =C72+C73 -> -645552.38 | D83: =D72+D73 -> 12989.844 | E83: =E72+E73 -> 13033.733 | F83: =F72+F73 -> 13077.622 | G83: =G72+G73 -> 13121.511 | H83: =H72+H73 -> 13165.4 | I83: =I72+I73 -> 13209.288 | J83: =J72+J73 -> 13253.177 | ... BJ83: =BJ72+BJ73 -> 196011.14
A84: Cumulative cash flow before financing | C84: =C83 -> -645552.38 | D84: =C84+D83 -> -632562.53 | E84: =D84+E83 -> -619528.8 | F84: =E84+F83 -> -606451.18 | G84: =F84+G83 -> -593329.67 | H84: =G84+H83 -> -580164.27 | I84: =H84+I83 -> -566954.98 | J84: =I84+J83 -> -553701.8 | K84: =J84+K83 -> -540404.74 | ... BJ84: =BI84+BJ83 -> 1681200
A85: Helper: lowest cumulative cash flow so far | C85: =C84 -> -645552.38 | D85: =MIN(C85,D84) -> -645552.38 | E85: =MIN(D85,E84) -> -645552.38 | F85: =MIN(E85,F84) -> -645552.38 | G85: =MIN(F85,G84) -> -645552.38 | H85: =MIN(G85,H84) -> -645552.38 | I85: =MIN(H85,I84) -> -645552.38 | J85: =MIN(I85,J84) -> -645552.38 | K85: =MIN(J85,K84) -> -645552.38 | ... BJ85: =MIN(BI85,BJ84) -> -645552.38
A86: Helper: investment paid back (1/0) | C86: =IF(AND(C84>=0,C85<0),1,0) -> 0 | D86: =IF(AND(D84>=0,D85<0),1,0) -> 0 | E86: =IF(AND(E84>=0,E85<0),1,0) -> 0 | F86: =IF(AND(F84>=0,F85<0),1,0) -> 0 | G86: =IF(AND(G84>=0,G85<0),1,0) -> 0 | H86: =IF(AND(H84>=0,H85<0),1,0) -> 0 | I86: =IF(AND(I84>=0,I85<0),1,0) -> 0 | J86: =IF(AND(J84>=0,J85<0),1,0) -> 0 | ... BJ86: =IF(AND(BJ84>=0,BJ85<0),1,0) -> 1
A87: Unlevered free cash flow (operating + after-tax interest − capex) | C87: =C72-C43*(1-Inputs!$E$70)+C73 -> -642919.04 | D87: =D72-D43*(1-Inputs!$E$70)+D73 -> 15601.233 | E87: =E72-E43*(1-Inputs!$E$70)+E73 -> 15601.233 | F87: =F72-F43*(1-Inputs!$E$70)+F73 -> 15601.233 | G87: =G72-G43*(1-Inputs!$E$70)+G73 -> 15601.233 | H87: =H72-H43*(1-Inputs!$E$70)+H73 -> 15601.233 | I87: =I72-I43*(1-Inputs!$E$70)+I73 -> 15601.233 | J87: =J72-J43*(1-Inputs!$E$70)+J73 -> 15601.233 | ... BJ87: =BJ72-BJ43*(1-Inputs!$E$70)+BJ73 -> 196076.97
A89: Balance sheet
A90: Paid-in capital | C90: =C74 -> 1500000 | D90: =C90+D74 -> 1500000 | E90: =D90+E74 -> 1500000 | F90: =E90+F74 -> 1500000 | G90: =F90+G74 -> 1500000 | H90: =G90+H74 -> 1500000 | I90: =H90+I74 -> 1500000 | J90: =I90+J74 -> 1500000 | K90: =J90+K74 -> 1500000 | ... BJ90: =BI90+BJ74 -> 1500000
A91: Retained earnings | C91: =C48 -> 8801.2329 | D91: =C91+D48 -> 17624.41 | E91: =D91+E48 -> 26491.477 | F91: =E91+F48 -> 35402.432 | G91: =F91+G48 -> 44357.276 | H91: =G91+H48 -> 53356.009 | I91: =H91+I48 -> 62398.631 | J91: =I91+J48 -> 71485.141 | K91: =J91+K48 -> 80615.541 | ... BJ91: =BI91+BJ48 -> 3163049.6
A92: Total assets | C92: =C78+C64+C65+C55 -> 2194799.1 | D92: =D78+D64+D65+D55 -> 2195288.9 | E92: =E78+E64+E65+E55 -> 2195822.7 | F92: =F78+F64+F65+F55 -> 2196400.3 | G92: =G78+G64+G65+G55 -> 2197021.8 | H92: =H78+H64+H65+H55 -> 2197687.2 | I92: =I78+I64+I65+I55 -> 2198396.5 | J92: =J78+J64+J65+J55 -> 2199149.7 | ... BJ92: =BJ78+BJ64+BJ65+BJ55 -> 5271923.9
A93: Total liabilities | C93: =C66+C61 -> 685997.87 | D93: =D66+D61 -> 677664.54 | E93: =E66+E61 -> 669331.2 | F93: =F66+F61 -> 660997.87 | G93: =G66+G61 -> 652664.54 | H93: =H66+H61 -> 644331.2 | I93: =I66+I61 -> 635997.87 | J93: =J66+J61 -> 627664.54 | ... BJ93: =BJ66+BJ61 -> 608874.24
A94: Total equity | C94: =C90+C91 -> 1508801.2 | D94: =D90+D91 -> 1517624.4 | E94: =E90+E91 -> 1526491.5 | F94: =F90+F91 -> 1535402.4 | G94: =G90+G91 -> 1544357.3 | H94: =H90+H91 -> 1553356 | I94: =I90+I91 -> 1562398.6 | J94: =J90+J91 -> 1571485.1 | ... BJ94: =BJ90+BJ91 -> 4663049.6
A95: Total liabilities & equity | C95: =C93+C94 -> 2194799.1 | D95: =D93+D94 -> 2195288.9 | E95: =E93+E94 -> 2195822.7 | F95: =F93+F94 -> 2196400.3 | G95: =G93+G94 -> 2197021.8 | H95: =H93+H94 -> 2197687.2 | I95: =I93+I94 -> 2198396.5 | J95: =J93+J94 -> 2199149.7 | ... BJ95: =BJ93+BJ94 -> 5271923.9
A96: Check: assets − liabilities − equity | C96: =C92-C95 -> 0 | D96: =D92-D95 -> 0 | E96: =E92-E95 -> 0 | F96: =F92-F95 -> 0 | G96: =G92-G95 -> 0 | H96: =H92-H95 -> 0 | I96: =I92-I95 -> 0 | J96: =J92-J95 -> 0 | ... BJ96: =BJ92-BJ95 -> 0

Sheet Headcount
A1: Headcount & payroll | D1: =HYPERLINK("#'Cover'!A1","◂ Contents") -> ◂ Contents
A2: $ unless stated; costs shown as negatives. Every period uses the same formula.
A3: Month | C3: M1 | D3: M2 | E3: M3 | F3: M4 | G3: M5 | H3: M6 | I3: M7 | J3: M8 | K3: M9 | L3: M10 | M3: M11 | N3: M12 | O3: M13 | P3: M14 | Q3: M15 | R3: M16 | S3: M17 | T3: M18 | U3: M19 | V3: M20 | W3: M21 | X3: M22 | Y3: M23 | Z3: M24 | AA3: M25 | AB3: M26 | AC3: M27 | AD3: M28 | AE3: M29 | AF3: M30 | AG3: M31 | AH3: M32 | AI3: M33 | AJ3: M34 | AK3: M35 | AL3: M36 | AM3: M37 | AN3: M38 | AO3: M39 | AP3: M40 | AQ3: M41 | AR3: M42 | AS3: M43 | AT3: M44 | AU3: M45 | AV3: M46 | AW3: M47 | AX3: M48 | AY3: M49 | AZ3: M50 | BA3: M51 | BB3: M52 | BC3: M53 | BD3: M54 | BE3: M55 | BF3: M56 | BG3: M57 | BH3: M58 | BI3: M59 | BJ3: M60
A4: Period # | C4: 1 | D4: 2 | E4: 3 | F4: 4 | G4: 5 | H4: 6 | I4: 7 | J4: 8 | K4: 9 | L4: 10 | M4: 11 | N4: 12 | O4: 13 | P4: 14 | Q4: 15 | R4: 16 | S4: 17 | T4: 18 | U4: 19 | V4: 20 | W4: 21 | X4: 22 | Y4: 23 | Z4: 24 | AA4: 25 | AB4: 26 | AC4: 27 | AD4: 28 | AE4: 29 | AF4: 30 | AG4: 31 | AH4: 32 | AI4: 33 | AJ4: 34 | AK4: 35 | AL4: 36 | AM4: 37 | AN4: 38 | AO4: 39 | AP4: 40 | AQ4: 41 | AR4: 42 | AS4: 43 | AT4: 44 | AU4: 45 | AV4: 46 | AW4: 47 | AX4: 48 | AY4: 49 | AZ4: 50 | BA4: 51 | BB4: 52 | BC4: 53 | BD4: 54 | BE4: 55 | BF4: 56 | BG4: 57 | BH4: 58 | BI4: 59 | BJ4: 60
A5: Year # | C5: =ROUNDUP(C4*1/12,0) -> 1 | D5: =ROUNDUP(D4*1/12,0) -> 1 | E5: =ROUNDUP(E4*1/12,0) -> 1 | F5: =ROUNDUP(F4*1/12,0) -> 1 | G5: =ROUNDUP(G4*1/12,0) -> 1 | H5: =ROUNDUP(H4*1/12,0) -> 1 | I5: =ROUNDUP(I4*1/12,0) -> 1 | J5: =ROUNDUP(J4*1/12,0) -> 1 | ... BJ5: =ROUNDUP(BJ4*1/12,0) -> 5
A7: Headcount (FTE)
A8: Operations & fulfilment — FTE | C8: =Inputs!$E$38*(1+Inputs!$E$40)^(C$5-1)*MAX(0,MIN(1,C$4*1-Inputs!$E$41+1))/1 -> 6 | D8: =Inputs!$E$38*(1+Inputs!$E$40)^(D$5-1)*MAX(0,MIN(1,D$4*1-Inputs!$E$41+1))/1 -> 6 | E8: =Inputs!$E$38*(1+Inputs!$E$40)^(E$5-1)*MAX(0,MIN(1,E$4*1-Inputs!$E$41+1))/1 -> 6 | F8: =Inputs!$E$38*(1+Inputs!$E$40)^(F$5-1)*MAX(0,MIN(1,F$4*1-Inputs!$E$41+1))/1 -> 6 | G8: =Inputs!$E$38*(1+Inputs!$E$40)^(G$5-1)*MAX(0,MIN(1,G$4*1-Inputs!$E$41+1))/1 -> 6 | H8: =Inputs!$E$38*(1+Inputs!$E$40)^(H$5-1)*MAX(0,MIN(1,H$4*1-Inputs!$E$41+1))/1 -> 6 | I8: =Inputs!$E$38*(1+Inputs!$E$40)^(I$5-1)*MAX(0,MIN(1,I$4*1-Inputs!$E$41+1))/1 -> 6 | J8: =Inputs!$E$38*(1+Inputs!$E$40)^(J$5-1)*MAX(0,MIN(1,J$4*1-Inputs!$E$41+1))/1 -> 6 | ... BJ8: =Inputs!$E$38*(1+Inputs!$E$40)^(BJ$5-1)*MAX(0,MIN(1,BJ$4*1-Inputs!$E$41+1))/1 -> 12.4416
A9: Marketing & e-commerce — FTE | C9: =Inputs!$E$42*(1+Inputs!$E$44)^(C$5-1)*MAX(0,MIN(1,C$4*1-Inputs!$E$45+1))/1 -> 4 | D9: =Inputs!$E$42*(1+Inputs!$E$44)^(D$5-1)*MAX(0,MIN(1,D$4*1-Inputs!$E$45+1))/1 -> 4 | E9: =Inputs!$E$42*(1+Inputs!$E$44)^(E$5-1)*MAX(0,MIN(1,E$4*1-Inputs!$E$45+1))/1 -> 4 | F9: =Inputs!$E$42*(1+Inputs!$E$44)^(F$5-1)*MAX(0,MIN(1,F$4*1-Inputs!$E$45+1))/1 -> 4 | G9: =Inputs!$E$42*(1+Inputs!$E$44)^(G$5-1)*MAX(0,MIN(1,G$4*1-Inputs!$E$45+1))/1 -> 4 | H9: =Inputs!$E$42*(1+Inputs!$E$44)^(H$5-1)*MAX(0,MIN(1,H$4*1-Inputs!$E$45+1))/1 -> 4 | I9: =Inputs!$E$42*(1+Inputs!$E$44)^(I$5-1)*MAX(0,MIN(1,I$4*1-Inputs!$E$45+1))/1 -> 4 | J9: =Inputs!$E$42*(1+Inputs!$E$44)^(J$5-1)*MAX(0,MIN(1,J$4*1-Inputs!$E$45+1))/1 -> 4 | ... BJ9: =Inputs!$E$42*(1+Inputs!$E$44)^(BJ$5-1)*MAX(0,MIN(1,BJ$4*1-Inputs!$E$45+1))/1 -> 8.2944
A10: Store staff — FTE | C10: =Inputs!$E$46*(1+Inputs!$E$48)^(C$5-1)*MAX(0,MIN(1,C$4*1-Inputs!$E$49+1))/1 -> 8 | D10: =Inputs!$E$46*(1+Inputs!$E$48)^(D$5-1)*MAX(0,MIN(1,D$4*1-Inputs!$E$49+1))/1 -> 8 | E10: =Inputs!$E$46*(1+Inputs!$E$48)^(E$5-1)*MAX(0,MIN(1,E$4*1-Inputs!$E$49+1))/1 -> 8 | F10: =Inputs!$E$46*(1+Inputs!$E$48)^(F$5-1)*MAX(0,MIN(1,F$4*1-Inputs!$E$49+1))/1 -> 8 | G10: =Inputs!$E$46*(1+Inputs!$E$48)^(G$5-1)*MAX(0,MIN(1,G$4*1-Inputs!$E$49+1))/1 -> 8 | H10: =Inputs!$E$46*(1+Inputs!$E$48)^(H$5-1)*MAX(0,MIN(1,H$4*1-Inputs!$E$49+1))/1 -> 8 | I10: =Inputs!$E$46*(1+Inputs!$E$48)^(I$5-1)*MAX(0,MIN(1,I$4*1-Inputs!$E$49+1))/1 -> 8 | J10: =Inputs!$E$46*(1+Inputs!$E$48)^(J$5-1)*MAX(0,MIN(1,J$4*1-Inputs!$E$49+1))/1 -> 8 | ... BJ10: =Inputs!$E$46*(1+Inputs!$E$48)^(BJ$5-1)*MAX(0,MIN(1,BJ$4*1-Inputs!$E$49+1))/1 -> 22.8488
A11: G&A (finance, admin) — FTE | C11: =Inputs!$E$50*(1+Inputs!$E$52)^(C$5-1)*MAX(0,MIN(1,C$4*1-Inputs!$E$53+1))/1 -> 3 | D11: =Inputs!$E$50*(1+Inputs!$E$52)^(D$5-1)*MAX(0,MIN(1,D$4*1-Inputs!$E$53+1))/1 -> 3 | E11: =Inputs!$E$50*(1+Inputs!$E$52)^(E$5-1)*MAX(0,MIN(1,E$4*1-Inputs!$E$53+1))/1 -> 3 | F11: =Inputs!$E$50*(1+Inputs!$E$52)^(F$5-1)*MAX(0,MIN(1,F$4*1-Inputs!$E$53+1))/1 -> 3 | G11: =Inputs!$E$50*(1+Inputs!$E$52)^(G$5-1)*MAX(0,MIN(1,G$4*1-Inputs!$E$53+1))/1 -> 3 | H11: =Inputs!$E$50*(1+Inputs!$E$52)^(H$5-1)*MAX(0,MIN(1,H$4*1-Inputs!$E$53+1))/1 -> 3 | I11: =Inputs!$E$50*(1+Inputs!$E$52)^(I$5-1)*MAX(0,MIN(1,I$4*1-Inputs!$E$53+1))/1 -> 3 | J11: =Inputs!$E$50*(1+Inputs!$E$52)^(J$5-1)*MAX(0,MIN(1,J$4*1-Inputs!$E$53+1))/1 -> 3 | ... BJ11: =Inputs!$E$50*(1+Inputs!$E$52)^(BJ$5-1)*MAX(0,MIN(1,BJ$4*1-Inputs!$E$53+1))/1 -> 5.2470187
A12: Total FTE | C12: =C8+C9+C10+C11 -> 21 | D12: =D8+D9+D10+D11 -> 21 | E12: =E8+E9+E10+E11 -> 21 | F12: =F8+F9+F10+F11 -> 21 | G12: =G8+G9+G10+G11 -> 21 | H12: =H8+H9+H10+H11 -> 21 | I12: =I8+I9+I10+I11 -> 21 | J12: =J8+J9+J10+J11 -> 21 | ... BJ12: =BJ8+BJ9+BJ10+BJ11 -> 48.831819
A14: Payroll cost (salary + taxes & benefits)
A15: Operations & fulfilment — payroll cost | C15: =-C8*Inputs!$E$39/12*1*(1+Inputs!$E$54)*(1+Inputs!$E$55)^(C$5-1) -> -28750 | D15: =-D8*Inputs!$E$39/12*1*(1+Inputs!$E$54)*(1+Inputs!$E$55)^(D$5-1) -> -28750 | E15: =-E8*Inputs!$E$39/12*1*(1+Inputs!$E$54)*(1+Inputs!$E$55)^(E$5-1) -> -28750 | F15: =-F8*Inputs!$E$39/12*1*(1+Inputs!$E$54)*(1+Inputs!$E$55)^(F$5-1) -> -28750 | G15: =-G8*Inputs!$E$39/12*1*(1+Inputs!$E$54)*(1+Inputs!$E$55)^(G$5-1) -> -28750 | H15: =-H8*Inputs!$E$39/12*1*(1+Inputs!$E$54)*(1+Inputs!$E$55)^(H$5-1) -> -28750 | I15: =-I8*Inputs!$E$39/12*1*(1+Inputs!$E$54)*(1+Inputs!$E$55)^(I$5-1) -> -28750 | J15: =-J8*Inputs!$E$39/12*1*(1+Inputs!$E$54)*(1+Inputs!$E$55)^(J$5-1) -> -28750 | ... BJ15: =-BJ8*Inputs!$E$39/12*1*(1+Inputs!$E$54)*(1+Inputs!$E$55)^(BJ$5-1) -> -67098.333
A16: Marketing & e-commerce — payroll cost | C16: =-C9*Inputs!$E$43/12*1*(1+Inputs!$E$54)*(1+Inputs!$E$55)^(C$5-1) -> -26833.333 | D16: =-D9*Inputs!$E$43/12*1*(1+Inputs!$E$54)*(1+Inputs!$E$55)^(D$5-1) -> -26833.333 | E16: =-E9*Inputs!$E$43/12*1*(1+Inputs!$E$54)*(1+Inputs!$E$55)^(E$5-1) -> -26833.333 | F16: =-F9*Inputs!$E$43/12*1*(1+Inputs!$E$54)*(1+Inputs!$E$55)^(F$5-1) -> -26833.333 | G16: =-G9*Inputs!$E$43/12*1*(1+Inputs!$E$54)*(1+Inputs!$E$55)^(G$5-1) -> -26833.333 | H16: =-H9*Inputs!$E$43/12*1*(1+Inputs!$E$54)*(1+Inputs!$E$55)^(H$5-1) -> -26833.333 | I16: =-I9*Inputs!$E$43/12*1*(1+Inputs!$E$54)*(1+Inputs!$E$55)^(I$5-1) -> -26833.333 | J16: =-J9*Inputs!$E$43/12*1*(1+Inputs!$E$54)*(1+Inputs!$E$55)^(J$5-1) -> -26833.333 | ... BJ16: =-BJ9*Inputs!$E$43/12*1*(1+Inputs!$E$54)*(1+Inputs!$E$55)^(BJ$5-1) -> -62625.111
A17: Store staff — payroll cost | C17: =-C10*Inputs!$E$47/12*1*(1+Inputs!$E$54)*(1+Inputs!$E$55)^(C$5-1) -> -29133.333 | D17: =-D10*Inputs!$E$47/12*1*(1+Inputs!$E$54)*(1+Inputs!$E$55)^(D$5-1) -> -29133.333 | E17: =-E10*Inputs!$E$47/12*1*(1+Inputs!$E$54)*(1+Inputs!$E$55)^(E$5-1) -> -29133.333 | F17: =-F10*Inputs!$E$47/12*1*(1+Inputs!$E$54)*(1+Inputs!$E$55)^(F$5-1) -> -29133.333 | G17: =-G10*Inputs!$E$47/12*1*(1+Inputs!$E$54)*(1+Inputs!$E$55)^(G$5-1) -> -29133.333 | H17: =-H10*Inputs!$E$47/12*1*(1+Inputs!$E$54)*(1+Inputs!$E$55)^(H$5-1) -> -29133.333 | I17: =-I10*Inputs!$E$47/12*1*(1+Inputs!$E$54)*(1+Inputs!$E$55)^(I$5-1) -> -29133.333 | J17: =-J10*Inputs!$E$47/12*1*(1+Inputs!$E$54)*(1+Inputs!$E$55)^(J$5-1) -> -29133.333 | ... BJ17: =-BJ10*Inputs!$E$47/12*1*(1+Inputs!$E$54)*(1+Inputs!$E$55)^(BJ$5-1) -> -93651.014
A18: G&A (finance, admin) — payroll cost | C18: =-C11*Inputs!$E$51/12*1*(1+Inputs!$E$54)*(1+Inputs!$E$55)^(C$5-1) -> -20125 | D18: =-D11*Inputs!$E$51/12*1*(1+Inputs!$E$54)*(1+Inputs!$E$55)^(D$5-1) -> -20125 | E18: =-E11*Inputs!$E$51/12*1*(1+Inputs!$E$54)*(1+Inputs!$E$55)^(E$5-1) -> -20125 | F18: =-F11*Inputs!$E$51/12*1*(1+Inputs!$E$54)*(1+Inputs!$E$55)^(F$5-1) -> -20125 | G18: =-G11*Inputs!$E$51/12*1*(1+Inputs!$E$54)*(1+Inputs!$E$55)^(G$5-1) -> -20125 | H18: =-H11*Inputs!$E$51/12*1*(1+Inputs!$E$54)*(1+Inputs!$E$55)^(H$5-1) -> -20125 | I18: =-I11*Inputs!$E$51/12*1*(1+Inputs!$E$54)*(1+Inputs!$E$55)^(I$5-1) -> -20125 | J18: =-J11*Inputs!$E$51/12*1*(1+Inputs!$E$54)*(1+Inputs!$E$55)^(J$5-1) -> -20125 | ... BJ18: =-BJ11*Inputs!$E$51/12*1*(1+Inputs!$E$54)*(1+Inputs!$E$55)^(BJ$5-1) -> -39616.504
A19: Total payroll | C19: =C15+C16+C17+C18 -> -104841.67 | D19: =D15+D16+D17+D18 -> -104841.67 | E19: =E15+E16+E17+E18 -> -104841.67 | F19: =F15+F16+F17+F18 -> -104841.67 | G19: =G15+G16+G17+G18 -> -104841.67 | H19: =H15+H16+H17+H18 -> -104841.67 | I19: =I15+I16+I17+I18 -> -104841.67 | J19: =J15+J16+J17+J18 -> -104841.67 | ... BJ19: =BJ15+BJ16+BJ17+BJ18 -> -262990.96

Sheet Scenario calc
A1: Scenario calculation — Low, Base and High side by side | D1: =HYPERLINK("#'Cover'!A1","◂ Contents") -> ◂ Contents
A2: The model's period calculation, copied three times; each copy reads its own Inputs column. Feeds the Scenarios sheet only.
A4: Low scenario — reads Inputs column B
A5: Month | C5: M1 | D5: M2 | E5: M3 | F5: M4 | G5: M5 | H5: M6 | I5: M7 | J5: M8 | K5: M9 | L5: M10 | M5: M11 | N5: M12 | O5: M13 | P5: M14 | Q5: M15 | R5: M16 | S5: M17 | T5: M18 | U5: M19 | V5: M20 | W5: M21 | X5: M22 | Y5: M23 | Z5: M24 | AA5: M25 | AB5: M26 | AC5: M27 | AD5: M28 | AE5: M29 | AF5: M30 | AG5: M31 | AH5: M32 | AI5: M33 | AJ5: M34 | AK5: M35 | AL5: M36 | AM5: M37 | AN5: M38 | AO5: M39 | AP5: M40 | AQ5: M41 | AR5: M42 | AS5: M43 | AT5: M44 | AU5: M45 | AV5: M46 | AW5: M47 | AX5: M48 | AY5: M49 | AZ5: M50 | BA5: M51 | BB5: M52 | BC5: M53 | BD5: M54 | BE5: M55 | BF5: M56 | BG5: M57 | BH5: M58 | BI5: M59 | BJ5: M60
A6: Period # | C6: 1 | D6: 2 | E6: 3 | F6: 4 | G6: 5 | H6: 6 | I6: 7 | J6: 8 | K6: 9 | L6: 10 | M6: 11 | N6: 12 | O6: 13 | P6: 14 | Q6: 15 | R6: 16 | S6: 17 | T6: 18 | U6: 19 | V6: 20 | W6: 21 | X6: 22 | Y6: 23 | Z6: 24 | AA6: 25 | AB6: 26 | AC6: 27 | AD6: 28 | AE6: 29 | AF6: 30 | AG6: 31 | AH6: 32 | AI6: 33 | AJ6: 34 | AK6: 35 | AL6: 36 | AM6: 37 | AN6: 38 | AO6: 39 | AP6: 40 | AQ6: 41 | AR6: 42 | AS6: 43 | AT6: 44 | AU6: 45 | AV6: 46 | AW6: 47 | AX6: 48 | AY6: 49 | AZ6: 50 | BA6: 51 | BB6: 52 | BC6: 53 | BD6: 54 | BE6: 55 | BF6: 56 | BG6: 57 | BH6: 58 | BI6: 59 | BJ6: 60
A7: Year # | C7: =ROUNDUP(C6*1/12,0) -> 1 | D7: =ROUNDUP(D6*1/12,0) -> 1 | E7: =ROUNDUP(E6*1/12,0) -> 1 | F7: =ROUNDUP(F6*1/12,0) -> 1 | G7: =ROUNDUP(G6*1/12,0) -> 1 | H7: =ROUNDUP(H6*1/12,0) -> 1 | I7: =ROUNDUP(I6*1/12,0) -> 1 | J7: =ROUNDUP(J6*1/12,0) -> 1 | ... BJ7: =ROUNDUP(BJ6*1/12,0) -> 5
A9: Online channel
A10: Seasonality factor (averages 1.0 over a year) | C10: =IF(MOD(C$6-1,12)>=10,1+Inputs!$B$28,1-Inputs!$B$28/5) -> 0.94 | D10: =IF(MOD(D$6-1,12)>=10,1+Inputs!$B$28,1-Inputs!$B$28/5) -> 0.94 | E10: =IF(MOD(E$6-1,12)>=10,1+Inputs!$B$28,1-Inputs!$B$28/5) -> 0.94 | F10: =IF(MOD(F$6-1,12)>=10,1+Inputs!$B$28,1-Inputs!$B$28/5) -> 0.94 | G10: =IF(MOD(G$6-1,12)>=10,1+Inputs!$B$28,1-Inputs!$B$28/5) -> 0.94 | H10: =IF(MOD(H$6-1,12)>=10,1+Inputs!$B$28,1-Inputs!$B$28/5) -> 0.94 | I10: =IF(MOD(I$6-1,12)>=10,1+Inputs!$B$28,1-Inputs!$B$28/5) -> 0.94 | J10: =IF(MOD(J$6-1,12)>=10,1+Inputs!$B$28,1-Inputs!$B$28/5) -> 0.94 | ... BJ10: =IF(MOD(BJ$6-1,12)>=10,1+Inputs!$B$28,1-Inputs!$B$28/5) -> 1.3
A11: Website visits | C11: =Inputs!$B$7*(1+Inputs!$B$8)^(C$7-1)*1*C10 -> 61100 | D11: =Inputs!$B$7*(1+Inputs!$B$8)^(D$7-1)*1*D10 -> 61100 | E11: =Inputs!$B$7*(1+Inputs!$B$8)^(E$7-1)*1*E10 -> 61100 | F11: =Inputs!$B$7*(1+Inputs!$B$8)^(F$7-1)*1*F10 -> 61100 | G11: =Inputs!$B$7*(1+Inputs!$B$8)^(G$7-1)*1*G10 -> 61100 | H11: =Inputs!$B$7*(1+Inputs!$B$8)^(H$7-1)*1*H10 -> 61100 | I11: =Inputs!$B$7*(1+Inputs!$B$8)^(I$7-1)*1*I10 -> 61100 | J11: =Inputs!$B$7*(1+Inputs!$B$8)^(J$7-1)*1*J10 -> 61100 | ... BJ11: =Inputs!$B$7*(1+Inputs!$B$8)^(BJ$7-1)*1*BJ10 -> 123716.45
A12: Orders from visits | C12: =C11*Inputs!$B$9 -> 1222 | D12: =D11*Inputs!$B$9 -> 1222 | E12: =E11*Inputs!$B$9 -> 1222 | F12: =F11*Inputs!$B$9 -> 1222 | G12: =G11*Inputs!$B$9 -> 1222 | H12: =H11*Inputs!$B$9 -> 1222 | I12: =I11*Inputs!$B$9 -> 1222 | J12: =J11*Inputs!$B$9 -> 1222 | ... BJ12: =BJ11*Inputs!$B$9 -> 2474.329
A13: Orders from paid ads | C13: =-C34/MAX(1,Inputs!$B$15) -> 1388.8889 | D13: =-D34/MAX(1,Inputs!$B$15) -> 1388.8889 | E13: =-E34/MAX(1,Inputs!$B$15) -> 1388.8889 | F13: =-F34/MAX(1,Inputs!$B$15) -> 1388.8889 | G13: =-G34/MAX(1,Inputs!$B$15) -> 1388.8889 | H13: =-H34/MAX(1,Inputs!$B$15) -> 1388.8889 | I13: =-I34/MAX(1,Inputs!$B$15) -> 1388.8889 | J13: =-J34/MAX(1,Inputs!$B$15) -> 1388.8889 | ... BJ13: =-BJ34/MAX(1,Inputs!$B$15) -> 2880
A14: Orders from new customers | C14: =C12+C13 -> 2610.8889 | D14: =D12+D13 -> 2610.8889 | E14: =E12+E13 -> 2610.8889 | F14: =F12+F13 -> 2610.8889 | G14: =G12+G13 -> 2610.8889 | H14: =H12+H13 -> 2610.8889 | I14: =I12+I13 -> 2610.8889 | J14: =J12+J13 -> 2610.8889 | ... BJ14: =BJ12+BJ13 -> 5354.329
A15: Repeat orders from returning customers | C15: =C14*Inputs!$B$12 -> 1044.3556 | D15: =D14*Inputs!$B$12 -> 1044.3556 | E15: =E14*Inputs!$B$12 -> 1044.3556 | F15: =F14*Inputs!$B$12 -> 1044.3556 | G15: =G14*Inputs!$B$12 -> 1044.3556 | H15: =H14*Inputs!$B$12 -> 1044.3556 | I15: =I14*Inputs!$B$12 -> 1044.3556 | J15: =J14*Inputs!$B$12 -> 1044.3556 | ... BJ15: =BJ14*Inputs!$B$12 -> 2141.7316
A16: Online orders | C16: =C14+C15 -> 3655.2444 | D16: =D14+D15 -> 3655.2444 | E16: =E14+E15 -> 3655.2444 | F16: =F14+F15 -> 3655.2444 | G16: =G14+G15 -> 3655.2444 | H16: =H14+H15 -> 3655.2444 | I16: =I14+I15 -> 3655.2444 | J16: =J14+J15 -> 3655.2444 | ... BJ16: =BJ14+BJ15 -> 7496.0606
A17: Average order value | C17: =Inputs!$B$10*(1+Inputs!$B$11)^(C$7-1) -> 65 | D17: =Inputs!$B$10*(1+Inputs!$B$11)^(D$7-1) -> 65 | E17: =Inputs!$B$10*(1+Inputs!$B$11)^(E$7-1) -> 65 | F17: =Inputs!$B$10*(1+Inputs!$B$11)^(F$7-1) -> 65 | G17: =Inputs!$B$10*(1+Inputs!$B$11)^(G$7-1) -> 65 | H17: =Inputs!$B$10*(1+Inputs!$B$11)^(H$7-1) -> 65 | I17: =Inputs!$B$10*(1+Inputs!$B$11)^(I$7-1) -> 65 | J17: =Inputs!$B$10*(1+Inputs!$B$11)^(J$7-1) -> 65 | ... BJ17: =Inputs!$B$10*(1+Inputs!$B$11)^(BJ$7-1) -> 65
A18: Online gross sales | C18: =C16*C17 -> 237590.89 | D18: =D16*D17 -> 237590.89 | E18: =E16*E17 -> 237590.89 | F18: =F16*F17 -> 237590.89 | G18: =G16*G17 -> 237590.89 | H18: =H16*H17 -> 237590.89 | I18: =I16*I17 -> 237590.89 | J18: =J16*J17 -> 237590.89 | ... BJ18: =BJ16*BJ17 -> 487243.94
A20: Store channel
A21: Stores open | C21: =Inputs!$B$18+Inputs!$B$19*(C$7-1) -> 2 | D21: =Inputs!$B$18+Inputs!$B$19*(D$7-1) -> 2 | E21: =Inputs!$B$18+Inputs!$B$19*(E$7-1) -> 2 | F21: =Inputs!$B$18+Inputs!$B$19*(F$7-1) -> 2 | G21: =Inputs!$B$18+Inputs!$B$19*(G$7-1) -> 2 | H21: =Inputs!$B$18+Inputs!$B$19*(H$7-1) -> 2 | I21: =Inputs!$B$18+Inputs!$B$19*(I$7-1) -> 2 | J21: =Inputs!$B$18+Inputs!$B$19*(J$7-1) -> 2 | ... BJ21: =Inputs!$B$18+Inputs!$B$19*(BJ$7-1) -> 6
A22: Store gross sales | C22: =C21*Inputs!$B$20*Inputs!$B$21*(1+Inputs!$B$22)^(C$7-1)/12*1*C10 -> 70500 | D22: =D21*Inputs!$B$20*Inputs!$B$21*(1+Inputs!$B$22)^(D$7-1)/12*1*D10 -> 70500 | E22: =E21*Inputs!$B$20*Inputs!$B$21*(1+Inputs!$B$22)^(E$7-1)/12*1*E10 -> 70500 | F22: =F21*Inputs!$B$20*Inputs!$B$21*(1+Inputs!$B$22)^(F$7-1)/12*1*F10 -> 70500 | G22: =G21*Inputs!$B$20*Inputs!$B$21*(1+Inputs!$B$22)^(G$7-1)/12*1*G10 -> 70500 | H22: =H21*Inputs!$B$20*Inputs!$B$21*(1+Inputs!$B$22)^(H$7-1)/12*1*H10 -> 70500 | I22: =I21*Inputs!$B$20*Inputs!$B$21*(1+Inputs!$B$22)^(I$7-1)/12*1*I10 -> 70500 | J22: =J21*Inputs!$B$20*Inputs!$B$21*(1+Inputs!$B$22)^(J$7-1)/12*1*J10 -> 70500 | ... BJ22: =BJ21*Inputs!$B$20*Inputs!$B$21*(1+Inputs!$B$22)^(BJ$7-1)/12*1*BJ10 -> 292500
A24: Net sales & product cost
A25: Gross sales | C25: =C18+C22 -> 308090.89 | D25: =D18+D22 -> 308090.89 | E25: =E18+E22 -> 308090.89 | F25: =F18+F22 -> 308090.89 | G25: =G18+G22 -> 308090.89 | H25: =H18+H22 -> 308090.89 | I25: =I18+I22 -> 308090.89 | J25: =J18+J22 -> 308090.89 | ... BJ25: =BJ18+BJ22 -> 779743.94
A26: Returns & refunds | C26: =-C25*Inputs!$B$29 -> -36970.907 | D26: =-D25*Inputs!$B$29 -> -36970.907 | E26: =-E25*Inputs!$B$29 -> -36970.907 | F26: =-F25*Inputs!$B$29 -> -36970.907 | G26: =-G25*Inputs!$B$29 -> -36970.907 | H26: =-H25*Inputs!$B$29 -> -36970.907 | I26: =-I25*Inputs!$B$29 -> -36970.907 | J26: =-J25*Inputs!$B$29 -> -36970.907 | ... BJ26: =-BJ25*Inputs!$B$29 -> -93569.273
A27: Net sales | C27: =C25+C26 -> 271119.98 | D27: =D25+D26 -> 271119.98 | E27: =E25+E26 -> 271119.98 | F27: =F25+F26 -> 271119.98 | G27: =G25+G26 -> 271119.98 | H27: =H25+H26 -> 271119.98 | I27: =I25+I26 -> 271119.98 | J27: =J25+J26 -> 271119.98 | ... BJ27: =BJ25+BJ26 -> 686174.67
A28: Product cost | C28: =-C27*Inputs!$B$30 -> -122003.99 | D28: =-D27*Inputs!$B$30 -> -122003.99 | E28: =-E27*Inputs!$B$30 -> -122003.99 | F28: =-F27*Inputs!$B$30 -> -122003.99 | G28: =-G27*Inputs!$B$30 -> -122003.99 | H28: =-H27*Inputs!$B$30 -> -122003.99 | I28: =-I27*Inputs!$B$30 -> -122003.99 | J28: =-J27*Inputs!$B$30 -> -122003.99 | ... BJ28: =-BJ27*Inputs!$B$30 -> -308778.6
A29: Gross profit | C29: =C27+C28 -> 149115.99 | D29: =D27+D28 -> 149115.99 | E29: =E27+E28 -> 149115.99 | F29: =F27+F28 -> 149115.99 | G29: =G27+G28 -> 149115.99 | H29: =H27+H28 -> 149115.99 | I29: =I27+I28 -> 149115.99 | J29: =J27+J28 -> 149115.99 | ... BJ29: =BJ27+BJ28 -> 377396.07
A31: Operating expenses
A32: Fulfilment & shipping | C32: =-C16*Inputs!$B$31 -> -32897.2 | D32: =-D16*Inputs!$B$31 -> -32897.2 | E32: =-E16*Inputs!$B$31 -> -32897.2 | F32: =-F16*Inputs!$B$31 -> -32897.2 | G32: =-G16*Inputs!$B$31 -> -32897.2 | H32: =-H16*Inputs!$B$31 -> -32897.2 | I32: =-I16*Inputs!$B$31 -> -32897.2 | J32: =-J16*Inputs!$B$31 -> -32897.2 | ... BJ32: =-BJ16*Inputs!$B$31 -> -67464.545
A33: Payment processing | C33: =-C27*Inputs!$B$32 -> -8133.5995 | D33: =-D27*Inputs!$B$32 -> -8133.5995 | E33: =-E27*Inputs!$B$32 -> -8133.5995 | F33: =-F27*Inputs!$B$32 -> -8133.5995 | G33: =-G27*Inputs!$B$32 -> -8133.5995 | H33: =-H27*Inputs!$B$32 -> -8133.5995 | I33: =-I27*Inputs!$B$32 -> -8133.5995 | J33: =-J27*Inputs!$B$32 -> -8133.5995 | ... BJ33: =-BJ27*Inputs!$B$32 -> -20585.24
A34: Paid ads | C34: =-Inputs!$B$13*(1+Inputs!$B$14)^(C$7-1)*1 -> -50000 | D34: =-Inputs!$B$13*(1+Inputs!$B$14)^(D$7-1)*1 -> -50000 | E34: =-Inputs!$B$13*(1+Inputs!$B$14)^(E$7-1)*1 -> -50000 | F34: =-Inputs!$B$13*(1+Inputs!$B$14)^(F$7-1)*1 -> -50000 | G34: =-Inputs!$B$13*(1+Inputs!$B$14)^(G$7-1)*1 -> -50000 | H34: =-Inputs!$B$13*(1+Inputs!$B$14)^(H$7-1)*1 -> -50000 | I34: =-Inputs!$B$13*(1+Inputs!$B$14)^(I$7-1)*1 -> -50000 | J34: =-Inputs!$B$13*(1+Inputs!$B$14)^(J$7-1)*1 -> -50000 | ... BJ34: =-Inputs!$B$13*(1+Inputs!$B$14)^(BJ$7-1)*1 -> -103680
A35: Payroll | C35: =C112 -> -104841.67 | D35: =D112 -> -104841.67 | E35: =E112 -> -104841.67 | F35: =F112 -> -104841.67 | G35: =G112 -> -104841.67 | H35: =H112 -> -104841.67 | I35: =I112 -> -104841.67 | J35: =J112 -> -104841.67 | ... BJ35: =BJ112 -> -262990.96
A36: Store rent | C36: =-C21*Inputs!$B$20*Inputs!$B$23/12*1 -> -10000 | D36: =-D21*Inputs!$B$20*Inputs!$B$23/12*1 -> -10000 | E36: =-E21*Inputs!$B$20*Inputs!$B$23/12*1 -> -10000 | F36: =-F21*Inputs!$B$20*Inputs!$B$23/12*1 -> -10000 | G36: =-G21*Inputs!$B$20*Inputs!$B$23/12*1 -> -10000 | H36: =-H21*Inputs!$B$20*Inputs!$B$23/12*1 -> -10000 | I36: =-I21*Inputs!$B$20*Inputs!$B$23/12*1 -> -10000 | J36: =-J21*Inputs!$B$20*Inputs!$B$23/12*1 -> -10000 | ... BJ36: =-BJ21*Inputs!$B$20*Inputs!$B$23/12*1 -> -30000
A37: Store running costs | C37: =-C21*Inputs!$B$24*1 -> -5000 | D37: =-D21*Inputs!$B$24*1 -> -5000 | E37: =-E21*Inputs!$B$24*1 -> -5000 | F37: =-F21*Inputs!$B$24*1 -> -5000 | G37: =-G21*Inputs!$B$24*1 -> -5000 | H37: =-H21*Inputs!$B$24*1 -> -5000 | I37: =-I21*Inputs!$B$24*1 -> -5000 | J37: =-J21*Inputs!$B$24*1 -> -5000 | ... BJ37: =-BJ21*Inputs!$B$24*1 -> -15000
A38: Platform & software | C38: =-Inputs!$B$33*1 -> -4000 | D38: =-Inputs!$B$33*1 -> -4000 | E38: =-Inputs!$B$33*1 -> -4000 | F38: =-Inputs!$B$33*1 -> -4000 | G38: =-Inputs!$B$33*1 -> -4000 | H38: =-Inputs!$B$33*1 -> -4000 | I38: =-Inputs!$B$33*1 -> -4000 | J38: =-Inputs!$B$33*1 -> -4000 | ... BJ38: =-Inputs!$B$33*1 -> -4000
A39: Other G&A | C39: =-Inputs!$B$34*1 -> -8000 | D39: =-Inputs!$B$34*1 -> -8000 | E39: =-Inputs!$B$34*1 -> -8000 | F39: =-Inputs!$B$34*1 -> -8000 | G39: =-Inputs!$B$34*1 -> -8000 | H39: =-Inputs!$B$34*1 -> -8000 | I39: =-Inputs!$B$34*1 -> -8000 | J39: =-Inputs!$B$34*1 -> -8000 | ... BJ39: =-Inputs!$B$34*1 -> -8000
A40: Total operating expenses | C40: =C32+C33+C34+C35+C36+C37+C38+C39 -> -222872.47 | D40: =D32+D33+D34+D35+D36+D37+D38+D39 -> -222872.47 | E40: =E32+E33+E34+E35+E36+E37+E38+E39 -> -222872.47 | F40: =F32+F33+F34+F35+F36+F37+F38+F39 -> -222872.47 | G40: =G32+G33+G34+G35+G36+G37+G38+G39 -> -222872.47 | H40: =H32+H33+H34+H35+H36+H37+H38+H39 -> -222872.47 | I40: =I32+I33+I34+I35+I36+I37+I38+I39 -> -222872.47 | J40: =J32+J33+J34+J35+J36+J37+J38+J39 -> -222872.47 | ... BJ40: =BJ32+BJ33+BJ34+BJ35+BJ36+BJ37+BJ38+BJ39 -> -511720.75
A41: EBITDA | C41: =C29+C40 -> -73756.476 | D41: =D29+D40 -> -73756.476 | E41: =E29+E40 -> -73756.476 | F41: =F29+F40 -> -73756.476 | G41: =G29+G40 -> -73756.476 | H41: =H29+H40 -> -73756.476 | I41: =I29+I40 -> -73756.476 | J41: =J29+J40 -> -73756.476 | ... BJ41: =BJ29+BJ40 -> -134324.68
A43: Profit after depreciation, interest, tax
A44: EBIT | C44: =C41+C55 -> -77923.143 | D44: =D41+D55 -> -77923.143 | E44: =E41+E55 -> -77923.143 | F44: =F41+F55 -> -77923.143 | G44: =G41+G55 -> -77923.143 | H44: =H41+H55 -> -77923.143 | I44: =I41+I55 -> -77923.143 | J44: =J41+J55 -> -77923.143 | ... BJ44: =BJ41+BJ55 -> -145634.21
A45: Interest on loan (average balance after drawdown) | C45: =-(C60+C61+C63)/2*Inputs!$B$60/12 -> -3333.3333 | D45: =-(D60+D61+D63)/2*Inputs!$B$60/12 -> -3305.5556 | E45: =-(E60+E61+E63)/2*Inputs!$B$60/12 -> -3250 | F45: =-(F60+F61+F63)/2*Inputs!$B$60/12 -> -3194.4444 | G45: =-(G60+G61+G63)/2*Inputs!$B$60/12 -> -3138.8889 | H45: =-(H60+H61+H63)/2*Inputs!$B$60/12 -> -3083.3333 | I45: =-(I60+I61+I63)/2*Inputs!$B$60/12 -> -3027.7778 | J45: =-(J60+J61+J63)/2*Inputs!$B$60/12 -> -2972.2222 | ... BJ45: =-(BJ60+BJ61+BJ63)/2*Inputs!$B$60/12 -> -83.333333
A46: Pre-tax income | C46: =C44+C45 -> -81256.476 | D46: =D44+D45 -> -81228.698 | E46: =E44+E45 -> -81173.143 | F46: =F44+F45 -> -81117.587 | G46: =G44+G45 -> -81062.031 | H46: =H44+H45 -> -81006.476 | I46: =I44+I45 -> -80950.92 | J46: =J44+J45 -> -80895.365 | ... BJ46: =BJ44+BJ45 -> -145717.54
A47: Helper: cumulative pre-tax income | C47: =C46 -> -81256.476 | D47: =C47+D46 -> -162485.17 | E47: =D47+E46 -> -243658.32 | F47: =E47+F46 -> -324775.9 | G47: =F47+G46 -> -405837.94 | H47: =G47+H46 -> -486844.41 | I47: =H47+I46 -> -567795.33 | J47: =I47+J46 -> -648690.7 | K47: =J47+K46 -> -729530.51 | ... BJ47: =BI47+BJ46 -> -7543588.7
A48: Helper: cumulative taxable income (losses carried forward) | C48: =MAX(0,C47) -> 0 | D48: =MAX(C48,D47) -> 0 | E48: =MAX(D48,E47) -> 0 | F48: =MAX(E48,F47) -> 0 | G48: =MAX(F48,G47) -> 0 | H48: =MAX(G48,H47) -> 0 | I48: =MAX(H48,I47) -> 0 | J48: =MAX(I48,J47) -> 0 | K48: =MAX(J48,K47) -> 0 | ... BJ48: =MAX(BI48,BJ47) -> 0
A49: Income tax | C49: =-C48*Inputs!$B$70 -> 0 | D49: =-(D48-C48)*Inputs!$B$70 -> 0 | E49: =-(E48-D48)*Inputs!$B$70 -> 0 | F49: =-(F48-E48)*Inputs!$B$70 -> 0 | G49: =-(G48-F48)*Inputs!$B$70 -> 0 | H49: =-(H48-G48)*Inputs!$B$70 -> 0 | I49: =-(I48-H48)*Inputs!$B$70 -> 0 | J49: =-(J48-I48)*Inputs!$B$70 -> 0 | K49: =-(K48-J48)*Inputs!$B$70 -> 0 | ... BJ49: =-(BJ48-BI48)*Inputs!$B$70 -> 0
A50: Net income | C50: =C46+C49 -> -81256.476 | D50: =D46+D49 -> -81228.698 | E50: =E46+E49 -> -81173.143 | F50: =F46+F49 -> -81117.587 | G50: =G46+G49 -> -81062.031 | H50: =H46+H49 -> -81006.476 | I50: =I46+I49 -> -80950.92 | J50: =J46+J49 -> -80895.365 | ... BJ50: =BJ46+BJ49 -> -145717.54
A52: Fixed assets & capital spending
A53: Capital spending (start-up + store fit-outs) | C53: =IF(C$6=1,Inputs!$B$35+Inputs!$B$18*Inputs!$B$25,0)+IF(AND(C$6>1,MOD(C$6-1,12)=0),Inputs!$B$19*Inputs!$B$25,0) -> 350000 | D53: =IF(D$6=1,Inputs!$B$35+Inputs!$B$18*Inputs!$B$25,0)+IF(AND(D$6>1,MOD(D$6-1,12)=0),Inputs!$B$19*Inputs!$B$25,0) -> 0 | E53: =IF(E$6=1,Inputs!$B$35+Inputs!$B$18*Inputs!$B$25,0)+IF(AND(E$6>1,MOD(E$6-1,12)=0),Inputs!$B$19*Inputs!$B$25,0) -> 0 | F53: =IF(F$6=1,Inputs!$B$35+Inputs!$B$18*Inputs!$B$25,0)+IF(AND(F$6>1,MOD(F$6-1,12)=0),Inputs!$B$19*Inputs!$B$25,0) -> 0 | G53: =IF(G$6=1,Inputs!$B$35+Inputs!$B$18*Inputs!$B$25,0)+IF(AND(G$6>1,MOD(G$6-1,12)=0),Inputs!$B$19*Inputs!$B$25,0) -> 0 | H53: =IF(H$6=1,Inputs!$B$35+Inputs!$B$18*Inputs!$B$25,0)+IF(AND(H$6>1,MOD(H$6-1,12)=0),Inputs!$B$19*Inputs!$B$25,0) -> 0 | I53: =IF(I$6=1,Inputs!$B$35+Inputs!$B$18*Inputs!$B$25,0)+IF(AND(I$6>1,MOD(I$6-1,12)=0),Inputs!$B$19*Inputs!$B$25,0) -> 0 | J53: =IF(J$6=1,Inputs!$B$35+Inputs!$B$18*Inputs!$B$25,0)+IF(AND(J$6>1,MOD(J$6-1,12)=0),Inputs!$B$19*Inputs!$B$25,0) -> 0 | ... BJ53: =IF(BJ$6=1,Inputs!$B$35+Inputs!$B$18*Inputs!$B$25,0)+IF(AND(BJ$6>1,MOD(BJ$6-1,12)=0),Inputs!$B$19*Inputs!$B$25,0) -> 0
A54: Fixed assets at cost | C54: =C53 -> 350000 | D54: =C54+D53 -> 350000 | E54: =D54+E53 -> 350000 | F54: =E54+F53 -> 350000 | G54: =F54+G53 -> 350000 | H54: =G54+H53 -> 350000 | I54: =H54+I53 -> 350000 | J54: =I54+J53 -> 350000 | K54: =J54+K53 -> 350000 | ... BJ54: =BI54+BJ53 -> 950000
A55: Depreciation | C55: =-MIN(C54/MAX(1,Inputs!$B$69*12),C53) -> -4166.6667 | D55: =-MIN(D54/MAX(1,Inputs!$B$69*12),C57+D53) -> -4166.6667 | E55: =-MIN(E54/MAX(1,Inputs!$B$69*12),D57+E53) -> -4166.6667 | F55: =-MIN(F54/MAX(1,Inputs!$B$69*12),E57+F53) -> -4166.6667 | G55: =-MIN(G54/MAX(1,Inputs!$B$69*12),F57+G53) -> -4166.6667 | H55: =-MIN(H54/MAX(1,Inputs!$B$69*12),G57+H53) -> -4166.6667 | I55: =-MIN(I54/MAX(1,Inputs!$B$69*12),H57+I53) -> -4166.6667 | J55: =-MIN(J54/MAX(1,Inputs!$B$69*12),I57+J53) -> -4166.6667 | K55: =-MIN(K54/MAX(1,Inputs!$B$69*12),J57+K53) -> -4166.6667 | ... BJ55: =-MIN(BJ54/MAX(1,Inputs!$B$69*12),BI57+BJ53) -> -11309.524
A56: Accumulated depreciation | C56: =C55 -> -4166.6667 | D56: =C56+D55 -> -8333.3333 | E56: =D56+E55 -> -12500 | F56: =E56+F55 -> -16666.667 | G56: =F56+G55 -> -20833.333 | H56: =G56+H55 -> -25000 | I56: =H56+I55 -> -29166.667 | J56: =I56+J55 -> -33333.333 | K56: =J56+K55 -> -37500 | ... BJ56: =BI56+BJ55 -> -464285.71
A57: Net fixed assets | C57: =C54+C56 -> 345833.33 | D57: =D54+D56 -> 341666.67 | E57: =E54+E56 -> 337500 | F57: =F54+F56 -> 333333.33 | G57: =G54+G56 -> 329166.67 | H57: =H54+H56 -> 325000 | I57: =I54+I56 -> 320833.33 | J57: =J54+J56 -> 316666.67 | ... BJ57: =BJ54+BJ56 -> 485714.29
A59: Debt
A60: Loan — opening balance | C60: =0 -> 0 | D60: =C63 -> 500000 | E60: =D63 -> 491666.67 | F60: =E63 -> 483333.33 | G60: =F63 -> 475000 | H60: =G63 -> 466666.67 | I60: =H63 -> 458333.33 | J60: =I63 -> 450000 | K60: =J63 -> 441666.67 | ... BJ60: =BI63 -> 16666.667
A61: Loan drawdown | C61: =IF(C$6=1,Inputs!$B$59,0) -> 500000 | D61: =IF(D$6=1,Inputs!$B$59,0) -> 0 | E61: =IF(E$6=1,Inputs!$B$59,0) -> 0 | F61: =IF(F$6=1,Inputs!$B$59,0) -> 0 | G61: =IF(G$6=1,Inputs!$B$59,0) -> 0 | H61: =IF(H$6=1,Inputs!$B$59,0) -> 0 | I61: =IF(I$6=1,Inputs!$B$59,0) -> 0 | J61: =IF(J$6=1,Inputs!$B$59,0) -> 0 | ... BJ61: =IF(BJ$6=1,Inputs!$B$59,0) -> 0
A62: Loan repayment | C62: =-MIN(C60,Inputs!$B$59/MAX(1,Inputs!$B$61*12)) -> 0 | D62: =-MIN(D60,Inputs!$B$59/MAX(1,Inputs!$B$61*12)) -> -8333.3333 | E62: =-MIN(E60,Inputs!$B$59/MAX(1,Inputs!$B$61*12)) -> -8333.3333 | F62: =-MIN(F60,Inputs!$B$59/MAX(1,Inputs!$B$61*12)) -> -8333.3333 | G62: =-MIN(G60,Inputs!$B$59/MAX(1,Inputs!$B$61*12)) -> -8333.3333 | H62: =-MIN(H60,Inputs!$B$59/MAX(1,Inputs!$B$61*12)) -> -8333.3333 | I62: =-MIN(I60,Inputs!$B$59/MAX(1,Inputs!$B$61*12)) -> -8333.3333 | J62: =-MIN(J60,Inputs!$B$59/MAX(1,Inputs!$B$61*12)) -> -8333.3333 | ... BJ62: =-MIN(BJ60,Inputs!$B$59/MAX(1,Inputs!$B$61*12)) -> -8333.3333
A63: Loan — closing balance | C63: =C60+C61+C62 -> 500000 | D63: =D60+D61+D62 -> 491666.67 | E63: =E60+E61+E62 -> 483333.33 | F63: =F60+F61+F62 -> 475000 | G63: =G60+G61+G62 -> 466666.67 | H63: =H60+H61+H62 -> 458333.33 | I63: =I60+I61+I62 -> 450000 | J63: =J60+J61+J62 -> 441666.67 | ... BJ63: =BJ60+BJ61+BJ62 -> 8333.3333
A65: Working capital
A66: Accounts receivable | C66: =C27*Inputs!$B$64/30 -> 18074.665 | D66: =D27*Inputs!$B$64/30 -> 18074.665 | E66: =E27*Inputs!$B$64/30 -> 18074.665 | F66: =F27*Inputs!$B$64/30 -> 18074.665 | G66: =G27*Inputs!$B$64/30 -> 18074.665 | H66: =H27*Inputs!$B$64/30 -> 18074.665 | I66: =I27*Inputs!$B$64/30 -> 18074.665 | J66: =J27*Inputs!$B$64/30 -> 18074.665 | ... BJ66: =BJ27*Inputs!$B$64/30 -> 45744.978
A67: Inventory | C67: =-C28*Inputs!$B$65/30 -> 305009.98 | D67: =-D28*Inputs!$B$65/30 -> 305009.98 | E67: =-E28*Inputs!$B$65/30 -> 305009.98 | F67: =-F28*Inputs!$B$65/30 -> 305009.98 | G67: =-G28*Inputs!$B$65/30 -> 305009.98 | H67: =-H28*Inputs!$B$65/30 -> 305009.98 | I67: =-I28*Inputs!$B$65/30 -> 305009.98 | J67: =-J28*Inputs!$B$65/30 -> 305009.98 | ... BJ67: =-BJ28*Inputs!$B$65/30 -> 771946.5
A68: Accounts payable | C68: =-C28*Inputs!$B$66/30 -> 122003.99 | D68: =-D28*Inputs!$B$66/30 -> 122003.99 | E68: =-E28*Inputs!$B$66/30 -> 122003.99 | F68: =-F28*Inputs!$B$66/30 -> 122003.99 | G68: =-G28*Inputs!$B$66/30 -> 122003.99 | H68: =-H28*Inputs!$B$66/30 -> 122003.99 | I68: =-I28*Inputs!$B$66/30 -> 122003.99 | J68: =-J28*Inputs!$B$66/30 -> 122003.99 | ... BJ68: =-BJ28*Inputs!$B$66/30 -> 308778.6
A69: (Increase) / decrease in receivables | C69: =-C66 -> -18074.665 | D69: =C66-D66 -> 0 | E69: =D66-E66 -> 0 | F69: =E66-F66 -> 0 | G69: =F66-G66 -> 0 | H69: =G66-H66 -> 0 | I69: =H66-I66 -> 0 | J69: =I66-J66 -> 0 | K69: =J66-K66 -> 0 | ... BJ69: =BI66-BJ66 -> 0
A70: (Increase) / decrease in inventory | C70: =-C67 -> -305009.98 | D70: =C67-D67 -> 0 | E70: =D67-E67 -> 0 | F70: =E67-F67 -> 0 | G70: =F67-G67 -> 0 | H70: =G67-H67 -> 0 | I70: =H67-I67 -> 0 | J70: =I67-J67 -> 0 | K70: =J67-K67 -> 0 | ... BJ70: =BI67-BJ67 -> 0
A71: Increase / (decrease) in payables | C71: =C68 -> 122003.99 | D71: =D68-C68 -> 0 | E71: =E68-D68 -> 0 | F71: =F68-E68 -> 0 | G71: =G68-F68 -> 0 | H71: =H68-G68 -> 0 | I71: =I68-H68 -> 0 | J71: =J68-I68 -> 0 | K71: =K68-J68 -> 0 | ... BJ71: =BJ68-BI68 -> 0
A73: Cash flow
A74: Operating cash flow | C74: =C50-C55+C69+C70+C71 -> -278170.46 | D74: =D50-D55+D69+D70+D71 -> -77062.031 | E74: =E50-E55+E69+E70+E71 -> -77006.476 | F74: =F50-F55+F69+F70+F71 -> -76950.92 | G74: =G50-G55+G69+G70+G71 -> -76895.365 | H74: =H50-H55+H69+H70+H71 -> -76839.809 | I74: =I50-I55+I69+I70+I71 -> -76784.254 | J74: =J50-J55+J69+J70+J71 -> -76728.698 | ... BJ74: =BJ50-BJ55+BJ69+BJ70+BJ71 -> -134408.01
A75: Investing cash flow (capex) | C75: =-C53 -> -350000 | D75: =-D53 -> 0 | E75: =-E53 -> 0 | F75: =-F53 -> 0 | G75: =-G53 -> 0 | H75: =-H53 -> 0 | I75: =-I53 -> 0 | J75: =-J53 -> 0 | ... BJ75: =-BJ53 -> 0
A76: Equity raised | C76: =IF(C$6=1,Inputs!$B$58,0) -> 1500000 | D76: =IF(D$6=1,Inputs!$B$58,0) -> 0 | E76: =IF(E$6=1,Inputs!$B$58,0) -> 0 | F76: =IF(F$6=1,Inputs!$B$58,0) -> 0 | G76: =IF(G$6=1,Inputs!$B$58,0) -> 0 | H76: =IF(H$6=1,Inputs!$B$58,0) -> 0 | I76: =IF(I$6=1,Inputs!$B$58,0) -> 0 | J76: =IF(J$6=1,Inputs!$B$58,0) -> 0 | ... BJ76: =IF(BJ$6=1,Inputs!$B$58,0) -> 0
A77: Financing cash flow | C77: =C76+C61+C62 -> 2000000 | D77: =D76+D61+D62 -> -8333.3333 | E77: =E76+E61+E62 -> -8333.3333 | F77: =F76+F61+F62 -> -8333.3333 | G77: =G76+G61+G62 -> -8333.3333 | H77: =H76+H61+H62 -> -8333.3333 | I77: =I76+I61+I62 -> -8333.3333 | J77: =J76+J61+J62 -> -8333.3333 | ... BJ77: =BJ76+BJ61+BJ62 -> -8333.3333
A78: Net cash flow | C78: =C74+C75+C77 -> 1371829.5 | D78: =D74+D75+D77 -> -85395.365 | E78: =E74+E75+E77 -> -85339.809 | F78: =F74+F75+F77 -> -85284.254 | G78: =G74+G75+G77 -> -85228.698 | H78: =H74+H75+H77 -> -85173.143 | I78: =I74+I75+I77 -> -85117.587 | J78: =J74+J75+J77 -> -85062.031 | ... BJ78: =BJ74+BJ75+BJ77 -> -142741.35
A79: Opening cash | C79: =0 -> 0 | D79: =C80 -> 1371829.5 | E79: =D80 -> 1286434.2 | F79: =E80 -> 1201094.4 | G79: =F80 -> 1115810.1 | H79: =G80 -> 1030581.4 | I79: =H80 -> 945408.27 | J79: =I80 -> 860290.68 | K79: =J80 -> 775228.65 | ... BJ79: =BI80 -> -6887141.2
A80: Closing cash | C80: =C79+C78 -> 1371829.5 | D80: =D79+D78 -> 1286434.2 | E80: =E79+E78 -> 1201094.4 | F80: =F79+F78 -> 1115810.1 | G80: =G79+G78 -> 1030581.4 | H80: =H79+H78 -> 945408.27 | I80: =I79+I78 -> 860290.68 | J80: =J79+J78 -> 775228.65 | ... BJ80: =BJ79+BJ78 -> -7029882.6
A81: Helper: EBITDA positive (1/0) | C81: =IF(C41>0,1,0) -> 0 | D81: =IF(D41>0,1,0) -> 0 | E81: =IF(E41>0,1,0) -> 0 | F81: =IF(F41>0,1,0) -> 0 | G81: =IF(G41>0,1,0) -> 0 | H81: =IF(H41>0,1,0) -> 0 | I81: =IF(I41>0,1,0) -> 0 | J81: =IF(J41>0,1,0) -> 0 | ... BJ81: =IF(BJ41>0,1,0) -> 0
A83: Goal modules
A84: Helper: net income positive (1/0) | C84: =IF(C50>0,1,0) -> 0 | D84: =IF(D50>0,1,0) -> 0 | E84: =IF(E50>0,1,0) -> 0 | F84: =IF(F50>0,1,0) -> 0 | G84: =IF(G50>0,1,0) -> 0 | H84: =IF(H50>0,1,0) -> 0 | I84: =IF(I50>0,1,0) -> 0 | J84: =IF(J50>0,1,0) -> 0 | ... BJ84: =IF(BJ50>0,1,0) -> 0
A85: Cash flow before financing (operating + investing) | C85: =C74+C75 -> -628170.46 | D85: =D74+D75 -> -77062.031 | E85: =E74+E75 -> -77006.476 | F85: =F74+F75 -> -76950.92 | G85: =G74+G75 -> -76895.365 | H85: =H74+H75 -> -76839.809 | I85: =I74+I75 -> -76784.254 | J85: =J74+J75 -> -76728.698 | ... BJ85: =BJ74+BJ75 -> -134408.01
A86: Cumulative cash flow before financing | C86: =C85 -> -628170.46 | D86: =C86+D85 -> -705232.49 | E86: =D86+E85 -> -782238.97 | F86: =E86+F85 -> -859189.89 | G86: =F86+G85 -> -936085.26 | H86: =G86+H85 -> -1012925.1 | I86: =H86+I85 -> -1089709.3 | J86: =I86+J85 -> -1166438 | K86: =J86+K85 -> -1243111.2 | ... BJ86: =BI86+BJ85 -> -8538215.9
A87: Helper: lowest cumulative cash flow so far | C87: =C86 -> -628170.46 | D87: =MIN(C87,D86) -> -705232.49 | E87: =MIN(D87,E86) -> -782238.97 | F87: =MIN(E87,F86) -> -859189.89 | G87: =MIN(F87,G86) -> -936085.26 | H87: =MIN(G87,H86) -> -1012925.1 | I87: =MIN(H87,I86) -> -1089709.3 | J87: =MIN(I87,J86) -> -1166438 | K87: =MIN(J87,K86) -> -1243111.2 | ... BJ87: =MIN(BI87,BJ86) -> -8538215.9
A88: Helper: investment paid back (1/0) | C88: =IF(AND(C86>=0,C87<0),1,0) -> 0 | D88: =IF(AND(D86>=0,D87<0),1,0) -> 0 | E88: =IF(AND(E86>=0,E87<0),1,0) -> 0 | F88: =IF(AND(F86>=0,F87<0),1,0) -> 0 | G88: =IF(AND(G86>=0,G87<0),1,0) -> 0 | H88: =IF(AND(H86>=0,H87<0),1,0) -> 0 | I88: =IF(AND(I86>=0,I87<0),1,0) -> 0 | J88: =IF(AND(J86>=0,J87<0),1,0) -> 0 | ... BJ88: =IF(AND(BJ86>=0,BJ87<0),1,0) -> 0
A89: Unlevered free cash flow (operating + after-tax interest − capex) | C89: =C74-C45*(1-Inputs!$B$70)+C75 -> -625537.13 | D89: =D74-D45*(1-Inputs!$B$70)+D75 -> -74450.643 | E89: =E74-E45*(1-Inputs!$B$70)+E75 -> -74438.976 | F89: =F74-F45*(1-Inputs!$B$70)+F75 -> -74427.309 | G89: =G74-G45*(1-Inputs!$B$70)+G75 -> -74415.643 | H89: =H74-H45*(1-Inputs!$B$70)+H75 -> -74403.976 | I89: =I74-I45*(1-Inputs!$B$70)+I75 -> -74392.309 | J89: =J74-J45*(1-Inputs!$B$70)+J75 -> -74380.643 | ... BJ89: =BJ74-BJ45*(1-Inputs!$B$70)+BJ75 -> -134342.18
A91: Balance sheet
A92: Paid-in capital | C92: =C76 -> 1500000 | D92: =C92+D76 -> 1500000 | E92: =D92+E76 -> 1500000 | F92: =E92+F76 -> 1500000 | G92: =F92+G76 -> 1500000 | H92: =G92+H76 -> 1500000 | I92: =H92+I76 -> 1500000 | J92: =I92+J76 -> 1500000 | K92: =J92+K76 -> 1500000 | ... BJ92: =BI92+BJ76 -> 1500000
A93: Retained earnings | C93: =C50 -> -81256.476 | D93: =C93+D50 -> -162485.17 | E93: =D93+E50 -> -243658.32 | F93: =E93+F50 -> -324775.9 | G93: =F93+G50 -> -405837.94 | H93: =G93+H50 -> -486844.41 | I93: =H93+I50 -> -567795.33 | J93: =I93+J50 -> -648690.7 | K93: =J93+K50 -> -729530.51 | ... BJ93: =BI93+BJ50 -> -7543588.7
A94: Total assets | C94: =C80+C66+C67+C57 -> 2040747.5 | D94: =D80+D66+D67+D57 -> 1951185.5 | E94: =E80+E66+E67+E57 -> 1861679 | F94: =F80+F66+F67+F57 -> 1772228.1 | G94: =G80+G66+G67+G57 -> 1682832.7 | H94: =H80+H66+H67+H57 -> 1593492.9 | I94: =I80+I66+I67+I57 -> 1504208.7 | J94: =J80+J66+J67+J57 -> 1414980 | ... BJ94: =BJ80+BJ66+BJ67+BJ57 -> -5726476.8
A95: Total liabilities | C95: =C68+C63 -> 622003.99 | D95: =D68+D63 -> 613670.66 | E95: =E68+E63 -> 605337.33 | F95: =F68+F63 -> 597003.99 | G95: =G68+G63 -> 588670.66 | H95: =H68+H63 -> 580337.33 | I95: =I68+I63 -> 572003.99 | J95: =J68+J63 -> 563670.66 | ... BJ95: =BJ68+BJ63 -> 317111.93
A96: Total equity | C96: =C92+C93 -> 1418743.5 | D96: =D92+D93 -> 1337514.8 | E96: =E92+E93 -> 1256341.7 | F96: =F92+F93 -> 1175224.1 | G96: =G92+G93 -> 1094162.1 | H96: =H92+H93 -> 1013155.6 | I96: =I92+I93 -> 932204.67 | J96: =J92+J93 -> 851309.3 | ... BJ96: =BJ92+BJ93 -> -6043588.7
A97: Total liabilities & equity | C97: =C95+C96 -> 2040747.5 | D97: =D95+D96 -> 1951185.5 | E97: =E95+E96 -> 1861679 | F97: =F95+F96 -> 1772228.1 | G97: =G95+G96 -> 1682832.7 | H97: =H95+H96 -> 1593492.9 | I97: =I95+I96 -> 1504208.7 | J97: =J95+J96 -> 1414980 | ... BJ97: =BJ95+BJ96 -> -5726476.8
A98: Check: assets − liabilities − equity | C98: =C94-C97 -> 0 | D98: =D94-D97 -> 0 | E98: =E94-E97 -> 0 | F98: =F94-F97 -> 0 | G98: =G94-G97 -> 0 | H98: =H94-H97 -> 0 | I98: =I94-I97 -> 0 | J98: =J94-J97 -> 0 | ... BJ98: =BJ94-BJ97 -> 0
A100: Headcount (FTE)
A101: Operations & fulfilment — FTE | C101: =Inputs!$B$38*(1+Inputs!$B$40)^(C$7-1)*MAX(0,MIN(1,C$6*1-Inputs!$B$41+1))/1 -> 6 | D101: =Inputs!$B$38*(1+Inputs!$B$40)^(D$7-1)*MAX(0,MIN(1,D$6*1-Inputs!$B$41+1))/1 -> 6 | E101: =Inputs!$B$38*(1+Inputs!$B$40)^(E$7-1)*MAX(0,MIN(1,E$6*1-Inputs!$B$41+1))/1 -> 6 | F101: =Inputs!$B$38*(1+Inputs!$B$40)^(F$7-1)*MAX(0,MIN(1,F$6*1-Inputs!$B$41+1))/1 -> 6 | G101: =Inputs!$B$38*(1+Inputs!$B$40)^(G$7-1)*MAX(0,MIN(1,G$6*1-Inputs!$B$41+1))/1 -> 6 | H101: =Inputs!$B$38*(1+Inputs!$B$40)^(H$7-1)*MAX(0,MIN(1,H$6*1-Inputs!$B$41+1))/1 -> 6 | I101: =Inputs!$B$38*(1+Inputs!$B$40)^(I$7-1)*MAX(0,MIN(1,I$6*1-Inputs!$B$41+1))/1 -> 6 | J101: =Inputs!$B$38*(1+Inputs!$B$40)^(J$7-1)*MAX(0,MIN(1,J$6*1-Inputs!$B$41+1))/1 -> 6 | ... BJ101: =Inputs!$B$38*(1+Inputs!$B$40)^(BJ$7-1)*MAX(0,MIN(1,BJ$6*1-Inputs!$B$41+1))/1 -> 12.4416
A102: Marketing & e-commerce — FTE | C102: =Inputs!$B$42*(1+Inputs!$B$44)^(C$7-1)*MAX(0,MIN(1,C$6*1-Inputs!$B$45+1))/1 -> 4 | D102: =Inputs!$B$42*(1+Inputs!$B$44)^(D$7-1)*MAX(0,MIN(1,D$6*1-Inputs!$B$45+1))/1 -> 4 | E102: =Inputs!$B$42*(1+Inputs!$B$44)^(E$7-1)*MAX(0,MIN(1,E$6*1-Inputs!$B$45+1))/1 -> 4 | F102: =Inputs!$B$42*(1+Inputs!$B$44)^(F$7-1)*MAX(0,MIN(1,F$6*1-Inputs!$B$45+1))/1 -> 4 | G102: =Inputs!$B$42*(1+Inputs!$B$44)^(G$7-1)*MAX(0,MIN(1,G$6*1-Inputs!$B$45+1))/1 -> 4 | H102: =Inputs!$B$42*(1+Inputs!$B$44)^(H$7-1)*MAX(0,MIN(1,H$6*1-Inputs!$B$45+1))/1 -> 4 | I102: =Inputs!$B$42*(1+Inputs!$B$44)^(I$7-1)*MAX(0,MIN(1,I$6*1-Inputs!$B$45+1))/1 -> 4 | J102: =Inputs!$B$42*(1+Inputs!$B$44)^(J$7-1)*MAX(0,MIN(1,J$6*1-Inputs!$B$45+1))/1 -> 4 | ... BJ102: =Inputs!$B$42*(1+Inputs!$B$44)^(BJ$7-1)*MAX(0,MIN(1,BJ$6*1-Inputs!$B$45+1))/1 -> 8.2944
A103: Store staff — FTE | C103: =Inputs!$B$46*(1+Inputs!$B$48)^(C$7-1)*MAX(0,MIN(1,C$6*1-Inputs!$B$49+1))/1 -> 8 | D103: =Inputs!$B$46*(1+Inputs!$B$48)^(D$7-1)*MAX(0,MIN(1,D$6*1-Inputs!$B$49+1))/1 -> 8 | E103: =Inputs!$B$46*(1+Inputs!$B$48)^(E$7-1)*MAX(0,MIN(1,E$6*1-Inputs!$B$49+1))/1 -> 8 | F103: =Inputs!$B$46*(1+Inputs!$B$48)^(F$7-1)*MAX(0,MIN(1,F$6*1-Inputs!$B$49+1))/1 -> 8 | G103: =Inputs!$B$46*(1+Inputs!$B$48)^(G$7-1)*MAX(0,MIN(1,G$6*1-Inputs!$B$49+1))/1 -> 8 | H103: =Inputs!$B$46*(1+Inputs!$B$48)^(H$7-1)*MAX(0,MIN(1,H$6*1-Inputs!$B$49+1))/1 -> 8 | I103: =Inputs!$B$46*(1+Inputs!$B$48)^(I$7-1)*MAX(0,MIN(1,I$6*1-Inputs!$B$49+1))/1 -> 8 | J103: =Inputs!$B$46*(1+Inputs!$B$48)^(J$7-1)*MAX(0,MIN(1,J$6*1-Inputs!$B$49+1))/1 -> 8 | ... BJ103: =Inputs!$B$46*(1+Inputs!$B$48)^(BJ$7-1)*MAX(0,MIN(1,BJ$6*1-Inputs!$B$49+1))/1 -> 22.8488
A104: G&A (finance, admin) — FTE | C104: =Inputs!$B$50*(1+Inputs!$B$52)^(C$7-1)*MAX(0,MIN(1,C$6*1-Inputs!$B$53+1))/1 -> 3 | D104: =Inputs!$B$50*(1+Inputs!$B$52)^(D$7-1)*MAX(0,MIN(1,D$6*1-Inputs!$B$53+1))/1 -> 3 | E104: =Inputs!$B$50*(1+Inputs!$B$52)^(E$7-1)*MAX(0,MIN(1,E$6*1-Inputs!$B$53+1))/1 -> 3 | F104: =Inputs!$B$50*(1+Inputs!$B$52)^(F$7-1)*MAX(0,MIN(1,F$6*1-Inputs!$B$53+1))/1 -> 3 | G104: =Inputs!$B$50*(1+Inputs!$B$52)^(G$7-1)*MAX(0,MIN(1,G$6*1-Inputs!$B$53+1))/1 -> 3 | H104: =Inputs!$B$50*(1+Inputs!$B$52)^(H$7-1)*MAX(0,MIN(1,H$6*1-Inputs!$B$53+1))/1 -> 3 | I104: =Inputs!$B$50*(1+Inputs!$B$52)^(I$7-1)*MAX(0,MIN(1,I$6*1-Inputs!$B$53+1))/1 -> 3 | J104: =Inputs!$B$50*(1+Inputs!$B$52)^(J$7-1)*MAX(0,MIN(1,J$6*1-Inputs!$B$53+1))/1 -> 3 | ... BJ104: =Inputs!$B$50*(1+Inputs!$B$52)^(BJ$7-1)*MAX(0,MIN(1,BJ$6*1-Inputs!$B$53+1))/1 -> 5.2470187
A105: Total FTE | C105: =C101+C102+C103+C104 -> 21 | D105: =D101+D102+D103+D104 -> 21 | E105: =E101+E102+E103+E104 -> 21 | F105: =F101+F102+F103+F104 -> 21 | G105: =G101+G102+G103+G104 -> 21 | H105: =H101+H102+H103+H104 -> 21 | I105: =I101+I102+I103+I104 -> 21 | J105: =J101+J102+J103+J104 -> 21 | ... BJ105: =BJ101+BJ102+BJ103+BJ104 -> 48.831819
A107: Payroll cost (salary + taxes & benefits)
A108: Operations & fulfilment — payroll cost | C108: =-C101*Inputs!$B$39/12*1*(1+Inputs!$B$54)*(1+Inputs!$B$55)^(C$7-1) -> -28750 | D108: =-D101*Inputs!$B$39/12*1*(1+Inputs!$B$54)*(1+Inputs!$B$55)^(D$7-1) -> -28750 | E108: =-E101*Inputs!$B$39/12*1*(1+Inputs!$B$54)*(1+Inputs!$B$55)^(E$7-1) -> -28750 | F108: =-F101*Inputs!$B$39/12*1*(1+Inputs!$B$54)*(1+Inputs!$B$55)^(F$7-1) -> -28750 | G108: =-G101*Inputs!$B$39/12*1*(1+Inputs!$B$54)*(1+Inputs!$B$55)^(G$7-1) -> -28750 | H108: =-H101*Inputs!$B$39/12*1*(1+Inputs!$B$54)*(1+Inputs!$B$55)^(H$7-1) -> -28750 | I108: =-I101*Inputs!$B$39/12*1*(1+Inputs!$B$54)*(1+Inputs!$B$55)^(I$7-1) -> -28750 | J108: =-J101*Inputs!$B$39/12*1*(1+Inputs!$B$54)*(1+Inputs!$B$55)^(J$7-1) -> -28750 | ... BJ108: =-BJ101*Inputs!$B$39/12*1*(1+Inputs!$B$54)*(1+Inputs!$B$55)^(BJ$7-1) -> -67098.333
A109: Marketing & e-commerce — payroll cost | C109: =-C102*Inputs!$B$43/12*1*(1+Inputs!$B$54)*(1+Inputs!$B$55)^(C$7-1) -> -26833.333 | D109: =-D102*Inputs!$B$43/12*1*(1+Inputs!$B$54)*(1+Inputs!$B$55)^(D$7-1) -> -26833.333 | E109: =-E102*Inputs!$B$43/12*1*(1+Inputs!$B$54)*(1+Inputs!$B$55)^(E$7-1) -> -26833.333 | F109: =-F102*Inputs!$B$43/12*1*(1+Inputs!$B$54)*(1+Inputs!$B$55)^(F$7-1) -> -26833.333 | G109: =-G102*Inputs!$B$43/12*1*(1+Inputs!$B$54)*(1+Inputs!$B$55)^(G$7-1) -> -26833.333 | H109: =-H102*Inputs!$B$43/12*1*(1+Inputs!$B$54)*(1+Inputs!$B$55)^(H$7-1) -> -26833.333 | I109: =-I102*Inputs!$B$43/12*1*(1+Inputs!$B$54)*(1+Inputs!$B$55)^(I$7-1) -> -26833.333 | J109: =-J102*Inputs!$B$43/12*1*(1+Inputs!$B$54)*(1+Inputs!$B$55)^(J$7-1) -> -26833.333 | ... BJ109: =-BJ102*Inputs!$B$43/12*1*(1+Inputs!$B$54)*(1+Inputs!$B$55)^(BJ$7-1) -> -62625.111
A110: Store staff — payroll cost | C110: =-C103*Inputs!$B$47/12*1*(1+Inputs!$B$54)*(1+Inputs!$B$55)^(C$7-1) -> -29133.333 | D110: =-D103*Inputs!$B$47/12*1*(1+Inputs!$B$54)*(1+Inputs!$B$55)^(D$7-1) -> -29133.333 | E110: =-E103*Inputs!$B$47/12*1*(1+Inputs!$B$54)*(1+Inputs!$B$55)^(E$7-1) -> -29133.333 | F110: =-F103*Inputs!$B$47/12*1*(1+Inputs!$B$54)*(1+Inputs!$B$55)^(F$7-1) -> -29133.333 | G110: =-G103*Inputs!$B$47/12*1*(1+Inputs!$B$54)*(1+Inputs!$B$55)^(G$7-1) -> -29133.333 | H110: =-H103*Inputs!$B$47/12*1*(1+Inputs!$B$54)*(1+Inputs!$B$55)^(H$7-1) -> -29133.333 | I110: =-I103*Inputs!$B$47/12*1*(1+Inputs!$B$54)*(1+Inputs!$B$55)^(I$7-1) -> -29133.333 | J110: =-J103*Inputs!$B$47/12*1*(1+Inputs!$B$54)*(1+Inputs!$B$55)^(J$7-1) -> -29133.333 | ... BJ110: =-BJ103*Inputs!$B$47/12*1*(1+Inputs!$B$54)*(1+Inputs!$B$55)^(BJ$7-1) -> -93651.014
A111: G&A (finance, admin) — payroll cost | C111: =-C104*Inputs!$B$51/12*1*(1+Inputs!$B$54)*(1+Inputs!$B$55)^(C$7-1) -> -20125 | D111: =-D104*Inputs!$B$51/12*1*(1+Inputs!$B$54)*(1+Inputs!$B$55)^(D$7-1) -> -20125 | E111: =-E104*Inputs!$B$51/12*1*(1+Inputs!$B$54)*(1+Inputs!$B$55)^(E$7-1) -> -20125 | F111: =-F104*Inputs!$B$51/12*1*(1+Inputs!$B$54)*(1+Inputs!$B$55)^(F$7-1) -> -20125 | G111: =-G104*Inputs!$B$51/12*1*(1+Inputs!$B$54)*(1+Inputs!$B$55)^(G$7-1) -> -20125 | H111: =-H104*Inputs!$B$51/12*1*(1+Inputs!$B$54)*(1+Inputs!$B$55)^(H$7-1) -> -20125 | I111: =-I104*Inputs!$B$51/12*1*(1+Inputs!$B$54)*(1+Inputs!$B$55)^(I$7-1) -> -20125 | J111: =-J104*Inputs!$B$51/12*1*(1+Inputs!$B$54)*(1+Inputs!$B$55)^(J$7-1) -> -20125 | ... BJ111: =-BJ104*Inputs!$B$51/12*1*(1+Inputs!$B$54)*(1+Inputs!$B$55)^(BJ$7-1) -> -39616.504
A112: Total payroll | C112: =C108+C109+C110+C111 -> -104841.67 | D112: =D108+D109+D110+D111 -> -104841.67 | E112: =E108+E109+E110+E111 -> -104841.67 | F112: =F108+F109+F110+F111 -> -104841.67 | G112: =G108+G109+G110+G111 -> -104841.67 | H112: =H108+H109+H110+H111 -> -104841.67 | I112: =I108+I109+I110+I111 -> -104841.67 | J112: =J108+J109+J110+J111 -> -104841.67 | ... BJ112: =BJ108+BJ109+BJ110+BJ111 -> -262990.96
A115: Base scenario — reads Inputs column C
A116: Month | C116: M1 | D116: M2 | E116: M3 | F116: M4 | G116: M5 | H116: M6 | I116: M7 | J116: M8 | K116: M9 | L116: M10 | M116: M11 | N116: M12 | O116: M13 | P116: M14 | Q116: M15 | R116: M16 | S116: M17 | T116: M18 | U116: M19 | V116: M20 | W116: M21 | X116: M22 | Y116: M23 | Z116: M24 | AA116: M25 | AB116: M26 | AC116: M27 | AD116: M28 | AE116: M29 | AF116: M30 | AG116: M31 | AH116: M32 | AI116: M33 | AJ116: M34 | AK116: M35 | AL116: M36 | AM116: M37 | AN116: M38 | AO116: M39 | AP116: M40 | AQ116: M41 | AR116: M42 | AS116: M43 | AT116: M44 | AU116: M45 | AV116: M46 | AW116: M47 | AX116: M48 | AY116: M49 | AZ116: M50 | BA116: M51 | BB116: M52 | BC116: M53 | BD116: M54 | BE116: M55 | BF116: M56 | BG116: M57 | BH116: M58 | BI116: M59 | BJ116: M60
...

Sheet Checks
A1: Model checks | E1: =HYPERLINK("#'Cover'!A1","◂ Contents") -> ◂ Contents
A2: Live formulas: they re-run every time an input changes.
A3: Check | B3: Result | C3: What it tests
A4: Annual revenue ties to period detail | B4: =IF(ABS(SUM('P&L'!$B$5:$F$5)-SUM(Monthly!$C$25:$BJ$25))<0.5,"PASS","FAIL") -> PASS | C4: Sum of annual revenue equals the sum of every period
A5: Annual net income ties to period detail | B5: =IF(ABS(SUM('P&L'!$B$25:$F$25)-SUM(Monthly!$C$48:$BJ$48))<0.5,"PASS","FAIL") -> PASS | C5: Sum of annual net income equals the sum of every period
A6: EBITDA reconciliation | B6: =IF(ABS(SUM(Monthly!$C$39:$BJ$39)-SUM(Monthly!$C$27:$BJ$27)-SUM(Monthly!$C$38:$BJ$38))<0.5,"PASS","FAIL") -> PASS | C6: EBITDA = gross profit + operating expenses (costs are negative)
A7: Cash roll-forward | B7: =IF(ABS(INDEX(Monthly!$C$78:$BJ$78,60)-SUM(Monthly!$C$76:$BJ$76))<0.5,"PASS","FAIL") -> PASS | C7: Closing cash = all net cash flows since the start (opening cash is zero)
A8: Scenario selector valid | B8: =IF(AND(ISNUMBER(Dashboard!B4),Dashboard!B4>=1,Dashboard!B4<=3,INT(Dashboard!B4)=Dashboard!B4),"PASS","FAIL") -> PASS | C8: Dashboard!B4 is 1, 2 or 3
A9: Scenario ordering of drivers | B9: =IF(AND(Inputs!$B$7<=Inputs!$C$7,Inputs!$C$7<=Inputs!$D$7,Inputs!$B$8<=Inputs!$C$8,Inputs!$C$8<=Inputs!$D$8,Inputs!$B$9<=Inputs!$C$9,Inputs!$C$9<=Inputs!$D$9,Inputs!$B$10<=Inputs!$C$10,Inputs!$C$10<=Inputs!$D$10,Inputs!$B$11<=Inputs!$C$11,Inputs!$C$11<=Inputs!$D$11,Inputs!$B$12<=Inputs!$C$12,Inputs!$C$12<=Inputs!$D$12,Inputs!$B$15>=Inputs!$C$15,Inputs!$C$15>=Inputs!$D$15,Inputs!$B$18<=Inputs!$C$18,Inputs!$C$18<=Inputs!$D$18,Inputs!$B$19<=Inputs!$C$19,Inputs!$C$19<=Inputs!$D$19,Inputs!$B$21<=Inputs!$C$21,Inputs!$C$21<=Inputs!$D$21,Inputs!$B$22<=Inputs!$C$22,Inputs!$C$22<=Inputs!$D$22,Inputs!$B$29>=Inputs!$C$29,Inputs!$C$29>=Inputs!$D$29,Inputs!$B$30>=Inputs!$C$30,Inputs!$C$30>=Inputs!$D$30,Inputs!$B$31>=Inputs!$C$31,Inputs!$C$31>=Inputs!$D$31,Inputs!$B$38<=Inputs!$C$38,Inputs!$C$38<=Inputs!$D$38,Inputs!$B$40<=Inputs!$C$40,Inputs!$C$40<=Inputs!$D$40,Inputs!$B$42<=Inputs!$C$42,Inputs!$C$42<=Inputs!$D$42,Inputs!$B$44<=Inputs!$C$44,Inputs!$C$44<=Inputs!$D$44,Inputs!$B$46<=Inputs!$C$46,Inputs!$C$46<=Inputs!$D$46,Inputs!$B$48<=Inputs!$C$48,Inputs!$C$48<=Inputs!$D$48,Inputs!$B$50<=Inputs!$C$50,Inputs!$C$50<=Inputs!$D$50,Inputs!$B$52<=Inputs!$C$52,Inputs!$C$52<=Inputs!$D$52,Inputs!$B$76>=Inputs!$C$76,Inputs!$C$76>=Inputs!$D$76,Inputs!$B$77<=Inputs!$C$77,Inputs!$C$77<=Inputs!$D$77,Inputs!$B$78<=Inputs!$C$78,Inputs!$C$78<=Inputs!$D$78),"PASS","FAIL") -> PASS | C9: Low / Base / High ordered the right way for every growth and cost driver
A10: Gross margin within 0–100% | B10: =IF(AND(MIN('P&L'!$B$8:$F$8)>=0,MAX('P&L'!$B$8:$F$8)<=1),"PASS","FAIL") -> PASS | C10: Gross margin never negative or above 100%
A11: Loan balance never negative | B11: =IF(MIN(Monthly!$C$61:$BJ$61)>=-0.5,"PASS","FAIL") -> PASS | C11: Repayments never exceed the loan
A12: Funding table ties to the cash flow | B12: =IF(ABS('Break-even'!B18-('Break-even'!B16-'Break-even'!B10))<0.5,"PASS","FAIL") -> PASS | C12: Lowest cash balance = sources of funds − uses of funds up to that point
A13: Valuation: discounting ties to NPV() | B13: =IF(ABS(Valuation!B23-NPV(Valuation!B6,Valuation!$B$17:$F$17))<0.5,"PASS","FAIL") -> PASS | C13: Sum of discounted free cash flows equals Excel's NPV of the same flows
A14: Valuation: WACC above terminal growth | B14: =IF(Valuation!B6>Valuation!B7,"PASS","FAIL") -> PASS | C14: The perpetual-growth formula needs WACC > g
A15: Valuation: sensitivity centre = enterprise value | B15: =IF(ABS(Valuation!D36-Valuation!B27)<0.5,"PASS","FAIL") -> PASS | C15: The middle of the WACC × growth table reproduces the headline value
A16: Valuation: final-year cash flow positive | B16: =IF(Valuation!$F$17>0,"PASS","WARN") -> PASS | C16: Business warning: a negative final-year cash flow gives a negative terminal value (often a 1-year plan still carrying start-up spending)
A17: Sources & uses balance | B17: =IF(ABS('Sources & Uses'!B21-'Sources & Uses'!B28)<0.5,"PASS","FAIL") -> PASS | C17: Sources of funds = uses of funds (incl. cash at the end) for the Sources & Uses period
A18: No error values | B18: =IF(SUMPRODUCT(--ISERROR(Monthly!$C$4:$BJ$96))+SUMPRODUCT(--ISERROR(Headcount!$C$4:$BJ$19))+SUMPRODUCT(--ISERROR('P&L'!$B$3:$F$26))+SUMPRODUCT(--ISERROR('Cash Flow'!$B$3:$F$18))+SUMPRODUCT(--ISERROR('Balance Sheet'!$B$3:$F$17))+SUMPRODUCT(--ISERROR(KPIs!$B$27:$F$44))+SUMPRODUCT(--ISERROR('Break-even'!$B$26:$F$33))+SUMPRODUCT(--ISERROR(Valuation!$B$14:$F$19))+SUMPRODUCT(--ISERROR('Break-even'!$B$3:$F$35))+SUMPRODUCT(--ISERROR(Valuation!$A$3:$F$40))+SUMPRODUCT(--ISERROR('Sources & Uses'!$B$3:$C$30))+SUMPRODUCT(--ISERROR(Dashboard!$A$6:$W$44))+SUMPRODUCT(--ISERROR(Summary!$A$5:$S$52))+SUMPRODUCT(--ISERROR(KPIs!$A$4:$G$44))+SUMPRODUCT(--ISERROR('Scenario calc'!$C$6:$BJ$112))+SUMPRODUCT(--ISERROR('Scenario calc'!$C$117:$BJ$223))+SUMPRODUCT(--ISERROR('Scenario calc'!$C$228:$BJ$334))+SUMPRODUCT(--ISERROR(Scenarios!$B$5:$F$50))=0,"PASS","FAIL") -> PASS | C18: No error values (divide-by-zero, broken references) on any calculation sheet
A19: Summary ties to statements | B19: =IF(IFERROR(AND(SUMPRODUCT(--(ABS(Summary!$B$7:$F$7-'P&L'!$B$5:$F$5)>0.5))=0,SUMPRODUCT(--(ABS(Summary!$B$19:$F$19-'P&L'!$B$25:$F$25)>0.5))=0,SUMPRODUCT(--(ABS(Summary!$B$31:$F$31-'Cash Flow'!$B$18:$F$18)>0.5))=0,SUMPRODUCT(--(ABS(Summary!$B$41:$F$41-'Balance Sheet'!$B$5:$F$5)>0.5))=0,ABS(SUM(Summary!$H$7:$S$7)-INDEX(Summary!$B$7:$F$7,Summary!$R$2))<0.5,ABS(SUM(Summary!$H$19:$S$19)-INDEX(Summary!$B$19:$F$19,Summary!$R$2))<0.5,ABS(Summary!$S$31-INDEX(Summary!$B$31:$F$31,Summary!$R$2))<0.5),FALSE()),"PASS","FAIL") -> PASS | C19: Summary revenue, net income and closing cash equal the statements every year; the detailed year adds up to its annual figure
A20: DuPont ties to return on equity | B20: =IF(SUMPRODUCT(--(ABS(KPIs!$B$24:$F$24)>0.000000001))>0,"FAIL",IF(SUMPRODUCT(ISNUMBER(KPIs!$B$23:$F$23)*ISNUMBER(KPIs!$B$16:$F$16))=0,"n/a","PASS")) -> PASS | C20: Net margin × asset turnover × equity multiplier equals return on equity every year; n/a = no year where both are defined (a one-sided n/a is a FAIL)
A21: Scenarios: Active = selected scenario | B21: =IF(IFERROR(AND(ABS(Scenarios!E17-INDEX(Scenarios!B17:D17,1,Dashboard!$B$4))<0.5,ABS(Scenarios!E18-INDEX(Scenarios!B18:D18,1,Dashboard!$B$4))<0.5,ABS(Scenarios!E19-INDEX(Scenarios!B19:D19,1,Dashboard!$B$4))<0.5,ABS(Scenarios!E20-INDEX(Scenarios!B20:D20,1,Dashboard!$B$4))<0.000001,ABS(Scenarios!E21-INDEX(Scenarios!B21:D21,1,Dashboard!$B$4))<0.5,ABS(Scenarios!E22-INDEX(Scenarios!B22:D22,1,Dashboard!$B$4))<0.5,ABS(Scenarios!E23-INDEX(Scenarios!B23:D23,1,Dashboard!$B$4))<0.5,ABS(Scenarios!E24-INDEX(Scenarios!B24:D24,1,Dashboard!$B$4))<0.5,ABS(Scenarios!E25-INDEX(Scenarios!B25:D25,1,Dashboard!$B$4))<0.5,ABS(Scenarios!E26-INDEX(Scenarios!B26:D26,1,Dashboard!$B$4))<0.5),FALSE()),"PASS","FAIL") -> PASS | C21: On the Scenarios sheet the live model (Active) equals the Low / Base / High column chosen on the Dashboard for every output
A22: Balance sheet balances every period | B22: =IF(SUMPRODUCT(--(ABS(Monthly!$C$96:$BJ$96)>0.5))=0,"PASS","FAIL") -> PASS | C22: Assets = liabilities + equity in every period
A23: Funding sufficient (cash ≥ 0) | B23: =IF(MIN(Monthly!$C$78:$BJ$78)>=0,"PASS","WARN") -> PASS | C23: Business warning, not an error: cash dips below zero in this scenario
A25: Overall verdict | B25: =IF(COUNTIF(B4:B23,"FAIL")>0,"FAIL",IF(COUNTIF(B4:B23,"WARN")>0,"PASS WITH WARNINGS","PASS")) -> PASS
