Workbook

Sheet Cover
B2: SaaS financial model (early)
B3: 5-year financial model · monthly detail · Low / Base / High scenarios · US dollars · Full plan
B5: Purpose | D5: Revenue and profit plan
B6: Active scenario | D6: =Dashboard!C4&" (change it on the Dashboard, cell B4)" -> Base (change it on the Dashboard, cell B4)
B7: Model checks | D7: =Checks!B25 -> PASS WITH WARNINGS
B8: Prepared | D8: 21 October 2026
B10: Contents
C11: PRESENTATION
B12: 1 | C12: =HYPERLINK("#Dashboard!A1","Dashboard") -> Dashboard | D12: Scenario switch, key numbers, core financials
B13: 2 | C13: =HYPERLINK("#Summary!A1","Summary") -> Summary | D13: Income statement, cash flow and balance sheet — every year and any year by month
B14: 3 | C14: =HYPERLINK("#Scenarios!A1","Scenarios") -> Scenarios | D14: Low / Base / High side by side: drivers, outputs, charts
B15: 4 | C15: =HYPERLINK("#'Break-even'!A1","Break-even") -> Break-even | D15: Startup costs, funding need, break-even timing and revenue
B16: 5 | C16: =HYPERLINK("#Valuation!A1","Valuation") -> Valuation | D16: Free cash flow, DCF (perpetual growth and exit multiple), WACC × growth sensitivity
B17: 6 | C17: =HYPERLINK("#'Sources & Uses'!A1","Sources & Uses") -> Sources & Uses | D17: Funding structure, sources and uses of cash for the first months
B18: 7 | C18: =HYPERLINK("#KPIs!A1","KPIs") -> KPIs | D18: Financial ratios, DuPont analysis, industry metrics
C19: INPUTS
B20: 8 | C20: =HYPERLINK("#Inputs!A1","Inputs") -> Inputs | D20: Every assumption, Low / Base / High, with units and comments
C21: STATEMENTS
B22: 9 | C22: =HYPERLINK("#'P&L'!A1","P&L") -> P&L | D22: Annual profit & loss
B23: 10 | C23: =HYPERLINK("#'Cash Flow'!A1","Cash Flow") -> Cash Flow | D23: Annual cash flow statement
B24: 11 | C24: =HYPERLINK("#'Balance Sheet'!A1","Balance Sheet") -> Balance Sheet | D24: Balance sheet at year end
C25: CALCULATIONS
B26: 12 | C26: =HYPERLINK("#Monthly!A1","Monthly") -> Monthly | D26: Month-by-month engine of the model
B27: 13 | C27: =HYPERLINK("#Headcount!A1","Headcount") -> Headcount | D27: Team and payroll
B28: 14 | C28: =HYPERLINK("#'Scenario calc'!A1","Scenario calc") -> Scenario calc | D28: Low, Base and High calculated side by side for the Scenarios sheet
C29: CONTROL
B30: 15 | C30: =HYPERLINK("#Checks!A1","Checks") -> Checks | D30: Live integrity checks and the overall verdict
B32: How to read this file
C33: 1000 | D33: Input you can change — yellow cell with a blue figure (Inputs sheet and the view switches)
C34: 1000 | D34: Formula — calculated, do not overwrite
C35: 1000 | D35: Link to another sheet
C36: 1000 | D36: Active value the model uses (follows the scenario)

Sheet Dashboard
A1: Dashboard | W1: =HYPERLINK("#'Cover'!A1","◂ Contents") -> ◂ Contents
A2: SaaS financial model (early)
A4: Active scenario | B4: 2 | C4: =CHOOSE(B4,"Low","Base","High") -> Base | D4: 1 = Low · 2 = Base · 3 = High — every sheet follows this cell | S4: Model checks | T4: =Checks!B25 -> PASS WITH WARNINGS
A6: REVENUE · YEAR 5 | C6: EBITDA MARGIN · YEAR 5 | H6: NET INCOME · YEAR 5 | L6: LOWEST CASH BALANCE | P6: FUNDING REQUIRED | T6: ENTERPRISE VALUE (DCF)
A7: =F12 -> 1939020.9 | C7: =F17 -> -1.5391458 | H7: =F18 -> -2984436 | L7: =F38 -> -4291369.5 | P7: =F36 -> 7516369.5 | T7: =F43 -> -9830787.7
A8: =IF(AND(B12>0,F12>=0),(F12/B12)^(1/4)-1,"CAGR n/a") -> 0.71257638 | C8: =F16 -> -2984436 | H8: =F19 -> -1.5391458 | L8: ='Break-even'!B6 -> 60 | P8: =IF(F37>=0,"Covered by funding raised",-F37) -> 4516369.5 | T8: Average of 2 methods
A10: Core financials ($'000) — active scenario
B11: 1 | C11: 2 | D11: 3 | E11: 4 | F11: 5
A12: Revenue | B12: =SUMIF(Monthly!$C$5:$BJ$5,B$11,Monthly!$C$24:$BJ$24) -> 225414.94 | C12: =SUMIF(Monthly!$C$5:$BJ$5,C$11,Monthly!$C$24:$BJ$24) -> 591123.33 | D12: =SUMIF(Monthly!$C$5:$BJ$5,D$11,Monthly!$C$24:$BJ$24) -> 979388.56 | E12: =SUMIF(Monthly!$C$5:$BJ$5,E$11,Monthly!$C$24:$BJ$24) -> 1418382.1 | F12: =SUMIF(Monthly!$C$5:$BJ$5,F$11,Monthly!$C$24:$BJ$24) -> 1939020.9
A13: Gross profit | B13: =SUMIF(Monthly!$C$5:$BJ$5,B$11,Monthly!$C$26:$BJ$26) -> 198403.52 | C13: =SUMIF(Monthly!$C$5:$BJ$5,C$11,Monthly!$C$26:$BJ$26) -> 520687.04 | D13: =SUMIF(Monthly!$C$5:$BJ$5,D$11,Monthly!$C$26:$BJ$26) -> 863384.95 | E13: =SUMIF(Monthly!$C$5:$BJ$5,E$11,Monthly!$C$26:$BJ$26) -> 1251317.7 | F13: =SUMIF(Monthly!$C$5:$BJ$5,F$11,Monthly!$C$26:$BJ$26) -> 1711809.6
A14: Gross margin | B14: =IF(B12=0,0,B13/B12) -> 0.88017025 | C14: =IF(C12=0,0,C13/C12) -> 0.88084332 | D14: =IF(D12=0,0,D13/D12) -> 0.88155507 | E14: =IF(E12=0,0,E13/E12) -> 0.88221481 | F14: =IF(F12=0,0,F13/F12) -> 0.88282162
A15: Operating expenses | B15: =SUMIF(Monthly!$C$5:$BJ$5,B$11,Monthly!$C$34:$BJ$34) -> -901800 | C15: =SUMIF(Monthly!$C$5:$BJ$5,C$11,Monthly!$C$34:$BJ$34) -> -1341360 | D15: =SUMIF(Monthly!$C$5:$BJ$5,D$11,Monthly!$C$34:$BJ$34) -> -2019837.6 | E15: =SUMIF(Monthly!$C$5:$BJ$5,E$11,Monthly!$C$34:$BJ$34) -> -3069482.3 | F15: =SUMIF(Monthly!$C$5:$BJ$5,F$11,Monthly!$C$34:$BJ$34) -> -4696245.6
A16: EBITDA | B16: =SUMIF(Monthly!$C$5:$BJ$5,B$11,Monthly!$C$35:$BJ$35) -> -703396.48 | C16: =SUMIF(Monthly!$C$5:$BJ$5,C$11,Monthly!$C$35:$BJ$35) -> -820672.96 | D16: =SUMIF(Monthly!$C$5:$BJ$5,D$11,Monthly!$C$35:$BJ$35) -> -1156452.6 | E16: =SUMIF(Monthly!$C$5:$BJ$5,E$11,Monthly!$C$35:$BJ$35) -> -1818164.6 | F16: =SUMIF(Monthly!$C$5:$BJ$5,F$11,Monthly!$C$35:$BJ$35) -> -2984436
A17: EBITDA margin | B17: =IF(B12=0,0,B16/B12) -> -3.1204519 | C17: =IF(C12=0,0,C16/C12) -> -1.3883278 | D17: =IF(D12=0,0,D16/D12) -> -1.1807904 | E17: =IF(E12=0,0,E16/E12) -> -1.2818581 | F17: =IF(F12=0,0,F16/F12) -> -1.5391458
A18: Net income | B18: =SUMIF(Monthly!$C$5:$BJ$5,B$11,Monthly!$C$44:$BJ$44) -> -710063.14 | C18: =SUMIF(Monthly!$C$5:$BJ$5,C$11,Monthly!$C$44:$BJ$44) -> -827339.63 | D18: =SUMIF(Monthly!$C$5:$BJ$5,D$11,Monthly!$C$44:$BJ$44) -> -1163119.3 | E18: =SUMIF(Monthly!$C$5:$BJ$5,E$11,Monthly!$C$44:$BJ$44) -> -1818164.6 | F18: =SUMIF(Monthly!$C$5:$BJ$5,F$11,Monthly!$C$44:$BJ$44) -> -2984436
A19: Net margin | B19: =IF(B12=0,0,B18/B12) -> -3.150027 | C19: =IF(C12=0,0,C18/C12) -> -1.3996058 | D19: =IF(D12=0,0,D18/D12) -> -1.1875974 | E19: =IF(E12=0,0,E18/E12) -> -1.2818581 | F19: =IF(F12=0,0,F18/F12) -> -1.5391458
A20: Operating cash flow | B20: =SUMIF(Monthly!$C$5:$BJ$5,B$11,Monthly!$C$70:$BJ$70) -> -665196.51 | C20: =SUMIF(Monthly!$C$5:$BJ$5,C$11,Monthly!$C$70:$BJ$70) -> -785208.42 | D20: =SUMIF(Monthly!$C$5:$BJ$5,D$11,Monthly!$C$70:$BJ$70) -> -1117614.5 | E20: =SUMIF(Monthly!$C$5:$BJ$5,E$11,Monthly!$C$70:$BJ$70) -> -1773179.4 | F20: =SUMIF(Monthly!$C$5:$BJ$5,F$11,Monthly!$C$70:$BJ$70) -> -2930170.7
A21: Investing cash flow | B21: =SUMIF(Monthly!$C$5:$BJ$5,B$11,Monthly!$C$71:$BJ$71) -> -20000 | C21: =SUMIF(Monthly!$C$5:$BJ$5,C$11,Monthly!$C$71:$BJ$71) -> 0 | D21: =SUMIF(Monthly!$C$5:$BJ$5,D$11,Monthly!$C$71:$BJ$71) -> 0 | E21: =SUMIF(Monthly!$C$5:$BJ$5,E$11,Monthly!$C$71:$BJ$71) -> 0 | F21: =SUMIF(Monthly!$C$5:$BJ$5,F$11,Monthly!$C$71:$BJ$71) -> 0
A22: Financing cash flow | B22: =SUMIF(Monthly!$C$5:$BJ$5,B$11,Monthly!$C$73:$BJ$73) -> 3000000 | C22: =SUMIF(Monthly!$C$5:$BJ$5,C$11,Monthly!$C$73:$BJ$73) -> 0 | D22: =SUMIF(Monthly!$C$5:$BJ$5,D$11,Monthly!$C$73:$BJ$73) -> 0 | E22: =SUMIF(Monthly!$C$5:$BJ$5,E$11,Monthly!$C$73:$BJ$73) -> 0 | F22: =SUMIF(Monthly!$C$5:$BJ$5,F$11,Monthly!$C$73:$BJ$73) -> 0
A23: Net change in cash | B23: =SUMIF(Monthly!$C$5:$BJ$5,B$11,Monthly!$C$74:$BJ$74) -> 2314803.5 | C23: =SUMIF(Monthly!$C$5:$BJ$5,C$11,Monthly!$C$74:$BJ$74) -> -785208.42 | D23: =SUMIF(Monthly!$C$5:$BJ$5,D$11,Monthly!$C$74:$BJ$74) -> -1117614.5 | E23: =SUMIF(Monthly!$C$5:$BJ$5,E$11,Monthly!$C$74:$BJ$74) -> -1773179.4 | F23: =SUMIF(Monthly!$C$5:$BJ$5,F$11,Monthly!$C$74:$BJ$74) -> -2930170.7
A24: Year-end cash | B24: =INDEX(Monthly!$C$76:$BJ$76,B$11*12) -> 2314803.5 | C24: =INDEX(Monthly!$C$76:$BJ$76,C$11*12) -> 1529595.1 | D24: =INDEX(Monthly!$C$76:$BJ$76,D$11*12) -> 411980.55 | E24: =INDEX(Monthly!$C$76:$BJ$76,E$11*12) -> -1361198.8 | F24: =INDEX(Monthly!$C$76:$BJ$76,F$11*12) -> -4291369.5
A26: SaaS metrics
B27: 1 | C27: 2 | D27: 3 | E27: 4 | F27: 5
A28: Paying customers (year end) | B28: =KPIs!B29 -> 324.70508 | C28: =KPIs!C29 -> 602.20821 | D28: =KPIs!D29 -> 886.05465 | E28: =KPIs!E29 -> 1197.339 | F28: =KPIs!F29 -> 1556.7378
A29: ARR (year-end MRR × 12) | B29: =KPIs!B33 -> 397045.08 | C29: =KPIs!C33 -> 766645.33 | D29: =KPIs!D33 -> 1171790.9 | E29: =KPIs!E33 -> 1641396.1 | F29: =KPIs!F33 -> 2208189.2
A30: LTV ÷ CAC | B30: =KPIs!B42 -> 11.128003 | C30: =KPIs!C42 -> 11.983709 | D30: =KPIs!D42 -> 12.897559 | E30: =KPIs!E42 -> 13.87231 | F30: =KPIs!F42 -> 14.916711
A31: Team (FTE, year end) | B31: =INDEX(Headcount!$C$12:$BJ$12,B$27*12) -> 6 | C31: =INDEX(Headcount!$C$12:$BJ$12,C$27*12) -> 9 | D31: =INDEX(Headcount!$C$12:$BJ$12,D$27*12) -> 13.5 | E31: =INDEX(Headcount!$C$12:$BJ$12,E$27*12) -> 20.25 | F31: =INDEX(Headcount!$C$12:$BJ$12,F$27*12) -> 30.375
A33: Funding & valuation ($'000) — active scenario
A34: Equity raised | F34: =Inputs!$E$46 -> 3000000
A35: Loan drawn | F35: =Inputs!$E$47 -> 0
A36: Funding required (incl. cash buffer) | F36: ='Break-even'!B12 -> 7516369.5
A37: Funding surplus / (shortfall) | F37: ='Break-even'!B17 -> -4516369.5
A38: ="Lowest cash balance (month "&'Break-even'!B6&")" -> Lowest cash balance (month 60) | F38: ='Break-even'!B18 -> -4291369.5
A39: First month with positive EBITDA | F39: ='Break-even'!B21 -> Not within horizon
A40: Cash invested paid back | F40: ='Break-even'!B23 -> Not within horizon
A41: Enterprise value — perpetual growth | F41: =Valuation!B27 -> -10468635
A42: Enterprise value — exit multiple | F42: =Valuation!C27 -> -9192940.1
A43: Enterprise value — average | F43: =Valuation!B30 -> -9830787.7

Sheet Summary
A1: Financial statements summary | U1: =HYPERLINK("#'Cover'!A1","◂ Contents") -> ◂ Contents
A2: SaaS financial model (early) | P2: Select detailed year: | R2: 1
A5: Income statement ($'000) — by year | H5: ="Income statement ($'000) — Year "&$R$2&", by month" -> Income statement ($'000) — Year 1, by month
B6: 1 | C6: 2 | D6: 3 | E6: 4 | F6: 5 | H6: =INDEX(Monthly!$C$4:$BJ$4,($R$2-1)*12+1) -> 1 | I6: =INDEX(Monthly!$C$4:$BJ$4,($R$2-1)*12+2) -> 2 | J6: =INDEX(Monthly!$C$4:$BJ$4,($R$2-1)*12+3) -> 3 | K6: =INDEX(Monthly!$C$4:$BJ$4,($R$2-1)*12+4) -> 4 | L6: =INDEX(Monthly!$C$4:$BJ$4,($R$2-1)*12+5) -> 5 | M6: =INDEX(Monthly!$C$4:$BJ$4,($R$2-1)*12+6) -> 6 | N6: =INDEX(Monthly!$C$4:$BJ$4,($R$2-1)*12+7) -> 7 | O6: =INDEX(Monthly!$C$4:$BJ$4,($R$2-1)*12+8) -> 8 | P6: =INDEX(Monthly!$C$4:$BJ$4,($R$2-1)*12+9) -> 9 | Q6: =INDEX(Monthly!$C$4:$BJ$4,($R$2-1)*12+10) -> 10 | R6: =INDEX(Monthly!$C$4:$BJ$4,($R$2-1)*12+11) -> 11 | S6: =INDEX(Monthly!$C$4:$BJ$4,($R$2-1)*12+12) -> 12
A7: Revenue | B7: ='P&L'!B5 -> 225414.94 | C7: ='P&L'!C5 -> 591123.33 | D7: ='P&L'!D5 -> 979388.56 | E7: ='P&L'!E5 -> 1418382.1 | F7: ='P&L'!F5 -> 1939020.9 | H7: =INDEX(Monthly!$C$24:$BJ$24,($R$2-1)*12+1) -> 4406.875 | I7: =INDEX(Monthly!$C$24:$BJ$24,($R$2-1)*12+2) -> 7244.7031 | J7: =INDEX(Monthly!$C$24:$BJ$24,($R$2-1)*12+3) -> 10011.586 | K7: =INDEX(Monthly!$C$24:$BJ$24,($R$2-1)*12+4) -> 12709.296 | L7: =INDEX(Monthly!$C$24:$BJ$24,($R$2-1)*12+5) -> 15339.564 | M7: =INDEX(Monthly!$C$24:$BJ$24,($R$2-1)*12+6) -> 17904.074 | N7: =INDEX(Monthly!$C$24:$BJ$24,($R$2-1)*12+7) -> 20404.473 | O7: =INDEX(Monthly!$C$24:$BJ$24,($R$2-1)*12+8) -> 22842.361 | P7: =INDEX(Monthly!$C$24:$BJ$24,($R$2-1)*12+9) -> 25219.302 | Q7: =INDEX(Monthly!$C$24:$BJ$24,($R$2-1)*12+10) -> 27536.819 | R7: =INDEX(Monthly!$C$24:$BJ$24,($R$2-1)*12+11) -> 29796.399 | S7: =INDEX(Monthly!$C$24:$BJ$24,($R$2-1)*12+12) -> 31999.489
A8: Hosting, payment fees & support | B8: ='P&L'!B6 -> -27011.416 | C8: ='P&L'!C6 -> -70436.294 | D8: ='P&L'!D6 -> -116003.61 | E8: ='P&L'!E6 -> -167064.4 | F8: ='P&L'!F6 -> -227211.34 | H8: =INDEX(Monthly!$C$25:$BJ$25,($R$2-1)*12+1) -> -529.56528 | I8: =INDEX(Monthly!$C$25:$BJ$25,($R$2-1)*12+2) -> -870.23731 | J8: =INDEX(Monthly!$C$25:$BJ$25,($R$2-1)*12+3) -> -1202.1081 | K8: =INDEX(Monthly!$C$25:$BJ$25,($R$2-1)*12+4) -> -1525.4062 | L8: =INDEX(Monthly!$C$25:$BJ$25,($R$2-1)*12+5) -> -1840.3542 | M8: =INDEX(Monthly!$C$25:$BJ$25,($R$2-1)*12+6) -> -2147.1689 | N8: =INDEX(Monthly!$C$25:$BJ$25,($R$2-1)*12+7) -> -2446.0615 | O8: =INDEX(Monthly!$C$25:$BJ$25,($R$2-1)*12+8) -> -2737.2374 | P8: =INDEX(Monthly!$C$25:$BJ$25,($R$2-1)*12+9) -> -3020.897 | Q8: =INDEX(Monthly!$C$25:$BJ$25,($R$2-1)*12+10) -> -3297.2353 | R8: =INDEX(Monthly!$C$25:$BJ$25,($R$2-1)*12+11) -> -3566.4422 | S8: =INDEX(Monthly!$C$25:$BJ$25,($R$2-1)*12+12) -> -3828.7027
A9: Gross profit | B9: ='P&L'!B7 -> 198403.52 | C9: ='P&L'!C7 -> 520687.04 | D9: ='P&L'!D7 -> 863384.95 | E9: ='P&L'!E7 -> 1251317.7 | F9: ='P&L'!F7 -> 1711809.6 | H9: =INDEX(Monthly!$C$26:$BJ$26,($R$2-1)*12+1) -> 3877.3097 | I9: =INDEX(Monthly!$C$26:$BJ$26,($R$2-1)*12+2) -> 6374.4658 | J9: =INDEX(Monthly!$C$26:$BJ$26,($R$2-1)*12+3) -> 8809.4774 | K9: =INDEX(Monthly!$C$26:$BJ$26,($R$2-1)*12+4) -> 11183.89 | L9: =INDEX(Monthly!$C$26:$BJ$26,($R$2-1)*12+5) -> 13499.209 | M9: =INDEX(Monthly!$C$26:$BJ$26,($R$2-1)*12+6) -> 15756.905 | N9: =INDEX(Monthly!$C$26:$BJ$26,($R$2-1)*12+7) -> 17958.411 | O9: =INDEX(Monthly!$C$26:$BJ$26,($R$2-1)*12+8) -> 20105.123 | P9: =INDEX(Monthly!$C$26:$BJ$26,($R$2-1)*12+9) -> 22198.405 | Q9: =INDEX(Monthly!$C$26:$BJ$26,($R$2-1)*12+10) -> 24239.584 | R9: =INDEX(Monthly!$C$26:$BJ$26,($R$2-1)*12+11) -> 26229.956 | S9: =INDEX(Monthly!$C$26:$BJ$26,($R$2-1)*12+12) -> 28170.786
A10: Gross margin | B10: ='P&L'!B8 -> 0.88017025 | C10: ='P&L'!C8 -> 0.88084332 | D10: ='P&L'!D8 -> 0.88155507 | E10: ='P&L'!E8 -> 0.88221481 | F10: ='P&L'!F8 -> 0.88282162 | H10: =IF(H7=0,0,H9/H7) -> 0.87983202 | I10: =IF(I7=0,0,I9/I7) -> 0.87987951 | J10: =IF(J7=0,0,J9/J7) -> 0.8799283 | K10: =IF(K7=0,0,K9/K7) -> 0.87997713 | L10: =IF(L7=0,0,L9/L7) -> 0.88002565 | M10: =IF(M7=0,0,M9/M7) -> 0.88007373 | N10: =IF(N7=0,0,N9/N7) -> 0.88012131 | O10: =IF(O7=0,0,O9/O7) -> 0.88016837 | ... S10: =IF(S7=0,0,S9/S7) -> 0.88035113
A11: Total operating expenses | B11: ='P&L'!B14 -> -901800 | C11: ='P&L'!C14 -> -1341360 | D11: ='P&L'!D14 -> -2019837.6 | E11: ='P&L'!E14 -> -3069482.3 | F11: ='P&L'!F14 -> -4696245.6 | H11: =INDEX(Monthly!$C$34:$BJ$34,($R$2-1)*12+1) -> -75150 | I11: =INDEX(Monthly!$C$34:$BJ$34,($R$2-1)*12+2) -> -75150 | J11: =INDEX(Monthly!$C$34:$BJ$34,($R$2-1)*12+3) -> -75150 | K11: =INDEX(Monthly!$C$34:$BJ$34,($R$2-1)*12+4) -> -75150 | L11: =INDEX(Monthly!$C$34:$BJ$34,($R$2-1)*12+5) -> -75150 | M11: =INDEX(Monthly!$C$34:$BJ$34,($R$2-1)*12+6) -> -75150 | N11: =INDEX(Monthly!$C$34:$BJ$34,($R$2-1)*12+7) -> -75150 | O11: =INDEX(Monthly!$C$34:$BJ$34,($R$2-1)*12+8) -> -75150 | P11: =INDEX(Monthly!$C$34:$BJ$34,($R$2-1)*12+9) -> -75150 | Q11: =INDEX(Monthly!$C$34:$BJ$34,($R$2-1)*12+10) -> -75150 | R11: =INDEX(Monthly!$C$34:$BJ$34,($R$2-1)*12+11) -> -75150 | S11: =INDEX(Monthly!$C$34:$BJ$34,($R$2-1)*12+12) -> -75150
A12: EBITDA | B12: ='P&L'!B15 -> -703396.48 | C12: ='P&L'!C15 -> -820672.96 | D12: ='P&L'!D15 -> -1156452.6 | E12: ='P&L'!E15 -> -1818164.6 | F12: ='P&L'!F15 -> -2984436 | H12: =INDEX(Monthly!$C$35:$BJ$35,($R$2-1)*12+1) -> -71272.69 | I12: =INDEX(Monthly!$C$35:$BJ$35,($R$2-1)*12+2) -> -68775.534 | J12: =INDEX(Monthly!$C$35:$BJ$35,($R$2-1)*12+3) -> -66340.523 | K12: =INDEX(Monthly!$C$35:$BJ$35,($R$2-1)*12+4) -> -63966.11 | L12: =INDEX(Monthly!$C$35:$BJ$35,($R$2-1)*12+5) -> -61650.791 | M12: =INDEX(Monthly!$C$35:$BJ$35,($R$2-1)*12+6) -> -59393.095 | N12: =INDEX(Monthly!$C$35:$BJ$35,($R$2-1)*12+7) -> -57191.589 | O12: =INDEX(Monthly!$C$35:$BJ$35,($R$2-1)*12+8) -> -55044.877 | P12: =INDEX(Monthly!$C$35:$BJ$35,($R$2-1)*12+9) -> -52951.595 | Q12: =INDEX(Monthly!$C$35:$BJ$35,($R$2-1)*12+10) -> -50910.416 | R12: =INDEX(Monthly!$C$35:$BJ$35,($R$2-1)*12+11) -> -48920.044 | S12: =INDEX(Monthly!$C$35:$BJ$35,($R$2-1)*12+12) -> -46979.214
A13: EBITDA margin | B13: ='P&L'!B16 -> -3.1204519 | C13: ='P&L'!C16 -> -1.3883278 | D13: ='P&L'!D16 -> -1.1807904 | E13: ='P&L'!E16 -> -1.2818581 | F13: ='P&L'!F16 -> -1.5391458 | H13: =IF(H7=0,0,H12/H7) -> -16.173068 | I13: =IF(I7=0,0,I12/I7) -> -9.4932164 | J13: =IF(J7=0,0,J12/J7) -> -6.6263752 | K13: =IF(K7=0,0,K12/K7) -> -5.0330176 | L13: =IF(L7=0,0,L12/L7) -> -4.0190707 | M13: =IF(M7=0,0,M12/M7) -> -3.3172949 | N13: =IF(N7=0,0,N12/N7) -> -2.8028947 | O13: =IF(O7=0,0,O12/O7) -> -2.4097718 | ... S13: =IF(S7=0,0,S12/S7) -> -1.4681239
A14: Depreciation | B14: ='P&L'!B17 -> -6666.6667 | C14: ='P&L'!C17 -> -6666.6667 | D14: ='P&L'!D17 -> -6666.6667 | E14: ='P&L'!E17 -> 0 | F14: ='P&L'!F17 -> 0 | H14: =INDEX(Monthly!$C$49:$BJ$49,($R$2-1)*12+1) -> -555.55556 | I14: =INDEX(Monthly!$C$49:$BJ$49,($R$2-1)*12+2) -> -555.55556 | J14: =INDEX(Monthly!$C$49:$BJ$49,($R$2-1)*12+3) -> -555.55556 | K14: =INDEX(Monthly!$C$49:$BJ$49,($R$2-1)*12+4) -> -555.55556 | L14: =INDEX(Monthly!$C$49:$BJ$49,($R$2-1)*12+5) -> -555.55556 | M14: =INDEX(Monthly!$C$49:$BJ$49,($R$2-1)*12+6) -> -555.55556 | N14: =INDEX(Monthly!$C$49:$BJ$49,($R$2-1)*12+7) -> -555.55556 | O14: =INDEX(Monthly!$C$49:$BJ$49,($R$2-1)*12+8) -> -555.55556 | P14: =INDEX(Monthly!$C$49:$BJ$49,($R$2-1)*12+9) -> -555.55556 | Q14: =INDEX(Monthly!$C$49:$BJ$49,($R$2-1)*12+10) -> -555.55556 | R14: =INDEX(Monthly!$C$49:$BJ$49,($R$2-1)*12+11) -> -555.55556 | S14: =INDEX(Monthly!$C$49:$BJ$49,($R$2-1)*12+12) -> -555.55556
A15: EBIT | B15: ='P&L'!B18 -> -710063.14 | C15: ='P&L'!C18 -> -827339.63 | D15: ='P&L'!D18 -> -1163119.3 | E15: ='P&L'!E18 -> -1818164.6 | F15: ='P&L'!F18 -> -2984436 | H15: =INDEX(Monthly!$C$38:$BJ$38,($R$2-1)*12+1) -> -71828.246 | I15: =INDEX(Monthly!$C$38:$BJ$38,($R$2-1)*12+2) -> -69331.09 | J15: =INDEX(Monthly!$C$38:$BJ$38,($R$2-1)*12+3) -> -66896.078 | K15: =INDEX(Monthly!$C$38:$BJ$38,($R$2-1)*12+4) -> -64521.666 | L15: =INDEX(Monthly!$C$38:$BJ$38,($R$2-1)*12+5) -> -62206.346 | M15: =INDEX(Monthly!$C$38:$BJ$38,($R$2-1)*12+6) -> -59948.65 | N15: =INDEX(Monthly!$C$38:$BJ$38,($R$2-1)*12+7) -> -57747.144 | O15: =INDEX(Monthly!$C$38:$BJ$38,($R$2-1)*12+8) -> -55600.432 | P15: =INDEX(Monthly!$C$38:$BJ$38,($R$2-1)*12+9) -> -53507.151 | Q15: =INDEX(Monthly!$C$38:$BJ$38,($R$2-1)*12+10) -> -51465.972 | R15: =INDEX(Monthly!$C$38:$BJ$38,($R$2-1)*12+11) -> -49475.599 | S15: =INDEX(Monthly!$C$38:$BJ$38,($R$2-1)*12+12) -> -47534.77
A16: Interest | B16: ='P&L'!B19 -> 0 | C16: ='P&L'!C19 -> 0 | D16: ='P&L'!D19 -> 0 | E16: ='P&L'!E19 -> 0 | F16: ='P&L'!F19 -> 0 | H16: =INDEX(Monthly!$C$39:$BJ$39,($R$2-1)*12+1) -> 0 | I16: =INDEX(Monthly!$C$39:$BJ$39,($R$2-1)*12+2) -> 0 | J16: =INDEX(Monthly!$C$39:$BJ$39,($R$2-1)*12+3) -> 0 | K16: =INDEX(Monthly!$C$39:$BJ$39,($R$2-1)*12+4) -> 0 | L16: =INDEX(Monthly!$C$39:$BJ$39,($R$2-1)*12+5) -> 0 | M16: =INDEX(Monthly!$C$39:$BJ$39,($R$2-1)*12+6) -> 0 | N16: =INDEX(Monthly!$C$39:$BJ$39,($R$2-1)*12+7) -> 0 | O16: =INDEX(Monthly!$C$39:$BJ$39,($R$2-1)*12+8) -> 0 | P16: =INDEX(Monthly!$C$39:$BJ$39,($R$2-1)*12+9) -> 0 | Q16: =INDEX(Monthly!$C$39:$BJ$39,($R$2-1)*12+10) -> 0 | R16: =INDEX(Monthly!$C$39:$BJ$39,($R$2-1)*12+11) -> 0 | S16: =INDEX(Monthly!$C$39:$BJ$39,($R$2-1)*12+12) -> 0
A17: Pre-tax income | B17: ='P&L'!B20 -> -710063.14 | C17: ='P&L'!C20 -> -827339.63 | D17: ='P&L'!D20 -> -1163119.3 | E17: ='P&L'!E20 -> -1818164.6 | F17: ='P&L'!F20 -> -2984436 | H17: =INDEX(Monthly!$C$40:$BJ$40,($R$2-1)*12+1) -> -71828.246 | I17: =INDEX(Monthly!$C$40:$BJ$40,($R$2-1)*12+2) -> -69331.09 | J17: =INDEX(Monthly!$C$40:$BJ$40,($R$2-1)*12+3) -> -66896.078 | K17: =INDEX(Monthly!$C$40:$BJ$40,($R$2-1)*12+4) -> -64521.666 | L17: =INDEX(Monthly!$C$40:$BJ$40,($R$2-1)*12+5) -> -62206.346 | M17: =INDEX(Monthly!$C$40:$BJ$40,($R$2-1)*12+6) -> -59948.65 | N17: =INDEX(Monthly!$C$40:$BJ$40,($R$2-1)*12+7) -> -57747.144 | O17: =INDEX(Monthly!$C$40:$BJ$40,($R$2-1)*12+8) -> -55600.432 | P17: =INDEX(Monthly!$C$40:$BJ$40,($R$2-1)*12+9) -> -53507.151 | Q17: =INDEX(Monthly!$C$40:$BJ$40,($R$2-1)*12+10) -> -51465.972 | R17: =INDEX(Monthly!$C$40:$BJ$40,($R$2-1)*12+11) -> -49475.599 | S17: =INDEX(Monthly!$C$40:$BJ$40,($R$2-1)*12+12) -> -47534.77
A18: Income tax | B18: ='P&L'!B21 -> 0 | C18: ='P&L'!C21 -> 0 | D18: ='P&L'!D21 -> 0 | E18: ='P&L'!E21 -> 0 | F18: ='P&L'!F21 -> 0 | H18: =INDEX(Monthly!$C$43:$BJ$43,($R$2-1)*12+1) -> 0 | I18: =INDEX(Monthly!$C$43:$BJ$43,($R$2-1)*12+2) -> 0 | J18: =INDEX(Monthly!$C$43:$BJ$43,($R$2-1)*12+3) -> 0 | K18: =INDEX(Monthly!$C$43:$BJ$43,($R$2-1)*12+4) -> 0 | L18: =INDEX(Monthly!$C$43:$BJ$43,($R$2-1)*12+5) -> 0 | M18: =INDEX(Monthly!$C$43:$BJ$43,($R$2-1)*12+6) -> 0 | N18: =INDEX(Monthly!$C$43:$BJ$43,($R$2-1)*12+7) -> 0 | O18: =INDEX(Monthly!$C$43:$BJ$43,($R$2-1)*12+8) -> 0 | P18: =INDEX(Monthly!$C$43:$BJ$43,($R$2-1)*12+9) -> 0 | Q18: =INDEX(Monthly!$C$43:$BJ$43,($R$2-1)*12+10) -> 0 | R18: =INDEX(Monthly!$C$43:$BJ$43,($R$2-1)*12+11) -> 0 | S18: =INDEX(Monthly!$C$43:$BJ$43,($R$2-1)*12+12) -> 0
A19: Net income | B19: ='P&L'!B22 -> -710063.14 | C19: ='P&L'!C22 -> -827339.63 | D19: ='P&L'!D22 -> -1163119.3 | E19: ='P&L'!E22 -> -1818164.6 | F19: ='P&L'!F22 -> -2984436 | H19: =INDEX(Monthly!$C$44:$BJ$44,($R$2-1)*12+1) -> -71828.246 | I19: =INDEX(Monthly!$C$44:$BJ$44,($R$2-1)*12+2) -> -69331.09 | J19: =INDEX(Monthly!$C$44:$BJ$44,($R$2-1)*12+3) -> -66896.078 | K19: =INDEX(Monthly!$C$44:$BJ$44,($R$2-1)*12+4) -> -64521.666 | L19: =INDEX(Monthly!$C$44:$BJ$44,($R$2-1)*12+5) -> -62206.346 | M19: =INDEX(Monthly!$C$44:$BJ$44,($R$2-1)*12+6) -> -59948.65 | N19: =INDEX(Monthly!$C$44:$BJ$44,($R$2-1)*12+7) -> -57747.144 | O19: =INDEX(Monthly!$C$44:$BJ$44,($R$2-1)*12+8) -> -55600.432 | P19: =INDEX(Monthly!$C$44:$BJ$44,($R$2-1)*12+9) -> -53507.151 | Q19: =INDEX(Monthly!$C$44:$BJ$44,($R$2-1)*12+10) -> -51465.972 | R19: =INDEX(Monthly!$C$44:$BJ$44,($R$2-1)*12+11) -> -49475.599 | S19: =INDEX(Monthly!$C$44:$BJ$44,($R$2-1)*12+12) -> -47534.77
A20: Net margin | B20: ='P&L'!B23 -> -3.150027 | C20: ='P&L'!C23 -> -1.3996058 | D20: ='P&L'!D23 -> -1.1875974 | E20: ='P&L'!E23 -> -1.2818581 | F20: ='P&L'!F23 -> -1.5391458 | H20: =IF(H7=0,0,H19/H7) -> -16.299134 | I20: =IF(I7=0,0,I19/I7) -> -9.5699007 | J20: =IF(J7=0,0,J19/J7) -> -6.6818665 | K20: =IF(K7=0,0,K19/K7) -> -5.0767302 | L20: =IF(L7=0,0,L19/L7) -> -4.0552879 | M20: =IF(M7=0,0,M19/M7) -> -3.3483244 | N20: =IF(N7=0,0,N19/N7) -> -2.8301219 | O20: =IF(O7=0,0,O19/O7) -> -2.4340931 | ... S20: =IF(S7=0,0,S19/S7) -> -1.4854853
A22: Cash flow ($'000) — by year | H22: ="Cash flow ($'000) — Year "&$R$2&", by month" -> Cash flow ($'000) — Year 1, by month
B23: 1 | C23: 2 | D23: 3 | E23: 4 | F23: 5 | H23: =INDEX(Monthly!$C$4:$BJ$4,($R$2-1)*12+1) -> 1 | I23: =INDEX(Monthly!$C$4:$BJ$4,($R$2-1)*12+2) -> 2 | J23: =INDEX(Monthly!$C$4:$BJ$4,($R$2-1)*12+3) -> 3 | K23: =INDEX(Monthly!$C$4:$BJ$4,($R$2-1)*12+4) -> 4 | L23: =INDEX(Monthly!$C$4:$BJ$4,($R$2-1)*12+5) -> 5 | M23: =INDEX(Monthly!$C$4:$BJ$4,($R$2-1)*12+6) -> 6 | N23: =INDEX(Monthly!$C$4:$BJ$4,($R$2-1)*12+7) -> 7 | O23: =INDEX(Monthly!$C$4:$BJ$4,($R$2-1)*12+8) -> 8 | P23: =INDEX(Monthly!$C$4:$BJ$4,($R$2-1)*12+9) -> 9 | Q23: =INDEX(Monthly!$C$4:$BJ$4,($R$2-1)*12+10) -> 10 | R23: =INDEX(Monthly!$C$4:$BJ$4,($R$2-1)*12+11) -> 11 | S23: =INDEX(Monthly!$C$4:$BJ$4,($R$2-1)*12+12) -> 12
A24: Operating cash flow | B24: ='Cash Flow'!B11 -> -665196.51 | C24: ='Cash Flow'!C11 -> -785208.42 | D24: ='Cash Flow'!D11 -> -1117614.5 | E24: ='Cash Flow'!E11 -> -1773179.4 | F24: ='Cash Flow'!F11 -> -2930170.7 | H24: =INDEX(Monthly!$C$70:$BJ$70,($R$2-1)*12+1) -> -64465.104 | I24: =INDEX(Monthly!$C$70:$BJ$70,($R$2-1)*12+2) -> -65545.546 | J24: =INDEX(Monthly!$C$70:$BJ$70,($R$2-1)*12+3) -> -63191.569 | K24: =INDEX(Monthly!$C$70:$BJ$70,($R$2-1)*12+4) -> -60896.156 | L24: =INDEX(Monthly!$C$70:$BJ$70,($R$2-1)*12+5) -> -58657.853 | M24: =INDEX(Monthly!$C$70:$BJ$70,($R$2-1)*12+6) -> -56475.24 | N24: =INDEX(Monthly!$C$70:$BJ$70,($R$2-1)*12+7) -> -54346.932 | O24: =INDEX(Monthly!$C$70:$BJ$70,($R$2-1)*12+8) -> -52271.581 | P24: =INDEX(Monthly!$C$70:$BJ$70,($R$2-1)*12+9) -> -50247.869 | Q24: =INDEX(Monthly!$C$70:$BJ$70,($R$2-1)*12+10) -> -48274.513 | R24: =INDEX(Monthly!$C$70:$BJ$70,($R$2-1)*12+11) -> -46350.26 | S24: =INDEX(Monthly!$C$70:$BJ$70,($R$2-1)*12+12) -> -44473.892
A25: Capital spending | B25: ='Cash Flow'!B12 -> -20000 | C25: ='Cash Flow'!C12 -> 0 | D25: ='Cash Flow'!D12 -> 0 | E25: ='Cash Flow'!E12 -> 0 | F25: ='Cash Flow'!F12 -> 0 | H25: =INDEX(Monthly!$C$71:$BJ$71,($R$2-1)*12+1) -> -20000 | I25: =INDEX(Monthly!$C$71:$BJ$71,($R$2-1)*12+2) -> 0 | J25: =INDEX(Monthly!$C$71:$BJ$71,($R$2-1)*12+3) -> 0 | K25: =INDEX(Monthly!$C$71:$BJ$71,($R$2-1)*12+4) -> 0 | L25: =INDEX(Monthly!$C$71:$BJ$71,($R$2-1)*12+5) -> 0 | M25: =INDEX(Monthly!$C$71:$BJ$71,($R$2-1)*12+6) -> 0 | N25: =INDEX(Monthly!$C$71:$BJ$71,($R$2-1)*12+7) -> 0 | O25: =INDEX(Monthly!$C$71:$BJ$71,($R$2-1)*12+8) -> 0 | P25: =INDEX(Monthly!$C$71:$BJ$71,($R$2-1)*12+9) -> 0 | Q25: =INDEX(Monthly!$C$71:$BJ$71,($R$2-1)*12+10) -> 0 | R25: =INDEX(Monthly!$C$71:$BJ$71,($R$2-1)*12+11) -> 0 | S25: =INDEX(Monthly!$C$71:$BJ$71,($R$2-1)*12+12) -> 0
A26: Equity raised | B26: ='Cash Flow'!B13 -> 3000000 | C26: ='Cash Flow'!C13 -> 0 | D26: ='Cash Flow'!D13 -> 0 | E26: ='Cash Flow'!E13 -> 0 | F26: ='Cash Flow'!F13 -> 0 | H26: =INDEX(Monthly!$C$72:$BJ$72,($R$2-1)*12+1) -> 3000000 | I26: =INDEX(Monthly!$C$72:$BJ$72,($R$2-1)*12+2) -> 0 | J26: =INDEX(Monthly!$C$72:$BJ$72,($R$2-1)*12+3) -> 0 | K26: =INDEX(Monthly!$C$72:$BJ$72,($R$2-1)*12+4) -> 0 | L26: =INDEX(Monthly!$C$72:$BJ$72,($R$2-1)*12+5) -> 0 | M26: =INDEX(Monthly!$C$72:$BJ$72,($R$2-1)*12+6) -> 0 | N26: =INDEX(Monthly!$C$72:$BJ$72,($R$2-1)*12+7) -> 0 | O26: =INDEX(Monthly!$C$72:$BJ$72,($R$2-1)*12+8) -> 0 | P26: =INDEX(Monthly!$C$72:$BJ$72,($R$2-1)*12+9) -> 0 | Q26: =INDEX(Monthly!$C$72:$BJ$72,($R$2-1)*12+10) -> 0 | R26: =INDEX(Monthly!$C$72:$BJ$72,($R$2-1)*12+11) -> 0 | S26: =INDEX(Monthly!$C$72:$BJ$72,($R$2-1)*12+12) -> 0
A27: Loan drawdown | B27: ='Cash Flow'!B14 -> 0 | C27: ='Cash Flow'!C14 -> 0 | D27: ='Cash Flow'!D14 -> 0 | E27: ='Cash Flow'!E14 -> 0 | F27: ='Cash Flow'!F14 -> 0 | H27: =INDEX(Monthly!$C$55:$BJ$55,($R$2-1)*12+1) -> 0 | I27: =INDEX(Monthly!$C$55:$BJ$55,($R$2-1)*12+2) -> 0 | J27: =INDEX(Monthly!$C$55:$BJ$55,($R$2-1)*12+3) -> 0 | K27: =INDEX(Monthly!$C$55:$BJ$55,($R$2-1)*12+4) -> 0 | L27: =INDEX(Monthly!$C$55:$BJ$55,($R$2-1)*12+5) -> 0 | M27: =INDEX(Monthly!$C$55:$BJ$55,($R$2-1)*12+6) -> 0 | N27: =INDEX(Monthly!$C$55:$BJ$55,($R$2-1)*12+7) -> 0 | O27: =INDEX(Monthly!$C$55:$BJ$55,($R$2-1)*12+8) -> 0 | P27: =INDEX(Monthly!$C$55:$BJ$55,($R$2-1)*12+9) -> 0 | Q27: =INDEX(Monthly!$C$55:$BJ$55,($R$2-1)*12+10) -> 0 | R27: =INDEX(Monthly!$C$55:$BJ$55,($R$2-1)*12+11) -> 0 | S27: =INDEX(Monthly!$C$55:$BJ$55,($R$2-1)*12+12) -> 0
A28: Loan repayment | B28: ='Cash Flow'!B15 -> 0 | C28: ='Cash Flow'!C15 -> 0 | D28: ='Cash Flow'!D15 -> 0 | E28: ='Cash Flow'!E15 -> 0 | F28: ='Cash Flow'!F15 -> 0 | H28: =INDEX(Monthly!$C$56:$BJ$56,($R$2-1)*12+1) -> 0 | I28: =INDEX(Monthly!$C$56:$BJ$56,($R$2-1)*12+2) -> 0 | J28: =INDEX(Monthly!$C$56:$BJ$56,($R$2-1)*12+3) -> 0 | K28: =INDEX(Monthly!$C$56:$BJ$56,($R$2-1)*12+4) -> 0 | L28: =INDEX(Monthly!$C$56:$BJ$56,($R$2-1)*12+5) -> 0 | M28: =INDEX(Monthly!$C$56:$BJ$56,($R$2-1)*12+6) -> 0 | N28: =INDEX(Monthly!$C$56:$BJ$56,($R$2-1)*12+7) -> 0 | O28: =INDEX(Monthly!$C$56:$BJ$56,($R$2-1)*12+8) -> 0 | P28: =INDEX(Monthly!$C$56:$BJ$56,($R$2-1)*12+9) -> 0 | Q28: =INDEX(Monthly!$C$56:$BJ$56,($R$2-1)*12+10) -> 0 | R28: =INDEX(Monthly!$C$56:$BJ$56,($R$2-1)*12+11) -> 0 | S28: =INDEX(Monthly!$C$56:$BJ$56,($R$2-1)*12+12) -> 0
A29: Financing cash flow | B29: ='Cash Flow'!B16 -> 3000000 | C29: ='Cash Flow'!C16 -> 0 | D29: ='Cash Flow'!D16 -> 0 | E29: ='Cash Flow'!E16 -> 0 | F29: ='Cash Flow'!F16 -> 0 | H29: =INDEX(Monthly!$C$73:$BJ$73,($R$2-1)*12+1) -> 3000000 | I29: =INDEX(Monthly!$C$73:$BJ$73,($R$2-1)*12+2) -> 0 | J29: =INDEX(Monthly!$C$73:$BJ$73,($R$2-1)*12+3) -> 0 | K29: =INDEX(Monthly!$C$73:$BJ$73,($R$2-1)*12+4) -> 0 | L29: =INDEX(Monthly!$C$73:$BJ$73,($R$2-1)*12+5) -> 0 | M29: =INDEX(Monthly!$C$73:$BJ$73,($R$2-1)*12+6) -> 0 | N29: =INDEX(Monthly!$C$73:$BJ$73,($R$2-1)*12+7) -> 0 | O29: =INDEX(Monthly!$C$73:$BJ$73,($R$2-1)*12+8) -> 0 | P29: =INDEX(Monthly!$C$73:$BJ$73,($R$2-1)*12+9) -> 0 | Q29: =INDEX(Monthly!$C$73:$BJ$73,($R$2-1)*12+10) -> 0 | R29: =INDEX(Monthly!$C$73:$BJ$73,($R$2-1)*12+11) -> 0 | S29: =INDEX(Monthly!$C$73:$BJ$73,($R$2-1)*12+12) -> 0
A30: Net change in cash | B30: ='Cash Flow'!B17 -> 2314803.5 | C30: ='Cash Flow'!C17 -> -785208.42 | D30: ='Cash Flow'!D17 -> -1117614.5 | E30: ='Cash Flow'!E17 -> -1773179.4 | F30: ='Cash Flow'!F17 -> -2930170.7 | H30: =INDEX(Monthly!$C$74:$BJ$74,($R$2-1)*12+1) -> 2915534.9 | I30: =INDEX(Monthly!$C$74:$BJ$74,($R$2-1)*12+2) -> -65545.546 | J30: =INDEX(Monthly!$C$74:$BJ$74,($R$2-1)*12+3) -> -63191.569 | K30: =INDEX(Monthly!$C$74:$BJ$74,($R$2-1)*12+4) -> -60896.156 | L30: =INDEX(Monthly!$C$74:$BJ$74,($R$2-1)*12+5) -> -58657.853 | M30: =INDEX(Monthly!$C$74:$BJ$74,($R$2-1)*12+6) -> -56475.24 | N30: =INDEX(Monthly!$C$74:$BJ$74,($R$2-1)*12+7) -> -54346.932 | O30: =INDEX(Monthly!$C$74:$BJ$74,($R$2-1)*12+8) -> -52271.581 | P30: =INDEX(Monthly!$C$74:$BJ$74,($R$2-1)*12+9) -> -50247.869 | Q30: =INDEX(Monthly!$C$74:$BJ$74,($R$2-1)*12+10) -> -48274.513 | R30: =INDEX(Monthly!$C$74:$BJ$74,($R$2-1)*12+11) -> -46350.26 | S30: =INDEX(Monthly!$C$74:$BJ$74,($R$2-1)*12+12) -> -44473.892
A31: Closing cash | B31: ='Cash Flow'!B19 -> 2314803.5 | C31: ='Cash Flow'!C19 -> 1529595.1 | D31: ='Cash Flow'!D19 -> 411980.55 | E31: ='Cash Flow'!E19 -> -1361198.8 | F31: ='Cash Flow'!F19 -> -4291369.5 | H31: =INDEX(Monthly!$C$76:$BJ$76,($R$2-1)*12+1) -> 2915534.9 | I31: =INDEX(Monthly!$C$76:$BJ$76,($R$2-1)*12+2) -> 2849989.3 | J31: =INDEX(Monthly!$C$76:$BJ$76,($R$2-1)*12+3) -> 2786797.8 | K31: =INDEX(Monthly!$C$76:$BJ$76,($R$2-1)*12+4) -> 2725901.6 | L31: =INDEX(Monthly!$C$76:$BJ$76,($R$2-1)*12+5) -> 2667243.8 | M31: =INDEX(Monthly!$C$76:$BJ$76,($R$2-1)*12+6) -> 2610768.5 | N31: =INDEX(Monthly!$C$76:$BJ$76,($R$2-1)*12+7) -> 2556421.6 | O31: =INDEX(Monthly!$C$76:$BJ$76,($R$2-1)*12+8) -> 2504150 | P31: =INDEX(Monthly!$C$76:$BJ$76,($R$2-1)*12+9) -> 2453902.2 | Q31: =INDEX(Monthly!$C$76:$BJ$76,($R$2-1)*12+10) -> 2405627.6 | R31: =INDEX(Monthly!$C$76:$BJ$76,($R$2-1)*12+11) -> 2359277.4 | S31: =INDEX(Monthly!$C$76:$BJ$76,($R$2-1)*12+12) -> 2314803.5
A39: Balance sheet at year end ($'000) | H39: ="Balance sheet at month end ($'000) — Year "&$R$2 -> Balance sheet at month end ($'000) — Year 1
B40: 1 | C40: 2 | D40: 3 | E40: 4 | F40: 5 | H40: =INDEX(Monthly!$C$4:$BJ$4,($R$2-1)*12+1) -> 1 | I40: =INDEX(Monthly!$C$4:$BJ$4,($R$2-1)*12+2) -> 2 | J40: =INDEX(Monthly!$C$4:$BJ$4,($R$2-1)*12+3) -> 3 | K40: =INDEX(Monthly!$C$4:$BJ$4,($R$2-1)*12+4) -> 4 | L40: =INDEX(Monthly!$C$4:$BJ$4,($R$2-1)*12+5) -> 5 | M40: =INDEX(Monthly!$C$4:$BJ$4,($R$2-1)*12+6) -> 6 | N40: =INDEX(Monthly!$C$4:$BJ$4,($R$2-1)*12+7) -> 7 | O40: =INDEX(Monthly!$C$4:$BJ$4,($R$2-1)*12+8) -> 8 | P40: =INDEX(Monthly!$C$4:$BJ$4,($R$2-1)*12+9) -> 9 | Q40: =INDEX(Monthly!$C$4:$BJ$4,($R$2-1)*12+10) -> 10 | R40: =INDEX(Monthly!$C$4:$BJ$4,($R$2-1)*12+11) -> 11 | S40: =INDEX(Monthly!$C$4:$BJ$4,($R$2-1)*12+12) -> 12
A41: Cash | B41: ='Balance Sheet'!B5 -> 2314803.5 | C41: ='Balance Sheet'!C5 -> 1529595.1 | D41: ='Balance Sheet'!D5 -> 411980.55 | E41: ='Balance Sheet'!E5 -> -1361198.8 | F41: ='Balance Sheet'!F5 -> -4291369.5 | H41: =INDEX(Monthly!$C$76:$BJ$76,($R$2-1)*12+1) -> 2915534.9 | I41: =INDEX(Monthly!$C$76:$BJ$76,($R$2-1)*12+2) -> 2849989.3 | J41: =INDEX(Monthly!$C$76:$BJ$76,($R$2-1)*12+3) -> 2786797.8 | K41: =INDEX(Monthly!$C$76:$BJ$76,($R$2-1)*12+4) -> 2725901.6 | L41: =INDEX(Monthly!$C$76:$BJ$76,($R$2-1)*12+5) -> 2667243.8 | M41: =INDEX(Monthly!$C$76:$BJ$76,($R$2-1)*12+6) -> 2610768.5 | N41: =INDEX(Monthly!$C$76:$BJ$76,($R$2-1)*12+7) -> 2556421.6 | O41: =INDEX(Monthly!$C$76:$BJ$76,($R$2-1)*12+8) -> 2504150 | P41: =INDEX(Monthly!$C$76:$BJ$76,($R$2-1)*12+9) -> 2453902.2 | Q41: =INDEX(Monthly!$C$76:$BJ$76,($R$2-1)*12+10) -> 2405627.6 | R41: =INDEX(Monthly!$C$76:$BJ$76,($R$2-1)*12+11) -> 2359277.4 | S41: =INDEX(Monthly!$C$76:$BJ$76,($R$2-1)*12+12) -> 2314803.5
A42: Accounts receivable | B42: ='Balance Sheet'!B6 -> 5333.2481 | C42: ='Balance Sheet'!C6 -> 10462.475 | D42: ='Balance Sheet'!D6 -> 16071.669 | E42: ='Balance Sheet'!E6 -> 22561.633 | F42: ='Balance Sheet'!F6 -> 30385.013 | H42: =INDEX(Monthly!$C$60:$BJ$60,($R$2-1)*12+1) -> 734.47917 | I42: =INDEX(Monthly!$C$60:$BJ$60,($R$2-1)*12+2) -> 1207.4505 | J42: =INDEX(Monthly!$C$60:$BJ$60,($R$2-1)*12+3) -> 1668.5976 | K42: =INDEX(Monthly!$C$60:$BJ$60,($R$2-1)*12+4) -> 2118.216 | L42: =INDEX(Monthly!$C$60:$BJ$60,($R$2-1)*12+5) -> 2556.5939 | M42: =INDEX(Monthly!$C$60:$BJ$60,($R$2-1)*12+6) -> 2984.0124 | N42: =INDEX(Monthly!$C$60:$BJ$60,($R$2-1)*12+7) -> 3400.7454 | O42: =INDEX(Monthly!$C$60:$BJ$60,($R$2-1)*12+8) -> 3807.0601 | P42: =INDEX(Monthly!$C$60:$BJ$60,($R$2-1)*12+9) -> 4203.217 | Q42: =INDEX(Monthly!$C$60:$BJ$60,($R$2-1)*12+10) -> 4589.4699 | R42: =INDEX(Monthly!$C$60:$BJ$60,($R$2-1)*12+11) -> 4966.0665 | S42: =INDEX(Monthly!$C$60:$BJ$60,($R$2-1)*12+12) -> 5333.2481
A43: Inventory | B43: ='Balance Sheet'!B7 -> 0 | C43: ='Balance Sheet'!C7 -> 0 | D43: ='Balance Sheet'!D7 -> 0 | E43: ='Balance Sheet'!E7 -> 0 | F43: ='Balance Sheet'!F7 -> 0 | H43: =INDEX(Monthly!$C$61:$BJ$61,($R$2-1)*12+1) -> 0 | I43: =INDEX(Monthly!$C$61:$BJ$61,($R$2-1)*12+2) -> 0 | J43: =INDEX(Monthly!$C$61:$BJ$61,($R$2-1)*12+3) -> 0 | K43: =INDEX(Monthly!$C$61:$BJ$61,($R$2-1)*12+4) -> 0 | L43: =INDEX(Monthly!$C$61:$BJ$61,($R$2-1)*12+5) -> 0 | M43: =INDEX(Monthly!$C$61:$BJ$61,($R$2-1)*12+6) -> 0 | N43: =INDEX(Monthly!$C$61:$BJ$61,($R$2-1)*12+7) -> 0 | O43: =INDEX(Monthly!$C$61:$BJ$61,($R$2-1)*12+8) -> 0 | P43: =INDEX(Monthly!$C$61:$BJ$61,($R$2-1)*12+9) -> 0 | Q43: =INDEX(Monthly!$C$61:$BJ$61,($R$2-1)*12+10) -> 0 | R43: =INDEX(Monthly!$C$61:$BJ$61,($R$2-1)*12+11) -> 0 | S43: =INDEX(Monthly!$C$61:$BJ$61,($R$2-1)*12+12) -> 0
A44: Net fixed assets | B44: ='Balance Sheet'!B8 -> 13333.333 | C44: ='Balance Sheet'!C8 -> 6666.6667 | D44: ='Balance Sheet'!D8 -> 0 | E44: ='Balance Sheet'!E8 -> 0 | F44: ='Balance Sheet'!F8 -> 0 | H44: =INDEX(Monthly!$C$51:$BJ$51,($R$2-1)*12+1) -> 19444.444 | I44: =INDEX(Monthly!$C$51:$BJ$51,($R$2-1)*12+2) -> 18888.889 | J44: =INDEX(Monthly!$C$51:$BJ$51,($R$2-1)*12+3) -> 18333.333 | K44: =INDEX(Monthly!$C$51:$BJ$51,($R$2-1)*12+4) -> 17777.778 | L44: =INDEX(Monthly!$C$51:$BJ$51,($R$2-1)*12+5) -> 17222.222 | M44: =INDEX(Monthly!$C$51:$BJ$51,($R$2-1)*12+6) -> 16666.667 | N44: =INDEX(Monthly!$C$51:$BJ$51,($R$2-1)*12+7) -> 16111.111 | O44: =INDEX(Monthly!$C$51:$BJ$51,($R$2-1)*12+8) -> 15555.556 | P44: =INDEX(Monthly!$C$51:$BJ$51,($R$2-1)*12+9) -> 15000 | Q44: =INDEX(Monthly!$C$51:$BJ$51,($R$2-1)*12+10) -> 14444.444 | R44: =INDEX(Monthly!$C$51:$BJ$51,($R$2-1)*12+11) -> 13888.889 | S44: =INDEX(Monthly!$C$51:$BJ$51,($R$2-1)*12+12) -> 13333.333
A45: Total assets | B45: ='Balance Sheet'!B9 -> 2333470.1 | C45: ='Balance Sheet'!C9 -> 1546724.2 | D45: ='Balance Sheet'!D9 -> 428052.22 | E45: ='Balance Sheet'!E9 -> -1338637.2 | F45: ='Balance Sheet'!F9 -> -4260984.5 | H45: =INDEX(Monthly!$C$94:$BJ$94,($R$2-1)*12+1) -> 2935713.8 | I45: =INDEX(Monthly!$C$94:$BJ$94,($R$2-1)*12+2) -> 2870085.7 | J45: =INDEX(Monthly!$C$94:$BJ$94,($R$2-1)*12+3) -> 2806799.7 | K45: =INDEX(Monthly!$C$94:$BJ$94,($R$2-1)*12+4) -> 2745797.6 | L45: =INDEX(Monthly!$C$94:$BJ$94,($R$2-1)*12+5) -> 2687022.6 | M45: =INDEX(Monthly!$C$94:$BJ$94,($R$2-1)*12+6) -> 2630419.2 | N45: =INDEX(Monthly!$C$94:$BJ$94,($R$2-1)*12+7) -> 2575933.5 | O45: =INDEX(Monthly!$C$94:$BJ$94,($R$2-1)*12+8) -> 2523512.6 | P45: =INDEX(Monthly!$C$94:$BJ$94,($R$2-1)*12+9) -> 2473105.4 | Q45: =INDEX(Monthly!$C$94:$BJ$94,($R$2-1)*12+10) -> 2424661.6 | R45: =INDEX(Monthly!$C$94:$BJ$94,($R$2-1)*12+11) -> 2378132.3 | S45: =INDEX(Monthly!$C$94:$BJ$94,($R$2-1)*12+12) -> 2333470.1
A46: Accounts payable | B46: ='Balance Sheet'!B10 -> 3828.7027 | C46: ='Balance Sheet'!C10 -> 7462.4506 | D46: ='Balance Sheet'!D10 -> 11395.215 | E46: ='Balance Sheet'!E10 -> 15909.839 | F46: ='Balance Sheet'!F10 -> 21319.292 | H46: =INDEX(Monthly!$C$62:$BJ$62,($R$2-1)*12+1) -> 529.56528 | I46: =INDEX(Monthly!$C$62:$BJ$62,($R$2-1)*12+2) -> 870.23731 | J46: =INDEX(Monthly!$C$62:$BJ$62,($R$2-1)*12+3) -> 1202.1081 | K46: =INDEX(Monthly!$C$62:$BJ$62,($R$2-1)*12+4) -> 1525.4062 | L46: =INDEX(Monthly!$C$62:$BJ$62,($R$2-1)*12+5) -> 1840.3542 | M46: =INDEX(Monthly!$C$62:$BJ$62,($R$2-1)*12+6) -> 2147.1689 | N46: =INDEX(Monthly!$C$62:$BJ$62,($R$2-1)*12+7) -> 2446.0615 | O46: =INDEX(Monthly!$C$62:$BJ$62,($R$2-1)*12+8) -> 2737.2374 | P46: =INDEX(Monthly!$C$62:$BJ$62,($R$2-1)*12+9) -> 3020.897 | Q46: =INDEX(Monthly!$C$62:$BJ$62,($R$2-1)*12+10) -> 3297.2353 | R46: =INDEX(Monthly!$C$62:$BJ$62,($R$2-1)*12+11) -> 3566.4422 | S46: =INDEX(Monthly!$C$62:$BJ$62,($R$2-1)*12+12) -> 3828.7027
A47: Deferred revenue (annual plans, ~6 months unearned) | B47: ='Balance Sheet'!B11 -> 39704.508 | C47: ='Balance Sheet'!C11 -> 76664.533 | D47: ='Balance Sheet'!D11 -> 117179.09 | E47: ='Balance Sheet'!E11 -> 164139.61 | F47: ='Balance Sheet'!F11 -> 220818.92 | H47: =INDEX(Monthly!$C$66:$BJ$66,($R$2-1)*12+1) -> 7012.5 | I47: =INDEX(Monthly!$C$66:$BJ$66,($R$2-1)*12+2) -> 10374.788 | J47: =INDEX(Monthly!$C$66:$BJ$66,($R$2-1)*12+3) -> 13653.018 | K47: =INDEX(Monthly!$C$66:$BJ$66,($R$2-1)*12+4) -> 16849.292 | L47: =INDEX(Monthly!$C$66:$BJ$66,($R$2-1)*12+5) -> 19965.66 | M47: =INDEX(Monthly!$C$66:$BJ$66,($R$2-1)*12+6) -> 23004.119 | N47: =INDEX(Monthly!$C$66:$BJ$66,($R$2-1)*12+7) -> 25966.616 | O47: =INDEX(Monthly!$C$66:$BJ$66,($R$2-1)*12+8) -> 28855.05 | P47: =INDEX(Monthly!$C$66:$BJ$66,($R$2-1)*12+9) -> 31671.274 | Q47: =INDEX(Monthly!$C$66:$BJ$66,($R$2-1)*12+10) -> 34417.092 | R47: =INDEX(Monthly!$C$66:$BJ$66,($R$2-1)*12+11) -> 37094.265 | S47: =INDEX(Monthly!$C$66:$BJ$66,($R$2-1)*12+12) -> 39704.508
A48: Loan | B48: ='Balance Sheet'!B12 -> 0 | C48: ='Balance Sheet'!C12 -> 0 | D48: ='Balance Sheet'!D12 -> 0 | E48: ='Balance Sheet'!E12 -> 0 | F48: ='Balance Sheet'!F12 -> 0 | H48: =INDEX(Monthly!$C$57:$BJ$57,($R$2-1)*12+1) -> 0 | I48: =INDEX(Monthly!$C$57:$BJ$57,($R$2-1)*12+2) -> 0 | J48: =INDEX(Monthly!$C$57:$BJ$57,($R$2-1)*12+3) -> 0 | K48: =INDEX(Monthly!$C$57:$BJ$57,($R$2-1)*12+4) -> 0 | L48: =INDEX(Monthly!$C$57:$BJ$57,($R$2-1)*12+5) -> 0 | M48: =INDEX(Monthly!$C$57:$BJ$57,($R$2-1)*12+6) -> 0 | N48: =INDEX(Monthly!$C$57:$BJ$57,($R$2-1)*12+7) -> 0 | O48: =INDEX(Monthly!$C$57:$BJ$57,($R$2-1)*12+8) -> 0 | P48: =INDEX(Monthly!$C$57:$BJ$57,($R$2-1)*12+9) -> 0 | Q48: =INDEX(Monthly!$C$57:$BJ$57,($R$2-1)*12+10) -> 0 | R48: =INDEX(Monthly!$C$57:$BJ$57,($R$2-1)*12+11) -> 0 | S48: =INDEX(Monthly!$C$57:$BJ$57,($R$2-1)*12+12) -> 0
A49: Total liabilities | B49: ='Balance Sheet'!B13 -> 43533.211 | C49: ='Balance Sheet'!C13 -> 84126.984 | D49: ='Balance Sheet'!D13 -> 128574.31 | E49: ='Balance Sheet'!E13 -> 180049.45 | F49: ='Balance Sheet'!F13 -> 242138.21 | H49: =INDEX(Monthly!$C$95:$BJ$95,($R$2-1)*12+1) -> 7542.0653 | I49: =INDEX(Monthly!$C$95:$BJ$95,($R$2-1)*12+2) -> 11245.025 | J49: =INDEX(Monthly!$C$95:$BJ$95,($R$2-1)*12+3) -> 14855.126 | K49: =INDEX(Monthly!$C$95:$BJ$95,($R$2-1)*12+4) -> 18374.699 | L49: =INDEX(Monthly!$C$95:$BJ$95,($R$2-1)*12+5) -> 21806.014 | M49: =INDEX(Monthly!$C$95:$BJ$95,($R$2-1)*12+6) -> 25151.287 | N49: =INDEX(Monthly!$C$95:$BJ$95,($R$2-1)*12+7) -> 28412.677 | O49: =INDEX(Monthly!$C$95:$BJ$95,($R$2-1)*12+8) -> 31592.288 | P49: =INDEX(Monthly!$C$95:$BJ$95,($R$2-1)*12+9) -> 34692.171 | Q49: =INDEX(Monthly!$C$95:$BJ$95,($R$2-1)*12+10) -> 37714.327 | R49: =INDEX(Monthly!$C$95:$BJ$95,($R$2-1)*12+11) -> 40660.707 | S49: =INDEX(Monthly!$C$95:$BJ$95,($R$2-1)*12+12) -> 43533.211
A50: Paid-in capital | B50: ='Balance Sheet'!B14 -> 3000000 | C50: ='Balance Sheet'!C14 -> 3000000 | D50: ='Balance Sheet'!D14 -> 3000000 | E50: ='Balance Sheet'!E14 -> 3000000 | F50: ='Balance Sheet'!F14 -> 3000000 | H50: =INDEX(Monthly!$C$92:$BJ$92,($R$2-1)*12+1) -> 3000000 | I50: =INDEX(Monthly!$C$92:$BJ$92,($R$2-1)*12+2) -> 3000000 | J50: =INDEX(Monthly!$C$92:$BJ$92,($R$2-1)*12+3) -> 3000000 | K50: =INDEX(Monthly!$C$92:$BJ$92,($R$2-1)*12+4) -> 3000000 | L50: =INDEX(Monthly!$C$92:$BJ$92,($R$2-1)*12+5) -> 3000000 | M50: =INDEX(Monthly!$C$92:$BJ$92,($R$2-1)*12+6) -> 3000000 | N50: =INDEX(Monthly!$C$92:$BJ$92,($R$2-1)*12+7) -> 3000000 | O50: =INDEX(Monthly!$C$92:$BJ$92,($R$2-1)*12+8) -> 3000000 | P50: =INDEX(Monthly!$C$92:$BJ$92,($R$2-1)*12+9) -> 3000000 | Q50: =INDEX(Monthly!$C$92:$BJ$92,($R$2-1)*12+10) -> 3000000 | R50: =INDEX(Monthly!$C$92:$BJ$92,($R$2-1)*12+11) -> 3000000 | S50: =INDEX(Monthly!$C$92:$BJ$92,($R$2-1)*12+12) -> 3000000
A51: Retained earnings | B51: ='Balance Sheet'!B15 -> -710063.14 | C51: ='Balance Sheet'!C15 -> -1537402.8 | D51: ='Balance Sheet'!D15 -> -2700522.1 | E51: ='Balance Sheet'!E15 -> -4518686.6 | F51: ='Balance Sheet'!F15 -> -7503122.7 | H51: =INDEX(Monthly!$C$93:$BJ$93,($R$2-1)*12+1) -> -71828.246 | I51: =INDEX(Monthly!$C$93:$BJ$93,($R$2-1)*12+2) -> -141159.34 | J51: =INDEX(Monthly!$C$93:$BJ$93,($R$2-1)*12+3) -> -208055.41 | K51: =INDEX(Monthly!$C$93:$BJ$93,($R$2-1)*12+4) -> -272577.08 | L51: =INDEX(Monthly!$C$93:$BJ$93,($R$2-1)*12+5) -> -334783.43 | M51: =INDEX(Monthly!$C$93:$BJ$93,($R$2-1)*12+6) -> -394732.08 | N51: =INDEX(Monthly!$C$93:$BJ$93,($R$2-1)*12+7) -> -452479.22 | O51: =INDEX(Monthly!$C$93:$BJ$93,($R$2-1)*12+8) -> -508079.65 | P51: =INDEX(Monthly!$C$93:$BJ$93,($R$2-1)*12+9) -> -561586.8 | Q51: =INDEX(Monthly!$C$93:$BJ$93,($R$2-1)*12+10) -> -613052.78 | R51: =INDEX(Monthly!$C$93:$BJ$93,($R$2-1)*12+11) -> -662528.37 | S51: =INDEX(Monthly!$C$93:$BJ$93,($R$2-1)*12+12) -> -710063.14
A52: Total equity | B52: ='Balance Sheet'!B16 -> 2289936.9 | C52: ='Balance Sheet'!C16 -> 1462597.2 | D52: ='Balance Sheet'!D16 -> 299477.91 | E52: ='Balance Sheet'!E16 -> -1518686.6 | F52: ='Balance Sheet'!F16 -> -4503122.7 | H52: =INDEX(Monthly!$C$96:$BJ$96,($R$2-1)*12+1) -> 2928171.8 | I52: =INDEX(Monthly!$C$96:$BJ$96,($R$2-1)*12+2) -> 2858840.7 | J52: =INDEX(Monthly!$C$96:$BJ$96,($R$2-1)*12+3) -> 2791944.6 | K52: =INDEX(Monthly!$C$96:$BJ$96,($R$2-1)*12+4) -> 2727422.9 | L52: =INDEX(Monthly!$C$96:$BJ$96,($R$2-1)*12+5) -> 2665216.6 | M52: =INDEX(Monthly!$C$96:$BJ$96,($R$2-1)*12+6) -> 2605267.9 | N52: =INDEX(Monthly!$C$96:$BJ$96,($R$2-1)*12+7) -> 2547520.8 | O52: =INDEX(Monthly!$C$96:$BJ$96,($R$2-1)*12+8) -> 2491920.3 | P52: =INDEX(Monthly!$C$96:$BJ$96,($R$2-1)*12+9) -> 2438413.2 | Q52: =INDEX(Monthly!$C$96:$BJ$96,($R$2-1)*12+10) -> 2386947.2 | R52: =INDEX(Monthly!$C$96:$BJ$96,($R$2-1)*12+11) -> 2337471.6 | S52: =INDEX(Monthly!$C$96:$BJ$96,($R$2-1)*12+12) -> 2289936.9
A53: Total liabilities & equity | B53: ='Balance Sheet'!B17 -> 2333470.1 | C53: ='Balance Sheet'!C17 -> 1546724.2 | D53: ='Balance Sheet'!D17 -> 428052.22 | E53: ='Balance Sheet'!E17 -> -1338637.2 | F53: ='Balance Sheet'!F17 -> -4260984.5 | H53: =INDEX(Monthly!$C$97:$BJ$97,($R$2-1)*12+1) -> 2935713.8 | I53: =INDEX(Monthly!$C$97:$BJ$97,($R$2-1)*12+2) -> 2870085.7 | J53: =INDEX(Monthly!$C$97:$BJ$97,($R$2-1)*12+3) -> 2806799.7 | K53: =INDEX(Monthly!$C$97:$BJ$97,($R$2-1)*12+4) -> 2745797.6 | L53: =INDEX(Monthly!$C$97:$BJ$97,($R$2-1)*12+5) -> 2687022.6 | M53: =INDEX(Monthly!$C$97:$BJ$97,($R$2-1)*12+6) -> 2630419.2 | N53: =INDEX(Monthly!$C$97:$BJ$97,($R$2-1)*12+7) -> 2575933.5 | O53: =INDEX(Monthly!$C$97:$BJ$97,($R$2-1)*12+8) -> 2523512.6 | P53: =INDEX(Monthly!$C$97:$BJ$97,($R$2-1)*12+9) -> 2473105.4 | Q53: =INDEX(Monthly!$C$97:$BJ$97,($R$2-1)*12+10) -> 2424661.6 | R53: =INDEX(Monthly!$C$97:$BJ$97,($R$2-1)*12+11) -> 2378132.3 | S53: =INDEX(Monthly!$C$97:$BJ$97,($R$2-1)*12+12) -> 2333470.1

Sheet Scenarios
A1: Scenarios — Low / Base / High | H1: =HYPERLINK("#'Cover'!A1","◂ Contents") -> ◂ Contents
A2: All three scenarios calculated side by side, live: change any input and every column updates. Active = the scenario chosen on the Dashboard.
A5: Key drivers
A6: Driver | B6: Low | C6: Base | D6: High | E6: Active
A7: Paying customers at start (#) | B7: =Inputs!$B$7 -> 30 | C7: =Inputs!$C$7 -> 30 | D7: =Inputs!$D$7 -> 30 | E7: =Inputs!$E$7 -> 30
A8: Average MRR per new customer (ARPA) ($ / month) | B8: =Inputs!$B$8 -> 79 | C8: =Inputs!$C$8 -> 99 | D8: =Inputs!$D$8 -> 119 | E8: =Inputs!$E$8 -> 99
A9: Customer churn per month (%) | B9: =Inputs!$B$10 -> 0.045 | C9: =Inputs!$C$10 -> 0.03 | D9: =Inputs!$D$10 -> 0.02 | E9: =Inputs!$E$10 -> 0.03
A10: Organic / referral new customers per month (year 1) (# / month) | B10: =Inputs!$B$12 -> 8 | C10: =Inputs!$C$12 -> 12 | D10: =Inputs!$D$12 -> 18 | E10: =Inputs!$E$12 -> 12
A11: Paid marketing budget per month (year 1) ($ / month) | B11: =Inputs!$B$14 -> 8000 | C11: =Inputs!$C$14 -> 8000 | D11: =Inputs!$D$14 -> 8000 | E11: =Inputs!$E$14 -> 8000
A12: Paid customer acquisition cost (CAC) ($) | B12: =Inputs!$B$16 -> 600 | C12: =Inputs!$C$16 -> 450 | D12: =Inputs!$D$16 -> 350 | E12: =Inputs!$E$16 -> 450
A13: Equity raised at start ($) | B13: =Inputs!$B$46 -> 3000000 | C13: =Inputs!$C$46 -> 3000000 | D13: =Inputs!$D$46 -> 3000000 | E13: =Inputs!$E$46 -> 3000000
A15: Results by scenario ($'000)
A16: Output | B16: Low | C16: Base | D16: High | E16: Active
A17: Revenue — final year | B17: =F30 -> 624519.48 | C17: =F31 -> 1939020.9 | D17: =F32 -> 5409456.9 | E17: ='P&L'!F5 -> 1939020.9
A18: Revenue — whole plan | B18: =SUM(B30:F30) -> 1947132 | C18: =SUM(B31:F31) -> 5153329.9 | D18: =SUM(B32:F32) -> 12539642 | E18: =SUM('P&L'!$B$5:$F$5) -> 5153329.9
A19: EBITDA — final year | B19: =F36 -> -4170384.4 | C19: =F37 -> -2984436 | D19: =F38 -> 229990.22 | E19: ='P&L'!F15 -> -2984436
A20: EBITDA margin — final year | B20: =IF(B17=0,0,B19/B17) -> -6.6777492 | C20: =IF(C17=0,0,C19/C17) -> -1.5391458 | D20: =IF(D17=0,0,D19/D17) -> 0.042516324 | E20: =IF(E17=0,0,E19/E17) -> -1.5391458
A21: Net income — final year | B21: =F42 -> -4170384.4 | C21: =F43 -> -2984436 | D21: =F44 -> 229990.22 | E21: ='P&L'!F22 -> -2984436
A22: Net income — whole plan | B22: =SUM(B42:F42) -> -10409191 | C22: =SUM(B43:F43) -> -7503122.7 | D22: =SUM(B44:F44) -> -637423.03 | E22: =SUM('P&L'!$B$22:$F$22) -> -7503122.7
A23: Cash at the end of the plan | B23: =F48 -> -7342086.9 | C23: =F49 -> -4291369.5 | D23: =F50 -> 2972134.9 | E23: ='Balance Sheet'!F5 -> -4291369.5
A24: Lowest cash balance | B24: =MIN('Scenario calc'!$C$78:$BJ$78) -> -7342086.9 | C24: =MIN('Scenario calc'!$C$191:$BJ$191) -> -4291369.5 | D24: =MIN('Scenario calc'!$C$304:$BJ$304) -> 2138580.4 | E24: ='Break-even'!B18 -> -4291369.5
A25: Lowest cash point (month #) | B25: =MATCH(MIN('Scenario calc'!$C$78:$BJ$78),'Scenario calc'!$C$78:$BJ$78,0) -> 60 | C25: =MATCH(MIN('Scenario calc'!$C$191:$BJ$191),'Scenario calc'!$C$191:$BJ$191,0) -> 60 | D25: =MATCH(MIN('Scenario calc'!$C$304:$BJ$304),'Scenario calc'!$C$304:$BJ$304,0) -> 30 | E25: ='Break-even'!B6 -> 60
A26: Funding required (incl. cash buffer) | B26: =SUMPRODUCT(--('Scenario calc'!$C$6:$BJ$6<=B25),'Scenario calc'!$C$49:$BJ$49)-SUMPRODUCT(--('Scenario calc'!$C$6:$BJ$6<=B25),'Scenario calc'!$C$72:$BJ$72)-SUMPRODUCT(--('Scenario calc'!$C$6:$BJ$6<=B25),'Scenario calc'!$C$58:$BJ$58)+Inputs!$B$61 -> 10567087 | C26: =SUMPRODUCT(--('Scenario calc'!$C$119:$BJ$119<=C25),'Scenario calc'!$C$162:$BJ$162)-SUMPRODUCT(--('Scenario calc'!$C$119:$BJ$119<=C25),'Scenario calc'!$C$185:$BJ$185)-SUMPRODUCT(--('Scenario calc'!$C$119:$BJ$119<=C25),'Scenario calc'!$C$171:$BJ$171)+Inputs!$C$61 -> 7516369.5 | D26: =SUMPRODUCT(--('Scenario calc'!$C$232:$BJ$232<=D25),'Scenario calc'!$C$275:$BJ$275)-SUMPRODUCT(--('Scenario calc'!$C$232:$BJ$232<=D25),'Scenario calc'!$C$298:$BJ$298)-SUMPRODUCT(--('Scenario calc'!$C$232:$BJ$232<=D25),'Scenario calc'!$C$284:$BJ$284)+Inputs!$D$61 -> 1086419.6 | E26: ='Break-even'!B12 -> 7516369.5
A28: Revenue by year ($'000)
A29: Scenario | B29: 1 | C29: 2 | D29: 3 | E29: 4 | F29: 5
A30: Low | B30: =SUMIF('Scenario calc'!$C$7:$BJ$7,B$29,'Scenario calc'!$C$26:$BJ$26) -> 125924.63 | C30: =SUMIF('Scenario calc'!$C$7:$BJ$7,C$29,'Scenario calc'!$C$26:$BJ$26) -> 280162.87 | D30: =SUMIF('Scenario calc'!$C$7:$BJ$7,D$29,'Scenario calc'!$C$26:$BJ$26) -> 402920.19 | E30: =SUMIF('Scenario calc'!$C$7:$BJ$7,E$29,'Scenario calc'!$C$26:$BJ$26) -> 513604.81 | F30: =SUMIF('Scenario calc'!$C$7:$BJ$7,F$29,'Scenario calc'!$C$26:$BJ$26) -> 624519.48
A31: Base | B31: =SUMIF('Scenario calc'!$C$120:$BJ$120,B$29,'Scenario calc'!$C$139:$BJ$139) -> 225414.94 | C31: =SUMIF('Scenario calc'!$C$120:$BJ$120,C$29,'Scenario calc'!$C$139:$BJ$139) -> 591123.33 | D31: =SUMIF('Scenario calc'!$C$120:$BJ$120,D$29,'Scenario calc'!$C$139:$BJ$139) -> 979388.56 | E31: =SUMIF('Scenario calc'!$C$120:$BJ$120,E$29,'Scenario calc'!$C$139:$BJ$139) -> 1418382.1 | F31: =SUMIF('Scenario calc'!$C$120:$BJ$120,F$29,'Scenario calc'!$C$139:$BJ$139) -> 1939020.9
A32: High | B32: =SUMIF('Scenario calc'!$C$233:$BJ$233,B$29,'Scenario calc'!$C$252:$BJ$252) -> 378410.1 | C32: =SUMIF('Scenario calc'!$C$233:$BJ$233,C$29,'Scenario calc'!$C$252:$BJ$252) -> 1133100.3 | D32: =SUMIF('Scenario calc'!$C$233:$BJ$233,D$29,'Scenario calc'!$C$252:$BJ$252) -> 2128410.7 | E32: =SUMIF('Scenario calc'!$C$233:$BJ$233,E$29,'Scenario calc'!$C$252:$BJ$252) -> 3490263.9 | F32: =SUMIF('Scenario calc'!$C$233:$BJ$233,F$29,'Scenario calc'!$C$252:$BJ$252) -> 5409456.9
A34: EBITDA by year ($'000)
A35: Scenario | B35: 1 | C35: 2 | D35: 3 | E35: 4 | F35: 5
A36: Low | B36: =SUMIF('Scenario calc'!$C$7:$BJ$7,B$35,'Scenario calc'!$C$37:$BJ$37) -> -795768.28 | C36: =SUMIF('Scenario calc'!$C$7:$BJ$7,C$35,'Scenario calc'!$C$37:$BJ$37) -> -1105455.8 | D36: =SUMIF('Scenario calc'!$C$7:$BJ$7,D$35,'Scenario calc'!$C$37:$BJ$37) -> -1680568.6 | E36: =SUMIF('Scenario calc'!$C$7:$BJ$7,E$35,'Scenario calc'!$C$37:$BJ$37) -> -2637014 | F36: =SUMIF('Scenario calc'!$C$7:$BJ$7,F$35,'Scenario calc'!$C$37:$BJ$37) -> -4170384.4
A37: Base | B37: =SUMIF('Scenario calc'!$C$120:$BJ$120,B$35,'Scenario calc'!$C$150:$BJ$150) -> -703396.48 | C37: =SUMIF('Scenario calc'!$C$120:$BJ$120,C$35,'Scenario calc'!$C$150:$BJ$150) -> -820672.96 | D37: =SUMIF('Scenario calc'!$C$120:$BJ$120,D$35,'Scenario calc'!$C$150:$BJ$150) -> -1156452.6 | E37: =SUMIF('Scenario calc'!$C$120:$BJ$120,E$35,'Scenario calc'!$C$150:$BJ$150) -> -1818164.6 | F37: =SUMIF('Scenario calc'!$C$120:$BJ$120,F$35,'Scenario calc'!$C$150:$BJ$150) -> -2984436
A38: High | B38: =SUMIF('Scenario calc'!$C$233:$BJ$233,B$35,'Scenario calc'!$C$263:$BJ$263) -> -558259.05 | C38: =SUMIF('Scenario calc'!$C$233:$BJ$233,C$35,'Scenario calc'!$C$263:$BJ$263) -> -311798.28 | D38: =SUMIF('Scenario calc'!$C$233:$BJ$233,D$35,'Scenario calc'!$C$263:$BJ$263) -> -84273.989 | E38: =SUMIF('Scenario calc'!$C$233:$BJ$233,E$35,'Scenario calc'!$C$263:$BJ$263) -> 106918.07 | F38: =SUMIF('Scenario calc'!$C$233:$BJ$233,F$35,'Scenario calc'!$C$263:$BJ$263) -> 229990.22
A40: Net income by year ($'000)
A41: Scenario | B41: 1 | C41: 2 | D41: 3 | E41: 4 | F41: 5
A42: Low | B42: =SUMIF('Scenario calc'!$C$7:$BJ$7,B$41,'Scenario calc'!$C$46:$BJ$46) -> -802434.94 | C42: =SUMIF('Scenario calc'!$C$7:$BJ$7,C$41,'Scenario calc'!$C$46:$BJ$46) -> -1112122.4 | D42: =SUMIF('Scenario calc'!$C$7:$BJ$7,D$41,'Scenario calc'!$C$46:$BJ$46) -> -1687235.3 | E42: =SUMIF('Scenario calc'!$C$7:$BJ$7,E$41,'Scenario calc'!$C$46:$BJ$46) -> -2637014 | F42: =SUMIF('Scenario calc'!$C$7:$BJ$7,F$41,'Scenario calc'!$C$46:$BJ$46) -> -4170384.4
A43: Base | B43: =SUMIF('Scenario calc'!$C$120:$BJ$120,B$41,'Scenario calc'!$C$159:$BJ$159) -> -710063.14 | C43: =SUMIF('Scenario calc'!$C$120:$BJ$120,C$41,'Scenario calc'!$C$159:$BJ$159) -> -827339.63 | D43: =SUMIF('Scenario calc'!$C$120:$BJ$120,D$41,'Scenario calc'!$C$159:$BJ$159) -> -1163119.3 | E43: =SUMIF('Scenario calc'!$C$120:$BJ$120,E$41,'Scenario calc'!$C$159:$BJ$159) -> -1818164.6 | F43: =SUMIF('Scenario calc'!$C$120:$BJ$120,F$41,'Scenario calc'!$C$159:$BJ$159) -> -2984436
A44: High | B44: =SUMIF('Scenario calc'!$C$233:$BJ$233,B$41,'Scenario calc'!$C$272:$BJ$272) -> -564925.72 | C44: =SUMIF('Scenario calc'!$C$233:$BJ$233,C$41,'Scenario calc'!$C$272:$BJ$272) -> -318464.95 | D44: =SUMIF('Scenario calc'!$C$233:$BJ$233,D$41,'Scenario calc'!$C$272:$BJ$272) -> -90940.655 | E44: =SUMIF('Scenario calc'!$C$233:$BJ$233,E$41,'Scenario calc'!$C$272:$BJ$272) -> 106918.07 | F44: =SUMIF('Scenario calc'!$C$233:$BJ$233,F$41,'Scenario calc'!$C$272:$BJ$272) -> 229990.22
A46: Cash at year end by year ($'000)
A47: Scenario | B47: 1 | C47: 2 | D47: 3 | E47: 4 | F47: 5
A48: Low | B48: =INDEX('Scenario calc'!$C$78:$BJ$78,B$47*12) -> 2204800.8 | C48: =INDEX('Scenario calc'!$C$78:$BJ$78,C$47*12) -> 1112631.9 | D48: =INDEX('Scenario calc'!$C$78:$BJ$78,D$47*12) -> -556667.82 | E48: =INDEX('Scenario calc'!$C$78:$BJ$78,E$47*12) -> -3182927.9 | F48: =INDEX('Scenario calc'!$C$78:$BJ$78,F$47*12) -> -7342086.9
A49: Base | B49: =INDEX('Scenario calc'!$C$191:$BJ$191,B$47*12) -> 2314803.5 | C49: =INDEX('Scenario calc'!$C$191:$BJ$191,C$47*12) -> 1529595.1 | D49: =INDEX('Scenario calc'!$C$191:$BJ$191,D$47*12) -> 411980.55 | E49: =INDEX('Scenario calc'!$C$191:$BJ$191,E$47*12) -> -1361198.8 | F49: =INDEX('Scenario calc'!$C$191:$BJ$191,F$47*12) -> -4291369.5
A50: High | B50: =INDEX('Scenario calc'!$C$304:$BJ$304,B$47*12) -> 2487622.2 | C50: =INDEX('Scenario calc'!$C$304:$BJ$304,C$47*12) -> 2255241.5 | D50: =INDEX('Scenario calc'!$C$304:$BJ$304,D$47*12) -> 2277434.8 | E50: =INDEX('Scenario calc'!$C$304:$BJ$304,E$47*12) -> 2531964.3 | F50: =INDEX('Scenario calc'!$C$304:$BJ$304,F$47*12) -> 2972134.9

Sheet Break-even
A1: Startup costs, funding need and break-even | H1: =HYPERLINK("#'Cover'!A1","◂ Contents") -> ◂ Contents
A2: Live for the selected scenario. Periods are counted in months from the start of the plan.
A3: Scenario shown | B3: =CHOOSE(Dashboard!$B$4,"Low","Base","High") -> Base
A5: Startup costs & funding need (up to the lowest cash point)
A6: Lowest cash point (month #) | B6: =MATCH(MIN(Monthly!$C$76:$BJ$76),Monthly!$C$76:$BJ$76,0) -> 60
A7: Capital spending up to the lowest cash point | B7: =SUMPRODUCT(--(Monthly!$C$4:$BJ$4<=$B$6),Monthly!$C$47:$BJ$47) -> 20000
A8: Operating cash burn up to the lowest cash point | B8: =-SUMPRODUCT(--(Monthly!$C$4:$BJ$4<=$B$6),Monthly!$C$70:$BJ$70) -> 7271369.5 | D8: Losses and working capital before the business funds itself
A9: Loan repayments up to the lowest cash point | B9: =-SUMPRODUCT(--(Monthly!$C$4:$BJ$4<=$B$6),Monthly!$C$56:$BJ$56) -> 0
A10: Total uses of funds | B10: =B7+B8+B9 -> 7291369.5
A11: Minimum cash buffer to keep | B11: =Inputs!$E$61 -> 225000 | D11: Input on the Inputs sheet
A12: Funding required (uses + buffer) | B12: =B10+B11 -> 7516369.5
A14: Equity raised | B14: =Inputs!$E$46 -> 3000000
A15: Loan drawn | B15: =Inputs!$E$47 -> 0
A16: Total sources of funds | B16: =B14+B15 -> 3000000
A17: Funding surplus / (shortfall) | B17: =B16-B12 -> -4516369.5 | D17: Negative = raise at least this much more
A18: Lowest cash balance in the plan | B18: =MIN(Monthly!$C$76:$BJ$76) -> -4291369.5 | D18: Equals sources minus uses
A20: Break-even timing
A21: First month with positive EBITDA (month #) | B21: =IFERROR(MATCH(1,Monthly!$C$77:$BJ$77,0),"Not within horizon") -> Not within horizon
A22: First month with positive net income (month #) | B22: =IFERROR(MATCH(1,Monthly!$C$84:$BJ$84,0),"Not within horizon") -> Not within horizon
A23: Cash invested paid back (month #) | B23: =IF(MIN(Monthly!$C$86:$BJ$86)>=0,"No investment to pay back",IFERROR(MATCH(1,Monthly!$C$88:$BJ$88,0),"Not within horizon")) -> Not within horizon | D23: Cumulative operating + investing cash flow back to zero
A25: Annual break-even revenue
A26: Year # | B26: 1 | C26: 2 | D26: 3 | E26: 4 | F26: 5
B27: Year 1 | C27: Year 2 | D27: Year 3 | E27: Year 4 | F27: Year 5
A28: Revenue | B28: =SUMIF(Monthly!$C$5:$BJ$5,B$26,Monthly!$C$24:$BJ$24) -> 225414.94 | C28: =SUMIF(Monthly!$C$5:$BJ$5,C$26,Monthly!$C$24:$BJ$24) -> 591123.33 | D28: =SUMIF(Monthly!$C$5:$BJ$5,D$26,Monthly!$C$24:$BJ$24) -> 979388.56 | E28: =SUMIF(Monthly!$C$5:$BJ$5,E$26,Monthly!$C$24:$BJ$24) -> 1418382.1 | F28: =SUMIF(Monthly!$C$5:$BJ$5,F$26,Monthly!$C$24:$BJ$24) -> 1939020.9
A29: Gross profit | B29: =SUMIF(Monthly!$C$5:$BJ$5,B$26,Monthly!$C$26:$BJ$26) -> 198403.52 | C29: =SUMIF(Monthly!$C$5:$BJ$5,C$26,Monthly!$C$26:$BJ$26) -> 520687.04 | D29: =SUMIF(Monthly!$C$5:$BJ$5,D$26,Monthly!$C$26:$BJ$26) -> 863384.95 | E29: =SUMIF(Monthly!$C$5:$BJ$5,E$26,Monthly!$C$26:$BJ$26) -> 1251317.7 | F29: =SUMIF(Monthly!$C$5:$BJ$5,F$26,Monthly!$C$26:$BJ$26) -> 1711809.6
A30: Gross margin (contribution) | B30: =IF(B28=0,0,B29/B28) -> 0.88017025 | C30: =IF(C28=0,0,C29/C28) -> 0.88084332 | D30: =IF(D28=0,0,D29/D28) -> 0.88155507 | E30: =IF(E28=0,0,E29/E28) -> 0.88221481 | F30: =IF(F28=0,0,F29/F28) -> 0.88282162
A31: Operating expenses (treated as fixed) | B31: =-SUMIF(Monthly!$C$5:$BJ$5,B$26,Monthly!$C$34:$BJ$34) -> 901800 | C31: =-SUMIF(Monthly!$C$5:$BJ$5,C$26,Monthly!$C$34:$BJ$34) -> 1341360 | D31: =-SUMIF(Monthly!$C$5:$BJ$5,D$26,Monthly!$C$34:$BJ$34) -> 2019837.6 | E31: =-SUMIF(Monthly!$C$5:$BJ$5,E$26,Monthly!$C$34:$BJ$34) -> 3069482.3 | F31: =-SUMIF(Monthly!$C$5:$BJ$5,F$26,Monthly!$C$34:$BJ$34) -> 4696245.6
A32: Break-even revenue (EBITDA = 0) | B32: =IF(B30>0,B31/B30,"n/a") -> 1024574.5 | C32: =IF(C30>0,C31/C30,"n/a") -> 1522813.4 | D32: =IF(D30>0,D31/D30,"n/a") -> 2291221.1 | E32: =IF(E30>0,E31/E30,"n/a") -> 3479291.2 | F32: =IF(F30>0,F31/F30,"n/a") -> 5319586.1
A33: Margin of safety (revenue above break-even) | B33: =IF(AND(ISNUMBER(B32),B28>0),(B28-B32)/B28,"n/a") -> -3.5452822 | C33: =IF(AND(ISNUMBER(C32),C28>0),(C28-C32)/C28,"n/a") -> -1.5761348 | D33: =IF(AND(ISNUMBER(D32),D28>0),(D28-D32)/D28,"n/a") -> -1.3394404 | E33: =IF(AND(ISNUMBER(E32),E28>0),(E28-E32)/E28,"n/a") -> -1.453 | F33: =IF(AND(ISNUMBER(F32),F28>0),(F28-F32)/F28,"n/a") -> -1.7434392
A35: Simplification: cost of sales is treated as variable and operating expenses as fixed, so break-even revenue = operating expenses ÷ gross margin.

Sheet Valuation
A1: Discounted cash flow valuation | H1: =HYPERLINK("#'Cover'!A1","◂ Contents") -> ◂ Contents
A2: Enterprise value at the start of the plan, before the funding raised in period 1. Year-end discounting.
A3: Scenario shown | B3: =CHOOSE(Dashboard!$B$4,"Low","Base","High") -> Base
A5: Assumptions (active scenario, from the Inputs sheet)
A6: Discount rate (WACC) | B6: =Inputs!$E$64 -> 0.2
A7: Terminal growth rate | B7: =Inputs!$E$65 -> 0.02
A8: Exit multiple (EV ÷ final-year EBITDA) | B8: =Inputs!$E$66 -> 4.5
A9: Tax rate (for the interest tax shield) | B9: =Inputs!$E$58 -> 0.21
A10: Sensitivity step: WACC | B10: =Inputs!$E$67 -> 0.01
A11: Sensitivity step: terminal growth | B11: =Inputs!$E$68 -> 0.005
A13: Free cash flow by year
A14: Year # | B14: 1 | C14: 2 | D14: 3 | E14: 4 | F14: 5
B15: Year 1 | C15: Year 2 | D15: Year 3 | E15: Year 4 | F15: Year 5
A16: EBITDA | B16: =SUMIF(Monthly!$C$5:$BJ$5,B$14,Monthly!$C$35:$BJ$35) -> -703396.48 | C16: =SUMIF(Monthly!$C$5:$BJ$5,C$14,Monthly!$C$35:$BJ$35) -> -820672.96 | D16: =SUMIF(Monthly!$C$5:$BJ$5,D$14,Monthly!$C$35:$BJ$35) -> -1156452.6 | E16: =SUMIF(Monthly!$C$5:$BJ$5,E$14,Monthly!$C$35:$BJ$35) -> -1818164.6 | F16: =SUMIF(Monthly!$C$5:$BJ$5,F$14,Monthly!$C$35:$BJ$35) -> -2984436
A17: Unlevered free cash flow | B17: =SUMIF(Monthly!$C$5:$BJ$5,B$14,Monthly!$C$89:$BJ$89) -> -685196.51 | C17: =SUMIF(Monthly!$C$5:$BJ$5,C$14,Monthly!$C$89:$BJ$89) -> -785208.42 | D17: =SUMIF(Monthly!$C$5:$BJ$5,D$14,Monthly!$C$89:$BJ$89) -> -1117614.5 | E17: =SUMIF(Monthly!$C$5:$BJ$5,E$14,Monthly!$C$89:$BJ$89) -> -1773179.4 | F17: =SUMIF(Monthly!$C$5:$BJ$5,F$14,Monthly!$C$89:$BJ$89) -> -2930170.7
A18: Discount factor | B18: =1/(1+Inputs!$E$64)^B$14 -> 0.83333333 | C18: =1/(1+Inputs!$E$64)^C$14 -> 0.69444444 | D18: =1/(1+Inputs!$E$64)^D$14 -> 0.5787037 | E18: =1/(1+Inputs!$E$64)^E$14 -> 0.48225309 | F18: =1/(1+Inputs!$E$64)^F$14 -> 0.40187757
A19: Present value of free cash flow | B19: =B17*B18 -> -570997.1 | C19: =C17*C18 -> -545283.62 | D19: =D17*D18 -> -646767.66 | E19: =E17*E18 -> -855121.23 | F19: =F17*F18 -> -1177569.9
A21: Enterprise value
B22: Perpetual growth | C22: Exit multiple
A23: Present value of the plan's free cash flows | B23: =SUM($B$19:$F$19) -> -3795739.5 | C23: =B23 -> -3795739.5
A24: Final-year free cash flow | final-year EBITDA | B24: =$F$17 -> -2930170.7 | C24: =$F$16 -> -2984436
A25: Terminal value at the end of year 5 | B25: =IF($B$6>$B$7,B24*(1+$B$7)/($B$6-$B$7),0) -> -16604300 | C25: =C24*$B$8 -> -13429962
A26: Present value of the terminal value | B26: =B25/(1+$B$6)^$F$14 -> -6672895.9 | C26: =C25/(1+$B$6)^$F$14 -> -5397200.6
A27: Enterprise value | B27: =B23+B26 -> -10468635 | C27: =C23+C26 -> -9192940.1
A28: Terminal value share of enterprise value | B28: =IF(B27<>0,B26/B27,0) -> 0.63741793 | C28: =IF(C27<>0,C26/C27,0) -> 0.58710277
A29: Cross-check: implied exit multiple | implied perpetual growth | B29: =IF(C24>0,B25/C24,"n/a") -> n/a | C29: =IF(C25+B24<>0,(C25*$B$6-B24)/(C25+B24),"n/a") -> -0.014925198
A30: Enterprise value — average of the two methods | B30: =AVERAGE(B27,C27) -> -9830787.7
A32: Sensitivity: enterprise value (perpetual growth) by WACC and terminal growth
A33: WACC ↓ · terminal growth → | B33: =$B$7+(-2)*$B$11 -> 0.01 | C33: =$B$7+(-1)*$B$11 -> 0.015 | D33: =$B$7+(0)*$B$11 -> 0.02 | E33: =$B$7+(1)*$B$11 -> 0.025 | F33: =$B$7+(2)*$B$11 -> 0.03
A34: =$B$6+(-2)*$B$10 -> 0.18 | B34: =IF($A34>B$33,SUMPRODUCT($B$17:$F$17/(1+$A34)^$B$14:$F$14)+$F$17*(1+B$33)/($A34-B$33)/(1+$A34)^$F$14,"n/a") -> -11629691 | C34: =IF($A34>C$33,SUMPRODUCT($B$17:$F$17/(1+$A34)^$B$14:$F$14)+$F$17*(1+C$33)/($A34-C$33)/(1+$A34)^$F$14,"n/a") -> -11899094 | D34: =IF($A34>D$33,SUMPRODUCT($B$17:$F$17/(1+$A34)^$B$14:$F$14)+$F$17*(1+D$33)/($A34-D$33)/(1+$A34)^$F$14,"n/a") -> -12185334 | E34: =IF($A34>E$33,SUMPRODUCT($B$17:$F$17/(1+$A34)^$B$14:$F$14)+$F$17*(1+E$33)/($A34-E$33)/(1+$A34)^$F$14,"n/a") -> -12490042 | F34: =IF($A34>F$33,SUMPRODUCT($B$17:$F$17/(1+$A34)^$B$14:$F$14)+$F$17*(1+F$33)/($A34-F$33)/(1+$A34)^$F$14,"n/a") -> -12815063
A35: =$B$6+(-1)*$B$10 -> 0.19 | B35: =IF($A35>B$33,SUMPRODUCT($B$17:$F$17/(1+$A35)^$B$14:$F$14)+$F$17*(1+B$33)/($A35-B$33)/(1+$A35)^$F$14,"n/a") -> -10795413 | C35: =IF($A35>C$33,SUMPRODUCT($B$17:$F$17/(1+$A35)^$B$14:$F$14)+$F$17*(1+C$33)/($A35-C$33)/(1+$A35)^$F$14,"n/a") -> -11027347 | D35: =IF($A35>D$33,SUMPRODUCT($B$17:$F$17/(1+$A35)^$B$14:$F$14)+$F$17*(1+D$33)/($A35-D$33)/(1+$A35)^$F$14,"n/a") -> -11272924 | E35: =IF($A35>E$33,SUMPRODUCT($B$17:$F$17/(1+$A35)^$B$14:$F$14)+$F$17*(1+E$33)/($A35-E$33)/(1+$A35)^$F$14,"n/a") -> -11533385 | F35: =IF($A35>F$33,SUMPRODUCT($B$17:$F$17/(1+$A35)^$B$14:$F$14)+$F$17*(1+F$33)/($A35-F$33)/(1+$A35)^$F$14,"n/a") -> -11810125
A36: =$B$6+(0)*$B$10 -> 0.2 | B36: =IF($A36>B$33,SUMPRODUCT($B$17:$F$17/(1+$A36)^$B$14:$F$14)+$F$17*(1+B$33)/($A36-B$33)/(1+$A36)^$F$14,"n/a") -> -10055453 | C36: =IF($A36>C$33,SUMPRODUCT($B$17:$F$17/(1+$A36)^$B$14:$F$14)+$F$17*(1+C$33)/($A36-C$33)/(1+$A36)^$F$14,"n/a") -> -10256461 | D36: =IF($A36>D$33,SUMPRODUCT($B$17:$F$17/(1+$A36)^$B$14:$F$14)+$F$17*(1+D$33)/($A36-D$33)/(1+$A36)^$F$14,"n/a") -> -10468635 | E36: =IF($A36>E$33,SUMPRODUCT($B$17:$F$17/(1+$A36)^$B$14:$F$14)+$F$17*(1+E$33)/($A36-E$33)/(1+$A36)^$F$14,"n/a") -> -10692934 | F36: =IF($A36>F$33,SUMPRODUCT($B$17:$F$17/(1+$A36)^$B$14:$F$14)+$F$17*(1+F$33)/($A36-F$33)/(1+$A36)^$F$14,"n/a") -> -10930428
A37: =$B$6+(1)*$B$10 -> 0.21 | B37: =IF($A37>B$33,SUMPRODUCT($B$17:$F$17/(1+$A37)^$B$14:$F$14)+$F$17*(1+B$33)/($A37-B$33)/(1+$A37)^$F$14,"n/a") -> -9395382.7 | C37: =IF($A37>C$33,SUMPRODUCT($B$17:$F$17/(1+$A37)^$B$14:$F$14)+$F$17*(1+C$33)/($A37-C$33)/(1+$A37)^$F$14,"n/a") -> -9570632.3 | D37: =IF($A37>D$33,SUMPRODUCT($B$17:$F$17/(1+$A37)^$B$14:$F$14)+$F$17*(1+D$33)/($A37-D$33)/(1+$A37)^$F$14,"n/a") -> -9755105.4 | E37: =IF($A37>E$33,SUMPRODUCT($B$17:$F$17/(1+$A37)^$B$14:$F$14)+$F$17*(1+E$33)/($A37-E$33)/(1+$A37)^$F$14,"n/a") -> -9949550.1 | F37: =IF($A37>F$33,SUMPRODUCT($B$17:$F$17/(1+$A37)^$B$14:$F$14)+$F$17*(1+F$33)/($A37-F$33)/(1+$A37)^$F$14,"n/a") -> -10154797
A38: =$B$6+(2)*$B$10 -> 0.22 | B38: =IF($A38>B$33,SUMPRODUCT($B$17:$F$17/(1+$A38)^$B$14:$F$14)+$F$17*(1+B$33)/($A38-B$33)/(1+$A38)^$F$14,"n/a") -> -8803536.9 | C38: =IF($A38>C$33,SUMPRODUCT($B$17:$F$17/(1+$A38)^$B$14:$F$14)+$F$17*(1+C$33)/($A38-C$33)/(1+$A38)^$F$14,"n/a") -> -8957157.9 | D38: =IF($A38>D$33,SUMPRODUCT($B$17:$F$17/(1+$A38)^$B$14:$F$14)+$F$17*(1+D$33)/($A38-D$33)/(1+$A38)^$F$14,"n/a") -> -9118459.9 | E38: =IF($A38>E$33,SUMPRODUCT($B$17:$F$17/(1+$A38)^$B$14:$F$14)+$F$17*(1+E$33)/($A38-E$33)/(1+$A38)^$F$14,"n/a") -> -9288033.8 | F38: =IF($A38>F$33,SUMPRODUCT($B$17:$F$17/(1+$A38)^$B$14:$F$14)+$F$17*(1+F$33)/($A38-F$33)/(1+$A38)^$F$14,"n/a") -> -9466532.6
A40: Free cash flow = operating cash flow + interest × (1 − tax rate) − capital spending. Cells marked n/a: WACC not above growth.

Sheet Sources & Uses
A1: Sources and uses of funds | E1: =HYPERLINK("#'Cover'!A1","◂ Contents") -> ◂ Contents
A2: Live for the selected scenario. Where the money comes from and where it goes in the period set below.
A3: Scenario shown | B3: =CHOOSE(Dashboard!$B$4,"Low","Base","High") -> Base
A5: Funding structure ($'000) — raised at the start of the plan
B6: Amount | C6: Share
A7: Equity | B7: =Inputs!$E$46 -> 3000000 | C7: =IF($B$9=0,0,B7/$B$9) -> 1
A8: Debt (loan) | B8: =Inputs!$E$47 -> 0 | C8: =IF($B$9=0,0,B8/$B$9) -> 0
A9: Total funding | B9: =B7+B8 -> 3000000 | C9: =IF(B9=0,0,1) -> 1
A10: Gearing (debt ÷ equity) | B10: =IF(B7<=0,IF(B8>0,"n/a",0),B8/B7) -> 0 | D10: n/a: debt without positive equity
A11: Funding required by the plan (Break-even sheet) | B11: ='Break-even'!B12 -> 7516369.5
A12: Funding surplus / (shortfall) | B12: ='Break-even'!B17 -> -4516369.5
A14: ="Sources and uses of cash in the first "&$B$16&IF($B$16=1," month"," months")&" ($'000)" -> Sources and uses of cash in the first 12 months ($'000)
A15: Period covered (months from the start) | B15: 12 | D15: 1 to 60 (capped)
A16: Months used | B16: =MIN(60,MAX(1,ROUND(B15,0))) -> 12
A17: Sources | B17: Amount | C17: Share
A18: Equity raised | B18: =SUMPRODUCT(--(Monthly!$C$4:$BJ$4<=$B$16),Monthly!$C$72:$BJ$72) -> 3000000 | C18: =IF($B$21=0,0,B18/$B$21) -> 1
A19: Loan drawdowns | B19: =SUMPRODUCT(--(Monthly!$C$4:$BJ$4<=$B$16),Monthly!$C$55:$BJ$55) -> 0 | C19: =IF($B$21=0,0,B19/$B$21) -> 0
A20: Cash generated by operations | B20: =MAX(0,SUMPRODUCT(--(Monthly!$C$4:$BJ$4<=$B$16),Monthly!$C$70:$BJ$70)) -> 0 | C20: =IF($B$21=0,0,B20/$B$21) -> 0
A21: Total sources | B21: =SUM(B18:B20) -> 3000000 | C21: =IF(B21=0,0,1) -> 1
A23: Uses | B23: Amount | C23: Share
A24: Cash used by operations | B24: =MAX(0,-SUMPRODUCT(--(Monthly!$C$4:$BJ$4<=$B$16),Monthly!$C$70:$BJ$70)) -> 665196.51 | C24: =IF($B$28=0,0,B24/$B$28) -> 0.22173217
A25: Capital spending | B25: =-SUMPRODUCT(--(Monthly!$C$4:$BJ$4<=$B$16),Monthly!$C$71:$BJ$71) -> 20000 | C25: =IF($B$28=0,0,B25/$B$28) -> 0.0066666667
A26: Loan repayments | B26: =-SUMPRODUCT(--(Monthly!$C$4:$BJ$4<=$B$16),Monthly!$C$56:$BJ$56) -> 0 | C26: =IF($B$28=0,0,B26/$B$28) -> 0
A27: Cash at the end of the period | B27: =INDEX(Monthly!$C$76:$BJ$76,$B$16) -> 2314803.5 | C27: =IF($B$28=0,0,B27/$B$28) -> 0.77160116
A28: Total uses | B28: =SUM(B24:B27) -> 3000000 | C28: =IF(B28=0,0,1) -> 1
A29: Sources − uses (must be 0; opening cash is 0) | B29: =B21-B28 -> 0

Sheet KPIs
A1: KPIs & ratios | I1: =HYPERLINK("#'Cover'!A1","◂ Contents") -> ◂ Contents
A2: SaaS financial model (early) — industry metrics and financial ratios for the active scenario
A4: Financial ratios
B5: 1 | C5: 2 | D5: 3 | E5: 4 | F5: 5 | G5: Target
A6: Revenue growth | B6: =IF(N('P&L'!A5)<=0,"n/a",'P&L'!B5/'P&L'!A5-1) -> n/a | C6: =IF(N('P&L'!B5)<=0,"n/a",'P&L'!C5/'P&L'!B5-1) -> 1.6223787 | D6: =IF(N('P&L'!C5)<=0,"n/a",'P&L'!D5/'P&L'!C5-1) -> 0.6568261 | E6: =IF(N('P&L'!D5)<=0,"n/a",'P&L'!E5/'P&L'!D5-1) -> 0.44823225 | F6: =IF(N('P&L'!E5)<=0,"n/a",'P&L'!F5/'P&L'!E5-1) -> 0.36706529
A7: Gross margin | B7: =IF('P&L'!B5<=0,"n/a",'P&L'!B7/'P&L'!B5) -> 0.88017025 | C7: =IF('P&L'!C5<=0,"n/a",'P&L'!C7/'P&L'!C5) -> 0.88084332 | D7: =IF('P&L'!D5<=0,"n/a",'P&L'!D7/'P&L'!D5) -> 0.88155507 | E7: =IF('P&L'!E5<=0,"n/a",'P&L'!E7/'P&L'!E5) -> 0.88221481 | F7: =IF('P&L'!F5<=0,"n/a",'P&L'!F7/'P&L'!F5) -> 0.88282162
A8: EBITDA margin | B8: =IF('P&L'!B5<=0,"n/a",'P&L'!B15/'P&L'!B5) -> -3.1204519 | C8: =IF('P&L'!C5<=0,"n/a",'P&L'!C15/'P&L'!C5) -> -1.3883278 | D8: =IF('P&L'!D5<=0,"n/a",'P&L'!D15/'P&L'!D5) -> -1.1807904 | E8: =IF('P&L'!E5<=0,"n/a",'P&L'!E15/'P&L'!E5) -> -1.2818581 | F8: =IF('P&L'!F5<=0,"n/a",'P&L'!F15/'P&L'!F5) -> -1.5391458
A9: Net margin | B9: =IF('P&L'!B5<=0,"n/a",'P&L'!B22/'P&L'!B5) -> -3.150027 | C9: =IF('P&L'!C5<=0,"n/a",'P&L'!C22/'P&L'!C5) -> -1.3996058 | D9: =IF('P&L'!D5<=0,"n/a",'P&L'!D22/'P&L'!D5) -> -1.1875974 | E9: =IF('P&L'!E5<=0,"n/a",'P&L'!E22/'P&L'!E5) -> -1.2818581 | F9: =IF('P&L'!F5<=0,"n/a",'P&L'!F22/'P&L'!F5) -> -1.5391458
A10: Payroll, % of revenue | B10: =IF('P&L'!B5<=0,"n/a",-SUMIF(Headcount!$C$5:$BJ$5,B$5,Headcount!$C$19:$BJ$19)/'P&L'!B5) -> 3.287271 | C10: =IF('P&L'!C5<=0,"n/a",-SUMIF(Headcount!$C$5:$BJ$5,C$5,Headcount!$C$19:$BJ$19)/'P&L'!C5) -> 1.955531 | D10: =IF('P&L'!D5<=0,"n/a",-SUMIF(Headcount!$C$5:$BJ$5,D$5,Headcount!$C$19:$BJ$19)/'P&L'!D5) -> 1.8412484 | E10: =IF('P&L'!E5<=0,"n/a",-SUMIF(Headcount!$C$5:$BJ$5,E$5,Headcount!$C$19:$BJ$19)/'P&L'!E5) -> 1.9833473 | F10: =IF('P&L'!F5<=0,"n/a",-SUMIF(Headcount!$C$5:$BJ$5,F$5,Headcount!$C$19:$BJ$19)/'P&L'!F5) -> 2.2632582
A11: Marketing, % of revenue | B11: =IF('P&L'!B5<=0,"n/a",-'P&L'!B10/'P&L'!B5) -> 0.42588127 | C11: =IF('P&L'!C5<=0,"n/a",-'P&L'!C10/'P&L'!C5) -> 0.19488319 | D11: =IF('P&L'!D5<=0,"n/a",-'P&L'!D10/'P&L'!D5) -> 0.14114929 | E11: =IF('P&L'!E5<=0,"n/a",-'P&L'!E10/'P&L'!E5) -> 0.11695579 | F11: =IF('P&L'!F5<=0,"n/a",-'P&L'!F10/'P&L'!F5) -> 0.10266294
A12: Operating expenses, % of revenue | B12: =IF('P&L'!B5<=0,"n/a",-'P&L'!B14/'P&L'!B5) -> 4.0006222 | C12: =IF('P&L'!C5<=0,"n/a",-'P&L'!C14/'P&L'!C5) -> 2.2691711 | D12: =IF('P&L'!D5<=0,"n/a",-'P&L'!D14/'P&L'!D5) -> 2.0623455 | E12: =IF('P&L'!E5<=0,"n/a",-'P&L'!E14/'P&L'!E5) -> 2.1640729 | F12: =IF('P&L'!F5<=0,"n/a",-'P&L'!F14/'P&L'!F5) -> 2.4219675
A13: Current ratio (current assets ÷ current liabilities) | B13: =IF(('Balance Sheet'!B13-'Balance Sheet'!B12)<=0,"n/a",('Balance Sheet'!B5+'Balance Sheet'!B6+'Balance Sheet'!B7)/('Balance Sheet'!B13-'Balance Sheet'!B12)) -> 53.295787 | C13: =IF(('Balance Sheet'!C13-'Balance Sheet'!C12)<=0,"n/a",('Balance Sheet'!C5+'Balance Sheet'!C6+'Balance Sheet'!C7)/('Balance Sheet'!C13-'Balance Sheet'!C12)) -> 18.306344 | D13: =IF(('Balance Sheet'!D13-'Balance Sheet'!D12)<=0,"n/a",('Balance Sheet'!D5+'Balance Sheet'!D6+'Balance Sheet'!D7)/('Balance Sheet'!D13-'Balance Sheet'!D12)) -> 3.3292205 | E13: =IF(('Balance Sheet'!E13-'Balance Sheet'!E12)<=0,"n/a",('Balance Sheet'!E5+'Balance Sheet'!E6+'Balance Sheet'!E7)/('Balance Sheet'!E13-'Balance Sheet'!E12)) -> -7.4348307 | F13: =IF(('Balance Sheet'!F13-'Balance Sheet'!F12)<=0,"n/a",('Balance Sheet'!F5+'Balance Sheet'!F6+'Balance Sheet'!F7)/('Balance Sheet'!F13-'Balance Sheet'!F12)) -> -17.597324
A14: Debt ÷ equity (loan ÷ total equity) | B14: =IF('Balance Sheet'!B16<=0,"n/a",'Balance Sheet'!B12/'Balance Sheet'!B16) -> 0 | C14: =IF('Balance Sheet'!C16<=0,"n/a",'Balance Sheet'!C12/'Balance Sheet'!C16) -> 0 | D14: =IF('Balance Sheet'!D16<=0,"n/a",'Balance Sheet'!D12/'Balance Sheet'!D16) -> 0 | E14: =IF('Balance Sheet'!E16<=0,"n/a",'Balance Sheet'!E12/'Balance Sheet'!E16) -> n/a | F14: =IF('Balance Sheet'!F16<=0,"n/a",'Balance Sheet'!F12/'Balance Sheet'!F16) -> n/a
A15: Return on assets (net income ÷ year-end assets) | B15: =IF('Balance Sheet'!B9<=0,"n/a",'P&L'!B22/'Balance Sheet'!B9) -> -0.30429494 | C15: =IF('Balance Sheet'!C9<=0,"n/a",'P&L'!C22/'Balance Sheet'!C9) -> -0.53489796 | D15: =IF('Balance Sheet'!D9<=0,"n/a",'P&L'!D22/'Balance Sheet'!D9) -> -2.7172369 | E15: =IF('Balance Sheet'!E9<=0,"n/a",'P&L'!E22/'Balance Sheet'!E9) -> n/a | F15: =IF('Balance Sheet'!F9<=0,"n/a",'P&L'!F22/'Balance Sheet'!F9) -> n/a
A16: Return on equity (net income ÷ year-end equity) | B16: =IF('Balance Sheet'!B16<=0,"n/a",'P&L'!B22/'Balance Sheet'!B16) -> -0.31007979 | C16: =IF('Balance Sheet'!C16<=0,"n/a",'P&L'!C22/'Balance Sheet'!C16) -> -0.56566471 | D16: =IF('Balance Sheet'!D16<=0,"n/a",'P&L'!D22/'Balance Sheet'!D16) -> -3.8838234 | E16: =IF('Balance Sheet'!E16<=0,"n/a",'P&L'!E22/'Balance Sheet'!E16) -> n/a | F16: =IF('Balance Sheet'!F16<=0,"n/a",'P&L'!F22/'Balance Sheet'!F16) -> n/a
A18: DuPont analysis — return on equity = net margin × asset turnover × equity multiplier
B19: 1 | C19: 2 | D19: 3 | E19: 4 | F19: 5
A20: Net margin | B20: =IF('P&L'!B5<=0,"n/a",'P&L'!B22/'P&L'!B5) -> -3.150027 | C20: =IF('P&L'!C5<=0,"n/a",'P&L'!C22/'P&L'!C5) -> -1.3996058 | D20: =IF('P&L'!D5<=0,"n/a",'P&L'!D22/'P&L'!D5) -> -1.1875974 | E20: =IF('P&L'!E5<=0,"n/a",'P&L'!E22/'P&L'!E5) -> -1.2818581 | F20: =IF('P&L'!F5<=0,"n/a",'P&L'!F22/'P&L'!F5) -> -1.5391458
A21: × Asset turnover (revenue ÷ assets) | B21: =IF('Balance Sheet'!B9<=0,"n/a",'P&L'!B5/'Balance Sheet'!B9) -> 0.096600742 | C21: =IF('Balance Sheet'!C9<=0,"n/a",'P&L'!C5/'Balance Sheet'!C9) -> 0.38217759 | D21: =IF('Balance Sheet'!D9<=0,"n/a",'P&L'!D5/'Balance Sheet'!D9) -> 2.2880119 | E21: =IF('Balance Sheet'!E9<=0,"n/a",'P&L'!E5/'Balance Sheet'!E9) -> n/a | F21: =IF('Balance Sheet'!F9<=0,"n/a",'P&L'!F5/'Balance Sheet'!F9) -> n/a
A22: × Equity multiplier (assets ÷ equity) | B22: =IF('Balance Sheet'!B16<=0,"n/a",'Balance Sheet'!B9/'Balance Sheet'!B16) -> 1.0190107 | C22: =IF('Balance Sheet'!C16<=0,"n/a",'Balance Sheet'!C9/'Balance Sheet'!C16) -> 1.0575189 | D22: =IF('Balance Sheet'!D16<=0,"n/a",'Balance Sheet'!D9/'Balance Sheet'!D16) -> 1.4293282 | E22: =IF('Balance Sheet'!E16<=0,"n/a",'Balance Sheet'!E9/'Balance Sheet'!E16) -> n/a | F22: =IF('Balance Sheet'!F16<=0,"n/a",'Balance Sheet'!F9/'Balance Sheet'!F16) -> n/a
A23: Return on equity (product of the three) | B23: =IF(AND(ISNUMBER(B20),ISNUMBER(B21),ISNUMBER(B22)),B20*B21*B22,"n/a") -> -0.31007979 | C23: =IF(AND(ISNUMBER(C20),ISNUMBER(C21),ISNUMBER(C22)),C20*C21*C22,"n/a") -> -0.56566471 | D23: =IF(AND(ISNUMBER(D20),ISNUMBER(D21),ISNUMBER(D22)),D20*D21*D22,"n/a") -> -3.8838234 | E23: =IF(AND(ISNUMBER(E20),ISNUMBER(E21),ISNUMBER(E22)),E20*E21*E22,"n/a") -> n/a | F23: =IF(AND(ISNUMBER(F20),ISNUMBER(F21),ISNUMBER(F22)),F20*F21*F22,"n/a") -> n/a
A24: Check: product − return on equity (must be 0) | B24: =IF(AND(ISNUMBER(B23),ISNUMBER(B16)),B23-B16,IF(ISNUMBER(B23),1,IF(AND(ISNUMBER(B16),ISNUMBER(B20),ISNUMBER(B21)),1,0))) -> 0 | C24: =IF(AND(ISNUMBER(C23),ISNUMBER(C16)),C23-C16,IF(ISNUMBER(C23),1,IF(AND(ISNUMBER(C16),ISNUMBER(C20),ISNUMBER(C21)),1,0))) -> 0 | D24: =IF(AND(ISNUMBER(D23),ISNUMBER(D16)),D23-D16,IF(ISNUMBER(D23),1,IF(AND(ISNUMBER(D16),ISNUMBER(D20),ISNUMBER(D21)),1,0))) -> 0 | E24: =IF(AND(ISNUMBER(E23),ISNUMBER(E16)),E23-E16,IF(ISNUMBER(E23),1,IF(AND(ISNUMBER(E16),ISNUMBER(E20),ISNUMBER(E21)),1,0))) -> 0 | F24: =IF(AND(ISNUMBER(F23),ISNUMBER(F16)),F23-F16,IF(ISNUMBER(F23),1,IF(AND(ISNUMBER(F16),ISNUMBER(F20),ISNUMBER(F21)),1,0))) -> 0
A26: SaaS metrics ($'000; per-unit rows in $)
A27: Year # | B27: 1 | C27: 2 | D27: 3 | E27: 4 | F27: 5
B28: Year 1 | C28: Year 2 | D28: Year 3 | E28: Year 4 | F28: Year 5 | G28: Target
A29: Customers (year end) | B29: =INDEX(Monthly!$C$13:$BJ$13,B$27*12) -> 324.70508 | C29: =INDEX(Monthly!$C$13:$BJ$13,C$27*12) -> 602.20821 | D29: =INDEX(Monthly!$C$13:$BJ$13,D$27*12) -> 886.05465 | E29: =INDEX(Monthly!$C$13:$BJ$13,E$27*12) -> 1197.339 | F29: =INDEX(Monthly!$C$13:$BJ$13,F$27*12) -> 1556.7378
A30: New customers in the year | B30: =SUMIF(Monthly!$C$5:$BJ$5,B$27,Monthly!$C$10:$BJ$10) -> 357.33333 | C30: =SUMIF(Monthly!$C$5:$BJ$5,C$27,Monthly!$C$10:$BJ$10) -> 443.2 | D30: =SUMIF(Monthly!$C$5:$BJ$5,D$27,Monthly!$C$10:$BJ$10) -> 550.56 | E30: =SUMIF(Monthly!$C$5:$BJ$5,E$27,Monthly!$C$10:$BJ$10) -> 685.008 | F30: =SUMIF(Monthly!$C$5:$BJ$5,F$27,Monthly!$C$10:$BJ$10) -> 853.6464
A31: Customers lost in the year | B31: =SUMIF(Monthly!$C$5:$BJ$5,B$27,Monthly!$C$12:$BJ$12) -> -62.628258 | C31: =SUMIF(Monthly!$C$5:$BJ$5,C$27,Monthly!$C$12:$BJ$12) -> -165.69687 | D31: =SUMIF(Monthly!$C$5:$BJ$5,D$27,Monthly!$C$12:$BJ$12) -> -266.71356 | E31: =SUMIF(Monthly!$C$5:$BJ$5,E$27,Monthly!$C$12:$BJ$12) -> -373.72364 | F31: =SUMIF(Monthly!$C$5:$BJ$5,F$27,Monthly!$C$12:$BJ$12) -> -494.24764
A32: MRR (year end) | B32: =INDEX(Monthly!$C$21:$BJ$21,B$27*12) -> 33087.09 | C32: =INDEX(Monthly!$C$21:$BJ$21,C$27*12) -> 63887.111 | D32: =INDEX(Monthly!$C$21:$BJ$21,D$27*12) -> 97649.245 | E32: =INDEX(Monthly!$C$21:$BJ$21,E$27*12) -> 136783.01 | F32: =INDEX(Monthly!$C$21:$BJ$21,F$27*12) -> 184015.77
A33: ARR (year-end MRR × 12) | B33: =B32*12 -> 397045.08 | C33: =C32*12 -> 766645.33 | D33: =D32*12 -> 1171790.9 | E33: =E32*12 -> 1641396.1 | F33: =F32*12 -> 2208189.2
A34: Average MRR per customer (year end) ($) | B34: =IF(B29=0,0,B32/B29) -> 101.8989 | C34: =IF(C29=0,0,C32/C29) -> 106.08808 | D34: =IF(D29=0,0,D32/D29) -> 110.2068 | E34: =IF(E29=0,0,E32/E29) -> 114.23917 | F34: =IF(F29=0,0,F32/F29) -> 118.20601
A35: Revenue | B35: =SUMIF(Monthly!$C$5:$BJ$5,B$27,Monthly!$C$24:$BJ$24) -> 225414.94 | C35: =SUMIF(Monthly!$C$5:$BJ$5,C$27,Monthly!$C$24:$BJ$24) -> 591123.33 | D35: =SUMIF(Monthly!$C$5:$BJ$5,D$27,Monthly!$C$24:$BJ$24) -> 979388.56 | E35: =SUMIF(Monthly!$C$5:$BJ$5,E$27,Monthly!$C$24:$BJ$24) -> 1418382.1 | F35: =SUMIF(Monthly!$C$5:$BJ$5,F$27,Monthly!$C$24:$BJ$24) -> 1939020.9
A36: Gross profit | B36: =SUMIF(Monthly!$C$5:$BJ$5,B$27,Monthly!$C$26:$BJ$26) -> 198403.52 | C36: =SUMIF(Monthly!$C$5:$BJ$5,C$27,Monthly!$C$26:$BJ$26) -> 520687.04 | D36: =SUMIF(Monthly!$C$5:$BJ$5,D$27,Monthly!$C$26:$BJ$26) -> 863384.95 | E36: =SUMIF(Monthly!$C$5:$BJ$5,E$27,Monthly!$C$26:$BJ$26) -> 1251317.7 | F36: =SUMIF(Monthly!$C$5:$BJ$5,F$27,Monthly!$C$26:$BJ$26) -> 1711809.6
A37: Gross margin | B37: =IF(B35=0,0,B36/B35) -> 0.88017025 | C37: =IF(C35=0,0,C36/C35) -> 0.88084332 | D37: =IF(D35=0,0,D36/D35) -> 0.88155507 | E37: =IF(E35=0,0,E36/E35) -> 0.88221481 | F37: =IF(F35=0,0,F36/F35) -> 0.88282162
A38: Paid marketing spend | B38: =-SUMIF(Monthly!$C$5:$BJ$5,B$27,Monthly!$C$30:$BJ$30) -> 96000 | C38: =-SUMIF(Monthly!$C$5:$BJ$5,C$27,Monthly!$C$30:$BJ$30) -> 115200 | D38: =-SUMIF(Monthly!$C$5:$BJ$5,D$27,Monthly!$C$30:$BJ$30) -> 138240 | E38: =-SUMIF(Monthly!$C$5:$BJ$5,E$27,Monthly!$C$30:$BJ$30) -> 165888 | F38: =-SUMIF(Monthly!$C$5:$BJ$5,F$27,Monthly!$C$30:$BJ$30) -> 199065.6
A39: Blended CAC (paid spend ÷ all new customers) ($) | B39: =IF(B30=0,0,B38/B30) -> 268.65672 | C39: =IF(C30=0,0,C38/C30) -> 259.9278 | D39: =IF(D30=0,0,D38/D30) -> 251.0898 | E39: =IF(E30=0,0,E38/E30) -> 242.16943 | F39: =IF(F30=0,0,F38/F30) -> 233.19445
A40: Customer churn per month | B40: =INDEX(Monthly!$C$81:$BJ$81,B$27*12) -> 0.03 | C40: =INDEX(Monthly!$C$81:$BJ$81,C$27*12) -> 0.03 | D40: =INDEX(Monthly!$C$81:$BJ$81,D$27*12) -> 0.03 | E40: =INDEX(Monthly!$C$81:$BJ$81,E$27*12) -> 0.03 | F40: =INDEX(Monthly!$C$81:$BJ$81,F$27*12) -> 0.03
A41: Customer lifetime value (MRR × margin ÷ churn) ($) | B41: =IF(B40=0,0,B34*B37/B40) -> 2989.6127 | C41: =IF(C40=0,0,C34*C37/C40) -> 3114.8992 | D41: =IF(D40=0,0,D34*D37/D40) -> 3238.4454 | E41: =IF(E40=0,0,E34*E37/E40) -> 3359.4495 | F41: =IF(F40=0,0,F34*F37/F40) -> 3478.4941
A42: LTV ÷ CAC | B42: =IF(B39=0,0,B41/B39) -> 11.128003 | C42: =IF(C39=0,0,C41/C39) -> 11.983709 | D42: =IF(D39=0,0,D41/D39) -> 12.897559 | E42: =IF(E39=0,0,E41/E39) -> 13.87231 | F42: =IF(F39=0,0,F41/F39) -> 14.916711
A43: CAC payback (months of gross profit) | B43: =IF(B34*B37<=0,0,B39/(B34*B37)) -> 2.9954462 | C43: =IF(C34*C37<=0,0,C39/(C34*C37)) -> 2.7815539 | D43: =IF(D34*D37<=0,0,D39/(D34*D37)) -> 2.5844685 | E43: =IF(E34*E37<=0,0,E39/(E34*E37)) -> 2.4028682 | F43: =IF(F34*F37<=0,0,F39/(F34*F37)) -> 2.2346302
A44: Net burn per month (year end) | B44: =INDEX(Monthly!$C$80:$BJ$80,B$27*12) -> 44473.892 | C44: =INDEX(Monthly!$C$80:$BJ$80,C$27*12) -> 53908.871 | D44: =INDEX(Monthly!$C$80:$BJ$80,D$27*12) -> 80483.087 | E44: =INDEX(Monthly!$C$80:$BJ$80,E$27*12) -> 133085.05 | F44: =INDEX(Monthly!$C$80:$BJ$80,F$27*12) -> 226448.54
A45: Cash (year end) | B45: =INDEX(Monthly!$C$76:$BJ$76,B$27*12) -> 2314803.5 | C45: =INDEX(Monthly!$C$76:$BJ$76,C$27*12) -> 1529595.1 | D45: =INDEX(Monthly!$C$76:$BJ$76,D$27*12) -> 411980.55 | E45: =INDEX(Monthly!$C$76:$BJ$76,E$27*12) -> -1361198.8 | F45: =INDEX(Monthly!$C$76:$BJ$76,F$27*12) -> -4291369.5
A46: Runway at year-end burn (months; - = not burning) | B46: =IF(B44<=0,0,MAX(0,B45)/B44) -> 52.048593 | C46: =IF(C44<=0,0,MAX(0,C45)/C44) -> 28.373718 | D46: =IF(D44<=0,0,MAX(0,D45)/D44) -> 5.1188463 | E46: =IF(E44<=0,0,MAX(0,E45)/E44) -> 0 | F46: =IF(F44<=0,0,MAX(0,F45)/F44) -> 0

Sheet Inputs
A1: Inputs — Low / Base / High | I1: =HYPERLINK("#'Cover'!A1","◂ Contents") -> ◂ Contents
A2: Illustrative assumptions — replace them with your own numbers.
A5: Driver | B5: Low | C5: Base | D5: High | E5: Active | F5: Unit | G5: Source / comment
A6: Business drivers
A7: Paying customers at start | B7: 30 | C7: 30 | D7: 30 | E7: =CHOOSE(Dashboard!$B$4,B7,C7,D7) -> 30 | F7: # | G7: Low ≤ Base ≤ High
A8: Average MRR per new customer (ARPA) | B8: 79 | C8: 99 | D8: 119 | E8: =CHOOSE(Dashboard!$B$4,B8,C8,D8) -> 99 | F8: $ / month | G8: Low ≤ Base ≤ High
A9: Price increase per year for new customers | B9: 0 | C9: 0.03 | D9: 0.05 | E9: =CHOOSE(Dashboard!$B$4,B9,C9,D9) -> 0.03 | F9: % | G9: Low ≤ Base ≤ High
A10: Customer churn per month | B10: 0.045 | C10: 0.03 | D10: 0.02 | E10: =CHOOSE(Dashboard!$B$4,B10,C10,D10) -> 0.03 | F10: % | G10: Low ≥ Base ≥ High (lower is better)
A11: Expansion MRR per month, % of opening MRR | B11: 0 | C11: 0.005 | D11: 0.01 | E11: =CHOOSE(Dashboard!$B$4,B11,C11,D11) -> 0.005 | F11: % | G11: Low ≤ Base ≤ High
A12: Organic / referral new customers per month (year 1) | B12: 8 | C12: 12 | D12: 18 | E12: =CHOOSE(Dashboard!$B$4,B12,C12,D12) -> 12 | F12: # / month | G12: Low ≤ Base ≤ High
A13: Growth of organic new customers per year | B13: 0.1 | C13: 0.3 | D13: 0.5 | E13: =CHOOSE(Dashboard!$B$4,B13,C13,D13) -> 0.3 | F13: % | G13: Low ≤ Base ≤ High
A14: Paid marketing budget per month (year 1) | B14: 8000 | C14: 8000 | D14: 8000 | E14: =CHOOSE(Dashboard!$B$4,B14,C14,D14) -> 8000 | F14: $ / month
A15: Paid marketing budget growth per year | B15: 0.2 | C15: 0.2 | D15: 0.2 | E15: =CHOOSE(Dashboard!$B$4,B15,C15,D15) -> 0.2 | F15: %
A16: Paid customer acquisition cost (CAC) | B16: 600 | C16: 450 | D16: 350 | E16: =CHOOSE(Dashboard!$B$4,B16,C16,D16) -> 450 | F16: $ | G16: Low ≥ Base ≥ High (lower is better)
A17: Share of MRR billed annually in advance | B17: 0.2 | C17: 0.2 | D17: 0.2 | E17: =CHOOSE(Dashboard!$B$4,B17,C17,D17) -> 0.2 | F17: %
A18: Hosting & payment fees, % of revenue | B18: 0.12 | C18: 0.1 | D18: 0.08 | E18: =CHOOSE(Dashboard!$B$4,B18,C18,D18) -> 0.1 | F18: % | G18: Low ≥ Base ≥ High (lower is better)
A19: Support & onboarding cost per customer per month | B19: 3 | C19: 2 | D19: 1.5 | E19: =CHOOSE(Dashboard!$B$4,B19,C19,D19) -> 2 | F19: $ | G19: Low ≥ Base ≥ High (lower is better)
A20: Software & tools per FTE per month | B20: 150 | C20: 150 | D20: 150 | E20: =CHOOSE(Dashboard!$B$4,B20,C20,D20) -> 150 | F20: $
A21: Office & rent per month | B21: 1500 | C21: 1500 | D21: 1500 | E21: =CHOOSE(Dashboard!$B$4,B21,C21,D21) -> 1500 | F21: $
A22: Other G&A per month (legal, accounting, insurance) | B22: 3000 | C22: 3000 | D22: 3000 | E22: =CHOOSE(Dashboard!$B$4,B22,C22,D22) -> 3000 | F22: $
A23: Start-up capex (equipment) | B23: 20000 | C23: 20000 | D23: 20000 | E23: =CHOOSE(Dashboard!$B$4,B23,C23,D23) -> 20000 | F23: $
A25: Headcount
A26: Engineering & product: headcount (FTE) | B26: 3 | C26: 3 | D26: 3 | E26: =CHOOSE(Dashboard!$B$4,B26,C26,D26) -> 3 | F26: FTE | G26: Low ≤ Base ≤ High
A27: Engineering & product: salary per FTE per year | B27: 125000 | C27: 125000 | D27: 125000 | E27: =CHOOSE(Dashboard!$B$4,B27,C27,D27) -> 125000 | F27: $
A28: Engineering & product: headcount growth per year | B28: 0.5 | C28: 0.5 | D28: 0.5 | E28: =CHOOSE(Dashboard!$B$4,B28,C28,D28) -> 0.5 | F28: % | G28: Low ≤ Base ≤ High
A29: Engineering & product: first month on payroll | B29: 1 | C29: 1 | D29: 1 | E29: =CHOOSE(Dashboard!$B$4,B29,C29,D29) -> 1 | F29: month #
A30: Sales & marketing: headcount (FTE) | B30: 1.5 | C30: 1.5 | D30: 1.5 | E30: =CHOOSE(Dashboard!$B$4,B30,C30,D30) -> 1.5 | F30: FTE | G30: Low ≤ Base ≤ High
A31: Sales & marketing: salary per FTE per year | B31: 95000 | C31: 95000 | D31: 95000 | E31: =CHOOSE(Dashboard!$B$4,B31,C31,D31) -> 95000 | F31: $
A32: Sales & marketing: headcount growth per year | B32: 0.5 | C32: 0.5 | D32: 0.5 | E32: =CHOOSE(Dashboard!$B$4,B32,C32,D32) -> 0.5 | F32: % | G32: Low ≤ Base ≤ High
A33: Sales & marketing: first month on payroll | B33: 1 | C33: 1 | D33: 1 | E33: =CHOOSE(Dashboard!$B$4,B33,C33,D33) -> 1 | F33: month #
A34: Customer success: headcount (FTE) | B34: 1 | C34: 1 | D34: 1 | E34: =CHOOSE(Dashboard!$B$4,B34,C34,D34) -> 1 | F34: FTE | G34: Low ≤ Base ≤ High
A35: Customer success: salary per FTE per year | B35: 60000 | C35: 60000 | D35: 60000 | E35: =CHOOSE(Dashboard!$B$4,B35,C35,D35) -> 60000 | F35: $
A36: Customer success: headcount growth per year | B36: 0.5 | C36: 0.5 | D36: 0.5 | E36: =CHOOSE(Dashboard!$B$4,B36,C36,D36) -> 0.5 | F36: % | G36: Low ≤ Base ≤ High
A37: Customer success: first month on payroll | B37: 1 | C37: 1 | D37: 1 | E37: =CHOOSE(Dashboard!$B$4,B37,C37,D37) -> 1 | F37: month #
A38: G&A (finance, ops): headcount (FTE) | B38: 0.5 | C38: 0.5 | D38: 0.5 | E38: =CHOOSE(Dashboard!$B$4,B38,C38,D38) -> 0.5 | F38: FTE | G38: Low ≤ Base ≤ High
A39: G&A (finance, ops): salary per FTE per year | B39: 80000 | C39: 80000 | D39: 80000 | E39: =CHOOSE(Dashboard!$B$4,B39,C39,D39) -> 80000 | F39: $
A40: G&A (finance, ops): headcount growth per year | B40: 0.5 | C40: 0.5 | D40: 0.5 | E40: =CHOOSE(Dashboard!$B$4,B40,C40,D40) -> 0.5 | F40: % | G40: Low ≤ Base ≤ High
A41: G&A (finance, ops): first month on payroll | B41: 1 | C41: 1 | D41: 1 | E41: =CHOOSE(Dashboard!$B$4,B41,C41,D41) -> 1 | F41: month #
A42: Payroll taxes & benefits, % of salary | B42: 0.2 | C42: 0.2 | D42: 0.2 | E42: =CHOOSE(Dashboard!$B$4,B42,C42,D42) -> 0.2 | F42: %
A43: Wage growth per year | B43: 0.04 | C43: 0.04 | D43: 0.04 | E43: =CHOOSE(Dashboard!$B$4,B43,C43,D43) -> 0.04 | F43: %
A45: Funding
A46: Equity raised at start | B46: 3000000 | C46: 3000000 | D46: 3000000 | E46: =CHOOSE(Dashboard!$B$4,B46,C46,D46) -> 3000000 | F46: $
A47: Loan drawn at start | B47: 0 | C47: 0 | D47: 0 | E47: =CHOOSE(Dashboard!$B$4,B47,C47,D47) -> 0 | F47: $
A48: Loan interest rate per year | B48: 0 | C48: 0 | D48: 0 | E48: =CHOOSE(Dashboard!$B$4,B48,C48,D48) -> 0 | F48: %
A49: Loan repayment term | B49: 1 | C49: 1 | D49: 1 | E49: =CHOOSE(Dashboard!$B$4,B49,C49,D49) -> 1 | F49: years
A51: Working capital
A52: Customer payment terms (receivable days) | B52: 5 | C52: 5 | D52: 5 | E52: =CHOOSE(Dashboard!$B$4,B52,C52,D52) -> 5 | F52: days
A53: Inventory held (days of COGS) | B53: 0 | C53: 0 | D53: 0 | E53: =CHOOSE(Dashboard!$B$4,B53,C53,D53) -> 0 | F53: days
A54: Supplier payment terms (payable days) | B54: 30 | C54: 30 | D54: 30 | E54: =CHOOSE(Dashboard!$B$4,B54,C54,D54) -> 30 | F54: days
A56: Tax & depreciation
A57: Depreciation period for capex | B57: 3 | C57: 3 | D57: 3 | E57: =CHOOSE(Dashboard!$B$4,B57,C57,D57) -> 3 | F57: years
A58: Income tax rate | B58: 0.21 | C58: 0.21 | D58: 0.21 | E58: =CHOOSE(Dashboard!$B$4,B58,C58,D58) -> 0.21 | F58: %
A60: Break-even & funding
A61: Minimum cash buffer to keep | B61: 225000 | C61: 225000 | D61: 225000 | E61: =CHOOSE(Dashboard!$B$4,B61,C61,D61) -> 225000 | F61: $ | G61: About 3 months of costs
A63: Valuation
A64: Discount rate (WACC) | B64: 0.25 | C64: 0.2 | D64: 0.17 | E64: =CHOOSE(Dashboard!$B$4,B64,C64,D64) -> 0.2 | F64: % | G64: Low ≥ Base ≥ High (lower is better)
A65: Terminal growth rate (perpetuity) | B65: 0.01 | C65: 0.02 | D65: 0.03 | E65: =CHOOSE(Dashboard!$B$4,B65,C65,D65) -> 0.02 | F65: % | G65: Low ≤ Base ≤ High
A66: Exit multiple (EV ÷ final-year EBITDA) | B66: 3.5 | C66: 4.5 | D66: 6 | E66: =CHOOSE(Dashboard!$B$4,B66,C66,D66) -> 4.5 | F66: x | G66: Low ≤ Base ≤ High
A67: Sensitivity table: WACC step | B67: 0.01 | C67: 0.01 | D67: 0.01 | E67: =CHOOSE(Dashboard!$B$4,B67,C67,D67) -> 0.01 | F67: %
A68: Sensitivity table: growth step | B68: 0.005 | C68: 0.005 | D68: 0.005 | E68: =CHOOSE(Dashboard!$B$4,B68,C68,D68) -> 0.005 | F68: %
A70: Legend: yellow cell with blue figure = input you can change · black = formula · green = link to another sheet · grey = active value (column E follows the scenario on the Dashboard).

Sheet P&L
A1: Annual profit & loss | H1: =HYPERLINK("#'Cover'!A1","◂ Contents") -> ◂ Contents
A2: Rolled up from the period detail (SUMIF on the year row; balances at year end).
A3: Year # | B3: 1 | C3: 2 | D3: 3 | E3: 4 | F3: 5
B4: Year 1 | C4: Year 2 | D4: Year 3 | E4: Year 4 | F4: Year 5
A5: Revenue | B5: =SUMIF(Monthly!$C$5:$BJ$5,B$3,Monthly!$C$24:$BJ$24) -> 225414.94 | C5: =SUMIF(Monthly!$C$5:$BJ$5,C$3,Monthly!$C$24:$BJ$24) -> 591123.33 | D5: =SUMIF(Monthly!$C$5:$BJ$5,D$3,Monthly!$C$24:$BJ$24) -> 979388.56 | E5: =SUMIF(Monthly!$C$5:$BJ$5,E$3,Monthly!$C$24:$BJ$24) -> 1418382.1 | F5: =SUMIF(Monthly!$C$5:$BJ$5,F$3,Monthly!$C$24:$BJ$24) -> 1939020.9
A6: Hosting, payment fees & support | B6: =SUMIF(Monthly!$C$5:$BJ$5,B$3,Monthly!$C$25:$BJ$25) -> -27011.416 | C6: =SUMIF(Monthly!$C$5:$BJ$5,C$3,Monthly!$C$25:$BJ$25) -> -70436.294 | D6: =SUMIF(Monthly!$C$5:$BJ$5,D$3,Monthly!$C$25:$BJ$25) -> -116003.61 | E6: =SUMIF(Monthly!$C$5:$BJ$5,E$3,Monthly!$C$25:$BJ$25) -> -167064.4 | F6: =SUMIF(Monthly!$C$5:$BJ$5,F$3,Monthly!$C$25:$BJ$25) -> -227211.34
A7: Gross profit | B7: =SUMIF(Monthly!$C$5:$BJ$5,B$3,Monthly!$C$26:$BJ$26) -> 198403.52 | C7: =SUMIF(Monthly!$C$5:$BJ$5,C$3,Monthly!$C$26:$BJ$26) -> 520687.04 | D7: =SUMIF(Monthly!$C$5:$BJ$5,D$3,Monthly!$C$26:$BJ$26) -> 863384.95 | E7: =SUMIF(Monthly!$C$5:$BJ$5,E$3,Monthly!$C$26:$BJ$26) -> 1251317.7 | F7: =SUMIF(Monthly!$C$5:$BJ$5,F$3,Monthly!$C$26:$BJ$26) -> 1711809.6
A8: Gross margin | B8: =IF(B5=0,0,B7/B5) -> 0.88017025 | C8: =IF(C5=0,0,C7/C5) -> 0.88084332 | D8: =IF(D5=0,0,D7/D5) -> 0.88155507 | E8: =IF(E5=0,0,E7/E5) -> 0.88221481 | F8: =IF(F5=0,0,F7/F5) -> 0.88282162
A9: Payroll | B9: =SUMIF(Monthly!$C$5:$BJ$5,B$3,Monthly!$C$29:$BJ$29) -> -741000 | C9: =SUMIF(Monthly!$C$5:$BJ$5,C$3,Monthly!$C$29:$BJ$29) -> -1155960 | D9: =SUMIF(Monthly!$C$5:$BJ$5,D$3,Monthly!$C$29:$BJ$29) -> -1803297.6 | E9: =SUMIF(Monthly!$C$5:$BJ$5,E$3,Monthly!$C$29:$BJ$29) -> -2813144.3 | F9: =SUMIF(Monthly!$C$5:$BJ$5,F$3,Monthly!$C$29:$BJ$29) -> -4388505
A10: Paid marketing | B10: =SUMIF(Monthly!$C$5:$BJ$5,B$3,Monthly!$C$30:$BJ$30) -> -96000 | C10: =SUMIF(Monthly!$C$5:$BJ$5,C$3,Monthly!$C$30:$BJ$30) -> -115200 | D10: =SUMIF(Monthly!$C$5:$BJ$5,D$3,Monthly!$C$30:$BJ$30) -> -138240 | E10: =SUMIF(Monthly!$C$5:$BJ$5,E$3,Monthly!$C$30:$BJ$30) -> -165888 | F10: =SUMIF(Monthly!$C$5:$BJ$5,F$3,Monthly!$C$30:$BJ$30) -> -199065.6
A11: Software & tools | B11: =SUMIF(Monthly!$C$5:$BJ$5,B$3,Monthly!$C$31:$BJ$31) -> -10800 | C11: =SUMIF(Monthly!$C$5:$BJ$5,C$3,Monthly!$C$31:$BJ$31) -> -16200 | D11: =SUMIF(Monthly!$C$5:$BJ$5,D$3,Monthly!$C$31:$BJ$31) -> -24300 | E11: =SUMIF(Monthly!$C$5:$BJ$5,E$3,Monthly!$C$31:$BJ$31) -> -36450 | F11: =SUMIF(Monthly!$C$5:$BJ$5,F$3,Monthly!$C$31:$BJ$31) -> -54675
A12: Office & rent | B12: =SUMIF(Monthly!$C$5:$BJ$5,B$3,Monthly!$C$32:$BJ$32) -> -18000 | C12: =SUMIF(Monthly!$C$5:$BJ$5,C$3,Monthly!$C$32:$BJ$32) -> -18000 | D12: =SUMIF(Monthly!$C$5:$BJ$5,D$3,Monthly!$C$32:$BJ$32) -> -18000 | E12: =SUMIF(Monthly!$C$5:$BJ$5,E$3,Monthly!$C$32:$BJ$32) -> -18000 | F12: =SUMIF(Monthly!$C$5:$BJ$5,F$3,Monthly!$C$32:$BJ$32) -> -18000
A13: Other G&A | B13: =SUMIF(Monthly!$C$5:$BJ$5,B$3,Monthly!$C$33:$BJ$33) -> -36000 | C13: =SUMIF(Monthly!$C$5:$BJ$5,C$3,Monthly!$C$33:$BJ$33) -> -36000 | D13: =SUMIF(Monthly!$C$5:$BJ$5,D$3,Monthly!$C$33:$BJ$33) -> -36000 | E13: =SUMIF(Monthly!$C$5:$BJ$5,E$3,Monthly!$C$33:$BJ$33) -> -36000 | F13: =SUMIF(Monthly!$C$5:$BJ$5,F$3,Monthly!$C$33:$BJ$33) -> -36000
A14: Total operating expenses | B14: =SUMIF(Monthly!$C$5:$BJ$5,B$3,Monthly!$C$34:$BJ$34) -> -901800 | C14: =SUMIF(Monthly!$C$5:$BJ$5,C$3,Monthly!$C$34:$BJ$34) -> -1341360 | D14: =SUMIF(Monthly!$C$5:$BJ$5,D$3,Monthly!$C$34:$BJ$34) -> -2019837.6 | E14: =SUMIF(Monthly!$C$5:$BJ$5,E$3,Monthly!$C$34:$BJ$34) -> -3069482.3 | F14: =SUMIF(Monthly!$C$5:$BJ$5,F$3,Monthly!$C$34:$BJ$34) -> -4696245.6
A15: EBITDA | B15: =SUMIF(Monthly!$C$5:$BJ$5,B$3,Monthly!$C$35:$BJ$35) -> -703396.48 | C15: =SUMIF(Monthly!$C$5:$BJ$5,C$3,Monthly!$C$35:$BJ$35) -> -820672.96 | D15: =SUMIF(Monthly!$C$5:$BJ$5,D$3,Monthly!$C$35:$BJ$35) -> -1156452.6 | E15: =SUMIF(Monthly!$C$5:$BJ$5,E$3,Monthly!$C$35:$BJ$35) -> -1818164.6 | F15: =SUMIF(Monthly!$C$5:$BJ$5,F$3,Monthly!$C$35:$BJ$35) -> -2984436
A16: EBITDA margin | B16: =IF(B5=0,0,B15/B5) -> -3.1204519 | C16: =IF(C5=0,0,C15/C5) -> -1.3883278 | D16: =IF(D5=0,0,D15/D5) -> -1.1807904 | E16: =IF(E5=0,0,E15/E5) -> -1.2818581 | F16: =IF(F5=0,0,F15/F5) -> -1.5391458
A17: Depreciation | B17: =SUMIF(Monthly!$C$5:$BJ$5,B$3,Monthly!$C$49:$BJ$49) -> -6666.6667 | C17: =SUMIF(Monthly!$C$5:$BJ$5,C$3,Monthly!$C$49:$BJ$49) -> -6666.6667 | D17: =SUMIF(Monthly!$C$5:$BJ$5,D$3,Monthly!$C$49:$BJ$49) -> -6666.6667 | E17: =SUMIF(Monthly!$C$5:$BJ$5,E$3,Monthly!$C$49:$BJ$49) -> 0 | F17: =SUMIF(Monthly!$C$5:$BJ$5,F$3,Monthly!$C$49:$BJ$49) -> 0
A18: EBIT | B18: =SUMIF(Monthly!$C$5:$BJ$5,B$3,Monthly!$C$38:$BJ$38) -> -710063.14 | C18: =SUMIF(Monthly!$C$5:$BJ$5,C$3,Monthly!$C$38:$BJ$38) -> -827339.63 | D18: =SUMIF(Monthly!$C$5:$BJ$5,D$3,Monthly!$C$38:$BJ$38) -> -1163119.3 | E18: =SUMIF(Monthly!$C$5:$BJ$5,E$3,Monthly!$C$38:$BJ$38) -> -1818164.6 | F18: =SUMIF(Monthly!$C$5:$BJ$5,F$3,Monthly!$C$38:$BJ$38) -> -2984436
A19: Interest | B19: =SUMIF(Monthly!$C$5:$BJ$5,B$3,Monthly!$C$39:$BJ$39) -> 0 | C19: =SUMIF(Monthly!$C$5:$BJ$5,C$3,Monthly!$C$39:$BJ$39) -> 0 | D19: =SUMIF(Monthly!$C$5:$BJ$5,D$3,Monthly!$C$39:$BJ$39) -> 0 | E19: =SUMIF(Monthly!$C$5:$BJ$5,E$3,Monthly!$C$39:$BJ$39) -> 0 | F19: =SUMIF(Monthly!$C$5:$BJ$5,F$3,Monthly!$C$39:$BJ$39) -> 0
A20: Pre-tax income | B20: =SUMIF(Monthly!$C$5:$BJ$5,B$3,Monthly!$C$40:$BJ$40) -> -710063.14 | C20: =SUMIF(Monthly!$C$5:$BJ$5,C$3,Monthly!$C$40:$BJ$40) -> -827339.63 | D20: =SUMIF(Monthly!$C$5:$BJ$5,D$3,Monthly!$C$40:$BJ$40) -> -1163119.3 | E20: =SUMIF(Monthly!$C$5:$BJ$5,E$3,Monthly!$C$40:$BJ$40) -> -1818164.6 | F20: =SUMIF(Monthly!$C$5:$BJ$5,F$3,Monthly!$C$40:$BJ$40) -> -2984436
A21: Income tax | B21: =SUMIF(Monthly!$C$5:$BJ$5,B$3,Monthly!$C$43:$BJ$43) -> 0 | C21: =SUMIF(Monthly!$C$5:$BJ$5,C$3,Monthly!$C$43:$BJ$43) -> 0 | D21: =SUMIF(Monthly!$C$5:$BJ$5,D$3,Monthly!$C$43:$BJ$43) -> 0 | E21: =SUMIF(Monthly!$C$5:$BJ$5,E$3,Monthly!$C$43:$BJ$43) -> 0 | F21: =SUMIF(Monthly!$C$5:$BJ$5,F$3,Monthly!$C$43:$BJ$43) -> 0
A22: Net income | B22: =SUMIF(Monthly!$C$5:$BJ$5,B$3,Monthly!$C$44:$BJ$44) -> -710063.14 | C22: =SUMIF(Monthly!$C$5:$BJ$5,C$3,Monthly!$C$44:$BJ$44) -> -827339.63 | D22: =SUMIF(Monthly!$C$5:$BJ$5,D$3,Monthly!$C$44:$BJ$44) -> -1163119.3 | E22: =SUMIF(Monthly!$C$5:$BJ$5,E$3,Monthly!$C$44:$BJ$44) -> -1818164.6 | F22: =SUMIF(Monthly!$C$5:$BJ$5,F$3,Monthly!$C$44:$BJ$44) -> -2984436
A23: Net margin | B23: =IF(B5=0,0,B22/B5) -> -3.150027 | C23: =IF(C5=0,0,C22/C5) -> -1.3996058 | D23: =IF(D5=0,0,D22/D5) -> -1.1875974 | E23: =IF(E5=0,0,E22/E5) -> -1.2818581 | F23: =IF(F5=0,0,F22/F5) -> -1.5391458

Sheet Cash Flow
A1: Annual cash flow statement | H1: =HYPERLINK("#'Cover'!A1","◂ Contents") -> ◂ Contents
A2: Rolled up from the period detail (SUMIF on the year row; balances at year end).
A3: Year # | B3: 1 | C3: 2 | D3: 3 | E3: 4 | F3: 5
B4: Year 1 | C4: Year 2 | D4: Year 3 | E4: Year 4 | F4: Year 5
A5: Net income | B5: =SUMIF(Monthly!$C$5:$BJ$5,B$3,Monthly!$C$44:$BJ$44) -> -710063.14 | C5: =SUMIF(Monthly!$C$5:$BJ$5,C$3,Monthly!$C$44:$BJ$44) -> -827339.63 | D5: =SUMIF(Monthly!$C$5:$BJ$5,D$3,Monthly!$C$44:$BJ$44) -> -1163119.3 | E5: =SUMIF(Monthly!$C$5:$BJ$5,E$3,Monthly!$C$44:$BJ$44) -> -1818164.6 | F5: =SUMIF(Monthly!$C$5:$BJ$5,F$3,Monthly!$C$44:$BJ$44) -> -2984436
A6: Add back depreciation | B6: =-SUMIF(Monthly!$C$5:$BJ$5,B$3,Monthly!$C$49:$BJ$49) -> 6666.6667 | C6: =-SUMIF(Monthly!$C$5:$BJ$5,C$3,Monthly!$C$49:$BJ$49) -> 6666.6667 | D6: =-SUMIF(Monthly!$C$5:$BJ$5,D$3,Monthly!$C$49:$BJ$49) -> 6666.6667 | E6: =-SUMIF(Monthly!$C$5:$BJ$5,E$3,Monthly!$C$49:$BJ$49) -> 0 | F6: =-SUMIF(Monthly!$C$5:$BJ$5,F$3,Monthly!$C$49:$BJ$49) -> 0
A7: (Increase) / decrease in receivables | B7: =SUMIF(Monthly!$C$5:$BJ$5,B$3,Monthly!$C$63:$BJ$63) -> -5333.2481 | C7: =SUMIF(Monthly!$C$5:$BJ$5,C$3,Monthly!$C$63:$BJ$63) -> -5129.2265 | D7: =SUMIF(Monthly!$C$5:$BJ$5,D$3,Monthly!$C$63:$BJ$63) -> -5609.1941 | E7: =SUMIF(Monthly!$C$5:$BJ$5,E$3,Monthly!$C$63:$BJ$63) -> -6489.964 | F7: =SUMIF(Monthly!$C$5:$BJ$5,F$3,Monthly!$C$63:$BJ$63) -> -7823.3799
A8: (Increase) / decrease in inventory | B8: =SUMIF(Monthly!$C$5:$BJ$5,B$3,Monthly!$C$64:$BJ$64) -> 0 | C8: =SUMIF(Monthly!$C$5:$BJ$5,C$3,Monthly!$C$64:$BJ$64) -> 0 | D8: =SUMIF(Monthly!$C$5:$BJ$5,D$3,Monthly!$C$64:$BJ$64) -> 0 | E8: =SUMIF(Monthly!$C$5:$BJ$5,E$3,Monthly!$C$64:$BJ$64) -> 0 | F8: =SUMIF(Monthly!$C$5:$BJ$5,F$3,Monthly!$C$64:$BJ$64) -> 0
A9: Increase / (decrease) in payables | B9: =SUMIF(Monthly!$C$5:$BJ$5,B$3,Monthly!$C$65:$BJ$65) -> 3828.7027 | C9: =SUMIF(Monthly!$C$5:$BJ$5,C$3,Monthly!$C$65:$BJ$65) -> 3633.7478 | D9: =SUMIF(Monthly!$C$5:$BJ$5,D$3,Monthly!$C$65:$BJ$65) -> 3932.7648 | E9: =SUMIF(Monthly!$C$5:$BJ$5,E$3,Monthly!$C$65:$BJ$65) -> 4514.6239 | F9: =SUMIF(Monthly!$C$5:$BJ$5,F$3,Monthly!$C$65:$BJ$65) -> 5409.4531
A10: Increase / (decrease) in deferred revenue (annual plans, ~6 months unearned) | B10: =SUMIF(Monthly!$C$5:$BJ$5,B$3,Monthly!$C$67:$BJ$67) -> 39704.508 | C10: =SUMIF(Monthly!$C$5:$BJ$5,C$3,Monthly!$C$67:$BJ$67) -> 36960.025 | D10: =SUMIF(Monthly!$C$5:$BJ$5,D$3,Monthly!$C$67:$BJ$67) -> 40514.561 | E10: =SUMIF(Monthly!$C$5:$BJ$5,E$3,Monthly!$C$67:$BJ$67) -> 46960.52 | F10: =SUMIF(Monthly!$C$5:$BJ$5,F$3,Monthly!$C$67:$BJ$67) -> 56679.304
A11: Operating cash flow | B11: =SUMIF(Monthly!$C$5:$BJ$5,B$3,Monthly!$C$70:$BJ$70) -> -665196.51 | C11: =SUMIF(Monthly!$C$5:$BJ$5,C$3,Monthly!$C$70:$BJ$70) -> -785208.42 | D11: =SUMIF(Monthly!$C$5:$BJ$5,D$3,Monthly!$C$70:$BJ$70) -> -1117614.5 | E11: =SUMIF(Monthly!$C$5:$BJ$5,E$3,Monthly!$C$70:$BJ$70) -> -1773179.4 | F11: =SUMIF(Monthly!$C$5:$BJ$5,F$3,Monthly!$C$70:$BJ$70) -> -2930170.7
A12: Capital spending | B12: =SUMIF(Monthly!$C$5:$BJ$5,B$3,Monthly!$C$71:$BJ$71) -> -20000 | C12: =SUMIF(Monthly!$C$5:$BJ$5,C$3,Monthly!$C$71:$BJ$71) -> 0 | D12: =SUMIF(Monthly!$C$5:$BJ$5,D$3,Monthly!$C$71:$BJ$71) -> 0 | E12: =SUMIF(Monthly!$C$5:$BJ$5,E$3,Monthly!$C$71:$BJ$71) -> 0 | F12: =SUMIF(Monthly!$C$5:$BJ$5,F$3,Monthly!$C$71:$BJ$71) -> 0
A13: Equity raised | B13: =SUMIF(Monthly!$C$5:$BJ$5,B$3,Monthly!$C$72:$BJ$72) -> 3000000 | C13: =SUMIF(Monthly!$C$5:$BJ$5,C$3,Monthly!$C$72:$BJ$72) -> 0 | D13: =SUMIF(Monthly!$C$5:$BJ$5,D$3,Monthly!$C$72:$BJ$72) -> 0 | E13: =SUMIF(Monthly!$C$5:$BJ$5,E$3,Monthly!$C$72:$BJ$72) -> 0 | F13: =SUMIF(Monthly!$C$5:$BJ$5,F$3,Monthly!$C$72:$BJ$72) -> 0
A14: Loan drawdown | B14: =SUMIF(Monthly!$C$5:$BJ$5,B$3,Monthly!$C$55:$BJ$55) -> 0 | C14: =SUMIF(Monthly!$C$5:$BJ$5,C$3,Monthly!$C$55:$BJ$55) -> 0 | D14: =SUMIF(Monthly!$C$5:$BJ$5,D$3,Monthly!$C$55:$BJ$55) -> 0 | E14: =SUMIF(Monthly!$C$5:$BJ$5,E$3,Monthly!$C$55:$BJ$55) -> 0 | F14: =SUMIF(Monthly!$C$5:$BJ$5,F$3,Monthly!$C$55:$BJ$55) -> 0
A15: Loan repayment | B15: =SUMIF(Monthly!$C$5:$BJ$5,B$3,Monthly!$C$56:$BJ$56) -> 0 | C15: =SUMIF(Monthly!$C$5:$BJ$5,C$3,Monthly!$C$56:$BJ$56) -> 0 | D15: =SUMIF(Monthly!$C$5:$BJ$5,D$3,Monthly!$C$56:$BJ$56) -> 0 | E15: =SUMIF(Monthly!$C$5:$BJ$5,E$3,Monthly!$C$56:$BJ$56) -> 0 | F15: =SUMIF(Monthly!$C$5:$BJ$5,F$3,Monthly!$C$56:$BJ$56) -> 0
A16: Financing cash flow | B16: =SUMIF(Monthly!$C$5:$BJ$5,B$3,Monthly!$C$73:$BJ$73) -> 3000000 | C16: =SUMIF(Monthly!$C$5:$BJ$5,C$3,Monthly!$C$73:$BJ$73) -> 0 | D16: =SUMIF(Monthly!$C$5:$BJ$5,D$3,Monthly!$C$73:$BJ$73) -> 0 | E16: =SUMIF(Monthly!$C$5:$BJ$5,E$3,Monthly!$C$73:$BJ$73) -> 0 | F16: =SUMIF(Monthly!$C$5:$BJ$5,F$3,Monthly!$C$73:$BJ$73) -> 0
A17: Net change in cash | B17: =SUMIF(Monthly!$C$5:$BJ$5,B$3,Monthly!$C$74:$BJ$74) -> 2314803.5 | C17: =SUMIF(Monthly!$C$5:$BJ$5,C$3,Monthly!$C$74:$BJ$74) -> -785208.42 | D17: =SUMIF(Monthly!$C$5:$BJ$5,D$3,Monthly!$C$74:$BJ$74) -> -1117614.5 | E17: =SUMIF(Monthly!$C$5:$BJ$5,E$3,Monthly!$C$74:$BJ$74) -> -1773179.4 | F17: =SUMIF(Monthly!$C$5:$BJ$5,F$3,Monthly!$C$74:$BJ$74) -> -2930170.7
A18: Opening cash | B18: =INDEX(Monthly!$C$75:$BJ$75,(B$3-1)*12+1) -> 0 | C18: =INDEX(Monthly!$C$75:$BJ$75,(C$3-1)*12+1) -> 2314803.5 | D18: =INDEX(Monthly!$C$75:$BJ$75,(D$3-1)*12+1) -> 1529595.1 | E18: =INDEX(Monthly!$C$75:$BJ$75,(E$3-1)*12+1) -> 411980.55 | F18: =INDEX(Monthly!$C$75:$BJ$75,(F$3-1)*12+1) -> -1361198.8
A19: Closing cash | B19: =INDEX(Monthly!$C$76:$BJ$76,B$3*12) -> 2314803.5 | C19: =INDEX(Monthly!$C$76:$BJ$76,C$3*12) -> 1529595.1 | D19: =INDEX(Monthly!$C$76:$BJ$76,D$3*12) -> 411980.55 | E19: =INDEX(Monthly!$C$76:$BJ$76,E$3*12) -> -1361198.8 | F19: =INDEX(Monthly!$C$76:$BJ$76,F$3*12) -> -4291369.5

Sheet Balance Sheet
A1: Balance sheet at year end | H1: =HYPERLINK("#'Cover'!A1","◂ Contents") -> ◂ Contents
A2: Rolled up from the period detail (SUMIF on the year row; balances at year end).
A3: Year # | B3: 1 | C3: 2 | D3: 3 | E3: 4 | F3: 5
B4: Year 1 | C4: Year 2 | D4: Year 3 | E4: Year 4 | F4: Year 5
A5: Cash | B5: =INDEX(Monthly!$C$76:$BJ$76,B$3*12) -> 2314803.5 | C5: =INDEX(Monthly!$C$76:$BJ$76,C$3*12) -> 1529595.1 | D5: =INDEX(Monthly!$C$76:$BJ$76,D$3*12) -> 411980.55 | E5: =INDEX(Monthly!$C$76:$BJ$76,E$3*12) -> -1361198.8 | F5: =INDEX(Monthly!$C$76:$BJ$76,F$3*12) -> -4291369.5
A6: Accounts receivable | B6: =INDEX(Monthly!$C$60:$BJ$60,B$3*12) -> 5333.2481 | C6: =INDEX(Monthly!$C$60:$BJ$60,C$3*12) -> 10462.475 | D6: =INDEX(Monthly!$C$60:$BJ$60,D$3*12) -> 16071.669 | E6: =INDEX(Monthly!$C$60:$BJ$60,E$3*12) -> 22561.633 | F6: =INDEX(Monthly!$C$60:$BJ$60,F$3*12) -> 30385.013
A7: Inventory | B7: =INDEX(Monthly!$C$61:$BJ$61,B$3*12) -> 0 | C7: =INDEX(Monthly!$C$61:$BJ$61,C$3*12) -> 0 | D7: =INDEX(Monthly!$C$61:$BJ$61,D$3*12) -> 0 | E7: =INDEX(Monthly!$C$61:$BJ$61,E$3*12) -> 0 | F7: =INDEX(Monthly!$C$61:$BJ$61,F$3*12) -> 0
A8: Net fixed assets | B8: =INDEX(Monthly!$C$51:$BJ$51,B$3*12) -> 13333.333 | C8: =INDEX(Monthly!$C$51:$BJ$51,C$3*12) -> 6666.6667 | D8: =INDEX(Monthly!$C$51:$BJ$51,D$3*12) -> 0 | E8: =INDEX(Monthly!$C$51:$BJ$51,E$3*12) -> 0 | F8: =INDEX(Monthly!$C$51:$BJ$51,F$3*12) -> 0
A9: Total assets | B9: =INDEX(Monthly!$C$94:$BJ$94,B$3*12) -> 2333470.1 | C9: =INDEX(Monthly!$C$94:$BJ$94,C$3*12) -> 1546724.2 | D9: =INDEX(Monthly!$C$94:$BJ$94,D$3*12) -> 428052.22 | E9: =INDEX(Monthly!$C$94:$BJ$94,E$3*12) -> -1338637.2 | F9: =INDEX(Monthly!$C$94:$BJ$94,F$3*12) -> -4260984.5
A10: Accounts payable | B10: =INDEX(Monthly!$C$62:$BJ$62,B$3*12) -> 3828.7027 | C10: =INDEX(Monthly!$C$62:$BJ$62,C$3*12) -> 7462.4506 | D10: =INDEX(Monthly!$C$62:$BJ$62,D$3*12) -> 11395.215 | E10: =INDEX(Monthly!$C$62:$BJ$62,E$3*12) -> 15909.839 | F10: =INDEX(Monthly!$C$62:$BJ$62,F$3*12) -> 21319.292
A11: Deferred revenue (annual plans, ~6 months unearned) | B11: =INDEX(Monthly!$C$66:$BJ$66,B$3*12) -> 39704.508 | C11: =INDEX(Monthly!$C$66:$BJ$66,C$3*12) -> 76664.533 | D11: =INDEX(Monthly!$C$66:$BJ$66,D$3*12) -> 117179.09 | E11: =INDEX(Monthly!$C$66:$BJ$66,E$3*12) -> 164139.61 | F11: =INDEX(Monthly!$C$66:$BJ$66,F$3*12) -> 220818.92
A12: Loan | B12: =INDEX(Monthly!$C$57:$BJ$57,B$3*12) -> 0 | C12: =INDEX(Monthly!$C$57:$BJ$57,C$3*12) -> 0 | D12: =INDEX(Monthly!$C$57:$BJ$57,D$3*12) -> 0 | E12: =INDEX(Monthly!$C$57:$BJ$57,E$3*12) -> 0 | F12: =INDEX(Monthly!$C$57:$BJ$57,F$3*12) -> 0
A13: Total liabilities | B13: =INDEX(Monthly!$C$95:$BJ$95,B$3*12) -> 43533.211 | C13: =INDEX(Monthly!$C$95:$BJ$95,C$3*12) -> 84126.984 | D13: =INDEX(Monthly!$C$95:$BJ$95,D$3*12) -> 128574.31 | E13: =INDEX(Monthly!$C$95:$BJ$95,E$3*12) -> 180049.45 | F13: =INDEX(Monthly!$C$95:$BJ$95,F$3*12) -> 242138.21
A14: Paid-in capital | B14: =INDEX(Monthly!$C$92:$BJ$92,B$3*12) -> 3000000 | C14: =INDEX(Monthly!$C$92:$BJ$92,C$3*12) -> 3000000 | D14: =INDEX(Monthly!$C$92:$BJ$92,D$3*12) -> 3000000 | E14: =INDEX(Monthly!$C$92:$BJ$92,E$3*12) -> 3000000 | F14: =INDEX(Monthly!$C$92:$BJ$92,F$3*12) -> 3000000
A15: Retained earnings | B15: =INDEX(Monthly!$C$93:$BJ$93,B$3*12) -> -710063.14 | C15: =INDEX(Monthly!$C$93:$BJ$93,C$3*12) -> -1537402.8 | D15: =INDEX(Monthly!$C$93:$BJ$93,D$3*12) -> -2700522.1 | E15: =INDEX(Monthly!$C$93:$BJ$93,E$3*12) -> -4518686.6 | F15: =INDEX(Monthly!$C$93:$BJ$93,F$3*12) -> -7503122.7
A16: Total equity | B16: =INDEX(Monthly!$C$96:$BJ$96,B$3*12) -> 2289936.9 | C16: =INDEX(Monthly!$C$96:$BJ$96,C$3*12) -> 1462597.2 | D16: =INDEX(Monthly!$C$96:$BJ$96,D$3*12) -> 299477.91 | E16: =INDEX(Monthly!$C$96:$BJ$96,E$3*12) -> -1518686.6 | F16: =INDEX(Monthly!$C$96:$BJ$96,F$3*12) -> -4503122.7
A17: Total liabilities & equity | B17: =INDEX(Monthly!$C$97:$BJ$97,B$3*12) -> 2333470.1 | C17: =INDEX(Monthly!$C$97:$BJ$97,C$3*12) -> 1546724.2 | D17: =INDEX(Monthly!$C$97:$BJ$97,D$3*12) -> 428052.22 | E17: =INDEX(Monthly!$C$97:$BJ$97,E$3*12) -> -1338637.2 | F17: =INDEX(Monthly!$C$97:$BJ$97,F$3*12) -> -4260984.5
A18: Check: assets − liabilities − equity (must be 0) | B18: =INDEX(Monthly!$C$98:$BJ$98,B$3*12) -> 0 | C18: =INDEX(Monthly!$C$98:$BJ$98,C$3*12) -> 0 | D18: =INDEX(Monthly!$C$98:$BJ$98,D$3*12) -> 0 | E18: =INDEX(Monthly!$C$98:$BJ$98,E$3*12) -> 0 | F18: =INDEX(Monthly!$C$98:$BJ$98,F$3*12) -> 0

Sheet Monthly
A1: Monthly projection | D1: =HYPERLINK("#'Cover'!A1","◂ Contents") -> ◂ Contents
A2: $ unless stated; costs shown as negatives. Every period uses the same formula.
A3: Month | C3: M1 | D3: M2 | E3: M3 | F3: M4 | G3: M5 | H3: M6 | I3: M7 | J3: M8 | K3: M9 | L3: M10 | M3: M11 | N3: M12 | O3: M13 | P3: M14 | Q3: M15 | R3: M16 | S3: M17 | T3: M18 | U3: M19 | V3: M20 | W3: M21 | X3: M22 | Y3: M23 | Z3: M24 | AA3: M25 | AB3: M26 | AC3: M27 | AD3: M28 | AE3: M29 | AF3: M30 | AG3: M31 | AH3: M32 | AI3: M33 | AJ3: M34 | AK3: M35 | AL3: M36 | AM3: M37 | AN3: M38 | AO3: M39 | AP3: M40 | AQ3: M41 | AR3: M42 | AS3: M43 | AT3: M44 | AU3: M45 | AV3: M46 | AW3: M47 | AX3: M48 | AY3: M49 | AZ3: M50 | BA3: M51 | BB3: M52 | BC3: M53 | BD3: M54 | BE3: M55 | BF3: M56 | BG3: M57 | BH3: M58 | BI3: M59 | BJ3: M60
A4: Period # | C4: 1 | D4: 2 | E4: 3 | F4: 4 | G4: 5 | H4: 6 | I4: 7 | J4: 8 | K4: 9 | L4: 10 | M4: 11 | N4: 12 | O4: 13 | P4: 14 | Q4: 15 | R4: 16 | S4: 17 | T4: 18 | U4: 19 | V4: 20 | W4: 21 | X4: 22 | Y4: 23 | Z4: 24 | AA4: 25 | AB4: 26 | AC4: 27 | AD4: 28 | AE4: 29 | AF4: 30 | AG4: 31 | AH4: 32 | AI4: 33 | AJ4: 34 | AK4: 35 | AL4: 36 | AM4: 37 | AN4: 38 | AO4: 39 | AP4: 40 | AQ4: 41 | AR4: 42 | AS4: 43 | AT4: 44 | AU4: 45 | AV4: 46 | AW4: 47 | AX4: 48 | AY4: 49 | AZ4: 50 | BA4: 51 | BB4: 52 | BC4: 53 | BD4: 54 | BE4: 55 | BF4: 56 | BG4: 57 | BH4: 58 | BI4: 59 | BJ4: 60
A5: Year # | C5: =ROUNDUP(C4*1/12,0) -> 1 | D5: =ROUNDUP(D4*1/12,0) -> 1 | E5: =ROUNDUP(E4*1/12,0) -> 1 | F5: =ROUNDUP(F4*1/12,0) -> 1 | G5: =ROUNDUP(G4*1/12,0) -> 1 | H5: =ROUNDUP(H4*1/12,0) -> 1 | I5: =ROUNDUP(I4*1/12,0) -> 1 | J5: =ROUNDUP(J4*1/12,0) -> 1 | ... BJ5: =ROUNDUP(BJ4*1/12,0) -> 5
A7: Customers
A8: New customers — organic / referral | C8: =Inputs!$E$12*(1+Inputs!$E$13)^(C$5-1)*1 -> 12 | D8: =Inputs!$E$12*(1+Inputs!$E$13)^(D$5-1)*1 -> 12 | E8: =Inputs!$E$12*(1+Inputs!$E$13)^(E$5-1)*1 -> 12 | F8: =Inputs!$E$12*(1+Inputs!$E$13)^(F$5-1)*1 -> 12 | G8: =Inputs!$E$12*(1+Inputs!$E$13)^(G$5-1)*1 -> 12 | H8: =Inputs!$E$12*(1+Inputs!$E$13)^(H$5-1)*1 -> 12 | I8: =Inputs!$E$12*(1+Inputs!$E$13)^(I$5-1)*1 -> 12 | J8: =Inputs!$E$12*(1+Inputs!$E$13)^(J$5-1)*1 -> 12 | ... BJ8: =Inputs!$E$12*(1+Inputs!$E$13)^(BJ$5-1)*1 -> 34.2732
A9: New customers — paid marketing | C9: =-C30/MAX(1,Inputs!$E$16) -> 17.777778 | D9: =-D30/MAX(1,Inputs!$E$16) -> 17.777778 | E9: =-E30/MAX(1,Inputs!$E$16) -> 17.777778 | F9: =-F30/MAX(1,Inputs!$E$16) -> 17.777778 | G9: =-G30/MAX(1,Inputs!$E$16) -> 17.777778 | H9: =-H30/MAX(1,Inputs!$E$16) -> 17.777778 | I9: =-I30/MAX(1,Inputs!$E$16) -> 17.777778 | J9: =-J30/MAX(1,Inputs!$E$16) -> 17.777778 | ... BJ9: =-BJ30/MAX(1,Inputs!$E$16) -> 36.864
A10: New customers — total | C10: =C8+C9 -> 29.777778 | D10: =D8+D9 -> 29.777778 | E10: =E8+E9 -> 29.777778 | F10: =F8+F9 -> 29.777778 | G10: =G8+G9 -> 29.777778 | H10: =H8+H9 -> 29.777778 | I10: =I8+I9 -> 29.777778 | J10: =J8+J9 -> 29.777778 | ... BJ10: =BJ8+BJ9 -> 71.1372
A11: Customers — opening | C11: =Inputs!$E$7 -> 30 | D11: =C13 -> 58.877778 | E11: =D13 -> 86.889222 | F11: =E13 -> 114.06032 | G11: =F13 -> 140.41629 | H11: =G13 -> 165.98158 | I11: =H13 -> 190.77991 | J11: =I13 -> 214.83429 | K11: =J13 -> 238.16704 | ... BJ11: =BI13 -> 1531.547
A12: Customers lost (churn) | C12: =-C11*Inputs!$E$10 -> -0.9 | D12: =-D11*Inputs!$E$10 -> -1.7663333 | E12: =-E11*Inputs!$E$10 -> -2.6066767 | F12: =-F11*Inputs!$E$10 -> -3.4218097 | G12: =-G11*Inputs!$E$10 -> -4.2124887 | H12: =-H11*Inputs!$E$10 -> -4.9794474 | I12: =-I11*Inputs!$E$10 -> -5.7233973 | J12: =-J11*Inputs!$E$10 -> -6.4450287 | ... BJ12: =-BJ11*Inputs!$E$10 -> -45.946409
A13: Customers — closing | C13: =C11+C10+C12 -> 58.877778 | D13: =D11+D10+D12 -> 86.889222 | E13: =E11+E10+E12 -> 114.06032 | F13: =F11+F10+F12 -> 140.41629 | G13: =G11+G10+G12 -> 165.98158 | H13: =H11+H10+H12 -> 190.77991 | I13: =I11+I10+I12 -> 214.83429 | J13: =J11+J10+J12 -> 238.16704 | ... BJ13: =BJ11+BJ10+BJ12 -> 1556.7378
A14: MRR per new customer | C14: =Inputs!$E$8*(1+Inputs!$E$9)^(C$5-1) -> 99 | D14: =Inputs!$E$8*(1+Inputs!$E$9)^(D$5-1) -> 99 | E14: =Inputs!$E$8*(1+Inputs!$E$9)^(E$5-1) -> 99 | F14: =Inputs!$E$8*(1+Inputs!$E$9)^(F$5-1) -> 99 | G14: =Inputs!$E$8*(1+Inputs!$E$9)^(G$5-1) -> 99 | H14: =Inputs!$E$8*(1+Inputs!$E$9)^(H$5-1) -> 99 | I14: =Inputs!$E$8*(1+Inputs!$E$9)^(I$5-1) -> 99 | J14: =Inputs!$E$8*(1+Inputs!$E$9)^(J$5-1) -> 99 | ... BJ14: =Inputs!$E$8*(1+Inputs!$E$9)^(BJ$5-1) -> 111.42537
A16: MRR waterfall
A17: Opening MRR | C17: =Inputs!$E$7*Inputs!$E$8 -> 2970 | D17: =C21 -> 5843.75 | E17: =D21 -> 8645.6562 | F17: =E21 -> 11377.515 | G17: =F21 -> 14041.077 | H17: =G21 -> 16638.05 | I17: =H21 -> 19170.099 | J17: =I21 -> 21638.846 | K17: =J21 -> 24045.875 | ... BJ17: =BI21 -> 180604.39
A18: New MRR | C18: =C10*C14 -> 2948 | D18: =D10*D14 -> 2948 | E18: =E10*E14 -> 2948 | F18: =F10*F14 -> 2948 | G18: =G10*G14 -> 2948 | H18: =H10*H14 -> 2948 | I18: =I10*I14 -> 2948 | J18: =J10*J14 -> 2948 | ... BJ18: =BJ10*BJ14 -> 7926.489
A19: Expansion MRR | C19: =C17*Inputs!$E$11 -> 14.85 | D19: =D17*Inputs!$E$11 -> 29.21875 | E19: =E17*Inputs!$E$11 -> 43.228281 | F19: =F17*Inputs!$E$11 -> 56.887574 | G19: =G17*Inputs!$E$11 -> 70.205385 | H19: =H17*Inputs!$E$11 -> 83.19025 | I19: =I17*Inputs!$E$11 -> 95.850494 | J19: =J17*Inputs!$E$11 -> 108.19423 | ... BJ19: =BJ17*Inputs!$E$11 -> 903.02193
A20: Churned MRR | C20: =-C17*Inputs!$E$10 -> -89.1 | D20: =-D17*Inputs!$E$10 -> -175.3125 | E20: =-E17*Inputs!$E$10 -> -259.36969 | F20: =-F17*Inputs!$E$10 -> -341.32545 | G20: =-G17*Inputs!$E$10 -> -421.23231 | H20: =-H17*Inputs!$E$10 -> -499.1415 | I20: =-I17*Inputs!$E$10 -> -575.10296 | J20: =-J17*Inputs!$E$10 -> -649.16539 | ... BJ20: =-BJ17*Inputs!$E$10 -> -5418.1316
A21: Closing MRR | C21: =C17+C18+C19+C20 -> 5843.75 | D21: =D17+D18+D19+D20 -> 8645.6562 | E21: =E17+E18+E19+E20 -> 11377.515 | F21: =F17+F18+F19+F20 -> 14041.077 | G21: =G17+G18+G19+G20 -> 16638.05 | H21: =H17+H18+H19+H20 -> 19170.099 | I21: =I17+I18+I19+I20 -> 21638.846 | J21: =J17+J18+J19+J20 -> 24045.875 | ... BJ21: =BJ17+BJ18+BJ19+BJ20 -> 184015.77
A23: Revenue & cost of revenue
A24: Revenue (average MRR × months) | C24: =(C17+C21)/2*1 -> 4406.875 | D24: =(D17+D21)/2*1 -> 7244.7031 | E24: =(E17+E21)/2*1 -> 10011.586 | F24: =(F17+F21)/2*1 -> 12709.296 | G24: =(G17+G21)/2*1 -> 15339.564 | H24: =(H17+H21)/2*1 -> 17904.074 | I24: =(I17+I21)/2*1 -> 20404.473 | J24: =(J17+J21)/2*1 -> 22842.361 | ... BJ24: =(BJ17+BJ21)/2*1 -> 182310.08
A25: Hosting, payment fees & support | C25: =-(C24*Inputs!$E$18+(C11+C13)/2*Inputs!$E$19*1) -> -529.56528 | D25: =-(D24*Inputs!$E$18+(D11+D13)/2*Inputs!$E$19*1) -> -870.23731 | E25: =-(E24*Inputs!$E$18+(E11+E13)/2*Inputs!$E$19*1) -> -1202.1081 | F25: =-(F24*Inputs!$E$18+(F11+F13)/2*Inputs!$E$19*1) -> -1525.4062 | G25: =-(G24*Inputs!$E$18+(G11+G13)/2*Inputs!$E$19*1) -> -1840.3542 | H25: =-(H24*Inputs!$E$18+(H11+H13)/2*Inputs!$E$19*1) -> -2147.1689 | I25: =-(I24*Inputs!$E$18+(I11+I13)/2*Inputs!$E$19*1) -> -2446.0615 | J25: =-(J24*Inputs!$E$18+(J11+J13)/2*Inputs!$E$19*1) -> -2737.2374 | ... BJ25: =-(BJ24*Inputs!$E$18+(BJ11+BJ13)/2*Inputs!$E$19*1) -> -21319.292
A26: Gross profit | C26: =C24+C25 -> 3877.3097 | D26: =D24+D25 -> 6374.4658 | E26: =E24+E25 -> 8809.4774 | F26: =F24+F25 -> 11183.89 | G26: =G24+G25 -> 13499.209 | H26: =H24+H25 -> 15756.905 | I26: =I24+I25 -> 17958.411 | J26: =J24+J25 -> 20105.123 | ... BJ26: =BJ24+BJ25 -> 160990.78
A28: Operating expenses
A29: Payroll | C29: =Headcount!C19 -> -61750 | D29: =Headcount!D19 -> -61750 | E29: =Headcount!E19 -> -61750 | F29: =Headcount!F19 -> -61750 | G29: =Headcount!G19 -> -61750 | H29: =Headcount!H19 -> -61750 | I29: =Headcount!I19 -> -61750 | J29: =Headcount!J19 -> -61750 | ... BJ29: =Headcount!BJ19 -> -365708.75
A30: Paid marketing | C30: =-Inputs!$E$14*(1+Inputs!$E$15)^(C$5-1)*1 -> -8000 | D30: =-Inputs!$E$14*(1+Inputs!$E$15)^(D$5-1)*1 -> -8000 | E30: =-Inputs!$E$14*(1+Inputs!$E$15)^(E$5-1)*1 -> -8000 | F30: =-Inputs!$E$14*(1+Inputs!$E$15)^(F$5-1)*1 -> -8000 | G30: =-Inputs!$E$14*(1+Inputs!$E$15)^(G$5-1)*1 -> -8000 | H30: =-Inputs!$E$14*(1+Inputs!$E$15)^(H$5-1)*1 -> -8000 | I30: =-Inputs!$E$14*(1+Inputs!$E$15)^(I$5-1)*1 -> -8000 | J30: =-Inputs!$E$14*(1+Inputs!$E$15)^(J$5-1)*1 -> -8000 | ... BJ30: =-Inputs!$E$14*(1+Inputs!$E$15)^(BJ$5-1)*1 -> -16588.8
A31: Software & tools | C31: =-Headcount!C12*Inputs!$E$20*1 -> -900 | D31: =-Headcount!D12*Inputs!$E$20*1 -> -900 | E31: =-Headcount!E12*Inputs!$E$20*1 -> -900 | F31: =-Headcount!F12*Inputs!$E$20*1 -> -900 | G31: =-Headcount!G12*Inputs!$E$20*1 -> -900 | H31: =-Headcount!H12*Inputs!$E$20*1 -> -900 | I31: =-Headcount!I12*Inputs!$E$20*1 -> -900 | J31: =-Headcount!J12*Inputs!$E$20*1 -> -900 | ... BJ31: =-Headcount!BJ12*Inputs!$E$20*1 -> -4556.25
A32: Office & rent | C32: =-Inputs!$E$21*1 -> -1500 | D32: =-Inputs!$E$21*1 -> -1500 | E32: =-Inputs!$E$21*1 -> -1500 | F32: =-Inputs!$E$21*1 -> -1500 | G32: =-Inputs!$E$21*1 -> -1500 | H32: =-Inputs!$E$21*1 -> -1500 | I32: =-Inputs!$E$21*1 -> -1500 | J32: =-Inputs!$E$21*1 -> -1500 | ... BJ32: =-Inputs!$E$21*1 -> -1500
A33: Other G&A | C33: =-Inputs!$E$22*1 -> -3000 | D33: =-Inputs!$E$22*1 -> -3000 | E33: =-Inputs!$E$22*1 -> -3000 | F33: =-Inputs!$E$22*1 -> -3000 | G33: =-Inputs!$E$22*1 -> -3000 | H33: =-Inputs!$E$22*1 -> -3000 | I33: =-Inputs!$E$22*1 -> -3000 | J33: =-Inputs!$E$22*1 -> -3000 | ... BJ33: =-Inputs!$E$22*1 -> -3000
A34: Total operating expenses | C34: =C29+C30+C31+C32+C33 -> -75150 | D34: =D29+D30+D31+D32+D33 -> -75150 | E34: =E29+E30+E31+E32+E33 -> -75150 | F34: =F29+F30+F31+F32+F33 -> -75150 | G34: =G29+G30+G31+G32+G33 -> -75150 | H34: =H29+H30+H31+H32+H33 -> -75150 | I34: =I29+I30+I31+I32+I33 -> -75150 | J34: =J29+J30+J31+J32+J33 -> -75150 | ... BJ34: =BJ29+BJ30+BJ31+BJ32+BJ33 -> -391353.8
A35: EBITDA | C35: =C26+C34 -> -71272.69 | D35: =D26+D34 -> -68775.534 | E35: =E26+E34 -> -66340.523 | F35: =F26+F34 -> -63966.11 | G35: =G26+G34 -> -61650.791 | H35: =H26+H34 -> -59393.095 | I35: =I26+I34 -> -57191.589 | J35: =J26+J34 -> -55044.877 | ... BJ35: =BJ26+BJ34 -> -230363.02
A37: Profit after depreciation, interest, tax
A38: EBIT | C38: =C35+C49 -> -71828.246 | D38: =D35+D49 -> -69331.09 | E38: =E35+E49 -> -66896.078 | F38: =F35+F49 -> -64521.666 | G38: =G35+G49 -> -62206.346 | H38: =H35+H49 -> -59948.65 | I38: =I35+I49 -> -57747.144 | J38: =J35+J49 -> -55600.432 | ... BJ38: =BJ35+BJ49 -> -230363.02
A39: Interest on loan (average balance after drawdown) | C39: =-(C54+C55+C57)/2*Inputs!$E$48/12 -> 0 | D39: =-(D54+D55+D57)/2*Inputs!$E$48/12 -> 0 | E39: =-(E54+E55+E57)/2*Inputs!$E$48/12 -> 0 | F39: =-(F54+F55+F57)/2*Inputs!$E$48/12 -> 0 | G39: =-(G54+G55+G57)/2*Inputs!$E$48/12 -> 0 | H39: =-(H54+H55+H57)/2*Inputs!$E$48/12 -> 0 | I39: =-(I54+I55+I57)/2*Inputs!$E$48/12 -> 0 | J39: =-(J54+J55+J57)/2*Inputs!$E$48/12 -> 0 | ... BJ39: =-(BJ54+BJ55+BJ57)/2*Inputs!$E$48/12 -> 0
A40: Pre-tax income | C40: =C38+C39 -> -71828.246 | D40: =D38+D39 -> -69331.09 | E40: =E38+E39 -> -66896.078 | F40: =F38+F39 -> -64521.666 | G40: =G38+G39 -> -62206.346 | H40: =H38+H39 -> -59948.65 | I40: =I38+I39 -> -57747.144 | J40: =J38+J39 -> -55600.432 | ... BJ40: =BJ38+BJ39 -> -230363.02
A41: Helper: cumulative pre-tax income | C41: =C40 -> -71828.246 | D41: =C41+D40 -> -141159.34 | E41: =D41+E40 -> -208055.41 | F41: =E41+F40 -> -272577.08 | G41: =F41+G40 -> -334783.43 | H41: =G41+H40 -> -394732.08 | I41: =H41+I40 -> -452479.22 | J41: =I41+J40 -> -508079.65 | K41: =J41+K40 -> -561586.8 | ... BJ41: =BI41+BJ40 -> -7503122.7
A42: Helper: cumulative taxable income (losses carried forward) | C42: =MAX(0,C41) -> 0 | D42: =MAX(C42,D41) -> 0 | E42: =MAX(D42,E41) -> 0 | F42: =MAX(E42,F41) -> 0 | G42: =MAX(F42,G41) -> 0 | H42: =MAX(G42,H41) -> 0 | I42: =MAX(H42,I41) -> 0 | J42: =MAX(I42,J41) -> 0 | K42: =MAX(J42,K41) -> 0 | ... BJ42: =MAX(BI42,BJ41) -> 0
A43: Income tax | C43: =-C42*Inputs!$E$58 -> 0 | D43: =-(D42-C42)*Inputs!$E$58 -> 0 | E43: =-(E42-D42)*Inputs!$E$58 -> 0 | F43: =-(F42-E42)*Inputs!$E$58 -> 0 | G43: =-(G42-F42)*Inputs!$E$58 -> 0 | H43: =-(H42-G42)*Inputs!$E$58 -> 0 | I43: =-(I42-H42)*Inputs!$E$58 -> 0 | J43: =-(J42-I42)*Inputs!$E$58 -> 0 | K43: =-(K42-J42)*Inputs!$E$58 -> 0 | ... BJ43: =-(BJ42-BI42)*Inputs!$E$58 -> 0
A44: Net income | C44: =C40+C43 -> -71828.246 | D44: =D40+D43 -> -69331.09 | E44: =E40+E43 -> -66896.078 | F44: =F40+F43 -> -64521.666 | G44: =G40+G43 -> -62206.346 | H44: =H40+H43 -> -59948.65 | I44: =I40+I43 -> -57747.144 | J44: =J40+J43 -> -55600.432 | ... BJ44: =BJ40+BJ43 -> -230363.02
A46: Fixed assets & capital spending
A47: Capital spending | C47: =IF(C$4=1,Inputs!$E$23,0) -> 20000 | D47: =IF(D$4=1,Inputs!$E$23,0) -> 0 | E47: =IF(E$4=1,Inputs!$E$23,0) -> 0 | F47: =IF(F$4=1,Inputs!$E$23,0) -> 0 | G47: =IF(G$4=1,Inputs!$E$23,0) -> 0 | H47: =IF(H$4=1,Inputs!$E$23,0) -> 0 | I47: =IF(I$4=1,Inputs!$E$23,0) -> 0 | J47: =IF(J$4=1,Inputs!$E$23,0) -> 0 | ... BJ47: =IF(BJ$4=1,Inputs!$E$23,0) -> 0
A48: Fixed assets at cost | C48: =C47 -> 20000 | D48: =C48+D47 -> 20000 | E48: =D48+E47 -> 20000 | F48: =E48+F47 -> 20000 | G48: =F48+G47 -> 20000 | H48: =G48+H47 -> 20000 | I48: =H48+I47 -> 20000 | J48: =I48+J47 -> 20000 | K48: =J48+K47 -> 20000 | ... BJ48: =BI48+BJ47 -> 20000
A49: Depreciation | C49: =-MIN(C48/MAX(1,Inputs!$E$57*12),C47) -> -555.55556 | D49: =-MIN(D48/MAX(1,Inputs!$E$57*12),C51+D47) -> -555.55556 | E49: =-MIN(E48/MAX(1,Inputs!$E$57*12),D51+E47) -> -555.55556 | F49: =-MIN(F48/MAX(1,Inputs!$E$57*12),E51+F47) -> -555.55556 | G49: =-MIN(G48/MAX(1,Inputs!$E$57*12),F51+G47) -> -555.55556 | H49: =-MIN(H48/MAX(1,Inputs!$E$57*12),G51+H47) -> -555.55556 | I49: =-MIN(I48/MAX(1,Inputs!$E$57*12),H51+I47) -> -555.55556 | J49: =-MIN(J48/MAX(1,Inputs!$E$57*12),I51+J47) -> -555.55556 | K49: =-MIN(K48/MAX(1,Inputs!$E$57*12),J51+K47) -> -555.55556 | ... BJ49: =-MIN(BJ48/MAX(1,Inputs!$E$57*12),BI51+BJ47) -> 0
A50: Accumulated depreciation | C50: =C49 -> -555.55556 | D50: =C50+D49 -> -1111.1111 | E50: =D50+E49 -> -1666.6667 | F50: =E50+F49 -> -2222.2222 | G50: =F50+G49 -> -2777.7778 | H50: =G50+H49 -> -3333.3333 | I50: =H50+I49 -> -3888.8889 | J50: =I50+J49 -> -4444.4444 | K50: =J50+K49 -> -5000 | ... BJ50: =BI50+BJ49 -> -20000
A51: Net fixed assets | C51: =C48+C50 -> 19444.444 | D51: =D48+D50 -> 18888.889 | E51: =E48+E50 -> 18333.333 | F51: =F48+F50 -> 17777.778 | G51: =G48+G50 -> 17222.222 | H51: =H48+H50 -> 16666.667 | I51: =I48+I50 -> 16111.111 | J51: =J48+J50 -> 15555.556 | ... BJ51: =BJ48+BJ50 -> 0
A53: Debt
A54: Loan — opening balance | C54: =0 -> 0 | D54: =C57 -> 0 | E54: =D57 -> 0 | F54: =E57 -> 0 | G54: =F57 -> 0 | H54: =G57 -> 0 | I54: =H57 -> 0 | J54: =I57 -> 0 | K54: =J57 -> 0 | ... BJ54: =BI57 -> 0
A55: Loan drawdown | C55: =IF(C$4=1,Inputs!$E$47,0) -> 0 | D55: =IF(D$4=1,Inputs!$E$47,0) -> 0 | E55: =IF(E$4=1,Inputs!$E$47,0) -> 0 | F55: =IF(F$4=1,Inputs!$E$47,0) -> 0 | G55: =IF(G$4=1,Inputs!$E$47,0) -> 0 | H55: =IF(H$4=1,Inputs!$E$47,0) -> 0 | I55: =IF(I$4=1,Inputs!$E$47,0) -> 0 | J55: =IF(J$4=1,Inputs!$E$47,0) -> 0 | ... BJ55: =IF(BJ$4=1,Inputs!$E$47,0) -> 0
A56: Loan repayment | C56: =-MIN(C54,Inputs!$E$47/MAX(1,Inputs!$E$49*12)) -> 0 | D56: =-MIN(D54,Inputs!$E$47/MAX(1,Inputs!$E$49*12)) -> 0 | E56: =-MIN(E54,Inputs!$E$47/MAX(1,Inputs!$E$49*12)) -> 0 | F56: =-MIN(F54,Inputs!$E$47/MAX(1,Inputs!$E$49*12)) -> 0 | G56: =-MIN(G54,Inputs!$E$47/MAX(1,Inputs!$E$49*12)) -> 0 | H56: =-MIN(H54,Inputs!$E$47/MAX(1,Inputs!$E$49*12)) -> 0 | I56: =-MIN(I54,Inputs!$E$47/MAX(1,Inputs!$E$49*12)) -> 0 | J56: =-MIN(J54,Inputs!$E$47/MAX(1,Inputs!$E$49*12)) -> 0 | ... BJ56: =-MIN(BJ54,Inputs!$E$47/MAX(1,Inputs!$E$49*12)) -> 0
A57: Loan — closing balance | C57: =C54+C55+C56 -> 0 | D57: =D54+D55+D56 -> 0 | E57: =E54+E55+E56 -> 0 | F57: =F54+F55+F56 -> 0 | G57: =G54+G55+G56 -> 0 | H57: =H54+H55+H56 -> 0 | I57: =I54+I55+I56 -> 0 | J57: =J54+J55+J56 -> 0 | ... BJ57: =BJ54+BJ55+BJ56 -> 0
A59: Working capital
A60: Accounts receivable | C60: =C24*Inputs!$E$52/30 -> 734.47917 | D60: =D24*Inputs!$E$52/30 -> 1207.4505 | E60: =E24*Inputs!$E$52/30 -> 1668.5976 | F60: =F24*Inputs!$E$52/30 -> 2118.216 | G60: =G24*Inputs!$E$52/30 -> 2556.5939 | H60: =H24*Inputs!$E$52/30 -> 2984.0124 | I60: =I24*Inputs!$E$52/30 -> 3400.7454 | J60: =J24*Inputs!$E$52/30 -> 3807.0601 | ... BJ60: =BJ24*Inputs!$E$52/30 -> 30385.013
A61: Inventory | C61: =-C25*Inputs!$E$53/30 -> 0 | D61: =-D25*Inputs!$E$53/30 -> 0 | E61: =-E25*Inputs!$E$53/30 -> 0 | F61: =-F25*Inputs!$E$53/30 -> 0 | G61: =-G25*Inputs!$E$53/30 -> 0 | H61: =-H25*Inputs!$E$53/30 -> 0 | I61: =-I25*Inputs!$E$53/30 -> 0 | J61: =-J25*Inputs!$E$53/30 -> 0 | ... BJ61: =-BJ25*Inputs!$E$53/30 -> 0
A62: Accounts payable | C62: =-C25*Inputs!$E$54/30 -> 529.56528 | D62: =-D25*Inputs!$E$54/30 -> 870.23731 | E62: =-E25*Inputs!$E$54/30 -> 1202.1081 | F62: =-F25*Inputs!$E$54/30 -> 1525.4062 | G62: =-G25*Inputs!$E$54/30 -> 1840.3542 | H62: =-H25*Inputs!$E$54/30 -> 2147.1689 | I62: =-I25*Inputs!$E$54/30 -> 2446.0615 | J62: =-J25*Inputs!$E$54/30 -> 2737.2374 | ... BJ62: =-BJ25*Inputs!$E$54/30 -> 21319.292
A63: (Increase) / decrease in receivables | C63: =-C60 -> -734.47917 | D63: =C60-D60 -> -472.97135 | E63: =D60-E60 -> -461.14707 | F63: =E60-F60 -> -449.61839 | G63: =F60-G60 -> -438.37793 | H63: =G60-H60 -> -427.41849 | I63: =H60-I60 -> -416.73302 | J63: =I60-J60 -> -406.3147 | K63: =J60-K60 -> -396.15683 | ... BJ63: =BI60-BJ60 -> -575.85249
A64: (Increase) / decrease in inventory | C64: =-C61 -> 0 | D64: =C61-D61 -> 0 | E64: =D61-E61 -> 0 | F64: =E61-F61 -> 0 | G64: =F61-G61 -> 0 | H64: =G61-H61 -> 0 | I64: =H61-I61 -> 0 | J64: =I61-J61 -> 0 | K64: =J61-K61 -> 0 | ... BJ64: =BI61-BJ61 -> 0
A65: Increase / (decrease) in payables | C65: =C62 -> 529.56528 | D65: =D62-C62 -> 340.67203 | E65: =E62-D62 -> 331.87079 | F65: =F62-E62 -> 323.29811 | G65: =G62-F62 -> 314.94802 | H65: =H62-G62 -> 306.81471 | I65: =I62-H62 -> 298.89252 | J65: =J62-I62 -> 291.17595 | K65: =K62-J62 -> 283.65961 | ... BJ65: =BJ62-BI62 -> 396.67218
A66: Deferred revenue (annual plans, ~6 months unearned) | C66: =C21*Inputs!$E$17*6 -> 7012.5 | D66: =D21*Inputs!$E$17*6 -> 10374.788 | E66: =E21*Inputs!$E$17*6 -> 13653.018 | F66: =F21*Inputs!$E$17*6 -> 16849.292 | G66: =G21*Inputs!$E$17*6 -> 19965.66 | H66: =H21*Inputs!$E$17*6 -> 23004.119 | I66: =I21*Inputs!$E$17*6 -> 25966.616 | J66: =J21*Inputs!$E$17*6 -> 28855.05 | ... BJ66: =BJ21*Inputs!$E$17*6 -> 220818.92
A67: Increase / (decrease) in deferred revenue (annual plans, ~6 months unearned) | C67: =C66 -> 7012.5 | D67: =D66-C66 -> 3362.2875 | E67: =E66-D66 -> 3278.2303 | F67: =F66-E66 -> 3196.2746 | G67: =G66-F66 -> 3116.3677 | H67: =H66-G66 -> 3038.4585 | I67: =I66-H66 -> 2962.497 | J67: =J66-I66 -> 2888.4346 | K67: =K66-J66 -> 2816.2237 | ... BJ67: =BJ66-BI66 -> 4093.6552
A69: Cash flow
A70: Operating cash flow | C70: =C44-C49+C63+C64+C65+C67 -> -64465.104 | D70: =D44-D49+D63+D64+D65+D67 -> -65545.546 | E70: =E44-E49+E63+E64+E65+E67 -> -63191.569 | F70: =F44-F49+F63+F64+F65+F67 -> -60896.156 | G70: =G44-G49+G63+G64+G65+G67 -> -58657.853 | H70: =H44-H49+H63+H64+H65+H67 -> -56475.24 | I70: =I44-I49+I63+I64+I65+I67 -> -54346.932 | J70: =J44-J49+J63+J64+J65+J67 -> -52271.581 | ... BJ70: =BJ44-BJ49+BJ63+BJ64+BJ65+BJ67 -> -226448.54
A71: Investing cash flow (capex) | C71: =-C47 -> -20000 | D71: =-D47 -> 0 | E71: =-E47 -> 0 | F71: =-F47 -> 0 | G71: =-G47 -> 0 | H71: =-H47 -> 0 | I71: =-I47 -> 0 | J71: =-J47 -> 0 | ... BJ71: =-BJ47 -> 0
A72: Equity raised | C72: =IF(C$4=1,Inputs!$E$46,0) -> 3000000 | D72: =IF(D$4=1,Inputs!$E$46,0) -> 0 | E72: =IF(E$4=1,Inputs!$E$46,0) -> 0 | F72: =IF(F$4=1,Inputs!$E$46,0) -> 0 | G72: =IF(G$4=1,Inputs!$E$46,0) -> 0 | H72: =IF(H$4=1,Inputs!$E$46,0) -> 0 | I72: =IF(I$4=1,Inputs!$E$46,0) -> 0 | J72: =IF(J$4=1,Inputs!$E$46,0) -> 0 | ... BJ72: =IF(BJ$4=1,Inputs!$E$46,0) -> 0
A73: Financing cash flow | C73: =C72+C55+C56 -> 3000000 | D73: =D72+D55+D56 -> 0 | E73: =E72+E55+E56 -> 0 | F73: =F72+F55+F56 -> 0 | G73: =G72+G55+G56 -> 0 | H73: =H72+H55+H56 -> 0 | I73: =I72+I55+I56 -> 0 | J73: =J72+J55+J56 -> 0 | ... BJ73: =BJ72+BJ55+BJ56 -> 0
A74: Net cash flow | C74: =C70+C71+C73 -> 2915534.9 | D74: =D70+D71+D73 -> -65545.546 | E74: =E70+E71+E73 -> -63191.569 | F74: =F70+F71+F73 -> -60896.156 | G74: =G70+G71+G73 -> -58657.853 | H74: =H70+H71+H73 -> -56475.24 | I74: =I70+I71+I73 -> -54346.932 | J74: =J70+J71+J73 -> -52271.581 | ... BJ74: =BJ70+BJ71+BJ73 -> -226448.54
A75: Opening cash | C75: =0 -> 0 | D75: =C76 -> 2915534.9 | E75: =D76 -> 2849989.3 | F75: =E76 -> 2786797.8 | G75: =F76 -> 2725901.6 | H75: =G76 -> 2667243.8 | I75: =H76 -> 2610768.5 | J75: =I76 -> 2556421.6 | K75: =J76 -> 2504150 | ... BJ75: =BI76 -> -4064920.9
A76: Closing cash | C76: =C75+C74 -> 2915534.9 | D76: =D75+D74 -> 2849989.3 | E76: =E75+E74 -> 2786797.8 | F76: =F75+F74 -> 2725901.6 | G76: =G75+G74 -> 2667243.8 | H76: =H75+H74 -> 2610768.5 | I76: =I75+I74 -> 2556421.6 | J76: =J75+J74 -> 2504150 | ... BJ76: =BJ75+BJ74 -> -4291369.5
A77: Helper: EBITDA positive (1/0) | C77: =IF(C35>0,1,0) -> 0 | D77: =IF(D35>0,1,0) -> 0 | E77: =IF(E35>0,1,0) -> 0 | F77: =IF(F35>0,1,0) -> 0 | G77: =IF(G35>0,1,0) -> 0 | H77: =IF(H35>0,1,0) -> 0 | I77: =IF(I35>0,1,0) -> 0 | J77: =IF(J35>0,1,0) -> 0 | ... BJ77: =IF(BJ35>0,1,0) -> 0
A79: SaaS metric helpers
A80: Net burn per month (operating + investing; negative = cash generative) | C80: =-(C70+C71)/1 -> 84465.104 | D80: =-(D70+D71)/1 -> 65545.546 | E80: =-(E70+E71)/1 -> 63191.569 | F80: =-(F70+F71)/1 -> 60896.156 | G80: =-(G70+G71)/1 -> 58657.853 | H80: =-(H70+H71)/1 -> 56475.24 | I80: =-(I70+I71)/1 -> 54346.932 | J80: =-(J70+J71)/1 -> 52271.581 | ... BJ80: =-(BJ70+BJ71)/1 -> 226448.54
A81: Customer churn per month | C81: =Inputs!$E$10 -> 0.03 | D81: =Inputs!$E$10 -> 0.03 | E81: =Inputs!$E$10 -> 0.03 | F81: =Inputs!$E$10 -> 0.03 | G81: =Inputs!$E$10 -> 0.03 | H81: =Inputs!$E$10 -> 0.03 | I81: =Inputs!$E$10 -> 0.03 | J81: =Inputs!$E$10 -> 0.03 | ... BJ81: =Inputs!$E$10 -> 0.03
A83: Goal modules
A84: Helper: net income positive (1/0) | C84: =IF(C44>0,1,0) -> 0 | D84: =IF(D44>0,1,0) -> 0 | E84: =IF(E44>0,1,0) -> 0 | F84: =IF(F44>0,1,0) -> 0 | G84: =IF(G44>0,1,0) -> 0 | H84: =IF(H44>0,1,0) -> 0 | I84: =IF(I44>0,1,0) -> 0 | J84: =IF(J44>0,1,0) -> 0 | ... BJ84: =IF(BJ44>0,1,0) -> 0
A85: Cash flow before financing (operating + investing) | C85: =C70+C71 -> -84465.104 | D85: =D70+D71 -> -65545.546 | E85: =E70+E71 -> -63191.569 | F85: =F70+F71 -> -60896.156 | G85: =G70+G71 -> -58657.853 | H85: =H70+H71 -> -56475.24 | I85: =I70+I71 -> -54346.932 | J85: =J70+J71 -> -52271.581 | ... BJ85: =BJ70+BJ71 -> -226448.54
A86: Cumulative cash flow before financing | C86: =C85 -> -84465.104 | D86: =C86+D85 -> -150010.65 | E86: =D86+E85 -> -213202.22 | F86: =E86+F85 -> -274098.37 | G86: =F86+G85 -> -332756.23 | H86: =G86+H85 -> -389231.47 | I86: =H86+I85 -> -443578.4 | J86: =I86+J85 -> -495849.98 | K86: =J86+K85 -> -546097.85 | ... BJ86: =BI86+BJ85 -> -7291369.5
A87: Helper: lowest cumulative cash flow so far | C87: =C86 -> -84465.104 | D87: =MIN(C87,D86) -> -150010.65 | E87: =MIN(D87,E86) -> -213202.22 | F87: =MIN(E87,F86) -> -274098.37 | G87: =MIN(F87,G86) -> -332756.23 | H87: =MIN(G87,H86) -> -389231.47 | I87: =MIN(H87,I86) -> -443578.4 | J87: =MIN(I87,J86) -> -495849.98 | K87: =MIN(J87,K86) -> -546097.85 | ... BJ87: =MIN(BI87,BJ86) -> -7291369.5
A88: Helper: investment paid back (1/0) | C88: =IF(AND(C86>=0,C87<0),1,0) -> 0 | D88: =IF(AND(D86>=0,D87<0),1,0) -> 0 | E88: =IF(AND(E86>=0,E87<0),1,0) -> 0 | F88: =IF(AND(F86>=0,F87<0),1,0) -> 0 | G88: =IF(AND(G86>=0,G87<0),1,0) -> 0 | H88: =IF(AND(H86>=0,H87<0),1,0) -> 0 | I88: =IF(AND(I86>=0,I87<0),1,0) -> 0 | J88: =IF(AND(J86>=0,J87<0),1,0) -> 0 | ... BJ88: =IF(AND(BJ86>=0,BJ87<0),1,0) -> 0
A89: Unlevered free cash flow (operating + after-tax interest − capex) | C89: =C70-C39*(1-Inputs!$E$58)+C71 -> -84465.104 | D89: =D70-D39*(1-Inputs!$E$58)+D71 -> -65545.546 | E89: =E70-E39*(1-Inputs!$E$58)+E71 -> -63191.569 | F89: =F70-F39*(1-Inputs!$E$58)+F71 -> -60896.156 | G89: =G70-G39*(1-Inputs!$E$58)+G71 -> -58657.853 | H89: =H70-H39*(1-Inputs!$E$58)+H71 -> -56475.24 | I89: =I70-I39*(1-Inputs!$E$58)+I71 -> -54346.932 | J89: =J70-J39*(1-Inputs!$E$58)+J71 -> -52271.581 | ... BJ89: =BJ70-BJ39*(1-Inputs!$E$58)+BJ71 -> -226448.54
A91: Balance sheet
A92: Paid-in capital | C92: =C72 -> 3000000 | D92: =C92+D72 -> 3000000 | E92: =D92+E72 -> 3000000 | F92: =E92+F72 -> 3000000 | G92: =F92+G72 -> 3000000 | H92: =G92+H72 -> 3000000 | I92: =H92+I72 -> 3000000 | J92: =I92+J72 -> 3000000 | K92: =J92+K72 -> 3000000 | ... BJ92: =BI92+BJ72 -> 3000000
A93: Retained earnings | C93: =C44 -> -71828.246 | D93: =C93+D44 -> -141159.34 | E93: =D93+E44 -> -208055.41 | F93: =E93+F44 -> -272577.08 | G93: =F93+G44 -> -334783.43 | H93: =G93+H44 -> -394732.08 | I93: =H93+I44 -> -452479.22 | J93: =I93+J44 -> -508079.65 | K93: =J93+K44 -> -561586.8 | ... BJ93: =BI93+BJ44 -> -7503122.7
A94: Total assets | C94: =C76+C60+C61+C51 -> 2935713.8 | D94: =D76+D60+D61+D51 -> 2870085.7 | E94: =E76+E60+E61+E51 -> 2806799.7 | F94: =F76+F60+F61+F51 -> 2745797.6 | G94: =G76+G60+G61+G51 -> 2687022.6 | H94: =H76+H60+H61+H51 -> 2630419.2 | I94: =I76+I60+I61+I51 -> 2575933.5 | J94: =J76+J60+J61+J51 -> 2523512.6 | ... BJ94: =BJ76+BJ60+BJ61+BJ51 -> -4260984.5
A95: Total liabilities | C95: =C62+C57+C66 -> 7542.0653 | D95: =D62+D57+D66 -> 11245.025 | E95: =E62+E57+E66 -> 14855.126 | F95: =F62+F57+F66 -> 18374.699 | G95: =G62+G57+G66 -> 21806.014 | H95: =H62+H57+H66 -> 25151.287 | I95: =I62+I57+I66 -> 28412.677 | J95: =J62+J57+J66 -> 31592.288 | ... BJ95: =BJ62+BJ57+BJ66 -> 242138.21
A96: Total equity | C96: =C92+C93 -> 2928171.8 | D96: =D92+D93 -> 2858840.7 | E96: =E92+E93 -> 2791944.6 | F96: =F92+F93 -> 2727422.9 | G96: =G92+G93 -> 2665216.6 | H96: =H92+H93 -> 2605267.9 | I96: =I92+I93 -> 2547520.8 | J96: =J92+J93 -> 2491920.3 | ... BJ96: =BJ92+BJ93 -> -4503122.7
A97: Total liabilities & equity | C97: =C95+C96 -> 2935713.8 | D97: =D95+D96 -> 2870085.7 | E97: =E95+E96 -> 2806799.7 | F97: =F95+F96 -> 2745797.6 | G97: =G95+G96 -> 2687022.6 | H97: =H95+H96 -> 2630419.2 | I97: =I95+I96 -> 2575933.5 | J97: =J95+J96 -> 2523512.6 | ... BJ97: =BJ95+BJ96 -> -4260984.5
A98: Check: assets − liabilities − equity | C98: =C94-C97 -> 0 | D98: =D94-D97 -> 0 | E98: =E94-E97 -> 0 | F98: =F94-F97 -> 0 | G98: =G94-G97 -> 0 | H98: =H94-H97 -> 0 | I98: =I94-I97 -> 0 | J98: =J94-J97 -> 0 | ... BJ98: =BJ94-BJ97 -> 0

Sheet Headcount
A1: Headcount & payroll | D1: =HYPERLINK("#'Cover'!A1","◂ Contents") -> ◂ Contents
A2: $ unless stated; costs shown as negatives. Every period uses the same formula.
A3: Month | C3: M1 | D3: M2 | E3: M3 | F3: M4 | G3: M5 | H3: M6 | I3: M7 | J3: M8 | K3: M9 | L3: M10 | M3: M11 | N3: M12 | O3: M13 | P3: M14 | Q3: M15 | R3: M16 | S3: M17 | T3: M18 | U3: M19 | V3: M20 | W3: M21 | X3: M22 | Y3: M23 | Z3: M24 | AA3: M25 | AB3: M26 | AC3: M27 | AD3: M28 | AE3: M29 | AF3: M30 | AG3: M31 | AH3: M32 | AI3: M33 | AJ3: M34 | AK3: M35 | AL3: M36 | AM3: M37 | AN3: M38 | AO3: M39 | AP3: M40 | AQ3: M41 | AR3: M42 | AS3: M43 | AT3: M44 | AU3: M45 | AV3: M46 | AW3: M47 | AX3: M48 | AY3: M49 | AZ3: M50 | BA3: M51 | BB3: M52 | BC3: M53 | BD3: M54 | BE3: M55 | BF3: M56 | BG3: M57 | BH3: M58 | BI3: M59 | BJ3: M60
A4: Period # | C4: 1 | D4: 2 | E4: 3 | F4: 4 | G4: 5 | H4: 6 | I4: 7 | J4: 8 | K4: 9 | L4: 10 | M4: 11 | N4: 12 | O4: 13 | P4: 14 | Q4: 15 | R4: 16 | S4: 17 | T4: 18 | U4: 19 | V4: 20 | W4: 21 | X4: 22 | Y4: 23 | Z4: 24 | AA4: 25 | AB4: 26 | AC4: 27 | AD4: 28 | AE4: 29 | AF4: 30 | AG4: 31 | AH4: 32 | AI4: 33 | AJ4: 34 | AK4: 35 | AL4: 36 | AM4: 37 | AN4: 38 | AO4: 39 | AP4: 40 | AQ4: 41 | AR4: 42 | AS4: 43 | AT4: 44 | AU4: 45 | AV4: 46 | AW4: 47 | AX4: 48 | AY4: 49 | AZ4: 50 | BA4: 51 | BB4: 52 | BC4: 53 | BD4: 54 | BE4: 55 | BF4: 56 | BG4: 57 | BH4: 58 | BI4: 59 | BJ4: 60
A5: Year # | C5: =ROUNDUP(C4*1/12,0) -> 1 | D5: =ROUNDUP(D4*1/12,0) -> 1 | E5: =ROUNDUP(E4*1/12,0) -> 1 | F5: =ROUNDUP(F4*1/12,0) -> 1 | G5: =ROUNDUP(G4*1/12,0) -> 1 | H5: =ROUNDUP(H4*1/12,0) -> 1 | I5: =ROUNDUP(I4*1/12,0) -> 1 | J5: =ROUNDUP(J4*1/12,0) -> 1 | ... BJ5: =ROUNDUP(BJ4*1/12,0) -> 5
A7: Headcount (FTE)
A8: Engineering & product — FTE | C8: =Inputs!$E$26*(1+Inputs!$E$28)^(C$5-1)*MAX(0,MIN(1,C$4*1-Inputs!$E$29+1))/1 -> 3 | D8: =Inputs!$E$26*(1+Inputs!$E$28)^(D$5-1)*MAX(0,MIN(1,D$4*1-Inputs!$E$29+1))/1 -> 3 | E8: =Inputs!$E$26*(1+Inputs!$E$28)^(E$5-1)*MAX(0,MIN(1,E$4*1-Inputs!$E$29+1))/1 -> 3 | F8: =Inputs!$E$26*(1+Inputs!$E$28)^(F$5-1)*MAX(0,MIN(1,F$4*1-Inputs!$E$29+1))/1 -> 3 | G8: =Inputs!$E$26*(1+Inputs!$E$28)^(G$5-1)*MAX(0,MIN(1,G$4*1-Inputs!$E$29+1))/1 -> 3 | H8: =Inputs!$E$26*(1+Inputs!$E$28)^(H$5-1)*MAX(0,MIN(1,H$4*1-Inputs!$E$29+1))/1 -> 3 | I8: =Inputs!$E$26*(1+Inputs!$E$28)^(I$5-1)*MAX(0,MIN(1,I$4*1-Inputs!$E$29+1))/1 -> 3 | J8: =Inputs!$E$26*(1+Inputs!$E$28)^(J$5-1)*MAX(0,MIN(1,J$4*1-Inputs!$E$29+1))/1 -> 3 | ... BJ8: =Inputs!$E$26*(1+Inputs!$E$28)^(BJ$5-1)*MAX(0,MIN(1,BJ$4*1-Inputs!$E$29+1))/1 -> 15.1875
A9: Sales & marketing — FTE | C9: =Inputs!$E$30*(1+Inputs!$E$32)^(C$5-1)*MAX(0,MIN(1,C$4*1-Inputs!$E$33+1))/1 -> 1.5 | D9: =Inputs!$E$30*(1+Inputs!$E$32)^(D$5-1)*MAX(0,MIN(1,D$4*1-Inputs!$E$33+1))/1 -> 1.5 | E9: =Inputs!$E$30*(1+Inputs!$E$32)^(E$5-1)*MAX(0,MIN(1,E$4*1-Inputs!$E$33+1))/1 -> 1.5 | F9: =Inputs!$E$30*(1+Inputs!$E$32)^(F$5-1)*MAX(0,MIN(1,F$4*1-Inputs!$E$33+1))/1 -> 1.5 | G9: =Inputs!$E$30*(1+Inputs!$E$32)^(G$5-1)*MAX(0,MIN(1,G$4*1-Inputs!$E$33+1))/1 -> 1.5 | H9: =Inputs!$E$30*(1+Inputs!$E$32)^(H$5-1)*MAX(0,MIN(1,H$4*1-Inputs!$E$33+1))/1 -> 1.5 | I9: =Inputs!$E$30*(1+Inputs!$E$32)^(I$5-1)*MAX(0,MIN(1,I$4*1-Inputs!$E$33+1))/1 -> 1.5 | J9: =Inputs!$E$30*(1+Inputs!$E$32)^(J$5-1)*MAX(0,MIN(1,J$4*1-Inputs!$E$33+1))/1 -> 1.5 | ... BJ9: =Inputs!$E$30*(1+Inputs!$E$32)^(BJ$5-1)*MAX(0,MIN(1,BJ$4*1-Inputs!$E$33+1))/1 -> 7.59375
A10: Customer success — FTE | C10: =Inputs!$E$34*(1+Inputs!$E$36)^(C$5-1)*MAX(0,MIN(1,C$4*1-Inputs!$E$37+1))/1 -> 1 | D10: =Inputs!$E$34*(1+Inputs!$E$36)^(D$5-1)*MAX(0,MIN(1,D$4*1-Inputs!$E$37+1))/1 -> 1 | E10: =Inputs!$E$34*(1+Inputs!$E$36)^(E$5-1)*MAX(0,MIN(1,E$4*1-Inputs!$E$37+1))/1 -> 1 | F10: =Inputs!$E$34*(1+Inputs!$E$36)^(F$5-1)*MAX(0,MIN(1,F$4*1-Inputs!$E$37+1))/1 -> 1 | G10: =Inputs!$E$34*(1+Inputs!$E$36)^(G$5-1)*MAX(0,MIN(1,G$4*1-Inputs!$E$37+1))/1 -> 1 | H10: =Inputs!$E$34*(1+Inputs!$E$36)^(H$5-1)*MAX(0,MIN(1,H$4*1-Inputs!$E$37+1))/1 -> 1 | I10: =Inputs!$E$34*(1+Inputs!$E$36)^(I$5-1)*MAX(0,MIN(1,I$4*1-Inputs!$E$37+1))/1 -> 1 | J10: =Inputs!$E$34*(1+Inputs!$E$36)^(J$5-1)*MAX(0,MIN(1,J$4*1-Inputs!$E$37+1))/1 -> 1 | ... BJ10: =Inputs!$E$34*(1+Inputs!$E$36)^(BJ$5-1)*MAX(0,MIN(1,BJ$4*1-Inputs!$E$37+1))/1 -> 5.0625
A11: G&A (finance, ops) — FTE | C11: =Inputs!$E$38*(1+Inputs!$E$40)^(C$5-1)*MAX(0,MIN(1,C$4*1-Inputs!$E$41+1))/1 -> 0.5 | D11: =Inputs!$E$38*(1+Inputs!$E$40)^(D$5-1)*MAX(0,MIN(1,D$4*1-Inputs!$E$41+1))/1 -> 0.5 | E11: =Inputs!$E$38*(1+Inputs!$E$40)^(E$5-1)*MAX(0,MIN(1,E$4*1-Inputs!$E$41+1))/1 -> 0.5 | F11: =Inputs!$E$38*(1+Inputs!$E$40)^(F$5-1)*MAX(0,MIN(1,F$4*1-Inputs!$E$41+1))/1 -> 0.5 | G11: =Inputs!$E$38*(1+Inputs!$E$40)^(G$5-1)*MAX(0,MIN(1,G$4*1-Inputs!$E$41+1))/1 -> 0.5 | H11: =Inputs!$E$38*(1+Inputs!$E$40)^(H$5-1)*MAX(0,MIN(1,H$4*1-Inputs!$E$41+1))/1 -> 0.5 | I11: =Inputs!$E$38*(1+Inputs!$E$40)^(I$5-1)*MAX(0,MIN(1,I$4*1-Inputs!$E$41+1))/1 -> 0.5 | J11: =Inputs!$E$38*(1+Inputs!$E$40)^(J$5-1)*MAX(0,MIN(1,J$4*1-Inputs!$E$41+1))/1 -> 0.5 | ... BJ11: =Inputs!$E$38*(1+Inputs!$E$40)^(BJ$5-1)*MAX(0,MIN(1,BJ$4*1-Inputs!$E$41+1))/1 -> 2.53125
A12: Total FTE | C12: =C8+C9+C10+C11 -> 6 | D12: =D8+D9+D10+D11 -> 6 | E12: =E8+E9+E10+E11 -> 6 | F12: =F8+F9+F10+F11 -> 6 | G12: =G8+G9+G10+G11 -> 6 | H12: =H8+H9+H10+H11 -> 6 | I12: =I8+I9+I10+I11 -> 6 | J12: =J8+J9+J10+J11 -> 6 | ... BJ12: =BJ8+BJ9+BJ10+BJ11 -> 30.375
A14: Payroll cost (salary + taxes & benefits)
A15: Engineering & product — payroll cost | C15: =-C8*Inputs!$E$27/12*1*(1+Inputs!$E$42)*(1+Inputs!$E$43)^(C$5-1) -> -37500 | D15: =-D8*Inputs!$E$27/12*1*(1+Inputs!$E$42)*(1+Inputs!$E$43)^(D$5-1) -> -37500 | E15: =-E8*Inputs!$E$27/12*1*(1+Inputs!$E$42)*(1+Inputs!$E$43)^(E$5-1) -> -37500 | F15: =-F8*Inputs!$E$27/12*1*(1+Inputs!$E$42)*(1+Inputs!$E$43)^(F$5-1) -> -37500 | G15: =-G8*Inputs!$E$27/12*1*(1+Inputs!$E$42)*(1+Inputs!$E$43)^(G$5-1) -> -37500 | H15: =-H8*Inputs!$E$27/12*1*(1+Inputs!$E$42)*(1+Inputs!$E$43)^(H$5-1) -> -37500 | I15: =-I8*Inputs!$E$27/12*1*(1+Inputs!$E$42)*(1+Inputs!$E$43)^(I$5-1) -> -37500 | J15: =-J8*Inputs!$E$27/12*1*(1+Inputs!$E$42)*(1+Inputs!$E$43)^(J$5-1) -> -37500 | ... BJ15: =-BJ8*Inputs!$E$27/12*1*(1+Inputs!$E$42)*(1+Inputs!$E$43)^(BJ$5-1) -> -222090.34
A16: Sales & marketing — payroll cost | C16: =-C9*Inputs!$E$31/12*1*(1+Inputs!$E$42)*(1+Inputs!$E$43)^(C$5-1) -> -14250 | D16: =-D9*Inputs!$E$31/12*1*(1+Inputs!$E$42)*(1+Inputs!$E$43)^(D$5-1) -> -14250 | E16: =-E9*Inputs!$E$31/12*1*(1+Inputs!$E$42)*(1+Inputs!$E$43)^(E$5-1) -> -14250 | F16: =-F9*Inputs!$E$31/12*1*(1+Inputs!$E$42)*(1+Inputs!$E$43)^(F$5-1) -> -14250 | G16: =-G9*Inputs!$E$31/12*1*(1+Inputs!$E$42)*(1+Inputs!$E$43)^(G$5-1) -> -14250 | H16: =-H9*Inputs!$E$31/12*1*(1+Inputs!$E$42)*(1+Inputs!$E$43)^(H$5-1) -> -14250 | I16: =-I9*Inputs!$E$31/12*1*(1+Inputs!$E$42)*(1+Inputs!$E$43)^(I$5-1) -> -14250 | J16: =-J9*Inputs!$E$31/12*1*(1+Inputs!$E$42)*(1+Inputs!$E$43)^(J$5-1) -> -14250 | ... BJ16: =-BJ9*Inputs!$E$31/12*1*(1+Inputs!$E$42)*(1+Inputs!$E$43)^(BJ$5-1) -> -84394.328
A17: Customer success — payroll cost | C17: =-C10*Inputs!$E$35/12*1*(1+Inputs!$E$42)*(1+Inputs!$E$43)^(C$5-1) -> -6000 | D17: =-D10*Inputs!$E$35/12*1*(1+Inputs!$E$42)*(1+Inputs!$E$43)^(D$5-1) -> -6000 | E17: =-E10*Inputs!$E$35/12*1*(1+Inputs!$E$42)*(1+Inputs!$E$43)^(E$5-1) -> -6000 | F17: =-F10*Inputs!$E$35/12*1*(1+Inputs!$E$42)*(1+Inputs!$E$43)^(F$5-1) -> -6000 | G17: =-G10*Inputs!$E$35/12*1*(1+Inputs!$E$42)*(1+Inputs!$E$43)^(G$5-1) -> -6000 | H17: =-H10*Inputs!$E$35/12*1*(1+Inputs!$E$42)*(1+Inputs!$E$43)^(H$5-1) -> -6000 | I17: =-I10*Inputs!$E$35/12*1*(1+Inputs!$E$42)*(1+Inputs!$E$43)^(I$5-1) -> -6000 | J17: =-J10*Inputs!$E$35/12*1*(1+Inputs!$E$42)*(1+Inputs!$E$43)^(J$5-1) -> -6000 | ... BJ17: =-BJ10*Inputs!$E$35/12*1*(1+Inputs!$E$42)*(1+Inputs!$E$43)^(BJ$5-1) -> -35534.454
A18: G&A (finance, ops) — payroll cost | C18: =-C11*Inputs!$E$39/12*1*(1+Inputs!$E$42)*(1+Inputs!$E$43)^(C$5-1) -> -4000 | D18: =-D11*Inputs!$E$39/12*1*(1+Inputs!$E$42)*(1+Inputs!$E$43)^(D$5-1) -> -4000 | E18: =-E11*Inputs!$E$39/12*1*(1+Inputs!$E$42)*(1+Inputs!$E$43)^(E$5-1) -> -4000 | F18: =-F11*Inputs!$E$39/12*1*(1+Inputs!$E$42)*(1+Inputs!$E$43)^(F$5-1) -> -4000 | G18: =-G11*Inputs!$E$39/12*1*(1+Inputs!$E$42)*(1+Inputs!$E$43)^(G$5-1) -> -4000 | H18: =-H11*Inputs!$E$39/12*1*(1+Inputs!$E$42)*(1+Inputs!$E$43)^(H$5-1) -> -4000 | I18: =-I11*Inputs!$E$39/12*1*(1+Inputs!$E$42)*(1+Inputs!$E$43)^(I$5-1) -> -4000 | J18: =-J11*Inputs!$E$39/12*1*(1+Inputs!$E$42)*(1+Inputs!$E$43)^(J$5-1) -> -4000 | ... BJ18: =-BJ11*Inputs!$E$39/12*1*(1+Inputs!$E$42)*(1+Inputs!$E$43)^(BJ$5-1) -> -23689.636
A19: Total payroll | C19: =C15+C16+C17+C18 -> -61750 | D19: =D15+D16+D17+D18 -> -61750 | E19: =E15+E16+E17+E18 -> -61750 | F19: =F15+F16+F17+F18 -> -61750 | G19: =G15+G16+G17+G18 -> -61750 | H19: =H15+H16+H17+H18 -> -61750 | I19: =I15+I16+I17+I18 -> -61750 | J19: =J15+J16+J17+J18 -> -61750 | ... BJ19: =BJ15+BJ16+BJ17+BJ18 -> -365708.75

Sheet Scenario calc
A1: Scenario calculation — Low, Base and High side by side | D1: =HYPERLINK("#'Cover'!A1","◂ Contents") -> ◂ Contents
A2: The model's period calculation, copied three times; each copy reads its own Inputs column. Feeds the Scenarios sheet only.
A4: Low scenario — reads Inputs column B
A5: Month | C5: M1 | D5: M2 | E5: M3 | F5: M4 | G5: M5 | H5: M6 | I5: M7 | J5: M8 | K5: M9 | L5: M10 | M5: M11 | N5: M12 | O5: M13 | P5: M14 | Q5: M15 | R5: M16 | S5: M17 | T5: M18 | U5: M19 | V5: M20 | W5: M21 | X5: M22 | Y5: M23 | Z5: M24 | AA5: M25 | AB5: M26 | AC5: M27 | AD5: M28 | AE5: M29 | AF5: M30 | AG5: M31 | AH5: M32 | AI5: M33 | AJ5: M34 | AK5: M35 | AL5: M36 | AM5: M37 | AN5: M38 | AO5: M39 | AP5: M40 | AQ5: M41 | AR5: M42 | AS5: M43 | AT5: M44 | AU5: M45 | AV5: M46 | AW5: M47 | AX5: M48 | AY5: M49 | AZ5: M50 | BA5: M51 | BB5: M52 | BC5: M53 | BD5: M54 | BE5: M55 | BF5: M56 | BG5: M57 | BH5: M58 | BI5: M59 | BJ5: M60
A6: Period # | C6: 1 | D6: 2 | E6: 3 | F6: 4 | G6: 5 | H6: 6 | I6: 7 | J6: 8 | K6: 9 | L6: 10 | M6: 11 | N6: 12 | O6: 13 | P6: 14 | Q6: 15 | R6: 16 | S6: 17 | T6: 18 | U6: 19 | V6: 20 | W6: 21 | X6: 22 | Y6: 23 | Z6: 24 | AA6: 25 | AB6: 26 | AC6: 27 | AD6: 28 | AE6: 29 | AF6: 30 | AG6: 31 | AH6: 32 | AI6: 33 | AJ6: 34 | AK6: 35 | AL6: 36 | AM6: 37 | AN6: 38 | AO6: 39 | AP6: 40 | AQ6: 41 | AR6: 42 | AS6: 43 | AT6: 44 | AU6: 45 | AV6: 46 | AW6: 47 | AX6: 48 | AY6: 49 | AZ6: 50 | BA6: 51 | BB6: 52 | BC6: 53 | BD6: 54 | BE6: 55 | BF6: 56 | BG6: 57 | BH6: 58 | BI6: 59 | BJ6: 60
A7: Year # | C7: =ROUNDUP(C6*1/12,0) -> 1 | D7: =ROUNDUP(D6*1/12,0) -> 1 | E7: =ROUNDUP(E6*1/12,0) -> 1 | F7: =ROUNDUP(F6*1/12,0) -> 1 | G7: =ROUNDUP(G6*1/12,0) -> 1 | H7: =ROUNDUP(H6*1/12,0) -> 1 | I7: =ROUNDUP(I6*1/12,0) -> 1 | J7: =ROUNDUP(J6*1/12,0) -> 1 | ... BJ7: =ROUNDUP(BJ6*1/12,0) -> 5
A9: Customers
A10: New customers — organic / referral | C10: =Inputs!$B$12*(1+Inputs!$B$13)^(C$7-1)*1 -> 8 | D10: =Inputs!$B$12*(1+Inputs!$B$13)^(D$7-1)*1 -> 8 | E10: =Inputs!$B$12*(1+Inputs!$B$13)^(E$7-1)*1 -> 8 | F10: =Inputs!$B$12*(1+Inputs!$B$13)^(F$7-1)*1 -> 8 | G10: =Inputs!$B$12*(1+Inputs!$B$13)^(G$7-1)*1 -> 8 | H10: =Inputs!$B$12*(1+Inputs!$B$13)^(H$7-1)*1 -> 8 | I10: =Inputs!$B$12*(1+Inputs!$B$13)^(I$7-1)*1 -> 8 | J10: =Inputs!$B$12*(1+Inputs!$B$13)^(J$7-1)*1 -> 8 | ... BJ10: =Inputs!$B$12*(1+Inputs!$B$13)^(BJ$7-1)*1 -> 11.7128
A11: New customers — paid marketing | C11: =-C32/MAX(1,Inputs!$B$16) -> 13.333333 | D11: =-D32/MAX(1,Inputs!$B$16) -> 13.333333 | E11: =-E32/MAX(1,Inputs!$B$16) -> 13.333333 | F11: =-F32/MAX(1,Inputs!$B$16) -> 13.333333 | G11: =-G32/MAX(1,Inputs!$B$16) -> 13.333333 | H11: =-H32/MAX(1,Inputs!$B$16) -> 13.333333 | I11: =-I32/MAX(1,Inputs!$B$16) -> 13.333333 | J11: =-J32/MAX(1,Inputs!$B$16) -> 13.333333 | ... BJ11: =-BJ32/MAX(1,Inputs!$B$16) -> 27.648
A12: New customers — total | C12: =C10+C11 -> 21.333333 | D12: =D10+D11 -> 21.333333 | E12: =E10+E11 -> 21.333333 | F12: =F10+F11 -> 21.333333 | G12: =G10+G11 -> 21.333333 | H12: =H10+H11 -> 21.333333 | I12: =I10+I11 -> 21.333333 | J12: =J10+J11 -> 21.333333 | ... BJ12: =BJ10+BJ11 -> 39.3608
A13: Customers — opening | C13: =Inputs!$B$7 -> 30 | D13: =C15 -> 49.983333 | E13: =D15 -> 69.067417 | F13: =E15 -> 87.292716 | G13: =F15 -> 104.69788 | H13: =G15 -> 121.31981 | I13: =H15 -> 137.19375 | J13: =I15 -> 152.35336 | K13: =J15 -> 166.83079 | ... BJ13: =BI15 -> 705.36775
A14: Customers lost (churn) | C14: =-C13*Inputs!$B$10 -> -1.35 | D14: =-D13*Inputs!$B$10 -> -2.24925 | E14: =-E13*Inputs!$B$10 -> -3.1080338 | F14: =-F13*Inputs!$B$10 -> -3.9281722 | G14: =-G13*Inputs!$B$10 -> -4.7114045 | H14: =-H13*Inputs!$B$10 -> -5.4593913 | I14: =-I13*Inputs!$B$10 -> -6.1737187 | J14: =-J13*Inputs!$B$10 -> -6.8559013 | ... BJ14: =-BJ13*Inputs!$B$10 -> -31.741549
A15: Customers — closing | C15: =C13+C12+C14 -> 49.983333 | D15: =D13+D12+D14 -> 69.067417 | E15: =E13+E12+E14 -> 87.292716 | F15: =F13+F12+F14 -> 104.69788 | G15: =G13+G12+G14 -> 121.31981 | H15: =H13+H12+H14 -> 137.19375 | I15: =I13+I12+I14 -> 152.35336 | J15: =J13+J12+J14 -> 166.83079 | ... BJ15: =BJ13+BJ12+BJ14 -> 712.987
A16: MRR per new customer | C16: =Inputs!$B$8*(1+Inputs!$B$9)^(C$7-1) -> 79 | D16: =Inputs!$B$8*(1+Inputs!$B$9)^(D$7-1) -> 79 | E16: =Inputs!$B$8*(1+Inputs!$B$9)^(E$7-1) -> 79 | F16: =Inputs!$B$8*(1+Inputs!$B$9)^(F$7-1) -> 79 | G16: =Inputs!$B$8*(1+Inputs!$B$9)^(G$7-1) -> 79 | H16: =Inputs!$B$8*(1+Inputs!$B$9)^(H$7-1) -> 79 | I16: =Inputs!$B$8*(1+Inputs!$B$9)^(I$7-1) -> 79 | J16: =Inputs!$B$8*(1+Inputs!$B$9)^(J$7-1) -> 79 | ... BJ16: =Inputs!$B$8*(1+Inputs!$B$9)^(BJ$7-1) -> 79
A18: MRR waterfall
A19: Opening MRR | C19: =Inputs!$B$7*Inputs!$B$8 -> 2370 | D19: =C23 -> 3948.6833 | E19: =D23 -> 5456.3259 | F19: =E23 -> 6896.1246 | G19: =F23 -> 8271.1323 | H19: =G23 -> 9584.2647 | I19: =H23 -> 10838.306 | J19: =I23 -> 12035.916 | K19: =J23 -> 13179.633 | ... BJ19: =BI23 -> 55724.052
A20: New MRR | C20: =C12*C16 -> 1685.3333 | D20: =D12*D16 -> 1685.3333 | E20: =E12*E16 -> 1685.3333 | F20: =F12*F16 -> 1685.3333 | G20: =G12*G16 -> 1685.3333 | H20: =H12*H16 -> 1685.3333 | I20: =I12*I16 -> 1685.3333 | J20: =J12*J16 -> 1685.3333 | ... BJ20: =BJ12*BJ16 -> 3109.5032
A21: Expansion MRR | C21: =C19*Inputs!$B$11 -> 0 | D21: =D19*Inputs!$B$11 -> 0 | E21: =E19*Inputs!$B$11 -> 0 | F21: =F19*Inputs!$B$11 -> 0 | G21: =G19*Inputs!$B$11 -> 0 | H21: =H19*Inputs!$B$11 -> 0 | I21: =I19*Inputs!$B$11 -> 0 | J21: =J19*Inputs!$B$11 -> 0 | ... BJ21: =BJ19*Inputs!$B$11 -> 0
A22: Churned MRR | C22: =-C19*Inputs!$B$10 -> -106.65 | D22: =-D19*Inputs!$B$10 -> -177.69075 | E22: =-E19*Inputs!$B$10 -> -245.53467 | F22: =-F19*Inputs!$B$10 -> -310.32561 | G22: =-G19*Inputs!$B$10 -> -372.20095 | H22: =-H19*Inputs!$B$10 -> -431.29191 | I22: =-I19*Inputs!$B$10 -> -487.72378 | J22: =-J19*Inputs!$B$10 -> -541.61621 | ... BJ22: =-BJ19*Inputs!$B$10 -> -2507.5824
A23: Closing MRR | C23: =C19+C20+C21+C22 -> 3948.6833 | D23: =D19+D20+D21+D22 -> 5456.3259 | E23: =E19+E20+E21+E22 -> 6896.1246 | F23: =F19+F20+F21+F22 -> 8271.1323 | G23: =G19+G20+G21+G22 -> 9584.2647 | H23: =H19+H20+H21+H22 -> 10838.306 | I23: =I19+I20+I21+I22 -> 12035.916 | J23: =J19+J20+J21+J22 -> 13179.633 | ... BJ23: =BJ19+BJ20+BJ21+BJ22 -> 56325.973
A25: Revenue & cost of revenue
A26: Revenue (average MRR × months) | C26: =(C19+C23)/2*1 -> 3159.3417 | D26: =(D19+D23)/2*1 -> 4702.5046 | E26: =(E19+E23)/2*1 -> 6176.2253 | F26: =(F19+F23)/2*1 -> 7583.6284 | G26: =(G19+G23)/2*1 -> 8927.6985 | H26: =(H19+H23)/2*1 -> 10211.285 | I26: =(I19+I23)/2*1 -> 11437.111 | J26: =(J19+J23)/2*1 -> 12607.774 | ... BJ26: =(BJ19+BJ23)/2*1 -> 56025.013
A27: Hosting, payment fees & support | C27: =-(C26*Inputs!$B$18+(C13+C15)/2*Inputs!$B$19*1) -> -499.096 | D27: =-(D26*Inputs!$B$18+(D13+D15)/2*Inputs!$B$19*1) -> -742.87668 | E27: =-(E26*Inputs!$B$18+(E13+E15)/2*Inputs!$B$19*1) -> -975.68723 | F27: =-(F26*Inputs!$B$18+(F13+F15)/2*Inputs!$B$19*1) -> -1198.0213 | G27: =-(G26*Inputs!$B$18+(G13+G15)/2*Inputs!$B$19*1) -> -1410.3503 | H27: =-(H26*Inputs!$B$18+(H13+H15)/2*Inputs!$B$19*1) -> -1613.1246 | I27: =-(I26*Inputs!$B$18+(I13+I15)/2*Inputs!$B$19*1) -> -1806.774 | J27: =-(J26*Inputs!$B$18+(J13+J15)/2*Inputs!$B$19*1) -> -1991.7091 | ... BJ27: =-(BJ26*Inputs!$B$18+(BJ13+BJ15)/2*Inputs!$B$19*1) -> -8850.5337
A28: Gross profit | C28: =C26+C27 -> 2660.2457 | D28: =D26+D27 -> 3959.6279 | E28: =E26+E27 -> 5200.538 | F28: =F26+F27 -> 6385.6071 | G28: =G26+G27 -> 7517.3482 | H28: =H26+H27 -> 8598.1608 | I28: =I26+I27 -> 9630.3369 | J28: =J26+J27 -> 10616.065 | ... BJ28: =BJ26+BJ27 -> 47174.479
A30: Operating expenses
A31: Payroll | C31: =C114 -> -61750 | D31: =D114 -> -61750 | E31: =E114 -> -61750 | F31: =F114 -> -61750 | G31: =G114 -> -61750 | H31: =H114 -> -61750 | I31: =I114 -> -61750 | J31: =J114 -> -61750 | ... BJ31: =BJ114 -> -365708.75
A32: Paid marketing | C32: =-Inputs!$B$14*(1+Inputs!$B$15)^(C$7-1)*1 -> -8000 | D32: =-Inputs!$B$14*(1+Inputs!$B$15)^(D$7-1)*1 -> -8000 | E32: =-Inputs!$B$14*(1+Inputs!$B$15)^(E$7-1)*1 -> -8000 | F32: =-Inputs!$B$14*(1+Inputs!$B$15)^(F$7-1)*1 -> -8000 | G32: =-Inputs!$B$14*(1+Inputs!$B$15)^(G$7-1)*1 -> -8000 | H32: =-Inputs!$B$14*(1+Inputs!$B$15)^(H$7-1)*1 -> -8000 | I32: =-Inputs!$B$14*(1+Inputs!$B$15)^(I$7-1)*1 -> -8000 | J32: =-Inputs!$B$14*(1+Inputs!$B$15)^(J$7-1)*1 -> -8000 | ... BJ32: =-Inputs!$B$14*(1+Inputs!$B$15)^(BJ$7-1)*1 -> -16588.8
A33: Software & tools | C33: =-C107*Inputs!$B$20*1 -> -900 | D33: =-D107*Inputs!$B$20*1 -> -900 | E33: =-E107*Inputs!$B$20*1 -> -900 | F33: =-F107*Inputs!$B$20*1 -> -900 | G33: =-G107*Inputs!$B$20*1 -> -900 | H33: =-H107*Inputs!$B$20*1 -> -900 | I33: =-I107*Inputs!$B$20*1 -> -900 | J33: =-J107*Inputs!$B$20*1 -> -900 | ... BJ33: =-BJ107*Inputs!$B$20*1 -> -4556.25
A34: Office & rent | C34: =-Inputs!$B$21*1 -> -1500 | D34: =-Inputs!$B$21*1 -> -1500 | E34: =-Inputs!$B$21*1 -> -1500 | F34: =-Inputs!$B$21*1 -> -1500 | G34: =-Inputs!$B$21*1 -> -1500 | H34: =-Inputs!$B$21*1 -> -1500 | I34: =-Inputs!$B$21*1 -> -1500 | J34: =-Inputs!$B$21*1 -> -1500 | ... BJ34: =-Inputs!$B$21*1 -> -1500
A35: Other G&A | C35: =-Inputs!$B$22*1 -> -3000 | D35: =-Inputs!$B$22*1 -> -3000 | E35: =-Inputs!$B$22*1 -> -3000 | F35: =-Inputs!$B$22*1 -> -3000 | G35: =-Inputs!$B$22*1 -> -3000 | H35: =-Inputs!$B$22*1 -> -3000 | I35: =-Inputs!$B$22*1 -> -3000 | J35: =-Inputs!$B$22*1 -> -3000 | ... BJ35: =-Inputs!$B$22*1 -> -3000
A36: Total operating expenses | C36: =C31+C32+C33+C34+C35 -> -75150 | D36: =D31+D32+D33+D34+D35 -> -75150 | E36: =E31+E32+E33+E34+E35 -> -75150 | F36: =F31+F32+F33+F34+F35 -> -75150 | G36: =G31+G32+G33+G34+G35 -> -75150 | H36: =H31+H32+H33+H34+H35 -> -75150 | I36: =I31+I32+I33+I34+I35 -> -75150 | J36: =J31+J32+J33+J34+J35 -> -75150 | ... BJ36: =BJ31+BJ32+BJ33+BJ34+BJ35 -> -391353.8
A37: EBITDA | C37: =C28+C36 -> -72489.754 | D37: =D28+D36 -> -71190.372 | E37: =E28+E36 -> -69949.462 | F37: =F28+F36 -> -68764.393 | G37: =G28+G36 -> -67632.652 | H37: =H28+H36 -> -66551.839 | I37: =I28+I36 -> -65519.663 | J37: =J28+J36 -> -64533.935 | ... BJ37: =BJ28+BJ36 -> -344179.32
A39: Profit after depreciation, interest, tax
A40: EBIT | C40: =C37+C51 -> -73045.31 | D40: =D37+D51 -> -71745.928 | E40: =E37+E51 -> -70505.018 | F40: =F37+F51 -> -69319.948 | G40: =G37+G51 -> -68188.207 | H40: =H37+H51 -> -67107.395 | I40: =I37+I51 -> -66075.219 | J40: =J37+J51 -> -65089.49 | ... BJ40: =BJ37+BJ51 -> -344179.32
A41: Interest on loan (average balance after drawdown) | C41: =-(C56+C57+C59)/2*Inputs!$B$48/12 -> 0 | D41: =-(D56+D57+D59)/2*Inputs!$B$48/12 -> 0 | E41: =-(E56+E57+E59)/2*Inputs!$B$48/12 -> 0 | F41: =-(F56+F57+F59)/2*Inputs!$B$48/12 -> 0 | G41: =-(G56+G57+G59)/2*Inputs!$B$48/12 -> 0 | H41: =-(H56+H57+H59)/2*Inputs!$B$48/12 -> 0 | I41: =-(I56+I57+I59)/2*Inputs!$B$48/12 -> 0 | J41: =-(J56+J57+J59)/2*Inputs!$B$48/12 -> 0 | ... BJ41: =-(BJ56+BJ57+BJ59)/2*Inputs!$B$48/12 -> 0
A42: Pre-tax income | C42: =C40+C41 -> -73045.31 | D42: =D40+D41 -> -71745.928 | E42: =E40+E41 -> -70505.018 | F42: =F40+F41 -> -69319.948 | G42: =G40+G41 -> -68188.207 | H42: =H40+H41 -> -67107.395 | I42: =I40+I41 -> -66075.219 | J42: =J40+J41 -> -65089.49 | ... BJ42: =BJ40+BJ41 -> -344179.32
A43: Helper: cumulative pre-tax income | C43: =C42 -> -73045.31 | D43: =C43+D42 -> -144791.24 | E43: =D43+E42 -> -215296.26 | F43: =E43+F42 -> -284616.2 | G43: =F43+G42 -> -352804.41 | H43: =G43+H42 -> -419911.81 | I43: =H43+I42 -> -485987.02 | J43: =I43+J42 -> -551076.51 | K43: =J43+K42 -> -615224.63 | ... BJ43: =BI43+BJ42 -> -10409191
A44: Helper: cumulative taxable income (losses carried forward) | C44: =MAX(0,C43) -> 0 | D44: =MAX(C44,D43) -> 0 | E44: =MAX(D44,E43) -> 0 | F44: =MAX(E44,F43) -> 0 | G44: =MAX(F44,G43) -> 0 | H44: =MAX(G44,H43) -> 0 | I44: =MAX(H44,I43) -> 0 | J44: =MAX(I44,J43) -> 0 | K44: =MAX(J44,K43) -> 0 | ... BJ44: =MAX(BI44,BJ43) -> 0
A45: Income tax | C45: =-C44*Inputs!$B$58 -> 0 | D45: =-(D44-C44)*Inputs!$B$58 -> 0 | E45: =-(E44-D44)*Inputs!$B$58 -> 0 | F45: =-(F44-E44)*Inputs!$B$58 -> 0 | G45: =-(G44-F44)*Inputs!$B$58 -> 0 | H45: =-(H44-G44)*Inputs!$B$58 -> 0 | I45: =-(I44-H44)*Inputs!$B$58 -> 0 | J45: =-(J44-I44)*Inputs!$B$58 -> 0 | K45: =-(K44-J44)*Inputs!$B$58 -> 0 | ... BJ45: =-(BJ44-BI44)*Inputs!$B$58 -> 0
A46: Net income | C46: =C42+C45 -> -73045.31 | D46: =D42+D45 -> -71745.928 | E46: =E42+E45 -> -70505.018 | F46: =F42+F45 -> -69319.948 | G46: =G42+G45 -> -68188.207 | H46: =H42+H45 -> -67107.395 | I46: =I42+I45 -> -66075.219 | J46: =J42+J45 -> -65089.49 | ... BJ46: =BJ42+BJ45 -> -344179.32
A48: Fixed assets & capital spending
A49: Capital spending | C49: =IF(C$6=1,Inputs!$B$23,0) -> 20000 | D49: =IF(D$6=1,Inputs!$B$23,0) -> 0 | E49: =IF(E$6=1,Inputs!$B$23,0) -> 0 | F49: =IF(F$6=1,Inputs!$B$23,0) -> 0 | G49: =IF(G$6=1,Inputs!$B$23,0) -> 0 | H49: =IF(H$6=1,Inputs!$B$23,0) -> 0 | I49: =IF(I$6=1,Inputs!$B$23,0) -> 0 | J49: =IF(J$6=1,Inputs!$B$23,0) -> 0 | ... BJ49: =IF(BJ$6=1,Inputs!$B$23,0) -> 0
A50: Fixed assets at cost | C50: =C49 -> 20000 | D50: =C50+D49 -> 20000 | E50: =D50+E49 -> 20000 | F50: =E50+F49 -> 20000 | G50: =F50+G49 -> 20000 | H50: =G50+H49 -> 20000 | I50: =H50+I49 -> 20000 | J50: =I50+J49 -> 20000 | K50: =J50+K49 -> 20000 | ... BJ50: =BI50+BJ49 -> 20000
A51: Depreciation | C51: =-MIN(C50/MAX(1,Inputs!$B$57*12),C49) -> -555.55556 | D51: =-MIN(D50/MAX(1,Inputs!$B$57*12),C53+D49) -> -555.55556 | E51: =-MIN(E50/MAX(1,Inputs!$B$57*12),D53+E49) -> -555.55556 | F51: =-MIN(F50/MAX(1,Inputs!$B$57*12),E53+F49) -> -555.55556 | G51: =-MIN(G50/MAX(1,Inputs!$B$57*12),F53+G49) -> -555.55556 | H51: =-MIN(H50/MAX(1,Inputs!$B$57*12),G53+H49) -> -555.55556 | I51: =-MIN(I50/MAX(1,Inputs!$B$57*12),H53+I49) -> -555.55556 | J51: =-MIN(J50/MAX(1,Inputs!$B$57*12),I53+J49) -> -555.55556 | K51: =-MIN(K50/MAX(1,Inputs!$B$57*12),J53+K49) -> -555.55556 | ... BJ51: =-MIN(BJ50/MAX(1,Inputs!$B$57*12),BI53+BJ49) -> 0
A52: Accumulated depreciation | C52: =C51 -> -555.55556 | D52: =C52+D51 -> -1111.1111 | E52: =D52+E51 -> -1666.6667 | F52: =E52+F51 -> -2222.2222 | G52: =F52+G51 -> -2777.7778 | H52: =G52+H51 -> -3333.3333 | I52: =H52+I51 -> -3888.8889 | J52: =I52+J51 -> -4444.4444 | K52: =J52+K51 -> -5000 | ... BJ52: =BI52+BJ51 -> -20000
A53: Net fixed assets | C53: =C50+C52 -> 19444.444 | D53: =D50+D52 -> 18888.889 | E53: =E50+E52 -> 18333.333 | F53: =F50+F52 -> 17777.778 | G53: =G50+G52 -> 17222.222 | H53: =H50+H52 -> 16666.667 | I53: =I50+I52 -> 16111.111 | J53: =J50+J52 -> 15555.556 | ... BJ53: =BJ50+BJ52 -> 0
A55: Debt
A56: Loan — opening balance | C56: =0 -> 0 | D56: =C59 -> 0 | E56: =D59 -> 0 | F56: =E59 -> 0 | G56: =F59 -> 0 | H56: =G59 -> 0 | I56: =H59 -> 0 | J56: =I59 -> 0 | K56: =J59 -> 0 | ... BJ56: =BI59 -> 0
A57: Loan drawdown | C57: =IF(C$6=1,Inputs!$B$47,0) -> 0 | D57: =IF(D$6=1,Inputs!$B$47,0) -> 0 | E57: =IF(E$6=1,Inputs!$B$47,0) -> 0 | F57: =IF(F$6=1,Inputs!$B$47,0) -> 0 | G57: =IF(G$6=1,Inputs!$B$47,0) -> 0 | H57: =IF(H$6=1,Inputs!$B$47,0) -> 0 | I57: =IF(I$6=1,Inputs!$B$47,0) -> 0 | J57: =IF(J$6=1,Inputs!$B$47,0) -> 0 | ... BJ57: =IF(BJ$6=1,Inputs!$B$47,0) -> 0
A58: Loan repayment | C58: =-MIN(C56,Inputs!$B$47/MAX(1,Inputs!$B$49*12)) -> 0 | D58: =-MIN(D56,Inputs!$B$47/MAX(1,Inputs!$B$49*12)) -> 0 | E58: =-MIN(E56,Inputs!$B$47/MAX(1,Inputs!$B$49*12)) -> 0 | F58: =-MIN(F56,Inputs!$B$47/MAX(1,Inputs!$B$49*12)) -> 0 | G58: =-MIN(G56,Inputs!$B$47/MAX(1,Inputs!$B$49*12)) -> 0 | H58: =-MIN(H56,Inputs!$B$47/MAX(1,Inputs!$B$49*12)) -> 0 | I58: =-MIN(I56,Inputs!$B$47/MAX(1,Inputs!$B$49*12)) -> 0 | J58: =-MIN(J56,Inputs!$B$47/MAX(1,Inputs!$B$49*12)) -> 0 | ... BJ58: =-MIN(BJ56,Inputs!$B$47/MAX(1,Inputs!$B$49*12)) -> 0
A59: Loan — closing balance | C59: =C56+C57+C58 -> 0 | D59: =D56+D57+D58 -> 0 | E59: =E56+E57+E58 -> 0 | F59: =F56+F57+F58 -> 0 | G59: =G56+G57+G58 -> 0 | H59: =H56+H57+H58 -> 0 | I59: =I56+I57+I58 -> 0 | J59: =J56+J57+J58 -> 0 | ... BJ59: =BJ56+BJ57+BJ58 -> 0
A61: Working capital
A62: Accounts receivable | C62: =C26*Inputs!$B$52/30 -> 526.55694 | D62: =D26*Inputs!$B$52/30 -> 783.75077 | E62: =E26*Inputs!$B$52/30 -> 1029.3709 | F62: =F26*Inputs!$B$52/30 -> 1263.9381 | G62: =G26*Inputs!$B$52/30 -> 1487.9498 | H62: =H26*Inputs!$B$52/30 -> 1701.8809 | I62: =I26*Inputs!$B$52/30 -> 1906.1851 | J62: =J26*Inputs!$B$52/30 -> 2101.2957 | ... BJ62: =BJ26*Inputs!$B$52/30 -> 9337.5021
A63: Inventory | C63: =-C27*Inputs!$B$53/30 -> 0 | D63: =-D27*Inputs!$B$53/30 -> 0 | E63: =-E27*Inputs!$B$53/30 -> 0 | F63: =-F27*Inputs!$B$53/30 -> 0 | G63: =-G27*Inputs!$B$53/30 -> 0 | H63: =-H27*Inputs!$B$53/30 -> 0 | I63: =-I27*Inputs!$B$53/30 -> 0 | J63: =-J27*Inputs!$B$53/30 -> 0 | ... BJ63: =-BJ27*Inputs!$B$53/30 -> 0
A64: Accounts payable | C64: =-C27*Inputs!$B$54/30 -> 499.096 | D64: =-D27*Inputs!$B$54/30 -> 742.87668 | E64: =-E27*Inputs!$B$54/30 -> 975.68723 | F64: =-F27*Inputs!$B$54/30 -> 1198.0213 | G64: =-G27*Inputs!$B$54/30 -> 1410.3503 | H64: =-H27*Inputs!$B$54/30 -> 1613.1246 | I64: =-I27*Inputs!$B$54/30 -> 1806.774 | J64: =-J27*Inputs!$B$54/30 -> 1991.7091 | ... BJ64: =-BJ27*Inputs!$B$54/30 -> 8850.5337
A65: (Increase) / decrease in receivables | C65: =-C62 -> -526.55694 | D65: =C62-D62 -> -257.19383 | E65: =D62-E62 -> -245.6201 | F65: =E62-F62 -> -234.5672 | G65: =F62-G62 -> -224.01168 | H65: =G62-H62 -> -213.93115 | I65: =H62-I62 -> -204.30425 | J65: =I62-J62 -> -195.11056 | K65: =J62-K62 -> -186.33058 | ... BJ65: =BI62-BJ62 -> -102.6837
A66: (Increase) / decrease in inventory | C66: =-C63 -> 0 | D66: =C63-D63 -> 0 | E66: =D63-E63 -> 0 | F66: =E63-F63 -> 0 | G66: =F63-G63 -> 0 | H66: =G63-H63 -> 0 | I66: =H63-I63 -> 0 | J66: =I63-J63 -> 0 | K66: =J63-K63 -> 0 | ... BJ66: =BI63-BJ63 -> 0
A67: Increase / (decrease) in payables | C67: =C64 -> 499.096 | D67: =D64-C64 -> 243.78068 | E67: =E64-D64 -> 232.81055 | F67: =F64-E64 -> 222.33407 | G67: =G64-F64 -> 212.32904 | H67: =H64-G64 -> 202.77423 | I67: =I64-H64 -> 193.64939 | J67: =J64-I64 -> 184.93517 | K67: =K64-J64 -> 176.61309 | ... BJ67: =BJ64-BI64 -> 97.328553
A68: Deferred revenue (annual plans, ~6 months unearned) | C68: =C23*Inputs!$B$17*6 -> 4738.42 | D68: =D23*Inputs!$B$17*6 -> 6547.5911 | E68: =E23*Inputs!$B$17*6 -> 8275.3495 | F68: =F23*Inputs!$B$17*6 -> 9925.3588 | G68: =G23*Inputs!$B$17*6 -> 11501.118 | H68: =H23*Inputs!$B$17*6 -> 13005.967 | I68: =I23*Inputs!$B$17*6 -> 14443.099 | J68: =J23*Inputs!$B$17*6 -> 15815.559 | ... BJ68: =BJ23*Inputs!$B$17*6 -> 67591.168
A69: Increase / (decrease) in deferred revenue (annual plans, ~6 months unearned) | C69: =C68 -> 4738.42 | D69: =D68-C68 -> 1809.1711 | E69: =E68-D68 -> 1727.7584 | F69: =F68-E68 -> 1650.0093 | G69: =G68-F68 -> 1575.7589 | H69: =H68-G68 -> 1504.8497 | I69: =I68-H68 -> 1437.1315 | J69: =J68-I68 -> 1372.4606 | K69: =K68-J68 -> 1310.6998 | ... BJ69: =BJ68-BI68 -> 722.30501
A71: Cash flow
A72: Operating cash flow | C72: =C46-C51+C65+C66+C67+C69 -> -67778.795 | D72: =D46-D51+D65+D66+D67+D69 -> -69394.614 | E72: =E46-E51+E65+E66+E67+E69 -> -68234.513 | F72: =F46-F51+F65+F66+F67+F69 -> -67126.617 | G72: =G46-G51+G65+G66+G67+G69 -> -66068.576 | H72: =H46-H51+H65+H66+H67+H69 -> -65058.146 | I72: =I46-I51+I65+I66+I67+I69 -> -64093.186 | J72: =J46-J51+J65+J66+J67+J69 -> -63171.65 | ... BJ72: =BJ46-BJ51+BJ65+BJ66+BJ67+BJ69 -> -343462.37
A73: Investing cash flow (capex) | C73: =-C49 -> -20000 | D73: =-D49 -> 0 | E73: =-E49 -> 0 | F73: =-F49 -> 0 | G73: =-G49 -> 0 | H73: =-H49 -> 0 | I73: =-I49 -> 0 | J73: =-J49 -> 0 | ... BJ73: =-BJ49 -> 0
A74: Equity raised | C74: =IF(C$6=1,Inputs!$B$46,0) -> 3000000 | D74: =IF(D$6=1,Inputs!$B$46,0) -> 0 | E74: =IF(E$6=1,Inputs!$B$46,0) -> 0 | F74: =IF(F$6=1,Inputs!$B$46,0) -> 0 | G74: =IF(G$6=1,Inputs!$B$46,0) -> 0 | H74: =IF(H$6=1,Inputs!$B$46,0) -> 0 | I74: =IF(I$6=1,Inputs!$B$46,0) -> 0 | J74: =IF(J$6=1,Inputs!$B$46,0) -> 0 | ... BJ74: =IF(BJ$6=1,Inputs!$B$46,0) -> 0
A75: Financing cash flow | C75: =C74+C57+C58 -> 3000000 | D75: =D74+D57+D58 -> 0 | E75: =E74+E57+E58 -> 0 | F75: =F74+F57+F58 -> 0 | G75: =G74+G57+G58 -> 0 | H75: =H74+H57+H58 -> 0 | I75: =I74+I57+I58 -> 0 | J75: =J74+J57+J58 -> 0 | ... BJ75: =BJ74+BJ57+BJ58 -> 0
A76: Net cash flow | C76: =C72+C73+C75 -> 2912221.2 | D76: =D72+D73+D75 -> -69394.614 | E76: =E72+E73+E75 -> -68234.513 | F76: =F72+F73+F75 -> -67126.617 | G76: =G72+G73+G75 -> -66068.576 | H76: =H72+H73+H75 -> -65058.146 | I76: =I72+I73+I75 -> -64093.186 | J76: =J72+J73+J75 -> -63171.65 | ... BJ76: =BJ72+BJ73+BJ75 -> -343462.37
A77: Opening cash | C77: =0 -> 0 | D77: =C78 -> 2912221.2 | E77: =D78 -> 2842826.6 | F77: =E78 -> 2774592.1 | G77: =F78 -> 2707465.5 | H77: =G78 -> 2641396.9 | I77: =H78 -> 2576338.7 | J77: =I78 -> 2512245.6 | K77: =J78 -> 2449073.9 | ... BJ77: =BI78 -> -6998624.5
A78: Closing cash | C78: =C77+C76 -> 2912221.2 | D78: =D77+D76 -> 2842826.6 | E78: =E77+E76 -> 2774592.1 | F78: =F77+F76 -> 2707465.5 | G78: =G77+G76 -> 2641396.9 | H78: =H77+H76 -> 2576338.7 | I78: =I77+I76 -> 2512245.6 | J78: =J77+J76 -> 2449073.9 | ... BJ78: =BJ77+BJ76 -> -7342086.9
A79: Helper: EBITDA positive (1/0) | C79: =IF(C37>0,1,0) -> 0 | D79: =IF(D37>0,1,0) -> 0 | E79: =IF(E37>0,1,0) -> 0 | F79: =IF(F37>0,1,0) -> 0 | G79: =IF(G37>0,1,0) -> 0 | H79: =IF(H37>0,1,0) -> 0 | I79: =IF(I37>0,1,0) -> 0 | J79: =IF(J37>0,1,0) -> 0 | ... BJ79: =IF(BJ37>0,1,0) -> 0
A81: SaaS metric helpers
A82: Net burn per month (operating + investing; negative = cash generative) | C82: =-(C72+C73)/1 -> 87778.795 | D82: =-(D72+D73)/1 -> 69394.614 | E82: =-(E72+E73)/1 -> 68234.513 | F82: =-(F72+F73)/1 -> 67126.617 | G82: =-(G72+G73)/1 -> 66068.576 | H82: =-(H72+H73)/1 -> 65058.146 | I82: =-(I72+I73)/1 -> 64093.186 | J82: =-(J72+J73)/1 -> 63171.65 | ... BJ82: =-(BJ72+BJ73)/1 -> 343462.37
A83: Customer churn per month | C83: =Inputs!$B$10 -> 0.045 | D83: =Inputs!$B$10 -> 0.045 | E83: =Inputs!$B$10 -> 0.045 | F83: =Inputs!$B$10 -> 0.045 | G83: =Inputs!$B$10 -> 0.045 | H83: =Inputs!$B$10 -> 0.045 | I83: =Inputs!$B$10 -> 0.045 | J83: =Inputs!$B$10 -> 0.045 | ... BJ83: =Inputs!$B$10 -> 0.045
A85: Goal modules
A86: Helper: net income positive (1/0) | C86: =IF(C46>0,1,0) -> 0 | D86: =IF(D46>0,1,0) -> 0 | E86: =IF(E46>0,1,0) -> 0 | F86: =IF(F46>0,1,0) -> 0 | G86: =IF(G46>0,1,0) -> 0 | H86: =IF(H46>0,1,0) -> 0 | I86: =IF(I46>0,1,0) -> 0 | J86: =IF(J46>0,1,0) -> 0 | ... BJ86: =IF(BJ46>0,1,0) -> 0
A87: Cash flow before financing (operating + investing) | C87: =C72+C73 -> -87778.795 | D87: =D72+D73 -> -69394.614 | E87: =E72+E73 -> -68234.513 | F87: =F72+F73 -> -67126.617 | G87: =G72+G73 -> -66068.576 | H87: =H72+H73 -> -65058.146 | I87: =I72+I73 -> -64093.186 | J87: =J72+J73 -> -63171.65 | ... BJ87: =BJ72+BJ73 -> -343462.37
A88: Cumulative cash flow before financing | C88: =C87 -> -87778.795 | D88: =C88+D87 -> -157173.41 | E88: =D88+E87 -> -225407.92 | F88: =E88+F87 -> -292534.54 | G88: =F88+G87 -> -358603.11 | H88: =G88+H87 -> -423661.26 | I88: =H88+I87 -> -487754.45 | J88: =I88+J87 -> -550926.1 | K88: =J88+K87 -> -613217.68 | ... BJ88: =BI88+BJ87 -> -10342087
A89: Helper: lowest cumulative cash flow so far | C89: =C88 -> -87778.795 | D89: =MIN(C89,D88) -> -157173.41 | E89: =MIN(D89,E88) -> -225407.92 | F89: =MIN(E89,F88) -> -292534.54 | G89: =MIN(F89,G88) -> -358603.11 | H89: =MIN(G89,H88) -> -423661.26 | I89: =MIN(H89,I88) -> -487754.45 | J89: =MIN(I89,J88) -> -550926.1 | K89: =MIN(J89,K88) -> -613217.68 | ... BJ89: =MIN(BI89,BJ88) -> -10342087
A90: Helper: investment paid back (1/0) | C90: =IF(AND(C88>=0,C89<0),1,0) -> 0 | D90: =IF(AND(D88>=0,D89<0),1,0) -> 0 | E90: =IF(AND(E88>=0,E89<0),1,0) -> 0 | F90: =IF(AND(F88>=0,F89<0),1,0) -> 0 | G90: =IF(AND(G88>=0,G89<0),1,0) -> 0 | H90: =IF(AND(H88>=0,H89<0),1,0) -> 0 | I90: =IF(AND(I88>=0,I89<0),1,0) -> 0 | J90: =IF(AND(J88>=0,J89<0),1,0) -> 0 | ... BJ90: =IF(AND(BJ88>=0,BJ89<0),1,0) -> 0
A91: Unlevered free cash flow (operating + after-tax interest − capex) | C91: =C72-C41*(1-Inputs!$B$58)+C73 -> -87778.795 | D91: =D72-D41*(1-Inputs!$B$58)+D73 -> -69394.614 | E91: =E72-E41*(1-Inputs!$B$58)+E73 -> -68234.513 | F91: =F72-F41*(1-Inputs!$B$58)+F73 -> -67126.617 | G91: =G72-G41*(1-Inputs!$B$58)+G73 -> -66068.576 | H91: =H72-H41*(1-Inputs!$B$58)+H73 -> -65058.146 | I91: =I72-I41*(1-Inputs!$B$58)+I73 -> -64093.186 | J91: =J72-J41*(1-Inputs!$B$58)+J73 -> -63171.65 | ... BJ91: =BJ72-BJ41*(1-Inputs!$B$58)+BJ73 -> -343462.37
A93: Balance sheet
A94: Paid-in capital | C94: =C74 -> 3000000 | D94: =C94+D74 -> 3000000 | E94: =D94+E74 -> 3000000 | F94: =E94+F74 -> 3000000 | G94: =F94+G74 -> 3000000 | H94: =G94+H74 -> 3000000 | I94: =H94+I74 -> 3000000 | J94: =I94+J74 -> 3000000 | K94: =J94+K74 -> 3000000 | ... BJ94: =BI94+BJ74 -> 3000000
A95: Retained earnings | C95: =C46 -> -73045.31 | D95: =C95+D46 -> -144791.24 | E95: =D95+E46 -> -215296.26 | F95: =E95+F46 -> -284616.2 | G95: =F95+G46 -> -352804.41 | H95: =G95+H46 -> -419911.81 | I95: =H95+I46 -> -485987.02 | J95: =I95+J46 -> -551076.51 | K95: =J95+K46 -> -615224.63 | ... BJ95: =BI95+BJ46 -> -10409191
A96: Total assets | C96: =C78+C62+C63+C53 -> 2932192.2 | D96: =D78+D62+D63+D53 -> 2862499.2 | E96: =E78+E62+E63+E53 -> 2793954.8 | F96: =F78+F62+F63+F53 -> 2726507.2 | G96: =G78+G62+G63+G53 -> 2660107.1 | H96: =H78+H62+H63+H53 -> 2594707.3 | I96: =I78+I62+I63+I53 -> 2530262.8 | J96: =J78+J62+J63+J53 -> 2466730.8 | ... BJ96: =BJ78+BJ62+BJ63+BJ53 -> -7332749.4
A97: Total liabilities | C97: =C64+C59+C68 -> 5237.516 | D97: =D64+D59+D68 -> 7290.4678 | E97: =E64+E59+E68 -> 9251.0367 | F97: =F64+F59+F68 -> 11123.38 | G97: =G64+G59+G68 -> 12911.468 | H97: =H64+H59+H68 -> 14619.092 | I97: =I64+I59+I68 -> 16249.873 | J97: =J64+J59+J68 -> 17807.269 | ... BJ97: =BJ64+BJ59+BJ68 -> 76441.702
A98: Total equity | C98: =C94+C95 -> 2926954.7 | D98: =D94+D95 -> 2855208.8 | E98: =E94+E95 -> 2784703.7 | F98: =F94+F95 -> 2715383.8 | G98: =G94+G95 -> 2647195.6 | H98: =H94+H95 -> 2580088.2 | I98: =I94+I95 -> 2514013 | J98: =J94+J95 -> 2448923.5 | ... BJ98: =BJ94+BJ95 -> -7409191.1
A99: Total liabilities & equity | C99: =C97+C98 -> 2932192.2 | D99: =D97+D98 -> 2862499.2 | E99: =E97+E98 -> 2793954.8 | F99: =F97+F98 -> 2726507.2 | G99: =G97+G98 -> 2660107.1 | H99: =H97+H98 -> 2594707.3 | I99: =I97+I98 -> 2530262.8 | J99: =J97+J98 -> 2466730.8 | ... BJ99: =BJ97+BJ98 -> -7332749.4
A100: Check: assets − liabilities − equity | C100: =C96-C99 -> 0 | D100: =D96-D99 -> 0 | E100: =E96-E99 -> 0 | F100: =F96-F99 -> 0 | G100: =G96-G99 -> 0 | H100: =H96-H99 -> 0 | I100: =I96-I99 -> 0 | J100: =J96-J99 -> 0 | ... BJ100: =BJ96-BJ99 -> 0
A102: Headcount (FTE)
A103: Engineering & product — FTE | C103: =Inputs!$B$26*(1+Inputs!$B$28)^(C$7-1)*MAX(0,MIN(1,C$6*1-Inputs!$B$29+1))/1 -> 3 | D103: =Inputs!$B$26*(1+Inputs!$B$28)^(D$7-1)*MAX(0,MIN(1,D$6*1-Inputs!$B$29+1))/1 -> 3 | E103: =Inputs!$B$26*(1+Inputs!$B$28)^(E$7-1)*MAX(0,MIN(1,E$6*1-Inputs!$B$29+1))/1 -> 3 | F103: =Inputs!$B$26*(1+Inputs!$B$28)^(F$7-1)*MAX(0,MIN(1,F$6*1-Inputs!$B$29+1))/1 -> 3 | G103: =Inputs!$B$26*(1+Inputs!$B$28)^(G$7-1)*MAX(0,MIN(1,G$6*1-Inputs!$B$29+1))/1 -> 3 | H103: =Inputs!$B$26*(1+Inputs!$B$28)^(H$7-1)*MAX(0,MIN(1,H$6*1-Inputs!$B$29+1))/1 -> 3 | I103: =Inputs!$B$26*(1+Inputs!$B$28)^(I$7-1)*MAX(0,MIN(1,I$6*1-Inputs!$B$29+1))/1 -> 3 | J103: =Inputs!$B$26*(1+Inputs!$B$28)^(J$7-1)*MAX(0,MIN(1,J$6*1-Inputs!$B$29+1))/1 -> 3 | ... BJ103: =Inputs!$B$26*(1+Inputs!$B$28)^(BJ$7-1)*MAX(0,MIN(1,BJ$6*1-Inputs!$B$29+1))/1 -> 15.1875
A104: Sales & marketing — FTE | C104: =Inputs!$B$30*(1+Inputs!$B$32)^(C$7-1)*MAX(0,MIN(1,C$6*1-Inputs!$B$33+1))/1 -> 1.5 | D104: =Inputs!$B$30*(1+Inputs!$B$32)^(D$7-1)*MAX(0,MIN(1,D$6*1-Inputs!$B$33+1))/1 -> 1.5 | E104: =Inputs!$B$30*(1+Inputs!$B$32)^(E$7-1)*MAX(0,MIN(1,E$6*1-Inputs!$B$33+1))/1 -> 1.5 | F104: =Inputs!$B$30*(1+Inputs!$B$32)^(F$7-1)*MAX(0,MIN(1,F$6*1-Inputs!$B$33+1))/1 -> 1.5 | G104: =Inputs!$B$30*(1+Inputs!$B$32)^(G$7-1)*MAX(0,MIN(1,G$6*1-Inputs!$B$33+1))/1 -> 1.5 | H104: =Inputs!$B$30*(1+Inputs!$B$32)^(H$7-1)*MAX(0,MIN(1,H$6*1-Inputs!$B$33+1))/1 -> 1.5 | I104: =Inputs!$B$30*(1+Inputs!$B$32)^(I$7-1)*MAX(0,MIN(1,I$6*1-Inputs!$B$33+1))/1 -> 1.5 | J104: =Inputs!$B$30*(1+Inputs!$B$32)^(J$7-1)*MAX(0,MIN(1,J$6*1-Inputs!$B$33+1))/1 -> 1.5 | ... BJ104: =Inputs!$B$30*(1+Inputs!$B$32)^(BJ$7-1)*MAX(0,MIN(1,BJ$6*1-Inputs!$B$33+1))/1 -> 7.59375
A105: Customer success — FTE | C105: =Inputs!$B$34*(1+Inputs!$B$36)^(C$7-1)*MAX(0,MIN(1,C$6*1-Inputs!$B$37+1))/1 -> 1 | D105: =Inputs!$B$34*(1+Inputs!$B$36)^(D$7-1)*MAX(0,MIN(1,D$6*1-Inputs!$B$37+1))/1 -> 1 | E105: =Inputs!$B$34*(1+Inputs!$B$36)^(E$7-1)*MAX(0,MIN(1,E$6*1-Inputs!$B$37+1))/1 -> 1 | F105: =Inputs!$B$34*(1+Inputs!$B$36)^(F$7-1)*MAX(0,MIN(1,F$6*1-Inputs!$B$37+1))/1 -> 1 | G105: =Inputs!$B$34*(1+Inputs!$B$36)^(G$7-1)*MAX(0,MIN(1,G$6*1-Inputs!$B$37+1))/1 -> 1 | H105: =Inputs!$B$34*(1+Inputs!$B$36)^(H$7-1)*MAX(0,MIN(1,H$6*1-Inputs!$B$37+1))/1 -> 1 | I105: =Inputs!$B$34*(1+Inputs!$B$36)^(I$7-1)*MAX(0,MIN(1,I$6*1-Inputs!$B$37+1))/1 -> 1 | J105: =Inputs!$B$34*(1+Inputs!$B$36)^(J$7-1)*MAX(0,MIN(1,J$6*1-Inputs!$B$37+1))/1 -> 1 | ... BJ105: =Inputs!$B$34*(1+Inputs!$B$36)^(BJ$7-1)*MAX(0,MIN(1,BJ$6*1-Inputs!$B$37+1))/1 -> 5.0625
A106: G&A (finance, ops) — FTE | C106: =Inputs!$B$38*(1+Inputs!$B$40)^(C$7-1)*MAX(0,MIN(1,C$6*1-Inputs!$B$41+1))/1 -> 0.5 | D106: =Inputs!$B$38*(1+Inputs!$B$40)^(D$7-1)*MAX(0,MIN(1,D$6*1-Inputs!$B$41+1))/1 -> 0.5 | E106: =Inputs!$B$38*(1+Inputs!$B$40)^(E$7-1)*MAX(0,MIN(1,E$6*1-Inputs!$B$41+1))/1 -> 0.5 | F106: =Inputs!$B$38*(1+Inputs!$B$40)^(F$7-1)*MAX(0,MIN(1,F$6*1-Inputs!$B$41+1))/1 -> 0.5 | G106: =Inputs!$B$38*(1+Inputs!$B$40)^(G$7-1)*MAX(0,MIN(1,G$6*1-Inputs!$B$41+1))/1 -> 0.5 | H106: =Inputs!$B$38*(1+Inputs!$B$40)^(H$7-1)*MAX(0,MIN(1,H$6*1-Inputs!$B$41+1))/1 -> 0.5 | I106: =Inputs!$B$38*(1+Inputs!$B$40)^(I$7-1)*MAX(0,MIN(1,I$6*1-Inputs!$B$41+1))/1 -> 0.5 | J106: =Inputs!$B$38*(1+Inputs!$B$40)^(J$7-1)*MAX(0,MIN(1,J$6*1-Inputs!$B$41+1))/1 -> 0.5 | ... BJ106: =Inputs!$B$38*(1+Inputs!$B$40)^(BJ$7-1)*MAX(0,MIN(1,BJ$6*1-Inputs!$B$41+1))/1 -> 2.53125
A107: Total FTE | C107: =C103+C104+C105+C106 -> 6 | D107: =D103+D104+D105+D106 -> 6 | E107: =E103+E104+E105+E106 -> 6 | F107: =F103+F104+F105+F106 -> 6 | G107: =G103+G104+G105+G106 -> 6 | H107: =H103+H104+H105+H106 -> 6 | I107: =I103+I104+I105+I106 -> 6 | J107: =J103+J104+J105+J106 -> 6 | ... BJ107: =BJ103+BJ104+BJ105+BJ106 -> 30.375
A109: Payroll cost (salary + taxes & benefits)
A110: Engineering & product — payroll cost | C110: =-C103*Inputs!$B$27/12*1*(1+Inputs!$B$42)*(1+Inputs!$B$43)^(C$7-1) -> -37500 | D110: =-D103*Inputs!$B$27/12*1*(1+Inputs!$B$42)*(1+Inputs!$B$43)^(D$7-1) -> -37500 | E110: =-E103*Inputs!$B$27/12*1*(1+Inputs!$B$42)*(1+Inputs!$B$43)^(E$7-1) -> -37500 | F110: =-F103*Inputs!$B$27/12*1*(1+Inputs!$B$42)*(1+Inputs!$B$43)^(F$7-1) -> -37500 | G110: =-G103*Inputs!$B$27/12*1*(1+Inputs!$B$42)*(1+Inputs!$B$43)^(G$7-1) -> -37500 | H110: =-H103*Inputs!$B$27/12*1*(1+Inputs!$B$42)*(1+Inputs!$B$43)^(H$7-1) -> -37500 | I110: =-I103*Inputs!$B$27/12*1*(1+Inputs!$B$42)*(1+Inputs!$B$43)^(I$7-1) -> -37500 | J110: =-J103*Inputs!$B$27/12*1*(1+Inputs!$B$42)*(1+Inputs!$B$43)^(J$7-1) -> -37500 | ... BJ110: =-BJ103*Inputs!$B$27/12*1*(1+Inputs!$B$42)*(1+Inputs!$B$43)^(BJ$7-1) -> -222090.34
A111: Sales & marketing — payroll cost | C111: =-C104*Inputs!$B$31/12*1*(1+Inputs!$B$42)*(1+Inputs!$B$43)^(C$7-1) -> -14250 | D111: =-D104*Inputs!$B$31/12*1*(1+Inputs!$B$42)*(1+Inputs!$B$43)^(D$7-1) -> -14250 | E111: =-E104*Inputs!$B$31/12*1*(1+Inputs!$B$42)*(1+Inputs!$B$43)^(E$7-1) -> -14250 | F111: =-F104*Inputs!$B$31/12*1*(1+Inputs!$B$42)*(1+Inputs!$B$43)^(F$7-1) -> -14250 | G111: =-G104*Inputs!$B$31/12*1*(1+Inputs!$B$42)*(1+Inputs!$B$43)^(G$7-1) -> -14250 | H111: =-H104*Inputs!$B$31/12*1*(1+Inputs!$B$42)*(1+Inputs!$B$43)^(H$7-1) -> -14250 | I111: =-I104*Inputs!$B$31/12*1*(1+Inputs!$B$42)*(1+Inputs!$B$43)^(I$7-1) -> -14250 | J111: =-J104*Inputs!$B$31/12*1*(1+Inputs!$B$42)*(1+Inputs!$B$43)^(J$7-1) -> -14250 | ... BJ111: =-BJ104*Inputs!$B$31/12*1*(1+Inputs!$B$42)*(1+Inputs!$B$43)^(BJ$7-1) -> -84394.328
A112: Customer success — payroll cost | C112: =-C105*Inputs!$B$35/12*1*(1+Inputs!$B$42)*(1+Inputs!$B$43)^(C$7-1) -> -6000 | D112: =-D105*Inputs!$B$35/12*1*(1+Inputs!$B$42)*(1+Inputs!$B$43)^(D$7-1) -> -6000 | E112: =-E105*Inputs!$B$35/12*1*(1+Inputs!$B$42)*(1+Inputs!$B$43)^(E$7-1) -> -6000 | F112: =-F105*Inputs!$B$35/12*1*(1+Inputs!$B$42)*(1+Inputs!$B$43)^(F$7-1) -> -6000 | G112: =-G105*Inputs!$B$35/12*1*(1+Inputs!$B$42)*(1+Inputs!$B$43)^(G$7-1) -> -6000 | H112: =-H105*Inputs!$B$35/12*1*(1+Inputs!$B$42)*(1+Inputs!$B$43)^(H$7-1) -> -6000 | I112: =-I105*Inputs!$B$35/12*1*(1+Inputs!$B$42)*(1+Inputs!$B$43)^(I$7-1) -> -6000 | J112: =-J105*Inputs!$B$35/12*1*(1+Inputs!$B$42)*(1+Inputs!$B$43)^(J$7-1) -> -6000 | ... BJ112: =-BJ105*Inputs!$B$35/12*1*(1+Inputs!$B$42)*(1+Inputs!$B$43)^(BJ$7-1) -> -35534.454
A113: G&A (finance, ops) — payroll cost | C113: =-C106*Inputs!$B$39/12*1*(1+Inputs!$B$42)*(1+Inputs!$B$43)^(C$7-1) -> -4000 | D113: =-D106*Inputs!$B$39/12*1*(1+Inputs!$B$42)*(1+Inputs!$B$43)^(D$7-1) -> -4000 | E113: =-E106*Inputs!$B$39/12*1*(1+Inputs!$B$42)*(1+Inputs!$B$43)^(E$7-1) -> -4000 | F113: =-F106*Inputs!$B$39/12*1*(1+Inputs!$B$42)*(1+Inputs!$B$43)^(F$7-1) -> -4000 | G113: =-G106*Inputs!$B$39/12*1*(1+Inputs!$B$42)*(1+Inputs!$B$43)^(G$7-1) -> -4000 | H113: =-H106*Inputs!$B$39/12*1*(1+Inputs!$B$42)*(1+Inputs!$B$43)^(H$7-1) -> -4000 | I113: =-I106*Inputs!$B$39/12*1*(1+Inputs!$B$42)*(1+Inputs!$B$43)^(I$7-1) -> -4000 | J113: =-J106*Inputs!$B$39/12*1*(1+Inputs!$B$42)*(1+Inputs!$B$43)^(J$7-1) -> -4000 | ... BJ113: =-BJ106*Inputs!$B$39/12*1*(1+Inputs!$B$42)*(1+Inputs!$B$43)^(BJ$7-1) -> -23689.636
A114: Total payroll | C114: =C110+C111+C112+C113 -> -61750 | D114: =D110+D111+D112+D113 -> -61750 | E114: =E110+E111+E112+E113 -> -61750 | F114: =F110+F111+F112+F113 -> -61750 | G114: =G110+G111+G112+G113 -> -61750 | H114: =H110+H111+H112+H113 -> -61750 | I114: =I110+I111+I112+I113 -> -61750 | J114: =J110+J111+J112+J113 -> -61750 | ... BJ114: =BJ110+BJ111+BJ112+BJ113 -> -365708.75
A117: Base scenario — reads Inputs column C
...

Sheet Checks
A1: Model checks | E1: =HYPERLINK("#'Cover'!A1","◂ Contents") -> ◂ Contents
A2: Live formulas: they re-run every time an input changes.
A3: Check | B3: Result | C3: What it tests
A4: Annual revenue ties to period detail | B4: =IF(ABS(SUM('P&L'!$B$5:$F$5)-SUM(Monthly!$C$24:$BJ$24))<0.5,"PASS","FAIL") -> PASS | C4: Sum of annual revenue equals the sum of every period
A5: Annual net income ties to period detail | B5: =IF(ABS(SUM('P&L'!$B$22:$F$22)-SUM(Monthly!$C$44:$BJ$44))<0.5,"PASS","FAIL") -> PASS | C5: Sum of annual net income equals the sum of every period
A6: EBITDA reconciliation | B6: =IF(ABS(SUM(Monthly!$C$35:$BJ$35)-SUM(Monthly!$C$26:$BJ$26)-SUM(Monthly!$C$34:$BJ$34))<0.5,"PASS","FAIL") -> PASS | C6: EBITDA = gross profit + operating expenses (costs are negative)
A7: Cash roll-forward | B7: =IF(ABS(INDEX(Monthly!$C$76:$BJ$76,60)-SUM(Monthly!$C$74:$BJ$74))<0.5,"PASS","FAIL") -> PASS | C7: Closing cash = all net cash flows since the start (opening cash is zero)
A8: Scenario selector valid | B8: =IF(AND(ISNUMBER(Dashboard!B4),Dashboard!B4>=1,Dashboard!B4<=3,INT(Dashboard!B4)=Dashboard!B4),"PASS","FAIL") -> PASS | C8: Dashboard!B4 is 1, 2 or 3
A9: Scenario ordering of drivers | B9: =IF(AND(Inputs!$B$7<=Inputs!$C$7,Inputs!$C$7<=Inputs!$D$7,Inputs!$B$8<=Inputs!$C$8,Inputs!$C$8<=Inputs!$D$8,Inputs!$B$9<=Inputs!$C$9,Inputs!$C$9<=Inputs!$D$9,Inputs!$B$10>=Inputs!$C$10,Inputs!$C$10>=Inputs!$D$10,Inputs!$B$11<=Inputs!$C$11,Inputs!$C$11<=Inputs!$D$11,Inputs!$B$12<=Inputs!$C$12,Inputs!$C$12<=Inputs!$D$12,Inputs!$B$13<=Inputs!$C$13,Inputs!$C$13<=Inputs!$D$13,Inputs!$B$16>=Inputs!$C$16,Inputs!$C$16>=Inputs!$D$16,Inputs!$B$18>=Inputs!$C$18,Inputs!$C$18>=Inputs!$D$18,Inputs!$B$19>=Inputs!$C$19,Inputs!$C$19>=Inputs!$D$19,Inputs!$B$26<=Inputs!$C$26,Inputs!$C$26<=Inputs!$D$26,Inputs!$B$28<=Inputs!$C$28,Inputs!$C$28<=Inputs!$D$28,Inputs!$B$30<=Inputs!$C$30,Inputs!$C$30<=Inputs!$D$30,Inputs!$B$32<=Inputs!$C$32,Inputs!$C$32<=Inputs!$D$32,Inputs!$B$34<=Inputs!$C$34,Inputs!$C$34<=Inputs!$D$34,Inputs!$B$36<=Inputs!$C$36,Inputs!$C$36<=Inputs!$D$36,Inputs!$B$38<=Inputs!$C$38,Inputs!$C$38<=Inputs!$D$38,Inputs!$B$40<=Inputs!$C$40,Inputs!$C$40<=Inputs!$D$40,Inputs!$B$64>=Inputs!$C$64,Inputs!$C$64>=Inputs!$D$64,Inputs!$B$65<=Inputs!$C$65,Inputs!$C$65<=Inputs!$D$65,Inputs!$B$66<=Inputs!$C$66,Inputs!$C$66<=Inputs!$D$66),"PASS","FAIL") -> PASS | C9: Low / Base / High ordered the right way for every growth and cost driver
A10: Gross margin within 0–100% | B10: =IF(AND(MIN('P&L'!$B$8:$F$8)>=0,MAX('P&L'!$B$8:$F$8)<=1),"PASS","FAIL") -> PASS | C10: Gross margin never negative or above 100%
A11: Loan balance never negative | B11: =IF(MIN(Monthly!$C$57:$BJ$57)>=-0.5,"PASS","FAIL") -> PASS | C11: Repayments never exceed the loan
A12: Funding table ties to the cash flow | B12: =IF(ABS('Break-even'!B18-('Break-even'!B16-'Break-even'!B10))<0.5,"PASS","FAIL") -> PASS | C12: Lowest cash balance = sources of funds − uses of funds up to that point
A13: Valuation: discounting ties to NPV() | B13: =IF(ABS(Valuation!B23-NPV(Valuation!B6,Valuation!$B$17:$F$17))<0.5,"PASS","FAIL") -> PASS | C13: Sum of discounted free cash flows equals Excel's NPV of the same flows
A14: Valuation: WACC above terminal growth | B14: =IF(Valuation!B6>Valuation!B7,"PASS","FAIL") -> PASS | C14: The perpetual-growth formula needs WACC > g
A15: Valuation: sensitivity centre = enterprise value | B15: =IF(ABS(Valuation!D36-Valuation!B27)<0.5,"PASS","FAIL") -> PASS | C15: The middle of the WACC × growth table reproduces the headline value
A16: Valuation: final-year cash flow positive | B16: =IF(Valuation!$F$17>0,"PASS","WARN") -> WARN | C16: Business warning: a negative final-year cash flow gives a negative terminal value (often a 1-year plan still carrying start-up spending)
A17: Sources & uses balance | B17: =IF(ABS('Sources & Uses'!B21-'Sources & Uses'!B28)<0.5,"PASS","FAIL") -> PASS | C17: Sources of funds = uses of funds (incl. cash at the end) for the Sources & Uses period
A18: No error values | B18: =IF(SUMPRODUCT(--ISERROR(Monthly!$C$4:$BJ$98))+SUMPRODUCT(--ISERROR(Headcount!$C$4:$BJ$19))+SUMPRODUCT(--ISERROR('P&L'!$B$3:$F$23))+SUMPRODUCT(--ISERROR('Cash Flow'!$B$3:$F$19))+SUMPRODUCT(--ISERROR('Balance Sheet'!$B$3:$F$18))+SUMPRODUCT(--ISERROR(KPIs!$B$27:$F$46))+SUMPRODUCT(--ISERROR('Break-even'!$B$26:$F$33))+SUMPRODUCT(--ISERROR(Valuation!$B$14:$F$19))+SUMPRODUCT(--ISERROR('Break-even'!$B$3:$F$35))+SUMPRODUCT(--ISERROR(Valuation!$A$3:$F$40))+SUMPRODUCT(--ISERROR('Sources & Uses'!$B$3:$C$30))+SUMPRODUCT(--ISERROR(Dashboard!$A$6:$W$43))+SUMPRODUCT(--ISERROR(Summary!$A$5:$S$53))+SUMPRODUCT(--ISERROR(KPIs!$A$4:$G$46))+SUMPRODUCT(--ISERROR('Scenario calc'!$C$6:$BJ$114))+SUMPRODUCT(--ISERROR('Scenario calc'!$C$119:$BJ$227))+SUMPRODUCT(--ISERROR('Scenario calc'!$C$232:$BJ$340))+SUMPRODUCT(--ISERROR(Scenarios!$B$5:$F$50))=0,"PASS","FAIL") -> PASS | C18: No error values (divide-by-zero, broken references) on any calculation sheet
A19: Summary ties to statements | B19: =IF(IFERROR(AND(SUMPRODUCT(--(ABS(Summary!$B$7:$F$7-'P&L'!$B$5:$F$5)>0.5))=0,SUMPRODUCT(--(ABS(Summary!$B$19:$F$19-'P&L'!$B$22:$F$22)>0.5))=0,SUMPRODUCT(--(ABS(Summary!$B$31:$F$31-'Cash Flow'!$B$19:$F$19)>0.5))=0,SUMPRODUCT(--(ABS(Summary!$B$41:$F$41-'Balance Sheet'!$B$5:$F$5)>0.5))=0,ABS(SUM(Summary!$H$7:$S$7)-INDEX(Summary!$B$7:$F$7,Summary!$R$2))<0.5,ABS(SUM(Summary!$H$19:$S$19)-INDEX(Summary!$B$19:$F$19,Summary!$R$2))<0.5,ABS(Summary!$S$31-INDEX(Summary!$B$31:$F$31,Summary!$R$2))<0.5),FALSE()),"PASS","FAIL") -> PASS | C19: Summary revenue, net income and closing cash equal the statements every year; the detailed year adds up to its annual figure
A20: DuPont ties to return on equity | B20: =IF(SUMPRODUCT(--(ABS(KPIs!$B$24:$F$24)>0.000000001))>0,"FAIL",IF(SUMPRODUCT(ISNUMBER(KPIs!$B$23:$F$23)*ISNUMBER(KPIs!$B$16:$F$16))=0,"n/a","PASS")) -> PASS | C20: Net margin × asset turnover × equity multiplier equals return on equity every year; n/a = no year where both are defined (a one-sided n/a is a FAIL)
A21: Scenarios: Active = selected scenario | B21: =IF(IFERROR(AND(ABS(Scenarios!E17-INDEX(Scenarios!B17:D17,1,Dashboard!$B$4))<0.5,ABS(Scenarios!E18-INDEX(Scenarios!B18:D18,1,Dashboard!$B$4))<0.5,ABS(Scenarios!E19-INDEX(Scenarios!B19:D19,1,Dashboard!$B$4))<0.5,ABS(Scenarios!E20-INDEX(Scenarios!B20:D20,1,Dashboard!$B$4))<0.000001,ABS(Scenarios!E21-INDEX(Scenarios!B21:D21,1,Dashboard!$B$4))<0.5,ABS(Scenarios!E22-INDEX(Scenarios!B22:D22,1,Dashboard!$B$4))<0.5,ABS(Scenarios!E23-INDEX(Scenarios!B23:D23,1,Dashboard!$B$4))<0.5,ABS(Scenarios!E24-INDEX(Scenarios!B24:D24,1,Dashboard!$B$4))<0.5,ABS(Scenarios!E25-INDEX(Scenarios!B25:D25,1,Dashboard!$B$4))<0.5,ABS(Scenarios!E26-INDEX(Scenarios!B26:D26,1,Dashboard!$B$4))<0.5),FALSE()),"PASS","FAIL") -> PASS | C21: On the Scenarios sheet the live model (Active) equals the Low / Base / High column chosen on the Dashboard for every output
A22: Balance sheet balances every period | B22: =IF(SUMPRODUCT(--(ABS(Monthly!$C$98:$BJ$98)>0.5))=0,"PASS","FAIL") -> PASS | C22: Assets = liabilities + equity in every period
A23: Funding sufficient (cash ≥ 0) | B23: =IF(MIN(Monthly!$C$76:$BJ$76)>=0,"PASS","WARN") -> WARN | C23: Business warning, not an error: cash dips below zero in this scenario
A25: Overall verdict | B25: =IF(COUNTIF(B4:B23,"FAIL")>0,"FAIL",IF(COUNTIF(B4:B23,"WARN")>0,"PASS WITH WARNINGS","PASS")) -> PASS WITH WARNINGS
