Workbook

Sheet Cover
B2: Hair salon financial model (planning)
B3: 5-year financial model · monthly detail · Low / Base / High scenarios · US dollars · Full plan
B5: Purpose | D5: Revenue and profit plan
B6: Active scenario | D6: =Dashboard!C4&" (change it on the Dashboard, cell B4)" -> Base (change it on the Dashboard, cell B4)
B7: Model checks | D7: =Checks!B24 -> PASS
B8: Prepared | D8: 21 October 2026
B10: Contents
C11: PRESENTATION
B12: 1 | C12: =HYPERLINK("#Dashboard!A1","Dashboard") -> Dashboard | D12: Scenario switch, key numbers, core financials
B13: 2 | C13: =HYPERLINK("#Summary!A1","Summary") -> Summary | D13: Income statement, cash flow and balance sheet — every year and any year by month
B14: 3 | C14: =HYPERLINK("#'Break-even'!A1","Break-even") -> Break-even | D14: Startup costs, funding need, break-even timing and revenue
B15: 4 | C15: =HYPERLINK("#Valuation!A1","Valuation") -> Valuation | D15: Free cash flow, DCF (perpetual growth and exit multiple), WACC × growth sensitivity
B16: 5 | C16: =HYPERLINK("#'Sources & Uses'!A1","Sources & Uses") -> Sources & Uses | D16: Funding structure, sources and uses of cash for the first months
B17: 6 | C17: =HYPERLINK("#KPIs!A1","KPIs") -> KPIs | D17: Financial ratios, DuPont analysis, industry metrics
C18: INPUTS
B19: 7 | C19: =HYPERLINK("#Inputs!A1","Inputs") -> Inputs | D19: Every assumption, Low / Base / High, with units and comments
C20: STATEMENTS
B21: 8 | C21: =HYPERLINK("#'P&L'!A1","P&L") -> P&L | D21: Annual profit & loss
B22: 9 | C22: =HYPERLINK("#'Cash Flow'!A1","Cash Flow") -> Cash Flow | D22: Annual cash flow statement
B23: 10 | C23: =HYPERLINK("#'Balance Sheet'!A1","Balance Sheet") -> Balance Sheet | D23: Balance sheet at year end
C24: CALCULATIONS
B25: 11 | C25: =HYPERLINK("#Monthly!A1","Monthly") -> Monthly | D25: Month-by-month engine of the model
B26: 12 | C26: =HYPERLINK("#Headcount!A1","Headcount") -> Headcount | D26: Team and payroll
C27: CONTROL
B28: 13 | C28: =HYPERLINK("#Checks!A1","Checks") -> Checks | D28: Live integrity checks and the overall verdict
B30: How to read this file
C31: 1000 | D31: Input you can change — yellow cell with a blue figure (Inputs sheet and the view switches)
C32: 1000 | D32: Formula — calculated, do not overwrite
C33: 1000 | D33: Link to another sheet
C34: 1000 | D34: Active value the model uses (follows the scenario)

Sheet Dashboard
A1: Dashboard | W1: =HYPERLINK("#'Cover'!A1","◂ Contents") -> ◂ Contents
A2: Hair salon financial model (planning)
A4: Active scenario | B4: 2 | C4: =CHOOSE(B4,"Low","Base","High") -> Base | D4: 1 = Low · 2 = Base · 3 = High — every sheet follows this cell | S4: Model checks | T4: =Checks!B24 -> PASS
A6: REVENUE · YEAR 5 | C6: EBITDA MARGIN · YEAR 5 | H6: NET INCOME · YEAR 5 | L6: LOWEST CASH BALANCE | P6: FUNDING REQUIRED | T6: ENTERPRISE VALUE (DCF)
A7: =F12 -> 942164.33 | C7: =F17 -> 0.1591247 | H7: =F18 -> 103543.94 | L7: =F38 -> 43432.925 | P7: =F36 -> 236567.08 | T7: =F43 -> 185713.55
A8: =IF(AND(B12>0,F12>=0),(F12/B12)^(1/4)-1,"CAGR n/a") -> 0.18422539 | C8: =F16 -> 149921.61 | H8: =F19 -> 0.10990009 | L8: ='Break-even'!B6 -> 24 | P8: =IF(F37>=0,"Covered by funding raised",-F37) -> 16567.075 | T8: Average of 2 methods
A10: Core financials ($'000) — active scenario
B11: 1 | C11: 2 | D11: 3 | E11: 4 | F11: 5
A12: Revenue | B12: =SUMIF(Monthly!$C$5:$BJ$5,B$11,Monthly!$C$21:$BJ$21) -> 479059.2 | C12: =SUMIF(Monthly!$C$5:$BJ$5,C$11,Monthly!$C$21:$BJ$21) -> 598797.5 | D12: =SUMIF(Monthly!$C$5:$BJ$5,D$11,Monthly!$C$21:$BJ$21) -> 725288.95 | E12: =SUMIF(Monthly!$C$5:$BJ$5,E$11,Monthly!$C$21:$BJ$21) -> 858830.97 | F12: =SUMIF(Monthly!$C$5:$BJ$5,F$11,Monthly!$C$21:$BJ$21) -> 942164.33
A13: Gross profit | B13: =SUMIF(Monthly!$C$5:$BJ$5,B$11,Monthly!$C$29:$BJ$29) -> 208964.51 | C13: =SUMIF(Monthly!$C$5:$BJ$5,C$11,Monthly!$C$29:$BJ$29) -> 258778.29 | D13: =SUMIF(Monthly!$C$5:$BJ$5,D$11,Monthly!$C$29:$BJ$29) -> 311392.84 | E13: =SUMIF(Monthly!$C$5:$BJ$5,E$11,Monthly!$C$29:$BJ$29) -> 366931.36 | F13: =SUMIF(Monthly!$C$5:$BJ$5,F$11,Monthly!$C$29:$BJ$29) -> 401730.62
A14: Gross margin | B14: =IF(B12=0,0,B13/B12) -> 0.43619767 | C14: =IF(C12=0,0,C13/C12) -> 0.43216328 | D14: =IF(D12=0,0,D13/D12) -> 0.42933625 | E14: =IF(E12=0,0,E13/E12) -> 0.42724514 | F14: =IF(F12=0,0,F13/F12) -> 0.42639125
A15: Operating expenses | B15: =SUMIF(Monthly!$C$5:$BJ$5,B$11,Monthly!$C$40:$BJ$40) -> -239720 | C15: =SUMIF(Monthly!$C$5:$BJ$5,C$11,Monthly!$C$40:$BJ$40) -> -242609.6 | D15: =SUMIF(Monthly!$C$5:$BJ$5,D$11,Monthly!$C$40:$BJ$40) -> -245585.89 | E15: =SUMIF(Monthly!$C$5:$BJ$5,E$11,Monthly!$C$40:$BJ$40) -> -248651.46 | F15: =SUMIF(Monthly!$C$5:$BJ$5,F$11,Monthly!$C$40:$BJ$40) -> -251809.01
A16: EBITDA | B16: =SUMIF(Monthly!$C$5:$BJ$5,B$11,Monthly!$C$41:$BJ$41) -> -30755.494 | C16: =SUMIF(Monthly!$C$5:$BJ$5,C$11,Monthly!$C$41:$BJ$41) -> 16168.694 | D16: =SUMIF(Monthly!$C$5:$BJ$5,D$11,Monthly!$C$41:$BJ$41) -> 65806.954 | E16: =SUMIF(Monthly!$C$5:$BJ$5,E$11,Monthly!$C$41:$BJ$41) -> 118279.9 | F16: =SUMIF(Monthly!$C$5:$BJ$5,F$11,Monthly!$C$41:$BJ$41) -> 149921.61
A17: EBITDA margin | B17: =IF(B12=0,0,B16/B12) -> -0.064199778 | C17: =IF(C12=0,0,C16/C12) -> 0.02700194 | D17: =IF(D12=0,0,D16/D12) -> 0.090732051 | E17: =IF(E12=0,0,E16/E12) -> 0.13772198 | F17: =IF(F12=0,0,F16/F12) -> 0.1591247
A18: Net income | B18: =SUMIF(Monthly!$C$5:$BJ$5,B$11,Monthly!$C$50:$BJ$50) -> -54084.939 | C18: =SUMIF(Monthly!$C$5:$BJ$5,C$11,Monthly!$C$50:$BJ$50) -> -6044.6391 | D18: =SUMIF(Monthly!$C$5:$BJ$5,D$11,Monthly!$C$50:$BJ$50) -> 44713.621 | E18: =SUMIF(Monthly!$C$5:$BJ$5,E$11,Monthly!$C$50:$BJ$50) -> 80899.537 | F18: =SUMIF(Monthly!$C$5:$BJ$5,F$11,Monthly!$C$50:$BJ$50) -> 103543.94
A19: Net margin | B19: =IF(B12=0,0,B18/B12) -> -0.11289824 | C19: =IF(C12=0,0,C18/C12) -> -0.01009463 | D19: =IF(D12=0,0,D18/D12) -> 0.061649389 | E19: =IF(E12=0,0,E18/E12) -> 0.094197275 | F19: =IF(F12=0,0,F18/F12) -> 0.10990009
A20: Operating cash flow | B20: =SUMIF(Monthly!$C$5:$BJ$5,B$11,Monthly!$C$74:$BJ$74) -> -34795.064 | C20: =SUMIF(Monthly!$C$5:$BJ$5,C$11,Monthly!$C$74:$BJ$74) -> 12461.322 | D20: =SUMIF(Monthly!$C$5:$BJ$5,D$11,Monthly!$C$74:$BJ$74) -> 63236.959 | E20: =SUMIF(Monthly!$C$5:$BJ$5,E$11,Monthly!$C$74:$BJ$74) -> 99441.019 | F20: =SUMIF(Monthly!$C$5:$BJ$5,F$11,Monthly!$C$74:$BJ$74) -> 121955.06
A21: Investing cash flow | B21: =SUMIF(Monthly!$C$5:$BJ$5,B$11,Monthly!$C$75:$BJ$75) -> -127400 | C21: =SUMIF(Monthly!$C$5:$BJ$5,C$11,Monthly!$C$75:$BJ$75) -> 0 | D21: =SUMIF(Monthly!$C$5:$BJ$5,D$11,Monthly!$C$75:$BJ$75) -> 0 | E21: =SUMIF(Monthly!$C$5:$BJ$5,E$11,Monthly!$C$75:$BJ$75) -> 0 | F21: =SUMIF(Monthly!$C$5:$BJ$5,F$11,Monthly!$C$75:$BJ$75) -> 0
A22: Financing cash flow | B22: =SUMIF(Monthly!$C$5:$BJ$5,B$11,Monthly!$C$77:$BJ$77) -> 207166.67 | C22: =SUMIF(Monthly!$C$5:$BJ$5,C$11,Monthly!$C$77:$BJ$77) -> -14000 | D22: =SUMIF(Monthly!$C$5:$BJ$5,D$11,Monthly!$C$77:$BJ$77) -> -14000 | E22: =SUMIF(Monthly!$C$5:$BJ$5,E$11,Monthly!$C$77:$BJ$77) -> -14000 | F22: =SUMIF(Monthly!$C$5:$BJ$5,F$11,Monthly!$C$77:$BJ$77) -> -14000
A23: Net change in cash | B23: =SUMIF(Monthly!$C$5:$BJ$5,B$11,Monthly!$C$78:$BJ$78) -> 44971.603 | C23: =SUMIF(Monthly!$C$5:$BJ$5,C$11,Monthly!$C$78:$BJ$78) -> -1538.678 | D23: =SUMIF(Monthly!$C$5:$BJ$5,D$11,Monthly!$C$78:$BJ$78) -> 49236.959 | E23: =SUMIF(Monthly!$C$5:$BJ$5,E$11,Monthly!$C$78:$BJ$78) -> 85441.019 | F23: =SUMIF(Monthly!$C$5:$BJ$5,F$11,Monthly!$C$78:$BJ$78) -> 107955.06
A24: Year-end cash | B24: =INDEX(Monthly!$C$80:$BJ$80,B$11*12) -> 44971.603 | C24: =INDEX(Monthly!$C$80:$BJ$80,C$11*12) -> 43432.925 | D24: =INDEX(Monthly!$C$80:$BJ$80,D$11*12) -> 92669.884 | E24: =INDEX(Monthly!$C$80:$BJ$80,E$11*12) -> 178110.9 | F24: =INDEX(Monthly!$C$80:$BJ$80,F$11*12) -> 286065.97
A26: Salon metrics
B27: 1 | C27: 2 | D27: 3 | E27: 4 | F27: 5
A28: Services performed | B28: =KPIs!B34 -> 6220.8 | C28: =KPIs!C34 -> 7603.2 | D28: =KPIs!D34 -> 8985.6 | E28: =KPIs!E34 -> 10368 | F28: =KPIs!F34 -> 11059.2
A29: Chair utilisation | B29: =KPIs!B33 -> 0.45 | C29: =KPIs!C33 -> 0.55 | D29: =KPIs!D33 -> 0.65 | E29: =KPIs!E33 -> 0.75 | F29: =KPIs!F33 -> 0.8
A30: Revenue per service (service revenue ÷ services) | B30: =KPIs!B37 -> 68 | C30: =KPIs!C37 -> 70.04 | D30: =KPIs!D37 -> 72.1412 | E30: =KPIs!E37 -> 74.305436 | F30: =KPIs!F37 -> 76.534599
A31: Team (FTE, year end) | B31: =INDEX(Headcount!$C$11:$BJ$11,B$27*12) -> 2.5 | C31: =INDEX(Headcount!$C$11:$BJ$11,C$27*12) -> 2.5 | D31: =INDEX(Headcount!$C$11:$BJ$11,D$27*12) -> 2.5 | E31: =INDEX(Headcount!$C$11:$BJ$11,E$27*12) -> 2.5 | F31: =INDEX(Headcount!$C$11:$BJ$11,F$27*12) -> 2.5
A33: Funding & valuation ($'000) — active scenario
A34: Equity raised | F34: =Inputs!$E$69 -> 150000
A35: Loan drawn | F35: =Inputs!$E$70 -> 70000
A36: Funding required (incl. cash buffer) | F36: ='Break-even'!B12 -> 236567.08
A37: Funding surplus / (shortfall) | F37: ='Break-even'!B17 -> -16567.075
A38: ="Lowest cash balance (month "&'Break-even'!B6&")" -> Lowest cash balance (month 24) | F38: ='Break-even'!B18 -> 43432.925
A39: First month with positive EBITDA | F39: ='Break-even'!B21 -> 13
A40: Cash invested paid back | F40: ='Break-even'!B23 -> 47
A41: Enterprise value — perpetual growth | F41: =Valuation!B27 -> 176447.85
A42: Enterprise value — exit multiple | F42: =Valuation!C27 -> 194979.25
A43: Enterprise value — average | F43: =Valuation!B30 -> 185713.55

Sheet Summary
A1: Financial statements summary | U1: =HYPERLINK("#'Cover'!A1","◂ Contents") -> ◂ Contents
A2: Hair salon financial model (planning) | P2: Select detailed year: | R2: 1
A5: Income statement ($'000) — by year | H5: ="Income statement ($'000) — Year "&$R$2&", by month" -> Income statement ($'000) — Year 1, by month
B6: 1 | C6: 2 | D6: 3 | E6: 4 | F6: 5 | H6: =INDEX(Monthly!$C$4:$BJ$4,($R$2-1)*12+1) -> 1 | I6: =INDEX(Monthly!$C$4:$BJ$4,($R$2-1)*12+2) -> 2 | J6: =INDEX(Monthly!$C$4:$BJ$4,($R$2-1)*12+3) -> 3 | K6: =INDEX(Monthly!$C$4:$BJ$4,($R$2-1)*12+4) -> 4 | L6: =INDEX(Monthly!$C$4:$BJ$4,($R$2-1)*12+5) -> 5 | M6: =INDEX(Monthly!$C$4:$BJ$4,($R$2-1)*12+6) -> 6 | N6: =INDEX(Monthly!$C$4:$BJ$4,($R$2-1)*12+7) -> 7 | O6: =INDEX(Monthly!$C$4:$BJ$4,($R$2-1)*12+8) -> 8 | P6: =INDEX(Monthly!$C$4:$BJ$4,($R$2-1)*12+9) -> 9 | Q6: =INDEX(Monthly!$C$4:$BJ$4,($R$2-1)*12+10) -> 10 | R6: =INDEX(Monthly!$C$4:$BJ$4,($R$2-1)*12+11) -> 11 | S6: =INDEX(Monthly!$C$4:$BJ$4,($R$2-1)*12+12) -> 12
A7: Revenue | B7: ='P&L'!B5 -> 479059.2 | C7: ='P&L'!C5 -> 598797.5 | D7: ='P&L'!D5 -> 725288.95 | E7: ='P&L'!E5 -> 858830.97 | F7: ='P&L'!F5 -> 942164.33 | H7: =INDEX(Monthly!$C$21:$BJ$21,($R$2-1)*12+1) -> 39921.6 | I7: =INDEX(Monthly!$C$21:$BJ$21,($R$2-1)*12+2) -> 39921.6 | J7: =INDEX(Monthly!$C$21:$BJ$21,($R$2-1)*12+3) -> 39921.6 | K7: =INDEX(Monthly!$C$21:$BJ$21,($R$2-1)*12+4) -> 39921.6 | L7: =INDEX(Monthly!$C$21:$BJ$21,($R$2-1)*12+5) -> 39921.6 | M7: =INDEX(Monthly!$C$21:$BJ$21,($R$2-1)*12+6) -> 39921.6 | N7: =INDEX(Monthly!$C$21:$BJ$21,($R$2-1)*12+7) -> 39921.6 | O7: =INDEX(Monthly!$C$21:$BJ$21,($R$2-1)*12+8) -> 39921.6 | P7: =INDEX(Monthly!$C$21:$BJ$21,($R$2-1)*12+9) -> 39921.6 | Q7: =INDEX(Monthly!$C$21:$BJ$21,($R$2-1)*12+10) -> 39921.6 | R7: =INDEX(Monthly!$C$21:$BJ$21,($R$2-1)*12+11) -> 39921.6 | S7: =INDEX(Monthly!$C$21:$BJ$21,($R$2-1)*12+12) -> 39921.6
A8: Cost of sales | B8: ='P&L'!B6 -> -270094.69 | C8: ='P&L'!C6 -> -340019.21 | D8: ='P&L'!D6 -> -413896.11 | E8: ='P&L'!E6 -> -491899.61 | F8: ='P&L'!F6 -> -540433.7 | H8: =INDEX(Monthly!$C$28:$BJ$28,($R$2-1)*12+1) -> -22507.891 | I8: =INDEX(Monthly!$C$28:$BJ$28,($R$2-1)*12+2) -> -22507.891 | J8: =INDEX(Monthly!$C$28:$BJ$28,($R$2-1)*12+3) -> -22507.891 | K8: =INDEX(Monthly!$C$28:$BJ$28,($R$2-1)*12+4) -> -22507.891 | L8: =INDEX(Monthly!$C$28:$BJ$28,($R$2-1)*12+5) -> -22507.891 | M8: =INDEX(Monthly!$C$28:$BJ$28,($R$2-1)*12+6) -> -22507.891 | N8: =INDEX(Monthly!$C$28:$BJ$28,($R$2-1)*12+7) -> -22507.891 | O8: =INDEX(Monthly!$C$28:$BJ$28,($R$2-1)*12+8) -> -22507.891 | P8: =INDEX(Monthly!$C$28:$BJ$28,($R$2-1)*12+9) -> -22507.891 | Q8: =INDEX(Monthly!$C$28:$BJ$28,($R$2-1)*12+10) -> -22507.891 | R8: =INDEX(Monthly!$C$28:$BJ$28,($R$2-1)*12+11) -> -22507.891 | S8: =INDEX(Monthly!$C$28:$BJ$28,($R$2-1)*12+12) -> -22507.891
A9: Gross profit | B9: ='P&L'!B7 -> 208964.51 | C9: ='P&L'!C7 -> 258778.29 | D9: ='P&L'!D7 -> 311392.84 | E9: ='P&L'!E7 -> 366931.36 | F9: ='P&L'!F7 -> 401730.62 | H9: =INDEX(Monthly!$C$29:$BJ$29,($R$2-1)*12+1) -> 17413.709 | I9: =INDEX(Monthly!$C$29:$BJ$29,($R$2-1)*12+2) -> 17413.709 | J9: =INDEX(Monthly!$C$29:$BJ$29,($R$2-1)*12+3) -> 17413.709 | K9: =INDEX(Monthly!$C$29:$BJ$29,($R$2-1)*12+4) -> 17413.709 | L9: =INDEX(Monthly!$C$29:$BJ$29,($R$2-1)*12+5) -> 17413.709 | M9: =INDEX(Monthly!$C$29:$BJ$29,($R$2-1)*12+6) -> 17413.709 | N9: =INDEX(Monthly!$C$29:$BJ$29,($R$2-1)*12+7) -> 17413.709 | O9: =INDEX(Monthly!$C$29:$BJ$29,($R$2-1)*12+8) -> 17413.709 | P9: =INDEX(Monthly!$C$29:$BJ$29,($R$2-1)*12+9) -> 17413.709 | Q9: =INDEX(Monthly!$C$29:$BJ$29,($R$2-1)*12+10) -> 17413.709 | R9: =INDEX(Monthly!$C$29:$BJ$29,($R$2-1)*12+11) -> 17413.709 | S9: =INDEX(Monthly!$C$29:$BJ$29,($R$2-1)*12+12) -> 17413.709
A10: Gross margin | B10: ='P&L'!B8 -> 0.43619767 | C10: ='P&L'!C8 -> 0.43216328 | D10: ='P&L'!D8 -> 0.42933625 | E10: ='P&L'!E8 -> 0.42724514 | F10: ='P&L'!F8 -> 0.42639125 | H10: =IF(H7=0,0,H9/H7) -> 0.43619767 | I10: =IF(I7=0,0,I9/I7) -> 0.43619767 | J10: =IF(J7=0,0,J9/J7) -> 0.43619767 | K10: =IF(K7=0,0,K9/K7) -> 0.43619767 | L10: =IF(L7=0,0,L9/L7) -> 0.43619767 | M10: =IF(M7=0,0,M9/M7) -> 0.43619767 | N10: =IF(N7=0,0,N9/N7) -> 0.43619767 | O10: =IF(O7=0,0,O9/O7) -> 0.43619767 | ... S10: =IF(S7=0,0,S9/S7) -> 0.43619767
A11: Total operating expenses | B11: ='P&L'!B17 -> -239720 | C11: ='P&L'!C17 -> -242609.6 | D11: ='P&L'!D17 -> -245585.89 | E11: ='P&L'!E17 -> -248651.46 | F11: ='P&L'!F17 -> -251809.01 | H11: =INDEX(Monthly!$C$40:$BJ$40,($R$2-1)*12+1) -> -19976.667 | I11: =INDEX(Monthly!$C$40:$BJ$40,($R$2-1)*12+2) -> -19976.667 | J11: =INDEX(Monthly!$C$40:$BJ$40,($R$2-1)*12+3) -> -19976.667 | K11: =INDEX(Monthly!$C$40:$BJ$40,($R$2-1)*12+4) -> -19976.667 | L11: =INDEX(Monthly!$C$40:$BJ$40,($R$2-1)*12+5) -> -19976.667 | M11: =INDEX(Monthly!$C$40:$BJ$40,($R$2-1)*12+6) -> -19976.667 | N11: =INDEX(Monthly!$C$40:$BJ$40,($R$2-1)*12+7) -> -19976.667 | O11: =INDEX(Monthly!$C$40:$BJ$40,($R$2-1)*12+8) -> -19976.667 | P11: =INDEX(Monthly!$C$40:$BJ$40,($R$2-1)*12+9) -> -19976.667 | Q11: =INDEX(Monthly!$C$40:$BJ$40,($R$2-1)*12+10) -> -19976.667 | R11: =INDEX(Monthly!$C$40:$BJ$40,($R$2-1)*12+11) -> -19976.667 | S11: =INDEX(Monthly!$C$40:$BJ$40,($R$2-1)*12+12) -> -19976.667
A12: EBITDA | B12: ='P&L'!B18 -> -30755.494 | C12: ='P&L'!C18 -> 16168.694 | D12: ='P&L'!D18 -> 65806.954 | E12: ='P&L'!E18 -> 118279.9 | F12: ='P&L'!F18 -> 149921.61 | H12: =INDEX(Monthly!$C$41:$BJ$41,($R$2-1)*12+1) -> -2562.9579 | I12: =INDEX(Monthly!$C$41:$BJ$41,($R$2-1)*12+2) -> -2562.9579 | J12: =INDEX(Monthly!$C$41:$BJ$41,($R$2-1)*12+3) -> -2562.9579 | K12: =INDEX(Monthly!$C$41:$BJ$41,($R$2-1)*12+4) -> -2562.9579 | L12: =INDEX(Monthly!$C$41:$BJ$41,($R$2-1)*12+5) -> -2562.9579 | M12: =INDEX(Monthly!$C$41:$BJ$41,($R$2-1)*12+6) -> -2562.9579 | N12: =INDEX(Monthly!$C$41:$BJ$41,($R$2-1)*12+7) -> -2562.9579 | O12: =INDEX(Monthly!$C$41:$BJ$41,($R$2-1)*12+8) -> -2562.9579 | P12: =INDEX(Monthly!$C$41:$BJ$41,($R$2-1)*12+9) -> -2562.9579 | Q12: =INDEX(Monthly!$C$41:$BJ$41,($R$2-1)*12+10) -> -2562.9579 | R12: =INDEX(Monthly!$C$41:$BJ$41,($R$2-1)*12+11) -> -2562.9579 | S12: =INDEX(Monthly!$C$41:$BJ$41,($R$2-1)*12+12) -> -2562.9579
A13: EBITDA margin | B13: ='P&L'!B19 -> -0.064199778 | C13: ='P&L'!C19 -> 0.02700194 | D13: ='P&L'!D19 -> 0.090732051 | E13: ='P&L'!E19 -> 0.13772198 | F13: ='P&L'!F19 -> 0.1591247 | H13: =IF(H7=0,0,H12/H7) -> -0.064199778 | I13: =IF(I7=0,0,I12/I7) -> -0.064199778 | J13: =IF(J7=0,0,J12/J7) -> -0.064199778 | K13: =IF(K7=0,0,K12/K7) -> -0.064199778 | L13: =IF(L7=0,0,L12/L7) -> -0.064199778 | M13: =IF(M7=0,0,M12/M7) -> -0.064199778 | N13: =IF(N7=0,0,N12/N7) -> -0.064199778 | O13: =IF(O7=0,0,O12/O7) -> -0.064199778 | ... S13: =IF(S7=0,0,S12/S7) -> -0.064199778
A14: Depreciation | B14: ='P&L'!B20 -> -18200 | C14: ='P&L'!C20 -> -18200 | D14: ='P&L'!D20 -> -18200 | E14: ='P&L'!E20 -> -18200 | F14: ='P&L'!F20 -> -18200 | H14: =INDEX(Monthly!$C$55:$BJ$55,($R$2-1)*12+1) -> -1516.6667 | I14: =INDEX(Monthly!$C$55:$BJ$55,($R$2-1)*12+2) -> -1516.6667 | J14: =INDEX(Monthly!$C$55:$BJ$55,($R$2-1)*12+3) -> -1516.6667 | K14: =INDEX(Monthly!$C$55:$BJ$55,($R$2-1)*12+4) -> -1516.6667 | L14: =INDEX(Monthly!$C$55:$BJ$55,($R$2-1)*12+5) -> -1516.6667 | M14: =INDEX(Monthly!$C$55:$BJ$55,($R$2-1)*12+6) -> -1516.6667 | N14: =INDEX(Monthly!$C$55:$BJ$55,($R$2-1)*12+7) -> -1516.6667 | O14: =INDEX(Monthly!$C$55:$BJ$55,($R$2-1)*12+8) -> -1516.6667 | P14: =INDEX(Monthly!$C$55:$BJ$55,($R$2-1)*12+9) -> -1516.6667 | Q14: =INDEX(Monthly!$C$55:$BJ$55,($R$2-1)*12+10) -> -1516.6667 | R14: =INDEX(Monthly!$C$55:$BJ$55,($R$2-1)*12+11) -> -1516.6667 | S14: =INDEX(Monthly!$C$55:$BJ$55,($R$2-1)*12+12) -> -1516.6667
A15: EBIT | B15: ='P&L'!B21 -> -48955.494 | C15: ='P&L'!C21 -> -2031.3057 | D15: ='P&L'!D21 -> 47606.954 | E15: ='P&L'!E21 -> 100079.9 | F15: ='P&L'!F21 -> 131721.61 | H15: =INDEX(Monthly!$C$44:$BJ$44,($R$2-1)*12+1) -> -4079.6245 | I15: =INDEX(Monthly!$C$44:$BJ$44,($R$2-1)*12+2) -> -4079.6245 | J15: =INDEX(Monthly!$C$44:$BJ$44,($R$2-1)*12+3) -> -4079.6245 | K15: =INDEX(Monthly!$C$44:$BJ$44,($R$2-1)*12+4) -> -4079.6245 | L15: =INDEX(Monthly!$C$44:$BJ$44,($R$2-1)*12+5) -> -4079.6245 | M15: =INDEX(Monthly!$C$44:$BJ$44,($R$2-1)*12+6) -> -4079.6245 | N15: =INDEX(Monthly!$C$44:$BJ$44,($R$2-1)*12+7) -> -4079.6245 | O15: =INDEX(Monthly!$C$44:$BJ$44,($R$2-1)*12+8) -> -4079.6245 | P15: =INDEX(Monthly!$C$44:$BJ$44,($R$2-1)*12+9) -> -4079.6245 | Q15: =INDEX(Monthly!$C$44:$BJ$44,($R$2-1)*12+10) -> -4079.6245 | R15: =INDEX(Monthly!$C$44:$BJ$44,($R$2-1)*12+11) -> -4079.6245 | S15: =INDEX(Monthly!$C$44:$BJ$44,($R$2-1)*12+12) -> -4079.6245
A16: Interest | B16: ='P&L'!B22 -> -5129.4444 | C16: ='P&L'!C22 -> -4013.3333 | D16: ='P&L'!D22 -> -2893.3333 | E16: ='P&L'!E22 -> -1773.3333 | F16: ='P&L'!F22 -> -653.33333 | H16: =INDEX(Monthly!$C$45:$BJ$45,($R$2-1)*12+1) -> -466.66667 | I16: =INDEX(Monthly!$C$45:$BJ$45,($R$2-1)*12+2) -> -462.77778 | J16: =INDEX(Monthly!$C$45:$BJ$45,($R$2-1)*12+3) -> -455 | K16: =INDEX(Monthly!$C$45:$BJ$45,($R$2-1)*12+4) -> -447.22222 | L16: =INDEX(Monthly!$C$45:$BJ$45,($R$2-1)*12+5) -> -439.44444 | M16: =INDEX(Monthly!$C$45:$BJ$45,($R$2-1)*12+6) -> -431.66667 | N16: =INDEX(Monthly!$C$45:$BJ$45,($R$2-1)*12+7) -> -423.88889 | O16: =INDEX(Monthly!$C$45:$BJ$45,($R$2-1)*12+8) -> -416.11111 | P16: =INDEX(Monthly!$C$45:$BJ$45,($R$2-1)*12+9) -> -408.33333 | Q16: =INDEX(Monthly!$C$45:$BJ$45,($R$2-1)*12+10) -> -400.55556 | R16: =INDEX(Monthly!$C$45:$BJ$45,($R$2-1)*12+11) -> -392.77778 | S16: =INDEX(Monthly!$C$45:$BJ$45,($R$2-1)*12+12) -> -385
A17: Pre-tax income | B17: ='P&L'!B23 -> -54084.939 | C17: ='P&L'!C23 -> -6044.6391 | D17: ='P&L'!D23 -> 44713.621 | E17: ='P&L'!E23 -> 98306.565 | F17: ='P&L'!F23 -> 131068.28 | H17: =INDEX(Monthly!$C$46:$BJ$46,($R$2-1)*12+1) -> -4546.2912 | I17: =INDEX(Monthly!$C$46:$BJ$46,($R$2-1)*12+2) -> -4542.4023 | J17: =INDEX(Monthly!$C$46:$BJ$46,($R$2-1)*12+3) -> -4534.6245 | K17: =INDEX(Monthly!$C$46:$BJ$46,($R$2-1)*12+4) -> -4526.8468 | L17: =INDEX(Monthly!$C$46:$BJ$46,($R$2-1)*12+5) -> -4519.069 | M17: =INDEX(Monthly!$C$46:$BJ$46,($R$2-1)*12+6) -> -4511.2912 | N17: =INDEX(Monthly!$C$46:$BJ$46,($R$2-1)*12+7) -> -4503.5134 | O17: =INDEX(Monthly!$C$46:$BJ$46,($R$2-1)*12+8) -> -4495.7356 | P17: =INDEX(Monthly!$C$46:$BJ$46,($R$2-1)*12+9) -> -4487.9579 | Q17: =INDEX(Monthly!$C$46:$BJ$46,($R$2-1)*12+10) -> -4480.1801 | R17: =INDEX(Monthly!$C$46:$BJ$46,($R$2-1)*12+11) -> -4472.4023 | S17: =INDEX(Monthly!$C$46:$BJ$46,($R$2-1)*12+12) -> -4464.6245
A18: Income tax | B18: ='P&L'!B24 -> 0 | C18: ='P&L'!C24 -> 0 | D18: ='P&L'!D24 -> 0 | E18: ='P&L'!E24 -> -17407.028 | F18: ='P&L'!F24 -> -27524.339 | H18: =INDEX(Monthly!$C$49:$BJ$49,($R$2-1)*12+1) -> 0 | I18: =INDEX(Monthly!$C$49:$BJ$49,($R$2-1)*12+2) -> 0 | J18: =INDEX(Monthly!$C$49:$BJ$49,($R$2-1)*12+3) -> 0 | K18: =INDEX(Monthly!$C$49:$BJ$49,($R$2-1)*12+4) -> 0 | L18: =INDEX(Monthly!$C$49:$BJ$49,($R$2-1)*12+5) -> 0 | M18: =INDEX(Monthly!$C$49:$BJ$49,($R$2-1)*12+6) -> 0 | N18: =INDEX(Monthly!$C$49:$BJ$49,($R$2-1)*12+7) -> 0 | O18: =INDEX(Monthly!$C$49:$BJ$49,($R$2-1)*12+8) -> 0 | P18: =INDEX(Monthly!$C$49:$BJ$49,($R$2-1)*12+9) -> 0 | Q18: =INDEX(Monthly!$C$49:$BJ$49,($R$2-1)*12+10) -> 0 | R18: =INDEX(Monthly!$C$49:$BJ$49,($R$2-1)*12+11) -> 0 | S18: =INDEX(Monthly!$C$49:$BJ$49,($R$2-1)*12+12) -> 0
A19: Net income | B19: ='P&L'!B25 -> -54084.939 | C19: ='P&L'!C25 -> -6044.6391 | D19: ='P&L'!D25 -> 44713.621 | E19: ='P&L'!E25 -> 80899.537 | F19: ='P&L'!F25 -> 103543.94 | H19: =INDEX(Monthly!$C$50:$BJ$50,($R$2-1)*12+1) -> -4546.2912 | I19: =INDEX(Monthly!$C$50:$BJ$50,($R$2-1)*12+2) -> -4542.4023 | J19: =INDEX(Monthly!$C$50:$BJ$50,($R$2-1)*12+3) -> -4534.6245 | K19: =INDEX(Monthly!$C$50:$BJ$50,($R$2-1)*12+4) -> -4526.8468 | L19: =INDEX(Monthly!$C$50:$BJ$50,($R$2-1)*12+5) -> -4519.069 | M19: =INDEX(Monthly!$C$50:$BJ$50,($R$2-1)*12+6) -> -4511.2912 | N19: =INDEX(Monthly!$C$50:$BJ$50,($R$2-1)*12+7) -> -4503.5134 | O19: =INDEX(Monthly!$C$50:$BJ$50,($R$2-1)*12+8) -> -4495.7356 | P19: =INDEX(Monthly!$C$50:$BJ$50,($R$2-1)*12+9) -> -4487.9579 | Q19: =INDEX(Monthly!$C$50:$BJ$50,($R$2-1)*12+10) -> -4480.1801 | R19: =INDEX(Monthly!$C$50:$BJ$50,($R$2-1)*12+11) -> -4472.4023 | S19: =INDEX(Monthly!$C$50:$BJ$50,($R$2-1)*12+12) -> -4464.6245
A20: Net margin | B20: ='P&L'!B26 -> -0.11289824 | C20: ='P&L'!C26 -> -0.01009463 | D20: ='P&L'!D26 -> 0.061649389 | E20: ='P&L'!E26 -> 0.094197275 | F20: ='P&L'!F26 -> 0.10990009 | H20: =IF(H7=0,0,H19/H7) -> -0.11388049 | I20: =IF(I7=0,0,I19/I7) -> -0.11378307 | J20: =IF(J7=0,0,J19/J7) -> -0.11358825 | K20: =IF(K7=0,0,K19/K7) -> -0.11339342 | L20: =IF(L7=0,0,L19/L7) -> -0.11319859 | M20: =IF(M7=0,0,M19/M7) -> -0.11300377 | N20: =IF(N7=0,0,N19/N7) -> -0.11280894 | O20: =IF(O7=0,0,O19/O7) -> -0.11261411 | ... S20: =IF(S7=0,0,S19/S7) -> -0.11183481
A22: Cash flow ($'000) — by year | H22: ="Cash flow ($'000) — Year "&$R$2&", by month" -> Cash flow ($'000) — Year 1, by month
B23: 1 | C23: 2 | D23: 3 | E23: 4 | F23: 5 | H23: =INDEX(Monthly!$C$4:$BJ$4,($R$2-1)*12+1) -> 1 | I23: =INDEX(Monthly!$C$4:$BJ$4,($R$2-1)*12+2) -> 2 | J23: =INDEX(Monthly!$C$4:$BJ$4,($R$2-1)*12+3) -> 3 | K23: =INDEX(Monthly!$C$4:$BJ$4,($R$2-1)*12+4) -> 4 | L23: =INDEX(Monthly!$C$4:$BJ$4,($R$2-1)*12+5) -> 5 | M23: =INDEX(Monthly!$C$4:$BJ$4,($R$2-1)*12+6) -> 6 | N23: =INDEX(Monthly!$C$4:$BJ$4,($R$2-1)*12+7) -> 7 | O23: =INDEX(Monthly!$C$4:$BJ$4,($R$2-1)*12+8) -> 8 | P23: =INDEX(Monthly!$C$4:$BJ$4,($R$2-1)*12+9) -> 9 | Q23: =INDEX(Monthly!$C$4:$BJ$4,($R$2-1)*12+10) -> 10 | R23: =INDEX(Monthly!$C$4:$BJ$4,($R$2-1)*12+11) -> 11 | S23: =INDEX(Monthly!$C$4:$BJ$4,($R$2-1)*12+12) -> 12
A24: Operating cash flow | B24: ='Cash Flow'!B10 -> -34795.064 | C24: ='Cash Flow'!C10 -> 12461.322 | D24: ='Cash Flow'!D10 -> 63236.959 | E24: ='Cash Flow'!E10 -> 99441.019 | F24: ='Cash Flow'!F10 -> 121955.06 | H24: =INDEX(Monthly!$C$74:$BJ$74,($R$2-1)*12+1) -> -1939.7493 | I24: =INDEX(Monthly!$C$74:$BJ$74,($R$2-1)*12+2) -> -3025.7356 | J24: =INDEX(Monthly!$C$74:$BJ$74,($R$2-1)*12+3) -> -3017.9579 | K24: =INDEX(Monthly!$C$74:$BJ$74,($R$2-1)*12+4) -> -3010.1801 | L24: =INDEX(Monthly!$C$74:$BJ$74,($R$2-1)*12+5) -> -3002.4023 | M24: =INDEX(Monthly!$C$74:$BJ$74,($R$2-1)*12+6) -> -2994.6245 | N24: =INDEX(Monthly!$C$74:$BJ$74,($R$2-1)*12+7) -> -2986.8468 | O24: =INDEX(Monthly!$C$74:$BJ$74,($R$2-1)*12+8) -> -2979.069 | P24: =INDEX(Monthly!$C$74:$BJ$74,($R$2-1)*12+9) -> -2971.2912 | Q24: =INDEX(Monthly!$C$74:$BJ$74,($R$2-1)*12+10) -> -2963.5134 | R24: =INDEX(Monthly!$C$74:$BJ$74,($R$2-1)*12+11) -> -2955.7356 | S24: =INDEX(Monthly!$C$74:$BJ$74,($R$2-1)*12+12) -> -2947.9579
A25: Capital spending | B25: ='Cash Flow'!B11 -> -127400 | C25: ='Cash Flow'!C11 -> 0 | D25: ='Cash Flow'!D11 -> 0 | E25: ='Cash Flow'!E11 -> 0 | F25: ='Cash Flow'!F11 -> 0 | H25: =INDEX(Monthly!$C$75:$BJ$75,($R$2-1)*12+1) -> -127400 | I25: =INDEX(Monthly!$C$75:$BJ$75,($R$2-1)*12+2) -> 0 | J25: =INDEX(Monthly!$C$75:$BJ$75,($R$2-1)*12+3) -> 0 | K25: =INDEX(Monthly!$C$75:$BJ$75,($R$2-1)*12+4) -> 0 | L25: =INDEX(Monthly!$C$75:$BJ$75,($R$2-1)*12+5) -> 0 | M25: =INDEX(Monthly!$C$75:$BJ$75,($R$2-1)*12+6) -> 0 | N25: =INDEX(Monthly!$C$75:$BJ$75,($R$2-1)*12+7) -> 0 | O25: =INDEX(Monthly!$C$75:$BJ$75,($R$2-1)*12+8) -> 0 | P25: =INDEX(Monthly!$C$75:$BJ$75,($R$2-1)*12+9) -> 0 | Q25: =INDEX(Monthly!$C$75:$BJ$75,($R$2-1)*12+10) -> 0 | R25: =INDEX(Monthly!$C$75:$BJ$75,($R$2-1)*12+11) -> 0 | S25: =INDEX(Monthly!$C$75:$BJ$75,($R$2-1)*12+12) -> 0
A26: Equity raised | B26: ='Cash Flow'!B12 -> 150000 | C26: ='Cash Flow'!C12 -> 0 | D26: ='Cash Flow'!D12 -> 0 | E26: ='Cash Flow'!E12 -> 0 | F26: ='Cash Flow'!F12 -> 0 | H26: =INDEX(Monthly!$C$76:$BJ$76,($R$2-1)*12+1) -> 150000 | I26: =INDEX(Monthly!$C$76:$BJ$76,($R$2-1)*12+2) -> 0 | J26: =INDEX(Monthly!$C$76:$BJ$76,($R$2-1)*12+3) -> 0 | K26: =INDEX(Monthly!$C$76:$BJ$76,($R$2-1)*12+4) -> 0 | L26: =INDEX(Monthly!$C$76:$BJ$76,($R$2-1)*12+5) -> 0 | M26: =INDEX(Monthly!$C$76:$BJ$76,($R$2-1)*12+6) -> 0 | N26: =INDEX(Monthly!$C$76:$BJ$76,($R$2-1)*12+7) -> 0 | O26: =INDEX(Monthly!$C$76:$BJ$76,($R$2-1)*12+8) -> 0 | P26: =INDEX(Monthly!$C$76:$BJ$76,($R$2-1)*12+9) -> 0 | Q26: =INDEX(Monthly!$C$76:$BJ$76,($R$2-1)*12+10) -> 0 | R26: =INDEX(Monthly!$C$76:$BJ$76,($R$2-1)*12+11) -> 0 | S26: =INDEX(Monthly!$C$76:$BJ$76,($R$2-1)*12+12) -> 0
A27: Loan drawdown | B27: ='Cash Flow'!B13 -> 70000 | C27: ='Cash Flow'!C13 -> 0 | D27: ='Cash Flow'!D13 -> 0 | E27: ='Cash Flow'!E13 -> 0 | F27: ='Cash Flow'!F13 -> 0 | H27: =INDEX(Monthly!$C$61:$BJ$61,($R$2-1)*12+1) -> 70000 | I27: =INDEX(Monthly!$C$61:$BJ$61,($R$2-1)*12+2) -> 0 | J27: =INDEX(Monthly!$C$61:$BJ$61,($R$2-1)*12+3) -> 0 | K27: =INDEX(Monthly!$C$61:$BJ$61,($R$2-1)*12+4) -> 0 | L27: =INDEX(Monthly!$C$61:$BJ$61,($R$2-1)*12+5) -> 0 | M27: =INDEX(Monthly!$C$61:$BJ$61,($R$2-1)*12+6) -> 0 | N27: =INDEX(Monthly!$C$61:$BJ$61,($R$2-1)*12+7) -> 0 | O27: =INDEX(Monthly!$C$61:$BJ$61,($R$2-1)*12+8) -> 0 | P27: =INDEX(Monthly!$C$61:$BJ$61,($R$2-1)*12+9) -> 0 | Q27: =INDEX(Monthly!$C$61:$BJ$61,($R$2-1)*12+10) -> 0 | R27: =INDEX(Monthly!$C$61:$BJ$61,($R$2-1)*12+11) -> 0 | S27: =INDEX(Monthly!$C$61:$BJ$61,($R$2-1)*12+12) -> 0
A28: Loan repayment | B28: ='Cash Flow'!B14 -> -12833.333 | C28: ='Cash Flow'!C14 -> -14000 | D28: ='Cash Flow'!D14 -> -14000 | E28: ='Cash Flow'!E14 -> -14000 | F28: ='Cash Flow'!F14 -> -14000 | H28: =INDEX(Monthly!$C$62:$BJ$62,($R$2-1)*12+1) -> 0 | I28: =INDEX(Monthly!$C$62:$BJ$62,($R$2-1)*12+2) -> -1166.6667 | J28: =INDEX(Monthly!$C$62:$BJ$62,($R$2-1)*12+3) -> -1166.6667 | K28: =INDEX(Monthly!$C$62:$BJ$62,($R$2-1)*12+4) -> -1166.6667 | L28: =INDEX(Monthly!$C$62:$BJ$62,($R$2-1)*12+5) -> -1166.6667 | M28: =INDEX(Monthly!$C$62:$BJ$62,($R$2-1)*12+6) -> -1166.6667 | N28: =INDEX(Monthly!$C$62:$BJ$62,($R$2-1)*12+7) -> -1166.6667 | O28: =INDEX(Monthly!$C$62:$BJ$62,($R$2-1)*12+8) -> -1166.6667 | P28: =INDEX(Monthly!$C$62:$BJ$62,($R$2-1)*12+9) -> -1166.6667 | Q28: =INDEX(Monthly!$C$62:$BJ$62,($R$2-1)*12+10) -> -1166.6667 | R28: =INDEX(Monthly!$C$62:$BJ$62,($R$2-1)*12+11) -> -1166.6667 | S28: =INDEX(Monthly!$C$62:$BJ$62,($R$2-1)*12+12) -> -1166.6667
A29: Financing cash flow | B29: ='Cash Flow'!B15 -> 207166.67 | C29: ='Cash Flow'!C15 -> -14000 | D29: ='Cash Flow'!D15 -> -14000 | E29: ='Cash Flow'!E15 -> -14000 | F29: ='Cash Flow'!F15 -> -14000 | H29: =INDEX(Monthly!$C$77:$BJ$77,($R$2-1)*12+1) -> 220000 | I29: =INDEX(Monthly!$C$77:$BJ$77,($R$2-1)*12+2) -> -1166.6667 | J29: =INDEX(Monthly!$C$77:$BJ$77,($R$2-1)*12+3) -> -1166.6667 | K29: =INDEX(Monthly!$C$77:$BJ$77,($R$2-1)*12+4) -> -1166.6667 | L29: =INDEX(Monthly!$C$77:$BJ$77,($R$2-1)*12+5) -> -1166.6667 | M29: =INDEX(Monthly!$C$77:$BJ$77,($R$2-1)*12+6) -> -1166.6667 | N29: =INDEX(Monthly!$C$77:$BJ$77,($R$2-1)*12+7) -> -1166.6667 | O29: =INDEX(Monthly!$C$77:$BJ$77,($R$2-1)*12+8) -> -1166.6667 | P29: =INDEX(Monthly!$C$77:$BJ$77,($R$2-1)*12+9) -> -1166.6667 | Q29: =INDEX(Monthly!$C$77:$BJ$77,($R$2-1)*12+10) -> -1166.6667 | R29: =INDEX(Monthly!$C$77:$BJ$77,($R$2-1)*12+11) -> -1166.6667 | S29: =INDEX(Monthly!$C$77:$BJ$77,($R$2-1)*12+12) -> -1166.6667
A30: Net change in cash | B30: ='Cash Flow'!B16 -> 44971.603 | C30: ='Cash Flow'!C16 -> -1538.678 | D30: ='Cash Flow'!D16 -> 49236.959 | E30: ='Cash Flow'!E16 -> 85441.019 | F30: ='Cash Flow'!F16 -> 107955.06 | H30: =INDEX(Monthly!$C$78:$BJ$78,($R$2-1)*12+1) -> 90660.251 | I30: =INDEX(Monthly!$C$78:$BJ$78,($R$2-1)*12+2) -> -4192.4023 | J30: =INDEX(Monthly!$C$78:$BJ$78,($R$2-1)*12+3) -> -4184.6245 | K30: =INDEX(Monthly!$C$78:$BJ$78,($R$2-1)*12+4) -> -4176.8468 | L30: =INDEX(Monthly!$C$78:$BJ$78,($R$2-1)*12+5) -> -4169.069 | M30: =INDEX(Monthly!$C$78:$BJ$78,($R$2-1)*12+6) -> -4161.2912 | N30: =INDEX(Monthly!$C$78:$BJ$78,($R$2-1)*12+7) -> -4153.5134 | O30: =INDEX(Monthly!$C$78:$BJ$78,($R$2-1)*12+8) -> -4145.7356 | P30: =INDEX(Monthly!$C$78:$BJ$78,($R$2-1)*12+9) -> -4137.9579 | Q30: =INDEX(Monthly!$C$78:$BJ$78,($R$2-1)*12+10) -> -4130.1801 | R30: =INDEX(Monthly!$C$78:$BJ$78,($R$2-1)*12+11) -> -4122.4023 | S30: =INDEX(Monthly!$C$78:$BJ$78,($R$2-1)*12+12) -> -4114.6245
A31: Closing cash | B31: ='Cash Flow'!B18 -> 44971.603 | C31: ='Cash Flow'!C18 -> 43432.925 | D31: ='Cash Flow'!D18 -> 92669.884 | E31: ='Cash Flow'!E18 -> 178110.9 | F31: ='Cash Flow'!F18 -> 286065.97 | H31: =INDEX(Monthly!$C$80:$BJ$80,($R$2-1)*12+1) -> 90660.251 | I31: =INDEX(Monthly!$C$80:$BJ$80,($R$2-1)*12+2) -> 86467.848 | J31: =INDEX(Monthly!$C$80:$BJ$80,($R$2-1)*12+3) -> 82283.224 | K31: =INDEX(Monthly!$C$80:$BJ$80,($R$2-1)*12+4) -> 78106.377 | L31: =INDEX(Monthly!$C$80:$BJ$80,($R$2-1)*12+5) -> 73937.308 | M31: =INDEX(Monthly!$C$80:$BJ$80,($R$2-1)*12+6) -> 69776.017 | N31: =INDEX(Monthly!$C$80:$BJ$80,($R$2-1)*12+7) -> 65622.503 | O31: =INDEX(Monthly!$C$80:$BJ$80,($R$2-1)*12+8) -> 61476.768 | P31: =INDEX(Monthly!$C$80:$BJ$80,($R$2-1)*12+9) -> 57338.81 | Q31: =INDEX(Monthly!$C$80:$BJ$80,($R$2-1)*12+10) -> 53208.63 | R31: =INDEX(Monthly!$C$80:$BJ$80,($R$2-1)*12+11) -> 49086.228 | S31: =INDEX(Monthly!$C$80:$BJ$80,($R$2-1)*12+12) -> 44971.603
A39: Balance sheet at year end ($'000) | H39: ="Balance sheet at month end ($'000) — Year "&$R$2 -> Balance sheet at month end ($'000) — Year 1
B40: 1 | C40: 2 | D40: 3 | E40: 4 | F40: 5 | H40: =INDEX(Monthly!$C$4:$BJ$4,($R$2-1)*12+1) -> 1 | I40: =INDEX(Monthly!$C$4:$BJ$4,($R$2-1)*12+2) -> 2 | J40: =INDEX(Monthly!$C$4:$BJ$4,($R$2-1)*12+3) -> 3 | K40: =INDEX(Monthly!$C$4:$BJ$4,($R$2-1)*12+4) -> 4 | L40: =INDEX(Monthly!$C$4:$BJ$4,($R$2-1)*12+5) -> 5 | M40: =INDEX(Monthly!$C$4:$BJ$4,($R$2-1)*12+6) -> 6 | N40: =INDEX(Monthly!$C$4:$BJ$4,($R$2-1)*12+7) -> 7 | O40: =INDEX(Monthly!$C$4:$BJ$4,($R$2-1)*12+8) -> 8 | P40: =INDEX(Monthly!$C$4:$BJ$4,($R$2-1)*12+9) -> 9 | Q40: =INDEX(Monthly!$C$4:$BJ$4,($R$2-1)*12+10) -> 10 | R40: =INDEX(Monthly!$C$4:$BJ$4,($R$2-1)*12+11) -> 11 | S40: =INDEX(Monthly!$C$4:$BJ$4,($R$2-1)*12+12) -> 12
A41: Cash | B41: ='Balance Sheet'!B5 -> 44971.603 | C41: ='Balance Sheet'!C5 -> 43432.925 | D41: ='Balance Sheet'!D5 -> 92669.884 | E41: ='Balance Sheet'!E5 -> 178110.9 | F41: ='Balance Sheet'!F5 -> 286065.97 | H41: =INDEX(Monthly!$C$80:$BJ$80,($R$2-1)*12+1) -> 90660.251 | I41: =INDEX(Monthly!$C$80:$BJ$80,($R$2-1)*12+2) -> 86467.848 | J41: =INDEX(Monthly!$C$80:$BJ$80,($R$2-1)*12+3) -> 82283.224 | K41: =INDEX(Monthly!$C$80:$BJ$80,($R$2-1)*12+4) -> 78106.377 | L41: =INDEX(Monthly!$C$80:$BJ$80,($R$2-1)*12+5) -> 73937.308 | M41: =INDEX(Monthly!$C$80:$BJ$80,($R$2-1)*12+6) -> 69776.017 | N41: =INDEX(Monthly!$C$80:$BJ$80,($R$2-1)*12+7) -> 65622.503 | O41: =INDEX(Monthly!$C$80:$BJ$80,($R$2-1)*12+8) -> 61476.768 | P41: =INDEX(Monthly!$C$80:$BJ$80,($R$2-1)*12+9) -> 57338.81 | Q41: =INDEX(Monthly!$C$80:$BJ$80,($R$2-1)*12+10) -> 53208.63 | R41: =INDEX(Monthly!$C$80:$BJ$80,($R$2-1)*12+11) -> 49086.228 | S41: =INDEX(Monthly!$C$80:$BJ$80,($R$2-1)*12+12) -> 44971.603
A42: Accounts receivable | B42: ='Balance Sheet'!B6 -> 2661.44 | C42: ='Balance Sheet'!C6 -> 3326.6528 | D42: ='Balance Sheet'!D6 -> 4029.3831 | E42: ='Balance Sheet'!E6 -> 4771.2832 | F42: ='Balance Sheet'!F6 -> 5234.2463 | H42: =INDEX(Monthly!$C$66:$BJ$66,($R$2-1)*12+1) -> 2661.44 | I42: =INDEX(Monthly!$C$66:$BJ$66,($R$2-1)*12+2) -> 2661.44 | J42: =INDEX(Monthly!$C$66:$BJ$66,($R$2-1)*12+3) -> 2661.44 | K42: =INDEX(Monthly!$C$66:$BJ$66,($R$2-1)*12+4) -> 2661.44 | L42: =INDEX(Monthly!$C$66:$BJ$66,($R$2-1)*12+5) -> 2661.44 | M42: =INDEX(Monthly!$C$66:$BJ$66,($R$2-1)*12+6) -> 2661.44 | N42: =INDEX(Monthly!$C$66:$BJ$66,($R$2-1)*12+7) -> 2661.44 | O42: =INDEX(Monthly!$C$66:$BJ$66,($R$2-1)*12+8) -> 2661.44 | P42: =INDEX(Monthly!$C$66:$BJ$66,($R$2-1)*12+9) -> 2661.44 | Q42: =INDEX(Monthly!$C$66:$BJ$66,($R$2-1)*12+10) -> 2661.44 | R42: =INDEX(Monthly!$C$66:$BJ$66,($R$2-1)*12+11) -> 2661.44 | S42: =INDEX(Monthly!$C$66:$BJ$66,($R$2-1)*12+12) -> 2661.44
A43: Inventory | B43: ='Balance Sheet'!B7 -> 11253.946 | C43: ='Balance Sheet'!C7 -> 14167.467 | D43: ='Balance Sheet'!D7 -> 17245.671 | E43: ='Balance Sheet'!E7 -> 20495.817 | F43: ='Balance Sheet'!F7 -> 22518.071 | H43: =INDEX(Monthly!$C$67:$BJ$67,($R$2-1)*12+1) -> 11253.946 | I43: =INDEX(Monthly!$C$67:$BJ$67,($R$2-1)*12+2) -> 11253.946 | J43: =INDEX(Monthly!$C$67:$BJ$67,($R$2-1)*12+3) -> 11253.946 | K43: =INDEX(Monthly!$C$67:$BJ$67,($R$2-1)*12+4) -> 11253.946 | L43: =INDEX(Monthly!$C$67:$BJ$67,($R$2-1)*12+5) -> 11253.946 | M43: =INDEX(Monthly!$C$67:$BJ$67,($R$2-1)*12+6) -> 11253.946 | N43: =INDEX(Monthly!$C$67:$BJ$67,($R$2-1)*12+7) -> 11253.946 | O43: =INDEX(Monthly!$C$67:$BJ$67,($R$2-1)*12+8) -> 11253.946 | P43: =INDEX(Monthly!$C$67:$BJ$67,($R$2-1)*12+9) -> 11253.946 | Q43: =INDEX(Monthly!$C$67:$BJ$67,($R$2-1)*12+10) -> 11253.946 | R43: =INDEX(Monthly!$C$67:$BJ$67,($R$2-1)*12+11) -> 11253.946 | S43: =INDEX(Monthly!$C$67:$BJ$67,($R$2-1)*12+12) -> 11253.946
A44: Net fixed assets | B44: ='Balance Sheet'!B8 -> 109200 | C44: ='Balance Sheet'!C8 -> 91000 | D44: ='Balance Sheet'!D8 -> 72800 | E44: ='Balance Sheet'!E8 -> 54600 | F44: ='Balance Sheet'!F8 -> 36400 | H44: =INDEX(Monthly!$C$57:$BJ$57,($R$2-1)*12+1) -> 125883.33 | I44: =INDEX(Monthly!$C$57:$BJ$57,($R$2-1)*12+2) -> 124366.67 | J44: =INDEX(Monthly!$C$57:$BJ$57,($R$2-1)*12+3) -> 122850 | K44: =INDEX(Monthly!$C$57:$BJ$57,($R$2-1)*12+4) -> 121333.33 | L44: =INDEX(Monthly!$C$57:$BJ$57,($R$2-1)*12+5) -> 119816.67 | M44: =INDEX(Monthly!$C$57:$BJ$57,($R$2-1)*12+6) -> 118300 | N44: =INDEX(Monthly!$C$57:$BJ$57,($R$2-1)*12+7) -> 116783.33 | O44: =INDEX(Monthly!$C$57:$BJ$57,($R$2-1)*12+8) -> 115266.67 | P44: =INDEX(Monthly!$C$57:$BJ$57,($R$2-1)*12+9) -> 113750 | Q44: =INDEX(Monthly!$C$57:$BJ$57,($R$2-1)*12+10) -> 112233.33 | R44: =INDEX(Monthly!$C$57:$BJ$57,($R$2-1)*12+11) -> 110716.67 | S44: =INDEX(Monthly!$C$57:$BJ$57,($R$2-1)*12+12) -> 109200
A45: Total assets | B45: ='Balance Sheet'!B9 -> 168086.99 | C45: ='Balance Sheet'!C9 -> 151927.04 | D45: ='Balance Sheet'!D9 -> 186744.94 | E45: ='Balance Sheet'!E9 -> 257978 | F45: ='Balance Sheet'!F9 -> 350218.28 | H45: =INDEX(Monthly!$C$94:$BJ$94,($R$2-1)*12+1) -> 230458.97 | I45: =INDEX(Monthly!$C$94:$BJ$94,($R$2-1)*12+2) -> 224749.9 | J45: =INDEX(Monthly!$C$94:$BJ$94,($R$2-1)*12+3) -> 219048.61 | K45: =INDEX(Monthly!$C$94:$BJ$94,($R$2-1)*12+4) -> 213355.1 | L45: =INDEX(Monthly!$C$94:$BJ$94,($R$2-1)*12+5) -> 207669.36 | M45: =INDEX(Monthly!$C$94:$BJ$94,($R$2-1)*12+6) -> 201991.4 | N45: =INDEX(Monthly!$C$94:$BJ$94,($R$2-1)*12+7) -> 196321.22 | O45: =INDEX(Monthly!$C$94:$BJ$94,($R$2-1)*12+8) -> 190658.82 | P45: =INDEX(Monthly!$C$94:$BJ$94,($R$2-1)*12+9) -> 185004.2 | Q45: =INDEX(Monthly!$C$94:$BJ$94,($R$2-1)*12+10) -> 179357.35 | R45: =INDEX(Monthly!$C$94:$BJ$94,($R$2-1)*12+11) -> 173718.28 | S45: =INDEX(Monthly!$C$94:$BJ$94,($R$2-1)*12+12) -> 168086.99
A46: Accounts payable | B46: ='Balance Sheet'!B10 -> 15005.261 | C46: ='Balance Sheet'!C10 -> 18889.956 | D46: ='Balance Sheet'!D10 -> 22994.228 | E46: ='Balance Sheet'!E10 -> 27327.756 | F46: ='Balance Sheet'!F10 -> 30024.095 | H46: =INDEX(Monthly!$C$68:$BJ$68,($R$2-1)*12+1) -> 15005.261 | I46: =INDEX(Monthly!$C$68:$BJ$68,($R$2-1)*12+2) -> 15005.261 | J46: =INDEX(Monthly!$C$68:$BJ$68,($R$2-1)*12+3) -> 15005.261 | K46: =INDEX(Monthly!$C$68:$BJ$68,($R$2-1)*12+4) -> 15005.261 | L46: =INDEX(Monthly!$C$68:$BJ$68,($R$2-1)*12+5) -> 15005.261 | M46: =INDEX(Monthly!$C$68:$BJ$68,($R$2-1)*12+6) -> 15005.261 | N46: =INDEX(Monthly!$C$68:$BJ$68,($R$2-1)*12+7) -> 15005.261 | O46: =INDEX(Monthly!$C$68:$BJ$68,($R$2-1)*12+8) -> 15005.261 | P46: =INDEX(Monthly!$C$68:$BJ$68,($R$2-1)*12+9) -> 15005.261 | Q46: =INDEX(Monthly!$C$68:$BJ$68,($R$2-1)*12+10) -> 15005.261 | R46: =INDEX(Monthly!$C$68:$BJ$68,($R$2-1)*12+11) -> 15005.261 | S46: =INDEX(Monthly!$C$68:$BJ$68,($R$2-1)*12+12) -> 15005.261
A47: Loan | B47: ='Balance Sheet'!B11 -> 57166.667 | C47: ='Balance Sheet'!C11 -> 43166.667 | D47: ='Balance Sheet'!D11 -> 29166.667 | E47: ='Balance Sheet'!E11 -> 15166.667 | F47: ='Balance Sheet'!F11 -> 1166.6667 | H47: =INDEX(Monthly!$C$63:$BJ$63,($R$2-1)*12+1) -> 70000 | I47: =INDEX(Monthly!$C$63:$BJ$63,($R$2-1)*12+2) -> 68833.333 | J47: =INDEX(Monthly!$C$63:$BJ$63,($R$2-1)*12+3) -> 67666.667 | K47: =INDEX(Monthly!$C$63:$BJ$63,($R$2-1)*12+4) -> 66500 | L47: =INDEX(Monthly!$C$63:$BJ$63,($R$2-1)*12+5) -> 65333.333 | M47: =INDEX(Monthly!$C$63:$BJ$63,($R$2-1)*12+6) -> 64166.667 | N47: =INDEX(Monthly!$C$63:$BJ$63,($R$2-1)*12+7) -> 63000 | O47: =INDEX(Monthly!$C$63:$BJ$63,($R$2-1)*12+8) -> 61833.333 | P47: =INDEX(Monthly!$C$63:$BJ$63,($R$2-1)*12+9) -> 60666.667 | Q47: =INDEX(Monthly!$C$63:$BJ$63,($R$2-1)*12+10) -> 59500 | R47: =INDEX(Monthly!$C$63:$BJ$63,($R$2-1)*12+11) -> 58333.333 | S47: =INDEX(Monthly!$C$63:$BJ$63,($R$2-1)*12+12) -> 57166.667
A48: Total liabilities | B48: ='Balance Sheet'!B12 -> 72171.927 | C48: ='Balance Sheet'!C12 -> 62056.623 | D48: ='Balance Sheet'!D12 -> 52160.895 | E48: ='Balance Sheet'!E12 -> 42494.423 | F48: ='Balance Sheet'!F12 -> 31190.761 | H48: =INDEX(Monthly!$C$95:$BJ$95,($R$2-1)*12+1) -> 85005.261 | I48: =INDEX(Monthly!$C$95:$BJ$95,($R$2-1)*12+2) -> 83838.594 | J48: =INDEX(Monthly!$C$95:$BJ$95,($R$2-1)*12+3) -> 82671.927 | K48: =INDEX(Monthly!$C$95:$BJ$95,($R$2-1)*12+4) -> 81505.261 | L48: =INDEX(Monthly!$C$95:$BJ$95,($R$2-1)*12+5) -> 80338.594 | M48: =INDEX(Monthly!$C$95:$BJ$95,($R$2-1)*12+6) -> 79171.927 | N48: =INDEX(Monthly!$C$95:$BJ$95,($R$2-1)*12+7) -> 78005.261 | O48: =INDEX(Monthly!$C$95:$BJ$95,($R$2-1)*12+8) -> 76838.594 | P48: =INDEX(Monthly!$C$95:$BJ$95,($R$2-1)*12+9) -> 75671.927 | Q48: =INDEX(Monthly!$C$95:$BJ$95,($R$2-1)*12+10) -> 74505.261 | R48: =INDEX(Monthly!$C$95:$BJ$95,($R$2-1)*12+11) -> 73338.594 | S48: =INDEX(Monthly!$C$95:$BJ$95,($R$2-1)*12+12) -> 72171.927
A49: Paid-in capital | B49: ='Balance Sheet'!B13 -> 150000 | C49: ='Balance Sheet'!C13 -> 150000 | D49: ='Balance Sheet'!D13 -> 150000 | E49: ='Balance Sheet'!E13 -> 150000 | F49: ='Balance Sheet'!F13 -> 150000 | H49: =INDEX(Monthly!$C$92:$BJ$92,($R$2-1)*12+1) -> 150000 | I49: =INDEX(Monthly!$C$92:$BJ$92,($R$2-1)*12+2) -> 150000 | J49: =INDEX(Monthly!$C$92:$BJ$92,($R$2-1)*12+3) -> 150000 | K49: =INDEX(Monthly!$C$92:$BJ$92,($R$2-1)*12+4) -> 150000 | L49: =INDEX(Monthly!$C$92:$BJ$92,($R$2-1)*12+5) -> 150000 | M49: =INDEX(Monthly!$C$92:$BJ$92,($R$2-1)*12+6) -> 150000 | N49: =INDEX(Monthly!$C$92:$BJ$92,($R$2-1)*12+7) -> 150000 | O49: =INDEX(Monthly!$C$92:$BJ$92,($R$2-1)*12+8) -> 150000 | P49: =INDEX(Monthly!$C$92:$BJ$92,($R$2-1)*12+9) -> 150000 | Q49: =INDEX(Monthly!$C$92:$BJ$92,($R$2-1)*12+10) -> 150000 | R49: =INDEX(Monthly!$C$92:$BJ$92,($R$2-1)*12+11) -> 150000 | S49: =INDEX(Monthly!$C$92:$BJ$92,($R$2-1)*12+12) -> 150000
A50: Retained earnings | B50: ='Balance Sheet'!B14 -> -54084.939 | C50: ='Balance Sheet'!C14 -> -60129.578 | D50: ='Balance Sheet'!D14 -> -15415.957 | E50: ='Balance Sheet'!E14 -> 65483.58 | F50: ='Balance Sheet'!F14 -> 169027.52 | H50: =INDEX(Monthly!$C$93:$BJ$93,($R$2-1)*12+1) -> -4546.2912 | I50: =INDEX(Monthly!$C$93:$BJ$93,($R$2-1)*12+2) -> -9088.6935 | J50: =INDEX(Monthly!$C$93:$BJ$93,($R$2-1)*12+3) -> -13623.318 | K50: =INDEX(Monthly!$C$93:$BJ$93,($R$2-1)*12+4) -> -18150.165 | L50: =INDEX(Monthly!$C$93:$BJ$93,($R$2-1)*12+5) -> -22669.234 | M50: =INDEX(Monthly!$C$93:$BJ$93,($R$2-1)*12+6) -> -27180.525 | N50: =INDEX(Monthly!$C$93:$BJ$93,($R$2-1)*12+7) -> -31684.038 | O50: =INDEX(Monthly!$C$93:$BJ$93,($R$2-1)*12+8) -> -36179.774 | P50: =INDEX(Monthly!$C$93:$BJ$93,($R$2-1)*12+9) -> -40667.732 | Q50: =INDEX(Monthly!$C$93:$BJ$93,($R$2-1)*12+10) -> -45147.912 | R50: =INDEX(Monthly!$C$93:$BJ$93,($R$2-1)*12+11) -> -49620.314 | S50: =INDEX(Monthly!$C$93:$BJ$93,($R$2-1)*12+12) -> -54084.939
A51: Total equity | B51: ='Balance Sheet'!B15 -> 95915.061 | C51: ='Balance Sheet'!C15 -> 89870.422 | D51: ='Balance Sheet'!D15 -> 134584.04 | E51: ='Balance Sheet'!E15 -> 215483.58 | F51: ='Balance Sheet'!F15 -> 319027.52 | H51: =INDEX(Monthly!$C$96:$BJ$96,($R$2-1)*12+1) -> 145453.71 | I51: =INDEX(Monthly!$C$96:$BJ$96,($R$2-1)*12+2) -> 140911.31 | J51: =INDEX(Monthly!$C$96:$BJ$96,($R$2-1)*12+3) -> 136376.68 | K51: =INDEX(Monthly!$C$96:$BJ$96,($R$2-1)*12+4) -> 131849.84 | L51: =INDEX(Monthly!$C$96:$BJ$96,($R$2-1)*12+5) -> 127330.77 | M51: =INDEX(Monthly!$C$96:$BJ$96,($R$2-1)*12+6) -> 122819.48 | N51: =INDEX(Monthly!$C$96:$BJ$96,($R$2-1)*12+7) -> 118315.96 | O51: =INDEX(Monthly!$C$96:$BJ$96,($R$2-1)*12+8) -> 113820.23 | P51: =INDEX(Monthly!$C$96:$BJ$96,($R$2-1)*12+9) -> 109332.27 | Q51: =INDEX(Monthly!$C$96:$BJ$96,($R$2-1)*12+10) -> 104852.09 | R51: =INDEX(Monthly!$C$96:$BJ$96,($R$2-1)*12+11) -> 100379.69 | S51: =INDEX(Monthly!$C$96:$BJ$96,($R$2-1)*12+12) -> 95915.061
A52: Total liabilities & equity | B52: ='Balance Sheet'!B16 -> 168086.99 | C52: ='Balance Sheet'!C16 -> 151927.04 | D52: ='Balance Sheet'!D16 -> 186744.94 | E52: ='Balance Sheet'!E16 -> 257978 | F52: ='Balance Sheet'!F16 -> 350218.28 | H52: =INDEX(Monthly!$C$97:$BJ$97,($R$2-1)*12+1) -> 230458.97 | I52: =INDEX(Monthly!$C$97:$BJ$97,($R$2-1)*12+2) -> 224749.9 | J52: =INDEX(Monthly!$C$97:$BJ$97,($R$2-1)*12+3) -> 219048.61 | K52: =INDEX(Monthly!$C$97:$BJ$97,($R$2-1)*12+4) -> 213355.1 | L52: =INDEX(Monthly!$C$97:$BJ$97,($R$2-1)*12+5) -> 207669.36 | M52: =INDEX(Monthly!$C$97:$BJ$97,($R$2-1)*12+6) -> 201991.4 | N52: =INDEX(Monthly!$C$97:$BJ$97,($R$2-1)*12+7) -> 196321.22 | O52: =INDEX(Monthly!$C$97:$BJ$97,($R$2-1)*12+8) -> 190658.82 | P52: =INDEX(Monthly!$C$97:$BJ$97,($R$2-1)*12+9) -> 185004.2 | Q52: =INDEX(Monthly!$C$97:$BJ$97,($R$2-1)*12+10) -> 179357.35 | R52: =INDEX(Monthly!$C$97:$BJ$97,($R$2-1)*12+11) -> 173718.28 | S52: =INDEX(Monthly!$C$97:$BJ$97,($R$2-1)*12+12) -> 168086.99

Sheet Break-even
A1: Startup costs, funding need and break-even | H1: =HYPERLINK("#'Cover'!A1","◂ Contents") -> ◂ Contents
A2: Live for the selected scenario. Periods are counted in months from the start of the plan.
A3: Scenario shown | B3: =CHOOSE(Dashboard!$B$4,"Low","Base","High") -> Base
A5: Startup costs & funding need (up to the lowest cash point)
A6: Lowest cash point (month #) | B6: =MATCH(MIN(Monthly!$C$80:$BJ$80),Monthly!$C$80:$BJ$80,0) -> 24
A7: Capital spending up to the lowest cash point | B7: =SUMPRODUCT(--(Monthly!$C$4:$BJ$4<=$B$6),Monthly!$C$53:$BJ$53) -> 127400
A8: Operating cash burn up to the lowest cash point | B8: =-SUMPRODUCT(--(Monthly!$C$4:$BJ$4<=$B$6),Monthly!$C$74:$BJ$74) -> 22333.742 | D8: Losses and working capital before the business funds itself
A9: Loan repayments up to the lowest cash point | B9: =-SUMPRODUCT(--(Monthly!$C$4:$BJ$4<=$B$6),Monthly!$C$62:$BJ$62) -> 26833.333
A10: Total uses of funds | B10: =B7+B8+B9 -> 176567.08
A11: Minimum cash buffer to keep | B11: =Inputs!$E$84 -> 60000 | D11: Input on the Inputs sheet
A12: Funding required (uses + buffer) | B12: =B10+B11 -> 236567.08
A14: Equity raised | B14: =Inputs!$E$69 -> 150000
A15: Loan drawn | B15: =Inputs!$E$70 -> 70000
A16: Total sources of funds | B16: =B14+B15 -> 220000
A17: Funding surplus / (shortfall) | B17: =B16-B12 -> -16567.075 | D17: Negative = raise at least this much more
A18: Lowest cash balance in the plan | B18: =MIN(Monthly!$C$80:$BJ$80) -> 43432.925 | D18: Equals sources minus uses
A20: Break-even timing
A21: First month with positive EBITDA (month #) | B21: =IFERROR(MATCH(1,Monthly!$C$81:$BJ$81,0),"Not within horizon") -> 13
A22: First month with positive net income (month #) | B22: =IFERROR(MATCH(1,Monthly!$C$84:$BJ$84,0),"Not within horizon") -> 25
A23: Cash invested paid back (month #) | B23: =IF(MIN(Monthly!$C$86:$BJ$86)>=0,"No investment to pay back",IFERROR(MATCH(1,Monthly!$C$88:$BJ$88,0),"Not within horizon")) -> 47 | D23: Cumulative operating + investing cash flow back to zero
A25: Annual break-even revenue
A26: Year # | B26: 1 | C26: 2 | D26: 3 | E26: 4 | F26: 5
B27: Year 1 | C27: Year 2 | D27: Year 3 | E27: Year 4 | F27: Year 5
A28: Revenue | B28: =SUMIF(Monthly!$C$5:$BJ$5,B$26,Monthly!$C$21:$BJ$21) -> 479059.2 | C28: =SUMIF(Monthly!$C$5:$BJ$5,C$26,Monthly!$C$21:$BJ$21) -> 598797.5 | D28: =SUMIF(Monthly!$C$5:$BJ$5,D$26,Monthly!$C$21:$BJ$21) -> 725288.95 | E28: =SUMIF(Monthly!$C$5:$BJ$5,E$26,Monthly!$C$21:$BJ$21) -> 858830.97 | F28: =SUMIF(Monthly!$C$5:$BJ$5,F$26,Monthly!$C$21:$BJ$21) -> 942164.33
A29: Gross profit | B29: =SUMIF(Monthly!$C$5:$BJ$5,B$26,Monthly!$C$29:$BJ$29) -> 208964.51 | C29: =SUMIF(Monthly!$C$5:$BJ$5,C$26,Monthly!$C$29:$BJ$29) -> 258778.29 | D29: =SUMIF(Monthly!$C$5:$BJ$5,D$26,Monthly!$C$29:$BJ$29) -> 311392.84 | E29: =SUMIF(Monthly!$C$5:$BJ$5,E$26,Monthly!$C$29:$BJ$29) -> 366931.36 | F29: =SUMIF(Monthly!$C$5:$BJ$5,F$26,Monthly!$C$29:$BJ$29) -> 401730.62
A30: Gross margin (contribution) | B30: =IF(B28=0,0,B29/B28) -> 0.43619767 | C30: =IF(C28=0,0,C29/C28) -> 0.43216328 | D30: =IF(D28=0,0,D29/D28) -> 0.42933625 | E30: =IF(E28=0,0,E29/E28) -> 0.42724514 | F30: =IF(F28=0,0,F29/F28) -> 0.42639125
A31: Operating expenses (treated as fixed) | B31: =-SUMIF(Monthly!$C$5:$BJ$5,B$26,Monthly!$C$40:$BJ$40) -> 239720 | C31: =-SUMIF(Monthly!$C$5:$BJ$5,C$26,Monthly!$C$40:$BJ$40) -> 242609.6 | D31: =-SUMIF(Monthly!$C$5:$BJ$5,D$26,Monthly!$C$40:$BJ$40) -> 245585.89 | E31: =-SUMIF(Monthly!$C$5:$BJ$5,E$26,Monthly!$C$40:$BJ$40) -> 248651.46 | F31: =-SUMIF(Monthly!$C$5:$BJ$5,F$26,Monthly!$C$40:$BJ$40) -> 251809.01
A32: Break-even revenue (EBITDA = 0) | B32: =IF(B30>0,B31/B30,"n/a") -> 549567.36 | C32: =IF(C30>0,C31/C30,"n/a") -> 561384.11 | D32: =IF(D30>0,D31/D30,"n/a") -> 572012.93 | E32: =IF(E30>0,E31/E30,"n/a") -> 581987.81 | F32: =IF(F30>0,F31/F30,"n/a") -> 590558.58
A33: Margin of safety (revenue above break-even) | B33: =IF(AND(ISNUMBER(B32),B28>0),(B28-B32)/B28,"n/a") -> -0.14718047 | C33: =IF(AND(ISNUMBER(C32),C28>0),(C28-C32)/C28,"n/a") -> 0.062480875 | D33: =IF(AND(ISNUMBER(D32),D28>0),(D28-D32)/D28,"n/a") -> 0.21133098 | E33: =IF(AND(ISNUMBER(E32),E28>0),(E28-E32)/E28,"n/a") -> 0.32234884 | F33: =IF(AND(ISNUMBER(F32),F28>0),(F28-F32)/F28,"n/a") -> 0.37318941
A35: Simplification: cost of sales is treated as variable and operating expenses as fixed, so break-even revenue = operating expenses ÷ gross margin.

Sheet Valuation
A1: Discounted cash flow valuation | H1: =HYPERLINK("#'Cover'!A1","◂ Contents") -> ◂ Contents
A2: Enterprise value at the start of the plan, before the funding raised in period 1. Year-end discounting.
A3: Scenario shown | B3: =CHOOSE(Dashboard!$B$4,"Low","Base","High") -> Base
A5: Assumptions (active scenario, from the Inputs sheet)
A6: Discount rate (WACC) | B6: =Inputs!$E$87 -> 0.25
A7: Terminal growth rate | B7: =Inputs!$E$88 -> 0.02
A8: Exit multiple (EV ÷ final-year EBITDA) | B8: =Inputs!$E$89 -> 4
A9: Tax rate (for the interest tax shield) | B9: =Inputs!$E$81 -> 0.21
A10: Sensitivity step: WACC | B10: =Inputs!$E$90 -> 0.01
A11: Sensitivity step: terminal growth | B11: =Inputs!$E$91 -> 0.005
A13: Free cash flow by year
A14: Year # | B14: 1 | C14: 2 | D14: 3 | E14: 4 | F14: 5
B15: Year 1 | C15: Year 2 | D15: Year 3 | E15: Year 4 | F15: Year 5
A16: EBITDA | B16: =SUMIF(Monthly!$C$5:$BJ$5,B$14,Monthly!$C$41:$BJ$41) -> -30755.494 | C16: =SUMIF(Monthly!$C$5:$BJ$5,C$14,Monthly!$C$41:$BJ$41) -> 16168.694 | D16: =SUMIF(Monthly!$C$5:$BJ$5,D$14,Monthly!$C$41:$BJ$41) -> 65806.954 | E16: =SUMIF(Monthly!$C$5:$BJ$5,E$14,Monthly!$C$41:$BJ$41) -> 118279.9 | F16: =SUMIF(Monthly!$C$5:$BJ$5,F$14,Monthly!$C$41:$BJ$41) -> 149921.61
A17: Unlevered free cash flow | B17: =SUMIF(Monthly!$C$5:$BJ$5,B$14,Monthly!$C$89:$BJ$89) -> -158142.8 | C17: =SUMIF(Monthly!$C$5:$BJ$5,C$14,Monthly!$C$89:$BJ$89) -> 15631.855 | D17: =SUMIF(Monthly!$C$5:$BJ$5,D$14,Monthly!$C$89:$BJ$89) -> 65522.692 | E17: =SUMIF(Monthly!$C$5:$BJ$5,E$14,Monthly!$C$89:$BJ$89) -> 100841.95 | F17: =SUMIF(Monthly!$C$5:$BJ$5,F$14,Monthly!$C$89:$BJ$89) -> 122471.2
A18: Discount factor | B18: =1/(1+Inputs!$E$87)^B$14 -> 0.8 | C18: =1/(1+Inputs!$E$87)^C$14 -> 0.64 | D18: =1/(1+Inputs!$E$87)^D$14 -> 0.512 | E18: =1/(1+Inputs!$E$87)^E$14 -> 0.4096 | F18: =1/(1+Inputs!$E$87)^F$14 -> 0.32768
A19: Present value of free cash flow | B19: =B17*B18 -> -126514.24 | C19: =C17*C18 -> 10004.387 | D19: =D17*D18 -> 33547.618 | E19: =E17*E18 -> 41304.864 | F19: =F17*F18 -> 40131.362
A21: Enterprise value
B22: Perpetual growth | C22: Exit multiple
A23: Present value of the plan's free cash flows | B23: =SUM($B$19:$F$19) -> -1526.0112 | C23: =B23 -> -1526.0112
A24: Final-year free cash flow | final-year EBITDA | B24: =$F$17 -> 122471.2 | C24: =$F$16 -> 149921.61
A25: Terminal value at the end of year 5 | B25: =IF($B$6>$B$7,B24*(1+$B$7)/($B$6-$B$7),0) -> 543133.13 | C25: =C24*$B$8 -> 599686.45
A26: Present value of the terminal value | B26: =B25/(1+$B$6)^$F$14 -> 177973.86 | C26: =C25/(1+$B$6)^$F$14 -> 196505.26
A27: Enterprise value | B27: =B23+B26 -> 176447.85 | C27: =C23+C26 -> 194979.25
A28: Terminal value share of enterprise value | B28: =IF(B27<>0,B26/B27,0) -> 1.0086485 | C28: =IF(C27<>0,C26/C27,0) -> 1.0078265
A29: Cross-check: implied exit multiple | implied perpetual growth | B29: =IF(C24>0,B25/C24,"n/a") -> 3.6227807 | C29: =IF(C25+B24<>0,(C25*$B$6-B24)/(C25+B24),"n/a") -> 0.038011669
A30: Enterprise value — average of the two methods | B30: =AVERAGE(B27,C27) -> 185713.55
A32: Sensitivity: enterprise value (perpetual growth) by WACC and terminal growth
A33: WACC ↓ · terminal growth → | B33: =$B$7+(-2)*$B$11 -> 0.01 | C33: =$B$7+(-1)*$B$11 -> 0.015 | D33: =$B$7+(0)*$B$11 -> 0.02 | E33: =$B$7+(1)*$B$11 -> 0.025 | F33: =$B$7+(2)*$B$11 -> 0.03
A34: =$B$6+(-2)*$B$10 -> 0.23 | B34: =IF($A34>B$33,SUMPRODUCT($B$17:$F$17/(1+$A34)^$B$14:$F$14)+$F$17*(1+B$33)/($A34-B$33)/(1+$A34)^$F$14,"n/a") -> 204244.7 | C34: =IF($A34>C$33,SUMPRODUCT($B$17:$F$17/(1+$A34)^$B$14:$F$14)+$F$17*(1+C$33)/($A34-C$33)/(1+$A34)^$F$14,"n/a") -> 209900.87 | D34: =IF($A34>D$33,SUMPRODUCT($B$17:$F$17/(1+$A34)^$B$14:$F$14)+$F$17*(1+D$33)/($A34-D$33)/(1+$A34)^$F$14,"n/a") -> 215826.38 | E34: =IF($A34>E$33,SUMPRODUCT($B$17:$F$17/(1+$A34)^$B$14:$F$14)+$F$17*(1+E$33)/($A34-E$33)/(1+$A34)^$F$14,"n/a") -> 222040.94 | F34: =IF($A34>F$33,SUMPRODUCT($B$17:$F$17/(1+$A34)^$B$14:$F$14)+$F$17*(1+F$33)/($A34-F$33)/(1+$A34)^$F$14,"n/a") -> 228566.23
A35: =$B$6+(-1)*$B$10 -> 0.24 | B35: =IF($A35>B$33,SUMPRODUCT($B$17:$F$17/(1+$A35)^$B$14:$F$14)+$F$17*(1+B$33)/($A35-B$33)/(1+$A35)^$F$14,"n/a") -> 184877.63 | C35: =IF($A35>C$33,SUMPRODUCT($B$17:$F$17/(1+$A35)^$B$14:$F$14)+$F$17*(1+C$33)/($A35-C$33)/(1+$A35)^$F$14,"n/a") -> 189882.66 | D35: =IF($A35>D$33,SUMPRODUCT($B$17:$F$17/(1+$A35)^$B$14:$F$14)+$F$17*(1+D$33)/($A35-D$33)/(1+$A35)^$F$14,"n/a") -> 195115.19 | E35: =IF($A35>E$33,SUMPRODUCT($B$17:$F$17/(1+$A35)^$B$14:$F$14)+$F$17*(1+E$33)/($A35-E$33)/(1+$A35)^$F$14,"n/a") -> 200591.1 | F35: =IF($A35>F$33,SUMPRODUCT($B$17:$F$17/(1+$A35)^$B$14:$F$14)+$F$17*(1+F$33)/($A35-F$33)/(1+$A35)^$F$14,"n/a") -> 206327.76
A36: =$B$6+(0)*$B$10 -> 0.25 | B36: =IF($A36>B$33,SUMPRODUCT($B$17:$F$17/(1+$A36)^$B$14:$F$14)+$F$17*(1+B$33)/($A36-B$33)/(1+$A36)^$F$14,"n/a") -> 167360.14 | C36: =IF($A36>C$33,SUMPRODUCT($B$17:$F$17/(1+$A36)^$B$14:$F$14)+$F$17*(1+C$33)/($A36-C$33)/(1+$A36)^$F$14,"n/a") -> 171807.32 | D36: =IF($A36>D$33,SUMPRODUCT($B$17:$F$17/(1+$A36)^$B$14:$F$14)+$F$17*(1+D$33)/($A36-D$33)/(1+$A36)^$F$14,"n/a") -> 176447.85 | E36: =IF($A36>E$33,SUMPRODUCT($B$17:$F$17/(1+$A36)^$B$14:$F$14)+$F$17*(1+E$33)/($A36-E$33)/(1+$A36)^$F$14,"n/a") -> 181294.64 | F36: =IF($A36>F$33,SUMPRODUCT($B$17:$F$17/(1+$A36)^$B$14:$F$14)+$F$17*(1+F$33)/($A36-F$33)/(1+$A36)^$F$14,"n/a") -> 186361.73
A37: =$B$6+(1)*$B$10 -> 0.26 | B37: =IF($A37>B$33,SUMPRODUCT($B$17:$F$17/(1+$A37)^$B$14:$F$14)+$F$17*(1+B$33)/($A37-B$33)/(1+$A37)^$F$14,"n/a") -> 151462.55 | C37: =IF($A37>C$33,SUMPRODUCT($B$17:$F$17/(1+$A37)^$B$14:$F$14)+$F$17*(1+C$33)/($A37-C$33)/(1+$A37)^$F$14,"n/a") -> 155429.13 | D37: =IF($A37>D$33,SUMPRODUCT($B$17:$F$17/(1+$A37)^$B$14:$F$14)+$F$17*(1+D$33)/($A37-D$33)/(1+$A37)^$F$14,"n/a") -> 159560.98 | E37: =IF($A37>E$33,SUMPRODUCT($B$17:$F$17/(1+$A37)^$B$14:$F$14)+$F$17*(1+E$33)/($A37-E$33)/(1+$A37)^$F$14,"n/a") -> 163868.65 | F37: =IF($A37>F$33,SUMPRODUCT($B$17:$F$17/(1+$A37)^$B$14:$F$14)+$F$17*(1+F$33)/($A37-F$33)/(1+$A37)^$F$14,"n/a") -> 168363.61
A38: =$B$6+(2)*$B$10 -> 0.27 | B38: =IF($A38>B$33,SUMPRODUCT($B$17:$F$17/(1+$A38)^$B$14:$F$14)+$F$17*(1+B$33)/($A38-B$33)/(1+$A38)^$F$14,"n/a") -> 136990.88 | C38: =IF($A38>C$33,SUMPRODUCT($B$17:$F$17/(1+$A38)^$B$14:$F$14)+$F$17*(1+C$33)/($A38-C$33)/(1+$A38)^$F$14,"n/a") -> 140541.26 | D38: =IF($A38>D$33,SUMPRODUCT($B$17:$F$17/(1+$A38)^$B$14:$F$14)+$F$17*(1+D$33)/($A38-D$33)/(1+$A38)^$F$14,"n/a") -> 144233.66 | E38: =IF($A38>E$33,SUMPRODUCT($B$17:$F$17/(1+$A38)^$B$14:$F$14)+$F$17*(1+E$33)/($A38-E$33)/(1+$A38)^$F$14,"n/a") -> 148076.78 | F38: =IF($A38>F$33,SUMPRODUCT($B$17:$F$17/(1+$A38)^$B$14:$F$14)+$F$17*(1+F$33)/($A38-F$33)/(1+$A38)^$F$14,"n/a") -> 152080.02
A40: Free cash flow = operating cash flow + interest × (1 − tax rate) − capital spending. Cells marked n/a: WACC not above growth.

Sheet Sources & Uses
A1: Sources and uses of funds | E1: =HYPERLINK("#'Cover'!A1","◂ Contents") -> ◂ Contents
A2: Live for the selected scenario. Where the money comes from and where it goes in the period set below.
A3: Scenario shown | B3: =CHOOSE(Dashboard!$B$4,"Low","Base","High") -> Base
A5: Funding structure ($'000) — raised at the start of the plan
B6: Amount | C6: Share
A7: Equity | B7: =Inputs!$E$69 -> 150000 | C7: =IF($B$9=0,0,B7/$B$9) -> 0.68181818
A8: Debt (loan) | B8: =Inputs!$E$70 -> 70000 | C8: =IF($B$9=0,0,B8/$B$9) -> 0.31818182
A9: Total funding | B9: =B7+B8 -> 220000 | C9: =IF(B9=0,0,1) -> 1
A10: Gearing (debt ÷ equity) | B10: =IF(B7<=0,IF(B8>0,"n/a",0),B8/B7) -> 0.46666667 | D10: n/a: debt without positive equity
A11: Funding required by the plan (Break-even sheet) | B11: ='Break-even'!B12 -> 236567.08
A12: Funding surplus / (shortfall) | B12: ='Break-even'!B17 -> -16567.075
A14: ="Sources and uses of cash in the first "&$B$16&IF($B$16=1," month"," months")&" ($'000)" -> Sources and uses of cash in the first 12 months ($'000)
A15: Period covered (months from the start) | B15: 12 | D15: 1 to 60 (capped)
A16: Months used | B16: =MIN(60,MAX(1,ROUND(B15,0))) -> 12
A17: Sources | B17: Amount | C17: Share
A18: Equity raised | B18: =SUMPRODUCT(--(Monthly!$C$4:$BJ$4<=$B$16),Monthly!$C$76:$BJ$76) -> 150000 | C18: =IF($B$21=0,0,B18/$B$21) -> 0.68181818
A19: Loan drawdowns | B19: =SUMPRODUCT(--(Monthly!$C$4:$BJ$4<=$B$16),Monthly!$C$61:$BJ$61) -> 70000 | C19: =IF($B$21=0,0,B19/$B$21) -> 0.31818182
A20: Cash generated by operations | B20: =MAX(0,SUMPRODUCT(--(Monthly!$C$4:$BJ$4<=$B$16),Monthly!$C$74:$BJ$74)) -> 0 | C20: =IF($B$21=0,0,B20/$B$21) -> 0
A21: Total sources | B21: =SUM(B18:B20) -> 220000 | C21: =IF(B21=0,0,1) -> 1
A23: Uses | B23: Amount | C23: Share
A24: Cash used by operations | B24: =MAX(0,-SUMPRODUCT(--(Monthly!$C$4:$BJ$4<=$B$16),Monthly!$C$74:$BJ$74)) -> 34795.064 | C24: =IF($B$28=0,0,B24/$B$28) -> 0.15815938
A25: Capital spending | B25: =-SUMPRODUCT(--(Monthly!$C$4:$BJ$4<=$B$16),Monthly!$C$75:$BJ$75) -> 127400 | C25: =IF($B$28=0,0,B25/$B$28) -> 0.57909091
A26: Loan repayments | B26: =-SUMPRODUCT(--(Monthly!$C$4:$BJ$4<=$B$16),Monthly!$C$62:$BJ$62) -> 12833.333 | C26: =IF($B$28=0,0,B26/$B$28) -> 0.058333333
A27: Cash at the end of the period | B27: =INDEX(Monthly!$C$80:$BJ$80,$B$16) -> 44971.603 | C27: =IF($B$28=0,0,B27/$B$28) -> 0.20441638
A28: Total uses | B28: =SUM(B24:B27) -> 220000 | C28: =IF(B28=0,0,1) -> 1
A29: Sources − uses (must be 0; opening cash is 0) | B29: =B21-B28 -> 0

Sheet KPIs
A1: KPIs & ratios | I1: =HYPERLINK("#'Cover'!A1","◂ Contents") -> ◂ Contents
A2: Hair salon financial model (planning) — industry metrics and financial ratios for the active scenario
A4: Financial ratios
B5: 1 | C5: 2 | D5: 3 | E5: 4 | F5: 5 | G5: Target
A6: Revenue growth | B6: =IF(N('P&L'!A5)<=0,"n/a",'P&L'!B5/'P&L'!A5-1) -> n/a | C6: =IF(N('P&L'!B5)<=0,"n/a",'P&L'!C5/'P&L'!B5-1) -> 0.24994469 | D6: =IF(N('P&L'!C5)<=0,"n/a",'P&L'!D5/'P&L'!C5-1) -> 0.21124245 | E6: =IF(N('P&L'!D5)<=0,"n/a",'P&L'!E5/'P&L'!D5-1) -> 0.1841225 | F6: =IF(N('P&L'!E5)<=0,"n/a",'P&L'!F5/'P&L'!E5-1) -> 0.097031147
A7: Gross margin | B7: =IF('P&L'!B5<=0,"n/a",'P&L'!B7/'P&L'!B5) -> 0.43619767 | C7: =IF('P&L'!C5<=0,"n/a",'P&L'!C7/'P&L'!C5) -> 0.43216328 | D7: =IF('P&L'!D5<=0,"n/a",'P&L'!D7/'P&L'!D5) -> 0.42933625 | E7: =IF('P&L'!E5<=0,"n/a",'P&L'!E7/'P&L'!E5) -> 0.42724514 | F7: =IF('P&L'!F5<=0,"n/a",'P&L'!F7/'P&L'!F5) -> 0.42639125
A8: EBITDA margin | B8: =IF('P&L'!B5<=0,"n/a",'P&L'!B18/'P&L'!B5) -> -0.064199778 | C8: =IF('P&L'!C5<=0,"n/a",'P&L'!C18/'P&L'!C5) -> 0.02700194 | D8: =IF('P&L'!D5<=0,"n/a",'P&L'!D18/'P&L'!D5) -> 0.090732051 | E8: =IF('P&L'!E5<=0,"n/a",'P&L'!E18/'P&L'!E5) -> 0.13772198 | F8: =IF('P&L'!F5<=0,"n/a",'P&L'!F18/'P&L'!F5) -> 0.1591247
A9: Net margin | B9: =IF('P&L'!B5<=0,"n/a",'P&L'!B25/'P&L'!B5) -> -0.11289824 | C9: =IF('P&L'!C5<=0,"n/a",'P&L'!C25/'P&L'!C5) -> -0.01009463 | D9: =IF('P&L'!D5<=0,"n/a",'P&L'!D25/'P&L'!D5) -> 0.061649389 | E9: =IF('P&L'!E5<=0,"n/a",'P&L'!E25/'P&L'!E5) -> 0.094197275 | F9: =IF('P&L'!F5<=0,"n/a",'P&L'!F25/'P&L'!F5) -> 0.10990009
A10: Payroll, % of revenue | B10: =IF('P&L'!B5<=0,"n/a",-SUMIF(Headcount!$C$5:$BJ$5,B$5,Headcount!$C$17:$BJ$17)/'P&L'!B5) -> 0.20106075 | C10: =IF('P&L'!C5<=0,"n/a",-SUMIF(Headcount!$C$5:$BJ$5,C$5,Headcount!$C$17:$BJ$17)/'P&L'!C5) -> 0.16568139 | D10: =IF('P&L'!D5<=0,"n/a",-SUMIF(Headcount!$C$5:$BJ$5,D$5,Headcount!$C$17:$BJ$17)/'P&L'!D5) -> 0.1408899 | E10: =IF('P&L'!E5<=0,"n/a",-SUMIF(Headcount!$C$5:$BJ$5,E$5,Headcount!$C$17:$BJ$17)/'P&L'!E5) -> 0.12255201 | F10: =IF('P&L'!F5<=0,"n/a",-SUMIF(Headcount!$C$5:$BJ$5,F$5,Headcount!$C$17:$BJ$17)/'P&L'!F5) -> 0.1150638
A11: Marketing, % of revenue | B11: =IF('P&L'!B5<=0,"n/a",-'P&L'!B10/'P&L'!B5) -> 0.062622741 | C11: =IF('P&L'!C5<=0,"n/a",-'P&L'!C10/'P&L'!C5) -> 0.050100409 | D11: =IF('P&L'!D5<=0,"n/a",-'P&L'!D10/'P&L'!D5) -> 0.041362825 | E11: =IF('P&L'!E5<=0,"n/a",-'P&L'!E10/'P&L'!E5) -> 0.034931204 | F11: =IF('P&L'!F5<=0,"n/a",-'P&L'!F10/'P&L'!F5) -> 0.031841579
A12: Operating expenses, % of revenue | B12: =IF('P&L'!B5<=0,"n/a",-'P&L'!B17/'P&L'!B5) -> 0.50039745 | C12: =IF('P&L'!C5<=0,"n/a",-'P&L'!C17/'P&L'!C5) -> 0.40516134 | D12: =IF('P&L'!D5<=0,"n/a",-'P&L'!D17/'P&L'!D5) -> 0.3386042 | E12: =IF('P&L'!E5<=0,"n/a",-'P&L'!E17/'P&L'!E5) -> 0.28952317 | F12: =IF('P&L'!F5<=0,"n/a",-'P&L'!F17/'P&L'!F5) -> 0.26726655
A13: Current ratio (current assets ÷ current liabilities) | B13: =IF(('Balance Sheet'!B12-'Balance Sheet'!B11)<=0,"n/a",('Balance Sheet'!B5+'Balance Sheet'!B6+'Balance Sheet'!B7)/('Balance Sheet'!B12-'Balance Sheet'!B11)) -> 3.9244229 | C13: =IF(('Balance Sheet'!C12-'Balance Sheet'!C11)<=0,"n/a",('Balance Sheet'!C5+'Balance Sheet'!C6+'Balance Sheet'!C7)/('Balance Sheet'!C12-'Balance Sheet'!C11)) -> 3.2253672 | D13: =IF(('Balance Sheet'!D12-'Balance Sheet'!D11)<=0,"n/a",('Balance Sheet'!D5+'Balance Sheet'!D6+'Balance Sheet'!D7)/('Balance Sheet'!D12-'Balance Sheet'!D11)) -> 4.9553712 | E13: =IF(('Balance Sheet'!E12-'Balance Sheet'!E11)<=0,"n/a",('Balance Sheet'!E5+'Balance Sheet'!E6+'Balance Sheet'!E7)/('Balance Sheet'!E12-'Balance Sheet'!E11)) -> 7.4421772 | F13: =IF(('Balance Sheet'!F12-'Balance Sheet'!F11)<=0,"n/a",('Balance Sheet'!F5+'Balance Sheet'!F6+'Balance Sheet'!F7)/('Balance Sheet'!F12-'Balance Sheet'!F11)) -> 10.452215
A14: Debt ÷ equity (loan ÷ total equity) | B14: =IF('Balance Sheet'!B15<=0,"n/a",'Balance Sheet'!B11/'Balance Sheet'!B15) -> 0.59601345 | C14: =IF('Balance Sheet'!C15<=0,"n/a",'Balance Sheet'!C11/'Balance Sheet'!C15) -> 0.48032117 | D14: =IF('Balance Sheet'!D15<=0,"n/a",'Balance Sheet'!D11/'Balance Sheet'!D15) -> 0.21671712 | E14: =IF('Balance Sheet'!E15<=0,"n/a",'Balance Sheet'!E11/'Balance Sheet'!E15) -> 0.070384327 | F14: =IF('Balance Sheet'!F15<=0,"n/a",'Balance Sheet'!F11/'Balance Sheet'!F15) -> 0.0036569468
A15: Return on assets (net income ÷ year-end assets) | B15: =IF('Balance Sheet'!B9<=0,"n/a",'P&L'!B25/'Balance Sheet'!B9) -> -0.32176755 | C15: =IF('Balance Sheet'!C9<=0,"n/a",'P&L'!C25/'Balance Sheet'!C9) -> -0.039786458 | D15: =IF('Balance Sheet'!D9<=0,"n/a",'P&L'!D25/'Balance Sheet'!D9) -> 0.23943686 | E15: =IF('Balance Sheet'!E9<=0,"n/a",'P&L'!E25/'Balance Sheet'!E9) -> 0.31359083 | F15: =IF('Balance Sheet'!F9<=0,"n/a",'P&L'!F25/'Balance Sheet'!F9) -> 0.29565544
A16: Return on equity (net income ÷ year-end equity) | B16: =IF('Balance Sheet'!B15<=0,"n/a",'P&L'!B25/'Balance Sheet'!B15) -> -0.56388369 | C16: =IF('Balance Sheet'!C15<=0,"n/a",'P&L'!C25/'Balance Sheet'!C15) -> -0.067259493 | D16: =IF('Balance Sheet'!D15<=0,"n/a",'P&L'!D25/'Balance Sheet'!D15) -> 0.33223568 | E16: =IF('Balance Sheet'!E15<=0,"n/a",'P&L'!E25/'Balance Sheet'!E15) -> 0.37543249 | F16: =IF('Balance Sheet'!F15<=0,"n/a",'P&L'!F25/'Balance Sheet'!F15) -> 0.32456116
A18: DuPont analysis — return on equity = net margin × asset turnover × equity multiplier
B19: 1 | C19: 2 | D19: 3 | E19: 4 | F19: 5
A20: Net margin | B20: =IF('P&L'!B5<=0,"n/a",'P&L'!B25/'P&L'!B5) -> -0.11289824 | C20: =IF('P&L'!C5<=0,"n/a",'P&L'!C25/'P&L'!C5) -> -0.01009463 | D20: =IF('P&L'!D5<=0,"n/a",'P&L'!D25/'P&L'!D5) -> 0.061649389 | E20: =IF('P&L'!E5<=0,"n/a",'P&L'!E25/'P&L'!E5) -> 0.094197275 | F20: =IF('P&L'!F5<=0,"n/a",'P&L'!F25/'P&L'!F5) -> 0.10990009
A21: × Asset turnover (revenue ÷ assets) | B21: =IF('Balance Sheet'!B9<=0,"n/a",'P&L'!B5/'Balance Sheet'!B9) -> 2.8500671 | C21: =IF('Balance Sheet'!C9<=0,"n/a",'P&L'!C5/'Balance Sheet'!C9) -> 3.941349 | D21: =IF('Balance Sheet'!D9<=0,"n/a",'P&L'!D5/'Balance Sheet'!D9) -> 3.883848 | E21: =IF('Balance Sheet'!E9<=0,"n/a",'P&L'!E5/'Balance Sheet'!E9) -> 3.3290861 | F21: =IF('Balance Sheet'!F9<=0,"n/a",'P&L'!F5/'Balance Sheet'!F9) -> 2.6902203
A22: × Equity multiplier (assets ÷ equity) | B22: =IF('Balance Sheet'!B15<=0,"n/a",'Balance Sheet'!B9/'Balance Sheet'!B15) -> 1.7524567 | C22: =IF('Balance Sheet'!C15<=0,"n/a",'Balance Sheet'!C9/'Balance Sheet'!C15) -> 1.6905122 | D22: =IF('Balance Sheet'!D15<=0,"n/a",'Balance Sheet'!D9/'Balance Sheet'!D15) -> 1.3875712 | E22: =IF('Balance Sheet'!E15<=0,"n/a",'Balance Sheet'!E9/'Balance Sheet'!E15) -> 1.1972049 | F22: =IF('Balance Sheet'!F15<=0,"n/a",'Balance Sheet'!F9/'Balance Sheet'!F15) -> 1.0977682
A23: Return on equity (product of the three) | B23: =IF(AND(ISNUMBER(B20),ISNUMBER(B21),ISNUMBER(B22)),B20*B21*B22,"n/a") -> -0.56388369 | C23: =IF(AND(ISNUMBER(C20),ISNUMBER(C21),ISNUMBER(C22)),C20*C21*C22,"n/a") -> -0.067259493 | D23: =IF(AND(ISNUMBER(D20),ISNUMBER(D21),ISNUMBER(D22)),D20*D21*D22,"n/a") -> 0.33223568 | E23: =IF(AND(ISNUMBER(E20),ISNUMBER(E21),ISNUMBER(E22)),E20*E21*E22,"n/a") -> 0.37543249 | F23: =IF(AND(ISNUMBER(F20),ISNUMBER(F21),ISNUMBER(F22)),F20*F21*F22,"n/a") -> 0.32456116
A24: Check: product − return on equity (must be 0) | B24: =IF(AND(ISNUMBER(B23),ISNUMBER(B16)),B23-B16,IF(ISNUMBER(B23),1,IF(AND(ISNUMBER(B16),ISNUMBER(B20),ISNUMBER(B21)),1,0))) -> 0 | C24: =IF(AND(ISNUMBER(C23),ISNUMBER(C16)),C23-C16,IF(ISNUMBER(C23),1,IF(AND(ISNUMBER(C16),ISNUMBER(C20),ISNUMBER(C21)),1,0))) -> 0 | D24: =IF(AND(ISNUMBER(D23),ISNUMBER(D16)),D23-D16,IF(ISNUMBER(D23),1,IF(AND(ISNUMBER(D16),ISNUMBER(D20),ISNUMBER(D21)),1,0))) -> 0 | E24: =IF(AND(ISNUMBER(E23),ISNUMBER(E16)),E23-E16,IF(ISNUMBER(E23),1,IF(AND(ISNUMBER(E16),ISNUMBER(E20),ISNUMBER(E21)),1,0))) -> 0 | F24: =IF(AND(ISNUMBER(F23),ISNUMBER(F16)),F23-F16,IF(ISNUMBER(F23),1,IF(AND(ISNUMBER(F16),ISNUMBER(F20),ISNUMBER(F21)),1,0))) -> 0
A26: Salon metrics ($'000; per-unit rows in $)
A27: Year # | B27: 1 | C27: 2 | D27: 3 | E27: 4 | F27: 5
B28: Year 1 | C28: Year 2 | D28: Year 3 | E28: Year 4 | F28: Year 5 | G28: Target
A29: Styling chairs (year end) | B29: =INDEX(Monthly!$C$8:$BJ$8,B$27*12) -> 8 | C29: =INDEX(Monthly!$C$8:$BJ$8,C$27*12) -> 8 | D29: =INDEX(Monthly!$C$8:$BJ$8,D$27*12) -> 8 | E29: =INDEX(Monthly!$C$8:$BJ$8,E$27*12) -> 8 | F29: =INDEX(Monthly!$C$8:$BJ$8,F$27*12) -> 8
A30: Chairs rented to independent stylists | B30: =INDEX(Monthly!$C$9:$BJ$9,B$27*12) -> 2 | C30: =INDEX(Monthly!$C$9:$BJ$9,C$27*12) -> 2 | D30: =INDEX(Monthly!$C$9:$BJ$9,D$27*12) -> 2 | E30: =INDEX(Monthly!$C$9:$BJ$9,E$27*12) -> 2 | F30: =INDEX(Monthly!$C$9:$BJ$9,F$27*12) -> 2
A31: Bookable chair hours (employed chairs) | B31: =SUMIF(Monthly!$C$5:$BJ$5,B$27,Monthly!$C$11:$BJ$11) -> 13824 | C31: =SUMIF(Monthly!$C$5:$BJ$5,C$27,Monthly!$C$11:$BJ$11) -> 13824 | D31: =SUMIF(Monthly!$C$5:$BJ$5,D$27,Monthly!$C$11:$BJ$11) -> 13824 | E31: =SUMIF(Monthly!$C$5:$BJ$5,E$27,Monthly!$C$11:$BJ$11) -> 13824 | F31: =SUMIF(Monthly!$C$5:$BJ$5,F$27,Monthly!$C$11:$BJ$11) -> 13824
A32: Booked chair hours | B32: =SUMIF(Monthly!$C$5:$BJ$5,B$27,Monthly!$C$13:$BJ$13) -> 6220.8 | C32: =SUMIF(Monthly!$C$5:$BJ$5,C$27,Monthly!$C$13:$BJ$13) -> 7603.2 | D32: =SUMIF(Monthly!$C$5:$BJ$5,D$27,Monthly!$C$13:$BJ$13) -> 8985.6 | E32: =SUMIF(Monthly!$C$5:$BJ$5,E$27,Monthly!$C$13:$BJ$13) -> 10368 | F32: =SUMIF(Monthly!$C$5:$BJ$5,F$27,Monthly!$C$13:$BJ$13) -> 11059.2
A33: Chair utilisation (booked ÷ bookable hours) | B33: =IF(B31=0,0,B32/B31) -> 0.45 | C33: =IF(C31=0,0,C32/C31) -> 0.55 | D33: =IF(D31=0,0,D32/D31) -> 0.65 | E33: =IF(E31=0,0,E32/E31) -> 0.75 | F33: =IF(F31=0,0,F32/F31) -> 0.8
A34: Services performed | B34: =SUMIF(Monthly!$C$5:$BJ$5,B$27,Monthly!$C$14:$BJ$14) -> 6220.8 | C34: =SUMIF(Monthly!$C$5:$BJ$5,C$27,Monthly!$C$14:$BJ$14) -> 7603.2 | D34: =SUMIF(Monthly!$C$5:$BJ$5,D$27,Monthly!$C$14:$BJ$14) -> 8985.6 | E34: =SUMIF(Monthly!$C$5:$BJ$5,E$27,Monthly!$C$14:$BJ$14) -> 10368 | F34: =SUMIF(Monthly!$C$5:$BJ$5,F$27,Monthly!$C$14:$BJ$14) -> 11059.2
A35: Revenue | B35: =SUMIF(Monthly!$C$5:$BJ$5,B$27,Monthly!$C$21:$BJ$21) -> 479059.2 | C35: =SUMIF(Monthly!$C$5:$BJ$5,C$27,Monthly!$C$21:$BJ$21) -> 598797.5 | D35: =SUMIF(Monthly!$C$5:$BJ$5,D$27,Monthly!$C$21:$BJ$21) -> 725288.95 | E35: =SUMIF(Monthly!$C$5:$BJ$5,E$27,Monthly!$C$21:$BJ$21) -> 858830.97 | F35: =SUMIF(Monthly!$C$5:$BJ$5,F$27,Monthly!$C$21:$BJ$21) -> 942164.33
A36: Service revenue | B36: =SUMIF(Monthly!$C$5:$BJ$5,B$27,Monthly!$C$18:$BJ$18) -> 423014.4 | C36: =SUMIF(Monthly!$C$5:$BJ$5,C$27,Monthly!$C$18:$BJ$18) -> 532528.13 | D36: =SUMIF(Monthly!$C$5:$BJ$5,D$27,Monthly!$C$18:$BJ$18) -> 648231.97 | E36: =SUMIF(Monthly!$C$5:$BJ$5,E$27,Monthly!$C$18:$BJ$18) -> 770398.76 | F36: =SUMIF(Monthly!$C$5:$BJ$5,F$27,Monthly!$C$18:$BJ$18) -> 846411.44
A37: Revenue per service ($) | B37: =IF(B34=0,0,B36/B34) -> 68 | C37: =IF(C34=0,0,C36/C34) -> 70.04 | D37: =IF(D34=0,0,D36/D34) -> 72.1412 | E37: =IF(E34=0,0,E36/E34) -> 74.305436 | F37: =IF(F34=0,0,F36/F34) -> 76.534599
A38: Retail product sales | B38: =SUMIF(Monthly!$C$5:$BJ$5,B$27,Monthly!$C$19:$BJ$19) -> 37324.8 | C38: =SUMIF(Monthly!$C$5:$BJ$5,C$27,Monthly!$C$19:$BJ$19) -> 46987.776 | D38: =SUMIF(Monthly!$C$5:$BJ$5,D$27,Monthly!$C$19:$BJ$19) -> 57196.938 | E38: =SUMIF(Monthly!$C$5:$BJ$5,E$27,Monthly!$C$19:$BJ$19) -> 67976.361 | F38: =SUMIF(Monthly!$C$5:$BJ$5,F$27,Monthly!$C$19:$BJ$19) -> 74683.362
A39: Retail products, % of service revenue | B39: =IF(B36=0,0,B38/B36) -> 0.088235294 | C39: =IF(C36=0,0,C38/C36) -> 0.088235294 | D39: =IF(D36=0,0,D38/D36) -> 0.088235294 | E39: =IF(E36=0,0,E38/E36) -> 0.088235294 | F39: =IF(F36=0,0,F38/F36) -> 0.088235294
A40: Chair rent income | B40: =SUMIF(Monthly!$C$5:$BJ$5,B$27,Monthly!$C$20:$BJ$20) -> 18720 | C40: =SUMIF(Monthly!$C$5:$BJ$5,C$27,Monthly!$C$20:$BJ$20) -> 19281.6 | D40: =SUMIF(Monthly!$C$5:$BJ$5,D$27,Monthly!$C$20:$BJ$20) -> 19860.048 | E40: =SUMIF(Monthly!$C$5:$BJ$5,E$27,Monthly!$C$20:$BJ$20) -> 20455.849 | F40: =SUMIF(Monthly!$C$5:$BJ$5,F$27,Monthly!$C$20:$BJ$20) -> 21069.525
A41: Service revenue per employed chair (year-end chairs) | B41: =IF(B29-B30=0,0,B36/(B29-B30)) -> 70502.4 | C41: =IF(C29-C30=0,0,C36/(C29-C30)) -> 88754.688 | D41: =IF(D29-D30=0,0,D36/(D29-D30)) -> 108038.66 | E41: =IF(E29-E30=0,0,E36/(E29-E30)) -> 128399.79 | F41: =IF(F29-F30=0,0,F36/(F29-F30)) -> 141068.57
A42: Chair rent per rented chair per month ($) | B42: =IF(B30=0,0,B40/B30/12) -> 780 | C42: =IF(C30=0,0,C40/C30/12) -> 803.4 | D42: =IF(D30=0,0,D40/D30/12) -> 827.502 | E42: =IF(E30=0,0,E40/E30/12) -> 852.32706 | F42: =IF(F30=0,0,F40/F30/12) -> 877.89687
A43: Gross profit | B43: =SUMIF(Monthly!$C$5:$BJ$5,B$27,Monthly!$C$29:$BJ$29) -> 208964.51 | C43: =SUMIF(Monthly!$C$5:$BJ$5,C$27,Monthly!$C$29:$BJ$29) -> 258778.29 | D43: =SUMIF(Monthly!$C$5:$BJ$5,D$27,Monthly!$C$29:$BJ$29) -> 311392.84 | E43: =SUMIF(Monthly!$C$5:$BJ$5,E$27,Monthly!$C$29:$BJ$29) -> 366931.36 | F43: =SUMIF(Monthly!$C$5:$BJ$5,F$27,Monthly!$C$29:$BJ$29) -> 401730.62
A44: Gross margin | B44: =IF(B35=0,0,B43/B35) -> 0.43619767 | C44: =IF(C35=0,0,C43/C35) -> 0.43216328 | D44: =IF(D35=0,0,D43/D35) -> 0.42933625 | E44: =IF(E35=0,0,E43/E35) -> 0.42724514 | F44: =IF(F35=0,0,F43/F35) -> 0.42639125
A45: EBITDA | B45: =SUMIF(Monthly!$C$5:$BJ$5,B$27,Monthly!$C$41:$BJ$41) -> -30755.494 | C45: =SUMIF(Monthly!$C$5:$BJ$5,C$27,Monthly!$C$41:$BJ$41) -> 16168.694 | D45: =SUMIF(Monthly!$C$5:$BJ$5,D$27,Monthly!$C$41:$BJ$41) -> 65806.954 | E45: =SUMIF(Monthly!$C$5:$BJ$5,E$27,Monthly!$C$41:$BJ$41) -> 118279.9 | F45: =SUMIF(Monthly!$C$5:$BJ$5,F$27,Monthly!$C$41:$BJ$41) -> 149921.61
A46: EBITDA margin | B46: =IF(B35=0,0,B45/B35) -> -0.064199778 | C46: =IF(C35=0,0,C45/C35) -> 0.02700194 | D46: =IF(D35=0,0,D45/D35) -> 0.090732051 | E46: =IF(E35=0,0,E45/E35) -> 0.13772198 | F46: =IF(F35=0,0,F45/F35) -> 0.1591247

Sheet Inputs
A1: Inputs — Low / Base / High | I1: =HYPERLINK("#'Cover'!A1","◂ Contents") -> ◂ Contents
A2: Illustrative assumptions — replace them with your own numbers.
A5: Driver | B5: Low | C5: Base | D5: High | E5: Active | F5: Unit | G5: Source / comment
A6: Chairs & booking
A7: Styling chairs at start | B7: 8 | C7: 8 | D7: 8 | E7: =CHOOSE(Dashboard!$B$4,B7,C7,D7) -> 8 | F7: #
A8: Chairs added each year (from year 2) | B8: 0 | C8: 0 | D8: 0 | E8: =CHOOSE(Dashboard!$B$4,B8,C8,D8) -> 0 | F8: # | G8: Low ≤ Base ≤ High
A9: Days open per month | B9: 24 | C9: 24 | D9: 24 | E9: =CHOOSE(Dashboard!$B$4,B9,C9,D9) -> 24 | F9: days
A10: Bookable service hours per chair per day | B10: 8 | C10: 8 | D10: 8 | E10: =CHOOSE(Dashboard!$B$4,B10,C10,D10) -> 8 | F10: hours
A11: Chair utilisation, booked ÷ bookable hours (year 1) | B11: 0.38 | C11: 0.45 | D11: 0.52 | E11: =CHOOSE(Dashboard!$B$4,B11,C11,D11) -> 0.45 | F11: % | G11: Low ≤ Base ≤ High
A12: Utilisation gain per year (percentage points) | B12: 0.08 | C12: 0.1 | D12: 0.12 | E12: =CHOOSE(Dashboard!$B$4,B12,C12,D12) -> 0.1 | F12: % | G12: Low ≤ Base ≤ High
A13: Utilisation ceiling | B13: 0.8 | C13: 0.8 | D13: 0.8 | E13: =CHOOSE(Dashboard!$B$4,B13,C13,D13) -> 0.8 | F13: %
A14: Services per booked hour | B14: 0.9 | C14: 1 | D14: 1.1 | E14: =CHOOSE(Dashboard!$B$4,B14,C14,D14) -> 1 | F14: # | G14: Low ≤ Base ≤ High
A16: Prices
A17: Average service price (year 1) | B17: 62 | C17: 68 | D17: 74 | E17: =CHOOSE(Dashboard!$B$4,B17,C17,D17) -> 68 | F17: $ | G17: Low ≤ Base ≤ High
A18: Price increase per year | B18: 0.02 | C18: 0.03 | D18: 0.04 | E18: =CHOOSE(Dashboard!$B$4,B18,C18,D18) -> 0.03 | F18: % | G18: Low ≤ Base ≤ High
A20: Retail products
A21: Services with a retail product sale (attach rate) | B21: 0.15 | C21: 0.2 | D21: 0.25 | E21: =CHOOSE(Dashboard!$B$4,B21,C21,D21) -> 0.2 | F21: % | G21: Low ≤ Base ≤ High
A22: Average retail product sale (year 1) | B22: 26 | C22: 30 | D22: 34 | E22: =CHOOSE(Dashboard!$B$4,B22,C22,D22) -> 30 | F22: $ | G22: Low ≤ Base ≤ High
A24: Chair rent
A25: Chairs rented to independent stylists | B25: 0.25 | C25: 0.25 | D25: 0.25 | E25: =CHOOSE(Dashboard!$B$4,B25,C25,D25) -> 0.25 | F25: %
A26: Chair rent per rented chair per week (year 1) | B26: 180 | C26: 200 | D26: 220 | E26: =CHOOSE(Dashboard!$B$4,B26,C26,D26) -> 200 | F26: $ | G26: Low ≤ Base ≤ High
A27: Rented chairs paying rent (occupancy) | B27: 0.85 | C27: 0.9 | D27: 0.95 | E27: =CHOOSE(Dashboard!$B$4,B27,C27,D27) -> 0.9 | F27: % | G27: Low ≤ Base ≤ High
A29: Cost of sales
A30: Stylist commission, % of service revenue | B30: 0.48 | C30: 0.45 | D30: 0.42 | E30: =CHOOSE(Dashboard!$B$4,B30,C30,D30) -> 0.45 | F30: % | G30: Low ≥ Base ≥ High (lower is better)
A31: Retail product cost, % of product sales | B31: 0.55 | C31: 0.5 | D31: 0.45 | E31: =CHOOSE(Dashboard!$B$4,B31,C31,D31) -> 0.5 | F31: % | G31: Low ≥ Base ≥ High (lower is better)
A32: Backbar supplies per service (year 1) | B32: 4.5 | C32: 4 | D32: 3.5 | E32: =CHOOSE(Dashboard!$B$4,B32,C32,D32) -> 4 | F32: $ | G32: Low ≥ Base ≥ High (lower is better)
A33: Card fees, % of service & product sales | B33: 0.031 | C33: 0.029 | D33: 0.027 | E33: =CHOOSE(Dashboard!$B$4,B33,C33,D33) -> 0.029 | F33: % | G33: Low ≥ Base ≥ High (lower is better)
A35: Operating costs
A36: Marketing budget per month (year 1) | B36: 2500 | C36: 2500 | D36: 2500 | E36: =CHOOSE(Dashboard!$B$4,B36,C36,D36) -> 2500 | F36: $
A37: Marketing budget growth per year | B37: -0.1 | C37: 0 | D37: 0.1 | E37: =CHOOSE(Dashboard!$B$4,B37,C37,D37) -> 0 | F37: % | G37: Low ≤ Base ≤ High
A38: Salon rent per month | B38: 6500 | C38: 6500 | D38: 6500 | E38: =CHOOSE(Dashboard!$B$4,B38,C38,D38) -> 6500 | F38: $
A39: Utilities per month | B39: 900 | C39: 900 | D39: 900 | E39: =CHOOSE(Dashboard!$B$4,B39,C39,D39) -> 900 | F39: $
A40: Booking software per month | B40: 250 | C40: 250 | D40: 250 | E40: =CHOOSE(Dashboard!$B$4,B40,C40,D40) -> 250 | F40: $
A41: Insurance & licences per month | B41: 650 | C41: 650 | D41: 650 | E41: =CHOOSE(Dashboard!$B$4,B41,C41,D41) -> 650 | F41: $
A42: Towels, laundry & cleaning per month | B42: 450 | C42: 450 | D42: 450 | E42: =CHOOSE(Dashboard!$B$4,B42,C42,D42) -> 450 | F42: $
A43: Other G&A per month (accounting, bank, legal) | B43: 700 | C43: 700 | D43: 700 | E43: =CHOOSE(Dashboard!$B$4,B43,C43,D43) -> 700 | F43: $
A45: Capex
A46: Fit-out & refurbishment (month 1) | B46: 95000 | C46: 95000 | D46: 95000 | E46: =CHOOSE(Dashboard!$B$4,B46,C46,D46) -> 95000 | F46: $
A47: Styling station & chair, per chair | B47: 3200 | C47: 3200 | D47: 3200 | E47: =CHOOSE(Dashboard!$B$4,B47,C47,D47) -> 3200 | F47: $
A48: Chairs already equipped at start | B48: 0 | C48: 0 | D48: 0 | E48: =CHOOSE(Dashboard!$B$4,B48,C48,D48) -> 0 | F48: #
A49: Backwash units to buy at start | B49: 2 | C49: 2 | D49: 2 | E49: =CHOOSE(Dashboard!$B$4,B49,C49,D49) -> 2 | F49: #
A50: Backwash unit, each | B50: 3400 | C50: 3400 | D50: 3400 | E50: =CHOOSE(Dashboard!$B$4,B50,C50,D50) -> 3400 | F50: $
A52: Headcount
A53: Salon manager: headcount (FTE) | B53: 0.5 | C53: 0.5 | D53: 0.5 | E53: =CHOOSE(Dashboard!$B$4,B53,C53,D53) -> 0.5 | F53: FTE | G53: Low ≤ Base ≤ High
A54: Salon manager: salary per FTE per year | B54: 48000 | C54: 48000 | D54: 48000 | E54: =CHOOSE(Dashboard!$B$4,B54,C54,D54) -> 48000 | F54: $
A55: Salon manager: headcount growth per year | B55: 0 | C55: 0 | D55: 0 | E55: =CHOOSE(Dashboard!$B$4,B55,C55,D55) -> 0 | F55: % | G55: Low ≤ Base ≤ High
A56: Salon manager: first month on payroll | B56: 1 | C56: 1 | D56: 1 | E56: =CHOOSE(Dashboard!$B$4,B56,C56,D56) -> 1 | F56: month #
A57: Receptionist: headcount (FTE) | B57: 1 | C57: 1 | D57: 1 | E57: =CHOOSE(Dashboard!$B$4,B57,C57,D57) -> 1 | F57: FTE | G57: Low ≤ Base ≤ High
A58: Receptionist: salary per FTE per year | B58: 33000 | C58: 33000 | D58: 33000 | E58: =CHOOSE(Dashboard!$B$4,B58,C58,D58) -> 33000 | F58: $
A59: Receptionist: headcount growth per year | B59: 0 | C59: 0 | D59: 0 | E59: =CHOOSE(Dashboard!$B$4,B59,C59,D59) -> 0 | F59: % | G59: Low ≤ Base ≤ High
A60: Receptionist: first month on payroll | B60: 1 | C60: 1 | D60: 1 | E60: =CHOOSE(Dashboard!$B$4,B60,C60,D60) -> 1 | F60: month #
A61: Shampoo & floor assistants: headcount (FTE) | B61: 1 | C61: 1 | D61: 1 | E61: =CHOOSE(Dashboard!$B$4,B61,C61,D61) -> 1 | F61: FTE | G61: Low ≤ Base ≤ High
A62: Shampoo & floor assistants: salary per FTE per year | B62: 29000 | C62: 29000 | D62: 29000 | E62: =CHOOSE(Dashboard!$B$4,B62,C62,D62) -> 29000 | F62: $
A63: Shampoo & floor assistants: headcount growth per year | B63: 0 | C63: 0 | D63: 0 | E63: =CHOOSE(Dashboard!$B$4,B63,C63,D63) -> 0 | F63: % | G63: Low ≤ Base ≤ High
A64: Shampoo & floor assistants: first month on payroll | B64: 1 | C64: 1 | D64: 1 | E64: =CHOOSE(Dashboard!$B$4,B64,C64,D64) -> 1 | F64: month #
A65: Payroll taxes & benefits, % of salary | B65: 0.12 | C65: 0.12 | D65: 0.12 | E65: =CHOOSE(Dashboard!$B$4,B65,C65,D65) -> 0.12 | F65: %
A66: Wage growth per year | B66: 0.03 | C66: 0.03 | D66: 0.03 | E66: =CHOOSE(Dashboard!$B$4,B66,C66,D66) -> 0.03 | F66: %
A68: Funding
A69: Equity raised at start | B69: 150000 | C69: 150000 | D69: 150000 | E69: =CHOOSE(Dashboard!$B$4,B69,C69,D69) -> 150000 | F69: $
A70: Loan drawn at start | B70: 70000 | C70: 70000 | D70: 70000 | E70: =CHOOSE(Dashboard!$B$4,B70,C70,D70) -> 70000 | F70: $
A71: Loan interest rate per year | B71: 0.08 | C71: 0.08 | D71: 0.08 | E71: =CHOOSE(Dashboard!$B$4,B71,C71,D71) -> 0.08 | F71: %
A72: Loan repayment term | B72: 5 | C72: 5 | D72: 5 | E72: =CHOOSE(Dashboard!$B$4,B72,C72,D72) -> 5 | F72: years
A74: Working capital
A75: Customer payment terms (receivable days) | B75: 2 | C75: 2 | D75: 2 | E75: =CHOOSE(Dashboard!$B$4,B75,C75,D75) -> 2 | F75: days
A76: Inventory held (days of COGS) | B76: 15 | C76: 15 | D76: 15 | E76: =CHOOSE(Dashboard!$B$4,B76,C76,D76) -> 15 | F76: days
A77: Supplier payment terms (payable days) | B77: 20 | C77: 20 | D77: 20 | E77: =CHOOSE(Dashboard!$B$4,B77,C77,D77) -> 20 | F77: days
A79: Tax & depreciation
A80: Depreciation period for capex | B80: 7 | C80: 7 | D80: 7 | E80: =CHOOSE(Dashboard!$B$4,B80,C80,D80) -> 7 | F80: years
A81: Income tax rate | B81: 0.21 | C81: 0.21 | D81: 0.21 | E81: =CHOOSE(Dashboard!$B$4,B81,C81,D81) -> 0.21 | F81: %
A83: Break-even & funding
A84: Minimum cash buffer to keep | B84: 60000 | C84: 60000 | D84: 60000 | E84: =CHOOSE(Dashboard!$B$4,B84,C84,D84) -> 60000 | F84: $ | G84: About 3 months of costs
A86: Valuation
A87: Discount rate (WACC) | B87: 0.3 | C87: 0.25 | D87: 0.2 | E87: =CHOOSE(Dashboard!$B$4,B87,C87,D87) -> 0.25 | F87: % | G87: Low ≥ Base ≥ High (lower is better)
A88: Terminal growth rate (perpetuity) | B88: 0.01 | C88: 0.02 | D88: 0.03 | E88: =CHOOSE(Dashboard!$B$4,B88,C88,D88) -> 0.02 | F88: % | G88: Low ≤ Base ≤ High
A89: Exit multiple (EV ÷ final-year EBITDA) | B89: 3 | C89: 4 | D89: 5 | E89: =CHOOSE(Dashboard!$B$4,B89,C89,D89) -> 4 | F89: x | G89: Low ≤ Base ≤ High
A90: Sensitivity table: WACC step | B90: 0.01 | C90: 0.01 | D90: 0.01 | E90: =CHOOSE(Dashboard!$B$4,B90,C90,D90) -> 0.01 | F90: %
A91: Sensitivity table: growth step | B91: 0.005 | C91: 0.005 | D91: 0.005 | E91: =CHOOSE(Dashboard!$B$4,B91,C91,D91) -> 0.005 | F91: %
A93: Legend: yellow cell with blue figure = input you can change · black = formula · green = link to another sheet · grey = active value (column E follows the scenario on the Dashboard).

Sheet P&L
A1: Annual profit & loss | H1: =HYPERLINK("#'Cover'!A1","◂ Contents") -> ◂ Contents
A2: Rolled up from the period detail (SUMIF on the year row; balances at year end).
A3: Year # | B3: 1 | C3: 2 | D3: 3 | E3: 4 | F3: 5
B4: Year 1 | C4: Year 2 | D4: Year 3 | E4: Year 4 | F4: Year 5
A5: Revenue | B5: =SUMIF(Monthly!$C$5:$BJ$5,B$3,Monthly!$C$21:$BJ$21) -> 479059.2 | C5: =SUMIF(Monthly!$C$5:$BJ$5,C$3,Monthly!$C$21:$BJ$21) -> 598797.5 | D5: =SUMIF(Monthly!$C$5:$BJ$5,D$3,Monthly!$C$21:$BJ$21) -> 725288.95 | E5: =SUMIF(Monthly!$C$5:$BJ$5,E$3,Monthly!$C$21:$BJ$21) -> 858830.97 | F5: =SUMIF(Monthly!$C$5:$BJ$5,F$3,Monthly!$C$21:$BJ$21) -> 942164.33
A6: Cost of sales | B6: =SUMIF(Monthly!$C$5:$BJ$5,B$3,Monthly!$C$28:$BJ$28) -> -270094.69 | C6: =SUMIF(Monthly!$C$5:$BJ$5,C$3,Monthly!$C$28:$BJ$28) -> -340019.21 | D6: =SUMIF(Monthly!$C$5:$BJ$5,D$3,Monthly!$C$28:$BJ$28) -> -413896.11 | E6: =SUMIF(Monthly!$C$5:$BJ$5,E$3,Monthly!$C$28:$BJ$28) -> -491899.61 | F6: =SUMIF(Monthly!$C$5:$BJ$5,F$3,Monthly!$C$28:$BJ$28) -> -540433.7
A7: Gross profit | B7: =SUMIF(Monthly!$C$5:$BJ$5,B$3,Monthly!$C$29:$BJ$29) -> 208964.51 | C7: =SUMIF(Monthly!$C$5:$BJ$5,C$3,Monthly!$C$29:$BJ$29) -> 258778.29 | D7: =SUMIF(Monthly!$C$5:$BJ$5,D$3,Monthly!$C$29:$BJ$29) -> 311392.84 | E7: =SUMIF(Monthly!$C$5:$BJ$5,E$3,Monthly!$C$29:$BJ$29) -> 366931.36 | F7: =SUMIF(Monthly!$C$5:$BJ$5,F$3,Monthly!$C$29:$BJ$29) -> 401730.62
A8: Gross margin | B8: =IF(B5=0,0,B7/B5) -> 0.43619767 | C8: =IF(C5=0,0,C7/C5) -> 0.43216328 | D8: =IF(D5=0,0,D7/D5) -> 0.42933625 | E8: =IF(E5=0,0,E7/E5) -> 0.42724514 | F8: =IF(F5=0,0,F7/F5) -> 0.42639125
A9: Staff payroll (manager, reception, assistants) | B9: =SUMIF(Monthly!$C$5:$BJ$5,B$3,Monthly!$C$32:$BJ$32) -> -96320 | C9: =SUMIF(Monthly!$C$5:$BJ$5,C$3,Monthly!$C$32:$BJ$32) -> -99209.6 | D9: =SUMIF(Monthly!$C$5:$BJ$5,D$3,Monthly!$C$32:$BJ$32) -> -102185.89 | E9: =SUMIF(Monthly!$C$5:$BJ$5,E$3,Monthly!$C$32:$BJ$32) -> -105251.46 | F9: =SUMIF(Monthly!$C$5:$BJ$5,F$3,Monthly!$C$32:$BJ$32) -> -108409.01
A10: Marketing | B10: =SUMIF(Monthly!$C$5:$BJ$5,B$3,Monthly!$C$33:$BJ$33) -> -30000 | C10: =SUMIF(Monthly!$C$5:$BJ$5,C$3,Monthly!$C$33:$BJ$33) -> -30000 | D10: =SUMIF(Monthly!$C$5:$BJ$5,D$3,Monthly!$C$33:$BJ$33) -> -30000 | E10: =SUMIF(Monthly!$C$5:$BJ$5,E$3,Monthly!$C$33:$BJ$33) -> -30000 | F10: =SUMIF(Monthly!$C$5:$BJ$5,F$3,Monthly!$C$33:$BJ$33) -> -30000
A11: Salon rent | B11: =SUMIF(Monthly!$C$5:$BJ$5,B$3,Monthly!$C$34:$BJ$34) -> -78000 | C11: =SUMIF(Monthly!$C$5:$BJ$5,C$3,Monthly!$C$34:$BJ$34) -> -78000 | D11: =SUMIF(Monthly!$C$5:$BJ$5,D$3,Monthly!$C$34:$BJ$34) -> -78000 | E11: =SUMIF(Monthly!$C$5:$BJ$5,E$3,Monthly!$C$34:$BJ$34) -> -78000 | F11: =SUMIF(Monthly!$C$5:$BJ$5,F$3,Monthly!$C$34:$BJ$34) -> -78000
A12: Utilities | B12: =SUMIF(Monthly!$C$5:$BJ$5,B$3,Monthly!$C$35:$BJ$35) -> -10800 | C12: =SUMIF(Monthly!$C$5:$BJ$5,C$3,Monthly!$C$35:$BJ$35) -> -10800 | D12: =SUMIF(Monthly!$C$5:$BJ$5,D$3,Monthly!$C$35:$BJ$35) -> -10800 | E12: =SUMIF(Monthly!$C$5:$BJ$5,E$3,Monthly!$C$35:$BJ$35) -> -10800 | F12: =SUMIF(Monthly!$C$5:$BJ$5,F$3,Monthly!$C$35:$BJ$35) -> -10800
A13: Booking software | B13: =SUMIF(Monthly!$C$5:$BJ$5,B$3,Monthly!$C$36:$BJ$36) -> -3000 | C13: =SUMIF(Monthly!$C$5:$BJ$5,C$3,Monthly!$C$36:$BJ$36) -> -3000 | D13: =SUMIF(Monthly!$C$5:$BJ$5,D$3,Monthly!$C$36:$BJ$36) -> -3000 | E13: =SUMIF(Monthly!$C$5:$BJ$5,E$3,Monthly!$C$36:$BJ$36) -> -3000 | F13: =SUMIF(Monthly!$C$5:$BJ$5,F$3,Monthly!$C$36:$BJ$36) -> -3000
A14: Insurance & licences | B14: =SUMIF(Monthly!$C$5:$BJ$5,B$3,Monthly!$C$37:$BJ$37) -> -7800 | C14: =SUMIF(Monthly!$C$5:$BJ$5,C$3,Monthly!$C$37:$BJ$37) -> -7800 | D14: =SUMIF(Monthly!$C$5:$BJ$5,D$3,Monthly!$C$37:$BJ$37) -> -7800 | E14: =SUMIF(Monthly!$C$5:$BJ$5,E$3,Monthly!$C$37:$BJ$37) -> -7800 | F14: =SUMIF(Monthly!$C$5:$BJ$5,F$3,Monthly!$C$37:$BJ$37) -> -7800
A15: Towels, laundry & cleaning | B15: =SUMIF(Monthly!$C$5:$BJ$5,B$3,Monthly!$C$38:$BJ$38) -> -5400 | C15: =SUMIF(Monthly!$C$5:$BJ$5,C$3,Monthly!$C$38:$BJ$38) -> -5400 | D15: =SUMIF(Monthly!$C$5:$BJ$5,D$3,Monthly!$C$38:$BJ$38) -> -5400 | E15: =SUMIF(Monthly!$C$5:$BJ$5,E$3,Monthly!$C$38:$BJ$38) -> -5400 | F15: =SUMIF(Monthly!$C$5:$BJ$5,F$3,Monthly!$C$38:$BJ$38) -> -5400
A16: Other G&A | B16: =SUMIF(Monthly!$C$5:$BJ$5,B$3,Monthly!$C$39:$BJ$39) -> -8400 | C16: =SUMIF(Monthly!$C$5:$BJ$5,C$3,Monthly!$C$39:$BJ$39) -> -8400 | D16: =SUMIF(Monthly!$C$5:$BJ$5,D$3,Monthly!$C$39:$BJ$39) -> -8400 | E16: =SUMIF(Monthly!$C$5:$BJ$5,E$3,Monthly!$C$39:$BJ$39) -> -8400 | F16: =SUMIF(Monthly!$C$5:$BJ$5,F$3,Monthly!$C$39:$BJ$39) -> -8400
A17: Total operating expenses | B17: =SUMIF(Monthly!$C$5:$BJ$5,B$3,Monthly!$C$40:$BJ$40) -> -239720 | C17: =SUMIF(Monthly!$C$5:$BJ$5,C$3,Monthly!$C$40:$BJ$40) -> -242609.6 | D17: =SUMIF(Monthly!$C$5:$BJ$5,D$3,Monthly!$C$40:$BJ$40) -> -245585.89 | E17: =SUMIF(Monthly!$C$5:$BJ$5,E$3,Monthly!$C$40:$BJ$40) -> -248651.46 | F17: =SUMIF(Monthly!$C$5:$BJ$5,F$3,Monthly!$C$40:$BJ$40) -> -251809.01
A18: EBITDA | B18: =SUMIF(Monthly!$C$5:$BJ$5,B$3,Monthly!$C$41:$BJ$41) -> -30755.494 | C18: =SUMIF(Monthly!$C$5:$BJ$5,C$3,Monthly!$C$41:$BJ$41) -> 16168.694 | D18: =SUMIF(Monthly!$C$5:$BJ$5,D$3,Monthly!$C$41:$BJ$41) -> 65806.954 | E18: =SUMIF(Monthly!$C$5:$BJ$5,E$3,Monthly!$C$41:$BJ$41) -> 118279.9 | F18: =SUMIF(Monthly!$C$5:$BJ$5,F$3,Monthly!$C$41:$BJ$41) -> 149921.61
A19: EBITDA margin | B19: =IF(B5=0,0,B18/B5) -> -0.064199778 | C19: =IF(C5=0,0,C18/C5) -> 0.02700194 | D19: =IF(D5=0,0,D18/D5) -> 0.090732051 | E19: =IF(E5=0,0,E18/E5) -> 0.13772198 | F19: =IF(F5=0,0,F18/F5) -> 0.1591247
A20: Depreciation | B20: =SUMIF(Monthly!$C$5:$BJ$5,B$3,Monthly!$C$55:$BJ$55) -> -18200 | C20: =SUMIF(Monthly!$C$5:$BJ$5,C$3,Monthly!$C$55:$BJ$55) -> -18200 | D20: =SUMIF(Monthly!$C$5:$BJ$5,D$3,Monthly!$C$55:$BJ$55) -> -18200 | E20: =SUMIF(Monthly!$C$5:$BJ$5,E$3,Monthly!$C$55:$BJ$55) -> -18200 | F20: =SUMIF(Monthly!$C$5:$BJ$5,F$3,Monthly!$C$55:$BJ$55) -> -18200
A21: EBIT | B21: =SUMIF(Monthly!$C$5:$BJ$5,B$3,Monthly!$C$44:$BJ$44) -> -48955.494 | C21: =SUMIF(Monthly!$C$5:$BJ$5,C$3,Monthly!$C$44:$BJ$44) -> -2031.3057 | D21: =SUMIF(Monthly!$C$5:$BJ$5,D$3,Monthly!$C$44:$BJ$44) -> 47606.954 | E21: =SUMIF(Monthly!$C$5:$BJ$5,E$3,Monthly!$C$44:$BJ$44) -> 100079.9 | F21: =SUMIF(Monthly!$C$5:$BJ$5,F$3,Monthly!$C$44:$BJ$44) -> 131721.61
A22: Interest | B22: =SUMIF(Monthly!$C$5:$BJ$5,B$3,Monthly!$C$45:$BJ$45) -> -5129.4444 | C22: =SUMIF(Monthly!$C$5:$BJ$5,C$3,Monthly!$C$45:$BJ$45) -> -4013.3333 | D22: =SUMIF(Monthly!$C$5:$BJ$5,D$3,Monthly!$C$45:$BJ$45) -> -2893.3333 | E22: =SUMIF(Monthly!$C$5:$BJ$5,E$3,Monthly!$C$45:$BJ$45) -> -1773.3333 | F22: =SUMIF(Monthly!$C$5:$BJ$5,F$3,Monthly!$C$45:$BJ$45) -> -653.33333
A23: Pre-tax income | B23: =SUMIF(Monthly!$C$5:$BJ$5,B$3,Monthly!$C$46:$BJ$46) -> -54084.939 | C23: =SUMIF(Monthly!$C$5:$BJ$5,C$3,Monthly!$C$46:$BJ$46) -> -6044.6391 | D23: =SUMIF(Monthly!$C$5:$BJ$5,D$3,Monthly!$C$46:$BJ$46) -> 44713.621 | E23: =SUMIF(Monthly!$C$5:$BJ$5,E$3,Monthly!$C$46:$BJ$46) -> 98306.565 | F23: =SUMIF(Monthly!$C$5:$BJ$5,F$3,Monthly!$C$46:$BJ$46) -> 131068.28
A24: Income tax | B24: =SUMIF(Monthly!$C$5:$BJ$5,B$3,Monthly!$C$49:$BJ$49) -> 0 | C24: =SUMIF(Monthly!$C$5:$BJ$5,C$3,Monthly!$C$49:$BJ$49) -> 0 | D24: =SUMIF(Monthly!$C$5:$BJ$5,D$3,Monthly!$C$49:$BJ$49) -> 0 | E24: =SUMIF(Monthly!$C$5:$BJ$5,E$3,Monthly!$C$49:$BJ$49) -> -17407.028 | F24: =SUMIF(Monthly!$C$5:$BJ$5,F$3,Monthly!$C$49:$BJ$49) -> -27524.339
A25: Net income | B25: =SUMIF(Monthly!$C$5:$BJ$5,B$3,Monthly!$C$50:$BJ$50) -> -54084.939 | C25: =SUMIF(Monthly!$C$5:$BJ$5,C$3,Monthly!$C$50:$BJ$50) -> -6044.6391 | D25: =SUMIF(Monthly!$C$5:$BJ$5,D$3,Monthly!$C$50:$BJ$50) -> 44713.621 | E25: =SUMIF(Monthly!$C$5:$BJ$5,E$3,Monthly!$C$50:$BJ$50) -> 80899.537 | F25: =SUMIF(Monthly!$C$5:$BJ$5,F$3,Monthly!$C$50:$BJ$50) -> 103543.94
A26: Net margin | B26: =IF(B5=0,0,B25/B5) -> -0.11289824 | C26: =IF(C5=0,0,C25/C5) -> -0.01009463 | D26: =IF(D5=0,0,D25/D5) -> 0.061649389 | E26: =IF(E5=0,0,E25/E5) -> 0.094197275 | F26: =IF(F5=0,0,F25/F5) -> 0.10990009

Sheet Cash Flow
A1: Annual cash flow statement | H1: =HYPERLINK("#'Cover'!A1","◂ Contents") -> ◂ Contents
A2: Rolled up from the period detail (SUMIF on the year row; balances at year end).
A3: Year # | B3: 1 | C3: 2 | D3: 3 | E3: 4 | F3: 5
B4: Year 1 | C4: Year 2 | D4: Year 3 | E4: Year 4 | F4: Year 5
A5: Net income | B5: =SUMIF(Monthly!$C$5:$BJ$5,B$3,Monthly!$C$50:$BJ$50) -> -54084.939 | C5: =SUMIF(Monthly!$C$5:$BJ$5,C$3,Monthly!$C$50:$BJ$50) -> -6044.6391 | D5: =SUMIF(Monthly!$C$5:$BJ$5,D$3,Monthly!$C$50:$BJ$50) -> 44713.621 | E5: =SUMIF(Monthly!$C$5:$BJ$5,E$3,Monthly!$C$50:$BJ$50) -> 80899.537 | F5: =SUMIF(Monthly!$C$5:$BJ$5,F$3,Monthly!$C$50:$BJ$50) -> 103543.94
A6: Add back depreciation | B6: =-SUMIF(Monthly!$C$5:$BJ$5,B$3,Monthly!$C$55:$BJ$55) -> 18200 | C6: =-SUMIF(Monthly!$C$5:$BJ$5,C$3,Monthly!$C$55:$BJ$55) -> 18200 | D6: =-SUMIF(Monthly!$C$5:$BJ$5,D$3,Monthly!$C$55:$BJ$55) -> 18200 | E6: =-SUMIF(Monthly!$C$5:$BJ$5,E$3,Monthly!$C$55:$BJ$55) -> 18200 | F6: =-SUMIF(Monthly!$C$5:$BJ$5,F$3,Monthly!$C$55:$BJ$55) -> 18200
A7: (Increase) / decrease in receivables | B7: =SUMIF(Monthly!$C$5:$BJ$5,B$3,Monthly!$C$69:$BJ$69) -> -2661.44 | C7: =SUMIF(Monthly!$C$5:$BJ$5,C$3,Monthly!$C$69:$BJ$69) -> -665.2128 | D7: =SUMIF(Monthly!$C$5:$BJ$5,D$3,Monthly!$C$69:$BJ$69) -> -702.73027 | E7: =SUMIF(Monthly!$C$5:$BJ$5,E$3,Monthly!$C$69:$BJ$69) -> -741.9001 | F7: =SUMIF(Monthly!$C$5:$BJ$5,F$3,Monthly!$C$69:$BJ$69) -> -462.96308
A8: (Increase) / decrease in inventory | B8: =SUMIF(Monthly!$C$5:$BJ$5,B$3,Monthly!$C$70:$BJ$70) -> -11253.946 | C8: =SUMIF(Monthly!$C$5:$BJ$5,C$3,Monthly!$C$70:$BJ$70) -> -2913.5215 | D8: =SUMIF(Monthly!$C$5:$BJ$5,D$3,Monthly!$C$70:$BJ$70) -> -3078.2042 | E8: =SUMIF(Monthly!$C$5:$BJ$5,E$3,Monthly!$C$70:$BJ$70) -> -3250.1457 | F8: =SUMIF(Monthly!$C$5:$BJ$5,F$3,Monthly!$C$70:$BJ$70) -> -2022.2539
A9: Increase / (decrease) in payables | B9: =SUMIF(Monthly!$C$5:$BJ$5,B$3,Monthly!$C$71:$BJ$71) -> 15005.261 | C9: =SUMIF(Monthly!$C$5:$BJ$5,C$3,Monthly!$C$71:$BJ$71) -> 3884.6953 | D9: =SUMIF(Monthly!$C$5:$BJ$5,D$3,Monthly!$C$71:$BJ$71) -> 4104.2723 | E9: =SUMIF(Monthly!$C$5:$BJ$5,E$3,Monthly!$C$71:$BJ$71) -> 4333.5277 | F9: =SUMIF(Monthly!$C$5:$BJ$5,F$3,Monthly!$C$71:$BJ$71) -> 2696.3386
A10: Operating cash flow | B10: =SUMIF(Monthly!$C$5:$BJ$5,B$3,Monthly!$C$74:$BJ$74) -> -34795.064 | C10: =SUMIF(Monthly!$C$5:$BJ$5,C$3,Monthly!$C$74:$BJ$74) -> 12461.322 | D10: =SUMIF(Monthly!$C$5:$BJ$5,D$3,Monthly!$C$74:$BJ$74) -> 63236.959 | E10: =SUMIF(Monthly!$C$5:$BJ$5,E$3,Monthly!$C$74:$BJ$74) -> 99441.019 | F10: =SUMIF(Monthly!$C$5:$BJ$5,F$3,Monthly!$C$74:$BJ$74) -> 121955.06
A11: Capital spending | B11: =SUMIF(Monthly!$C$5:$BJ$5,B$3,Monthly!$C$75:$BJ$75) -> -127400 | C11: =SUMIF(Monthly!$C$5:$BJ$5,C$3,Monthly!$C$75:$BJ$75) -> 0 | D11: =SUMIF(Monthly!$C$5:$BJ$5,D$3,Monthly!$C$75:$BJ$75) -> 0 | E11: =SUMIF(Monthly!$C$5:$BJ$5,E$3,Monthly!$C$75:$BJ$75) -> 0 | F11: =SUMIF(Monthly!$C$5:$BJ$5,F$3,Monthly!$C$75:$BJ$75) -> 0
A12: Equity raised | B12: =SUMIF(Monthly!$C$5:$BJ$5,B$3,Monthly!$C$76:$BJ$76) -> 150000 | C12: =SUMIF(Monthly!$C$5:$BJ$5,C$3,Monthly!$C$76:$BJ$76) -> 0 | D12: =SUMIF(Monthly!$C$5:$BJ$5,D$3,Monthly!$C$76:$BJ$76) -> 0 | E12: =SUMIF(Monthly!$C$5:$BJ$5,E$3,Monthly!$C$76:$BJ$76) -> 0 | F12: =SUMIF(Monthly!$C$5:$BJ$5,F$3,Monthly!$C$76:$BJ$76) -> 0
A13: Loan drawdown | B13: =SUMIF(Monthly!$C$5:$BJ$5,B$3,Monthly!$C$61:$BJ$61) -> 70000 | C13: =SUMIF(Monthly!$C$5:$BJ$5,C$3,Monthly!$C$61:$BJ$61) -> 0 | D13: =SUMIF(Monthly!$C$5:$BJ$5,D$3,Monthly!$C$61:$BJ$61) -> 0 | E13: =SUMIF(Monthly!$C$5:$BJ$5,E$3,Monthly!$C$61:$BJ$61) -> 0 | F13: =SUMIF(Monthly!$C$5:$BJ$5,F$3,Monthly!$C$61:$BJ$61) -> 0
A14: Loan repayment | B14: =SUMIF(Monthly!$C$5:$BJ$5,B$3,Monthly!$C$62:$BJ$62) -> -12833.333 | C14: =SUMIF(Monthly!$C$5:$BJ$5,C$3,Monthly!$C$62:$BJ$62) -> -14000 | D14: =SUMIF(Monthly!$C$5:$BJ$5,D$3,Monthly!$C$62:$BJ$62) -> -14000 | E14: =SUMIF(Monthly!$C$5:$BJ$5,E$3,Monthly!$C$62:$BJ$62) -> -14000 | F14: =SUMIF(Monthly!$C$5:$BJ$5,F$3,Monthly!$C$62:$BJ$62) -> -14000
A15: Financing cash flow | B15: =SUMIF(Monthly!$C$5:$BJ$5,B$3,Monthly!$C$77:$BJ$77) -> 207166.67 | C15: =SUMIF(Monthly!$C$5:$BJ$5,C$3,Monthly!$C$77:$BJ$77) -> -14000 | D15: =SUMIF(Monthly!$C$5:$BJ$5,D$3,Monthly!$C$77:$BJ$77) -> -14000 | E15: =SUMIF(Monthly!$C$5:$BJ$5,E$3,Monthly!$C$77:$BJ$77) -> -14000 | F15: =SUMIF(Monthly!$C$5:$BJ$5,F$3,Monthly!$C$77:$BJ$77) -> -14000
A16: Net change in cash | B16: =SUMIF(Monthly!$C$5:$BJ$5,B$3,Monthly!$C$78:$BJ$78) -> 44971.603 | C16: =SUMIF(Monthly!$C$5:$BJ$5,C$3,Monthly!$C$78:$BJ$78) -> -1538.678 | D16: =SUMIF(Monthly!$C$5:$BJ$5,D$3,Monthly!$C$78:$BJ$78) -> 49236.959 | E16: =SUMIF(Monthly!$C$5:$BJ$5,E$3,Monthly!$C$78:$BJ$78) -> 85441.019 | F16: =SUMIF(Monthly!$C$5:$BJ$5,F$3,Monthly!$C$78:$BJ$78) -> 107955.06
A17: Opening cash | B17: =INDEX(Monthly!$C$79:$BJ$79,(B$3-1)*12+1) -> 0 | C17: =INDEX(Monthly!$C$79:$BJ$79,(C$3-1)*12+1) -> 44971.603 | D17: =INDEX(Monthly!$C$79:$BJ$79,(D$3-1)*12+1) -> 43432.925 | E17: =INDEX(Monthly!$C$79:$BJ$79,(E$3-1)*12+1) -> 92669.884 | F17: =INDEX(Monthly!$C$79:$BJ$79,(F$3-1)*12+1) -> 178110.9
A18: Closing cash | B18: =INDEX(Monthly!$C$80:$BJ$80,B$3*12) -> 44971.603 | C18: =INDEX(Monthly!$C$80:$BJ$80,C$3*12) -> 43432.925 | D18: =INDEX(Monthly!$C$80:$BJ$80,D$3*12) -> 92669.884 | E18: =INDEX(Monthly!$C$80:$BJ$80,E$3*12) -> 178110.9 | F18: =INDEX(Monthly!$C$80:$BJ$80,F$3*12) -> 286065.97

Sheet Balance Sheet
A1: Balance sheet at year end | H1: =HYPERLINK("#'Cover'!A1","◂ Contents") -> ◂ Contents
A2: Rolled up from the period detail (SUMIF on the year row; balances at year end).
A3: Year # | B3: 1 | C3: 2 | D3: 3 | E3: 4 | F3: 5
B4: Year 1 | C4: Year 2 | D4: Year 3 | E4: Year 4 | F4: Year 5
A5: Cash | B5: =INDEX(Monthly!$C$80:$BJ$80,B$3*12) -> 44971.603 | C5: =INDEX(Monthly!$C$80:$BJ$80,C$3*12) -> 43432.925 | D5: =INDEX(Monthly!$C$80:$BJ$80,D$3*12) -> 92669.884 | E5: =INDEX(Monthly!$C$80:$BJ$80,E$3*12) -> 178110.9 | F5: =INDEX(Monthly!$C$80:$BJ$80,F$3*12) -> 286065.97
A6: Accounts receivable | B6: =INDEX(Monthly!$C$66:$BJ$66,B$3*12) -> 2661.44 | C6: =INDEX(Monthly!$C$66:$BJ$66,C$3*12) -> 3326.6528 | D6: =INDEX(Monthly!$C$66:$BJ$66,D$3*12) -> 4029.3831 | E6: =INDEX(Monthly!$C$66:$BJ$66,E$3*12) -> 4771.2832 | F6: =INDEX(Monthly!$C$66:$BJ$66,F$3*12) -> 5234.2463
A7: Inventory | B7: =INDEX(Monthly!$C$67:$BJ$67,B$3*12) -> 11253.946 | C7: =INDEX(Monthly!$C$67:$BJ$67,C$3*12) -> 14167.467 | D7: =INDEX(Monthly!$C$67:$BJ$67,D$3*12) -> 17245.671 | E7: =INDEX(Monthly!$C$67:$BJ$67,E$3*12) -> 20495.817 | F7: =INDEX(Monthly!$C$67:$BJ$67,F$3*12) -> 22518.071
A8: Net fixed assets | B8: =INDEX(Monthly!$C$57:$BJ$57,B$3*12) -> 109200 | C8: =INDEX(Monthly!$C$57:$BJ$57,C$3*12) -> 91000 | D8: =INDEX(Monthly!$C$57:$BJ$57,D$3*12) -> 72800 | E8: =INDEX(Monthly!$C$57:$BJ$57,E$3*12) -> 54600 | F8: =INDEX(Monthly!$C$57:$BJ$57,F$3*12) -> 36400
A9: Total assets | B9: =INDEX(Monthly!$C$94:$BJ$94,B$3*12) -> 168086.99 | C9: =INDEX(Monthly!$C$94:$BJ$94,C$3*12) -> 151927.04 | D9: =INDEX(Monthly!$C$94:$BJ$94,D$3*12) -> 186744.94 | E9: =INDEX(Monthly!$C$94:$BJ$94,E$3*12) -> 257978 | F9: =INDEX(Monthly!$C$94:$BJ$94,F$3*12) -> 350218.28
A10: Accounts payable | B10: =INDEX(Monthly!$C$68:$BJ$68,B$3*12) -> 15005.261 | C10: =INDEX(Monthly!$C$68:$BJ$68,C$3*12) -> 18889.956 | D10: =INDEX(Monthly!$C$68:$BJ$68,D$3*12) -> 22994.228 | E10: =INDEX(Monthly!$C$68:$BJ$68,E$3*12) -> 27327.756 | F10: =INDEX(Monthly!$C$68:$BJ$68,F$3*12) -> 30024.095
A11: Loan | B11: =INDEX(Monthly!$C$63:$BJ$63,B$3*12) -> 57166.667 | C11: =INDEX(Monthly!$C$63:$BJ$63,C$3*12) -> 43166.667 | D11: =INDEX(Monthly!$C$63:$BJ$63,D$3*12) -> 29166.667 | E11: =INDEX(Monthly!$C$63:$BJ$63,E$3*12) -> 15166.667 | F11: =INDEX(Monthly!$C$63:$BJ$63,F$3*12) -> 1166.6667
A12: Total liabilities | B12: =INDEX(Monthly!$C$95:$BJ$95,B$3*12) -> 72171.927 | C12: =INDEX(Monthly!$C$95:$BJ$95,C$3*12) -> 62056.623 | D12: =INDEX(Monthly!$C$95:$BJ$95,D$3*12) -> 52160.895 | E12: =INDEX(Monthly!$C$95:$BJ$95,E$3*12) -> 42494.423 | F12: =INDEX(Monthly!$C$95:$BJ$95,F$3*12) -> 31190.761
A13: Paid-in capital | B13: =INDEX(Monthly!$C$92:$BJ$92,B$3*12) -> 150000 | C13: =INDEX(Monthly!$C$92:$BJ$92,C$3*12) -> 150000 | D13: =INDEX(Monthly!$C$92:$BJ$92,D$3*12) -> 150000 | E13: =INDEX(Monthly!$C$92:$BJ$92,E$3*12) -> 150000 | F13: =INDEX(Monthly!$C$92:$BJ$92,F$3*12) -> 150000
A14: Retained earnings | B14: =INDEX(Monthly!$C$93:$BJ$93,B$3*12) -> -54084.939 | C14: =INDEX(Monthly!$C$93:$BJ$93,C$3*12) -> -60129.578 | D14: =INDEX(Monthly!$C$93:$BJ$93,D$3*12) -> -15415.957 | E14: =INDEX(Monthly!$C$93:$BJ$93,E$3*12) -> 65483.58 | F14: =INDEX(Monthly!$C$93:$BJ$93,F$3*12) -> 169027.52
A15: Total equity | B15: =INDEX(Monthly!$C$96:$BJ$96,B$3*12) -> 95915.061 | C15: =INDEX(Monthly!$C$96:$BJ$96,C$3*12) -> 89870.422 | D15: =INDEX(Monthly!$C$96:$BJ$96,D$3*12) -> 134584.04 | E15: =INDEX(Monthly!$C$96:$BJ$96,E$3*12) -> 215483.58 | F15: =INDEX(Monthly!$C$96:$BJ$96,F$3*12) -> 319027.52
A16: Total liabilities & equity | B16: =INDEX(Monthly!$C$97:$BJ$97,B$3*12) -> 168086.99 | C16: =INDEX(Monthly!$C$97:$BJ$97,C$3*12) -> 151927.04 | D16: =INDEX(Monthly!$C$97:$BJ$97,D$3*12) -> 186744.94 | E16: =INDEX(Monthly!$C$97:$BJ$97,E$3*12) -> 257978 | F16: =INDEX(Monthly!$C$97:$BJ$97,F$3*12) -> 350218.28
A17: Check: assets − liabilities − equity (must be 0) | B17: =INDEX(Monthly!$C$98:$BJ$98,B$3*12) -> 0 | C17: =INDEX(Monthly!$C$98:$BJ$98,C$3*12) -> 0 | D17: =INDEX(Monthly!$C$98:$BJ$98,D$3*12) -> 0 | E17: =INDEX(Monthly!$C$98:$BJ$98,E$3*12) -> 0 | F17: =INDEX(Monthly!$C$98:$BJ$98,F$3*12) -> 0

Sheet Monthly
A1: Monthly projection | D1: =HYPERLINK("#'Cover'!A1","◂ Contents") -> ◂ Contents
A2: $ unless stated; costs shown as negatives. Every period uses the same formula.
A3: Month | C3: M1 | D3: M2 | E3: M3 | F3: M4 | G3: M5 | H3: M6 | I3: M7 | J3: M8 | K3: M9 | L3: M10 | M3: M11 | N3: M12 | O3: M13 | P3: M14 | Q3: M15 | R3: M16 | S3: M17 | T3: M18 | U3: M19 | V3: M20 | W3: M21 | X3: M22 | Y3: M23 | Z3: M24 | AA3: M25 | AB3: M26 | AC3: M27 | AD3: M28 | AE3: M29 | AF3: M30 | AG3: M31 | AH3: M32 | AI3: M33 | AJ3: M34 | AK3: M35 | AL3: M36 | AM3: M37 | AN3: M38 | AO3: M39 | AP3: M40 | AQ3: M41 | AR3: M42 | AS3: M43 | AT3: M44 | AU3: M45 | AV3: M46 | AW3: M47 | AX3: M48 | AY3: M49 | AZ3: M50 | BA3: M51 | BB3: M52 | BC3: M53 | BD3: M54 | BE3: M55 | BF3: M56 | BG3: M57 | BH3: M58 | BI3: M59 | BJ3: M60
A4: Period # | C4: 1 | D4: 2 | E4: 3 | F4: 4 | G4: 5 | H4: 6 | I4: 7 | J4: 8 | K4: 9 | L4: 10 | M4: 11 | N4: 12 | O4: 13 | P4: 14 | Q4: 15 | R4: 16 | S4: 17 | T4: 18 | U4: 19 | V4: 20 | W4: 21 | X4: 22 | Y4: 23 | Z4: 24 | AA4: 25 | AB4: 26 | AC4: 27 | AD4: 28 | AE4: 29 | AF4: 30 | AG4: 31 | AH4: 32 | AI4: 33 | AJ4: 34 | AK4: 35 | AL4: 36 | AM4: 37 | AN4: 38 | AO4: 39 | AP4: 40 | AQ4: 41 | AR4: 42 | AS4: 43 | AT4: 44 | AU4: 45 | AV4: 46 | AW4: 47 | AX4: 48 | AY4: 49 | AZ4: 50 | BA4: 51 | BB4: 52 | BC4: 53 | BD4: 54 | BE4: 55 | BF4: 56 | BG4: 57 | BH4: 58 | BI4: 59 | BJ4: 60
A5: Year # | C5: =ROUNDUP(C4*1/12,0) -> 1 | D5: =ROUNDUP(D4*1/12,0) -> 1 | E5: =ROUNDUP(E4*1/12,0) -> 1 | F5: =ROUNDUP(F4*1/12,0) -> 1 | G5: =ROUNDUP(G4*1/12,0) -> 1 | H5: =ROUNDUP(H4*1/12,0) -> 1 | I5: =ROUNDUP(I4*1/12,0) -> 1 | J5: =ROUNDUP(J4*1/12,0) -> 1 | ... BJ5: =ROUNDUP(BJ4*1/12,0) -> 5
A7: Chairs & booking
A8: Styling chairs | C8: =Inputs!$E$7+Inputs!$E$8*(C$5-1) -> 8 | D8: =Inputs!$E$7+Inputs!$E$8*(D$5-1) -> 8 | E8: =Inputs!$E$7+Inputs!$E$8*(E$5-1) -> 8 | F8: =Inputs!$E$7+Inputs!$E$8*(F$5-1) -> 8 | G8: =Inputs!$E$7+Inputs!$E$8*(G$5-1) -> 8 | H8: =Inputs!$E$7+Inputs!$E$8*(H$5-1) -> 8 | I8: =Inputs!$E$7+Inputs!$E$8*(I$5-1) -> 8 | J8: =Inputs!$E$7+Inputs!$E$8*(J$5-1) -> 8 | ... BJ8: =Inputs!$E$7+Inputs!$E$8*(BJ$5-1) -> 8
A9: Chairs rented to independent stylists | C9: =C8*Inputs!$E$25 -> 2 | D9: =D8*Inputs!$E$25 -> 2 | E9: =E8*Inputs!$E$25 -> 2 | F9: =F8*Inputs!$E$25 -> 2 | G9: =G8*Inputs!$E$25 -> 2 | H9: =H8*Inputs!$E$25 -> 2 | I9: =I8*Inputs!$E$25 -> 2 | J9: =J8*Inputs!$E$25 -> 2 | ... BJ9: =BJ8*Inputs!$E$25 -> 2
A10: Chairs worked by employed stylists | C10: =C8-C9 -> 6 | D10: =D8-D9 -> 6 | E10: =E8-E9 -> 6 | F10: =F8-F9 -> 6 | G10: =G8-G9 -> 6 | H10: =H8-H9 -> 6 | I10: =I8-I9 -> 6 | J10: =J8-J9 -> 6 | ... BJ10: =BJ8-BJ9 -> 6
A11: Bookable chair hours (employed chairs) | C11: =C10*Inputs!$E$9*Inputs!$E$10*1 -> 1152 | D11: =D10*Inputs!$E$9*Inputs!$E$10*1 -> 1152 | E11: =E10*Inputs!$E$9*Inputs!$E$10*1 -> 1152 | F11: =F10*Inputs!$E$9*Inputs!$E$10*1 -> 1152 | G11: =G10*Inputs!$E$9*Inputs!$E$10*1 -> 1152 | H11: =H10*Inputs!$E$9*Inputs!$E$10*1 -> 1152 | I11: =I10*Inputs!$E$9*Inputs!$E$10*1 -> 1152 | J11: =J10*Inputs!$E$9*Inputs!$E$10*1 -> 1152 | ... BJ11: =BJ10*Inputs!$E$9*Inputs!$E$10*1 -> 1152
A12: Chair utilisation | C12: =MIN(Inputs!$E$13,Inputs!$E$11+Inputs!$E$12*(C$5-1)) -> 0.45 | D12: =MIN(Inputs!$E$13,Inputs!$E$11+Inputs!$E$12*(D$5-1)) -> 0.45 | E12: =MIN(Inputs!$E$13,Inputs!$E$11+Inputs!$E$12*(E$5-1)) -> 0.45 | F12: =MIN(Inputs!$E$13,Inputs!$E$11+Inputs!$E$12*(F$5-1)) -> 0.45 | G12: =MIN(Inputs!$E$13,Inputs!$E$11+Inputs!$E$12*(G$5-1)) -> 0.45 | H12: =MIN(Inputs!$E$13,Inputs!$E$11+Inputs!$E$12*(H$5-1)) -> 0.45 | I12: =MIN(Inputs!$E$13,Inputs!$E$11+Inputs!$E$12*(I$5-1)) -> 0.45 | J12: =MIN(Inputs!$E$13,Inputs!$E$11+Inputs!$E$12*(J$5-1)) -> 0.45 | ... BJ12: =MIN(Inputs!$E$13,Inputs!$E$11+Inputs!$E$12*(BJ$5-1)) -> 0.8
A13: Booked chair hours | C13: =C11*C12 -> 518.4 | D13: =D11*D12 -> 518.4 | E13: =E11*E12 -> 518.4 | F13: =F11*F12 -> 518.4 | G13: =G11*G12 -> 518.4 | H13: =H11*H12 -> 518.4 | I13: =I11*I12 -> 518.4 | J13: =J11*J12 -> 518.4 | ... BJ13: =BJ11*BJ12 -> 921.6
A14: Services performed | C14: =C13*Inputs!$E$14 -> 518.4 | D14: =D13*Inputs!$E$14 -> 518.4 | E14: =E13*Inputs!$E$14 -> 518.4 | F14: =F13*Inputs!$E$14 -> 518.4 | G14: =G13*Inputs!$E$14 -> 518.4 | H14: =H13*Inputs!$E$14 -> 518.4 | I14: =I13*Inputs!$E$14 -> 518.4 | J14: =J13*Inputs!$E$14 -> 518.4 | ... BJ14: =BJ13*Inputs!$E$14 -> 921.6
A16: Revenue
A17: Average service price | C17: =Inputs!$E$17*(1+Inputs!$E$18)^(C$5-1) -> 68 | D17: =Inputs!$E$17*(1+Inputs!$E$18)^(D$5-1) -> 68 | E17: =Inputs!$E$17*(1+Inputs!$E$18)^(E$5-1) -> 68 | F17: =Inputs!$E$17*(1+Inputs!$E$18)^(F$5-1) -> 68 | G17: =Inputs!$E$17*(1+Inputs!$E$18)^(G$5-1) -> 68 | H17: =Inputs!$E$17*(1+Inputs!$E$18)^(H$5-1) -> 68 | I17: =Inputs!$E$17*(1+Inputs!$E$18)^(I$5-1) -> 68 | J17: =Inputs!$E$17*(1+Inputs!$E$18)^(J$5-1) -> 68 | ... BJ17: =Inputs!$E$17*(1+Inputs!$E$18)^(BJ$5-1) -> 76.534599
A18: Service revenue | C18: =C14*C17 -> 35251.2 | D18: =D14*D17 -> 35251.2 | E18: =E14*E17 -> 35251.2 | F18: =F14*F17 -> 35251.2 | G18: =G14*G17 -> 35251.2 | H18: =H14*H17 -> 35251.2 | I18: =I14*I17 -> 35251.2 | J18: =J14*J17 -> 35251.2 | ... BJ18: =BJ14*BJ17 -> 70534.287
A19: Retail product sales | C19: =C14*Inputs!$E$21*Inputs!$E$22*(1+Inputs!$E$18)^(C$5-1) -> 3110.4 | D19: =D14*Inputs!$E$21*Inputs!$E$22*(1+Inputs!$E$18)^(D$5-1) -> 3110.4 | E19: =E14*Inputs!$E$21*Inputs!$E$22*(1+Inputs!$E$18)^(E$5-1) -> 3110.4 | F19: =F14*Inputs!$E$21*Inputs!$E$22*(1+Inputs!$E$18)^(F$5-1) -> 3110.4 | G19: =G14*Inputs!$E$21*Inputs!$E$22*(1+Inputs!$E$18)^(G$5-1) -> 3110.4 | H19: =H14*Inputs!$E$21*Inputs!$E$22*(1+Inputs!$E$18)^(H$5-1) -> 3110.4 | I19: =I14*Inputs!$E$21*Inputs!$E$22*(1+Inputs!$E$18)^(I$5-1) -> 3110.4 | J19: =J14*Inputs!$E$21*Inputs!$E$22*(1+Inputs!$E$18)^(J$5-1) -> 3110.4 | ... BJ19: =BJ14*Inputs!$E$21*Inputs!$E$22*(1+Inputs!$E$18)^(BJ$5-1) -> 6223.6135
A20: Chair rent income | C20: =C9*Inputs!$E$26*52/12*1*Inputs!$E$27*(1+Inputs!$E$18)^(C$5-1) -> 1560 | D20: =D9*Inputs!$E$26*52/12*1*Inputs!$E$27*(1+Inputs!$E$18)^(D$5-1) -> 1560 | E20: =E9*Inputs!$E$26*52/12*1*Inputs!$E$27*(1+Inputs!$E$18)^(E$5-1) -> 1560 | F20: =F9*Inputs!$E$26*52/12*1*Inputs!$E$27*(1+Inputs!$E$18)^(F$5-1) -> 1560 | G20: =G9*Inputs!$E$26*52/12*1*Inputs!$E$27*(1+Inputs!$E$18)^(G$5-1) -> 1560 | H20: =H9*Inputs!$E$26*52/12*1*Inputs!$E$27*(1+Inputs!$E$18)^(H$5-1) -> 1560 | I20: =I9*Inputs!$E$26*52/12*1*Inputs!$E$27*(1+Inputs!$E$18)^(I$5-1) -> 1560 | J20: =J9*Inputs!$E$26*52/12*1*Inputs!$E$27*(1+Inputs!$E$18)^(J$5-1) -> 1560 | ... BJ20: =BJ9*Inputs!$E$26*52/12*1*Inputs!$E$27*(1+Inputs!$E$18)^(BJ$5-1) -> 1755.7937
A21: Revenue | C21: =C18+C19+C20 -> 39921.6 | D21: =D18+D19+D20 -> 39921.6 | E21: =E18+E19+E20 -> 39921.6 | F21: =F18+F19+F20 -> 39921.6 | G21: =G18+G19+G20 -> 39921.6 | H21: =H18+H19+H20 -> 39921.6 | I21: =I18+I19+I20 -> 39921.6 | J21: =J18+J19+J20 -> 39921.6 | ... BJ21: =BJ18+BJ19+BJ20 -> 78513.694
A23: Cost of sales
A24: Stylist commission (with payroll taxes) | C24: =-C18*Inputs!$E$30*(1+Inputs!$E$65) -> -17766.605 | D24: =-D18*Inputs!$E$30*(1+Inputs!$E$65) -> -17766.605 | E24: =-E18*Inputs!$E$30*(1+Inputs!$E$65) -> -17766.605 | F24: =-F18*Inputs!$E$30*(1+Inputs!$E$65) -> -17766.605 | G24: =-G18*Inputs!$E$30*(1+Inputs!$E$65) -> -17766.605 | H24: =-H18*Inputs!$E$30*(1+Inputs!$E$65) -> -17766.605 | I24: =-I18*Inputs!$E$30*(1+Inputs!$E$65) -> -17766.605 | J24: =-J18*Inputs!$E$30*(1+Inputs!$E$65) -> -17766.605 | ... BJ24: =-BJ18*Inputs!$E$30*(1+Inputs!$E$65) -> -35549.28
A25: Retail product cost | C25: =-C19*Inputs!$E$31 -> -1555.2 | D25: =-D19*Inputs!$E$31 -> -1555.2 | E25: =-E19*Inputs!$E$31 -> -1555.2 | F25: =-F19*Inputs!$E$31 -> -1555.2 | G25: =-G19*Inputs!$E$31 -> -1555.2 | H25: =-H19*Inputs!$E$31 -> -1555.2 | I25: =-I19*Inputs!$E$31 -> -1555.2 | J25: =-J19*Inputs!$E$31 -> -1555.2 | ... BJ25: =-BJ19*Inputs!$E$31 -> -3111.8068
A26: Backbar supplies | C26: =-C14*Inputs!$E$32*(1+Inputs!$E$18)^(C$5-1) -> -2073.6 | D26: =-D14*Inputs!$E$32*(1+Inputs!$E$18)^(D$5-1) -> -2073.6 | E26: =-E14*Inputs!$E$32*(1+Inputs!$E$18)^(E$5-1) -> -2073.6 | F26: =-F14*Inputs!$E$32*(1+Inputs!$E$18)^(F$5-1) -> -2073.6 | G26: =-G14*Inputs!$E$32*(1+Inputs!$E$18)^(G$5-1) -> -2073.6 | H26: =-H14*Inputs!$E$32*(1+Inputs!$E$18)^(H$5-1) -> -2073.6 | I26: =-I14*Inputs!$E$32*(1+Inputs!$E$18)^(I$5-1) -> -2073.6 | J26: =-J14*Inputs!$E$32*(1+Inputs!$E$18)^(J$5-1) -> -2073.6 | ... BJ26: =-BJ14*Inputs!$E$32*(1+Inputs!$E$18)^(BJ$5-1) -> -4149.0757
A27: Card fees | C27: =-(C18+C19)*Inputs!$E$33 -> -1112.4864 | D27: =-(D18+D19)*Inputs!$E$33 -> -1112.4864 | E27: =-(E18+E19)*Inputs!$E$33 -> -1112.4864 | F27: =-(F18+F19)*Inputs!$E$33 -> -1112.4864 | G27: =-(G18+G19)*Inputs!$E$33 -> -1112.4864 | H27: =-(H18+H19)*Inputs!$E$33 -> -1112.4864 | I27: =-(I18+I19)*Inputs!$E$33 -> -1112.4864 | J27: =-(J18+J19)*Inputs!$E$33 -> -1112.4864 | ... BJ27: =-(BJ18+BJ19)*Inputs!$E$33 -> -2225.9791
A28: Cost of sales | C28: =C24+C25+C26+C27 -> -22507.891 | D28: =D24+D25+D26+D27 -> -22507.891 | E28: =E24+E25+E26+E27 -> -22507.891 | F28: =F24+F25+F26+F27 -> -22507.891 | G28: =G24+G25+G26+G27 -> -22507.891 | H28: =H24+H25+H26+H27 -> -22507.891 | I28: =I24+I25+I26+I27 -> -22507.891 | J28: =J24+J25+J26+J27 -> -22507.891 | ... BJ28: =BJ24+BJ25+BJ26+BJ27 -> -45036.142
A29: Gross profit | C29: =C21+C28 -> 17413.709 | D29: =D21+D28 -> 17413.709 | E29: =E21+E28 -> 17413.709 | F29: =F21+F28 -> 17413.709 | G29: =G21+G28 -> 17413.709 | H29: =H21+H28 -> 17413.709 | I29: =I21+I28 -> 17413.709 | J29: =J21+J28 -> 17413.709 | ... BJ29: =BJ21+BJ28 -> 33477.552
A31: Operating expenses
A32: Staff payroll (manager, reception, assistants) | C32: =Headcount!C17 -> -8026.6667 | D32: =Headcount!D17 -> -8026.6667 | E32: =Headcount!E17 -> -8026.6667 | F32: =Headcount!F17 -> -8026.6667 | G32: =Headcount!G17 -> -8026.6667 | H32: =Headcount!H17 -> -8026.6667 | I32: =Headcount!I17 -> -8026.6667 | J32: =Headcount!J17 -> -8026.6667 | ... BJ32: =Headcount!BJ17 -> -9034.084
A33: Marketing | C33: =-Inputs!$E$36*(1+Inputs!$E$37)^(C$5-1)*1 -> -2500 | D33: =-Inputs!$E$36*(1+Inputs!$E$37)^(D$5-1)*1 -> -2500 | E33: =-Inputs!$E$36*(1+Inputs!$E$37)^(E$5-1)*1 -> -2500 | F33: =-Inputs!$E$36*(1+Inputs!$E$37)^(F$5-1)*1 -> -2500 | G33: =-Inputs!$E$36*(1+Inputs!$E$37)^(G$5-1)*1 -> -2500 | H33: =-Inputs!$E$36*(1+Inputs!$E$37)^(H$5-1)*1 -> -2500 | I33: =-Inputs!$E$36*(1+Inputs!$E$37)^(I$5-1)*1 -> -2500 | J33: =-Inputs!$E$36*(1+Inputs!$E$37)^(J$5-1)*1 -> -2500 | ... BJ33: =-Inputs!$E$36*(1+Inputs!$E$37)^(BJ$5-1)*1 -> -2500
A34: Salon rent | C34: =-Inputs!$E$38*1 -> -6500 | D34: =-Inputs!$E$38*1 -> -6500 | E34: =-Inputs!$E$38*1 -> -6500 | F34: =-Inputs!$E$38*1 -> -6500 | G34: =-Inputs!$E$38*1 -> -6500 | H34: =-Inputs!$E$38*1 -> -6500 | I34: =-Inputs!$E$38*1 -> -6500 | J34: =-Inputs!$E$38*1 -> -6500 | ... BJ34: =-Inputs!$E$38*1 -> -6500
A35: Utilities | C35: =-Inputs!$E$39*1 -> -900 | D35: =-Inputs!$E$39*1 -> -900 | E35: =-Inputs!$E$39*1 -> -900 | F35: =-Inputs!$E$39*1 -> -900 | G35: =-Inputs!$E$39*1 -> -900 | H35: =-Inputs!$E$39*1 -> -900 | I35: =-Inputs!$E$39*1 -> -900 | J35: =-Inputs!$E$39*1 -> -900 | ... BJ35: =-Inputs!$E$39*1 -> -900
A36: Booking software | C36: =-Inputs!$E$40*1 -> -250 | D36: =-Inputs!$E$40*1 -> -250 | E36: =-Inputs!$E$40*1 -> -250 | F36: =-Inputs!$E$40*1 -> -250 | G36: =-Inputs!$E$40*1 -> -250 | H36: =-Inputs!$E$40*1 -> -250 | I36: =-Inputs!$E$40*1 -> -250 | J36: =-Inputs!$E$40*1 -> -250 | ... BJ36: =-Inputs!$E$40*1 -> -250
A37: Insurance & licences | C37: =-Inputs!$E$41*1 -> -650 | D37: =-Inputs!$E$41*1 -> -650 | E37: =-Inputs!$E$41*1 -> -650 | F37: =-Inputs!$E$41*1 -> -650 | G37: =-Inputs!$E$41*1 -> -650 | H37: =-Inputs!$E$41*1 -> -650 | I37: =-Inputs!$E$41*1 -> -650 | J37: =-Inputs!$E$41*1 -> -650 | ... BJ37: =-Inputs!$E$41*1 -> -650
A38: Towels, laundry & cleaning | C38: =-Inputs!$E$42*1 -> -450 | D38: =-Inputs!$E$42*1 -> -450 | E38: =-Inputs!$E$42*1 -> -450 | F38: =-Inputs!$E$42*1 -> -450 | G38: =-Inputs!$E$42*1 -> -450 | H38: =-Inputs!$E$42*1 -> -450 | I38: =-Inputs!$E$42*1 -> -450 | J38: =-Inputs!$E$42*1 -> -450 | ... BJ38: =-Inputs!$E$42*1 -> -450
A39: Other G&A | C39: =-Inputs!$E$43*1 -> -700 | D39: =-Inputs!$E$43*1 -> -700 | E39: =-Inputs!$E$43*1 -> -700 | F39: =-Inputs!$E$43*1 -> -700 | G39: =-Inputs!$E$43*1 -> -700 | H39: =-Inputs!$E$43*1 -> -700 | I39: =-Inputs!$E$43*1 -> -700 | J39: =-Inputs!$E$43*1 -> -700 | ... BJ39: =-Inputs!$E$43*1 -> -700
A40: Total operating expenses | C40: =C32+C33+C34+C35+C36+C37+C38+C39 -> -19976.667 | D40: =D32+D33+D34+D35+D36+D37+D38+D39 -> -19976.667 | E40: =E32+E33+E34+E35+E36+E37+E38+E39 -> -19976.667 | F40: =F32+F33+F34+F35+F36+F37+F38+F39 -> -19976.667 | G40: =G32+G33+G34+G35+G36+G37+G38+G39 -> -19976.667 | H40: =H32+H33+H34+H35+H36+H37+H38+H39 -> -19976.667 | I40: =I32+I33+I34+I35+I36+I37+I38+I39 -> -19976.667 | J40: =J32+J33+J34+J35+J36+J37+J38+J39 -> -19976.667 | ... BJ40: =BJ32+BJ33+BJ34+BJ35+BJ36+BJ37+BJ38+BJ39 -> -20984.084
A41: EBITDA | C41: =C29+C40 -> -2562.9579 | D41: =D29+D40 -> -2562.9579 | E41: =E29+E40 -> -2562.9579 | F41: =F29+F40 -> -2562.9579 | G41: =G29+G40 -> -2562.9579 | H41: =H29+H40 -> -2562.9579 | I41: =I29+I40 -> -2562.9579 | J41: =J29+J40 -> -2562.9579 | ... BJ41: =BJ29+BJ40 -> 12493.468
A43: Profit after depreciation, interest, tax
A44: EBIT | C44: =C41+C55 -> -4079.6245 | D44: =D41+D55 -> -4079.6245 | E44: =E41+E55 -> -4079.6245 | F44: =F41+F55 -> -4079.6245 | G44: =G41+G55 -> -4079.6245 | H44: =H41+H55 -> -4079.6245 | I44: =I41+I55 -> -4079.6245 | J44: =J41+J55 -> -4079.6245 | ... BJ44: =BJ41+BJ55 -> 10976.801
A45: Interest on loan (average balance after drawdown) | C45: =-(C60+C61+C63)/2*Inputs!$E$71/12 -> -466.66667 | D45: =-(D60+D61+D63)/2*Inputs!$E$71/12 -> -462.77778 | E45: =-(E60+E61+E63)/2*Inputs!$E$71/12 -> -455 | F45: =-(F60+F61+F63)/2*Inputs!$E$71/12 -> -447.22222 | G45: =-(G60+G61+G63)/2*Inputs!$E$71/12 -> -439.44444 | H45: =-(H60+H61+H63)/2*Inputs!$E$71/12 -> -431.66667 | I45: =-(I60+I61+I63)/2*Inputs!$E$71/12 -> -423.88889 | J45: =-(J60+J61+J63)/2*Inputs!$E$71/12 -> -416.11111 | ... BJ45: =-(BJ60+BJ61+BJ63)/2*Inputs!$E$71/12 -> -11.666667
A46: Pre-tax income | C46: =C44+C45 -> -4546.2912 | D46: =D44+D45 -> -4542.4023 | E46: =E44+E45 -> -4534.6245 | F46: =F44+F45 -> -4526.8468 | G46: =G44+G45 -> -4519.069 | H46: =H44+H45 -> -4511.2912 | I46: =I44+I45 -> -4503.5134 | J46: =J44+J45 -> -4495.7356 | ... BJ46: =BJ44+BJ45 -> 10965.134
A47: Helper: cumulative pre-tax income | C47: =C46 -> -4546.2912 | D47: =C47+D46 -> -9088.6935 | E47: =D47+E46 -> -13623.318 | F47: =E47+F46 -> -18150.165 | G47: =F47+G46 -> -22669.234 | H47: =G47+H46 -> -27180.525 | I47: =H47+I46 -> -31684.038 | J47: =I47+J46 -> -36179.774 | K47: =J47+K46 -> -40667.732 | ... BJ47: =BI47+BJ46 -> 213958.89
A48: Helper: cumulative taxable income (losses carried forward) | C48: =MAX(0,C47) -> 0 | D48: =MAX(C48,D47) -> 0 | E48: =MAX(D48,E47) -> 0 | F48: =MAX(E48,F47) -> 0 | G48: =MAX(F48,G47) -> 0 | H48: =MAX(G48,H47) -> 0 | I48: =MAX(H48,I47) -> 0 | J48: =MAX(I48,J47) -> 0 | K48: =MAX(J48,K47) -> 0 | ... BJ48: =MAX(BI48,BJ47) -> 213958.89
A49: Income tax | C49: =-C48*Inputs!$E$81 -> 0 | D49: =-(D48-C48)*Inputs!$E$81 -> 0 | E49: =-(E48-D48)*Inputs!$E$81 -> 0 | F49: =-(F48-E48)*Inputs!$E$81 -> 0 | G49: =-(G48-F48)*Inputs!$E$81 -> 0 | H49: =-(H48-G48)*Inputs!$E$81 -> 0 | I49: =-(I48-H48)*Inputs!$E$81 -> 0 | J49: =-(J48-I48)*Inputs!$E$81 -> 0 | K49: =-(K48-J48)*Inputs!$E$81 -> 0 | ... BJ49: =-(BJ48-BI48)*Inputs!$E$81 -> -2302.6782
A50: Net income | C50: =C46+C49 -> -4546.2912 | D50: =D46+D49 -> -4542.4023 | E50: =E46+E49 -> -4534.6245 | F50: =F46+F49 -> -4526.8468 | G50: =G46+G49 -> -4519.069 | H50: =H46+H49 -> -4511.2912 | I50: =I46+I49 -> -4503.5134 | J50: =J46+J49 -> -4495.7356 | ... BJ50: =BJ46+BJ49 -> 8662.4562
A52: Fixed assets & capital spending
A53: Capital spending (fit-out, stations, wash units; stations for chairs added) | C53: =Inputs!$E$46+MAX(0,Inputs!$E$7-Inputs!$E$48)*Inputs!$E$47+Inputs!$E$49*Inputs!$E$50 -> 127400 | D53: =IF(AND(D$5>1,MOD(D$4-1,12)=0),Inputs!$E$8*Inputs!$E$47,0) -> 0 | E53: =IF(AND(E$5>1,MOD(E$4-1,12)=0),Inputs!$E$8*Inputs!$E$47,0) -> 0 | F53: =IF(AND(F$5>1,MOD(F$4-1,12)=0),Inputs!$E$8*Inputs!$E$47,0) -> 0 | G53: =IF(AND(G$5>1,MOD(G$4-1,12)=0),Inputs!$E$8*Inputs!$E$47,0) -> 0 | H53: =IF(AND(H$5>1,MOD(H$4-1,12)=0),Inputs!$E$8*Inputs!$E$47,0) -> 0 | I53: =IF(AND(I$5>1,MOD(I$4-1,12)=0),Inputs!$E$8*Inputs!$E$47,0) -> 0 | J53: =IF(AND(J$5>1,MOD(J$4-1,12)=0),Inputs!$E$8*Inputs!$E$47,0) -> 0 | K53: =IF(AND(K$5>1,MOD(K$4-1,12)=0),Inputs!$E$8*Inputs!$E$47,0) -> 0 | ... BJ53: =IF(AND(BJ$5>1,MOD(BJ$4-1,12)=0),Inputs!$E$8*Inputs!$E$47,0) -> 0
A54: Fixed assets at cost | C54: =C53 -> 127400 | D54: =C54+D53 -> 127400 | E54: =D54+E53 -> 127400 | F54: =E54+F53 -> 127400 | G54: =F54+G53 -> 127400 | H54: =G54+H53 -> 127400 | I54: =H54+I53 -> 127400 | J54: =I54+J53 -> 127400 | K54: =J54+K53 -> 127400 | ... BJ54: =BI54+BJ53 -> 127400
A55: Depreciation | C55: =-MIN(C54/MAX(1,Inputs!$E$80*12),C53) -> -1516.6667 | D55: =-MIN(D54/MAX(1,Inputs!$E$80*12),C57+D53) -> -1516.6667 | E55: =-MIN(E54/MAX(1,Inputs!$E$80*12),D57+E53) -> -1516.6667 | F55: =-MIN(F54/MAX(1,Inputs!$E$80*12),E57+F53) -> -1516.6667 | G55: =-MIN(G54/MAX(1,Inputs!$E$80*12),F57+G53) -> -1516.6667 | H55: =-MIN(H54/MAX(1,Inputs!$E$80*12),G57+H53) -> -1516.6667 | I55: =-MIN(I54/MAX(1,Inputs!$E$80*12),H57+I53) -> -1516.6667 | J55: =-MIN(J54/MAX(1,Inputs!$E$80*12),I57+J53) -> -1516.6667 | K55: =-MIN(K54/MAX(1,Inputs!$E$80*12),J57+K53) -> -1516.6667 | ... BJ55: =-MIN(BJ54/MAX(1,Inputs!$E$80*12),BI57+BJ53) -> -1516.6667
A56: Accumulated depreciation | C56: =C55 -> -1516.6667 | D56: =C56+D55 -> -3033.3333 | E56: =D56+E55 -> -4550 | F56: =E56+F55 -> -6066.6667 | G56: =F56+G55 -> -7583.3333 | H56: =G56+H55 -> -9100 | I56: =H56+I55 -> -10616.667 | J56: =I56+J55 -> -12133.333 | K56: =J56+K55 -> -13650 | ... BJ56: =BI56+BJ55 -> -91000
A57: Net fixed assets | C57: =C54+C56 -> 125883.33 | D57: =D54+D56 -> 124366.67 | E57: =E54+E56 -> 122850 | F57: =F54+F56 -> 121333.33 | G57: =G54+G56 -> 119816.67 | H57: =H54+H56 -> 118300 | I57: =I54+I56 -> 116783.33 | J57: =J54+J56 -> 115266.67 | ... BJ57: =BJ54+BJ56 -> 36400
A59: Debt
A60: Loan — opening balance | C60: =0 -> 0 | D60: =C63 -> 70000 | E60: =D63 -> 68833.333 | F60: =E63 -> 67666.667 | G60: =F63 -> 66500 | H60: =G63 -> 65333.333 | I60: =H63 -> 64166.667 | J60: =I63 -> 63000 | K60: =J63 -> 61833.333 | ... BJ60: =BI63 -> 2333.3333
A61: Loan drawdown | C61: =IF(C$4=1,Inputs!$E$70,0) -> 70000 | D61: =IF(D$4=1,Inputs!$E$70,0) -> 0 | E61: =IF(E$4=1,Inputs!$E$70,0) -> 0 | F61: =IF(F$4=1,Inputs!$E$70,0) -> 0 | G61: =IF(G$4=1,Inputs!$E$70,0) -> 0 | H61: =IF(H$4=1,Inputs!$E$70,0) -> 0 | I61: =IF(I$4=1,Inputs!$E$70,0) -> 0 | J61: =IF(J$4=1,Inputs!$E$70,0) -> 0 | ... BJ61: =IF(BJ$4=1,Inputs!$E$70,0) -> 0
A62: Loan repayment | C62: =-MIN(C60,Inputs!$E$70/MAX(1,Inputs!$E$72*12)) -> 0 | D62: =-MIN(D60,Inputs!$E$70/MAX(1,Inputs!$E$72*12)) -> -1166.6667 | E62: =-MIN(E60,Inputs!$E$70/MAX(1,Inputs!$E$72*12)) -> -1166.6667 | F62: =-MIN(F60,Inputs!$E$70/MAX(1,Inputs!$E$72*12)) -> -1166.6667 | G62: =-MIN(G60,Inputs!$E$70/MAX(1,Inputs!$E$72*12)) -> -1166.6667 | H62: =-MIN(H60,Inputs!$E$70/MAX(1,Inputs!$E$72*12)) -> -1166.6667 | I62: =-MIN(I60,Inputs!$E$70/MAX(1,Inputs!$E$72*12)) -> -1166.6667 | J62: =-MIN(J60,Inputs!$E$70/MAX(1,Inputs!$E$72*12)) -> -1166.6667 | ... BJ62: =-MIN(BJ60,Inputs!$E$70/MAX(1,Inputs!$E$72*12)) -> -1166.6667
A63: Loan — closing balance | C63: =C60+C61+C62 -> 70000 | D63: =D60+D61+D62 -> 68833.333 | E63: =E60+E61+E62 -> 67666.667 | F63: =F60+F61+F62 -> 66500 | G63: =G60+G61+G62 -> 65333.333 | H63: =H60+H61+H62 -> 64166.667 | I63: =I60+I61+I62 -> 63000 | J63: =J60+J61+J62 -> 61833.333 | ... BJ63: =BJ60+BJ61+BJ62 -> 1166.6667
A65: Working capital
A66: Accounts receivable | C66: =C21*Inputs!$E$75/30 -> 2661.44 | D66: =D21*Inputs!$E$75/30 -> 2661.44 | E66: =E21*Inputs!$E$75/30 -> 2661.44 | F66: =F21*Inputs!$E$75/30 -> 2661.44 | G66: =G21*Inputs!$E$75/30 -> 2661.44 | H66: =H21*Inputs!$E$75/30 -> 2661.44 | I66: =I21*Inputs!$E$75/30 -> 2661.44 | J66: =J21*Inputs!$E$75/30 -> 2661.44 | ... BJ66: =BJ21*Inputs!$E$75/30 -> 5234.2463
A67: Inventory | C67: =-C28*Inputs!$E$76/30 -> 11253.946 | D67: =-D28*Inputs!$E$76/30 -> 11253.946 | E67: =-E28*Inputs!$E$76/30 -> 11253.946 | F67: =-F28*Inputs!$E$76/30 -> 11253.946 | G67: =-G28*Inputs!$E$76/30 -> 11253.946 | H67: =-H28*Inputs!$E$76/30 -> 11253.946 | I67: =-I28*Inputs!$E$76/30 -> 11253.946 | J67: =-J28*Inputs!$E$76/30 -> 11253.946 | ... BJ67: =-BJ28*Inputs!$E$76/30 -> 22518.071
A68: Accounts payable | C68: =-C28*Inputs!$E$77/30 -> 15005.261 | D68: =-D28*Inputs!$E$77/30 -> 15005.261 | E68: =-E28*Inputs!$E$77/30 -> 15005.261 | F68: =-F28*Inputs!$E$77/30 -> 15005.261 | G68: =-G28*Inputs!$E$77/30 -> 15005.261 | H68: =-H28*Inputs!$E$77/30 -> 15005.261 | I68: =-I28*Inputs!$E$77/30 -> 15005.261 | J68: =-J28*Inputs!$E$77/30 -> 15005.261 | ... BJ68: =-BJ28*Inputs!$E$77/30 -> 30024.095
A69: (Increase) / decrease in receivables | C69: =-C66 -> -2661.44 | D69: =C66-D66 -> 0 | E69: =D66-E66 -> 0 | F69: =E66-F66 -> 0 | G69: =F66-G66 -> 0 | H69: =G66-H66 -> 0 | I69: =H66-I66 -> 0 | J69: =I66-J66 -> 0 | K69: =J66-K66 -> 0 | ... BJ69: =BI66-BJ66 -> 0
A70: (Increase) / decrease in inventory | C70: =-C67 -> -11253.946 | D70: =C67-D67 -> 0 | E70: =D67-E67 -> 0 | F70: =E67-F67 -> 0 | G70: =F67-G67 -> 0 | H70: =G67-H67 -> 0 | I70: =H67-I67 -> 0 | J70: =I67-J67 -> 0 | K70: =J67-K67 -> 0 | ... BJ70: =BI67-BJ67 -> 0
A71: Increase / (decrease) in payables | C71: =C68 -> 15005.261 | D71: =D68-C68 -> 0 | E71: =E68-D68 -> 0 | F71: =F68-E68 -> 0 | G71: =G68-F68 -> 0 | H71: =H68-G68 -> 0 | I71: =I68-H68 -> 0 | J71: =J68-I68 -> 0 | K71: =K68-J68 -> 0 | ... BJ71: =BJ68-BI68 -> 0
A73: Cash flow
A74: Operating cash flow | C74: =C50-C55+C69+C70+C71 -> -1939.7493 | D74: =D50-D55+D69+D70+D71 -> -3025.7356 | E74: =E50-E55+E69+E70+E71 -> -3017.9579 | F74: =F50-F55+F69+F70+F71 -> -3010.1801 | G74: =G50-G55+G69+G70+G71 -> -3002.4023 | H74: =H50-H55+H69+H70+H71 -> -2994.6245 | I74: =I50-I55+I69+I70+I71 -> -2986.8468 | J74: =J50-J55+J69+J70+J71 -> -2979.069 | ... BJ74: =BJ50-BJ55+BJ69+BJ70+BJ71 -> 10179.123
A75: Investing cash flow (capex) | C75: =-C53 -> -127400 | D75: =-D53 -> 0 | E75: =-E53 -> 0 | F75: =-F53 -> 0 | G75: =-G53 -> 0 | H75: =-H53 -> 0 | I75: =-I53 -> 0 | J75: =-J53 -> 0 | ... BJ75: =-BJ53 -> 0
A76: Equity raised | C76: =IF(C$4=1,Inputs!$E$69,0) -> 150000 | D76: =IF(D$4=1,Inputs!$E$69,0) -> 0 | E76: =IF(E$4=1,Inputs!$E$69,0) -> 0 | F76: =IF(F$4=1,Inputs!$E$69,0) -> 0 | G76: =IF(G$4=1,Inputs!$E$69,0) -> 0 | H76: =IF(H$4=1,Inputs!$E$69,0) -> 0 | I76: =IF(I$4=1,Inputs!$E$69,0) -> 0 | J76: =IF(J$4=1,Inputs!$E$69,0) -> 0 | ... BJ76: =IF(BJ$4=1,Inputs!$E$69,0) -> 0
A77: Financing cash flow | C77: =C76+C61+C62 -> 220000 | D77: =D76+D61+D62 -> -1166.6667 | E77: =E76+E61+E62 -> -1166.6667 | F77: =F76+F61+F62 -> -1166.6667 | G77: =G76+G61+G62 -> -1166.6667 | H77: =H76+H61+H62 -> -1166.6667 | I77: =I76+I61+I62 -> -1166.6667 | J77: =J76+J61+J62 -> -1166.6667 | ... BJ77: =BJ76+BJ61+BJ62 -> -1166.6667
A78: Net cash flow | C78: =C74+C75+C77 -> 90660.251 | D78: =D74+D75+D77 -> -4192.4023 | E78: =E74+E75+E77 -> -4184.6245 | F78: =F74+F75+F77 -> -4176.8468 | G78: =G74+G75+G77 -> -4169.069 | H78: =H74+H75+H77 -> -4161.2912 | I78: =I74+I75+I77 -> -4153.5134 | J78: =J74+J75+J77 -> -4145.7356 | ... BJ78: =BJ74+BJ75+BJ77 -> 9012.4562
A79: Opening cash | C79: =0 -> 0 | D79: =C80 -> 90660.251 | E79: =D80 -> 86467.848 | F79: =E80 -> 82283.224 | G79: =F80 -> 78106.377 | H79: =G80 -> 73937.308 | I79: =H80 -> 69776.017 | J79: =I80 -> 65622.503 | K79: =J80 -> 61476.768 | ... BJ79: =BI80 -> 277053.51
A80: Closing cash | C80: =C79+C78 -> 90660.251 | D80: =D79+D78 -> 86467.848 | E80: =E79+E78 -> 82283.224 | F80: =F79+F78 -> 78106.377 | G80: =G79+G78 -> 73937.308 | H80: =H79+H78 -> 69776.017 | I80: =I79+I78 -> 65622.503 | J80: =J79+J78 -> 61476.768 | ... BJ80: =BJ79+BJ78 -> 286065.97
A81: Helper: EBITDA positive (1/0) | C81: =IF(C41>0,1,0) -> 0 | D81: =IF(D41>0,1,0) -> 0 | E81: =IF(E41>0,1,0) -> 0 | F81: =IF(F41>0,1,0) -> 0 | G81: =IF(G41>0,1,0) -> 0 | H81: =IF(H41>0,1,0) -> 0 | I81: =IF(I41>0,1,0) -> 0 | J81: =IF(J41>0,1,0) -> 0 | ... BJ81: =IF(BJ41>0,1,0) -> 1
A83: Goal modules
A84: Helper: net income positive (1/0) | C84: =IF(C50>0,1,0) -> 0 | D84: =IF(D50>0,1,0) -> 0 | E84: =IF(E50>0,1,0) -> 0 | F84: =IF(F50>0,1,0) -> 0 | G84: =IF(G50>0,1,0) -> 0 | H84: =IF(H50>0,1,0) -> 0 | I84: =IF(I50>0,1,0) -> 0 | J84: =IF(J50>0,1,0) -> 0 | ... BJ84: =IF(BJ50>0,1,0) -> 1
A85: Cash flow before financing (operating + investing) | C85: =C74+C75 -> -129339.75 | D85: =D74+D75 -> -3025.7356 | E85: =E74+E75 -> -3017.9579 | F85: =F74+F75 -> -3010.1801 | G85: =G74+G75 -> -3002.4023 | H85: =H74+H75 -> -2994.6245 | I85: =I74+I75 -> -2986.8468 | J85: =J74+J75 -> -2979.069 | ... BJ85: =BJ74+BJ75 -> 10179.123
A86: Cumulative cash flow before financing | C86: =C85 -> -129339.75 | D86: =C86+D85 -> -132365.48 | E86: =D86+E85 -> -135383.44 | F86: =E86+F85 -> -138393.62 | G86: =F86+G85 -> -141396.03 | H86: =G86+H85 -> -144390.65 | I86: =H86+I85 -> -147377.5 | J86: =I86+J85 -> -150356.57 | K86: =J86+K85 -> -153327.86 | ... BJ86: =BI86+BJ85 -> 134899.3
A87: Helper: lowest cumulative cash flow so far | C87: =C86 -> -129339.75 | D87: =MIN(C87,D86) -> -132365.48 | E87: =MIN(D87,E86) -> -135383.44 | F87: =MIN(E87,F86) -> -138393.62 | G87: =MIN(F87,G86) -> -141396.03 | H87: =MIN(G87,H86) -> -144390.65 | I87: =MIN(H87,I86) -> -147377.5 | J87: =MIN(I87,J86) -> -150356.57 | K87: =MIN(J87,K86) -> -153327.86 | ... BJ87: =MIN(BI87,BJ86) -> -162195.06
A88: Helper: investment paid back (1/0) | C88: =IF(AND(C86>=0,C87<0),1,0) -> 0 | D88: =IF(AND(D86>=0,D87<0),1,0) -> 0 | E88: =IF(AND(E86>=0,E87<0),1,0) -> 0 | F88: =IF(AND(F86>=0,F87<0),1,0) -> 0 | G88: =IF(AND(G86>=0,G87<0),1,0) -> 0 | H88: =IF(AND(H86>=0,H87<0),1,0) -> 0 | I88: =IF(AND(I86>=0,I87<0),1,0) -> 0 | J88: =IF(AND(J86>=0,J87<0),1,0) -> 0 | ... BJ88: =IF(AND(BJ86>=0,BJ87<0),1,0) -> 1
A89: Unlevered free cash flow (operating + after-tax interest − capex) | C89: =C74-C45*(1-Inputs!$E$81)+C75 -> -128971.08 | D89: =D74-D45*(1-Inputs!$E$81)+D75 -> -2660.1412 | E89: =E74-E45*(1-Inputs!$E$81)+E75 -> -2658.5079 | F89: =F74-F45*(1-Inputs!$E$81)+F75 -> -2656.8745 | G89: =G74-G45*(1-Inputs!$E$81)+G75 -> -2655.2412 | H89: =H74-H45*(1-Inputs!$E$81)+H75 -> -2653.6079 | I89: =I74-I45*(1-Inputs!$E$81)+I75 -> -2651.9745 | J89: =J74-J45*(1-Inputs!$E$81)+J75 -> -2650.3412 | ... BJ89: =BJ74-BJ45*(1-Inputs!$E$81)+BJ75 -> 10188.34
A91: Balance sheet
A92: Paid-in capital | C92: =C76 -> 150000 | D92: =C92+D76 -> 150000 | E92: =D92+E76 -> 150000 | F92: =E92+F76 -> 150000 | G92: =F92+G76 -> 150000 | H92: =G92+H76 -> 150000 | I92: =H92+I76 -> 150000 | J92: =I92+J76 -> 150000 | K92: =J92+K76 -> 150000 | ... BJ92: =BI92+BJ76 -> 150000
A93: Retained earnings | C93: =C50 -> -4546.2912 | D93: =C93+D50 -> -9088.6935 | E93: =D93+E50 -> -13623.318 | F93: =E93+F50 -> -18150.165 | G93: =F93+G50 -> -22669.234 | H93: =G93+H50 -> -27180.525 | I93: =H93+I50 -> -31684.038 | J93: =I93+J50 -> -36179.774 | K93: =J93+K50 -> -40667.732 | ... BJ93: =BI93+BJ50 -> 169027.52
A94: Total assets | C94: =C80+C66+C67+C57 -> 230458.97 | D94: =D80+D66+D67+D57 -> 224749.9 | E94: =E80+E66+E67+E57 -> 219048.61 | F94: =F80+F66+F67+F57 -> 213355.1 | G94: =G80+G66+G67+G57 -> 207669.36 | H94: =H80+H66+H67+H57 -> 201991.4 | I94: =I80+I66+I67+I57 -> 196321.22 | J94: =J80+J66+J67+J57 -> 190658.82 | ... BJ94: =BJ80+BJ66+BJ67+BJ57 -> 350218.28
A95: Total liabilities | C95: =C68+C63 -> 85005.261 | D95: =D68+D63 -> 83838.594 | E95: =E68+E63 -> 82671.927 | F95: =F68+F63 -> 81505.261 | G95: =G68+G63 -> 80338.594 | H95: =H68+H63 -> 79171.927 | I95: =I68+I63 -> 78005.261 | J95: =J68+J63 -> 76838.594 | ... BJ95: =BJ68+BJ63 -> 31190.761
A96: Total equity | C96: =C92+C93 -> 145453.71 | D96: =D92+D93 -> 140911.31 | E96: =E92+E93 -> 136376.68 | F96: =F92+F93 -> 131849.84 | G96: =G92+G93 -> 127330.77 | H96: =H92+H93 -> 122819.48 | I96: =I92+I93 -> 118315.96 | J96: =J92+J93 -> 113820.23 | ... BJ96: =BJ92+BJ93 -> 319027.52
A97: Total liabilities & equity | C97: =C95+C96 -> 230458.97 | D97: =D95+D96 -> 224749.9 | E97: =E95+E96 -> 219048.61 | F97: =F95+F96 -> 213355.1 | G97: =G95+G96 -> 207669.36 | H97: =H95+H96 -> 201991.4 | I97: =I95+I96 -> 196321.22 | J97: =J95+J96 -> 190658.82 | ... BJ97: =BJ95+BJ96 -> 350218.28
A98: Check: assets − liabilities − equity | C98: =C94-C97 -> 0 | D98: =D94-D97 -> 0 | E98: =E94-E97 -> 0 | F98: =F94-F97 -> 0 | G98: =G94-G97 -> 0 | H98: =H94-H97 -> 0 | I98: =I94-I97 -> 0 | J98: =J94-J97 -> 0 | ... BJ98: =BJ94-BJ97 -> 0

Sheet Headcount
A1: Headcount & payroll | D1: =HYPERLINK("#'Cover'!A1","◂ Contents") -> ◂ Contents
A2: $ unless stated; costs shown as negatives. Every period uses the same formula.
A3: Month | C3: M1 | D3: M2 | E3: M3 | F3: M4 | G3: M5 | H3: M6 | I3: M7 | J3: M8 | K3: M9 | L3: M10 | M3: M11 | N3: M12 | O3: M13 | P3: M14 | Q3: M15 | R3: M16 | S3: M17 | T3: M18 | U3: M19 | V3: M20 | W3: M21 | X3: M22 | Y3: M23 | Z3: M24 | AA3: M25 | AB3: M26 | AC3: M27 | AD3: M28 | AE3: M29 | AF3: M30 | AG3: M31 | AH3: M32 | AI3: M33 | AJ3: M34 | AK3: M35 | AL3: M36 | AM3: M37 | AN3: M38 | AO3: M39 | AP3: M40 | AQ3: M41 | AR3: M42 | AS3: M43 | AT3: M44 | AU3: M45 | AV3: M46 | AW3: M47 | AX3: M48 | AY3: M49 | AZ3: M50 | BA3: M51 | BB3: M52 | BC3: M53 | BD3: M54 | BE3: M55 | BF3: M56 | BG3: M57 | BH3: M58 | BI3: M59 | BJ3: M60
A4: Period # | C4: 1 | D4: 2 | E4: 3 | F4: 4 | G4: 5 | H4: 6 | I4: 7 | J4: 8 | K4: 9 | L4: 10 | M4: 11 | N4: 12 | O4: 13 | P4: 14 | Q4: 15 | R4: 16 | S4: 17 | T4: 18 | U4: 19 | V4: 20 | W4: 21 | X4: 22 | Y4: 23 | Z4: 24 | AA4: 25 | AB4: 26 | AC4: 27 | AD4: 28 | AE4: 29 | AF4: 30 | AG4: 31 | AH4: 32 | AI4: 33 | AJ4: 34 | AK4: 35 | AL4: 36 | AM4: 37 | AN4: 38 | AO4: 39 | AP4: 40 | AQ4: 41 | AR4: 42 | AS4: 43 | AT4: 44 | AU4: 45 | AV4: 46 | AW4: 47 | AX4: 48 | AY4: 49 | AZ4: 50 | BA4: 51 | BB4: 52 | BC4: 53 | BD4: 54 | BE4: 55 | BF4: 56 | BG4: 57 | BH4: 58 | BI4: 59 | BJ4: 60
A5: Year # | C5: =ROUNDUP(C4*1/12,0) -> 1 | D5: =ROUNDUP(D4*1/12,0) -> 1 | E5: =ROUNDUP(E4*1/12,0) -> 1 | F5: =ROUNDUP(F4*1/12,0) -> 1 | G5: =ROUNDUP(G4*1/12,0) -> 1 | H5: =ROUNDUP(H4*1/12,0) -> 1 | I5: =ROUNDUP(I4*1/12,0) -> 1 | J5: =ROUNDUP(J4*1/12,0) -> 1 | ... BJ5: =ROUNDUP(BJ4*1/12,0) -> 5
A7: Headcount (FTE)
A8: Salon manager — FTE | C8: =Inputs!$E$53*(1+Inputs!$E$55)^(C$5-1)*MAX(0,MIN(1,C$4*1-Inputs!$E$56+1))/1 -> 0.5 | D8: =Inputs!$E$53*(1+Inputs!$E$55)^(D$5-1)*MAX(0,MIN(1,D$4*1-Inputs!$E$56+1))/1 -> 0.5 | E8: =Inputs!$E$53*(1+Inputs!$E$55)^(E$5-1)*MAX(0,MIN(1,E$4*1-Inputs!$E$56+1))/1 -> 0.5 | F8: =Inputs!$E$53*(1+Inputs!$E$55)^(F$5-1)*MAX(0,MIN(1,F$4*1-Inputs!$E$56+1))/1 -> 0.5 | G8: =Inputs!$E$53*(1+Inputs!$E$55)^(G$5-1)*MAX(0,MIN(1,G$4*1-Inputs!$E$56+1))/1 -> 0.5 | H8: =Inputs!$E$53*(1+Inputs!$E$55)^(H$5-1)*MAX(0,MIN(1,H$4*1-Inputs!$E$56+1))/1 -> 0.5 | I8: =Inputs!$E$53*(1+Inputs!$E$55)^(I$5-1)*MAX(0,MIN(1,I$4*1-Inputs!$E$56+1))/1 -> 0.5 | J8: =Inputs!$E$53*(1+Inputs!$E$55)^(J$5-1)*MAX(0,MIN(1,J$4*1-Inputs!$E$56+1))/1 -> 0.5 | ... BJ8: =Inputs!$E$53*(1+Inputs!$E$55)^(BJ$5-1)*MAX(0,MIN(1,BJ$4*1-Inputs!$E$56+1))/1 -> 0.5
A9: Receptionist — FTE | C9: =Inputs!$E$57*(1+Inputs!$E$59)^(C$5-1)*MAX(0,MIN(1,C$4*1-Inputs!$E$60+1))/1 -> 1 | D9: =Inputs!$E$57*(1+Inputs!$E$59)^(D$5-1)*MAX(0,MIN(1,D$4*1-Inputs!$E$60+1))/1 -> 1 | E9: =Inputs!$E$57*(1+Inputs!$E$59)^(E$5-1)*MAX(0,MIN(1,E$4*1-Inputs!$E$60+1))/1 -> 1 | F9: =Inputs!$E$57*(1+Inputs!$E$59)^(F$5-1)*MAX(0,MIN(1,F$4*1-Inputs!$E$60+1))/1 -> 1 | G9: =Inputs!$E$57*(1+Inputs!$E$59)^(G$5-1)*MAX(0,MIN(1,G$4*1-Inputs!$E$60+1))/1 -> 1 | H9: =Inputs!$E$57*(1+Inputs!$E$59)^(H$5-1)*MAX(0,MIN(1,H$4*1-Inputs!$E$60+1))/1 -> 1 | I9: =Inputs!$E$57*(1+Inputs!$E$59)^(I$5-1)*MAX(0,MIN(1,I$4*1-Inputs!$E$60+1))/1 -> 1 | J9: =Inputs!$E$57*(1+Inputs!$E$59)^(J$5-1)*MAX(0,MIN(1,J$4*1-Inputs!$E$60+1))/1 -> 1 | ... BJ9: =Inputs!$E$57*(1+Inputs!$E$59)^(BJ$5-1)*MAX(0,MIN(1,BJ$4*1-Inputs!$E$60+1))/1 -> 1
A10: Shampoo & floor assistants — FTE | C10: =Inputs!$E$61*(1+Inputs!$E$63)^(C$5-1)*MAX(0,MIN(1,C$4*1-Inputs!$E$64+1))/1 -> 1 | D10: =Inputs!$E$61*(1+Inputs!$E$63)^(D$5-1)*MAX(0,MIN(1,D$4*1-Inputs!$E$64+1))/1 -> 1 | E10: =Inputs!$E$61*(1+Inputs!$E$63)^(E$5-1)*MAX(0,MIN(1,E$4*1-Inputs!$E$64+1))/1 -> 1 | F10: =Inputs!$E$61*(1+Inputs!$E$63)^(F$5-1)*MAX(0,MIN(1,F$4*1-Inputs!$E$64+1))/1 -> 1 | G10: =Inputs!$E$61*(1+Inputs!$E$63)^(G$5-1)*MAX(0,MIN(1,G$4*1-Inputs!$E$64+1))/1 -> 1 | H10: =Inputs!$E$61*(1+Inputs!$E$63)^(H$5-1)*MAX(0,MIN(1,H$4*1-Inputs!$E$64+1))/1 -> 1 | I10: =Inputs!$E$61*(1+Inputs!$E$63)^(I$5-1)*MAX(0,MIN(1,I$4*1-Inputs!$E$64+1))/1 -> 1 | J10: =Inputs!$E$61*(1+Inputs!$E$63)^(J$5-1)*MAX(0,MIN(1,J$4*1-Inputs!$E$64+1))/1 -> 1 | ... BJ10: =Inputs!$E$61*(1+Inputs!$E$63)^(BJ$5-1)*MAX(0,MIN(1,BJ$4*1-Inputs!$E$64+1))/1 -> 1
A11: Total FTE | C11: =C8+C9+C10 -> 2.5 | D11: =D8+D9+D10 -> 2.5 | E11: =E8+E9+E10 -> 2.5 | F11: =F8+F9+F10 -> 2.5 | G11: =G8+G9+G10 -> 2.5 | H11: =H8+H9+H10 -> 2.5 | I11: =I8+I9+I10 -> 2.5 | J11: =J8+J9+J10 -> 2.5 | ... BJ11: =BJ8+BJ9+BJ10 -> 2.5
A13: Payroll cost (salary + taxes & benefits)
A14: Salon manager — payroll cost | C14: =-C8*Inputs!$E$54/12*1*(1+Inputs!$E$65)*(1+Inputs!$E$66)^(C$5-1) -> -2240 | D14: =-D8*Inputs!$E$54/12*1*(1+Inputs!$E$65)*(1+Inputs!$E$66)^(D$5-1) -> -2240 | E14: =-E8*Inputs!$E$54/12*1*(1+Inputs!$E$65)*(1+Inputs!$E$66)^(E$5-1) -> -2240 | F14: =-F8*Inputs!$E$54/12*1*(1+Inputs!$E$65)*(1+Inputs!$E$66)^(F$5-1) -> -2240 | G14: =-G8*Inputs!$E$54/12*1*(1+Inputs!$E$65)*(1+Inputs!$E$66)^(G$5-1) -> -2240 | H14: =-H8*Inputs!$E$54/12*1*(1+Inputs!$E$65)*(1+Inputs!$E$66)^(H$5-1) -> -2240 | I14: =-I8*Inputs!$E$54/12*1*(1+Inputs!$E$65)*(1+Inputs!$E$66)^(I$5-1) -> -2240 | J14: =-J8*Inputs!$E$54/12*1*(1+Inputs!$E$65)*(1+Inputs!$E$66)^(J$5-1) -> -2240 | ... BJ14: =-BJ8*Inputs!$E$54/12*1*(1+Inputs!$E$65)*(1+Inputs!$E$66)^(BJ$5-1) -> -2521.1397
A15: Receptionist — payroll cost | C15: =-C9*Inputs!$E$58/12*1*(1+Inputs!$E$65)*(1+Inputs!$E$66)^(C$5-1) -> -3080 | D15: =-D9*Inputs!$E$58/12*1*(1+Inputs!$E$65)*(1+Inputs!$E$66)^(D$5-1) -> -3080 | E15: =-E9*Inputs!$E$58/12*1*(1+Inputs!$E$65)*(1+Inputs!$E$66)^(E$5-1) -> -3080 | F15: =-F9*Inputs!$E$58/12*1*(1+Inputs!$E$65)*(1+Inputs!$E$66)^(F$5-1) -> -3080 | G15: =-G9*Inputs!$E$58/12*1*(1+Inputs!$E$65)*(1+Inputs!$E$66)^(G$5-1) -> -3080 | H15: =-H9*Inputs!$E$58/12*1*(1+Inputs!$E$65)*(1+Inputs!$E$66)^(H$5-1) -> -3080 | I15: =-I9*Inputs!$E$58/12*1*(1+Inputs!$E$65)*(1+Inputs!$E$66)^(I$5-1) -> -3080 | J15: =-J9*Inputs!$E$58/12*1*(1+Inputs!$E$65)*(1+Inputs!$E$66)^(J$5-1) -> -3080 | ... BJ15: =-BJ9*Inputs!$E$58/12*1*(1+Inputs!$E$65)*(1+Inputs!$E$66)^(BJ$5-1) -> -3466.5671
A16: Shampoo & floor assistants — payroll cost | C16: =-C10*Inputs!$E$62/12*1*(1+Inputs!$E$65)*(1+Inputs!$E$66)^(C$5-1) -> -2706.6667 | D16: =-D10*Inputs!$E$62/12*1*(1+Inputs!$E$65)*(1+Inputs!$E$66)^(D$5-1) -> -2706.6667 | E16: =-E10*Inputs!$E$62/12*1*(1+Inputs!$E$65)*(1+Inputs!$E$66)^(E$5-1) -> -2706.6667 | F16: =-F10*Inputs!$E$62/12*1*(1+Inputs!$E$65)*(1+Inputs!$E$66)^(F$5-1) -> -2706.6667 | G16: =-G10*Inputs!$E$62/12*1*(1+Inputs!$E$65)*(1+Inputs!$E$66)^(G$5-1) -> -2706.6667 | H16: =-H10*Inputs!$E$62/12*1*(1+Inputs!$E$65)*(1+Inputs!$E$66)^(H$5-1) -> -2706.6667 | I16: =-I10*Inputs!$E$62/12*1*(1+Inputs!$E$65)*(1+Inputs!$E$66)^(I$5-1) -> -2706.6667 | J16: =-J10*Inputs!$E$62/12*1*(1+Inputs!$E$65)*(1+Inputs!$E$66)^(J$5-1) -> -2706.6667 | ... BJ16: =-BJ10*Inputs!$E$62/12*1*(1+Inputs!$E$65)*(1+Inputs!$E$66)^(BJ$5-1) -> -3046.3772
A17: Total payroll | C17: =C14+C15+C16 -> -8026.6667 | D17: =D14+D15+D16 -> -8026.6667 | E17: =E14+E15+E16 -> -8026.6667 | F17: =F14+F15+F16 -> -8026.6667 | G17: =G14+G15+G16 -> -8026.6667 | H17: =H14+H15+H16 -> -8026.6667 | I17: =I14+I15+I16 -> -8026.6667 | J17: =J14+J15+J16 -> -8026.6667 | ... BJ17: =BJ14+BJ15+BJ16 -> -9034.084

Sheet Checks
A1: Model checks | E1: =HYPERLINK("#'Cover'!A1","◂ Contents") -> ◂ Contents
A2: Live formulas: they re-run every time an input changes.
A3: Check | B3: Result | C3: What it tests
A4: Annual revenue ties to period detail | B4: =IF(ABS(SUM('P&L'!$B$5:$F$5)-SUM(Monthly!$C$21:$BJ$21))<0.5,"PASS","FAIL") -> PASS | C4: Sum of annual revenue equals the sum of every period
A5: Annual net income ties to period detail | B5: =IF(ABS(SUM('P&L'!$B$25:$F$25)-SUM(Monthly!$C$50:$BJ$50))<0.5,"PASS","FAIL") -> PASS | C5: Sum of annual net income equals the sum of every period
A6: EBITDA reconciliation | B6: =IF(ABS(SUM(Monthly!$C$41:$BJ$41)-SUM(Monthly!$C$29:$BJ$29)-SUM(Monthly!$C$40:$BJ$40))<0.5,"PASS","FAIL") -> PASS | C6: EBITDA = gross profit + operating expenses (costs are negative)
A7: Cash roll-forward | B7: =IF(ABS(INDEX(Monthly!$C$80:$BJ$80,60)-SUM(Monthly!$C$78:$BJ$78))<0.5,"PASS","FAIL") -> PASS | C7: Closing cash = all net cash flows since the start (opening cash is zero)
A8: Scenario selector valid | B8: =IF(AND(ISNUMBER(Dashboard!B4),Dashboard!B4>=1,Dashboard!B4<=3,INT(Dashboard!B4)=Dashboard!B4),"PASS","FAIL") -> PASS | C8: Dashboard!B4 is 1, 2 or 3
A9: Scenario ordering of drivers | B9: =IF(AND(Inputs!$B$8<=Inputs!$C$8,Inputs!$C$8<=Inputs!$D$8,Inputs!$B$11<=Inputs!$C$11,Inputs!$C$11<=Inputs!$D$11,Inputs!$B$12<=Inputs!$C$12,Inputs!$C$12<=Inputs!$D$12,Inputs!$B$14<=Inputs!$C$14,Inputs!$C$14<=Inputs!$D$14,Inputs!$B$17<=Inputs!$C$17,Inputs!$C$17<=Inputs!$D$17,Inputs!$B$18<=Inputs!$C$18,Inputs!$C$18<=Inputs!$D$18,Inputs!$B$21<=Inputs!$C$21,Inputs!$C$21<=Inputs!$D$21,Inputs!$B$22<=Inputs!$C$22,Inputs!$C$22<=Inputs!$D$22,Inputs!$B$26<=Inputs!$C$26,Inputs!$C$26<=Inputs!$D$26,Inputs!$B$27<=Inputs!$C$27,Inputs!$C$27<=Inputs!$D$27,Inputs!$B$30>=Inputs!$C$30,Inputs!$C$30>=Inputs!$D$30,Inputs!$B$31>=Inputs!$C$31,Inputs!$C$31>=Inputs!$D$31,Inputs!$B$32>=Inputs!$C$32,Inputs!$C$32>=Inputs!$D$32,Inputs!$B$33>=Inputs!$C$33,Inputs!$C$33>=Inputs!$D$33,Inputs!$B$37<=Inputs!$C$37,Inputs!$C$37<=Inputs!$D$37,Inputs!$B$53<=Inputs!$C$53,Inputs!$C$53<=Inputs!$D$53,Inputs!$B$55<=Inputs!$C$55,Inputs!$C$55<=Inputs!$D$55,Inputs!$B$57<=Inputs!$C$57,Inputs!$C$57<=Inputs!$D$57,Inputs!$B$59<=Inputs!$C$59,Inputs!$C$59<=Inputs!$D$59,Inputs!$B$61<=Inputs!$C$61,Inputs!$C$61<=Inputs!$D$61,Inputs!$B$63<=Inputs!$C$63,Inputs!$C$63<=Inputs!$D$63,Inputs!$B$87>=Inputs!$C$87,Inputs!$C$87>=Inputs!$D$87,Inputs!$B$88<=Inputs!$C$88,Inputs!$C$88<=Inputs!$D$88,Inputs!$B$89<=Inputs!$C$89,Inputs!$C$89<=Inputs!$D$89),"PASS","FAIL") -> PASS | C9: Low / Base / High ordered the right way for every growth and cost driver
A10: Gross margin within 0–100% | B10: =IF(AND(MIN('P&L'!$B$8:$F$8)>=0,MAX('P&L'!$B$8:$F$8)<=1),"PASS","FAIL") -> PASS | C10: Gross margin never negative or above 100%
A11: Loan balance never negative | B11: =IF(MIN(Monthly!$C$63:$BJ$63)>=-0.5,"PASS","FAIL") -> PASS | C11: Repayments never exceed the loan
A12: Funding table ties to the cash flow | B12: =IF(ABS('Break-even'!B18-('Break-even'!B16-'Break-even'!B10))<0.5,"PASS","FAIL") -> PASS | C12: Lowest cash balance = sources of funds − uses of funds up to that point
A13: Valuation: discounting ties to NPV() | B13: =IF(ABS(Valuation!B23-NPV(Valuation!B6,Valuation!$B$17:$F$17))<0.5,"PASS","FAIL") -> PASS | C13: Sum of discounted free cash flows equals Excel's NPV of the same flows
A14: Valuation: WACC above terminal growth | B14: =IF(Valuation!B6>Valuation!B7,"PASS","FAIL") -> PASS | C14: The perpetual-growth formula needs WACC > g
A15: Valuation: sensitivity centre = enterprise value | B15: =IF(ABS(Valuation!D36-Valuation!B27)<0.5,"PASS","FAIL") -> PASS | C15: The middle of the WACC × growth table reproduces the headline value
A16: Valuation: final-year cash flow positive | B16: =IF(Valuation!$F$17>0,"PASS","WARN") -> PASS | C16: Business warning: a negative final-year cash flow gives a negative terminal value (often a 1-year plan still carrying start-up spending)
A17: Sources & uses balance | B17: =IF(ABS('Sources & Uses'!B21-'Sources & Uses'!B28)<0.5,"PASS","FAIL") -> PASS | C17: Sources of funds = uses of funds (incl. cash at the end) for the Sources & Uses period
A18: No error values | B18: =IF(SUMPRODUCT(--ISERROR(Monthly!$C$4:$BJ$98))+SUMPRODUCT(--ISERROR(Headcount!$C$4:$BJ$17))+SUMPRODUCT(--ISERROR('P&L'!$B$3:$F$26))+SUMPRODUCT(--ISERROR('Cash Flow'!$B$3:$F$18))+SUMPRODUCT(--ISERROR('Balance Sheet'!$B$3:$F$17))+SUMPRODUCT(--ISERROR(KPIs!$B$27:$F$46))+SUMPRODUCT(--ISERROR('Break-even'!$B$26:$F$33))+SUMPRODUCT(--ISERROR(Valuation!$B$14:$F$19))+SUMPRODUCT(--ISERROR('Break-even'!$B$3:$F$35))+SUMPRODUCT(--ISERROR(Valuation!$A$3:$F$40))+SUMPRODUCT(--ISERROR('Sources & Uses'!$B$3:$C$30))+SUMPRODUCT(--ISERROR(Dashboard!$A$6:$W$43))+SUMPRODUCT(--ISERROR(Summary!$A$5:$S$52))+SUMPRODUCT(--ISERROR(KPIs!$A$4:$G$46))=0,"PASS","FAIL") -> PASS | C18: No error values (divide-by-zero, broken references) on any calculation sheet
A19: Summary ties to statements | B19: =IF(IFERROR(AND(SUMPRODUCT(--(ABS(Summary!$B$7:$F$7-'P&L'!$B$5:$F$5)>0.5))=0,SUMPRODUCT(--(ABS(Summary!$B$19:$F$19-'P&L'!$B$25:$F$25)>0.5))=0,SUMPRODUCT(--(ABS(Summary!$B$31:$F$31-'Cash Flow'!$B$18:$F$18)>0.5))=0,SUMPRODUCT(--(ABS(Summary!$B$41:$F$41-'Balance Sheet'!$B$5:$F$5)>0.5))=0,ABS(SUM(Summary!$H$7:$S$7)-INDEX(Summary!$B$7:$F$7,Summary!$R$2))<0.5,ABS(SUM(Summary!$H$19:$S$19)-INDEX(Summary!$B$19:$F$19,Summary!$R$2))<0.5,ABS(Summary!$S$31-INDEX(Summary!$B$31:$F$31,Summary!$R$2))<0.5),FALSE()),"PASS","FAIL") -> PASS | C19: Summary revenue, net income and closing cash equal the statements every year; the detailed year adds up to its annual figure
A20: DuPont ties to return on equity | B20: =IF(SUMPRODUCT(--(ABS(KPIs!$B$24:$F$24)>0.000000001))>0,"FAIL",IF(SUMPRODUCT(ISNUMBER(KPIs!$B$23:$F$23)*ISNUMBER(KPIs!$B$16:$F$16))=0,"n/a","PASS")) -> PASS | C20: Net margin × asset turnover × equity multiplier equals return on equity every year; n/a = no year where both are defined (a one-sided n/a is a FAIL)
A21: Balance sheet balances every period | B21: =IF(SUMPRODUCT(--(ABS(Monthly!$C$98:$BJ$98)>0.5))=0,"PASS","FAIL") -> PASS | C21: Assets = liabilities + equity in every period
A22: Funding sufficient (cash ≥ 0) | B22: =IF(MIN(Monthly!$C$80:$BJ$80)>=0,"PASS","WARN") -> PASS | C22: Business warning, not an error: cash dips below zero in this scenario
A24: Overall verdict | B24: =IF(COUNTIF(B4:B22,"FAIL")>0,"FAIL",IF(COUNTIF(B4:B22,"WARN")>0,"PASS WITH WARNINGS","PASS")) -> PASS
