Workbook

Sheet Cover
B2: Professional services financial model (growing)
B3: 5-year financial model · monthly detail · Low / Base / High scenarios · US dollars · Full plan
B5: Purpose | D5: Revenue and profit plan
B6: Active scenario | D6: =Dashboard!C4&" (change it on the Dashboard, cell B4)" -> Base (change it on the Dashboard, cell B4)
B7: Model checks | D7: =Checks!B25 -> PASS
B8: Prepared | D8: 21 October 2026
B10: Contents
C11: PRESENTATION
B12: 1 | C12: =HYPERLINK("#Dashboard!A1","Dashboard") -> Dashboard | D12: Scenario switch, key numbers, core financials
B13: 2 | C13: =HYPERLINK("#Summary!A1","Summary") -> Summary | D13: Income statement, cash flow and balance sheet — every year and any year by month
B14: 3 | C14: =HYPERLINK("#Scenarios!A1","Scenarios") -> Scenarios | D14: Low / Base / High side by side: drivers, outputs, charts
B15: 4 | C15: =HYPERLINK("#'Break-even'!A1","Break-even") -> Break-even | D15: Startup costs, funding need, break-even timing and revenue
B16: 5 | C16: =HYPERLINK("#Valuation!A1","Valuation") -> Valuation | D16: Free cash flow, DCF (perpetual growth and exit multiple), WACC × growth sensitivity
B17: 6 | C17: =HYPERLINK("#'Sources & Uses'!A1","Sources & Uses") -> Sources & Uses | D17: Funding structure, sources and uses of cash for the first months
B18: 7 | C18: =HYPERLINK("#KPIs!A1","KPIs") -> KPIs | D18: Financial ratios, DuPont analysis, industry metrics
C19: INPUTS
B20: 8 | C20: =HYPERLINK("#Inputs!A1","Inputs") -> Inputs | D20: Every assumption, Low / Base / High, with units and comments
C21: STATEMENTS
B22: 9 | C22: =HYPERLINK("#'P&L'!A1","P&L") -> P&L | D22: Annual profit & loss
B23: 10 | C23: =HYPERLINK("#'Cash Flow'!A1","Cash Flow") -> Cash Flow | D23: Annual cash flow statement
B24: 11 | C24: =HYPERLINK("#'Balance Sheet'!A1","Balance Sheet") -> Balance Sheet | D24: Balance sheet at year end
C25: CALCULATIONS
B26: 12 | C26: =HYPERLINK("#Monthly!A1","Monthly") -> Monthly | D26: Month-by-month engine of the model
B27: 13 | C27: =HYPERLINK("#Headcount!A1","Headcount") -> Headcount | D27: Team and payroll
B28: 14 | C28: =HYPERLINK("#'Scenario calc'!A1","Scenario calc") -> Scenario calc | D28: Low, Base and High calculated side by side for the Scenarios sheet
C29: CONTROL
B30: 15 | C30: =HYPERLINK("#Checks!A1","Checks") -> Checks | D30: Live integrity checks and the overall verdict
B32: How to read this file
C33: 1000 | D33: Input you can change — yellow cell with a blue figure (Inputs sheet and the view switches)
C34: 1000 | D34: Formula — calculated, do not overwrite
C35: 1000 | D35: Link to another sheet
C36: 1000 | D36: Active value the model uses (follows the scenario)

Sheet Dashboard
A1: Dashboard | W1: =HYPERLINK("#'Cover'!A1","◂ Contents") -> ◂ Contents
A2: Professional services financial model (growing)
A4: Active scenario | B4: 2 | C4: =CHOOSE(B4,"Low","Base","High") -> Base | D4: 1 = Low · 2 = Base · 3 = High — every sheet follows this cell | S4: Model checks | T4: =Checks!B25 -> PASS
A6: REVENUE · YEAR 5 | C6: EBITDA MARGIN · YEAR 5 | H6: NET INCOME · YEAR 5 | L6: LOWEST CASH BALANCE | P6: FUNDING REQUIRED | T6: ENTERPRISE VALUE (DCF)
A7: =F12 -> 12793894 | C7: =F17 -> 0.30377587 | H7: =F18 -> 3059361.6 | L7: =F39 -> 57680.317 | P7: =F37 -> 630319.68 | T7: =F44 -> 14337567
A8: =IF(AND(B12>0,F12>=0),(F12/B12)^(1/4)-1,"CAGR n/a") -> 0.29807045 | C8: =F16 -> 3886476.3 | H8: =F19 -> 0.2391267 | L8: ='Break-even'!B6 -> 1 | P8: =IF(F38>=0,"Covered by funding raised",-F38) -> 130319.68 | T8: Average of 2 methods
A10: Core financials ($'000) — active scenario
B11: 1 | C11: 2 | D11: 3 | E11: 4 | F11: 5
A12: Revenue | B12: =SUMIF(Monthly!$C$5:$BJ$5,B$11,Monthly!$C$22:$BJ$22) -> 4506192 | C12: =SUMIF(Monthly!$C$5:$BJ$5,C$11,Monthly!$C$22:$BJ$22) -> 5835961.9 | D12: =SUMIF(Monthly!$C$5:$BJ$5,D$11,Monthly!$C$22:$BJ$22) -> 7569836 | E12: =SUMIF(Monthly!$C$5:$BJ$5,E$11,Monthly!$C$22:$BJ$22) -> 9833787.5 | F12: =SUMIF(Monthly!$C$5:$BJ$5,F$11,Monthly!$C$22:$BJ$22) -> 12793894
A13: Gross profit | B13: =SUMIF(Monthly!$C$5:$BJ$5,B$11,Monthly!$C$29:$BJ$29) -> 1803006.2 | C13: =SUMIF(Monthly!$C$5:$BJ$5,C$11,Monthly!$C$29:$BJ$29) -> 2345931 | D13: =SUMIF(Monthly!$C$5:$BJ$5,D$11,Monthly!$C$29:$BJ$29) -> 3056789.8 | E13: =SUMIF(Monthly!$C$5:$BJ$5,E$11,Monthly!$C$29:$BJ$29) -> 3988708.6 | F13: =SUMIF(Monthly!$C$5:$BJ$5,F$11,Monthly!$C$29:$BJ$29) -> 5211925.2
A14: Gross margin | B14: =IF(B12=0,0,B13/B12) -> 0.40011749 | C14: =IF(C12=0,0,C13/C12) -> 0.40197847 | D14: =IF(D12=0,0,D13/D12) -> 0.40381189 | E14: =IF(E12=0,0,E13/E12) -> 0.40561265 | F14: =IF(F12=0,0,F13/F12) -> 0.40737599
A15: Operating expenses | B15: =SUMIF(Monthly!$C$5:$BJ$5,B$11,Monthly!$C$37:$BJ$37) -> -752400 | C15: =SUMIF(Monthly!$C$5:$BJ$5,C$11,Monthly!$C$37:$BJ$37) -> -856317 | D15: =SUMIF(Monthly!$C$5:$BJ$5,D$11,Monthly!$C$37:$BJ$37) -> -982891.4 | E15: =SUMIF(Monthly!$C$5:$BJ$5,E$11,Monthly!$C$37:$BJ$37) -> -1137191.4 | F15: =SUMIF(Monthly!$C$5:$BJ$5,F$11,Monthly!$C$37:$BJ$37) -> -1325448.9
A16: EBITDA | B16: =SUMIF(Monthly!$C$5:$BJ$5,B$11,Monthly!$C$38:$BJ$38) -> 1050606.2 | C16: =SUMIF(Monthly!$C$5:$BJ$5,C$11,Monthly!$C$38:$BJ$38) -> 1489614 | D16: =SUMIF(Monthly!$C$5:$BJ$5,D$11,Monthly!$C$38:$BJ$38) -> 2073898.4 | E16: =SUMIF(Monthly!$C$5:$BJ$5,E$11,Monthly!$C$38:$BJ$38) -> 2851517.2 | F16: =SUMIF(Monthly!$C$5:$BJ$5,F$11,Monthly!$C$38:$BJ$38) -> 3886476.3
A17: EBITDA margin | B17: =IF(B12=0,0,B16/B12) -> 0.23314724 | C17: =IF(C12=0,0,C16/C12) -> 0.25524739 | D17: =IF(D12=0,0,D16/D12) -> 0.27396874 | E17: =IF(E12=0,0,E16/E12) -> 0.28997141 | F17: =IF(F12=0,0,F16/F12) -> 0.30377587
A18: Net income | B18: =SUMIF(Monthly!$C$5:$BJ$5,B$11,Monthly!$C$47:$BJ$47) -> 808921.04 | C18: =SUMIF(Monthly!$C$5:$BJ$5,C$11,Monthly!$C$47:$BJ$47) -> 1158256.4 | D18: =SUMIF(Monthly!$C$5:$BJ$5,D$11,Monthly!$C$47:$BJ$47) -> 1622369.1 | E18: =SUMIF(Monthly!$C$5:$BJ$5,E$11,Monthly!$C$47:$BJ$47) -> 2239215.9 | F18: =SUMIF(Monthly!$C$5:$BJ$5,F$11,Monthly!$C$47:$BJ$47) -> 3059361.6
A19: Net margin | B19: =IF(B12=0,0,B18/B12) -> 0.17951322 | C19: =IF(C12=0,0,C18/C12) -> 0.19846881 | D19: =IF(D12=0,0,D18/D12) -> 0.21432024 | E19: =IF(E12=0,0,E18/E12) -> 0.22770636 | F19: =IF(F12=0,0,F18/F12) -> 0.2391267
A20: Operating cash flow | B20: =SUMIF(Monthly!$C$5:$BJ$5,B$11,Monthly!$C$71:$BJ$71) -> 370279.78 | C20: =SUMIF(Monthly!$C$5:$BJ$5,C$11,Monthly!$C$71:$BJ$71) -> 1036820.4 | D20: =SUMIF(Monthly!$C$5:$BJ$5,D$11,Monthly!$C$71:$BJ$71) -> 1460260.5 | E20: =SUMIF(Monthly!$C$5:$BJ$5,E$11,Monthly!$C$71:$BJ$71) -> 2023723.4 | F20: =SUMIF(Monthly!$C$5:$BJ$5,F$11,Monthly!$C$71:$BJ$71) -> 2773718.7
A21: Investing cash flow | B21: =SUMIF(Monthly!$C$5:$BJ$5,B$11,Monthly!$C$72:$BJ$72) -> -60000 | C21: =SUMIF(Monthly!$C$5:$BJ$5,C$11,Monthly!$C$72:$BJ$72) -> 0 | D21: =SUMIF(Monthly!$C$5:$BJ$5,D$11,Monthly!$C$72:$BJ$72) -> 0 | E21: =SUMIF(Monthly!$C$5:$BJ$5,E$11,Monthly!$C$72:$BJ$72) -> 0 | F21: =SUMIF(Monthly!$C$5:$BJ$5,F$11,Monthly!$C$72:$BJ$72) -> 0
A22: Financing cash flow | B22: =SUMIF(Monthly!$C$5:$BJ$5,B$11,Monthly!$C$74:$BJ$74) -> 463333.33 | C22: =SUMIF(Monthly!$C$5:$BJ$5,C$11,Monthly!$C$74:$BJ$74) -> -40000 | D22: =SUMIF(Monthly!$C$5:$BJ$5,D$11,Monthly!$C$74:$BJ$74) -> -40000 | E22: =SUMIF(Monthly!$C$5:$BJ$5,E$11,Monthly!$C$74:$BJ$74) -> -40000 | F22: =SUMIF(Monthly!$C$5:$BJ$5,F$11,Monthly!$C$74:$BJ$74) -> -40000
A23: Net change in cash | B23: =SUMIF(Monthly!$C$5:$BJ$5,B$11,Monthly!$C$75:$BJ$75) -> 773613.11 | C23: =SUMIF(Monthly!$C$5:$BJ$5,C$11,Monthly!$C$75:$BJ$75) -> 996820.38 | D23: =SUMIF(Monthly!$C$5:$BJ$5,D$11,Monthly!$C$75:$BJ$75) -> 1420260.5 | E23: =SUMIF(Monthly!$C$5:$BJ$5,E$11,Monthly!$C$75:$BJ$75) -> 1983723.4 | F23: =SUMIF(Monthly!$C$5:$BJ$5,F$11,Monthly!$C$75:$BJ$75) -> 2733718.7
A24: Year-end cash | B24: =INDEX(Monthly!$C$77:$BJ$77,B$11*12) -> 773613.11 | C24: =INDEX(Monthly!$C$77:$BJ$77,C$11*12) -> 1770433.5 | D24: =INDEX(Monthly!$C$77:$BJ$77,D$11*12) -> 3190694 | E24: =INDEX(Monthly!$C$77:$BJ$77,E$11*12) -> 5174417.3 | F24: =INDEX(Monthly!$C$77:$BJ$77,F$11*12) -> 7908136
A26: Services metrics
B27: 1 | C27: 2 | D27: 3 | E27: 4 | F27: 5
A28: Billable hours | B28: =KPIs!B30 -> 24960 | C28: =KPIs!C30 -> 31572 | D28: =KPIs!D30 -> 39992.4 | E28: =KPIs!E30 -> 50728.68 | F28: =KPIs!F30 -> 64433.556
A29: Utilisation of billable employees | B29: =KPIs!B34 -> 0.7 | C29: =KPIs!C34 -> 0.70294118 | D29: =KPIs!D34 -> 0.70576037 | E29: =KPIs!E34 -> 0.70845655 | F29: =KPIs!F34 -> 0.71102952
A30: Effective rate per billable hour | B30: =KPIs!B41 -> 180.53654 | C30: =KPIs!C41 -> 184.84613 | D30: =KPIs!D41 -> 189.28186 | E30: =KPIs!E41 -> 193.85065 | F30: =KPIs!F41 -> 198.55949
A31: Revenue per billable FTE | B31: =KPIs!B42 -> 281637 | C31: =KPIs!C42 -> 286076.56 | D31: =KPIs!D42 -> 290700.31 | E31: =KPIs!E42 -> 295521.92 | F31: =KPIs!F42 -> 300554.74
A32: Team (FTE, year end) | B32: =INDEX(Headcount!$C$12:$BJ$12,B$27*12) -> 21 | C32: =INDEX(Headcount!$C$12:$BJ$12,C$27*12) -> 26.25 | D32: =INDEX(Headcount!$C$12:$BJ$12,D$27*12) -> 32.8875 | E32: =INDEX(Headcount!$C$12:$BJ$12,E$27*12) -> 41.294625 | F32: =INDEX(Headcount!$C$12:$BJ$12,F$27*12) -> 51.961819
A34: Funding & valuation ($'000) — active scenario
A35: Equity raised | F35: =Inputs!$E$54 -> 300000
A36: Loan drawn | F36: =Inputs!$E$55 -> 200000
A37: Funding required (incl. cash buffer) | F37: ='Break-even'!B12 -> 630319.68
A38: Funding surplus / (shortfall) | F38: ='Break-even'!B17 -> -130319.68
A39: ="Lowest cash balance (month "&'Break-even'!B6&")" -> Lowest cash balance (month 1) | F39: ='Break-even'!B18 -> 57680.317
A40: First month with positive EBITDA | F40: ='Break-even'!B21 -> 1
A41: Cash invested paid back | F41: ='Break-even'!B23 -> 8
A42: Enterprise value — perpetual growth | F42: =Valuation!B27 -> 14062289
A43: Enterprise value — exit multiple | F43: =Valuation!C27 -> 14612844
A44: Enterprise value — average | F44: =Valuation!B30 -> 14337567

Sheet Summary
A1: Financial statements summary | U1: =HYPERLINK("#'Cover'!A1","◂ Contents") -> ◂ Contents
A2: Professional services financial model (growing) | P2: Select detailed year: | R2: 1
A5: Income statement ($'000) — by year | H5: ="Income statement ($'000) — Year "&$R$2&", by month" -> Income statement ($'000) — Year 1, by month
B6: 1 | C6: 2 | D6: 3 | E6: 4 | F6: 5 | H6: =INDEX(Monthly!$C$4:$BJ$4,($R$2-1)*12+1) -> 1 | I6: =INDEX(Monthly!$C$4:$BJ$4,($R$2-1)*12+2) -> 2 | J6: =INDEX(Monthly!$C$4:$BJ$4,($R$2-1)*12+3) -> 3 | K6: =INDEX(Monthly!$C$4:$BJ$4,($R$2-1)*12+4) -> 4 | L6: =INDEX(Monthly!$C$4:$BJ$4,($R$2-1)*12+5) -> 5 | M6: =INDEX(Monthly!$C$4:$BJ$4,($R$2-1)*12+6) -> 6 | N6: =INDEX(Monthly!$C$4:$BJ$4,($R$2-1)*12+7) -> 7 | O6: =INDEX(Monthly!$C$4:$BJ$4,($R$2-1)*12+8) -> 8 | P6: =INDEX(Monthly!$C$4:$BJ$4,($R$2-1)*12+9) -> 9 | Q6: =INDEX(Monthly!$C$4:$BJ$4,($R$2-1)*12+10) -> 10 | R6: =INDEX(Monthly!$C$4:$BJ$4,($R$2-1)*12+11) -> 11 | S6: =INDEX(Monthly!$C$4:$BJ$4,($R$2-1)*12+12) -> 12
A7: Revenue | B7: ='P&L'!B5 -> 4506192 | C7: ='P&L'!C5 -> 5835961.9 | D7: ='P&L'!D5 -> 7569836 | E7: ='P&L'!E5 -> 9833787.5 | F7: ='P&L'!F5 -> 12793894 | H7: =INDEX(Monthly!$C$22:$BJ$22,($R$2-1)*12+1) -> 375516 | I7: =INDEX(Monthly!$C$22:$BJ$22,($R$2-1)*12+2) -> 375516 | J7: =INDEX(Monthly!$C$22:$BJ$22,($R$2-1)*12+3) -> 375516 | K7: =INDEX(Monthly!$C$22:$BJ$22,($R$2-1)*12+4) -> 375516 | L7: =INDEX(Monthly!$C$22:$BJ$22,($R$2-1)*12+5) -> 375516 | M7: =INDEX(Monthly!$C$22:$BJ$22,($R$2-1)*12+6) -> 375516 | N7: =INDEX(Monthly!$C$22:$BJ$22,($R$2-1)*12+7) -> 375516 | O7: =INDEX(Monthly!$C$22:$BJ$22,($R$2-1)*12+8) -> 375516 | P7: =INDEX(Monthly!$C$22:$BJ$22,($R$2-1)*12+9) -> 375516 | Q7: =INDEX(Monthly!$C$22:$BJ$22,($R$2-1)*12+10) -> 375516 | R7: =INDEX(Monthly!$C$22:$BJ$22,($R$2-1)*12+11) -> 375516 | S7: =INDEX(Monthly!$C$22:$BJ$22,($R$2-1)*12+12) -> 375516
A8: Cost of delivery | B8: ='P&L'!B6 -> -2703185.8 | C8: ='P&L'!C6 -> -3490030.9 | D8: ='P&L'!D6 -> -4513046.2 | E8: ='P&L'!E6 -> -5845079 | F8: ='P&L'!F6 -> -7581968.8 | H8: =INDEX(Monthly!$C$28:$BJ$28,($R$2-1)*12+1) -> -225265.48 | I8: =INDEX(Monthly!$C$28:$BJ$28,($R$2-1)*12+2) -> -225265.48 | J8: =INDEX(Monthly!$C$28:$BJ$28,($R$2-1)*12+3) -> -225265.48 | K8: =INDEX(Monthly!$C$28:$BJ$28,($R$2-1)*12+4) -> -225265.48 | L8: =INDEX(Monthly!$C$28:$BJ$28,($R$2-1)*12+5) -> -225265.48 | M8: =INDEX(Monthly!$C$28:$BJ$28,($R$2-1)*12+6) -> -225265.48 | N8: =INDEX(Monthly!$C$28:$BJ$28,($R$2-1)*12+7) -> -225265.48 | O8: =INDEX(Monthly!$C$28:$BJ$28,($R$2-1)*12+8) -> -225265.48 | P8: =INDEX(Monthly!$C$28:$BJ$28,($R$2-1)*12+9) -> -225265.48 | Q8: =INDEX(Monthly!$C$28:$BJ$28,($R$2-1)*12+10) -> -225265.48 | R8: =INDEX(Monthly!$C$28:$BJ$28,($R$2-1)*12+11) -> -225265.48 | S8: =INDEX(Monthly!$C$28:$BJ$28,($R$2-1)*12+12) -> -225265.48
A9: Gross profit | B9: ='P&L'!B7 -> 1803006.2 | C9: ='P&L'!C7 -> 2345931 | D9: ='P&L'!D7 -> 3056789.8 | E9: ='P&L'!E7 -> 3988708.6 | F9: ='P&L'!F7 -> 5211925.2 | H9: =INDEX(Monthly!$C$29:$BJ$29,($R$2-1)*12+1) -> 150250.52 | I9: =INDEX(Monthly!$C$29:$BJ$29,($R$2-1)*12+2) -> 150250.52 | J9: =INDEX(Monthly!$C$29:$BJ$29,($R$2-1)*12+3) -> 150250.52 | K9: =INDEX(Monthly!$C$29:$BJ$29,($R$2-1)*12+4) -> 150250.52 | L9: =INDEX(Monthly!$C$29:$BJ$29,($R$2-1)*12+5) -> 150250.52 | M9: =INDEX(Monthly!$C$29:$BJ$29,($R$2-1)*12+6) -> 150250.52 | N9: =INDEX(Monthly!$C$29:$BJ$29,($R$2-1)*12+7) -> 150250.52 | O9: =INDEX(Monthly!$C$29:$BJ$29,($R$2-1)*12+8) -> 150250.52 | P9: =INDEX(Monthly!$C$29:$BJ$29,($R$2-1)*12+9) -> 150250.52 | Q9: =INDEX(Monthly!$C$29:$BJ$29,($R$2-1)*12+10) -> 150250.52 | R9: =INDEX(Monthly!$C$29:$BJ$29,($R$2-1)*12+11) -> 150250.52 | S9: =INDEX(Monthly!$C$29:$BJ$29,($R$2-1)*12+12) -> 150250.52
A10: Gross margin | B10: ='P&L'!B8 -> 0.40011749 | C10: ='P&L'!C8 -> 0.40197847 | D10: ='P&L'!D8 -> 0.40381189 | E10: ='P&L'!E8 -> 0.40561265 | F10: ='P&L'!F8 -> 0.40737599 | H10: =IF(H7=0,0,H9/H7) -> 0.40011749 | I10: =IF(I7=0,0,I9/I7) -> 0.40011749 | J10: =IF(J7=0,0,J9/J7) -> 0.40011749 | K10: =IF(K7=0,0,K9/K7) -> 0.40011749 | L10: =IF(L7=0,0,L9/L7) -> 0.40011749 | M10: =IF(M7=0,0,M9/M7) -> 0.40011749 | N10: =IF(N7=0,0,N9/N7) -> 0.40011749 | O10: =IF(O7=0,0,O9/O7) -> 0.40011749 | ... S10: =IF(S7=0,0,S9/S7) -> 0.40011749
A11: Total operating expenses | B11: ='P&L'!B14 -> -752400 | C11: ='P&L'!C14 -> -856317 | D11: ='P&L'!D14 -> -982891.4 | E11: ='P&L'!E14 -> -1137191.4 | F11: ='P&L'!F14 -> -1325448.9 | H11: =INDEX(Monthly!$C$37:$BJ$37,($R$2-1)*12+1) -> -62700 | I11: =INDEX(Monthly!$C$37:$BJ$37,($R$2-1)*12+2) -> -62700 | J11: =INDEX(Monthly!$C$37:$BJ$37,($R$2-1)*12+3) -> -62700 | K11: =INDEX(Monthly!$C$37:$BJ$37,($R$2-1)*12+4) -> -62700 | L11: =INDEX(Monthly!$C$37:$BJ$37,($R$2-1)*12+5) -> -62700 | M11: =INDEX(Monthly!$C$37:$BJ$37,($R$2-1)*12+6) -> -62700 | N11: =INDEX(Monthly!$C$37:$BJ$37,($R$2-1)*12+7) -> -62700 | O11: =INDEX(Monthly!$C$37:$BJ$37,($R$2-1)*12+8) -> -62700 | P11: =INDEX(Monthly!$C$37:$BJ$37,($R$2-1)*12+9) -> -62700 | Q11: =INDEX(Monthly!$C$37:$BJ$37,($R$2-1)*12+10) -> -62700 | R11: =INDEX(Monthly!$C$37:$BJ$37,($R$2-1)*12+11) -> -62700 | S11: =INDEX(Monthly!$C$37:$BJ$37,($R$2-1)*12+12) -> -62700
A12: EBITDA | B12: ='P&L'!B15 -> 1050606.2 | C12: ='P&L'!C15 -> 1489614 | D12: ='P&L'!D15 -> 2073898.4 | E12: ='P&L'!E15 -> 2851517.2 | F12: ='P&L'!F15 -> 3886476.3 | H12: =INDEX(Monthly!$C$38:$BJ$38,($R$2-1)*12+1) -> 87550.52 | I12: =INDEX(Monthly!$C$38:$BJ$38,($R$2-1)*12+2) -> 87550.52 | J12: =INDEX(Monthly!$C$38:$BJ$38,($R$2-1)*12+3) -> 87550.52 | K12: =INDEX(Monthly!$C$38:$BJ$38,($R$2-1)*12+4) -> 87550.52 | L12: =INDEX(Monthly!$C$38:$BJ$38,($R$2-1)*12+5) -> 87550.52 | M12: =INDEX(Monthly!$C$38:$BJ$38,($R$2-1)*12+6) -> 87550.52 | N12: =INDEX(Monthly!$C$38:$BJ$38,($R$2-1)*12+7) -> 87550.52 | O12: =INDEX(Monthly!$C$38:$BJ$38,($R$2-1)*12+8) -> 87550.52 | P12: =INDEX(Monthly!$C$38:$BJ$38,($R$2-1)*12+9) -> 87550.52 | Q12: =INDEX(Monthly!$C$38:$BJ$38,($R$2-1)*12+10) -> 87550.52 | R12: =INDEX(Monthly!$C$38:$BJ$38,($R$2-1)*12+11) -> 87550.52 | S12: =INDEX(Monthly!$C$38:$BJ$38,($R$2-1)*12+12) -> 87550.52
A13: EBITDA margin | B13: ='P&L'!B16 -> 0.23314724 | C13: ='P&L'!C16 -> 0.25524739 | D13: ='P&L'!D16 -> 0.27396874 | E13: ='P&L'!E16 -> 0.28997141 | F13: ='P&L'!F16 -> 0.30377587 | H13: =IF(H7=0,0,H12/H7) -> 0.23314724 | I13: =IF(I7=0,0,I12/I7) -> 0.23314724 | J13: =IF(J7=0,0,J12/J7) -> 0.23314724 | K13: =IF(K7=0,0,K12/K7) -> 0.23314724 | L13: =IF(L7=0,0,L12/L7) -> 0.23314724 | M13: =IF(M7=0,0,M12/M7) -> 0.23314724 | N13: =IF(N7=0,0,N12/N7) -> 0.23314724 | O13: =IF(O7=0,0,O12/O7) -> 0.23314724 | ... S13: =IF(S7=0,0,S12/S7) -> 0.23314724
A14: Depreciation | B14: ='P&L'!B17 -> -12000 | C14: ='P&L'!C17 -> -12000 | D14: ='P&L'!D17 -> -12000 | E14: ='P&L'!E17 -> -12000 | F14: ='P&L'!F17 -> -12000 | H14: =INDEX(Monthly!$C$52:$BJ$52,($R$2-1)*12+1) -> -1000 | I14: =INDEX(Monthly!$C$52:$BJ$52,($R$2-1)*12+2) -> -1000 | J14: =INDEX(Monthly!$C$52:$BJ$52,($R$2-1)*12+3) -> -1000 | K14: =INDEX(Monthly!$C$52:$BJ$52,($R$2-1)*12+4) -> -1000 | L14: =INDEX(Monthly!$C$52:$BJ$52,($R$2-1)*12+5) -> -1000 | M14: =INDEX(Monthly!$C$52:$BJ$52,($R$2-1)*12+6) -> -1000 | N14: =INDEX(Monthly!$C$52:$BJ$52,($R$2-1)*12+7) -> -1000 | O14: =INDEX(Monthly!$C$52:$BJ$52,($R$2-1)*12+8) -> -1000 | P14: =INDEX(Monthly!$C$52:$BJ$52,($R$2-1)*12+9) -> -1000 | Q14: =INDEX(Monthly!$C$52:$BJ$52,($R$2-1)*12+10) -> -1000 | R14: =INDEX(Monthly!$C$52:$BJ$52,($R$2-1)*12+11) -> -1000 | S14: =INDEX(Monthly!$C$52:$BJ$52,($R$2-1)*12+12) -> -1000
A15: EBIT | B15: ='P&L'!B18 -> 1038606.2 | C15: ='P&L'!C18 -> 1477614 | D15: ='P&L'!D18 -> 2061898.4 | E15: ='P&L'!E18 -> 2839517.2 | F15: ='P&L'!F18 -> 3874476.3 | H15: =INDEX(Monthly!$C$41:$BJ$41,($R$2-1)*12+1) -> 86550.52 | I15: =INDEX(Monthly!$C$41:$BJ$41,($R$2-1)*12+2) -> 86550.52 | J15: =INDEX(Monthly!$C$41:$BJ$41,($R$2-1)*12+3) -> 86550.52 | K15: =INDEX(Monthly!$C$41:$BJ$41,($R$2-1)*12+4) -> 86550.52 | L15: =INDEX(Monthly!$C$41:$BJ$41,($R$2-1)*12+5) -> 86550.52 | M15: =INDEX(Monthly!$C$41:$BJ$41,($R$2-1)*12+6) -> 86550.52 | N15: =INDEX(Monthly!$C$41:$BJ$41,($R$2-1)*12+7) -> 86550.52 | O15: =INDEX(Monthly!$C$41:$BJ$41,($R$2-1)*12+8) -> 86550.52 | P15: =INDEX(Monthly!$C$41:$BJ$41,($R$2-1)*12+9) -> 86550.52 | Q15: =INDEX(Monthly!$C$41:$BJ$41,($R$2-1)*12+10) -> 86550.52 | R15: =INDEX(Monthly!$C$41:$BJ$41,($R$2-1)*12+11) -> 86550.52 | S15: =INDEX(Monthly!$C$41:$BJ$41,($R$2-1)*12+12) -> 86550.52
A16: Interest | B16: ='P&L'!B19 -> -14655.556 | C16: ='P&L'!C19 -> -11466.667 | D16: ='P&L'!D19 -> -8266.6667 | E16: ='P&L'!E19 -> -5066.6667 | F16: ='P&L'!F19 -> -1866.6667 | H16: =INDEX(Monthly!$C$42:$BJ$42,($R$2-1)*12+1) -> -1333.3333 | I16: =INDEX(Monthly!$C$42:$BJ$42,($R$2-1)*12+2) -> -1322.2222 | J16: =INDEX(Monthly!$C$42:$BJ$42,($R$2-1)*12+3) -> -1300 | K16: =INDEX(Monthly!$C$42:$BJ$42,($R$2-1)*12+4) -> -1277.7778 | L16: =INDEX(Monthly!$C$42:$BJ$42,($R$2-1)*12+5) -> -1255.5556 | M16: =INDEX(Monthly!$C$42:$BJ$42,($R$2-1)*12+6) -> -1233.3333 | N16: =INDEX(Monthly!$C$42:$BJ$42,($R$2-1)*12+7) -> -1211.1111 | O16: =INDEX(Monthly!$C$42:$BJ$42,($R$2-1)*12+8) -> -1188.8889 | P16: =INDEX(Monthly!$C$42:$BJ$42,($R$2-1)*12+9) -> -1166.6667 | Q16: =INDEX(Monthly!$C$42:$BJ$42,($R$2-1)*12+10) -> -1144.4444 | R16: =INDEX(Monthly!$C$42:$BJ$42,($R$2-1)*12+11) -> -1122.2222 | S16: =INDEX(Monthly!$C$42:$BJ$42,($R$2-1)*12+12) -> -1100
A17: Pre-tax income | B17: ='P&L'!B20 -> 1023950.7 | C17: ='P&L'!C20 -> 1466147.3 | D17: ='P&L'!D20 -> 2053631.8 | E17: ='P&L'!E20 -> 2834450.6 | F17: ='P&L'!F20 -> 3872609.6 | H17: =INDEX(Monthly!$C$43:$BJ$43,($R$2-1)*12+1) -> 85217.187 | I17: =INDEX(Monthly!$C$43:$BJ$43,($R$2-1)*12+2) -> 85228.298 | J17: =INDEX(Monthly!$C$43:$BJ$43,($R$2-1)*12+3) -> 85250.52 | K17: =INDEX(Monthly!$C$43:$BJ$43,($R$2-1)*12+4) -> 85272.742 | L17: =INDEX(Monthly!$C$43:$BJ$43,($R$2-1)*12+5) -> 85294.964 | M17: =INDEX(Monthly!$C$43:$BJ$43,($R$2-1)*12+6) -> 85317.187 | N17: =INDEX(Monthly!$C$43:$BJ$43,($R$2-1)*12+7) -> 85339.409 | O17: =INDEX(Monthly!$C$43:$BJ$43,($R$2-1)*12+8) -> 85361.631 | P17: =INDEX(Monthly!$C$43:$BJ$43,($R$2-1)*12+9) -> 85383.853 | Q17: =INDEX(Monthly!$C$43:$BJ$43,($R$2-1)*12+10) -> 85406.076 | R17: =INDEX(Monthly!$C$43:$BJ$43,($R$2-1)*12+11) -> 85428.298 | S17: =INDEX(Monthly!$C$43:$BJ$43,($R$2-1)*12+12) -> 85450.52
A18: Income tax | B18: ='P&L'!B21 -> -215029.64 | C18: ='P&L'!C21 -> -307890.94 | D18: ='P&L'!D21 -> -431262.67 | E18: ='P&L'!E21 -> -595234.62 | F18: ='P&L'!F21 -> -813248.02 | H18: =INDEX(Monthly!$C$46:$BJ$46,($R$2-1)*12+1) -> -17895.609 | I18: =INDEX(Monthly!$C$46:$BJ$46,($R$2-1)*12+2) -> -17897.943 | J18: =INDEX(Monthly!$C$46:$BJ$46,($R$2-1)*12+3) -> -17902.609 | K18: =INDEX(Monthly!$C$46:$BJ$46,($R$2-1)*12+4) -> -17907.276 | L18: =INDEX(Monthly!$C$46:$BJ$46,($R$2-1)*12+5) -> -17911.943 | M18: =INDEX(Monthly!$C$46:$BJ$46,($R$2-1)*12+6) -> -17916.609 | N18: =INDEX(Monthly!$C$46:$BJ$46,($R$2-1)*12+7) -> -17921.276 | O18: =INDEX(Monthly!$C$46:$BJ$46,($R$2-1)*12+8) -> -17925.943 | P18: =INDEX(Monthly!$C$46:$BJ$46,($R$2-1)*12+9) -> -17930.609 | Q18: =INDEX(Monthly!$C$46:$BJ$46,($R$2-1)*12+10) -> -17935.276 | R18: =INDEX(Monthly!$C$46:$BJ$46,($R$2-1)*12+11) -> -17939.943 | S18: =INDEX(Monthly!$C$46:$BJ$46,($R$2-1)*12+12) -> -17944.609
A19: Net income | B19: ='P&L'!B22 -> 808921.04 | C19: ='P&L'!C22 -> 1158256.4 | D19: ='P&L'!D22 -> 1622369.1 | E19: ='P&L'!E22 -> 2239215.9 | F19: ='P&L'!F22 -> 3059361.6 | H19: =INDEX(Monthly!$C$47:$BJ$47,($R$2-1)*12+1) -> 67321.577 | I19: =INDEX(Monthly!$C$47:$BJ$47,($R$2-1)*12+2) -> 67330.355 | J19: =INDEX(Monthly!$C$47:$BJ$47,($R$2-1)*12+3) -> 67347.911 | K19: =INDEX(Monthly!$C$47:$BJ$47,($R$2-1)*12+4) -> 67365.466 | L19: =INDEX(Monthly!$C$47:$BJ$47,($R$2-1)*12+5) -> 67383.022 | M19: =INDEX(Monthly!$C$47:$BJ$47,($R$2-1)*12+6) -> 67400.577 | N19: =INDEX(Monthly!$C$47:$BJ$47,($R$2-1)*12+7) -> 67418.133 | O19: =INDEX(Monthly!$C$47:$BJ$47,($R$2-1)*12+8) -> 67435.689 | P19: =INDEX(Monthly!$C$47:$BJ$47,($R$2-1)*12+9) -> 67453.244 | Q19: =INDEX(Monthly!$C$47:$BJ$47,($R$2-1)*12+10) -> 67470.8 | R19: =INDEX(Monthly!$C$47:$BJ$47,($R$2-1)*12+11) -> 67488.355 | S19: =INDEX(Monthly!$C$47:$BJ$47,($R$2-1)*12+12) -> 67505.911
A20: Net margin | B20: ='P&L'!B23 -> 0.17951322 | C20: ='P&L'!C23 -> 0.19846881 | D20: ='P&L'!D23 -> 0.21432024 | E20: ='P&L'!E23 -> 0.22770636 | F20: ='P&L'!F23 -> 0.2391267 | H20: =IF(H7=0,0,H19/H7) -> 0.17927752 | I20: =IF(I7=0,0,I19/I7) -> 0.1793009 | J20: =IF(J7=0,0,J19/J7) -> 0.17934765 | K20: =IF(K7=0,0,K19/K7) -> 0.1793944 | L20: =IF(L7=0,0,L19/L7) -> 0.17944115 | M20: =IF(M7=0,0,M19/M7) -> 0.1794879 | N20: =IF(N7=0,0,N19/N7) -> 0.17953465 | O20: =IF(O7=0,0,O19/O7) -> 0.1795814 | ... S20: =IF(S7=0,0,S19/S7) -> 0.1797684
A22: Cash flow ($'000) — by year | H22: ="Cash flow ($'000) — Year "&$R$2&", by month" -> Cash flow ($'000) — Year 1, by month
B23: 1 | C23: 2 | D23: 3 | E23: 4 | F23: 5 | H23: =INDEX(Monthly!$C$4:$BJ$4,($R$2-1)*12+1) -> 1 | I23: =INDEX(Monthly!$C$4:$BJ$4,($R$2-1)*12+2) -> 2 | J23: =INDEX(Monthly!$C$4:$BJ$4,($R$2-1)*12+3) -> 3 | K23: =INDEX(Monthly!$C$4:$BJ$4,($R$2-1)*12+4) -> 4 | L23: =INDEX(Monthly!$C$4:$BJ$4,($R$2-1)*12+5) -> 5 | M23: =INDEX(Monthly!$C$4:$BJ$4,($R$2-1)*12+6) -> 6 | N23: =INDEX(Monthly!$C$4:$BJ$4,($R$2-1)*12+7) -> 7 | O23: =INDEX(Monthly!$C$4:$BJ$4,($R$2-1)*12+8) -> 8 | P23: =INDEX(Monthly!$C$4:$BJ$4,($R$2-1)*12+9) -> 9 | Q23: =INDEX(Monthly!$C$4:$BJ$4,($R$2-1)*12+10) -> 10 | R23: =INDEX(Monthly!$C$4:$BJ$4,($R$2-1)*12+11) -> 11 | S23: =INDEX(Monthly!$C$4:$BJ$4,($R$2-1)*12+12) -> 12
A24: Operating cash flow | B24: ='Cash Flow'!B10 -> 370279.78 | C24: ='Cash Flow'!C10 -> 1036820.4 | D24: ='Cash Flow'!D10 -> 1460260.5 | E24: ='Cash Flow'!E10 -> 2023723.4 | F24: ='Cash Flow'!F10 -> 2773718.7 | H24: =INDEX(Monthly!$C$71:$BJ$71,($R$2-1)*12+1) -> -382319.68 | I24: =INDEX(Monthly!$C$71:$BJ$71,($R$2-1)*12+2) -> 68330.355 | J24: =INDEX(Monthly!$C$71:$BJ$71,($R$2-1)*12+3) -> 68347.911 | K24: =INDEX(Monthly!$C$71:$BJ$71,($R$2-1)*12+4) -> 68365.466 | L24: =INDEX(Monthly!$C$71:$BJ$71,($R$2-1)*12+5) -> 68383.022 | M24: =INDEX(Monthly!$C$71:$BJ$71,($R$2-1)*12+6) -> 68400.577 | N24: =INDEX(Monthly!$C$71:$BJ$71,($R$2-1)*12+7) -> 68418.133 | O24: =INDEX(Monthly!$C$71:$BJ$71,($R$2-1)*12+8) -> 68435.689 | P24: =INDEX(Monthly!$C$71:$BJ$71,($R$2-1)*12+9) -> 68453.244 | Q24: =INDEX(Monthly!$C$71:$BJ$71,($R$2-1)*12+10) -> 68470.8 | R24: =INDEX(Monthly!$C$71:$BJ$71,($R$2-1)*12+11) -> 68488.355 | S24: =INDEX(Monthly!$C$71:$BJ$71,($R$2-1)*12+12) -> 68505.911
A25: Capital spending | B25: ='Cash Flow'!B11 -> -60000 | C25: ='Cash Flow'!C11 -> 0 | D25: ='Cash Flow'!D11 -> 0 | E25: ='Cash Flow'!E11 -> 0 | F25: ='Cash Flow'!F11 -> 0 | H25: =INDEX(Monthly!$C$72:$BJ$72,($R$2-1)*12+1) -> -60000 | I25: =INDEX(Monthly!$C$72:$BJ$72,($R$2-1)*12+2) -> 0 | J25: =INDEX(Monthly!$C$72:$BJ$72,($R$2-1)*12+3) -> 0 | K25: =INDEX(Monthly!$C$72:$BJ$72,($R$2-1)*12+4) -> 0 | L25: =INDEX(Monthly!$C$72:$BJ$72,($R$2-1)*12+5) -> 0 | M25: =INDEX(Monthly!$C$72:$BJ$72,($R$2-1)*12+6) -> 0 | N25: =INDEX(Monthly!$C$72:$BJ$72,($R$2-1)*12+7) -> 0 | O25: =INDEX(Monthly!$C$72:$BJ$72,($R$2-1)*12+8) -> 0 | P25: =INDEX(Monthly!$C$72:$BJ$72,($R$2-1)*12+9) -> 0 | Q25: =INDEX(Monthly!$C$72:$BJ$72,($R$2-1)*12+10) -> 0 | R25: =INDEX(Monthly!$C$72:$BJ$72,($R$2-1)*12+11) -> 0 | S25: =INDEX(Monthly!$C$72:$BJ$72,($R$2-1)*12+12) -> 0
A26: Equity raised | B26: ='Cash Flow'!B12 -> 300000 | C26: ='Cash Flow'!C12 -> 0 | D26: ='Cash Flow'!D12 -> 0 | E26: ='Cash Flow'!E12 -> 0 | F26: ='Cash Flow'!F12 -> 0 | H26: =INDEX(Monthly!$C$73:$BJ$73,($R$2-1)*12+1) -> 300000 | I26: =INDEX(Monthly!$C$73:$BJ$73,($R$2-1)*12+2) -> 0 | J26: =INDEX(Monthly!$C$73:$BJ$73,($R$2-1)*12+3) -> 0 | K26: =INDEX(Monthly!$C$73:$BJ$73,($R$2-1)*12+4) -> 0 | L26: =INDEX(Monthly!$C$73:$BJ$73,($R$2-1)*12+5) -> 0 | M26: =INDEX(Monthly!$C$73:$BJ$73,($R$2-1)*12+6) -> 0 | N26: =INDEX(Monthly!$C$73:$BJ$73,($R$2-1)*12+7) -> 0 | O26: =INDEX(Monthly!$C$73:$BJ$73,($R$2-1)*12+8) -> 0 | P26: =INDEX(Monthly!$C$73:$BJ$73,($R$2-1)*12+9) -> 0 | Q26: =INDEX(Monthly!$C$73:$BJ$73,($R$2-1)*12+10) -> 0 | R26: =INDEX(Monthly!$C$73:$BJ$73,($R$2-1)*12+11) -> 0 | S26: =INDEX(Monthly!$C$73:$BJ$73,($R$2-1)*12+12) -> 0
A27: Loan drawdown | B27: ='Cash Flow'!B13 -> 200000 | C27: ='Cash Flow'!C13 -> 0 | D27: ='Cash Flow'!D13 -> 0 | E27: ='Cash Flow'!E13 -> 0 | F27: ='Cash Flow'!F13 -> 0 | H27: =INDEX(Monthly!$C$58:$BJ$58,($R$2-1)*12+1) -> 200000 | I27: =INDEX(Monthly!$C$58:$BJ$58,($R$2-1)*12+2) -> 0 | J27: =INDEX(Monthly!$C$58:$BJ$58,($R$2-1)*12+3) -> 0 | K27: =INDEX(Monthly!$C$58:$BJ$58,($R$2-1)*12+4) -> 0 | L27: =INDEX(Monthly!$C$58:$BJ$58,($R$2-1)*12+5) -> 0 | M27: =INDEX(Monthly!$C$58:$BJ$58,($R$2-1)*12+6) -> 0 | N27: =INDEX(Monthly!$C$58:$BJ$58,($R$2-1)*12+7) -> 0 | O27: =INDEX(Monthly!$C$58:$BJ$58,($R$2-1)*12+8) -> 0 | P27: =INDEX(Monthly!$C$58:$BJ$58,($R$2-1)*12+9) -> 0 | Q27: =INDEX(Monthly!$C$58:$BJ$58,($R$2-1)*12+10) -> 0 | R27: =INDEX(Monthly!$C$58:$BJ$58,($R$2-1)*12+11) -> 0 | S27: =INDEX(Monthly!$C$58:$BJ$58,($R$2-1)*12+12) -> 0
A28: Loan repayment | B28: ='Cash Flow'!B14 -> -36666.667 | C28: ='Cash Flow'!C14 -> -40000 | D28: ='Cash Flow'!D14 -> -40000 | E28: ='Cash Flow'!E14 -> -40000 | F28: ='Cash Flow'!F14 -> -40000 | H28: =INDEX(Monthly!$C$59:$BJ$59,($R$2-1)*12+1) -> 0 | I28: =INDEX(Monthly!$C$59:$BJ$59,($R$2-1)*12+2) -> -3333.3333 | J28: =INDEX(Monthly!$C$59:$BJ$59,($R$2-1)*12+3) -> -3333.3333 | K28: =INDEX(Monthly!$C$59:$BJ$59,($R$2-1)*12+4) -> -3333.3333 | L28: =INDEX(Monthly!$C$59:$BJ$59,($R$2-1)*12+5) -> -3333.3333 | M28: =INDEX(Monthly!$C$59:$BJ$59,($R$2-1)*12+6) -> -3333.3333 | N28: =INDEX(Monthly!$C$59:$BJ$59,($R$2-1)*12+7) -> -3333.3333 | O28: =INDEX(Monthly!$C$59:$BJ$59,($R$2-1)*12+8) -> -3333.3333 | P28: =INDEX(Monthly!$C$59:$BJ$59,($R$2-1)*12+9) -> -3333.3333 | Q28: =INDEX(Monthly!$C$59:$BJ$59,($R$2-1)*12+10) -> -3333.3333 | R28: =INDEX(Monthly!$C$59:$BJ$59,($R$2-1)*12+11) -> -3333.3333 | S28: =INDEX(Monthly!$C$59:$BJ$59,($R$2-1)*12+12) -> -3333.3333
A29: Financing cash flow | B29: ='Cash Flow'!B15 -> 463333.33 | C29: ='Cash Flow'!C15 -> -40000 | D29: ='Cash Flow'!D15 -> -40000 | E29: ='Cash Flow'!E15 -> -40000 | F29: ='Cash Flow'!F15 -> -40000 | H29: =INDEX(Monthly!$C$74:$BJ$74,($R$2-1)*12+1) -> 500000 | I29: =INDEX(Monthly!$C$74:$BJ$74,($R$2-1)*12+2) -> -3333.3333 | J29: =INDEX(Monthly!$C$74:$BJ$74,($R$2-1)*12+3) -> -3333.3333 | K29: =INDEX(Monthly!$C$74:$BJ$74,($R$2-1)*12+4) -> -3333.3333 | L29: =INDEX(Monthly!$C$74:$BJ$74,($R$2-1)*12+5) -> -3333.3333 | M29: =INDEX(Monthly!$C$74:$BJ$74,($R$2-1)*12+6) -> -3333.3333 | N29: =INDEX(Monthly!$C$74:$BJ$74,($R$2-1)*12+7) -> -3333.3333 | O29: =INDEX(Monthly!$C$74:$BJ$74,($R$2-1)*12+8) -> -3333.3333 | P29: =INDEX(Monthly!$C$74:$BJ$74,($R$2-1)*12+9) -> -3333.3333 | Q29: =INDEX(Monthly!$C$74:$BJ$74,($R$2-1)*12+10) -> -3333.3333 | R29: =INDEX(Monthly!$C$74:$BJ$74,($R$2-1)*12+11) -> -3333.3333 | S29: =INDEX(Monthly!$C$74:$BJ$74,($R$2-1)*12+12) -> -3333.3333
A30: Net change in cash | B30: ='Cash Flow'!B16 -> 773613.11 | C30: ='Cash Flow'!C16 -> 996820.38 | D30: ='Cash Flow'!D16 -> 1420260.5 | E30: ='Cash Flow'!E16 -> 1983723.4 | F30: ='Cash Flow'!F16 -> 2733718.7 | H30: =INDEX(Monthly!$C$75:$BJ$75,($R$2-1)*12+1) -> 57680.317 | I30: =INDEX(Monthly!$C$75:$BJ$75,($R$2-1)*12+2) -> 64997.022 | J30: =INDEX(Monthly!$C$75:$BJ$75,($R$2-1)*12+3) -> 65014.577 | K30: =INDEX(Monthly!$C$75:$BJ$75,($R$2-1)*12+4) -> 65032.133 | L30: =INDEX(Monthly!$C$75:$BJ$75,($R$2-1)*12+5) -> 65049.689 | M30: =INDEX(Monthly!$C$75:$BJ$75,($R$2-1)*12+6) -> 65067.244 | N30: =INDEX(Monthly!$C$75:$BJ$75,($R$2-1)*12+7) -> 65084.8 | O30: =INDEX(Monthly!$C$75:$BJ$75,($R$2-1)*12+8) -> 65102.355 | P30: =INDEX(Monthly!$C$75:$BJ$75,($R$2-1)*12+9) -> 65119.911 | Q30: =INDEX(Monthly!$C$75:$BJ$75,($R$2-1)*12+10) -> 65137.466 | R30: =INDEX(Monthly!$C$75:$BJ$75,($R$2-1)*12+11) -> 65155.022 | S30: =INDEX(Monthly!$C$75:$BJ$75,($R$2-1)*12+12) -> 65172.577
A31: Closing cash | B31: ='Cash Flow'!B18 -> 773613.11 | C31: ='Cash Flow'!C18 -> 1770433.5 | D31: ='Cash Flow'!D18 -> 3190694 | E31: ='Cash Flow'!E18 -> 5174417.3 | F31: ='Cash Flow'!F18 -> 7908136 | H31: =INDEX(Monthly!$C$77:$BJ$77,($R$2-1)*12+1) -> 57680.317 | I31: =INDEX(Monthly!$C$77:$BJ$77,($R$2-1)*12+2) -> 122677.34 | J31: =INDEX(Monthly!$C$77:$BJ$77,($R$2-1)*12+3) -> 187691.92 | K31: =INDEX(Monthly!$C$77:$BJ$77,($R$2-1)*12+4) -> 252724.05 | L31: =INDEX(Monthly!$C$77:$BJ$77,($R$2-1)*12+5) -> 317773.74 | M31: =INDEX(Monthly!$C$77:$BJ$77,($R$2-1)*12+6) -> 382840.98 | N31: =INDEX(Monthly!$C$77:$BJ$77,($R$2-1)*12+7) -> 447925.78 | O31: =INDEX(Monthly!$C$77:$BJ$77,($R$2-1)*12+8) -> 513028.14 | P31: =INDEX(Monthly!$C$77:$BJ$77,($R$2-1)*12+9) -> 578148.05 | Q31: =INDEX(Monthly!$C$77:$BJ$77,($R$2-1)*12+10) -> 643285.51 | R31: =INDEX(Monthly!$C$77:$BJ$77,($R$2-1)*12+11) -> 708440.54 | S31: =INDEX(Monthly!$C$77:$BJ$77,($R$2-1)*12+12) -> 773613.11
A39: Balance sheet at year end ($'000) | H39: ="Balance sheet at month end ($'000) — Year "&$R$2 -> Balance sheet at month end ($'000) — Year 1
B40: 1 | C40: 2 | D40: 3 | E40: 4 | F40: 5 | H40: =INDEX(Monthly!$C$4:$BJ$4,($R$2-1)*12+1) -> 1 | I40: =INDEX(Monthly!$C$4:$BJ$4,($R$2-1)*12+2) -> 2 | J40: =INDEX(Monthly!$C$4:$BJ$4,($R$2-1)*12+3) -> 3 | K40: =INDEX(Monthly!$C$4:$BJ$4,($R$2-1)*12+4) -> 4 | L40: =INDEX(Monthly!$C$4:$BJ$4,($R$2-1)*12+5) -> 5 | M40: =INDEX(Monthly!$C$4:$BJ$4,($R$2-1)*12+6) -> 6 | N40: =INDEX(Monthly!$C$4:$BJ$4,($R$2-1)*12+7) -> 7 | O40: =INDEX(Monthly!$C$4:$BJ$4,($R$2-1)*12+8) -> 8 | P40: =INDEX(Monthly!$C$4:$BJ$4,($R$2-1)*12+9) -> 9 | Q40: =INDEX(Monthly!$C$4:$BJ$4,($R$2-1)*12+10) -> 10 | R40: =INDEX(Monthly!$C$4:$BJ$4,($R$2-1)*12+11) -> 11 | S40: =INDEX(Monthly!$C$4:$BJ$4,($R$2-1)*12+12) -> 12
A41: Cash | B41: ='Balance Sheet'!B5 -> 773613.11 | C41: ='Balance Sheet'!C5 -> 1770433.5 | D41: ='Balance Sheet'!D5 -> 3190694 | E41: ='Balance Sheet'!E5 -> 5174417.3 | F41: ='Balance Sheet'!F5 -> 7908136 | H41: =INDEX(Monthly!$C$77:$BJ$77,($R$2-1)*12+1) -> 57680.317 | I41: =INDEX(Monthly!$C$77:$BJ$77,($R$2-1)*12+2) -> 122677.34 | J41: =INDEX(Monthly!$C$77:$BJ$77,($R$2-1)*12+3) -> 187691.92 | K41: =INDEX(Monthly!$C$77:$BJ$77,($R$2-1)*12+4) -> 252724.05 | L41: =INDEX(Monthly!$C$77:$BJ$77,($R$2-1)*12+5) -> 317773.74 | M41: =INDEX(Monthly!$C$77:$BJ$77,($R$2-1)*12+6) -> 382840.98 | N41: =INDEX(Monthly!$C$77:$BJ$77,($R$2-1)*12+7) -> 447925.78 | O41: =INDEX(Monthly!$C$77:$BJ$77,($R$2-1)*12+8) -> 513028.14 | P41: =INDEX(Monthly!$C$77:$BJ$77,($R$2-1)*12+9) -> 578148.05 | Q41: =INDEX(Monthly!$C$77:$BJ$77,($R$2-1)*12+10) -> 643285.51 | R41: =INDEX(Monthly!$C$77:$BJ$77,($R$2-1)*12+11) -> 708440.54 | S41: =INDEX(Monthly!$C$77:$BJ$77,($R$2-1)*12+12) -> 773613.11
A42: Accounts receivable | B42: ='Balance Sheet'!B6 -> 563274 | C42: ='Balance Sheet'!C6 -> 729495.23 | D42: ='Balance Sheet'!D6 -> 946229.5 | E42: ='Balance Sheet'!E6 -> 1229223.4 | F42: ='Balance Sheet'!F6 -> 1599236.8 | H42: =INDEX(Monthly!$C$63:$BJ$63,($R$2-1)*12+1) -> 563274 | I42: =INDEX(Monthly!$C$63:$BJ$63,($R$2-1)*12+2) -> 563274 | J42: =INDEX(Monthly!$C$63:$BJ$63,($R$2-1)*12+3) -> 563274 | K42: =INDEX(Monthly!$C$63:$BJ$63,($R$2-1)*12+4) -> 563274 | L42: =INDEX(Monthly!$C$63:$BJ$63,($R$2-1)*12+5) -> 563274 | M42: =INDEX(Monthly!$C$63:$BJ$63,($R$2-1)*12+6) -> 563274 | N42: =INDEX(Monthly!$C$63:$BJ$63,($R$2-1)*12+7) -> 563274 | O42: =INDEX(Monthly!$C$63:$BJ$63,($R$2-1)*12+8) -> 563274 | P42: =INDEX(Monthly!$C$63:$BJ$63,($R$2-1)*12+9) -> 563274 | Q42: =INDEX(Monthly!$C$63:$BJ$63,($R$2-1)*12+10) -> 563274 | R42: =INDEX(Monthly!$C$63:$BJ$63,($R$2-1)*12+11) -> 563274 | S42: =INDEX(Monthly!$C$63:$BJ$63,($R$2-1)*12+12) -> 563274
A43: Inventory | B43: ='Balance Sheet'!B7 -> 0 | C43: ='Balance Sheet'!C7 -> 0 | D43: ='Balance Sheet'!D7 -> 0 | E43: ='Balance Sheet'!E7 -> 0 | F43: ='Balance Sheet'!F7 -> 0 | H43: =INDEX(Monthly!$C$64:$BJ$64,($R$2-1)*12+1) -> 0 | I43: =INDEX(Monthly!$C$64:$BJ$64,($R$2-1)*12+2) -> 0 | J43: =INDEX(Monthly!$C$64:$BJ$64,($R$2-1)*12+3) -> 0 | K43: =INDEX(Monthly!$C$64:$BJ$64,($R$2-1)*12+4) -> 0 | L43: =INDEX(Monthly!$C$64:$BJ$64,($R$2-1)*12+5) -> 0 | M43: =INDEX(Monthly!$C$64:$BJ$64,($R$2-1)*12+6) -> 0 | N43: =INDEX(Monthly!$C$64:$BJ$64,($R$2-1)*12+7) -> 0 | O43: =INDEX(Monthly!$C$64:$BJ$64,($R$2-1)*12+8) -> 0 | P43: =INDEX(Monthly!$C$64:$BJ$64,($R$2-1)*12+9) -> 0 | Q43: =INDEX(Monthly!$C$64:$BJ$64,($R$2-1)*12+10) -> 0 | R43: =INDEX(Monthly!$C$64:$BJ$64,($R$2-1)*12+11) -> 0 | S43: =INDEX(Monthly!$C$64:$BJ$64,($R$2-1)*12+12) -> 0
A44: Net fixed assets | B44: ='Balance Sheet'!B8 -> 48000 | C44: ='Balance Sheet'!C8 -> 36000 | D44: ='Balance Sheet'!D8 -> 24000 | E44: ='Balance Sheet'!E8 -> 12000 | F44: ='Balance Sheet'!F8 -> 0 | H44: =INDEX(Monthly!$C$54:$BJ$54,($R$2-1)*12+1) -> 59000 | I44: =INDEX(Monthly!$C$54:$BJ$54,($R$2-1)*12+2) -> 58000 | J44: =INDEX(Monthly!$C$54:$BJ$54,($R$2-1)*12+3) -> 57000 | K44: =INDEX(Monthly!$C$54:$BJ$54,($R$2-1)*12+4) -> 56000 | L44: =INDEX(Monthly!$C$54:$BJ$54,($R$2-1)*12+5) -> 55000 | M44: =INDEX(Monthly!$C$54:$BJ$54,($R$2-1)*12+6) -> 54000 | N44: =INDEX(Monthly!$C$54:$BJ$54,($R$2-1)*12+7) -> 53000 | O44: =INDEX(Monthly!$C$54:$BJ$54,($R$2-1)*12+8) -> 52000 | P44: =INDEX(Monthly!$C$54:$BJ$54,($R$2-1)*12+9) -> 51000 | Q44: =INDEX(Monthly!$C$54:$BJ$54,($R$2-1)*12+10) -> 50000 | R44: =INDEX(Monthly!$C$54:$BJ$54,($R$2-1)*12+11) -> 49000 | S44: =INDEX(Monthly!$C$54:$BJ$54,($R$2-1)*12+12) -> 48000
A45: Total assets | B45: ='Balance Sheet'!B9 -> 1384887.1 | C45: ='Balance Sheet'!C9 -> 2535928.7 | D45: ='Balance Sheet'!D9 -> 4160923.5 | E45: ='Balance Sheet'!E9 -> 6415640.8 | F45: ='Balance Sheet'!F9 -> 9507372.8 | H45: =INDEX(Monthly!$C$91:$BJ$91,($R$2-1)*12+1) -> 679954.32 | I45: =INDEX(Monthly!$C$91:$BJ$91,($R$2-1)*12+2) -> 743951.34 | J45: =INDEX(Monthly!$C$91:$BJ$91,($R$2-1)*12+3) -> 807965.92 | K45: =INDEX(Monthly!$C$91:$BJ$91,($R$2-1)*12+4) -> 871998.05 | L45: =INDEX(Monthly!$C$91:$BJ$91,($R$2-1)*12+5) -> 936047.74 | M45: =INDEX(Monthly!$C$91:$BJ$91,($R$2-1)*12+6) -> 1000115 | N45: =INDEX(Monthly!$C$91:$BJ$91,($R$2-1)*12+7) -> 1064199.8 | O45: =INDEX(Monthly!$C$91:$BJ$91,($R$2-1)*12+8) -> 1128302.1 | P45: =INDEX(Monthly!$C$91:$BJ$91,($R$2-1)*12+9) -> 1192422 | Q45: =INDEX(Monthly!$C$91:$BJ$91,($R$2-1)*12+10) -> 1256559.5 | R45: =INDEX(Monthly!$C$91:$BJ$91,($R$2-1)*12+11) -> 1320714.5 | S45: =INDEX(Monthly!$C$91:$BJ$91,($R$2-1)*12+12) -> 1384887.1
A46: Accounts payable | B46: ='Balance Sheet'!B10 -> 112632.74 | C46: ='Balance Sheet'!C10 -> 145417.95 | D46: ='Balance Sheet'!D10 -> 188043.59 | E46: ='Balance Sheet'!E10 -> 243544.96 | F46: ='Balance Sheet'!F10 -> 315915.37 | H46: =INDEX(Monthly!$C$65:$BJ$65,($R$2-1)*12+1) -> 112632.74 | I46: =INDEX(Monthly!$C$65:$BJ$65,($R$2-1)*12+2) -> 112632.74 | J46: =INDEX(Monthly!$C$65:$BJ$65,($R$2-1)*12+3) -> 112632.74 | K46: =INDEX(Monthly!$C$65:$BJ$65,($R$2-1)*12+4) -> 112632.74 | L46: =INDEX(Monthly!$C$65:$BJ$65,($R$2-1)*12+5) -> 112632.74 | M46: =INDEX(Monthly!$C$65:$BJ$65,($R$2-1)*12+6) -> 112632.74 | N46: =INDEX(Monthly!$C$65:$BJ$65,($R$2-1)*12+7) -> 112632.74 | O46: =INDEX(Monthly!$C$65:$BJ$65,($R$2-1)*12+8) -> 112632.74 | P46: =INDEX(Monthly!$C$65:$BJ$65,($R$2-1)*12+9) -> 112632.74 | Q46: =INDEX(Monthly!$C$65:$BJ$65,($R$2-1)*12+10) -> 112632.74 | R46: =INDEX(Monthly!$C$65:$BJ$65,($R$2-1)*12+11) -> 112632.74 | S46: =INDEX(Monthly!$C$65:$BJ$65,($R$2-1)*12+12) -> 112632.74
A47: Loan | B47: ='Balance Sheet'!B11 -> 163333.33 | C47: ='Balance Sheet'!C11 -> 123333.33 | D47: ='Balance Sheet'!D11 -> 83333.333 | E47: ='Balance Sheet'!E11 -> 43333.333 | F47: ='Balance Sheet'!F11 -> 3333.3333 | H47: =INDEX(Monthly!$C$60:$BJ$60,($R$2-1)*12+1) -> 200000 | I47: =INDEX(Monthly!$C$60:$BJ$60,($R$2-1)*12+2) -> 196666.67 | J47: =INDEX(Monthly!$C$60:$BJ$60,($R$2-1)*12+3) -> 193333.33 | K47: =INDEX(Monthly!$C$60:$BJ$60,($R$2-1)*12+4) -> 190000 | L47: =INDEX(Monthly!$C$60:$BJ$60,($R$2-1)*12+5) -> 186666.67 | M47: =INDEX(Monthly!$C$60:$BJ$60,($R$2-1)*12+6) -> 183333.33 | N47: =INDEX(Monthly!$C$60:$BJ$60,($R$2-1)*12+7) -> 180000 | O47: =INDEX(Monthly!$C$60:$BJ$60,($R$2-1)*12+8) -> 176666.67 | P47: =INDEX(Monthly!$C$60:$BJ$60,($R$2-1)*12+9) -> 173333.33 | Q47: =INDEX(Monthly!$C$60:$BJ$60,($R$2-1)*12+10) -> 170000 | R47: =INDEX(Monthly!$C$60:$BJ$60,($R$2-1)*12+11) -> 166666.67 | S47: =INDEX(Monthly!$C$60:$BJ$60,($R$2-1)*12+12) -> 163333.33
A48: Total liabilities | B48: ='Balance Sheet'!B12 -> 275966.07 | C48: ='Balance Sheet'!C12 -> 268751.29 | D48: ='Balance Sheet'!D12 -> 271376.93 | E48: ='Balance Sheet'!E12 -> 286878.29 | F48: ='Balance Sheet'!F12 -> 319248.7 | H48: =INDEX(Monthly!$C$92:$BJ$92,($R$2-1)*12+1) -> 312632.74 | I48: =INDEX(Monthly!$C$92:$BJ$92,($R$2-1)*12+2) -> 309299.41 | J48: =INDEX(Monthly!$C$92:$BJ$92,($R$2-1)*12+3) -> 305966.07 | K48: =INDEX(Monthly!$C$92:$BJ$92,($R$2-1)*12+4) -> 302632.74 | L48: =INDEX(Monthly!$C$92:$BJ$92,($R$2-1)*12+5) -> 299299.41 | M48: =INDEX(Monthly!$C$92:$BJ$92,($R$2-1)*12+6) -> 295966.07 | N48: =INDEX(Monthly!$C$92:$BJ$92,($R$2-1)*12+7) -> 292632.74 | O48: =INDEX(Monthly!$C$92:$BJ$92,($R$2-1)*12+8) -> 289299.41 | P48: =INDEX(Monthly!$C$92:$BJ$92,($R$2-1)*12+9) -> 285966.07 | Q48: =INDEX(Monthly!$C$92:$BJ$92,($R$2-1)*12+10) -> 282632.74 | R48: =INDEX(Monthly!$C$92:$BJ$92,($R$2-1)*12+11) -> 279299.41 | S48: =INDEX(Monthly!$C$92:$BJ$92,($R$2-1)*12+12) -> 275966.07
A49: Paid-in capital | B49: ='Balance Sheet'!B13 -> 300000 | C49: ='Balance Sheet'!C13 -> 300000 | D49: ='Balance Sheet'!D13 -> 300000 | E49: ='Balance Sheet'!E13 -> 300000 | F49: ='Balance Sheet'!F13 -> 300000 | H49: =INDEX(Monthly!$C$89:$BJ$89,($R$2-1)*12+1) -> 300000 | I49: =INDEX(Monthly!$C$89:$BJ$89,($R$2-1)*12+2) -> 300000 | J49: =INDEX(Monthly!$C$89:$BJ$89,($R$2-1)*12+3) -> 300000 | K49: =INDEX(Monthly!$C$89:$BJ$89,($R$2-1)*12+4) -> 300000 | L49: =INDEX(Monthly!$C$89:$BJ$89,($R$2-1)*12+5) -> 300000 | M49: =INDEX(Monthly!$C$89:$BJ$89,($R$2-1)*12+6) -> 300000 | N49: =INDEX(Monthly!$C$89:$BJ$89,($R$2-1)*12+7) -> 300000 | O49: =INDEX(Monthly!$C$89:$BJ$89,($R$2-1)*12+8) -> 300000 | P49: =INDEX(Monthly!$C$89:$BJ$89,($R$2-1)*12+9) -> 300000 | Q49: =INDEX(Monthly!$C$89:$BJ$89,($R$2-1)*12+10) -> 300000 | R49: =INDEX(Monthly!$C$89:$BJ$89,($R$2-1)*12+11) -> 300000 | S49: =INDEX(Monthly!$C$89:$BJ$89,($R$2-1)*12+12) -> 300000
A50: Retained earnings | B50: ='Balance Sheet'!B14 -> 808921.04 | C50: ='Balance Sheet'!C14 -> 1967177.4 | D50: ='Balance Sheet'!D14 -> 3589546.5 | E50: ='Balance Sheet'!E14 -> 5828762.5 | F50: ='Balance Sheet'!F14 -> 8888124.1 | H50: =INDEX(Monthly!$C$90:$BJ$90,($R$2-1)*12+1) -> 67321.577 | I50: =INDEX(Monthly!$C$90:$BJ$90,($R$2-1)*12+2) -> 134651.93 | J50: =INDEX(Monthly!$C$90:$BJ$90,($R$2-1)*12+3) -> 201999.84 | K50: =INDEX(Monthly!$C$90:$BJ$90,($R$2-1)*12+4) -> 269365.31 | L50: =INDEX(Monthly!$C$90:$BJ$90,($R$2-1)*12+5) -> 336748.33 | M50: =INDEX(Monthly!$C$90:$BJ$90,($R$2-1)*12+6) -> 404148.91 | N50: =INDEX(Monthly!$C$90:$BJ$90,($R$2-1)*12+7) -> 471567.04 | O50: =INDEX(Monthly!$C$90:$BJ$90,($R$2-1)*12+8) -> 539002.73 | P50: =INDEX(Monthly!$C$90:$BJ$90,($R$2-1)*12+9) -> 606455.97 | Q50: =INDEX(Monthly!$C$90:$BJ$90,($R$2-1)*12+10) -> 673926.77 | R50: =INDEX(Monthly!$C$90:$BJ$90,($R$2-1)*12+11) -> 741415.13 | S50: =INDEX(Monthly!$C$90:$BJ$90,($R$2-1)*12+12) -> 808921.04
A51: Total equity | B51: ='Balance Sheet'!B15 -> 1108921 | C51: ='Balance Sheet'!C15 -> 2267177.4 | D51: ='Balance Sheet'!D15 -> 3889546.5 | E51: ='Balance Sheet'!E15 -> 6128762.5 | F51: ='Balance Sheet'!F15 -> 9188124.1 | H51: =INDEX(Monthly!$C$93:$BJ$93,($R$2-1)*12+1) -> 367321.58 | I51: =INDEX(Monthly!$C$93:$BJ$93,($R$2-1)*12+2) -> 434651.93 | J51: =INDEX(Monthly!$C$93:$BJ$93,($R$2-1)*12+3) -> 501999.84 | K51: =INDEX(Monthly!$C$93:$BJ$93,($R$2-1)*12+4) -> 569365.31 | L51: =INDEX(Monthly!$C$93:$BJ$93,($R$2-1)*12+5) -> 636748.33 | M51: =INDEX(Monthly!$C$93:$BJ$93,($R$2-1)*12+6) -> 704148.91 | N51: =INDEX(Monthly!$C$93:$BJ$93,($R$2-1)*12+7) -> 771567.04 | O51: =INDEX(Monthly!$C$93:$BJ$93,($R$2-1)*12+8) -> 839002.73 | P51: =INDEX(Monthly!$C$93:$BJ$93,($R$2-1)*12+9) -> 906455.97 | Q51: =INDEX(Monthly!$C$93:$BJ$93,($R$2-1)*12+10) -> 973926.77 | R51: =INDEX(Monthly!$C$93:$BJ$93,($R$2-1)*12+11) -> 1041415.1 | S51: =INDEX(Monthly!$C$93:$BJ$93,($R$2-1)*12+12) -> 1108921
A52: Total liabilities & equity | B52: ='Balance Sheet'!B16 -> 1384887.1 | C52: ='Balance Sheet'!C16 -> 2535928.7 | D52: ='Balance Sheet'!D16 -> 4160923.5 | E52: ='Balance Sheet'!E16 -> 6415640.8 | F52: ='Balance Sheet'!F16 -> 9507372.8 | H52: =INDEX(Monthly!$C$94:$BJ$94,($R$2-1)*12+1) -> 679954.32 | I52: =INDEX(Monthly!$C$94:$BJ$94,($R$2-1)*12+2) -> 743951.34 | J52: =INDEX(Monthly!$C$94:$BJ$94,($R$2-1)*12+3) -> 807965.92 | K52: =INDEX(Monthly!$C$94:$BJ$94,($R$2-1)*12+4) -> 871998.05 | L52: =INDEX(Monthly!$C$94:$BJ$94,($R$2-1)*12+5) -> 936047.74 | M52: =INDEX(Monthly!$C$94:$BJ$94,($R$2-1)*12+6) -> 1000115 | N52: =INDEX(Monthly!$C$94:$BJ$94,($R$2-1)*12+7) -> 1064199.8 | O52: =INDEX(Monthly!$C$94:$BJ$94,($R$2-1)*12+8) -> 1128302.1 | P52: =INDEX(Monthly!$C$94:$BJ$94,($R$2-1)*12+9) -> 1192422 | Q52: =INDEX(Monthly!$C$94:$BJ$94,($R$2-1)*12+10) -> 1256559.5 | R52: =INDEX(Monthly!$C$94:$BJ$94,($R$2-1)*12+11) -> 1320714.5 | S52: =INDEX(Monthly!$C$94:$BJ$94,($R$2-1)*12+12) -> 1384887.1

Sheet Scenarios
A1: Scenarios — Low / Base / High | H1: =HYPERLINK("#'Cover'!A1","◂ Contents") -> ◂ Contents
A2: All three scenarios calculated side by side, live: change any input and every column updates. Active = the scenario chosen on the Dashboard.
A5: Key drivers
A6: Driver | B6: Low | C6: Base | D6: High | E6: Active
A7: Hourly rate — partners & senior consultants ($ / hour) | B7: =Inputs!$B$14 -> 300 | C7: =Inputs!$C$14 -> 350 | D7: =Inputs!$D$14 -> 400 | E7: =Inputs!$E$14 -> 350
A8: Hourly rate — consultants ($ / hour) | B8: =Inputs!$B$15 -> 150 | C8: =Inputs!$C$15 -> 175 | D8: =Inputs!$D$15 -> 200 | E8: =Inputs!$E$15 -> 175
A9: Utilisation — consultants (%) | B9: =Inputs!$B$9 -> 0.68 | C9: =Inputs!$C$9 -> 0.75 | D9: =Inputs!$D$9 -> 0.8 | E9: =Inputs!$E$9 -> 0.75
A10: Contractor billable hours per month (year 1) (hours) | B10: =Inputs!$B$10 -> 300 | C10: =Inputs!$C$10 -> 400 | D10: =Inputs!$D$10 -> 500 | E10: =Inputs!$E$10 -> 400
A11: Customer payment terms (receivable days) (days) | B11: =Inputs!$B$60 -> 45 | C11: =Inputs!$C$60 -> 45 | D11: =Inputs!$D$60 -> 45 | E11: =Inputs!$E$60 -> 45
A12: Equity raised at start ($) | B12: =Inputs!$B$54 -> 300000 | C12: =Inputs!$C$54 -> 300000 | D12: =Inputs!$D$54 -> 300000 | E12: =Inputs!$E$54 -> 300000
A14: Results by scenario ($'000)
A15: Output | B15: Low | C15: Base | D15: High | E15: Active
A16: Revenue — final year | B16: =F29 -> 8830004.7 | C16: =F30 -> 12793894 | D16: =F31 -> 17866027 | E16: ='P&L'!F5 -> 12793894
A17: Revenue — whole plan | B17: =SUM(B29:F29) -> 28675279 | C17: =SUM(B30:F30) -> 40539671 | D17: =SUM(B31:F31) -> 54922754 | E17: =SUM('P&L'!$B$5:$F$5) -> 40539671
A18: EBITDA — final year | B18: =F35 -> 397861.74 | C18: =F36 -> 3886476.3 | D18: =F37 -> 8264572 | E18: ='P&L'!F15 -> 3886476.3
A19: EBITDA margin — final year | B19: =IF(B16=0,0,B18/B16) -> 0.045057931 | C19: =IF(C16=0,0,C18/C16) -> 0.30377587 | D19: =IF(D16=0,0,D18/D16) -> 0.4625859 | E19: =IF(E16=0,0,E18/E16) -> 0.30377587
A20: Net income — final year | B20: =F41 -> 303356.11 | C20: =F42 -> 3059361.6 | D20: =F43 -> 6518057.2 | E20: ='P&L'!F22 -> 3059361.6
A21: Net income — whole plan | B21: =SUM(B41:F41) -> 533999.64 | C21: =SUM(B42:F42) -> 8888124.1 | D21: =SUM(B43:F43) -> 18925064 | E21: =SUM('P&L'!$B$22:$F$22) -> 8888124.1
A22: Cash at the end of the plan | B22: =F47 -> 29694.634 | C22: =F48 -> 7908136 | D22: =F49 -> 17339977 | E22: ='Balance Sheet'!F5 -> 7908136
A23: Lowest cash balance | B23: =MIN('Scenario calc'!$C$79:$BJ$79) -> -222811.69 | C23: =MIN('Scenario calc'!$C$189:$BJ$189) -> 57680.317 | D23: =MIN('Scenario calc'!$C$299:$BJ$299) -> -20466.901 | E23: ='Break-even'!B18 -> 57680.317
A24: Lowest cash point (month #) | B24: =MATCH(MIN('Scenario calc'!$C$79:$BJ$79),'Scenario calc'!$C$79:$BJ$79,0) -> 49 | C24: =MATCH(MIN('Scenario calc'!$C$189:$BJ$189),'Scenario calc'!$C$189:$BJ$189,0) -> 1 | D24: =MATCH(MIN('Scenario calc'!$C$299:$BJ$299),'Scenario calc'!$C$299:$BJ$299,0) -> 1 | E24: ='Break-even'!B6 -> 1
A25: Funding required (incl. cash buffer) | B25: =SUMPRODUCT(--('Scenario calc'!$C$6:$BJ$6<=B24),'Scenario calc'!$C$52:$BJ$52)-SUMPRODUCT(--('Scenario calc'!$C$6:$BJ$6<=B24),'Scenario calc'!$C$73:$BJ$73)-SUMPRODUCT(--('Scenario calc'!$C$6:$BJ$6<=B24),'Scenario calc'!$C$61:$BJ$61)+Inputs!$B$69 -> 910811.69 | C25: =SUMPRODUCT(--('Scenario calc'!$C$116:$BJ$116<=C24),'Scenario calc'!$C$162:$BJ$162)-SUMPRODUCT(--('Scenario calc'!$C$116:$BJ$116<=C24),'Scenario calc'!$C$183:$BJ$183)-SUMPRODUCT(--('Scenario calc'!$C$116:$BJ$116<=C24),'Scenario calc'!$C$171:$BJ$171)+Inputs!$C$69 -> 630319.68 | D25: =SUMPRODUCT(--('Scenario calc'!$C$226:$BJ$226<=D24),'Scenario calc'!$C$272:$BJ$272)-SUMPRODUCT(--('Scenario calc'!$C$226:$BJ$226<=D24),'Scenario calc'!$C$293:$BJ$293)-SUMPRODUCT(--('Scenario calc'!$C$226:$BJ$226<=D24),'Scenario calc'!$C$281:$BJ$281)+Inputs!$D$69 -> 708466.9 | E25: ='Break-even'!B12 -> 630319.68
A27: Revenue by year ($'000)
A28: Scenario | B28: 1 | C28: 2 | D28: 3 | E28: 4 | F28: 5
A29: Low | B29: =SUMIF('Scenario calc'!$C$7:$BJ$7,B$28,'Scenario calc'!$C$24:$BJ$24) -> 3332736 | C29: =SUMIF('Scenario calc'!$C$7:$BJ$7,C$28,'Scenario calc'!$C$24:$BJ$24) -> 4231789.1 | D29: =SUMIF('Scenario calc'!$C$7:$BJ$7,D$28,'Scenario calc'!$C$24:$BJ$24) -> 5391180.3 | E29: =SUMIF('Scenario calc'!$C$7:$BJ$7,E$28,'Scenario calc'!$C$24:$BJ$24) -> 6889569.3 | F29: =SUMIF('Scenario calc'!$C$7:$BJ$7,F$28,'Scenario calc'!$C$24:$BJ$24) -> 8830004.7
A30: Base | B30: =SUMIF('Scenario calc'!$C$117:$BJ$117,B$28,'Scenario calc'!$C$134:$BJ$134) -> 4506192 | C30: =SUMIF('Scenario calc'!$C$117:$BJ$117,C$28,'Scenario calc'!$C$134:$BJ$134) -> 5835961.9 | D30: =SUMIF('Scenario calc'!$C$117:$BJ$117,D$28,'Scenario calc'!$C$134:$BJ$134) -> 7569836 | E30: =SUMIF('Scenario calc'!$C$117:$BJ$117,E$28,'Scenario calc'!$C$134:$BJ$134) -> 9833787.5 | F30: =SUMIF('Scenario calc'!$C$117:$BJ$117,F$28,'Scenario calc'!$C$134:$BJ$134) -> 12793894
A31: High | B31: =SUMIF('Scenario calc'!$C$227:$BJ$227,B$28,'Scenario calc'!$C$244:$BJ$244) -> 5791212 | C31: =SUMIF('Scenario calc'!$C$227:$BJ$227,C$28,'Scenario calc'!$C$244:$BJ$244) -> 7661148.8 | D31: =SUMIF('Scenario calc'!$C$227:$BJ$227,D$28,'Scenario calc'!$C$244:$BJ$244) -> 10147498 | E31: =SUMIF('Scenario calc'!$C$227:$BJ$227,E$28,'Scenario calc'!$C$244:$BJ$244) -> 13456869 | F31: =SUMIF('Scenario calc'!$C$227:$BJ$227,F$28,'Scenario calc'!$C$244:$BJ$244) -> 17866027
A33: EBITDA by year ($'000)
A34: Scenario | B34: 1 | C34: 2 | D34: 3 | E34: 4 | F34: 5
A35: Low | B35: =SUMIF('Scenario calc'!$C$7:$BJ$7,B$34,'Scenario calc'!$C$40:$BJ$40) -> -30973.44 | C35: =SUMIF('Scenario calc'!$C$7:$BJ$7,C$34,'Scenario calc'!$C$40:$BJ$40) -> 37714.494 | D35: =SUMIF('Scenario calc'!$C$7:$BJ$7,D$34,'Scenario calc'!$C$40:$BJ$40) -> 127633.63 | E35: =SUMIF('Scenario calc'!$C$7:$BJ$7,E$34,'Scenario calc'!$C$40:$BJ$40) -> 245034.7 | F35: =SUMIF('Scenario calc'!$C$7:$BJ$7,F$34,'Scenario calc'!$C$40:$BJ$40) -> 397861.74
A36: Base | B36: =SUMIF('Scenario calc'!$C$117:$BJ$117,B$34,'Scenario calc'!$C$150:$BJ$150) -> 1050606.2 | C36: =SUMIF('Scenario calc'!$C$117:$BJ$117,C$34,'Scenario calc'!$C$150:$BJ$150) -> 1489614 | D36: =SUMIF('Scenario calc'!$C$117:$BJ$117,D$34,'Scenario calc'!$C$150:$BJ$150) -> 2073898.4 | E36: =SUMIF('Scenario calc'!$C$117:$BJ$117,E$34,'Scenario calc'!$C$150:$BJ$150) -> 2851517.2 | F36: =SUMIF('Scenario calc'!$C$117:$BJ$117,F$34,'Scenario calc'!$C$150:$BJ$150) -> 3886476.3
A37: High | B37: =SUMIF('Scenario calc'!$C$227:$BJ$227,B$34,'Scenario calc'!$C$260:$BJ$260) -> 2248031.7 | C37: =SUMIF('Scenario calc'!$C$227:$BJ$227,C$34,'Scenario calc'!$C$260:$BJ$260) -> 3149413 | D37: =SUMIF('Scenario calc'!$C$227:$BJ$227,D$34,'Scenario calc'!$C$260:$BJ$260) -> 4370542.9 | E37: =SUMIF('Scenario calc'!$C$227:$BJ$227,E$34,'Scenario calc'!$C$260:$BJ$260) -> 6024539.1 | F37: =SUMIF('Scenario calc'!$C$227:$BJ$227,F$34,'Scenario calc'!$C$260:$BJ$260) -> 8264572
A39: Net income by year ($'000)
A40: Scenario | B40: 1 | C40: 2 | D40: 3 | E40: 4 | F40: 5
A41: Low | B41: =SUMIF('Scenario calc'!$C$7:$BJ$7,B$40,'Scenario calc'!$C$49:$BJ$49) -> -57628.996 | C41: =SUMIF('Scenario calc'!$C$7:$BJ$7,C$40,'Scenario calc'!$C$49:$BJ$49) -> 14247.827 | D41: =SUMIF('Scenario calc'!$C$7:$BJ$7,D$40,'Scenario calc'!$C$49:$BJ$49) -> 93929.949 | E41: =SUMIF('Scenario calc'!$C$7:$BJ$7,E$40,'Scenario calc'!$C$49:$BJ$49) -> 180094.75 | F41: =SUMIF('Scenario calc'!$C$7:$BJ$7,F$40,'Scenario calc'!$C$49:$BJ$49) -> 303356.11
A42: Base | B42: =SUMIF('Scenario calc'!$C$117:$BJ$117,B$40,'Scenario calc'!$C$159:$BJ$159) -> 808921.04 | C42: =SUMIF('Scenario calc'!$C$117:$BJ$117,C$40,'Scenario calc'!$C$159:$BJ$159) -> 1158256.4 | D42: =SUMIF('Scenario calc'!$C$117:$BJ$117,D$40,'Scenario calc'!$C$159:$BJ$159) -> 1622369.1 | E42: =SUMIF('Scenario calc'!$C$117:$BJ$117,E$40,'Scenario calc'!$C$159:$BJ$159) -> 2239215.9 | F42: =SUMIF('Scenario calc'!$C$117:$BJ$117,F$40,'Scenario calc'!$C$159:$BJ$159) -> 3059361.6
A43: High | B43: =SUMIF('Scenario calc'!$C$227:$BJ$227,B$40,'Scenario calc'!$C$269:$BJ$269) -> 1754887.2 | C43: =SUMIF('Scenario calc'!$C$227:$BJ$227,C$40,'Scenario calc'!$C$269:$BJ$269) -> 2469497.6 | D43: =SUMIF('Scenario calc'!$C$227:$BJ$227,D$40,'Scenario calc'!$C$269:$BJ$269) -> 3436718.3 | E43: =SUMIF('Scenario calc'!$C$227:$BJ$227,E$40,'Scenario calc'!$C$269:$BJ$269) -> 4745903.2 | F43: =SUMIF('Scenario calc'!$C$227:$BJ$227,F$40,'Scenario calc'!$C$269:$BJ$269) -> 6518057.2
A45: Cash at year end by year ($'000)
A46: Scenario | B46: 1 | C46: 2 | D46: 3 | E46: 4 | F46: 5
A47: Low | B47: =INDEX('Scenario calc'!$C$79:$BJ$79,B$46*12) -> 49916.898 | C47: =INDEX('Scenario calc'!$C$79:$BJ$79,C$46*12) -> -45948.235 | D47: =INDEX('Scenario calc'!$C$79:$BJ$79,D$46*12) -> -85654.791 | E47: =INDEX('Scenario calc'!$C$79:$BJ$79,E$46*12) -> -69746.669 | F47: =INDEX('Scenario calc'!$C$79:$BJ$79,F$46*12) -> 29694.634
A48: Base | B48: =INDEX('Scenario calc'!$C$189:$BJ$189,B$46*12) -> 773613.11 | C48: =INDEX('Scenario calc'!$C$189:$BJ$189,C$46*12) -> 1770433.5 | D48: =INDEX('Scenario calc'!$C$189:$BJ$189,D$46*12) -> 3190694 | E48: =INDEX('Scenario calc'!$C$189:$BJ$189,E$46*12) -> 5174417.3 | F48: =INDEX('Scenario calc'!$C$189:$BJ$189,F$46*12) -> 7908136
A49: High | B49: =INDEX('Scenario calc'!$C$299:$BJ$299,B$46*12) -> 1562601.5 | C49: =INDEX('Scenario calc'!$C$299:$BJ$299,C$46*12) -> 3806383.6 | D49: =INDEX('Scenario calc'!$C$299:$BJ$299,D$46*12) -> 6951751.8 | E49: =INDEX('Scenario calc'!$C$299:$BJ$299,E$46*12) -> 11318528 | F49: =INDEX('Scenario calc'!$C$299:$BJ$299,F$46*12) -> 17339977

Sheet Break-even
A1: Startup costs, funding need and break-even | H1: =HYPERLINK("#'Cover'!A1","◂ Contents") -> ◂ Contents
A2: Live for the selected scenario. Periods are counted in months from the start of the plan.
A3: Scenario shown | B3: =CHOOSE(Dashboard!$B$4,"Low","Base","High") -> Base
A5: Startup costs & funding need (up to the lowest cash point)
A6: Lowest cash point (month #) | B6: =MATCH(MIN(Monthly!$C$77:$BJ$77),Monthly!$C$77:$BJ$77,0) -> 1
A7: Capital spending up to the lowest cash point | B7: =SUMPRODUCT(--(Monthly!$C$4:$BJ$4<=$B$6),Monthly!$C$50:$BJ$50) -> 60000
A8: Operating cash burn up to the lowest cash point | B8: =-SUMPRODUCT(--(Monthly!$C$4:$BJ$4<=$B$6),Monthly!$C$71:$BJ$71) -> 382319.68 | D8: Losses and working capital before the business funds itself
A9: Loan repayments up to the lowest cash point | B9: =-SUMPRODUCT(--(Monthly!$C$4:$BJ$4<=$B$6),Monthly!$C$59:$BJ$59) -> 0
A10: Total uses of funds | B10: =B7+B8+B9 -> 442319.68
A11: Minimum cash buffer to keep | B11: =Inputs!$E$69 -> 188000 | D11: Input on the Inputs sheet
A12: Funding required (uses + buffer) | B12: =B10+B11 -> 630319.68
A14: Equity raised | B14: =Inputs!$E$54 -> 300000
A15: Loan drawn | B15: =Inputs!$E$55 -> 200000
A16: Total sources of funds | B16: =B14+B15 -> 500000
A17: Funding surplus / (shortfall) | B17: =B16-B12 -> -130319.68 | D17: Negative = raise at least this much more
A18: Lowest cash balance in the plan | B18: =MIN(Monthly!$C$77:$BJ$77) -> 57680.317 | D18: Equals sources minus uses
A20: Break-even timing
A21: First month with positive EBITDA (month #) | B21: =IFERROR(MATCH(1,Monthly!$C$78:$BJ$78,0),"Not within horizon") -> 1
A22: First month with positive net income (month #) | B22: =IFERROR(MATCH(1,Monthly!$C$81:$BJ$81,0),"Not within horizon") -> 1
A23: Cash invested paid back (month #) | B23: =IF(MIN(Monthly!$C$83:$BJ$83)>=0,"No investment to pay back",IFERROR(MATCH(1,Monthly!$C$85:$BJ$85,0),"Not within horizon")) -> 8 | D23: Cumulative operating + investing cash flow back to zero
A25: Annual break-even revenue
A26: Year # | B26: 1 | C26: 2 | D26: 3 | E26: 4 | F26: 5
B27: Year 1 | C27: Year 2 | D27: Year 3 | E27: Year 4 | F27: Year 5
A28: Revenue | B28: =SUMIF(Monthly!$C$5:$BJ$5,B$26,Monthly!$C$22:$BJ$22) -> 4506192 | C28: =SUMIF(Monthly!$C$5:$BJ$5,C$26,Monthly!$C$22:$BJ$22) -> 5835961.9 | D28: =SUMIF(Monthly!$C$5:$BJ$5,D$26,Monthly!$C$22:$BJ$22) -> 7569836 | E28: =SUMIF(Monthly!$C$5:$BJ$5,E$26,Monthly!$C$22:$BJ$22) -> 9833787.5 | F28: =SUMIF(Monthly!$C$5:$BJ$5,F$26,Monthly!$C$22:$BJ$22) -> 12793894
A29: Gross profit | B29: =SUMIF(Monthly!$C$5:$BJ$5,B$26,Monthly!$C$29:$BJ$29) -> 1803006.2 | C29: =SUMIF(Monthly!$C$5:$BJ$5,C$26,Monthly!$C$29:$BJ$29) -> 2345931 | D29: =SUMIF(Monthly!$C$5:$BJ$5,D$26,Monthly!$C$29:$BJ$29) -> 3056789.8 | E29: =SUMIF(Monthly!$C$5:$BJ$5,E$26,Monthly!$C$29:$BJ$29) -> 3988708.6 | F29: =SUMIF(Monthly!$C$5:$BJ$5,F$26,Monthly!$C$29:$BJ$29) -> 5211925.2
A30: Gross margin (contribution) | B30: =IF(B28=0,0,B29/B28) -> 0.40011749 | C30: =IF(C28=0,0,C29/C28) -> 0.40197847 | D30: =IF(D28=0,0,D29/D28) -> 0.40381189 | E30: =IF(E28=0,0,E29/E28) -> 0.40561265 | F30: =IF(F28=0,0,F29/F28) -> 0.40737599
A31: Operating expenses (treated as fixed) | B31: =-SUMIF(Monthly!$C$5:$BJ$5,B$26,Monthly!$C$37:$BJ$37) -> 752400 | C31: =-SUMIF(Monthly!$C$5:$BJ$5,C$26,Monthly!$C$37:$BJ$37) -> 856317 | D31: =-SUMIF(Monthly!$C$5:$BJ$5,D$26,Monthly!$C$37:$BJ$37) -> 982891.4 | E31: =-SUMIF(Monthly!$C$5:$BJ$5,E$26,Monthly!$C$37:$BJ$37) -> 1137191.4 | F31: =-SUMIF(Monthly!$C$5:$BJ$5,F$26,Monthly!$C$37:$BJ$37) -> 1325448.9
A32: Break-even revenue (EBITDA = 0) | B32: =IF(B30>0,B31/B30,"n/a") -> 1880447.7 | C32: =IF(C30>0,C31/C30,"n/a") -> 2130255.9 | D32: =IF(D30>0,D31/D30,"n/a") -> 2434032.8 | E32: =IF(E30>0,E31/E30,"n/a") -> 2803638.8 | F32: =IF(F30>0,F31/F30,"n/a") -> 3253625.6
A33: Margin of safety (revenue above break-even) | B33: =IF(AND(ISNUMBER(B32),B28>0),(B28-B32)/B28,"n/a") -> 0.58269695 | C33: =IF(AND(ISNUMBER(C32),C28>0),(C28-C32)/C28,"n/a") -> 0.63497776 | D33: =IF(AND(ISNUMBER(D32),D28>0),(D28-D32)/D28,"n/a") -> 0.67845634 | E33: =IF(AND(ISNUMBER(E32),E28>0),(E28-E32)/E28,"n/a") -> 0.71489736 | F33: =IF(AND(ISNUMBER(F32),F28>0),(F28-F32)/F28,"n/a") -> 0.74568919
A35: Simplification: cost of sales is treated as variable and operating expenses as fixed, so break-even revenue = operating expenses ÷ gross margin.

Sheet Valuation
A1: Discounted cash flow valuation | H1: =HYPERLINK("#'Cover'!A1","◂ Contents") -> ◂ Contents
A2: Enterprise value at the start of the plan, before the funding raised in period 1. Year-end discounting.
A3: Scenario shown | B3: =CHOOSE(Dashboard!$B$4,"Low","Base","High") -> Base
A5: Assumptions (active scenario, from the Inputs sheet)
A6: Discount rate (WACC) | B6: =Inputs!$E$72 -> 0.16
A7: Terminal growth rate | B7: =Inputs!$E$73 -> 0.02
A8: Exit multiple (EV ÷ final-year EBITDA) | B8: =Inputs!$E$74 -> 5.5
A9: Tax rate (for the interest tax shield) | B9: =Inputs!$E$66 -> 0.21
A10: Sensitivity step: WACC | B10: =Inputs!$E$75 -> 0.01
A11: Sensitivity step: terminal growth | B11: =Inputs!$E$76 -> 0.005
A13: Free cash flow by year
A14: Year # | B14: 1 | C14: 2 | D14: 3 | E14: 4 | F14: 5
B15: Year 1 | C15: Year 2 | D15: Year 3 | E15: Year 4 | F15: Year 5
A16: EBITDA | B16: =SUMIF(Monthly!$C$5:$BJ$5,B$14,Monthly!$C$38:$BJ$38) -> 1050606.2 | C16: =SUMIF(Monthly!$C$5:$BJ$5,C$14,Monthly!$C$38:$BJ$38) -> 1489614 | D16: =SUMIF(Monthly!$C$5:$BJ$5,D$14,Monthly!$C$38:$BJ$38) -> 2073898.4 | E16: =SUMIF(Monthly!$C$5:$BJ$5,E$14,Monthly!$C$38:$BJ$38) -> 2851517.2 | F16: =SUMIF(Monthly!$C$5:$BJ$5,F$14,Monthly!$C$38:$BJ$38) -> 3886476.3
A17: Unlevered free cash flow | B17: =SUMIF(Monthly!$C$5:$BJ$5,B$14,Monthly!$C$86:$BJ$86) -> 321857.67 | C17: =SUMIF(Monthly!$C$5:$BJ$5,C$14,Monthly!$C$86:$BJ$86) -> 1045879.1 | D17: =SUMIF(Monthly!$C$5:$BJ$5,D$14,Monthly!$C$86:$BJ$86) -> 1466791.1 | E17: =SUMIF(Monthly!$C$5:$BJ$5,E$14,Monthly!$C$86:$BJ$86) -> 2027726 | F17: =SUMIF(Monthly!$C$5:$BJ$5,F$14,Monthly!$C$86:$BJ$86) -> 2775193.4
A18: Discount factor | B18: =1/(1+Inputs!$E$72)^B$14 -> 0.86206897 | C18: =1/(1+Inputs!$E$72)^C$14 -> 0.7431629 | D18: =1/(1+Inputs!$E$72)^D$14 -> 0.64065767 | E18: =1/(1+Inputs!$E$72)^E$14 -> 0.5522911 | F18: =1/(1+Inputs!$E$72)^F$14 -> 0.47611302
A19: Present value of free cash flow | B19: =B17*B18 -> 277463.51 | C19: =C17*C18 -> 777258.51 | D19: =D17*D18 -> 939710.99 | E19: =E17*E18 -> 1119895 | F19: =F17*F18 -> 1321305.7
A21: Enterprise value
B22: Perpetual growth | C22: Exit multiple
A23: Present value of the plan's free cash flows | B23: =SUM($B$19:$F$19) -> 4435633.7 | C23: =B23 -> 4435633.7
A24: Final-year free cash flow | final-year EBITDA | B24: =$F$17 -> 2775193.4 | C24: =$F$16 -> 3886476.3
A25: Terminal value at the end of year 5 | B25: =IF($B$6>$B$7,B24*(1+$B$7)/($B$6-$B$7),0) -> 20219266 | C25: =C24*$B$8 -> 21375620
A26: Present value of the terminal value | B26: =B25/(1+$B$6)^$F$14 -> 9626655.7 | C26: =C25/(1+$B$6)^$F$14 -> 10177211
A27: Enterprise value | B27: =B23+B26 -> 14062289 | C27: =C23+C26 -> 14612844
A28: Terminal value share of enterprise value | B28: =IF(B27<>0,B26/B27,0) -> 0.68457243 | C28: =IF(C27<>0,C26/C27,0) -> 0.69645651
A29: Cross-check: implied exit multiple | implied perpetual growth | B29: =IF(C24>0,B25/C24,"n/a") -> 5.2024673 | C29: =IF(C25+B24<>0,(C25*$B$6-B24)/(C25+B24),"n/a") -> 0.026703274
A30: Enterprise value — average of the two methods | B30: =AVERAGE(B27,C27) -> 14337567
A32: Sensitivity: enterprise value (perpetual growth) by WACC and terminal growth
A33: WACC ↓ · terminal growth → | B33: =$B$7+(-2)*$B$11 -> 0.01 | C33: =$B$7+(-1)*$B$11 -> 0.015 | D33: =$B$7+(0)*$B$11 -> 0.02 | E33: =$B$7+(1)*$B$11 -> 0.025 | F33: =$B$7+(2)*$B$11 -> 0.03
A34: =$B$6+(-2)*$B$10 -> 0.14 | B34: =IF($A34>B$33,SUMPRODUCT($B$17:$F$17/(1+$A34)^$B$14:$F$14)+$F$17*(1+B$33)/($A34-B$33)/(1+$A34)^$F$14,"n/a") -> 15917237 | C34: =IF($A34>C$33,SUMPRODUCT($B$17:$F$17/(1+$A34)^$B$14:$F$14)+$F$17*(1+C$33)/($A34-C$33)/(1+$A34)^$F$14,"n/a") -> 16422818 | D34: =IF($A34>D$33,SUMPRODUCT($B$17:$F$17/(1+$A34)^$B$14:$F$14)+$F$17*(1+D$33)/($A34-D$33)/(1+$A34)^$F$14,"n/a") -> 16970531 | E34: =IF($A34>E$33,SUMPRODUCT($B$17:$F$17/(1+$A34)^$B$14:$F$14)+$F$17*(1+E$33)/($A34-E$33)/(1+$A34)^$F$14,"n/a") -> 17565870 | F34: =IF($A34>F$33,SUMPRODUCT($B$17:$F$17/(1+$A34)^$B$14:$F$14)+$F$17*(1+F$33)/($A34-F$33)/(1+$A34)^$F$14,"n/a") -> 18215332
A35: =$B$6+(-1)*$B$10 -> 0.15 | B35: =IF($A35>B$33,SUMPRODUCT($B$17:$F$17/(1+$A35)^$B$14:$F$14)+$F$17*(1+B$33)/($A35-B$33)/(1+$A35)^$F$14,"n/a") -> 14528265 | C35: =IF($A35>C$33,SUMPRODUCT($B$17:$F$17/(1+$A35)^$B$14:$F$14)+$F$17*(1+C$33)/($A35-C$33)/(1+$A35)^$F$14,"n/a") -> 14948034 | D35: =IF($A35>D$33,SUMPRODUCT($B$17:$F$17/(1+$A35)^$B$14:$F$14)+$F$17*(1+D$33)/($A35-D$33)/(1+$A35)^$F$14,"n/a") -> 15400092 | E35: =IF($A35>E$33,SUMPRODUCT($B$17:$F$17/(1+$A35)^$B$14:$F$14)+$F$17*(1+E$33)/($A35-E$33)/(1+$A35)^$F$14,"n/a") -> 15888316 | F35: =IF($A35>F$33,SUMPRODUCT($B$17:$F$17/(1+$A35)^$B$14:$F$14)+$F$17*(1+F$33)/($A35-F$33)/(1+$A35)^$F$14,"n/a") -> 16417224
A36: =$B$6+(0)*$B$10 -> 0.16 | B36: =IF($A36>B$33,SUMPRODUCT($B$17:$F$17/(1+$A36)^$B$14:$F$14)+$F$17*(1+B$33)/($A36-B$33)/(1+$A36)^$F$14,"n/a") -> 13332425 | C36: =IF($A36>C$33,SUMPRODUCT($B$17:$F$17/(1+$A36)^$B$14:$F$14)+$F$17*(1+C$33)/($A36-C$33)/(1+$A36)^$F$14,"n/a") -> 13684774 | D36: =IF($A36>D$33,SUMPRODUCT($B$17:$F$17/(1+$A36)^$B$14:$F$14)+$F$17*(1+D$33)/($A36-D$33)/(1+$A36)^$F$14,"n/a") -> 14062289 | E36: =IF($A36>E$33,SUMPRODUCT($B$17:$F$17/(1+$A36)^$B$14:$F$14)+$F$17*(1+E$33)/($A36-E$33)/(1+$A36)^$F$14,"n/a") -> 14467769 | F36: =IF($A36>F$33,SUMPRODUCT($B$17:$F$17/(1+$A36)^$B$14:$F$14)+$F$17*(1+F$33)/($A36-F$33)/(1+$A36)^$F$14,"n/a") -> 14904440
A37: =$B$6+(1)*$B$10 -> 0.17 | B37: =IF($A37>B$33,SUMPRODUCT($B$17:$F$17/(1+$A37)^$B$14:$F$14)+$F$17*(1+B$33)/($A37-B$33)/(1+$A37)^$F$14,"n/a") -> 12293176 | C37: =IF($A37>C$33,SUMPRODUCT($B$17:$F$17/(1+$A37)^$B$14:$F$14)+$F$17*(1+C$33)/($A37-C$33)/(1+$A37)^$F$14,"n/a") -> 12591761 | D37: =IF($A37>D$33,SUMPRODUCT($B$17:$F$17/(1+$A37)^$B$14:$F$14)+$F$17*(1+D$33)/($A37-D$33)/(1+$A37)^$F$14,"n/a") -> 12910252 | E37: =IF($A37>E$33,SUMPRODUCT($B$17:$F$17/(1+$A37)^$B$14:$F$14)+$F$17*(1+E$33)/($A37-E$33)/(1+$A37)^$F$14,"n/a") -> 13250708 | F37: =IF($A37>F$33,SUMPRODUCT($B$17:$F$17/(1+$A37)^$B$14:$F$14)+$F$17*(1+F$33)/($A37-F$33)/(1+$A37)^$F$14,"n/a") -> 13615482
A38: =$B$6+(2)*$B$10 -> 0.18 | B38: =IF($A38>B$33,SUMPRODUCT($B$17:$F$17/(1+$A38)^$B$14:$F$14)+$F$17*(1+B$33)/($A38-B$33)/(1+$A38)^$F$14,"n/a") -> 11382589 | C38: =IF($A38>C$33,SUMPRODUCT($B$17:$F$17/(1+$A38)^$B$14:$F$14)+$F$17*(1+C$33)/($A38-C$33)/(1+$A38)^$F$14,"n/a") -> 11637743 | D38: =IF($A38>D$33,SUMPRODUCT($B$17:$F$17/(1+$A38)^$B$14:$F$14)+$F$17*(1+D$33)/($A38-D$33)/(1+$A38)^$F$14,"n/a") -> 11908844 | E38: =IF($A38>E$33,SUMPRODUCT($B$17:$F$17/(1+$A38)^$B$14:$F$14)+$F$17*(1+E$33)/($A38-E$33)/(1+$A38)^$F$14,"n/a") -> 12197436 | F38: =IF($A38>F$33,SUMPRODUCT($B$17:$F$17/(1+$A38)^$B$14:$F$14)+$F$17*(1+F$33)/($A38-F$33)/(1+$A38)^$F$14,"n/a") -> 12505267
A40: Free cash flow = operating cash flow + interest × (1 − tax rate) − capital spending. Cells marked n/a: WACC not above growth.

Sheet Sources & Uses
A1: Sources and uses of funds | E1: =HYPERLINK("#'Cover'!A1","◂ Contents") -> ◂ Contents
A2: Live for the selected scenario. Where the money comes from and where it goes in the period set below.
A3: Scenario shown | B3: =CHOOSE(Dashboard!$B$4,"Low","Base","High") -> Base
A5: Funding structure ($'000) — raised at the start of the plan
B6: Amount | C6: Share
A7: Equity | B7: =Inputs!$E$54 -> 300000 | C7: =IF($B$9=0,0,B7/$B$9) -> 0.6
A8: Debt (loan) | B8: =Inputs!$E$55 -> 200000 | C8: =IF($B$9=0,0,B8/$B$9) -> 0.4
A9: Total funding | B9: =B7+B8 -> 500000 | C9: =IF(B9=0,0,1) -> 1
A10: Gearing (debt ÷ equity) | B10: =IF(B7<=0,IF(B8>0,"n/a",0),B8/B7) -> 0.66666667 | D10: n/a: debt without positive equity
A11: Funding required by the plan (Break-even sheet) | B11: ='Break-even'!B12 -> 630319.68
A12: Funding surplus / (shortfall) | B12: ='Break-even'!B17 -> -130319.68
A14: ="Sources and uses of cash in the first "&$B$16&IF($B$16=1," month"," months")&" ($'000)" -> Sources and uses of cash in the first 12 months ($'000)
A15: Period covered (months from the start) | B15: 12 | D15: 1 to 60 (capped)
A16: Months used | B16: =MIN(60,MAX(1,ROUND(B15,0))) -> 12
A17: Sources | B17: Amount | C17: Share
A18: Equity raised | B18: =SUMPRODUCT(--(Monthly!$C$4:$BJ$4<=$B$16),Monthly!$C$73:$BJ$73) -> 300000 | C18: =IF($B$21=0,0,B18/$B$21) -> 0.34471673
A19: Loan drawdowns | B19: =SUMPRODUCT(--(Monthly!$C$4:$BJ$4<=$B$16),Monthly!$C$58:$BJ$58) -> 200000 | C19: =IF($B$21=0,0,B19/$B$21) -> 0.22981115
A20: Cash generated by operations | B20: =MAX(0,SUMPRODUCT(--(Monthly!$C$4:$BJ$4<=$B$16),Monthly!$C$71:$BJ$71)) -> 370279.78 | C20: =IF($B$21=0,0,B20/$B$21) -> 0.42547212
A21: Total sources | B21: =SUM(B18:B20) -> 870279.78 | C21: =IF(B21=0,0,1) -> 1
A23: Uses | B23: Amount | C23: Share
A24: Cash used by operations | B24: =MAX(0,-SUMPRODUCT(--(Monthly!$C$4:$BJ$4<=$B$16),Monthly!$C$71:$BJ$71)) -> 0 | C24: =IF($B$28=0,0,B24/$B$28) -> 0
A25: Capital spending | B25: =-SUMPRODUCT(--(Monthly!$C$4:$BJ$4<=$B$16),Monthly!$C$72:$BJ$72) -> 60000 | C25: =IF($B$28=0,0,B25/$B$28) -> 0.068943346
A26: Loan repayments | B26: =-SUMPRODUCT(--(Monthly!$C$4:$BJ$4<=$B$16),Monthly!$C$59:$BJ$59) -> 36666.667 | C26: =IF($B$28=0,0,B26/$B$28) -> 0.042132045
A27: Cash at the end of the period | B27: =INDEX(Monthly!$C$77:$BJ$77,$B$16) -> 773613.11 | C27: =IF($B$28=0,0,B27/$B$28) -> 0.88892461
A28: Total uses | B28: =SUM(B24:B27) -> 870279.78 | C28: =IF(B28=0,0,1) -> 1
A29: Sources − uses (must be 0; opening cash is 0) | B29: =B21-B28 -> 0

Sheet KPIs
A1: KPIs & ratios | I1: =HYPERLINK("#'Cover'!A1","◂ Contents") -> ◂ Contents
A2: Professional services financial model (growing) — industry metrics and financial ratios for the active scenario
A4: Financial ratios
B5: 1 | C5: 2 | D5: 3 | E5: 4 | F5: 5 | G5: Target
A6: Revenue growth | B6: =IF(N('P&L'!A5)<=0,"n/a",'P&L'!B5/'P&L'!A5-1) -> n/a | C6: =IF(N('P&L'!B5)<=0,"n/a",'P&L'!C5/'P&L'!B5-1) -> 0.29509836 | D6: =IF(N('P&L'!C5)<=0,"n/a",'P&L'!D5/'P&L'!C5-1) -> 0.29710169 | E6: =IF(N('P&L'!D5)<=0,"n/a",'P&L'!E5/'P&L'!D5-1) -> 0.29907537 | F6: =IF(N('P&L'!E5)<=0,"n/a",'P&L'!F5/'P&L'!E5-1) -> 0.30101387
A7: Gross margin | B7: =IF('P&L'!B5<=0,"n/a",'P&L'!B7/'P&L'!B5) -> 0.40011749 | C7: =IF('P&L'!C5<=0,"n/a",'P&L'!C7/'P&L'!C5) -> 0.40197847 | D7: =IF('P&L'!D5<=0,"n/a",'P&L'!D7/'P&L'!D5) -> 0.40381189 | E7: =IF('P&L'!E5<=0,"n/a",'P&L'!E7/'P&L'!E5) -> 0.40561265 | F7: =IF('P&L'!F5<=0,"n/a",'P&L'!F7/'P&L'!F5) -> 0.40737599
A8: EBITDA margin | B8: =IF('P&L'!B5<=0,"n/a",'P&L'!B15/'P&L'!B5) -> 0.23314724 | C8: =IF('P&L'!C5<=0,"n/a",'P&L'!C15/'P&L'!C5) -> 0.25524739 | D8: =IF('P&L'!D5<=0,"n/a",'P&L'!D15/'P&L'!D5) -> 0.27396874 | E8: =IF('P&L'!E5<=0,"n/a",'P&L'!E15/'P&L'!E5) -> 0.28997141 | F8: =IF('P&L'!F5<=0,"n/a",'P&L'!F15/'P&L'!F5) -> 0.30377587
A9: Net margin | B9: =IF('P&L'!B5<=0,"n/a",'P&L'!B22/'P&L'!B5) -> 0.17951322 | C9: =IF('P&L'!C5<=0,"n/a",'P&L'!C22/'P&L'!C5) -> 0.19846881 | D9: =IF('P&L'!D5<=0,"n/a",'P&L'!D22/'P&L'!D5) -> 0.21432024 | E9: =IF('P&L'!E5<=0,"n/a",'P&L'!E22/'P&L'!E5) -> 0.22770636 | F9: =IF('P&L'!F5<=0,"n/a",'P&L'!F22/'P&L'!F5) -> 0.2391267
A10: Payroll, % of revenue | B10: =IF('P&L'!B5<=0,"n/a",-SUMIF(Headcount!$C$5:$BJ$5,B$5,Headcount!$C$19:$BJ$19)/'P&L'!B5) -> 0.57121401 | C10: =IF('P&L'!C5<=0,"n/a",-SUMIF(Headcount!$C$5:$BJ$5,C$5,Headcount!$C$19:$BJ$19)/'P&L'!C5) -> 0.56722732 | D10: =IF('P&L'!D5<=0,"n/a",-SUMIF(Headcount!$C$5:$BJ$5,D$5,Headcount!$C$19:$BJ$19)/'P&L'!D5) -> 0.56354561 | E10: =IF('P&L'!E5<=0,"n/a",-SUMIF(Headcount!$C$5:$BJ$5,E$5,Headcount!$C$19:$BJ$19)/'P&L'!E5) -> 0.56015378 | F10: =IF('P&L'!F5<=0,"n/a",-SUMIF(Headcount!$C$5:$BJ$5,F$5,Headcount!$C$19:$BJ$19)/'P&L'!F5) -> 0.55703659
A11: Marketing, % of revenue | B11: =IF('P&L'!B5<=0,"n/a",-'P&L'!B10/'P&L'!B5) -> 0.021304019 | C11: =IF('P&L'!C5<=0,"n/a",-'P&L'!C10/'P&L'!C5) -> 0.01644973 | D11: =IF('P&L'!D5<=0,"n/a",-'P&L'!D10/'P&L'!D5) -> 0.012681913 | E11: =IF('P&L'!E5<=0,"n/a",-'P&L'!E10/'P&L'!E5) -> 0.0097622609 | F11: =IF('P&L'!F5<=0,"n/a",-'P&L'!F10/'P&L'!F5) -> 0.0075035794
A12: Operating expenses, % of revenue | B12: =IF('P&L'!B5<=0,"n/a",-'P&L'!B14/'P&L'!B5) -> 0.16697025 | C12: =IF('P&L'!C5<=0,"n/a",-'P&L'!C14/'P&L'!C5) -> 0.14673108 | D12: =IF('P&L'!D5<=0,"n/a",-'P&L'!D14/'P&L'!D5) -> 0.12984316 | E12: =IF('P&L'!E5<=0,"n/a",-'P&L'!E14/'P&L'!E5) -> 0.11564124 | F12: =IF('P&L'!F5<=0,"n/a",-'P&L'!F14/'P&L'!F5) -> 0.10360012
A13: Current ratio (current assets ÷ current liabilities) | B13: =IF(('Balance Sheet'!B12-'Balance Sheet'!B11)<=0,"n/a",('Balance Sheet'!B5+'Balance Sheet'!B6+'Balance Sheet'!B7)/('Balance Sheet'!B12-'Balance Sheet'!B11)) -> 11.869436 | C13: =IF(('Balance Sheet'!C12-'Balance Sheet'!C11)<=0,"n/a",('Balance Sheet'!C5+'Balance Sheet'!C6+'Balance Sheet'!C7)/('Balance Sheet'!C12-'Balance Sheet'!C11)) -> 17.191335 | D13: =IF(('Balance Sheet'!D12-'Balance Sheet'!D11)<=0,"n/a",('Balance Sheet'!D5+'Balance Sheet'!D6+'Balance Sheet'!D7)/('Balance Sheet'!D12-'Balance Sheet'!D11)) -> 21.999811 | E13: =IF(('Balance Sheet'!E12-'Balance Sheet'!E11)<=0,"n/a",('Balance Sheet'!E5+'Balance Sheet'!E6+'Balance Sheet'!E7)/('Balance Sheet'!E12-'Balance Sheet'!E11)) -> 26.293465 | F13: =IF(('Balance Sheet'!F12-'Balance Sheet'!F11)<=0,"n/a",('Balance Sheet'!F5+'Balance Sheet'!F6+'Balance Sheet'!F7)/('Balance Sheet'!F12-'Balance Sheet'!F11)) -> 30.094683
A14: Debt ÷ equity (loan ÷ total equity) | B14: =IF('Balance Sheet'!B15<=0,"n/a",'Balance Sheet'!B11/'Balance Sheet'!B15) -> 0.14729032 | C14: =IF('Balance Sheet'!C15<=0,"n/a",'Balance Sheet'!C11/'Balance Sheet'!C15) -> 0.054399506 | D14: =IF('Balance Sheet'!D15<=0,"n/a",'Balance Sheet'!D11/'Balance Sheet'!D15) -> 0.021424948 | E14: =IF('Balance Sheet'!E15<=0,"n/a",'Balance Sheet'!E11/'Balance Sheet'!E15) -> 0.0070704867 | F14: =IF('Balance Sheet'!F15<=0,"n/a",'Balance Sheet'!F11/'Balance Sheet'!F15) -> 0.00036278715
A15: Return on assets (net income ÷ year-end assets) | B15: =IF('Balance Sheet'!B9<=0,"n/a",'P&L'!B22/'Balance Sheet'!B9) -> 0.58410612 | C15: =IF('Balance Sheet'!C9<=0,"n/a",'P&L'!C22/'Balance Sheet'!C9) -> 0.45673855 | D15: =IF('Balance Sheet'!D9<=0,"n/a",'P&L'!D22/'Balance Sheet'!D9) -> 0.38990602 | E15: =IF('Balance Sheet'!E9<=0,"n/a",'P&L'!E22/'Balance Sheet'!E9) -> 0.34902452 | F15: =IF('Balance Sheet'!F9<=0,"n/a",'P&L'!F22/'Balance Sheet'!F9) -> 0.32178833
A16: Return on equity (net income ÷ year-end equity) | B16: =IF('Balance Sheet'!B15<=0,"n/a",'P&L'!B22/'Balance Sheet'!B15) -> 0.72946676 | C16: =IF('Balance Sheet'!C15<=0,"n/a",'P&L'!C22/'Balance Sheet'!C15) -> 0.51088035 | D16: =IF('Balance Sheet'!D15<=0,"n/a",'P&L'!D22/'Balance Sheet'!D15) -> 0.41711009 | E16: =IF('Balance Sheet'!E15<=0,"n/a",'P&L'!E22/'Balance Sheet'!E15) -> 0.36536184 | F16: =IF('Balance Sheet'!F15<=0,"n/a",'P&L'!F22/'Balance Sheet'!F15) -> 0.33296912
A18: DuPont analysis — return on equity = net margin × asset turnover × equity multiplier
B19: 1 | C19: 2 | D19: 3 | E19: 4 | F19: 5
A20: Net margin | B20: =IF('P&L'!B5<=0,"n/a",'P&L'!B22/'P&L'!B5) -> 0.17951322 | C20: =IF('P&L'!C5<=0,"n/a",'P&L'!C22/'P&L'!C5) -> 0.19846881 | D20: =IF('P&L'!D5<=0,"n/a",'P&L'!D22/'P&L'!D5) -> 0.21432024 | E20: =IF('P&L'!E5<=0,"n/a",'P&L'!E22/'P&L'!E5) -> 0.22770636 | F20: =IF('P&L'!F5<=0,"n/a",'P&L'!F22/'P&L'!F5) -> 0.2391267
A21: × Asset turnover (revenue ÷ assets) | B21: =IF('Balance Sheet'!B9<=0,"n/a",'P&L'!B5/'Balance Sheet'!B9) -> 3.2538334 | C21: =IF('Balance Sheet'!C9<=0,"n/a",'P&L'!C5/'Balance Sheet'!C9) -> 2.3013115 | D21: =IF('Balance Sheet'!D9<=0,"n/a",'P&L'!D5/'Balance Sheet'!D9) -> 1.8192683 | E21: =IF('Balance Sheet'!E9<=0,"n/a",'P&L'!E5/'Balance Sheet'!E9) -> 1.5327834 | F21: =IF('Balance Sheet'!F9<=0,"n/a",'P&L'!F5/'Balance Sheet'!F9) -> 1.3456813
A22: × Equity multiplier (assets ÷ equity) | B22: =IF('Balance Sheet'!B15<=0,"n/a",'Balance Sheet'!B9/'Balance Sheet'!B15) -> 1.24886 | C22: =IF('Balance Sheet'!C15<=0,"n/a",'Balance Sheet'!C9/'Balance Sheet'!C15) -> 1.11854 | D22: =IF('Balance Sheet'!D15<=0,"n/a",'Balance Sheet'!D9/'Balance Sheet'!D15) -> 1.0697708 | E22: =IF('Balance Sheet'!E15<=0,"n/a",'Balance Sheet'!E9/'Balance Sheet'!E15) -> 1.0468085 | F22: =IF('Balance Sheet'!F15<=0,"n/a",'Balance Sheet'!F9/'Balance Sheet'!F15) -> 1.0347458
A23: Return on equity (product of the three) | B23: =IF(AND(ISNUMBER(B20),ISNUMBER(B21),ISNUMBER(B22)),B20*B21*B22,"n/a") -> 0.72946676 | C23: =IF(AND(ISNUMBER(C20),ISNUMBER(C21),ISNUMBER(C22)),C20*C21*C22,"n/a") -> 0.51088035 | D23: =IF(AND(ISNUMBER(D20),ISNUMBER(D21),ISNUMBER(D22)),D20*D21*D22,"n/a") -> 0.41711009 | E23: =IF(AND(ISNUMBER(E20),ISNUMBER(E21),ISNUMBER(E22)),E20*E21*E22,"n/a") -> 0.36536184 | F23: =IF(AND(ISNUMBER(F20),ISNUMBER(F21),ISNUMBER(F22)),F20*F21*F22,"n/a") -> 0.33296912
A24: Check: product − return on equity (must be 0) | B24: =IF(AND(ISNUMBER(B23),ISNUMBER(B16)),B23-B16,IF(ISNUMBER(B23),1,IF(AND(ISNUMBER(B16),ISNUMBER(B20),ISNUMBER(B21)),1,0))) -> 0 | C24: =IF(AND(ISNUMBER(C23),ISNUMBER(C16)),C23-C16,IF(ISNUMBER(C23),1,IF(AND(ISNUMBER(C16),ISNUMBER(C20),ISNUMBER(C21)),1,0))) -> 0 | D24: =IF(AND(ISNUMBER(D23),ISNUMBER(D16)),D23-D16,IF(ISNUMBER(D23),1,IF(AND(ISNUMBER(D16),ISNUMBER(D20),ISNUMBER(D21)),1,0))) -> 0 | E24: =IF(AND(ISNUMBER(E23),ISNUMBER(E16)),E23-E16,IF(ISNUMBER(E23),1,IF(AND(ISNUMBER(E16),ISNUMBER(E20),ISNUMBER(E21)),1,0))) -> 0 | F24: =IF(AND(ISNUMBER(F23),ISNUMBER(F16)),F23-F16,IF(ISNUMBER(F23),1,IF(AND(ISNUMBER(F16),ISNUMBER(F20),ISNUMBER(F21)),1,0))) -> 0
A26: Services metrics ($'000; per-unit rows in $)
A27: Year # | B27: 1 | C27: 2 | D27: 3 | E27: 4 | F27: 5
B28: Year 1 | C28: Year 2 | D28: Year 3 | E28: Year 4 | F28: Year 5 | G28: Target
A29: Billable employees (FTE, year end) | B29: =INDEX(Monthly!$C$8:$BJ$8,B$27*12) -> 16 | C29: =INDEX(Monthly!$C$8:$BJ$8,C$27*12) -> 20.4 | D29: =INDEX(Monthly!$C$8:$BJ$8,D$27*12) -> 26.04 | E29: =INDEX(Monthly!$C$8:$BJ$8,E$27*12) -> 33.276 | F29: =INDEX(Monthly!$C$8:$BJ$8,F$27*12) -> 42.5676
A30: Billable hours | B30: =SUMIF(Monthly!$C$5:$BJ$5,B$27,Monthly!$C$13:$BJ$13) -> 24960 | C30: =SUMIF(Monthly!$C$5:$BJ$5,C$27,Monthly!$C$13:$BJ$13) -> 31572 | D30: =SUMIF(Monthly!$C$5:$BJ$5,D$27,Monthly!$C$13:$BJ$13) -> 39992.4 | E30: =SUMIF(Monthly!$C$5:$BJ$5,E$27,Monthly!$C$13:$BJ$13) -> 50728.68 | F30: =SUMIF(Monthly!$C$5:$BJ$5,F$27,Monthly!$C$13:$BJ$13) -> 64433.556
A31: Billable hours — employees | B31: =B30-B32 -> 20160 | C31: =C30-C32 -> 25812 | D31: =D30-D32 -> 33080.4 | E31: =E30-E32 -> 42434.28 | F31: =F30-F32 -> 54480.276
A32: Billable hours — contractors | B32: =SUMIF(Monthly!$C$5:$BJ$5,B$27,Monthly!$C$12:$BJ$12) -> 4800 | C32: =SUMIF(Monthly!$C$5:$BJ$5,C$27,Monthly!$C$12:$BJ$12) -> 5760 | D32: =SUMIF(Monthly!$C$5:$BJ$5,D$27,Monthly!$C$12:$BJ$12) -> 6912 | E32: =SUMIF(Monthly!$C$5:$BJ$5,E$27,Monthly!$C$12:$BJ$12) -> 8294.4 | F32: =SUMIF(Monthly!$C$5:$BJ$5,F$27,Monthly!$C$12:$BJ$12) -> 9953.28
A33: Available hours — billable employees | B33: =SUMIF(Monthly!$C$5:$BJ$5,B$27,Monthly!$C$9:$BJ$9) -> 28800 | C33: =SUMIF(Monthly!$C$5:$BJ$5,C$27,Monthly!$C$9:$BJ$9) -> 36720 | D33: =SUMIF(Monthly!$C$5:$BJ$5,D$27,Monthly!$C$9:$BJ$9) -> 46872 | E33: =SUMIF(Monthly!$C$5:$BJ$5,E$27,Monthly!$C$9:$BJ$9) -> 59896.8 | F33: =SUMIF(Monthly!$C$5:$BJ$5,F$27,Monthly!$C$9:$BJ$9) -> 76621.68
A34: Utilisation of billable employees | B34: =IF(B33=0,0,B31/B33) -> 0.7 | C34: =IF(C33=0,0,C31/C33) -> 0.70294118 | D34: =IF(D33=0,0,D31/D33) -> 0.70576037 | E34: =IF(E33=0,0,E31/E33) -> 0.70845655 | F34: =IF(F33=0,0,F31/F33) -> 0.71102952
A35: Contractor share of billable hours | B35: =IF(B30=0,0,B32/B30) -> 0.19230769 | C35: =IF(C30=0,0,C32/C30) -> 0.18244014 | D35: =IF(D30=0,0,D32/D30) -> 0.17283284 | E35: =IF(E30=0,0,E32/E30) -> 0.16350514 | F35: =IF(F30=0,0,F32/F30) -> 0.15447355
A36: Fees at rate card | B36: =SUMIF(Monthly!$C$5:$BJ$5,B$27,Monthly!$C$19:$BJ$19) -> 4941000 | C36: =SUMIF(Monthly!$C$5:$BJ$5,C$27,Monthly!$C$19:$BJ$19) -> 6399081 | D36: =SUMIF(Monthly!$C$5:$BJ$5,D$27,Monthly!$C$19:$BJ$19) -> 8300258.8 | E36: =SUMIF(Monthly!$C$5:$BJ$5,E$27,Monthly!$C$19:$BJ$19) -> 10782662 | F36: =SUMIF(Monthly!$C$5:$BJ$5,F$27,Monthly!$C$19:$BJ$19) -> 14028393
A37: Fee revenue | B37: =SUMIF(Monthly!$C$5:$BJ$5,B$27,Monthly!$C$22:$BJ$22) -> 4506192 | C37: =SUMIF(Monthly!$C$5:$BJ$5,C$27,Monthly!$C$22:$BJ$22) -> 5835961.9 | D37: =SUMIF(Monthly!$C$5:$BJ$5,D$27,Monthly!$C$22:$BJ$22) -> 7569836 | E37: =SUMIF(Monthly!$C$5:$BJ$5,E$27,Monthly!$C$22:$BJ$22) -> 9833787.5 | F37: =SUMIF(Monthly!$C$5:$BJ$5,F$27,Monthly!$C$22:$BJ$22) -> 12793894
A38: Retainer fees | B38: =SUMIF(Monthly!$C$5:$BJ$5,B$27,Monthly!$C$20:$BJ$20) -> 1778760 | C38: =SUMIF(Monthly!$C$5:$BJ$5,C$27,Monthly!$C$20:$BJ$20) -> 2303669.2 | D38: =SUMIF(Monthly!$C$5:$BJ$5,D$27,Monthly!$C$20:$BJ$20) -> 2988093.2 | E38: =SUMIF(Monthly!$C$5:$BJ$5,E$27,Monthly!$C$20:$BJ$20) -> 3881758.2 | F38: =SUMIF(Monthly!$C$5:$BJ$5,F$27,Monthly!$C$20:$BJ$20) -> 5050221.3
A39: Retainer share of revenue | B39: =IF(B37=0,0,B38/B37) -> 0.39473684 | C39: =IF(C37=0,0,C38/C37) -> 0.39473684 | D39: =IF(D37=0,0,D38/D37) -> 0.39473684 | E39: =IF(E37=0,0,E38/E37) -> 0.39473684 | F39: =IF(F37=0,0,F38/F37) -> 0.39473684
A40: Realisation vs rate card (all work) | B40: =IF(B36=0,0,B37/B36) -> 0.912 | C40: =IF(C36=0,0,C37/C36) -> 0.912 | D40: =IF(D36=0,0,D37/D36) -> 0.912 | E40: =IF(E36=0,0,E37/E36) -> 0.912 | F40: =IF(F36=0,0,F37/F36) -> 0.912
A41: Effective rate per billable hour ($) | B41: =IF(B30=0,0,B37/B30) -> 180.53654 | C41: =IF(C30=0,0,C37/C30) -> 184.84613 | D41: =IF(D30=0,0,D37/D30) -> 189.28186 | E41: =IF(E30=0,0,E37/E30) -> 193.85065 | F41: =IF(F30=0,0,F37/F30) -> 198.55949
A42: Revenue per billable FTE (year-end FTE) | B42: =IF(B29=0,0,B37/B29) -> 281637 | C42: =IF(C29=0,0,C37/C29) -> 286076.56 | D42: =IF(D29=0,0,D37/D29) -> 290700.31 | E42: =IF(E29=0,0,E37/E29) -> 295521.92 | F42: =IF(F29=0,0,F37/F29) -> 300554.74
A43: Billable staff payroll | B43: =-SUMIF(Monthly!$C$5:$BJ$5,B$27,Monthly!$C$25:$BJ$25) -> 2136000 | C43: =-SUMIF(Monthly!$C$5:$BJ$5,C$27,Monthly!$C$25:$BJ$25) -> 2781000 | D43: =-SUMIF(Monthly!$C$5:$BJ$5,D$27,Monthly!$C$25:$BJ$25) -> 3625986.5 | E43: =-SUMIF(Monthly!$C$5:$BJ$5,E$27,Monthly!$C$25:$BJ$25) -> 4734349 | F43: =-SUMIF(Monthly!$C$5:$BJ$5,F$27,Monthly!$C$25:$BJ$25) -> 6189926.6
A44: Contractor cost | B44: =-SUMIF(Monthly!$C$5:$BJ$5,B$27,Monthly!$C$26:$BJ$26) -> 432000 | C44: =-SUMIF(Monthly!$C$5:$BJ$5,C$27,Monthly!$C$26:$BJ$26) -> 533952 | D44: =-SUMIF(Monthly!$C$5:$BJ$5,D$27,Monthly!$C$26:$BJ$26) -> 659964.67 | E44: =-SUMIF(Monthly!$C$5:$BJ$5,E$27,Monthly!$C$26:$BJ$26) -> 815716.33 | F44: =-SUMIF(Monthly!$C$5:$BJ$5,F$27,Monthly!$C$26:$BJ$26) -> 1008225.4
A45: Employee cost per billable hour ($) | B45: =IF(B31=0,0,B43/B31) -> 105.95238 | C45: =IF(C31=0,0,C43/C31) -> 107.74059 | D45: =IF(D31=0,0,D43/D31) -> 109.61132 | E45: =IF(E31=0,0,E43/E31) -> 111.56897 | F45: =IF(F31=0,0,F43/F31) -> 113.61775
A46: Contractor cost per billable hour ($) | B46: =IF(B32=0,0,B44/B32) -> 90 | C46: =IF(C32=0,0,C44/C32) -> 92.7 | D46: =IF(D32=0,0,D44/D32) -> 95.481 | E46: =IF(E32=0,0,E44/E32) -> 98.34543 | F46: =IF(F32=0,0,F44/F32) -> 101.29579
A47: Gross profit (delivery margin) | B47: =SUMIF(Monthly!$C$5:$BJ$5,B$27,Monthly!$C$29:$BJ$29) -> 1803006.2 | C47: =SUMIF(Monthly!$C$5:$BJ$5,C$27,Monthly!$C$29:$BJ$29) -> 2345931 | D47: =SUMIF(Monthly!$C$5:$BJ$5,D$27,Monthly!$C$29:$BJ$29) -> 3056789.8 | E47: =SUMIF(Monthly!$C$5:$BJ$5,E$27,Monthly!$C$29:$BJ$29) -> 3988708.6 | F47: =SUMIF(Monthly!$C$5:$BJ$5,F$27,Monthly!$C$29:$BJ$29) -> 5211925.2
A48: Gross margin | B48: =IF(B37=0,0,B47/B37) -> 0.40011749 | C48: =IF(C37=0,0,C47/C37) -> 0.40197847 | D48: =IF(D37=0,0,D47/D37) -> 0.40381189 | E48: =IF(E37=0,0,E47/E37) -> 0.40561265 | F48: =IF(F37=0,0,F47/F37) -> 0.40737599
A49: Receivables (year end) | B49: =INDEX(Monthly!$C$63:$BJ$63,B$27*12) -> 563274 | C49: =INDEX(Monthly!$C$63:$BJ$63,C$27*12) -> 729495.23 | D49: =INDEX(Monthly!$C$63:$BJ$63,D$27*12) -> 946229.5 | E49: =INDEX(Monthly!$C$63:$BJ$63,E$27*12) -> 1229223.4 | F49: =INDEX(Monthly!$C$63:$BJ$63,F$27*12) -> 1599236.8

Sheet Inputs
A1: Inputs — Low / Base / High | I1: =HYPERLINK("#'Cover'!A1","◂ Contents") -> ◂ Contents
A2: Illustrative assumptions — replace them with your own numbers.
A5: Driver | B5: Low | C5: Base | D5: High | E5: Active | F5: Unit | G5: Source / comment
A6: Billable capacity
A7: Available hours per billable FTE per year | B7: 1800 | C7: 1800 | D7: 1800 | E7: =CHOOSE(Dashboard!$B$4,B7,C7,D7) -> 1800 | F7: hours
A8: Utilisation — partners & senior consultants | B8: 0.5 | C8: 0.55 | D8: 0.6 | E8: =CHOOSE(Dashboard!$B$4,B8,C8,D8) -> 0.55 | F8: % | G8: Low ≤ Base ≤ High
A9: Utilisation — consultants | B9: 0.68 | C9: 0.75 | D9: 0.8 | E9: =CHOOSE(Dashboard!$B$4,B9,C9,D9) -> 0.75 | F9: % | G9: Low ≤ Base ≤ High
A10: Contractor billable hours per month (year 1) | B10: 300 | C10: 400 | D10: 500 | E10: =CHOOSE(Dashboard!$B$4,B10,C10,D10) -> 400 | F10: hours | G10: Low ≤ Base ≤ High
A11: Contractor hours growth per year | B11: 0.1 | C11: 0.2 | D11: 0.3 | E11: =CHOOSE(Dashboard!$B$4,B11,C11,D11) -> 0.2 | F11: % | G11: Low ≤ Base ≤ High
A13: Rate card
A14: Hourly rate — partners & senior consultants | B14: 300 | C14: 350 | D14: 400 | E14: =CHOOSE(Dashboard!$B$4,B14,C14,D14) -> 350 | F14: $ / hour | G14: Low ≤ Base ≤ High
A15: Hourly rate — consultants | B15: 150 | C15: 175 | D15: 200 | E15: =CHOOSE(Dashboard!$B$4,B15,C15,D15) -> 175 | F15: $ / hour | G15: Low ≤ Base ≤ High
A16: Hourly rate billed for contractor hours | B16: 140 | C16: 150 | D16: 165 | E16: =CHOOSE(Dashboard!$B$4,B16,C16,D16) -> 150 | F16: $ / hour | G16: Low ≤ Base ≤ High
A17: Rate card increase per year | B17: 0.02 | C17: 0.03 | D17: 0.04 | E17: =CHOOSE(Dashboard!$B$4,B17,C17,D17) -> 0.03 | F17: % | G17: Low ≤ Base ≤ High
A19: Retainer vs project
A20: Share of billable hours under retainers | B20: 0.4 | C20: 0.4 | D20: 0.4 | E20: =CHOOSE(Dashboard!$B$4,B20,C20,D20) -> 0.4 | F20: %
A21: Retainer discount vs rate card | B21: 0.12 | C21: 0.1 | D21: 0.08 | E21: =CHOOSE(Dashboard!$B$4,B21,C21,D21) -> 0.1 | F21: % | G21: Low ≥ Base ≥ High (lower is better)
A22: Project realisation (billed ÷ rate-card value) | B22: 0.88 | C22: 0.92 | D22: 0.95 | E22: =CHOOSE(Dashboard!$B$4,B22,C22,D22) -> 0.92 | F22: % | G22: Low ≤ Base ≤ High
A24: Costs
A25: Contractor cost per hour (year 1) | B25: 95 | C25: 90 | D25: 85 | E25: =CHOOSE(Dashboard!$B$4,B25,C25,D25) -> 90 | F25: $ / hour | G25: Low ≥ Base ≥ High (lower is better)
A26: Non-rebillable delivery costs, % of fees | B26: 0.04 | C26: 0.03 | D26: 0.025 | E26: =CHOOSE(Dashboard!$B$4,B26,C26,D26) -> 0.03 | F26: % | G26: Low ≥ Base ≥ High (lower is better)
A27: Software & tools per FTE per month | B27: 200 | C27: 200 | D27: 200 | E27: =CHOOSE(Dashboard!$B$4,B27,C27,D27) -> 200 | F27: $
A28: Marketing & business development per month | B28: 8000 | C28: 8000 | D28: 8000 | E28: =CHOOSE(Dashboard!$B$4,B28,C28,D28) -> 8000 | F28: $
A29: Office & rent per month | B29: 8000 | C29: 8000 | D29: 8000 | E29: =CHOOSE(Dashboard!$B$4,B29,C29,D29) -> 8000 | F29: $
A30: Other G&A per month (insurance, legal, accounting) | B30: 6000 | C30: 6000 | D30: 6000 | E30: =CHOOSE(Dashboard!$B$4,B30,C30,D30) -> 6000 | F30: $
A31: Start-up capex (equipment, fit-out) | B31: 60000 | C31: 60000 | D31: 60000 | E31: =CHOOSE(Dashboard!$B$4,B31,C31,D31) -> 60000 | F31: $
A33: Headcount
A34: Partners & senior consultants: headcount (FTE) | B34: 4 | C34: 4 | D34: 4 | E34: =CHOOSE(Dashboard!$B$4,B34,C34,D34) -> 4 | F34: FTE | G34: Low ≤ Base ≤ High
A35: Partners & senior consultants: salary per FTE per year | B35: 160000 | C35: 160000 | D35: 160000 | E35: =CHOOSE(Dashboard!$B$4,B35,C35,D35) -> 160000 | F35: $
A36: Partners & senior consultants: headcount growth per year | B36: 0.2 | C36: 0.2 | D36: 0.2 | E36: =CHOOSE(Dashboard!$B$4,B36,C36,D36) -> 0.2 | F36: % | G36: Low ≤ Base ≤ High
A37: Partners & senior consultants: first month on payroll | B37: 1 | C37: 1 | D37: 1 | E37: =CHOOSE(Dashboard!$B$4,B37,C37,D37) -> 1 | F37: month #
A38: Consultants: headcount (FTE) | B38: 12 | C38: 12 | D38: 12 | E38: =CHOOSE(Dashboard!$B$4,B38,C38,D38) -> 12 | F38: FTE | G38: Low ≤ Base ≤ High
A39: Consultants: salary per FTE per year | B39: 95000 | C39: 95000 | D39: 95000 | E39: =CHOOSE(Dashboard!$B$4,B39,C39,D39) -> 95000 | F39: $
A40: Consultants: headcount growth per year | B40: 0.3 | C40: 0.3 | D40: 0.3 | E40: =CHOOSE(Dashboard!$B$4,B40,C40,D40) -> 0.3 | F40: % | G40: Low ≤ Base ≤ High
A41: Consultants: first month on payroll | B41: 1 | C41: 1 | D41: 1 | E41: =CHOOSE(Dashboard!$B$4,B41,C41,D41) -> 1 | F41: month #
A42: Business development: headcount (FTE) | B42: 2 | C42: 2 | D42: 2 | E42: =CHOOSE(Dashboard!$B$4,B42,C42,D42) -> 2 | F42: FTE | G42: Low ≤ Base ≤ High
A43: Business development: salary per FTE per year | B43: 85000 | C43: 85000 | D43: 85000 | E43: =CHOOSE(Dashboard!$B$4,B43,C43,D43) -> 85000 | F43: $
A44: Business development: headcount growth per year | B44: 0.2 | C44: 0.2 | D44: 0.2 | E44: =CHOOSE(Dashboard!$B$4,B44,C44,D44) -> 0.2 | F44: % | G44: Low ≤ Base ≤ High
A45: Business development: first month on payroll | B45: 1 | C45: 1 | D45: 1 | E45: =CHOOSE(Dashboard!$B$4,B45,C45,D45) -> 1 | F45: month #
A46: Operations & admin: headcount (FTE) | B46: 3 | C46: 3 | D46: 3 | E46: =CHOOSE(Dashboard!$B$4,B46,C46,D46) -> 3 | F46: FTE | G46: Low ≤ Base ≤ High
A47: Operations & admin: salary per FTE per year | B47: 65000 | C47: 65000 | D47: 65000 | E47: =CHOOSE(Dashboard!$B$4,B47,C47,D47) -> 65000 | F47: $
A48: Operations & admin: headcount growth per year | B48: 0.15 | C48: 0.15 | D48: 0.15 | E48: =CHOOSE(Dashboard!$B$4,B48,C48,D48) -> 0.15 | F48: % | G48: Low ≤ Base ≤ High
A49: Operations & admin: first month on payroll | B49: 1 | C49: 1 | D49: 1 | E49: =CHOOSE(Dashboard!$B$4,B49,C49,D49) -> 1 | F49: month #
A50: Payroll taxes & benefits, % of salary | B50: 0.2 | C50: 0.2 | D50: 0.2 | E50: =CHOOSE(Dashboard!$B$4,B50,C50,D50) -> 0.2 | F50: %
A51: Wage growth per year | B51: 0.03 | C51: 0.03 | D51: 0.03 | E51: =CHOOSE(Dashboard!$B$4,B51,C51,D51) -> 0.03 | F51: %
A53: Funding
A54: Equity raised at start | B54: 300000 | C54: 300000 | D54: 300000 | E54: =CHOOSE(Dashboard!$B$4,B54,C54,D54) -> 300000 | F54: $
A55: Loan drawn at start | B55: 200000 | C55: 200000 | D55: 200000 | E55: =CHOOSE(Dashboard!$B$4,B55,C55,D55) -> 200000 | F55: $
A56: Loan interest rate per year | B56: 0.08 | C56: 0.08 | D56: 0.08 | E56: =CHOOSE(Dashboard!$B$4,B56,C56,D56) -> 0.08 | F56: %
A57: Loan repayment term | B57: 5 | C57: 5 | D57: 5 | E57: =CHOOSE(Dashboard!$B$4,B57,C57,D57) -> 5 | F57: years
A59: Working capital
A60: Customer payment terms (receivable days) | B60: 45 | C60: 45 | D60: 45 | E60: =CHOOSE(Dashboard!$B$4,B60,C60,D60) -> 45 | F60: days
A61: Inventory held (days of COGS) | B61: 0 | C61: 0 | D61: 0 | E61: =CHOOSE(Dashboard!$B$4,B61,C61,D61) -> 0 | F61: days
A62: Supplier payment terms (payable days) | B62: 15 | C62: 15 | D62: 15 | E62: =CHOOSE(Dashboard!$B$4,B62,C62,D62) -> 15 | F62: days
A64: Tax & depreciation
A65: Depreciation period for capex | B65: 5 | C65: 5 | D65: 5 | E65: =CHOOSE(Dashboard!$B$4,B65,C65,D65) -> 5 | F65: years
A66: Income tax rate | B66: 0.21 | C66: 0.21 | D66: 0.21 | E66: =CHOOSE(Dashboard!$B$4,B66,C66,D66) -> 0.21 | F66: %
A68: Break-even & funding
A69: Minimum cash buffer to keep | B69: 188000 | C69: 188000 | D69: 188000 | E69: =CHOOSE(Dashboard!$B$4,B69,C69,D69) -> 188000 | F69: $ | G69: About 3 months of costs
A71: Valuation
A72: Discount rate (WACC) | B72: 0.2 | C72: 0.16 | D72: 0.13 | E72: =CHOOSE(Dashboard!$B$4,B72,C72,D72) -> 0.16 | F72: % | G72: Low ≥ Base ≥ High (lower is better)
A73: Terminal growth rate (perpetuity) | B73: 0.01 | C73: 0.02 | D73: 0.03 | E73: =CHOOSE(Dashboard!$B$4,B73,C73,D73) -> 0.02 | F73: % | G73: Low ≤ Base ≤ High
A74: Exit multiple (EV ÷ final-year EBITDA) | B74: 4 | C74: 5.5 | D74: 7 | E74: =CHOOSE(Dashboard!$B$4,B74,C74,D74) -> 5.5 | F74: x | G74: Low ≤ Base ≤ High
A75: Sensitivity table: WACC step | B75: 0.01 | C75: 0.01 | D75: 0.01 | E75: =CHOOSE(Dashboard!$B$4,B75,C75,D75) -> 0.01 | F75: %
A76: Sensitivity table: growth step | B76: 0.005 | C76: 0.005 | D76: 0.005 | E76: =CHOOSE(Dashboard!$B$4,B76,C76,D76) -> 0.005 | F76: %
A78: Legend: yellow cell with blue figure = input you can change · black = formula · green = link to another sheet · grey = active value (column E follows the scenario on the Dashboard).

Sheet P&L
A1: Annual profit & loss | H1: =HYPERLINK("#'Cover'!A1","◂ Contents") -> ◂ Contents
A2: Rolled up from the period detail (SUMIF on the year row; balances at year end).
A3: Year # | B3: 1 | C3: 2 | D3: 3 | E3: 4 | F3: 5
B4: Year 1 | C4: Year 2 | D4: Year 3 | E4: Year 4 | F4: Year 5
A5: Revenue | B5: =SUMIF(Monthly!$C$5:$BJ$5,B$3,Monthly!$C$22:$BJ$22) -> 4506192 | C5: =SUMIF(Monthly!$C$5:$BJ$5,C$3,Monthly!$C$22:$BJ$22) -> 5835961.9 | D5: =SUMIF(Monthly!$C$5:$BJ$5,D$3,Monthly!$C$22:$BJ$22) -> 7569836 | E5: =SUMIF(Monthly!$C$5:$BJ$5,E$3,Monthly!$C$22:$BJ$22) -> 9833787.5 | F5: =SUMIF(Monthly!$C$5:$BJ$5,F$3,Monthly!$C$22:$BJ$22) -> 12793894
A6: Cost of delivery | B6: =SUMIF(Monthly!$C$5:$BJ$5,B$3,Monthly!$C$28:$BJ$28) -> -2703185.8 | C6: =SUMIF(Monthly!$C$5:$BJ$5,C$3,Monthly!$C$28:$BJ$28) -> -3490030.9 | D6: =SUMIF(Monthly!$C$5:$BJ$5,D$3,Monthly!$C$28:$BJ$28) -> -4513046.2 | E6: =SUMIF(Monthly!$C$5:$BJ$5,E$3,Monthly!$C$28:$BJ$28) -> -5845079 | F6: =SUMIF(Monthly!$C$5:$BJ$5,F$3,Monthly!$C$28:$BJ$28) -> -7581968.8
A7: Gross profit | B7: =SUMIF(Monthly!$C$5:$BJ$5,B$3,Monthly!$C$29:$BJ$29) -> 1803006.2 | C7: =SUMIF(Monthly!$C$5:$BJ$5,C$3,Monthly!$C$29:$BJ$29) -> 2345931 | D7: =SUMIF(Monthly!$C$5:$BJ$5,D$3,Monthly!$C$29:$BJ$29) -> 3056789.8 | E7: =SUMIF(Monthly!$C$5:$BJ$5,E$3,Monthly!$C$29:$BJ$29) -> 3988708.6 | F7: =SUMIF(Monthly!$C$5:$BJ$5,F$3,Monthly!$C$29:$BJ$29) -> 5211925.2
A8: Gross margin | B8: =IF(B5=0,0,B7/B5) -> 0.40011749 | C8: =IF(C5=0,0,C7/C5) -> 0.40197847 | D8: =IF(D5=0,0,D7/D5) -> 0.40381189 | E8: =IF(E5=0,0,E7/E5) -> 0.40561265 | F8: =IF(F5=0,0,F7/F5) -> 0.40737599
A9: Non-billable payroll | B9: =SUMIF(Monthly!$C$5:$BJ$5,B$3,Monthly!$C$32:$BJ$32) -> -438000 | C9: =SUMIF(Monthly!$C$5:$BJ$5,C$3,Monthly!$C$32:$BJ$32) -> -529317 | D9: =SUMIF(Monthly!$C$5:$BJ$5,D$3,Monthly!$C$32:$BJ$32) -> -639961.4 | E9: =SUMIF(Monthly!$C$5:$BJ$5,E$3,Monthly!$C$32:$BJ$32) -> -774084.26 | F9: =SUMIF(Monthly!$C$5:$BJ$5,F$3,Monthly!$C$32:$BJ$32) -> -936740.57
A10: Marketing & business development | B10: =SUMIF(Monthly!$C$5:$BJ$5,B$3,Monthly!$C$33:$BJ$33) -> -96000 | C10: =SUMIF(Monthly!$C$5:$BJ$5,C$3,Monthly!$C$33:$BJ$33) -> -96000 | D10: =SUMIF(Monthly!$C$5:$BJ$5,D$3,Monthly!$C$33:$BJ$33) -> -96000 | E10: =SUMIF(Monthly!$C$5:$BJ$5,E$3,Monthly!$C$33:$BJ$33) -> -96000 | F10: =SUMIF(Monthly!$C$5:$BJ$5,F$3,Monthly!$C$33:$BJ$33) -> -96000
A11: Software & tools | B11: =SUMIF(Monthly!$C$5:$BJ$5,B$3,Monthly!$C$34:$BJ$34) -> -50400 | C11: =SUMIF(Monthly!$C$5:$BJ$5,C$3,Monthly!$C$34:$BJ$34) -> -63000 | D11: =SUMIF(Monthly!$C$5:$BJ$5,D$3,Monthly!$C$34:$BJ$34) -> -78930 | E11: =SUMIF(Monthly!$C$5:$BJ$5,E$3,Monthly!$C$34:$BJ$34) -> -99107.1 | F11: =SUMIF(Monthly!$C$5:$BJ$5,F$3,Monthly!$C$34:$BJ$34) -> -124708.37
A12: Office & rent | B12: =SUMIF(Monthly!$C$5:$BJ$5,B$3,Monthly!$C$35:$BJ$35) -> -96000 | C12: =SUMIF(Monthly!$C$5:$BJ$5,C$3,Monthly!$C$35:$BJ$35) -> -96000 | D12: =SUMIF(Monthly!$C$5:$BJ$5,D$3,Monthly!$C$35:$BJ$35) -> -96000 | E12: =SUMIF(Monthly!$C$5:$BJ$5,E$3,Monthly!$C$35:$BJ$35) -> -96000 | F12: =SUMIF(Monthly!$C$5:$BJ$5,F$3,Monthly!$C$35:$BJ$35) -> -96000
A13: Other G&A | B13: =SUMIF(Monthly!$C$5:$BJ$5,B$3,Monthly!$C$36:$BJ$36) -> -72000 | C13: =SUMIF(Monthly!$C$5:$BJ$5,C$3,Monthly!$C$36:$BJ$36) -> -72000 | D13: =SUMIF(Monthly!$C$5:$BJ$5,D$3,Monthly!$C$36:$BJ$36) -> -72000 | E13: =SUMIF(Monthly!$C$5:$BJ$5,E$3,Monthly!$C$36:$BJ$36) -> -72000 | F13: =SUMIF(Monthly!$C$5:$BJ$5,F$3,Monthly!$C$36:$BJ$36) -> -72000
A14: Total operating expenses | B14: =SUMIF(Monthly!$C$5:$BJ$5,B$3,Monthly!$C$37:$BJ$37) -> -752400 | C14: =SUMIF(Monthly!$C$5:$BJ$5,C$3,Monthly!$C$37:$BJ$37) -> -856317 | D14: =SUMIF(Monthly!$C$5:$BJ$5,D$3,Monthly!$C$37:$BJ$37) -> -982891.4 | E14: =SUMIF(Monthly!$C$5:$BJ$5,E$3,Monthly!$C$37:$BJ$37) -> -1137191.4 | F14: =SUMIF(Monthly!$C$5:$BJ$5,F$3,Monthly!$C$37:$BJ$37) -> -1325448.9
A15: EBITDA | B15: =SUMIF(Monthly!$C$5:$BJ$5,B$3,Monthly!$C$38:$BJ$38) -> 1050606.2 | C15: =SUMIF(Monthly!$C$5:$BJ$5,C$3,Monthly!$C$38:$BJ$38) -> 1489614 | D15: =SUMIF(Monthly!$C$5:$BJ$5,D$3,Monthly!$C$38:$BJ$38) -> 2073898.4 | E15: =SUMIF(Monthly!$C$5:$BJ$5,E$3,Monthly!$C$38:$BJ$38) -> 2851517.2 | F15: =SUMIF(Monthly!$C$5:$BJ$5,F$3,Monthly!$C$38:$BJ$38) -> 3886476.3
A16: EBITDA margin | B16: =IF(B5=0,0,B15/B5) -> 0.23314724 | C16: =IF(C5=0,0,C15/C5) -> 0.25524739 | D16: =IF(D5=0,0,D15/D5) -> 0.27396874 | E16: =IF(E5=0,0,E15/E5) -> 0.28997141 | F16: =IF(F5=0,0,F15/F5) -> 0.30377587
A17: Depreciation | B17: =SUMIF(Monthly!$C$5:$BJ$5,B$3,Monthly!$C$52:$BJ$52) -> -12000 | C17: =SUMIF(Monthly!$C$5:$BJ$5,C$3,Monthly!$C$52:$BJ$52) -> -12000 | D17: =SUMIF(Monthly!$C$5:$BJ$5,D$3,Monthly!$C$52:$BJ$52) -> -12000 | E17: =SUMIF(Monthly!$C$5:$BJ$5,E$3,Monthly!$C$52:$BJ$52) -> -12000 | F17: =SUMIF(Monthly!$C$5:$BJ$5,F$3,Monthly!$C$52:$BJ$52) -> -12000
A18: EBIT | B18: =SUMIF(Monthly!$C$5:$BJ$5,B$3,Monthly!$C$41:$BJ$41) -> 1038606.2 | C18: =SUMIF(Monthly!$C$5:$BJ$5,C$3,Monthly!$C$41:$BJ$41) -> 1477614 | D18: =SUMIF(Monthly!$C$5:$BJ$5,D$3,Monthly!$C$41:$BJ$41) -> 2061898.4 | E18: =SUMIF(Monthly!$C$5:$BJ$5,E$3,Monthly!$C$41:$BJ$41) -> 2839517.2 | F18: =SUMIF(Monthly!$C$5:$BJ$5,F$3,Monthly!$C$41:$BJ$41) -> 3874476.3
A19: Interest | B19: =SUMIF(Monthly!$C$5:$BJ$5,B$3,Monthly!$C$42:$BJ$42) -> -14655.556 | C19: =SUMIF(Monthly!$C$5:$BJ$5,C$3,Monthly!$C$42:$BJ$42) -> -11466.667 | D19: =SUMIF(Monthly!$C$5:$BJ$5,D$3,Monthly!$C$42:$BJ$42) -> -8266.6667 | E19: =SUMIF(Monthly!$C$5:$BJ$5,E$3,Monthly!$C$42:$BJ$42) -> -5066.6667 | F19: =SUMIF(Monthly!$C$5:$BJ$5,F$3,Monthly!$C$42:$BJ$42) -> -1866.6667
A20: Pre-tax income | B20: =SUMIF(Monthly!$C$5:$BJ$5,B$3,Monthly!$C$43:$BJ$43) -> 1023950.7 | C20: =SUMIF(Monthly!$C$5:$BJ$5,C$3,Monthly!$C$43:$BJ$43) -> 1466147.3 | D20: =SUMIF(Monthly!$C$5:$BJ$5,D$3,Monthly!$C$43:$BJ$43) -> 2053631.8 | E20: =SUMIF(Monthly!$C$5:$BJ$5,E$3,Monthly!$C$43:$BJ$43) -> 2834450.6 | F20: =SUMIF(Monthly!$C$5:$BJ$5,F$3,Monthly!$C$43:$BJ$43) -> 3872609.6
A21: Income tax | B21: =SUMIF(Monthly!$C$5:$BJ$5,B$3,Monthly!$C$46:$BJ$46) -> -215029.64 | C21: =SUMIF(Monthly!$C$5:$BJ$5,C$3,Monthly!$C$46:$BJ$46) -> -307890.94 | D21: =SUMIF(Monthly!$C$5:$BJ$5,D$3,Monthly!$C$46:$BJ$46) -> -431262.67 | E21: =SUMIF(Monthly!$C$5:$BJ$5,E$3,Monthly!$C$46:$BJ$46) -> -595234.62 | F21: =SUMIF(Monthly!$C$5:$BJ$5,F$3,Monthly!$C$46:$BJ$46) -> -813248.02
A22: Net income | B22: =SUMIF(Monthly!$C$5:$BJ$5,B$3,Monthly!$C$47:$BJ$47) -> 808921.04 | C22: =SUMIF(Monthly!$C$5:$BJ$5,C$3,Monthly!$C$47:$BJ$47) -> 1158256.4 | D22: =SUMIF(Monthly!$C$5:$BJ$5,D$3,Monthly!$C$47:$BJ$47) -> 1622369.1 | E22: =SUMIF(Monthly!$C$5:$BJ$5,E$3,Monthly!$C$47:$BJ$47) -> 2239215.9 | F22: =SUMIF(Monthly!$C$5:$BJ$5,F$3,Monthly!$C$47:$BJ$47) -> 3059361.6
A23: Net margin | B23: =IF(B5=0,0,B22/B5) -> 0.17951322 | C23: =IF(C5=0,0,C22/C5) -> 0.19846881 | D23: =IF(D5=0,0,D22/D5) -> 0.21432024 | E23: =IF(E5=0,0,E22/E5) -> 0.22770636 | F23: =IF(F5=0,0,F22/F5) -> 0.2391267

Sheet Cash Flow
A1: Annual cash flow statement | H1: =HYPERLINK("#'Cover'!A1","◂ Contents") -> ◂ Contents
A2: Rolled up from the period detail (SUMIF on the year row; balances at year end).
A3: Year # | B3: 1 | C3: 2 | D3: 3 | E3: 4 | F3: 5
B4: Year 1 | C4: Year 2 | D4: Year 3 | E4: Year 4 | F4: Year 5
A5: Net income | B5: =SUMIF(Monthly!$C$5:$BJ$5,B$3,Monthly!$C$47:$BJ$47) -> 808921.04 | C5: =SUMIF(Monthly!$C$5:$BJ$5,C$3,Monthly!$C$47:$BJ$47) -> 1158256.4 | D5: =SUMIF(Monthly!$C$5:$BJ$5,D$3,Monthly!$C$47:$BJ$47) -> 1622369.1 | E5: =SUMIF(Monthly!$C$5:$BJ$5,E$3,Monthly!$C$47:$BJ$47) -> 2239215.9 | F5: =SUMIF(Monthly!$C$5:$BJ$5,F$3,Monthly!$C$47:$BJ$47) -> 3059361.6
A6: Add back depreciation | B6: =-SUMIF(Monthly!$C$5:$BJ$5,B$3,Monthly!$C$52:$BJ$52) -> 12000 | C6: =-SUMIF(Monthly!$C$5:$BJ$5,C$3,Monthly!$C$52:$BJ$52) -> 12000 | D6: =-SUMIF(Monthly!$C$5:$BJ$5,D$3,Monthly!$C$52:$BJ$52) -> 12000 | E6: =-SUMIF(Monthly!$C$5:$BJ$5,E$3,Monthly!$C$52:$BJ$52) -> 12000 | F6: =-SUMIF(Monthly!$C$5:$BJ$5,F$3,Monthly!$C$52:$BJ$52) -> 12000
A7: (Increase) / decrease in receivables | B7: =SUMIF(Monthly!$C$5:$BJ$5,B$3,Monthly!$C$66:$BJ$66) -> -563274 | C7: =SUMIF(Monthly!$C$5:$BJ$5,C$3,Monthly!$C$66:$BJ$66) -> -166221.23 | D7: =SUMIF(Monthly!$C$5:$BJ$5,D$3,Monthly!$C$66:$BJ$66) -> -216734.27 | E7: =SUMIF(Monthly!$C$5:$BJ$5,E$3,Monthly!$C$66:$BJ$66) -> -282993.94 | F7: =SUMIF(Monthly!$C$5:$BJ$5,F$3,Monthly!$C$66:$BJ$66) -> -370013.31
A8: (Increase) / decrease in inventory | B8: =SUMIF(Monthly!$C$5:$BJ$5,B$3,Monthly!$C$67:$BJ$67) -> 0 | C8: =SUMIF(Monthly!$C$5:$BJ$5,C$3,Monthly!$C$67:$BJ$67) -> 0 | D8: =SUMIF(Monthly!$C$5:$BJ$5,D$3,Monthly!$C$67:$BJ$67) -> 0 | E8: =SUMIF(Monthly!$C$5:$BJ$5,E$3,Monthly!$C$67:$BJ$67) -> 0 | F8: =SUMIF(Monthly!$C$5:$BJ$5,F$3,Monthly!$C$67:$BJ$67) -> 0
A9: Increase / (decrease) in payables | B9: =SUMIF(Monthly!$C$5:$BJ$5,B$3,Monthly!$C$68:$BJ$68) -> 112632.74 | C9: =SUMIF(Monthly!$C$5:$BJ$5,C$3,Monthly!$C$68:$BJ$68) -> 32785.212 | D9: =SUMIF(Monthly!$C$5:$BJ$5,D$3,Monthly!$C$68:$BJ$68) -> 42625.64 | E9: =SUMIF(Monthly!$C$5:$BJ$5,E$3,Monthly!$C$68:$BJ$68) -> 55501.365 | F9: =SUMIF(Monthly!$C$5:$BJ$5,F$3,Monthly!$C$68:$BJ$68) -> 72370.41
A10: Operating cash flow | B10: =SUMIF(Monthly!$C$5:$BJ$5,B$3,Monthly!$C$71:$BJ$71) -> 370279.78 | C10: =SUMIF(Monthly!$C$5:$BJ$5,C$3,Monthly!$C$71:$BJ$71) -> 1036820.4 | D10: =SUMIF(Monthly!$C$5:$BJ$5,D$3,Monthly!$C$71:$BJ$71) -> 1460260.5 | E10: =SUMIF(Monthly!$C$5:$BJ$5,E$3,Monthly!$C$71:$BJ$71) -> 2023723.4 | F10: =SUMIF(Monthly!$C$5:$BJ$5,F$3,Monthly!$C$71:$BJ$71) -> 2773718.7
A11: Capital spending | B11: =SUMIF(Monthly!$C$5:$BJ$5,B$3,Monthly!$C$72:$BJ$72) -> -60000 | C11: =SUMIF(Monthly!$C$5:$BJ$5,C$3,Monthly!$C$72:$BJ$72) -> 0 | D11: =SUMIF(Monthly!$C$5:$BJ$5,D$3,Monthly!$C$72:$BJ$72) -> 0 | E11: =SUMIF(Monthly!$C$5:$BJ$5,E$3,Monthly!$C$72:$BJ$72) -> 0 | F11: =SUMIF(Monthly!$C$5:$BJ$5,F$3,Monthly!$C$72:$BJ$72) -> 0
A12: Equity raised | B12: =SUMIF(Monthly!$C$5:$BJ$5,B$3,Monthly!$C$73:$BJ$73) -> 300000 | C12: =SUMIF(Monthly!$C$5:$BJ$5,C$3,Monthly!$C$73:$BJ$73) -> 0 | D12: =SUMIF(Monthly!$C$5:$BJ$5,D$3,Monthly!$C$73:$BJ$73) -> 0 | E12: =SUMIF(Monthly!$C$5:$BJ$5,E$3,Monthly!$C$73:$BJ$73) -> 0 | F12: =SUMIF(Monthly!$C$5:$BJ$5,F$3,Monthly!$C$73:$BJ$73) -> 0
A13: Loan drawdown | B13: =SUMIF(Monthly!$C$5:$BJ$5,B$3,Monthly!$C$58:$BJ$58) -> 200000 | C13: =SUMIF(Monthly!$C$5:$BJ$5,C$3,Monthly!$C$58:$BJ$58) -> 0 | D13: =SUMIF(Monthly!$C$5:$BJ$5,D$3,Monthly!$C$58:$BJ$58) -> 0 | E13: =SUMIF(Monthly!$C$5:$BJ$5,E$3,Monthly!$C$58:$BJ$58) -> 0 | F13: =SUMIF(Monthly!$C$5:$BJ$5,F$3,Monthly!$C$58:$BJ$58) -> 0
A14: Loan repayment | B14: =SUMIF(Monthly!$C$5:$BJ$5,B$3,Monthly!$C$59:$BJ$59) -> -36666.667 | C14: =SUMIF(Monthly!$C$5:$BJ$5,C$3,Monthly!$C$59:$BJ$59) -> -40000 | D14: =SUMIF(Monthly!$C$5:$BJ$5,D$3,Monthly!$C$59:$BJ$59) -> -40000 | E14: =SUMIF(Monthly!$C$5:$BJ$5,E$3,Monthly!$C$59:$BJ$59) -> -40000 | F14: =SUMIF(Monthly!$C$5:$BJ$5,F$3,Monthly!$C$59:$BJ$59) -> -40000
A15: Financing cash flow | B15: =SUMIF(Monthly!$C$5:$BJ$5,B$3,Monthly!$C$74:$BJ$74) -> 463333.33 | C15: =SUMIF(Monthly!$C$5:$BJ$5,C$3,Monthly!$C$74:$BJ$74) -> -40000 | D15: =SUMIF(Monthly!$C$5:$BJ$5,D$3,Monthly!$C$74:$BJ$74) -> -40000 | E15: =SUMIF(Monthly!$C$5:$BJ$5,E$3,Monthly!$C$74:$BJ$74) -> -40000 | F15: =SUMIF(Monthly!$C$5:$BJ$5,F$3,Monthly!$C$74:$BJ$74) -> -40000
A16: Net change in cash | B16: =SUMIF(Monthly!$C$5:$BJ$5,B$3,Monthly!$C$75:$BJ$75) -> 773613.11 | C16: =SUMIF(Monthly!$C$5:$BJ$5,C$3,Monthly!$C$75:$BJ$75) -> 996820.38 | D16: =SUMIF(Monthly!$C$5:$BJ$5,D$3,Monthly!$C$75:$BJ$75) -> 1420260.5 | E16: =SUMIF(Monthly!$C$5:$BJ$5,E$3,Monthly!$C$75:$BJ$75) -> 1983723.4 | F16: =SUMIF(Monthly!$C$5:$BJ$5,F$3,Monthly!$C$75:$BJ$75) -> 2733718.7
A17: Opening cash | B17: =INDEX(Monthly!$C$76:$BJ$76,(B$3-1)*12+1) -> 0 | C17: =INDEX(Monthly!$C$76:$BJ$76,(C$3-1)*12+1) -> 773613.11 | D17: =INDEX(Monthly!$C$76:$BJ$76,(D$3-1)*12+1) -> 1770433.5 | E17: =INDEX(Monthly!$C$76:$BJ$76,(E$3-1)*12+1) -> 3190694 | F17: =INDEX(Monthly!$C$76:$BJ$76,(F$3-1)*12+1) -> 5174417.3
A18: Closing cash | B18: =INDEX(Monthly!$C$77:$BJ$77,B$3*12) -> 773613.11 | C18: =INDEX(Monthly!$C$77:$BJ$77,C$3*12) -> 1770433.5 | D18: =INDEX(Monthly!$C$77:$BJ$77,D$3*12) -> 3190694 | E18: =INDEX(Monthly!$C$77:$BJ$77,E$3*12) -> 5174417.3 | F18: =INDEX(Monthly!$C$77:$BJ$77,F$3*12) -> 7908136

Sheet Balance Sheet
A1: Balance sheet at year end | H1: =HYPERLINK("#'Cover'!A1","◂ Contents") -> ◂ Contents
A2: Rolled up from the period detail (SUMIF on the year row; balances at year end).
A3: Year # | B3: 1 | C3: 2 | D3: 3 | E3: 4 | F3: 5
B4: Year 1 | C4: Year 2 | D4: Year 3 | E4: Year 4 | F4: Year 5
A5: Cash | B5: =INDEX(Monthly!$C$77:$BJ$77,B$3*12) -> 773613.11 | C5: =INDEX(Monthly!$C$77:$BJ$77,C$3*12) -> 1770433.5 | D5: =INDEX(Monthly!$C$77:$BJ$77,D$3*12) -> 3190694 | E5: =INDEX(Monthly!$C$77:$BJ$77,E$3*12) -> 5174417.3 | F5: =INDEX(Monthly!$C$77:$BJ$77,F$3*12) -> 7908136
A6: Accounts receivable | B6: =INDEX(Monthly!$C$63:$BJ$63,B$3*12) -> 563274 | C6: =INDEX(Monthly!$C$63:$BJ$63,C$3*12) -> 729495.23 | D6: =INDEX(Monthly!$C$63:$BJ$63,D$3*12) -> 946229.5 | E6: =INDEX(Monthly!$C$63:$BJ$63,E$3*12) -> 1229223.4 | F6: =INDEX(Monthly!$C$63:$BJ$63,F$3*12) -> 1599236.8
A7: Inventory | B7: =INDEX(Monthly!$C$64:$BJ$64,B$3*12) -> 0 | C7: =INDEX(Monthly!$C$64:$BJ$64,C$3*12) -> 0 | D7: =INDEX(Monthly!$C$64:$BJ$64,D$3*12) -> 0 | E7: =INDEX(Monthly!$C$64:$BJ$64,E$3*12) -> 0 | F7: =INDEX(Monthly!$C$64:$BJ$64,F$3*12) -> 0
A8: Net fixed assets | B8: =INDEX(Monthly!$C$54:$BJ$54,B$3*12) -> 48000 | C8: =INDEX(Monthly!$C$54:$BJ$54,C$3*12) -> 36000 | D8: =INDEX(Monthly!$C$54:$BJ$54,D$3*12) -> 24000 | E8: =INDEX(Monthly!$C$54:$BJ$54,E$3*12) -> 12000 | F8: =INDEX(Monthly!$C$54:$BJ$54,F$3*12) -> 0
A9: Total assets | B9: =INDEX(Monthly!$C$91:$BJ$91,B$3*12) -> 1384887.1 | C9: =INDEX(Monthly!$C$91:$BJ$91,C$3*12) -> 2535928.7 | D9: =INDEX(Monthly!$C$91:$BJ$91,D$3*12) -> 4160923.5 | E9: =INDEX(Monthly!$C$91:$BJ$91,E$3*12) -> 6415640.8 | F9: =INDEX(Monthly!$C$91:$BJ$91,F$3*12) -> 9507372.8
A10: Accounts payable | B10: =INDEX(Monthly!$C$65:$BJ$65,B$3*12) -> 112632.74 | C10: =INDEX(Monthly!$C$65:$BJ$65,C$3*12) -> 145417.95 | D10: =INDEX(Monthly!$C$65:$BJ$65,D$3*12) -> 188043.59 | E10: =INDEX(Monthly!$C$65:$BJ$65,E$3*12) -> 243544.96 | F10: =INDEX(Monthly!$C$65:$BJ$65,F$3*12) -> 315915.37
A11: Loan | B11: =INDEX(Monthly!$C$60:$BJ$60,B$3*12) -> 163333.33 | C11: =INDEX(Monthly!$C$60:$BJ$60,C$3*12) -> 123333.33 | D11: =INDEX(Monthly!$C$60:$BJ$60,D$3*12) -> 83333.333 | E11: =INDEX(Monthly!$C$60:$BJ$60,E$3*12) -> 43333.333 | F11: =INDEX(Monthly!$C$60:$BJ$60,F$3*12) -> 3333.3333
A12: Total liabilities | B12: =INDEX(Monthly!$C$92:$BJ$92,B$3*12) -> 275966.07 | C12: =INDEX(Monthly!$C$92:$BJ$92,C$3*12) -> 268751.29 | D12: =INDEX(Monthly!$C$92:$BJ$92,D$3*12) -> 271376.93 | E12: =INDEX(Monthly!$C$92:$BJ$92,E$3*12) -> 286878.29 | F12: =INDEX(Monthly!$C$92:$BJ$92,F$3*12) -> 319248.7
A13: Paid-in capital | B13: =INDEX(Monthly!$C$89:$BJ$89,B$3*12) -> 300000 | C13: =INDEX(Monthly!$C$89:$BJ$89,C$3*12) -> 300000 | D13: =INDEX(Monthly!$C$89:$BJ$89,D$3*12) -> 300000 | E13: =INDEX(Monthly!$C$89:$BJ$89,E$3*12) -> 300000 | F13: =INDEX(Monthly!$C$89:$BJ$89,F$3*12) -> 300000
A14: Retained earnings | B14: =INDEX(Monthly!$C$90:$BJ$90,B$3*12) -> 808921.04 | C14: =INDEX(Monthly!$C$90:$BJ$90,C$3*12) -> 1967177.4 | D14: =INDEX(Monthly!$C$90:$BJ$90,D$3*12) -> 3589546.5 | E14: =INDEX(Monthly!$C$90:$BJ$90,E$3*12) -> 5828762.5 | F14: =INDEX(Monthly!$C$90:$BJ$90,F$3*12) -> 8888124.1
A15: Total equity | B15: =INDEX(Monthly!$C$93:$BJ$93,B$3*12) -> 1108921 | C15: =INDEX(Monthly!$C$93:$BJ$93,C$3*12) -> 2267177.4 | D15: =INDEX(Monthly!$C$93:$BJ$93,D$3*12) -> 3889546.5 | E15: =INDEX(Monthly!$C$93:$BJ$93,E$3*12) -> 6128762.5 | F15: =INDEX(Monthly!$C$93:$BJ$93,F$3*12) -> 9188124.1
A16: Total liabilities & equity | B16: =INDEX(Monthly!$C$94:$BJ$94,B$3*12) -> 1384887.1 | C16: =INDEX(Monthly!$C$94:$BJ$94,C$3*12) -> 2535928.7 | D16: =INDEX(Monthly!$C$94:$BJ$94,D$3*12) -> 4160923.5 | E16: =INDEX(Monthly!$C$94:$BJ$94,E$3*12) -> 6415640.8 | F16: =INDEX(Monthly!$C$94:$BJ$94,F$3*12) -> 9507372.8
A17: Check: assets − liabilities − equity (must be 0) | B17: =INDEX(Monthly!$C$95:$BJ$95,B$3*12) -> 0 | C17: =INDEX(Monthly!$C$95:$BJ$95,C$3*12) -> 0 | D17: =INDEX(Monthly!$C$95:$BJ$95,D$3*12) -> 0 | E17: =INDEX(Monthly!$C$95:$BJ$95,E$3*12) -> 0 | F17: =INDEX(Monthly!$C$95:$BJ$95,F$3*12) -> 0

Sheet Monthly
A1: Monthly projection | D1: =HYPERLINK("#'Cover'!A1","◂ Contents") -> ◂ Contents
A2: $ unless stated; costs shown as negatives. Every period uses the same formula.
A3: Month | C3: M1 | D3: M2 | E3: M3 | F3: M4 | G3: M5 | H3: M6 | I3: M7 | J3: M8 | K3: M9 | L3: M10 | M3: M11 | N3: M12 | O3: M13 | P3: M14 | Q3: M15 | R3: M16 | S3: M17 | T3: M18 | U3: M19 | V3: M20 | W3: M21 | X3: M22 | Y3: M23 | Z3: M24 | AA3: M25 | AB3: M26 | AC3: M27 | AD3: M28 | AE3: M29 | AF3: M30 | AG3: M31 | AH3: M32 | AI3: M33 | AJ3: M34 | AK3: M35 | AL3: M36 | AM3: M37 | AN3: M38 | AO3: M39 | AP3: M40 | AQ3: M41 | AR3: M42 | AS3: M43 | AT3: M44 | AU3: M45 | AV3: M46 | AW3: M47 | AX3: M48 | AY3: M49 | AZ3: M50 | BA3: M51 | BB3: M52 | BC3: M53 | BD3: M54 | BE3: M55 | BF3: M56 | BG3: M57 | BH3: M58 | BI3: M59 | BJ3: M60
A4: Period # | C4: 1 | D4: 2 | E4: 3 | F4: 4 | G4: 5 | H4: 6 | I4: 7 | J4: 8 | K4: 9 | L4: 10 | M4: 11 | N4: 12 | O4: 13 | P4: 14 | Q4: 15 | R4: 16 | S4: 17 | T4: 18 | U4: 19 | V4: 20 | W4: 21 | X4: 22 | Y4: 23 | Z4: 24 | AA4: 25 | AB4: 26 | AC4: 27 | AD4: 28 | AE4: 29 | AF4: 30 | AG4: 31 | AH4: 32 | AI4: 33 | AJ4: 34 | AK4: 35 | AL4: 36 | AM4: 37 | AN4: 38 | AO4: 39 | AP4: 40 | AQ4: 41 | AR4: 42 | AS4: 43 | AT4: 44 | AU4: 45 | AV4: 46 | AW4: 47 | AX4: 48 | AY4: 49 | AZ4: 50 | BA4: 51 | BB4: 52 | BC4: 53 | BD4: 54 | BE4: 55 | BF4: 56 | BG4: 57 | BH4: 58 | BI4: 59 | BJ4: 60
A5: Year # | C5: =ROUNDUP(C4*1/12,0) -> 1 | D5: =ROUNDUP(D4*1/12,0) -> 1 | E5: =ROUNDUP(E4*1/12,0) -> 1 | F5: =ROUNDUP(F4*1/12,0) -> 1 | G5: =ROUNDUP(G4*1/12,0) -> 1 | H5: =ROUNDUP(H4*1/12,0) -> 1 | I5: =ROUNDUP(I4*1/12,0) -> 1 | J5: =ROUNDUP(J4*1/12,0) -> 1 | ... BJ5: =ROUNDUP(BJ4*1/12,0) -> 5
A7: Billable capacity
A8: Billable employees (FTE) | C8: =Headcount!C8+Headcount!C9 -> 16 | D8: =Headcount!D8+Headcount!D9 -> 16 | E8: =Headcount!E8+Headcount!E9 -> 16 | F8: =Headcount!F8+Headcount!F9 -> 16 | G8: =Headcount!G8+Headcount!G9 -> 16 | H8: =Headcount!H8+Headcount!H9 -> 16 | I8: =Headcount!I8+Headcount!I9 -> 16 | J8: =Headcount!J8+Headcount!J9 -> 16 | ... BJ8: =Headcount!BJ8+Headcount!BJ9 -> 42.5676
A9: Available hours — billable employees | C9: =C8*Inputs!$E$7/12*1 -> 2400 | D9: =D8*Inputs!$E$7/12*1 -> 2400 | E9: =E8*Inputs!$E$7/12*1 -> 2400 | F9: =F8*Inputs!$E$7/12*1 -> 2400 | G9: =G8*Inputs!$E$7/12*1 -> 2400 | H9: =H8*Inputs!$E$7/12*1 -> 2400 | I9: =I8*Inputs!$E$7/12*1 -> 2400 | J9: =J8*Inputs!$E$7/12*1 -> 2400 | ... BJ9: =BJ8*Inputs!$E$7/12*1 -> 6385.14
A10: Billable hours — partners & senior | C10: =Headcount!C8*Inputs!$E$7/12*1*Inputs!$E$8 -> 330 | D10: =Headcount!D8*Inputs!$E$7/12*1*Inputs!$E$8 -> 330 | E10: =Headcount!E8*Inputs!$E$7/12*1*Inputs!$E$8 -> 330 | F10: =Headcount!F8*Inputs!$E$7/12*1*Inputs!$E$8 -> 330 | G10: =Headcount!G8*Inputs!$E$7/12*1*Inputs!$E$8 -> 330 | H10: =Headcount!H8*Inputs!$E$7/12*1*Inputs!$E$8 -> 330 | I10: =Headcount!I8*Inputs!$E$7/12*1*Inputs!$E$8 -> 330 | J10: =Headcount!J8*Inputs!$E$7/12*1*Inputs!$E$8 -> 330 | ... BJ10: =Headcount!BJ8*Inputs!$E$7/12*1*Inputs!$E$8 -> 684.288
A11: Billable hours — consultants | C11: =Headcount!C9*Inputs!$E$7/12*1*Inputs!$E$9 -> 1350 | D11: =Headcount!D9*Inputs!$E$7/12*1*Inputs!$E$9 -> 1350 | E11: =Headcount!E9*Inputs!$E$7/12*1*Inputs!$E$9 -> 1350 | F11: =Headcount!F9*Inputs!$E$7/12*1*Inputs!$E$9 -> 1350 | G11: =Headcount!G9*Inputs!$E$7/12*1*Inputs!$E$9 -> 1350 | H11: =Headcount!H9*Inputs!$E$7/12*1*Inputs!$E$9 -> 1350 | I11: =Headcount!I9*Inputs!$E$7/12*1*Inputs!$E$9 -> 1350 | J11: =Headcount!J9*Inputs!$E$7/12*1*Inputs!$E$9 -> 1350 | ... BJ11: =Headcount!BJ9*Inputs!$E$7/12*1*Inputs!$E$9 -> 3855.735
A12: Billable hours — contractors | C12: =Inputs!$E$10*(1+Inputs!$E$11)^(C$5-1)*1 -> 400 | D12: =Inputs!$E$10*(1+Inputs!$E$11)^(D$5-1)*1 -> 400 | E12: =Inputs!$E$10*(1+Inputs!$E$11)^(E$5-1)*1 -> 400 | F12: =Inputs!$E$10*(1+Inputs!$E$11)^(F$5-1)*1 -> 400 | G12: =Inputs!$E$10*(1+Inputs!$E$11)^(G$5-1)*1 -> 400 | H12: =Inputs!$E$10*(1+Inputs!$E$11)^(H$5-1)*1 -> 400 | I12: =Inputs!$E$10*(1+Inputs!$E$11)^(I$5-1)*1 -> 400 | J12: =Inputs!$E$10*(1+Inputs!$E$11)^(J$5-1)*1 -> 400 | ... BJ12: =Inputs!$E$10*(1+Inputs!$E$11)^(BJ$5-1)*1 -> 829.44
A13: Billable hours — total | C13: =C10+C11+C12 -> 2080 | D13: =D10+D11+D12 -> 2080 | E13: =E10+E11+E12 -> 2080 | F13: =F10+F11+F12 -> 2080 | G13: =G10+G11+G12 -> 2080 | H13: =H10+H11+H12 -> 2080 | I13: =I10+I11+I12 -> 2080 | J13: =J10+J11+J12 -> 2080 | ... BJ13: =BJ10+BJ11+BJ12 -> 5369.463
A15: Fees
A16: Rate — partners & senior | C16: =Inputs!$E$14*(1+Inputs!$E$17)^(C$5-1) -> 350 | D16: =Inputs!$E$14*(1+Inputs!$E$17)^(D$5-1) -> 350 | E16: =Inputs!$E$14*(1+Inputs!$E$17)^(E$5-1) -> 350 | F16: =Inputs!$E$14*(1+Inputs!$E$17)^(F$5-1) -> 350 | G16: =Inputs!$E$14*(1+Inputs!$E$17)^(G$5-1) -> 350 | H16: =Inputs!$E$14*(1+Inputs!$E$17)^(H$5-1) -> 350 | I16: =Inputs!$E$14*(1+Inputs!$E$17)^(I$5-1) -> 350 | J16: =Inputs!$E$14*(1+Inputs!$E$17)^(J$5-1) -> 350 | ... BJ16: =Inputs!$E$14*(1+Inputs!$E$17)^(BJ$5-1) -> 393.92808
A17: Rate — consultants | C17: =Inputs!$E$15*(1+Inputs!$E$17)^(C$5-1) -> 175 | D17: =Inputs!$E$15*(1+Inputs!$E$17)^(D$5-1) -> 175 | E17: =Inputs!$E$15*(1+Inputs!$E$17)^(E$5-1) -> 175 | F17: =Inputs!$E$15*(1+Inputs!$E$17)^(F$5-1) -> 175 | G17: =Inputs!$E$15*(1+Inputs!$E$17)^(G$5-1) -> 175 | H17: =Inputs!$E$15*(1+Inputs!$E$17)^(H$5-1) -> 175 | I17: =Inputs!$E$15*(1+Inputs!$E$17)^(I$5-1) -> 175 | J17: =Inputs!$E$15*(1+Inputs!$E$17)^(J$5-1) -> 175 | ... BJ17: =Inputs!$E$15*(1+Inputs!$E$17)^(BJ$5-1) -> 196.96404
A18: Rate — contractor hours | C18: =Inputs!$E$16*(1+Inputs!$E$17)^(C$5-1) -> 150 | D18: =Inputs!$E$16*(1+Inputs!$E$17)^(D$5-1) -> 150 | E18: =Inputs!$E$16*(1+Inputs!$E$17)^(E$5-1) -> 150 | F18: =Inputs!$E$16*(1+Inputs!$E$17)^(F$5-1) -> 150 | G18: =Inputs!$E$16*(1+Inputs!$E$17)^(G$5-1) -> 150 | H18: =Inputs!$E$16*(1+Inputs!$E$17)^(H$5-1) -> 150 | I18: =Inputs!$E$16*(1+Inputs!$E$17)^(I$5-1) -> 150 | J18: =Inputs!$E$16*(1+Inputs!$E$17)^(J$5-1) -> 150 | ... BJ18: =Inputs!$E$16*(1+Inputs!$E$17)^(BJ$5-1) -> 168.82632
A19: Fees at rate card | C19: =C10*C16+C11*C17+C12*C18 -> 411750 | D19: =D10*D16+D11*D17+D12*D18 -> 411750 | E19: =E10*E16+E11*E17+E12*E18 -> 411750 | F19: =F10*F16+F11*F17+F12*F18 -> 411750 | G19: =G10*G16+G11*G17+G12*G18 -> 411750 | H19: =H10*H16+H11*H17+H12*H18 -> 411750 | I19: =I10*I16+I11*I17+I12*I18 -> 411750 | J19: =J10*J16+J11*J17+J12*J18 -> 411750 | ... BJ19: =BJ10*BJ16+BJ11*BJ17+BJ12*BJ18 -> 1169032.7
A20: Retainer fees | C20: =C19*Inputs!$E$20*(1-Inputs!$E$21) -> 148230 | D20: =D19*Inputs!$E$20*(1-Inputs!$E$21) -> 148230 | E20: =E19*Inputs!$E$20*(1-Inputs!$E$21) -> 148230 | F20: =F19*Inputs!$E$20*(1-Inputs!$E$21) -> 148230 | G20: =G19*Inputs!$E$20*(1-Inputs!$E$21) -> 148230 | H20: =H19*Inputs!$E$20*(1-Inputs!$E$21) -> 148230 | I20: =I19*Inputs!$E$20*(1-Inputs!$E$21) -> 148230 | J20: =J19*Inputs!$E$20*(1-Inputs!$E$21) -> 148230 | ... BJ20: =BJ19*Inputs!$E$20*(1-Inputs!$E$21) -> 420851.78
A21: Project fees | C21: =C19*(1-Inputs!$E$20)*Inputs!$E$22 -> 227286 | D21: =D19*(1-Inputs!$E$20)*Inputs!$E$22 -> 227286 | E21: =E19*(1-Inputs!$E$20)*Inputs!$E$22 -> 227286 | F21: =F19*(1-Inputs!$E$20)*Inputs!$E$22 -> 227286 | G21: =G19*(1-Inputs!$E$20)*Inputs!$E$22 -> 227286 | H21: =H19*(1-Inputs!$E$20)*Inputs!$E$22 -> 227286 | I21: =I19*(1-Inputs!$E$20)*Inputs!$E$22 -> 227286 | J21: =J19*(1-Inputs!$E$20)*Inputs!$E$22 -> 227286 | ... BJ21: =BJ19*(1-Inputs!$E$20)*Inputs!$E$22 -> 645306.06
A22: Fee revenue | C22: =C20+C21 -> 375516 | D22: =D20+D21 -> 375516 | E22: =E20+E21 -> 375516 | F22: =F20+F21 -> 375516 | G22: =G20+G21 -> 375516 | H22: =H20+H21 -> 375516 | I22: =I20+I21 -> 375516 | J22: =J20+J21 -> 375516 | ... BJ22: =BJ20+BJ21 -> 1066157.8
A24: Cost of delivery
A25: Billable staff payroll | C25: =Headcount!C15+Headcount!C16 -> -178000 | D25: =Headcount!D15+Headcount!D16 -> -178000 | E25: =Headcount!E15+Headcount!E16 -> -178000 | F25: =Headcount!F15+Headcount!F16 -> -178000 | G25: =Headcount!G15+Headcount!G16 -> -178000 | H25: =Headcount!H15+Headcount!H16 -> -178000 | I25: =Headcount!I15+Headcount!I16 -> -178000 | J25: =Headcount!J15+Headcount!J16 -> -178000 | ... BJ25: =Headcount!BJ15+Headcount!BJ16 -> -515827.22
A26: Contractor cost | C26: =-C12*Inputs!$E$25*(1+Inputs!$E$51)^(C$5-1) -> -36000 | D26: =-D12*Inputs!$E$25*(1+Inputs!$E$51)^(D$5-1) -> -36000 | E26: =-E12*Inputs!$E$25*(1+Inputs!$E$51)^(E$5-1) -> -36000 | F26: =-F12*Inputs!$E$25*(1+Inputs!$E$51)^(F$5-1) -> -36000 | G26: =-G12*Inputs!$E$25*(1+Inputs!$E$51)^(G$5-1) -> -36000 | H26: =-H12*Inputs!$E$25*(1+Inputs!$E$51)^(H$5-1) -> -36000 | I26: =-I12*Inputs!$E$25*(1+Inputs!$E$51)^(I$5-1) -> -36000 | J26: =-J12*Inputs!$E$25*(1+Inputs!$E$51)^(J$5-1) -> -36000 | ... BJ26: =-BJ12*Inputs!$E$25*(1+Inputs!$E$51)^(BJ$5-1) -> -84018.782
A27: Non-rebillable delivery costs | C27: =-C22*Inputs!$E$26 -> -11265.48 | D27: =-D22*Inputs!$E$26 -> -11265.48 | E27: =-E22*Inputs!$E$26 -> -11265.48 | F27: =-F22*Inputs!$E$26 -> -11265.48 | G27: =-G22*Inputs!$E$26 -> -11265.48 | H27: =-H22*Inputs!$E$26 -> -11265.48 | I27: =-I22*Inputs!$E$26 -> -11265.48 | J27: =-J22*Inputs!$E$26 -> -11265.48 | ... BJ27: =-BJ22*Inputs!$E$26 -> -31984.735
A28: Cost of delivery | C28: =C25+C26+C27 -> -225265.48 | D28: =D25+D26+D27 -> -225265.48 | E28: =E25+E26+E27 -> -225265.48 | F28: =F25+F26+F27 -> -225265.48 | G28: =G25+G26+G27 -> -225265.48 | H28: =H25+H26+H27 -> -225265.48 | I28: =I25+I26+I27 -> -225265.48 | J28: =J25+J26+J27 -> -225265.48 | ... BJ28: =BJ25+BJ26+BJ27 -> -631830.73
A29: Gross profit | C29: =C22+C28 -> 150250.52 | D29: =D22+D28 -> 150250.52 | E29: =E22+E28 -> 150250.52 | F29: =F22+F28 -> 150250.52 | G29: =G22+G28 -> 150250.52 | H29: =H22+H28 -> 150250.52 | I29: =I22+I28 -> 150250.52 | J29: =J22+J28 -> 150250.52 | ... BJ29: =BJ22+BJ28 -> 434327.1
A31: Operating expenses
A32: Non-billable payroll | C32: =Headcount!C19-Headcount!C15-Headcount!C16 -> -36500 | D32: =Headcount!D19-Headcount!D15-Headcount!D16 -> -36500 | E32: =Headcount!E19-Headcount!E15-Headcount!E16 -> -36500 | F32: =Headcount!F19-Headcount!F15-Headcount!F16 -> -36500 | G32: =Headcount!G19-Headcount!G15-Headcount!G16 -> -36500 | H32: =Headcount!H19-Headcount!H15-Headcount!H16 -> -36500 | I32: =Headcount!I19-Headcount!I15-Headcount!I16 -> -36500 | J32: =Headcount!J19-Headcount!J15-Headcount!J16 -> -36500 | ... BJ32: =Headcount!BJ19-Headcount!BJ15-Headcount!BJ16 -> -78061.714
A33: Marketing & business development | C33: =-Inputs!$E$28*1 -> -8000 | D33: =-Inputs!$E$28*1 -> -8000 | E33: =-Inputs!$E$28*1 -> -8000 | F33: =-Inputs!$E$28*1 -> -8000 | G33: =-Inputs!$E$28*1 -> -8000 | H33: =-Inputs!$E$28*1 -> -8000 | I33: =-Inputs!$E$28*1 -> -8000 | J33: =-Inputs!$E$28*1 -> -8000 | ... BJ33: =-Inputs!$E$28*1 -> -8000
A34: Software & tools | C34: =-Headcount!C12*Inputs!$E$27*1 -> -4200 | D34: =-Headcount!D12*Inputs!$E$27*1 -> -4200 | E34: =-Headcount!E12*Inputs!$E$27*1 -> -4200 | F34: =-Headcount!F12*Inputs!$E$27*1 -> -4200 | G34: =-Headcount!G12*Inputs!$E$27*1 -> -4200 | H34: =-Headcount!H12*Inputs!$E$27*1 -> -4200 | I34: =-Headcount!I12*Inputs!$E$27*1 -> -4200 | J34: =-Headcount!J12*Inputs!$E$27*1 -> -4200 | ... BJ34: =-Headcount!BJ12*Inputs!$E$27*1 -> -10392.364
A35: Office & rent | C35: =-Inputs!$E$29*1 -> -8000 | D35: =-Inputs!$E$29*1 -> -8000 | E35: =-Inputs!$E$29*1 -> -8000 | F35: =-Inputs!$E$29*1 -> -8000 | G35: =-Inputs!$E$29*1 -> -8000 | H35: =-Inputs!$E$29*1 -> -8000 | I35: =-Inputs!$E$29*1 -> -8000 | J35: =-Inputs!$E$29*1 -> -8000 | ... BJ35: =-Inputs!$E$29*1 -> -8000
A36: Other G&A | C36: =-Inputs!$E$30*1 -> -6000 | D36: =-Inputs!$E$30*1 -> -6000 | E36: =-Inputs!$E$30*1 -> -6000 | F36: =-Inputs!$E$30*1 -> -6000 | G36: =-Inputs!$E$30*1 -> -6000 | H36: =-Inputs!$E$30*1 -> -6000 | I36: =-Inputs!$E$30*1 -> -6000 | J36: =-Inputs!$E$30*1 -> -6000 | ... BJ36: =-Inputs!$E$30*1 -> -6000
A37: Total operating expenses | C37: =C32+C33+C34+C35+C36 -> -62700 | D37: =D32+D33+D34+D35+D36 -> -62700 | E37: =E32+E33+E34+E35+E36 -> -62700 | F37: =F32+F33+F34+F35+F36 -> -62700 | G37: =G32+G33+G34+G35+G36 -> -62700 | H37: =H32+H33+H34+H35+H36 -> -62700 | I37: =I32+I33+I34+I35+I36 -> -62700 | J37: =J32+J33+J34+J35+J36 -> -62700 | ... BJ37: =BJ32+BJ33+BJ34+BJ35+BJ36 -> -110454.08
A38: EBITDA | C38: =C29+C37 -> 87550.52 | D38: =D29+D37 -> 87550.52 | E38: =E29+E37 -> 87550.52 | F38: =F29+F37 -> 87550.52 | G38: =G29+G37 -> 87550.52 | H38: =H29+H37 -> 87550.52 | I38: =I29+I37 -> 87550.52 | J38: =J29+J37 -> 87550.52 | ... BJ38: =BJ29+BJ37 -> 323873.02
A40: Profit after depreciation, interest, tax
A41: EBIT | C41: =C38+C52 -> 86550.52 | D41: =D38+D52 -> 86550.52 | E41: =E38+E52 -> 86550.52 | F41: =F38+F52 -> 86550.52 | G41: =G38+G52 -> 86550.52 | H41: =H38+H52 -> 86550.52 | I41: =I38+I52 -> 86550.52 | J41: =J38+J52 -> 86550.52 | ... BJ41: =BJ38+BJ52 -> 322873.02
A42: Interest on loan (average balance after drawdown) | C42: =-(C57+C58+C60)/2*Inputs!$E$56/12 -> -1333.3333 | D42: =-(D57+D58+D60)/2*Inputs!$E$56/12 -> -1322.2222 | E42: =-(E57+E58+E60)/2*Inputs!$E$56/12 -> -1300 | F42: =-(F57+F58+F60)/2*Inputs!$E$56/12 -> -1277.7778 | G42: =-(G57+G58+G60)/2*Inputs!$E$56/12 -> -1255.5556 | H42: =-(H57+H58+H60)/2*Inputs!$E$56/12 -> -1233.3333 | I42: =-(I57+I58+I60)/2*Inputs!$E$56/12 -> -1211.1111 | J42: =-(J57+J58+J60)/2*Inputs!$E$56/12 -> -1188.8889 | ... BJ42: =-(BJ57+BJ58+BJ60)/2*Inputs!$E$56/12 -> -33.333333
A43: Pre-tax income | C43: =C41+C42 -> 85217.187 | D43: =D41+D42 -> 85228.298 | E43: =E41+E42 -> 85250.52 | F43: =F41+F42 -> 85272.742 | G43: =G41+G42 -> 85294.964 | H43: =H41+H42 -> 85317.187 | I43: =I41+I42 -> 85339.409 | J43: =J41+J42 -> 85361.631 | ... BJ43: =BJ41+BJ42 -> 322839.69
A44: Helper: cumulative pre-tax income | C44: =C43 -> 85217.187 | D44: =C44+D43 -> 170445.48 | E44: =D44+E43 -> 255696 | F44: =E44+F43 -> 340968.75 | G44: =F44+G43 -> 426263.71 | H44: =G44+H43 -> 511580.9 | I44: =H44+I43 -> 596920.31 | J44: =I44+J43 -> 682281.94 | K44: =J44+K43 -> 767665.79 | ... BJ44: =BI44+BJ43 -> 11250790
A45: Helper: cumulative taxable income (losses carried forward) | C45: =MAX(0,C44) -> 85217.187 | D45: =MAX(C45,D44) -> 170445.48 | E45: =MAX(D45,E44) -> 255696 | F45: =MAX(E45,F44) -> 340968.75 | G45: =MAX(F45,G44) -> 426263.71 | H45: =MAX(G45,H44) -> 511580.9 | I45: =MAX(H45,I44) -> 596920.31 | J45: =MAX(I45,J44) -> 682281.94 | K45: =MAX(J45,K44) -> 767665.79 | ... BJ45: =MAX(BI45,BJ44) -> 11250790
A46: Income tax | C46: =-C45*Inputs!$E$66 -> -17895.609 | D46: =-(D45-C45)*Inputs!$E$66 -> -17897.943 | E46: =-(E45-D45)*Inputs!$E$66 -> -17902.609 | F46: =-(F45-E45)*Inputs!$E$66 -> -17907.276 | G46: =-(G45-F45)*Inputs!$E$66 -> -17911.943 | H46: =-(H45-G45)*Inputs!$E$66 -> -17916.609 | I46: =-(I45-H45)*Inputs!$E$66 -> -17921.276 | J46: =-(J45-I45)*Inputs!$E$66 -> -17925.943 | K46: =-(K45-J45)*Inputs!$E$66 -> -17930.609 | ... BJ46: =-(BJ45-BI45)*Inputs!$E$66 -> -67796.335
A47: Net income | C47: =C43+C46 -> 67321.577 | D47: =D43+D46 -> 67330.355 | E47: =E43+E46 -> 67347.911 | F47: =F43+F46 -> 67365.466 | G47: =G43+G46 -> 67383.022 | H47: =H43+H46 -> 67400.577 | I47: =I43+I46 -> 67418.133 | J47: =J43+J46 -> 67435.689 | ... BJ47: =BJ43+BJ46 -> 255043.36
A49: Fixed assets & capital spending
A50: Capital spending | C50: =IF(C$4=1,Inputs!$E$31,0) -> 60000 | D50: =IF(D$4=1,Inputs!$E$31,0) -> 0 | E50: =IF(E$4=1,Inputs!$E$31,0) -> 0 | F50: =IF(F$4=1,Inputs!$E$31,0) -> 0 | G50: =IF(G$4=1,Inputs!$E$31,0) -> 0 | H50: =IF(H$4=1,Inputs!$E$31,0) -> 0 | I50: =IF(I$4=1,Inputs!$E$31,0) -> 0 | J50: =IF(J$4=1,Inputs!$E$31,0) -> 0 | ... BJ50: =IF(BJ$4=1,Inputs!$E$31,0) -> 0
A51: Fixed assets at cost | C51: =C50 -> 60000 | D51: =C51+D50 -> 60000 | E51: =D51+E50 -> 60000 | F51: =E51+F50 -> 60000 | G51: =F51+G50 -> 60000 | H51: =G51+H50 -> 60000 | I51: =H51+I50 -> 60000 | J51: =I51+J50 -> 60000 | K51: =J51+K50 -> 60000 | ... BJ51: =BI51+BJ50 -> 60000
A52: Depreciation | C52: =-MIN(C51/MAX(1,Inputs!$E$65*12),C50) -> -1000 | D52: =-MIN(D51/MAX(1,Inputs!$E$65*12),C54+D50) -> -1000 | E52: =-MIN(E51/MAX(1,Inputs!$E$65*12),D54+E50) -> -1000 | F52: =-MIN(F51/MAX(1,Inputs!$E$65*12),E54+F50) -> -1000 | G52: =-MIN(G51/MAX(1,Inputs!$E$65*12),F54+G50) -> -1000 | H52: =-MIN(H51/MAX(1,Inputs!$E$65*12),G54+H50) -> -1000 | I52: =-MIN(I51/MAX(1,Inputs!$E$65*12),H54+I50) -> -1000 | J52: =-MIN(J51/MAX(1,Inputs!$E$65*12),I54+J50) -> -1000 | K52: =-MIN(K51/MAX(1,Inputs!$E$65*12),J54+K50) -> -1000 | ... BJ52: =-MIN(BJ51/MAX(1,Inputs!$E$65*12),BI54+BJ50) -> -1000
A53: Accumulated depreciation | C53: =C52 -> -1000 | D53: =C53+D52 -> -2000 | E53: =D53+E52 -> -3000 | F53: =E53+F52 -> -4000 | G53: =F53+G52 -> -5000 | H53: =G53+H52 -> -6000 | I53: =H53+I52 -> -7000 | J53: =I53+J52 -> -8000 | K53: =J53+K52 -> -9000 | ... BJ53: =BI53+BJ52 -> -60000
A54: Net fixed assets | C54: =C51+C53 -> 59000 | D54: =D51+D53 -> 58000 | E54: =E51+E53 -> 57000 | F54: =F51+F53 -> 56000 | G54: =G51+G53 -> 55000 | H54: =H51+H53 -> 54000 | I54: =I51+I53 -> 53000 | J54: =J51+J53 -> 52000 | ... BJ54: =BJ51+BJ53 -> 0
A56: Debt
A57: Loan — opening balance | C57: =0 -> 0 | D57: =C60 -> 200000 | E57: =D60 -> 196666.67 | F57: =E60 -> 193333.33 | G57: =F60 -> 190000 | H57: =G60 -> 186666.67 | I57: =H60 -> 183333.33 | J57: =I60 -> 180000 | K57: =J60 -> 176666.67 | ... BJ57: =BI60 -> 6666.6667
A58: Loan drawdown | C58: =IF(C$4=1,Inputs!$E$55,0) -> 200000 | D58: =IF(D$4=1,Inputs!$E$55,0) -> 0 | E58: =IF(E$4=1,Inputs!$E$55,0) -> 0 | F58: =IF(F$4=1,Inputs!$E$55,0) -> 0 | G58: =IF(G$4=1,Inputs!$E$55,0) -> 0 | H58: =IF(H$4=1,Inputs!$E$55,0) -> 0 | I58: =IF(I$4=1,Inputs!$E$55,0) -> 0 | J58: =IF(J$4=1,Inputs!$E$55,0) -> 0 | ... BJ58: =IF(BJ$4=1,Inputs!$E$55,0) -> 0
A59: Loan repayment | C59: =-MIN(C57,Inputs!$E$55/MAX(1,Inputs!$E$57*12)) -> 0 | D59: =-MIN(D57,Inputs!$E$55/MAX(1,Inputs!$E$57*12)) -> -3333.3333 | E59: =-MIN(E57,Inputs!$E$55/MAX(1,Inputs!$E$57*12)) -> -3333.3333 | F59: =-MIN(F57,Inputs!$E$55/MAX(1,Inputs!$E$57*12)) -> -3333.3333 | G59: =-MIN(G57,Inputs!$E$55/MAX(1,Inputs!$E$57*12)) -> -3333.3333 | H59: =-MIN(H57,Inputs!$E$55/MAX(1,Inputs!$E$57*12)) -> -3333.3333 | I59: =-MIN(I57,Inputs!$E$55/MAX(1,Inputs!$E$57*12)) -> -3333.3333 | J59: =-MIN(J57,Inputs!$E$55/MAX(1,Inputs!$E$57*12)) -> -3333.3333 | ... BJ59: =-MIN(BJ57,Inputs!$E$55/MAX(1,Inputs!$E$57*12)) -> -3333.3333
A60: Loan — closing balance | C60: =C57+C58+C59 -> 200000 | D60: =D57+D58+D59 -> 196666.67 | E60: =E57+E58+E59 -> 193333.33 | F60: =F57+F58+F59 -> 190000 | G60: =G57+G58+G59 -> 186666.67 | H60: =H57+H58+H59 -> 183333.33 | I60: =I57+I58+I59 -> 180000 | J60: =J57+J58+J59 -> 176666.67 | ... BJ60: =BJ57+BJ58+BJ59 -> 3333.3333
A62: Working capital
A63: Accounts receivable | C63: =C22*Inputs!$E$60/30 -> 563274 | D63: =D22*Inputs!$E$60/30 -> 563274 | E63: =E22*Inputs!$E$60/30 -> 563274 | F63: =F22*Inputs!$E$60/30 -> 563274 | G63: =G22*Inputs!$E$60/30 -> 563274 | H63: =H22*Inputs!$E$60/30 -> 563274 | I63: =I22*Inputs!$E$60/30 -> 563274 | J63: =J22*Inputs!$E$60/30 -> 563274 | ... BJ63: =BJ22*Inputs!$E$60/30 -> 1599236.8
A64: Inventory | C64: =-C28*Inputs!$E$61/30 -> 0 | D64: =-D28*Inputs!$E$61/30 -> 0 | E64: =-E28*Inputs!$E$61/30 -> 0 | F64: =-F28*Inputs!$E$61/30 -> 0 | G64: =-G28*Inputs!$E$61/30 -> 0 | H64: =-H28*Inputs!$E$61/30 -> 0 | I64: =-I28*Inputs!$E$61/30 -> 0 | J64: =-J28*Inputs!$E$61/30 -> 0 | ... BJ64: =-BJ28*Inputs!$E$61/30 -> 0
A65: Accounts payable | C65: =-C28*Inputs!$E$62/30 -> 112632.74 | D65: =-D28*Inputs!$E$62/30 -> 112632.74 | E65: =-E28*Inputs!$E$62/30 -> 112632.74 | F65: =-F28*Inputs!$E$62/30 -> 112632.74 | G65: =-G28*Inputs!$E$62/30 -> 112632.74 | H65: =-H28*Inputs!$E$62/30 -> 112632.74 | I65: =-I28*Inputs!$E$62/30 -> 112632.74 | J65: =-J28*Inputs!$E$62/30 -> 112632.74 | ... BJ65: =-BJ28*Inputs!$E$62/30 -> 315915.37
A66: (Increase) / decrease in receivables | C66: =-C63 -> -563274 | D66: =C63-D63 -> 0 | E66: =D63-E63 -> 0 | F66: =E63-F63 -> 0 | G66: =F63-G63 -> 0 | H66: =G63-H63 -> 0 | I66: =H63-I63 -> 0 | J66: =I63-J63 -> 0 | K66: =J63-K63 -> 0 | ... BJ66: =BI63-BJ63 -> 0
A67: (Increase) / decrease in inventory | C67: =-C64 -> 0 | D67: =C64-D64 -> 0 | E67: =D64-E64 -> 0 | F67: =E64-F64 -> 0 | G67: =F64-G64 -> 0 | H67: =G64-H64 -> 0 | I67: =H64-I64 -> 0 | J67: =I64-J64 -> 0 | K67: =J64-K64 -> 0 | ... BJ67: =BI64-BJ64 -> 0
A68: Increase / (decrease) in payables | C68: =C65 -> 112632.74 | D68: =D65-C65 -> 0 | E68: =E65-D65 -> 0 | F68: =F65-E65 -> 0 | G68: =G65-F65 -> 0 | H68: =H65-G65 -> 0 | I68: =I65-H65 -> 0 | J68: =J65-I65 -> 0 | K68: =K65-J65 -> 0 | ... BJ68: =BJ65-BI65 -> 0
A70: Cash flow
A71: Operating cash flow | C71: =C47-C52+C66+C67+C68 -> -382319.68 | D71: =D47-D52+D66+D67+D68 -> 68330.355 | E71: =E47-E52+E66+E67+E68 -> 68347.911 | F71: =F47-F52+F66+F67+F68 -> 68365.466 | G71: =G47-G52+G66+G67+G68 -> 68383.022 | H71: =H47-H52+H66+H67+H68 -> 68400.577 | I71: =I47-I52+I66+I67+I68 -> 68418.133 | J71: =J47-J52+J66+J67+J68 -> 68435.689 | ... BJ71: =BJ47-BJ52+BJ66+BJ67+BJ68 -> 256043.36
A72: Investing cash flow (capex) | C72: =-C50 -> -60000 | D72: =-D50 -> 0 | E72: =-E50 -> 0 | F72: =-F50 -> 0 | G72: =-G50 -> 0 | H72: =-H50 -> 0 | I72: =-I50 -> 0 | J72: =-J50 -> 0 | ... BJ72: =-BJ50 -> 0
A73: Equity raised | C73: =IF(C$4=1,Inputs!$E$54,0) -> 300000 | D73: =IF(D$4=1,Inputs!$E$54,0) -> 0 | E73: =IF(E$4=1,Inputs!$E$54,0) -> 0 | F73: =IF(F$4=1,Inputs!$E$54,0) -> 0 | G73: =IF(G$4=1,Inputs!$E$54,0) -> 0 | H73: =IF(H$4=1,Inputs!$E$54,0) -> 0 | I73: =IF(I$4=1,Inputs!$E$54,0) -> 0 | J73: =IF(J$4=1,Inputs!$E$54,0) -> 0 | ... BJ73: =IF(BJ$4=1,Inputs!$E$54,0) -> 0
A74: Financing cash flow | C74: =C73+C58+C59 -> 500000 | D74: =D73+D58+D59 -> -3333.3333 | E74: =E73+E58+E59 -> -3333.3333 | F74: =F73+F58+F59 -> -3333.3333 | G74: =G73+G58+G59 -> -3333.3333 | H74: =H73+H58+H59 -> -3333.3333 | I74: =I73+I58+I59 -> -3333.3333 | J74: =J73+J58+J59 -> -3333.3333 | ... BJ74: =BJ73+BJ58+BJ59 -> -3333.3333
A75: Net cash flow | C75: =C71+C72+C74 -> 57680.317 | D75: =D71+D72+D74 -> 64997.022 | E75: =E71+E72+E74 -> 65014.577 | F75: =F71+F72+F74 -> 65032.133 | G75: =G71+G72+G74 -> 65049.689 | H75: =H71+H72+H74 -> 65067.244 | I75: =I71+I72+I74 -> 65084.8 | J75: =J71+J72+J74 -> 65102.355 | ... BJ75: =BJ71+BJ72+BJ74 -> 252710.02
A76: Opening cash | C76: =0 -> 0 | D76: =C77 -> 57680.317 | E76: =D77 -> 122677.34 | F76: =E77 -> 187691.92 | G76: =F77 -> 252724.05 | H76: =G77 -> 317773.74 | I76: =H77 -> 382840.98 | J76: =I77 -> 447925.78 | K76: =J77 -> 513028.14 | ... BJ76: =BI77 -> 7655426
A77: Closing cash | C77: =C76+C75 -> 57680.317 | D77: =D76+D75 -> 122677.34 | E77: =E76+E75 -> 187691.92 | F77: =F76+F75 -> 252724.05 | G77: =G76+G75 -> 317773.74 | H77: =H76+H75 -> 382840.98 | I77: =I76+I75 -> 447925.78 | J77: =J76+J75 -> 513028.14 | ... BJ77: =BJ76+BJ75 -> 7908136
A78: Helper: EBITDA positive (1/0) | C78: =IF(C38>0,1,0) -> 1 | D78: =IF(D38>0,1,0) -> 1 | E78: =IF(E38>0,1,0) -> 1 | F78: =IF(F38>0,1,0) -> 1 | G78: =IF(G38>0,1,0) -> 1 | H78: =IF(H38>0,1,0) -> 1 | I78: =IF(I38>0,1,0) -> 1 | J78: =IF(J38>0,1,0) -> 1 | ... BJ78: =IF(BJ38>0,1,0) -> 1
A80: Goal modules
A81: Helper: net income positive (1/0) | C81: =IF(C47>0,1,0) -> 1 | D81: =IF(D47>0,1,0) -> 1 | E81: =IF(E47>0,1,0) -> 1 | F81: =IF(F47>0,1,0) -> 1 | G81: =IF(G47>0,1,0) -> 1 | H81: =IF(H47>0,1,0) -> 1 | I81: =IF(I47>0,1,0) -> 1 | J81: =IF(J47>0,1,0) -> 1 | ... BJ81: =IF(BJ47>0,1,0) -> 1
A82: Cash flow before financing (operating + investing) | C82: =C71+C72 -> -442319.68 | D82: =D71+D72 -> 68330.355 | E82: =E71+E72 -> 68347.911 | F82: =F71+F72 -> 68365.466 | G82: =G71+G72 -> 68383.022 | H82: =H71+H72 -> 68400.577 | I82: =I71+I72 -> 68418.133 | J82: =J71+J72 -> 68435.689 | ... BJ82: =BJ71+BJ72 -> 256043.36
A83: Cumulative cash flow before financing | C83: =C82 -> -442319.68 | D83: =C83+D82 -> -373989.33 | E83: =D83+E82 -> -305641.42 | F83: =E83+F82 -> -237275.95 | G83: =F83+G82 -> -168892.93 | H83: =G83+H82 -> -100492.35 | I83: =H83+I82 -> -32074.218 | J83: =I83+J82 -> 36361.471 | K83: =J83+K82 -> 104814.71 | ... BJ83: =BI83+BJ82 -> 7604802.7
A84: Helper: lowest cumulative cash flow so far | C84: =C83 -> -442319.68 | D84: =MIN(C84,D83) -> -442319.68 | E84: =MIN(D84,E83) -> -442319.68 | F84: =MIN(E84,F83) -> -442319.68 | G84: =MIN(F84,G83) -> -442319.68 | H84: =MIN(G84,H83) -> -442319.68 | I84: =MIN(H84,I83) -> -442319.68 | J84: =MIN(I84,J83) -> -442319.68 | K84: =MIN(J84,K83) -> -442319.68 | ... BJ84: =MIN(BI84,BJ83) -> -442319.68
A85: Helper: investment paid back (1/0) | C85: =IF(AND(C83>=0,C84<0),1,0) -> 0 | D85: =IF(AND(D83>=0,D84<0),1,0) -> 0 | E85: =IF(AND(E83>=0,E84<0),1,0) -> 0 | F85: =IF(AND(F83>=0,F84<0),1,0) -> 0 | G85: =IF(AND(G83>=0,G84<0),1,0) -> 0 | H85: =IF(AND(H83>=0,H84<0),1,0) -> 0 | I85: =IF(AND(I83>=0,I84<0),1,0) -> 0 | J85: =IF(AND(J83>=0,J84<0),1,0) -> 1 | ... BJ85: =IF(AND(BJ83>=0,BJ84<0),1,0) -> 1
A86: Unlevered free cash flow (operating + after-tax interest − capex) | C86: =C71-C42*(1-Inputs!$E$66)+C72 -> -441266.35 | D86: =D71-D42*(1-Inputs!$E$66)+D72 -> 69374.911 | E86: =E71-E42*(1-Inputs!$E$66)+E72 -> 69374.911 | F86: =F71-F42*(1-Inputs!$E$66)+F72 -> 69374.911 | G86: =G71-G42*(1-Inputs!$E$66)+G72 -> 69374.911 | H86: =H71-H42*(1-Inputs!$E$66)+H72 -> 69374.911 | I86: =I71-I42*(1-Inputs!$E$66)+I72 -> 69374.911 | J86: =J71-J42*(1-Inputs!$E$66)+J72 -> 69374.911 | ... BJ86: =BJ71-BJ42*(1-Inputs!$E$66)+BJ72 -> 256069.69
A88: Balance sheet
A89: Paid-in capital | C89: =C73 -> 300000 | D89: =C89+D73 -> 300000 | E89: =D89+E73 -> 300000 | F89: =E89+F73 -> 300000 | G89: =F89+G73 -> 300000 | H89: =G89+H73 -> 300000 | I89: =H89+I73 -> 300000 | J89: =I89+J73 -> 300000 | K89: =J89+K73 -> 300000 | ... BJ89: =BI89+BJ73 -> 300000
A90: Retained earnings | C90: =C47 -> 67321.577 | D90: =C90+D47 -> 134651.93 | E90: =D90+E47 -> 201999.84 | F90: =E90+F47 -> 269365.31 | G90: =F90+G47 -> 336748.33 | H90: =G90+H47 -> 404148.91 | I90: =H90+I47 -> 471567.04 | J90: =I90+J47 -> 539002.73 | K90: =J90+K47 -> 606455.97 | ... BJ90: =BI90+BJ47 -> 8888124.1
A91: Total assets | C91: =C77+C63+C64+C54 -> 679954.32 | D91: =D77+D63+D64+D54 -> 743951.34 | E91: =E77+E63+E64+E54 -> 807965.92 | F91: =F77+F63+F64+F54 -> 871998.05 | G91: =G77+G63+G64+G54 -> 936047.74 | H91: =H77+H63+H64+H54 -> 1000115 | I91: =I77+I63+I64+I54 -> 1064199.8 | J91: =J77+J63+J64+J54 -> 1128302.1 | ... BJ91: =BJ77+BJ63+BJ64+BJ54 -> 9507372.8
A92: Total liabilities | C92: =C65+C60 -> 312632.74 | D92: =D65+D60 -> 309299.41 | E92: =E65+E60 -> 305966.07 | F92: =F65+F60 -> 302632.74 | G92: =G65+G60 -> 299299.41 | H92: =H65+H60 -> 295966.07 | I92: =I65+I60 -> 292632.74 | J92: =J65+J60 -> 289299.41 | ... BJ92: =BJ65+BJ60 -> 319248.7
A93: Total equity | C93: =C89+C90 -> 367321.58 | D93: =D89+D90 -> 434651.93 | E93: =E89+E90 -> 501999.84 | F93: =F89+F90 -> 569365.31 | G93: =G89+G90 -> 636748.33 | H93: =H89+H90 -> 704148.91 | I93: =I89+I90 -> 771567.04 | J93: =J89+J90 -> 839002.73 | ... BJ93: =BJ89+BJ90 -> 9188124.1
A94: Total liabilities & equity | C94: =C92+C93 -> 679954.32 | D94: =D92+D93 -> 743951.34 | E94: =E92+E93 -> 807965.92 | F94: =F92+F93 -> 871998.05 | G94: =G92+G93 -> 936047.74 | H94: =H92+H93 -> 1000115 | I94: =I92+I93 -> 1064199.8 | J94: =J92+J93 -> 1128302.1 | ... BJ94: =BJ92+BJ93 -> 9507372.8
A95: Check: assets − liabilities − equity | C95: =C91-C94 -> 0 | D95: =D91-D94 -> 0 | E95: =E91-E94 -> 0 | F95: =F91-F94 -> 0 | G95: =G91-G94 -> 0 | H95: =H91-H94 -> 0 | I95: =I91-I94 -> 0 | J95: =J91-J94 -> 0 | ... BJ95: =BJ91-BJ94 -> 0

Sheet Headcount
A1: Headcount & payroll | D1: =HYPERLINK("#'Cover'!A1","◂ Contents") -> ◂ Contents
A2: $ unless stated; costs shown as negatives. Every period uses the same formula.
A3: Month | C3: M1 | D3: M2 | E3: M3 | F3: M4 | G3: M5 | H3: M6 | I3: M7 | J3: M8 | K3: M9 | L3: M10 | M3: M11 | N3: M12 | O3: M13 | P3: M14 | Q3: M15 | R3: M16 | S3: M17 | T3: M18 | U3: M19 | V3: M20 | W3: M21 | X3: M22 | Y3: M23 | Z3: M24 | AA3: M25 | AB3: M26 | AC3: M27 | AD3: M28 | AE3: M29 | AF3: M30 | AG3: M31 | AH3: M32 | AI3: M33 | AJ3: M34 | AK3: M35 | AL3: M36 | AM3: M37 | AN3: M38 | AO3: M39 | AP3: M40 | AQ3: M41 | AR3: M42 | AS3: M43 | AT3: M44 | AU3: M45 | AV3: M46 | AW3: M47 | AX3: M48 | AY3: M49 | AZ3: M50 | BA3: M51 | BB3: M52 | BC3: M53 | BD3: M54 | BE3: M55 | BF3: M56 | BG3: M57 | BH3: M58 | BI3: M59 | BJ3: M60
A4: Period # | C4: 1 | D4: 2 | E4: 3 | F4: 4 | G4: 5 | H4: 6 | I4: 7 | J4: 8 | K4: 9 | L4: 10 | M4: 11 | N4: 12 | O4: 13 | P4: 14 | Q4: 15 | R4: 16 | S4: 17 | T4: 18 | U4: 19 | V4: 20 | W4: 21 | X4: 22 | Y4: 23 | Z4: 24 | AA4: 25 | AB4: 26 | AC4: 27 | AD4: 28 | AE4: 29 | AF4: 30 | AG4: 31 | AH4: 32 | AI4: 33 | AJ4: 34 | AK4: 35 | AL4: 36 | AM4: 37 | AN4: 38 | AO4: 39 | AP4: 40 | AQ4: 41 | AR4: 42 | AS4: 43 | AT4: 44 | AU4: 45 | AV4: 46 | AW4: 47 | AX4: 48 | AY4: 49 | AZ4: 50 | BA4: 51 | BB4: 52 | BC4: 53 | BD4: 54 | BE4: 55 | BF4: 56 | BG4: 57 | BH4: 58 | BI4: 59 | BJ4: 60
A5: Year # | C5: =ROUNDUP(C4*1/12,0) -> 1 | D5: =ROUNDUP(D4*1/12,0) -> 1 | E5: =ROUNDUP(E4*1/12,0) -> 1 | F5: =ROUNDUP(F4*1/12,0) -> 1 | G5: =ROUNDUP(G4*1/12,0) -> 1 | H5: =ROUNDUP(H4*1/12,0) -> 1 | I5: =ROUNDUP(I4*1/12,0) -> 1 | J5: =ROUNDUP(J4*1/12,0) -> 1 | ... BJ5: =ROUNDUP(BJ4*1/12,0) -> 5
A7: Headcount (FTE)
A8: Partners & senior consultants — FTE | C8: =Inputs!$E$34*(1+Inputs!$E$36)^(C$5-1)*MAX(0,MIN(1,C$4*1-Inputs!$E$37+1))/1 -> 4 | D8: =Inputs!$E$34*(1+Inputs!$E$36)^(D$5-1)*MAX(0,MIN(1,D$4*1-Inputs!$E$37+1))/1 -> 4 | E8: =Inputs!$E$34*(1+Inputs!$E$36)^(E$5-1)*MAX(0,MIN(1,E$4*1-Inputs!$E$37+1))/1 -> 4 | F8: =Inputs!$E$34*(1+Inputs!$E$36)^(F$5-1)*MAX(0,MIN(1,F$4*1-Inputs!$E$37+1))/1 -> 4 | G8: =Inputs!$E$34*(1+Inputs!$E$36)^(G$5-1)*MAX(0,MIN(1,G$4*1-Inputs!$E$37+1))/1 -> 4 | H8: =Inputs!$E$34*(1+Inputs!$E$36)^(H$5-1)*MAX(0,MIN(1,H$4*1-Inputs!$E$37+1))/1 -> 4 | I8: =Inputs!$E$34*(1+Inputs!$E$36)^(I$5-1)*MAX(0,MIN(1,I$4*1-Inputs!$E$37+1))/1 -> 4 | J8: =Inputs!$E$34*(1+Inputs!$E$36)^(J$5-1)*MAX(0,MIN(1,J$4*1-Inputs!$E$37+1))/1 -> 4 | ... BJ8: =Inputs!$E$34*(1+Inputs!$E$36)^(BJ$5-1)*MAX(0,MIN(1,BJ$4*1-Inputs!$E$37+1))/1 -> 8.2944
A9: Consultants — FTE | C9: =Inputs!$E$38*(1+Inputs!$E$40)^(C$5-1)*MAX(0,MIN(1,C$4*1-Inputs!$E$41+1))/1 -> 12 | D9: =Inputs!$E$38*(1+Inputs!$E$40)^(D$5-1)*MAX(0,MIN(1,D$4*1-Inputs!$E$41+1))/1 -> 12 | E9: =Inputs!$E$38*(1+Inputs!$E$40)^(E$5-1)*MAX(0,MIN(1,E$4*1-Inputs!$E$41+1))/1 -> 12 | F9: =Inputs!$E$38*(1+Inputs!$E$40)^(F$5-1)*MAX(0,MIN(1,F$4*1-Inputs!$E$41+1))/1 -> 12 | G9: =Inputs!$E$38*(1+Inputs!$E$40)^(G$5-1)*MAX(0,MIN(1,G$4*1-Inputs!$E$41+1))/1 -> 12 | H9: =Inputs!$E$38*(1+Inputs!$E$40)^(H$5-1)*MAX(0,MIN(1,H$4*1-Inputs!$E$41+1))/1 -> 12 | I9: =Inputs!$E$38*(1+Inputs!$E$40)^(I$5-1)*MAX(0,MIN(1,I$4*1-Inputs!$E$41+1))/1 -> 12 | J9: =Inputs!$E$38*(1+Inputs!$E$40)^(J$5-1)*MAX(0,MIN(1,J$4*1-Inputs!$E$41+1))/1 -> 12 | ... BJ9: =Inputs!$E$38*(1+Inputs!$E$40)^(BJ$5-1)*MAX(0,MIN(1,BJ$4*1-Inputs!$E$41+1))/1 -> 34.2732
A10: Business development — FTE | C10: =Inputs!$E$42*(1+Inputs!$E$44)^(C$5-1)*MAX(0,MIN(1,C$4*1-Inputs!$E$45+1))/1 -> 2 | D10: =Inputs!$E$42*(1+Inputs!$E$44)^(D$5-1)*MAX(0,MIN(1,D$4*1-Inputs!$E$45+1))/1 -> 2 | E10: =Inputs!$E$42*(1+Inputs!$E$44)^(E$5-1)*MAX(0,MIN(1,E$4*1-Inputs!$E$45+1))/1 -> 2 | F10: =Inputs!$E$42*(1+Inputs!$E$44)^(F$5-1)*MAX(0,MIN(1,F$4*1-Inputs!$E$45+1))/1 -> 2 | G10: =Inputs!$E$42*(1+Inputs!$E$44)^(G$5-1)*MAX(0,MIN(1,G$4*1-Inputs!$E$45+1))/1 -> 2 | H10: =Inputs!$E$42*(1+Inputs!$E$44)^(H$5-1)*MAX(0,MIN(1,H$4*1-Inputs!$E$45+1))/1 -> 2 | I10: =Inputs!$E$42*(1+Inputs!$E$44)^(I$5-1)*MAX(0,MIN(1,I$4*1-Inputs!$E$45+1))/1 -> 2 | J10: =Inputs!$E$42*(1+Inputs!$E$44)^(J$5-1)*MAX(0,MIN(1,J$4*1-Inputs!$E$45+1))/1 -> 2 | ... BJ10: =Inputs!$E$42*(1+Inputs!$E$44)^(BJ$5-1)*MAX(0,MIN(1,BJ$4*1-Inputs!$E$45+1))/1 -> 4.1472
A11: Operations & admin — FTE | C11: =Inputs!$E$46*(1+Inputs!$E$48)^(C$5-1)*MAX(0,MIN(1,C$4*1-Inputs!$E$49+1))/1 -> 3 | D11: =Inputs!$E$46*(1+Inputs!$E$48)^(D$5-1)*MAX(0,MIN(1,D$4*1-Inputs!$E$49+1))/1 -> 3 | E11: =Inputs!$E$46*(1+Inputs!$E$48)^(E$5-1)*MAX(0,MIN(1,E$4*1-Inputs!$E$49+1))/1 -> 3 | F11: =Inputs!$E$46*(1+Inputs!$E$48)^(F$5-1)*MAX(0,MIN(1,F$4*1-Inputs!$E$49+1))/1 -> 3 | G11: =Inputs!$E$46*(1+Inputs!$E$48)^(G$5-1)*MAX(0,MIN(1,G$4*1-Inputs!$E$49+1))/1 -> 3 | H11: =Inputs!$E$46*(1+Inputs!$E$48)^(H$5-1)*MAX(0,MIN(1,H$4*1-Inputs!$E$49+1))/1 -> 3 | I11: =Inputs!$E$46*(1+Inputs!$E$48)^(I$5-1)*MAX(0,MIN(1,I$4*1-Inputs!$E$49+1))/1 -> 3 | J11: =Inputs!$E$46*(1+Inputs!$E$48)^(J$5-1)*MAX(0,MIN(1,J$4*1-Inputs!$E$49+1))/1 -> 3 | ... BJ11: =Inputs!$E$46*(1+Inputs!$E$48)^(BJ$5-1)*MAX(0,MIN(1,BJ$4*1-Inputs!$E$49+1))/1 -> 5.2470187
A12: Total FTE | C12: =C8+C9+C10+C11 -> 21 | D12: =D8+D9+D10+D11 -> 21 | E12: =E8+E9+E10+E11 -> 21 | F12: =F8+F9+F10+F11 -> 21 | G12: =G8+G9+G10+G11 -> 21 | H12: =H8+H9+H10+H11 -> 21 | I12: =I8+I9+I10+I11 -> 21 | J12: =J8+J9+J10+J11 -> 21 | ... BJ12: =BJ8+BJ9+BJ10+BJ11 -> 51.961819
A14: Payroll cost (salary + taxes & benefits)
A15: Partners & senior consultants — payroll cost | C15: =-C8*Inputs!$E$35/12*1*(1+Inputs!$E$50)*(1+Inputs!$E$51)^(C$5-1) -> -64000 | D15: =-D8*Inputs!$E$35/12*1*(1+Inputs!$E$50)*(1+Inputs!$E$51)^(D$5-1) -> -64000 | E15: =-E8*Inputs!$E$35/12*1*(1+Inputs!$E$50)*(1+Inputs!$E$51)^(E$5-1) -> -64000 | F15: =-F8*Inputs!$E$35/12*1*(1+Inputs!$E$50)*(1+Inputs!$E$51)^(F$5-1) -> -64000 | G15: =-G8*Inputs!$E$35/12*1*(1+Inputs!$E$50)*(1+Inputs!$E$51)^(G$5-1) -> -64000 | H15: =-H8*Inputs!$E$35/12*1*(1+Inputs!$E$50)*(1+Inputs!$E$51)^(H$5-1) -> -64000 | I15: =-I8*Inputs!$E$35/12*1*(1+Inputs!$E$50)*(1+Inputs!$E$51)^(I$5-1) -> -64000 | J15: =-J8*Inputs!$E$35/12*1*(1+Inputs!$E$50)*(1+Inputs!$E$51)^(J$5-1) -> -64000 | ... BJ15: =-BJ8*Inputs!$E$35/12*1*(1+Inputs!$E$50)*(1+Inputs!$E$51)^(BJ$5-1) -> -149366.72
A16: Consultants — payroll cost | C16: =-C9*Inputs!$E$39/12*1*(1+Inputs!$E$50)*(1+Inputs!$E$51)^(C$5-1) -> -114000 | D16: =-D9*Inputs!$E$39/12*1*(1+Inputs!$E$50)*(1+Inputs!$E$51)^(D$5-1) -> -114000 | E16: =-E9*Inputs!$E$39/12*1*(1+Inputs!$E$50)*(1+Inputs!$E$51)^(E$5-1) -> -114000 | F16: =-F9*Inputs!$E$39/12*1*(1+Inputs!$E$50)*(1+Inputs!$E$51)^(F$5-1) -> -114000 | G16: =-G9*Inputs!$E$39/12*1*(1+Inputs!$E$50)*(1+Inputs!$E$51)^(G$5-1) -> -114000 | H16: =-H9*Inputs!$E$39/12*1*(1+Inputs!$E$50)*(1+Inputs!$E$51)^(H$5-1) -> -114000 | I16: =-I9*Inputs!$E$39/12*1*(1+Inputs!$E$50)*(1+Inputs!$E$51)^(I$5-1) -> -114000 | J16: =-J9*Inputs!$E$39/12*1*(1+Inputs!$E$50)*(1+Inputs!$E$51)^(J$5-1) -> -114000 | ... BJ16: =-BJ9*Inputs!$E$39/12*1*(1+Inputs!$E$50)*(1+Inputs!$E$51)^(BJ$5-1) -> -366460.49
A17: Business development — payroll cost | C17: =-C10*Inputs!$E$43/12*1*(1+Inputs!$E$50)*(1+Inputs!$E$51)^(C$5-1) -> -17000 | D17: =-D10*Inputs!$E$43/12*1*(1+Inputs!$E$50)*(1+Inputs!$E$51)^(D$5-1) -> -17000 | E17: =-E10*Inputs!$E$43/12*1*(1+Inputs!$E$50)*(1+Inputs!$E$51)^(E$5-1) -> -17000 | F17: =-F10*Inputs!$E$43/12*1*(1+Inputs!$E$50)*(1+Inputs!$E$51)^(F$5-1) -> -17000 | G17: =-G10*Inputs!$E$43/12*1*(1+Inputs!$E$50)*(1+Inputs!$E$51)^(G$5-1) -> -17000 | H17: =-H10*Inputs!$E$43/12*1*(1+Inputs!$E$50)*(1+Inputs!$E$51)^(H$5-1) -> -17000 | I17: =-I10*Inputs!$E$43/12*1*(1+Inputs!$E$50)*(1+Inputs!$E$51)^(I$5-1) -> -17000 | J17: =-J10*Inputs!$E$43/12*1*(1+Inputs!$E$50)*(1+Inputs!$E$51)^(J$5-1) -> -17000 | ... BJ17: =-BJ10*Inputs!$E$43/12*1*(1+Inputs!$E$50)*(1+Inputs!$E$51)^(BJ$5-1) -> -39675.536
A18: Operations & admin — payroll cost | C18: =-C11*Inputs!$E$47/12*1*(1+Inputs!$E$50)*(1+Inputs!$E$51)^(C$5-1) -> -19500 | D18: =-D11*Inputs!$E$47/12*1*(1+Inputs!$E$50)*(1+Inputs!$E$51)^(D$5-1) -> -19500 | E18: =-E11*Inputs!$E$47/12*1*(1+Inputs!$E$50)*(1+Inputs!$E$51)^(E$5-1) -> -19500 | F18: =-F11*Inputs!$E$47/12*1*(1+Inputs!$E$50)*(1+Inputs!$E$51)^(F$5-1) -> -19500 | G18: =-G11*Inputs!$E$47/12*1*(1+Inputs!$E$50)*(1+Inputs!$E$51)^(G$5-1) -> -19500 | H18: =-H11*Inputs!$E$47/12*1*(1+Inputs!$E$50)*(1+Inputs!$E$51)^(H$5-1) -> -19500 | I18: =-I11*Inputs!$E$47/12*1*(1+Inputs!$E$50)*(1+Inputs!$E$51)^(I$5-1) -> -19500 | J18: =-J11*Inputs!$E$47/12*1*(1+Inputs!$E$50)*(1+Inputs!$E$51)^(J$5-1) -> -19500 | ... BJ18: =-BJ11*Inputs!$E$47/12*1*(1+Inputs!$E$50)*(1+Inputs!$E$51)^(BJ$5-1) -> -38386.178
A19: Total payroll | C19: =C15+C16+C17+C18 -> -214500 | D19: =D15+D16+D17+D18 -> -214500 | E19: =E15+E16+E17+E18 -> -214500 | F19: =F15+F16+F17+F18 -> -214500 | G19: =G15+G16+G17+G18 -> -214500 | H19: =H15+H16+H17+H18 -> -214500 | I19: =I15+I16+I17+I18 -> -214500 | J19: =J15+J16+J17+J18 -> -214500 | ... BJ19: =BJ15+BJ16+BJ17+BJ18 -> -593888.93

Sheet Scenario calc
A1: Scenario calculation — Low, Base and High side by side | D1: =HYPERLINK("#'Cover'!A1","◂ Contents") -> ◂ Contents
A2: The model's period calculation, copied three times; each copy reads its own Inputs column. Feeds the Scenarios sheet only.
A4: Low scenario — reads Inputs column B
A5: Month | C5: M1 | D5: M2 | E5: M3 | F5: M4 | G5: M5 | H5: M6 | I5: M7 | J5: M8 | K5: M9 | L5: M10 | M5: M11 | N5: M12 | O5: M13 | P5: M14 | Q5: M15 | R5: M16 | S5: M17 | T5: M18 | U5: M19 | V5: M20 | W5: M21 | X5: M22 | Y5: M23 | Z5: M24 | AA5: M25 | AB5: M26 | AC5: M27 | AD5: M28 | AE5: M29 | AF5: M30 | AG5: M31 | AH5: M32 | AI5: M33 | AJ5: M34 | AK5: M35 | AL5: M36 | AM5: M37 | AN5: M38 | AO5: M39 | AP5: M40 | AQ5: M41 | AR5: M42 | AS5: M43 | AT5: M44 | AU5: M45 | AV5: M46 | AW5: M47 | AX5: M48 | AY5: M49 | AZ5: M50 | BA5: M51 | BB5: M52 | BC5: M53 | BD5: M54 | BE5: M55 | BF5: M56 | BG5: M57 | BH5: M58 | BI5: M59 | BJ5: M60
A6: Period # | C6: 1 | D6: 2 | E6: 3 | F6: 4 | G6: 5 | H6: 6 | I6: 7 | J6: 8 | K6: 9 | L6: 10 | M6: 11 | N6: 12 | O6: 13 | P6: 14 | Q6: 15 | R6: 16 | S6: 17 | T6: 18 | U6: 19 | V6: 20 | W6: 21 | X6: 22 | Y6: 23 | Z6: 24 | AA6: 25 | AB6: 26 | AC6: 27 | AD6: 28 | AE6: 29 | AF6: 30 | AG6: 31 | AH6: 32 | AI6: 33 | AJ6: 34 | AK6: 35 | AL6: 36 | AM6: 37 | AN6: 38 | AO6: 39 | AP6: 40 | AQ6: 41 | AR6: 42 | AS6: 43 | AT6: 44 | AU6: 45 | AV6: 46 | AW6: 47 | AX6: 48 | AY6: 49 | AZ6: 50 | BA6: 51 | BB6: 52 | BC6: 53 | BD6: 54 | BE6: 55 | BF6: 56 | BG6: 57 | BH6: 58 | BI6: 59 | BJ6: 60
A7: Year # | C7: =ROUNDUP(C6*1/12,0) -> 1 | D7: =ROUNDUP(D6*1/12,0) -> 1 | E7: =ROUNDUP(E6*1/12,0) -> 1 | F7: =ROUNDUP(F6*1/12,0) -> 1 | G7: =ROUNDUP(G6*1/12,0) -> 1 | H7: =ROUNDUP(H6*1/12,0) -> 1 | I7: =ROUNDUP(I6*1/12,0) -> 1 | J7: =ROUNDUP(J6*1/12,0) -> 1 | ... BJ7: =ROUNDUP(BJ6*1/12,0) -> 5
A9: Billable capacity
A10: Billable employees (FTE) | C10: =C100+C101 -> 16 | D10: =D100+D101 -> 16 | E10: =E100+E101 -> 16 | F10: =F100+F101 -> 16 | G10: =G100+G101 -> 16 | H10: =H100+H101 -> 16 | I10: =I100+I101 -> 16 | J10: =J100+J101 -> 16 | ... BJ10: =BJ100+BJ101 -> 42.5676
A11: Available hours — billable employees | C11: =C10*Inputs!$B$7/12*1 -> 2400 | D11: =D10*Inputs!$B$7/12*1 -> 2400 | E11: =E10*Inputs!$B$7/12*1 -> 2400 | F11: =F10*Inputs!$B$7/12*1 -> 2400 | G11: =G10*Inputs!$B$7/12*1 -> 2400 | H11: =H10*Inputs!$B$7/12*1 -> 2400 | I11: =I10*Inputs!$B$7/12*1 -> 2400 | J11: =J10*Inputs!$B$7/12*1 -> 2400 | ... BJ11: =BJ10*Inputs!$B$7/12*1 -> 6385.14
A12: Billable hours — partners & senior | C12: =C100*Inputs!$B$7/12*1*Inputs!$B$8 -> 300 | D12: =D100*Inputs!$B$7/12*1*Inputs!$B$8 -> 300 | E12: =E100*Inputs!$B$7/12*1*Inputs!$B$8 -> 300 | F12: =F100*Inputs!$B$7/12*1*Inputs!$B$8 -> 300 | G12: =G100*Inputs!$B$7/12*1*Inputs!$B$8 -> 300 | H12: =H100*Inputs!$B$7/12*1*Inputs!$B$8 -> 300 | I12: =I100*Inputs!$B$7/12*1*Inputs!$B$8 -> 300 | J12: =J100*Inputs!$B$7/12*1*Inputs!$B$8 -> 300 | ... BJ12: =BJ100*Inputs!$B$7/12*1*Inputs!$B$8 -> 622.08
A13: Billable hours — consultants | C13: =C101*Inputs!$B$7/12*1*Inputs!$B$9 -> 1224 | D13: =D101*Inputs!$B$7/12*1*Inputs!$B$9 -> 1224 | E13: =E101*Inputs!$B$7/12*1*Inputs!$B$9 -> 1224 | F13: =F101*Inputs!$B$7/12*1*Inputs!$B$9 -> 1224 | G13: =G101*Inputs!$B$7/12*1*Inputs!$B$9 -> 1224 | H13: =H101*Inputs!$B$7/12*1*Inputs!$B$9 -> 1224 | I13: =I101*Inputs!$B$7/12*1*Inputs!$B$9 -> 1224 | J13: =J101*Inputs!$B$7/12*1*Inputs!$B$9 -> 1224 | ... BJ13: =BJ101*Inputs!$B$7/12*1*Inputs!$B$9 -> 3495.8664
A14: Billable hours — contractors | C14: =Inputs!$B$10*(1+Inputs!$B$11)^(C$7-1)*1 -> 300 | D14: =Inputs!$B$10*(1+Inputs!$B$11)^(D$7-1)*1 -> 300 | E14: =Inputs!$B$10*(1+Inputs!$B$11)^(E$7-1)*1 -> 300 | F14: =Inputs!$B$10*(1+Inputs!$B$11)^(F$7-1)*1 -> 300 | G14: =Inputs!$B$10*(1+Inputs!$B$11)^(G$7-1)*1 -> 300 | H14: =Inputs!$B$10*(1+Inputs!$B$11)^(H$7-1)*1 -> 300 | I14: =Inputs!$B$10*(1+Inputs!$B$11)^(I$7-1)*1 -> 300 | J14: =Inputs!$B$10*(1+Inputs!$B$11)^(J$7-1)*1 -> 300 | ... BJ14: =Inputs!$B$10*(1+Inputs!$B$11)^(BJ$7-1)*1 -> 439.23
A15: Billable hours — total | C15: =C12+C13+C14 -> 1824 | D15: =D12+D13+D14 -> 1824 | E15: =E12+E13+E14 -> 1824 | F15: =F12+F13+F14 -> 1824 | G15: =G12+G13+G14 -> 1824 | H15: =H12+H13+H14 -> 1824 | I15: =I12+I13+I14 -> 1824 | J15: =J12+J13+J14 -> 1824 | ... BJ15: =BJ12+BJ13+BJ14 -> 4557.1764
A17: Fees
A18: Rate — partners & senior | C18: =Inputs!$B$14*(1+Inputs!$B$17)^(C$7-1) -> 300 | D18: =Inputs!$B$14*(1+Inputs!$B$17)^(D$7-1) -> 300 | E18: =Inputs!$B$14*(1+Inputs!$B$17)^(E$7-1) -> 300 | F18: =Inputs!$B$14*(1+Inputs!$B$17)^(F$7-1) -> 300 | G18: =Inputs!$B$14*(1+Inputs!$B$17)^(G$7-1) -> 300 | H18: =Inputs!$B$14*(1+Inputs!$B$17)^(H$7-1) -> 300 | I18: =Inputs!$B$14*(1+Inputs!$B$17)^(I$7-1) -> 300 | J18: =Inputs!$B$14*(1+Inputs!$B$17)^(J$7-1) -> 300 | ... BJ18: =Inputs!$B$14*(1+Inputs!$B$17)^(BJ$7-1) -> 324.72965
A19: Rate — consultants | C19: =Inputs!$B$15*(1+Inputs!$B$17)^(C$7-1) -> 150 | D19: =Inputs!$B$15*(1+Inputs!$B$17)^(D$7-1) -> 150 | E19: =Inputs!$B$15*(1+Inputs!$B$17)^(E$7-1) -> 150 | F19: =Inputs!$B$15*(1+Inputs!$B$17)^(F$7-1) -> 150 | G19: =Inputs!$B$15*(1+Inputs!$B$17)^(G$7-1) -> 150 | H19: =Inputs!$B$15*(1+Inputs!$B$17)^(H$7-1) -> 150 | I19: =Inputs!$B$15*(1+Inputs!$B$17)^(I$7-1) -> 150 | J19: =Inputs!$B$15*(1+Inputs!$B$17)^(J$7-1) -> 150 | ... BJ19: =Inputs!$B$15*(1+Inputs!$B$17)^(BJ$7-1) -> 162.36482
A20: Rate — contractor hours | C20: =Inputs!$B$16*(1+Inputs!$B$17)^(C$7-1) -> 140 | D20: =Inputs!$B$16*(1+Inputs!$B$17)^(D$7-1) -> 140 | E20: =Inputs!$B$16*(1+Inputs!$B$17)^(E$7-1) -> 140 | F20: =Inputs!$B$16*(1+Inputs!$B$17)^(F$7-1) -> 140 | G20: =Inputs!$B$16*(1+Inputs!$B$17)^(G$7-1) -> 140 | H20: =Inputs!$B$16*(1+Inputs!$B$17)^(H$7-1) -> 140 | I20: =Inputs!$B$16*(1+Inputs!$B$17)^(I$7-1) -> 140 | J20: =Inputs!$B$16*(1+Inputs!$B$17)^(J$7-1) -> 140 | ... BJ20: =Inputs!$B$16*(1+Inputs!$B$17)^(BJ$7-1) -> 151.5405
A21: Fees at rate card | C21: =C12*C18+C13*C19+C14*C20 -> 315600 | D21: =D12*D18+D13*D19+D14*D20 -> 315600 | E21: =E12*E18+E13*E19+E14*E20 -> 315600 | F21: =F12*F18+F13*F19+F14*F20 -> 315600 | G21: =G12*G18+G13*G19+G14*G20 -> 315600 | H21: =H12*H18+H13*H19+H14*H20 -> 315600 | I21: =I12*I18+I13*I19+I14*I20 -> 315600 | J21: =J12*J18+J13*J19+J14*J20 -> 315600 | ... BJ21: =BJ12*BJ18+BJ13*BJ19+BJ14*BJ20 -> 836174.69
A22: Retainer fees | C22: =C21*Inputs!$B$20*(1-Inputs!$B$21) -> 111091.2 | D22: =D21*Inputs!$B$20*(1-Inputs!$B$21) -> 111091.2 | E22: =E21*Inputs!$B$20*(1-Inputs!$B$21) -> 111091.2 | F22: =F21*Inputs!$B$20*(1-Inputs!$B$21) -> 111091.2 | G22: =G21*Inputs!$B$20*(1-Inputs!$B$21) -> 111091.2 | H22: =H21*Inputs!$B$20*(1-Inputs!$B$21) -> 111091.2 | I22: =I21*Inputs!$B$20*(1-Inputs!$B$21) -> 111091.2 | J22: =J21*Inputs!$B$20*(1-Inputs!$B$21) -> 111091.2 | ... BJ22: =BJ21*Inputs!$B$20*(1-Inputs!$B$21) -> 294333.49
A23: Project fees | C23: =C21*(1-Inputs!$B$20)*Inputs!$B$22 -> 166636.8 | D23: =D21*(1-Inputs!$B$20)*Inputs!$B$22 -> 166636.8 | E23: =E21*(1-Inputs!$B$20)*Inputs!$B$22 -> 166636.8 | F23: =F21*(1-Inputs!$B$20)*Inputs!$B$22 -> 166636.8 | G23: =G21*(1-Inputs!$B$20)*Inputs!$B$22 -> 166636.8 | H23: =H21*(1-Inputs!$B$20)*Inputs!$B$22 -> 166636.8 | I23: =I21*(1-Inputs!$B$20)*Inputs!$B$22 -> 166636.8 | J23: =J21*(1-Inputs!$B$20)*Inputs!$B$22 -> 166636.8 | ... BJ23: =BJ21*(1-Inputs!$B$20)*Inputs!$B$22 -> 441500.23
A24: Fee revenue | C24: =C22+C23 -> 277728 | D24: =D22+D23 -> 277728 | E24: =E22+E23 -> 277728 | F24: =F22+F23 -> 277728 | G24: =G22+G23 -> 277728 | H24: =H22+H23 -> 277728 | I24: =I22+I23 -> 277728 | J24: =J22+J23 -> 277728 | ... BJ24: =BJ22+BJ23 -> 735833.72
A26: Cost of delivery
A27: Billable staff payroll | C27: =C107+C108 -> -178000 | D27: =D107+D108 -> -178000 | E27: =E107+E108 -> -178000 | F27: =F107+F108 -> -178000 | G27: =G107+G108 -> -178000 | H27: =H107+H108 -> -178000 | I27: =I107+I108 -> -178000 | J27: =J107+J108 -> -178000 | ... BJ27: =BJ107+BJ108 -> -515827.22
A28: Contractor cost | C28: =-C14*Inputs!$B$25*(1+Inputs!$B$51)^(C$7-1) -> -28500 | D28: =-D14*Inputs!$B$25*(1+Inputs!$B$51)^(D$7-1) -> -28500 | E28: =-E14*Inputs!$B$25*(1+Inputs!$B$51)^(E$7-1) -> -28500 | F28: =-F14*Inputs!$B$25*(1+Inputs!$B$51)^(F$7-1) -> -28500 | G28: =-G14*Inputs!$B$25*(1+Inputs!$B$51)^(G$7-1) -> -28500 | H28: =-H14*Inputs!$B$25*(1+Inputs!$B$51)^(H$7-1) -> -28500 | I28: =-I14*Inputs!$B$25*(1+Inputs!$B$51)^(I$7-1) -> -28500 | J28: =-J14*Inputs!$B$25*(1+Inputs!$B$51)^(J$7-1) -> -28500 | ... BJ28: =-BJ14*Inputs!$B$25*(1+Inputs!$B$51)^(BJ$7-1) -> -46963.937
A29: Non-rebillable delivery costs | C29: =-C24*Inputs!$B$26 -> -11109.12 | D29: =-D24*Inputs!$B$26 -> -11109.12 | E29: =-E24*Inputs!$B$26 -> -11109.12 | F29: =-F24*Inputs!$B$26 -> -11109.12 | G29: =-G24*Inputs!$B$26 -> -11109.12 | H29: =-H24*Inputs!$B$26 -> -11109.12 | I29: =-I24*Inputs!$B$26 -> -11109.12 | J29: =-J24*Inputs!$B$26 -> -11109.12 | ... BJ29: =-BJ24*Inputs!$B$26 -> -29433.349
A30: Cost of delivery | C30: =C27+C28+C29 -> -217609.12 | D30: =D27+D28+D29 -> -217609.12 | E30: =E27+E28+E29 -> -217609.12 | F30: =F27+F28+F29 -> -217609.12 | G30: =G27+G28+G29 -> -217609.12 | H30: =H27+H28+H29 -> -217609.12 | I30: =I27+I28+I29 -> -217609.12 | J30: =J27+J28+J29 -> -217609.12 | ... BJ30: =BJ27+BJ28+BJ29 -> -592224.5
A31: Gross profit | C31: =C24+C30 -> 60118.88 | D31: =D24+D30 -> 60118.88 | E31: =E24+E30 -> 60118.88 | F31: =F24+F30 -> 60118.88 | G31: =G24+G30 -> 60118.88 | H31: =H24+H30 -> 60118.88 | I31: =I24+I30 -> 60118.88 | J31: =J24+J30 -> 60118.88 | ... BJ31: =BJ24+BJ30 -> 143609.22
A33: Operating expenses
A34: Non-billable payroll | C34: =C111-C107-C108 -> -36500 | D34: =D111-D107-D108 -> -36500 | E34: =E111-E107-E108 -> -36500 | F34: =F111-F107-F108 -> -36500 | G34: =G111-G107-G108 -> -36500 | H34: =H111-H107-H108 -> -36500 | I34: =I111-I107-I108 -> -36500 | J34: =J111-J107-J108 -> -36500 | ... BJ34: =BJ111-BJ107-BJ108 -> -78061.714
A35: Marketing & business development | C35: =-Inputs!$B$28*1 -> -8000 | D35: =-Inputs!$B$28*1 -> -8000 | E35: =-Inputs!$B$28*1 -> -8000 | F35: =-Inputs!$B$28*1 -> -8000 | G35: =-Inputs!$B$28*1 -> -8000 | H35: =-Inputs!$B$28*1 -> -8000 | I35: =-Inputs!$B$28*1 -> -8000 | J35: =-Inputs!$B$28*1 -> -8000 | ... BJ35: =-Inputs!$B$28*1 -> -8000
A36: Software & tools | C36: =-C104*Inputs!$B$27*1 -> -4200 | D36: =-D104*Inputs!$B$27*1 -> -4200 | E36: =-E104*Inputs!$B$27*1 -> -4200 | F36: =-F104*Inputs!$B$27*1 -> -4200 | G36: =-G104*Inputs!$B$27*1 -> -4200 | H36: =-H104*Inputs!$B$27*1 -> -4200 | I36: =-I104*Inputs!$B$27*1 -> -4200 | J36: =-J104*Inputs!$B$27*1 -> -4200 | ... BJ36: =-BJ104*Inputs!$B$27*1 -> -10392.364
A37: Office & rent | C37: =-Inputs!$B$29*1 -> -8000 | D37: =-Inputs!$B$29*1 -> -8000 | E37: =-Inputs!$B$29*1 -> -8000 | F37: =-Inputs!$B$29*1 -> -8000 | G37: =-Inputs!$B$29*1 -> -8000 | H37: =-Inputs!$B$29*1 -> -8000 | I37: =-Inputs!$B$29*1 -> -8000 | J37: =-Inputs!$B$29*1 -> -8000 | ... BJ37: =-Inputs!$B$29*1 -> -8000
A38: Other G&A | C38: =-Inputs!$B$30*1 -> -6000 | D38: =-Inputs!$B$30*1 -> -6000 | E38: =-Inputs!$B$30*1 -> -6000 | F38: =-Inputs!$B$30*1 -> -6000 | G38: =-Inputs!$B$30*1 -> -6000 | H38: =-Inputs!$B$30*1 -> -6000 | I38: =-Inputs!$B$30*1 -> -6000 | J38: =-Inputs!$B$30*1 -> -6000 | ... BJ38: =-Inputs!$B$30*1 -> -6000
A39: Total operating expenses | C39: =C34+C35+C36+C37+C38 -> -62700 | D39: =D34+D35+D36+D37+D38 -> -62700 | E39: =E34+E35+E36+E37+E38 -> -62700 | F39: =F34+F35+F36+F37+F38 -> -62700 | G39: =G34+G35+G36+G37+G38 -> -62700 | H39: =H34+H35+H36+H37+H38 -> -62700 | I39: =I34+I35+I36+I37+I38 -> -62700 | J39: =J34+J35+J36+J37+J38 -> -62700 | ... BJ39: =BJ34+BJ35+BJ36+BJ37+BJ38 -> -110454.08
A40: EBITDA | C40: =C31+C39 -> -2581.12 | D40: =D31+D39 -> -2581.12 | E40: =E31+E39 -> -2581.12 | F40: =F31+F39 -> -2581.12 | G40: =G31+G39 -> -2581.12 | H40: =H31+H39 -> -2581.12 | I40: =I31+I39 -> -2581.12 | J40: =J31+J39 -> -2581.12 | ... BJ40: =BJ31+BJ39 -> 33155.145
A42: Profit after depreciation, interest, tax
A43: EBIT | C43: =C40+C54 -> -3581.12 | D43: =D40+D54 -> -3581.12 | E43: =E40+E54 -> -3581.12 | F43: =F40+F54 -> -3581.12 | G43: =G40+G54 -> -3581.12 | H43: =H40+H54 -> -3581.12 | I43: =I40+I54 -> -3581.12 | J43: =J40+J54 -> -3581.12 | ... BJ43: =BJ40+BJ54 -> 32155.145
A44: Interest on loan (average balance after drawdown) | C44: =-(C59+C60+C62)/2*Inputs!$B$56/12 -> -1333.3333 | D44: =-(D59+D60+D62)/2*Inputs!$B$56/12 -> -1322.2222 | E44: =-(E59+E60+E62)/2*Inputs!$B$56/12 -> -1300 | F44: =-(F59+F60+F62)/2*Inputs!$B$56/12 -> -1277.7778 | G44: =-(G59+G60+G62)/2*Inputs!$B$56/12 -> -1255.5556 | H44: =-(H59+H60+H62)/2*Inputs!$B$56/12 -> -1233.3333 | I44: =-(I59+I60+I62)/2*Inputs!$B$56/12 -> -1211.1111 | J44: =-(J59+J60+J62)/2*Inputs!$B$56/12 -> -1188.8889 | ... BJ44: =-(BJ59+BJ60+BJ62)/2*Inputs!$B$56/12 -> -33.333333
A45: Pre-tax income | C45: =C43+C44 -> -4914.4533 | D45: =D43+D44 -> -4903.3422 | E45: =E43+E44 -> -4881.12 | F45: =F43+F44 -> -4858.8978 | G45: =G43+G44 -> -4836.6756 | H45: =H43+H44 -> -4814.4533 | I45: =I43+I44 -> -4792.2311 | J45: =J43+J44 -> -4770.0089 | ... BJ45: =BJ43+BJ44 -> 32121.812
A46: Helper: cumulative pre-tax income | C46: =C45 -> -4914.4533 | D46: =C46+D45 -> -9817.7956 | E46: =D46+E45 -> -14698.916 | F46: =E46+F45 -> -19557.813 | G46: =F46+G45 -> -24394.489 | H46: =G46+H45 -> -29208.942 | I46: =H46+I45 -> -34001.173 | J46: =I46+J45 -> -38771.182 | K46: =J46+K45 -> -43518.969 | ... BJ46: =BI46+BJ45 -> 675948.91
A47: Helper: cumulative taxable income (losses carried forward) | C47: =MAX(0,C46) -> 0 | D47: =MAX(C47,D46) -> 0 | E47: =MAX(D47,E46) -> 0 | F47: =MAX(E47,F46) -> 0 | G47: =MAX(F47,G46) -> 0 | H47: =MAX(G47,H46) -> 0 | I47: =MAX(H47,I46) -> 0 | J47: =MAX(I47,J46) -> 0 | K47: =MAX(J47,K46) -> 0 | ... BJ47: =MAX(BI47,BJ46) -> 675948.91
A48: Income tax | C48: =-C47*Inputs!$B$66 -> 0 | D48: =-(D47-C47)*Inputs!$B$66 -> 0 | E48: =-(E47-D47)*Inputs!$B$66 -> 0 | F48: =-(F47-E47)*Inputs!$B$66 -> 0 | G48: =-(G47-F47)*Inputs!$B$66 -> 0 | H48: =-(H47-G47)*Inputs!$B$66 -> 0 | I48: =-(I47-H47)*Inputs!$B$66 -> 0 | J48: =-(J47-I47)*Inputs!$B$66 -> 0 | K48: =-(K47-J47)*Inputs!$B$66 -> 0 | ... BJ48: =-(BJ47-BI47)*Inputs!$B$66 -> -6745.5804
A49: Net income | C49: =C45+C48 -> -4914.4533 | D49: =D45+D48 -> -4903.3422 | E49: =E45+E48 -> -4881.12 | F49: =F45+F48 -> -4858.8978 | G49: =G45+G48 -> -4836.6756 | H49: =H45+H48 -> -4814.4533 | I49: =I45+I48 -> -4792.2311 | J49: =J45+J48 -> -4770.0089 | ... BJ49: =BJ45+BJ48 -> 25376.231
A51: Fixed assets & capital spending
A52: Capital spending | C52: =IF(C$6=1,Inputs!$B$31,0) -> 60000 | D52: =IF(D$6=1,Inputs!$B$31,0) -> 0 | E52: =IF(E$6=1,Inputs!$B$31,0) -> 0 | F52: =IF(F$6=1,Inputs!$B$31,0) -> 0 | G52: =IF(G$6=1,Inputs!$B$31,0) -> 0 | H52: =IF(H$6=1,Inputs!$B$31,0) -> 0 | I52: =IF(I$6=1,Inputs!$B$31,0) -> 0 | J52: =IF(J$6=1,Inputs!$B$31,0) -> 0 | ... BJ52: =IF(BJ$6=1,Inputs!$B$31,0) -> 0
A53: Fixed assets at cost | C53: =C52 -> 60000 | D53: =C53+D52 -> 60000 | E53: =D53+E52 -> 60000 | F53: =E53+F52 -> 60000 | G53: =F53+G52 -> 60000 | H53: =G53+H52 -> 60000 | I53: =H53+I52 -> 60000 | J53: =I53+J52 -> 60000 | K53: =J53+K52 -> 60000 | ... BJ53: =BI53+BJ52 -> 60000
A54: Depreciation | C54: =-MIN(C53/MAX(1,Inputs!$B$65*12),C52) -> -1000 | D54: =-MIN(D53/MAX(1,Inputs!$B$65*12),C56+D52) -> -1000 | E54: =-MIN(E53/MAX(1,Inputs!$B$65*12),D56+E52) -> -1000 | F54: =-MIN(F53/MAX(1,Inputs!$B$65*12),E56+F52) -> -1000 | G54: =-MIN(G53/MAX(1,Inputs!$B$65*12),F56+G52) -> -1000 | H54: =-MIN(H53/MAX(1,Inputs!$B$65*12),G56+H52) -> -1000 | I54: =-MIN(I53/MAX(1,Inputs!$B$65*12),H56+I52) -> -1000 | J54: =-MIN(J53/MAX(1,Inputs!$B$65*12),I56+J52) -> -1000 | K54: =-MIN(K53/MAX(1,Inputs!$B$65*12),J56+K52) -> -1000 | ... BJ54: =-MIN(BJ53/MAX(1,Inputs!$B$65*12),BI56+BJ52) -> -1000
A55: Accumulated depreciation | C55: =C54 -> -1000 | D55: =C55+D54 -> -2000 | E55: =D55+E54 -> -3000 | F55: =E55+F54 -> -4000 | G55: =F55+G54 -> -5000 | H55: =G55+H54 -> -6000 | I55: =H55+I54 -> -7000 | J55: =I55+J54 -> -8000 | K55: =J55+K54 -> -9000 | ... BJ55: =BI55+BJ54 -> -60000
A56: Net fixed assets | C56: =C53+C55 -> 59000 | D56: =D53+D55 -> 58000 | E56: =E53+E55 -> 57000 | F56: =F53+F55 -> 56000 | G56: =G53+G55 -> 55000 | H56: =H53+H55 -> 54000 | I56: =I53+I55 -> 53000 | J56: =J53+J55 -> 52000 | ... BJ56: =BJ53+BJ55 -> 0
A58: Debt
A59: Loan — opening balance | C59: =0 -> 0 | D59: =C62 -> 200000 | E59: =D62 -> 196666.67 | F59: =E62 -> 193333.33 | G59: =F62 -> 190000 | H59: =G62 -> 186666.67 | I59: =H62 -> 183333.33 | J59: =I62 -> 180000 | K59: =J62 -> 176666.67 | ... BJ59: =BI62 -> 6666.6667
A60: Loan drawdown | C60: =IF(C$6=1,Inputs!$B$55,0) -> 200000 | D60: =IF(D$6=1,Inputs!$B$55,0) -> 0 | E60: =IF(E$6=1,Inputs!$B$55,0) -> 0 | F60: =IF(F$6=1,Inputs!$B$55,0) -> 0 | G60: =IF(G$6=1,Inputs!$B$55,0) -> 0 | H60: =IF(H$6=1,Inputs!$B$55,0) -> 0 | I60: =IF(I$6=1,Inputs!$B$55,0) -> 0 | J60: =IF(J$6=1,Inputs!$B$55,0) -> 0 | ... BJ60: =IF(BJ$6=1,Inputs!$B$55,0) -> 0
A61: Loan repayment | C61: =-MIN(C59,Inputs!$B$55/MAX(1,Inputs!$B$57*12)) -> 0 | D61: =-MIN(D59,Inputs!$B$55/MAX(1,Inputs!$B$57*12)) -> -3333.3333 | E61: =-MIN(E59,Inputs!$B$55/MAX(1,Inputs!$B$57*12)) -> -3333.3333 | F61: =-MIN(F59,Inputs!$B$55/MAX(1,Inputs!$B$57*12)) -> -3333.3333 | G61: =-MIN(G59,Inputs!$B$55/MAX(1,Inputs!$B$57*12)) -> -3333.3333 | H61: =-MIN(H59,Inputs!$B$55/MAX(1,Inputs!$B$57*12)) -> -3333.3333 | I61: =-MIN(I59,Inputs!$B$55/MAX(1,Inputs!$B$57*12)) -> -3333.3333 | J61: =-MIN(J59,Inputs!$B$55/MAX(1,Inputs!$B$57*12)) -> -3333.3333 | ... BJ61: =-MIN(BJ59,Inputs!$B$55/MAX(1,Inputs!$B$57*12)) -> -3333.3333
A62: Loan — closing balance | C62: =C59+C60+C61 -> 200000 | D62: =D59+D60+D61 -> 196666.67 | E62: =E59+E60+E61 -> 193333.33 | F62: =F59+F60+F61 -> 190000 | G62: =G59+G60+G61 -> 186666.67 | H62: =H59+H60+H61 -> 183333.33 | I62: =I59+I60+I61 -> 180000 | J62: =J59+J60+J61 -> 176666.67 | ... BJ62: =BJ59+BJ60+BJ61 -> 3333.3333
A64: Working capital
A65: Accounts receivable | C65: =C24*Inputs!$B$60/30 -> 416592 | D65: =D24*Inputs!$B$60/30 -> 416592 | E65: =E24*Inputs!$B$60/30 -> 416592 | F65: =F24*Inputs!$B$60/30 -> 416592 | G65: =G24*Inputs!$B$60/30 -> 416592 | H65: =H24*Inputs!$B$60/30 -> 416592 | I65: =I24*Inputs!$B$60/30 -> 416592 | J65: =J24*Inputs!$B$60/30 -> 416592 | ... BJ65: =BJ24*Inputs!$B$60/30 -> 1103750.6
A66: Inventory | C66: =-C30*Inputs!$B$61/30 -> 0 | D66: =-D30*Inputs!$B$61/30 -> 0 | E66: =-E30*Inputs!$B$61/30 -> 0 | F66: =-F30*Inputs!$B$61/30 -> 0 | G66: =-G30*Inputs!$B$61/30 -> 0 | H66: =-H30*Inputs!$B$61/30 -> 0 | I66: =-I30*Inputs!$B$61/30 -> 0 | J66: =-J30*Inputs!$B$61/30 -> 0 | ... BJ66: =-BJ30*Inputs!$B$61/30 -> 0
A67: Accounts payable | C67: =-C30*Inputs!$B$62/30 -> 108804.56 | D67: =-D30*Inputs!$B$62/30 -> 108804.56 | E67: =-E30*Inputs!$B$62/30 -> 108804.56 | F67: =-F30*Inputs!$B$62/30 -> 108804.56 | G67: =-G30*Inputs!$B$62/30 -> 108804.56 | H67: =-H30*Inputs!$B$62/30 -> 108804.56 | I67: =-I30*Inputs!$B$62/30 -> 108804.56 | J67: =-J30*Inputs!$B$62/30 -> 108804.56 | ... BJ67: =-BJ30*Inputs!$B$62/30 -> 296112.25
A68: (Increase) / decrease in receivables | C68: =-C65 -> -416592 | D68: =C65-D65 -> 0 | E68: =D65-E65 -> 0 | F68: =E65-F65 -> 0 | G68: =F65-G65 -> 0 | H68: =G65-H65 -> 0 | I68: =H65-I65 -> 0 | J68: =I65-J65 -> 0 | K68: =J65-K65 -> 0 | ... BJ68: =BI65-BJ65 -> 0
A69: (Increase) / decrease in inventory | C69: =-C66 -> 0 | D69: =C66-D66 -> 0 | E69: =D66-E66 -> 0 | F69: =E66-F66 -> 0 | G69: =F66-G66 -> 0 | H69: =G66-H66 -> 0 | I69: =H66-I66 -> 0 | J69: =I66-J66 -> 0 | K69: =J66-K66 -> 0 | ... BJ69: =BI66-BJ66 -> 0
A70: Increase / (decrease) in payables | C70: =C67 -> 108804.56 | D70: =D67-C67 -> 0 | E70: =E67-D67 -> 0 | F70: =F67-E67 -> 0 | G70: =G67-F67 -> 0 | H70: =H67-G67 -> 0 | I70: =I67-H67 -> 0 | J70: =J67-I67 -> 0 | K70: =K67-J67 -> 0 | ... BJ70: =BJ67-BI67 -> 0
A72: Cash flow
A73: Operating cash flow | C73: =C49-C54+C68+C69+C70 -> -311701.89 | D73: =D49-D54+D68+D69+D70 -> -3903.3422 | E73: =E49-E54+E68+E69+E70 -> -3881.12 | F73: =F49-F54+F68+F69+F70 -> -3858.8978 | G73: =G49-G54+G68+G69+G70 -> -3836.6756 | H73: =H49-H54+H68+H69+H70 -> -3814.4533 | I73: =I49-I54+I68+I69+I70 -> -3792.2311 | J73: =J49-J54+J68+J69+J70 -> -3770.0089 | ... BJ73: =BJ49-BJ54+BJ68+BJ69+BJ70 -> 26376.231
A74: Investing cash flow (capex) | C74: =-C52 -> -60000 | D74: =-D52 -> 0 | E74: =-E52 -> 0 | F74: =-F52 -> 0 | G74: =-G52 -> 0 | H74: =-H52 -> 0 | I74: =-I52 -> 0 | J74: =-J52 -> 0 | ... BJ74: =-BJ52 -> 0
A75: Equity raised | C75: =IF(C$6=1,Inputs!$B$54,0) -> 300000 | D75: =IF(D$6=1,Inputs!$B$54,0) -> 0 | E75: =IF(E$6=1,Inputs!$B$54,0) -> 0 | F75: =IF(F$6=1,Inputs!$B$54,0) -> 0 | G75: =IF(G$6=1,Inputs!$B$54,0) -> 0 | H75: =IF(H$6=1,Inputs!$B$54,0) -> 0 | I75: =IF(I$6=1,Inputs!$B$54,0) -> 0 | J75: =IF(J$6=1,Inputs!$B$54,0) -> 0 | ... BJ75: =IF(BJ$6=1,Inputs!$B$54,0) -> 0
A76: Financing cash flow | C76: =C75+C60+C61 -> 500000 | D76: =D75+D60+D61 -> -3333.3333 | E76: =E75+E60+E61 -> -3333.3333 | F76: =F75+F60+F61 -> -3333.3333 | G76: =G75+G60+G61 -> -3333.3333 | H76: =H75+H60+H61 -> -3333.3333 | I76: =I75+I60+I61 -> -3333.3333 | J76: =J75+J60+J61 -> -3333.3333 | ... BJ76: =BJ75+BJ60+BJ61 -> -3333.3333
A77: Net cash flow | C77: =C73+C74+C76 -> 128298.11 | D77: =D73+D74+D76 -> -7236.6756 | E77: =E73+E74+E76 -> -7214.4533 | F77: =F73+F74+F76 -> -7192.2311 | G77: =G73+G74+G76 -> -7170.0089 | H77: =H73+H74+H76 -> -7147.7867 | I77: =I73+I74+I76 -> -7125.5644 | J77: =J73+J74+J76 -> -7103.3422 | ... BJ77: =BJ73+BJ74+BJ76 -> 23042.898
A78: Opening cash | C78: =0 -> 0 | D78: =C79 -> 128298.11 | E78: =D79 -> 121061.43 | F78: =E79 -> 113846.98 | G78: =F79 -> 106654.75 | H78: =G79 -> 99484.738 | I78: =H79 -> 92336.951 | J78: =I79 -> 85211.387 | K78: =J79 -> 78108.044 | ... BJ78: =BI79 -> 6651.7358
A79: Closing cash | C79: =C78+C77 -> 128298.11 | D79: =D78+D77 -> 121061.43 | E79: =E78+E77 -> 113846.98 | F79: =F78+F77 -> 106654.75 | G79: =G78+G77 -> 99484.738 | H79: =H78+H77 -> 92336.951 | I79: =I78+I77 -> 85211.387 | J79: =J78+J77 -> 78108.044 | ... BJ79: =BJ78+BJ77 -> 29694.634
A80: Helper: EBITDA positive (1/0) | C80: =IF(C40>0,1,0) -> 0 | D80: =IF(D40>0,1,0) -> 0 | E80: =IF(E40>0,1,0) -> 0 | F80: =IF(F40>0,1,0) -> 0 | G80: =IF(G40>0,1,0) -> 0 | H80: =IF(H40>0,1,0) -> 0 | I80: =IF(I40>0,1,0) -> 0 | J80: =IF(J40>0,1,0) -> 0 | ... BJ80: =IF(BJ40>0,1,0) -> 1
A82: Goal modules
A83: Helper: net income positive (1/0) | C83: =IF(C49>0,1,0) -> 0 | D83: =IF(D49>0,1,0) -> 0 | E83: =IF(E49>0,1,0) -> 0 | F83: =IF(F49>0,1,0) -> 0 | G83: =IF(G49>0,1,0) -> 0 | H83: =IF(H49>0,1,0) -> 0 | I83: =IF(I49>0,1,0) -> 0 | J83: =IF(J49>0,1,0) -> 0 | ... BJ83: =IF(BJ49>0,1,0) -> 1
A84: Cash flow before financing (operating + investing) | C84: =C73+C74 -> -371701.89 | D84: =D73+D74 -> -3903.3422 | E84: =E73+E74 -> -3881.12 | F84: =F73+F74 -> -3858.8978 | G84: =G73+G74 -> -3836.6756 | H84: =H73+H74 -> -3814.4533 | I84: =I73+I74 -> -3792.2311 | J84: =J73+J74 -> -3770.0089 | ... BJ84: =BJ73+BJ74 -> 26376.231
A85: Cumulative cash flow before financing | C85: =C84 -> -371701.89 | D85: =C85+D84 -> -375605.24 | E85: =D85+E84 -> -379486.36 | F85: =E85+F84 -> -383345.25 | G85: =F85+G84 -> -387181.93 | H85: =G85+H84 -> -390996.38 | I85: =H85+I84 -> -394788.61 | J85: =I85+J84 -> -398558.62 | K85: =J85+K84 -> -402306.41 | ... BJ85: =BI85+BJ84 -> -273638.7
A86: Helper: lowest cumulative cash flow so far | C86: =C85 -> -371701.89 | D86: =MIN(C86,D85) -> -375605.24 | E86: =MIN(D86,E85) -> -379486.36 | F86: =MIN(E86,F85) -> -383345.25 | G86: =MIN(F86,G85) -> -387181.93 | H86: =MIN(G86,H85) -> -390996.38 | I86: =MIN(H86,I85) -> -394788.61 | J86: =MIN(I86,J85) -> -398558.62 | K86: =MIN(J86,K85) -> -402306.41 | ... BJ86: =MIN(BI86,BJ85) -> -589263.41
A87: Helper: investment paid back (1/0) | C87: =IF(AND(C85>=0,C86<0),1,0) -> 0 | D87: =IF(AND(D85>=0,D86<0),1,0) -> 0 | E87: =IF(AND(E85>=0,E86<0),1,0) -> 0 | F87: =IF(AND(F85>=0,F86<0),1,0) -> 0 | G87: =IF(AND(G85>=0,G86<0),1,0) -> 0 | H87: =IF(AND(H85>=0,H86<0),1,0) -> 0 | I87: =IF(AND(I85>=0,I86<0),1,0) -> 0 | J87: =IF(AND(J85>=0,J86<0),1,0) -> 0 | ... BJ87: =IF(AND(BJ85>=0,BJ86<0),1,0) -> 0
A88: Unlevered free cash flow (operating + after-tax interest − capex) | C88: =C73-C44*(1-Inputs!$B$66)+C74 -> -370648.56 | D88: =D73-D44*(1-Inputs!$B$66)+D74 -> -2858.7867 | E88: =E73-E44*(1-Inputs!$B$66)+E74 -> -2854.12 | F88: =F73-F44*(1-Inputs!$B$66)+F74 -> -2849.4533 | G88: =G73-G44*(1-Inputs!$B$66)+G74 -> -2844.7867 | H88: =H73-H44*(1-Inputs!$B$66)+H74 -> -2840.12 | I88: =I73-I44*(1-Inputs!$B$66)+I74 -> -2835.4533 | J88: =J73-J44*(1-Inputs!$B$66)+J74 -> -2830.7867 | ... BJ88: =BJ73-BJ44*(1-Inputs!$B$66)+BJ74 -> 26402.565
A90: Balance sheet
A91: Paid-in capital | C91: =C75 -> 300000 | D91: =C91+D75 -> 300000 | E91: =D91+E75 -> 300000 | F91: =E91+F75 -> 300000 | G91: =F91+G75 -> 300000 | H91: =G91+H75 -> 300000 | I91: =H91+I75 -> 300000 | J91: =I91+J75 -> 300000 | K91: =J91+K75 -> 300000 | ... BJ91: =BI91+BJ75 -> 300000
A92: Retained earnings | C92: =C49 -> -4914.4533 | D92: =C92+D49 -> -9817.7956 | E92: =D92+E49 -> -14698.916 | F92: =E92+F49 -> -19557.813 | G92: =F92+G49 -> -24394.489 | H92: =G92+H49 -> -29208.942 | I92: =H92+I49 -> -34001.173 | J92: =I92+J49 -> -38771.182 | K92: =J92+K49 -> -43518.969 | ... BJ92: =BI92+BJ49 -> 533999.64
A93: Total assets | C93: =C79+C65+C66+C56 -> 603890.11 | D93: =D79+D65+D66+D56 -> 595653.43 | E93: =E79+E65+E66+E56 -> 587438.98 | F93: =F79+F65+F66+F56 -> 579246.75 | G93: =G79+G65+G66+G56 -> 571076.74 | H93: =H79+H65+H66+H56 -> 562928.95 | I93: =I79+I65+I66+I56 -> 554803.39 | J93: =J79+J65+J66+J56 -> 546700.04 | ... BJ93: =BJ79+BJ65+BJ66+BJ56 -> 1133445.2
A94: Total liabilities | C94: =C67+C62 -> 308804.56 | D94: =D67+D62 -> 305471.23 | E94: =E67+E62 -> 302137.89 | F94: =F67+F62 -> 298804.56 | G94: =G67+G62 -> 295471.23 | H94: =H67+H62 -> 292137.89 | I94: =I67+I62 -> 288804.56 | J94: =J67+J62 -> 285471.23 | ... BJ94: =BJ67+BJ62 -> 299445.58
A95: Total equity | C95: =C91+C92 -> 295085.55 | D95: =D91+D92 -> 290182.2 | E95: =E91+E92 -> 285301.08 | F95: =F91+F92 -> 280442.19 | G95: =G91+G92 -> 275605.51 | H95: =H91+H92 -> 270791.06 | I95: =I91+I92 -> 265998.83 | J95: =J91+J92 -> 261228.82 | ... BJ95: =BJ91+BJ92 -> 833999.64
A96: Total liabilities & equity | C96: =C94+C95 -> 603890.11 | D96: =D94+D95 -> 595653.43 | E96: =E94+E95 -> 587438.98 | F96: =F94+F95 -> 579246.75 | G96: =G94+G95 -> 571076.74 | H96: =H94+H95 -> 562928.95 | I96: =I94+I95 -> 554803.39 | J96: =J94+J95 -> 546700.04 | ... BJ96: =BJ94+BJ95 -> 1133445.2
A97: Check: assets − liabilities − equity | C97: =C93-C96 -> 0 | D97: =D93-D96 -> 0 | E97: =E93-E96 -> 0 | F97: =F93-F96 -> 0 | G97: =G93-G96 -> 0 | H97: =H93-H96 -> 0 | I97: =I93-I96 -> 0 | J97: =J93-J96 -> 0 | ... BJ97: =BJ93-BJ96 -> 0
A99: Headcount (FTE)
A100: Partners & senior consultants — FTE | C100: =Inputs!$B$34*(1+Inputs!$B$36)^(C$7-1)*MAX(0,MIN(1,C$6*1-Inputs!$B$37+1))/1 -> 4 | D100: =Inputs!$B$34*(1+Inputs!$B$36)^(D$7-1)*MAX(0,MIN(1,D$6*1-Inputs!$B$37+1))/1 -> 4 | E100: =Inputs!$B$34*(1+Inputs!$B$36)^(E$7-1)*MAX(0,MIN(1,E$6*1-Inputs!$B$37+1))/1 -> 4 | F100: =Inputs!$B$34*(1+Inputs!$B$36)^(F$7-1)*MAX(0,MIN(1,F$6*1-Inputs!$B$37+1))/1 -> 4 | G100: =Inputs!$B$34*(1+Inputs!$B$36)^(G$7-1)*MAX(0,MIN(1,G$6*1-Inputs!$B$37+1))/1 -> 4 | H100: =Inputs!$B$34*(1+Inputs!$B$36)^(H$7-1)*MAX(0,MIN(1,H$6*1-Inputs!$B$37+1))/1 -> 4 | I100: =Inputs!$B$34*(1+Inputs!$B$36)^(I$7-1)*MAX(0,MIN(1,I$6*1-Inputs!$B$37+1))/1 -> 4 | J100: =Inputs!$B$34*(1+Inputs!$B$36)^(J$7-1)*MAX(0,MIN(1,J$6*1-Inputs!$B$37+1))/1 -> 4 | ... BJ100: =Inputs!$B$34*(1+Inputs!$B$36)^(BJ$7-1)*MAX(0,MIN(1,BJ$6*1-Inputs!$B$37+1))/1 -> 8.2944
A101: Consultants — FTE | C101: =Inputs!$B$38*(1+Inputs!$B$40)^(C$7-1)*MAX(0,MIN(1,C$6*1-Inputs!$B$41+1))/1 -> 12 | D101: =Inputs!$B$38*(1+Inputs!$B$40)^(D$7-1)*MAX(0,MIN(1,D$6*1-Inputs!$B$41+1))/1 -> 12 | E101: =Inputs!$B$38*(1+Inputs!$B$40)^(E$7-1)*MAX(0,MIN(1,E$6*1-Inputs!$B$41+1))/1 -> 12 | F101: =Inputs!$B$38*(1+Inputs!$B$40)^(F$7-1)*MAX(0,MIN(1,F$6*1-Inputs!$B$41+1))/1 -> 12 | G101: =Inputs!$B$38*(1+Inputs!$B$40)^(G$7-1)*MAX(0,MIN(1,G$6*1-Inputs!$B$41+1))/1 -> 12 | H101: =Inputs!$B$38*(1+Inputs!$B$40)^(H$7-1)*MAX(0,MIN(1,H$6*1-Inputs!$B$41+1))/1 -> 12 | I101: =Inputs!$B$38*(1+Inputs!$B$40)^(I$7-1)*MAX(0,MIN(1,I$6*1-Inputs!$B$41+1))/1 -> 12 | J101: =Inputs!$B$38*(1+Inputs!$B$40)^(J$7-1)*MAX(0,MIN(1,J$6*1-Inputs!$B$41+1))/1 -> 12 | ... BJ101: =Inputs!$B$38*(1+Inputs!$B$40)^(BJ$7-1)*MAX(0,MIN(1,BJ$6*1-Inputs!$B$41+1))/1 -> 34.2732
A102: Business development — FTE | C102: =Inputs!$B$42*(1+Inputs!$B$44)^(C$7-1)*MAX(0,MIN(1,C$6*1-Inputs!$B$45+1))/1 -> 2 | D102: =Inputs!$B$42*(1+Inputs!$B$44)^(D$7-1)*MAX(0,MIN(1,D$6*1-Inputs!$B$45+1))/1 -> 2 | E102: =Inputs!$B$42*(1+Inputs!$B$44)^(E$7-1)*MAX(0,MIN(1,E$6*1-Inputs!$B$45+1))/1 -> 2 | F102: =Inputs!$B$42*(1+Inputs!$B$44)^(F$7-1)*MAX(0,MIN(1,F$6*1-Inputs!$B$45+1))/1 -> 2 | G102: =Inputs!$B$42*(1+Inputs!$B$44)^(G$7-1)*MAX(0,MIN(1,G$6*1-Inputs!$B$45+1))/1 -> 2 | H102: =Inputs!$B$42*(1+Inputs!$B$44)^(H$7-1)*MAX(0,MIN(1,H$6*1-Inputs!$B$45+1))/1 -> 2 | I102: =Inputs!$B$42*(1+Inputs!$B$44)^(I$7-1)*MAX(0,MIN(1,I$6*1-Inputs!$B$45+1))/1 -> 2 | J102: =Inputs!$B$42*(1+Inputs!$B$44)^(J$7-1)*MAX(0,MIN(1,J$6*1-Inputs!$B$45+1))/1 -> 2 | ... BJ102: =Inputs!$B$42*(1+Inputs!$B$44)^(BJ$7-1)*MAX(0,MIN(1,BJ$6*1-Inputs!$B$45+1))/1 -> 4.1472
A103: Operations & admin — FTE | C103: =Inputs!$B$46*(1+Inputs!$B$48)^(C$7-1)*MAX(0,MIN(1,C$6*1-Inputs!$B$49+1))/1 -> 3 | D103: =Inputs!$B$46*(1+Inputs!$B$48)^(D$7-1)*MAX(0,MIN(1,D$6*1-Inputs!$B$49+1))/1 -> 3 | E103: =Inputs!$B$46*(1+Inputs!$B$48)^(E$7-1)*MAX(0,MIN(1,E$6*1-Inputs!$B$49+1))/1 -> 3 | F103: =Inputs!$B$46*(1+Inputs!$B$48)^(F$7-1)*MAX(0,MIN(1,F$6*1-Inputs!$B$49+1))/1 -> 3 | G103: =Inputs!$B$46*(1+Inputs!$B$48)^(G$7-1)*MAX(0,MIN(1,G$6*1-Inputs!$B$49+1))/1 -> 3 | H103: =Inputs!$B$46*(1+Inputs!$B$48)^(H$7-1)*MAX(0,MIN(1,H$6*1-Inputs!$B$49+1))/1 -> 3 | I103: =Inputs!$B$46*(1+Inputs!$B$48)^(I$7-1)*MAX(0,MIN(1,I$6*1-Inputs!$B$49+1))/1 -> 3 | J103: =Inputs!$B$46*(1+Inputs!$B$48)^(J$7-1)*MAX(0,MIN(1,J$6*1-Inputs!$B$49+1))/1 -> 3 | ... BJ103: =Inputs!$B$46*(1+Inputs!$B$48)^(BJ$7-1)*MAX(0,MIN(1,BJ$6*1-Inputs!$B$49+1))/1 -> 5.2470187
A104: Total FTE | C104: =C100+C101+C102+C103 -> 21 | D104: =D100+D101+D102+D103 -> 21 | E104: =E100+E101+E102+E103 -> 21 | F104: =F100+F101+F102+F103 -> 21 | G104: =G100+G101+G102+G103 -> 21 | H104: =H100+H101+H102+H103 -> 21 | I104: =I100+I101+I102+I103 -> 21 | J104: =J100+J101+J102+J103 -> 21 | ... BJ104: =BJ100+BJ101+BJ102+BJ103 -> 51.961819
A106: Payroll cost (salary + taxes & benefits)
A107: Partners & senior consultants — payroll cost | C107: =-C100*Inputs!$B$35/12*1*(1+Inputs!$B$50)*(1+Inputs!$B$51)^(C$7-1) -> -64000 | D107: =-D100*Inputs!$B$35/12*1*(1+Inputs!$B$50)*(1+Inputs!$B$51)^(D$7-1) -> -64000 | E107: =-E100*Inputs!$B$35/12*1*(1+Inputs!$B$50)*(1+Inputs!$B$51)^(E$7-1) -> -64000 | F107: =-F100*Inputs!$B$35/12*1*(1+Inputs!$B$50)*(1+Inputs!$B$51)^(F$7-1) -> -64000 | G107: =-G100*Inputs!$B$35/12*1*(1+Inputs!$B$50)*(1+Inputs!$B$51)^(G$7-1) -> -64000 | H107: =-H100*Inputs!$B$35/12*1*(1+Inputs!$B$50)*(1+Inputs!$B$51)^(H$7-1) -> -64000 | I107: =-I100*Inputs!$B$35/12*1*(1+Inputs!$B$50)*(1+Inputs!$B$51)^(I$7-1) -> -64000 | J107: =-J100*Inputs!$B$35/12*1*(1+Inputs!$B$50)*(1+Inputs!$B$51)^(J$7-1) -> -64000 | ... BJ107: =-BJ100*Inputs!$B$35/12*1*(1+Inputs!$B$50)*(1+Inputs!$B$51)^(BJ$7-1) -> -149366.72
A108: Consultants — payroll cost | C108: =-C101*Inputs!$B$39/12*1*(1+Inputs!$B$50)*(1+Inputs!$B$51)^(C$7-1) -> -114000 | D108: =-D101*Inputs!$B$39/12*1*(1+Inputs!$B$50)*(1+Inputs!$B$51)^(D$7-1) -> -114000 | E108: =-E101*Inputs!$B$39/12*1*(1+Inputs!$B$50)*(1+Inputs!$B$51)^(E$7-1) -> -114000 | F108: =-F101*Inputs!$B$39/12*1*(1+Inputs!$B$50)*(1+Inputs!$B$51)^(F$7-1) -> -114000 | G108: =-G101*Inputs!$B$39/12*1*(1+Inputs!$B$50)*(1+Inputs!$B$51)^(G$7-1) -> -114000 | H108: =-H101*Inputs!$B$39/12*1*(1+Inputs!$B$50)*(1+Inputs!$B$51)^(H$7-1) -> -114000 | I108: =-I101*Inputs!$B$39/12*1*(1+Inputs!$B$50)*(1+Inputs!$B$51)^(I$7-1) -> -114000 | J108: =-J101*Inputs!$B$39/12*1*(1+Inputs!$B$50)*(1+Inputs!$B$51)^(J$7-1) -> -114000 | ... BJ108: =-BJ101*Inputs!$B$39/12*1*(1+Inputs!$B$50)*(1+Inputs!$B$51)^(BJ$7-1) -> -366460.49
A109: Business development — payroll cost | C109: =-C102*Inputs!$B$43/12*1*(1+Inputs!$B$50)*(1+Inputs!$B$51)^(C$7-1) -> -17000 | D109: =-D102*Inputs!$B$43/12*1*(1+Inputs!$B$50)*(1+Inputs!$B$51)^(D$7-1) -> -17000 | E109: =-E102*Inputs!$B$43/12*1*(1+Inputs!$B$50)*(1+Inputs!$B$51)^(E$7-1) -> -17000 | F109: =-F102*Inputs!$B$43/12*1*(1+Inputs!$B$50)*(1+Inputs!$B$51)^(F$7-1) -> -17000 | G109: =-G102*Inputs!$B$43/12*1*(1+Inputs!$B$50)*(1+Inputs!$B$51)^(G$7-1) -> -17000 | H109: =-H102*Inputs!$B$43/12*1*(1+Inputs!$B$50)*(1+Inputs!$B$51)^(H$7-1) -> -17000 | I109: =-I102*Inputs!$B$43/12*1*(1+Inputs!$B$50)*(1+Inputs!$B$51)^(I$7-1) -> -17000 | J109: =-J102*Inputs!$B$43/12*1*(1+Inputs!$B$50)*(1+Inputs!$B$51)^(J$7-1) -> -17000 | ... BJ109: =-BJ102*Inputs!$B$43/12*1*(1+Inputs!$B$50)*(1+Inputs!$B$51)^(BJ$7-1) -> -39675.536
A110: Operations & admin — payroll cost | C110: =-C103*Inputs!$B$47/12*1*(1+Inputs!$B$50)*(1+Inputs!$B$51)^(C$7-1) -> -19500 | D110: =-D103*Inputs!$B$47/12*1*(1+Inputs!$B$50)*(1+Inputs!$B$51)^(D$7-1) -> -19500 | E110: =-E103*Inputs!$B$47/12*1*(1+Inputs!$B$50)*(1+Inputs!$B$51)^(E$7-1) -> -19500 | F110: =-F103*Inputs!$B$47/12*1*(1+Inputs!$B$50)*(1+Inputs!$B$51)^(F$7-1) -> -19500 | G110: =-G103*Inputs!$B$47/12*1*(1+Inputs!$B$50)*(1+Inputs!$B$51)^(G$7-1) -> -19500 | H110: =-H103*Inputs!$B$47/12*1*(1+Inputs!$B$50)*(1+Inputs!$B$51)^(H$7-1) -> -19500 | I110: =-I103*Inputs!$B$47/12*1*(1+Inputs!$B$50)*(1+Inputs!$B$51)^(I$7-1) -> -19500 | J110: =-J103*Inputs!$B$47/12*1*(1+Inputs!$B$50)*(1+Inputs!$B$51)^(J$7-1) -> -19500 | ... BJ110: =-BJ103*Inputs!$B$47/12*1*(1+Inputs!$B$50)*(1+Inputs!$B$51)^(BJ$7-1) -> -38386.178
A111: Total payroll | C111: =C107+C108+C109+C110 -> -214500 | D111: =D107+D108+D109+D110 -> -214500 | E111: =E107+E108+E109+E110 -> -214500 | F111: =F107+F108+F109+F110 -> -214500 | G111: =G107+G108+G109+G110 -> -214500 | H111: =H107+H108+H109+H110 -> -214500 | I111: =I107+I108+I109+I110 -> -214500 | J111: =J107+J108+J109+J110 -> -214500 | ... BJ111: =BJ107+BJ108+BJ109+BJ110 -> -593888.93
A114: Base scenario — reads Inputs column C
A115: Month | C115: M1 | D115: M2 | E115: M3 | F115: M4 | G115: M5 | H115: M6 | I115: M7 | J115: M8 | K115: M9 | L115: M10 | M115: M11 | N115: M12 | O115: M13 | P115: M14 | Q115: M15 | R115: M16 | S115: M17 | T115: M18 | U115: M19 | V115: M20 | W115: M21 | X115: M22 | Y115: M23 | Z115: M24 | AA115: M25 | AB115: M26 | AC115: M27 | AD115: M28 | AE115: M29 | AF115: M30 | AG115: M31 | AH115: M32 | AI115: M33 | AJ115: M34 | AK115: M35 | AL115: M36 | AM115: M37 | AN115: M38 | AO115: M39 | AP115: M40 | AQ115: M41 | AR115: M42 | AS115: M43 | AT115: M44 | AU115: M45 | AV115: M46 | AW115: M47 | AX115: M48 | AY115: M49 | AZ115: M50 | BA115: M51 | BB115: M52 | BC115: M53 | BD115: M54 | BE115: M55 | BF115: M56 | BG115: M57 | BH115: M58 | BI115: M59 | BJ115: M60
A116: Period # | C116: 1 | D116: 2 | E116: 3 | F116: 4 | G116: 5 | H116: 6 | I116: 7 | J116: 8 | K116: 9 | L116: 10 | M116: 11 | N116: 12 | O116: 13 | P116: 14 | Q116: 15 | R116: 16 | S116: 17 | T116: 18 | U116: 19 | V116: 20 | W116: 21 | X116: 22 | Y116: 23 | Z116: 24 | AA116: 25 | AB116: 26 | AC116: 27 | AD116: 28 | AE116: 29 | AF116: 30 | AG116: 31 | AH116: 32 | AI116: 33 | AJ116: 34 | AK116: 35 | AL116: 36 | AM116: 37 | AN116: 38 | AO116: 39 | AP116: 40 | AQ116: 41 | AR116: 42 | AS116: 43 | AT116: 44 | AU116: 45 | AV116: 46 | AW116: 47 | AX116: 48 | AY116: 49 | AZ116: 50 | BA116: 51 | BB116: 52 | BC116: 53 | BD116: 54 | BE116: 55 | BF116: 56 | BG116: 57 | BH116: 58 | BI116: 59 | BJ116: 60
...

Sheet Checks
A1: Model checks | E1: =HYPERLINK("#'Cover'!A1","◂ Contents") -> ◂ Contents
A2: Live formulas: they re-run every time an input changes.
A3: Check | B3: Result | C3: What it tests
A4: Annual revenue ties to period detail | B4: =IF(ABS(SUM('P&L'!$B$5:$F$5)-SUM(Monthly!$C$22:$BJ$22))<0.5,"PASS","FAIL") -> PASS | C4: Sum of annual revenue equals the sum of every period
A5: Annual net income ties to period detail | B5: =IF(ABS(SUM('P&L'!$B$22:$F$22)-SUM(Monthly!$C$47:$BJ$47))<0.5,"PASS","FAIL") -> PASS | C5: Sum of annual net income equals the sum of every period
A6: EBITDA reconciliation | B6: =IF(ABS(SUM(Monthly!$C$38:$BJ$38)-SUM(Monthly!$C$29:$BJ$29)-SUM(Monthly!$C$37:$BJ$37))<0.5,"PASS","FAIL") -> PASS | C6: EBITDA = gross profit + operating expenses (costs are negative)
A7: Cash roll-forward | B7: =IF(ABS(INDEX(Monthly!$C$77:$BJ$77,60)-SUM(Monthly!$C$75:$BJ$75))<0.5,"PASS","FAIL") -> PASS | C7: Closing cash = all net cash flows since the start (opening cash is zero)
A8: Scenario selector valid | B8: =IF(AND(ISNUMBER(Dashboard!B4),Dashboard!B4>=1,Dashboard!B4<=3,INT(Dashboard!B4)=Dashboard!B4),"PASS","FAIL") -> PASS | C8: Dashboard!B4 is 1, 2 or 3
A9: Scenario ordering of drivers | B9: =IF(AND(Inputs!$B$8<=Inputs!$C$8,Inputs!$C$8<=Inputs!$D$8,Inputs!$B$9<=Inputs!$C$9,Inputs!$C$9<=Inputs!$D$9,Inputs!$B$10<=Inputs!$C$10,Inputs!$C$10<=Inputs!$D$10,Inputs!$B$11<=Inputs!$C$11,Inputs!$C$11<=Inputs!$D$11,Inputs!$B$14<=Inputs!$C$14,Inputs!$C$14<=Inputs!$D$14,Inputs!$B$15<=Inputs!$C$15,Inputs!$C$15<=Inputs!$D$15,Inputs!$B$16<=Inputs!$C$16,Inputs!$C$16<=Inputs!$D$16,Inputs!$B$17<=Inputs!$C$17,Inputs!$C$17<=Inputs!$D$17,Inputs!$B$21>=Inputs!$C$21,Inputs!$C$21>=Inputs!$D$21,Inputs!$B$22<=Inputs!$C$22,Inputs!$C$22<=Inputs!$D$22,Inputs!$B$25>=Inputs!$C$25,Inputs!$C$25>=Inputs!$D$25,Inputs!$B$26>=Inputs!$C$26,Inputs!$C$26>=Inputs!$D$26,Inputs!$B$34<=Inputs!$C$34,Inputs!$C$34<=Inputs!$D$34,Inputs!$B$36<=Inputs!$C$36,Inputs!$C$36<=Inputs!$D$36,Inputs!$B$38<=Inputs!$C$38,Inputs!$C$38<=Inputs!$D$38,Inputs!$B$40<=Inputs!$C$40,Inputs!$C$40<=Inputs!$D$40,Inputs!$B$42<=Inputs!$C$42,Inputs!$C$42<=Inputs!$D$42,Inputs!$B$44<=Inputs!$C$44,Inputs!$C$44<=Inputs!$D$44,Inputs!$B$46<=Inputs!$C$46,Inputs!$C$46<=Inputs!$D$46,Inputs!$B$48<=Inputs!$C$48,Inputs!$C$48<=Inputs!$D$48,Inputs!$B$72>=Inputs!$C$72,Inputs!$C$72>=Inputs!$D$72,Inputs!$B$73<=Inputs!$C$73,Inputs!$C$73<=Inputs!$D$73,Inputs!$B$74<=Inputs!$C$74,Inputs!$C$74<=Inputs!$D$74),"PASS","FAIL") -> PASS | C9: Low / Base / High ordered the right way for every growth and cost driver
A10: Gross margin within 0–100% | B10: =IF(AND(MIN('P&L'!$B$8:$F$8)>=0,MAX('P&L'!$B$8:$F$8)<=1),"PASS","FAIL") -> PASS | C10: Gross margin never negative or above 100%
A11: Loan balance never negative | B11: =IF(MIN(Monthly!$C$60:$BJ$60)>=-0.5,"PASS","FAIL") -> PASS | C11: Repayments never exceed the loan
A12: Funding table ties to the cash flow | B12: =IF(ABS('Break-even'!B18-('Break-even'!B16-'Break-even'!B10))<0.5,"PASS","FAIL") -> PASS | C12: Lowest cash balance = sources of funds − uses of funds up to that point
A13: Valuation: discounting ties to NPV() | B13: =IF(ABS(Valuation!B23-NPV(Valuation!B6,Valuation!$B$17:$F$17))<0.5,"PASS","FAIL") -> PASS | C13: Sum of discounted free cash flows equals Excel's NPV of the same flows
A14: Valuation: WACC above terminal growth | B14: =IF(Valuation!B6>Valuation!B7,"PASS","FAIL") -> PASS | C14: The perpetual-growth formula needs WACC > g
A15: Valuation: sensitivity centre = enterprise value | B15: =IF(ABS(Valuation!D36-Valuation!B27)<0.5,"PASS","FAIL") -> PASS | C15: The middle of the WACC × growth table reproduces the headline value
A16: Valuation: final-year cash flow positive | B16: =IF(Valuation!$F$17>0,"PASS","WARN") -> PASS | C16: Business warning: a negative final-year cash flow gives a negative terminal value (often a 1-year plan still carrying start-up spending)
A17: Sources & uses balance | B17: =IF(ABS('Sources & Uses'!B21-'Sources & Uses'!B28)<0.5,"PASS","FAIL") -> PASS | C17: Sources of funds = uses of funds (incl. cash at the end) for the Sources & Uses period
A18: No error values | B18: =IF(SUMPRODUCT(--ISERROR(Monthly!$C$4:$BJ$95))+SUMPRODUCT(--ISERROR(Headcount!$C$4:$BJ$19))+SUMPRODUCT(--ISERROR('P&L'!$B$3:$F$23))+SUMPRODUCT(--ISERROR('Cash Flow'!$B$3:$F$18))+SUMPRODUCT(--ISERROR('Balance Sheet'!$B$3:$F$17))+SUMPRODUCT(--ISERROR(KPIs!$B$27:$F$49))+SUMPRODUCT(--ISERROR('Break-even'!$B$26:$F$33))+SUMPRODUCT(--ISERROR(Valuation!$B$14:$F$19))+SUMPRODUCT(--ISERROR('Break-even'!$B$3:$F$35))+SUMPRODUCT(--ISERROR(Valuation!$A$3:$F$40))+SUMPRODUCT(--ISERROR('Sources & Uses'!$B$3:$C$30))+SUMPRODUCT(--ISERROR(Dashboard!$A$6:$W$44))+SUMPRODUCT(--ISERROR(Summary!$A$5:$S$52))+SUMPRODUCT(--ISERROR(KPIs!$A$4:$G$49))+SUMPRODUCT(--ISERROR('Scenario calc'!$C$6:$BJ$111))+SUMPRODUCT(--ISERROR('Scenario calc'!$C$116:$BJ$221))+SUMPRODUCT(--ISERROR('Scenario calc'!$C$226:$BJ$331))+SUMPRODUCT(--ISERROR(Scenarios!$B$5:$F$49))=0,"PASS","FAIL") -> PASS | C18: No error values (divide-by-zero, broken references) on any calculation sheet
A19: Summary ties to statements | B19: =IF(IFERROR(AND(SUMPRODUCT(--(ABS(Summary!$B$7:$F$7-'P&L'!$B$5:$F$5)>0.5))=0,SUMPRODUCT(--(ABS(Summary!$B$19:$F$19-'P&L'!$B$22:$F$22)>0.5))=0,SUMPRODUCT(--(ABS(Summary!$B$31:$F$31-'Cash Flow'!$B$18:$F$18)>0.5))=0,SUMPRODUCT(--(ABS(Summary!$B$41:$F$41-'Balance Sheet'!$B$5:$F$5)>0.5))=0,ABS(SUM(Summary!$H$7:$S$7)-INDEX(Summary!$B$7:$F$7,Summary!$R$2))<0.5,ABS(SUM(Summary!$H$19:$S$19)-INDEX(Summary!$B$19:$F$19,Summary!$R$2))<0.5,ABS(Summary!$S$31-INDEX(Summary!$B$31:$F$31,Summary!$R$2))<0.5),FALSE()),"PASS","FAIL") -> PASS | C19: Summary revenue, net income and closing cash equal the statements every year; the detailed year adds up to its annual figure
A20: DuPont ties to return on equity | B20: =IF(SUMPRODUCT(--(ABS(KPIs!$B$24:$F$24)>0.000000001))>0,"FAIL",IF(SUMPRODUCT(ISNUMBER(KPIs!$B$23:$F$23)*ISNUMBER(KPIs!$B$16:$F$16))=0,"n/a","PASS")) -> PASS | C20: Net margin × asset turnover × equity multiplier equals return on equity every year; n/a = no year where both are defined (a one-sided n/a is a FAIL)
A21: Scenarios: Active = selected scenario | B21: =IF(IFERROR(AND(ABS(Scenarios!E16-INDEX(Scenarios!B16:D16,1,Dashboard!$B$4))<0.5,ABS(Scenarios!E17-INDEX(Scenarios!B17:D17,1,Dashboard!$B$4))<0.5,ABS(Scenarios!E18-INDEX(Scenarios!B18:D18,1,Dashboard!$B$4))<0.5,ABS(Scenarios!E19-INDEX(Scenarios!B19:D19,1,Dashboard!$B$4))<0.000001,ABS(Scenarios!E20-INDEX(Scenarios!B20:D20,1,Dashboard!$B$4))<0.5,ABS(Scenarios!E21-INDEX(Scenarios!B21:D21,1,Dashboard!$B$4))<0.5,ABS(Scenarios!E22-INDEX(Scenarios!B22:D22,1,Dashboard!$B$4))<0.5,ABS(Scenarios!E23-INDEX(Scenarios!B23:D23,1,Dashboard!$B$4))<0.5,ABS(Scenarios!E24-INDEX(Scenarios!B24:D24,1,Dashboard!$B$4))<0.5,ABS(Scenarios!E25-INDEX(Scenarios!B25:D25,1,Dashboard!$B$4))<0.5),FALSE()),"PASS","FAIL") -> PASS | C21: On the Scenarios sheet the live model (Active) equals the Low / Base / High column chosen on the Dashboard for every output
A22: Balance sheet balances every period | B22: =IF(SUMPRODUCT(--(ABS(Monthly!$C$95:$BJ$95)>0.5))=0,"PASS","FAIL") -> PASS | C22: Assets = liabilities + equity in every period
A23: Funding sufficient (cash ≥ 0) | B23: =IF(MIN(Monthly!$C$77:$BJ$77)>=0,"PASS","WARN") -> PASS | C23: Business warning, not an error: cash dips below zero in this scenario
A25: Overall verdict | B25: =IF(COUNTIF(B4:B23,"FAIL")>0,"FAIL",IF(COUNTIF(B4:B23,"WARN")>0,"PASS WITH WARNINGS","PASS")) -> PASS
